// Bytecode for: ext.mods.gameserver.model.residence.clanhall.ClanHall
// File: ext\mods\gameserver\model\residence\clanhall\ClanHall.class

Classfile /c:/Users/User/Desktop/BrProject/bin/main/ext/mods/gameserver/model/residence/clanhall/ClanHall.class
  Last modified 9 de jul de 2026; size 13235 bytes
  MD5 checksum 32d17aee32b2829cebe4e413379a7044
  Compiled from "ClanHall.java"
public class ext.mods.gameserver.model.residence.clanhall.ClanHall extends ext.mods.gameserver.model.residence.Residence
  minor version: 0
  major version: 69
  flags: (0x0021) ACC_PUBLIC, ACC_SUPER
  this_class: #13                         // ext/mods/gameserver/model/residence/clanhall/ClanHall
  super_class: #2                         // ext/mods/gameserver/model/residence/Residence
  interfaces: 0, fields: 26, methods: 28, attributes: 4
Constant pool:
    #1 = Methodref          #2.#3         // ext/mods/gameserver/model/residence/Residence."<init>":(Lext/mods/commons/data/StatSet;)V
    #2 = Class              #4            // ext/mods/gameserver/model/residence/Residence
    #3 = NameAndType        #5:#6         // "<init>":(Lext/mods/commons/data/StatSet;)V
    #4 = Utf8               ext/mods/gameserver/model/residence/Residence
    #5 = Utf8               <init>
    #6 = Utf8               (Lext/mods/commons/data/StatSet;)V
    #7 = Class              #8            // java/util/concurrent/ConcurrentHashMap
    #8 = Utf8               java/util/concurrent/ConcurrentHashMap
    #9 = Methodref          #7.#10        // java/util/concurrent/ConcurrentHashMap."<init>":()V
   #10 = NameAndType        #5:#11        // "<init>":()V
   #11 = Utf8               ()V
   #12 = Fieldref           #13.#14       // ext/mods/gameserver/model/residence/clanhall/ClanHall._functions:Ljava/util/Map;
   #13 = Class              #15           // ext/mods/gameserver/model/residence/clanhall/ClanHall
   #14 = NameAndType        #16:#17       // _functions:Ljava/util/Map;
   #15 = Utf8               ext/mods/gameserver/model/residence/clanhall/ClanHall
   #16 = Utf8               _functions
   #17 = Utf8               Ljava/util/Map;
   #18 = Class              #19           // java/util/ArrayList
   #19 = Utf8               java/util/ArrayList
   #20 = Methodref          #18.#10       // java/util/ArrayList."<init>":()V
   #21 = Fieldref           #13.#22       // ext/mods/gameserver/model/residence/clanhall/ClanHall._buffs:Ljava/util/List;
   #22 = NameAndType        #23:#24       // _buffs:Ljava/util/List;
   #23 = Utf8               _buffs
   #24 = Utf8               Ljava/util/List;
   #25 = String             #26           // desc
   #26 = Utf8               desc
   #27 = Methodref          #28.#29       // ext/mods/commons/data/StatSet.getString:(Ljava/lang/String;)Ljava/lang/String;
   #28 = Class              #30           // ext/mods/commons/data/StatSet
   #29 = NameAndType        #31:#32       // getString:(Ljava/lang/String;)Ljava/lang/String;
   #30 = Utf8               ext/mods/commons/data/StatSet
   #31 = Utf8               getString
   #32 = Utf8               (Ljava/lang/String;)Ljava/lang/String;
   #33 = Fieldref           #13.#34       // ext/mods/gameserver/model/residence/clanhall/ClanHall._desc:Ljava/lang/String;
   #34 = NameAndType        #35:#36       // _desc:Ljava/lang/String;
   #35 = Utf8               _desc
   #36 = Utf8               Ljava/lang/String;
   #37 = String             #38           // loc
   #38 = Utf8               loc
   #39 = Fieldref           #13.#40       // ext/mods/gameserver/model/residence/clanhall/ClanHall._townName:Ljava/lang/String;
   #40 = NameAndType        #41:#36       // _townName:Ljava/lang/String;
   #41 = Utf8               _townName
   #42 = String             #43           // auctionMin
   #43 = Utf8               auctionMin
   #44 = Methodref          #28.#45       // ext/mods/commons/data/StatSet.getInteger:(Ljava/lang/String;I)I
   #45 = NameAndType        #46:#47       // getInteger:(Ljava/lang/String;I)I
   #46 = Utf8               getInteger
   #47 = Utf8               (Ljava/lang/String;I)I
   #48 = Fieldref           #13.#49       // ext/mods/gameserver/model/residence/clanhall/ClanHall._auctionMin:I
   #49 = NameAndType        #50:#51       // _auctionMin:I
   #50 = Utf8               _auctionMin
   #51 = Utf8               I
   #52 = String             #53           // deposit
   #53 = Utf8               deposit
   #54 = Fieldref           #13.#55       // ext/mods/gameserver/model/residence/clanhall/ClanHall._deposit:I
   #55 = NameAndType        #56:#51       // _deposit:I
   #56 = Utf8               _deposit
   #57 = String             #58           // lease
   #58 = Utf8               lease
   #59 = Fieldref           #13.#60       // ext/mods/gameserver/model/residence/clanhall/ClanHall._lease:I
   #60 = NameAndType        #61:#51       // _lease:I
   #61 = Utf8               _lease
   #62 = String             #63           // size
   #63 = Utf8               size
   #64 = Fieldref           #13.#65       // ext/mods/gameserver/model/residence/clanhall/ClanHall._size:I
   #65 = NameAndType        #66:#51       // _size:I
   #66 = Utf8               _size
   #67 = Fieldref           #13.#68       // ext/mods/gameserver/model/residence/clanhall/ClanHall.GRADE_LIST:Ljava/util/Map;
   #68 = NameAndType        #69:#17       // GRADE_LIST:Ljava/util/Map;
   #69 = Utf8               GRADE_LIST
   #70 = Fieldref           #13.#71       // ext/mods/gameserver/model/residence/clanhall/ClanHall._id:I
   #71 = NameAndType        #72:#51       // _id:I
   #72 = Utf8               _id
   #73 = Methodref          #74.#75       // java/lang/Integer.valueOf:(I)Ljava/lang/Integer;
   #74 = Class              #76           // java/lang/Integer
   #75 = NameAndType        #77:#78       // valueOf:(I)Ljava/lang/Integer;
   #76 = Utf8               java/lang/Integer
   #77 = Utf8               valueOf
   #78 = Utf8               (I)Ljava/lang/Integer;
   #79 = InterfaceMethodref #80.#81       // java/util/Map.get:(Ljava/lang/Object;)Ljava/lang/Object;
   #80 = Class              #82           // java/util/Map
   #81 = NameAndType        #83:#84       // get:(Ljava/lang/Object;)Ljava/lang/Object;
   #82 = Utf8               java/util/Map
   #83 = Utf8               get
   #84 = Utf8               (Ljava/lang/Object;)Ljava/lang/Object;
   #85 = Methodref          #74.#86       // java/lang/Integer.intValue:()I
   #86 = NameAndType        #87:#88       // intValue:()I
   #87 = Utf8               intValue
   #88 = Utf8               ()I
   #89 = Fieldref           #13.#90       // ext/mods/gameserver/model/residence/clanhall/ClanHall._auction:Lext/mods/gameserver/model/residence/clanhall/Auction;
   #90 = NameAndType        #91:#92       // _auction:Lext/mods/gameserver/model/residence/clanhall/Auction;
   #91 = Utf8               _auction
   #92 = Utf8               Lext/mods/gameserver/model/residence/clanhall/Auction;
   #93 = Fieldref           #13.#94       // ext/mods/gameserver/model/residence/clanhall/ClanHall._paidUntil:J
   #94 = NameAndType        #95:#96       // _paidUntil:J
   #95 = Utf8               _paidUntil
   #96 = Utf8               J
   #97 = Fieldref           #13.#98       // ext/mods/gameserver/model/residence/clanhall/ClanHall._isPaid:Z
   #98 = NameAndType        #99:#100      // _isPaid:Z
   #99 = Utf8               _isPaid
  #100 = Utf8               Z
  #101 = Fieldref           #13.#102      // ext/mods/gameserver/model/residence/clanhall/ClanHall._zone:Lext/mods/gameserver/model/zone/type/ClanHallZone;
  #102 = NameAndType        #103:#104     // _zone:Lext/mods/gameserver/model/zone/type/ClanHallZone;
  #103 = Utf8               _zone
  #104 = Utf8               Lext/mods/gameserver/model/zone/type/ClanHallZone;
  #105 = Class              #106          // ext/mods/gameserver/model/residence/clanhall/ClanHallFunction
  #106 = Utf8               ext/mods/gameserver/model/residence/clanhall/ClanHallFunction
  #107 = Fieldref           #13.#108      // ext/mods/gameserver/model/residence/clanhall/ClanHall._feeTask:Ljava/util/concurrent/ScheduledFuture;
  #108 = NameAndType        #109:#110     // _feeTask:Ljava/util/concurrent/ScheduledFuture;
  #109 = Utf8               _feeTask
  #110 = Utf8               Ljava/util/concurrent/ScheduledFuture;
  #111 = InterfaceMethodref #112.#113     // java/util/concurrent/ScheduledFuture.cancel:(Z)Z
  #112 = Class              #114          // java/util/concurrent/ScheduledFuture
  #113 = NameAndType        #115:#116     // cancel:(Z)Z
  #114 = Utf8               java/util/concurrent/ScheduledFuture
  #115 = Utf8               cancel
  #116 = Utf8               (Z)Z
  #117 = Methodref          #118.#119     // ext/mods/gameserver/data/sql/ClanTable.getInstance:()Lext/mods/gameserver/data/sql/ClanTable;
  #118 = Class              #120          // ext/mods/gameserver/data/sql/ClanTable
  #119 = NameAndType        #121:#122     // getInstance:()Lext/mods/gameserver/data/sql/ClanTable;
  #120 = Utf8               ext/mods/gameserver/data/sql/ClanTable
  #121 = Utf8               getInstance
  #122 = Utf8               ()Lext/mods/gameserver/data/sql/ClanTable;
  #123 = Fieldref           #13.#124      // ext/mods/gameserver/model/residence/clanhall/ClanHall._ownerId:I
  #124 = NameAndType        #125:#51      // _ownerId:I
  #125 = Utf8               _ownerId
  #126 = Methodref          #118.#127     // ext/mods/gameserver/data/sql/ClanTable.getClan:(I)Lext/mods/gameserver/model/pledge/Clan;
  #127 = NameAndType        #128:#129     // getClan:(I)Lext/mods/gameserver/model/pledge/Clan;
  #128 = Utf8               getClan
  #129 = Utf8               (I)Lext/mods/gameserver/model/pledge/Clan;
  #130 = Methodref          #131.#132     // ext/mods/gameserver/model/pledge/Clan.setClanHallId:(I)V
  #131 = Class              #133          // ext/mods/gameserver/model/pledge/Clan
  #132 = NameAndType        #134:#135     // setClanHallId:(I)V
  #133 = Utf8               ext/mods/gameserver/model/pledge/Clan
  #134 = Utf8               setClanHallId
  #135 = Utf8               (I)V
  #136 = Class              #137          // ext/mods/gameserver/network/serverpackets/L2GameServerPacket
  #137 = Utf8               ext/mods/gameserver/network/serverpackets/L2GameServerPacket
  #138 = Class              #139          // ext/mods/gameserver/network/serverpackets/PledgeShowInfoUpdate
  #139 = Utf8               ext/mods/gameserver/network/serverpackets/PledgeShowInfoUpdate
  #140 = Methodref          #138.#141     // ext/mods/gameserver/network/serverpackets/PledgeShowInfoUpdate."<init>":(Lext/mods/gameserver/model/pledge/Clan;)V
  #141 = NameAndType        #5:#142       // "<init>":(Lext/mods/gameserver/model/pledge/Clan;)V
  #142 = Utf8               (Lext/mods/gameserver/model/pledge/Clan;)V
  #143 = Methodref          #131.#144     // ext/mods/gameserver/model/pledge/Clan.broadcastToMembers:([Lext/mods/gameserver/network/serverpackets/L2GameServerPacket;)V
  #144 = NameAndType        #145:#146     // broadcastToMembers:([Lext/mods/gameserver/network/serverpackets/L2GameServerPacket;)V
  #145 = Utf8               broadcastToMembers
  #146 = Utf8               ([Lext/mods/gameserver/network/serverpackets/L2GameServerPacket;)V
  #147 = Methodref          #13.#148      // ext/mods/gameserver/model/residence/clanhall/ClanHall.removeAllFunctions:()V
  #148 = NameAndType        #149:#11      // removeAllFunctions:()V
  #149 = Utf8               removeAllFunctions
  #150 = Methodref          #13.#151      // ext/mods/gameserver/model/residence/clanhall/ClanHall.closeDoors:()V
  #151 = NameAndType        #152:#11      // closeDoors:()V
  #152 = Utf8               closeDoors
  #153 = Methodref          #154.#155     // ext/mods/gameserver/model/residence/clanhall/Auction.removeBids:(Lext/mods/gameserver/model/pledge/Clan;)V
  #154 = Class              #156          // ext/mods/gameserver/model/residence/clanhall/Auction
  #155 = NameAndType        #157:#142     // removeBids:(Lext/mods/gameserver/model/pledge/Clan;)V
  #156 = Utf8               ext/mods/gameserver/model/residence/clanhall/Auction
  #157 = Utf8               removeBids
  #158 = Methodref          #154.#159     // ext/mods/gameserver/model/residence/clanhall/Auction.reset:(Z)V
  #159 = NameAndType        #160:#161     // reset:(Z)V
  #160 = Utf8               reset
  #161 = Utf8               (Z)V
  #162 = Methodref          #154.#163     // ext/mods/gameserver/model/residence/clanhall/Auction.startAutoTask:()V
  #163 = NameAndType        #164:#11      // startAutoTask:()V
  #164 = Utf8               startAutoTask
  #165 = Methodref          #13.#166      // ext/mods/gameserver/model/residence/clanhall/ClanHall.updateDb:()V
  #166 = NameAndType        #167:#11      // updateDb:()V
  #167 = Utf8               updateDb
  #168 = Methodref          #131.#169     // ext/mods/gameserver/model/pledge/Clan.getClanId:()I
  #169 = NameAndType        #170:#88      // getClanId:()I
  #170 = Utf8               getClanId
  #171 = Methodref          #172.#173     // java/lang/System.currentTimeMillis:()J
  #172 = Class              #174          // java/lang/System
  #173 = NameAndType        #175:#176     // currentTimeMillis:()J
  #174 = Utf8               java/lang/System
  #175 = Utf8               currentTimeMillis
  #176 = Utf8               ()J
  #177 = Long               604800000l
  #179 = Methodref          #13.#180      // ext/mods/gameserver/model/residence/clanhall/ClanHall.initializeFeeTask:()V
  #180 = NameAndType        #181:#11      // initializeFeeTask:()V
  #181 = Utf8               initializeFeeTask
  #182 = Methodref          #13.#183      // ext/mods/gameserver/model/residence/clanhall/ClanHall.banishForeigners:()V
  #183 = NameAndType        #184:#11      // banishForeigners:()V
  #184 = Utf8               banishForeigners
  #185 = Methodref          #13.#186      // ext/mods/gameserver/model/residence/clanhall/ClanHall.getOwnerId:()I
  #186 = NameAndType        #187:#88      // getOwnerId:()I
  #187 = Utf8               getOwnerId
  #188 = Methodref          #189.#190     // ext/mods/gameserver/model/zone/type/ClanHallZone.banishForeigners:(I)V
  #189 = Class              #191          // ext/mods/gameserver/model/zone/type/ClanHallZone
  #190 = NameAndType        #184:#135     // banishForeigners:(I)V
  #191 = Utf8               ext/mods/gameserver/model/zone/type/ClanHallZone
  #192 = InterfaceMethodref #80.#193      // java/util/Map.clear:()V
  #193 = NameAndType        #194:#11      // clear:()V
  #194 = Utf8               clear
  #195 = Methodref          #196.#197     // ext/mods/commons/pool/ConnectionPool.getConnection:()Ljava/sql/Connection;
  #196 = Class              #198          // ext/mods/commons/pool/ConnectionPool
  #197 = NameAndType        #199:#200     // getConnection:()Ljava/sql/Connection;
  #198 = Utf8               ext/mods/commons/pool/ConnectionPool
  #199 = Utf8               getConnection
  #200 = Utf8               ()Ljava/sql/Connection;
  #201 = String             #202          // DELETE FROM clanhall_functions WHERE hall_id=?
  #202 = Utf8               DELETE FROM clanhall_functions WHERE hall_id=?
  #203 = InterfaceMethodref #204.#205     // java/sql/Connection.prepareStatement:(Ljava/lang/String;)Ljava/sql/PreparedStatement;
  #204 = Class              #206          // java/sql/Connection
  #205 = NameAndType        #207:#208     // prepareStatement:(Ljava/lang/String;)Ljava/sql/PreparedStatement;
  #206 = Utf8               java/sql/Connection
  #207 = Utf8               prepareStatement
  #208 = Utf8               (Ljava/lang/String;)Ljava/sql/PreparedStatement;
  #209 = Methodref          #13.#210      // ext/mods/gameserver/model/residence/clanhall/ClanHall.getId:()I
  #210 = NameAndType        #211:#88      // getId:()I
  #211 = Utf8               getId
  #212 = InterfaceMethodref #213.#214     // java/sql/PreparedStatement.setInt:(II)V
  #213 = Class              #215          // java/sql/PreparedStatement
  #214 = NameAndType        #216:#217     // setInt:(II)V
  #215 = Utf8               java/sql/PreparedStatement
  #216 = Utf8               setInt
  #217 = Utf8               (II)V
  #218 = InterfaceMethodref #213.#219     // java/sql/PreparedStatement.execute:()Z
  #219 = NameAndType        #220:#221     // execute:()Z
  #220 = Utf8               execute
  #221 = Utf8               ()Z
  #222 = InterfaceMethodref #213.#223     // java/sql/PreparedStatement.close:()V
  #223 = NameAndType        #224:#11      // close:()V
  #224 = Utf8               close
  #225 = Class              #226          // java/lang/Throwable
  #226 = Utf8               java/lang/Throwable
  #227 = Methodref          #225.#228     // java/lang/Throwable.addSuppressed:(Ljava/lang/Throwable;)V
  #228 = NameAndType        #229:#230     // addSuppressed:(Ljava/lang/Throwable;)V
  #229 = Utf8               addSuppressed
  #230 = Utf8               (Ljava/lang/Throwable;)V
  #231 = InterfaceMethodref #204.#223     // java/sql/Connection.close:()V
  #232 = Class              #233          // java/lang/Exception
  #233 = Utf8               java/lang/Exception
  #234 = Fieldref           #13.#235      // ext/mods/gameserver/model/residence/clanhall/ClanHall.LOGGER:Lext/mods/commons/logging/CLogger;
  #235 = NameAndType        #236:#237     // LOGGER:Lext/mods/commons/logging/CLogger;
  #236 = Utf8               LOGGER
  #237 = Utf8               Lext/mods/commons/logging/CLogger;
  #238 = String             #239          // Couldn\'t delete all clan hall functions.
  #239 = Utf8               Couldn\'t delete all clan hall functions.
  #240 = Methodref          #241.#242     // ext/mods/commons/logging/CLogger.error:(Ljava/lang/Object;Ljava/lang/Throwable;)V
  #241 = Class              #243          // ext/mods/commons/logging/CLogger
  #242 = NameAndType        #244:#245     // error:(Ljava/lang/Object;Ljava/lang/Throwable;)V
  #243 = Utf8               ext/mods/commons/logging/CLogger
  #244 = Utf8               error
  #245 = Utf8               (Ljava/lang/Object;Ljava/lang/Throwable;)V
  #246 = Methodref          #247.#248     // ext/mods/gameserver/model/actor/Player.destroyItemByItemId:(IIZ)Z
  #247 = Class              #249          // ext/mods/gameserver/model/actor/Player
  #248 = NameAndType        #250:#251     // destroyItemByItemId:(IIZ)Z
  #249 = Utf8               ext/mods/gameserver/model/actor/Player
  #250 = Utf8               destroyItemByItemId
  #251 = Utf8               (IIZ)Z
  #252 = Methodref          #105.#253     // ext/mods/gameserver/model/residence/clanhall/ClanHallFunction."<init>":(Lext/mods/gameserver/model/residence/clanhall/ClanHall;IIIJJ)V
  #253 = NameAndType        #5:#254       // "<init>":(Lext/mods/gameserver/model/residence/clanhall/ClanHall;IIIJJ)V
  #254 = Utf8               (Lext/mods/gameserver/model/residence/clanhall/ClanHall;IIIJJ)V
  #255 = Methodref          #105.#256     // ext/mods/gameserver/model/residence/clanhall/ClanHallFunction.dbSave:()V
  #256 = NameAndType        #257:#11      // dbSave:()V
  #257 = Utf8               dbSave
  #258 = InterfaceMethodref #80.#259      // java/util/Map.put:(Ljava/lang/Object;Ljava/lang/Object;)Ljava/lang/Object;
  #259 = NameAndType        #260:#261     // put:(Ljava/lang/Object;Ljava/lang/Object;)Ljava/lang/Object;
  #260 = Utf8               put
  #261 = Utf8               (Ljava/lang/Object;Ljava/lang/Object;)Ljava/lang/Object;
  #262 = Methodref          #105.#263     // ext/mods/gameserver/model/residence/clanhall/ClanHallFunction.removeFunction:()V
  #263 = NameAndType        #264:#11      // removeFunction:()V
  #264 = Utf8               removeFunction
  #265 = Methodref          #105.#266     // ext/mods/gameserver/model/residence/clanhall/ClanHallFunction.refreshFunction:(II)V
  #266 = NameAndType        #267:#217     // refreshFunction:(II)V
  #267 = Utf8               refreshFunction
  #268 = String             #269          // UPDATE clanhall SET ownerId=?, paidUntil=?, paid=?, sellerBid=?, sellerName=?, sellerClanName=?, endDate=? WHERE id=?
  #269 = Utf8               UPDATE clanhall SET ownerId=?, paidUntil=?, paid=?, sellerBid=?, sellerName=?, sellerClanName=?, endDate=? WHERE id=?
  #270 = InterfaceMethodref #213.#271     // java/sql/PreparedStatement.setLong:(IJ)V
  #271 = NameAndType        #272:#273     // setLong:(IJ)V
  #272 = Utf8               setLong
  #273 = Utf8               (IJ)V
  #274 = Methodref          #154.#275     // ext/mods/gameserver/model/residence/clanhall/Auction.getSeller:()Lext/mods/gameserver/model/residence/clanhall/Seller;
  #275 = NameAndType        #276:#277     // getSeller:()Lext/mods/gameserver/model/residence/clanhall/Seller;
  #276 = Utf8               getSeller
  #277 = Utf8               ()Lext/mods/gameserver/model/residence/clanhall/Seller;
  #278 = Methodref          #279.#280     // ext/mods/gameserver/model/residence/clanhall/Seller.getBid:()I
  #279 = Class              #281          // ext/mods/gameserver/model/residence/clanhall/Seller
  #280 = NameAndType        #282:#88      // getBid:()I
  #281 = Utf8               ext/mods/gameserver/model/residence/clanhall/Seller
  #282 = Utf8               getBid
  #283 = Methodref          #279.#284     // ext/mods/gameserver/model/residence/clanhall/Seller.getName:()Ljava/lang/String;
  #284 = NameAndType        #285:#286     // getName:()Ljava/lang/String;
  #285 = Utf8               getName
  #286 = Utf8               ()Ljava/lang/String;
  #287 = InterfaceMethodref #213.#288     // java/sql/PreparedStatement.setString:(ILjava/lang/String;)V
  #288 = NameAndType        #289:#290     // setString:(ILjava/lang/String;)V
  #289 = Utf8               setString
  #290 = Utf8               (ILjava/lang/String;)V
  #291 = Methodref          #279.#292     // ext/mods/gameserver/model/residence/clanhall/Seller.getClanName:()Ljava/lang/String;
  #292 = NameAndType        #293:#286     // getClanName:()Ljava/lang/String;
  #293 = Utf8               getClanName
  #294 = String             #295          //
  #295 = Utf8
  #296 = Methodref          #154.#297     // ext/mods/gameserver/model/residence/clanhall/Auction.getEndDate:()J
  #297 = NameAndType        #298:#176     // getEndDate:()J
  #298 = Utf8               getEndDate
  #299 = String             #300          // Couldn\'t update clan hall.
  #300 = Utf8               Couldn\'t update clan hall.
  #301 = InvokeDynamic      #0:#302       // #0:run:(Lext/mods/gameserver/model/residence/clanhall/ClanHall;)Ljava/lang/Runnable;
  #302 = NameAndType        #303:#304     // run:(Lext/mods/gameserver/model/residence/clanhall/ClanHall;)Ljava/lang/Runnable;
  #303 = Utf8               run
  #304 = Utf8               (Lext/mods/gameserver/model/residence/clanhall/ClanHall;)Ljava/lang/Runnable;
  #305 = Methodref          #306.#307     // ext/mods/commons/pool/ThreadPool.schedule:(Ljava/lang/Runnable;J)Ljava/util/concurrent/ScheduledFuture;
  #306 = Class              #308          // ext/mods/commons/pool/ThreadPool
  #307 = NameAndType        #309:#310     // schedule:(Ljava/lang/Runnable;J)Ljava/util/concurrent/ScheduledFuture;
  #308 = Utf8               ext/mods/commons/pool/ThreadPool
  #309 = Utf8               schedule
  #310 = Utf8               (Ljava/lang/Runnable;J)Ljava/util/concurrent/ScheduledFuture;
  #311 = Methodref          #13.#312      // ext/mods/gameserver/model/residence/clanhall/ClanHall.isFree:()Z
  #312 = NameAndType        #313:#221     // isFree:()Z
  #313 = Utf8               isFree
  #314 = Methodref          #13.#315      // ext/mods/gameserver/model/residence/clanhall/ClanHall.free:()V
  #315 = NameAndType        #316:#11      // free:()V
  #316 = Utf8               free
  #317 = Methodref          #131.#318     // ext/mods/gameserver/model/pledge/Clan.getWarehouse:()Lext/mods/gameserver/model/itemcontainer/ItemContainer;
  #318 = NameAndType        #319:#320     // getWarehouse:()Lext/mods/gameserver/model/itemcontainer/ItemContainer;
  #319 = Utf8               getWarehouse
  #320 = Utf8               ()Lext/mods/gameserver/model/itemcontainer/ItemContainer;
  #321 = Methodref          #322.#323     // ext/mods/gameserver/model/itemcontainer/ItemContainer.getAdena:()I
  #322 = Class              #324          // ext/mods/gameserver/model/itemcontainer/ItemContainer
  #323 = NameAndType        #325:#88      // getAdena:()I
  #324 = Utf8               ext/mods/gameserver/model/itemcontainer/ItemContainer
  #325 = Utf8               getAdena
  #326 = Methodref          #13.#327      // ext/mods/gameserver/model/residence/clanhall/ClanHall.getLease:()I
  #327 = NameAndType        #328:#88      // getLease:()I
  #328 = Utf8               getLease
  #329 = Methodref          #322.#330     // ext/mods/gameserver/model/itemcontainer/ItemContainer.destroyItemByItemId:(II)Lext/mods/gameserver/model/item/instance/ItemInstance;
  #330 = NameAndType        #250:#331     // destroyItemByItemId:(II)Lext/mods/gameserver/model/item/instance/ItemInstance;
  #331 = Utf8               (II)Lext/mods/gameserver/model/item/instance/ItemInstance;
  #332 = Long               86400000l
  #334 = Fieldref           #335.#336     // ext/mods/gameserver/network/SystemMessageId.PAYMENT_FOR_YOUR_CLAN_HALL_HAS_NOT_BEEN_MADE_PLEASE_MAKE_PAYMENT_TO_YOUR_CLAN_WAREHOUSE_BY_S1_TOMORROW:Lext/mods/gameserver/network/SystemMessageId;
  #335 = Class              #337          // ext/mods/gameserver/network/SystemMessageId
  #336 = NameAndType        #338:#339     // PAYMENT_FOR_YOUR_CLAN_HALL_HAS_NOT_BEEN_MADE_PLEASE_MAKE_PAYMENT_TO_YOUR_CLAN_WAREHOUSE_BY_S1_TOMORROW:Lext/mods/gameserver/network/SystemMessageId;
  #337 = Utf8               ext/mods/gameserver/network/SystemMessageId
  #338 = Utf8               PAYMENT_FOR_YOUR_CLAN_HALL_HAS_NOT_BEEN_MADE_PLEASE_MAKE_PAYMENT_TO_YOUR_CLAN_WAREHOUSE_BY_S1_TOMORROW
  #339 = Utf8               Lext/mods/gameserver/network/SystemMessageId;
  #340 = Methodref          #341.#342     // ext/mods/gameserver/network/serverpackets/SystemMessage.getSystemMessage:(Lext/mods/gameserver/network/SystemMessageId;)Lext/mods/gameserver/network/serverpackets/SystemMessage;
  #341 = Class              #343          // ext/mods/gameserver/network/serverpackets/SystemMessage
  #342 = NameAndType        #344:#345     // getSystemMessage:(Lext/mods/gameserver/network/SystemMessageId;)Lext/mods/gameserver/network/serverpackets/SystemMessage;
  #343 = Utf8               ext/mods/gameserver/network/serverpackets/SystemMessage
  #344 = Utf8               getSystemMessage
  #345 = Utf8               (Lext/mods/gameserver/network/SystemMessageId;)Lext/mods/gameserver/network/serverpackets/SystemMessage;
  #346 = Methodref          #341.#347     // ext/mods/gameserver/network/serverpackets/SystemMessage.addNumber:(I)Lext/mods/gameserver/network/serverpackets/SystemMessage;
  #347 = NameAndType        #348:#349     // addNumber:(I)Lext/mods/gameserver/network/serverpackets/SystemMessage;
  #348 = Utf8               addNumber
  #349 = Utf8               (I)Lext/mods/gameserver/network/serverpackets/SystemMessage;
  #350 = Fieldref           #335.#351     // ext/mods/gameserver/network/SystemMessageId.THE_CLAN_HALL_FEE_IS_ONE_WEEK_OVERDUE_THEREFORE_THE_CLAN_HALL_OWNERSHIP_HAS_BEEN_REVOKED:Lext/mods/gameserver/network/SystemMessageId;
  #351 = NameAndType        #352:#339     // THE_CLAN_HALL_FEE_IS_ONE_WEEK_OVERDUE_THEREFORE_THE_CLAN_HALL_OWNERSHIP_HAS_BEEN_REVOKED:Lext/mods/gameserver/network/SystemMessageId;
  #352 = Utf8               THE_CLAN_HALL_FEE_IS_ONE_WEEK_OVERDUE_THEREFORE_THE_CLAN_HALL_OWNERSHIP_HAS_BEEN_REVOKED
  #353 = Class              #354          // ext/mods/gameserver/model/residence/clanhall/ClanHall$Buff
  #354 = Utf8               ext/mods/gameserver/model/residence/clanhall/ClanHall$Buff
  #355 = Methodref          #353.#356     // ext/mods/gameserver/model/residence/clanhall/ClanHall$Buff."<init>":(IILjava/lang/String;I)V
  #356 = NameAndType        #5:#357       // "<init>":(IILjava/lang/String;I)V
  #357 = Utf8               (IILjava/lang/String;I)V
  #358 = InterfaceMethodref #359.#360     // java/util/List.add:(Ljava/lang/Object;)Z
  #359 = Class              #361          // java/util/List
  #360 = NameAndType        #362:#363     // add:(Ljava/lang/Object;)Z
  #361 = Utf8               java/util/List
  #362 = Utf8               add
  #363 = Utf8               (Ljava/lang/Object;)Z
  #364 = Methodref          #365.#284     // java/lang/Class.getName:()Ljava/lang/String;
  #365 = Class              #366          // java/lang/Class
  #366 = Utf8               java/lang/Class
  #367 = Methodref          #241.#368     // ext/mods/commons/logging/CLogger."<init>":(Ljava/lang/String;)V
  #368 = NameAndType        #5:#369       // "<init>":(Ljava/lang/String;)V
  #369 = Utf8               (Ljava/lang/String;)V
  #370 = Class              #371          // java/util/Map$Entry
  #371 = Utf8               java/util/Map$Entry
  #372 = InterfaceMethodref #80.#373      // java/util/Map.entry:(Ljava/lang/Object;Ljava/lang/Object;)Ljava/util/Map$Entry;
  #373 = NameAndType        #374:#375     // entry:(Ljava/lang/Object;Ljava/lang/Object;)Ljava/util/Map$Entry;
  #374 = Utf8               entry
  #375 = Utf8               (Ljava/lang/Object;Ljava/lang/Object;)Ljava/util/Map$Entry;
  #376 = InterfaceMethodref #80.#377      // java/util/Map.ofEntries:([Ljava/util/Map$Entry;)Ljava/util/Map;
  #377 = NameAndType        #378:#379     // ofEntries:([Ljava/util/Map$Entry;)Ljava/util/Map;
  #378 = Utf8               ofEntries
  #379 = Utf8               ([Ljava/util/Map$Entry;)Ljava/util/Map;
  #380 = Utf8               DELETE_FUNCTIONS
  #381 = Utf8               ConstantValue
  #382 = Utf8               UPDATE_CH
  #383 = Utf8               ONE_DAY
  #384 = Integer            86400000
  #385 = Utf8               ONE_WEEK
  #386 = Integer            604800000
  #387 = Utf8               FUNC_RESTORE_HP
  #388 = Integer            1
  #389 = Utf8               FUNC_RESTORE_MP
  #390 = Integer            2
  #391 = Utf8               FUNC_RESTORE_EXP
  #392 = Integer            4
  #393 = Utf8               FUNC_TELEPORT
  #394 = Integer            5
  #395 = Utf8               FUNC_DECO_CURTAINS
  #396 = Integer            7
  #397 = Utf8               FUNC_SUPPORT
  #398 = Integer            9
  #399 = Utf8               FUNC_DECO_FRONTPLATEFORM
  #400 = Integer            11
  #401 = Utf8               FUNC_ITEM_CREATE
  #402 = Integer            12
  #403 = Utf8               Signature
  #404 = Utf8               Ljava/util/Map<Ljava/lang/Integer;Ljava/lang/Integer;>;
  #405 = Utf8               Ljava/util/Map<Ljava/lang/Integer;Lext/mods/gameserver/model/residence/clanhall/ClanHallFunction;>;
  #406 = Utf8               Ljava/util/concurrent/ScheduledFuture<*>;
  #407 = Utf8               Ljava/util/List<Lext/mods/gameserver/model/residence/clanhall/ClanHall$Buff;>;
  #408 = Utf8               Code
  #409 = Utf8               LineNumberTable
  #410 = Utf8               LocalVariableTable
  #411 = Utf8               this
  #412 = Utf8               Lext/mods/gameserver/model/residence/clanhall/ClanHall;
  #413 = Utf8               set
  #414 = Utf8               Lext/mods/commons/data/StatSet;
  #415 = Utf8               getDesc
  #416 = Utf8               getAuctionMin
  #417 = Utf8               getDeposit
  #418 = Utf8               getSize
  #419 = Utf8               getGrade
  #420 = Utf8               getAuction
  #421 = Utf8               ()Lext/mods/gameserver/model/residence/clanhall/Auction;
  #422 = Utf8               setAuction
  #423 = Utf8               (Lext/mods/gameserver/model/residence/clanhall/Auction;)V
  #424 = Utf8               auction
  #425 = Utf8               getPaidUntil
  #426 = Utf8               setPaidUntil
  #427 = Utf8               (J)V
  #428 = Utf8               paidUntil
  #429 = Utf8               getPaid
  #430 = Utf8               setPaid
  #431 = Utf8               isPaid
  #432 = Utf8               getZone
  #433 = Utf8               ()Lext/mods/gameserver/model/zone/type/ClanHallZone;
  #434 = Utf8               setZone
  #435 = Utf8               (Lext/mods/gameserver/model/zone/type/ClanHallZone;)V
  #436 = Utf8               zone
  #437 = Utf8               getFunctions
  #438 = Utf8               ()Ljava/util/Map;
  #439 = Utf8               ()Ljava/util/Map<Ljava/lang/Integer;Lext/mods/gameserver/model/residence/clanhall/ClanHallFunction;>;
  #440 = Utf8               getFunction
  #441 = Utf8               (I)Lext/mods/gameserver/model/residence/clanhall/ClanHallFunction;
  #442 = Utf8               type
  #443 = Utf8               clan
  #444 = Utf8               Lext/mods/gameserver/model/pledge/Clan;
  #445 = Utf8               StackMapTable
  #446 = Utf8               setOwner
  #447 = Utf8               owner
  #448 = Utf8               ps
  #449 = Utf8               Ljava/sql/PreparedStatement;
  #450 = Utf8               con
  #451 = Utf8               Ljava/sql/Connection;
  #452 = Utf8               e
  #453 = Utf8               Ljava/lang/Exception;
  #454 = Utf8               updateFunction
  #455 = Utf8               (Lext/mods/gameserver/model/actor/Player;IIIJ)Z
  #456 = Utf8               player
  #457 = Utf8               Lext/mods/gameserver/model/actor/Player;
  #458 = Utf8               lvl
  #459 = Utf8               rate
  #460 = Utf8               chf
  #461 = Utf8               Lext/mods/gameserver/model/residence/clanhall/ClanHallFunction;
  #462 = Utf8               time
  #463 = Utf8               payFee
  #464 = Utf8               addBuff
  #465 = Utf8               buffId
  #466 = Utf8               buffLvl
  #467 = Utf8               buffDesc
  #468 = Utf8               buffPrice
  #469 = Utf8               buff
  #470 = Utf8               Lext/mods/gameserver/model/residence/clanhall/ClanHall$Buff;
  #471 = Utf8               getBuffs
  #472 = Utf8               ()Ljava/util/List;
  #473 = Utf8               ()Ljava/util/List<Lext/mods/gameserver/model/residence/clanhall/ClanHall$Buff;>;
  #474 = Utf8               <clinit>
  #475 = Utf8               SourceFile
  #476 = Utf8               ClanHall.java
  #477 = Utf8               NestMembers
  #478 = Utf8               BootstrapMethods
  #479 = MethodType         #11           //  ()V
  #480 = MethodHandle       5:#481        // REF_invokeVirtual ext/mods/gameserver/model/residence/clanhall/ClanHall.payFee:()V
  #481 = Methodref          #13.#482      // ext/mods/gameserver/model/residence/clanhall/ClanHall.payFee:()V
  #482 = NameAndType        #463:#11      // payFee:()V
  #483 = MethodHandle       6:#484        // REF_invokeStatic java/lang/invoke/LambdaMetafactory.metafactory:(Ljava/lang/invoke/MethodHandles$Lookup;Ljava/lang/String;Ljava/lang/invoke/MethodType;Ljava/lang/invoke/MethodType;Ljava/lang/invoke/MethodHandle;Ljava/lang/invoke/MethodType;)Ljava/lang/invoke/CallSite;
  #484 = Methodref          #485.#486     // java/lang/invoke/LambdaMetafactory.metafactory:(Ljava/lang/invoke/MethodHandles$Lookup;Ljava/lang/String;Ljava/lang/invoke/MethodType;Ljava/lang/invoke/MethodType;Ljava/lang/invoke/MethodHandle;Ljava/lang/invoke/MethodType;)Ljava/lang/invoke/CallSite;
  #485 = Class              #487          // java/lang/invoke/LambdaMetafactory
  #486 = NameAndType        #488:#489     // metafactory:(Ljava/lang/invoke/MethodHandles$Lookup;Ljava/lang/String;Ljava/lang/invoke/MethodType;Ljava/lang/invoke/MethodType;Ljava/lang/invoke/MethodHandle;Ljava/lang/invoke/MethodType;)Ljava/lang/invoke/CallSite;
  #487 = Utf8               java/lang/invoke/LambdaMetafactory
  #488 = Utf8               metafactory
  #489 = Utf8               (Ljava/lang/invoke/MethodHandles$Lookup;Ljava/lang/String;Ljava/lang/invoke/MethodType;Ljava/lang/invoke/MethodType;Ljava/lang/invoke/MethodHandle;Ljava/lang/invoke/MethodType;)Ljava/lang/invoke/CallSite;
  #490 = Utf8               InnerClasses
  #491 = Utf8               Buff
  #492 = Utf8               Entry
  #493 = Class              #494          // java/lang/invoke/MethodHandles$Lookup
  #494 = Utf8               java/lang/invoke/MethodHandles$Lookup
  #495 = Class              #496          // java/lang/invoke/MethodHandles
  #496 = Utf8               java/lang/invoke/MethodHandles
  #497 = Utf8               Lookup
{
  protected static final ext.mods.commons.logging.CLogger LOGGER;
    descriptor: Lext/mods/commons/logging/CLogger;
    flags: (0x001c) ACC_PROTECTED, ACC_STATIC, ACC_FINAL

  public static final int FUNC_RESTORE_HP;
    descriptor: I
    flags: (0x0019) ACC_PUBLIC, ACC_STATIC, ACC_FINAL
    ConstantValue: int 1

  public static final int FUNC_RESTORE_MP;
    descriptor: I
    flags: (0x0019) ACC_PUBLIC, ACC_STATIC, ACC_FINAL
    ConstantValue: int 2

  public static final int FUNC_RESTORE_EXP;
    descriptor: I
    flags: (0x0019) ACC_PUBLIC, ACC_STATIC, ACC_FINAL
    ConstantValue: int 4

  public static final int FUNC_TELEPORT;
    descriptor: I
    flags: (0x0019) ACC_PUBLIC, ACC_STATIC, ACC_FINAL
    ConstantValue: int 5

  public static final int FUNC_DECO_CURTAINS;
    descriptor: I
    flags: (0x0019) ACC_PUBLIC, ACC_STATIC, ACC_FINAL
    ConstantValue: int 7

  public static final int FUNC_SUPPORT;
    descriptor: I
    flags: (0x0019) ACC_PUBLIC, ACC_STATIC, ACC_FINAL
    ConstantValue: int 9

  public static final int FUNC_DECO_FRONTPLATEFORM;
    descriptor: I
    flags: (0x0019) ACC_PUBLIC, ACC_STATIC, ACC_FINAL
    ConstantValue: int 11

  public static final int FUNC_ITEM_CREATE;
    descriptor: I
    flags: (0x0019) ACC_PUBLIC, ACC_STATIC, ACC_FINAL
    ConstantValue: int 12

  public ext.mods.gameserver.model.residence.clanhall.ClanHall(ext.mods.commons.data.StatSet);
    descriptor: (Lext/mods/commons/data/StatSet;)V
    flags: (0x0001) ACC_PUBLIC
    Code:
      stack=4, locals=2, args_size=2
         0: aload_0
         1: aload_1
         2: invokespecial #1                  // Method ext/mods/gameserver/model/residence/Residence."<init>":(Lext/mods/commons/data/StatSet;)V
         5: aload_0
         6: new           #7                  // class java/util/concurrent/ConcurrentHashMap
         9: dup
        10: invokespecial #9                  // Method java/util/concurrent/ConcurrentHashMap."<init>":()V
        13: putfield      #12                 // Field _functions:Ljava/util/Map;
        16: aload_0
        17: new           #18                 // class java/util/ArrayList
        20: dup
        21: invokespecial #20                 // Method java/util/ArrayList."<init>":()V
        24: putfield      #21                 // Field _buffs:Ljava/util/List;
        27: aload_0
        28: aload_1
        29: ldc           #25                 // String desc
        31: invokevirtual #27                 // Method ext/mods/commons/data/StatSet.getString:(Ljava/lang/String;)Ljava/lang/String;
        34: putfield      #33                 // Field _desc:Ljava/lang/String;
        37: aload_0
        38: aload_1
        39: ldc           #37                 // String loc
        41: invokevirtual #27                 // Method ext/mods/commons/data/StatSet.getString:(Ljava/lang/String;)Ljava/lang/String;
        44: putfield      #39                 // Field _townName:Ljava/lang/String;
        47: aload_0
        48: aload_1
        49: ldc           #42                 // String auctionMin
        51: iconst_0
        52: invokevirtual #44                 // Method ext/mods/commons/data/StatSet.getInteger:(Ljava/lang/String;I)I
        55: putfield      #48                 // Field _auctionMin:I
        58: aload_0
        59: aload_1
        60: ldc           #52                 // String deposit
        62: iconst_0
        63: invokevirtual #44                 // Method ext/mods/commons/data/StatSet.getInteger:(Ljava/lang/String;I)I
        66: putfield      #54                 // Field _deposit:I
        69: aload_0
        70: aload_1
        71: ldc           #57                 // String lease
        73: iconst_0
        74: invokevirtual #44                 // Method ext/mods/commons/data/StatSet.getInteger:(Ljava/lang/String;I)I
        77: putfield      #59                 // Field _lease:I
        80: aload_0
        81: aload_1
        82: ldc           #62                 // String size
        84: iconst_0
        85: invokevirtual #44                 // Method ext/mods/commons/data/StatSet.getInteger:(Ljava/lang/String;I)I
        88: putfield      #64                 // Field _size:I
        91: return
      LineNumberTable:
        line 136: 0
        line 117: 5
        line 132: 16
        line 138: 27
        line 139: 37
        line 140: 47
        line 141: 58
        line 142: 69
        line 143: 80
        line 144: 91
      LocalVariableTable:
        Start  Length  Slot  Name   Signature
            0      92     0  this   Lext/mods/gameserver/model/residence/clanhall/ClanHall;
            0      92     1   set   Lext/mods/commons/data/StatSet;

  public final java.lang.String getDesc();
    descriptor: ()Ljava/lang/String;
    flags: (0x0011) ACC_PUBLIC, ACC_FINAL
    Code:
      stack=1, locals=1, args_size=1
         0: aload_0
         1: getfield      #33                 // Field _desc:Ljava/lang/String;
         4: areturn
      LineNumberTable:
        line 148: 0
      LocalVariableTable:
        Start  Length  Slot  Name   Signature
            0       5     0  this   Lext/mods/gameserver/model/residence/clanhall/ClanHall;

  public final int getAuctionMin();
    descriptor: ()I
    flags: (0x0011) ACC_PUBLIC, ACC_FINAL
    Code:
      stack=1, locals=1, args_size=1
         0: aload_0
         1: getfield      #48                 // Field _auctionMin:I
         4: ireturn
      LineNumberTable:
        line 153: 0
      LocalVariableTable:
        Start  Length  Slot  Name   Signature
            0       5     0  this   Lext/mods/gameserver/model/residence/clanhall/ClanHall;

  public final int getDeposit();
    descriptor: ()I
    flags: (0x0011) ACC_PUBLIC, ACC_FINAL
    Code:
      stack=1, locals=1, args_size=1
         0: aload_0
         1: getfield      #54                 // Field _deposit:I
         4: ireturn
      LineNumberTable:
        line 158: 0
      LocalVariableTable:
        Start  Length  Slot  Name   Signature
            0       5     0  this   Lext/mods/gameserver/model/residence/clanhall/ClanHall;

  public final int getLease();
    descriptor: ()I
    flags: (0x0011) ACC_PUBLIC, ACC_FINAL
    Code:
      stack=1, locals=1, args_size=1
         0: aload_0
         1: getfield      #59                 // Field _lease:I
         4: ireturn
      LineNumberTable:
        line 163: 0
      LocalVariableTable:
        Start  Length  Slot  Name   Signature
            0       5     0  this   Lext/mods/gameserver/model/residence/clanhall/ClanHall;

  public final int getSize();
    descriptor: ()I
    flags: (0x0011) ACC_PUBLIC, ACC_FINAL
    Code:
      stack=1, locals=1, args_size=1
         0: aload_0
         1: getfield      #64                 // Field _size:I
         4: ireturn
      LineNumberTable:
        line 168: 0
      LocalVariableTable:
        Start  Length  Slot  Name   Signature
            0       5     0  this   Lext/mods/gameserver/model/residence/clanhall/ClanHall;

  public final int getGrade();
    descriptor: ()I
    flags: (0x0011) ACC_PUBLIC, ACC_FINAL
    Code:
      stack=2, locals=1, args_size=1
         0: getstatic     #67                 // Field GRADE_LIST:Ljava/util/Map;
         3: aload_0
         4: getfield      #70                 // Field _id:I
         7: invokestatic  #73                 // Method java/lang/Integer.valueOf:(I)Ljava/lang/Integer;
        10: invokeinterface #79,  2           // InterfaceMethod java/util/Map.get:(Ljava/lang/Object;)Ljava/lang/Object;
        15: checkcast     #74                 // class java/lang/Integer
        18: invokevirtual #85                 // Method java/lang/Integer.intValue:()I
        21: ireturn
      LineNumberTable:
        line 173: 0
      LocalVariableTable:
        Start  Length  Slot  Name   Signature
            0      22     0  this   Lext/mods/gameserver/model/residence/clanhall/ClanHall;

  public final ext.mods.gameserver.model.residence.clanhall.Auction getAuction();
    descriptor: ()Lext/mods/gameserver/model/residence/clanhall/Auction;
    flags: (0x0011) ACC_PUBLIC, ACC_FINAL
    Code:
      stack=1, locals=1, args_size=1
         0: aload_0
         1: getfield      #89                 // Field _auction:Lext/mods/gameserver/model/residence/clanhall/Auction;
         4: areturn
      LineNumberTable:
        line 178: 0
      LocalVariableTable:
        Start  Length  Slot  Name   Signature
            0       5     0  this   Lext/mods/gameserver/model/residence/clanhall/ClanHall;

  public final void setAuction(ext.mods.gameserver.model.residence.clanhall.Auction);
    descriptor: (Lext/mods/gameserver/model/residence/clanhall/Auction;)V
    flags: (0x0011) ACC_PUBLIC, ACC_FINAL
    Code:
      stack=2, locals=2, args_size=2
         0: aload_0
         1: aload_1
         2: putfield      #89                 // Field _auction:Lext/mods/gameserver/model/residence/clanhall/Auction;
         5: return
      LineNumberTable:
        line 183: 0
        line 184: 5
      LocalVariableTable:
        Start  Length  Slot  Name   Signature
            0       6     0  this   Lext/mods/gameserver/model/residence/clanhall/ClanHall;
            0       6     1 auction   Lext/mods/gameserver/model/residence/clanhall/Auction;

  public final long getPaidUntil();
    descriptor: ()J
    flags: (0x0011) ACC_PUBLIC, ACC_FINAL
    Code:
      stack=2, locals=1, args_size=1
         0: aload_0
         1: getfield      #93                 // Field _paidUntil:J
         4: lreturn
      LineNumberTable:
        line 188: 0
      LocalVariableTable:
        Start  Length  Slot  Name   Signature
            0       5     0  this   Lext/mods/gameserver/model/residence/clanhall/ClanHall;

  public void setPaidUntil(long);
    descriptor: (J)V
    flags: (0x0001) ACC_PUBLIC
    Code:
      stack=3, locals=3, args_size=2
         0: aload_0
         1: lload_1
         2: putfield      #93                 // Field _paidUntil:J
         5: return
      LineNumberTable:
        line 193: 0
        line 194: 5
      LocalVariableTable:
        Start  Length  Slot  Name   Signature
            0       6     0  this   Lext/mods/gameserver/model/residence/clanhall/ClanHall;
            0       6     1 paidUntil   J

  public final boolean getPaid();
    descriptor: ()Z
    flags: (0x0011) ACC_PUBLIC, ACC_FINAL
    Code:
      stack=1, locals=1, args_size=1
         0: aload_0
         1: getfield      #97                 // Field _isPaid:Z
         4: ireturn
      LineNumberTable:
        line 198: 0
      LocalVariableTable:
        Start  Length  Slot  Name   Signature
            0       5     0  this   Lext/mods/gameserver/model/residence/clanhall/ClanHall;

  public void setPaid(boolean);
    descriptor: (Z)V
    flags: (0x0001) ACC_PUBLIC
    Code:
      stack=2, locals=2, args_size=2
         0: aload_0
         1: iload_1
         2: putfield      #97                 // Field _isPaid:Z
         5: return
      LineNumberTable:
        line 203: 0
        line 204: 5
      LocalVariableTable:
        Start  Length  Slot  Name   Signature
            0       6     0  this   Lext/mods/gameserver/model/residence/clanhall/ClanHall;
            0       6     1 isPaid   Z

  public ext.mods.gameserver.model.zone.type.ClanHallZone getZone();
    descriptor: ()Lext/mods/gameserver/model/zone/type/ClanHallZone;
    flags: (0x0001) ACC_PUBLIC
    Code:
      stack=1, locals=1, args_size=1
         0: aload_0
         1: getfield      #101                // Field _zone:Lext/mods/gameserver/model/zone/type/ClanHallZone;
         4: areturn
      LineNumberTable:
        line 208: 0
      LocalVariableTable:
        Start  Length  Slot  Name   Signature
            0       5     0  this   Lext/mods/gameserver/model/residence/clanhall/ClanHall;

  public void setZone(ext.mods.gameserver.model.zone.type.ClanHallZone);
    descriptor: (Lext/mods/gameserver/model/zone/type/ClanHallZone;)V
    flags: (0x0001) ACC_PUBLIC
    Code:
      stack=2, locals=2, args_size=2
         0: aload_0
         1: aload_1
         2: putfield      #101                // Field _zone:Lext/mods/gameserver/model/zone/type/ClanHallZone;
         5: return
      LineNumberTable:
        line 213: 0
        line 214: 5
      LocalVariableTable:
        Start  Length  Slot  Name   Signature
            0       6     0  this   Lext/mods/gameserver/model/residence/clanhall/ClanHall;
            0       6     1  zone   Lext/mods/gameserver/model/zone/type/ClanHallZone;

  public final java.util.Map<java.lang.Integer, ext.mods.gameserver.model.residence.clanhall.ClanHallFunction> getFunctions();
    descriptor: ()Ljava/util/Map;
    flags: (0x0011) ACC_PUBLIC, ACC_FINAL
    Code:
      stack=1, locals=1, args_size=1
         0: aload_0
         1: getfield      #12                 // Field _functions:Ljava/util/Map;
         4: areturn
      LineNumberTable:
        line 221: 0
      LocalVariableTable:
        Start  Length  Slot  Name   Signature
            0       5     0  this   Lext/mods/gameserver/model/residence/clanhall/ClanHall;
    Signature: #439                         // ()Ljava/util/Map<Ljava/lang/Integer;Lext/mods/gameserver/model/residence/clanhall/ClanHallFunction;>;

  public ext.mods.gameserver.model.residence.clanhall.ClanHallFunction getFunction(int);
    descriptor: (I)Lext/mods/gameserver/model/residence/clanhall/ClanHallFunction;
    flags: (0x0001) ACC_PUBLIC
    Code:
      stack=2, locals=2, args_size=2
         0: aload_0
         1: getfield      #12                 // Field _functions:Ljava/util/Map;
         4: iload_1
         5: invokestatic  #73                 // Method java/lang/Integer.valueOf:(I)Ljava/lang/Integer;
         8: invokeinterface #79,  2           // InterfaceMethod java/util/Map.get:(Ljava/lang/Object;)Ljava/lang/Object;
        13: checkcast     #105                // class ext/mods/gameserver/model/residence/clanhall/ClanHallFunction
        16: areturn
      LineNumberTable:
        line 230: 0
      LocalVariableTable:
        Start  Length  Slot  Name   Signature
            0      17     0  this   Lext/mods/gameserver/model/residence/clanhall/ClanHall;
            0      17     1  type   I

  public void free();
    descriptor: ()V
    flags: (0x0001) ACC_PUBLIC
    Code:
      stack=7, locals=2, args_size=1
         0: aload_0
         1: getfield      #107                // Field _feeTask:Ljava/util/concurrent/ScheduledFuture;
         4: ifnull        23
         7: aload_0
         8: getfield      #107                // Field _feeTask:Ljava/util/concurrent/ScheduledFuture;
        11: iconst_0
        12: invokeinterface #111,  2          // InterfaceMethod java/util/concurrent/ScheduledFuture.cancel:(Z)Z
        17: pop
        18: aload_0
        19: aconst_null
        20: putfield      #107                // Field _feeTask:Ljava/util/concurrent/ScheduledFuture;
        23: invokestatic  #117                // Method ext/mods/gameserver/data/sql/ClanTable.getInstance:()Lext/mods/gameserver/data/sql/ClanTable;
        26: aload_0
        27: getfield      #123                // Field _ownerId:I
        30: invokevirtual #126                // Method ext/mods/gameserver/data/sql/ClanTable.getClan:(I)Lext/mods/gameserver/model/pledge/Clan;
        33: astore_1
        34: aload_1
        35: ifnull        62
        38: aload_1
        39: iconst_0
        40: invokevirtual #130                // Method ext/mods/gameserver/model/pledge/Clan.setClanHallId:(I)V
        43: aload_1
        44: iconst_1
        45: anewarray     #136                // class ext/mods/gameserver/network/serverpackets/L2GameServerPacket
        48: dup
        49: iconst_0
        50: new           #138                // class ext/mods/gameserver/network/serverpackets/PledgeShowInfoUpdate
        53: dup
        54: aload_1
        55: invokespecial #140                // Method ext/mods/gameserver/network/serverpackets/PledgeShowInfoUpdate."<init>":(Lext/mods/gameserver/model/pledge/Clan;)V
        58: aastore
        59: invokevirtual #143                // Method ext/mods/gameserver/model/pledge/Clan.broadcastToMembers:([Lext/mods/gameserver/network/serverpackets/L2GameServerPacket;)V
        62: aload_0
        63: iconst_0
        64: putfield      #123                // Field _ownerId:I
        67: aload_0
        68: lconst_0
        69: putfield      #93                 // Field _paidUntil:J
        72: aload_0
        73: iconst_0
        74: putfield      #97                 // Field _isPaid:Z
        77: aload_0
        78: invokevirtual #147                // Method removeAllFunctions:()V
        81: aload_0
        82: invokevirtual #150                // Method closeDoors:()V
        85: aload_0
        86: getfield      #89                 // Field _auction:Lext/mods/gameserver/model/residence/clanhall/Auction;
        89: ifnull        115
        92: aload_0
        93: getfield      #89                 // Field _auction:Lext/mods/gameserver/model/residence/clanhall/Auction;
        96: aconst_null
        97: invokevirtual #153                // Method ext/mods/gameserver/model/residence/clanhall/Auction.removeBids:(Lext/mods/gameserver/model/pledge/Clan;)V
       100: aload_0
       101: getfield      #89                 // Field _auction:Lext/mods/gameserver/model/residence/clanhall/Auction;
       104: iconst_1
       105: invokevirtual #158                // Method ext/mods/gameserver/model/residence/clanhall/Auction.reset:(Z)V
       108: aload_0
       109: getfield      #89                 // Field _auction:Lext/mods/gameserver/model/residence/clanhall/Auction;
       112: invokevirtual #162                // Method ext/mods/gameserver/model/residence/clanhall/Auction.startAutoTask:()V
       115: aload_0
       116: invokevirtual #165                // Method updateDb:()V
       119: return
      LineNumberTable:
        line 243: 0
        line 245: 7
        line 246: 18
        line 249: 23
        line 250: 34
        line 252: 38
        line 254: 43
        line 257: 62
        line 258: 67
        line 259: 72
        line 261: 77
        line 263: 81
        line 265: 85
        line 267: 92
        line 269: 100
        line 271: 108
        line 274: 115
        line 275: 119
      LocalVariableTable:
        Start  Length  Slot  Name   Signature
            0     120     0  this   Lext/mods/gameserver/model/residence/clanhall/ClanHall;
           34      86     1  clan   Lext/mods/gameserver/model/pledge/Clan;
      StackMapTable: number_of_entries = 3
        frame_type = 23 /* same */
        frame_type = 252 /* append */
          offset_delta = 38
          locals = [ class ext/mods/gameserver/model/pledge/Clan ]
        frame_type = 52 /* same */

  public void setOwner(ext.mods.gameserver.model.pledge.Clan);
    descriptor: (Lext/mods/gameserver/model/pledge/Clan;)V
    flags: (0x0001) ACC_PUBLIC
    Code:
      stack=7, locals=3, args_size=2
         0: aload_0
         1: getfield      #89                 // Field _auction:Lext/mods/gameserver/model/residence/clanhall/Auction;
         4: ifnull        23
         7: aload_0
         8: getfield      #89                 // Field _auction:Lext/mods/gameserver/model/residence/clanhall/Auction;
        11: aload_1
        12: invokevirtual #153                // Method ext/mods/gameserver/model/residence/clanhall/Auction.removeBids:(Lext/mods/gameserver/model/pledge/Clan;)V
        15: aload_0
        16: getfield      #89                 // Field _auction:Lext/mods/gameserver/model/residence/clanhall/Auction;
        19: iconst_0
        20: invokevirtual #158                // Method ext/mods/gameserver/model/residence/clanhall/Auction.reset:(Z)V
        23: aload_1
        24: ifnonnull     42
        27: aload_0
        28: getfield      #89                 // Field _auction:Lext/mods/gameserver/model/residence/clanhall/Auction;
        31: ifnull        41
        34: aload_0
        35: getfield      #89                 // Field _auction:Lext/mods/gameserver/model/residence/clanhall/Auction;
        38: invokevirtual #162                // Method ext/mods/gameserver/model/residence/clanhall/Auction.startAutoTask:()V
        41: return
        42: invokestatic  #117                // Method ext/mods/gameserver/data/sql/ClanTable.getInstance:()Lext/mods/gameserver/data/sql/ClanTable;
        45: aload_0
        46: getfield      #123                // Field _ownerId:I
        49: invokevirtual #126                // Method ext/mods/gameserver/data/sql/ClanTable.getClan:(I)Lext/mods/gameserver/model/pledge/Clan;
        52: astore_2
        53: aload_2
        54: ifnull        81
        57: aload_2
        58: iconst_0
        59: invokevirtual #130                // Method ext/mods/gameserver/model/pledge/Clan.setClanHallId:(I)V
        62: aload_2
        63: iconst_1
        64: anewarray     #136                // class ext/mods/gameserver/network/serverpackets/L2GameServerPacket
        67: dup
        68: iconst_0
        69: new           #138                // class ext/mods/gameserver/network/serverpackets/PledgeShowInfoUpdate
        72: dup
        73: aload_2
        74: invokespecial #140                // Method ext/mods/gameserver/network/serverpackets/PledgeShowInfoUpdate."<init>":(Lext/mods/gameserver/model/pledge/Clan;)V
        77: aastore
        78: invokevirtual #143                // Method ext/mods/gameserver/model/pledge/Clan.broadcastToMembers:([Lext/mods/gameserver/network/serverpackets/L2GameServerPacket;)V
        81: aload_0
        82: invokevirtual #147                // Method removeAllFunctions:()V
        85: aload_0
        86: invokevirtual #150                // Method closeDoors:()V
        89: aload_1
        90: aload_0
        91: getfield      #70                 // Field _id:I
        94: invokevirtual #130                // Method ext/mods/gameserver/model/pledge/Clan.setClanHallId:(I)V
        97: aload_0
        98: aload_1
        99: invokevirtual #168                // Method ext/mods/gameserver/model/pledge/Clan.getClanId:()I
       102: putfield      #123                // Field _ownerId:I
       105: aload_0
       106: invokestatic  #171                // Method java/lang/System.currentTimeMillis:()J
       109: ldc2_w        #177                // long 604800000l
       112: ladd
       113: putfield      #93                 // Field _paidUntil:J
       116: aload_0
       117: iconst_1
       118: putfield      #97                 // Field _isPaid:Z
       121: aload_0
       122: invokevirtual #179                // Method initializeFeeTask:()V
       125: aload_1
       126: iconst_1
       127: anewarray     #136                // class ext/mods/gameserver/network/serverpackets/L2GameServerPacket
       130: dup
       131: iconst_0
       132: new           #138                // class ext/mods/gameserver/network/serverpackets/PledgeShowInfoUpdate
       135: dup
       136: aload_1
       137: invokespecial #140                // Method ext/mods/gameserver/network/serverpackets/PledgeShowInfoUpdate."<init>":(Lext/mods/gameserver/model/pledge/Clan;)V
       140: aastore
       141: invokevirtual #143                // Method ext/mods/gameserver/model/pledge/Clan.broadcastToMembers:([Lext/mods/gameserver/network/serverpackets/L2GameServerPacket;)V
       144: aload_0
       145: invokevirtual #182                // Method banishForeigners:()V
       148: aload_0
       149: invokevirtual #165                // Method updateDb:()V
       152: return
      LineNumberTable:
        line 283: 0
        line 285: 7
        line 287: 15
        line 290: 23
        line 292: 27
        line 293: 34
        line 295: 41
        line 298: 42
        line 299: 53
        line 301: 57
        line 303: 62
        line 306: 81
        line 308: 85
        line 310: 89
        line 312: 97
        line 313: 105
        line 314: 116
        line 316: 121
        line 318: 125
        line 320: 144
        line 322: 148
        line 323: 152
      LocalVariableTable:
        Start  Length  Slot  Name   Signature
            0     153     0  this   Lext/mods/gameserver/model/residence/clanhall/ClanHall;
            0     153     1  clan   Lext/mods/gameserver/model/pledge/Clan;
           53     100     2 owner   Lext/mods/gameserver/model/pledge/Clan;
      StackMapTable: number_of_entries = 4
        frame_type = 23 /* same */
        frame_type = 17 /* same */
        frame_type = 0 /* same */
        frame_type = 252 /* append */
          offset_delta = 38
          locals = [ class ext/mods/gameserver/model/pledge/Clan ]

  public void banishForeigners();
    descriptor: ()V
    flags: (0x0001) ACC_PUBLIC
    Code:
      stack=2, locals=1, args_size=1
         0: aload_0
         1: getfield      #101                // Field _zone:Lext/mods/gameserver/model/zone/type/ClanHallZone;
         4: ifnull        18
         7: aload_0
         8: getfield      #101                // Field _zone:Lext/mods/gameserver/model/zone/type/ClanHallZone;
        11: aload_0
        12: invokevirtual #185                // Method getOwnerId:()I
        15: invokevirtual #188                // Method ext/mods/gameserver/model/zone/type/ClanHallZone.banishForeigners:(I)V
        18: return
      LineNumberTable:
        line 330: 0
        line 331: 7
        line 332: 18
      LocalVariableTable:
        Start  Length  Slot  Name   Signature
            0      19     0  this   Lext/mods/gameserver/model/residence/clanhall/ClanHall;
      StackMapTable: number_of_entries = 1
        frame_type = 18 /* same */

  public void removeAllFunctions();
    descriptor: ()V
    flags: (0x0001) ACC_PUBLIC
    Code:
      stack=3, locals=5, args_size=1
         0: aload_0
         1: getfield      #12                 // Field _functions:Ljava/util/Map;
         4: invokeinterface #192,  1          // InterfaceMethod java/util/Map.clear:()V
         9: invokestatic  #195                // Method ext/mods/commons/pool/ConnectionPool.getConnection:()Ljava/sql/Connection;
        12: astore_1
        13: aload_1
        14: ldc           #201                // String DELETE FROM clanhall_functions WHERE hall_id=?
        16: invokeinterface #203,  2          // InterfaceMethod java/sql/Connection.prepareStatement:(Ljava/lang/String;)Ljava/sql/PreparedStatement;
        21: astore_2
        22: aload_2
        23: iconst_1
        24: aload_0
        25: invokevirtual #209                // Method getId:()I
        28: invokeinterface #212,  3          // InterfaceMethod java/sql/PreparedStatement.setInt:(II)V
        33: aload_2
        34: invokeinterface #218,  1          // InterfaceMethod java/sql/PreparedStatement.execute:()Z
        39: pop
        40: aload_2
        41: ifnull        77
        44: aload_2
        45: invokeinterface #222,  1          // InterfaceMethod java/sql/PreparedStatement.close:()V
        50: goto          77
        53: astore_3
        54: aload_2
        55: ifnull        75
        58: aload_2
        59: invokeinterface #222,  1          // InterfaceMethod java/sql/PreparedStatement.close:()V
        64: goto          75
        67: astore        4
        69: aload_3
        70: aload         4
        72: invokevirtual #227                // Method java/lang/Throwable.addSuppressed:(Ljava/lang/Throwable;)V
        75: aload_3
        76: athrow
        77: aload_1
        78: ifnull        112
        81: aload_1
        82: invokeinterface #231,  1          // InterfaceMethod java/sql/Connection.close:()V
        87: goto          112
        90: astore_2
        91: aload_1
        92: ifnull        110
        95: aload_1
        96: invokeinterface #231,  1          // InterfaceMethod java/sql/Connection.close:()V
       101: goto          110
       104: astore_3
       105: aload_2
       106: aload_3
       107: invokevirtual #227                // Method java/lang/Throwable.addSuppressed:(Ljava/lang/Throwable;)V
       110: aload_2
       111: athrow
       112: goto          125
       115: astore_1
       116: getstatic     #234                // Field LOGGER:Lext/mods/commons/logging/CLogger;
       119: ldc           #238                // String Couldn\'t delete all clan hall functions.
       121: aload_1
       122: invokevirtual #240                // Method ext/mods/commons/logging/CLogger.error:(Ljava/lang/Object;Ljava/lang/Throwable;)V
       125: return
      Exception table:
         from    to  target type
            22    40    53   Class java/lang/Throwable
            58    64    67   Class java/lang/Throwable
            13    77    90   Class java/lang/Throwable
            95   101   104   Class java/lang/Throwable
             9   112   115   Class java/lang/Exception
      LineNumberTable:
        line 339: 0
        line 341: 9
        line 342: 13
        line 344: 22
        line 345: 33
        line 346: 40
        line 341: 53
        line 346: 77
        line 341: 90
        line 350: 112
        line 347: 115
        line 349: 116
        line 351: 125
      LocalVariableTable:
        Start  Length  Slot  Name   Signature
           22      55     2    ps   Ljava/sql/PreparedStatement;
           13      99     1   con   Ljava/sql/Connection;
          116       9     1     e   Ljava/lang/Exception;
            0     126     0  this   Lext/mods/gameserver/model/residence/clanhall/ClanHall;
      StackMapTable: number_of_entries = 10
        frame_type = 255 /* full_frame */
          offset_delta = 53
          locals = [ class ext/mods/gameserver/model/residence/clanhall/ClanHall, class java/sql/Connection, class java/sql/PreparedStatement ]
          stack = [ class java/lang/Throwable ]
        frame_type = 255 /* full_frame */
          offset_delta = 13
          locals = [ class ext/mods/gameserver/model/residence/clanhall/ClanHall, class java/sql/Connection, class java/sql/PreparedStatement, class java/lang/Throwable ]
          stack = [ class java/lang/Throwable ]
        frame_type = 7 /* same */
        frame_type = 249 /* chop */
          offset_delta = 1
        frame_type = 76 /* same_locals_1_stack_item */
          stack = [ class java/lang/Throwable ]
        frame_type = 255 /* full_frame */
          offset_delta = 13
          locals = [ class ext/mods/gameserver/model/residence/clanhall/ClanHall, class java/sql/Connection, class java/lang/Throwable ]
          stack = [ class java/lang/Throwable ]
        frame_type = 5 /* same */
        frame_type = 249 /* chop */
          offset_delta = 1
        frame_type = 66 /* same_locals_1_stack_item */
          stack = [ class java/lang/Exception ]
        frame_type = 9 /* same */

  public boolean updateFunction(ext.mods.gameserver.model.actor.Player, int, int, int, long);
    descriptor: (Lext/mods/gameserver/model/actor/Player;IIIJ)Z
    flags: (0x0001) ACC_PUBLIC
    Code:
      stack=12, locals=8, args_size=6
         0: aload_1
         1: ifnonnull     6
         4: iconst_0
         5: ireturn
         6: iload         4
         8: ifle          25
        11: aload_1
        12: bipush        57
        14: iload         4
        16: iconst_1
        17: invokevirtual #246                // Method ext/mods/gameserver/model/actor/Player.destroyItemByItemId:(IIZ)Z
        20: ifne          25
        23: iconst_0
        24: ireturn
        25: aload_0
        26: getfield      #12                 // Field _functions:Ljava/util/Map;
        29: iload_2
        30: invokestatic  #73                 // Method java/lang/Integer.valueOf:(I)Ljava/lang/Integer;
        33: invokeinterface #79,  2           // InterfaceMethod java/util/Map.get:(Ljava/lang/Object;)Ljava/lang/Object;
        38: checkcast     #105                // class ext/mods/gameserver/model/residence/clanhall/ClanHallFunction
        41: astore        7
        43: aload         7
        45: ifnonnull     93
        48: new           #105                // class ext/mods/gameserver/model/residence/clanhall/ClanHallFunction
        51: dup
        52: aload_0
        53: iload_2
        54: iload_3
        55: iload         4
        57: lload         5
        59: invokestatic  #171                // Method java/lang/System.currentTimeMillis:()J
        62: lload         5
        64: ladd
        65: invokespecial #252                // Method ext/mods/gameserver/model/residence/clanhall/ClanHallFunction."<init>":(Lext/mods/gameserver/model/residence/clanhall/ClanHall;IIIJJ)V
        68: astore        7
        70: aload         7
        72: invokevirtual #255                // Method ext/mods/gameserver/model/residence/clanhall/ClanHallFunction.dbSave:()V
        75: aload_0
        76: getfield      #12                 // Field _functions:Ljava/util/Map;
        79: iload_2
        80: invokestatic  #73                 // Method java/lang/Integer.valueOf:(I)Ljava/lang/Integer;
        83: aload         7
        85: invokeinterface #258,  3          // InterfaceMethod java/util/Map.put:(Ljava/lang/Object;Ljava/lang/Object;)Ljava/lang/Object;
        90: pop
        91: iconst_1
        92: ireturn
        93: iload_3
        94: ifne          110
        97: iload         4
        99: ifne          110
       102: aload         7
       104: invokevirtual #262                // Method ext/mods/gameserver/model/residence/clanhall/ClanHallFunction.removeFunction:()V
       107: goto          118
       110: aload         7
       112: iload         4
       114: iload_3
       115: invokevirtual #265                // Method ext/mods/gameserver/model/residence/clanhall/ClanHallFunction.refreshFunction:(II)V
       118: iconst_1
       119: ireturn
      LineNumberTable:
        line 364: 0
        line 365: 4
        line 367: 6
        line 368: 23
        line 370: 25
        line 371: 43
        line 373: 48
        line 374: 70
        line 376: 75
        line 378: 91
        line 381: 93
        line 382: 102
        line 384: 110
        line 386: 118
      LocalVariableTable:
        Start  Length  Slot  Name   Signature
            0     120     0  this   Lext/mods/gameserver/model/residence/clanhall/ClanHall;
            0     120     1 player   Lext/mods/gameserver/model/actor/Player;
            0     120     2  type   I
            0     120     3   lvl   I
            0     120     4 lease   I
            0     120     5  rate   J
           43      77     7   chf   Lext/mods/gameserver/model/residence/clanhall/ClanHallFunction;
      StackMapTable: number_of_entries = 5
        frame_type = 6 /* same */
        frame_type = 18 /* same */
        frame_type = 252 /* append */
          offset_delta = 67
          locals = [ class ext/mods/gameserver/model/residence/clanhall/ClanHallFunction ]
        frame_type = 16 /* same */
        frame_type = 7 /* same */

  public void updateDb();
    descriptor: ()V
    flags: (0x0001) ACC_PUBLIC
    Code:
      stack=4, locals=5, args_size=1
         0: invokestatic  #195                // Method ext/mods/commons/pool/ConnectionPool.getConnection:()Ljava/sql/Connection;
         3: astore_1
         4: aload_1
         5: ldc_w         #268                // String UPDATE clanhall SET ownerId=?, paidUntil=?, paid=?, sellerBid=?, sellerName=?, sellerClanName=?, endDate=? WHERE id=?
         8: invokeinterface #203,  2          // InterfaceMethod java/sql/Connection.prepareStatement:(Ljava/lang/String;)Ljava/sql/PreparedStatement;
        13: astore_2
        14: aload_2
        15: iconst_1
        16: aload_0
        17: getfield      #123                // Field _ownerId:I
        20: invokeinterface #212,  3          // InterfaceMethod java/sql/PreparedStatement.setInt:(II)V
        25: aload_2
        26: iconst_2
        27: aload_0
        28: getfield      #93                 // Field _paidUntil:J
        31: invokeinterface #270,  4          // InterfaceMethod java/sql/PreparedStatement.setLong:(IJ)V
        36: aload_2
        37: iconst_3
        38: aload_0
        39: getfield      #97                 // Field _isPaid:Z
        42: ifeq          49
        45: iconst_1
        46: goto          50
        49: iconst_0
        50: invokeinterface #212,  3          // InterfaceMethod java/sql/PreparedStatement.setInt:(II)V
        55: aload_0
        56: getfield      #89                 // Field _auction:Lext/mods/gameserver/model/residence/clanhall/Auction;
        59: ifnull        174
        62: aload_0
        63: getfield      #89                 // Field _auction:Lext/mods/gameserver/model/residence/clanhall/Auction;
        66: invokevirtual #274                // Method ext/mods/gameserver/model/residence/clanhall/Auction.getSeller:()Lext/mods/gameserver/model/residence/clanhall/Seller;
        69: ifnull        127
        72: aload_2
        73: iconst_4
        74: aload_0
        75: getfield      #89                 // Field _auction:Lext/mods/gameserver/model/residence/clanhall/Auction;
        78: invokevirtual #274                // Method ext/mods/gameserver/model/residence/clanhall/Auction.getSeller:()Lext/mods/gameserver/model/residence/clanhall/Seller;
        81: invokevirtual #278                // Method ext/mods/gameserver/model/residence/clanhall/Seller.getBid:()I
        84: invokeinterface #212,  3          // InterfaceMethod java/sql/PreparedStatement.setInt:(II)V
        89: aload_2
        90: iconst_5
        91: aload_0
        92: getfield      #89                 // Field _auction:Lext/mods/gameserver/model/residence/clanhall/Auction;
        95: invokevirtual #274                // Method ext/mods/gameserver/model/residence/clanhall/Auction.getSeller:()Lext/mods/gameserver/model/residence/clanhall/Seller;
        98: invokevirtual #283                // Method ext/mods/gameserver/model/residence/clanhall/Seller.getName:()Ljava/lang/String;
       101: invokeinterface #287,  3          // InterfaceMethod java/sql/PreparedStatement.setString:(ILjava/lang/String;)V
       106: aload_2
       107: bipush        6
       109: aload_0
       110: getfield      #89                 // Field _auction:Lext/mods/gameserver/model/residence/clanhall/Auction;
       113: invokevirtual #274                // Method ext/mods/gameserver/model/residence/clanhall/Auction.getSeller:()Lext/mods/gameserver/model/residence/clanhall/Seller;
       116: invokevirtual #291                // Method ext/mods/gameserver/model/residence/clanhall/Seller.getClanName:()Ljava/lang/String;
       119: invokeinterface #287,  3          // InterfaceMethod java/sql/PreparedStatement.setString:(ILjava/lang/String;)V
       124: goto          156
       127: aload_2
       128: iconst_4
       129: iconst_0
       130: invokeinterface #212,  3          // InterfaceMethod java/sql/PreparedStatement.setInt:(II)V
       135: aload_2
       136: iconst_5
       137: ldc_w         #294                // String
       140: invokeinterface #287,  3          // InterfaceMethod java/sql/PreparedStatement.setString:(ILjava/lang/String;)V
       145: aload_2
       146: bipush        6
       148: ldc_w         #294                // String
       151: invokeinterface #287,  3          // InterfaceMethod java/sql/PreparedStatement.setString:(ILjava/lang/String;)V
       156: aload_2
       157: bipush        7
       159: aload_0
       160: getfield      #89                 // Field _auction:Lext/mods/gameserver/model/residence/clanhall/Auction;
       163: invokevirtual #296                // Method ext/mods/gameserver/model/residence/clanhall/Auction.getEndDate:()J
       166: invokeinterface #270,  4          // InterfaceMethod java/sql/PreparedStatement.setLong:(IJ)V
       171: goto          212
       174: aload_2
       175: iconst_4
       176: iconst_0
       177: invokeinterface #212,  3          // InterfaceMethod java/sql/PreparedStatement.setInt:(II)V
       182: aload_2
       183: iconst_5
       184: ldc_w         #294                // String
       187: invokeinterface #287,  3          // InterfaceMethod java/sql/PreparedStatement.setString:(ILjava/lang/String;)V
       192: aload_2
       193: bipush        6
       195: ldc_w         #294                // String
       198: invokeinterface #287,  3          // InterfaceMethod java/sql/PreparedStatement.setString:(ILjava/lang/String;)V
       203: aload_2
       204: bipush        7
       206: lconst_0
       207: invokeinterface #270,  4          // InterfaceMethod java/sql/PreparedStatement.setLong:(IJ)V
       212: aload_2
       213: bipush        8
       215: aload_0
       216: getfield      #70                 // Field _id:I
       219: invokeinterface #212,  3          // InterfaceMethod java/sql/PreparedStatement.setInt:(II)V
       224: aload_2
       225: invokeinterface #218,  1          // InterfaceMethod java/sql/PreparedStatement.execute:()Z
       230: pop
       231: aload_2
       232: ifnull        268
       235: aload_2
       236: invokeinterface #222,  1          // InterfaceMethod java/sql/PreparedStatement.close:()V
       241: goto          268
       244: astore_3
       245: aload_2
       246: ifnull        266
       249: aload_2
       250: invokeinterface #222,  1          // InterfaceMethod java/sql/PreparedStatement.close:()V
       255: goto          266
       258: astore        4
       260: aload_3
       261: aload         4
       263: invokevirtual #227                // Method java/lang/Throwable.addSuppressed:(Ljava/lang/Throwable;)V
       266: aload_3
       267: athrow
       268: aload_1
       269: ifnull        303
       272: aload_1
       273: invokeinterface #231,  1          // InterfaceMethod java/sql/Connection.close:()V
       278: goto          303
       281: astore_2
       282: aload_1
       283: ifnull        301
       286: aload_1
       287: invokeinterface #231,  1          // InterfaceMethod java/sql/Connection.close:()V
       292: goto          301
       295: astore_3
       296: aload_2
       297: aload_3
       298: invokevirtual #227                // Method java/lang/Throwable.addSuppressed:(Ljava/lang/Throwable;)V
       301: aload_2
       302: athrow
       303: goto          317
       306: astore_1
       307: getstatic     #234                // Field LOGGER:Lext/mods/commons/logging/CLogger;
       310: ldc_w         #299                // String Couldn\'t update clan hall.
       313: aload_1
       314: invokevirtual #240                // Method ext/mods/commons/logging/CLogger.error:(Ljava/lang/Object;Ljava/lang/Throwable;)V
       317: return
      Exception table:
         from    to  target type
            14   231   244   Class java/lang/Throwable
           249   255   258   Class java/lang/Throwable
             4   268   281   Class java/lang/Throwable
           286   292   295   Class java/lang/Throwable
             0   303   306   Class java/lang/Exception
      LineNumberTable:
        line 394: 0
        line 395: 4
        line 397: 14
        line 398: 25
        line 399: 36
        line 401: 55
        line 403: 62
        line 405: 72
        line 406: 89
        line 407: 106
        line 411: 127
        line 412: 135
        line 413: 145
        line 415: 156
        line 419: 174
        line 420: 182
        line 421: 192
        line 422: 203
        line 424: 212
        line 425: 224
        line 426: 231
        line 394: 244
        line 426: 268
        line 394: 281
        line 430: 303
        line 427: 306
        line 429: 307
        line 431: 317
      LocalVariableTable:
        Start  Length  Slot  Name   Signature
           14     254     2    ps   Ljava/sql/PreparedStatement;
            4     299     1   con   Ljava/sql/Connection;
          307      10     1     e   Ljava/lang/Exception;
            0     318     0  this   Lext/mods/gameserver/model/residence/clanhall/ClanHall;
      StackMapTable: number_of_entries = 16
        frame_type = 255 /* full_frame */
          offset_delta = 49
          locals = [ class ext/mods/gameserver/model/residence/clanhall/ClanHall, class java/sql/Connection, class java/sql/PreparedStatement ]
          stack = [ class java/sql/PreparedStatement, int ]
        frame_type = 255 /* full_frame */
          offset_delta = 0
          locals = [ class ext/mods/gameserver/model/residence/clanhall/ClanHall, class java/sql/Connection, class java/sql/PreparedStatement ]
          stack = [ class java/sql/PreparedStatement, int, int ]
        frame_type = 251 /* same_frame_extended */
          offset_delta = 76
        frame_type = 28 /* same */
        frame_type = 17 /* same */
        frame_type = 37 /* same */
        frame_type = 95 /* same_locals_1_stack_item */
          stack = [ class java/lang/Throwable ]
        frame_type = 255 /* full_frame */
          offset_delta = 13
          locals = [ class ext/mods/gameserver/model/residence/clanhall/ClanHall, class java/sql/Connection, class java/sql/PreparedStatement, class java/lang/Throwable ]
          stack = [ class java/lang/Throwable ]
        frame_type = 7 /* same */
        frame_type = 249 /* chop */
          offset_delta = 1
        frame_type = 76 /* same_locals_1_stack_item */
          stack = [ class java/lang/Throwable ]
        frame_type = 255 /* full_frame */
          offset_delta = 13
          locals = [ class ext/mods/gameserver/model/residence/clanhall/ClanHall, class java/sql/Connection, class java/lang/Throwable ]
          stack = [ class java/lang/Throwable ]
        frame_type = 5 /* same */
        frame_type = 249 /* chop */
          offset_delta = 1
        frame_type = 66 /* same_locals_1_stack_item */
          stack = [ class java/lang/Exception ]
        frame_type = 10 /* same */

  public void initializeFeeTask();
    descriptor: ()V
    flags: (0x0001) ACC_PUBLIC
    Code:
      stack=4, locals=3, args_size=1
         0: aload_0
         1: getfield      #107                // Field _feeTask:Ljava/util/concurrent/ScheduledFuture;
         4: ifnull        18
         7: aload_0
         8: getfield      #107                // Field _feeTask:Ljava/util/concurrent/ScheduledFuture;
        11: iconst_0
        12: invokeinterface #111,  2          // InterfaceMethod java/util/concurrent/ScheduledFuture.cancel:(Z)Z
        17: pop
        18: invokestatic  #171                // Method java/lang/System.currentTimeMillis:()J
        21: lstore_1
        22: aload_0
        23: getfield      #93                 // Field _paidUntil:J
        26: lload_1
        27: lcmp
        28: ifle          40
        31: aload_0
        32: getfield      #93                 // Field _paidUntil:J
        35: lload_1
        36: lsub
        37: goto          41
        40: lconst_0
        41: lstore_1
        42: aload_0
        43: aload_0
        44: invokedynamic #301,  0            // InvokeDynamic #0:run:(Lext/mods/gameserver/model/residence/clanhall/ClanHall;)Ljava/lang/Runnable;
        49: lload_1
        50: invokestatic  #305                // Method ext/mods/commons/pool/ThreadPool.schedule:(Ljava/lang/Runnable;J)Ljava/util/concurrent/ScheduledFuture;
        53: putfield      #107                // Field _feeTask:Ljava/util/concurrent/ScheduledFuture;
        56: return
      LineNumberTable:
        line 438: 0
        line 439: 7
        line 441: 18
        line 443: 22
        line 445: 42
        line 446: 56
      LocalVariableTable:
        Start  Length  Slot  Name   Signature
            0      57     0  this   Lext/mods/gameserver/model/residence/clanhall/ClanHall;
           22      35     1  time   J
      StackMapTable: number_of_entries = 3
        frame_type = 18 /* same */
        frame_type = 252 /* append */
          offset_delta = 21
          locals = [ long ]
        frame_type = 64 /* same_locals_1_stack_item */
          stack = [ long ]

  public void addBuff(int, int, java.lang.String, int);
    descriptor: (IILjava/lang/String;I)V
    flags: (0x0001) ACC_PUBLIC
    Code:
      stack=6, locals=6, args_size=5
         0: new           #353                // class ext/mods/gameserver/model/residence/clanhall/ClanHall$Buff
         3: dup
         4: iload_1
         5: iload_2
         6: aload_3
         7: iload         4
         9: invokespecial #355                // Method ext/mods/gameserver/model/residence/clanhall/ClanHall$Buff."<init>":(IILjava/lang/String;I)V
        12: astore        5
        14: aload_0
        15: getfield      #21                 // Field _buffs:Ljava/util/List;
        18: aload         5
        20: invokeinterface #358,  2          // InterfaceMethod java/util/List.add:(Ljava/lang/Object;)Z
        25: pop
        26: return
      LineNumberTable:
        line 492: 0
        line 493: 14
        line 494: 26
      LocalVariableTable:
        Start  Length  Slot  Name   Signature
            0      27     0  this   Lext/mods/gameserver/model/residence/clanhall/ClanHall;
            0      27     1 buffId   I
            0      27     2 buffLvl   I
            0      27     3 buffDesc   Ljava/lang/String;
            0      27     4 buffPrice   I
           14      13     5  buff   Lext/mods/gameserver/model/residence/clanhall/ClanHall$Buff;

  public java.util.List<ext.mods.gameserver.model.residence.clanhall.ClanHall$Buff> getBuffs();
    descriptor: ()Ljava/util/List;
    flags: (0x0001) ACC_PUBLIC
    Code:
      stack=1, locals=1, args_size=1
         0: aload_0
         1: getfield      #21                 // Field _buffs:Ljava/util/List;
         4: areturn
      LineNumberTable:
        line 498: 0
      LocalVariableTable:
        Start  Length  Slot  Name   Signature
            0       5     0  this   Lext/mods/gameserver/model/residence/clanhall/ClanHall;
    Signature: #473                         // ()Ljava/util/List<Lext/mods/gameserver/model/residence/clanhall/ClanHall$Buff;>;

  static {};
    descriptor: ()V
    flags: (0x0008) ACC_STATIC
    Code:
      stack=5, locals=0, args_size=0
         0: new           #241                // class ext/mods/commons/logging/CLogger
         3: dup
         4: ldc           #13                 // class ext/mods/gameserver/model/residence/clanhall/ClanHall
         6: invokevirtual #364                // Method java/lang/Class.getName:()Ljava/lang/String;
         9: invokespecial #367                // Method ext/mods/commons/logging/CLogger."<init>":(Ljava/lang/String;)V
        12: putstatic     #234                // Field LOGGER:Lext/mods/commons/logging/CLogger;
        15: bipush        44
        17: anewarray     #370                // class java/util/Map$Entry
        20: dup
        21: iconst_0
        22: bipush        21
        24: invokestatic  #73                 // Method java/lang/Integer.valueOf:(I)Ljava/lang/Integer;
        27: iconst_2
        28: invokestatic  #73                 // Method java/lang/Integer.valueOf:(I)Ljava/lang/Integer;
        31: invokestatic  #372                // InterfaceMethod java/util/Map.entry:(Ljava/lang/Object;Ljava/lang/Object;)Ljava/util/Map$Entry;
        34: aastore
        35: dup
        36: iconst_1
        37: bipush        22
        39: invokestatic  #73                 // Method java/lang/Integer.valueOf:(I)Ljava/lang/Integer;
        42: iconst_2
        43: invokestatic  #73                 // Method java/lang/Integer.valueOf:(I)Ljava/lang/Integer;
        46: invokestatic  #372                // InterfaceMethod java/util/Map.entry:(Ljava/lang/Object;Ljava/lang/Object;)Ljava/util/Map$Entry;
        49: aastore
        50: dup
        51: iconst_2
        52: bipush        23
        54: invokestatic  #73                 // Method java/lang/Integer.valueOf:(I)Ljava/lang/Integer;
        57: iconst_2
        58: invokestatic  #73                 // Method java/lang/Integer.valueOf:(I)Ljava/lang/Integer;
        61: invokestatic  #372                // InterfaceMethod java/util/Map.entry:(Ljava/lang/Object;Ljava/lang/Object;)Ljava/util/Map$Entry;
        64: aastore
        65: dup
        66: iconst_3
        67: bipush        24
        69: invokestatic  #73                 // Method java/lang/Integer.valueOf:(I)Ljava/lang/Integer;
        72: iconst_2
        73: invokestatic  #73                 // Method java/lang/Integer.valueOf:(I)Ljava/lang/Integer;
        76: invokestatic  #372                // InterfaceMethod java/util/Map.entry:(Ljava/lang/Object;Ljava/lang/Object;)Ljava/util/Map$Entry;
        79: aastore
        80: dup
        81: iconst_4
        82: bipush        25
        84: invokestatic  #73                 // Method java/lang/Integer.valueOf:(I)Ljava/lang/Integer;
        87: iconst_2
        88: invokestatic  #73                 // Method java/lang/Integer.valueOf:(I)Ljava/lang/Integer;
        91: invokestatic  #372                // InterfaceMethod java/util/Map.entry:(Ljava/lang/Object;Ljava/lang/Object;)Ljava/util/Map$Entry;
        94: aastore
        95: dup
        96: iconst_5
        97: bipush        26
        99: invokestatic  #73                 // Method java/lang/Integer.valueOf:(I)Ljava/lang/Integer;
       102: iconst_2
       103: invokestatic  #73                 // Method java/lang/Integer.valueOf:(I)Ljava/lang/Integer;
       106: invokestatic  #372                // InterfaceMethod java/util/Map.entry:(Ljava/lang/Object;Ljava/lang/Object;)Ljava/util/Map$Entry;
       109: aastore
       110: dup
       111: bipush        6
       113: bipush        27
       115: invokestatic  #73                 // Method java/lang/Integer.valueOf:(I)Ljava/lang/Integer;
       118: iconst_2
       119: invokestatic  #73                 // Method java/lang/Integer.valueOf:(I)Ljava/lang/Integer;
       122: invokestatic  #372                // InterfaceMethod java/util/Map.entry:(Ljava/lang/Object;Ljava/lang/Object;)Ljava/util/Map$Entry;
       125: aastore
       126: dup
       127: bipush        7
       129: bipush        28
       131: invokestatic  #73                 // Method java/lang/Integer.valueOf:(I)Ljava/lang/Integer;
       134: iconst_2
       135: invokestatic  #73                 // Method java/lang/Integer.valueOf:(I)Ljava/lang/Integer;
       138: invokestatic  #372                // InterfaceMethod java/util/Map.entry:(Ljava/lang/Object;Ljava/lang/Object;)Ljava/util/Map$Entry;
       141: aastore
       142: dup
       143: bipush        8
       145: bipush        29
       147: invokestatic  #73                 // Method java/lang/Integer.valueOf:(I)Ljava/lang/Integer;
       150: iconst_2
       151: invokestatic  #73                 // Method java/lang/Integer.valueOf:(I)Ljava/lang/Integer;
       154: invokestatic  #372                // InterfaceMethod java/util/Map.entry:(Ljava/lang/Object;Ljava/lang/Object;)Ljava/util/Map$Entry;
       157: aastore
       158: dup
       159: bipush        9
       161: bipush        30
       163: invokestatic  #73                 // Method java/lang/Integer.valueOf:(I)Ljava/lang/Integer;
       166: iconst_2
       167: invokestatic  #73                 // Method java/lang/Integer.valueOf:(I)Ljava/lang/Integer;
       170: invokestatic  #372                // InterfaceMethod java/util/Map.entry:(Ljava/lang/Object;Ljava/lang/Object;)Ljava/util/Map$Entry;
       173: aastore
       174: dup
       175: bipush        10
       177: bipush        31
       179: invokestatic  #73                 // Method java/lang/Integer.valueOf:(I)Ljava/lang/Integer;
       182: iconst_1
       183: invokestatic  #73                 // Method java/lang/Integer.valueOf:(I)Ljava/lang/Integer;
       186: invokestatic  #372                // InterfaceMethod java/util/Map.entry:(Ljava/lang/Object;Ljava/lang/Object;)Ljava/util/Map$Entry;
       189: aastore
       190: dup
       191: bipush        11
       193: bipush        32
       195: invokestatic  #73                 // Method java/lang/Integer.valueOf:(I)Ljava/lang/Integer;
       198: iconst_1
       199: invokestatic  #73                 // Method java/lang/Integer.valueOf:(I)Ljava/lang/Integer;
       202: invokestatic  #372                // InterfaceMethod java/util/Map.entry:(Ljava/lang/Object;Ljava/lang/Object;)Ljava/util/Map$Entry;
       205: aastore
       206: dup
       207: bipush        12
       209: bipush        33
       211: invokestatic  #73                 // Method java/lang/Integer.valueOf:(I)Ljava/lang/Integer;
       214: iconst_1
       215: invokestatic  #73                 // Method java/lang/Integer.valueOf:(I)Ljava/lang/Integer;
       218: invokestatic  #372                // InterfaceMethod java/util/Map.entry:(Ljava/lang/Object;Ljava/lang/Object;)Ljava/util/Map$Entry;
       221: aastore
       222: dup
       223: bipush        13
       225: bipush        34
       227: invokestatic  #73                 // Method java/lang/Integer.valueOf:(I)Ljava/lang/Integer;
       230: iconst_3
       231: invokestatic  #73                 // Method java/lang/Integer.valueOf:(I)Ljava/lang/Integer;
       234: invokestatic  #372                // InterfaceMethod java/util/Map.entry:(Ljava/lang/Object;Ljava/lang/Object;)Ljava/util/Map$Entry;
       237: aastore
       238: dup
       239: bipush        14
       241: bipush        35
       243: invokestatic  #73                 // Method java/lang/Integer.valueOf:(I)Ljava/lang/Integer;
       246: iconst_3
       247: invokestatic  #73                 // Method java/lang/Integer.valueOf:(I)Ljava/lang/Integer;
       250: invokestatic  #372                // InterfaceMethod java/util/Map.entry:(Ljava/lang/Object;Ljava/lang/Object;)Ljava/util/Map$Entry;
       253: aastore
       254: dup
       255: bipush        15
       257: bipush        36
       259: invokestatic  #73                 // Method java/lang/Integer.valueOf:(I)Ljava/lang/Integer;
       262: iconst_3
       263: invokestatic  #73                 // Method java/lang/Integer.valueOf:(I)Ljava/lang/Integer;
       266: invokestatic  #372                // InterfaceMethod java/util/Map.entry:(Ljava/lang/Object;Ljava/lang/Object;)Ljava/util/Map$Entry;
       269: aastore
       270: dup
       271: bipush        16
       273: bipush        37
       275: invokestatic  #73                 // Method java/lang/Integer.valueOf:(I)Ljava/lang/Integer;
       278: iconst_3
       279: invokestatic  #73                 // Method java/lang/Integer.valueOf:(I)Ljava/lang/Integer;
       282: invokestatic  #372                // InterfaceMethod java/util/Map.entry:(Ljava/lang/Object;Ljava/lang/Object;)Ljava/util/Map$Entry;
       285: aastore
       286: dup
       287: bipush        17
       289: bipush        38
       291: invokestatic  #73                 // Method java/lang/Integer.valueOf:(I)Ljava/lang/Integer;
       294: iconst_3
       295: invokestatic  #73                 // Method java/lang/Integer.valueOf:(I)Ljava/lang/Integer;
       298: invokestatic  #372                // InterfaceMethod java/util/Map.entry:(Ljava/lang/Object;Ljava/lang/Object;)Ljava/util/Map$Entry;
       301: aastore
       302: dup
       303: bipush        18
       305: bipush        39
       307: invokestatic  #73                 // Method java/lang/Integer.valueOf:(I)Ljava/lang/Integer;
       310: iconst_3
       311: invokestatic  #73                 // Method java/lang/Integer.valueOf:(I)Ljava/lang/Integer;
       314: invokestatic  #372                // InterfaceMethod java/util/Map.entry:(Ljava/lang/Object;Ljava/lang/Object;)Ljava/util/Map$Entry;
       317: aastore
       318: dup
       319: bipush        19
       321: bipush        40
       323: invokestatic  #73                 // Method java/lang/Integer.valueOf:(I)Ljava/lang/Integer;
       326: iconst_3
       327: invokestatic  #73                 // Method java/lang/Integer.valueOf:(I)Ljava/lang/Integer;
       330: invokestatic  #372                // InterfaceMethod java/util/Map.entry:(Ljava/lang/Object;Ljava/lang/Object;)Ljava/util/Map$Entry;
       333: aastore
       334: dup
       335: bipush        20
       337: bipush        41
       339: invokestatic  #73                 // Method java/lang/Integer.valueOf:(I)Ljava/lang/Integer;
       342: iconst_3
       343: invokestatic  #73                 // Method java/lang/Integer.valueOf:(I)Ljava/lang/Integer;
       346: invokestatic  #372                // InterfaceMethod java/util/Map.entry:(Ljava/lang/Object;Ljava/lang/Object;)Ljava/util/Map$Entry;
       349: aastore
       350: dup
       351: bipush        21
       353: bipush        42
       355: invokestatic  #73                 // Method java/lang/Integer.valueOf:(I)Ljava/lang/Integer;
       358: iconst_3
       359: invokestatic  #73                 // Method java/lang/Integer.valueOf:(I)Ljava/lang/Integer;
       362: invokestatic  #372                // InterfaceMethod java/util/Map.entry:(Ljava/lang/Object;Ljava/lang/Object;)Ljava/util/Map$Entry;
       365: aastore
       366: dup
       367: bipush        22
       369: bipush        43
       371: invokestatic  #73                 // Method java/lang/Integer.valueOf:(I)Ljava/lang/Integer;
       374: iconst_3
       375: invokestatic  #73                 // Method java/lang/Integer.valueOf:(I)Ljava/lang/Integer;
       378: invokestatic  #372                // InterfaceMethod java/util/Map.entry:(Ljava/lang/Object;Ljava/lang/Object;)Ljava/util/Map$Entry;
       381: aastore
       382: dup
       383: bipush        23
       385: bipush        44
       387: invokestatic  #73                 // Method java/lang/Integer.valueOf:(I)Ljava/lang/Integer;
       390: iconst_3
       391: invokestatic  #73                 // Method java/lang/Integer.valueOf:(I)Ljava/lang/Integer;
       394: invokestatic  #372                // InterfaceMethod java/util/Map.entry:(Ljava/lang/Object;Ljava/lang/Object;)Ljava/util/Map$Entry;
       397: aastore
       398: dup
       399: bipush        24
       401: bipush        45
       403: invokestatic  #73                 // Method java/lang/Integer.valueOf:(I)Ljava/lang/Integer;
       406: iconst_3
       407: invokestatic  #73                 // Method java/lang/Integer.valueOf:(I)Ljava/lang/Integer;
       410: invokestatic  #372                // InterfaceMethod java/util/Map.entry:(Ljava/lang/Object;Ljava/lang/Object;)Ljava/util/Map$Entry;
       413: aastore
       414: dup
       415: bipush        25
       417: bipush        46
       419: invokestatic  #73                 // Method java/lang/Integer.valueOf:(I)Ljava/lang/Integer;
       422: iconst_3
       423: invokestatic  #73                 // Method java/lang/Integer.valueOf:(I)Ljava/lang/Integer;
       426: invokestatic  #372                // InterfaceMethod java/util/Map.entry:(Ljava/lang/Object;Ljava/lang/Object;)Ljava/util/Map$Entry;
       429: aastore
       430: dup
       431: bipush        26
       433: bipush        47
       435: invokestatic  #73                 // Method java/lang/Integer.valueOf:(I)Ljava/lang/Integer;
       438: iconst_3
       439: invokestatic  #73                 // Method java/lang/Integer.valueOf:(I)Ljava/lang/Integer;
       442: invokestatic  #372                // InterfaceMethod java/util/Map.entry:(Ljava/lang/Object;Ljava/lang/Object;)Ljava/util/Map$Entry;
       445: aastore
       446: dup
       447: bipush        27
       449: bipush        48
       451: invokestatic  #73                 // Method java/lang/Integer.valueOf:(I)Ljava/lang/Integer;
       454: iconst_3
       455: invokestatic  #73                 // Method java/lang/Integer.valueOf:(I)Ljava/lang/Integer;
       458: invokestatic  #372                // InterfaceMethod java/util/Map.entry:(Ljava/lang/Object;Ljava/lang/Object;)Ljava/util/Map$Entry;
       461: aastore
       462: dup
       463: bipush        28
       465: bipush        49
       467: invokestatic  #73                 // Method java/lang/Integer.valueOf:(I)Ljava/lang/Integer;
       470: iconst_3
       471: invokestatic  #73                 // Method java/lang/Integer.valueOf:(I)Ljava/lang/Integer;
       474: invokestatic  #372                // InterfaceMethod java/util/Map.entry:(Ljava/lang/Object;Ljava/lang/Object;)Ljava/util/Map$Entry;
       477: aastore
       478: dup
       479: bipush        29
       481: bipush        50
       483: invokestatic  #73                 // Method java/lang/Integer.valueOf:(I)Ljava/lang/Integer;
       486: iconst_3
       487: invokestatic  #73                 // Method java/lang/Integer.valueOf:(I)Ljava/lang/Integer;
       490: invokestatic  #372                // InterfaceMethod java/util/Map.entry:(Ljava/lang/Object;Ljava/lang/Object;)Ljava/util/Map$Entry;
       493: aastore
       494: dup
       495: bipush        30
       497: bipush        51
       499: invokestatic  #73                 // Method java/lang/Integer.valueOf:(I)Ljava/lang/Integer;
       502: iconst_3
       503: invokestatic  #73                 // Method java/lang/Integer.valueOf:(I)Ljava/lang/Integer;
       506: invokestatic  #372                // InterfaceMethod java/util/Map.entry:(Ljava/lang/Object;Ljava/lang/Object;)Ljava/util/Map$Entry;
       509: aastore
       510: dup
       511: bipush        31
       513: bipush        52
       515: invokestatic  #73                 // Method java/lang/Integer.valueOf:(I)Ljava/lang/Integer;
       518: iconst_3
       519: invokestatic  #73                 // Method java/lang/Integer.valueOf:(I)Ljava/lang/Integer;
       522: invokestatic  #372                // InterfaceMethod java/util/Map.entry:(Ljava/lang/Object;Ljava/lang/Object;)Ljava/util/Map$Entry;
       525: aastore
       526: dup
       527: bipush        32
       529: bipush        53
       531: invokestatic  #73                 // Method java/lang/Integer.valueOf:(I)Ljava/lang/Integer;
       534: iconst_3
       535: invokestatic  #73                 // Method java/lang/Integer.valueOf:(I)Ljava/lang/Integer;
       538: invokestatic  #372                // InterfaceMethod java/util/Map.entry:(Ljava/lang/Object;Ljava/lang/Object;)Ljava/util/Map$Entry;
       541: aastore
       542: dup
       543: bipush        33
       545: bipush        54
       547: invokestatic  #73                 // Method java/lang/Integer.valueOf:(I)Ljava/lang/Integer;
       550: iconst_3
       551: invokestatic  #73                 // Method java/lang/Integer.valueOf:(I)Ljava/lang/Integer;
       554: invokestatic  #372                // InterfaceMethod java/util/Map.entry:(Ljava/lang/Object;Ljava/lang/Object;)Ljava/util/Map$Entry;
       557: aastore
       558: dup
       559: bipush        34
       561: bipush        55
       563: invokestatic  #73                 // Method java/lang/Integer.valueOf:(I)Ljava/lang/Integer;
       566: iconst_3
       567: invokestatic  #73                 // Method java/lang/Integer.valueOf:(I)Ljava/lang/Integer;
       570: invokestatic  #372                // InterfaceMethod java/util/Map.entry:(Ljava/lang/Object;Ljava/lang/Object;)Ljava/util/Map$Entry;
       573: aastore
       574: dup
       575: bipush        35
       577: bipush        56
       579: invokestatic  #73                 // Method java/lang/Integer.valueOf:(I)Ljava/lang/Integer;
       582: iconst_3
       583: invokestatic  #73                 // Method java/lang/Integer.valueOf:(I)Ljava/lang/Integer;
       586: invokestatic  #372                // InterfaceMethod java/util/Map.entry:(Ljava/lang/Object;Ljava/lang/Object;)Ljava/util/Map$Entry;
       589: aastore
       590: dup
       591: bipush        36
       593: bipush        57
       595: invokestatic  #73                 // Method java/lang/Integer.valueOf:(I)Ljava/lang/Integer;
       598: iconst_3
       599: invokestatic  #73                 // Method java/lang/Integer.valueOf:(I)Ljava/lang/Integer;
       602: invokestatic  #372                // InterfaceMethod java/util/Map.entry:(Ljava/lang/Object;Ljava/lang/Object;)Ljava/util/Map$Entry;
       605: aastore
       606: dup
       607: bipush        37
       609: bipush        58
       611: invokestatic  #73                 // Method java/lang/Integer.valueOf:(I)Ljava/lang/Integer;
       614: iconst_2
       615: invokestatic  #73                 // Method java/lang/Integer.valueOf:(I)Ljava/lang/Integer;
       618: invokestatic  #372                // InterfaceMethod java/util/Map.entry:(Ljava/lang/Object;Ljava/lang/Object;)Ljava/util/Map$Entry;
       621: aastore
       622: dup
       623: bipush        38
       625: bipush        59
       627: invokestatic  #73                 // Method java/lang/Integer.valueOf:(I)Ljava/lang/Integer;
       630: iconst_2
       631: invokestatic  #73                 // Method java/lang/Integer.valueOf:(I)Ljava/lang/Integer;
       634: invokestatic  #372                // InterfaceMethod java/util/Map.entry:(Ljava/lang/Object;Ljava/lang/Object;)Ljava/util/Map$Entry;
       637: aastore
       638: dup
       639: bipush        39
       641: bipush        60
       643: invokestatic  #73                 // Method java/lang/Integer.valueOf:(I)Ljava/lang/Integer;
       646: iconst_2
       647: invokestatic  #73                 // Method java/lang/Integer.valueOf:(I)Ljava/lang/Integer;
       650: invokestatic  #372                // InterfaceMethod java/util/Map.entry:(Ljava/lang/Object;Ljava/lang/Object;)Ljava/util/Map$Entry;
       653: aastore
       654: dup
       655: bipush        40
       657: bipush        61
       659: invokestatic  #73                 // Method java/lang/Integer.valueOf:(I)Ljava/lang/Integer;
       662: iconst_2
       663: invokestatic  #73                 // Method java/lang/Integer.valueOf:(I)Ljava/lang/Integer;
       666: invokestatic  #372                // InterfaceMethod java/util/Map.entry:(Ljava/lang/Object;Ljava/lang/Object;)Ljava/util/Map$Entry;
       669: aastore
       670: dup
       671: bipush        41
       673: bipush        62
       675: invokestatic  #73                 // Method java/lang/Integer.valueOf:(I)Ljava/lang/Integer;
       678: iconst_3
       679: invokestatic  #73                 // Method java/lang/Integer.valueOf:(I)Ljava/lang/Integer;
       682: invokestatic  #372                // InterfaceMethod java/util/Map.entry:(Ljava/lang/Object;Ljava/lang/Object;)Ljava/util/Map$Entry;
       685: aastore
       686: dup
       687: bipush        42
       689: bipush        63
       691: invokestatic  #73                 // Method java/lang/Integer.valueOf:(I)Ljava/lang/Integer;
       694: iconst_3
       695: invokestatic  #73                 // Method java/lang/Integer.valueOf:(I)Ljava/lang/Integer;
       698: invokestatic  #372                // InterfaceMethod java/util/Map.entry:(Ljava/lang/Object;Ljava/lang/Object;)Ljava/util/Map$Entry;
       701: aastore
       702: dup
       703: bipush        43
       705: bipush        64
       707: invokestatic  #73                 // Method java/lang/Integer.valueOf:(I)Ljava/lang/Integer;
       710: iconst_3
       711: invokestatic  #73                 // Method java/lang/Integer.valueOf:(I)Ljava/lang/Integer;
       714: invokestatic  #372                // InterfaceMethod java/util/Map.entry:(Ljava/lang/Object;Ljava/lang/Object;)Ljava/util/Map$Entry;
       717: aastore
       718: invokestatic  #376                // InterfaceMethod java/util/Map.ofEntries:([Ljava/util/Map$Entry;)Ljava/util/Map;
       721: putstatic     #67                 // Field GRADE_LIST:Ljava/util/Map;
       724: return
      LineNumberTable:
        line 53: 0
        line 70: 15
        line 71: 24
        line 72: 39
        line 73: 54
        line 74: 69
        line 75: 84
        line 76: 99
        line 77: 115
        line 78: 131
        line 79: 147
        line 80: 163
        line 81: 179
        line 82: 195
        line 83: 211
        line 84: 227
        line 85: 243
        line 86: 259
        line 87: 275
        line 88: 291
        line 89: 307
        line 90: 323
        line 91: 339
        line 92: 355
        line 93: 371
        line 94: 387
        line 95: 403
        line 96: 419
        line 97: 435
        line 98: 451
        line 99: 467
        line 100: 483
        line 101: 499
        line 102: 515
        line 103: 531
        line 104: 547
        line 105: 563
        line 106: 579
        line 107: 595
        line 108: 611
        line 109: 627
        line 110: 643
        line 111: 659
        line 112: 675
        line 113: 691
        line 114: 707
        line 70: 718
}
SourceFile: "ClanHall.java"
NestMembers:
  ext/mods/gameserver/model/residence/clanhall/ClanHall$Buff
BootstrapMethods:
  0: #483 REF_invokeStatic java/lang/invoke/LambdaMetafactory.metafactory:(Ljava/lang/invoke/MethodHandles$Lookup;Ljava/lang/String;Ljava/lang/invoke/MethodType;Ljava/lang/invoke/MethodType;Ljava/lang/invoke/MethodHandle;Ljava/lang/invoke/MethodType;)Ljava/lang/invoke/CallSite;
    Method arguments:
      #479 ()V
      #480 REF_invokeVirtual ext/mods/gameserver/model/residence/clanhall/ClanHall.payFee:()V
      #479 ()V
InnerClasses:
  public static final #491= #353 of #13;  // Buff=class ext/mods/gameserver/model/residence/clanhall/ClanHall$Buff of class ext/mods/gameserver/model/residence/clanhall/ClanHall
  public static #492= #370 of #80;        // Entry=class java/util/Map$Entry of class java/util/Map
  public static final #497= #493 of #495; // Lookup=class java/lang/invoke/MethodHandles$Lookup of class java/lang/invoke/MethodHandles
