// Bytecode for: ext.mods.gameserver.enums.actors.HennaType
// File: ext\mods\gameserver\enums\actors\HennaType.class

Classfile /c:/Users/User/Desktop/BrProject/bin/main/ext/mods/gameserver/enums/actors/HennaType.class
  Last modified 9 de jul de 2026; size 1896 bytes
  MD5 checksum c7026e2bfebfad39b711b319a9691ee3
  Compiled from "HennaType.java"
public final class ext.mods.gameserver.enums.actors.HennaType extends java.lang.Enum<ext.mods.gameserver.enums.actors.HennaType>
  minor version: 0
  major version: 69
  flags: (0x4031) ACC_PUBLIC, ACC_FINAL, ACC_SUPER, ACC_ENUM
  this_class: #1                          // ext/mods/gameserver/enums/actors/HennaType
  super_class: #32                        // java/lang/Enum
  interfaces: 0, fields: 8, methods: 6, attributes: 2
Constant pool:
   #1 = Class              #2             // ext/mods/gameserver/enums/actors/HennaType
   #2 = Utf8               ext/mods/gameserver/enums/actors/HennaType
   #3 = Fieldref           #1.#4          // ext/mods/gameserver/enums/actors/HennaType.INT:Lext/mods/gameserver/enums/actors/HennaType;
   #4 = NameAndType        #5:#6          // INT:Lext/mods/gameserver/enums/actors/HennaType;
   #5 = Utf8               INT
   #6 = Utf8               Lext/mods/gameserver/enums/actors/HennaType;
   #7 = Fieldref           #1.#8          // ext/mods/gameserver/enums/actors/HennaType.STR:Lext/mods/gameserver/enums/actors/HennaType;
   #8 = NameAndType        #9:#6          // STR:Lext/mods/gameserver/enums/actors/HennaType;
   #9 = Utf8               STR
  #10 = Fieldref           #1.#11         // ext/mods/gameserver/enums/actors/HennaType.CON:Lext/mods/gameserver/enums/actors/HennaType;
  #11 = NameAndType        #12:#6         // CON:Lext/mods/gameserver/enums/actors/HennaType;
  #12 = Utf8               CON
  #13 = Fieldref           #1.#14         // ext/mods/gameserver/enums/actors/HennaType.MEN:Lext/mods/gameserver/enums/actors/HennaType;
  #14 = NameAndType        #15:#6         // MEN:Lext/mods/gameserver/enums/actors/HennaType;
  #15 = Utf8               MEN
  #16 = Fieldref           #1.#17         // ext/mods/gameserver/enums/actors/HennaType.DEX:Lext/mods/gameserver/enums/actors/HennaType;
  #17 = NameAndType        #18:#6         // DEX:Lext/mods/gameserver/enums/actors/HennaType;
  #18 = Utf8               DEX
  #19 = Fieldref           #1.#20         // ext/mods/gameserver/enums/actors/HennaType.WIT:Lext/mods/gameserver/enums/actors/HennaType;
  #20 = NameAndType        #21:#6         // WIT:Lext/mods/gameserver/enums/actors/HennaType;
  #21 = Utf8               WIT
  #22 = Fieldref           #1.#23         // ext/mods/gameserver/enums/actors/HennaType.$VALUES:[Lext/mods/gameserver/enums/actors/HennaType;
  #23 = NameAndType        #24:#25        // $VALUES:[Lext/mods/gameserver/enums/actors/HennaType;
  #24 = Utf8               $VALUES
  #25 = Utf8               [Lext/mods/gameserver/enums/actors/HennaType;
  #26 = Methodref          #27.#28        // "[Lext/mods/gameserver/enums/actors/HennaType;".clone:()Ljava/lang/Object;
  #27 = Class              #25            // "[Lext/mods/gameserver/enums/actors/HennaType;"
  #28 = NameAndType        #29:#30        // clone:()Ljava/lang/Object;
  #29 = Utf8               clone
  #30 = Utf8               ()Ljava/lang/Object;
  #31 = Methodref          #32.#33        // java/lang/Enum.valueOf:(Ljava/lang/Class;Ljava/lang/String;)Ljava/lang/Enum;
  #32 = Class              #34            // java/lang/Enum
  #33 = NameAndType        #35:#36        // valueOf:(Ljava/lang/Class;Ljava/lang/String;)Ljava/lang/Enum;
  #34 = Utf8               java/lang/Enum
  #35 = Utf8               valueOf
  #36 = Utf8               (Ljava/lang/Class;Ljava/lang/String;)Ljava/lang/Enum;
  #37 = Methodref          #32.#38        // java/lang/Enum."<init>":(Ljava/lang/String;I)V
  #38 = NameAndType        #39:#40        // "<init>":(Ljava/lang/String;I)V
  #39 = Utf8               <init>
  #40 = Utf8               (Ljava/lang/String;I)V
  #41 = Fieldref           #1.#42         // ext/mods/gameserver/enums/actors/HennaType._stats:Lext/mods/gameserver/enums/skills/Stats;
  #42 = NameAndType        #43:#44        // _stats:Lext/mods/gameserver/enums/skills/Stats;
  #43 = Utf8               _stats
  #44 = Utf8               Lext/mods/gameserver/enums/skills/Stats;
  #45 = String             #5             // INT
  #46 = Fieldref           #47.#48        // ext/mods/gameserver/enums/skills/Stats.STAT_INT:Lext/mods/gameserver/enums/skills/Stats;
  #47 = Class              #49            // ext/mods/gameserver/enums/skills/Stats
  #48 = NameAndType        #50:#44        // STAT_INT:Lext/mods/gameserver/enums/skills/Stats;
  #49 = Utf8               ext/mods/gameserver/enums/skills/Stats
  #50 = Utf8               STAT_INT
  #51 = Methodref          #1.#52         // ext/mods/gameserver/enums/actors/HennaType."<init>":(Ljava/lang/String;ILext/mods/gameserver/enums/skills/Stats;)V
  #52 = NameAndType        #39:#53        // "<init>":(Ljava/lang/String;ILext/mods/gameserver/enums/skills/Stats;)V
  #53 = Utf8               (Ljava/lang/String;ILext/mods/gameserver/enums/skills/Stats;)V
  #54 = String             #9             // STR
  #55 = Fieldref           #47.#56        // ext/mods/gameserver/enums/skills/Stats.STAT_STR:Lext/mods/gameserver/enums/skills/Stats;
  #56 = NameAndType        #57:#44        // STAT_STR:Lext/mods/gameserver/enums/skills/Stats;
  #57 = Utf8               STAT_STR
  #58 = String             #12            // CON
  #59 = Fieldref           #47.#60        // ext/mods/gameserver/enums/skills/Stats.STAT_CON:Lext/mods/gameserver/enums/skills/Stats;
  #60 = NameAndType        #61:#44        // STAT_CON:Lext/mods/gameserver/enums/skills/Stats;
  #61 = Utf8               STAT_CON
  #62 = String             #15            // MEN
  #63 = Fieldref           #47.#64        // ext/mods/gameserver/enums/skills/Stats.STAT_MEN:Lext/mods/gameserver/enums/skills/Stats;
  #64 = NameAndType        #65:#44        // STAT_MEN:Lext/mods/gameserver/enums/skills/Stats;
  #65 = Utf8               STAT_MEN
  #66 = String             #18            // DEX
  #67 = Fieldref           #47.#68        // ext/mods/gameserver/enums/skills/Stats.STAT_DEX:Lext/mods/gameserver/enums/skills/Stats;
  #68 = NameAndType        #69:#44        // STAT_DEX:Lext/mods/gameserver/enums/skills/Stats;
  #69 = Utf8               STAT_DEX
  #70 = String             #21            // WIT
  #71 = Fieldref           #47.#72        // ext/mods/gameserver/enums/skills/Stats.STAT_WIT:Lext/mods/gameserver/enums/skills/Stats;
  #72 = NameAndType        #73:#44        // STAT_WIT:Lext/mods/gameserver/enums/skills/Stats;
  #73 = Utf8               STAT_WIT
  #74 = Methodref          #1.#75         // ext/mods/gameserver/enums/actors/HennaType.$values:()[Lext/mods/gameserver/enums/actors/HennaType;
  #75 = NameAndType        #76:#77        // $values:()[Lext/mods/gameserver/enums/actors/HennaType;
  #76 = Utf8               $values
  #77 = Utf8               ()[Lext/mods/gameserver/enums/actors/HennaType;
  #78 = Utf8               values
  #79 = Utf8               Code
  #80 = Utf8               LineNumberTable
  #81 = Utf8               (Ljava/lang/String;)Lext/mods/gameserver/enums/actors/HennaType;
  #82 = Utf8               LocalVariableTable
  #83 = Utf8               name
  #84 = Utf8               Ljava/lang/String;
  #85 = Utf8               MethodParameters
  #86 = Utf8               this
  #87 = Utf8               stats
  #88 = Utf8               Signature
  #89 = Utf8               (Lext/mods/gameserver/enums/skills/Stats;)V
  #90 = Utf8               getStats
  #91 = Utf8               ()Lext/mods/gameserver/enums/skills/Stats;
  #92 = Utf8               <clinit>
  #93 = Utf8               ()V
  #94 = Utf8               Ljava/lang/Enum<Lext/mods/gameserver/enums/actors/HennaType;>;
  #95 = Utf8               SourceFile
  #96 = Utf8               HennaType.java
{
  public static final ext.mods.gameserver.enums.actors.HennaType INT;
    descriptor: Lext/mods/gameserver/enums/actors/HennaType;
    flags: (0x4019) ACC_PUBLIC, ACC_STATIC, ACC_FINAL, ACC_ENUM

  public static final ext.mods.gameserver.enums.actors.HennaType STR;
    descriptor: Lext/mods/gameserver/enums/actors/HennaType;
    flags: (0x4019) ACC_PUBLIC, ACC_STATIC, ACC_FINAL, ACC_ENUM

  public static final ext.mods.gameserver.enums.actors.HennaType CON;
    descriptor: Lext/mods/gameserver/enums/actors/HennaType;
    flags: (0x4019) ACC_PUBLIC, ACC_STATIC, ACC_FINAL, ACC_ENUM

  public static final ext.mods.gameserver.enums.actors.HennaType MEN;
    descriptor: Lext/mods/gameserver/enums/actors/HennaType;
    flags: (0x4019) ACC_PUBLIC, ACC_STATIC, ACC_FINAL, ACC_ENUM

  public static final ext.mods.gameserver.enums.actors.HennaType DEX;
    descriptor: Lext/mods/gameserver/enums/actors/HennaType;
    flags: (0x4019) ACC_PUBLIC, ACC_STATIC, ACC_FINAL, ACC_ENUM

  public static final ext.mods.gameserver.enums.actors.HennaType WIT;
    descriptor: Lext/mods/gameserver/enums/actors/HennaType;
    flags: (0x4019) ACC_PUBLIC, ACC_STATIC, ACC_FINAL, ACC_ENUM

  public static ext.mods.gameserver.enums.actors.HennaType[] values();
    descriptor: ()[Lext/mods/gameserver/enums/actors/HennaType;
    flags: (0x0009) ACC_PUBLIC, ACC_STATIC
    Code:
      stack=1, locals=0, args_size=0
         0: getstatic     #22                 // Field $VALUES:[Lext/mods/gameserver/enums/actors/HennaType;
         3: invokevirtual #26                 // Method "[Lext/mods/gameserver/enums/actors/HennaType;".clone:()Ljava/lang/Object;
         6: checkcast     #27                 // class "[Lext/mods/gameserver/enums/actors/HennaType;"
         9: areturn
      LineNumberTable:
        line 22: 0

  public static ext.mods.gameserver.enums.actors.HennaType valueOf(java.lang.String);
    descriptor: (Ljava/lang/String;)Lext/mods/gameserver/enums/actors/HennaType;
    flags: (0x0009) ACC_PUBLIC, ACC_STATIC
    Code:
      stack=2, locals=1, args_size=1
         0: ldc           #1                  // class ext/mods/gameserver/enums/actors/HennaType
         2: aload_0
         3: invokestatic  #31                 // Method java/lang/Enum.valueOf:(Ljava/lang/Class;Ljava/lang/String;)Ljava/lang/Enum;
         6: checkcast     #1                  // class ext/mods/gameserver/enums/actors/HennaType
         9: areturn
      LineNumberTable:
        line 22: 0
      LocalVariableTable:
        Start  Length  Slot  Name   Signature
            0      10     0  name   Ljava/lang/String;
    MethodParameters:
      Name                           Flags
      <no name>                      mandated

  public ext.mods.gameserver.enums.skills.Stats getStats();
    descriptor: ()Lext/mods/gameserver/enums/skills/Stats;
    flags: (0x0001) ACC_PUBLIC
    Code:
      stack=1, locals=1, args_size=1
         0: aload_0
         1: getfield      #41                 // Field _stats:Lext/mods/gameserver/enums/skills/Stats;
         4: areturn
      LineNumberTable:
        line 40: 0
      LocalVariableTable:
        Start  Length  Slot  Name   Signature
            0       5     0  this   Lext/mods/gameserver/enums/actors/HennaType;

  static {};
    descriptor: ()V
    flags: (0x0008) ACC_STATIC
    Code:
      stack=5, locals=0, args_size=0
         0: new           #1                  // class ext/mods/gameserver/enums/actors/HennaType
         3: dup
         4: ldc           #45                 // String INT
         6: iconst_0
         7: getstatic     #46                 // Field ext/mods/gameserver/enums/skills/Stats.STAT_INT:Lext/mods/gameserver/enums/skills/Stats;
        10: invokespecial #51                 // Method "<init>":(Ljava/lang/String;ILext/mods/gameserver/enums/skills/Stats;)V
        13: putstatic     #3                  // Field INT:Lext/mods/gameserver/enums/actors/HennaType;
        16: new           #1                  // class ext/mods/gameserver/enums/actors/HennaType
        19: dup
        20: ldc           #54                 // String STR
        22: iconst_1
        23: getstatic     #55                 // Field ext/mods/gameserver/enums/skills/Stats.STAT_STR:Lext/mods/gameserver/enums/skills/Stats;
        26: invokespecial #51                 // Method "<init>":(Ljava/lang/String;ILext/mods/gameserver/enums/skills/Stats;)V
        29: putstatic     #7                  // Field STR:Lext/mods/gameserver/enums/actors/HennaType;
        32: new           #1                  // class ext/mods/gameserver/enums/actors/HennaType
        35: dup
        36: ldc           #58                 // String CON
        38: iconst_2
        39: getstatic     #59                 // Field ext/mods/gameserver/enums/skills/Stats.STAT_CON:Lext/mods/gameserver/enums/skills/Stats;
        42: invokespecial #51                 // Method "<init>":(Ljava/lang/String;ILext/mods/gameserver/enums/skills/Stats;)V
        45: putstatic     #10                 // Field CON:Lext/mods/gameserver/enums/actors/HennaType;
        48: new           #1                  // class ext/mods/gameserver/enums/actors/HennaType
        51: dup
        52: ldc           #62                 // String MEN
        54: iconst_3
        55: getstatic     #63                 // Field ext/mods/gameserver/enums/skills/Stats.STAT_MEN:Lext/mods/gameserver/enums/skills/Stats;
        58: invokespecial #51                 // Method "<init>":(Ljava/lang/String;ILext/mods/gameserver/enums/skills/Stats;)V
        61: putstatic     #13                 // Field MEN:Lext/mods/gameserver/enums/actors/HennaType;
        64: new           #1                  // class ext/mods/gameserver/enums/actors/HennaType
        67: dup
        68: ldc           #66                 // String DEX
        70: iconst_4
        71: getstatic     #67                 // Field ext/mods/gameserver/enums/skills/Stats.STAT_DEX:Lext/mods/gameserver/enums/skills/Stats;
        74: invokespecial #51                 // Method "<init>":(Ljava/lang/String;ILext/mods/gameserver/enums/skills/Stats;)V
        77: putstatic     #16                 // Field DEX:Lext/mods/gameserver/enums/actors/HennaType;
        80: new           #1                  // class ext/mods/gameserver/enums/actors/HennaType
        83: dup
        84: ldc           #70                 // String WIT
        86: iconst_5
        87: getstatic     #71                 // Field ext/mods/gameserver/enums/skills/Stats.STAT_WIT:Lext/mods/gameserver/enums/skills/Stats;
        90: invokespecial #51                 // Method "<init>":(Ljava/lang/String;ILext/mods/gameserver/enums/skills/Stats;)V
        93: putstatic     #19                 // Field WIT:Lext/mods/gameserver/enums/actors/HennaType;
        96: invokestatic  #74                 // Method $values:()[Lext/mods/gameserver/enums/actors/HennaType;
        99: putstatic     #22                 // Field $VALUES:[Lext/mods/gameserver/enums/actors/HennaType;
       102: return
      LineNumberTable:
        line 24: 0
        line 25: 16
        line 26: 32
        line 27: 48
        line 28: 64
        line 29: 80
        line 22: 96
}
Signature: #94                          // Ljava/lang/Enum<Lext/mods/gameserver/enums/actors/HennaType;>;
SourceFile: "HennaType.java"
