// Bytecode for: ext.mods.Crypta.DeeplTranslator$Language
// File: ext\mods\Crypta\DeeplTranslator$Language.class

Classfile /c:/Users/User/Desktop/BrProject/bin/main/ext/mods/Crypta/DeeplTranslator$Language.class
  Last modified 9 de jul de 2026; size 4010 bytes
  MD5 checksum f739b7b11145b9d072414dc776b1d7b1
  Compiled from "DeeplTranslator.java"
public final class ext.mods.Crypta.DeeplTranslator$Language extends java.lang.Enum<ext.mods.Crypta.DeeplTranslator$Language>
  minor version: 0
  major version: 69
  flags: (0x4031) ACC_PUBLIC, ACC_FINAL, ACC_SUPER, ACC_ENUM
  this_class: #1                          // ext/mods/Crypta/DeeplTranslator$Language
  super_class: #50                        // java/lang/Enum
  interfaces: 0, fields: 16, methods: 10, attributes: 5
Constant pool:
    #1 = Class              #2            // ext/mods/Crypta/DeeplTranslator$Language
    #2 = Utf8               ext/mods/Crypta/DeeplTranslator$Language
    #3 = Fieldref           #1.#4         // ext/mods/Crypta/DeeplTranslator$Language.ENGLISH:Lext/mods/Crypta/DeeplTranslator$Language;
    #4 = NameAndType        #5:#6         // ENGLISH:Lext/mods/Crypta/DeeplTranslator$Language;
    #5 = Utf8               ENGLISH
    #6 = Utf8               Lext/mods/Crypta/DeeplTranslator$Language;
    #7 = Fieldref           #1.#8         // ext/mods/Crypta/DeeplTranslator$Language.PORTUGUESE:Lext/mods/Crypta/DeeplTranslator$Language;
    #8 = NameAndType        #9:#6         // PORTUGUESE:Lext/mods/Crypta/DeeplTranslator$Language;
    #9 = Utf8               PORTUGUESE
   #10 = Fieldref           #1.#11        // ext/mods/Crypta/DeeplTranslator$Language.SPANISH:Lext/mods/Crypta/DeeplTranslator$Language;
   #11 = NameAndType        #12:#6        // SPANISH:Lext/mods/Crypta/DeeplTranslator$Language;
   #12 = Utf8               SPANISH
   #13 = Fieldref           #1.#14        // ext/mods/Crypta/DeeplTranslator$Language.KOREAN:Lext/mods/Crypta/DeeplTranslator$Language;
   #14 = NameAndType        #15:#6        // KOREAN:Lext/mods/Crypta/DeeplTranslator$Language;
   #15 = Utf8               KOREAN
   #16 = Fieldref           #1.#17        // ext/mods/Crypta/DeeplTranslator$Language.RUSSIAN:Lext/mods/Crypta/DeeplTranslator$Language;
   #17 = NameAndType        #18:#6        // RUSSIAN:Lext/mods/Crypta/DeeplTranslator$Language;
   #18 = Utf8               RUSSIAN
   #19 = Fieldref           #1.#20        // ext/mods/Crypta/DeeplTranslator$Language.CHINESE:Lext/mods/Crypta/DeeplTranslator$Language;
   #20 = NameAndType        #21:#6        // CHINESE:Lext/mods/Crypta/DeeplTranslator$Language;
   #21 = Utf8               CHINESE
   #22 = Fieldref           #1.#23        // ext/mods/Crypta/DeeplTranslator$Language.GERMAN:Lext/mods/Crypta/DeeplTranslator$Language;
   #23 = NameAndType        #24:#6        // GERMAN:Lext/mods/Crypta/DeeplTranslator$Language;
   #24 = Utf8               GERMAN
   #25 = Fieldref           #1.#26        // ext/mods/Crypta/DeeplTranslator$Language.ITALIAN:Lext/mods/Crypta/DeeplTranslator$Language;
   #26 = NameAndType        #27:#6        // ITALIAN:Lext/mods/Crypta/DeeplTranslator$Language;
   #27 = Utf8               ITALIAN
   #28 = Fieldref           #1.#29        // ext/mods/Crypta/DeeplTranslator$Language.FRENCH:Lext/mods/Crypta/DeeplTranslator$Language;
   #29 = NameAndType        #30:#6        // FRENCH:Lext/mods/Crypta/DeeplTranslator$Language;
   #30 = Utf8               FRENCH
   #31 = Fieldref           #1.#32        // ext/mods/Crypta/DeeplTranslator$Language.POLISH:Lext/mods/Crypta/DeeplTranslator$Language;
   #32 = NameAndType        #33:#6        // POLISH:Lext/mods/Crypta/DeeplTranslator$Language;
   #33 = Utf8               POLISH
   #34 = Fieldref           #1.#35        // ext/mods/Crypta/DeeplTranslator$Language.GREEK:Lext/mods/Crypta/DeeplTranslator$Language;
   #35 = NameAndType        #36:#6        // GREEK:Lext/mods/Crypta/DeeplTranslator$Language;
   #36 = Utf8               GREEK
   #37 = Fieldref           #1.#38        // ext/mods/Crypta/DeeplTranslator$Language.JAPANESE:Lext/mods/Crypta/DeeplTranslator$Language;
   #38 = NameAndType        #39:#6        // JAPANESE:Lext/mods/Crypta/DeeplTranslator$Language;
   #39 = Utf8               JAPANESE
   #40 = Fieldref           #1.#41        // ext/mods/Crypta/DeeplTranslator$Language.$VALUES:[Lext/mods/Crypta/DeeplTranslator$Language;
   #41 = NameAndType        #42:#43       // $VALUES:[Lext/mods/Crypta/DeeplTranslator$Language;
   #42 = Utf8               $VALUES
   #43 = Utf8               [Lext/mods/Crypta/DeeplTranslator$Language;
   #44 = Methodref          #45.#46       // "[Lext/mods/Crypta/DeeplTranslator$Language;".clone:()Ljava/lang/Object;
   #45 = Class              #43           // "[Lext/mods/Crypta/DeeplTranslator$Language;"
   #46 = NameAndType        #47:#48       // clone:()Ljava/lang/Object;
   #47 = Utf8               clone
   #48 = Utf8               ()Ljava/lang/Object;
   #49 = Methodref          #50.#51       // java/lang/Enum.valueOf:(Ljava/lang/Class;Ljava/lang/String;)Ljava/lang/Enum;
   #50 = Class              #52           // java/lang/Enum
   #51 = NameAndType        #53:#54       // valueOf:(Ljava/lang/Class;Ljava/lang/String;)Ljava/lang/Enum;
   #52 = Utf8               java/lang/Enum
   #53 = Utf8               valueOf
   #54 = Utf8               (Ljava/lang/Class;Ljava/lang/String;)Ljava/lang/Enum;
   #55 = Methodref          #50.#56       // java/lang/Enum."<init>":(Ljava/lang/String;I)V
   #56 = NameAndType        #57:#58       // "<init>":(Ljava/lang/String;I)V
   #57 = Utf8               <init>
   #58 = Utf8               (Ljava/lang/String;I)V
   #59 = Fieldref           #1.#60        // ext/mods/Crypta/DeeplTranslator$Language._code:Ljava/lang/String;
   #60 = NameAndType        #61:#62       // _code:Ljava/lang/String;
   #61 = Utf8               _code
   #62 = Utf8               Ljava/lang/String;
   #63 = Fieldref           #1.#64        // ext/mods/Crypta/DeeplTranslator$Language._displayName:Ljava/lang/String;
   #64 = NameAndType        #65:#62       // _displayName:Ljava/lang/String;
   #65 = Utf8               _displayName
   #66 = Fieldref           #1.#67        // ext/mods/Crypta/DeeplTranslator$Language._isOriginal:Z
   #67 = NameAndType        #68:#69       // _isOriginal:Z
   #68 = Utf8               _isOriginal
   #69 = Utf8               Z
   #70 = Methodref          #1.#71        // ext/mods/Crypta/DeeplTranslator$Language.values:()[Lext/mods/Crypta/DeeplTranslator$Language;
   #71 = NameAndType        #72:#73       // values:()[Lext/mods/Crypta/DeeplTranslator$Language;
   #72 = Utf8               values
   #73 = Utf8               ()[Lext/mods/Crypta/DeeplTranslator$Language;
   #74 = Methodref          #75.#76       // java/util/Arrays.stream:([Ljava/lang/Object;)Ljava/util/stream/Stream;
   #75 = Class              #77           // java/util/Arrays
   #76 = NameAndType        #78:#79       // stream:([Ljava/lang/Object;)Ljava/util/stream/Stream;
   #77 = Utf8               java/util/Arrays
   #78 = Utf8               stream
   #79 = Utf8               ([Ljava/lang/Object;)Ljava/util/stream/Stream;
   #80 = InvokeDynamic      #0:#81        // #0:test:(Ljava/lang/String;)Ljava/util/function/Predicate;
   #81 = NameAndType        #82:#83       // test:(Ljava/lang/String;)Ljava/util/function/Predicate;
   #82 = Utf8               test
   #83 = Utf8               (Ljava/lang/String;)Ljava/util/function/Predicate;
   #84 = InterfaceMethodref #85.#86       // java/util/stream/Stream.filter:(Ljava/util/function/Predicate;)Ljava/util/stream/Stream;
   #85 = Class              #87           // java/util/stream/Stream
   #86 = NameAndType        #88:#89       // filter:(Ljava/util/function/Predicate;)Ljava/util/stream/Stream;
   #87 = Utf8               java/util/stream/Stream
   #88 = Utf8               filter
   #89 = Utf8               (Ljava/util/function/Predicate;)Ljava/util/stream/Stream;
   #90 = InterfaceMethodref #85.#91       // java/util/stream/Stream.findFirst:()Ljava/util/Optional;
   #91 = NameAndType        #92:#93       // findFirst:()Ljava/util/Optional;
   #92 = Utf8               findFirst
   #93 = Utf8               ()Ljava/util/Optional;
   #94 = Methodref          #1.#95        // ext/mods/Crypta/DeeplTranslator$Language.getCode:()Ljava/lang/String;
   #95 = NameAndType        #96:#97       // getCode:()Ljava/lang/String;
   #96 = Utf8               getCode
   #97 = Utf8               ()Ljava/lang/String;
   #98 = Methodref          #99.#100      // java/lang/String.equalsIgnoreCase:(Ljava/lang/String;)Z
   #99 = Class              #101          // java/lang/String
  #100 = NameAndType        #102:#103     // equalsIgnoreCase:(Ljava/lang/String;)Z
  #101 = Utf8               java/lang/String
  #102 = Utf8               equalsIgnoreCase
  #103 = Utf8               (Ljava/lang/String;)Z
  #104 = String             #5            // ENGLISH
  #105 = String             #106          // en_US
  #106 = Utf8               en_US
  #107 = String             #108          // English
  #108 = Utf8               English
  #109 = Methodref          #1.#110       // ext/mods/Crypta/DeeplTranslator$Language."<init>":(Ljava/lang/String;ILjava/lang/String;Ljava/lang/String;Z)V
  #110 = NameAndType        #57:#111      // "<init>":(Ljava/lang/String;ILjava/lang/String;Ljava/lang/String;Z)V
  #111 = Utf8               (Ljava/lang/String;ILjava/lang/String;Ljava/lang/String;Z)V
  #112 = String             #9            // PORTUGUESE
  #113 = String             #114          // pt-BR
  #114 = Utf8               pt-BR
  #115 = String             #116          // Portuguese
  #116 = Utf8               Portuguese
  #117 = String             #12           // SPANISH
  #118 = String             #119          // es
  #119 = Utf8               es
  #120 = String             #121          // Spanish
  #121 = Utf8               Spanish
  #122 = String             #15           // KOREAN
  #123 = String             #124          // ko
  #124 = Utf8               ko
  #125 = String             #126          // Korean
  #126 = Utf8               Korean
  #127 = String             #18           // RUSSIAN
  #128 = String             #129          // ru_RU
  #129 = Utf8               ru_RU
  #130 = String             #131          // Russian
  #131 = Utf8               Russian
  #132 = String             #21           // CHINESE
  #133 = String             #134          // zh
  #134 = Utf8               zh
  #135 = String             #136          // Chinese
  #136 = Utf8               Chinese
  #137 = String             #24           // GERMAN
  #138 = String             #139          // de
  #139 = Utf8               de
  #140 = String             #141          // German
  #141 = Utf8               German
  #142 = String             #27           // ITALIAN
  #143 = String             #144          // it
  #144 = Utf8               it
  #145 = String             #146          // Italian
  #146 = Utf8               Italian
  #147 = String             #30           // FRENCH
  #148 = String             #149          // fr
  #149 = Utf8               fr
  #150 = String             #151          // French
  #151 = Utf8               French
  #152 = String             #33           // POLISH
  #153 = String             #154          // pl
  #154 = Utf8               pl
  #155 = String             #156          // Polish
  #156 = Utf8               Polish
  #157 = String             #36           // GREEK
  #158 = String             #159          // el
  #159 = Utf8               el
  #160 = String             #161          // Greek
  #161 = Utf8               Greek
  #162 = String             #39           // JAPANESE
  #163 = String             #164          // ja
  #164 = Utf8               ja
  #165 = String             #166          // Japanese
  #166 = Utf8               Japanese
  #167 = Methodref          #1.#168       // ext/mods/Crypta/DeeplTranslator$Language.$values:()[Lext/mods/Crypta/DeeplTranslator$Language;
  #168 = NameAndType        #169:#73      // $values:()[Lext/mods/Crypta/DeeplTranslator$Language;
  #169 = Utf8               $values
  #170 = Utf8               Code
  #171 = Utf8               LineNumberTable
  #172 = Utf8               (Ljava/lang/String;)Lext/mods/Crypta/DeeplTranslator$Language;
  #173 = Utf8               LocalVariableTable
  #174 = Utf8               name
  #175 = Utf8               MethodParameters
  #176 = Utf8               this
  #177 = Utf8               code
  #178 = Utf8               displayName
  #179 = Utf8               isOriginal
  #180 = Utf8               Signature
  #181 = Utf8               (Ljava/lang/String;Ljava/lang/String;Z)V
  #182 = Utf8               getDisplayName
  #183 = Utf8               ()Z
  #184 = Utf8               fromCode
  #185 = Utf8               (Ljava/lang/String;)Ljava/util/Optional;
  #186 = Utf8               (Ljava/lang/String;)Ljava/util/Optional<Lext/mods/Crypta/DeeplTranslator$Language;>;
  #187 = Utf8               lambda$fromCode$0
  #188 = Utf8               (Ljava/lang/String;Lext/mods/Crypta/DeeplTranslator$Language;)Z
  #189 = Utf8               lang
  #190 = Utf8               <clinit>
  #191 = Utf8               ()V
  #192 = Utf8               Ljava/lang/Enum<Lext/mods/Crypta/DeeplTranslator$Language;>;
  #193 = Utf8               SourceFile
  #194 = Utf8               DeeplTranslator.java
  #195 = Utf8               NestHost
  #196 = Class              #197          // ext/mods/Crypta/DeeplTranslator
  #197 = Utf8               ext/mods/Crypta/DeeplTranslator
  #198 = Utf8               BootstrapMethods
  #199 = MethodType         #200          //  (Ljava/lang/Object;)Z
  #200 = Utf8               (Ljava/lang/Object;)Z
  #201 = MethodHandle       6:#202        // REF_invokeStatic ext/mods/Crypta/DeeplTranslator$Language.lambda$fromCode$0:(Ljava/lang/String;Lext/mods/Crypta/DeeplTranslator$Language;)Z
  #202 = Methodref          #1.#203       // ext/mods/Crypta/DeeplTranslator$Language.lambda$fromCode$0:(Ljava/lang/String;Lext/mods/Crypta/DeeplTranslator$Language;)Z
  #203 = NameAndType        #187:#188     // lambda$fromCode$0:(Ljava/lang/String;Lext/mods/Crypta/DeeplTranslator$Language;)Z
  #204 = MethodType         #205          //  (Lext/mods/Crypta/DeeplTranslator$Language;)Z
  #205 = Utf8               (Lext/mods/Crypta/DeeplTranslator$Language;)Z
  #206 = MethodHandle       6:#207        // REF_invokeStatic java/lang/invoke/LambdaMetafactory.metafactory:(Ljava/lang/invoke/MethodHandles$Lookup;Ljava/lang/String;Ljava/lang/invoke/MethodType;Ljava/lang/invoke/MethodType;Ljava/lang/invoke/MethodHandle;Ljava/lang/invoke/MethodType;)Ljava/lang/invoke/CallSite;
  #207 = Methodref          #208.#209     // java/lang/invoke/LambdaMetafactory.metafactory:(Ljava/lang/invoke/MethodHandles$Lookup;Ljava/lang/String;Ljava/lang/invoke/MethodType;Ljava/lang/invoke/MethodType;Ljava/lang/invoke/MethodHandle;Ljava/lang/invoke/MethodType;)Ljava/lang/invoke/CallSite;
  #208 = Class              #210          // java/lang/invoke/LambdaMetafactory
  #209 = NameAndType        #211:#212     // metafactory:(Ljava/lang/invoke/MethodHandles$Lookup;Ljava/lang/String;Ljava/lang/invoke/MethodType;Ljava/lang/invoke/MethodType;Ljava/lang/invoke/MethodHandle;Ljava/lang/invoke/MethodType;)Ljava/lang/invoke/CallSite;
  #210 = Utf8               java/lang/invoke/LambdaMetafactory
  #211 = Utf8               metafactory
  #212 = Utf8               (Ljava/lang/invoke/MethodHandles$Lookup;Ljava/lang/String;Ljava/lang/invoke/MethodType;Ljava/lang/invoke/MethodType;Ljava/lang/invoke/MethodHandle;Ljava/lang/invoke/MethodType;)Ljava/lang/invoke/CallSite;
  #213 = Utf8               InnerClasses
  #214 = Utf8               Language
  #215 = Class              #216          // java/lang/invoke/MethodHandles$Lookup
  #216 = Utf8               java/lang/invoke/MethodHandles$Lookup
  #217 = Class              #218          // java/lang/invoke/MethodHandles
  #218 = Utf8               java/lang/invoke/MethodHandles
  #219 = Utf8               Lookup
{
  public static final ext.mods.Crypta.DeeplTranslator$Language ENGLISH;
    descriptor: Lext/mods/Crypta/DeeplTranslator$Language;
    flags: (0x4019) ACC_PUBLIC, ACC_STATIC, ACC_FINAL, ACC_ENUM

  public static final ext.mods.Crypta.DeeplTranslator$Language PORTUGUESE;
    descriptor: Lext/mods/Crypta/DeeplTranslator$Language;
    flags: (0x4019) ACC_PUBLIC, ACC_STATIC, ACC_FINAL, ACC_ENUM

  public static final ext.mods.Crypta.DeeplTranslator$Language SPANISH;
    descriptor: Lext/mods/Crypta/DeeplTranslator$Language;
    flags: (0x4019) ACC_PUBLIC, ACC_STATIC, ACC_FINAL, ACC_ENUM

  public static final ext.mods.Crypta.DeeplTranslator$Language KOREAN;
    descriptor: Lext/mods/Crypta/DeeplTranslator$Language;
    flags: (0x4019) ACC_PUBLIC, ACC_STATIC, ACC_FINAL, ACC_ENUM

  public static final ext.mods.Crypta.DeeplTranslator$Language RUSSIAN;
    descriptor: Lext/mods/Crypta/DeeplTranslator$Language;
    flags: (0x4019) ACC_PUBLIC, ACC_STATIC, ACC_FINAL, ACC_ENUM

  public static final ext.mods.Crypta.DeeplTranslator$Language CHINESE;
    descriptor: Lext/mods/Crypta/DeeplTranslator$Language;
    flags: (0x4019) ACC_PUBLIC, ACC_STATIC, ACC_FINAL, ACC_ENUM

  public static final ext.mods.Crypta.DeeplTranslator$Language GERMAN;
    descriptor: Lext/mods/Crypta/DeeplTranslator$Language;
    flags: (0x4019) ACC_PUBLIC, ACC_STATIC, ACC_FINAL, ACC_ENUM

  public static final ext.mods.Crypta.DeeplTranslator$Language ITALIAN;
    descriptor: Lext/mods/Crypta/DeeplTranslator$Language;
    flags: (0x4019) ACC_PUBLIC, ACC_STATIC, ACC_FINAL, ACC_ENUM

  public static final ext.mods.Crypta.DeeplTranslator$Language FRENCH;
    descriptor: Lext/mods/Crypta/DeeplTranslator$Language;
    flags: (0x4019) ACC_PUBLIC, ACC_STATIC, ACC_FINAL, ACC_ENUM

  public static final ext.mods.Crypta.DeeplTranslator$Language POLISH;
    descriptor: Lext/mods/Crypta/DeeplTranslator$Language;
    flags: (0x4019) ACC_PUBLIC, ACC_STATIC, ACC_FINAL, ACC_ENUM

  public static final ext.mods.Crypta.DeeplTranslator$Language GREEK;
    descriptor: Lext/mods/Crypta/DeeplTranslator$Language;
    flags: (0x4019) ACC_PUBLIC, ACC_STATIC, ACC_FINAL, ACC_ENUM

  public static final ext.mods.Crypta.DeeplTranslator$Language JAPANESE;
    descriptor: Lext/mods/Crypta/DeeplTranslator$Language;
    flags: (0x4019) ACC_PUBLIC, ACC_STATIC, ACC_FINAL, ACC_ENUM

  public static ext.mods.Crypta.DeeplTranslator$Language[] values();
    descriptor: ()[Lext/mods/Crypta/DeeplTranslator$Language;
    flags: (0x0009) ACC_PUBLIC, ACC_STATIC
    Code:
      stack=1, locals=0, args_size=0
         0: getstatic     #40                 // Field $VALUES:[Lext/mods/Crypta/DeeplTranslator$Language;
         3: invokevirtual #44                 // Method "[Lext/mods/Crypta/DeeplTranslator$Language;".clone:()Ljava/lang/Object;
         6: checkcast     #45                 // class "[Lext/mods/Crypta/DeeplTranslator$Language;"
         9: areturn
      LineNumberTable:
        line 59: 0

  public static ext.mods.Crypta.DeeplTranslator$Language valueOf(java.lang.String);
    descriptor: (Ljava/lang/String;)Lext/mods/Crypta/DeeplTranslator$Language;
    flags: (0x0009) ACC_PUBLIC, ACC_STATIC
    Code:
      stack=2, locals=1, args_size=1
         0: ldc           #1                  // class ext/mods/Crypta/DeeplTranslator$Language
         2: aload_0
         3: invokestatic  #49                 // Method java/lang/Enum.valueOf:(Ljava/lang/Class;Ljava/lang/String;)Ljava/lang/Enum;
         6: checkcast     #1                  // class ext/mods/Crypta/DeeplTranslator$Language
         9: areturn
      LineNumberTable:
        line 59: 0
      LocalVariableTable:
        Start  Length  Slot  Name   Signature
            0      10     0  name   Ljava/lang/String;
    MethodParameters:
      Name                           Flags
      <no name>                      mandated

  public java.lang.String getCode();
    descriptor: ()Ljava/lang/String;
    flags: (0x0001) ACC_PUBLIC
    Code:
      stack=1, locals=1, args_size=1
         0: aload_0
         1: getfield      #59                 // Field _code:Ljava/lang/String;
         4: areturn
      LineNumberTable:
        line 84: 0
      LocalVariableTable:
        Start  Length  Slot  Name   Signature
            0       5     0  this   Lext/mods/Crypta/DeeplTranslator$Language;

  public java.lang.String getDisplayName();
    descriptor: ()Ljava/lang/String;
    flags: (0x0001) ACC_PUBLIC
    Code:
      stack=1, locals=1, args_size=1
         0: aload_0
         1: getfield      #63                 // Field _displayName:Ljava/lang/String;
         4: areturn
      LineNumberTable:
        line 88: 0
      LocalVariableTable:
        Start  Length  Slot  Name   Signature
            0       5     0  this   Lext/mods/Crypta/DeeplTranslator$Language;

  public boolean isOriginal();
    descriptor: ()Z
    flags: (0x0001) ACC_PUBLIC
    Code:
      stack=1, locals=1, args_size=1
         0: aload_0
         1: getfield      #66                 // Field _isOriginal:Z
         4: ireturn
      LineNumberTable:
        line 92: 0
      LocalVariableTable:
        Start  Length  Slot  Name   Signature
            0       5     0  this   Lext/mods/Crypta/DeeplTranslator$Language;

  public static java.util.Optional<ext.mods.Crypta.DeeplTranslator$Language> fromCode(java.lang.String);
    descriptor: (Ljava/lang/String;)Ljava/util/Optional;
    flags: (0x0009) ACC_PUBLIC, ACC_STATIC
    Code:
      stack=2, locals=1, args_size=1
         0: invokestatic  #70                 // Method values:()[Lext/mods/Crypta/DeeplTranslator$Language;
         3: invokestatic  #74                 // Method java/util/Arrays.stream:([Ljava/lang/Object;)Ljava/util/stream/Stream;
         6: aload_0
         7: invokedynamic #80,  0             // InvokeDynamic #0:test:(Ljava/lang/String;)Ljava/util/function/Predicate;
        12: invokeinterface #84,  2           // InterfaceMethod java/util/stream/Stream.filter:(Ljava/util/function/Predicate;)Ljava/util/stream/Stream;
        17: invokeinterface #90,  1           // InterfaceMethod java/util/stream/Stream.findFirst:()Ljava/util/Optional;
        22: areturn
      LineNumberTable:
        line 96: 0
        line 97: 12
        line 98: 17
        line 96: 22
      LocalVariableTable:
        Start  Length  Slot  Name   Signature
            0      23     0  code   Ljava/lang/String;
    Signature: #186                         // (Ljava/lang/String;)Ljava/util/Optional<Lext/mods/Crypta/DeeplTranslator$Language;>;

  static {};
    descriptor: ()V
    flags: (0x0008) ACC_STATIC
    Code:
      stack=7, locals=0, args_size=0
         0: new           #1                  // class ext/mods/Crypta/DeeplTranslator$Language
         3: dup
         4: ldc           #104                // String ENGLISH
         6: iconst_0
         7: ldc           #105                // String en_US
         9: ldc           #107                // String English
        11: iconst_1
        12: invokespecial #109                // Method "<init>":(Ljava/lang/String;ILjava/lang/String;Ljava/lang/String;Z)V
        15: putstatic     #3                  // Field ENGLISH:Lext/mods/Crypta/DeeplTranslator$Language;
        18: new           #1                  // class ext/mods/Crypta/DeeplTranslator$Language
        21: dup
        22: ldc           #112                // String PORTUGUESE
        24: iconst_1
        25: ldc           #113                // String pt-BR
        27: ldc           #115                // String Portuguese
        29: iconst_0
        30: invokespecial #109                // Method "<init>":(Ljava/lang/String;ILjava/lang/String;Ljava/lang/String;Z)V
        33: putstatic     #7                  // Field PORTUGUESE:Lext/mods/Crypta/DeeplTranslator$Language;
        36: new           #1                  // class ext/mods/Crypta/DeeplTranslator$Language
        39: dup
        40: ldc           #117                // String SPANISH
        42: iconst_2
        43: ldc           #118                // String es
        45: ldc           #120                // String Spanish
        47: iconst_0
        48: invokespecial #109                // Method "<init>":(Ljava/lang/String;ILjava/lang/String;Ljava/lang/String;Z)V
        51: putstatic     #10                 // Field SPANISH:Lext/mods/Crypta/DeeplTranslator$Language;
        54: new           #1                  // class ext/mods/Crypta/DeeplTranslator$Language
        57: dup
        58: ldc           #122                // String KOREAN
        60: iconst_3
        61: ldc           #123                // String ko
        63: ldc           #125                // String Korean
        65: iconst_0
        66: invokespecial #109                // Method "<init>":(Ljava/lang/String;ILjava/lang/String;Ljava/lang/String;Z)V
        69: putstatic     #13                 // Field KOREAN:Lext/mods/Crypta/DeeplTranslator$Language;
        72: new           #1                  // class ext/mods/Crypta/DeeplTranslator$Language
        75: dup
        76: ldc           #127                // String RUSSIAN
        78: iconst_4
        79: ldc           #128                // String ru_RU
        81: ldc           #130                // String Russian
        83: iconst_0
        84: invokespecial #109                // Method "<init>":(Ljava/lang/String;ILjava/lang/String;Ljava/lang/String;Z)V
        87: putstatic     #16                 // Field RUSSIAN:Lext/mods/Crypta/DeeplTranslator$Language;
        90: new           #1                  // class ext/mods/Crypta/DeeplTranslator$Language
        93: dup
        94: ldc           #132                // String CHINESE
        96: iconst_5
        97: ldc           #133                // String zh
        99: ldc           #135                // String Chinese
       101: iconst_0
       102: invokespecial #109                // Method "<init>":(Ljava/lang/String;ILjava/lang/String;Ljava/lang/String;Z)V
       105: putstatic     #19                 // Field CHINESE:Lext/mods/Crypta/DeeplTranslator$Language;
       108: new           #1                  // class ext/mods/Crypta/DeeplTranslator$Language
       111: dup
       112: ldc           #137                // String GERMAN
       114: bipush        6
       116: ldc           #138                // String de
       118: ldc           #140                // String German
       120: iconst_0
       121: invokespecial #109                // Method "<init>":(Ljava/lang/String;ILjava/lang/String;Ljava/lang/String;Z)V
       124: putstatic     #22                 // Field GERMAN:Lext/mods/Crypta/DeeplTranslator$Language;
       127: new           #1                  // class ext/mods/Crypta/DeeplTranslator$Language
       130: dup
       131: ldc           #142                // String ITALIAN
       133: bipush        7
       135: ldc           #143                // String it
       137: ldc           #145                // String Italian
       139: iconst_0
       140: invokespecial #109                // Method "<init>":(Ljava/lang/String;ILjava/lang/String;Ljava/lang/String;Z)V
       143: putstatic     #25                 // Field ITALIAN:Lext/mods/Crypta/DeeplTranslator$Language;
       146: new           #1                  // class ext/mods/Crypta/DeeplTranslator$Language
       149: dup
       150: ldc           #147                // String FRENCH
       152: bipush        8
       154: ldc           #148                // String fr
       156: ldc           #150                // String French
       158: iconst_0
       159: invokespecial #109                // Method "<init>":(Ljava/lang/String;ILjava/lang/String;Ljava/lang/String;Z)V
       162: putstatic     #28                 // Field FRENCH:Lext/mods/Crypta/DeeplTranslator$Language;
       165: new           #1                  // class ext/mods/Crypta/DeeplTranslator$Language
       168: dup
       169: ldc           #152                // String POLISH
       171: bipush        9
       173: ldc           #153                // String pl
       175: ldc           #155                // String Polish
       177: iconst_0
       178: invokespecial #109                // Method "<init>":(Ljava/lang/String;ILjava/lang/String;Ljava/lang/String;Z)V
       181: putstatic     #31                 // Field POLISH:Lext/mods/Crypta/DeeplTranslator$Language;
       184: new           #1                  // class ext/mods/Crypta/DeeplTranslator$Language
       187: dup
       188: ldc           #157                // String GREEK
       190: bipush        10
       192: ldc           #158                // String el
       194: ldc           #160                // String Greek
       196: iconst_0
       197: invokespecial #109                // Method "<init>":(Ljava/lang/String;ILjava/lang/String;Ljava/lang/String;Z)V
       200: putstatic     #34                 // Field GREEK:Lext/mods/Crypta/DeeplTranslator$Language;
       203: new           #1                  // class ext/mods/Crypta/DeeplTranslator$Language
       206: dup
       207: ldc           #162                // String JAPANESE
       209: bipush        11
       211: ldc           #163                // String ja
       213: ldc           #165                // String Japanese
       215: iconst_0
       216: invokespecial #109                // Method "<init>":(Ljava/lang/String;ILjava/lang/String;Ljava/lang/String;Z)V
       219: putstatic     #37                 // Field JAPANESE:Lext/mods/Crypta/DeeplTranslator$Language;
       222: invokestatic  #167                // Method $values:()[Lext/mods/Crypta/DeeplTranslator$Language;
       225: putstatic     #40                 // Field $VALUES:[Lext/mods/Crypta/DeeplTranslator$Language;
       228: return
      LineNumberTable:
        line 60: 0
        line 61: 18
        line 62: 36
        line 63: 54
        line 64: 72
        line 65: 90
        line 66: 108
        line 67: 127
        line 68: 146
        line 69: 165
        line 70: 184
        line 71: 203
        line 59: 222
}
Signature: #192                         // Ljava/lang/Enum<Lext/mods/Crypta/DeeplTranslator$Language;>;
SourceFile: "DeeplTranslator.java"
NestHost: class ext/mods/Crypta/DeeplTranslator
BootstrapMethods:
  0: #206 REF_invokeStatic java/lang/invoke/LambdaMetafactory.metafactory:(Ljava/lang/invoke/MethodHandles$Lookup;Ljava/lang/String;Ljava/lang/invoke/MethodType;Ljava/lang/invoke/MethodType;Ljava/lang/invoke/MethodHandle;Ljava/lang/invoke/MethodType;)Ljava/lang/invoke/CallSite;
    Method arguments:
      #199 (Ljava/lang/Object;)Z
      #201 REF_invokeStatic ext/mods/Crypta/DeeplTranslator$Language.lambda$fromCode$0:(Ljava/lang/String;Lext/mods/Crypta/DeeplTranslator$Language;)Z
      #204 (Lext/mods/Crypta/DeeplTranslator$Language;)Z
InnerClasses:
  public static final #214= #1 of #196;   // Language=class ext/mods/Crypta/DeeplTranslator$Language of class ext/mods/Crypta/DeeplTranslator
  public static final #219= #215 of #217; // Lookup=class java/lang/invoke/MethodHandles$Lookup of class java/lang/invoke/MethodHandles
