// Bytecode for: ext.mods.Crypta.PlayerEmailManager
// File: ext\mods\Crypta\PlayerEmailManager.class

Classfile /c:/Users/User/Desktop/BrProject/bin/main/ext/mods/Crypta/PlayerEmailManager.class
  Last modified 9 de jul de 2026; size 11286 bytes
  MD5 checksum 543c0569aa18ac8994f8896760455287
  Compiled from "PlayerEmailManager.java"
public class ext.mods.Crypta.PlayerEmailManager
  minor version: 0
  major version: 69
  flags: (0x0021) ACC_PUBLIC, ACC_SUPER
  this_class: #14                         // ext/mods/Crypta/PlayerEmailManager
  super_class: #2                         // java/lang/Object
  interfaces: 0, fields: 1, methods: 7, attributes: 4
Constant pool:
    #1 = Methodref          #2.#3         // java/lang/Object."<init>":()V
    #2 = Class              #4            // java/lang/Object
    #3 = NameAndType        #5:#6         // "<init>":()V
    #4 = Utf8               java/lang/Object
    #5 = Utf8               <init>
    #6 = Utf8               ()V
    #7 = Methodref          #8.#9         // ext/mods/util/Tokenizer.getToken:(I)Ljava/lang/String;
    #8 = Class              #10           // ext/mods/util/Tokenizer
    #9 = NameAndType        #11:#12       // getToken:(I)Ljava/lang/String;
   #10 = Utf8               ext/mods/util/Tokenizer
   #11 = Utf8               getToken
   #12 = Utf8               (I)Ljava/lang/String;
   #13 = Methodref          #14.#15       // ext/mods/Crypta/PlayerEmailManager.navi:(Lext/mods/gameserver/model/actor/Player;Ljava/lang/String;)V
   #14 = Class              #16           // ext/mods/Crypta/PlayerEmailManager
   #15 = NameAndType        #17:#18       // navi:(Lext/mods/gameserver/model/actor/Player;Ljava/lang/String;)V
   #16 = Utf8               ext/mods/Crypta/PlayerEmailManager
   #17 = Utf8               navi
   #18 = Utf8               (Lext/mods/gameserver/model/actor/Player;Ljava/lang/String;)V
   #19 = Class              #20           // ext/mods/gameserver/network/serverpackets/NpcHtmlMessage
   #20 = Utf8               ext/mods/gameserver/network/serverpackets/NpcHtmlMessage
   #21 = Methodref          #19.#22       // ext/mods/gameserver/network/serverpackets/NpcHtmlMessage."<init>":(I)V
   #22 = NameAndType        #5:#23        // "<init>":(I)V
   #23 = Utf8               (I)V
   #24 = Methodref          #25.#26       // ext/mods/gameserver/model/actor/Player.getLocale:()Ljava/util/Locale;
   #25 = Class              #27           // ext/mods/gameserver/model/actor/Player
   #26 = NameAndType        #28:#29       // getLocale:()Ljava/util/Locale;
   #27 = Utf8               ext/mods/gameserver/model/actor/Player
   #28 = Utf8               getLocale
   #29 = Utf8               ()Ljava/util/Locale;
   #30 = InvokeDynamic      #0:#31        // #0:makeConcatWithConstants:(Ljava/lang/String;)Ljava/lang/String;
   #31 = NameAndType        #32:#33       // makeConcatWithConstants:(Ljava/lang/String;)Ljava/lang/String;
   #32 = Utf8               makeConcatWithConstants
   #33 = Utf8               (Ljava/lang/String;)Ljava/lang/String;
   #34 = Methodref          #19.#35       // ext/mods/gameserver/network/serverpackets/NpcHtmlMessage.setFile:(Ljava/util/Locale;Ljava/lang/String;)V
   #35 = NameAndType        #36:#37       // setFile:(Ljava/util/Locale;Ljava/lang/String;)V
   #36 = Utf8               setFile
   #37 = Utf8               (Ljava/util/Locale;Ljava/lang/String;)V
   #38 = Class              #39           // java/lang/StringBuilder
   #39 = Utf8               java/lang/StringBuilder
   #40 = Methodref          #38.#3        // java/lang/StringBuilder."<init>":()V
   #41 = Methodref          #25.#42       // ext/mods/gameserver/model/actor/Player.getSelectedEmailTarget:()Ljava/lang/String;
   #42 = NameAndType        #43:#44       // getSelectedEmailTarget:()Ljava/lang/String;
   #43 = Utf8               getSelectedEmailTarget
   #44 = Utf8               ()Ljava/lang/String;
   #45 = String             #46           // <table width=300 cellpadding=2 cellspacing=2 align=center bgcolor=000000>
   #46 = Utf8               <table width=300 cellpadding=2 cellspacing=2 align=center bgcolor=000000>
   #47 = Methodref          #38.#48       // java/lang/StringBuilder.append:(Ljava/lang/String;)Ljava/lang/StringBuilder;
   #48 = NameAndType        #49:#50       // append:(Ljava/lang/String;)Ljava/lang/StringBuilder;
   #49 = Utf8               append
   #50 = Utf8               (Ljava/lang/String;)Ljava/lang/StringBuilder;
   #51 = String             #52           // <tr>
   #52 = Utf8               <tr>
   #53 = String             #54           // <td width=60 align=right><font color=LEVEL>Jogador:</font></td>
   #54 = Utf8               <td width=60 align=right><font color=LEVEL>Jogador:</font></td>
   #55 = InvokeDynamic      #1:#31        // #1:makeConcatWithConstants:(Ljava/lang/String;)Ljava/lang/String;
   #56 = String             #57           // <td width=80 align=center>
   #57 = Utf8               <td width=80 align=center>
   #58 = String             #59           // <button value=\"Limpar\" action=\"bypass -h voiced_email clean\" width=55 height=15 back=sek.cbui94 fore=sek.cbui92>
   #59 = Utf8               <button value=\"Limpar\" action=\"bypass -h voiced_email clean\" width=55 height=15 back=sek.cbui94 fore=sek.cbui92>
   #60 = String             #61           // </td>
   #61 = Utf8               </td>
   #62 = String             #63           // <td width=120 align=left><edit var=\"targetName\" width=150></td>
   #63 = Utf8               <td width=120 align=left><edit var=\"targetName\" width=150></td>
   #64 = String             #65           // <button value=\"Buscar\" action=\"bypass -h voiced_email search $targetName\" width=55 height=15 back=sek.cbui94 fore=sek.cbui92><br>
   #65 = Utf8               <button value=\"Buscar\" action=\"bypass -h voiced_email search $targetName\" width=55 height=15 back=sek.cbui94 fore=sek.cbui92><br>
   #66 = String             #67           // </tr>
   #67 = Utf8               </tr>
   #68 = String             #69           // </table><br>
   #69 = Utf8               </table><br>
   #70 = String             #71           // %playerinfo%
   #71 = Utf8               %playerinfo%
   #72 = Methodref          #38.#73       // java/lang/StringBuilder.toString:()Ljava/lang/String;
   #73 = NameAndType        #74:#44       // toString:()Ljava/lang/String;
   #74 = Utf8               toString
   #75 = Methodref          #19.#76       // ext/mods/gameserver/network/serverpackets/NpcHtmlMessage.replace:(Ljava/lang/String;Ljava/lang/String;)V
   #76 = NameAndType        #77:#78       // replace:(Ljava/lang/String;Ljava/lang/String;)V
   #77 = Utf8               replace
   #78 = Utf8               (Ljava/lang/String;Ljava/lang/String;)V
   #79 = String             #80           // %targetName%
   #80 = Utf8               %targetName%
   #81 = String             #82           // invalido
   #82 = Utf8               invalido
   #83 = Methodref          #25.#84       // ext/mods/gameserver/model/actor/Player.sendPacket:(Lext/mods/gameserver/network/serverpackets/L2GameServerPacket;)V
   #84 = NameAndType        #85:#86       // sendPacket:(Lext/mods/gameserver/network/serverpackets/L2GameServerPacket;)V
   #85 = Utf8               sendPacket
   #86 = Utf8               (Lext/mods/gameserver/network/serverpackets/L2GameServerPacket;)V
   #87 = String             #88           // <html><title>Email Search</title><body><center>
   #88 = Utf8               <html><title>Email Search</title><body><center>
   #89 = String             #90           // <font color=LEVEL>Resultado da Busca</font>
   #90 = Utf8               <font color=LEVEL>Resultado da Busca</font>
   #91 = String             #92           // <table width=300 border=1 cellspacing=0 cellpadding=3 bgcolor=000000>
   #92 = Utf8               <table width=300 border=1 cellspacing=0 cellpadding=3 bgcolor=000000>
   #93 = String             #94           // <td width=60 align=center><font color=LEVEL>Status</font></td>
   #94 = Utf8               <td width=60 align=center><font color=LEVEL>Status</font></td>
   #95 = String             #96           // <td width=110 align=center><font color=LEVEL>Nome</font></td>
   #96 = Utf8               <td width=110 align=center><font color=LEVEL>Nome</font></td>
   #97 = String             #98           // <td width=50 align=center><font color=LEVEL>Ação</font></td>
   #98 = Utf8               <td width=50 align=center><font color=LEVEL>Ação</font></td>
   #99 = String             #100          // </table>
  #100 = Utf8               </table>
  #101 = String             #102          // <table width=300 cellspacing=0 cellpadding=3 bgcolor=000000>
  #102 = Utf8               <table width=300 cellspacing=0 cellpadding=3 bgcolor=000000>
  #103 = Methodref          #104.#105     // ext/mods/commons/pool/ConnectionPool.getConnection:()Ljava/sql/Connection;
  #104 = Class              #106          // ext/mods/commons/pool/ConnectionPool
  #105 = NameAndType        #107:#108     // getConnection:()Ljava/sql/Connection;
  #106 = Utf8               ext/mods/commons/pool/ConnectionPool
  #107 = Utf8               getConnection
  #108 = Utf8               ()Ljava/sql/Connection;
  #109 = String             #110          // SELECT char_name, online FROM characters WHERE LOWER(char_name) LIKE ? AND char_name != ? AND accesslevel = 0 ORDER BY online DESC, char_name LIMIT 15
  #110 = Utf8               SELECT char_name, online FROM characters WHERE LOWER(char_name) LIKE ? AND char_name != ? AND accesslevel = 0 ORDER BY online DESC, char_name LIMIT 15
  #111 = InterfaceMethodref #112.#113     // java/sql/Connection.prepareStatement:(Ljava/lang/String;)Ljava/sql/PreparedStatement;
  #112 = Class              #114          // java/sql/Connection
  #113 = NameAndType        #115:#116     // prepareStatement:(Ljava/lang/String;)Ljava/sql/PreparedStatement;
  #114 = Utf8               java/sql/Connection
  #115 = Utf8               prepareStatement
  #116 = Utf8               (Ljava/lang/String;)Ljava/sql/PreparedStatement;
  #117 = Methodref          #118.#119     // java/lang/String.toLowerCase:()Ljava/lang/String;
  #118 = Class              #120          // java/lang/String
  #119 = NameAndType        #121:#44      // toLowerCase:()Ljava/lang/String;
  #120 = Utf8               java/lang/String
  #121 = Utf8               toLowerCase
  #122 = InvokeDynamic      #2:#31        // #2:makeConcatWithConstants:(Ljava/lang/String;)Ljava/lang/String;
  #123 = InterfaceMethodref #124.#125     // java/sql/PreparedStatement.setString:(ILjava/lang/String;)V
  #124 = Class              #126          // java/sql/PreparedStatement
  #125 = NameAndType        #127:#128     // setString:(ILjava/lang/String;)V
  #126 = Utf8               java/sql/PreparedStatement
  #127 = Utf8               setString
  #128 = Utf8               (ILjava/lang/String;)V
  #129 = Methodref          #25.#130      // ext/mods/gameserver/model/actor/Player.getName:()Ljava/lang/String;
  #130 = NameAndType        #131:#44      // getName:()Ljava/lang/String;
  #131 = Utf8               getName
  #132 = InterfaceMethodref #124.#133     // java/sql/PreparedStatement.executeQuery:()Ljava/sql/ResultSet;
  #133 = NameAndType        #134:#135     // executeQuery:()Ljava/sql/ResultSet;
  #134 = Utf8               executeQuery
  #135 = Utf8               ()Ljava/sql/ResultSet;
  #136 = InterfaceMethodref #137.#138     // java/sql/ResultSet.next:()Z
  #137 = Class              #139          // java/sql/ResultSet
  #138 = NameAndType        #140:#141     // next:()Z
  #139 = Utf8               java/sql/ResultSet
  #140 = Utf8               next
  #141 = Utf8               ()Z
  #142 = String             #143          // char_name
  #143 = Utf8               char_name
  #144 = InterfaceMethodref #137.#145     // java/sql/ResultSet.getString:(Ljava/lang/String;)Ljava/lang/String;
  #145 = NameAndType        #146:#33      // getString:(Ljava/lang/String;)Ljava/lang/String;
  #146 = Utf8               getString
  #147 = Methodref          #118.#148     // java/lang/String.length:()I
  #148 = NameAndType        #149:#150     // length:()I
  #149 = Utf8               length
  #150 = Utf8               ()I
  #151 = Methodref          #118.#152     // java/lang/String.substring:(II)Ljava/lang/String;
  #152 = NameAndType        #153:#154     // substring:(II)Ljava/lang/String;
  #153 = Utf8               substring
  #154 = Utf8               (II)Ljava/lang/String;
  #155 = InvokeDynamic      #3:#31        // #3:makeConcatWithConstants:(Ljava/lang/String;)Ljava/lang/String;
  #156 = String             #157          // online
  #157 = Utf8               online
  #158 = InterfaceMethodref #137.#159     // java/sql/ResultSet.getInt:(Ljava/lang/String;)I
  #159 = NameAndType        #160:#161     // getInt:(Ljava/lang/String;)I
  #160 = Utf8               getInt
  #161 = Utf8               (Ljava/lang/String;)I
  #162 = String             #163          // <td width=60 align=center><font color=
  #163 = Utf8               <td width=60 align=center><font color=
  #164 = String             #165          // 00FF00
  #165 = Utf8               00FF00
  #166 = String             #167          // FF0000
  #167 = Utf8               FF0000
  #168 = String             #169          // >
  #169 = Utf8               >
  #170 = String             #171          // Online
  #171 = Utf8               Online
  #172 = String             #173          // Offline
  #173 = Utf8               Offline
  #174 = String             #175          // </font></td>
  #175 = Utf8               </font></td>
  #176 = String             #177          // <td width=110 align=center>
  #177 = Utf8               <td width=110 align=center>
  #178 = String             #179          // <td width=50 align=center>
  #179 = Utf8               <td width=50 align=center>
  #180 = String             #181          // <button value=\"OK\" action=\"bypass -h voiced_email target
  #181 = Utf8               <button value=\"OK\" action=\"bypass -h voiced_email target
  #182 = String             #183          // \" width=40 height=21 back=sek.cbui94 fore=sek.cbui92>
  #183 = Utf8               \" width=40 height=21 back=sek.cbui94 fore=sek.cbui92>
  #184 = String             #185          // </td></tr>
  #185 = Utf8               </td></tr>
  #186 = InterfaceMethodref #137.#187     // java/sql/ResultSet.close:()V
  #187 = NameAndType        #188:#6       // close:()V
  #188 = Utf8               close
  #189 = Class              #190          // java/lang/Throwable
  #190 = Utf8               java/lang/Throwable
  #191 = Methodref          #189.#192     // java/lang/Throwable.addSuppressed:(Ljava/lang/Throwable;)V
  #192 = NameAndType        #193:#194     // addSuppressed:(Ljava/lang/Throwable;)V
  #193 = Utf8               addSuppressed
  #194 = Utf8               (Ljava/lang/Throwable;)V
  #195 = InterfaceMethodref #124.#187     // java/sql/PreparedStatement.close:()V
  #196 = InterfaceMethodref #112.#187     // java/sql/Connection.close:()V
  #197 = Class              #198          // java/lang/Exception
  #198 = Utf8               java/lang/Exception
  #199 = Fieldref           #14.#200      // ext/mods/Crypta/PlayerEmailManager.LOGGER:Ljava/util/logging/Logger;
  #200 = NameAndType        #201:#202     // LOGGER:Ljava/util/logging/Logger;
  #201 = Utf8               LOGGER
  #202 = Utf8               Ljava/util/logging/Logger;
  #203 = Methodref          #197.#204     // java/lang/Exception.getMessage:()Ljava/lang/String;
  #204 = NameAndType        #205:#44      // getMessage:()Ljava/lang/String;
  #205 = Utf8               getMessage
  #206 = InvokeDynamic      #4:#31        // #4:makeConcatWithConstants:(Ljava/lang/String;)Ljava/lang/String;
  #207 = Methodref          #208.#209     // java/util/logging/Logger.warning:(Ljava/lang/String;)V
  #208 = Class              #210          // java/util/logging/Logger
  #209 = NameAndType        #211:#212     // warning:(Ljava/lang/String;)V
  #210 = Utf8               java/util/logging/Logger
  #211 = Utf8               warning
  #212 = Utf8               (Ljava/lang/String;)V
  #213 = String             #214          // <button value=\"Voltar\" action=\"bypass -h voiced_email htm email_main.htm\" width=80 height=21 back=\"L2UI_CH3.Btn1_normalOn\" fore=\"L2UI_CH3.Btn1_normal\">
  #214 = Utf8               <button value=\"Voltar\" action=\"bypass -h voiced_email htm email_main.htm\" width=80 height=21 back=\"L2UI_CH3.Btn1_normalOn\" fore=\"L2UI_CH3.Btn1_normal\">
  #215 = String             #216          // </center></body></html>
  #216 = Utf8               </center></body></html>
  #217 = Methodref          #19.#218      // ext/mods/gameserver/network/serverpackets/NpcHtmlMessage.setHtml:(Ljava/lang/String;)V
  #218 = NameAndType        #219:#212     // setHtml:(Ljava/lang/String;)V
  #219 = Utf8               setHtml
  #220 = Fieldref           #221.#222     // ext/mods/Crypta/PlayerEmailManager$SingletonHolder.instance:Lext/mods/Crypta/PlayerEmailManager;
  #221 = Class              #223          // ext/mods/Crypta/PlayerEmailManager$SingletonHolder
  #222 = NameAndType        #224:#225     // instance:Lext/mods/Crypta/PlayerEmailManager;
  #223 = Utf8               ext/mods/Crypta/PlayerEmailManager$SingletonHolder
  #224 = Utf8               instance
  #225 = Utf8               Lext/mods/Crypta/PlayerEmailManager;
  #226 = String             #227          // <html><body>
  #227 = Utf8               <html><body>
  #228 = String             #229          // <table width=300><tr><td align=center><font color=\"LEVEL\">Sua Inbox de Emails</font></td></tr></table><br>
  #229 = Utf8               <table width=300><tr><td align=center><font color=\"LEVEL\">Sua Inbox de Emails</font></td></tr></table><br>
  #230 = String             #231          // SELECT DISTINCT email_id, sender_id, expiration_time, is_paid, payment_item_id, payment_item_count FROM player_emails WHERE target_id=? AND status=\'PENDING\' AND expiration_time > ? ORDER BY created_time DESC
  #231 = Utf8               SELECT DISTINCT email_id, sender_id, expiration_time, is_paid, payment_item_id, payment_item_count FROM player_emails WHERE target_id=? AND status=\'PENDING\' AND expiration_time > ? ORDER BY created_time DESC
  #232 = Methodref          #25.#233      // ext/mods/gameserver/model/actor/Player.getObjectId:()I
  #233 = NameAndType        #234:#150     // getObjectId:()I
  #234 = Utf8               getObjectId
  #235 = InterfaceMethodref #124.#236     // java/sql/PreparedStatement.setInt:(II)V
  #236 = NameAndType        #237:#238     // setInt:(II)V
  #237 = Utf8               setInt
  #238 = Utf8               (II)V
  #239 = Methodref          #240.#241     // java/lang/System.currentTimeMillis:()J
  #240 = Class              #242          // java/lang/System
  #241 = NameAndType        #243:#244     // currentTimeMillis:()J
  #242 = Utf8               java/lang/System
  #243 = Utf8               currentTimeMillis
  #244 = Utf8               ()J
  #245 = InterfaceMethodref #124.#246     // java/sql/PreparedStatement.setLong:(IJ)V
  #246 = NameAndType        #247:#248     // setLong:(IJ)V
  #247 = Utf8               setLong
  #248 = Utf8               (IJ)V
  #249 = String             #250          // Nenhum email pendente.<br>
  #250 = Utf8               Nenhum email pendente.<br>
  #251 = String             #252          // email_id
  #252 = Utf8               email_id
  #253 = String             #254          // sender_id
  #254 = Utf8               sender_id
  #255 = String             #256          // expiration_time
  #256 = Utf8               expiration_time
  #257 = InterfaceMethodref #137.#258     // java/sql/ResultSet.getLong:(Ljava/lang/String;)J
  #258 = NameAndType        #259:#260     // getLong:(Ljava/lang/String;)J
  #259 = Utf8               getLong
  #260 = Utf8               (Ljava/lang/String;)J
  #261 = String             #262          // is_paid
  #262 = Utf8               is_paid
  #263 = InterfaceMethodref #137.#264     // java/sql/ResultSet.getBoolean:(Ljava/lang/String;)Z
  #264 = NameAndType        #265:#266     // getBoolean:(Ljava/lang/String;)Z
  #265 = Utf8               getBoolean
  #266 = Utf8               (Ljava/lang/String;)Z
  #267 = String             #268          // payment_item_id
  #268 = Utf8               payment_item_id
  #269 = String             #270          // payment_item_count
  #270 = Utf8               payment_item_count
  #271 = Methodref          #272.#273     // ext/mods/gameserver/data/sql/PlayerInfoTable.getInstance:()Lext/mods/gameserver/data/sql/PlayerInfoTable;
  #272 = Class              #274          // ext/mods/gameserver/data/sql/PlayerInfoTable
  #273 = NameAndType        #275:#276     // getInstance:()Lext/mods/gameserver/data/sql/PlayerInfoTable;
  #274 = Utf8               ext/mods/gameserver/data/sql/PlayerInfoTable
  #275 = Utf8               getInstance
  #276 = Utf8               ()Lext/mods/gameserver/data/sql/PlayerInfoTable;
  #277 = Methodref          #272.#278     // ext/mods/gameserver/data/sql/PlayerInfoTable.getPlayerName:(I)Ljava/lang/String;
  #278 = NameAndType        #279:#12      // getPlayerName:(I)Ljava/lang/String;
  #279 = Utf8               getPlayerName
  #280 = Long               60000l
  #282 = String             #283          // <table width=300 border=0>
  #283 = Utf8               <table width=300 border=0>
  #284 = String             #285          // <tr><td>Email ID:
  #285 = Utf8               <tr><td>Email ID:
  #286 = Methodref          #38.#287      // java/lang/StringBuilder.append:(I)Ljava/lang/StringBuilder;
  #287 = NameAndType        #49:#288      // append:(I)Ljava/lang/StringBuilder;
  #288 = Utf8               (I)Ljava/lang/StringBuilder;
  #289 = String             #290          //  de
  #290 = Utf8                de
  #291 = String             #292          // <tr><td>Expira em:
  #292 = Utf8               <tr><td>Expira em:
  #293 = Methodref          #38.#294      // java/lang/StringBuilder.append:(J)Ljava/lang/StringBuilder;
  #294 = NameAndType        #49:#295      // append:(J)Ljava/lang/StringBuilder;
  #295 = Utf8               (J)Ljava/lang/StringBuilder;
  #296 = String             #297          //  minutos</td></tr>
  #297 = Utf8                minutos</td></tr>
  #298 = String             #299          // SELECT item_id, count, enchant_level, is_augmented FROM player_emails WHERE email_id=?
  #299 = Utf8               SELECT item_id, count, enchant_level, is_augmented FROM player_emails WHERE email_id=?
  #300 = String             #301          // <tr><td>Itens:</td></tr>
  #301 = Utf8               <tr><td>Itens:</td></tr>
  #302 = String             #303          // item_id
  #303 = Utf8               item_id
  #304 = String             #305          // count
  #305 = Utf8               count
  #306 = String             #307          // enchant_level
  #307 = Utf8               enchant_level
  #308 = String             #309          // is_augmented
  #309 = Utf8               is_augmented
  #310 = Methodref          #311.#312     // ext/mods/gameserver/data/xml/ItemData.getInstance:()Lext/mods/gameserver/data/xml/ItemData;
  #311 = Class              #313          // ext/mods/gameserver/data/xml/ItemData
  #312 = NameAndType        #275:#314     // getInstance:()Lext/mods/gameserver/data/xml/ItemData;
  #313 = Utf8               ext/mods/gameserver/data/xml/ItemData
  #314 = Utf8               ()Lext/mods/gameserver/data/xml/ItemData;
  #315 = Methodref          #311.#316     // ext/mods/gameserver/data/xml/ItemData.getTemplate:(I)Lext/mods/gameserver/model/item/kind/Item;
  #316 = NameAndType        #317:#318     // getTemplate:(I)Lext/mods/gameserver/model/item/kind/Item;
  #317 = Utf8               getTemplate
  #318 = Utf8               (I)Lext/mods/gameserver/model/item/kind/Item;
  #319 = Methodref          #320.#130     // ext/mods/gameserver/model/item/kind/Item.getName:()Ljava/lang/String;
  #320 = Class              #321          // ext/mods/gameserver/model/item/kind/Item
  #321 = Utf8               ext/mods/gameserver/model/item/kind/Item
  #322 = InvokeDynamic      #5:#323       // #5:makeConcatWithConstants:(I)Ljava/lang/String;
  #323 = NameAndType        #32:#12       // makeConcatWithConstants:(I)Ljava/lang/String;
  #324 = String             #325          //
  #325 = Utf8
  #326 = String             #327          //  (Aug)
  #327 = Utf8                (Aug)
  #328 = InvokeDynamic      #6:#329       // #6:makeConcatWithConstants:(Ljava/lang/String;Ljava/lang/String;Ljava/lang/String;)Ljava/lang/String;
  #329 = NameAndType        #32:#330      // makeConcatWithConstants:(Ljava/lang/String;Ljava/lang/String;Ljava/lang/String;)Ljava/lang/String;
  #330 = Utf8               (Ljava/lang/String;Ljava/lang/String;Ljava/lang/String;)Ljava/lang/String;
  #331 = String             #332          // <tr><td>-
  #332 = Utf8               <tr><td>-
  #333 = String             #334          //  x
  #334 = Utf8                x
  #335 = String             #336          // <tr><td>Pagamento requerido:
  #336 = Utf8               <tr><td>Pagamento requerido:
  #337 = String             #338          // <tr><td><button value=\"Reclamar\" action=\"bypass -h voiced_email claim
  #338 = Utf8               <tr><td><button value=\"Reclamar\" action=\"bypass -h voiced_email claim
  #339 = String             #340          // \" width=75 height=21 back=\"L2UI_ch3.Btn1_normalOn\" fore=\"L2UI_ch3.Btn1_normal\"></td></tr>
  #340 = Utf8               \" width=75 height=21 back=\"L2UI_ch3.Btn1_normalOn\" fore=\"L2UI_ch3.Btn1_normal\"></td></tr>
  #341 = InvokeDynamic      #7:#31        // #7:makeConcatWithConstants:(Ljava/lang/String;)Ljava/lang/String;
  #342 = Methodref          #208.#343     // java/util/logging/Logger.severe:(Ljava/lang/String;)V
  #343 = NameAndType        #344:#212     // severe:(Ljava/lang/String;)V
  #344 = Utf8               severe
  #345 = Methodref          #197.#346     // java/lang/Exception.printStackTrace:()V
  #346 = NameAndType        #347:#6       // printStackTrace:()V
  #347 = Utf8               printStackTrace
  #348 = String             #349          // <table width=300><tr><td align=center>
  #349 = Utf8               <table width=300><tr><td align=center>
  #350 = String             #351          // <button value=\"Voltar\" action=\"bypass -h voiced_email htm email_main.htm\" width=75 height=21 back=\"L2UI_ch3.Btn1_normalOn\" fore=\"L2UI_ch3.Btn1_normal\">
  #351 = Utf8               <button value=\"Voltar\" action=\"bypass -h voiced_email htm email_main.htm\" width=75 height=21 back=\"L2UI_ch3.Btn1_normalOn\" fore=\"L2UI_ch3.Btn1_normal\">
  #352 = String             #353          // </td></tr></table>
  #353 = Utf8               </td></tr></table>
  #354 = String             #355          // </body></html>
  #355 = Utf8               </body></html>
  #356 = Methodref          #357.#130     // java/lang/Class.getName:()Ljava/lang/String;
  #357 = Class              #358          // java/lang/Class
  #358 = Utf8               java/lang/Class
  #359 = Methodref          #208.#360     // java/util/logging/Logger.getLogger:(Ljava/lang/String;)Ljava/util/logging/Logger;
  #360 = NameAndType        #361:#362     // getLogger:(Ljava/lang/String;)Ljava/util/logging/Logger;
  #361 = Utf8               getLogger
  #362 = Utf8               (Ljava/lang/String;)Ljava/util/logging/Logger;
  #363 = Utf8               Code
  #364 = Utf8               LineNumberTable
  #365 = Utf8               LocalVariableTable
  #366 = Utf8               this
  #367 = Utf8               handlerHtm
  #368 = Utf8               (Lext/mods/gameserver/model/actor/Player;Lext/mods/util/Tokenizer;)V
  #369 = Utf8               player
  #370 = Utf8               Lext/mods/gameserver/model/actor/Player;
  #371 = Utf8               tokenizer
  #372 = Utf8               Lext/mods/util/Tokenizer;
  #373 = Utf8               filename
  #374 = Utf8               Ljava/lang/String;
  #375 = Utf8               htm
  #376 = Utf8               Lext/mods/gameserver/network/serverpackets/NpcHtmlMessage;
  #377 = Utf8               sb
  #378 = Utf8               Ljava/lang/StringBuilder;
  #379 = Utf8               targetName
  #380 = Utf8               StackMapTable
  #381 = Utf8               searchPlayer
  #382 = Utf8               name
  #383 = Utf8               displayName
  #384 = Utf8               isOnline
  #385 = Utf8               Z
  #386 = Utf8               rs
  #387 = Utf8               Ljava/sql/ResultSet;
  #388 = Utf8               ps
  #389 = Utf8               Ljava/sql/PreparedStatement;
  #390 = Utf8               con
  #391 = Utf8               Ljava/sql/Connection;
  #392 = Utf8               e
  #393 = Utf8               Ljava/lang/Exception;
  #394 = Utf8               html
  #395 = Utf8               ()Lext/mods/Crypta/PlayerEmailManager;
  #396 = Utf8               showInbox
  #397 = Utf8               (Lext/mods/gameserver/model/actor/Player;)V
  #398 = Utf8               itemId
  #399 = Utf8               I
  #400 = Utf8               enchant
  #401 = Utf8               isAug
  #402 = Utf8               itemName
  #403 = Utf8               rsItems
  #404 = Utf8               psItems
  #405 = Utf8               payName
  #406 = Utf8               emailId
  #407 = Utf8               senderId
  #408 = Utf8               exp
  #409 = Utf8               J
  #410 = Utf8               isPaid
  #411 = Utf8               payItem
  #412 = Utf8               payCount
  #413 = Utf8               senderName
  #414 = Utf8               remaining
  #415 = Utf8               <clinit>
  #416 = Utf8               SourceFile
  #417 = Utf8               PlayerEmailManager.java
  #418 = Utf8               NestMembers
  #419 = Utf8               BootstrapMethods
  #420 = String             #421          // html/mods/menu/\u0001
  #421 = Utf8               html/mods/menu/\u0001
  #422 = String             #423          // <td width=120 align=left><font color=00FF00>\u0001</font></td>
  #423 = Utf8               <td width=120 align=left><font color=00FF00>\u0001</font></td>
  #424 = String             #425          // %\u0001%
  #425 = Utf8               %\u0001%
  #426 = String             #427          // \u0001...
  #427 = Utf8               \u0001...
  #428 = String             #429          // searchPlayer DB error: \u0001
  #429 = Utf8               searchPlayer DB error: \u0001
  #430 = String             #431          // +\u0001
  #431 = Utf8               +\u0001
  #432 = String             #433          // \u0001\u0001\u0001
  #433 = Utf8               \u0001\u0001\u0001
  #434 = String             #435          // Erro ao mostrar inbox: \u0001
  #435 = Utf8               Erro ao mostrar inbox: \u0001
  #436 = MethodHandle       6:#437        // REF_invokeStatic java/lang/invoke/StringConcatFactory.makeConcatWithConstants:(Ljava/lang/invoke/MethodHandles$Lookup;Ljava/lang/String;Ljava/lang/invoke/MethodType;Ljava/lang/String;[Ljava/lang/Object;)Ljava/lang/invoke/CallSite;
  #437 = Methodref          #438.#439     // java/lang/invoke/StringConcatFactory.makeConcatWithConstants:(Ljava/lang/invoke/MethodHandles$Lookup;Ljava/lang/String;Ljava/lang/invoke/MethodType;Ljava/lang/String;[Ljava/lang/Object;)Ljava/lang/invoke/CallSite;
  #438 = Class              #440          // java/lang/invoke/StringConcatFactory
  #439 = NameAndType        #32:#441      // makeConcatWithConstants:(Ljava/lang/invoke/MethodHandles$Lookup;Ljava/lang/String;Ljava/lang/invoke/MethodType;Ljava/lang/String;[Ljava/lang/Object;)Ljava/lang/invoke/CallSite;
  #440 = Utf8               java/lang/invoke/StringConcatFactory
  #441 = Utf8               (Ljava/lang/invoke/MethodHandles$Lookup;Ljava/lang/String;Ljava/lang/invoke/MethodType;Ljava/lang/String;[Ljava/lang/Object;)Ljava/lang/invoke/CallSite;
  #442 = Utf8               InnerClasses
  #443 = Utf8               SingletonHolder
  #444 = Class              #445          // java/lang/invoke/MethodHandles$Lookup
  #445 = Utf8               java/lang/invoke/MethodHandles$Lookup
  #446 = Class              #447          // java/lang/invoke/MethodHandles
  #447 = Utf8               java/lang/invoke/MethodHandles
  #448 = Utf8               Lookup
{
  public ext.mods.Crypta.PlayerEmailManager();
    descriptor: ()V
    flags: (0x0001) ACC_PUBLIC
    Code:
      stack=1, locals=1, args_size=1
         0: aload_0
         1: invokespecial #1                  // Method java/lang/Object."<init>":()V
         4: return
      LineNumberTable:
        line 33: 0
      LocalVariableTable:
        Start  Length  Slot  Name   Signature
            0       5     0  this   Lext/mods/Crypta/PlayerEmailManager;

  public void handlerHtm(ext.mods.gameserver.model.actor.Player, ext.mods.util.Tokenizer);
    descriptor: (Lext/mods/gameserver/model/actor/Player;Lext/mods/util/Tokenizer;)V
    flags: (0x0001) ACC_PUBLIC
    Code:
      stack=3, locals=4, args_size=3
         0: aload_2
         1: iconst_2
         2: invokevirtual #7                  // Method ext/mods/util/Tokenizer.getToken:(I)Ljava/lang/String;
         5: astore_3
         6: aload_0
         7: aload_1
         8: aload_3
         9: invokevirtual #13                 // Method navi:(Lext/mods/gameserver/model/actor/Player;Ljava/lang/String;)V
        12: return
      LineNumberTable:
        line 39: 0
        line 40: 6
        line 41: 12
      LocalVariableTable:
        Start  Length  Slot  Name   Signature
            0      13     0  this   Lext/mods/Crypta/PlayerEmailManager;
            0      13     1 player   Lext/mods/gameserver/model/actor/Player;
            0      13     2 tokenizer   Lext/mods/util/Tokenizer;
            6       7     3 filename   Ljava/lang/String;

  public void navi(ext.mods.gameserver.model.actor.Player, java.lang.String);
    descriptor: (Lext/mods/gameserver/model/actor/Player;Ljava/lang/String;)V
    flags: (0x0001) ACC_PUBLIC
    Code:
      stack=3, locals=6, args_size=3
         0: new           #19                 // class ext/mods/gameserver/network/serverpackets/NpcHtmlMessage
         3: dup
         4: iconst_0
         5: invokespecial #21                 // Method ext/mods/gameserver/network/serverpackets/NpcHtmlMessage."<init>":(I)V
         8: astore_3
         9: aload_3
        10: aload_1
        11: invokevirtual #24                 // Method ext/mods/gameserver/model/actor/Player.getLocale:()Ljava/util/Locale;
        14: aload_2
        15: invokedynamic #30,  0             // InvokeDynamic #0:makeConcatWithConstants:(Ljava/lang/String;)Ljava/lang/String;
        20: invokevirtual #34                 // Method ext/mods/gameserver/network/serverpackets/NpcHtmlMessage.setFile:(Ljava/util/Locale;Ljava/lang/String;)V
        23: new           #38                 // class java/lang/StringBuilder
        26: dup
        27: invokespecial #40                 // Method java/lang/StringBuilder."<init>":()V
        30: astore        4
        32: aload_1
        33: invokevirtual #41                 // Method ext/mods/gameserver/model/actor/Player.getSelectedEmailTarget:()Ljava/lang/String;
        36: astore        5
        38: aload         4
        40: ldc           #45                 // String <table width=300 cellpadding=2 cellspacing=2 align=center bgcolor=000000>
        42: invokevirtual #47                 // Method java/lang/StringBuilder.append:(Ljava/lang/String;)Ljava/lang/StringBuilder;
        45: pop
        46: aload         4
        48: ldc           #51                 // String <tr>
        50: invokevirtual #47                 // Method java/lang/StringBuilder.append:(Ljava/lang/String;)Ljava/lang/StringBuilder;
        53: pop
        54: aload         4
        56: ldc           #53                 // String <td width=60 align=right><font color=LEVEL>Jogador:</font></td>
        58: invokevirtual #47                 // Method java/lang/StringBuilder.append:(Ljava/lang/String;)Ljava/lang/StringBuilder;
        61: pop
        62: aload         5
        64: ifnull        107
        67: aload         4
        69: aload         5
        71: invokedynamic #55,  0             // InvokeDynamic #1:makeConcatWithConstants:(Ljava/lang/String;)Ljava/lang/String;
        76: invokevirtual #47                 // Method java/lang/StringBuilder.append:(Ljava/lang/String;)Ljava/lang/StringBuilder;
        79: pop
        80: aload         4
        82: ldc           #56                 // String <td width=80 align=center>
        84: invokevirtual #47                 // Method java/lang/StringBuilder.append:(Ljava/lang/String;)Ljava/lang/StringBuilder;
        87: pop
        88: aload         4
        90: ldc           #58                 // String <button value=\"Limpar\" action=\"bypass -h voiced_email clean\" width=55 height=15 back=sek.cbui94 fore=sek.cbui92>
        92: invokevirtual #47                 // Method java/lang/StringBuilder.append:(Ljava/lang/String;)Ljava/lang/StringBuilder;
        95: pop
        96: aload         4
        98: ldc           #60                 // String </td>
       100: invokevirtual #47                 // Method java/lang/StringBuilder.append:(Ljava/lang/String;)Ljava/lang/StringBuilder;
       103: pop
       104: goto          139
       107: aload         4
       109: ldc           #62                 // String <td width=120 align=left><edit var=\"targetName\" width=150></td>
       111: invokevirtual #47                 // Method java/lang/StringBuilder.append:(Ljava/lang/String;)Ljava/lang/StringBuilder;
       114: pop
       115: aload         4
       117: ldc           #56                 // String <td width=80 align=center>
       119: invokevirtual #47                 // Method java/lang/StringBuilder.append:(Ljava/lang/String;)Ljava/lang/StringBuilder;
       122: pop
       123: aload         4
       125: ldc           #64                 // String <button value=\"Buscar\" action=\"bypass -h voiced_email search $targetName\" width=55 height=15 back=sek.cbui94 fore=sek.cbui92><br>
       127: invokevirtual #47                 // Method java/lang/StringBuilder.append:(Ljava/lang/String;)Ljava/lang/StringBuilder;
       130: pop
       131: aload         4
       133: ldc           #60                 // String </td>
       135: invokevirtual #47                 // Method java/lang/StringBuilder.append:(Ljava/lang/String;)Ljava/lang/StringBuilder;
       138: pop
       139: aload         4
       141: ldc           #66                 // String </tr>
       143: invokevirtual #47                 // Method java/lang/StringBuilder.append:(Ljava/lang/String;)Ljava/lang/StringBuilder;
       146: pop
       147: aload         4
       149: ldc           #68                 // String </table><br>
       151: invokevirtual #47                 // Method java/lang/StringBuilder.append:(Ljava/lang/String;)Ljava/lang/StringBuilder;
       154: pop
       155: aload_3
       156: ldc           #70                 // String %playerinfo%
       158: aload         4
       160: invokevirtual #72                 // Method java/lang/StringBuilder.toString:()Ljava/lang/String;
       163: invokevirtual #75                 // Method ext/mods/gameserver/network/serverpackets/NpcHtmlMessage.replace:(Ljava/lang/String;Ljava/lang/String;)V
       166: aload_3
       167: ldc           #79                 // String %targetName%
       169: aload         5
       171: ifnull        179
       174: aload         5
       176: goto          181
       179: ldc           #81                 // String invalido
       181: invokevirtual #75                 // Method ext/mods/gameserver/network/serverpackets/NpcHtmlMessage.replace:(Ljava/lang/String;Ljava/lang/String;)V
       184: aload_1
       185: aload_3
       186: invokevirtual #83                 // Method ext/mods/gameserver/model/actor/Player.sendPacket:(Lext/mods/gameserver/network/serverpackets/L2GameServerPacket;)V
       189: return
      LineNumberTable:
        line 45: 0
        line 46: 9
        line 48: 23
        line 49: 32
        line 51: 38
        line 53: 46
        line 54: 54
        line 56: 62
        line 58: 67
        line 59: 80
        line 60: 88
        line 61: 96
        line 66: 107
        line 67: 115
        line 68: 123
        line 69: 131
        line 71: 139
        line 72: 147
        line 74: 155
        line 75: 166
        line 76: 184
        line 77: 189
      LocalVariableTable:
        Start  Length  Slot  Name   Signature
            0     190     0  this   Lext/mods/Crypta/PlayerEmailManager;
            0     190     1 player   Lext/mods/gameserver/model/actor/Player;
            0     190     2 filename   Ljava/lang/String;
            9     181     3   htm   Lext/mods/gameserver/network/serverpackets/NpcHtmlMessage;
           32     158     4    sb   Ljava/lang/StringBuilder;
           38     152     5 targetName   Ljava/lang/String;
      StackMapTable: number_of_entries = 4
        frame_type = 254 /* append */
          offset_delta = 107
          locals = [ class ext/mods/gameserver/network/serverpackets/NpcHtmlMessage, class java/lang/StringBuilder, class java/lang/String ]
        frame_type = 31 /* same */
        frame_type = 255 /* full_frame */
          offset_delta = 39
          locals = [ class ext/mods/Crypta/PlayerEmailManager, class ext/mods/gameserver/model/actor/Player, class java/lang/String, class ext/mods/gameserver/network/serverpackets/NpcHtmlMessage, class java/lang/StringBuilder, class java/lang/String ]
          stack = [ class ext/mods/gameserver/network/serverpackets/NpcHtmlMessage, class java/lang/String ]
        frame_type = 255 /* full_frame */
          offset_delta = 1
          locals = [ class ext/mods/Crypta/PlayerEmailManager, class ext/mods/gameserver/model/actor/Player, class java/lang/String, class ext/mods/gameserver/network/serverpackets/NpcHtmlMessage, class java/lang/StringBuilder, class java/lang/String ]
          stack = [ class ext/mods/gameserver/network/serverpackets/NpcHtmlMessage, class java/lang/String, class java/lang/String ]

  public void searchPlayer(ext.mods.gameserver.model.actor.Player, java.lang.String);
    descriptor: (Lext/mods/gameserver/model/actor/Player;Ljava/lang/String;)V
    flags: (0x0001) ACC_PUBLIC
    Code:
      stack=3, locals=10, args_size=3
         0: new           #38                 // class java/lang/StringBuilder
         3: dup
         4: invokespecial #40                 // Method java/lang/StringBuilder."<init>":()V
         7: astore_3
         8: aload_3
         9: ldc           #87                 // String <html><title>Email Search</title><body><center>
        11: invokevirtual #47                 // Method java/lang/StringBuilder.append:(Ljava/lang/String;)Ljava/lang/StringBuilder;
        14: pop
        15: aload_3
        16: ldc           #89                 // String <font color=LEVEL>Resultado da Busca</font>
        18: invokevirtual #47                 // Method java/lang/StringBuilder.append:(Ljava/lang/String;)Ljava/lang/StringBuilder;
        21: pop
        22: aload_3
        23: ldc           #91                 // String <table width=300 border=1 cellspacing=0 cellpadding=3 bgcolor=000000>
        25: invokevirtual #47                 // Method java/lang/StringBuilder.append:(Ljava/lang/String;)Ljava/lang/StringBuilder;
        28: pop
        29: aload_3
        30: ldc           #51                 // String <tr>
        32: invokevirtual #47                 // Method java/lang/StringBuilder.append:(Ljava/lang/String;)Ljava/lang/StringBuilder;
        35: pop
        36: aload_3
        37: ldc           #93                 // String <td width=60 align=center><font color=LEVEL>Status</font></td>
        39: invokevirtual #47                 // Method java/lang/StringBuilder.append:(Ljava/lang/String;)Ljava/lang/StringBuilder;
        42: pop
        43: aload_3
        44: ldc           #95                 // String <td width=110 align=center><font color=LEVEL>Nome</font></td>
        46: invokevirtual #47                 // Method java/lang/StringBuilder.append:(Ljava/lang/String;)Ljava/lang/StringBuilder;
        49: pop
        50: aload_3
        51: ldc           #97                 // String <td width=50 align=center><font color=LEVEL>Ação</font></td>
        53: invokevirtual #47                 // Method java/lang/StringBuilder.append:(Ljava/lang/String;)Ljava/lang/StringBuilder;
        56: pop
        57: aload_3
        58: ldc           #66                 // String </tr>
        60: invokevirtual #47                 // Method java/lang/StringBuilder.append:(Ljava/lang/String;)Ljava/lang/StringBuilder;
        63: pop
        64: aload_3
        65: ldc           #99                 // String </table>
        67: invokevirtual #47                 // Method java/lang/StringBuilder.append:(Ljava/lang/String;)Ljava/lang/StringBuilder;
        70: pop
        71: aload_3
        72: ldc           #101                // String <table width=300 cellspacing=0 cellpadding=3 bgcolor=000000>
        74: invokevirtual #47                 // Method java/lang/StringBuilder.append:(Ljava/lang/String;)Ljava/lang/StringBuilder;
        77: pop
        78: invokestatic  #103                // Method ext/mods/commons/pool/ConnectionPool.getConnection:()Ljava/sql/Connection;
        81: astore        4
        83: aload         4
        85: ldc           #109                // String SELECT char_name, online FROM characters WHERE LOWER(char_name) LIKE ? AND char_name != ? AND accesslevel = 0 ORDER BY online DESC, char_name LIMIT 15
        87: invokeinterface #111,  2          // InterfaceMethod java/sql/Connection.prepareStatement:(Ljava/lang/String;)Ljava/sql/PreparedStatement;
        92: astore        5
        94: aload         5
        96: iconst_1
        97: aload_2
        98: invokevirtual #117                // Method java/lang/String.toLowerCase:()Ljava/lang/String;
       101: invokedynamic #122,  0            // InvokeDynamic #2:makeConcatWithConstants:(Ljava/lang/String;)Ljava/lang/String;
       106: invokeinterface #123,  3          // InterfaceMethod java/sql/PreparedStatement.setString:(ILjava/lang/String;)V
       111: aload         5
       113: iconst_2
       114: aload_1
       115: invokevirtual #129                // Method ext/mods/gameserver/model/actor/Player.getName:()Ljava/lang/String;
       118: invokeinterface #123,  3          // InterfaceMethod java/sql/PreparedStatement.setString:(ILjava/lang/String;)V
       123: aload         5
       125: invokeinterface #132,  1          // InterfaceMethod java/sql/PreparedStatement.executeQuery:()Ljava/sql/ResultSet;
       130: astore        6
       132: aload         6
       134: invokeinterface #136,  1          // InterfaceMethod java/sql/ResultSet.next:()Z
       139: ifeq          308
       142: aload         6
       144: ldc           #142                // String char_name
       146: invokeinterface #144,  2          // InterfaceMethod java/sql/ResultSet.getString:(Ljava/lang/String;)Ljava/lang/String;
       151: astore        7
       153: aload         7
       155: invokevirtual #147                // Method java/lang/String.length:()I
       158: bipush        12
       160: if_icmple     179
       163: aload         7
       165: iconst_0
       166: bipush        10
       168: invokevirtual #151                // Method java/lang/String.substring:(II)Ljava/lang/String;
       171: invokedynamic #155,  0            // InvokeDynamic #3:makeConcatWithConstants:(Ljava/lang/String;)Ljava/lang/String;
       176: goto          181
       179: aload         7
       181: astore        8
       183: aload         6
       185: ldc           #156                // String online
       187: invokeinterface #158,  2          // InterfaceMethod java/sql/ResultSet.getInt:(Ljava/lang/String;)I
       192: iconst_1
       193: if_icmpne     200
       196: iconst_1
       197: goto          201
       200: iconst_0
       201: istore        9
       203: aload_3
       204: ldc           #51                 // String <tr>
       206: invokevirtual #47                 // Method java/lang/StringBuilder.append:(Ljava/lang/String;)Ljava/lang/StringBuilder;
       209: pop
       210: aload_3
       211: ldc           #162                // String <td width=60 align=center><font color=
       213: invokevirtual #47                 // Method java/lang/StringBuilder.append:(Ljava/lang/String;)Ljava/lang/StringBuilder;
       216: iload         9
       218: ifeq          226
       221: ldc           #164                // String 00FF00
       223: goto          228
       226: ldc           #166                // String FF0000
       228: invokevirtual #47                 // Method java/lang/StringBuilder.append:(Ljava/lang/String;)Ljava/lang/StringBuilder;
       231: ldc           #168                // String >
       233: invokevirtual #47                 // Method java/lang/StringBuilder.append:(Ljava/lang/String;)Ljava/lang/StringBuilder;
       236: iload         9
       238: ifeq          246
       241: ldc           #170                // String Online
       243: goto          248
       246: ldc           #172                // String Offline
       248: invokevirtual #47                 // Method java/lang/StringBuilder.append:(Ljava/lang/String;)Ljava/lang/StringBuilder;
       251: ldc           #174                // String </font></td>
       253: invokevirtual #47                 // Method java/lang/StringBuilder.append:(Ljava/lang/String;)Ljava/lang/StringBuilder;
       256: pop
       257: aload_3
       258: ldc           #176                // String <td width=110 align=center>
       260: invokevirtual #47                 // Method java/lang/StringBuilder.append:(Ljava/lang/String;)Ljava/lang/StringBuilder;
       263: aload         8
       265: invokevirtual #47                 // Method java/lang/StringBuilder.append:(Ljava/lang/String;)Ljava/lang/StringBuilder;
       268: ldc           #60                 // String </td>
       270: invokevirtual #47                 // Method java/lang/StringBuilder.append:(Ljava/lang/String;)Ljava/lang/StringBuilder;
       273: pop
       274: aload_3
       275: ldc           #178                // String <td width=50 align=center>
       277: invokevirtual #47                 // Method java/lang/StringBuilder.append:(Ljava/lang/String;)Ljava/lang/StringBuilder;
       280: pop
       281: aload_3
       282: ldc           #180                // String <button value=\"OK\" action=\"bypass -h voiced_email target
       284: invokevirtual #47                 // Method java/lang/StringBuilder.append:(Ljava/lang/String;)Ljava/lang/StringBuilder;
       287: aload         7
       289: invokevirtual #47                 // Method java/lang/StringBuilder.append:(Ljava/lang/String;)Ljava/lang/StringBuilder;
       292: ldc           #182                // String \" width=40 height=21 back=sek.cbui94 fore=sek.cbui92>
       294: invokevirtual #47                 // Method java/lang/StringBuilder.append:(Ljava/lang/String;)Ljava/lang/StringBuilder;
       297: pop
       298: aload_3
       299: ldc           #184                // String </td></tr>
       301: invokevirtual #47                 // Method java/lang/StringBuilder.append:(Ljava/lang/String;)Ljava/lang/StringBuilder;
       304: pop
       305: goto          132
       308: aload         6
       310: ifnull        352
       313: aload         6
       315: invokeinterface #186,  1          // InterfaceMethod java/sql/ResultSet.close:()V
       320: goto          352
       323: astore        7
       325: aload         6
       327: ifnull        349
       330: aload         6
       332: invokeinterface #186,  1          // InterfaceMethod java/sql/ResultSet.close:()V
       337: goto          349
       340: astore        8
       342: aload         7
       344: aload         8
       346: invokevirtual #191                // Method java/lang/Throwable.addSuppressed:(Ljava/lang/Throwable;)V
       349: aload         7
       351: athrow
       352: aload         5
       354: ifnull        396
       357: aload         5
       359: invokeinterface #195,  1          // InterfaceMethod java/sql/PreparedStatement.close:()V
       364: goto          396
       367: astore        6
       369: aload         5
       371: ifnull        393
       374: aload         5
       376: invokeinterface #195,  1          // InterfaceMethod java/sql/PreparedStatement.close:()V
       381: goto          393
       384: astore        7
       386: aload         6
       388: aload         7
       390: invokevirtual #191                // Method java/lang/Throwable.addSuppressed:(Ljava/lang/Throwable;)V
       393: aload         6
       395: athrow
       396: aload         4
       398: ifnull        440
       401: aload         4
       403: invokeinterface #196,  1          // InterfaceMethod java/sql/Connection.close:()V
       408: goto          440
       411: astore        5
       413: aload         4
       415: ifnull        437
       418: aload         4
       420: invokeinterface #196,  1          // InterfaceMethod java/sql/Connection.close:()V
       425: goto          437
       428: astore        6
       430: aload         5
       432: aload         6
       434: invokevirtual #191                // Method java/lang/Throwable.addSuppressed:(Ljava/lang/Throwable;)V
       437: aload         5
       439: athrow
       440: goto          461
       443: astore        4
       445: getstatic     #199                // Field LOGGER:Ljava/util/logging/Logger;
       448: aload         4
       450: invokevirtual #203                // Method java/lang/Exception.getMessage:()Ljava/lang/String;
       453: invokedynamic #206,  0            // InvokeDynamic #4:makeConcatWithConstants:(Ljava/lang/String;)Ljava/lang/String;
       458: invokevirtual #207                // Method java/util/logging/Logger.warning:(Ljava/lang/String;)V
       461: aload_3
       462: ldc           #68                 // String </table><br>
       464: invokevirtual #47                 // Method java/lang/StringBuilder.append:(Ljava/lang/String;)Ljava/lang/StringBuilder;
       467: pop
       468: aload_3
       469: ldc           #213                // String <button value=\"Voltar\" action=\"bypass -h voiced_email htm email_main.htm\" width=80 height=21 back=\"L2UI_CH3.Btn1_normalOn\" fore=\"L2UI_CH3.Btn1_normal\">
       471: invokevirtual #47                 // Method java/lang/StringBuilder.append:(Ljava/lang/String;)Ljava/lang/StringBuilder;
       474: pop
       475: aload_3
       476: ldc           #215                // String </center></body></html>
       478: invokevirtual #47                 // Method java/lang/StringBuilder.append:(Ljava/lang/String;)Ljava/lang/StringBuilder;
       481: pop
       482: new           #19                 // class ext/mods/gameserver/network/serverpackets/NpcHtmlMessage
       485: dup
       486: iconst_0
       487: invokespecial #21                 // Method ext/mods/gameserver/network/serverpackets/NpcHtmlMessage."<init>":(I)V
       490: astore        4
       492: aload         4
       494: aload_3
       495: invokevirtual #72                 // Method java/lang/StringBuilder.toString:()Ljava/lang/String;
       498: invokevirtual #217                // Method ext/mods/gameserver/network/serverpackets/NpcHtmlMessage.setHtml:(Ljava/lang/String;)V
       501: aload_1
       502: aload         4
       504: invokevirtual #83                 // Method ext/mods/gameserver/model/actor/Player.sendPacket:(Lext/mods/gameserver/network/serverpackets/L2GameServerPacket;)V
       507: return
      Exception table:
         from    to  target type
           132   308   323   Class java/lang/Throwable
           330   337   340   Class java/lang/Throwable
            94   352   367   Class java/lang/Throwable
           374   381   384   Class java/lang/Throwable
            83   396   411   Class java/lang/Throwable
           418   425   428   Class java/lang/Throwable
            78   440   443   Class java/lang/Exception
      LineNumberTable:
        line 81: 0
        line 83: 8
        line 84: 15
        line 86: 22
        line 87: 29
        line 88: 36
        line 89: 43
        line 90: 50
        line 91: 57
        line 92: 64
        line 95: 71
        line 97: 78
        line 98: 83
        line 100: 94
        line 101: 111
        line 103: 123
        line 105: 132
        line 107: 142
        line 109: 153
        line 110: 183
        line 112: 203
        line 113: 210
        line 114: 257
        line 115: 274
        line 116: 281
        line 117: 298
        line 118: 305
        line 119: 308
        line 103: 323
        line 120: 352
        line 97: 367
        line 120: 396
        line 97: 411
        line 124: 440
        line 121: 443
        line 123: 445
        line 126: 461
        line 127: 468
        line 128: 475
        line 130: 482
        line 131: 492
        line 132: 501
        line 133: 507
      LocalVariableTable:
        Start  Length  Slot  Name   Signature
          153     152     7  name   Ljava/lang/String;
          183     122     8 displayName   Ljava/lang/String;
          203     102     9 isOnline   Z
          132     220     6    rs   Ljava/sql/ResultSet;
           94     302     5    ps   Ljava/sql/PreparedStatement;
           83     357     4   con   Ljava/sql/Connection;
          445      16     4     e   Ljava/lang/Exception;
            0     508     0  this   Lext/mods/Crypta/PlayerEmailManager;
            0     508     1 player   Lext/mods/gameserver/model/actor/Player;
            0     508     2 targetName   Ljava/lang/String;
            8     500     3    sb   Ljava/lang/StringBuilder;
          492      16     4  html   Lext/mods/gameserver/network/serverpackets/NpcHtmlMessage;
      StackMapTable: number_of_entries = 24
        frame_type = 255 /* full_frame */
          offset_delta = 132
          locals = [ class ext/mods/Crypta/PlayerEmailManager, class ext/mods/gameserver/model/actor/Player, class java/lang/String, class java/lang/StringBuilder, class java/sql/Connection, class java/sql/PreparedStatement, class java/sql/ResultSet ]
          stack = []
        frame_type = 252 /* append */
          offset_delta = 46
          locals = [ class java/lang/String ]
        frame_type = 65 /* same_locals_1_stack_item */
          stack = [ class java/lang/String ]
        frame_type = 252 /* append */
          offset_delta = 18
          locals = [ class java/lang/String ]
        frame_type = 64 /* same_locals_1_stack_item */
          stack = [ int ]
        frame_type = 255 /* full_frame */
          offset_delta = 24
          locals = [ class ext/mods/Crypta/PlayerEmailManager, class ext/mods/gameserver/model/actor/Player, class java/lang/String, class java/lang/StringBuilder, class java/sql/Connection, class java/sql/PreparedStatement, class java/sql/ResultSet, class java/lang/String, class java/lang/String, int ]
          stack = [ class java/lang/StringBuilder ]
        frame_type = 255 /* full_frame */
          offset_delta = 1
          locals = [ class ext/mods/Crypta/PlayerEmailManager, class ext/mods/gameserver/model/actor/Player, class java/lang/String, class java/lang/StringBuilder, class java/sql/Connection, class java/sql/PreparedStatement, class java/sql/ResultSet, class java/lang/String, class java/lang/String, int ]
          stack = [ class java/lang/StringBuilder, class java/lang/String ]
        frame_type = 81 /* same_locals_1_stack_item */
          stack = [ class java/lang/StringBuilder ]
        frame_type = 255 /* full_frame */
          offset_delta = 1
          locals = [ class ext/mods/Crypta/PlayerEmailManager, class ext/mods/gameserver/model/actor/Player, class java/lang/String, class java/lang/StringBuilder, class java/sql/Connection, class java/sql/PreparedStatement, class java/sql/ResultSet, class java/lang/String, class java/lang/String, int ]
          stack = [ class java/lang/StringBuilder, class java/lang/String ]
        frame_type = 248 /* chop */
          offset_delta = 59
        frame_type = 78 /* same_locals_1_stack_item */
          stack = [ class java/lang/Throwable ]
        frame_type = 255 /* full_frame */
          offset_delta = 16
          locals = [ class ext/mods/Crypta/PlayerEmailManager, class ext/mods/gameserver/model/actor/Player, class java/lang/String, class java/lang/StringBuilder, class java/sql/Connection, class java/sql/PreparedStatement, class java/sql/ResultSet, class java/lang/Throwable ]
          stack = [ class java/lang/Throwable ]
        frame_type = 8 /* same */
        frame_type = 249 /* chop */
          offset_delta = 2
        frame_type = 78 /* same_locals_1_stack_item */
          stack = [ class java/lang/Throwable ]
        frame_type = 255 /* full_frame */
          offset_delta = 16
          locals = [ class ext/mods/Crypta/PlayerEmailManager, class ext/mods/gameserver/model/actor/Player, class java/lang/String, class java/lang/StringBuilder, class java/sql/Connection, class java/sql/PreparedStatement, class java/lang/Throwable ]
          stack = [ class java/lang/Throwable ]
        frame_type = 8 /* same */
        frame_type = 249 /* chop */
          offset_delta = 2
        frame_type = 78 /* same_locals_1_stack_item */
          stack = [ class java/lang/Throwable ]
        frame_type = 255 /* full_frame */
          offset_delta = 16
          locals = [ class ext/mods/Crypta/PlayerEmailManager, class ext/mods/gameserver/model/actor/Player, class java/lang/String, class java/lang/StringBuilder, class java/sql/Connection, class java/lang/Throwable ]
          stack = [ class java/lang/Throwable ]
        frame_type = 8 /* same */
        frame_type = 249 /* chop */
          offset_delta = 2
        frame_type = 66 /* same_locals_1_stack_item */
          stack = [ class java/lang/Exception ]
        frame_type = 17 /* same */

  public static ext.mods.Crypta.PlayerEmailManager getInstance();
    descriptor: ()Lext/mods/Crypta/PlayerEmailManager;
    flags: (0x0009) ACC_PUBLIC, ACC_STATIC
    Code:
      stack=1, locals=0, args_size=0
         0: getstatic     #220                // Field ext/mods/Crypta/PlayerEmailManager$SingletonHolder.instance:Lext/mods/Crypta/PlayerEmailManager;
         3: areturn
      LineNumberTable:
        line 137: 0

  public void showInbox(ext.mods.gameserver.model.actor.Player);
    descriptor: (Lext/mods/gameserver/model/actor/Player;)V
    flags: (0x0001) ACC_PUBLIC
    Code:
      stack=4, locals=24, args_size=2
         0: new           #38                 // class java/lang/StringBuilder
         3: dup
         4: invokespecial #40                 // Method java/lang/StringBuilder."<init>":()V
         7: astore_2
         8: aload_2
         9: ldc           #226                // String <html><body>
        11: invokevirtual #47                 // Method java/lang/StringBuilder.append:(Ljava/lang/String;)Ljava/lang/StringBuilder;
        14: pop
        15: aload_2
        16: ldc           #228                // String <table width=300><tr><td align=center><font color=\"LEVEL\">Sua Inbox de Emails</font></td></tr></table><br>
        18: invokevirtual #47                 // Method java/lang/StringBuilder.append:(Ljava/lang/String;)Ljava/lang/StringBuilder;
        21: pop
        22: invokestatic  #103                // Method ext/mods/commons/pool/ConnectionPool.getConnection:()Ljava/sql/Connection;
        25: astore_3
        26: aload_3
        27: ldc           #230                // String SELECT DISTINCT email_id, sender_id, expiration_time, is_paid, payment_item_id, payment_item_count FROM player_emails WHERE target_id=? AND status=\'PENDING\' AND expiration_time > ? ORDER BY created_time DESC
        29: invokeinterface #111,  2          // InterfaceMethod java/sql/Connection.prepareStatement:(Ljava/lang/String;)Ljava/sql/PreparedStatement;
        34: astore        4
        36: aload         4
        38: iconst_1
        39: aload_1
        40: invokevirtual #232                // Method ext/mods/gameserver/model/actor/Player.getObjectId:()I
        43: invokeinterface #235,  3          // InterfaceMethod java/sql/PreparedStatement.setInt:(II)V
        48: aload         4
        50: iconst_2
        51: invokestatic  #239                // Method java/lang/System.currentTimeMillis:()J
        54: invokeinterface #245,  4          // InterfaceMethod java/sql/PreparedStatement.setLong:(IJ)V
        59: aload         4
        61: invokeinterface #132,  1          // InterfaceMethod java/sql/PreparedStatement.executeQuery:()Ljava/sql/ResultSet;
        66: astore        5
        68: aload         5
        70: invokeinterface #136,  1          // InterfaceMethod java/sql/ResultSet.next:()Z
        75: ifne          88
        78: aload_2
        79: ldc           #249                // String Nenhum email pendente.<br>
        81: invokevirtual #47                 // Method java/lang/StringBuilder.append:(Ljava/lang/String;)Ljava/lang/StringBuilder;
        84: pop
        85: goto          593
        88: aload         5
        90: ldc           #251                // String email_id
        92: invokeinterface #158,  2          // InterfaceMethod java/sql/ResultSet.getInt:(Ljava/lang/String;)I
        97: istore        6
        99: aload         5
       101: ldc           #253                // String sender_id
       103: invokeinterface #158,  2          // InterfaceMethod java/sql/ResultSet.getInt:(Ljava/lang/String;)I
       108: istore        7
       110: aload         5
       112: ldc           #255                // String expiration_time
       114: invokeinterface #257,  2          // InterfaceMethod java/sql/ResultSet.getLong:(Ljava/lang/String;)J
       119: lstore        8
       121: aload         5
       123: ldc_w         #261                // String is_paid
       126: invokeinterface #263,  2          // InterfaceMethod java/sql/ResultSet.getBoolean:(Ljava/lang/String;)Z
       131: istore        10
       133: aload         5
       135: ldc_w         #267                // String payment_item_id
       138: invokeinterface #158,  2          // InterfaceMethod java/sql/ResultSet.getInt:(Ljava/lang/String;)I
       143: istore        11
       145: aload         5
       147: ldc_w         #269                // String payment_item_count
       150: invokeinterface #158,  2          // InterfaceMethod java/sql/ResultSet.getInt:(Ljava/lang/String;)I
       155: istore        12
       157: invokestatic  #271                // Method ext/mods/gameserver/data/sql/PlayerInfoTable.getInstance:()Lext/mods/gameserver/data/sql/PlayerInfoTable;
       160: iload         7
       162: invokevirtual #277                // Method ext/mods/gameserver/data/sql/PlayerInfoTable.getPlayerName:(I)Ljava/lang/String;
       165: astore        13
       167: lload         8
       169: invokestatic  #239                // Method java/lang/System.currentTimeMillis:()J
       172: lsub
       173: ldc2_w        #280                // long 60000l
       176: ldiv
       177: lstore        14
       179: aload_2
       180: ldc_w         #282                // String <table width=300 border=0>
       183: invokevirtual #47                 // Method java/lang/StringBuilder.append:(Ljava/lang/String;)Ljava/lang/StringBuilder;
       186: pop
       187: aload_2
       188: ldc_w         #284                // String <tr><td>Email ID:
       191: invokevirtual #47                 // Method java/lang/StringBuilder.append:(Ljava/lang/String;)Ljava/lang/StringBuilder;
       194: iload         6
       196: invokevirtual #286                // Method java/lang/StringBuilder.append:(I)Ljava/lang/StringBuilder;
       199: ldc_w         #289                // String  de
       202: invokevirtual #47                 // Method java/lang/StringBuilder.append:(Ljava/lang/String;)Ljava/lang/StringBuilder;
       205: aload         13
       207: invokevirtual #47                 // Method java/lang/StringBuilder.append:(Ljava/lang/String;)Ljava/lang/StringBuilder;
       210: ldc           #184                // String </td></tr>
       212: invokevirtual #47                 // Method java/lang/StringBuilder.append:(Ljava/lang/String;)Ljava/lang/StringBuilder;
       215: pop
       216: aload_2
       217: ldc_w         #291                // String <tr><td>Expira em:
       220: invokevirtual #47                 // Method java/lang/StringBuilder.append:(Ljava/lang/String;)Ljava/lang/StringBuilder;
       223: lload         14
       225: invokevirtual #293                // Method java/lang/StringBuilder.append:(J)Ljava/lang/StringBuilder;
       228: ldc_w         #296                // String  minutos</td></tr>
       231: invokevirtual #47                 // Method java/lang/StringBuilder.append:(Ljava/lang/String;)Ljava/lang/StringBuilder;
       234: pop
       235: aload_3
       236: ldc_w         #298                // String SELECT item_id, count, enchant_level, is_augmented FROM player_emails WHERE email_id=?
       239: invokeinterface #111,  2          // InterfaceMethod java/sql/Connection.prepareStatement:(Ljava/lang/String;)Ljava/sql/PreparedStatement;
       244: astore        16
       246: aload         16
       248: iconst_1
       249: iload         6
       251: invokeinterface #235,  3          // InterfaceMethod java/sql/PreparedStatement.setInt:(II)V
       256: aload         16
       258: invokeinterface #132,  1          // InterfaceMethod java/sql/PreparedStatement.executeQuery:()Ljava/sql/ResultSet;
       263: astore        17
       265: aload_2
       266: ldc_w         #300                // String <tr><td>Itens:</td></tr>
       269: invokevirtual #47                 // Method java/lang/StringBuilder.append:(Ljava/lang/String;)Ljava/lang/StringBuilder;
       272: pop
       273: aload         17
       275: invokeinterface #136,  1          // InterfaceMethod java/sql/ResultSet.next:()Z
       280: ifeq          417
       283: aload         17
       285: ldc_w         #302                // String item_id
       288: invokeinterface #158,  2          // InterfaceMethod java/sql/ResultSet.getInt:(Ljava/lang/String;)I
       293: istore        18
       295: aload         17
       297: ldc_w         #304                // String count
       300: invokeinterface #158,  2          // InterfaceMethod java/sql/ResultSet.getInt:(Ljava/lang/String;)I
       305: istore        19
       307: aload         17
       309: ldc_w         #306                // String enchant_level
       312: invokeinterface #158,  2          // InterfaceMethod java/sql/ResultSet.getInt:(Ljava/lang/String;)I
       317: istore        20
       319: aload         17
       321: ldc_w         #308                // String is_augmented
       324: invokeinterface #263,  2          // InterfaceMethod java/sql/ResultSet.getBoolean:(Ljava/lang/String;)Z
       329: istore        21
       331: invokestatic  #310                // Method ext/mods/gameserver/data/xml/ItemData.getInstance:()Lext/mods/gameserver/data/xml/ItemData;
       334: iload         18
       336: invokevirtual #315                // Method ext/mods/gameserver/data/xml/ItemData.getTemplate:(I)Lext/mods/gameserver/model/item/kind/Item;
       339: invokevirtual #319                // Method ext/mods/gameserver/model/item/kind/Item.getName:()Ljava/lang/String;
       342: astore        22
       344: iload         20
       346: ifle          359
       349: iload         20
       351: invokedynamic #322,  0            // InvokeDynamic #5:makeConcatWithConstants:(I)Ljava/lang/String;
       356: goto          362
       359: ldc_w         #324                // String
       362: aload         22
       364: iload         21
       366: ifeq          375
       369: ldc_w         #326                // String  (Aug)
       372: goto          378
       375: ldc_w         #324                // String
       378: invokedynamic #328,  0            // InvokeDynamic #6:makeConcatWithConstants:(Ljava/lang/String;Ljava/lang/String;Ljava/lang/String;)Ljava/lang/String;
       383: astore        23
       385: aload_2
       386: ldc_w         #331                // String <tr><td>-
       389: invokevirtual #47                 // Method java/lang/StringBuilder.append:(Ljava/lang/String;)Ljava/lang/StringBuilder;
       392: aload         23
       394: invokevirtual #47                 // Method java/lang/StringBuilder.append:(Ljava/lang/String;)Ljava/lang/StringBuilder;
       397: ldc_w         #333                // String  x
       400: invokevirtual #47                 // Method java/lang/StringBuilder.append:(Ljava/lang/String;)Ljava/lang/StringBuilder;
       403: iload         19
       405: invokevirtual #286                // Method java/lang/StringBuilder.append:(I)Ljava/lang/StringBuilder;
       408: ldc           #184                // String </td></tr>
       410: invokevirtual #47                 // Method java/lang/StringBuilder.append:(Ljava/lang/String;)Ljava/lang/StringBuilder;
       413: pop
       414: goto          273
       417: aload         17
       419: ifnull        461
       422: aload         17
       424: invokeinterface #186,  1          // InterfaceMethod java/sql/ResultSet.close:()V
       429: goto          461
       432: astore        18
       434: aload         17
       436: ifnull        458
       439: aload         17
       441: invokeinterface #186,  1          // InterfaceMethod java/sql/ResultSet.close:()V
       446: goto          458
       449: astore        19
       451: aload         18
       453: aload         19
       455: invokevirtual #191                // Method java/lang/Throwable.addSuppressed:(Ljava/lang/Throwable;)V
       458: aload         18
       460: athrow
       461: aload         16
       463: ifnull        505
       466: aload         16
       468: invokeinterface #195,  1          // InterfaceMethod java/sql/PreparedStatement.close:()V
       473: goto          505
       476: astore        17
       478: aload         16
       480: ifnull        502
       483: aload         16
       485: invokeinterface #195,  1          // InterfaceMethod java/sql/PreparedStatement.close:()V
       490: goto          502
       493: astore        18
       495: aload         17
       497: aload         18
       499: invokevirtual #191                // Method java/lang/Throwable.addSuppressed:(Ljava/lang/Throwable;)V
       502: aload         17
       504: athrow
       505: iload         10
       507: ifeq          557
       510: iload         11
       512: ifle          557
       515: invokestatic  #310                // Method ext/mods/gameserver/data/xml/ItemData.getInstance:()Lext/mods/gameserver/data/xml/ItemData;
       518: iload         11
       520: invokevirtual #315                // Method ext/mods/gameserver/data/xml/ItemData.getTemplate:(I)Lext/mods/gameserver/model/item/kind/Item;
       523: invokevirtual #319                // Method ext/mods/gameserver/model/item/kind/Item.getName:()Ljava/lang/String;
       526: astore        16
       528: aload_2
       529: ldc_w         #335                // String <tr><td>Pagamento requerido:
       532: invokevirtual #47                 // Method java/lang/StringBuilder.append:(Ljava/lang/String;)Ljava/lang/StringBuilder;
       535: aload         16
       537: invokevirtual #47                 // Method java/lang/StringBuilder.append:(Ljava/lang/String;)Ljava/lang/StringBuilder;
       540: ldc_w         #333                // String  x
       543: invokevirtual #47                 // Method java/lang/StringBuilder.append:(Ljava/lang/String;)Ljava/lang/StringBuilder;
       546: iload         12
       548: invokevirtual #286                // Method java/lang/StringBuilder.append:(I)Ljava/lang/StringBuilder;
       551: ldc           #184                // String </td></tr>
       553: invokevirtual #47                 // Method java/lang/StringBuilder.append:(Ljava/lang/String;)Ljava/lang/StringBuilder;
       556: pop
       557: aload_2
       558: ldc_w         #337                // String <tr><td><button value=\"Reclamar\" action=\"bypass -h voiced_email claim
       561: invokevirtual #47                 // Method java/lang/StringBuilder.append:(Ljava/lang/String;)Ljava/lang/StringBuilder;
       564: iload         6
       566: invokevirtual #286                // Method java/lang/StringBuilder.append:(I)Ljava/lang/StringBuilder;
       569: ldc_w         #339                // String \" width=75 height=21 back=\"L2UI_ch3.Btn1_normalOn\" fore=\"L2UI_ch3.Btn1_normal\"></td></tr>
       572: invokevirtual #47                 // Method java/lang/StringBuilder.append:(Ljava/lang/String;)Ljava/lang/StringBuilder;
       575: pop
       576: aload_2
       577: ldc           #68                 // String </table><br>
       579: invokevirtual #47                 // Method java/lang/StringBuilder.append:(Ljava/lang/String;)Ljava/lang/StringBuilder;
       582: pop
       583: aload         5
       585: invokeinterface #136,  1          // InterfaceMethod java/sql/ResultSet.next:()Z
       590: ifne          88
       593: aload         5
       595: ifnull        637
       598: aload         5
       600: invokeinterface #186,  1          // InterfaceMethod java/sql/ResultSet.close:()V
       605: goto          637
       608: astore        6
       610: aload         5
       612: ifnull        634
       615: aload         5
       617: invokeinterface #186,  1          // InterfaceMethod java/sql/ResultSet.close:()V
       622: goto          634
       625: astore        7
       627: aload         6
       629: aload         7
       631: invokevirtual #191                // Method java/lang/Throwable.addSuppressed:(Ljava/lang/Throwable;)V
       634: aload         6
       636: athrow
       637: aload         4
       639: ifnull        681
       642: aload         4
       644: invokeinterface #195,  1          // InterfaceMethod java/sql/PreparedStatement.close:()V
       649: goto          681
       652: astore        5
       654: aload         4
       656: ifnull        678
       659: aload         4
       661: invokeinterface #195,  1          // InterfaceMethod java/sql/PreparedStatement.close:()V
       666: goto          678
       669: astore        6
       671: aload         5
       673: aload         6
       675: invokevirtual #191                // Method java/lang/Throwable.addSuppressed:(Ljava/lang/Throwable;)V
       678: aload         5
       680: athrow
       681: aload_3
       682: ifnull        721
       685: aload_3
       686: invokeinterface #196,  1          // InterfaceMethod java/sql/Connection.close:()V
       691: goto          721
       694: astore        4
       696: aload_3
       697: ifnull        718
       700: aload_3
       701: invokeinterface #196,  1          // InterfaceMethod java/sql/Connection.close:()V
       706: goto          718
       709: astore        5
       711: aload         4
       713: aload         5
       715: invokevirtual #191                // Method java/lang/Throwable.addSuppressed:(Ljava/lang/Throwable;)V
       718: aload         4
       720: athrow
       721: goto          744
       724: astore_3
       725: getstatic     #199                // Field LOGGER:Ljava/util/logging/Logger;
       728: aload_3
       729: invokevirtual #203                // Method java/lang/Exception.getMessage:()Ljava/lang/String;
       732: invokedynamic #341,  0            // InvokeDynamic #7:makeConcatWithConstants:(Ljava/lang/String;)Ljava/lang/String;
       737: invokevirtual #342                // Method java/util/logging/Logger.severe:(Ljava/lang/String;)V
       740: aload_3
       741: invokevirtual #345                // Method java/lang/Exception.printStackTrace:()V
       744: aload_2
       745: ldc_w         #348                // String <table width=300><tr><td align=center>
       748: invokevirtual #47                 // Method java/lang/StringBuilder.append:(Ljava/lang/String;)Ljava/lang/StringBuilder;
       751: pop
       752: aload_2
       753: ldc_w         #350                // String <button value=\"Voltar\" action=\"bypass -h voiced_email htm email_main.htm\" width=75 height=21 back=\"L2UI_ch3.Btn1_normalOn\" fore=\"L2UI_ch3.Btn1_normal\">
       756: invokevirtual #47                 // Method java/lang/StringBuilder.append:(Ljava/lang/String;)Ljava/lang/StringBuilder;
       759: pop
       760: aload_2
       761: ldc_w         #352                // String </td></tr></table>
       764: invokevirtual #47                 // Method java/lang/StringBuilder.append:(Ljava/lang/String;)Ljava/lang/StringBuilder;
       767: pop
       768: aload_2
       769: ldc_w         #354                // String </body></html>
       772: invokevirtual #47                 // Method java/lang/StringBuilder.append:(Ljava/lang/String;)Ljava/lang/StringBuilder;
       775: pop
       776: new           #19                 // class ext/mods/gameserver/network/serverpackets/NpcHtmlMessage
       779: dup
       780: iconst_0
       781: invokespecial #21                 // Method ext/mods/gameserver/network/serverpackets/NpcHtmlMessage."<init>":(I)V
       784: astore_3
       785: aload_3
       786: aload_2
       787: invokevirtual #72                 // Method java/lang/StringBuilder.toString:()Ljava/lang/String;
       790: invokevirtual #217                // Method ext/mods/gameserver/network/serverpackets/NpcHtmlMessage.setHtml:(Ljava/lang/String;)V
       793: aload_1
       794: aload_3
       795: invokevirtual #83                 // Method ext/mods/gameserver/model/actor/Player.sendPacket:(Lext/mods/gameserver/network/serverpackets/L2GameServerPacket;)V
       798: return
      Exception table:
         from    to  target type
           265   417   432   Class java/lang/Throwable
           439   446   449   Class java/lang/Throwable
           246   461   476   Class java/lang/Throwable
           483   490   493   Class java/lang/Throwable
            68   593   608   Class java/lang/Throwable
           615   622   625   Class java/lang/Throwable
            36   637   652   Class java/lang/Throwable
           659   666   669   Class java/lang/Throwable
            26   681   694   Class java/lang/Throwable
           700   706   709   Class java/lang/Throwable
            22   721   724   Class java/lang/Exception
      LineNumberTable:
        line 146: 0
        line 147: 8
        line 148: 15
        line 150: 22
        line 151: 26
        line 154: 36
        line 155: 48
        line 156: 59
        line 157: 68
        line 158: 78
        line 161: 88
        line 162: 99
        line 163: 110
        line 164: 121
        line 165: 133
        line 166: 145
        line 168: 157
        line 169: 167
        line 171: 179
        line 172: 187
        line 173: 216
        line 175: 235
        line 177: 246
        line 178: 256
        line 179: 265
        line 180: 273
        line 181: 283
        line 182: 295
        line 183: 307
        line 184: 319
        line 185: 331
        line 186: 344
        line 187: 385
        line 188: 414
        line 189: 417
        line 178: 432
        line 190: 461
        line 175: 476
        line 192: 505
        line 193: 515
        line 194: 528
        line 197: 557
        line 198: 576
        line 199: 583
        line 201: 593
        line 156: 608
        line 202: 637
        line 150: 652
        line 202: 681
        line 150: 694
        line 205: 721
        line 202: 724
        line 203: 725
        line 204: 740
        line 207: 744
        line 208: 752
        line 209: 760
        line 210: 768
        line 212: 776
        line 213: 785
        line 214: 793
        line 215: 798
      LocalVariableTable:
        Start  Length  Slot  Name   Signature
          295     119    18 itemId   I
          307     107    19 count   I
          319      95    20 enchant   I
          331      83    21 isAug   Z
          344      70    22 itemName   Ljava/lang/String;
          385      29    23 displayName   Ljava/lang/String;
          265     196    17 rsItems   Ljava/sql/ResultSet;
          246     259    16 psItems   Ljava/sql/PreparedStatement;
          528      29    16 payName   Ljava/lang/String;
           99     484     6 emailId   I
          110     473     7 senderId   I
          121     462     8   exp   J
          133     450    10 isPaid   Z
          145     438    11 payItem   I
          157     426    12 payCount   I
          167     416    13 senderName   Ljava/lang/String;
          179     404    14 remaining   J
           68     569     5    rs   Ljava/sql/ResultSet;
           36     645     4    ps   Ljava/sql/PreparedStatement;
           26     695     3   con   Ljava/sql/Connection;
          725      19     3     e   Ljava/lang/Exception;
            0     799     0  this   Lext/mods/Crypta/PlayerEmailManager;
            0     799     1 player   Lext/mods/gameserver/model/actor/Player;
            8     791     2    sb   Ljava/lang/StringBuilder;
          785      14     3  html   Lext/mods/gameserver/network/serverpackets/NpcHtmlMessage;
      StackMapTable: number_of_entries = 31
        frame_type = 255 /* full_frame */
          offset_delta = 88
          locals = [ class ext/mods/Crypta/PlayerEmailManager, class ext/mods/gameserver/model/actor/Player, class java/lang/StringBuilder, class java/sql/Connection, class java/sql/PreparedStatement, class java/sql/ResultSet ]
          stack = []
        frame_type = 255 /* full_frame */
          offset_delta = 184
          locals = [ class ext/mods/Crypta/PlayerEmailManager, class ext/mods/gameserver/model/actor/Player, class java/lang/StringBuilder, class java/sql/Connection, class java/sql/PreparedStatement, class java/sql/ResultSet, int, int, long, int, int, int, class java/lang/String, long, class java/sql/PreparedStatement, class java/sql/ResultSet ]
          stack = []
        frame_type = 255 /* full_frame */
          offset_delta = 85
          locals = [ class ext/mods/Crypta/PlayerEmailManager, class ext/mods/gameserver/model/actor/Player, class java/lang/StringBuilder, class java/sql/Connection, class java/sql/PreparedStatement, class java/sql/ResultSet, int, int, long, int, int, int, class java/lang/String, long, class java/sql/PreparedStatement, class java/sql/ResultSet, int, int, int, int, class java/lang/String ]
          stack = []
        frame_type = 66 /* same_locals_1_stack_item */
          stack = [ class java/lang/String ]
        frame_type = 255 /* full_frame */
          offset_delta = 12
          locals = [ class ext/mods/Crypta/PlayerEmailManager, class ext/mods/gameserver/model/actor/Player, class java/lang/StringBuilder, class java/sql/Connection, class java/sql/PreparedStatement, class java/sql/ResultSet, int, int, long, int, int, int, class java/lang/String, long, class java/sql/PreparedStatement, class java/sql/ResultSet, int, int, int, int, class java/lang/String ]
          stack = [ class java/lang/String, class java/lang/String ]
        frame_type = 255 /* full_frame */
          offset_delta = 2
          locals = [ class ext/mods/Crypta/PlayerEmailManager, class ext/mods/gameserver/model/actor/Player, class java/lang/StringBuilder, class java/sql/Connection, class java/sql/PreparedStatement, class java/sql/ResultSet, int, int, long, int, int, int, class java/lang/String, long, class java/sql/PreparedStatement, class java/sql/ResultSet, int, int, int, int, class java/lang/String ]
          stack = [ class java/lang/String, class java/lang/String, class java/lang/String ]
        frame_type = 255 /* full_frame */
          offset_delta = 38
          locals = [ class ext/mods/Crypta/PlayerEmailManager, class ext/mods/gameserver/model/actor/Player, class java/lang/StringBuilder, class java/sql/Connection, class java/sql/PreparedStatement, class java/sql/ResultSet, int, int, long, int, int, int, class java/lang/String, long, class java/sql/PreparedStatement, class java/sql/ResultSet ]
          stack = []
        frame_type = 78 /* same_locals_1_stack_item */
          stack = [ class java/lang/Throwable ]
        frame_type = 255 /* full_frame */
          offset_delta = 16
          locals = [ class ext/mods/Crypta/PlayerEmailManager, class ext/mods/gameserver/model/actor/Player, class java/lang/StringBuilder, class java/sql/Connection, class java/sql/PreparedStatement, class java/sql/ResultSet, int, int, long, int, int, int, class java/lang/String, long, class java/sql/PreparedStatement, class java/sql/ResultSet, class java/lang/Throwable ]
          stack = [ class java/lang/Throwable ]
        frame_type = 8 /* same */
        frame_type = 249 /* chop */
          offset_delta = 2
        frame_type = 78 /* same_locals_1_stack_item */
          stack = [ class java/lang/Throwable ]
        frame_type = 255 /* full_frame */
          offset_delta = 16
          locals = [ class ext/mods/Crypta/PlayerEmailManager, class ext/mods/gameserver/model/actor/Player, class java/lang/StringBuilder, class java/sql/Connection, class java/sql/PreparedStatement, class java/sql/ResultSet, int, int, long, int, int, int, class java/lang/String, long, class java/sql/PreparedStatement, class java/lang/Throwable ]
          stack = [ class java/lang/Throwable ]
        frame_type = 8 /* same */
        frame_type = 249 /* chop */
          offset_delta = 2
        frame_type = 51 /* same */
        frame_type = 255 /* full_frame */
          offset_delta = 35
          locals = [ class ext/mods/Crypta/PlayerEmailManager, class ext/mods/gameserver/model/actor/Player, class java/lang/StringBuilder, class java/sql/Connection, class java/sql/PreparedStatement, class java/sql/ResultSet ]
          stack = []
        frame_type = 78 /* same_locals_1_stack_item */
          stack = [ class java/lang/Throwable ]
        frame_type = 255 /* full_frame */
          offset_delta = 16
          locals = [ class ext/mods/Crypta/PlayerEmailManager, class ext/mods/gameserver/model/actor/Player, class java/lang/StringBuilder, class java/sql/Connection, class java/sql/PreparedStatement, class java/sql/ResultSet, class java/lang/Throwable ]
          stack = [ class java/lang/Throwable ]
        frame_type = 8 /* same */
        frame_type = 249 /* chop */
          offset_delta = 2
        frame_type = 78 /* same_locals_1_stack_item */
          stack = [ class java/lang/Throwable ]
        frame_type = 255 /* full_frame */
          offset_delta = 16
          locals = [ class ext/mods/Crypta/PlayerEmailManager, class ext/mods/gameserver/model/actor/Player, class java/lang/StringBuilder, class java/sql/Connection, class java/sql/PreparedStatement, class java/lang/Throwable ]
          stack = [ class java/lang/Throwable ]
        frame_type = 8 /* same */
        frame_type = 249 /* chop */
          offset_delta = 2
        frame_type = 76 /* same_locals_1_stack_item */
          stack = [ class java/lang/Throwable ]
        frame_type = 255 /* full_frame */
          offset_delta = 14
          locals = [ class ext/mods/Crypta/PlayerEmailManager, class ext/mods/gameserver/model/actor/Player, class java/lang/StringBuilder, class java/sql/Connection, class java/lang/Throwable ]
          stack = [ class java/lang/Throwable ]
        frame_type = 8 /* same */
        frame_type = 249 /* chop */
          offset_delta = 2
        frame_type = 66 /* same_locals_1_stack_item */
          stack = [ class java/lang/Exception ]
        frame_type = 19 /* same */

  static {};
    descriptor: ()V
    flags: (0x0008) ACC_STATIC
    Code:
      stack=1, locals=0, args_size=0
         0: ldc           #14                 // class ext/mods/Crypta/PlayerEmailManager
         2: invokevirtual #356                // Method java/lang/Class.getName:()Ljava/lang/String;
         5: invokestatic  #359                // Method java/util/logging/Logger.getLogger:(Ljava/lang/String;)Ljava/util/logging/Logger;
         8: putstatic     #199                // Field LOGGER:Ljava/util/logging/Logger;
        11: return
      LineNumberTable:
        line 35: 0
}
SourceFile: "PlayerEmailManager.java"
NestMembers:
  ext/mods/Crypta/PlayerEmailManager$SingletonHolder
BootstrapMethods:
  0: #436 REF_invokeStatic java/lang/invoke/StringConcatFactory.makeConcatWithConstants:(Ljava/lang/invoke/MethodHandles$Lookup;Ljava/lang/String;Ljava/lang/invoke/MethodType;Ljava/lang/String;[Ljava/lang/Object;)Ljava/lang/invoke/CallSite;
    Method arguments:
      #420 html/mods/menu/\u0001
  1: #436 REF_invokeStatic java/lang/invoke/StringConcatFactory.makeConcatWithConstants:(Ljava/lang/invoke/MethodHandles$Lookup;Ljava/lang/String;Ljava/lang/invoke/MethodType;Ljava/lang/String;[Ljava/lang/Object;)Ljava/lang/invoke/CallSite;
    Method arguments:
      #422 <td width=120 align=left><font color=00FF00>\u0001</font></td>
  2: #436 REF_invokeStatic java/lang/invoke/StringConcatFactory.makeConcatWithConstants:(Ljava/lang/invoke/MethodHandles$Lookup;Ljava/lang/String;Ljava/lang/invoke/MethodType;Ljava/lang/String;[Ljava/lang/Object;)Ljava/lang/invoke/CallSite;
    Method arguments:
      #424 %\u0001%
  3: #436 REF_invokeStatic java/lang/invoke/StringConcatFactory.makeConcatWithConstants:(Ljava/lang/invoke/MethodHandles$Lookup;Ljava/lang/String;Ljava/lang/invoke/MethodType;Ljava/lang/String;[Ljava/lang/Object;)Ljava/lang/invoke/CallSite;
    Method arguments:
      #426 \u0001...
  4: #436 REF_invokeStatic java/lang/invoke/StringConcatFactory.makeConcatWithConstants:(Ljava/lang/invoke/MethodHandles$Lookup;Ljava/lang/String;Ljava/lang/invoke/MethodType;Ljava/lang/String;[Ljava/lang/Object;)Ljava/lang/invoke/CallSite;
    Method arguments:
      #428 searchPlayer DB error: \u0001
  5: #436 REF_invokeStatic java/lang/invoke/StringConcatFactory.makeConcatWithConstants:(Ljava/lang/invoke/MethodHandles$Lookup;Ljava/lang/String;Ljava/lang/invoke/MethodType;Ljava/lang/String;[Ljava/lang/Object;)Ljava/lang/invoke/CallSite;
    Method arguments:
      #430 +\u0001
  6: #436 REF_invokeStatic java/lang/invoke/StringConcatFactory.makeConcatWithConstants:(Ljava/lang/invoke/MethodHandles$Lookup;Ljava/lang/String;Ljava/lang/invoke/MethodType;Ljava/lang/String;[Ljava/lang/Object;)Ljava/lang/invoke/CallSite;
    Method arguments:
      #432 \u0001\u0001\u0001
  7: #436 REF_invokeStatic java/lang/invoke/StringConcatFactory.makeConcatWithConstants:(Ljava/lang/invoke/MethodHandles$Lookup;Ljava/lang/String;Ljava/lang/invoke/MethodType;Ljava/lang/String;[Ljava/lang/Object;)Ljava/lang/invoke/CallSite;
    Method arguments:
      #434 Erro ao mostrar inbox: \u0001
InnerClasses:
  public static final #448= #444 of #446; // Lookup=class java/lang/invoke/MethodHandles$Lookup of class java/lang/invoke/MethodHandles
