// Bytecode for: ext.mods.gameserver.model.TimeAttackEventRoom$RoomIndex
// File: ext\mods\gameserver\model\TimeAttackEventRoom$RoomIndex.class

Classfile /c:/Users/User/Desktop/BrProject/bin/main/ext/mods/gameserver/model/TimeAttackEventRoom$RoomIndex.class
  Last modified 9 de jul de 2026; size 1718 bytes
  MD5 checksum aaf5e0188675b7a85ac5b54d28c137ce
  Compiled from "TimeAttackEventRoom.java"
final class ext.mods.gameserver.model.TimeAttackEventRoom$RoomIndex extends java.lang.Record
  minor version: 0
  major version: 69
  flags: (0x0030) ACC_FINAL, ACC_SUPER
  this_class: #8                          // ext/mods/gameserver/model/TimeAttackEventRoom$RoomIndex
  super_class: #2                         // java/lang/Record
  interfaces: 0, fields: 2, methods: 6, attributes: 5
Constant pool:
   #1 = Methodref          #2.#3          // java/lang/Record."<init>":()V
   #2 = Class              #4             // java/lang/Record
   #3 = NameAndType        #5:#6          // "<init>":()V
   #4 = Utf8               java/lang/Record
   #5 = Utf8               <init>
   #6 = Utf8               ()V
   #7 = Fieldref           #8.#9          // ext/mods/gameserver/model/TimeAttackEventRoom$RoomIndex.index:I
   #8 = Class              #10            // ext/mods/gameserver/model/TimeAttackEventRoom$RoomIndex
   #9 = NameAndType        #11:#12        // index:I
  #10 = Utf8               ext/mods/gameserver/model/TimeAttackEventRoom$RoomIndex
  #11 = Utf8               index
  #12 = Utf8               I
  #13 = Fieldref           #8.#14         // ext/mods/gameserver/model/TimeAttackEventRoom$RoomIndex.partType:I
  #14 = NameAndType        #15:#12        // partType:I
  #15 = Utf8               partType
  #16 = InvokeDynamic      #0:#17         // #0:toString:(Lext/mods/gameserver/model/TimeAttackEventRoom$RoomIndex;)Ljava/lang/String;
  #17 = NameAndType        #18:#19        // toString:(Lext/mods/gameserver/model/TimeAttackEventRoom$RoomIndex;)Ljava/lang/String;
  #18 = Utf8               toString
  #19 = Utf8               (Lext/mods/gameserver/model/TimeAttackEventRoom$RoomIndex;)Ljava/lang/String;
  #20 = InvokeDynamic      #0:#21         // #0:hashCode:(Lext/mods/gameserver/model/TimeAttackEventRoom$RoomIndex;)I
  #21 = NameAndType        #22:#23        // hashCode:(Lext/mods/gameserver/model/TimeAttackEventRoom$RoomIndex;)I
  #22 = Utf8               hashCode
  #23 = Utf8               (Lext/mods/gameserver/model/TimeAttackEventRoom$RoomIndex;)I
  #24 = InvokeDynamic      #0:#25         // #0:equals:(Lext/mods/gameserver/model/TimeAttackEventRoom$RoomIndex;Ljava/lang/Object;)Z
  #25 = NameAndType        #26:#27        // equals:(Lext/mods/gameserver/model/TimeAttackEventRoom$RoomIndex;Ljava/lang/Object;)Z
  #26 = Utf8               equals
  #27 = Utf8               (Lext/mods/gameserver/model/TimeAttackEventRoom$RoomIndex;Ljava/lang/Object;)Z
  #28 = Utf8               (II)V
  #29 = Utf8               Code
  #30 = Utf8               LineNumberTable
  #31 = Utf8               LocalVariableTable
  #32 = Utf8               this
  #33 = Utf8               Lext/mods/gameserver/model/TimeAttackEventRoom$RoomIndex;
  #34 = Utf8               MethodParameters
  #35 = Utf8               ()Ljava/lang/String;
  #36 = Utf8               ()I
  #37 = Utf8               (Ljava/lang/Object;)Z
  #38 = Utf8               o
  #39 = Utf8               Ljava/lang/Object;
  #40 = Utf8               SourceFile
  #41 = Utf8               TimeAttackEventRoom.java
  #42 = Utf8               NestHost
  #43 = Class              #44            // ext/mods/gameserver/model/TimeAttackEventRoom
  #44 = Utf8               ext/mods/gameserver/model/TimeAttackEventRoom
  #45 = Utf8               Record
  #46 = Utf8               BootstrapMethods
  #47 = String             #48            // index;partType
  #48 = Utf8               index;partType
  #49 = MethodHandle       1:#7           // REF_getField ext/mods/gameserver/model/TimeAttackEventRoom$RoomIndex.index:I
  #50 = MethodHandle       1:#13          // REF_getField ext/mods/gameserver/model/TimeAttackEventRoom$RoomIndex.partType:I
  #51 = MethodHandle       6:#52          // REF_invokeStatic java/lang/runtime/ObjectMethods.bootstrap:(Ljava/lang/invoke/MethodHandles$Lookup;Ljava/lang/String;Ljava/lang/invoke/TypeDescriptor;Ljava/lang/Class;Ljava/lang/String;[Ljava/lang/invoke/MethodHandle;)Ljava/lang/Object;
  #52 = Methodref          #53.#54        // java/lang/runtime/ObjectMethods.bootstrap:(Ljava/lang/invoke/MethodHandles$Lookup;Ljava/lang/String;Ljava/lang/invoke/TypeDescriptor;Ljava/lang/Class;Ljava/lang/String;[Ljava/lang/invoke/MethodHandle;)Ljava/lang/Object;
  #53 = Class              #55            // java/lang/runtime/ObjectMethods
  #54 = NameAndType        #56:#57        // bootstrap:(Ljava/lang/invoke/MethodHandles$Lookup;Ljava/lang/String;Ljava/lang/invoke/TypeDescriptor;Ljava/lang/Class;Ljava/lang/String;[Ljava/lang/invoke/MethodHandle;)Ljava/lang/Object;
  #55 = Utf8               java/lang/runtime/ObjectMethods
  #56 = Utf8               bootstrap
  #57 = Utf8               (Ljava/lang/invoke/MethodHandles$Lookup;Ljava/lang/String;Ljava/lang/invoke/TypeDescriptor;Ljava/lang/Class;Ljava/lang/String;[Ljava/lang/invoke/MethodHandle;)Ljava/lang/Object;
  #58 = Utf8               InnerClasses
  #59 = Utf8               RoomIndex
  #60 = Class              #61            // java/lang/invoke/MethodHandles$Lookup
  #61 = Utf8               java/lang/invoke/MethodHandles$Lookup
  #62 = Class              #63            // java/lang/invoke/MethodHandles
  #63 = Utf8               java/lang/invoke/MethodHandles
  #64 = Utf8               Lookup
{
  ext.mods.gameserver.model.TimeAttackEventRoom$RoomIndex(int, int);
    descriptor: (II)V
    flags: (0x0000)
    Code:
      stack=2, locals=3, args_size=3
         0: aload_0
         1: invokespecial #1                  // Method java/lang/Record."<init>":()V
         4: aload_0
         5: iload_1
         6: putfield      #7                  // Field index:I
         9: aload_0
        10: iload_2
        11: putfield      #13                 // Field partType:I
        14: return
      LineNumberTable:
        line 65: 0
      LocalVariableTable:
        Start  Length  Slot  Name   Signature
            0      15     0  this   Lext/mods/gameserver/model/TimeAttackEventRoom$RoomIndex;
            0      15     1 index   I
            0      15     2 partType   I
    MethodParameters:
      Name                           Flags
      index
      partType

  public final java.lang.String toString();
    descriptor: ()Ljava/lang/String;
    flags: (0x0011) ACC_PUBLIC, ACC_FINAL
    Code:
      stack=1, locals=1, args_size=1
         0: aload_0
         1: invokedynamic #16,  0             // InvokeDynamic #0:toString:(Lext/mods/gameserver/model/TimeAttackEventRoom$RoomIndex;)Ljava/lang/String;
         6: areturn
      LineNumberTable:
        line 65: 0
      LocalVariableTable:
        Start  Length  Slot  Name   Signature
            0       7     0  this   Lext/mods/gameserver/model/TimeAttackEventRoom$RoomIndex;

  public final int hashCode();
    descriptor: ()I
    flags: (0x0011) ACC_PUBLIC, ACC_FINAL
    Code:
      stack=1, locals=1, args_size=1
         0: aload_0
         1: invokedynamic #20,  0             // InvokeDynamic #0:hashCode:(Lext/mods/gameserver/model/TimeAttackEventRoom$RoomIndex;)I
         6: ireturn
      LineNumberTable:
        line 65: 0
      LocalVariableTable:
        Start  Length  Slot  Name   Signature
            0       7     0  this   Lext/mods/gameserver/model/TimeAttackEventRoom$RoomIndex;

  public final boolean equals(java.lang.Object);
    descriptor: (Ljava/lang/Object;)Z
    flags: (0x0011) ACC_PUBLIC, ACC_FINAL
    Code:
      stack=2, locals=2, args_size=2
         0: aload_0
         1: aload_1
         2: invokedynamic #24,  0             // InvokeDynamic #0:equals:(Lext/mods/gameserver/model/TimeAttackEventRoom$RoomIndex;Ljava/lang/Object;)Z
         7: ireturn
      LineNumberTable:
        line 65: 0
      LocalVariableTable:
        Start  Length  Slot  Name   Signature
            0       8     0  this   Lext/mods/gameserver/model/TimeAttackEventRoom$RoomIndex;
            0       8     1     o   Ljava/lang/Object;

  public int index();
    descriptor: ()I
    flags: (0x0001) ACC_PUBLIC
    Code:
      stack=1, locals=1, args_size=1
         0: aload_0
         1: getfield      #7                  // Field index:I
         4: ireturn
      LineNumberTable:
        line 65: 0
      LocalVariableTable:
        Start  Length  Slot  Name   Signature
            0       5     0  this   Lext/mods/gameserver/model/TimeAttackEventRoom$RoomIndex;

  public int partType();
    descriptor: ()I
    flags: (0x0001) ACC_PUBLIC
    Code:
      stack=1, locals=1, args_size=1
         0: aload_0
         1: getfield      #13                 // Field partType:I
         4: ireturn
      LineNumberTable:
        line 65: 0
      LocalVariableTable:
        Start  Length  Slot  Name   Signature
            0       5     0  this   Lext/mods/gameserver/model/TimeAttackEventRoom$RoomIndex;
}
SourceFile: "TimeAttackEventRoom.java"
NestHost: class ext/mods/gameserver/model/TimeAttackEventRoom
  Record: length = 0xE (unknown attribute)
   00 02 00 0B 00 0C 00 00 00 0F 00 0C 00 00
BootstrapMethods:
  0: #51 REF_invokeStatic java/lang/runtime/ObjectMethods.bootstrap:(Ljava/lang/invoke/MethodHandles$Lookup;Ljava/lang/String;Ljava/lang/invoke/TypeDescriptor;Ljava/lang/Class;Ljava/lang/String;[Ljava/lang/invoke/MethodHandle;)Ljava/lang/Object;
    Method arguments:
      #8 ext/mods/gameserver/model/TimeAttackEventRoom$RoomIndex
      #47 index;partType
      #49 REF_getField ext/mods/gameserver/model/TimeAttackEventRoom$RoomIndex.index:I
      #50 REF_getField ext/mods/gameserver/model/TimeAttackEventRoom$RoomIndex.partType:I
InnerClasses:
  static final #59= #8 of #43;            // RoomIndex=class ext/mods/gameserver/model/TimeAttackEventRoom$RoomIndex of class ext/mods/gameserver/model/TimeAttackEventRoom
  public static final #64= #60 of #62;    // Lookup=class java/lang/invoke/MethodHandles$Lookup of class java/lang/invoke/MethodHandles
