// Bytecode for: ext.mods.commons.crypt.BCrypt
// File: ext\mods\commons\crypt\BCrypt.class

Classfile /c:/Users/User/Desktop/BrProject/bin/main/ext/mods/commons/crypt/BCrypt.class
  Last modified 9 de jul de 2026; size 22536 bytes
  MD5 checksum c5160d13e77125842d230567d7d0dc63
  Compiled from "BCrypt.java"
public class ext.mods.commons.crypt.BCrypt
  minor version: 0
  major version: 69
  flags: (0x0021) ACC_PUBLIC, ACC_SUPER
  this_class: #18                         // ext/mods/commons/crypt/BCrypt
  super_class: #2                         // java/lang/Object
  interfaces: 0, fields: 10, methods: 17, attributes: 3
Constant pool:
     #1 = Methodref          #2.#3        // java/lang/Object."<init>":()V
     #2 = Class              #4           // java/lang/Object
     #3 = NameAndType        #5:#6        // "<init>":()V
     #4 = Utf8               java/lang/Object
     #5 = Utf8               <init>
     #6 = Utf8               ()V
     #7 = Class              #8           // java/lang/IllegalArgumentException
     #8 = Utf8               java/lang/IllegalArgumentException
     #9 = String             #10          // Invalid len
    #10 = Utf8               Invalid len
    #11 = Methodref          #7.#12       // java/lang/IllegalArgumentException."<init>":(Ljava/lang/String;)V
    #12 = NameAndType        #5:#13       // "<init>":(Ljava/lang/String;)V
    #13 = Utf8               (Ljava/lang/String;)V
    #14 = Class              #15          // java/lang/StringBuilder
    #15 = Utf8               java/lang/StringBuilder
    #16 = Methodref          #14.#3       // java/lang/StringBuilder."<init>":()V
    #17 = Fieldref           #18.#19      // ext/mods/commons/crypt/BCrypt.BASE64_CODE:[C
    #18 = Class              #20          // ext/mods/commons/crypt/BCrypt
    #19 = NameAndType        #21:#22      // BASE64_CODE:[C
    #20 = Utf8               ext/mods/commons/crypt/BCrypt
    #21 = Utf8               BASE64_CODE
    #22 = Utf8               [C
    #23 = Methodref          #14.#24      // java/lang/StringBuilder.append:(C)Ljava/lang/StringBuilder;
    #24 = NameAndType        #25:#26      // append:(C)Ljava/lang/StringBuilder;
    #25 = Utf8               append
    #26 = Utf8               (C)Ljava/lang/StringBuilder;
    #27 = Methodref          #14.#28      // java/lang/StringBuilder.toString:()Ljava/lang/String;
    #28 = NameAndType        #29:#30      // toString:()Ljava/lang/String;
    #29 = Utf8               toString
    #30 = Utf8               ()Ljava/lang/String;
    #31 = Fieldref           #18.#32      // ext/mods/commons/crypt/BCrypt.INDEX_64:[B
    #32 = NameAndType        #33:#34      // INDEX_64:[B
    #33 = Utf8               INDEX_64
    #34 = Utf8               [B
    #35 = String             #36          // Invalid maxolen
    #36 = Utf8               Invalid maxolen
    #37 = Methodref          #38.#39      // java/lang/String.length:()I
    #38 = Class              #40          // java/lang/String
    #39 = NameAndType        #41:#42      // length:()I
    #40 = Utf8               java/lang/String
    #41 = Utf8               length
    #42 = Utf8               ()I
    #43 = Methodref          #38.#44      // java/lang/String.charAt:(I)C
    #44 = NameAndType        #45:#46      // charAt:(I)C
    #45 = Utf8               charAt
    #46 = Utf8               (I)C
    #47 = Methodref          #18.#48      // ext/mods/commons/crypt/BCrypt.char64:(C)B
    #48 = NameAndType        #49:#50      // char64:(C)B
    #49 = Utf8               char64
    #50 = Utf8               (C)B
    #51 = Methodref          #14.#44      // java/lang/StringBuilder.charAt:(I)C
    #52 = Fieldref           #18.#53      // ext/mods/commons/crypt/BCrypt.P:[I
    #53 = NameAndType        #54:#55      // P:[I
    #54 = Utf8               P
    #55 = Utf8               [I
    #56 = Fieldref           #18.#57      // ext/mods/commons/crypt/BCrypt.S:[I
    #57 = NameAndType        #58:#55      // S:[I
    #58 = Utf8               S
    #59 = Fieldref           #18.#60      // ext/mods/commons/crypt/BCrypt.P_ORIG:[I
    #60 = NameAndType        #61:#55      // P_ORIG:[I
    #61 = Utf8               P_ORIG
    #62 = Methodref          #63.#64      // "[I".clone:()Ljava/lang/Object;
    #63 = Class              #55          // "[I"
    #64 = NameAndType        #65:#66      // clone:()Ljava/lang/Object;
    #65 = Utf8               clone
    #66 = Utf8               ()Ljava/lang/Object;
    #67 = Fieldref           #18.#68      // ext/mods/commons/crypt/BCrypt.S_ORIG:[I
    #68 = NameAndType        #69:#55      // S_ORIG:[I
    #69 = Utf8               S_ORIG
    #70 = Methodref          #18.#71      // ext/mods/commons/crypt/BCrypt.streamToWord:([B[I)I
    #71 = NameAndType        #72:#73      // streamToWord:([B[I)I
    #72 = Utf8               streamToWord
    #73 = Utf8               ([B[I)I
    #74 = Methodref          #18.#75      // ext/mods/commons/crypt/BCrypt.encipher:([II)V
    #75 = NameAndType        #76:#77      // encipher:([II)V
    #76 = Utf8               encipher
    #77 = Utf8               ([II)V
    #78 = String             #79          // Bad number of rounds
    #79 = Utf8               Bad number of rounds
    #80 = String             #81          // Bad salt length
    #81 = Utf8               Bad salt length
    #82 = Methodref          #18.#83      // ext/mods/commons/crypt/BCrypt.initKey:()V
    #83 = NameAndType        #84:#6       // initKey:()V
    #84 = Utf8               initKey
    #85 = Methodref          #18.#86      // ext/mods/commons/crypt/BCrypt.eksKey:([B[B)V
    #86 = NameAndType        #87:#88      // eksKey:([B[B)V
    #87 = Utf8               eksKey
    #88 = Utf8               ([B[B)V
    #89 = Methodref          #18.#90      // ext/mods/commons/crypt/BCrypt.key:([B)V
    #90 = NameAndType        #91:#92      // key:([B)V
    #91 = Utf8               key
    #92 = Utf8               ([B)V
    #93 = Methodref          #18.#94      // ext/mods/commons/crypt/BCrypt.generateSalt:()Ljava/lang/String;
    #94 = NameAndType        #95:#30      // generateSalt:()Ljava/lang/String;
    #95 = Utf8               generateSalt
    #96 = Methodref          #18.#97      // ext/mods/commons/crypt/BCrypt.hashPw:(Ljava/lang/String;Ljava/lang/String;)Ljava/lang/String;
    #97 = NameAndType        #98:#99      // hashPw:(Ljava/lang/String;Ljava/lang/String;)Ljava/lang/String;
    #98 = Utf8               hashPw
    #99 = Utf8               (Ljava/lang/String;Ljava/lang/String;)Ljava/lang/String;
   #100 = String             #101         // Invalid salt version
   #101 = Utf8               Invalid salt version
   #102 = String             #103         // Invalid salt revision
   #103 = Utf8               Invalid salt revision
   #104 = String             #105         // Missing salt rounds
   #105 = Utf8               Missing salt rounds
   #106 = Methodref          #38.#107     // java/lang/String.substring:(II)Ljava/lang/String;
   #107 = NameAndType        #108:#109    // substring:(II)Ljava/lang/String;
   #108 = Utf8               substring
   #109 = Utf8               (II)Ljava/lang/String;
   #110 = Methodref          #111.#112    // java/lang/Integer.parseInt:(Ljava/lang/String;)I
   #111 = Class              #113         // java/lang/Integer
   #112 = NameAndType        #114:#115    // parseInt:(Ljava/lang/String;)I
   #113 = Utf8               java/lang/Integer
   #114 = Utf8               parseInt
   #115 = Utf8               (Ljava/lang/String;)I
   #116 = String             #117         // \u0000
   #117 = Utf8               \u0000
   #118 = String             #119         //
   #119 = Utf8
   #120 = InvokeDynamic      #0:#121      // #0:makeConcatWithConstants:(Ljava/lang/String;Ljava/lang/String;)Ljava/lang/String;
   #121 = NameAndType        #122:#99     // makeConcatWithConstants:(Ljava/lang/String;Ljava/lang/String;)Ljava/lang/String;
   #122 = Utf8               makeConcatWithConstants
   #123 = Fieldref           #124.#125    // java/nio/charset/StandardCharsets.UTF_8:Ljava/nio/charset/Charset;
   #124 = Class              #126         // java/nio/charset/StandardCharsets
   #125 = NameAndType        #127:#128    // UTF_8:Ljava/nio/charset/Charset;
   #126 = Utf8               java/nio/charset/StandardCharsets
   #127 = Utf8               UTF_8
   #128 = Utf8               Ljava/nio/charset/Charset;
   #129 = Methodref          #38.#130     // java/lang/String.getBytes:(Ljava/nio/charset/Charset;)[B
   #130 = NameAndType        #131:#132    // getBytes:(Ljava/nio/charset/Charset;)[B
   #131 = Utf8               getBytes
   #132 = Utf8               (Ljava/nio/charset/Charset;)[B
   #133 = Methodref          #18.#134     // ext/mods/commons/crypt/BCrypt.decodeBase64:(Ljava/lang/String;I)[B
   #134 = NameAndType        #135:#136    // decodeBase64:(Ljava/lang/String;I)[B
   #135 = Utf8               decodeBase64
   #136 = Utf8               (Ljava/lang/String;I)[B
   #137 = Methodref          #18.#3       // ext/mods/commons/crypt/BCrypt."<init>":()V
   #138 = Fieldref           #18.#139     // ext/mods/commons/crypt/BCrypt.BF_CRYPT_CIPHERTEXT:[I
   #139 = NameAndType        #140:#55     // BF_CRYPT_CIPHERTEXT:[I
   #140 = Utf8               BF_CRYPT_CIPHERTEXT
   #141 = Methodref          #18.#142     // ext/mods/commons/crypt/BCrypt.cryptRaw:([B[BI[I)[B
   #142 = NameAndType        #143:#144    // cryptRaw:([B[BI[I)[B
   #143 = Utf8               cryptRaw
   #144 = Utf8               ([B[BI[I)[B
   #145 = String             #146         // $2
   #146 = Utf8               $2
   #147 = Methodref          #14.#148     // java/lang/StringBuilder.append:(Ljava/lang/String;)Ljava/lang/StringBuilder;
   #148 = NameAndType        #25:#149     // append:(Ljava/lang/String;)Ljava/lang/StringBuilder;
   #149 = Utf8               (Ljava/lang/String;)Ljava/lang/StringBuilder;
   #150 = String             #151         // $
   #151 = Utf8               $
   #152 = String             #153         // 0
   #153 = Utf8               0
   #154 = String             #155         // rounds exceeds maximum (30)
   #155 = Utf8               rounds exceeds maximum (30)
   #156 = Methodref          #111.#157    // java/lang/Integer.toString:(I)Ljava/lang/String;
   #157 = NameAndType        #29:#158     // toString:(I)Ljava/lang/String;
   #158 = Utf8               (I)Ljava/lang/String;
   #159 = Methodref          #18.#160     // ext/mods/commons/crypt/BCrypt.encodeBase64:([BI)Ljava/lang/String;
   #160 = NameAndType        #161:#162    // encodeBase64:([BI)Ljava/lang/String;
   #161 = Utf8               encodeBase64
   #162 = Utf8               ([BI)Ljava/lang/String;
   #163 = Methodref          #164.#165    // java/security/SecureRandom.nextBytes:([B)V
   #164 = Class              #166         // java/security/SecureRandom
   #165 = NameAndType        #167:#92     // nextBytes:([B)V
   #166 = Utf8               java/security/SecureRandom
   #167 = Utf8               nextBytes
   #168 = String             #169         // $2a$
   #169 = Utf8               $2a$
   #170 = String             #171         // log_rounds exceeds maximum (30)
   #171 = Utf8               log_rounds exceeds maximum (30)
   #172 = Methodref          #164.#3      // java/security/SecureRandom."<init>":()V
   #173 = Methodref          #18.#174     // ext/mods/commons/crypt/BCrypt.generateSalt:(ILjava/security/SecureRandom;)Ljava/lang/String;
   #174 = NameAndType        #95:#175     // generateSalt:(ILjava/security/SecureRandom;)Ljava/lang/String;
   #175 = Utf8               (ILjava/security/SecureRandom;)Ljava/lang/String;
   #176 = Methodref          #18.#177     // ext/mods/commons/crypt/BCrypt.generateSalt:(I)Ljava/lang/String;
   #177 = NameAndType        #95:#158     // generateSalt:(I)Ljava/lang/String;
   #178 = Integer            608135816
   #179 = Integer            -2052912941
   #180 = Integer            320440878
   #181 = Integer            57701188
   #182 = Integer            -1542899678
   #183 = Integer            698298832
   #184 = Integer            137296536
   #185 = Integer            -330404727
   #186 = Integer            1160258022
   #187 = Integer            953160567
   #188 = Integer            -1101764913
   #189 = Integer            887688300
   #190 = Integer            -1062458953
   #191 = Integer            -914599715
   #192 = Integer            1065670069
   #193 = Integer            -1253635817
   #194 = Integer            -1843997223
   #195 = Integer            -1988494565
   #196 = Integer            -785314906
   #197 = Integer            -1730169428
   #198 = Integer            805139163
   #199 = Integer            -803545161
   #200 = Integer            -1193168915
   #201 = Integer            1780907670
   #202 = Integer            -1166241723
   #203 = Integer            -248741991
   #204 = Integer            614570311
   #205 = Integer            -1282315017
   #206 = Integer            134345442
   #207 = Integer            -2054226922
   #208 = Integer            1667834072
   #209 = Integer            1901547113
   #210 = Integer            -1537671517
   #211 = Integer            -191677058
   #212 = Integer            227898511
   #213 = Integer            1921955416
   #214 = Integer            1904987480
   #215 = Integer            -2112533778
   #216 = Integer            2069144605
   #217 = Integer            -1034266187
   #218 = Integer            -1674521287
   #219 = Integer            720527379
   #220 = Integer            -976113629
   #221 = Integer            677414384
   #222 = Integer            -901678824
   #223 = Integer            -1193592593
   #224 = Integer            -1904616272
   #225 = Integer            1614419982
   #226 = Integer            1822297739
   #227 = Integer            -1340175810
   #228 = Integer            -686458943
   #229 = Integer            -1120842969
   #230 = Integer            2024746970
   #231 = Integer            1432378464
   #232 = Integer            -430627341
   #233 = Integer            -1437226092
   #234 = Integer            1464375394
   #235 = Integer            1676153920
   #236 = Integer            1439316330
   #237 = Integer            715854006
   #238 = Integer            -1261675468
   #239 = Integer            289532110
   #240 = Integer            -1588296017
   #241 = Integer            2087905683
   #242 = Integer            -1276242927
   #243 = Integer            1668267050
   #244 = Integer            732546397
   #245 = Integer            1947742710
   #246 = Integer            -832815594
   #247 = Integer            -1685613794
   #248 = Integer            -1344882125
   #249 = Integer            1814351708
   #250 = Integer            2050118529
   #251 = Integer            680887927
   #252 = Integer            999245976
   #253 = Integer            1800124847
   #254 = Integer            -994056165
   #255 = Integer            1713906067
   #256 = Integer            1641548236
   #257 = Integer            -81679983
   #258 = Integer            1216130144
   #259 = Integer            1575780402
   #260 = Integer            -276538019
   #261 = Integer            -377129551
   #262 = Integer            -601480446
   #263 = Integer            -345695352
   #264 = Integer            596196993
   #265 = Integer            -745100091
   #266 = Integer            258830323
   #267 = Integer            -2081144263
   #268 = Integer            772490370
   #269 = Integer            -1534844924
   #270 = Integer            1774776394
   #271 = Integer            -1642095778
   #272 = Integer            566650946
   #273 = Integer            -152474470
   #274 = Integer            1728879713
   #275 = Integer            -1412200208
   #276 = Integer            1783734482
   #277 = Integer            -665571480
   #278 = Integer            -1777359064
   #279 = Integer            -1420741725
   #280 = Integer            1861159788
   #281 = Integer            326777828
   #282 = Integer            -1170476976
   #283 = Integer            2130389656
   #284 = Integer            -1578015459
   #285 = Integer            967770486
   #286 = Integer            1724537150
   #287 = Integer            -2109534584
   #288 = Integer            -1930525159
   #289 = Integer            1164943284
   #290 = Integer            2105845187
   #291 = Integer            998989502
   #292 = Integer            -529566248
   #293 = Integer            -2050940813
   #294 = Integer            1075463327
   #295 = Integer            1455516326
   #296 = Integer            1322494562
   #297 = Integer            910128902
   #298 = Integer            469688178
   #299 = Integer            1117454909
   #300 = Integer            936433444
   #301 = Integer            -804646328
   #302 = Integer            -619713837
   #303 = Integer            1240580251
   #304 = Integer            122909385
   #305 = Integer            -2137449605
   #306 = Integer            634681816
   #307 = Integer            -152510729
   #308 = Integer            -469872614
   #309 = Integer            -1233564613
   #310 = Integer            -1754472259
   #311 = Integer            79693498
   #312 = Integer            -1045868618
   #313 = Integer            1084186820
   #314 = Integer            1583128258
   #315 = Integer            426386531
   #316 = Integer            1761308591
   #317 = Integer            1047286709
   #318 = Integer            322548459
   #319 = Integer            995290223
   #320 = Integer            1845252383
   #321 = Integer            -1691314900
   #322 = Integer            -863943356
   #323 = Integer            -1352745719
   #324 = Integer            -1092366332
   #325 = Integer            -567063811
   #326 = Integer            1712269319
   #327 = Integer            422464435
   #328 = Integer            -1060394921
   #329 = Integer            1170764815
   #330 = Integer            -771006663
   #331 = Integer            -1177289765
   #332 = Integer            1434042557
   #333 = Integer            442511882
   #334 = Integer            -694091578
   #335 = Integer            1076654713
   #336 = Integer            1738483198
   #337 = Integer            -81812532
   #338 = Integer            -1901729288
   #339 = Integer            -617471240
   #340 = Integer            1014306527
   #341 = Integer            -43947243
   #342 = Integer            793779912
   #343 = Integer            -1392160085
   #344 = Integer            842905082
   #345 = Integer            -48003232
   #346 = Integer            1395751752
   #347 = Integer            1040244610
   #348 = Integer            -1638115397
   #349 = Integer            -898659168
   #350 = Integer            445077038
   #351 = Integer            -552113701
   #352 = Integer            -717051658
   #353 = Integer            679411651
   #354 = Integer            -1402522938
   #355 = Integer            -1940957837
   #356 = Integer            1767581616
   #357 = Integer            -1144366904
   #358 = Integer            -503340195
   #359 = Integer            -1192226400
   #360 = Integer            284835224
   #361 = Integer            -48135240
   #362 = Integer            1258075500
   #363 = Integer            768725851
   #364 = Integer            -1705778055
   #365 = Integer            -1225243291
   #366 = Integer            -762426948
   #367 = Integer            1274779536
   #368 = Integer            -505548070
   #369 = Integer            -1530167757
   #370 = Integer            1660621633
   #371 = Integer            -823867672
   #372 = Integer            -283063590
   #373 = Integer            913787905
   #374 = Integer            -797008130
   #375 = Integer            737222580
   #376 = Integer            -1780753843
   #377 = Integer            -1366257256
   #378 = Integer            -357724559
   #379 = Integer            1804850592
   #380 = Integer            -795946544
   #381 = Integer            -1345903136
   #382 = Integer            -1908647121
   #383 = Integer            -1904896841
   #384 = Integer            -1879645445
   #385 = Integer            -233690268
   #386 = Integer            -2004305902
   #387 = Integer            -1878134756
   #388 = Integer            1336762016
   #389 = Integer            1754252060
   #390 = Integer            -774901359
   #391 = Integer            -1280786003
   #392 = Integer            791618072
   #393 = Integer            -1106372745
   #394 = Integer            -361419266
   #395 = Integer            -1962795103
   #396 = Integer            -442446833
   #397 = Integer            -1250986776
   #398 = Integer            413987798
   #399 = Integer            -829824359
   #400 = Integer            -1264037920
   #401 = Integer            -49028937
   #402 = Integer            2093235073
   #403 = Integer            -760370983
   #404 = Integer            375366246
   #405 = Integer            -2137688315
   #406 = Integer            -1815317740
   #407 = Integer            555357303
   #408 = Integer            -424861595
   #409 = Integer            2008414854
   #410 = Integer            -950779147
   #411 = Integer            -73583153
   #412 = Integer            -338841844
   #413 = Integer            2067696032
   #414 = Integer            -700376109
   #415 = Integer            -1373733303
   #416 = Integer            2428461
   #417 = Integer            544322398
   #418 = Integer            577241275
   #419 = Integer            1471733935
   #420 = Integer            610547355
   #421 = Integer            -267798242
   #422 = Integer            1432588573
   #423 = Integer            1507829418
   #424 = Integer            2025931657
   #425 = Integer            -648391809
   #426 = Integer            545086370
   #427 = Integer            48609733
   #428 = Integer            -2094660746
   #429 = Integer            1653985193
   #430 = Integer            298326376
   #431 = Integer            1316178497
   #432 = Integer            -1287180854
   #433 = Integer            2064951626
   #434 = Integer            458293330
   #435 = Integer            -1705826027
   #436 = Integer            -703637697
   #437 = Integer            -1130641692
   #438 = Integer            727753846
   #439 = Integer            -2115603456
   #440 = Integer            146436021
   #441 = Integer            1461446943
   #442 = Integer            -224990101
   #443 = Integer            705550613
   #444 = Integer            -1235000031
   #445 = Integer            -407242314
   #446 = Integer            -13368018
   #447 = Integer            -981117340
   #448 = Integer            1404054877
   #449 = Integer            -1449160799
   #450 = Integer            146425753
   #451 = Integer            1854211946
   #452 = Integer            1266315497
   #453 = Integer            -1246549692
   #454 = Integer            -613086930
   #455 = Integer            -1004984797
   #456 = Integer            -1385257296
   #457 = Integer            1235738493
   #458 = Integer            -1662099272
   #459 = Integer            -1880247706
   #460 = Integer            -324367247
   #461 = Integer            1771706367
   #462 = Integer            1449415276
   #463 = Integer            -1028546847
   #464 = Integer            422970021
   #465 = Integer            1963543593
   #466 = Integer            -1604775104
   #467 = Integer            -468174274
   #468 = Integer            1062508698
   #469 = Integer            1531092325
   #470 = Integer            1804592342
   #471 = Integer            -1711849514
   #472 = Integer            -1580033017
   #473 = Integer            -269995787
   #474 = Integer            1294809318
   #475 = Integer            -265986623
   #476 = Integer            1289560198
   #477 = Integer            -2072974554
   #478 = Integer            1669523910
   #479 = Integer            35572830
   #480 = Integer            157838143
   #481 = Integer            1052438473
   #482 = Integer            1016535060
   #483 = Integer            1802137761
   #484 = Integer            1753167236
   #485 = Integer            1386275462
   #486 = Integer            -1214491899
   #487 = Integer            -1437595849
   #488 = Integer            1040679964
   #489 = Integer            2145300060
   #490 = Integer            -1904392980
   #491 = Integer            1461121720
   #492 = Integer            -1338320329
   #493 = Integer            -263189491
   #494 = Integer            -266592508
   #495 = Integer            33600511
   #496 = Integer            -1374882534
   #497 = Integer            1018524850
   #498 = Integer            629373528
   #499 = Integer            -603381315
   #500 = Integer            -779021319
   #501 = Integer            2091462646
   #502 = Integer            -1808644237
   #503 = Integer            586499841
   #504 = Integer            988145025
   #505 = Integer            935516892
   #506 = Integer            -927631820
   #507 = Integer            -1695294041
   #508 = Integer            -1455136442
   #509 = Integer            265290510
   #510 = Integer            -322386114
   #511 = Integer            -1535828415
   #512 = Integer            -499593831
   #513 = Integer            1005194799
   #514 = Integer            847297441
   #515 = Integer            406762289
   #516 = Integer            1314163512
   #517 = Integer            1332590856
   #518 = Integer            1866599683
   #519 = Integer            -167115585
   #520 = Integer            750260880
   #521 = Integer            613907577
   #522 = Integer            1450815602
   #523 = Integer            -1129346641
   #524 = Integer            -560302305
   #525 = Integer            -644675568
   #526 = Integer            -1282691566
   #527 = Integer            -590397650
   #528 = Integer            1427272223
   #529 = Integer            778793252
   #530 = Integer            1343938022
   #531 = Integer            -1618686585
   #532 = Integer            2052605720
   #533 = Integer            1946737175
   #534 = Integer            -1130390852
   #535 = Integer            -380928628
   #536 = Integer            -327488454
   #537 = Integer            -612033030
   #538 = Integer            1661551462
   #539 = Integer            -1000029230
   #540 = Integer            -283371449
   #541 = Integer            840292616
   #542 = Integer            -582796489
   #543 = Integer            616741398
   #544 = Integer            312560963
   #545 = Integer            711312465
   #546 = Integer            1351876610
   #547 = Integer            322626781
   #548 = Integer            1910503582
   #549 = Integer            271666773
   #550 = Integer            -2119403562
   #551 = Integer            1594956187
   #552 = Integer            70604529
   #553 = Integer            -677132437
   #554 = Integer            1007753275
   #555 = Integer            1495573769
   #556 = Integer            -225450259
   #557 = Integer            -1745748998
   #558 = Integer            -1631928532
   #559 = Integer            504708206
   #560 = Integer            -2031925904
   #561 = Integer            -353800271
   #562 = Integer            -2045878774
   #563 = Integer            1514023603
   #564 = Integer            1998579484
   #565 = Integer            1312622330
   #566 = Integer            694541497
   #567 = Integer            -1712906993
   #568 = Integer            -2143385130
   #569 = Integer            1382467621
   #570 = Integer            776784248
   #571 = Integer            -1676627094
   #572 = Integer            -971698502
   #573 = Integer            -1797068168
   #574 = Integer            -1510196141
   #575 = Integer            503983604
   #576 = Integer            -218673497
   #577 = Integer            907881277
   #578 = Integer            423175695
   #579 = Integer            432175456
   #580 = Integer            1378068232
   #581 = Integer            -149744970
   #582 = Integer            -340918674
   #583 = Integer            -356311194
   #584 = Integer            -474200683
   #585 = Integer            -1501837181
   #586 = Integer            -1317062703
   #587 = Integer            26017576
   #588 = Integer            -1020076561
   #589 = Integer            -1100195163
   #590 = Integer            1700274565
   #591 = Integer            1756076034
   #592 = Integer            -288447217
   #593 = Integer            -617638597
   #594 = Integer            720338349
   #595 = Integer            1533947780
   #596 = Integer            354530856
   #597 = Integer            688349552
   #598 = Integer            -321042571
   #599 = Integer            1637815568
   #600 = Integer            332179504
   #601 = Integer            -345916010
   #602 = Integer            53804574
   #603 = Integer            -1442618417
   #604 = Integer            -1250730864
   #605 = Integer            1282449977
   #606 = Integer            -711025141
   #607 = Integer            -877994476
   #608 = Integer            -288586052
   #609 = Integer            1617046695
   #610 = Integer            -1666491221
   #611 = Integer            -1292663698
   #612 = Integer            1686838959
   #613 = Integer            431878346
   #614 = Integer            -1608291911
   #615 = Integer            1700445008
   #616 = Integer            1080580658
   #617 = Integer            1009431731
   #618 = Integer            832498133
   #619 = Integer            -1071531785
   #620 = Integer            -1688990951
   #621 = Integer            -2023776103
   #622 = Integer            -1778935426
   #623 = Integer            1648197032
   #624 = Integer            -130578278
   #625 = Integer            -1746719369
   #626 = Integer            300782431
   #627 = Integer            375919233
   #628 = Integer            238389289
   #629 = Integer            -941219882
   #630 = Integer            -1763778655
   #631 = Integer            2019080857
   #632 = Integer            1475708069
   #633 = Integer            455242339
   #634 = Integer            -1685863425
   #635 = Integer            448939670
   #636 = Integer            -843904277
   #637 = Integer            1395535956
   #638 = Integer            -1881585436
   #639 = Integer            1841049896
   #640 = Integer            1491858159
   #641 = Integer            885456874
   #642 = Integer            -30872223
   #643 = Integer            -293847949
   #644 = Integer            1565136089
   #645 = Integer            -396052509
   #646 = Integer            1108368660
   #647 = Integer            540939232
   #648 = Integer            1173283510
   #649 = Integer            -1549095958
   #650 = Integer            -613658859
   #651 = Integer            -87339056
   #652 = Integer            -951913406
   #653 = Integer            -278217803
   #654 = Integer            1699691293
   #655 = Integer            1103962373
   #656 = Integer            -669091426
   #657 = Integer            -2038084153
   #658 = Integer            -464828566
   #659 = Integer            1031889488
   #660 = Integer            -815619598
   #661 = Integer            1535977030
   #662 = Integer            -58162272
   #663 = Integer            -1043876189
   #664 = Integer            2132092099
   #665 = Integer            1774941330
   #666 = Integer            1199868427
   #667 = Integer            1452454533
   #668 = Integer            157007616
   #669 = Integer            -1390851939
   #670 = Integer            342012276
   #671 = Integer            595725824
   #672 = Integer            1480756522
   #673 = Integer            206960106
   #674 = Integer            497939518
   #675 = Integer            591360097
   #676 = Integer            863170706
   #677 = Integer            -1919713727
   #678 = Integer            -698356495
   #679 = Integer            1814182875
   #680 = Integer            2094937945
   #681 = Integer            -873565088
   #682 = Integer            1082520231
   #683 = Integer            -831049106
   #684 = Integer            -1509457788
   #685 = Integer            435703966
   #686 = Integer            -386934699
   #687 = Integer            1641649973
   #688 = Integer            -1452693590
   #689 = Integer            -989067582
   #690 = Integer            1510255612
   #691 = Integer            -2146710820
   #692 = Integer            -1639679442
   #693 = Integer            -1018874748
   #694 = Integer            -36346107
   #695 = Integer            236887753
   #696 = Integer            -613164077
   #697 = Integer            274041037
   #698 = Integer            1734335097
   #699 = Integer            -479771840
   #700 = Integer            -976997275
   #701 = Integer            1899903192
   #702 = Integer            1026095262
   #703 = Integer            -244449504
   #704 = Integer            356393447
   #705 = Integer            -1884275382
   #706 = Integer            -421290197
   #707 = Integer            -612127241
   #708 = Integer            -381855128
   #709 = Integer            -1803468553
   #710 = Integer            -162781668
   #711 = Integer            -1805047500
   #712 = Integer            1091903735
   #713 = Integer            1979897079
   #714 = Integer            -1124832466
   #715 = Integer            -727580568
   #716 = Integer            -737663887
   #717 = Integer            857797738
   #718 = Integer            1136121015
   #719 = Integer            1342202287
   #720 = Integer            507115054
   #721 = Integer            -1759230650
   #722 = Integer            337727348
   #723 = Integer            -1081374656
   #724 = Integer            1301675037
   #725 = Integer            -1766485585
   #726 = Integer            1895095763
   #727 = Integer            1721773893
   #728 = Integer            -1078195732
   #729 = Integer            62756741
   #730 = Integer            2142006736
   #731 = Integer            835421444
   #732 = Integer            -1762973773
   #733 = Integer            1442658625
   #734 = Integer            -635090970
   #735 = Integer            -1412822374
   #736 = Integer            676362277
   #737 = Integer            1392781812
   #738 = Integer            170690266
   #739 = Integer            -373920261
   #740 = Integer            1759253602
   #741 = Integer            -683120384
   #742 = Integer            1745797284
   #743 = Integer            664899054
   #744 = Integer            1329594018
   #745 = Integer            -393761396
   #746 = Integer            -1249058810
   #747 = Integer            2062866102
   #748 = Integer            -1429332356
   #749 = Integer            -751345684
   #750 = Integer            -830954599
   #751 = Integer            1080764994
   #752 = Integer            553557557
   #753 = Integer            -638351943
   #754 = Integer            -298199125
   #755 = Integer            991055499
   #756 = Integer            499776247
   #757 = Integer            1265440854
   #758 = Integer            648242737
   #759 = Integer            -354183246
   #760 = Integer            980351604
   #761 = Integer            -581221582
   #762 = Integer            1749149687
   #763 = Integer            -898096901
   #764 = Integer            -83167922
   #765 = Integer            -654396521
   #766 = Integer            1161844396
   #767 = Integer            -1169648345
   #768 = Integer            1431517754
   #769 = Integer            545492359
   #770 = Integer            -26498633
   #771 = Integer            -795437749
   #772 = Integer            1437099964
   #773 = Integer            -1592419752
   #774 = Integer            -861329053
   #775 = Integer            -1713251533
   #776 = Integer            -1507177898
   #777 = Integer            1060185593
   #778 = Integer            1593081372
   #779 = Integer            -1876348548
   #780 = Integer            -34019326
   #781 = Integer            69676912
   #782 = Integer            -2135222948
   #783 = Integer            86519011
   #784 = Integer            -1782508216
   #785 = Integer            -456757982
   #786 = Integer            1220612927
   #787 = Integer            -955283748
   #788 = Integer            133810670
   #789 = Integer            1090789135
   #790 = Integer            1078426020
   #791 = Integer            1569222167
   #792 = Integer            845107691
   #793 = Integer            -711212847
   #794 = Integer            -222510705
   #795 = Integer            1091646820
   #796 = Integer            628848692
   #797 = Integer            1613405280
   #798 = Integer            -537335645
   #799 = Integer            526609435
   #800 = Integer            236106946
   #801 = Integer            48312990
   #802 = Integer            -1352249391
   #803 = Integer            -892239595
   #804 = Integer            1797494240
   #805 = Integer            859738849
   #806 = Integer            992217954
   #807 = Integer            -289490654
   #808 = Integer            -2051890674
   #809 = Integer            -424014439
   #810 = Integer            -562951028
   #811 = Integer            765654824
   #812 = Integer            -804095931
   #813 = Integer            -1783130883
   #814 = Integer            1685915746
   #815 = Integer            -405998096
   #816 = Integer            1414112111
   #817 = Integer            -2021832454
   #818 = Integer            -1013056217
   #819 = Integer            -214004450
   #820 = Integer            172450625
   #821 = Integer            -1724973196
   #822 = Integer            980381355
   #823 = Integer            -185008841
   #824 = Integer            -1475158944
   #825 = Integer            -1578377736
   #826 = Integer            -1726226100
   #827 = Integer            -613520627
   #828 = Integer            -964995824
   #829 = Integer            1835478071
   #830 = Integer            660984891
   #831 = Integer            -590288892
   #832 = Integer            -248967737
   #833 = Integer            -872349789
   #834 = Integer            -1254551662
   #835 = Integer            1762651403
   #836 = Integer            1719377915
   #837 = Integer            -824476260
   #838 = Integer            -1601057013
   #839 = Integer            -652910941
   #840 = Integer            -1156370552
   #841 = Integer            1364962596
   #842 = Integer            2073328063
   #843 = Integer            1983633131
   #844 = Integer            926494387
   #845 = Integer            -871278215
   #846 = Integer            -2144935273
   #847 = Integer            -198299347
   #848 = Integer            1749200295
   #849 = Integer            -966120645
   #850 = Integer            309677260
   #851 = Integer            2016342300
   #852 = Integer            1779581495
   #853 = Integer            -1215147545
   #854 = Integer            111262694
   #855 = Integer            1274766160
   #856 = Integer            443224088
   #857 = Integer            298511866
   #858 = Integer            1025883608
   #859 = Integer            -488520759
   #860 = Integer            1145181785
   #861 = Integer            168956806
   #862 = Integer            -653464466
   #863 = Integer            -710153686
   #864 = Integer            1689216846
   #865 = Integer            -628709281
   #866 = Integer            -1094719096
   #867 = Integer            1692713982
   #868 = Integer            -1648590761
   #869 = Integer            -252198778
   #870 = Integer            1618508792
   #871 = Integer            1610833997
   #872 = Integer            -771914938
   #873 = Integer            -164094032
   #874 = Integer            2001055236
   #875 = Integer            -684262196
   #876 = Integer            -2092799181
   #877 = Integer            -266425487
   #878 = Integer            -1333771897
   #879 = Integer            1006657119
   #880 = Integer            2006996926
   #881 = Integer            -1108824540
   #882 = Integer            1430667929
   #883 = Integer            -1084739999
   #884 = Integer            1314452623
   #885 = Integer            -220332638
   #886 = Integer            -193663176
   #887 = Integer            -2021016126
   #888 = Integer            1399257539
   #889 = Integer            -927756684
   #890 = Integer            -1267338667
   #891 = Integer            1190975929
   #892 = Integer            2062231137
   #893 = Integer            -1960976508
   #894 = Integer            -2073424263
   #895 = Integer            -1856006686
   #896 = Integer            1181637006
   #897 = Integer            548689776
   #898 = Integer            -1932175983
   #899 = Integer            -922558900
   #900 = Integer            -1190417183
   #901 = Integer            -1149106736
   #902 = Integer            296247880
   #903 = Integer            1970579870
   #904 = Integer            -1216407114
   #905 = Integer            -525738999
   #906 = Integer            1714227617
   #907 = Integer            -1003338189
   #908 = Integer            -396747006
   #909 = Integer            166772364
   #910 = Integer            1251581989
   #911 = Integer            493813264
   #912 = Integer            448347421
   #913 = Integer            195405023
   #914 = Integer            -1584991729
   #915 = Integer            677966185
   #916 = Integer            -591930749
   #917 = Integer            1463355134
   #918 = Integer            -1578971493
   #919 = Integer            1338867538
   #920 = Integer            1343315457
   #921 = Integer            -1492745222
   #922 = Integer            -1610435132
   #923 = Integer            233230375
   #924 = Integer            -1694987225
   #925 = Integer            2000651841
   #926 = Integer            -1017099258
   #927 = Integer            1638401717
   #928 = Integer            -266896856
   #929 = Integer            -1057650976
   #930 = Integer            6314154
   #931 = Integer            819756386
   #932 = Integer            300326615
   #933 = Integer            590932579
   #934 = Integer            1405279636
   #935 = Integer            -1027467724
   #936 = Integer            -1144263082
   #937 = Integer            -1866680610
   #938 = Integer            -335774303
   #939 = Integer            -833020554
   #940 = Integer            1862657033
   #941 = Integer            1266418056
   #942 = Integer            963775037
   #943 = Integer            2089974820
   #944 = Integer            -2031914401
   #945 = Integer            1917689273
   #946 = Integer            448879540
   #947 = Integer            -744572676
   #948 = Integer            -313240200
   #949 = Integer            150775221
   #950 = Integer            -667058989
   #951 = Integer            1303187396
   #952 = Integer            508620638
   #953 = Integer            -1318983944
   #954 = Integer            -1568336679
   #955 = Integer            1817252668
   #956 = Integer            1876281319
   #957 = Integer            1457606340
   #958 = Integer            908771278
   #959 = Integer            -574175177
   #960 = Integer            -677760460
   #961 = Integer            -1838972398
   #962 = Integer            1729034894
   #963 = Integer            1080033504
   #964 = Integer            976866871
   #965 = Integer            -738527793
   #966 = Integer            -1413318857
   #967 = Integer            1522871579
   #968 = Integer            1555064734
   #969 = Integer            1336096578
   #970 = Integer            -746444992
   #971 = Integer            -1715692610
   #972 = Integer            -720269667
   #973 = Integer            -1089506539
   #974 = Integer            -701686658
   #975 = Integer            -956251013
   #976 = Integer            -1215554709
   #977 = Integer            564236357
   #978 = Integer            -1301368386
   #979 = Integer            1781952180
   #980 = Integer            1464380207
   #981 = Integer            -1131123079
   #982 = Integer            -962365742
   #983 = Integer            1699332808
   #984 = Integer            1393555694
   #985 = Integer            1183702653
   #986 = Integer            -713881059
   #987 = Integer            1288719814
   #988 = Integer            691649499
   #989 = Integer            -1447410096
   #990 = Integer            -1399511320
   #991 = Integer            -1101077756
   #992 = Integer            -1577396752
   #993 = Integer            1781354906
   #994 = Integer            1676643554
   #995 = Integer            -1702433246
   #996 = Integer            -1064713544
   #997 = Integer            1126444790
   #998 = Integer            -1524759638
   #999 = Integer            -1661808476
  #1000 = Integer            -2084544070
  #1001 = Integer            -1679201715
  #1002 = Integer            -1880812208
  #1003 = Integer            -1167828010
  #1004 = Integer            673620729
  #1005 = Integer            -1489356063
  #1006 = Integer            1269405062
  #1007 = Integer            -279616791
  #1008 = Integer            -953159725
  #1009 = Integer            -145557542
  #1010 = Integer            1057255273
  #1011 = Integer            2012875353
  #1012 = Integer            -2132498155
  #1013 = Integer            -2018474495
  #1014 = Integer            -1693849939
  #1015 = Integer            993977747
  #1016 = Integer            -376373926
  #1017 = Integer            -1640704105
  #1018 = Integer            753973209
  #1019 = Integer            36408145
  #1020 = Integer            -1764381638
  #1021 = Integer            25011837
  #1022 = Integer            -774947114
  #1023 = Integer            2088578344
  #1024 = Integer            530523599
  #1025 = Integer            -1376601957
  #1026 = Integer            1524020338
  #1027 = Integer            1518925132
  #1028 = Integer            -534139791
  #1029 = Integer            -535190042
  #1030 = Integer            1202760957
  #1031 = Integer            -309069157
  #1032 = Integer            -388774771
  #1033 = Integer            674977740
  #1034 = Integer            -120232407
  #1035 = Integer            2031300136
  #1036 = Integer            2019492241
  #1037 = Integer            -311074731
  #1038 = Integer            -141160892
  #1039 = Integer            -472686964
  #1040 = Integer            352677332
  #1041 = Integer            -1997247046
  #1042 = Integer            60907813
  #1043 = Integer            90501309
  #1044 = Integer            -1007968747
  #1045 = Integer            1016092578
  #1046 = Integer            -1759044884
  #1047 = Integer            -1455814870
  #1048 = Integer            457141659
  #1049 = Integer            509813237
  #1050 = Integer            -174299397
  #1051 = Integer            652014361
  #1052 = Integer            1966332200
  #1053 = Integer            -1319764491
  #1054 = Integer            55981186
  #1055 = Integer            -1967506245
  #1056 = Integer            676427537
  #1057 = Integer            -1039476232
  #1058 = Integer            -1412673177
  #1059 = Integer            -861040033
  #1060 = Integer            1307055953
  #1061 = Integer            942726286
  #1062 = Integer            933058658
  #1063 = Integer            -1826555503
  #1064 = Integer            -361066302
  #1065 = Integer            -79791154
  #1066 = Integer            1361170020
  #1067 = Integer            2001714738
  #1068 = Integer            -1464409218
  #1069 = Integer            -1020707514
  #1070 = Integer            1222529897
  #1071 = Integer            1679025792
  #1072 = Integer            -1565652976
  #1073 = Integer            -580013532
  #1074 = Integer            1770335741
  #1075 = Integer            151462246
  #1076 = Integer            -1281735158
  #1077 = Integer            1682292957
  #1078 = Integer            1483529935
  #1079 = Integer            471910574
  #1080 = Integer            1539241949
  #1081 = Integer            458788160
  #1082 = Integer            -858652289
  #1083 = Integer            1807016891
  #1084 = Integer            -576558466
  #1085 = Integer            978976581
  #1086 = Integer            1043663428
  #1087 = Integer            -1129001515
  #1088 = Integer            1927990952
  #1089 = Integer            -94075717
  #1090 = Integer            -1922690386
  #1091 = Integer            -1086558393
  #1092 = Integer            -761535389
  #1093 = Integer            1412390302
  #1094 = Integer            -1362987237
  #1095 = Integer            -162634896
  #1096 = Integer            1947078029
  #1097 = Integer            -413461673
  #1098 = Integer            -126740879
  #1099 = Integer            -1353482915
  #1100 = Integer            1077988104
  #1101 = Integer            1320477388
  #1102 = Integer            886195818
  #1103 = Integer            18198404
  #1104 = Integer            -508558296
  #1105 = Integer            -1785185763
  #1106 = Integer            112762804
  #1107 = Integer            -831610808
  #1108 = Integer            1866414978
  #1109 = Integer            891333506
  #1110 = Integer            18488651
  #1111 = Integer            661792760
  #1112 = Integer            1628790961
  #1113 = Integer            -409780260
  #1114 = Integer            -1153795797
  #1115 = Integer            876946877
  #1116 = Integer            -1601685023
  #1117 = Integer            1372485963
  #1118 = Integer            791857591
  #1119 = Integer            -1608533303
  #1120 = Integer            -534984578
  #1121 = Integer            -1127755274
  #1122 = Integer            -822013501
  #1123 = Integer            -1578587449
  #1124 = Integer            445679433
  #1125 = Integer            -732971622
  #1126 = Integer            -790962485
  #1127 = Integer            -720709064
  #1128 = Integer            54117162
  #1129 = Integer            -963561881
  #1130 = Integer            -1913048708
  #1131 = Integer            -525259953
  #1132 = Integer            -140617289
  #1133 = Integer            1140177722
  #1134 = Integer            -220915201
  #1135 = Integer            668550556
  #1136 = Integer            -1080614356
  #1137 = Integer            367459370
  #1138 = Integer            261225585
  #1139 = Integer            -1684794075
  #1140 = Integer            -85617823
  #1141 = Integer            -826893077
  #1142 = Integer            -1029151655
  #1143 = Integer            314222801
  #1144 = Integer            -1228863650
  #1145 = Integer            -486184436
  #1146 = Integer            282218597
  #1147 = Integer            -888953790
  #1148 = Integer            -521376242
  #1149 = Integer            379116347
  #1150 = Integer            1285071038
  #1151 = Integer            846784868
  #1152 = Integer            -1625320142
  #1153 = Integer            -523005217
  #1154 = Integer            -744475605
  #1155 = Integer            -1989021154
  #1156 = Integer            453669953
  #1157 = Integer            1268987020
  #1158 = Integer            -977374944
  #1159 = Integer            -1015663912
  #1160 = Integer            -550133875
  #1161 = Integer            -1684459730
  #1162 = Integer            -435458233
  #1163 = Integer            266596637
  #1164 = Integer            -447948204
  #1165 = Integer            517658769
  #1166 = Integer            -832407089
  #1167 = Integer            -851542417
  #1168 = Integer            370717030
  #1169 = Integer            -47440635
  #1170 = Integer            -2070949179
  #1171 = Integer            -151313767
  #1172 = Integer            -182193321
  #1173 = Integer            -1506642397
  #1174 = Integer            -1817692879
  #1175 = Integer            1456262402
  #1176 = Integer            -1393524382
  #1177 = Integer            1517677493
  #1178 = Integer            1846949527
  #1179 = Integer            -1999473716
  #1180 = Integer            -560569710
  #1181 = Integer            -2118563376
  #1182 = Integer            1280348187
  #1183 = Integer            1908823572
  #1184 = Integer            -423180355
  #1185 = Integer            846861322
  #1186 = Integer            1172426758
  #1187 = Integer            -1007518822
  #1188 = Integer            -911584259
  #1189 = Integer            1655181056
  #1190 = Integer            -1155153950
  #1191 = Integer            901632758
  #1192 = Integer            1897031941
  #1193 = Integer            -1308360158
  #1194 = Integer            -1228157060
  #1195 = Integer            -847864789
  #1196 = Integer            1393639104
  #1197 = Integer            373351379
  #1198 = Integer            950779232
  #1199 = Integer            625454576
  #1200 = Integer            -1170726756
  #1201 = Integer            -146354570
  #1202 = Integer            2007998917
  #1203 = Integer            544563296
  #1204 = Integer            -2050228658
  #1205 = Integer            -1964470824
  #1206 = Integer            2058025392
  #1207 = Integer            1291430526
  #1208 = Integer            424198748
  #1209 = Integer            50039436
  #1210 = Integer            29584100
  #1211 = Integer            -689184263
  #1212 = Integer            -1865090967
  #1213 = Integer            -1503863136
  #1214 = Integer            1057563949
  #1215 = Integer            -1039604065
  #1216 = Integer            -1219600078
  #1217 = Integer            -831004069
  #1218 = Integer            1469046755
  #1219 = Integer            985887462
  #1220 = Integer            1332899944
  #1221 = Integer            1700884034
  #1222 = Integer            1701343084
  #1223 = Integer            1684370003
  #1224 = Integer            1668446532
  #1225 = Integer            1869963892
  #1226 = Utf8               GENSALT_DEFAULT_LOG2_ROUNDS
  #1227 = Utf8               I
  #1228 = Utf8               ConstantValue
  #1229 = Integer            10
  #1230 = Utf8               BCRYPT_SALT_LEN
  #1231 = Integer            16
  #1232 = Utf8               BLOWFISH_NUM_ROUNDS
  #1233 = Utf8               Code
  #1234 = Utf8               LineNumberTable
  #1235 = Utf8               LocalVariableTable
  #1236 = Utf8               this
  #1237 = Utf8               Lext/mods/commons/crypt/BCrypt;
  #1238 = Utf8               c1
  #1239 = Utf8               c2
  #1240 = Utf8               d
  #1241 = Utf8               len
  #1242 = Utf8               rs
  #1243 = Utf8               Ljava/lang/StringBuilder;
  #1244 = Utf8               off
  #1245 = Utf8               StackMapTable
  #1246 = Utf8               Exceptions
  #1247 = Utf8               x
  #1248 = Utf8               C
  #1249 = Utf8               B
  #1250 = Utf8               c3
  #1251 = Utf8               c4
  #1252 = Utf8               o
  #1253 = Utf8               s
  #1254 = Utf8               Ljava/lang/String;
  #1255 = Utf8               maxolen
  #1256 = Utf8               slen
  #1257 = Utf8               olen
  #1258 = Utf8               ret
  #1259 = Class              #34          // "[B"
  #1260 = Utf8               n
  #1261 = Utf8               lr
  #1262 = Utf8               i
  #1263 = Utf8               l
  #1264 = Utf8               r
  #1265 = Utf8               data
  #1266 = Utf8               offp
  #1267 = Utf8               word
  #1268 = Utf8               koffp
  #1269 = Utf8               plen
  #1270 = Utf8               doffp
  #1271 = Utf8               j
  #1272 = Utf8               password
  #1273 = Utf8               salt
  #1274 = Utf8               logRounds
  #1275 = Utf8               cdata
  #1276 = Utf8               rounds
  #1277 = Utf8               clen
  #1278 = Utf8               (Ljava/lang/String;)Ljava/lang/String;
  #1279 = Utf8               bCrypt
  #1280 = Utf8               realSalt
  #1281 = Utf8               passwordb
  #1282 = Utf8               saltb
  #1283 = Utf8               hashed
  #1284 = Utf8               minor
  #1285 = Utf8               random
  #1286 = Utf8               Ljava/security/SecureRandom;
  #1287 = Utf8               rnd
  #1288 = Utf8               checkPw
  #1289 = Utf8               (Ljava/lang/String;Ljava/lang/String;)Z
  #1290 = Utf8               plainText
  #1291 = Utf8               tryPw
  #1292 = Utf8               hashedBytes
  #1293 = Utf8               tryBytes
  #1294 = Utf8               <clinit>
  #1295 = Utf8               SourceFile
  #1296 = Utf8               BCrypt.java
  #1297 = Utf8               BootstrapMethods
  #1298 = String             #1299        // \u0001\u0001
  #1299 = Utf8               \u0001\u0001
  #1300 = MethodHandle       6:#1301      // REF_invokeStatic java/lang/invoke/StringConcatFactory.makeConcatWithConstants:(Ljava/lang/invoke/MethodHandles$Lookup;Ljava/lang/String;Ljava/lang/invoke/MethodType;Ljava/lang/String;[Ljava/lang/Object;)Ljava/lang/invoke/CallSite;
  #1301 = Methodref          #1302.#1303  // java/lang/invoke/StringConcatFactory.makeConcatWithConstants:(Ljava/lang/invoke/MethodHandles$Lookup;Ljava/lang/String;Ljava/lang/invoke/MethodType;Ljava/lang/String;[Ljava/lang/Object;)Ljava/lang/invoke/CallSite;
  #1302 = Class              #1304        // java/lang/invoke/StringConcatFactory
  #1303 = NameAndType        #122:#1305   // makeConcatWithConstants:(Ljava/lang/invoke/MethodHandles$Lookup;Ljava/lang/String;Ljava/lang/invoke/MethodType;Ljava/lang/String;[Ljava/lang/Object;)Ljava/lang/invoke/CallSite;
  #1304 = Utf8               java/lang/invoke/StringConcatFactory
  #1305 = Utf8               (Ljava/lang/invoke/MethodHandles$Lookup;Ljava/lang/String;Ljava/lang/invoke/MethodType;Ljava/lang/String;[Ljava/lang/Object;)Ljava/lang/invoke/CallSite;
  #1306 = Utf8               InnerClasses
  #1307 = Class              #1308        // java/lang/invoke/MethodHandles$Lookup
  #1308 = Utf8               java/lang/invoke/MethodHandles$Lookup
  #1309 = Class              #1310        // java/lang/invoke/MethodHandles
  #1310 = Utf8               java/lang/invoke/MethodHandles
  #1311 = Utf8               Lookup
{
  public ext.mods.commons.crypt.BCrypt();
    descriptor: ()V
    flags: (0x0001) ACC_PUBLIC
    Code:
      stack=1, locals=1, args_size=1
         0: aload_0
         1: invokespecial #1                  // Method java/lang/Object."<init>":()V
         4: return
      LineNumberTable:
        line 54: 0
      LocalVariableTable:
        Start  Length  Slot  Name   Signature
            0       5     0  this   Lext/mods/commons/crypt/BCrypt;

  public byte[] cryptRaw(byte[], byte[], int, int[]);
    descriptor: ([B[BI[I)[B
    flags: (0x0001) ACC_PUBLIC
    Code:
      stack=4, locals=10, args_size=5
         0: aload         4
         2: arraylength
         3: istore        8
         5: iload_3
         6: iconst_4
         7: if_icmplt     16
        10: iload_3
        11: bipush        30
        13: if_icmple     26
        16: new           #7                  // class java/lang/IllegalArgumentException
        19: dup
        20: ldc           #78                 // String Bad number of rounds
        22: invokespecial #11                 // Method java/lang/IllegalArgumentException."<init>":(Ljava/lang/String;)V
        25: athrow
        26: iconst_1
        27: iload_3
        28: ishl
        29: istore        5
        31: aload_2
        32: arraylength
        33: bipush        16
        35: if_icmpeq     48
        38: new           #7                  // class java/lang/IllegalArgumentException
        41: dup
        42: ldc           #80                 // String Bad salt length
        44: invokespecial #11                 // Method java/lang/IllegalArgumentException."<init>":(Ljava/lang/String;)V
        47: athrow
        48: aload_0
        49: invokevirtual #82                 // Method initKey:()V
        52: aload_0
        53: aload_2
        54: aload_1
        55: invokevirtual #85                 // Method eksKey:([B[B)V
        58: iconst_0
        59: istore        6
        61: iload         6
        63: iload         5
        65: if_icmpeq     84
        68: aload_0
        69: aload_1
        70: invokevirtual #89                 // Method key:([B)V
        73: aload_0
        74: aload_2
        75: invokevirtual #89                 // Method key:([B)V
        78: iinc          6, 1
        81: goto          61
        84: iconst_0
        85: istore        6
        87: iload         6
        89: bipush        64
        91: if_icmpge     128
        94: iconst_0
        95: istore        7
        97: iload         7
        99: iload         8
       101: iconst_1
       102: ishr
       103: if_icmpge     122
       106: aload_0
       107: aload         4
       109: iload         7
       111: iconst_1
       112: ishl
       113: invokevirtual #74                 // Method encipher:([II)V
       116: iinc          7, 1
       119: goto          97
       122: iinc          6, 1
       125: goto          87
       128: iload         8
       130: iconst_4
       131: imul
       132: newarray       byte
       134: astore        9
       136: iconst_0
       137: istore        6
       139: iconst_0
       140: istore        7
       142: iload         6
       144: iload         8
       146: if_icmpge     236
       149: aload         9
       151: iload         7
       153: iinc          7, 1
       156: aload         4
       158: iload         6
       160: iaload
       161: bipush        24
       163: ishr
       164: sipush        255
       167: iand
       168: i2b
       169: bastore
       170: aload         9
       172: iload         7
       174: iinc          7, 1
       177: aload         4
       179: iload         6
       181: iaload
       182: bipush        16
       184: ishr
       185: sipush        255
       188: iand
       189: i2b
       190: bastore
       191: aload         9
       193: iload         7
       195: iinc          7, 1
       198: aload         4
       200: iload         6
       202: iaload
       203: bipush        8
       205: ishr
       206: sipush        255
       209: iand
       210: i2b
       211: bastore
       212: aload         9
       214: iload         7
       216: iinc          7, 1
       219: aload         4
       221: iload         6
       223: iaload
       224: sipush        255
       227: iand
       228: i2b
       229: bastore
       230: iinc          6, 1
       233: goto          142
       236: aload         9
       238: areturn
      LineNumberTable:
        line 1606: 0
        line 1610: 5
        line 1611: 16
        line 1613: 26
        line 1614: 31
        line 1615: 38
        line 1617: 48
        line 1618: 52
        line 1619: 58
        line 1621: 68
        line 1622: 73
        line 1619: 78
        line 1625: 84
        line 1627: 94
        line 1628: 106
        line 1627: 116
        line 1625: 122
        line 1631: 128
        line 1632: 136
        line 1634: 149
        line 1635: 170
        line 1636: 191
        line 1637: 212
        line 1632: 230
        line 1639: 236
      LocalVariableTable:
        Start  Length  Slot  Name   Signature
           97      31     7     j   I
            0     239     0  this   Lext/mods/commons/crypt/BCrypt;
            0     239     1 password   [B
            0     239     2  salt   [B
            0     239     3 logRounds   I
            0     239     4 cdata   [I
           31     208     5 rounds   I
           61     178     6     i   I
          142      97     7     j   I
            5     234     8  clen   I
          136     103     9   ret   [B
      StackMapTable: number_of_entries = 11
        frame_type = 255 /* full_frame */
          offset_delta = 16
          locals = [ class ext/mods/commons/crypt/BCrypt, class "[B", class "[B", int, class "[I", top, top, top, int ]
          stack = []
        frame_type = 9 /* same */
        frame_type = 255 /* full_frame */
          offset_delta = 21
          locals = [ class ext/mods/commons/crypt/BCrypt, class "[B", class "[B", int, class "[I", int, top, top, int ]
          stack = []
        frame_type = 255 /* full_frame */
          offset_delta = 12
          locals = [ class ext/mods/commons/crypt/BCrypt, class "[B", class "[B", int, class "[I", int, int, top, int ]
          stack = []
        frame_type = 22 /* same */
        frame_type = 2 /* same */
        frame_type = 255 /* full_frame */
          offset_delta = 9
          locals = [ class ext/mods/commons/crypt/BCrypt, class "[B", class "[B", int, class "[I", int, int, int, int ]
          stack = []
        frame_type = 24 /* same */
        frame_type = 255 /* full_frame */
          offset_delta = 5
          locals = [ class ext/mods/commons/crypt/BCrypt, class "[B", class "[B", int, class "[I", int, int, top, int ]
          stack = []
        frame_type = 255 /* full_frame */
          offset_delta = 13
          locals = [ class ext/mods/commons/crypt/BCrypt, class "[B", class "[B", int, class "[I", int, int, int, int, class "[B" ]
          stack = []
        frame_type = 251 /* same_frame_extended */
          offset_delta = 93

  public static java.lang.String hashPw(java.lang.String);
    descriptor: (Ljava/lang/String;)Ljava/lang/String;
    flags: (0x0009) ACC_PUBLIC, ACC_STATIC
    Code:
      stack=2, locals=1, args_size=1
         0: aload_0
         1: invokestatic  #93                 // Method generateSalt:()Ljava/lang/String;
         4: invokestatic  #96                 // Method hashPw:(Ljava/lang/String;Ljava/lang/String;)Ljava/lang/String;
         7: areturn
      LineNumberTable:
        line 1649: 0
      LocalVariableTable:
        Start  Length  Slot  Name   Signature
            0       8     0 password   Ljava/lang/String;

  public static java.lang.String hashPw(java.lang.String, java.lang.String);
    descriptor: (Ljava/lang/String;Ljava/lang/String;)Ljava/lang/String;
    flags: (0x0009) ACC_PUBLIC, ACC_STATIC
    Code:
      stack=5, locals=11, args_size=2
         0: iconst_0
         1: istore        7
         3: iconst_0
         4: istore        9
         6: new           #14                 // class java/lang/StringBuilder
         9: dup
        10: invokespecial #16                 // Method java/lang/StringBuilder."<init>":()V
        13: astore        10
        15: aload_1
        16: iconst_0
        17: invokevirtual #43                 // Method java/lang/String.charAt:(I)C
        20: bipush        36
        22: if_icmpne     35
        25: aload_1
        26: iconst_1
        27: invokevirtual #43                 // Method java/lang/String.charAt:(I)C
        30: bipush        50
        32: if_icmpeq     45
        35: new           #7                  // class java/lang/IllegalArgumentException
        38: dup
        39: ldc           #100                // String Invalid salt version
        41: invokespecial #11                 // Method java/lang/IllegalArgumentException."<init>":(Ljava/lang/String;)V
        44: athrow
        45: aload_1
        46: iconst_2
        47: invokevirtual #43                 // Method java/lang/String.charAt:(I)C
        50: bipush        36
        52: if_icmpne     61
        55: iconst_3
        56: istore        9
        58: goto          98
        61: aload_1
        62: iconst_2
        63: invokevirtual #43                 // Method java/lang/String.charAt:(I)C
        66: istore        7
        68: iload         7
        70: bipush        97
        72: if_icmpne     85
        75: aload_1
        76: iconst_3
        77: invokevirtual #43                 // Method java/lang/String.charAt:(I)C
        80: bipush        36
        82: if_icmpeq     95
        85: new           #7                  // class java/lang/IllegalArgumentException
        88: dup
        89: ldc           #102                // String Invalid salt revision
        91: invokespecial #11                 // Method java/lang/IllegalArgumentException."<init>":(Ljava/lang/String;)V
        94: athrow
        95: iconst_4
        96: istore        9
        98: aload_1
        99: iload         9
       101: iconst_2
       102: iadd
       103: invokevirtual #43                 // Method java/lang/String.charAt:(I)C
       106: bipush        36
       108: if_icmple     121
       111: new           #7                  // class java/lang/IllegalArgumentException
       114: dup
       115: ldc           #104                // String Missing salt rounds
       117: invokespecial #11                 // Method java/lang/IllegalArgumentException."<init>":(Ljava/lang/String;)V
       120: athrow
       121: aload_1
       122: iload         9
       124: iload         9
       126: iconst_2
       127: iadd
       128: invokevirtual #106                // Method java/lang/String.substring:(II)Ljava/lang/String;
       131: invokestatic  #110                // Method java/lang/Integer.parseInt:(Ljava/lang/String;)I
       134: istore        8
       136: aload_1
       137: iload         9
       139: iconst_3
       140: iadd
       141: iload         9
       143: bipush        25
       145: iadd
       146: invokevirtual #106                // Method java/lang/String.substring:(II)Ljava/lang/String;
       149: astore_3
       150: aload_0
       151: iload         7
       153: bipush        97
       155: if_icmplt     163
       158: ldc           #116                // String \u0000
       160: goto          165
       163: ldc           #118                // String
       165: invokedynamic #120,  0            // InvokeDynamic #0:makeConcatWithConstants:(Ljava/lang/String;Ljava/lang/String;)Ljava/lang/String;
       170: getstatic     #123                // Field java/nio/charset/StandardCharsets.UTF_8:Ljava/nio/charset/Charset;
       173: invokevirtual #129                // Method java/lang/String.getBytes:(Ljava/nio/charset/Charset;)[B
       176: astore        4
       178: aload_3
       179: bipush        16
       181: invokestatic  #133                // Method decodeBase64:(Ljava/lang/String;I)[B
       184: astore        5
       186: new           #18                 // class ext/mods/commons/crypt/BCrypt
       189: dup
       190: invokespecial #137                // Method "<init>":()V
       193: astore_2
       194: aload_2
       195: aload         4
       197: aload         5
       199: iload         8
       201: getstatic     #138                // Field BF_CRYPT_CIPHERTEXT:[I
       204: invokevirtual #62                 // Method "[I".clone:()Ljava/lang/Object;
       207: checkcast     #63                 // class "[I"
       210: invokevirtual #141                // Method cryptRaw:([B[BI[I)[B
       213: astore        6
       215: aload         10
       217: ldc           #145                // String $2
       219: invokevirtual #147                // Method java/lang/StringBuilder.append:(Ljava/lang/String;)Ljava/lang/StringBuilder;
       222: pop
       223: iload         7
       225: bipush        97
       227: if_icmplt     238
       230: aload         10
       232: iload         7
       234: invokevirtual #23                 // Method java/lang/StringBuilder.append:(C)Ljava/lang/StringBuilder;
       237: pop
       238: aload         10
       240: ldc           #150                // String $
       242: invokevirtual #147                // Method java/lang/StringBuilder.append:(Ljava/lang/String;)Ljava/lang/StringBuilder;
       245: pop
       246: iload         8
       248: bipush        10
       250: if_icmpge     261
       253: aload         10
       255: ldc           #152                // String 0
       257: invokevirtual #147                // Method java/lang/StringBuilder.append:(Ljava/lang/String;)Ljava/lang/StringBuilder;
       260: pop
       261: iload         8
       263: bipush        30
       265: if_icmple     278
       268: new           #7                  // class java/lang/IllegalArgumentException
       271: dup
       272: ldc           #154                // String rounds exceeds maximum (30)
       274: invokespecial #11                 // Method java/lang/IllegalArgumentException."<init>":(Ljava/lang/String;)V
       277: athrow
       278: aload         10
       280: iload         8
       282: invokestatic  #156                // Method java/lang/Integer.toString:(I)Ljava/lang/String;
       285: invokevirtual #147                // Method java/lang/StringBuilder.append:(Ljava/lang/String;)Ljava/lang/StringBuilder;
       288: pop
       289: aload         10
       291: ldc           #150                // String $
       293: invokevirtual #147                // Method java/lang/StringBuilder.append:(Ljava/lang/String;)Ljava/lang/StringBuilder;
       296: pop
       297: aload         10
       299: aload         5
       301: aload         5
       303: arraylength
       304: invokestatic  #159                // Method encodeBase64:([BI)Ljava/lang/String;
       307: invokevirtual #147                // Method java/lang/StringBuilder.append:(Ljava/lang/String;)Ljava/lang/StringBuilder;
       310: pop
       311: aload         10
       313: aload         6
       315: getstatic     #138                // Field BF_CRYPT_CIPHERTEXT:[I
       318: arraylength
       319: iconst_4
       320: imul
       321: iconst_1
       322: isub
       323: invokestatic  #159                // Method encodeBase64:([BI)Ljava/lang/String;
       326: invokevirtual #147                // Method java/lang/StringBuilder.append:(Ljava/lang/String;)Ljava/lang/StringBuilder;
       329: pop
       330: aload         10
       332: invokevirtual #27                 // Method java/lang/StringBuilder.toString:()Ljava/lang/String;
       335: areturn
      LineNumberTable:
        line 1667: 0
        line 1670: 3
        line 1672: 6
        line 1674: 15
        line 1675: 35
        line 1677: 45
        line 1678: 55
        line 1681: 61
        line 1682: 68
        line 1683: 85
        line 1685: 95
        line 1688: 98
        line 1689: 111
        line 1691: 121
        line 1693: 136
        line 1694: 150
        line 1696: 178
        line 1698: 186
        line 1699: 194
        line 1701: 215
        line 1703: 223
        line 1704: 230
        line 1706: 238
        line 1708: 246
        line 1709: 253
        line 1711: 261
        line 1712: 268
        line 1714: 278
        line 1715: 289
        line 1716: 297
        line 1717: 311
        line 1718: 330
      LocalVariableTable:
        Start  Length  Slot  Name   Signature
            0     336     0 password   Ljava/lang/String;
            0     336     1  salt   Ljava/lang/String;
          194     142     2 bCrypt   Lext/mods/commons/crypt/BCrypt;
          150     186     3 realSalt   Ljava/lang/String;
          178     158     4 passwordb   [B
          186     150     5 saltb   [B
          215     121     6 hashed   [B
            3     333     7 minor   C
          136     200     8 rounds   I
            6     330     9   off   I
           15     321    10    rs   Ljava/lang/StringBuilder;
      StackMapTable: number_of_entries = 12
        frame_type = 255 /* full_frame */
          offset_delta = 35
          locals = [ class java/lang/String, class java/lang/String, top, top, top, top, top, int, top, int, class java/lang/StringBuilder ]
          stack = []
        frame_type = 9 /* same */
        frame_type = 15 /* same */
        frame_type = 23 /* same */
        frame_type = 9 /* same */
        frame_type = 2 /* same */
        frame_type = 22 /* same */
        frame_type = 255 /* full_frame */
          offset_delta = 41
          locals = [ class java/lang/String, class java/lang/String, top, class java/lang/String, top, top, top, int, int, int, class java/lang/StringBuilder ]
          stack = [ class java/lang/String ]
        frame_type = 255 /* full_frame */
          offset_delta = 1
          locals = [ class java/lang/String, class java/lang/String, top, class java/lang/String, top, top, top, int, int, int, class java/lang/StringBuilder ]
          stack = [ class java/lang/String, class java/lang/String ]
        frame_type = 255 /* full_frame */
          offset_delta = 72
          locals = [ class java/lang/String, class java/lang/String, class ext/mods/commons/crypt/BCrypt, class java/lang/String, class "[B", class "[B", class "[B", int, int, int, class java/lang/StringBuilder ]
          stack = []
        frame_type = 22 /* same */
        frame_type = 16 /* same */

  public static java.lang.String generateSalt(int, java.security.SecureRandom);
    descriptor: (ILjava/security/SecureRandom;)Ljava/lang/String;
    flags: (0x0009) ACC_PUBLIC, ACC_STATIC
    Code:
      stack=3, locals=4, args_size=2
         0: bipush        16
         2: newarray       byte
         4: astore_2
         5: aload_1
         6: aload_2
         7: invokevirtual #163                // Method java/security/SecureRandom.nextBytes:([B)V
        10: new           #14                 // class java/lang/StringBuilder
        13: dup
        14: invokespecial #16                 // Method java/lang/StringBuilder."<init>":()V
        17: astore_3
        18: aload_3
        19: ldc           #168                // String $2a$
        21: invokevirtual #147                // Method java/lang/StringBuilder.append:(Ljava/lang/String;)Ljava/lang/StringBuilder;
        24: pop
        25: iload_0
        26: bipush        10
        28: if_icmpge     38
        31: aload_3
        32: ldc           #152                // String 0
        34: invokevirtual #147                // Method java/lang/StringBuilder.append:(Ljava/lang/String;)Ljava/lang/StringBuilder;
        37: pop
        38: iload_0
        39: bipush        30
        41: if_icmple     54
        44: new           #7                  // class java/lang/IllegalArgumentException
        47: dup
        48: ldc           #170                // String log_rounds exceeds maximum (30)
        50: invokespecial #11                 // Method java/lang/IllegalArgumentException."<init>":(Ljava/lang/String;)V
        53: athrow
        54: aload_3
        55: iload_0
        56: invokestatic  #156                // Method java/lang/Integer.toString:(I)Ljava/lang/String;
        59: invokevirtual #147                // Method java/lang/StringBuilder.append:(Ljava/lang/String;)Ljava/lang/StringBuilder;
        62: pop
        63: aload_3
        64: ldc           #150                // String $
        66: invokevirtual #147                // Method java/lang/StringBuilder.append:(Ljava/lang/String;)Ljava/lang/StringBuilder;
        69: pop
        70: aload_3
        71: aload_2
        72: aload_2
        73: arraylength
        74: invokestatic  #159                // Method encodeBase64:([BI)Ljava/lang/String;
        77: invokevirtual #147                // Method java/lang/StringBuilder.append:(Ljava/lang/String;)Ljava/lang/StringBuilder;
        80: pop
        81: aload_3
        82: invokevirtual #27                 // Method java/lang/StringBuilder.toString:()Ljava/lang/String;
        85: areturn
      LineNumberTable:
        line 1729: 0
        line 1731: 5
        line 1733: 10
        line 1734: 18
        line 1736: 25
        line 1737: 31
        line 1739: 38
        line 1740: 44
        line 1742: 54
        line 1743: 63
        line 1744: 70
        line 1745: 81
      LocalVariableTable:
        Start  Length  Slot  Name   Signature
            0      86     0 logRounds   I
            0      86     1 random   Ljava/security/SecureRandom;
            5      81     2   rnd   [B
           18      68     3    rs   Ljava/lang/StringBuilder;
      StackMapTable: number_of_entries = 2
        frame_type = 253 /* append */
          offset_delta = 38
          locals = [ class "[B", class java/lang/StringBuilder ]
        frame_type = 15 /* same */

  public static java.lang.String generateSalt(int);
    descriptor: (I)Ljava/lang/String;
    flags: (0x0009) ACC_PUBLIC, ACC_STATIC
    Code:
      stack=3, locals=1, args_size=1
         0: iload_0
         1: new           #164                // class java/security/SecureRandom
         4: dup
         5: invokespecial #172                // Method java/security/SecureRandom."<init>":()V
         8: invokestatic  #173                // Method generateSalt:(ILjava/security/SecureRandom;)Ljava/lang/String;
        11: areturn
      LineNumberTable:
        line 1755: 0
      LocalVariableTable:
        Start  Length  Slot  Name   Signature
            0      12     0 logRounds   I

  public static java.lang.String generateSalt();
    descriptor: ()Ljava/lang/String;
    flags: (0x0009) ACC_PUBLIC, ACC_STATIC
    Code:
      stack=1, locals=0, args_size=0
         0: bipush        10
         2: invokestatic  #176                // Method generateSalt:(I)Ljava/lang/String;
         5: areturn
      LineNumberTable:
        line 1764: 0

  public static boolean checkPw(java.lang.String, java.lang.String);
    descriptor: (Ljava/lang/String;Ljava/lang/String;)Z
    flags: (0x0009) ACC_PUBLIC, ACC_STATIC
    Code:
      stack=4, locals=7, args_size=2
         0: aload_0
         1: aload_1
         2: invokestatic  #96                 // Method hashPw:(Ljava/lang/String;Ljava/lang/String;)Ljava/lang/String;
         5: astore_2
         6: aload_1
         7: getstatic     #123                // Field java/nio/charset/StandardCharsets.UTF_8:Ljava/nio/charset/Charset;
        10: invokevirtual #129                // Method java/lang/String.getBytes:(Ljava/nio/charset/Charset;)[B
        13: astore_3
        14: aload_2
        15: getstatic     #123                // Field java/nio/charset/StandardCharsets.UTF_8:Ljava/nio/charset/Charset;
        18: invokevirtual #129                // Method java/lang/String.getBytes:(Ljava/nio/charset/Charset;)[B
        21: astore        4
        23: aload_3
        24: arraylength
        25: aload         4
        27: arraylength
        28: if_icmpeq     33
        31: iconst_0
        32: ireturn
        33: iconst_0
        34: istore        5
        36: iconst_0
        37: istore        6
        39: iload         6
        41: aload         4
        43: arraylength
        44: if_icmpge     69
        47: iload         5
        49: aload_3
        50: iload         6
        52: baload
        53: aload         4
        55: iload         6
        57: baload
        58: ixor
        59: ior
        60: i2b
        61: istore        5
        63: iinc          6, 1
        66: goto          39
        69: iload         5
        71: ifne          78
        74: iconst_1
        75: goto          79
        78: iconst_0
        79: ireturn
      LineNumberTable:
        line 1775: 0
        line 1776: 6
        line 1777: 14
        line 1779: 23
        line 1780: 31
        line 1782: 33
        line 1783: 36
        line 1784: 47
        line 1783: 63
        line 1786: 69
      LocalVariableTable:
        Start  Length  Slot  Name   Signature
           39      30     6     i   I
            0      80     0 plainText   Ljava/lang/String;
            0      80     1 hashed   Ljava/lang/String;
            6      74     2 tryPw   Ljava/lang/String;
           14      66     3 hashedBytes   [B
           23      57     4 tryBytes   [B
           36      44     5   ret   B
      StackMapTable: number_of_entries = 5
        frame_type = 254 /* append */
          offset_delta = 33
          locals = [ class java/lang/String, class "[B", class "[B" ]
        frame_type = 253 /* append */
          offset_delta = 5
          locals = [ int, int ]
        frame_type = 250 /* chop */
          offset_delta = 29
        frame_type = 8 /* same */
        frame_type = 64 /* same_locals_1_stack_item */
          stack = [ int ]

  static {};
    descriptor: ()V
    flags: (0x0008) ACC_STATIC
    Code:
      stack=4, locals=0, args_size=0
         0: bipush        18
         2: newarray       int
         4: dup
         5: iconst_0
         6: ldc           #178                // int 608135816
         8: iastore
         9: dup
        10: iconst_1
        11: ldc           #179                // int -2052912941
        13: iastore
        14: dup
        15: iconst_2
        16: ldc           #180                // int 320440878
        18: iastore
        19: dup
        20: iconst_3
        21: ldc           #181                // int 57701188
        23: iastore
        24: dup
        25: iconst_4
        26: ldc           #182                // int -1542899678
        28: iastore
        29: dup
        30: iconst_5
        31: ldc           #183                // int 698298832
        33: iastore
        34: dup
        35: bipush        6
        37: ldc           #184                // int 137296536
        39: iastore
        40: dup
        41: bipush        7
        43: ldc           #185                // int -330404727
        45: iastore
        46: dup
        47: bipush        8
        49: ldc           #186                // int 1160258022
        51: iastore
        52: dup
        53: bipush        9
        55: ldc           #187                // int 953160567
        57: iastore
        58: dup
        59: bipush        10
        61: ldc           #188                // int -1101764913
        63: iastore
        64: dup
        65: bipush        11
        67: ldc           #189                // int 887688300
        69: iastore
        70: dup
        71: bipush        12
        73: ldc           #190                // int -1062458953
        75: iastore
        76: dup
        77: bipush        13
        79: ldc           #191                // int -914599715
        81: iastore
        82: dup
        83: bipush        14
        85: ldc           #192                // int 1065670069
        87: iastore
        88: dup
        89: bipush        15
        91: ldc           #193                // int -1253635817
        93: iastore
        94: dup
        95: bipush        16
        97: ldc           #194                // int -1843997223
        99: iastore
       100: dup
       101: bipush        17
       103: ldc           #195                // int -1988494565
       105: iastore
       106: putstatic     #59                 // Field P_ORIG:[I
       109: sipush        1024
       112: newarray       int
       114: dup
       115: iconst_0
       116: ldc           #196                // int -785314906
       118: iastore
       119: dup
       120: iconst_1
       121: ldc           #197                // int -1730169428
       123: iastore
       124: dup
       125: iconst_2
       126: ldc           #198                // int 805139163
       128: iastore
       129: dup
       130: iconst_3
       131: ldc           #199                // int -803545161
       133: iastore
       134: dup
       135: iconst_4
       136: ldc           #200                // int -1193168915
       138: iastore
       139: dup
       140: iconst_5
       141: ldc           #201                // int 1780907670
       143: iastore
       144: dup
       145: bipush        6
       147: ldc           #202                // int -1166241723
       149: iastore
       150: dup
       151: bipush        7
       153: ldc           #203                // int -248741991
       155: iastore
       156: dup
       157: bipush        8
       159: ldc           #204                // int 614570311
       161: iastore
       162: dup
       163: bipush        9
       165: ldc           #205                // int -1282315017
       167: iastore
       168: dup
       169: bipush        10
       171: ldc           #206                // int 134345442
       173: iastore
       174: dup
       175: bipush        11
       177: ldc           #207                // int -2054226922
       179: iastore
       180: dup
       181: bipush        12
       183: ldc           #208                // int 1667834072
       185: iastore
       186: dup
       187: bipush        13
       189: ldc           #209                // int 1901547113
       191: iastore
       192: dup
       193: bipush        14
       195: ldc           #210                // int -1537671517
       197: iastore
       198: dup
       199: bipush        15
       201: ldc           #211                // int -191677058
       203: iastore
       204: dup
       205: bipush        16
       207: ldc           #212                // int 227898511
       209: iastore
       210: dup
       211: bipush        17
       213: ldc           #213                // int 1921955416
       215: iastore
       216: dup
       217: bipush        18
       219: ldc           #214                // int 1904987480
       221: iastore
       222: dup
       223: bipush        19
       225: ldc           #215                // int -2112533778
       227: iastore
       228: dup
       229: bipush        20
       231: ldc           #216                // int 2069144605
       233: iastore
       234: dup
       235: bipush        21
       237: ldc           #217                // int -1034266187
       239: iastore
       240: dup
       241: bipush        22
       243: ldc           #218                // int -1674521287
       245: iastore
       246: dup
       247: bipush        23
       249: ldc           #219                // int 720527379
       251: iastore
       252: dup
       253: bipush        24
       255: ldc           #220                // int -976113629
       257: iastore
       258: dup
       259: bipush        25
       261: ldc           #221                // int 677414384
       263: iastore
       264: dup
       265: bipush        26
       267: ldc           #222                // int -901678824
       269: iastore
       270: dup
       271: bipush        27
       273: ldc           #223                // int -1193592593
       275: iastore
       276: dup
       277: bipush        28
       279: ldc           #224                // int -1904616272
       281: iastore
       282: dup
       283: bipush        29
       285: ldc           #225                // int 1614419982
       287: iastore
       288: dup
       289: bipush        30
       291: ldc           #226                // int 1822297739
       293: iastore
       294: dup
       295: bipush        31
       297: ldc           #227                // int -1340175810
       299: iastore
       300: dup
       301: bipush        32
       303: ldc           #228                // int -686458943
       305: iastore
       306: dup
       307: bipush        33
       309: ldc           #229                // int -1120842969
       311: iastore
       312: dup
       313: bipush        34
       315: ldc           #230                // int 2024746970
       317: iastore
       318: dup
       319: bipush        35
       321: ldc           #231                // int 1432378464
       323: iastore
       324: dup
       325: bipush        36
       327: ldc           #232                // int -430627341
       329: iastore
       330: dup
       331: bipush        37
       333: ldc           #233                // int -1437226092
       335: iastore
       336: dup
       337: bipush        38
       339: ldc           #234                // int 1464375394
       341: iastore
       342: dup
       343: bipush        39
       345: ldc           #235                // int 1676153920
       347: iastore
       348: dup
       349: bipush        40
       351: ldc           #236                // int 1439316330
       353: iastore
       354: dup
       355: bipush        41
       357: ldc           #237                // int 715854006
       359: iastore
       360: dup
       361: bipush        42
       363: ldc           #238                // int -1261675468
       365: iastore
       366: dup
       367: bipush        43
       369: ldc           #239                // int 289532110
       371: iastore
       372: dup
       373: bipush        44
       375: ldc           #240                // int -1588296017
       377: iastore
       378: dup
       379: bipush        45
       381: ldc           #241                // int 2087905683
       383: iastore
       384: dup
       385: bipush        46
       387: ldc           #242                // int -1276242927
       389: iastore
       390: dup
       391: bipush        47
       393: ldc           #243                // int 1668267050
       395: iastore
       396: dup
       397: bipush        48
       399: ldc           #244                // int 732546397
       401: iastore
       402: dup
       403: bipush        49
       405: ldc           #245                // int 1947742710
       407: iastore
       408: dup
       409: bipush        50
       411: ldc           #246                // int -832815594
       413: iastore
       414: dup
       415: bipush        51
       417: ldc           #247                // int -1685613794
       419: iastore
       420: dup
       421: bipush        52
       423: ldc           #248                // int -1344882125
       425: iastore
       426: dup
       427: bipush        53
       429: ldc           #249                // int 1814351708
       431: iastore
       432: dup
       433: bipush        54
       435: ldc           #250                // int 2050118529
       437: iastore
       438: dup
       439: bipush        55
       441: ldc           #251                // int 680887927
       443: iastore
       444: dup
       445: bipush        56
       447: ldc           #252                // int 999245976
       449: iastore
       450: dup
       451: bipush        57
       453: ldc           #253                // int 1800124847
       455: iastore
       456: dup
       457: bipush        58
       459: ldc           #254                // int -994056165
       461: iastore
       462: dup
       463: bipush        59
       465: ldc           #255                // int 1713906067
       467: iastore
       468: dup
       469: bipush        60
       471: ldc_w         #256                // int 1641548236
       474: iastore
       475: dup
       476: bipush        61
       478: ldc_w         #257                // int -81679983
       481: iastore
       482: dup
       483: bipush        62
       485: ldc_w         #258                // int 1216130144
       488: iastore
       489: dup
       490: bipush        63
       492: ldc_w         #259                // int 1575780402
       495: iastore
       496: dup
       497: bipush        64
       499: ldc_w         #260                // int -276538019
       502: iastore
       503: dup
       504: bipush        65
       506: ldc_w         #261                // int -377129551
       509: iastore
       510: dup
       511: bipush        66
       513: ldc_w         #262                // int -601480446
       516: iastore
       517: dup
       518: bipush        67
       520: ldc_w         #263                // int -345695352
       523: iastore
       524: dup
       525: bipush        68
       527: ldc_w         #264                // int 596196993
       530: iastore
       531: dup
       532: bipush        69
       534: ldc_w         #265                // int -745100091
       537: iastore
       538: dup
       539: bipush        70
       541: ldc_w         #266                // int 258830323
       544: iastore
       545: dup
       546: bipush        71
       548: ldc_w         #267                // int -2081144263
       551: iastore
       552: dup
       553: bipush        72
       555: ldc_w         #268                // int 772490370
       558: iastore
       559: dup
       560: bipush        73
       562: ldc_w         #269                // int -1534844924
       565: iastore
       566: dup
       567: bipush        74
       569: ldc_w         #270                // int 1774776394
       572: iastore
       573: dup
       574: bipush        75
       576: ldc_w         #271                // int -1642095778
       579: iastore
       580: dup
       581: bipush        76
       583: ldc_w         #272                // int 566650946
       586: iastore
       587: dup
       588: bipush        77
       590: ldc_w         #273                // int -152474470
       593: iastore
       594: dup
       595: bipush        78
       597: ldc_w         #274                // int 1728879713
       600: iastore
       601: dup
       602: bipush        79
       604: ldc_w         #275                // int -1412200208
       607: iastore
       608: dup
       609: bipush        80
       611: ldc_w         #276                // int 1783734482
       614: iastore
       615: dup
       616: bipush        81
       618: ldc_w         #277                // int -665571480
       621: iastore
       622: dup
       623: bipush        82
       625: ldc_w         #278                // int -1777359064
       628: iastore
       629: dup
       630: bipush        83
       632: ldc_w         #279                // int -1420741725
       635: iastore
       636: dup
       637: bipush        84
       639: ldc_w         #280                // int 1861159788
       642: iastore
       643: dup
       644: bipush        85
       646: ldc_w         #281                // int 326777828
       649: iastore
       650: dup
       651: bipush        86
       653: ldc_w         #282                // int -1170476976
       656: iastore
       657: dup
       658: bipush        87
       660: ldc_w         #283                // int 2130389656
       663: iastore
       664: dup
       665: bipush        88
       667: ldc_w         #284                // int -1578015459
       670: iastore
       671: dup
       672: bipush        89
       674: ldc_w         #285                // int 967770486
       677: iastore
       678: dup
       679: bipush        90
       681: ldc_w         #286                // int 1724537150
       684: iastore
       685: dup
       686: bipush        91
       688: ldc_w         #287                // int -2109534584
       691: iastore
       692: dup
       693: bipush        92
       695: ldc_w         #288                // int -1930525159
       698: iastore
       699: dup
       700: bipush        93
       702: ldc_w         #289                // int 1164943284
       705: iastore
       706: dup
       707: bipush        94
       709: ldc_w         #290                // int 2105845187
       712: iastore
       713: dup
       714: bipush        95
       716: ldc_w         #291                // int 998989502
       719: iastore
       720: dup
       721: bipush        96
       723: ldc_w         #292                // int -529566248
       726: iastore
       727: dup
       728: bipush        97
       730: ldc_w         #293                // int -2050940813
       733: iastore
       734: dup
       735: bipush        98
       737: ldc_w         #294                // int 1075463327
       740: iastore
       741: dup
       742: bipush        99
       744: ldc_w         #295                // int 1455516326
       747: iastore
       748: dup
       749: bipush        100
       751: ldc_w         #296                // int 1322494562
       754: iastore
       755: dup
       756: bipush        101
       758: ldc_w         #297                // int 910128902
       761: iastore
       762: dup
       763: bipush        102
       765: ldc_w         #298                // int 469688178
       768: iastore
       769: dup
       770: bipush        103
       772: ldc_w         #299                // int 1117454909
       775: iastore
       776: dup
       777: bipush        104
       779: ldc_w         #300                // int 936433444
       782: iastore
       783: dup
       784: bipush        105
       786: ldc_w         #301                // int -804646328
       789: iastore
       790: dup
       791: bipush        106
       793: ldc_w         #302                // int -619713837
       796: iastore
       797: dup
       798: bipush        107
       800: ldc_w         #303                // int 1240580251
       803: iastore
       804: dup
       805: bipush        108
       807: ldc_w         #304                // int 122909385
       810: iastore
       811: dup
       812: bipush        109
       814: ldc_w         #305                // int -2137449605
       817: iastore
       818: dup
       819: bipush        110
       821: ldc_w         #306                // int 634681816
       824: iastore
       825: dup
       826: bipush        111
       828: ldc_w         #307                // int -152510729
       831: iastore
       832: dup
       833: bipush        112
       835: ldc_w         #308                // int -469872614
       838: iastore
       839: dup
       840: bipush        113
       842: ldc_w         #309                // int -1233564613
       845: iastore
       846: dup
       847: bipush        114
       849: ldc_w         #310                // int -1754472259
       852: iastore
       853: dup
       854: bipush        115
       856: ldc_w         #311                // int 79693498
       859: iastore
       860: dup
       861: bipush        116
       863: ldc_w         #312                // int -1045868618
       866: iastore
       867: dup
       868: bipush        117
       870: ldc_w         #313                // int 1084186820
       873: iastore
       874: dup
       875: bipush        118
       877: ldc_w         #314                // int 1583128258
       880: iastore
       881: dup
       882: bipush        119
       884: ldc_w         #315                // int 426386531
       887: iastore
       888: dup
       889: bipush        120
       891: ldc_w         #316                // int 1761308591
       894: iastore
       895: dup
       896: bipush        121
       898: ldc_w         #317                // int 1047286709
       901: iastore
       902: dup
       903: bipush        122
       905: ldc_w         #318                // int 322548459
       908: iastore
       909: dup
       910: bipush        123
       912: ldc_w         #319                // int 995290223
       915: iastore
       916: dup
       917: bipush        124
       919: ldc_w         #320                // int 1845252383
       922: iastore
       923: dup
       924: bipush        125
       926: ldc_w         #321                // int -1691314900
       929: iastore
       930: dup
       931: bipush        126
       933: ldc_w         #322                // int -863943356
       936: iastore
       937: dup
       938: bipush        127
       940: ldc_w         #323                // int -1352745719
       943: iastore
       944: dup
       945: sipush        128
       948: ldc_w         #324                // int -1092366332
       951: iastore
       952: dup
       953: sipush        129
       956: ldc_w         #325                // int -567063811
       959: iastore
       960: dup
       961: sipush        130
       964: ldc_w         #326                // int 1712269319
       967: iastore
       968: dup
       969: sipush        131
       972: ldc_w         #327                // int 422464435
       975: iastore
       976: dup
       977: sipush        132
       980: ldc_w         #328                // int -1060394921
       983: iastore
       984: dup
       985: sipush        133
       988: ldc_w         #329                // int 1170764815
       991: iastore
       992: dup
       993: sipush        134
       996: ldc_w         #330                // int -771006663
       999: iastore
      1000: dup
      1001: sipush        135
      1004: ldc_w         #331                // int -1177289765
      1007: iastore
      1008: dup
      1009: sipush        136
      1012: ldc_w         #332                // int 1434042557
      1015: iastore
      1016: dup
      1017: sipush        137
      1020: ldc_w         #333                // int 442511882
      1023: iastore
      1024: dup
      1025: sipush        138
      1028: ldc_w         #334                // int -694091578
      1031: iastore
      1032: dup
      1033: sipush        139
      1036: ldc_w         #335                // int 1076654713
      1039: iastore
      1040: dup
      1041: sipush        140
      1044: ldc_w         #336                // int 1738483198
      1047: iastore
      1048: dup
      1049: sipush        141
      1052: ldc_w         #337                // int -81812532
      1055: iastore
      1056: dup
      1057: sipush        142
      1060: ldc_w         #338                // int -1901729288
      1063: iastore
      1064: dup
      1065: sipush        143
      1068: ldc_w         #339                // int -617471240
      1071: iastore
      1072: dup
      1073: sipush        144
      1076: ldc_w         #340                // int 1014306527
      1079: iastore
      1080: dup
      1081: sipush        145
      1084: ldc_w         #341                // int -43947243
      1087: iastore
      1088: dup
      1089: sipush        146
      1092: ldc_w         #342                // int 793779912
      1095: iastore
      1096: dup
      1097: sipush        147
      1100: ldc_w         #343                // int -1392160085
      1103: iastore
      1104: dup
      1105: sipush        148
      1108: ldc_w         #344                // int 842905082
      1111: iastore
      1112: dup
      1113: sipush        149
      1116: ldc_w         #345                // int -48003232
      1119: iastore
      1120: dup
      1121: sipush        150
      1124: ldc_w         #346                // int 1395751752
      1127: iastore
      1128: dup
      1129: sipush        151
      1132: ldc_w         #347                // int 1040244610
      1135: iastore
      1136: dup
      1137: sipush        152
      1140: ldc_w         #348                // int -1638115397
      1143: iastore
      1144: dup
      1145: sipush        153
      1148: ldc_w         #349                // int -898659168
      1151: iastore
      1152: dup
      1153: sipush        154
      1156: ldc_w         #350                // int 445077038
      1159: iastore
      1160: dup
      1161: sipush        155
      1164: ldc_w         #351                // int -552113701
      1167: iastore
      1168: dup
      1169: sipush        156
      1172: ldc_w         #352                // int -717051658
      1175: iastore
      1176: dup
      1177: sipush        157
      1180: ldc_w         #353                // int 679411651
      1183: iastore
      1184: dup
      1185: sipush        158
      1188: ldc_w         #354                // int -1402522938
      1191: iastore
      1192: dup
      1193: sipush        159
      1196: ldc_w         #355                // int -1940957837
      1199: iastore
      1200: dup
      1201: sipush        160
      1204: ldc_w         #356                // int 1767581616
      1207: iastore
      1208: dup
      1209: sipush        161
      1212: ldc_w         #357                // int -1144366904
      1215: iastore
      1216: dup
      1217: sipush        162
      1220: ldc_w         #358                // int -503340195
      1223: iastore
      1224: dup
      1225: sipush        163
      1228: ldc_w         #359                // int -1192226400
      1231: iastore
      1232: dup
      1233: sipush        164
      1236: ldc_w         #360                // int 284835224
      1239: iastore
      1240: dup
      1241: sipush        165
      1244: ldc_w         #361                // int -48135240
      1247: iastore
      1248: dup
      1249: sipush        166
      1252: ldc_w         #362                // int 1258075500
      1255: iastore
      1256: dup
      1257: sipush        167
      1260: ldc_w         #363                // int 768725851
      1263: iastore
      1264: dup
      1265: sipush        168
      1268: ldc_w         #364                // int -1705778055
      1271: iastore
      1272: dup
      1273: sipush        169
      1276: ldc_w         #365                // int -1225243291
      1279: iastore
      1280: dup
      1281: sipush        170
      1284: ldc_w         #366                // int -762426948
      1287: iastore
      1288: dup
      1289: sipush        171
      1292: ldc_w         #367                // int 1274779536
      1295: iastore
      1296: dup
      1297: sipush        172
      1300: ldc_w         #368                // int -505548070
      1303: iastore
      1304: dup
      1305: sipush        173
      1308: ldc_w         #369                // int -1530167757
      1311: iastore
      1312: dup
      1313: sipush        174
      1316: ldc_w         #370                // int 1660621633
      1319: iastore
      1320: dup
      1321: sipush        175
      1324: ldc_w         #371                // int -823867672
      1327: iastore
      1328: dup
      1329: sipush        176
      1332: ldc_w         #372                // int -283063590
      1335: iastore
      1336: dup
      1337: sipush        177
      1340: ldc_w         #373                // int 913787905
      1343: iastore
      1344: dup
      1345: sipush        178
      1348: ldc_w         #374                // int -797008130
      1351: iastore
      1352: dup
      1353: sipush        179
      1356: ldc_w         #375                // int 737222580
      1359: iastore
      1360: dup
      1361: sipush        180
      1364: ldc_w         #376                // int -1780753843
      1367: iastore
      1368: dup
      1369: sipush        181
      1372: ldc_w         #377                // int -1366257256
      1375: iastore
      1376: dup
      1377: sipush        182
      1380: ldc_w         #378                // int -357724559
      1383: iastore
      1384: dup
      1385: sipush        183
      1388: ldc_w         #379                // int 1804850592
      1391: iastore
      1392: dup
      1393: sipush        184
      1396: ldc_w         #380                // int -795946544
      1399: iastore
      1400: dup
      1401: sipush        185
      1404: ldc_w         #381                // int -1345903136
      1407: iastore
      1408: dup
      1409: sipush        186
      1412: ldc_w         #382                // int -1908647121
      1415: iastore
      1416: dup
      1417: sipush        187
      1420: ldc_w         #383                // int -1904896841
      1423: iastore
      1424: dup
      1425: sipush        188
      1428: ldc_w         #384                // int -1879645445
      1431: iastore
      1432: dup
      1433: sipush        189
      1436: ldc_w         #385                // int -233690268
      1439: iastore
      1440: dup
      1441: sipush        190
      1444: ldc_w         #386                // int -2004305902
      1447: iastore
      1448: dup
      1449: sipush        191
      1452: ldc_w         #387                // int -1878134756
      1455: iastore
      1456: dup
      1457: sipush        192
      1460: ldc_w         #388                // int 1336762016
      1463: iastore
      1464: dup
      1465: sipush        193
      1468: ldc_w         #389                // int 1754252060
      1471: iastore
      1472: dup
      1473: sipush        194
      1476: ldc_w         #390                // int -774901359
      1479: iastore
      1480: dup
      1481: sipush        195
      1484: ldc_w         #391                // int -1280786003
      1487: iastore
      1488: dup
      1489: sipush        196
      1492: ldc_w         #392                // int 791618072
      1495: iastore
      1496: dup
      1497: sipush        197
      1500: ldc_w         #393                // int -1106372745
      1503: iastore
      1504: dup
      1505: sipush        198
      1508: ldc_w         #394                // int -361419266
      1511: iastore
      1512: dup
      1513: sipush        199
      1516: ldc_w         #395                // int -1962795103
      1519: iastore
      1520: dup
      1521: sipush        200
      1524: ldc_w         #396                // int -442446833
      1527: iastore
      1528: dup
      1529: sipush        201
      1532: ldc_w         #397                // int -1250986776
      1535: iastore
      1536: dup
      1537: sipush        202
      1540: ldc_w         #398                // int 413987798
      1543: iastore
      1544: dup
      1545: sipush        203
      1548: ldc_w         #399                // int -829824359
      1551: iastore
      1552: dup
      1553: sipush        204
      1556: ldc_w         #400                // int -1264037920
      1559: iastore
      1560: dup
      1561: sipush        205
      1564: ldc_w         #401                // int -49028937
      1567: iastore
      1568: dup
      1569: sipush        206
      1572: ldc_w         #402                // int 2093235073
      1575: iastore
      1576: dup
      1577: sipush        207
      1580: ldc_w         #403                // int -760370983
      1583: iastore
      1584: dup
      1585: sipush        208
      1588: ldc_w         #404                // int 375366246
      1591: iastore
      1592: dup
      1593: sipush        209
      1596: ldc_w         #405                // int -2137688315
      1599: iastore
      1600: dup
      1601: sipush        210
      1604: ldc_w         #406                // int -1815317740
      1607: iastore
      1608: dup
      1609: sipush        211
      1612: ldc_w         #407                // int 555357303
      1615: iastore
      1616: dup
      1617: sipush        212
      1620: ldc_w         #408                // int -424861595
      1623: iastore
      1624: dup
      1625: sipush        213
      1628: ldc_w         #409                // int 2008414854
      1631: iastore
      1632: dup
      1633: sipush        214
      1636: ldc_w         #410                // int -950779147
      1639: iastore
      1640: dup
      1641: sipush        215
      1644: ldc_w         #411                // int -73583153
      1647: iastore
      1648: dup
      1649: sipush        216
      1652: ldc_w         #412                // int -338841844
      1655: iastore
      1656: dup
      1657: sipush        217
      1660: ldc_w         #413                // int 2067696032
      1663: iastore
      1664: dup
      1665: sipush        218
      1668: ldc_w         #414                // int -700376109
      1671: iastore
      1672: dup
      1673: sipush        219
      1676: ldc_w         #415                // int -1373733303
      1679: iastore
      1680: dup
      1681: sipush        220
      1684: ldc_w         #416                // int 2428461
      1687: iastore
      1688: dup
      1689: sipush        221
      1692: ldc_w         #417                // int 544322398
      1695: iastore
      1696: dup
      1697: sipush        222
      1700: ldc_w         #418                // int 577241275
      1703: iastore
      1704: dup
      1705: sipush        223
      1708: ldc_w         #419                // int 1471733935
      1711: iastore
      1712: dup
      1713: sipush        224
      1716: ldc_w         #420                // int 610547355
      1719: iastore
      1720: dup
      1721: sipush        225
      1724: ldc_w         #421                // int -267798242
      1727: iastore
      1728: dup
      1729: sipush        226
      1732: ldc_w         #422                // int 1432588573
      1735: iastore
      1736: dup
      1737: sipush        227
      1740: ldc_w         #423                // int 1507829418
      1743: iastore
      1744: dup
      1745: sipush        228
      1748: ldc_w         #424                // int 2025931657
      1751: iastore
      1752: dup
      1753: sipush        229
      1756: ldc_w         #425                // int -648391809
      1759: iastore
      1760: dup
      1761: sipush        230
      1764: ldc_w         #426                // int 545086370
      1767: iastore
      1768: dup
      1769: sipush        231
      1772: ldc_w         #427                // int 48609733
      1775: iastore
      1776: dup
      1777: sipush        232
      1780: ldc_w         #428                // int -2094660746
      1783: iastore
      1784: dup
      1785: sipush        233
      1788: ldc_w         #429                // int 1653985193
      1791: iastore
      1792: dup
      1793: sipush        234
      1796: ldc_w         #430                // int 298326376
      1799: iastore
      1800: dup
      1801: sipush        235
      1804: ldc_w         #431                // int 1316178497
      1807: iastore
      1808: dup
      1809: sipush        236
      1812: ldc_w         #432                // int -1287180854
      1815: iastore
      1816: dup
      1817: sipush        237
      1820: ldc_w         #433                // int 2064951626
      1823: iastore
      1824: dup
      1825: sipush        238
      1828: ldc_w         #434                // int 458293330
      1831: iastore
      1832: dup
      1833: sipush        239
      1836: ldc_w         #435                // int -1705826027
      1839: iastore
      1840: dup
      1841: sipush        240
      1844: ldc_w         #436                // int -703637697
      1847: iastore
      1848: dup
      1849: sipush        241
      1852: ldc_w         #437                // int -1130641692
      1855: iastore
      1856: dup
      1857: sipush        242
      1860: ldc_w         #438                // int 727753846
      1863: iastore
      1864: dup
      1865: sipush        243
      1868: ldc_w         #439                // int -2115603456
      1871: iastore
      1872: dup
      1873: sipush        244
      1876: ldc_w         #440                // int 146436021
      1879: iastore
      1880: dup
      1881: sipush        245
      1884: ldc_w         #441                // int 1461446943
      1887: iastore
      1888: dup
      1889: sipush        246
      1892: ldc_w         #442                // int -224990101
      1895: iastore
      1896: dup
      1897: sipush        247
      1900: ldc_w         #443                // int 705550613
      1903: iastore
      1904: dup
      1905: sipush        248
      1908: ldc_w         #444                // int -1235000031
      1911: iastore
      1912: dup
      1913: sipush        249
      1916: ldc_w         #445                // int -407242314
      1919: iastore
      1920: dup
      1921: sipush        250
      1924: ldc_w         #446                // int -13368018
      1927: iastore
      1928: dup
      1929: sipush        251
      1932: ldc_w         #447                // int -981117340
      1935: iastore
      1936: dup
      1937: sipush        252
      1940: ldc_w         #448                // int 1404054877
      1943: iastore
      1944: dup
      1945: sipush        253
      1948: ldc_w         #449                // int -1449160799
      1951: iastore
      1952: dup
      1953: sipush        254
      1956: ldc_w         #450                // int 146425753
      1959: iastore
      1960: dup
      1961: sipush        255
      1964: ldc_w         #451                // int 1854211946
      1967: iastore
      1968: dup
      1969: sipush        256
      1972: ldc_w         #452                // int 1266315497
      1975: iastore
      1976: dup
      1977: sipush        257
      1980: ldc_w         #453                // int -1246549692
      1983: iastore
      1984: dup
      1985: sipush        258
      1988: ldc_w         #454                // int -613086930
      1991: iastore
      1992: dup
      1993: sipush        259
      1996: ldc_w         #455                // int -1004984797
      1999: iastore
      2000: dup
      2001: sipush        260
      2004: ldc_w         #456                // int -1385257296
      2007: iastore
      2008: dup
      2009: sipush        261
      2012: ldc_w         #457                // int 1235738493
      2015: iastore
      2016: dup
      2017: sipush        262
      2020: ldc_w         #458                // int -1662099272
      2023: iastore
      2024: dup
      2025: sipush        263
      2028: ldc_w         #459                // int -1880247706
      2031: iastore
      2032: dup
      2033: sipush        264
      2036: ldc_w         #460                // int -324367247
      2039: iastore
      2040: dup
      2041: sipush        265
      2044: ldc_w         #461                // int 1771706367
      2047: iastore
      2048: dup
      2049: sipush        266
      2052: ldc_w         #462                // int 1449415276
      2055: iastore
      2056: dup
      2057: sipush        267
      2060: ldc_w         #463                // int -1028546847
      2063: iastore
      2064: dup
      2065: sipush        268
      2068: ldc_w         #464                // int 422970021
      2071: iastore
      2072: dup
      2073: sipush        269
      2076: ldc_w         #465                // int 1963543593
      2079: iastore
      2080: dup
      2081: sipush        270
      2084: ldc_w         #466                // int -1604775104
      2087: iastore
      2088: dup
      2089: sipush        271
      2092: ldc_w         #467                // int -468174274
      2095: iastore
      2096: dup
      2097: sipush        272
      2100: ldc_w         #468                // int 1062508698
      2103: iastore
      2104: dup
      2105: sipush        273
      2108: ldc_w         #469                // int 1531092325
      2111: iastore
      2112: dup
      2113: sipush        274
      2116: ldc_w         #470                // int 1804592342
      2119: iastore
      2120: dup
      2121: sipush        275
      2124: ldc_w         #471                // int -1711849514
      2127: iastore
      2128: dup
      2129: sipush        276
      2132: ldc_w         #472                // int -1580033017
      2135: iastore
      2136: dup
      2137: sipush        277
      2140: ldc_w         #473                // int -269995787
      2143: iastore
      2144: dup
      2145: sipush        278
      2148: ldc_w         #474                // int 1294809318
      2151: iastore
      2152: dup
      2153: sipush        279
      2156: ldc_w         #475                // int -265986623
      2159: iastore
      2160: dup
      2161: sipush        280
      2164: ldc_w         #476                // int 1289560198
      2167: iastore
      2168: dup
      2169: sipush        281
      2172: ldc_w         #477                // int -2072974554
      2175: iastore
      2176: dup
      2177: sipush        282
      2180: ldc_w         #478                // int 1669523910
      2183: iastore
      2184: dup
      2185: sipush        283
      2188: ldc_w         #479                // int 35572830
      2191: iastore
      2192: dup
      2193: sipush        284
      2196: ldc_w         #480                // int 157838143
      2199: iastore
      2200: dup
      2201: sipush        285
      2204: ldc_w         #481                // int 1052438473
      2207: iastore
      2208: dup
      2209: sipush        286
      2212: ldc_w         #482                // int 1016535060
      2215: iastore
      2216: dup
      2217: sipush        287
      2220: ldc_w         #483                // int 1802137761
      2223: iastore
      2224: dup
      2225: sipush        288
      2228: ldc_w         #484                // int 1753167236
      2231: iastore
      2232: dup
      2233: sipush        289
      2236: ldc_w         #485                // int 1386275462
      2239: iastore
      2240: dup
      2241: sipush        290
      2244: ldc_w         #486                // int -1214491899
      2247: iastore
      2248: dup
      2249: sipush        291
      2252: ldc_w         #487                // int -1437595849
      2255: iastore
      2256: dup
      2257: sipush        292
      2260: ldc_w         #488                // int 1040679964
      2263: iastore
      2264: dup
      2265: sipush        293
      2268: ldc_w         #489                // int 2145300060
      2271: iastore
      2272: dup
      2273: sipush        294
      2276: ldc_w         #490                // int -1904392980
      2279: iastore
      2280: dup
      2281: sipush        295
      2284: ldc_w         #491                // int 1461121720
      2287: iastore
      2288: dup
      2289: sipush        296
      2292: ldc_w         #492                // int -1338320329
      2295: iastore
      2296: dup
      2297: sipush        297
      2300: ldc_w         #493                // int -263189491
      2303: iastore
      2304: dup
      2305: sipush        298
      2308: ldc_w         #494                // int -266592508
      2311: iastore
      2312: dup
      2313: sipush        299
      2316: ldc_w         #495                // int 33600511
      2319: iastore
      2320: dup
      2321: sipush        300
      2324: ldc_w         #496                // int -1374882534
      2327: iastore
      2328: dup
      2329: sipush        301
      2332: ldc_w         #497                // int 1018524850
      2335: iastore
      2336: dup
      2337: sipush        302
      2340: ldc_w         #498                // int 629373528
      2343: iastore
      2344: dup
      2345: sipush        303
      2348: ldc_w         #499                // int -603381315
      2351: iastore
      2352: dup
      2353: sipush        304
      2356: ldc_w         #500                // int -779021319
      2359: iastore
      2360: dup
      2361: sipush        305
      2364: ldc_w         #501                // int 2091462646
      2367: iastore
      2368: dup
      2369: sipush        306
      2372: ldc_w         #502                // int -1808644237
      2375: iastore
      2376: dup
      2377: sipush        307
      2380: ldc_w         #503                // int 586499841
      2383: iastore
      2384: dup
      2385: sipush        308
      2388: ldc_w         #504                // int 988145025
      2391: iastore
      2392: dup
      2393: sipush        309
      2396: ldc_w         #505                // int 935516892
      2399: iastore
      2400: dup
      2401: sipush        310
      2404: ldc_w         #506                // int -927631820
      2407: iastore
      2408: dup
      2409: sipush        311
      2412: ldc_w         #507                // int -1695294041
      2415: iastore
      2416: dup
      2417: sipush        312
      2420: ldc_w         #508                // int -1455136442
      2423: iastore
      2424: dup
      2425: sipush        313
      2428: ldc_w         #509                // int 265290510
      2431: iastore
      2432: dup
      2433: sipush        314
      2436: ldc_w         #510                // int -322386114
      2439: iastore
      2440: dup
      2441: sipush        315
      2444: ldc_w         #511                // int -1535828415
      2447: iastore
      2448: dup
      2449: sipush        316
      2452: ldc_w         #512                // int -499593831
      2455: iastore
      2456: dup
      2457: sipush        317
      2460: ldc_w         #513                // int 1005194799
      2463: iastore
      2464: dup
      2465: sipush        318
      2468: ldc_w         #514                // int 847297441
      2471: iastore
      2472: dup
      2473: sipush        319
      2476: ldc_w         #515                // int 406762289
      2479: iastore
      2480: dup
      2481: sipush        320
      2484: ldc_w         #516                // int 1314163512
      2487: iastore
      2488: dup
      2489: sipush        321
      2492: ldc_w         #517                // int 1332590856
      2495: iastore
      2496: dup
      2497: sipush        322
      2500: ldc_w         #518                // int 1866599683
      2503: iastore
      2504: dup
      2505: sipush        323
      2508: ldc_w         #519                // int -167115585
      2511: iastore
      2512: dup
      2513: sipush        324
      2516: ldc_w         #520                // int 750260880
      2519: iastore
      2520: dup
      2521: sipush        325
      2524: ldc_w         #521                // int 613907577
      2527: iastore
      2528: dup
      2529: sipush        326
      2532: ldc_w         #522                // int 1450815602
      2535: iastore
      2536: dup
      2537: sipush        327
      2540: ldc_w         #523                // int -1129346641
      2543: iastore
      2544: dup
      2545: sipush        328
      2548: ldc_w         #524                // int -560302305
      2551: iastore
      2552: dup
      2553: sipush        329
      2556: ldc_w         #525                // int -644675568
      2559: iastore
      2560: dup
      2561: sipush        330
      2564: ldc_w         #526                // int -1282691566
      2567: iastore
      2568: dup
      2569: sipush        331
      2572: ldc_w         #527                // int -590397650
      2575: iastore
      2576: dup
      2577: sipush        332
      2580: ldc_w         #528                // int 1427272223
      2583: iastore
      2584: dup
      2585: sipush        333
      2588: ldc_w         #529                // int 778793252
      2591: iastore
      2592: dup
      2593: sipush        334
      2596: ldc_w         #530                // int 1343938022
      2599: iastore
      2600: dup
      2601: sipush        335
      2604: ldc_w         #531                // int -1618686585
      2607: iastore
      2608: dup
      2609: sipush        336
      2612: ldc_w         #532                // int 2052605720
      2615: iastore
      2616: dup
      2617: sipush        337
      2620: ldc_w         #533                // int 1946737175
      2623: iastore
      2624: dup
      2625: sipush        338
      2628: ldc_w         #534                // int -1130390852
      2631: iastore
      2632: dup
      2633: sipush        339
      2636: ldc_w         #535                // int -380928628
      2639: iastore
      2640: dup
      2641: sipush        340
      2644: ldc_w         #536                // int -327488454
      2647: iastore
      2648: dup
      2649: sipush        341
      2652: ldc_w         #537                // int -612033030
      2655: iastore
      2656: dup
      2657: sipush        342
      2660: ldc_w         #538                // int 1661551462
      2663: iastore
      2664: dup
      2665: sipush        343
      2668: ldc_w         #539                // int -1000029230
      2671: iastore
      2672: dup
      2673: sipush        344
      2676: ldc_w         #540                // int -283371449
      2679: iastore
      2680: dup
      2681: sipush        345
      2684: ldc_w         #541                // int 840292616
      2687: iastore
      2688: dup
      2689: sipush        346
      2692: ldc_w         #542                // int -582796489
      2695: iastore
      2696: dup
      2697: sipush        347
      2700: ldc_w         #543                // int 616741398
      2703: iastore
      2704: dup
      2705: sipush        348
      2708: ldc_w         #544                // int 312560963
      2711: iastore
      2712: dup
      2713: sipush        349
      2716: ldc_w         #545                // int 711312465
      2719: iastore
      2720: dup
      2721: sipush        350
      2724: ldc_w         #546                // int 1351876610
      2727: iastore
      2728: dup
      2729: sipush        351
      2732: ldc_w         #547                // int 322626781
      2735: iastore
      2736: dup
      2737: sipush        352
      2740: ldc_w         #548                // int 1910503582
      2743: iastore
      2744: dup
      2745: sipush        353
      2748: ldc_w         #549                // int 271666773
      2751: iastore
      2752: dup
      2753: sipush        354
      2756: ldc_w         #550                // int -2119403562
      2759: iastore
      2760: dup
      2761: sipush        355
      2764: ldc_w         #551                // int 1594956187
      2767: iastore
      2768: dup
      2769: sipush        356
      2772: ldc_w         #552                // int 70604529
      2775: iastore
      2776: dup
      2777: sipush        357
      2780: ldc_w         #553                // int -677132437
      2783: iastore
      2784: dup
      2785: sipush        358
      2788: ldc_w         #554                // int 1007753275
      2791: iastore
      2792: dup
      2793: sipush        359
      2796: ldc_w         #555                // int 1495573769
      2799: iastore
      2800: dup
      2801: sipush        360
      2804: ldc_w         #556                // int -225450259
      2807: iastore
      2808: dup
      2809: sipush        361
      2812: ldc_w         #557                // int -1745748998
      2815: iastore
      2816: dup
      2817: sipush        362
      2820: ldc_w         #558                // int -1631928532
      2823: iastore
      2824: dup
      2825: sipush        363
      2828: ldc_w         #559                // int 504708206
      2831: iastore
      2832: dup
      2833: sipush        364
      2836: ldc_w         #560                // int -2031925904
      2839: iastore
      2840: dup
      2841: sipush        365
      2844: ldc_w         #561                // int -353800271
      2847: iastore
      2848: dup
      2849: sipush        366
      2852: ldc_w         #562                // int -2045878774
      2855: iastore
      2856: dup
      2857: sipush        367
      2860: ldc_w         #563                // int 1514023603
      2863: iastore
      2864: dup
      2865: sipush        368
      2868: ldc_w         #564                // int 1998579484
      2871: iastore
      2872: dup
      2873: sipush        369
      2876: ldc_w         #565                // int 1312622330
      2879: iastore
      2880: dup
      2881: sipush        370
      2884: ldc_w         #566                // int 694541497
      2887: iastore
      2888: dup
      2889: sipush        371
      2892: ldc_w         #567                // int -1712906993
      2895: iastore
      2896: dup
      2897: sipush        372
      2900: ldc_w         #568                // int -2143385130
      2903: iastore
      2904: dup
      2905: sipush        373
      2908: ldc_w         #569                // int 1382467621
      2911: iastore
      2912: dup
      2913: sipush        374
      2916: ldc_w         #570                // int 776784248
      2919: iastore
      2920: dup
      2921: sipush        375
      2924: ldc_w         #571                // int -1676627094
      2927: iastore
      2928: dup
      2929: sipush        376
      2932: ldc_w         #572                // int -971698502
      2935: iastore
      2936: dup
      2937: sipush        377
      2940: ldc_w         #573                // int -1797068168
      2943: iastore
      2944: dup
      2945: sipush        378
      2948: ldc_w         #574                // int -1510196141
      2951: iastore
      2952: dup
      2953: sipush        379
      2956: ldc_w         #575                // int 503983604
      2959: iastore
      2960: dup
      2961: sipush        380
      2964: ldc_w         #576                // int -218673497
      2967: iastore
      2968: dup
      2969: sipush        381
      2972: ldc_w         #577                // int 907881277
      2975: iastore
      2976: dup
      2977: sipush        382
      2980: ldc_w         #578                // int 423175695
      2983: iastore
      2984: dup
      2985: sipush        383
      2988: ldc_w         #579                // int 432175456
      2991: iastore
      2992: dup
      2993: sipush        384
      2996: ldc_w         #580                // int 1378068232
      2999: iastore
      3000: dup
      3001: sipush        385
      3004: ldc_w         #581                // int -149744970
      3007: iastore
      3008: dup
      3009: sipush        386
      3012: ldc_w         #582                // int -340918674
      3015: iastore
      3016: dup
      3017: sipush        387
      3020: ldc_w         #583                // int -356311194
      3023: iastore
      3024: dup
      3025: sipush        388
      3028: ldc_w         #584                // int -474200683
      3031: iastore
      3032: dup
      3033: sipush        389
      3036: ldc_w         #585                // int -1501837181
      3039: iastore
      3040: dup
      3041: sipush        390
      3044: ldc_w         #586                // int -1317062703
      3047: iastore
      3048: dup
      3049: sipush        391
      3052: ldc_w         #587                // int 26017576
      3055: iastore
      3056: dup
      3057: sipush        392
      3060: ldc_w         #588                // int -1020076561
      3063: iastore
      3064: dup
      3065: sipush        393
      3068: ldc_w         #589                // int -1100195163
      3071: iastore
      3072: dup
      3073: sipush        394
      3076: ldc_w         #590                // int 1700274565
      3079: iastore
      3080: dup
      3081: sipush        395
      3084: ldc_w         #591                // int 1756076034
      3087: iastore
      3088: dup
      3089: sipush        396
      3092: ldc_w         #592                // int -288447217
      3095: iastore
      3096: dup
      3097: sipush        397
      3100: ldc_w         #593                // int -617638597
      3103: iastore
      3104: dup
      3105: sipush        398
      3108: ldc_w         #594                // int 720338349
      3111: iastore
      3112: dup
      3113: sipush        399
      3116: ldc_w         #595                // int 1533947780
      3119: iastore
      3120: dup
      3121: sipush        400
      3124: ldc_w         #596                // int 354530856
      3127: iastore
      3128: dup
      3129: sipush        401
      3132: ldc_w         #597                // int 688349552
      3135: iastore
      3136: dup
      3137: sipush        402
      3140: ldc_w         #598                // int -321042571
      3143: iastore
      3144: dup
      3145: sipush        403
      3148: ldc_w         #599                // int 1637815568
      3151: iastore
      3152: dup
      3153: sipush        404
      3156: ldc_w         #600                // int 332179504
      3159: iastore
      3160: dup
      3161: sipush        405
      3164: ldc_w         #601                // int -345916010
      3167: iastore
      3168: dup
      3169: sipush        406
      3172: ldc_w         #602                // int 53804574
      3175: iastore
      3176: dup
      3177: sipush        407
      3180: ldc_w         #603                // int -1442618417
      3183: iastore
      3184: dup
      3185: sipush        408
      3188: ldc_w         #604                // int -1250730864
      3191: iastore
      3192: dup
      3193: sipush        409
      3196: ldc_w         #605                // int 1282449977
      3199: iastore
      3200: dup
      3201: sipush        410
      3204: ldc_w         #606                // int -711025141
      3207: iastore
      3208: dup
      3209: sipush        411
      3212: ldc_w         #607                // int -877994476
      3215: iastore
      3216: dup
      3217: sipush        412
      3220: ldc_w         #608                // int -288586052
      3223: iastore
      3224: dup
      3225: sipush        413
      3228: ldc_w         #609                // int 1617046695
      3231: iastore
      3232: dup
      3233: sipush        414
      3236: ldc_w         #610                // int -1666491221
      3239: iastore
      3240: dup
      3241: sipush        415
      3244: ldc_w         #611                // int -1292663698
      3247: iastore
      3248: dup
      3249: sipush        416
      3252: ldc_w         #612                // int 1686838959
      3255: iastore
      3256: dup
      3257: sipush        417
      3260: ldc_w         #613                // int 431878346
      3263: iastore
      3264: dup
      3265: sipush        418
      3268: ldc_w         #614                // int -1608291911
      3271: iastore
      3272: dup
      3273: sipush        419
      3276: ldc_w         #615                // int 1700445008
      3279: iastore
      3280: dup
      3281: sipush        420
      3284: ldc_w         #616                // int 1080580658
      3287: iastore
      3288: dup
      3289: sipush        421
      3292: ldc_w         #617                // int 1009431731
      3295: iastore
      3296: dup
      3297: sipush        422
      3300: ldc_w         #618                // int 832498133
      3303: iastore
      3304: dup
      3305: sipush        423
      3308: ldc_w         #619                // int -1071531785
      3311: iastore
      3312: dup
      3313: sipush        424
      3316: ldc_w         #620                // int -1688990951
      3319: iastore
      3320: dup
      3321: sipush        425
      3324: ldc_w         #621                // int -2023776103
      3327: iastore
      3328: dup
      3329: sipush        426
      3332: ldc_w         #622                // int -1778935426
      3335: iastore
      3336: dup
      3337: sipush        427
      3340: ldc_w         #623                // int 1648197032
      3343: iastore
      3344: dup
      3345: sipush        428
      3348: ldc_w         #624                // int -130578278
      3351: iastore
      3352: dup
      3353: sipush        429
      3356: ldc_w         #625                // int -1746719369
      3359: iastore
      3360: dup
      3361: sipush        430
      3364: ldc_w         #626                // int 300782431
      3367: iastore
      3368: dup
      3369: sipush        431
      3372: ldc_w         #627                // int 375919233
      3375: iastore
      3376: dup
      3377: sipush        432
      3380: ldc_w         #628                // int 238389289
      3383: iastore
      3384: dup
      3385: sipush        433
      3388: ldc_w         #629                // int -941219882
      3391: iastore
      3392: dup
      3393: sipush        434
      3396: ldc_w         #630                // int -1763778655
      3399: iastore
      3400: dup
      3401: sipush        435
      3404: ldc_w         #631                // int 2019080857
      3407: iastore
      3408: dup
      3409: sipush        436
      3412: ldc_w         #632                // int 1475708069
      3415: iastore
      3416: dup
      3417: sipush        437
      3420: ldc_w         #633                // int 455242339
      3423: iastore
      3424: dup
      3425: sipush        438
      3428: ldc_w         #634                // int -1685863425
      3431: iastore
      3432: dup
      3433: sipush        439
      3436: ldc_w         #635                // int 448939670
      3439: iastore
      3440: dup
      3441: sipush        440
      3444: ldc_w         #636                // int -843904277
      3447: iastore
      3448: dup
      3449: sipush        441
      3452: ldc_w         #637                // int 1395535956
      3455: iastore
      3456: dup
      3457: sipush        442
      3460: ldc_w         #638                // int -1881585436
      3463: iastore
      3464: dup
      3465: sipush        443
      3468: ldc_w         #639                // int 1841049896
      3471: iastore
      3472: dup
      3473: sipush        444
      3476: ldc_w         #640                // int 1491858159
      3479: iastore
      3480: dup
      3481: sipush        445
      3484: ldc_w         #641                // int 885456874
      3487: iastore
      3488: dup
      3489: sipush        446
      3492: ldc_w         #642                // int -30872223
      3495: iastore
      3496: dup
      3497: sipush        447
      3500: ldc_w         #643                // int -293847949
      3503: iastore
      3504: dup
      3505: sipush        448
      3508: ldc_w         #644                // int 1565136089
      3511: iastore
      3512: dup
      3513: sipush        449
      3516: ldc_w         #645                // int -396052509
      3519: iastore
      3520: dup
      3521: sipush        450
      3524: ldc_w         #646                // int 1108368660
      3527: iastore
      3528: dup
      3529: sipush        451
      3532: ldc_w         #647                // int 540939232
      3535: iastore
      3536: dup
      3537: sipush        452
      3540: ldc_w         #648                // int 1173283510
      3543: iastore
      3544: dup
      3545: sipush        453
      3548: ldc_w         #649                // int -1549095958
      3551: iastore
      3552: dup
      3553: sipush        454
      3556: ldc_w         #650                // int -613658859
      3559: iastore
      3560: dup
      3561: sipush        455
      3564: ldc_w         #651                // int -87339056
      3567: iastore
      3568: dup
      3569: sipush        456
      3572: ldc_w         #652                // int -951913406
      3575: iastore
      3576: dup
      3577: sipush        457
      3580: ldc_w         #653                // int -278217803
      3583: iastore
      3584: dup
      3585: sipush        458
      3588: ldc_w         #654                // int 1699691293
      3591: iastore
      3592: dup
      3593: sipush        459
      3596: ldc_w         #655                // int 1103962373
      3599: iastore
      3600: dup
      3601: sipush        460
      3604: ldc_w         #656                // int -669091426
      3607: iastore
      3608: dup
      3609: sipush        461
      3612: ldc_w         #657                // int -2038084153
      3615: iastore
      3616: dup
      3617: sipush        462
      3620: ldc_w         #658                // int -464828566
      3623: iastore
      3624: dup
      3625: sipush        463
      3628: ldc_w         #659                // int 1031889488
      3631: iastore
      3632: dup
      3633: sipush        464
      3636: ldc_w         #660                // int -815619598
      3639: iastore
      3640: dup
      3641: sipush        465
      3644: ldc_w         #661                // int 1535977030
      3647: iastore
      3648: dup
      3649: sipush        466
      3652: ldc_w         #662                // int -58162272
      3655: iastore
      3656: dup
      3657: sipush        467
      3660: ldc_w         #663                // int -1043876189
      3663: iastore
      3664: dup
      3665: sipush        468
      3668: ldc_w         #664                // int 2132092099
      3671: iastore
      3672: dup
      3673: sipush        469
      3676: ldc_w         #665                // int 1774941330
      3679: iastore
      3680: dup
      3681: sipush        470
      3684: ldc_w         #666                // int 1199868427
      3687: iastore
      3688: dup
      3689: sipush        471
      3692: ldc_w         #667                // int 1452454533
      3695: iastore
      3696: dup
      3697: sipush        472
      3700: ldc_w         #668                // int 157007616
      3703: iastore
      3704: dup
      3705: sipush        473
      3708: ldc_w         #669                // int -1390851939
      3711: iastore
      3712: dup
      3713: sipush        474
      3716: ldc_w         #670                // int 342012276
      3719: iastore
      3720: dup
      3721: sipush        475
      3724: ldc_w         #671                // int 595725824
      3727: iastore
      3728: dup
      3729: sipush        476
      3732: ldc_w         #672                // int 1480756522
      3735: iastore
      3736: dup
      3737: sipush        477
      3740: ldc_w         #673                // int 206960106
      3743: iastore
      3744: dup
      3745: sipush        478
      3748: ldc_w         #674                // int 497939518
      3751: iastore
      3752: dup
      3753: sipush        479
      3756: ldc_w         #675                // int 591360097
      3759: iastore
      3760: dup
      3761: sipush        480
      3764: ldc_w         #676                // int 863170706
      3767: iastore
      3768: dup
      3769: sipush        481
      3772: ldc_w         #677                // int -1919713727
      3775: iastore
      3776: dup
      3777: sipush        482
      3780: ldc_w         #678                // int -698356495
      3783: iastore
      3784: dup
      3785: sipush        483
      3788: ldc_w         #679                // int 1814182875
      3791: iastore
      3792: dup
      3793: sipush        484
      3796: ldc_w         #680                // int 2094937945
      3799: iastore
      3800: dup
      3801: sipush        485
      3804: ldc_w         #681                // int -873565088
      3807: iastore
      3808: dup
      3809: sipush        486
      3812: ldc_w         #682                // int 1082520231
      3815: iastore
      3816: dup
      3817: sipush        487
      3820: ldc_w         #683                // int -831049106
      3823: iastore
      3824: dup
      3825: sipush        488
      3828: ldc_w         #684                // int -1509457788
      3831: iastore
      3832: dup
      3833: sipush        489
      3836: ldc_w         #685                // int 435703966
      3839: iastore
      3840: dup
      3841: sipush        490
      3844: ldc_w         #686                // int -386934699
      3847: iastore
      3848: dup
      3849: sipush        491
      3852: ldc_w         #687                // int 1641649973
      3855: iastore
      3856: dup
      3857: sipush        492
      3860: ldc_w         #688                // int -1452693590
      3863: iastore
      3864: dup
      3865: sipush        493
      3868: ldc_w         #689                // int -989067582
      3871: iastore
      3872: dup
      3873: sipush        494
      3876: ldc_w         #690                // int 1510255612
      3879: iastore
      3880: dup
      3881: sipush        495
      3884: ldc_w         #691                // int -2146710820
      3887: iastore
      3888: dup
      3889: sipush        496
      3892: ldc_w         #692                // int -1639679442
      3895: iastore
      3896: dup
      3897: sipush        497
      3900: ldc_w         #693                // int -1018874748
      3903: iastore
      3904: dup
      3905: sipush        498
      3908: ldc_w         #694                // int -36346107
      3911: iastore
      3912: dup
      3913: sipush        499
      3916: ldc_w         #695                // int 236887753
      3919: iastore
      3920: dup
      3921: sipush        500
      3924: ldc_w         #696                // int -613164077
      3927: iastore
      3928: dup
      3929: sipush        501
      3932: ldc_w         #697                // int 274041037
      3935: iastore
      3936: dup
      3937: sipush        502
      3940: ldc_w         #698                // int 1734335097
      3943: iastore
      3944: dup
      3945: sipush        503
      3948: ldc_w         #699                // int -479771840
      3951: iastore
      3952: dup
      3953: sipush        504
      3956: ldc_w         #700                // int -976997275
      3959: iastore
      3960: dup
      3961: sipush        505
      3964: ldc_w         #701                // int 1899903192
      3967: iastore
      3968: dup
      3969: sipush        506
      3972: ldc_w         #702                // int 1026095262
      3975: iastore
      3976: dup
      3977: sipush        507
      3980: ldc_w         #703                // int -244449504
      3983: iastore
      3984: dup
      3985: sipush        508
      3988: ldc_w         #704                // int 356393447
      3991: iastore
      3992: dup
      3993: sipush        509
      3996: ldc_w         #705                // int -1884275382
      3999: iastore
      4000: dup
      4001: sipush        510
      4004: ldc_w         #706                // int -421290197
      4007: iastore
      4008: dup
      4009: sipush        511
      4012: ldc_w         #707                // int -612127241
      4015: iastore
      4016: dup
      4017: sipush        512
      4020: ldc_w         #708                // int -381855128
      4023: iastore
      4024: dup
      4025: sipush        513
      4028: ldc_w         #709                // int -1803468553
      4031: iastore
      4032: dup
      4033: sipush        514
      4036: ldc_w         #710                // int -162781668
      4039: iastore
      4040: dup
      4041: sipush        515
      4044: ldc_w         #711                // int -1805047500
      4047: iastore
      4048: dup
      4049: sipush        516
      4052: ldc_w         #712                // int 1091903735
      4055: iastore
      4056: dup
      4057: sipush        517
      4060: ldc_w         #713                // int 1979897079
      4063: iastore
      4064: dup
      4065: sipush        518
      4068: ldc_w         #714                // int -1124832466
      4071: iastore
      4072: dup
      4073: sipush        519
      4076: ldc_w         #715                // int -727580568
      4079: iastore
      4080: dup
      4081: sipush        520
      4084: ldc_w         #716                // int -737663887
      4087: iastore
      4088: dup
      4089: sipush        521
      4092: ldc_w         #717                // int 857797738
      4095: iastore
      4096: dup
      4097: sipush        522
      4100: ldc_w         #718                // int 1136121015
      4103: iastore
      4104: dup
      4105: sipush        523
      4108: ldc_w         #719                // int 1342202287
      4111: iastore
      4112: dup
      4113: sipush        524
      4116: ldc_w         #720                // int 507115054
      4119: iastore
      4120: dup
      4121: sipush        525
      4124: ldc_w         #721                // int -1759230650
      4127: iastore
      4128: dup
      4129: sipush        526
      4132: ldc_w         #722                // int 337727348
      4135: iastore
      4136: dup
      4137: sipush        527
      4140: ldc_w         #723                // int -1081374656
      4143: iastore
      4144: dup
      4145: sipush        528
      4148: ldc_w         #724                // int 1301675037
      4151: iastore
      4152: dup
      4153: sipush        529
      4156: ldc_w         #725                // int -1766485585
      4159: iastore
      4160: dup
      4161: sipush        530
      4164: ldc_w         #726                // int 1895095763
      4167: iastore
      4168: dup
      4169: sipush        531
      4172: ldc_w         #727                // int 1721773893
      4175: iastore
      4176: dup
      4177: sipush        532
      4180: ldc_w         #728                // int -1078195732
      4183: iastore
      4184: dup
      4185: sipush        533
      4188: ldc_w         #729                // int 62756741
      4191: iastore
      4192: dup
      4193: sipush        534
      4196: ldc_w         #730                // int 2142006736
      4199: iastore
      4200: dup
      4201: sipush        535
      4204: ldc_w         #731                // int 835421444
      4207: iastore
      4208: dup
      4209: sipush        536
      4212: ldc_w         #732                // int -1762973773
      4215: iastore
      4216: dup
      4217: sipush        537
      4220: ldc_w         #733                // int 1442658625
      4223: iastore
      4224: dup
      4225: sipush        538
      4228: ldc_w         #734                // int -635090970
      4231: iastore
      4232: dup
      4233: sipush        539
      4236: ldc_w         #735                // int -1412822374
      4239: iastore
      4240: dup
      4241: sipush        540
      4244: ldc_w         #736                // int 676362277
      4247: iastore
      4248: dup
      4249: sipush        541
      4252: ldc_w         #737                // int 1392781812
      4255: iastore
      4256: dup
      4257: sipush        542
      4260: ldc_w         #738                // int 170690266
      4263: iastore
      4264: dup
      4265: sipush        543
      4268: ldc_w         #739                // int -373920261
      4271: iastore
      4272: dup
      4273: sipush        544
      4276: ldc_w         #740                // int 1759253602
      4279: iastore
      4280: dup
      4281: sipush        545
      4284: ldc_w         #741                // int -683120384
      4287: iastore
      4288: dup
      4289: sipush        546
      4292: ldc_w         #742                // int 1745797284
      4295: iastore
      4296: dup
      4297: sipush        547
      4300: ldc_w         #743                // int 664899054
      4303: iastore
      4304: dup
      4305: sipush        548
      4308: ldc_w         #744                // int 1329594018
      4311: iastore
      4312: dup
      4313: sipush        549
      4316: ldc_w         #745                // int -393761396
      4319: iastore
      4320: dup
      4321: sipush        550
      4324: ldc_w         #746                // int -1249058810
      4327: iastore
      4328: dup
      4329: sipush        551
      4332: ldc_w         #747                // int 2062866102
      4335: iastore
      4336: dup
      4337: sipush        552
      4340: ldc_w         #748                // int -1429332356
      4343: iastore
      4344: dup
      4345: sipush        553
      4348: ldc_w         #749                // int -751345684
      4351: iastore
      4352: dup
      4353: sipush        554
      4356: ldc_w         #750                // int -830954599
      4359: iastore
      4360: dup
      4361: sipush        555
      4364: ldc_w         #751                // int 1080764994
      4367: iastore
      4368: dup
      4369: sipush        556
      4372: ldc_w         #752                // int 553557557
      4375: iastore
      4376: dup
      4377: sipush        557
      4380: ldc_w         #753                // int -638351943
      4383: iastore
      4384: dup
      4385: sipush        558
      4388: ldc_w         #754                // int -298199125
      4391: iastore
      4392: dup
      4393: sipush        559
      4396: ldc_w         #755                // int 991055499
      4399: iastore
      4400: dup
      4401: sipush        560
      4404: ldc_w         #756                // int 499776247
      4407: iastore
      4408: dup
      4409: sipush        561
      4412: ldc_w         #757                // int 1265440854
      4415: iastore
      4416: dup
      4417: sipush        562
      4420: ldc_w         #758                // int 648242737
      4423: iastore
      4424: dup
      4425: sipush        563
      4428: ldc_w         #759                // int -354183246
      4431: iastore
      4432: dup
      4433: sipush        564
      4436: ldc_w         #760                // int 980351604
      4439: iastore
      4440: dup
      4441: sipush        565
      4444: ldc_w         #761                // int -581221582
      4447: iastore
      4448: dup
      4449: sipush        566
      4452: ldc_w         #762                // int 1749149687
      4455: iastore
      4456: dup
      4457: sipush        567
      4460: ldc_w         #763                // int -898096901
      4463: iastore
      4464: dup
      4465: sipush        568
      4468: ldc_w         #764                // int -83167922
      4471: iastore
      4472: dup
      4473: sipush        569
      4476: ldc_w         #765                // int -654396521
      4479: iastore
      4480: dup
      4481: sipush        570
      4484: ldc_w         #766                // int 1161844396
      4487: iastore
      4488: dup
      4489: sipush        571
      4492: ldc_w         #767                // int -1169648345
      4495: iastore
      4496: dup
      4497: sipush        572
      4500: ldc_w         #768                // int 1431517754
      4503: iastore
      4504: dup
      4505: sipush        573
      4508: ldc_w         #769                // int 545492359
      4511: iastore
      4512: dup
      4513: sipush        574
      4516: ldc_w         #770                // int -26498633
      4519: iastore
      4520: dup
      4521: sipush        575
      4524: ldc_w         #771                // int -795437749
      4527: iastore
      4528: dup
      4529: sipush        576
      4532: ldc_w         #772                // int 1437099964
      4535: iastore
      4536: dup
      4537: sipush        577
      4540: ldc_w         #773                // int -1592419752
      4543: iastore
      4544: dup
      4545: sipush        578
      4548: ldc_w         #774                // int -861329053
      4551: iastore
      4552: dup
      4553: sipush        579
      4556: ldc_w         #775                // int -1713251533
      4559: iastore
      4560: dup
      4561: sipush        580
      4564: ldc_w         #776                // int -1507177898
      4567: iastore
      4568: dup
      4569: sipush        581
      4572: ldc_w         #777                // int 1060185593
      4575: iastore
      4576: dup
      4577: sipush        582
      4580: ldc_w         #778                // int 1593081372
      4583: iastore
      4584: dup
      4585: sipush        583
      4588: ldc_w         #779                // int -1876348548
      4591: iastore
      4592: dup
      4593: sipush        584
      4596: ldc_w         #780                // int -34019326
      4599: iastore
      4600: dup
      4601: sipush        585
      4604: ldc_w         #781                // int 69676912
      4607: iastore
      4608: dup
      4609: sipush        586
      4612: ldc_w         #782                // int -2135222948
      4615: iastore
      4616: dup
      4617: sipush        587
      4620: ldc_w         #783                // int 86519011
      4623: iastore
      4624: dup
      4625: sipush        588
      4628: ldc_w         #784                // int -1782508216
      4631: iastore
      4632: dup
      4633: sipush        589
      4636: ldc_w         #785                // int -456757982
      4639: iastore
      4640: dup
      4641: sipush        590
      4644: ldc_w         #786                // int 1220612927
      4647: iastore
      4648: dup
      4649: sipush        591
      4652: ldc_w         #787                // int -955283748
      4655: iastore
      4656: dup
      4657: sipush        592
      4660: ldc_w         #788                // int 133810670
      4663: iastore
      4664: dup
      4665: sipush        593
      4668: ldc_w         #789                // int 1090789135
      4671: iastore
      4672: dup
      4673: sipush        594
      4676: ldc_w         #790                // int 1078426020
      4679: iastore
      4680: dup
      4681: sipush        595
      4684: ldc_w         #791                // int 1569222167
      4687: iastore
      4688: dup
      4689: sipush        596
      4692: ldc_w         #792                // int 845107691
      4695: iastore
      4696: dup
      4697: sipush        597
      4700: ldc_w         #793                // int -711212847
      4703: iastore
      4704: dup
      4705: sipush        598
      4708: ldc_w         #794                // int -222510705
      4711: iastore
      4712: dup
      4713: sipush        599
      4716: ldc_w         #795                // int 1091646820
      4719: iastore
      4720: dup
      4721: sipush        600
      4724: ldc_w         #796                // int 628848692
      4727: iastore
      4728: dup
      4729: sipush        601
      4732: ldc_w         #797                // int 1613405280
      4735: iastore
      4736: dup
      4737: sipush        602
      4740: ldc_w         #798                // int -537335645
      4743: iastore
      4744: dup
      4745: sipush        603
      4748: ldc_w         #799                // int 526609435
      4751: iastore
      4752: dup
      4753: sipush        604
      4756: ldc_w         #800                // int 236106946
      4759: iastore
      4760: dup
      4761: sipush        605
      4764: ldc_w         #801                // int 48312990
      4767: iastore
      4768: dup
      4769: sipush        606
      4772: ldc_w         #802                // int -1352249391
      4775: iastore
      4776: dup
      4777: sipush        607
      4780: ldc_w         #803                // int -892239595
      4783: iastore
      4784: dup
      4785: sipush        608
      4788: ldc_w         #804                // int 1797494240
      4791: iastore
      4792: dup
      4793: sipush        609
      4796: ldc_w         #805                // int 859738849
      4799: iastore
      4800: dup
      4801: sipush        610
      4804: ldc_w         #806                // int 992217954
      4807: iastore
      4808: dup
      4809: sipush        611
      4812: ldc_w         #807                // int -289490654
      4815: iastore
      4816: dup
      4817: sipush        612
      4820: ldc_w         #808                // int -2051890674
      4823: iastore
      4824: dup
      4825: sipush        613
      4828: ldc_w         #809                // int -424014439
      4831: iastore
      4832: dup
      4833: sipush        614
      4836: ldc_w         #810                // int -562951028
      4839: iastore
      4840: dup
      4841: sipush        615
      4844: ldc_w         #811                // int 765654824
      4847: iastore
      4848: dup
      4849: sipush        616
      4852: ldc_w         #812                // int -804095931
      4855: iastore
      4856: dup
      4857: sipush        617
      4860: ldc_w         #813                // int -1783130883
      4863: iastore
      4864: dup
      4865: sipush        618
      4868: ldc_w         #814                // int 1685915746
      4871: iastore
      4872: dup
      4873: sipush        619
      4876: ldc_w         #815                // int -405998096
      4879: iastore
      4880: dup
      4881: sipush        620
      4884: ldc_w         #816                // int 1414112111
      4887: iastore
      4888: dup
      4889: sipush        621
      4892: ldc_w         #817                // int -2021832454
      4895: iastore
      4896: dup
      4897: sipush        622
      4900: ldc_w         #818                // int -1013056217
      4903: iastore
      4904: dup
      4905: sipush        623
      4908: ldc_w         #819                // int -214004450
      4911: iastore
      4912: dup
      4913: sipush        624
      4916: ldc_w         #820                // int 172450625
      4919: iastore
      4920: dup
      4921: sipush        625
      4924: ldc_w         #821                // int -1724973196
      4927: iastore
      4928: dup
      4929: sipush        626
      4932: ldc_w         #822                // int 980381355
      4935: iastore
      4936: dup
      4937: sipush        627
      4940: ldc_w         #823                // int -185008841
      4943: iastore
      4944: dup
      4945: sipush        628
      4948: ldc_w         #824                // int -1475158944
      4951: iastore
      4952: dup
      4953: sipush        629
      4956: ldc_w         #825                // int -1578377736
      4959: iastore
      4960: dup
      4961: sipush        630
      4964: ldc_w         #826                // int -1726226100
      4967: iastore
      4968: dup
      4969: sipush        631
      4972: ldc_w         #827                // int -613520627
      4975: iastore
      4976: dup
      4977: sipush        632
      4980: ldc_w         #828                // int -964995824
      4983: iastore
      4984: dup
      4985: sipush        633
      4988: ldc_w         #829                // int 1835478071
      4991: iastore
      4992: dup
      4993: sipush        634
      4996: ldc_w         #830                // int 660984891
      4999: iastore
      5000: dup
      5001: sipush        635
      5004: ldc_w         #831                // int -590288892
      5007: iastore
      5008: dup
      5009: sipush        636
      5012: ldc_w         #832                // int -248967737
      5015: iastore
      5016: dup
      5017: sipush        637
      5020: ldc_w         #833                // int -872349789
      5023: iastore
      5024: dup
      5025: sipush        638
      5028: ldc_w         #834                // int -1254551662
      5031: iastore
      5032: dup
      5033: sipush        639
      5036: ldc_w         #835                // int 1762651403
      5039: iastore
      5040: dup
      5041: sipush        640
      5044: ldc_w         #836                // int 1719377915
      5047: iastore
      5048: dup
      5049: sipush        641
      5052: ldc_w         #837                // int -824476260
      5055: iastore
      5056: dup
      5057: sipush        642
      5060: ldc_w         #838                // int -1601057013
      5063: iastore
      5064: dup
      5065: sipush        643
      5068: ldc_w         #839                // int -652910941
      5071: iastore
      5072: dup
      5073: sipush        644
      5076: ldc_w         #840                // int -1156370552
      5079: iastore
      5080: dup
      5081: sipush        645
      5084: ldc_w         #841                // int 1364962596
      5087: iastore
      5088: dup
      5089: sipush        646
      5092: ldc_w         #842                // int 2073328063
      5095: iastore
      5096: dup
      5097: sipush        647
      5100: ldc_w         #843                // int 1983633131
      5103: iastore
      5104: dup
      5105: sipush        648
      5108: ldc_w         #844                // int 926494387
      5111: iastore
      5112: dup
      5113: sipush        649
      5116: ldc_w         #845                // int -871278215
      5119: iastore
      5120: dup
      5121: sipush        650
      5124: ldc_w         #846                // int -2144935273
      5127: iastore
      5128: dup
      5129: sipush        651
      5132: ldc_w         #847                // int -198299347
      5135: iastore
      5136: dup
      5137: sipush        652
      5140: ldc_w         #848                // int 1749200295
      5143: iastore
      5144: dup
      5145: sipush        653
      5148: ldc_w         #849                // int -966120645
      5151: iastore
      5152: dup
      5153: sipush        654
      5156: ldc_w         #850                // int 309677260
      5159: iastore
      5160: dup
      5161: sipush        655
      5164: ldc_w         #851                // int 2016342300
      5167: iastore
      5168: dup
      5169: sipush        656
      5172: ldc_w         #852                // int 1779581495
      5175: iastore
      5176: dup
      5177: sipush        657
      5180: ldc_w         #853                // int -1215147545
      5183: iastore
      5184: dup
      5185: sipush        658
      5188: ldc_w         #854                // int 111262694
      5191: iastore
      5192: dup
      5193: sipush        659
      5196: ldc_w         #855                // int 1274766160
      5199: iastore
      5200: dup
      5201: sipush        660
      5204: ldc_w         #856                // int 443224088
      5207: iastore
      5208: dup
      5209: sipush        661
      5212: ldc_w         #857                // int 298511866
      5215: iastore
      5216: dup
      5217: sipush        662
      5220: ldc_w         #858                // int 1025883608
      5223: iastore
      5224: dup
      5225: sipush        663
      5228: ldc_w         #859                // int -488520759
      5231: iastore
      5232: dup
      5233: sipush        664
      5236: ldc_w         #860                // int 1145181785
      5239: iastore
      5240: dup
      5241: sipush        665
      5244: ldc_w         #861                // int 168956806
      5247: iastore
      5248: dup
      5249: sipush        666
      5252: ldc_w         #862                // int -653464466
      5255: iastore
      5256: dup
      5257: sipush        667
      5260: ldc_w         #863                // int -710153686
      5263: iastore
      5264: dup
      5265: sipush        668
      5268: ldc_w         #864                // int 1689216846
      5271: iastore
      5272: dup
      5273: sipush        669
      5276: ldc_w         #865                // int -628709281
      5279: iastore
      5280: dup
      5281: sipush        670
      5284: ldc_w         #866                // int -1094719096
      5287: iastore
      5288: dup
      5289: sipush        671
      5292: ldc_w         #867                // int 1692713982
      5295: iastore
      5296: dup
      5297: sipush        672
      5300: ldc_w         #868                // int -1648590761
      5303: iastore
      5304: dup
      5305: sipush        673
      5308: ldc_w         #869                // int -252198778
      5311: iastore
      5312: dup
      5313: sipush        674
      5316: ldc_w         #870                // int 1618508792
      5319: iastore
      5320: dup
      5321: sipush        675
      5324: ldc_w         #871                // int 1610833997
      5327: iastore
      5328: dup
      5329: sipush        676
      5332: ldc_w         #872                // int -771914938
      5335: iastore
      5336: dup
      5337: sipush        677
      5340: ldc_w         #873                // int -164094032
      5343: iastore
      5344: dup
      5345: sipush        678
      5348: ldc_w         #874                // int 2001055236
      5351: iastore
      5352: dup
      5353: sipush        679
      5356: ldc_w         #875                // int -684262196
      5359: iastore
      5360: dup
      5361: sipush        680
      5364: ldc_w         #876                // int -2092799181
      5367: iastore
      5368: dup
      5369: sipush        681
      5372: ldc_w         #877                // int -266425487
      5375: iastore
      5376: dup
      5377: sipush        682
      5380: ldc_w         #878                // int -1333771897
      5383: iastore
      5384: dup
      5385: sipush        683
      5388: ldc_w         #879                // int 1006657119
      5391: iastore
      5392: dup
      5393: sipush        684
      5396: ldc_w         #880                // int 2006996926
      5399: iastore
      5400: dup
      5401: sipush        685
      5404: ldc_w         #881                // int -1108824540
      5407: iastore
      5408: dup
      5409: sipush        686
      5412: ldc_w         #882                // int 1430667929
      5415: iastore
      5416: dup
      5417: sipush        687
      5420: ldc_w         #883                // int -1084739999
      5423: iastore
      5424: dup
      5425: sipush        688
      5428: ldc_w         #884                // int 1314452623
      5431: iastore
      5432: dup
      5433: sipush        689
      5436: ldc_w         #885                // int -220332638
      5439: iastore
      5440: dup
      5441: sipush        690
      5444: ldc_w         #886                // int -193663176
      5447: iastore
      5448: dup
      5449: sipush        691
      5452: ldc_w         #887                // int -2021016126
      5455: iastore
      5456: dup
      5457: sipush        692
      5460: ldc_w         #888                // int 1399257539
      5463: iastore
      5464: dup
      5465: sipush        693
      5468: ldc_w         #889                // int -927756684
      5471: iastore
      5472: dup
      5473: sipush        694
      5476: ldc_w         #890                // int -1267338667
      5479: iastore
      5480: dup
      5481: sipush        695
      5484: ldc_w         #891                // int 1190975929
      5487: iastore
      5488: dup
      5489: sipush        696
      5492: ldc_w         #892                // int 2062231137
      5495: iastore
      5496: dup
      5497: sipush        697
      5500: ldc_w         #893                // int -1960976508
      5503: iastore
      5504: dup
      5505: sipush        698
      5508: ldc_w         #894                // int -2073424263
      5511: iastore
      5512: dup
      5513: sipush        699
      5516: ldc_w         #895                // int -1856006686
      5519: iastore
      5520: dup
      5521: sipush        700
      5524: ldc_w         #896                // int 1181637006
      5527: iastore
      5528: dup
      5529: sipush        701
      5532: ldc_w         #897                // int 548689776
      5535: iastore
      5536: dup
      5537: sipush        702
      5540: ldc_w         #898                // int -1932175983
      5543: iastore
      5544: dup
      5545: sipush        703
      5548: ldc_w         #899                // int -922558900
      5551: iastore
      5552: dup
      5553: sipush        704
      5556: ldc_w         #900                // int -1190417183
      5559: iastore
      5560: dup
      5561: sipush        705
      5564: ldc_w         #901                // int -1149106736
      5567: iastore
      5568: dup
      5569: sipush        706
      5572: ldc_w         #902                // int 296247880
      5575: iastore
      5576: dup
      5577: sipush        707
      5580: ldc_w         #903                // int 1970579870
      5583: iastore
      5584: dup
      5585: sipush        708
      5588: ldc_w         #904                // int -1216407114
      5591: iastore
      5592: dup
      5593: sipush        709
      5596: ldc_w         #905                // int -525738999
      5599: iastore
      5600: dup
      5601: sipush        710
      5604: ldc_w         #906                // int 1714227617
      5607: iastore
      5608: dup
      5609: sipush        711
      5612: ldc_w         #907                // int -1003338189
      5615: iastore
      5616: dup
      5617: sipush        712
      5620: ldc_w         #908                // int -396747006
      5623: iastore
      5624: dup
      5625: sipush        713
      5628: ldc_w         #909                // int 166772364
      5631: iastore
      5632: dup
      5633: sipush        714
      5636: ldc_w         #910                // int 1251581989
      5639: iastore
      5640: dup
      5641: sipush        715
      5644: ldc_w         #911                // int 493813264
      5647: iastore
      5648: dup
      5649: sipush        716
      5652: ldc_w         #912                // int 448347421
      5655: iastore
      5656: dup
      5657: sipush        717
      5660: ldc_w         #913                // int 195405023
      5663: iastore
      5664: dup
      5665: sipush        718
      5668: ldc_w         #914                // int -1584991729
      5671: iastore
      5672: dup
      5673: sipush        719
      5676: ldc_w         #915                // int 677966185
      5679: iastore
      5680: dup
      5681: sipush        720
      5684: ldc_w         #916                // int -591930749
      5687: iastore
      5688: dup
      5689: sipush        721
      5692: ldc_w         #917                // int 1463355134
      5695: iastore
      5696: dup
      5697: sipush        722
      5700: ldc_w         #918                // int -1578971493
      5703: iastore
      5704: dup
      5705: sipush        723
      5708: ldc_w         #919                // int 1338867538
      5711: iastore
      5712: dup
      5713: sipush        724
      5716: ldc_w         #920                // int 1343315457
      5719: iastore
      5720: dup
      5721: sipush        725
      5724: ldc_w         #921                // int -1492745222
      5727: iastore
      5728: dup
      5729: sipush        726
      5732: ldc_w         #922                // int -1610435132
      5735: iastore
      5736: dup
      5737: sipush        727
      5740: ldc_w         #923                // int 233230375
      5743: iastore
      5744: dup
      5745: sipush        728
      5748: ldc_w         #924                // int -1694987225
      5751: iastore
      5752: dup
      5753: sipush        729
      5756: ldc_w         #925                // int 2000651841
      5759: iastore
      5760: dup
      5761: sipush        730
      5764: ldc_w         #926                // int -1017099258
      5767: iastore
      5768: dup
      5769: sipush        731
      5772: ldc_w         #927                // int 1638401717
      5775: iastore
      5776: dup
      5777: sipush        732
      5780: ldc_w         #928                // int -266896856
      5783: iastore
      5784: dup
      5785: sipush        733
      5788: ldc_w         #929                // int -1057650976
      5791: iastore
      5792: dup
      5793: sipush        734
      5796: ldc_w         #930                // int 6314154
      5799: iastore
      5800: dup
      5801: sipush        735
      5804: ldc_w         #931                // int 819756386
      5807: iastore
      5808: dup
      5809: sipush        736
      5812: ldc_w         #932                // int 300326615
      5815: iastore
      5816: dup
      5817: sipush        737
      5820: ldc_w         #933                // int 590932579
      5823: iastore
      5824: dup
      5825: sipush        738
      5828: ldc_w         #934                // int 1405279636
      5831: iastore
      5832: dup
      5833: sipush        739
      5836: ldc_w         #935                // int -1027467724
      5839: iastore
      5840: dup
      5841: sipush        740
      5844: ldc_w         #936                // int -1144263082
      5847: iastore
      5848: dup
      5849: sipush        741
      5852: ldc_w         #937                // int -1866680610
      5855: iastore
      5856: dup
      5857: sipush        742
      5860: ldc_w         #938                // int -335774303
      5863: iastore
      5864: dup
      5865: sipush        743
      5868: ldc_w         #939                // int -833020554
      5871: iastore
      5872: dup
      5873: sipush        744
      5876: ldc_w         #940                // int 1862657033
      5879: iastore
      5880: dup
      5881: sipush        745
      5884: ldc_w         #941                // int 1266418056
      5887: iastore
      5888: dup
      5889: sipush        746
      5892: ldc_w         #942                // int 963775037
      5895: iastore
      5896: dup
      5897: sipush        747
      5900: ldc_w         #943                // int 2089974820
      5903: iastore
      5904: dup
      5905: sipush        748
      5908: ldc_w         #944                // int -2031914401
      5911: iastore
      5912: dup
      5913: sipush        749
      5916: ldc_w         #945                // int 1917689273
      5919: iastore
      5920: dup
      5921: sipush        750
      5924: ldc_w         #946                // int 448879540
      5927: iastore
      5928: dup
      5929: sipush        751
      5932: ldc_w         #947                // int -744572676
      5935: iastore
      5936: dup
      5937: sipush        752
      5940: ldc_w         #948                // int -313240200
      5943: iastore
      5944: dup
      5945: sipush        753
      5948: ldc_w         #949                // int 150775221
      5951: iastore
      5952: dup
      5953: sipush        754
      5956: ldc_w         #950                // int -667058989
      5959: iastore
      5960: dup
      5961: sipush        755
      5964: ldc_w         #951                // int 1303187396
      5967: iastore
      5968: dup
      5969: sipush        756
      5972: ldc_w         #952                // int 508620638
      5975: iastore
      5976: dup
      5977: sipush        757
      5980: ldc_w         #953                // int -1318983944
      5983: iastore
      5984: dup
      5985: sipush        758
      5988: ldc_w         #954                // int -1568336679
      5991: iastore
      5992: dup
      5993: sipush        759
      5996: ldc_w         #955                // int 1817252668
      5999: iastore
      6000: dup
      6001: sipush        760
      6004: ldc_w         #956                // int 1876281319
      6007: iastore
      6008: dup
      6009: sipush        761
      6012: ldc_w         #957                // int 1457606340
      6015: iastore
      6016: dup
      6017: sipush        762
      6020: ldc_w         #958                // int 908771278
      6023: iastore
      6024: dup
      6025: sipush        763
      6028: ldc_w         #959                // int -574175177
      6031: iastore
      6032: dup
      6033: sipush        764
      6036: ldc_w         #960                // int -677760460
      6039: iastore
      6040: dup
      6041: sipush        765
      6044: ldc_w         #961                // int -1838972398
      6047: iastore
      6048: dup
      6049: sipush        766
      6052: ldc_w         #962                // int 1729034894
      6055: iastore
      6056: dup
      6057: sipush        767
      6060: ldc_w         #963                // int 1080033504
      6063: iastore
      6064: dup
      6065: sipush        768
      6068: ldc_w         #964                // int 976866871
      6071: iastore
      6072: dup
      6073: sipush        769
      6076: ldc_w         #965                // int -738527793
      6079: iastore
      6080: dup
      6081: sipush        770
      6084: ldc_w         #966                // int -1413318857
      6087: iastore
      6088: dup
      6089: sipush        771
      6092: ldc_w         #967                // int 1522871579
      6095: iastore
      6096: dup
      6097: sipush        772
      6100: ldc_w         #968                // int 1555064734
      6103: iastore
      6104: dup
      6105: sipush        773
      6108: ldc_w         #969                // int 1336096578
      6111: iastore
      6112: dup
      6113: sipush        774
      6116: ldc_w         #970                // int -746444992
      6119: iastore
      6120: dup
      6121: sipush        775
      6124: ldc_w         #971                // int -1715692610
      6127: iastore
      6128: dup
      6129: sipush        776
      6132: ldc_w         #972                // int -720269667
      6135: iastore
      6136: dup
      6137: sipush        777
      6140: ldc_w         #973                // int -1089506539
      6143: iastore
      6144: dup
      6145: sipush        778
      6148: ldc_w         #974                // int -701686658
      6151: iastore
      6152: dup
      6153: sipush        779
      6156: ldc_w         #975                // int -956251013
      6159: iastore
      6160: dup
      6161: sipush        780
      6164: ldc_w         #976                // int -1215554709
      6167: iastore
      6168: dup
      6169: sipush        781
      6172: ldc_w         #977                // int 564236357
      6175: iastore
      6176: dup
      6177: sipush        782
      6180: ldc_w         #978                // int -1301368386
      6183: iastore
      6184: dup
      6185: sipush        783
      6188: ldc_w         #979                // int 1781952180
      6191: iastore
      6192: dup
      6193: sipush        784
      6196: ldc_w         #980                // int 1464380207
      6199: iastore
      6200: dup
      6201: sipush        785
      6204: ldc_w         #981                // int -1131123079
      6207: iastore
      6208: dup
      6209: sipush        786
      6212: ldc_w         #982                // int -962365742
      6215: iastore
      6216: dup
      6217: sipush        787
      6220: ldc_w         #983                // int 1699332808
      6223: iastore
      6224: dup
      6225: sipush        788
      6228: ldc_w         #984                // int 1393555694
      6231: iastore
      6232: dup
      6233: sipush        789
      6236: ldc_w         #985                // int 1183702653
      6239: iastore
      6240: dup
      6241: sipush        790
      6244: ldc_w         #986                // int -713881059
      6247: iastore
      6248: dup
      6249: sipush        791
      6252: ldc_w         #987                // int 1288719814
      6255: iastore
      6256: dup
      6257: sipush        792
      6260: ldc_w         #988                // int 691649499
      6263: iastore
      6264: dup
      6265: sipush        793
      6268: ldc_w         #989                // int -1447410096
      6271: iastore
      6272: dup
      6273: sipush        794
      6276: ldc_w         #990                // int -1399511320
      6279: iastore
      6280: dup
      6281: sipush        795
      6284: ldc_w         #991                // int -1101077756
      6287: iastore
      6288: dup
      6289: sipush        796
      6292: ldc_w         #992                // int -1577396752
      6295: iastore
      6296: dup
      6297: sipush        797
      6300: ldc_w         #993                // int 1781354906
      6303: iastore
      6304: dup
      6305: sipush        798
      6308: ldc_w         #994                // int 1676643554
      6311: iastore
      6312: dup
      6313: sipush        799
      6316: ldc_w         #995                // int -1702433246
      6319: iastore
      6320: dup
      6321: sipush        800
      6324: ldc_w         #996                // int -1064713544
      6327: iastore
      6328: dup
      6329: sipush        801
      6332: ldc_w         #997                // int 1126444790
      6335: iastore
      6336: dup
      6337: sipush        802
      6340: ldc_w         #998                // int -1524759638
      6343: iastore
      6344: dup
      6345: sipush        803
      6348: ldc_w         #999                // int -1661808476
      6351: iastore
      6352: dup
      6353: sipush        804
      6356: ldc_w         #1000               // int -2084544070
      6359: iastore
      6360: dup
      6361: sipush        805
      6364: ldc_w         #1001               // int -1679201715
      6367: iastore
      6368: dup
      6369: sipush        806
      6372: ldc_w         #1002               // int -1880812208
      6375: iastore
      6376: dup
      6377: sipush        807
      6380: ldc_w         #1003               // int -1167828010
      6383: iastore
      6384: dup
      6385: sipush        808
      6388: ldc_w         #1004               // int 673620729
      6391: iastore
      6392: dup
      6393: sipush        809
      6396: ldc_w         #1005               // int -1489356063
      6399: iastore
      6400: dup
      6401: sipush        810
      6404: ldc_w         #1006               // int 1269405062
      6407: iastore
      6408: dup
      6409: sipush        811
      6412: ldc_w         #1007               // int -279616791
      6415: iastore
      6416: dup
      6417: sipush        812
      6420: ldc_w         #1008               // int -953159725
      6423: iastore
      6424: dup
      6425: sipush        813
      6428: ldc_w         #1009               // int -145557542
      6431: iastore
      6432: dup
      6433: sipush        814
      6436: ldc_w         #1010               // int 1057255273
      6439: iastore
      6440: dup
      6441: sipush        815
      6444: ldc_w         #1011               // int 2012875353
      6447: iastore
      6448: dup
      6449: sipush        816
      6452: ldc_w         #1012               // int -2132498155
      6455: iastore
      6456: dup
      6457: sipush        817
      6460: ldc_w         #1013               // int -2018474495
      6463: iastore
      6464: dup
      6465: sipush        818
      6468: ldc_w         #1014               // int -1693849939
      6471: iastore
      6472: dup
      6473: sipush        819
      6476: ldc_w         #1015               // int 993977747
      6479: iastore
      6480: dup
      6481: sipush        820
      6484: ldc_w         #1016               // int -376373926
      6487: iastore
      6488: dup
      6489: sipush        821
      6492: ldc_w         #1017               // int -1640704105
      6495: iastore
      6496: dup
      6497: sipush        822
      6500: ldc_w         #1018               // int 753973209
      6503: iastore
      6504: dup
      6505: sipush        823
      6508: ldc_w         #1019               // int 36408145
      6511: iastore
      6512: dup
      6513: sipush        824
      6516: ldc_w         #1020               // int -1764381638
      6519: iastore
      6520: dup
      6521: sipush        825
      6524: ldc_w         #1021               // int 25011837
      6527: iastore
      6528: dup
      6529: sipush        826
      6532: ldc_w         #1022               // int -774947114
      6535: iastore
      6536: dup
      6537: sipush        827
      6540: ldc_w         #1023               // int 2088578344
      6543: iastore
      6544: dup
      6545: sipush        828
      6548: ldc_w         #1024               // int 530523599
      6551: iastore
      6552: dup
      6553: sipush        829
      6556: ldc_w         #1025               // int -1376601957
      6559: iastore
      6560: dup
      6561: sipush        830
      6564: ldc_w         #1026               // int 1524020338
      6567: iastore
      6568: dup
      6569: sipush        831
      6572: ldc_w         #1027               // int 1518925132
      6575: iastore
      6576: dup
      6577: sipush        832
      6580: ldc_w         #1028               // int -534139791
      6583: iastore
      6584: dup
      6585: sipush        833
      6588: ldc_w         #1029               // int -535190042
      6591: iastore
      6592: dup
      6593: sipush        834
      6596: ldc_w         #1030               // int 1202760957
      6599: iastore
      6600: dup
      6601: sipush        835
      6604: ldc_w         #1031               // int -309069157
      6607: iastore
      6608: dup
      6609: sipush        836
      6612: ldc_w         #1032               // int -388774771
      6615: iastore
      6616: dup
      6617: sipush        837
      6620: ldc_w         #1033               // int 674977740
      6623: iastore
      6624: dup
      6625: sipush        838
      6628: ldc_w         #1034               // int -120232407
      6631: iastore
      6632: dup
      6633: sipush        839
      6636: ldc_w         #1035               // int 2031300136
      6639: iastore
      6640: dup
      6641: sipush        840
      6644: ldc_w         #1036               // int 2019492241
      6647: iastore
      6648: dup
      6649: sipush        841
      6652: ldc_w         #1037               // int -311074731
      6655: iastore
      6656: dup
      6657: sipush        842
      6660: ldc_w         #1038               // int -141160892
      6663: iastore
      6664: dup
      6665: sipush        843
      6668: ldc_w         #1039               // int -472686964
      6671: iastore
      6672: dup
      6673: sipush        844
      6676: ldc_w         #1040               // int 352677332
      6679: iastore
      6680: dup
      6681: sipush        845
      6684: ldc_w         #1041               // int -1997247046
      6687: iastore
      6688: dup
      6689: sipush        846
      6692: ldc_w         #1042               // int 60907813
      6695: iastore
      6696: dup
      6697: sipush        847
      6700: ldc_w         #1043               // int 90501309
      6703: iastore
      6704: dup
      6705: sipush        848
      6708: ldc_w         #1044               // int -1007968747
      6711: iastore
      6712: dup
      6713: sipush        849
      6716: ldc_w         #1045               // int 1016092578
      6719: iastore
      6720: dup
      6721: sipush        850
      6724: ldc_w         #1046               // int -1759044884
      6727: iastore
      6728: dup
      6729: sipush        851
      6732: ldc_w         #1047               // int -1455814870
      6735: iastore
      6736: dup
      6737: sipush        852
      6740: ldc_w         #1048               // int 457141659
      6743: iastore
      6744: dup
      6745: sipush        853
      6748: ldc_w         #1049               // int 509813237
      6751: iastore
      6752: dup
      6753: sipush        854
      6756: ldc_w         #1050               // int -174299397
      6759: iastore
      6760: dup
      6761: sipush        855
      6764: ldc_w         #1051               // int 652014361
      6767: iastore
      6768: dup
      6769: sipush        856
      6772: ldc_w         #1052               // int 1966332200
      6775: iastore
      6776: dup
      6777: sipush        857
      6780: ldc_w         #1053               // int -1319764491
      6783: iastore
      6784: dup
      6785: sipush        858
      6788: ldc_w         #1054               // int 55981186
      6791: iastore
      6792: dup
      6793: sipush        859
      6796: ldc_w         #1055               // int -1967506245
      6799: iastore
      6800: dup
      6801: sipush        860
      6804: ldc_w         #1056               // int 676427537
      6807: iastore
      6808: dup
      6809: sipush        861
      6812: ldc_w         #1057               // int -1039476232
      6815: iastore
      6816: dup
      6817: sipush        862
      6820: ldc_w         #1058               // int -1412673177
      6823: iastore
      6824: dup
      6825: sipush        863
      6828: ldc_w         #1059               // int -861040033
      6831: iastore
      6832: dup
      6833: sipush        864
      6836: ldc_w         #1060               // int 1307055953
      6839: iastore
      6840: dup
      6841: sipush        865
      6844: ldc_w         #1061               // int 942726286
      6847: iastore
      6848: dup
      6849: sipush        866
      6852: ldc_w         #1062               // int 933058658
      6855: iastore
      6856: dup
      6857: sipush        867
      6860: ldc_w         #1063               // int -1826555503
      6863: iastore
      6864: dup
      6865: sipush        868
      6868: ldc_w         #1064               // int -361066302
      6871: iastore
      6872: dup
      6873: sipush        869
      6876: ldc_w         #1065               // int -79791154
      6879: iastore
      6880: dup
      6881: sipush        870
      6884: ldc_w         #1066               // int 1361170020
      6887: iastore
      6888: dup
      6889: sipush        871
      6892: ldc_w         #1067               // int 2001714738
      6895: iastore
      6896: dup
      6897: sipush        872
      6900: ldc_w         #1068               // int -1464409218
      6903: iastore
      6904: dup
      6905: sipush        873
      6908: ldc_w         #1069               // int -1020707514
      6911: iastore
      6912: dup
      6913: sipush        874
      6916: ldc_w         #1070               // int 1222529897
      6919: iastore
      6920: dup
      6921: sipush        875
      6924: ldc_w         #1071               // int 1679025792
      6927: iastore
      6928: dup
      6929: sipush        876
      6932: ldc_w         #1072               // int -1565652976
      6935: iastore
      6936: dup
      6937: sipush        877
      6940: ldc_w         #1073               // int -580013532
      6943: iastore
      6944: dup
      6945: sipush        878
      6948: ldc_w         #1074               // int 1770335741
      6951: iastore
      6952: dup
      6953: sipush        879
      6956: ldc_w         #1075               // int 151462246
      6959: iastore
      6960: dup
      6961: sipush        880
      6964: ldc_w         #1076               // int -1281735158
      6967: iastore
      6968: dup
      6969: sipush        881
      6972: ldc_w         #1077               // int 1682292957
      6975: iastore
      6976: dup
      6977: sipush        882
      6980: ldc_w         #1078               // int 1483529935
      6983: iastore
      6984: dup
      6985: sipush        883
      6988: ldc_w         #1079               // int 471910574
      6991: iastore
      6992: dup
      6993: sipush        884
      6996: ldc_w         #1080               // int 1539241949
      6999: iastore
      7000: dup
      7001: sipush        885
      7004: ldc_w         #1081               // int 458788160
      7007: iastore
      7008: dup
      7009: sipush        886
      7012: ldc_w         #1082               // int -858652289
      7015: iastore
      7016: dup
      7017: sipush        887
      7020: ldc_w         #1083               // int 1807016891
      7023: iastore
      7024: dup
      7025: sipush        888
      7028: ldc_w         #1084               // int -576558466
      7031: iastore
      7032: dup
      7033: sipush        889
      7036: ldc_w         #1085               // int 978976581
      7039: iastore
      7040: dup
      7041: sipush        890
      7044: ldc_w         #1086               // int 1043663428
      7047: iastore
      7048: dup
      7049: sipush        891
      7052: ldc_w         #1087               // int -1129001515
      7055: iastore
      7056: dup
      7057: sipush        892
      7060: ldc_w         #1088               // int 1927990952
      7063: iastore
      7064: dup
      7065: sipush        893
      7068: ldc_w         #1089               // int -94075717
      7071: iastore
      7072: dup
      7073: sipush        894
      7076: ldc_w         #1090               // int -1922690386
      7079: iastore
      7080: dup
      7081: sipush        895
      7084: ldc_w         #1091               // int -1086558393
      7087: iastore
      7088: dup
      7089: sipush        896
      7092: ldc_w         #1092               // int -761535389
      7095: iastore
      7096: dup
      7097: sipush        897
      7100: ldc_w         #1093               // int 1412390302
      7103: iastore
      7104: dup
      7105: sipush        898
      7108: ldc_w         #1094               // int -1362987237
      7111: iastore
      7112: dup
      7113: sipush        899
      7116: ldc_w         #1095               // int -162634896
      7119: iastore
      7120: dup
      7121: sipush        900
      7124: ldc_w         #1096               // int 1947078029
      7127: iastore
      7128: dup
      7129: sipush        901
      7132: ldc_w         #1097               // int -413461673
      7135: iastore
      7136: dup
      7137: sipush        902
      7140: ldc_w         #1098               // int -126740879
      7143: iastore
      7144: dup
      7145: sipush        903
      7148: ldc_w         #1099               // int -1353482915
      7151: iastore
      7152: dup
      7153: sipush        904
      7156: ldc_w         #1100               // int 1077988104
      7159: iastore
      7160: dup
      7161: sipush        905
      7164: ldc_w         #1101               // int 1320477388
      7167: iastore
      7168: dup
      7169: sipush        906
      7172: ldc_w         #1102               // int 886195818
      7175: iastore
      7176: dup
      7177: sipush        907
      7180: ldc_w         #1103               // int 18198404
      7183: iastore
      7184: dup
      7185: sipush        908
      7188: ldc_w         #1104               // int -508558296
      7191: iastore
      7192: dup
      7193: sipush        909
      7196: ldc_w         #1105               // int -1785185763
      7199: iastore
      7200: dup
      7201: sipush        910
      7204: ldc_w         #1106               // int 112762804
      7207: iastore
      7208: dup
      7209: sipush        911
      7212: ldc_w         #1107               // int -831610808
      7215: iastore
      7216: dup
      7217: sipush        912
      7220: ldc_w         #1108               // int 1866414978
      7223: iastore
      7224: dup
      7225: sipush        913
      7228: ldc_w         #1109               // int 891333506
      7231: iastore
      7232: dup
      7233: sipush        914
      7236: ldc_w         #1110               // int 18488651
      7239: iastore
      7240: dup
      7241: sipush        915
      7244: ldc_w         #1111               // int 661792760
      7247: iastore
      7248: dup
      7249: sipush        916
      7252: ldc_w         #1112               // int 1628790961
      7255: iastore
      7256: dup
      7257: sipush        917
      7260: ldc_w         #1113               // int -409780260
      7263: iastore
      7264: dup
      7265: sipush        918
      7268: ldc_w         #1114               // int -1153795797
      7271: iastore
      7272: dup
      7273: sipush        919
      7276: ldc_w         #1115               // int 876946877
      7279: iastore
      7280: dup
      7281: sipush        920
      7284: ldc_w         #1116               // int -1601685023
      7287: iastore
      7288: dup
      7289: sipush        921
      7292: ldc_w         #1117               // int 1372485963
      7295: iastore
      7296: dup
      7297: sipush        922
      7300: ldc_w         #1118               // int 791857591
      7303: iastore
      7304: dup
      7305: sipush        923
      7308: ldc_w         #1119               // int -1608533303
      7311: iastore
      7312: dup
      7313: sipush        924
      7316: ldc_w         #1120               // int -534984578
      7319: iastore
      7320: dup
      7321: sipush        925
      7324: ldc_w         #1121               // int -1127755274
      7327: iastore
      7328: dup
      7329: sipush        926
      7332: ldc_w         #1122               // int -822013501
      7335: iastore
      7336: dup
      7337: sipush        927
      7340: ldc_w         #1123               // int -1578587449
      7343: iastore
      7344: dup
      7345: sipush        928
      7348: ldc_w         #1124               // int 445679433
      7351: iastore
      7352: dup
      7353: sipush        929
      7356: ldc_w         #1125               // int -732971622
      7359: iastore
      7360: dup
      7361: sipush        930
      7364: ldc_w         #1126               // int -790962485
      7367: iastore
      7368: dup
      7369: sipush        931
      7372: ldc_w         #1127               // int -720709064
      7375: iastore
      7376: dup
      7377: sipush        932
      7380: ldc_w         #1128               // int 54117162
      7383: iastore
      7384: dup
      7385: sipush        933
      7388: ldc_w         #1129               // int -963561881
      7391: iastore
      7392: dup
      7393: sipush        934
      7396: ldc_w         #1130               // int -1913048708
      7399: iastore
      7400: dup
      7401: sipush        935
      7404: ldc_w         #1131               // int -525259953
      7407: iastore
      7408: dup
      7409: sipush        936
      7412: ldc_w         #1132               // int -140617289
      7415: iastore
      7416: dup
      7417: sipush        937
      7420: ldc_w         #1133               // int 1140177722
      7423: iastore
      7424: dup
      7425: sipush        938
      7428: ldc_w         #1134               // int -220915201
      7431: iastore
      7432: dup
      7433: sipush        939
      7436: ldc_w         #1135               // int 668550556
      7439: iastore
      7440: dup
      7441: sipush        940
      7444: ldc_w         #1136               // int -1080614356
      7447: iastore
      7448: dup
      7449: sipush        941
      7452: ldc_w         #1137               // int 367459370
      7455: iastore
      7456: dup
      7457: sipush        942
      7460: ldc_w         #1138               // int 261225585
      7463: iastore
      7464: dup
      7465: sipush        943
      7468: ldc_w         #1139               // int -1684794075
      7471: iastore
      7472: dup
      7473: sipush        944
      7476: ldc_w         #1140               // int -85617823
      7479: iastore
      7480: dup
      7481: sipush        945
      7484: ldc_w         #1141               // int -826893077
      7487: iastore
      7488: dup
      7489: sipush        946
      7492: ldc_w         #1142               // int -1029151655
      7495: iastore
      7496: dup
      7497: sipush        947
      7500: ldc_w         #1143               // int 314222801
      7503: iastore
      7504: dup
      7505: sipush        948
      7508: ldc_w         #1144               // int -1228863650
      7511: iastore
      7512: dup
      7513: sipush        949
      7516: ldc_w         #1145               // int -486184436
      7519: iastore
      7520: dup
      7521: sipush        950
      7524: ldc_w         #1146               // int 282218597
      7527: iastore
      7528: dup
      7529: sipush        951
      7532: ldc_w         #1147               // int -888953790
      7535: iastore
      7536: dup
      7537: sipush        952
      7540: ldc_w         #1148               // int -521376242
      7543: iastore
      7544: dup
      7545: sipush        953
      7548: ldc_w         #1149               // int 379116347
      7551: iastore
      7552: dup
      7553: sipush        954
      7556: ldc_w         #1150               // int 1285071038
      7559: iastore
      7560: dup
      7561: sipush        955
      7564: ldc_w         #1151               // int 846784868
      7567: iastore
      7568: dup
      7569: sipush        956
      7572: ldc_w         #1152               // int -1625320142
      7575: iastore
      7576: dup
      7577: sipush        957
      7580: ldc_w         #1153               // int -523005217
      7583: iastore
      7584: dup
      7585: sipush        958
      7588: ldc_w         #1154               // int -744475605
      7591: iastore
      7592: dup
      7593: sipush        959
      7596: ldc_w         #1155               // int -1989021154
      7599: iastore
      7600: dup
      7601: sipush        960
      7604: ldc_w         #1156               // int 453669953
      7607: iastore
      7608: dup
      7609: sipush        961
      7612: ldc_w         #1157               // int 1268987020
      7615: iastore
      7616: dup
      7617: sipush        962
      7620: ldc_w         #1158               // int -977374944
      7623: iastore
      7624: dup
      7625: sipush        963
      7628: ldc_w         #1159               // int -1015663912
      7631: iastore
      7632: dup
      7633: sipush        964
      7636: ldc_w         #1160               // int -550133875
      7639: iastore
      7640: dup
      7641: sipush        965
      7644: ldc_w         #1161               // int -1684459730
      7647: iastore
      7648: dup
      7649: sipush        966
      7652: ldc_w         #1162               // int -435458233
      7655: iastore
      7656: dup
      7657: sipush        967
      7660: ldc_w         #1163               // int 266596637
      7663: iastore
      7664: dup
      7665: sipush        968
      7668: ldc_w         #1164               // int -447948204
      7671: iastore
      7672: dup
      7673: sipush        969
      7676: ldc_w         #1165               // int 517658769
      7679: iastore
      7680: dup
      7681: sipush        970
      7684: ldc_w         #1166               // int -832407089
      7687: iastore
      7688: dup
      7689: sipush        971
      7692: ldc_w         #1167               // int -851542417
      7695: iastore
      7696: dup
      7697: sipush        972
      7700: ldc_w         #1168               // int 370717030
      7703: iastore
      7704: dup
      7705: sipush        973
      7708: ldc_w         #1169               // int -47440635
      7711: iastore
      7712: dup
      7713: sipush        974
      7716: ldc_w         #1170               // int -2070949179
      7719: iastore
      7720: dup
      7721: sipush        975
      7724: ldc_w         #1171               // int -151313767
      7727: iastore
      7728: dup
      7729: sipush        976
      7732: ldc_w         #1172               // int -182193321
      7735: iastore
      7736: dup
      7737: sipush        977
      7740: ldc_w         #1173               // int -1506642397
      7743: iastore
      7744: dup
      7745: sipush        978
      7748: ldc_w         #1174               // int -1817692879
      7751: iastore
      7752: dup
      7753: sipush        979
      7756: ldc_w         #1175               // int 1456262402
      7759: iastore
      7760: dup
      7761: sipush        980
      7764: ldc_w         #1176               // int -1393524382
      7767: iastore
      7768: dup
      7769: sipush        981
      7772: ldc_w         #1177               // int 1517677493
      7775: iastore
      7776: dup
      7777: sipush        982
      7780: ldc_w         #1178               // int 1846949527
      7783: iastore
      7784: dup
      7785: sipush        983
      7788: ldc_w         #1179               // int -1999473716
      7791: iastore
      7792: dup
      7793: sipush        984
      7796: ldc_w         #1180               // int -560569710
      7799: iastore
      7800: dup
      7801: sipush        985
      7804: ldc_w         #1181               // int -2118563376
      7807: iastore
      7808: dup
      7809: sipush        986
      7812: ldc_w         #1182               // int 1280348187
      7815: iastore
      7816: dup
      7817: sipush        987
      7820: ldc_w         #1183               // int 1908823572
      7823: iastore
      7824: dup
      7825: sipush        988
      7828: ldc_w         #1184               // int -423180355
      7831: iastore
      7832: dup
      7833: sipush        989
      7836: ldc_w         #1185               // int 846861322
      7839: iastore
      7840: dup
      7841: sipush        990
      7844: ldc_w         #1186               // int 1172426758
      7847: iastore
      7848: dup
      7849: sipush        991
      7852: ldc_w         #1187               // int -1007518822
      7855: iastore
      7856: dup
      7857: sipush        992
      7860: ldc_w         #1188               // int -911584259
      7863: iastore
      7864: dup
      7865: sipush        993
      7868: ldc_w         #1189               // int 1655181056
      7871: iastore
      7872: dup
      7873: sipush        994
      7876: ldc_w         #1190               // int -1155153950
      7879: iastore
      7880: dup
      7881: sipush        995
      7884: ldc_w         #1191               // int 901632758
      7887: iastore
      7888: dup
      7889: sipush        996
      7892: ldc_w         #1192               // int 1897031941
      7895: iastore
      7896: dup
      7897: sipush        997
      7900: ldc_w         #1193               // int -1308360158
      7903: iastore
      7904: dup
      7905: sipush        998
      7908: ldc_w         #1194               // int -1228157060
      7911: iastore
      7912: dup
      7913: sipush        999
      7916: ldc_w         #1195               // int -847864789
      7919: iastore
      7920: dup
      7921: sipush        1000
      7924: ldc_w         #1196               // int 1393639104
      7927: iastore
      7928: dup
      7929: sipush        1001
      7932: ldc_w         #1197               // int 373351379
      7935: iastore
      7936: dup
      7937: sipush        1002
      7940: ldc_w         #1198               // int 950779232
      7943: iastore
      7944: dup
      7945: sipush        1003
      7948: ldc_w         #1199               // int 625454576
      7951: iastore
      7952: dup
      7953: sipush        1004
      7956: ldc_w         #1200               // int -1170726756
      7959: iastore
      7960: dup
      7961: sipush        1005
      7964: ldc_w         #1201               // int -146354570
      7967: iastore
      7968: dup
      7969: sipush        1006
      7972: ldc_w         #1202               // int 2007998917
      7975: iastore
      7976: dup
      7977: sipush        1007
      7980: ldc_w         #1203               // int 544563296
      7983: iastore
      7984: dup
      7985: sipush        1008
      7988: ldc_w         #1204               // int -2050228658
      7991: iastore
      7992: dup
      7993: sipush        1009
      7996: ldc_w         #1205               // int -1964470824
      7999: iastore
      8000: dup
      8001: sipush        1010
      8004: ldc_w         #1206               // int 2058025392
      8007: iastore
      8008: dup
      8009: sipush        1011
      8012: ldc_w         #1207               // int 1291430526
      8015: iastore
      8016: dup
      8017: sipush        1012
      8020: ldc_w         #1208               // int 424198748
      8023: iastore
      8024: dup
      8025: sipush        1013
      8028: ldc_w         #1209               // int 50039436
      8031: iastore
      8032: dup
      8033: sipush        1014
      8036: ldc_w         #1210               // int 29584100
      8039: iastore
      8040: dup
      8041: sipush        1015
      8044: ldc_w         #1211               // int -689184263
      8047: iastore
      8048: dup
      8049: sipush        1016
      8052: ldc_w         #1212               // int -1865090967
      8055: iastore
      8056: dup
      8057: sipush        1017
      8060: ldc_w         #1213               // int -1503863136
      8063: iastore
      8064: dup
      8065: sipush        1018
      8068: ldc_w         #1214               // int 1057563949
      8071: iastore
      8072: dup
      8073: sipush        1019
      8076: ldc_w         #1215               // int -1039604065
      8079: iastore
      8080: dup
      8081: sipush        1020
      8084: ldc_w         #1216               // int -1219600078
      8087: iastore
      8088: dup
      8089: sipush        1021
      8092: ldc_w         #1217               // int -831004069
      8095: iastore
      8096: dup
      8097: sipush        1022
      8100: ldc_w         #1218               // int 1469046755
      8103: iastore
      8104: dup
      8105: sipush        1023
      8108: ldc_w         #1219               // int 985887462
      8111: iastore
      8112: putstatic     #67                 // Field S_ORIG:[I
      8115: bipush        6
      8117: newarray       int
      8119: dup
      8120: iconst_0
      8121: ldc_w         #1220               // int 1332899944
      8124: iastore
      8125: dup
      8126: iconst_1
      8127: ldc_w         #1221               // int 1700884034
      8130: iastore
      8131: dup
      8132: iconst_2
      8133: ldc_w         #1222               // int 1701343084
      8136: iastore
      8137: dup
      8138: iconst_3
      8139: ldc_w         #1223               // int 1684370003
      8142: iastore
      8143: dup
      8144: iconst_4
      8145: ldc_w         #1224               // int 1668446532
      8148: iastore
      8149: dup
      8150: iconst_5
      8151: ldc_w         #1225               // int 1869963892
      8154: iastore
      8155: putstatic     #138                // Field BF_CRYPT_CIPHERTEXT:[I
      8158: bipush        64
      8160: newarray       char
      8162: dup
      8163: iconst_0
      8164: bipush        46
      8166: castore
      8167: dup
      8168: iconst_1
      8169: bipush        47
      8171: castore
      8172: dup
      8173: iconst_2
      8174: bipush        65
      8176: castore
      8177: dup
      8178: iconst_3
      8179: bipush        66
      8181: castore
      8182: dup
      8183: iconst_4
      8184: bipush        67
      8186: castore
      8187: dup
      8188: iconst_5
      8189: bipush        68
      8191: castore
      8192: dup
      8193: bipush        6
      8195: bipush        69
      8197: castore
      8198: dup
      8199: bipush        7
      8201: bipush        70
      8203: castore
      8204: dup
      8205: bipush        8
      8207: bipush        71
      8209: castore
      8210: dup
      8211: bipush        9
      8213: bipush        72
      8215: castore
      8216: dup
      8217: bipush        10
      8219: bipush        73
      8221: castore
      8222: dup
      8223: bipush        11
      8225: bipush        74
      8227: castore
      8228: dup
      8229: bipush        12
      8231: bipush        75
      8233: castore
      8234: dup
      8235: bipush        13
      8237: bipush        76
      8239: castore
      8240: dup
      8241: bipush        14
      8243: bipush        77
      8245: castore
      8246: dup
      8247: bipush        15
      8249: bipush        78
      8251: castore
      8252: dup
      8253: bipush        16
      8255: bipush        79
      8257: castore
      8258: dup
      8259: bipush        17
      8261: bipush        80
      8263: castore
      8264: dup
      8265: bipush        18
      8267: bipush        81
      8269: castore
      8270: dup
      8271: bipush        19
      8273: bipush        82
      8275: castore
      8276: dup
      8277: bipush        20
      8279: bipush        83
      8281: castore
      8282: dup
      8283: bipush        21
      8285: bipush        84
      8287: castore
      8288: dup
      8289: bipush        22
      8291: bipush        85
      8293: castore
      8294: dup
      8295: bipush        23
      8297: bipush        86
      8299: castore
      8300: dup
      8301: bipush        24
      8303: bipush        87
      8305: castore
      8306: dup
      8307: bipush        25
      8309: bipush        88
      8311: castore
      8312: dup
      8313: bipush        26
      8315: bipush        89
      8317: castore
      8318: dup
      8319: bipush        27
      8321: bipush        90
      8323: castore
      8324: dup
      8325: bipush        28
      8327: bipush        97
      8329: castore
      8330: dup
      8331: bipush        29
      8333: bipush        98
      8335: castore
      8336: dup
      8337: bipush        30
      8339: bipush        99
      8341: castore
      8342: dup
      8343: bipush        31
      8345: bipush        100
      8347: castore
      8348: dup
      8349: bipush        32
      8351: bipush        101
      8353: castore
      8354: dup
      8355: bipush        33
      8357: bipush        102
      8359: castore
      8360: dup
      8361: bipush        34
      8363: bipush        103
      8365: castore
      8366: dup
      8367: bipush        35
      8369: bipush        104
      8371: castore
      8372: dup
      8373: bipush        36
      8375: bipush        105
      8377: castore
      8378: dup
      8379: bipush        37
      8381: bipush        106
      8383: castore
      8384: dup
      8385: bipush        38
      8387: bipush        107
      8389: castore
      8390: dup
      8391: bipush        39
      8393: bipush        108
      8395: castore
      8396: dup
      8397: bipush        40
      8399: bipush        109
      8401: castore
      8402: dup
      8403: bipush        41
      8405: bipush        110
      8407: castore
      8408: dup
      8409: bipush        42
      8411: bipush        111
      8413: castore
      8414: dup
      8415: bipush        43
      8417: bipush        112
      8419: castore
      8420: dup
      8421: bipush        44
      8423: bipush        113
      8425: castore
      8426: dup
      8427: bipush        45
      8429: bipush        114
      8431: castore
      8432: dup
      8433: bipush        46
      8435: bipush        115
      8437: castore
      8438: dup
      8439: bipush        47
      8441: bipush        116
      8443: castore
      8444: dup
      8445: bipush        48
      8447: bipush        117
      8449: castore
      8450: dup
      8451: bipush        49
      8453: bipush        118
      8455: castore
      8456: dup
      8457: bipush        50
      8459: bipush        119
      8461: castore
      8462: dup
      8463: bipush        51
      8465: bipush        120
      8467: castore
      8468: dup
      8469: bipush        52
      8471: bipush        121
      8473: castore
      8474: dup
      8475: bipush        53
      8477: bipush        122
      8479: castore
      8480: dup
      8481: bipush        54
      8483: bipush        48
      8485: castore
      8486: dup
      8487: bipush        55
      8489: bipush        49
      8491: castore
      8492: dup
      8493: bipush        56
      8495: bipush        50
      8497: castore
      8498: dup
      8499: bipush        57
      8501: bipush        51
      8503: castore
      8504: dup
      8505: bipush        58
      8507: bipush        52
      8509: castore
      8510: dup
      8511: bipush        59
      8513: bipush        53
      8515: castore
      8516: dup
      8517: bipush        60
      8519: bipush        54
      8521: castore
      8522: dup
      8523: bipush        61
      8525: bipush        55
      8527: castore
      8528: dup
      8529: bipush        62
      8531: bipush        56
      8533: castore
      8534: dup
      8535: bipush        63
      8537: bipush        57
      8539: castore
      8540: putstatic     #17                 // Field BASE64_CODE:[C
      8543: sipush        128
      8546: newarray       byte
      8548: dup
      8549: iconst_0
      8550: iconst_m1
      8551: bastore
      8552: dup
      8553: iconst_1
      8554: iconst_m1
      8555: bastore
      8556: dup
      8557: iconst_2
      8558: iconst_m1
      8559: bastore
      8560: dup
      8561: iconst_3
      8562: iconst_m1
      8563: bastore
      8564: dup
      8565: iconst_4
      8566: iconst_m1
      8567: bastore
      8568: dup
      8569: iconst_5
      8570: iconst_m1
      8571: bastore
      8572: dup
      8573: bipush        6
      8575: iconst_m1
      8576: bastore
      8577: dup
      8578: bipush        7
      8580: iconst_m1
      8581: bastore
      8582: dup
      8583: bipush        8
      8585: iconst_m1
      8586: bastore
      8587: dup
      8588: bipush        9
      8590: iconst_m1
      8591: bastore
      8592: dup
      8593: bipush        10
      8595: iconst_m1
      8596: bastore
      8597: dup
      8598: bipush        11
      8600: iconst_m1
      8601: bastore
      8602: dup
      8603: bipush        12
      8605: iconst_m1
      8606: bastore
      8607: dup
      8608: bipush        13
      8610: iconst_m1
      8611: bastore
      8612: dup
      8613: bipush        14
      8615: iconst_m1
      8616: bastore
      8617: dup
      8618: bipush        15
      8620: iconst_m1
      8621: bastore
      8622: dup
      8623: bipush        16
      8625: iconst_m1
      8626: bastore
      8627: dup
      8628: bipush        17
      8630: iconst_m1
      8631: bastore
      8632: dup
      8633: bipush        18
      8635: iconst_m1
      8636: bastore
      8637: dup
      8638: bipush        19
      8640: iconst_m1
      8641: bastore
      8642: dup
      8643: bipush        20
      8645: iconst_m1
      8646: bastore
      8647: dup
      8648: bipush        21
      8650: iconst_m1
      8651: bastore
      8652: dup
      8653: bipush        22
      8655: iconst_m1
      8656: bastore
      8657: dup
      8658: bipush        23
      8660: iconst_m1
      8661: bastore
      8662: dup
      8663: bipush        24
      8665: iconst_m1
      8666: bastore
      8667: dup
      8668: bipush        25
      8670: iconst_m1
      8671: bastore
      8672: dup
      8673: bipush        26
      8675: iconst_m1
      8676: bastore
      8677: dup
      8678: bipush        27
      8680: iconst_m1
      8681: bastore
      8682: dup
      8683: bipush        28
      8685: iconst_m1
      8686: bastore
      8687: dup
      8688: bipush        29
      8690: iconst_m1
      8691: bastore
      8692: dup
      8693: bipush        30
      8695: iconst_m1
      8696: bastore
      8697: dup
      8698: bipush        31
      8700: iconst_m1
      8701: bastore
      8702: dup
      8703: bipush        32
      8705: iconst_m1
      8706: bastore
      8707: dup
      8708: bipush        33
      8710: iconst_m1
      8711: bastore
      8712: dup
      8713: bipush        34
      8715: iconst_m1
      8716: bastore
      8717: dup
      8718: bipush        35
      8720: iconst_m1
      8721: bastore
      8722: dup
      8723: bipush        36
      8725: iconst_m1
      8726: bastore
      8727: dup
      8728: bipush        37
      8730: iconst_m1
      8731: bastore
      8732: dup
      8733: bipush        38
      8735: iconst_m1
      8736: bastore
      8737: dup
      8738: bipush        39
      8740: iconst_m1
      8741: bastore
      8742: dup
      8743: bipush        40
      8745: iconst_m1
      8746: bastore
      8747: dup
      8748: bipush        41
      8750: iconst_m1
      8751: bastore
      8752: dup
      8753: bipush        42
      8755: iconst_m1
      8756: bastore
      8757: dup
      8758: bipush        43
      8760: iconst_m1
      8761: bastore
      8762: dup
      8763: bipush        44
      8765: iconst_m1
      8766: bastore
      8767: dup
      8768: bipush        45
      8770: iconst_m1
      8771: bastore
      8772: dup
      8773: bipush        46
      8775: iconst_0
      8776: bastore
      8777: dup
      8778: bipush        47
      8780: iconst_1
      8781: bastore
      8782: dup
      8783: bipush        48
      8785: bipush        54
      8787: bastore
      8788: dup
      8789: bipush        49
      8791: bipush        55
      8793: bastore
      8794: dup
      8795: bipush        50
      8797: bipush        56
      8799: bastore
      8800: dup
      8801: bipush        51
      8803: bipush        57
      8805: bastore
      8806: dup
      8807: bipush        52
      8809: bipush        58
      8811: bastore
      8812: dup
      8813: bipush        53
      8815: bipush        59
      8817: bastore
      8818: dup
      8819: bipush        54
      8821: bipush        60
      8823: bastore
      8824: dup
      8825: bipush        55
      8827: bipush        61
      8829: bastore
      8830: dup
      8831: bipush        56
      8833: bipush        62
      8835: bastore
      8836: dup
      8837: bipush        57
      8839: bipush        63
      8841: bastore
      8842: dup
      8843: bipush        58
      8845: iconst_m1
      8846: bastore
      8847: dup
      8848: bipush        59
      8850: iconst_m1
      8851: bastore
      8852: dup
      8853: bipush        60
      8855: iconst_m1
      8856: bastore
      8857: dup
      8858: bipush        61
      8860: iconst_m1
      8861: bastore
      8862: dup
      8863: bipush        62
      8865: iconst_m1
      8866: bastore
      8867: dup
      8868: bipush        63
      8870: iconst_m1
      8871: bastore
      8872: dup
      8873: bipush        64
      8875: iconst_m1
      8876: bastore
      8877: dup
      8878: bipush        65
      8880: iconst_2
      8881: bastore
      8882: dup
      8883: bipush        66
      8885: iconst_3
      8886: bastore
      8887: dup
      8888: bipush        67
      8890: iconst_4
      8891: bastore
      8892: dup
      8893: bipush        68
      8895: iconst_5
      8896: bastore
      8897: dup
      8898: bipush        69
      8900: bipush        6
      8902: bastore
      8903: dup
      8904: bipush        70
      8906: bipush        7
      8908: bastore
      8909: dup
      8910: bipush        71
      8912: bipush        8
      8914: bastore
      8915: dup
      8916: bipush        72
      8918: bipush        9
      8920: bastore
      8921: dup
      8922: bipush        73
      8924: bipush        10
      8926: bastore
      8927: dup
      8928: bipush        74
      8930: bipush        11
      8932: bastore
      8933: dup
      8934: bipush        75
      8936: bipush        12
      8938: bastore
      8939: dup
      8940: bipush        76
      8942: bipush        13
      8944: bastore
      8945: dup
      8946: bipush        77
      8948: bipush        14
      8950: bastore
      8951: dup
      8952: bipush        78
      8954: bipush        15
      8956: bastore
      8957: dup
      8958: bipush        79
      8960: bipush        16
      8962: bastore
      8963: dup
      8964: bipush        80
      8966: bipush        17
      8968: bastore
      8969: dup
      8970: bipush        81
      8972: bipush        18
      8974: bastore
      8975: dup
      8976: bipush        82
      8978: bipush        19
      8980: bastore
      8981: dup
      8982: bipush        83
      8984: bipush        20
      8986: bastore
      8987: dup
      8988: bipush        84
      8990: bipush        21
      8992: bastore
      8993: dup
      8994: bipush        85
      8996: bipush        22
      8998: bastore
      8999: dup
      9000: bipush        86
      9002: bipush        23
      9004: bastore
      9005: dup
      9006: bipush        87
      9008: bipush        24
      9010: bastore
      9011: dup
      9012: bipush        88
      9014: bipush        25
      9016: bastore
      9017: dup
      9018: bipush        89
      9020: bipush        26
      9022: bastore
      9023: dup
      9024: bipush        90
      9026: bipush        27
      9028: bastore
      9029: dup
      9030: bipush        91
      9032: iconst_m1
      9033: bastore
      9034: dup
      9035: bipush        92
      9037: iconst_m1
      9038: bastore
      9039: dup
      9040: bipush        93
      9042: iconst_m1
      9043: bastore
      9044: dup
      9045: bipush        94
      9047: iconst_m1
      9048: bastore
      9049: dup
      9050: bipush        95
      9052: iconst_m1
      9053: bastore
      9054: dup
      9055: bipush        96
      9057: iconst_m1
      9058: bastore
      9059: dup
      9060: bipush        97
      9062: bipush        28
      9064: bastore
      9065: dup
      9066: bipush        98
      9068: bipush        29
      9070: bastore
      9071: dup
      9072: bipush        99
      9074: bipush        30
      9076: bastore
      9077: dup
      9078: bipush        100
      9080: bipush        31
      9082: bastore
      9083: dup
      9084: bipush        101
      9086: bipush        32
      9088: bastore
      9089: dup
      9090: bipush        102
      9092: bipush        33
      9094: bastore
      9095: dup
      9096: bipush        103
      9098: bipush        34
      9100: bastore
      9101: dup
      9102: bipush        104
      9104: bipush        35
      9106: bastore
      9107: dup
      9108: bipush        105
      9110: bipush        36
      9112: bastore
      9113: dup
      9114: bipush        106
      9116: bipush        37
      9118: bastore
      9119: dup
      9120: bipush        107
      9122: bipush        38
      9124: bastore
      9125: dup
      9126: bipush        108
      9128: bipush        39
      9130: bastore
      9131: dup
      9132: bipush        109
      9134: bipush        40
      9136: bastore
      9137: dup
      9138: bipush        110
      9140: bipush        41
      9142: bastore
      9143: dup
      9144: bipush        111
      9146: bipush        42
      9148: bastore
      9149: dup
      9150: bipush        112
      9152: bipush        43
      9154: bastore
      9155: dup
      9156: bipush        113
      9158: bipush        44
      9160: bastore
      9161: dup
      9162: bipush        114
      9164: bipush        45
      9166: bastore
      9167: dup
      9168: bipush        115
      9170: bipush        46
      9172: bastore
      9173: dup
      9174: bipush        116
      9176: bipush        47
      9178: bastore
      9179: dup
      9180: bipush        117
      9182: bipush        48
      9184: bastore
      9185: dup
      9186: bipush        118
      9188: bipush        49
      9190: bastore
      9191: dup
      9192: bipush        119
      9194: bipush        50
      9196: bastore
      9197: dup
      9198: bipush        120
      9200: bipush        51
      9202: bastore
      9203: dup
      9204: bipush        121
      9206: bipush        52
      9208: bastore
      9209: dup
      9210: bipush        122
      9212: bipush        53
      9214: bastore
      9215: dup
      9216: bipush        123
      9218: iconst_m1
      9219: bastore
      9220: dup
      9221: bipush        124
      9223: iconst_m1
      9224: bastore
      9225: dup
      9226: bipush        125
      9228: iconst_m1
      9229: bastore
      9230: dup
      9231: bipush        126
      9233: iconst_m1
      9234: bastore
      9235: dup
      9236: bipush        127
      9238: iconst_m1
      9239: bastore
      9240: putstatic     #31                 // Field INDEX_64:[B
      9243: return
      LineNumberTable:
        line 61: 0
        line 82: 109
        line 1110: 8115
        line 1120: 8158
        line 1188: 8543
}
SourceFile: "BCrypt.java"
BootstrapMethods:
  0: #1300 REF_invokeStatic java/lang/invoke/StringConcatFactory.makeConcatWithConstants:(Ljava/lang/invoke/MethodHandles$Lookup;Ljava/lang/String;Ljava/lang/invoke/MethodType;Ljava/lang/String;[Ljava/lang/Object;)Ljava/lang/invoke/CallSite;
    Method arguments:
      #1298 \u0001\u0001
InnerClasses:
  public static final #1311= #1307 of #1309; // Lookup=class java/lang/invoke/MethodHandles$Lookup of class java/lang/invoke/MethodHandles
