// Bytecode for: ext.mods.gameserver.model.actor.instance.DuskPriest
// File: ext\mods\gameserver\model\actor\instance\DuskPriest.class

Classfile /c:/Users/User/Desktop/BrProject/bin/main/ext/mods/gameserver/model/actor/instance/DuskPriest.class
  Last modified 9 de jul de 2026; size 3904 bytes
  MD5 checksum 8edd6e6641cba4f851e034200e4bd54b
  Compiled from "DuskPriest.java"
public class ext.mods.gameserver.model.actor.instance.DuskPriest extends ext.mods.gameserver.model.actor.instance.SignsPriest
  minor version: 0
  major version: 69
  flags: (0x0021) ACC_PUBLIC, ACC_SUPER
  this_class: #16                         // ext/mods/gameserver/model/actor/instance/DuskPriest
  super_class: #2                         // ext/mods/gameserver/model/actor/instance/SignsPriest
  interfaces: 0, fields: 0, methods: 3, attributes: 4
Constant pool:
    #1 = Methodref          #2.#3         // ext/mods/gameserver/model/actor/instance/SignsPriest."<init>":(ILext/mods/gameserver/model/actor/template/NpcTemplate;)V
    #2 = Class              #4            // ext/mods/gameserver/model/actor/instance/SignsPriest
    #3 = NameAndType        #5:#6         // "<init>":(ILext/mods/gameserver/model/actor/template/NpcTemplate;)V
    #4 = Utf8               ext/mods/gameserver/model/actor/instance/SignsPriest
    #5 = Utf8               <init>
    #6 = Utf8               (ILext/mods/gameserver/model/actor/template/NpcTemplate;)V
    #7 = String             #8            // Chat
    #8 = Utf8               Chat
    #9 = Methodref          #10.#11       // java/lang/String.startsWith:(Ljava/lang/String;)Z
   #10 = Class              #12           // java/lang/String
   #11 = NameAndType        #13:#14       // startsWith:(Ljava/lang/String;)Z
   #12 = Utf8               java/lang/String
   #13 = Utf8               startsWith
   #14 = Utf8               (Ljava/lang/String;)Z
   #15 = Methodref          #16.#17       // ext/mods/gameserver/model/actor/instance/DuskPriest.showChatWindow:(Lext/mods/gameserver/model/actor/Player;)V
   #16 = Class              #18           // ext/mods/gameserver/model/actor/instance/DuskPriest
   #17 = NameAndType        #19:#20       // showChatWindow:(Lext/mods/gameserver/model/actor/Player;)V
   #18 = Utf8               ext/mods/gameserver/model/actor/instance/DuskPriest
   #19 = Utf8               showChatWindow
   #20 = Utf8               (Lext/mods/gameserver/model/actor/Player;)V
   #21 = Methodref          #2.#22        // ext/mods/gameserver/model/actor/instance/SignsPriest.onBypassFeedback:(Lext/mods/gameserver/model/actor/Player;Ljava/lang/String;)V
   #22 = NameAndType        #23:#24       // onBypassFeedback:(Lext/mods/gameserver/model/actor/Player;Ljava/lang/String;)V
   #23 = Utf8               onBypassFeedback
   #24 = Utf8               (Lext/mods/gameserver/model/actor/Player;Ljava/lang/String;)V
   #25 = Fieldref           #26.#27       // ext/mods/gameserver/network/serverpackets/ActionFailed.STATIC_PACKET:Lext/mods/gameserver/network/serverpackets/ActionFailed;
   #26 = Class              #28           // ext/mods/gameserver/network/serverpackets/ActionFailed
   #27 = NameAndType        #29:#30       // STATIC_PACKET:Lext/mods/gameserver/network/serverpackets/ActionFailed;
   #28 = Utf8               ext/mods/gameserver/network/serverpackets/ActionFailed
   #29 = Utf8               STATIC_PACKET
   #30 = Utf8               Lext/mods/gameserver/network/serverpackets/ActionFailed;
   #31 = Methodref          #32.#33       // ext/mods/gameserver/model/actor/Player.sendPacket:(Lext/mods/gameserver/network/serverpackets/L2GameServerPacket;)V
   #32 = Class              #34           // ext/mods/gameserver/model/actor/Player
   #33 = NameAndType        #35:#36       // sendPacket:(Lext/mods/gameserver/network/serverpackets/L2GameServerPacket;)V
   #34 = Utf8               ext/mods/gameserver/model/actor/Player
   #35 = Utf8               sendPacket
   #36 = Utf8               (Lext/mods/gameserver/network/serverpackets/L2GameServerPacket;)V
   #37 = Class              #38           // ext/mods/gameserver/data/manager/SevenSignsManager
   #38 = Utf8               ext/mods/gameserver/data/manager/SevenSignsManager
   #39 = String             #40           // html/seven_signs/
   #40 = Utf8               html/seven_signs/
   #41 = Methodref          #37.#42       // ext/mods/gameserver/data/manager/SevenSignsManager.getInstance:()Lext/mods/gameserver/data/manager/SevenSignsManager;
   #42 = NameAndType        #43:#44       // getInstance:()Lext/mods/gameserver/data/manager/SevenSignsManager;
   #43 = Utf8               getInstance
   #44 = Utf8               ()Lext/mods/gameserver/data/manager/SevenSignsManager;
   #45 = Methodref          #37.#46       // ext/mods/gameserver/data/manager/SevenSignsManager.getWinningCabal:()Lext/mods/gameserver/enums/CabalType;
   #46 = NameAndType        #47:#48       // getWinningCabal:()Lext/mods/gameserver/enums/CabalType;
   #47 = Utf8               getWinningCabal
   #48 = Utf8               ()Lext/mods/gameserver/enums/CabalType;
   #49 = Fieldref           #50.#51       // ext/mods/gameserver/model/actor/instance/DuskPriest$1.$SwitchMap$ext$mods$gameserver$enums$CabalType:[I
   #50 = Class              #52           // ext/mods/gameserver/model/actor/instance/DuskPriest$1
   #51 = NameAndType        #53:#54       // $SwitchMap$ext$mods$gameserver$enums$CabalType:[I
   #52 = Utf8               ext/mods/gameserver/model/actor/instance/DuskPriest$1
   #53 = Utf8               $SwitchMap$ext$mods$gameserver$enums$CabalType
   #54 = Utf8               [I
   #55 = Methodref          #32.#56       // ext/mods/gameserver/model/actor/Player.getObjectId:()I
   #56 = NameAndType        #57:#58       // getObjectId:()I
   #57 = Utf8               getObjectId
   #58 = Utf8               ()I
   #59 = Methodref          #37.#60       // ext/mods/gameserver/data/manager/SevenSignsManager.getPlayerCabal:(I)Lext/mods/gameserver/enums/CabalType;
   #60 = NameAndType        #61:#62       // getPlayerCabal:(I)Lext/mods/gameserver/enums/CabalType;
   #61 = Utf8               getPlayerCabal
   #62 = Utf8               (I)Lext/mods/gameserver/enums/CabalType;
   #63 = Methodref          #64.#65       // ext/mods/gameserver/enums/CabalType.ordinal:()I
   #64 = Class              #66           // ext/mods/gameserver/enums/CabalType
   #65 = NameAndType        #67:#58       // ordinal:()I
   #66 = Utf8               ext/mods/gameserver/enums/CabalType
   #67 = Utf8               ordinal
   #68 = Methodref          #37.#69       // ext/mods/gameserver/data/manager/SevenSignsManager.isCompResultsPeriod:()Z
   #69 = NameAndType        #70:#71       // isCompResultsPeriod:()Z
   #70 = Utf8               isCompResultsPeriod
   #71 = Utf8               ()Z
   #72 = InvokeDynamic      #0:#73        // #0:makeConcatWithConstants:(Ljava/lang/String;)Ljava/lang/String;
   #73 = NameAndType        #74:#75       // makeConcatWithConstants:(Ljava/lang/String;)Ljava/lang/String;
   #74 = Utf8               makeConcatWithConstants
   #75 = Utf8               (Ljava/lang/String;)Ljava/lang/String;
   #76 = Methodref          #37.#77       // ext/mods/gameserver/data/manager/SevenSignsManager.isRecruitingPeriod:()Z
   #77 = NameAndType        #78:#71       // isRecruitingPeriod:()Z
   #78 = Utf8               isRecruitingPeriod
   #79 = InvokeDynamic      #1:#73        // #1:makeConcatWithConstants:(Ljava/lang/String;)Ljava/lang/String;
   #80 = Methodref          #37.#81       // ext/mods/gameserver/data/manager/SevenSignsManager.isSealValidationPeriod:()Z
   #81 = NameAndType        #82:#71       // isSealValidationPeriod:()Z
   #82 = Utf8               isSealValidationPeriod
   #83 = Fieldref           #64.#84       // ext/mods/gameserver/enums/CabalType.DUSK:Lext/mods/gameserver/enums/CabalType;
   #84 = NameAndType        #85:#86       // DUSK:Lext/mods/gameserver/enums/CabalType;
   #85 = Utf8               DUSK
   #86 = Utf8               Lext/mods/gameserver/enums/CabalType;
   #87 = Fieldref           #88.#89       // ext/mods/gameserver/enums/SealType.GNOSIS:Lext/mods/gameserver/enums/SealType;
   #88 = Class              #90           // ext/mods/gameserver/enums/SealType
   #89 = NameAndType        #91:#92       // GNOSIS:Lext/mods/gameserver/enums/SealType;
   #90 = Utf8               ext/mods/gameserver/enums/SealType
   #91 = Utf8               GNOSIS
   #92 = Utf8               Lext/mods/gameserver/enums/SealType;
   #93 = Methodref          #37.#94       // ext/mods/gameserver/data/manager/SevenSignsManager.getSealOwner:(Lext/mods/gameserver/enums/SealType;)Lext/mods/gameserver/enums/CabalType;
   #94 = NameAndType        #95:#96       // getSealOwner:(Lext/mods/gameserver/enums/SealType;)Lext/mods/gameserver/enums/CabalType;
   #95 = Utf8               getSealOwner
   #96 = Utf8               (Lext/mods/gameserver/enums/SealType;)Lext/mods/gameserver/enums/CabalType;
   #97 = InvokeDynamic      #2:#73        // #2:makeConcatWithConstants:(Ljava/lang/String;)Ljava/lang/String;
   #98 = InvokeDynamic      #3:#73        // #3:makeConcatWithConstants:(Ljava/lang/String;)Ljava/lang/String;
   #99 = Fieldref           #64.#100      // ext/mods/gameserver/enums/CabalType.NORMAL:Lext/mods/gameserver/enums/CabalType;
  #100 = NameAndType        #101:#86      // NORMAL:Lext/mods/gameserver/enums/CabalType;
  #101 = Utf8               NORMAL
  #102 = InvokeDynamic      #4:#73        // #4:makeConcatWithConstants:(Ljava/lang/String;)Ljava/lang/String;
  #103 = InvokeDynamic      #5:#73        // #5:makeConcatWithConstants:(Ljava/lang/String;)Ljava/lang/String;
  #104 = InvokeDynamic      #6:#73        // #6:makeConcatWithConstants:(Ljava/lang/String;)Ljava/lang/String;
  #105 = InvokeDynamic      #7:#73        // #7:makeConcatWithConstants:(Ljava/lang/String;)Ljava/lang/String;
  #106 = InvokeDynamic      #8:#73        // #8:makeConcatWithConstants:(Ljava/lang/String;)Ljava/lang/String;
  #107 = Class              #108          // ext/mods/gameserver/network/serverpackets/NpcHtmlMessage
  #108 = Utf8               ext/mods/gameserver/network/serverpackets/NpcHtmlMessage
  #109 = Methodref          #16.#56       // ext/mods/gameserver/model/actor/instance/DuskPriest.getObjectId:()I
  #110 = Methodref          #107.#111     // ext/mods/gameserver/network/serverpackets/NpcHtmlMessage."<init>":(I)V
  #111 = NameAndType        #5:#112       // "<init>":(I)V
  #112 = Utf8               (I)V
  #113 = Methodref          #32.#114      // ext/mods/gameserver/model/actor/Player.getLocale:()Ljava/util/Locale;
  #114 = NameAndType        #115:#116     // getLocale:()Ljava/util/Locale;
  #115 = Utf8               getLocale
  #116 = Utf8               ()Ljava/util/Locale;
  #117 = Methodref          #107.#118     // ext/mods/gameserver/network/serverpackets/NpcHtmlMessage.setFile:(Ljava/util/Locale;Ljava/lang/String;)V
  #118 = NameAndType        #119:#120     // setFile:(Ljava/util/Locale;Ljava/lang/String;)V
  #119 = Utf8               setFile
  #120 = Utf8               (Ljava/util/Locale;Ljava/lang/String;)V
  #121 = String             #122          // %objectId%
  #122 = Utf8               %objectId%
  #123 = Methodref          #107.#124     // ext/mods/gameserver/network/serverpackets/NpcHtmlMessage.replace:(Ljava/lang/String;I)V
  #124 = NameAndType        #125:#126     // replace:(Ljava/lang/String;I)V
  #125 = Utf8               replace
  #126 = Utf8               (Ljava/lang/String;I)V
  #127 = Utf8               Code
  #128 = Utf8               LineNumberTable
  #129 = Utf8               LocalVariableTable
  #130 = Utf8               this
  #131 = Utf8               Lext/mods/gameserver/model/actor/instance/DuskPriest;
  #132 = Utf8               objectId
  #133 = Utf8               I
  #134 = Utf8               template
  #135 = Utf8               Lext/mods/gameserver/model/actor/template/NpcTemplate;
  #136 = Utf8               player
  #137 = Utf8               Lext/mods/gameserver/model/actor/Player;
  #138 = Utf8               command
  #139 = Utf8               Ljava/lang/String;
  #140 = Utf8               StackMapTable
  #141 = Utf8               filename
  #142 = Utf8               winningCabal
  #143 = Utf8               html
  #144 = Utf8               Lext/mods/gameserver/network/serverpackets/NpcHtmlMessage;
  #145 = Utf8               SourceFile
  #146 = Utf8               DuskPriest.java
  #147 = Utf8               NestMembers
  #148 = Utf8               BootstrapMethods
  #149 = String             #150          // \u0001dusk_priest_5.htm
  #150 = Utf8               \u0001dusk_priest_5.htm
  #151 = String             #152          // \u0001dusk_priest_6.htm
  #152 = Utf8               \u0001dusk_priest_6.htm
  #153 = String             #154          // \u0001dusk_priest_2c.htm
  #154 = Utf8               \u0001dusk_priest_2c.htm
  #155 = String             #156          // \u0001dusk_priest_2a.htm
  #156 = Utf8               \u0001dusk_priest_2a.htm
  #157 = String             #158          // \u0001dusk_priest_2d.htm
  #158 = Utf8               \u0001dusk_priest_2d.htm
  #159 = String             #160          // \u0001dusk_priest_2b.htm
  #160 = Utf8               \u0001dusk_priest_2b.htm
  #161 = String             #162          // \u0001dusk_priest_1.htm
  #162 = Utf8               \u0001dusk_priest_1.htm
  #163 = String             #164          // \u0001dusk_priest_3.htm
  #164 = Utf8               \u0001dusk_priest_3.htm
  #165 = String             #166          // \u0001dusk_priest_4.htm
  #166 = Utf8               \u0001dusk_priest_4.htm
  #167 = MethodHandle       6:#168        // REF_invokeStatic java/lang/invoke/StringConcatFactory.makeConcatWithConstants:(Ljava/lang/invoke/MethodHandles$Lookup;Ljava/lang/String;Ljava/lang/invoke/MethodType;Ljava/lang/String;[Ljava/lang/Object;)Ljava/lang/invoke/CallSite;
  #168 = Methodref          #169.#170     // java/lang/invoke/StringConcatFactory.makeConcatWithConstants:(Ljava/lang/invoke/MethodHandles$Lookup;Ljava/lang/String;Ljava/lang/invoke/MethodType;Ljava/lang/String;[Ljava/lang/Object;)Ljava/lang/invoke/CallSite;
  #169 = Class              #171          // java/lang/invoke/StringConcatFactory
  #170 = NameAndType        #74:#172      // makeConcatWithConstants:(Ljava/lang/invoke/MethodHandles$Lookup;Ljava/lang/String;Ljava/lang/invoke/MethodType;Ljava/lang/String;[Ljava/lang/Object;)Ljava/lang/invoke/CallSite;
  #171 = Utf8               java/lang/invoke/StringConcatFactory
  #172 = Utf8               (Ljava/lang/invoke/MethodHandles$Lookup;Ljava/lang/String;Ljava/lang/invoke/MethodType;Ljava/lang/String;[Ljava/lang/Object;)Ljava/lang/invoke/CallSite;
  #173 = Utf8               InnerClasses
  #174 = Class              #175          // java/lang/invoke/MethodHandles$Lookup
  #175 = Utf8               java/lang/invoke/MethodHandles$Lookup
  #176 = Class              #177          // java/lang/invoke/MethodHandles
  #177 = Utf8               java/lang/invoke/MethodHandles
  #178 = Utf8               Lookup
{
  public ext.mods.gameserver.model.actor.instance.DuskPriest(int, ext.mods.gameserver.model.actor.template.NpcTemplate);
    descriptor: (ILext/mods/gameserver/model/actor/template/NpcTemplate;)V
    flags: (0x0001) ACC_PUBLIC
    Code:
      stack=3, locals=3, args_size=3
         0: aload_0
         1: iload_1
         2: aload_2
         3: invokespecial #1                  // Method ext/mods/gameserver/model/actor/instance/SignsPriest."<init>":(ILext/mods/gameserver/model/actor/template/NpcTemplate;)V
         6: return
      LineNumberTable:
        line 32: 0
        line 33: 6
      LocalVariableTable:
        Start  Length  Slot  Name   Signature
            0       7     0  this   Lext/mods/gameserver/model/actor/instance/DuskPriest;
            0       7     1 objectId   I
            0       7     2 template   Lext/mods/gameserver/model/actor/template/NpcTemplate;

  public void onBypassFeedback(ext.mods.gameserver.model.actor.Player, java.lang.String);
    descriptor: (Lext/mods/gameserver/model/actor/Player;Ljava/lang/String;)V
    flags: (0x0001) ACC_PUBLIC
    Code:
      stack=3, locals=3, args_size=3
         0: aload_2
         1: ldc           #7                  // String Chat
         3: invokevirtual #9                  // Method java/lang/String.startsWith:(Ljava/lang/String;)Z
         6: ifeq          17
         9: aload_0
        10: aload_1
        11: invokevirtual #15                 // Method showChatWindow:(Lext/mods/gameserver/model/actor/Player;)V
        14: goto          23
        17: aload_0
        18: aload_1
        19: aload_2
        20: invokespecial #21                 // Method ext/mods/gameserver/model/actor/instance/SignsPriest.onBypassFeedback:(Lext/mods/gameserver/model/actor/Player;Ljava/lang/String;)V
        23: return
      LineNumberTable:
        line 38: 0
        line 39: 9
        line 41: 17
        line 42: 23
      LocalVariableTable:
        Start  Length  Slot  Name   Signature
            0      24     0  this   Lext/mods/gameserver/model/actor/instance/DuskPriest;
            0      24     1 player   Lext/mods/gameserver/model/actor/Player;
            0      24     2 command   Ljava/lang/String;
      StackMapTable: number_of_entries = 2
        frame_type = 17 /* same */
        frame_type = 5 /* same */

  public void showChatWindow(ext.mods.gameserver.model.actor.Player);
    descriptor: (Lext/mods/gameserver/model/actor/Player;)V
    flags: (0x0001) ACC_PUBLIC
    Code:
      stack=3, locals=5, args_size=2
         0: aload_1
         1: getstatic     #25                 // Field ext/mods/gameserver/network/serverpackets/ActionFailed.STATIC_PACKET:Lext/mods/gameserver/network/serverpackets/ActionFailed;
         4: invokevirtual #31                 // Method ext/mods/gameserver/model/actor/Player.sendPacket:(Lext/mods/gameserver/network/serverpackets/L2GameServerPacket;)V
         7: ldc           #39                 // String html/seven_signs/
         9: astore_2
        10: invokestatic  #41                 // Method ext/mods/gameserver/data/manager/SevenSignsManager.getInstance:()Lext/mods/gameserver/data/manager/SevenSignsManager;
        13: invokevirtual #45                 // Method ext/mods/gameserver/data/manager/SevenSignsManager.getWinningCabal:()Lext/mods/gameserver/enums/CabalType;
        16: astore_3
        17: getstatic     #49                 // Field ext/mods/gameserver/model/actor/instance/DuskPriest$1.$SwitchMap$ext$mods$gameserver$enums$CabalType:[I
        20: invokestatic  #41                 // Method ext/mods/gameserver/data/manager/SevenSignsManager.getInstance:()Lext/mods/gameserver/data/manager/SevenSignsManager;
        23: aload_1
        24: invokevirtual #55                 // Method ext/mods/gameserver/model/actor/Player.getObjectId:()I
        27: invokevirtual #59                 // Method ext/mods/gameserver/data/manager/SevenSignsManager.getPlayerCabal:(I)Lext/mods/gameserver/enums/CabalType;
        30: invokevirtual #63                 // Method ext/mods/gameserver/enums/CabalType.ordinal:()I
        33: iaload
        34: lookupswitch  { // 2

                       1: 60

                       2: 184
                 default: 194
            }
        60: invokestatic  #41                 // Method ext/mods/gameserver/data/manager/SevenSignsManager.getInstance:()Lext/mods/gameserver/data/manager/SevenSignsManager;
        63: invokevirtual #68                 // Method ext/mods/gameserver/data/manager/SevenSignsManager.isCompResultsPeriod:()Z
        66: ifeq          79
        69: aload_2
        70: invokedynamic #72,  0             // InvokeDynamic #0:makeConcatWithConstants:(Ljava/lang/String;)Ljava/lang/String;
        75: astore_2
        76: goto          292
        79: invokestatic  #41                 // Method ext/mods/gameserver/data/manager/SevenSignsManager.getInstance:()Lext/mods/gameserver/data/manager/SevenSignsManager;
        82: invokevirtual #76                 // Method ext/mods/gameserver/data/manager/SevenSignsManager.isRecruitingPeriod:()Z
        85: ifeq          98
        88: aload_2
        89: invokedynamic #79,  0             // InvokeDynamic #1:makeConcatWithConstants:(Ljava/lang/String;)Ljava/lang/String;
        94: astore_2
        95: goto          292
        98: invokestatic  #41                 // Method ext/mods/gameserver/data/manager/SevenSignsManager.getInstance:()Lext/mods/gameserver/data/manager/SevenSignsManager;
       101: invokevirtual #80                 // Method ext/mods/gameserver/data/manager/SevenSignsManager.isSealValidationPeriod:()Z
       104: ifeq          174
       107: aload_3
       108: getstatic     #83                 // Field ext/mods/gameserver/enums/CabalType.DUSK:Lext/mods/gameserver/enums/CabalType;
       111: if_acmpne     147
       114: aload_3
       115: invokestatic  #41                 // Method ext/mods/gameserver/data/manager/SevenSignsManager.getInstance:()Lext/mods/gameserver/data/manager/SevenSignsManager;
       118: getstatic     #87                 // Field ext/mods/gameserver/enums/SealType.GNOSIS:Lext/mods/gameserver/enums/SealType;
       121: invokevirtual #93                 // Method ext/mods/gameserver/data/manager/SevenSignsManager.getSealOwner:(Lext/mods/gameserver/enums/SealType;)Lext/mods/gameserver/enums/CabalType;
       124: if_acmpeq     137
       127: aload_2
       128: invokedynamic #97,  0             // InvokeDynamic #2:makeConcatWithConstants:(Ljava/lang/String;)Ljava/lang/String;
       133: astore_2
       134: goto          292
       137: aload_2
       138: invokedynamic #98,  0             // InvokeDynamic #3:makeConcatWithConstants:(Ljava/lang/String;)Ljava/lang/String;
       143: astore_2
       144: goto          292
       147: aload_3
       148: getstatic     #99                 // Field ext/mods/gameserver/enums/CabalType.NORMAL:Lext/mods/gameserver/enums/CabalType;
       151: if_acmpne     164
       154: aload_2
       155: invokedynamic #102,  0            // InvokeDynamic #4:makeConcatWithConstants:(Ljava/lang/String;)Ljava/lang/String;
       160: astore_2
       161: goto          292
       164: aload_2
       165: invokedynamic #103,  0            // InvokeDynamic #5:makeConcatWithConstants:(Ljava/lang/String;)Ljava/lang/String;
       170: astore_2
       171: goto          292
       174: aload_2
       175: invokedynamic #104,  0            // InvokeDynamic #6:makeConcatWithConstants:(Ljava/lang/String;)Ljava/lang/String;
       180: astore_2
       181: goto          292
       184: aload_2
       185: invokedynamic #105,  0            // InvokeDynamic #7:makeConcatWithConstants:(Ljava/lang/String;)Ljava/lang/String;
       190: astore_2
       191: goto          292
       194: invokestatic  #41                 // Method ext/mods/gameserver/data/manager/SevenSignsManager.getInstance:()Lext/mods/gameserver/data/manager/SevenSignsManager;
       197: invokevirtual #68                 // Method ext/mods/gameserver/data/manager/SevenSignsManager.isCompResultsPeriod:()Z
       200: ifeq          213
       203: aload_2
       204: invokedynamic #72,  0             // InvokeDynamic #0:makeConcatWithConstants:(Ljava/lang/String;)Ljava/lang/String;
       209: astore_2
       210: goto          292
       213: invokestatic  #41                 // Method ext/mods/gameserver/data/manager/SevenSignsManager.getInstance:()Lext/mods/gameserver/data/manager/SevenSignsManager;
       216: invokevirtual #76                 // Method ext/mods/gameserver/data/manager/SevenSignsManager.isRecruitingPeriod:()Z
       219: ifeq          232
       222: aload_2
       223: invokedynamic #79,  0             // InvokeDynamic #1:makeConcatWithConstants:(Ljava/lang/String;)Ljava/lang/String;
       228: astore_2
       229: goto          292
       232: invokestatic  #41                 // Method ext/mods/gameserver/data/manager/SevenSignsManager.getInstance:()Lext/mods/gameserver/data/manager/SevenSignsManager;
       235: invokevirtual #80                 // Method ext/mods/gameserver/data/manager/SevenSignsManager.isSealValidationPeriod:()Z
       238: ifeq          285
       241: aload_3
       242: getstatic     #83                 // Field ext/mods/gameserver/enums/CabalType.DUSK:Lext/mods/gameserver/enums/CabalType;
       245: if_acmpne     258
       248: aload_2
       249: invokedynamic #106,  0            // InvokeDynamic #8:makeConcatWithConstants:(Ljava/lang/String;)Ljava/lang/String;
       254: astore_2
       255: goto          292
       258: aload_3
       259: getstatic     #99                 // Field ext/mods/gameserver/enums/CabalType.NORMAL:Lext/mods/gameserver/enums/CabalType;
       262: if_acmpne     275
       265: aload_2
       266: invokedynamic #102,  0            // InvokeDynamic #4:makeConcatWithConstants:(Ljava/lang/String;)Ljava/lang/String;
       271: astore_2
       272: goto          292
       275: aload_2
       276: invokedynamic #103,  0            // InvokeDynamic #5:makeConcatWithConstants:(Ljava/lang/String;)Ljava/lang/String;
       281: astore_2
       282: goto          292
       285: aload_2
       286: invokedynamic #104,  0            // InvokeDynamic #6:makeConcatWithConstants:(Ljava/lang/String;)Ljava/lang/String;
       291: astore_2
       292: new           #107                // class ext/mods/gameserver/network/serverpackets/NpcHtmlMessage
       295: dup
       296: aload_0
       297: invokevirtual #109                // Method getObjectId:()I
       300: invokespecial #110                // Method ext/mods/gameserver/network/serverpackets/NpcHtmlMessage."<init>":(I)V
       303: astore        4
       305: aload         4
       307: aload_1
       308: invokevirtual #113                // Method ext/mods/gameserver/model/actor/Player.getLocale:()Ljava/util/Locale;
       311: aload_2
       312: invokevirtual #117                // Method ext/mods/gameserver/network/serverpackets/NpcHtmlMessage.setFile:(Ljava/util/Locale;Ljava/lang/String;)V
       315: aload         4
       317: ldc           #121                // String %objectId%
       319: aload_0
       320: invokevirtual #109                // Method getObjectId:()I
       323: invokevirtual #123                // Method ext/mods/gameserver/network/serverpackets/NpcHtmlMessage.replace:(Ljava/lang/String;I)V
       326: aload_1
       327: aload         4
       329: invokevirtual #31                 // Method ext/mods/gameserver/model/actor/Player.sendPacket:(Lext/mods/gameserver/network/serverpackets/L2GameServerPacket;)V
       332: return
      LineNumberTable:
        line 47: 0
        line 49: 7
        line 51: 10
        line 53: 17
        line 56: 60
        line 57: 69
        line 58: 79
        line 59: 88
        line 60: 98
        line 62: 107
        line 64: 114
        line 65: 127
        line 67: 137
        line 69: 147
        line 70: 154
        line 72: 164
        line 75: 174
        line 76: 181
        line 79: 184
        line 80: 191
        line 83: 194
        line 84: 203
        line 85: 213
        line 86: 222
        line 87: 232
        line 89: 241
        line 90: 248
        line 91: 258
        line 92: 265
        line 94: 275
        line 97: 285
        line 101: 292
        line 102: 305
        line 103: 315
        line 104: 326
        line 105: 332
      LocalVariableTable:
        Start  Length  Slot  Name   Signature
            0     333     0  this   Lext/mods/gameserver/model/actor/instance/DuskPriest;
            0     333     1 player   Lext/mods/gameserver/model/actor/Player;
           10     323     2 filename   Ljava/lang/String;
           17     316     3 winningCabal   Lext/mods/gameserver/enums/CabalType;
          305      28     4  html   Lext/mods/gameserver/network/serverpackets/NpcHtmlMessage;
      StackMapTable: number_of_entries = 15
        frame_type = 253 /* append */
          offset_delta = 60
          locals = [ class java/lang/String, class ext/mods/gameserver/enums/CabalType ]
        frame_type = 18 /* same */
        frame_type = 18 /* same */
        frame_type = 38 /* same */
        frame_type = 9 /* same */
        frame_type = 16 /* same */
        frame_type = 9 /* same */
        frame_type = 9 /* same */
        frame_type = 9 /* same */
        frame_type = 18 /* same */
        frame_type = 18 /* same */
        frame_type = 25 /* same */
        frame_type = 16 /* same */
        frame_type = 9 /* same */
        frame_type = 6 /* same */
}
SourceFile: "DuskPriest.java"
NestMembers:
  ext/mods/gameserver/model/actor/instance/DuskPriest$1
BootstrapMethods:
  0: #167 REF_invokeStatic java/lang/invoke/StringConcatFactory.makeConcatWithConstants:(Ljava/lang/invoke/MethodHandles$Lookup;Ljava/lang/String;Ljava/lang/invoke/MethodType;Ljava/lang/String;[Ljava/lang/Object;)Ljava/lang/invoke/CallSite;
    Method arguments:
      #149 \u0001dusk_priest_5.htm
  1: #167 REF_invokeStatic java/lang/invoke/StringConcatFactory.makeConcatWithConstants:(Ljava/lang/invoke/MethodHandles$Lookup;Ljava/lang/String;Ljava/lang/invoke/MethodType;Ljava/lang/String;[Ljava/lang/Object;)Ljava/lang/invoke/CallSite;
    Method arguments:
      #151 \u0001dusk_priest_6.htm
  2: #167 REF_invokeStatic java/lang/invoke/StringConcatFactory.makeConcatWithConstants:(Ljava/lang/invoke/MethodHandles$Lookup;Ljava/lang/String;Ljava/lang/invoke/MethodType;Ljava/lang/String;[Ljava/lang/Object;)Ljava/lang/invoke/CallSite;
    Method arguments:
      #153 \u0001dusk_priest_2c.htm
  3: #167 REF_invokeStatic java/lang/invoke/StringConcatFactory.makeConcatWithConstants:(Ljava/lang/invoke/MethodHandles$Lookup;Ljava/lang/String;Ljava/lang/invoke/MethodType;Ljava/lang/String;[Ljava/lang/Object;)Ljava/lang/invoke/CallSite;
    Method arguments:
      #155 \u0001dusk_priest_2a.htm
  4: #167 REF_invokeStatic java/lang/invoke/StringConcatFactory.makeConcatWithConstants:(Ljava/lang/invoke/MethodHandles$Lookup;Ljava/lang/String;Ljava/lang/invoke/MethodType;Ljava/lang/String;[Ljava/lang/Object;)Ljava/lang/invoke/CallSite;
    Method arguments:
      #157 \u0001dusk_priest_2d.htm
  5: #167 REF_invokeStatic java/lang/invoke/StringConcatFactory.makeConcatWithConstants:(Ljava/lang/invoke/MethodHandles$Lookup;Ljava/lang/String;Ljava/lang/invoke/MethodType;Ljava/lang/String;[Ljava/lang/Object;)Ljava/lang/invoke/CallSite;
    Method arguments:
      #159 \u0001dusk_priest_2b.htm
  6: #167 REF_invokeStatic java/lang/invoke/StringConcatFactory.makeConcatWithConstants:(Ljava/lang/invoke/MethodHandles$Lookup;Ljava/lang/String;Ljava/lang/invoke/MethodType;Ljava/lang/String;[Ljava/lang/Object;)Ljava/lang/invoke/CallSite;
    Method arguments:
      #161 \u0001dusk_priest_1.htm
  7: #167 REF_invokeStatic java/lang/invoke/StringConcatFactory.makeConcatWithConstants:(Ljava/lang/invoke/MethodHandles$Lookup;Ljava/lang/String;Ljava/lang/invoke/MethodType;Ljava/lang/String;[Ljava/lang/Object;)Ljava/lang/invoke/CallSite;
    Method arguments:
      #163 \u0001dusk_priest_3.htm
  8: #167 REF_invokeStatic java/lang/invoke/StringConcatFactory.makeConcatWithConstants:(Ljava/lang/invoke/MethodHandles$Lookup;Ljava/lang/String;Ljava/lang/invoke/MethodType;Ljava/lang/String;[Ljava/lang/Object;)Ljava/lang/invoke/CallSite;
    Method arguments:
      #165 \u0001dusk_priest_4.htm
InnerClasses:
  static #50;                             // class ext/mods/gameserver/model/actor/instance/DuskPriest$1
  public static final #178= #174 of #176; // Lookup=class java/lang/invoke/MethodHandles$Lookup of class java/lang/invoke/MethodHandles
