// Bytecode for: ext.mods.gameserver.model.actor.instance.SignsPriest
// File: ext\mods\gameserver\model\actor\instance\SignsPriest.class

Classfile /c:/Users/User/Desktop/BrProject/bin/main/ext/mods/gameserver/model/actor/instance/SignsPriest.class
  Last modified 9 de jul de 2026; size 18386 bytes
  MD5 checksum 4afeda2f71b5b5a29741dc4a53710ad0
  Compiled from "SignsPriest.java"
public class ext.mods.gameserver.model.actor.instance.SignsPriest extends ext.mods.gameserver.model.actor.instance.Folk
  minor version: 0
  major version: 69
  flags: (0x0021) ACC_PUBLIC, ACC_SUPER
  this_class: #18                         // ext/mods/gameserver/model/actor/instance/SignsPriest
  super_class: #2                         // ext/mods/gameserver/model/actor/instance/Folk
  interfaces: 0, fields: 0, methods: 4, attributes: 4
Constant pool:
    #1 = Methodref          #2.#3         // ext/mods/gameserver/model/actor/instance/Folk."<init>":(ILext/mods/gameserver/model/actor/template/NpcTemplate;)V
    #2 = Class              #4            // ext/mods/gameserver/model/actor/instance/Folk
    #3 = NameAndType        #5:#6         // "<init>":(ILext/mods/gameserver/model/actor/template/NpcTemplate;)V
    #4 = Utf8               ext/mods/gameserver/model/actor/instance/Folk
    #5 = Utf8               <init>
    #6 = Utf8               (ILext/mods/gameserver/model/actor/template/NpcTemplate;)V
    #7 = Methodref          #8.#9         // ext/mods/gameserver/model/actor/Player.getCurrentFolk:()Lext/mods/gameserver/model/actor/instance/Folk;
    #8 = Class              #10           // ext/mods/gameserver/model/actor/Player
    #9 = NameAndType        #11:#12       // getCurrentFolk:()Lext/mods/gameserver/model/actor/instance/Folk;
   #10 = Utf8               ext/mods/gameserver/model/actor/Player
   #11 = Utf8               getCurrentFolk
   #12 = Utf8               ()Lext/mods/gameserver/model/actor/instance/Folk;
   #13 = Methodref          #2.#14        // ext/mods/gameserver/model/actor/instance/Folk.getObjectId:()I
   #14 = NameAndType        #15:#16       // getObjectId:()I
   #15 = Utf8               getObjectId
   #16 = Utf8               ()I
   #17 = Methodref          #18.#14       // ext/mods/gameserver/model/actor/instance/SignsPriest.getObjectId:()I
   #18 = Class              #19           // ext/mods/gameserver/model/actor/instance/SignsPriest
   #19 = Utf8               ext/mods/gameserver/model/actor/instance/SignsPriest
   #20 = String             #21           // SevenSignsDesc
   #21 = Utf8               SevenSignsDesc
   #22 = Methodref          #23.#24       // java/lang/String.startsWith:(Ljava/lang/String;)Z
   #23 = Class              #25           // java/lang/String
   #24 = NameAndType        #26:#27       // startsWith:(Ljava/lang/String;)Z
   #25 = Utf8               java/lang/String
   #26 = Utf8               startsWith
   #27 = Utf8               (Ljava/lang/String;)Z
   #28 = Methodref          #23.#29       // java/lang/String.substring:(I)Ljava/lang/String;
   #29 = NameAndType        #30:#31       // substring:(I)Ljava/lang/String;
   #30 = Utf8               substring
   #31 = Utf8               (I)Ljava/lang/String;
   #32 = Methodref          #33.#34       // java/lang/Integer.parseInt:(Ljava/lang/String;)I
   #33 = Class              #35           // java/lang/Integer
   #34 = NameAndType        #36:#37       // parseInt:(Ljava/lang/String;)I
   #35 = Utf8               java/lang/Integer
   #36 = Utf8               parseInt
   #37 = Utf8               (Ljava/lang/String;)I
   #38 = Methodref          #18.#39       // ext/mods/gameserver/model/actor/instance/SignsPriest.showChatWindow:(Lext/mods/gameserver/model/actor/Player;ILjava/lang/String;Z)V
   #39 = NameAndType        #40:#41       // showChatWindow:(Lext/mods/gameserver/model/actor/Player;ILjava/lang/String;Z)V
   #40 = Utf8               showChatWindow
   #41 = Utf8               (Lext/mods/gameserver/model/actor/Player;ILjava/lang/String;Z)V
   #42 = String             #43           // SevenSigns
   #43 = Utf8               SevenSigns
   #44 = Class              #45           // java/util/StringTokenizer
   #45 = Utf8               java/util/StringTokenizer
   #46 = Methodref          #23.#47       // java/lang/String.trim:()Ljava/lang/String;
   #47 = NameAndType        #48:#49       // trim:()Ljava/lang/String;
   #48 = Utf8               trim
   #49 = Utf8               ()Ljava/lang/String;
   #50 = Methodref          #44.#51       // java/util/StringTokenizer."<init>":(Ljava/lang/String;)V
   #51 = NameAndType        #5:#52        // "<init>":(Ljava/lang/String;)V
   #52 = Utf8               (Ljava/lang/String;)V
   #53 = Methodref          #44.#54       // java/util/StringTokenizer.nextToken:()Ljava/lang/String;
   #54 = NameAndType        #55:#49       // nextToken:()Ljava/lang/String;
   #55 = Utf8               nextToken
   #56 = Methodref          #8.#57        // ext/mods/gameserver/model/actor/Player.getInventory:()Lext/mods/gameserver/model/itemcontainer/PcInventory;
   #57 = NameAndType        #58:#59       // getInventory:()Lext/mods/gameserver/model/itemcontainer/PcInventory;
   #58 = Utf8               getInventory
   #59 = Utf8               ()Lext/mods/gameserver/model/itemcontainer/PcInventory;
   #60 = Methodref          #61.#62       // ext/mods/gameserver/model/itemcontainer/PcInventory.validateCapacity:(I)Z
   #61 = Class              #63           // ext/mods/gameserver/model/itemcontainer/PcInventory
   #62 = NameAndType        #64:#65       // validateCapacity:(I)Z
   #63 = Utf8               ext/mods/gameserver/model/itemcontainer/PcInventory
   #64 = Utf8               validateCapacity
   #65 = Utf8               (I)Z
   #66 = Fieldref           #67.#68       // ext/mods/gameserver/network/SystemMessageId.SLOTS_FULL:Lext/mods/gameserver/network/SystemMessageId;
   #67 = Class              #69           // ext/mods/gameserver/network/SystemMessageId
   #68 = NameAndType        #70:#71       // SLOTS_FULL:Lext/mods/gameserver/network/SystemMessageId;
   #69 = Utf8               ext/mods/gameserver/network/SystemMessageId
   #70 = Utf8               SLOTS_FULL
   #71 = Utf8               Lext/mods/gameserver/network/SystemMessageId;
   #72 = Methodref          #8.#73        // ext/mods/gameserver/model/actor/Player.sendPacket:(Lext/mods/gameserver/network/SystemMessageId;)V
   #73 = NameAndType        #74:#75       // sendPacket:(Lext/mods/gameserver/network/SystemMessageId;)V
   #74 = Utf8               sendPacket
   #75 = Utf8               (Lext/mods/gameserver/network/SystemMessageId;)V
   #76 = Class              #77           // ext/mods/gameserver/data/manager/SevenSignsManager
   #77 = Utf8               ext/mods/gameserver/data/manager/SevenSignsManager
   #78 = Methodref          #8.#79        // ext/mods/gameserver/model/actor/Player.reduceAdena:(IZ)Z
   #79 = NameAndType        #80:#81       // reduceAdena:(IZ)Z
   #80 = Utf8               reduceAdena
   #81 = Utf8               (IZ)Z
   #82 = Class              #83           // ext/mods/gameserver/model/actor/instance/DawnPriest
   #83 = Utf8               ext/mods/gameserver/model/actor/instance/DawnPriest
   #84 = String             #85           // dawn_no
   #85 = Utf8               dawn_no
   #86 = String             #87           // dusk_no
   #87 = Utf8               dusk_no
   #88 = Methodref          #8.#89        // ext/mods/gameserver/model/actor/Player.addItem:(IIZ)Lext/mods/gameserver/model/item/instance/ItemInstance;
   #89 = NameAndType        #90:#91       // addItem:(IIZ)Lext/mods/gameserver/model/item/instance/ItemInstance;
   #90 = Utf8               addItem
   #91 = Utf8               (IIZ)Lext/mods/gameserver/model/item/instance/ItemInstance;
   #92 = String             #93           // dawn
   #93 = Utf8               dawn
   #94 = String             #95           // dusk
   #95 = Utf8               dusk
   #96 = Fieldref           #97.#98       // ext/mods/gameserver/enums/CabalType.VALUES:[Lext/mods/gameserver/enums/CabalType;
   #97 = Class              #99           // ext/mods/gameserver/enums/CabalType
   #98 = NameAndType        #100:#101     // VALUES:[Lext/mods/gameserver/enums/CabalType;
   #99 = Utf8               ext/mods/gameserver/enums/CabalType
  #100 = Utf8               VALUES
  #101 = Utf8               [Lext/mods/gameserver/enums/CabalType;
  #102 = Methodref          #76.#103      // ext/mods/gameserver/data/manager/SevenSignsManager.getInstance:()Lext/mods/gameserver/data/manager/SevenSignsManager;
  #103 = NameAndType        #104:#105     // getInstance:()Lext/mods/gameserver/data/manager/SevenSignsManager;
  #104 = Utf8               getInstance
  #105 = Utf8               ()Lext/mods/gameserver/data/manager/SevenSignsManager;
  #106 = Methodref          #8.#14        // ext/mods/gameserver/model/actor/Player.getObjectId:()I
  #107 = Methodref          #76.#108      // ext/mods/gameserver/data/manager/SevenSignsManager.getPlayerCabal:(I)Lext/mods/gameserver/enums/CabalType;
  #108 = NameAndType        #109:#110     // getPlayerCabal:(I)Lext/mods/gameserver/enums/CabalType;
  #109 = Utf8               getPlayerCabal
  #110 = Utf8               (I)Lext/mods/gameserver/enums/CabalType;
  #111 = Fieldref           #97.#112      // ext/mods/gameserver/enums/CabalType.NORMAL:Lext/mods/gameserver/enums/CabalType;
  #112 = NameAndType        #113:#114     // NORMAL:Lext/mods/gameserver/enums/CabalType;
  #113 = Utf8               NORMAL
  #114 = Utf8               Lext/mods/gameserver/enums/CabalType;
  #115 = String             #116          // dawn_member
  #116 = Utf8               dawn_member
  #117 = String             #118          // dusk_member
  #118 = Utf8               dusk_member
  #119 = Fieldref           #120.#121     // ext/mods/Config.SEVEN_SIGNS_BYPASS_PREREQUISITES:Z
  #120 = Class              #122          // ext/mods/Config
  #121 = NameAndType        #123:#124     // SEVEN_SIGNS_BYPASS_PREREQUISITES:Z
  #122 = Utf8               ext/mods/Config
  #123 = Utf8               SEVEN_SIGNS_BYPASS_PREREQUISITES
  #124 = Utf8               Z
  #125 = Methodref          #8.#126       // ext/mods/gameserver/model/actor/Player.getClassId:()Lext/mods/gameserver/enums/actors/ClassId;
  #126 = NameAndType        #127:#128     // getClassId:()Lext/mods/gameserver/enums/actors/ClassId;
  #127 = Utf8               getClassId
  #128 = Utf8               ()Lext/mods/gameserver/enums/actors/ClassId;
  #129 = Methodref          #130.#131     // ext/mods/gameserver/enums/actors/ClassId.getLevel:()I
  #130 = Class              #132          // ext/mods/gameserver/enums/actors/ClassId
  #131 = NameAndType        #133:#16      // getLevel:()I
  #132 = Utf8               ext/mods/gameserver/enums/actors/ClassId
  #133 = Utf8               getLevel
  #134 = String             #135          // dawn_firstclass
  #135 = Utf8               dawn_firstclass
  #136 = String             #137          // dusk_firstclass
  #137 = Utf8               dusk_firstclass
  #138 = Methodref          #8.#139       // ext/mods/gameserver/model/actor/Player.getClan:()Lext/mods/gameserver/model/pledge/Clan;
  #139 = NameAndType        #140:#141     // getClan:()Lext/mods/gameserver/model/pledge/Clan;
  #140 = Utf8               getClan
  #141 = Utf8               ()Lext/mods/gameserver/model/pledge/Clan;
  #142 = Methodref          #143.#144     // ext/mods/gameserver/model/pledge/Clan.hasCastle:()Z
  #143 = Class              #145          // ext/mods/gameserver/model/pledge/Clan
  #144 = NameAndType        #146:#147     // hasCastle:()Z
  #145 = Utf8               ext/mods/gameserver/model/pledge/Clan
  #146 = Utf8               hasCastle
  #147 = Utf8               ()Z
  #148 = Fieldref           #97.#149      // ext/mods/gameserver/enums/CabalType.DUSK:Lext/mods/gameserver/enums/CabalType;
  #149 = NameAndType        #150:#114     // DUSK:Lext/mods/gameserver/enums/CabalType;
  #150 = Utf8               DUSK
  #151 = String             #152          // html/seven_signs/signs_33_dusk_no.htm
  #152 = Utf8               html/seven_signs/signs_33_dusk_no.htm
  #153 = Methodref          #18.#154      // ext/mods/gameserver/model/actor/instance/SignsPriest.showChatWindow:(Lext/mods/gameserver/model/actor/Player;Ljava/lang/String;)V
  #154 = NameAndType        #40:#155      // showChatWindow:(Lext/mods/gameserver/model/actor/Player;Ljava/lang/String;)V
  #155 = Utf8               (Lext/mods/gameserver/model/actor/Player;Ljava/lang/String;)V
  #156 = Fieldref           #97.#157      // ext/mods/gameserver/enums/CabalType.DAWN:Lext/mods/gameserver/enums/CabalType;
  #157 = NameAndType        #158:#114     // DAWN:Lext/mods/gameserver/enums/CabalType;
  #158 = Utf8               DAWN
  #159 = String             #160          // html/seven_signs/signs_33_dawn_fee.htm
  #160 = Utf8               html/seven_signs/signs_33_dawn_fee.htm
  #161 = Methodref          #8.#162       // ext/mods/gameserver/model/actor/Player.getAdena:()I
  #162 = NameAndType        #163:#16      // getAdena:()I
  #163 = Utf8               getAdena
  #164 = Integer            50000
  #165 = Methodref          #61.#166      // ext/mods/gameserver/model/itemcontainer/PcInventory.hasItems:(I)Z
  #166 = NameAndType        #167:#65      // hasItems:(I)Z
  #167 = Utf8               hasItems
  #168 = String             #169          // signs_33_dawn.htm
  #169 = Utf8               signs_33_dawn.htm
  #170 = String             #171          // signs_33_dawn_no.htm
  #171 = Utf8               signs_33_dawn_no.htm
  #172 = InvokeDynamic      #0:#173       // #0:makeConcatWithConstants:(Ljava/lang/String;)Ljava/lang/String;
  #173 = NameAndType        #174:#175     // makeConcatWithConstants:(Ljava/lang/String;)Ljava/lang/String;
  #174 = Utf8               makeConcatWithConstants
  #175 = Utf8               (Ljava/lang/String;)Ljava/lang/String;
  #176 = Methodref          #97.#177      // ext/mods/gameserver/enums/CabalType.getShortName:()Ljava/lang/String;
  #177 = NameAndType        #178:#49      // getShortName:()Ljava/lang/String;
  #178 = Utf8               getShortName
  #179 = Fieldref           #180.#181     // ext/mods/gameserver/enums/SealType.VALUES:[Lext/mods/gameserver/enums/SealType;
  #180 = Class              #182          // ext/mods/gameserver/enums/SealType
  #181 = NameAndType        #100:#183     // VALUES:[Lext/mods/gameserver/enums/SealType;
  #182 = Utf8               ext/mods/gameserver/enums/SealType
  #183 = Utf8               [Lext/mods/gameserver/enums/SealType;
  #184 = Methodref          #8.#185       // ext/mods/gameserver/model/actor/Player.destroyItemByItemId:(IIZ)Z
  #185 = NameAndType        #186:#187     // destroyItemByItemId:(IIZ)Z
  #186 = Utf8               destroyItemByItemId
  #187 = Utf8               (IIZ)Z
  #188 = String             #189          // html/seven_signs/signs_33_dawn_no.htm
  #189 = Utf8               html/seven_signs/signs_33_dawn_no.htm
  #190 = Methodref          #76.#191      // ext/mods/gameserver/data/manager/SevenSignsManager.setPlayerInfo:(ILext/mods/gameserver/enums/CabalType;Lext/mods/gameserver/enums/SealType;)Lext/mods/gameserver/enums/CabalType;
  #191 = NameAndType        #192:#193     // setPlayerInfo:(ILext/mods/gameserver/enums/CabalType;Lext/mods/gameserver/enums/SealType;)Lext/mods/gameserver/enums/CabalType;
  #192 = Utf8               setPlayerInfo
  #193 = Utf8               (ILext/mods/gameserver/enums/CabalType;Lext/mods/gameserver/enums/SealType;)Lext/mods/gameserver/enums/CabalType;
  #194 = Fieldref           #67.#195      // ext/mods/gameserver/network/SystemMessageId.SEVENSIGNS_PARTECIPATION_DAWN:Lext/mods/gameserver/network/SystemMessageId;
  #195 = NameAndType        #196:#71      // SEVENSIGNS_PARTECIPATION_DAWN:Lext/mods/gameserver/network/SystemMessageId;
  #196 = Utf8               SEVENSIGNS_PARTECIPATION_DAWN
  #197 = Fieldref           #67.#198      // ext/mods/gameserver/network/SystemMessageId.SEVENSIGNS_PARTECIPATION_DUSK:Lext/mods/gameserver/network/SystemMessageId;
  #198 = NameAndType        #199:#71      // SEVENSIGNS_PARTECIPATION_DUSK:Lext/mods/gameserver/network/SystemMessageId;
  #199 = Utf8               SEVENSIGNS_PARTECIPATION_DUSK
  #200 = Fieldref           #201.#202     // ext/mods/gameserver/model/actor/instance/SignsPriest$1.$SwitchMap$ext$mods$gameserver$enums$SealType:[I
  #201 = Class              #203          // ext/mods/gameserver/model/actor/instance/SignsPriest$1
  #202 = NameAndType        #204:#205     // $SwitchMap$ext$mods$gameserver$enums$SealType:[I
  #203 = Utf8               ext/mods/gameserver/model/actor/instance/SignsPriest$1
  #204 = Utf8               $SwitchMap$ext$mods$gameserver$enums$SealType
  #205 = Utf8               [I
  #206 = Methodref          #180.#207     // ext/mods/gameserver/enums/SealType.ordinal:()I
  #207 = NameAndType        #208:#16      // ordinal:()I
  #208 = Utf8               ordinal
  #209 = Fieldref           #67.#210      // ext/mods/gameserver/network/SystemMessageId.FIGHT_FOR_AVARICE:Lext/mods/gameserver/network/SystemMessageId;
  #210 = NameAndType        #211:#71      // FIGHT_FOR_AVARICE:Lext/mods/gameserver/network/SystemMessageId;
  #211 = Utf8               FIGHT_FOR_AVARICE
  #212 = Fieldref           #67.#213      // ext/mods/gameserver/network/SystemMessageId.FIGHT_FOR_GNOSIS:Lext/mods/gameserver/network/SystemMessageId;
  #213 = NameAndType        #214:#71      // FIGHT_FOR_GNOSIS:Lext/mods/gameserver/network/SystemMessageId;
  #214 = Utf8               FIGHT_FOR_GNOSIS
  #215 = Fieldref           #67.#216      // ext/mods/gameserver/network/SystemMessageId.FIGHT_FOR_STRIFE:Lext/mods/gameserver/network/SystemMessageId;
  #216 = NameAndType        #217:#71      // FIGHT_FOR_STRIFE:Lext/mods/gameserver/network/SystemMessageId;
  #217 = Utf8               FIGHT_FOR_STRIFE
  #218 = Methodref          #61.#219      // ext/mods/gameserver/model/itemcontainer/PcInventory.getItemByItemId:(I)Lext/mods/gameserver/model/item/instance/ItemInstance;
  #219 = NameAndType        #220:#221     // getItemByItemId:(I)Lext/mods/gameserver/model/item/instance/ItemInstance;
  #220 = Utf8               getItemByItemId
  #221 = Utf8               (I)Lext/mods/gameserver/model/item/instance/ItemInstance;
  #222 = Methodref          #223.#224     // ext/mods/gameserver/model/item/instance/ItemInstance.getCount:()I
  #223 = Class              #225          // ext/mods/gameserver/model/item/instance/ItemInstance
  #224 = NameAndType        #226:#16      // getCount:()I
  #225 = Utf8               ext/mods/gameserver/model/item/instance/ItemInstance
  #226 = Utf8               getCount
  #227 = Methodref          #76.#228      // ext/mods/gameserver/data/manager/SevenSignsManager.getPlayerContribScore:(I)I
  #228 = NameAndType        #229:#230     // getPlayerContribScore:(I)I
  #229 = Utf8               getPlayerContribScore
  #230 = Utf8               (I)I
  #231 = Fieldref           #120.#232     // ext/mods/Config.MAXIMUM_PLAYER_CONTRIB:I
  #232 = NameAndType        #233:#234     // MAXIMUM_PLAYER_CONTRIB:I
  #233 = Utf8               MAXIMUM_PLAYER_CONTRIB
  #234 = Utf8               I
  #235 = Fieldref           #67.#236      // ext/mods/gameserver/network/SystemMessageId.CONTRIB_SCORE_EXCEEDED:Lext/mods/gameserver/network/SystemMessageId;
  #236 = NameAndType        #237:#71      // CONTRIB_SCORE_EXCEEDED:Lext/mods/gameserver/network/SystemMessageId;
  #237 = Utf8               CONTRIB_SCORE_EXCEEDED
  #238 = String             #239          //
  #239 = Utf8
  #240 = String             #241          // Blue
  #241 = Utf8               Blue
  #242 = String             #243          // Green
  #243 = Utf8               Green
  #244 = String             #245          // Red
  #245 = Utf8               Red
  #246 = String             #247          // dawn_no_stones
  #247 = Utf8               dawn_no_stones
  #248 = String             #249          // dusk_no_stones
  #249 = Utf8               dusk_no_stones
  #250 = Methodref          #76.#251      // ext/mods/gameserver/data/manager/SevenSignsManager.addPlayerStoneContrib:(IIII)I
  #251 = NameAndType        #252:#253     // addPlayerStoneContrib:(IIII)I
  #252 = Utf8               addPlayerStoneContrib
  #253 = Utf8               (IIII)I
  #254 = Fieldref           #67.#255      // ext/mods/gameserver/network/SystemMessageId.CONTRIB_SCORE_INCREASED_S1:Lext/mods/gameserver/network/SystemMessageId;
  #255 = NameAndType        #256:#71      // CONTRIB_SCORE_INCREASED_S1:Lext/mods/gameserver/network/SystemMessageId;
  #256 = Utf8               CONTRIB_SCORE_INCREASED_S1
  #257 = Methodref          #258.#259     // ext/mods/gameserver/network/serverpackets/SystemMessage.getSystemMessage:(Lext/mods/gameserver/network/SystemMessageId;)Lext/mods/gameserver/network/serverpackets/SystemMessage;
  #258 = Class              #260          // ext/mods/gameserver/network/serverpackets/SystemMessage
  #259 = NameAndType        #261:#262     // getSystemMessage:(Lext/mods/gameserver/network/SystemMessageId;)Lext/mods/gameserver/network/serverpackets/SystemMessage;
  #260 = Utf8               ext/mods/gameserver/network/serverpackets/SystemMessage
  #261 = Utf8               getSystemMessage
  #262 = Utf8               (Lext/mods/gameserver/network/SystemMessageId;)Lext/mods/gameserver/network/serverpackets/SystemMessage;
  #263 = Methodref          #258.#264     // ext/mods/gameserver/network/serverpackets/SystemMessage.addItemNumber:(I)Lext/mods/gameserver/network/serverpackets/SystemMessage;
  #264 = NameAndType        #265:#266     // addItemNumber:(I)Lext/mods/gameserver/network/serverpackets/SystemMessage;
  #265 = Utf8               addItemNumber
  #266 = Utf8               (I)Lext/mods/gameserver/network/serverpackets/SystemMessage;
  #267 = Methodref          #8.#268       // ext/mods/gameserver/model/actor/Player.sendPacket:(Lext/mods/gameserver/network/serverpackets/L2GameServerPacket;)V
  #268 = NameAndType        #74:#269      // sendPacket:(Lext/mods/gameserver/network/serverpackets/L2GameServerPacket;)V
  #269 = Utf8               (Lext/mods/gameserver/network/serverpackets/L2GameServerPacket;)V
  #270 = Class              #271          // ext/mods/gameserver/network/serverpackets/NpcHtmlMessage
  #271 = Utf8               ext/mods/gameserver/network/serverpackets/NpcHtmlMessage
  #272 = Methodref          #270.#273     // ext/mods/gameserver/network/serverpackets/NpcHtmlMessage."<init>":(I)V
  #273 = NameAndType        #5:#274       // "<init>":(I)V
  #274 = Utf8               (I)V
  #275 = Methodref          #8.#276       // ext/mods/gameserver/model/actor/Player.getLocale:()Ljava/util/Locale;
  #276 = NameAndType        #277:#278     // getLocale:()Ljava/util/Locale;
  #277 = Utf8               getLocale
  #278 = Utf8               ()Ljava/util/Locale;
  #279 = String             #280          // signs_6_dawn_contribute.htm
  #280 = Utf8               signs_6_dawn_contribute.htm
  #281 = String             #282          // signs_6_dusk_contribute.htm
  #282 = Utf8               signs_6_dusk_contribute.htm
  #283 = Methodref          #270.#284     // ext/mods/gameserver/network/serverpackets/NpcHtmlMessage.setFile:(Ljava/util/Locale;Ljava/lang/String;)V
  #284 = NameAndType        #285:#286     // setFile:(Ljava/util/Locale;Ljava/lang/String;)V
  #285 = Utf8               setFile
  #286 = Utf8               (Ljava/util/Locale;Ljava/lang/String;)V
  #287 = String             #288          // %stoneColor%
  #288 = Utf8               %stoneColor%
  #289 = Methodref          #270.#290     // ext/mods/gameserver/network/serverpackets/NpcHtmlMessage.replace:(Ljava/lang/String;Ljava/lang/String;)V
  #290 = NameAndType        #291:#292     // replace:(Ljava/lang/String;Ljava/lang/String;)V
  #291 = Utf8               replace
  #292 = Utf8               (Ljava/lang/String;Ljava/lang/String;)V
  #293 = String             #294          // %stoneCount%
  #294 = Utf8               %stoneCount%
  #295 = Methodref          #270.#296     // ext/mods/gameserver/network/serverpackets/NpcHtmlMessage.replace:(Ljava/lang/String;I)V
  #296 = NameAndType        #291:#297     // replace:(Ljava/lang/String;I)V
  #297 = Utf8               (Ljava/lang/String;I)V
  #298 = String             #299          // %stoneItemId%
  #299 = Utf8               %stoneItemId%
  #300 = String             #301          // %objectId%
  #301 = Utf8               %objectId%
  #302 = Class              #303          // java/lang/Exception
  #303 = Utf8               java/lang/Exception
  #304 = String             #305          // html/seven_signs/blkmrkt_3.htm
  #305 = Utf8               html/seven_signs/blkmrkt_3.htm
  #306 = Methodref          #8.#307       // ext/mods/gameserver/model/actor/Player.getAncientAdena:()I
  #307 = NameAndType        #308:#16      // getAncientAdena:()I
  #308 = Utf8               getAncientAdena
  #309 = String             #310          // html/seven_signs/blkmrkt_4.htm
  #310 = Utf8               html/seven_signs/blkmrkt_4.htm
  #311 = Integer            2147483647
  #312 = Methodref          #61.#162      // ext/mods/gameserver/model/itemcontainer/PcInventory.getAdena:()I
  #313 = Methodref          #8.#314       // ext/mods/gameserver/model/actor/Player.reduceAncientAdena:(IZ)Z
  #314 = NameAndType        #315:#81      // reduceAncientAdena:(IZ)Z
  #315 = Utf8               reduceAncientAdena
  #316 = Methodref          #8.#317       // ext/mods/gameserver/model/actor/Player.addAdena:(IZ)V
  #317 = NameAndType        #318:#319     // addAdena:(IZ)V
  #318 = Utf8               addAdena
  #319 = Utf8               (IZ)V
  #320 = String             #321          // html/seven_signs/blkmrkt_5.htm
  #321 = Utf8               html/seven_signs/blkmrkt_5.htm
  #322 = Methodref          #76.#323      // ext/mods/gameserver/data/manager/SevenSignsManager.isSealValidationPeriod:()Z
  #323 = NameAndType        #324:#147     // isSealValidationPeriod:()Z
  #324 = Utf8               isSealValidationPeriod
  #325 = Methodref          #76.#326      // ext/mods/gameserver/data/manager/SevenSignsManager.getWinningCabal:()Lext/mods/gameserver/enums/CabalType;
  #326 = NameAndType        #327:#328     // getWinningCabal:()Lext/mods/gameserver/enums/CabalType;
  #327 = Utf8               getWinningCabal
  #328 = Utf8               ()Lext/mods/gameserver/enums/CabalType;
  #329 = Methodref          #76.#330      // ext/mods/gameserver/data/manager/SevenSignsManager.getAncientAdenaReward:(I)I
  #330 = NameAndType        #331:#230     // getAncientAdenaReward:(I)I
  #331 = Utf8               getAncientAdenaReward
  #332 = String             #333          // dawn_b
  #333 = Utf8               dawn_b
  #334 = String             #335          // dusk_b
  #335 = Utf8               dusk_b
  #336 = Methodref          #8.#337       // ext/mods/gameserver/model/actor/Player.addAncientAdena:(IZ)V
  #337 = NameAndType        #338:#319     // addAncientAdena:(IZ)V
  #338 = Utf8               addAncientAdena
  #339 = String             #340          // dawn_a
  #340 = Utf8               dawn_a
  #341 = String             #342          // dusk_a
  #342 = Utf8               dusk_a
  #343 = Methodref          #8.#344       // ext/mods/gameserver/model/actor/Player.teleportTo:(IIII)Z
  #344 = NameAndType        #345:#346     // teleportTo:(IIII)Z
  #345 = Utf8               teleportTo
  #346 = Utf8               (IIII)Z
  #347 = Fieldref           #18.#348      // ext/mods/gameserver/model/actor/instance/SignsPriest.LOGGER:Lext/mods/commons/logging/CLogger;
  #348 = NameAndType        #349:#350     // LOGGER:Lext/mods/commons/logging/CLogger;
  #349 = Utf8               LOGGER
  #350 = Utf8               Lext/mods/commons/logging/CLogger;
  #351 = String             #352          // An error occurred while teleporting a player.
  #352 = Utf8               An error occurred while teleporting a player.
  #353 = Methodref          #354.#355     // ext/mods/commons/logging/CLogger.error:(Ljava/lang/Object;Ljava/lang/Throwable;)V
  #354 = Class              #356          // ext/mods/commons/logging/CLogger
  #355 = NameAndType        #357:#358     // error:(Ljava/lang/Object;Ljava/lang/Throwable;)V
  #356 = Utf8               ext/mods/commons/logging/CLogger
  #357 = Utf8               error
  #358 = Utf8               (Ljava/lang/Object;Ljava/lang/Throwable;)V
  #359 = String             #360          // blue
  #360 = Utf8               blue
  #361 = String             #362          // green
  #362 = Utf8               green
  #363 = String             #364          // red
  #364 = Utf8               red
  #365 = Methodref          #76.#366      // ext/mods/gameserver/data/manager/SevenSignsManager.calcScore:(III)I
  #366 = NameAndType        #367:#368     // calcScore:(III)I
  #367 = Utf8               calcScore
  #368 = Utf8               (III)I
  #369 = String             #370          // signs_17_dawn.htm
  #370 = Utf8               signs_17_dawn.htm
  #371 = String             #372          // signs_17_dusk.htm
  #372 = Utf8               signs_17_dusk.htm
  #373 = String             #374          // %stoneValue%
  #374 = Utf8               %stoneValue%
  #375 = String             #376          // dawn_failed
  #376 = Utf8               dawn_failed
  #377 = String             #378          // dusk_failed
  #378 = Utf8               dusk_failed
  #379 = String             #380          // dawn_low_stones
  #380 = Utf8               dawn_low_stones
  #381 = String             #382          // dusk_low_stones
  #382 = Utf8               dusk_low_stones
  #383 = Methodref          #180.#177     // ext/mods/gameserver/enums/SealType.getShortName:()Ljava/lang/String;
  #384 = InvokeDynamic      #1:#385       // #1:makeConcatWithConstants:(Ljava/lang/String;Ljava/lang/String;)Ljava/lang/String;
  #385 = NameAndType        #174:#386     // makeConcatWithConstants:(Ljava/lang/String;Ljava/lang/String;)Ljava/lang/String;
  #386 = Utf8               (Ljava/lang/String;Ljava/lang/String;)Ljava/lang/String;
  #387 = Class              #388          // java/lang/StringBuilder
  #388 = Utf8               java/lang/StringBuilder
  #389 = Methodref          #387.#390     // java/lang/StringBuilder."<init>":()V
  #390 = NameAndType        #5:#391       // "<init>":()V
  #391 = Utf8               ()V
  #392 = String             #393          // <html><body>Priest of Dawn:<br><font color=\"LEVEL\">[ Seal Status ]</font><br>
  #393 = Utf8               <html><body>Priest of Dawn:<br><font color=\"LEVEL\">[ Seal Status ]</font><br>
  #394 = Methodref          #387.#395     // java/lang/StringBuilder.append:(Ljava/lang/String;)Ljava/lang/StringBuilder;
  #395 = NameAndType        #396:#397     // append:(Ljava/lang/String;)Ljava/lang/StringBuilder;
  #396 = Utf8               append
  #397 = Utf8               (Ljava/lang/String;)Ljava/lang/StringBuilder;
  #398 = String             #399          // <html><body>Dusk Priestess:<br><font color=\"LEVEL\">[ Status of the Seals ]</font><br>
  #399 = Utf8               <html><body>Dusk Priestess:<br><font color=\"LEVEL\">[ Status of the Seals ]</font><br>
  #400 = Methodref          #76.#401      // ext/mods/gameserver/data/manager/SevenSignsManager.getSealOwners:()Ljava/util/Map;
  #401 = NameAndType        #402:#403     // getSealOwners:()Ljava/util/Map;
  #402 = Utf8               getSealOwners
  #403 = Utf8               ()Ljava/util/Map;
  #404 = InterfaceMethodref #405.#406     // java/util/Map.entrySet:()Ljava/util/Set;
  #405 = Class              #407          // java/util/Map
  #406 = NameAndType        #408:#409     // entrySet:()Ljava/util/Set;
  #407 = Utf8               java/util/Map
  #408 = Utf8               entrySet
  #409 = Utf8               ()Ljava/util/Set;
  #410 = InterfaceMethodref #411.#412     // java/util/Set.iterator:()Ljava/util/Iterator;
  #411 = Class              #413          // java/util/Set
  #412 = NameAndType        #414:#415     // iterator:()Ljava/util/Iterator;
  #413 = Utf8               java/util/Set
  #414 = Utf8               iterator
  #415 = Utf8               ()Ljava/util/Iterator;
  #416 = InterfaceMethodref #417.#418     // java/util/Iterator.hasNext:()Z
  #417 = Class              #419          // java/util/Iterator
  #418 = NameAndType        #420:#147     // hasNext:()Z
  #419 = Utf8               java/util/Iterator
  #420 = Utf8               hasNext
  #421 = InterfaceMethodref #417.#422     // java/util/Iterator.next:()Ljava/lang/Object;
  #422 = NameAndType        #423:#424     // next:()Ljava/lang/Object;
  #423 = Utf8               next
  #424 = Utf8               ()Ljava/lang/Object;
  #425 = Class              #426          // java/util/Map$Entry
  #426 = Utf8               java/util/Map$Entry
  #427 = InterfaceMethodref #425.#428     // java/util/Map$Entry.getKey:()Ljava/lang/Object;
  #428 = NameAndType        #429:#424     // getKey:()Ljava/lang/Object;
  #429 = Utf8               getKey
  #430 = InterfaceMethodref #425.#431     // java/util/Map$Entry.getValue:()Ljava/lang/Object;
  #431 = NameAndType        #432:#424     // getValue:()Ljava/lang/Object;
  #432 = Utf8               getValue
  #433 = Methodref          #180.#434     // ext/mods/gameserver/enums/SealType.getFullName:()Ljava/lang/String;
  #434 = NameAndType        #435:#49      // getFullName:()Ljava/lang/String;
  #435 = Utf8               getFullName
  #436 = Methodref          #97.#434      // ext/mods/gameserver/enums/CabalType.getFullName:()Ljava/lang/String;
  #437 = InvokeDynamic      #2:#385       // #2:makeConcatWithConstants:(Ljava/lang/String;Ljava/lang/String;)Ljava/lang/String;
  #438 = InvokeDynamic      #3:#173       // #3:makeConcatWithConstants:(Ljava/lang/String;)Ljava/lang/String;
  #439 = InvokeDynamic      #4:#440       // #4:makeConcatWithConstants:(I)Ljava/lang/String;
  #440 = NameAndType        #174:#31      // makeConcatWithConstants:(I)Ljava/lang/String;
  #441 = Methodref          #387.#442     // java/lang/StringBuilder.toString:()Ljava/lang/String;
  #442 = NameAndType        #443:#49      // toString:()Ljava/lang/String;
  #443 = Utf8               toString
  #444 = Methodref          #270.#445     // ext/mods/gameserver/network/serverpackets/NpcHtmlMessage.setHtml:(Ljava/lang/String;)V
  #445 = NameAndType        #446:#52      // setHtml:(Ljava/lang/String;)V
  #446 = Utf8               setHtml
  #447 = String             #448          // dawn_failure
  #448 = Utf8               dawn_failure
  #449 = String             #450          // dusk_failure
  #450 = Utf8               dusk_failure
  #451 = Methodref          #61.#452      // ext/mods/gameserver/model/itemcontainer/PcInventory.getItemCount:(I)I
  #452 = NameAndType        #453:#230     // getItemCount:(I)I
  #453 = Utf8               getItemCount
  #454 = Methodref          #455.#456     // java/lang/Math.min:(II)I
  #455 = Class              #457          // java/lang/Math
  #456 = NameAndType        #458:#459     // min:(II)I
  #457 = Utf8               java/lang/Math
  #458 = Utf8               min
  #459 = Utf8               (II)I
  #460 = Methodref          #2.#461       // ext/mods/gameserver/model/actor/instance/Folk.onBypassFeedback:(Lext/mods/gameserver/model/actor/Player;Ljava/lang/String;)V
  #461 = NameAndType        #462:#155     // onBypassFeedback:(Lext/mods/gameserver/model/actor/Player;Ljava/lang/String;)V
  #462 = Utf8               onBypassFeedback
  #463 = Methodref          #18.#464      // ext/mods/gameserver/model/actor/instance/SignsPriest.getTemplate:()Lext/mods/gameserver/model/actor/template/NpcTemplate;
  #464 = NameAndType        #465:#466     // getTemplate:()Lext/mods/gameserver/model/actor/template/NpcTemplate;
  #465 = Utf8               getTemplate
  #466 = Utf8               ()Lext/mods/gameserver/model/actor/template/NpcTemplate;
  #467 = Methodref          #468.#469     // ext/mods/gameserver/model/actor/template/NpcTemplate.getNpcId:()I
  #468 = Class              #470          // ext/mods/gameserver/model/actor/template/NpcTemplate
  #469 = NameAndType        #471:#16      // getNpcId:()I
  #470 = Utf8               ext/mods/gameserver/model/actor/template/NpcTemplate
  #471 = Utf8               getNpcId
  #472 = String             #473          // html/seven_signs/
  #473 = Utf8               html/seven_signs/
  #474 = InvokeDynamic      #5:#173       // #5:makeConcatWithConstants:(Ljava/lang/String;)Ljava/lang/String;
  #475 = Fieldref           #120.#476     // ext/mods/Config.STRICT_SEVENSIGNS:Z
  #476 = NameAndType        #477:#124     // STRICT_SEVENSIGNS:Z
  #477 = Utf8               STRICT_SEVENSIGNS
  #478 = Fieldref           #180.#479     // ext/mods/gameserver/enums/SealType.AVARICE:Lext/mods/gameserver/enums/SealType;
  #479 = NameAndType        #480:#481     // AVARICE:Lext/mods/gameserver/enums/SealType;
  #480 = Utf8               AVARICE
  #481 = Utf8               Lext/mods/gameserver/enums/SealType;
  #482 = Methodref          #76.#483      // ext/mods/gameserver/data/manager/SevenSignsManager.getSealOwner:(Lext/mods/gameserver/enums/SealType;)Lext/mods/gameserver/enums/CabalType;
  #483 = NameAndType        #484:#485     // getSealOwner:(Lext/mods/gameserver/enums/SealType;)Lext/mods/gameserver/enums/CabalType;
  #484 = Utf8               getSealOwner
  #485 = Utf8               (Lext/mods/gameserver/enums/SealType;)Lext/mods/gameserver/enums/CabalType;
  #486 = Fieldref           #201.#487     // ext/mods/gameserver/model/actor/instance/SignsPriest$1.$SwitchMap$ext$mods$gameserver$enums$CabalType:[I
  #487 = NameAndType        #488:#205     // $SwitchMap$ext$mods$gameserver$enums$CabalType:[I
  #488 = Utf8               $SwitchMap$ext$mods$gameserver$enums$CabalType
  #489 = Methodref          #97.#207      // ext/mods/gameserver/enums/CabalType.ordinal:()I
  #490 = Fieldref           #67.#491      // ext/mods/gameserver/network/SystemMessageId.CAN_BE_USED_BY_DAWN:Lext/mods/gameserver/network/SystemMessageId;
  #491 = NameAndType        #492:#71      // CAN_BE_USED_BY_DAWN:Lext/mods/gameserver/network/SystemMessageId;
  #492 = Utf8               CAN_BE_USED_BY_DAWN
  #493 = Fieldref           #494.#495     // ext/mods/gameserver/network/serverpackets/ActionFailed.STATIC_PACKET:Lext/mods/gameserver/network/serverpackets/ActionFailed;
  #494 = Class              #496          // ext/mods/gameserver/network/serverpackets/ActionFailed
  #495 = NameAndType        #497:#498     // STATIC_PACKET:Lext/mods/gameserver/network/serverpackets/ActionFailed;
  #496 = Utf8               ext/mods/gameserver/network/serverpackets/ActionFailed
  #497 = Utf8               STATIC_PACKET
  #498 = Utf8               Lext/mods/gameserver/network/serverpackets/ActionFailed;
  #499 = Fieldref           #67.#500      // ext/mods/gameserver/network/SystemMessageId.CAN_BE_USED_BY_DUSK:Lext/mods/gameserver/network/SystemMessageId;
  #500 = NameAndType        #501:#71      // CAN_BE_USED_BY_DUSK:Lext/mods/gameserver/network/SystemMessageId;
  #501 = Utf8               CAN_BE_USED_BY_DUSK
  #502 = Fieldref           #67.#503      // ext/mods/gameserver/network/SystemMessageId.QUEST_EVENT_PERIOD:Lext/mods/gameserver/network/SystemMessageId;
  #503 = NameAndType        #504:#71      // QUEST_EVENT_PERIOD:Lext/mods/gameserver/network/SystemMessageId;
  #504 = Utf8               QUEST_EVENT_PERIOD
  #505 = InvokeDynamic      #6:#173       // #6:makeConcatWithConstants:(Ljava/lang/String;)Ljava/lang/String;
  #506 = Fieldref           #180.#507     // ext/mods/gameserver/enums/SealType.GNOSIS:Lext/mods/gameserver/enums/SealType;
  #507 = NameAndType        #508:#481     // GNOSIS:Lext/mods/gameserver/enums/SealType;
  #508 = Utf8               GNOSIS
  #509 = InvokeDynamic      #7:#173       // #7:makeConcatWithConstants:(Ljava/lang/String;)Ljava/lang/String;
  #510 = Methodref          #18.#511      // ext/mods/gameserver/model/actor/instance/SignsPriest.getHtmlPath:(Lext/mods/gameserver/model/actor/Player;II)Ljava/lang/String;
  #511 = NameAndType        #512:#513     // getHtmlPath:(Lext/mods/gameserver/model/actor/Player;II)Ljava/lang/String;
  #512 = Utf8               getHtmlPath
  #513 = Utf8               (Lext/mods/gameserver/model/actor/Player;II)Ljava/lang/String;
  #514 = InvokeDynamic      #8:#440       // #8:makeConcatWithConstants:(I)Ljava/lang/String;
  #515 = InvokeDynamic      #9:#440       // #9:makeConcatWithConstants:(I)Ljava/lang/String;
  #516 = InvokeDynamic      #10:#385      // #10:makeConcatWithConstants:(Ljava/lang/String;Ljava/lang/String;)Ljava/lang/String;
  #517 = InvokeDynamic      #11:#173      // #11:makeConcatWithConstants:(Ljava/lang/String;)Ljava/lang/String;
  #518 = String             #519          // .htm
  #519 = Utf8               .htm
  #520 = Utf8               Code
  #521 = Utf8               LineNumberTable
  #522 = Utf8               LocalVariableTable
  #523 = Utf8               this
  #524 = Utf8               Lext/mods/gameserver/model/actor/instance/SignsPriest;
  #525 = Utf8               objectId
  #526 = Utf8               template
  #527 = Utf8               Lext/mods/gameserver/model/actor/template/NpcTemplate;
  #528 = Utf8               classLevel
  #529 = Utf8               cabal
  #530 = Utf8               canPayFee
  #531 = Utf8               seal
  #532 = Utf8               tempContribScore
  #533 = Utf8               redContribCount
  #534 = Utf8               greenContribCount
  #535 = Utf8               blueContribCount
  #536 = Utf8               stoneColor
  #537 = Utf8               Ljava/lang/String;
  #538 = Utf8               stoneCount
  #539 = Utf8               stoneId
  #540 = Utf8               html
  #541 = Utf8               Lext/mods/gameserver/network/serverpackets/NpcHtmlMessage;
  #542 = Utf8               stoneType
  #543 = Utf8               blueStones
  #544 = Utf8               Lext/mods/gameserver/model/item/instance/ItemInstance;
  #545 = Utf8               greenStones
  #546 = Utf8               redStones
  #547 = Utf8               blueStoneCount
  #548 = Utf8               greenStoneCount
  #549 = Utf8               redStoneCount
  #550 = Utf8               contribScore
  #551 = Utf8               stonesFound
  #552 = Utf8               e
  #553 = Utf8               Ljava/lang/Exception;
  #554 = Utf8               amount
  #555 = Utf8               reward
  #556 = Utf8               x
  #557 = Utf8               y
  #558 = Utf8               z
  #559 = Utf8               ancientAdenaCost
  #560 = Utf8               blueStonesAll
  #561 = Utf8               greenStonesAll
  #562 = Utf8               redStonesAll
  #563 = Utf8               blueStoneCountAll
  #564 = Utf8               greenStoneCountAll
  #565 = Utf8               redStoneCountAll
  #566 = Utf8               ancientAdenaRewardAll
  #567 = Utf8               stoneValue
  #568 = Utf8               stoneInstance
  #569 = Utf8               itemId
  #570 = Utf8               convertItem
  #571 = Utf8               s
  #572 = Utf8               so
  #573 = Utf8               entry
  #574 = Utf8               Ljava/util/Map$Entry;
  #575 = Utf8               sb
  #576 = Utf8               Ljava/lang/StringBuilder;
  #577 = Utf8               score
  #578 = Utf8               maxStoneCountToContribute
  #579 = Utf8               st
  #580 = Utf8               Ljava/util/StringTokenizer;
  #581 = Utf8               value
  #582 = Utf8               player
  #583 = Utf8               Lext/mods/gameserver/model/actor/Player;
  #584 = Utf8               command
  #585 = Utf8               LocalVariableTypeTable
  #586 = Utf8               Ljava/util/Map$Entry<Lext/mods/gameserver/enums/SealType;Lext/mods/gameserver/enums/CabalType;>;
  #587 = Utf8               StackMapTable
  #588 = Class              #589          // java/util/Locale
  #589 = Utf8               java/util/Locale
  #590 = Utf8               (Lext/mods/gameserver/model/actor/Player;I)V
  #591 = Utf8               sealAvariceOwner
  #592 = Utf8               sealGnosisOwner
  #593 = Utf8               val
  #594 = Utf8               npcId
  #595 = Utf8               filename
  #596 = Utf8               playerCabal
  #597 = Utf8               winningCabal
  #598 = Utf8               suffix
  #599 = Utf8               isDescription
  #600 = Utf8               SourceFile
  #601 = Utf8               SignsPriest.java
  #602 = Utf8               NestMembers
  #603 = Utf8               BootstrapMethods
  #604 = String             #605          // html/seven_signs/\u0001
  #605 = Utf8               html/seven_signs/\u0001
  #606 = String             #607          // \u0001_\u0001
  #607 = Utf8               \u0001_\u0001
  #608 = String             #609          // [\u0001: \u0001]<br>
  #609 = Utf8               [\u0001: \u0001]<br>
  #610 = String             #611          // [\u0001: Nothingness]<br>
  #611 = Utf8               [\u0001: Nothingness]<br>
  #612 = String             #613          // <a action=\"bypass -h npc_\u0001_Chat 0\">Go back.</a></body></html>
  #613 = Utf8               <a action=\"bypass -h npc_\u0001_Chat 0\">Go back.</a></body></html>
  #614 = String             #615          // \u0001blkmrkt_1.htm
  #615 = Utf8               \u0001blkmrkt_1.htm
  #616 = String             #617          // \u0001mammmerch_1.htm
  #617 = Utf8               \u0001mammmerch_1.htm
  #618 = String             #619          // \u0001mammblack_1.htm
  #619 = Utf8               \u0001mammblack_1.htm
  #620 = String             #621          // desc_\u0001
  #621 = Utf8               desc_\u0001
  #622 = String             #623          // signs_\u0001
  #623 = Utf8               signs_\u0001
  #624 = String             #625          // \u0001\u0001
  #625 = Utf8               \u0001\u0001
  #626 = String             #627          // _\u0001.htm
  #627 = Utf8               _\u0001.htm
  #628 = MethodHandle       6:#629        // REF_invokeStatic java/lang/invoke/StringConcatFactory.makeConcatWithConstants:(Ljava/lang/invoke/MethodHandles$Lookup;Ljava/lang/String;Ljava/lang/invoke/MethodType;Ljava/lang/String;[Ljava/lang/Object;)Ljava/lang/invoke/CallSite;
  #629 = Methodref          #630.#631     // java/lang/invoke/StringConcatFactory.makeConcatWithConstants:(Ljava/lang/invoke/MethodHandles$Lookup;Ljava/lang/String;Ljava/lang/invoke/MethodType;Ljava/lang/String;[Ljava/lang/Object;)Ljava/lang/invoke/CallSite;
  #630 = Class              #632          // java/lang/invoke/StringConcatFactory
  #631 = NameAndType        #174:#633     // makeConcatWithConstants:(Ljava/lang/invoke/MethodHandles$Lookup;Ljava/lang/String;Ljava/lang/invoke/MethodType;Ljava/lang/String;[Ljava/lang/Object;)Ljava/lang/invoke/CallSite;
  #632 = Utf8               java/lang/invoke/StringConcatFactory
  #633 = Utf8               (Ljava/lang/invoke/MethodHandles$Lookup;Ljava/lang/String;Ljava/lang/invoke/MethodType;Ljava/lang/String;[Ljava/lang/Object;)Ljava/lang/invoke/CallSite;
  #634 = Utf8               InnerClasses
  #635 = Utf8               Entry
  #636 = Class              #637          // java/lang/invoke/MethodHandles$Lookup
  #637 = Utf8               java/lang/invoke/MethodHandles$Lookup
  #638 = Class              #639          // java/lang/invoke/MethodHandles
  #639 = Utf8               java/lang/invoke/MethodHandles
  #640 = Utf8               Lookup
{
  public ext.mods.gameserver.model.actor.instance.SignsPriest(int, ext.mods.gameserver.model.actor.template.NpcTemplate);
    descriptor: (ILext/mods/gameserver/model/actor/template/NpcTemplate;)V
    flags: (0x0001) ACC_PUBLIC
    Code:
      stack=3, locals=3, args_size=3
         0: aload_0
         1: iload_1
         2: aload_2
         3: invokespecial #1                  // Method ext/mods/gameserver/model/actor/instance/Folk."<init>":(ILext/mods/gameserver/model/actor/template/NpcTemplate;)V
         6: return
      LineNumberTable:
        line 39: 0
        line 40: 6
      LocalVariableTable:
        Start  Length  Slot  Name   Signature
            0       7     0  this   Lext/mods/gameserver/model/actor/instance/SignsPriest;
            0       7     1 objectId   I
            0       7     2 template   Lext/mods/gameserver/model/actor/template/NpcTemplate;

  public void onBypassFeedback(ext.mods.gameserver.model.actor.Player, java.lang.String);
    descriptor: (Lext/mods/gameserver/model/actor/Player;Ljava/lang/String;)V
    flags: (0x0001) ACC_PUBLIC
    Code:
      stack=5, locals=32, args_size=3
         0: aload_1
         1: invokevirtual #7                  // Method ext/mods/gameserver/model/actor/Player.getCurrentFolk:()Lext/mods/gameserver/model/actor/instance/Folk;
         4: ifnull        21
         7: aload_1
         8: invokevirtual #7                  // Method ext/mods/gameserver/model/actor/Player.getCurrentFolk:()Lext/mods/gameserver/model/actor/instance/Folk;
        11: invokevirtual #13                 // Method ext/mods/gameserver/model/actor/instance/Folk.getObjectId:()I
        14: aload_0
        15: invokevirtual #17                 // Method getObjectId:()I
        18: if_icmpeq     22
        21: return
        22: aload_2
        23: ldc           #20                 // String SevenSignsDesc
        25: invokevirtual #22                 // Method java/lang/String.startsWith:(Ljava/lang/String;)Z
        28: ifeq          50
        31: aload_0
        32: aload_1
        33: aload_2
        34: bipush        15
        36: invokevirtual #28                 // Method java/lang/String.substring:(I)Ljava/lang/String;
        39: invokestatic  #32                 // Method java/lang/Integer.parseInt:(Ljava/lang/String;)I
        42: aconst_null
        43: iconst_1
        44: invokevirtual #38                 // Method showChatWindow:(Lext/mods/gameserver/model/actor/Player;ILjava/lang/String;Z)V
        47: goto          3072
        50: aload_2
        51: ldc           #42                 // String SevenSigns
        53: invokevirtual #22                 // Method java/lang/String.startsWith:(Ljava/lang/String;)Z
        56: ifeq          3066
        59: new           #44                 // class java/util/StringTokenizer
        62: dup
        63: aload_2
        64: invokevirtual #46                 // Method java/lang/String.trim:()Ljava/lang/String;
        67: invokespecial #50                 // Method java/util/StringTokenizer."<init>":(Ljava/lang/String;)V
        70: astore_3
        71: aload_3
        72: invokevirtual #53                 // Method java/util/StringTokenizer.nextToken:()Ljava/lang/String;
        75: pop
        76: aload_3
        77: invokevirtual #53                 // Method java/util/StringTokenizer.nextToken:()Ljava/lang/String;
        80: invokestatic  #32                 // Method java/lang/Integer.parseInt:(Ljava/lang/String;)I
        83: istore        4
        85: iload         4
        87: tableswitch   { // 2 to 34

                       2: 232

                       3: 566

                       4: 595

                       5: 834

                       6: 900

                       7: 1443

                       8: 566

                       9: 1553

                      10: 3054

                      11: 1676

                      12: 3054

                      13: 3054

                      14: 3054

                      15: 3054

                      16: 1759

                      17: 1784

                      18: 2240

                      19: 2486

                      20: 2538

                      21: 2737

                      22: 3054

                      23: 3054

                      24: 3054

                      25: 3054

                      26: 3054

                      27: 3054

                      28: 3054

                      29: 3054

                      30: 3054

                      31: 3054

                      32: 3054

                      33: 320

                      34: 512
                 default: 3054
            }
       232: aload_1
       233: invokevirtual #56                 // Method ext/mods/gameserver/model/actor/Player.getInventory:()Lext/mods/gameserver/model/itemcontainer/PcInventory;
       236: iconst_1
       237: invokevirtual #60                 // Method ext/mods/gameserver/model/itemcontainer/PcInventory.validateCapacity:(I)Z
       240: ifne          251
       243: aload_1
       244: getstatic     #66                 // Field ext/mods/gameserver/network/SystemMessageId.SLOTS_FULL:Lext/mods/gameserver/network/SystemMessageId;
       247: invokevirtual #72                 // Method ext/mods/gameserver/model/actor/Player.sendPacket:(Lext/mods/gameserver/network/SystemMessageId;)V
       250: return
       251: aload_1
       252: sipush        500
       255: iconst_1
       256: invokevirtual #78                 // Method ext/mods/gameserver/model/actor/Player.reduceAdena:(IZ)Z
       259: ifne          285
       262: aload_0
       263: aload_1
       264: iload         4
       266: aload_0
       267: instanceof    #82                 // class ext/mods/gameserver/model/actor/instance/DawnPriest
       270: ifeq          278
       273: ldc           #84                 // String dawn_no
       275: goto          280
       278: ldc           #86                 // String dusk_no
       280: iconst_0
       281: invokevirtual #38                 // Method showChatWindow:(Lext/mods/gameserver/model/actor/Player;ILjava/lang/String;Z)V
       284: return
       285: aload_1
       286: sipush        5707
       289: iconst_1
       290: iconst_1
       291: invokevirtual #88                 // Method ext/mods/gameserver/model/actor/Player.addItem:(IIZ)Lext/mods/gameserver/model/item/instance/ItemInstance;
       294: pop
       295: aload_0
       296: aload_1
       297: iload         4
       299: aload_0
       300: instanceof    #82                 // class ext/mods/gameserver/model/actor/instance/DawnPriest
       303: ifeq          311
       306: ldc           #92                 // String dawn
       308: goto          313
       311: ldc           #94                 // String dusk
       313: iconst_0
       314: invokevirtual #38                 // Method showChatWindow:(Lext/mods/gameserver/model/actor/Player;ILjava/lang/String;Z)V
       317: goto          3063
       320: getstatic     #96                 // Field ext/mods/gameserver/enums/CabalType.VALUES:[Lext/mods/gameserver/enums/CabalType;
       323: aload_3
       324: invokevirtual #53                 // Method java/util/StringTokenizer.nextToken:()Ljava/lang/String;
       327: invokestatic  #32                 // Method java/lang/Integer.parseInt:(Ljava/lang/String;)I
       330: aaload
       331: astore        5
       333: invokestatic  #102                // Method ext/mods/gameserver/data/manager/SevenSignsManager.getInstance:()Lext/mods/gameserver/data/manager/SevenSignsManager;
       336: aload_1
       337: invokevirtual #106                // Method ext/mods/gameserver/model/actor/Player.getObjectId:()I
       340: invokevirtual #107                // Method ext/mods/gameserver/data/manager/SevenSignsManager.getPlayerCabal:(I)Lext/mods/gameserver/enums/CabalType;
       343: getstatic     #111                // Field ext/mods/gameserver/enums/CabalType.NORMAL:Lext/mods/gameserver/enums/CabalType;
       346: if_acmpeq     372
       349: aload_0
       350: aload_1
       351: iload         4
       353: aload_0
       354: instanceof    #82                 // class ext/mods/gameserver/model/actor/instance/DawnPriest
       357: ifeq          365
       360: ldc           #115                // String dawn_member
       362: goto          367
       365: ldc           #117                // String dusk_member
       367: iconst_0
       368: invokevirtual #38                 // Method showChatWindow:(Lext/mods/gameserver/model/actor/Player;ILjava/lang/String;Z)V
       371: return
       372: getstatic     #119                // Field ext/mods/Config.SEVEN_SIGNS_BYPASS_PREREQUISITES:Z
       375: ifne          487
       378: aload_1
       379: invokevirtual #125                // Method ext/mods/gameserver/model/actor/Player.getClassId:()Lext/mods/gameserver/enums/actors/ClassId;
       382: invokevirtual #129                // Method ext/mods/gameserver/enums/actors/ClassId.getLevel:()I
       385: istore        6
       387: iload         6
       389: ifne          415
       392: aload_0
       393: aload_1
       394: iload         4
       396: aload_0
       397: instanceof    #82                 // class ext/mods/gameserver/model/actor/instance/DawnPriest
       400: ifeq          408
       403: ldc           #134                // String dawn_firstclass
       405: goto          410
       408: ldc           #136                // String dusk_firstclass
       410: iconst_0
       411: invokevirtual #38                 // Method showChatWindow:(Lext/mods/gameserver/model/actor/Player;ILjava/lang/String;Z)V
       414: return
       415: iload         6
       417: iconst_1
       418: if_icmple     487
       421: aload_1
       422: invokevirtual #138                // Method ext/mods/gameserver/model/actor/Player.getClan:()Lext/mods/gameserver/model/pledge/Clan;
       425: ifnull        442
       428: aload_1
       429: invokevirtual #138                // Method ext/mods/gameserver/model/actor/Player.getClan:()Lext/mods/gameserver/model/pledge/Clan;
       432: invokevirtual #142                // Method ext/mods/gameserver/model/pledge/Clan.hasCastle:()Z
       435: ifeq          442
       438: iconst_1
       439: goto          443
       442: iconst_0
       443: istore        7
       445: aload         5
       447: getstatic     #148                // Field ext/mods/gameserver/enums/CabalType.DUSK:Lext/mods/gameserver/enums/CabalType;
       450: if_acmpne     466
       453: iload         7
       455: ifeq          466
       458: aload_0
       459: aload_1
       460: ldc           #151                // String html/seven_signs/signs_33_dusk_no.htm
       462: invokevirtual #153                // Method showChatWindow:(Lext/mods/gameserver/model/actor/Player;Ljava/lang/String;)V
       465: return
       466: aload         5
       468: getstatic     #156                // Field ext/mods/gameserver/enums/CabalType.DAWN:Lext/mods/gameserver/enums/CabalType;
       471: if_acmpne     487
       474: iload         7
       476: ifne          487
       479: aload_0
       480: aload_1
       481: ldc           #159                // String html/seven_signs/signs_33_dawn_fee.htm
       483: invokevirtual #153                // Method showChatWindow:(Lext/mods/gameserver/model/actor/Player;Ljava/lang/String;)V
       486: return
       487: aload_0
       488: aload_1
       489: iload         4
       491: aload_0
       492: instanceof    #82                 // class ext/mods/gameserver/model/actor/instance/DawnPriest
       495: ifeq          503
       498: ldc           #92                 // String dawn
       500: goto          505
       503: ldc           #94                 // String dusk
       505: iconst_0
       506: invokevirtual #38                 // Method showChatWindow:(Lext/mods/gameserver/model/actor/Player;ILjava/lang/String;Z)V
       509: goto          3063
       512: aload_1
       513: invokevirtual #161                // Method ext/mods/gameserver/model/actor/Player.getAdena:()I
       516: ldc           #164                // int 50000
       518: if_icmpge     534
       521: aload_1
       522: invokevirtual #56                 // Method ext/mods/gameserver/model/actor/Player.getInventory:()Lext/mods/gameserver/model/itemcontainer/PcInventory;
       525: sipush        6388
       528: invokevirtual #165                // Method ext/mods/gameserver/model/itemcontainer/PcInventory.hasItems:(I)Z
       531: ifeq          538
       534: iconst_1
       535: goto          539
       538: iconst_0
       539: istore        6
       541: aload_0
       542: aload_1
       543: iload         6
       545: ifeq          553
       548: ldc           #168                // String signs_33_dawn.htm
       550: goto          555
       553: ldc           #170                // String signs_33_dawn_no.htm
       555: invokedynamic #172,  0            // InvokeDynamic #0:makeConcatWithConstants:(Ljava/lang/String;)Ljava/lang/String;
       560: invokevirtual #153                // Method showChatWindow:(Lext/mods/gameserver/model/actor/Player;Ljava/lang/String;)V
       563: goto          3063
       566: getstatic     #96                 // Field ext/mods/gameserver/enums/CabalType.VALUES:[Lext/mods/gameserver/enums/CabalType;
       569: aload_3
       570: invokevirtual #53                 // Method java/util/StringTokenizer.nextToken:()Ljava/lang/String;
       573: invokestatic  #32                 // Method java/lang/Integer.parseInt:(Ljava/lang/String;)I
       576: aaload
       577: astore        5
       579: aload_0
       580: aload_1
       581: iload         4
       583: aload         5
       585: invokevirtual #176                // Method ext/mods/gameserver/enums/CabalType.getShortName:()Ljava/lang/String;
       588: iconst_0
       589: invokevirtual #38                 // Method showChatWindow:(Lext/mods/gameserver/model/actor/Player;ILjava/lang/String;Z)V
       592: goto          3063
       595: getstatic     #96                 // Field ext/mods/gameserver/enums/CabalType.VALUES:[Lext/mods/gameserver/enums/CabalType;
       598: aload_3
       599: invokevirtual #53                 // Method java/util/StringTokenizer.nextToken:()Ljava/lang/String;
       602: invokestatic  #32                 // Method java/lang/Integer.parseInt:(Ljava/lang/String;)I
       605: aaload
       606: astore        5
       608: getstatic     #179                // Field ext/mods/gameserver/enums/SealType.VALUES:[Lext/mods/gameserver/enums/SealType;
       611: aload_3
       612: invokevirtual #53                 // Method java/util/StringTokenizer.nextToken:()Ljava/lang/String;
       615: invokestatic  #32                 // Method java/lang/Integer.parseInt:(Ljava/lang/String;)I
       618: aaload
       619: astore        7
       621: getstatic     #119                // Field ext/mods/Config.SEVEN_SIGNS_BYPASS_PREREQUISITES:Z
       624: ifne          715
       627: aload_1
       628: invokevirtual #138                // Method ext/mods/gameserver/model/actor/Player.getClan:()Lext/mods/gameserver/model/pledge/Clan;
       631: ifnull        648
       634: aload_1
       635: invokevirtual #138                // Method ext/mods/gameserver/model/actor/Player.getClan:()Lext/mods/gameserver/model/pledge/Clan;
       638: invokevirtual #142                // Method ext/mods/gameserver/model/pledge/Clan.hasCastle:()Z
       641: ifeq          648
       644: iconst_1
       645: goto          649
       648: iconst_0
       649: istore        8
       651: aload         5
       653: getstatic     #148                // Field ext/mods/gameserver/enums/CabalType.DUSK:Lext/mods/gameserver/enums/CabalType;
       656: if_acmpne     672
       659: iload         8
       661: ifeq          672
       664: aload_0
       665: aload_1
       666: ldc           #151                // String html/seven_signs/signs_33_dusk_no.htm
       668: invokevirtual #153                // Method showChatWindow:(Lext/mods/gameserver/model/actor/Player;Ljava/lang/String;)V
       671: return
       672: aload         5
       674: getstatic     #156                // Field ext/mods/gameserver/enums/CabalType.DAWN:Lext/mods/gameserver/enums/CabalType;
       677: if_acmpne     715
       680: iload         8
       682: ifne          715
       685: aload_1
       686: sipush        6388
       689: iconst_1
       690: iconst_0
       691: invokevirtual #184                // Method ext/mods/gameserver/model/actor/Player.destroyItemByItemId:(IIZ)Z
       694: ifne          715
       697: aload_1
       698: ldc           #164                // int 50000
       700: iconst_0
       701: invokevirtual #78                 // Method ext/mods/gameserver/model/actor/Player.reduceAdena:(IZ)Z
       704: ifne          715
       707: aload_0
       708: aload_1
       709: ldc           #188                // String html/seven_signs/signs_33_dawn_no.htm
       711: invokevirtual #153                // Method showChatWindow:(Lext/mods/gameserver/model/actor/Player;Ljava/lang/String;)V
       714: return
       715: invokestatic  #102                // Method ext/mods/gameserver/data/manager/SevenSignsManager.getInstance:()Lext/mods/gameserver/data/manager/SevenSignsManager;
       718: aload_1
       719: invokevirtual #106                // Method ext/mods/gameserver/model/actor/Player.getObjectId:()I
       722: aload         5
       724: aload         7
       726: invokevirtual #190                // Method ext/mods/gameserver/data/manager/SevenSignsManager.setPlayerInfo:(ILext/mods/gameserver/enums/CabalType;Lext/mods/gameserver/enums/SealType;)Lext/mods/gameserver/enums/CabalType;
       729: pop
       730: aload         5
       732: getstatic     #156                // Field ext/mods/gameserver/enums/CabalType.DAWN:Lext/mods/gameserver/enums/CabalType;
       735: if_acmpne     748
       738: aload_1
       739: getstatic     #194                // Field ext/mods/gameserver/network/SystemMessageId.SEVENSIGNS_PARTECIPATION_DAWN:Lext/mods/gameserver/network/SystemMessageId;
       742: invokevirtual #72                 // Method ext/mods/gameserver/model/actor/Player.sendPacket:(Lext/mods/gameserver/network/SystemMessageId;)V
       745: goto          755
       748: aload_1
       749: getstatic     #197                // Field ext/mods/gameserver/network/SystemMessageId.SEVENSIGNS_PARTECIPATION_DUSK:Lext/mods/gameserver/network/SystemMessageId;
       752: invokevirtual #72                 // Method ext/mods/gameserver/model/actor/Player.sendPacket:(Lext/mods/gameserver/network/SystemMessageId;)V
       755: getstatic     #200                // Field ext/mods/gameserver/model/actor/instance/SignsPriest$1.$SwitchMap$ext$mods$gameserver$enums$SealType:[I
       758: aload         7
       760: invokevirtual #206                // Method ext/mods/gameserver/enums/SealType.ordinal:()I
       763: iaload
       764: tableswitch   { // 1 to 3

                       1: 792

                       2: 802

                       3: 812
                 default: 819
            }
       792: aload_1
       793: getstatic     #209                // Field ext/mods/gameserver/network/SystemMessageId.FIGHT_FOR_AVARICE:Lext/mods/gameserver/network/SystemMessageId;
       796: invokevirtual #72                 // Method ext/mods/gameserver/model/actor/Player.sendPacket:(Lext/mods/gameserver/network/SystemMessageId;)V
       799: goto          819
       802: aload_1
       803: getstatic     #212                // Field ext/mods/gameserver/network/SystemMessageId.FIGHT_FOR_GNOSIS:Lext/mods/gameserver/network/SystemMessageId;
       806: invokevirtual #72                 // Method ext/mods/gameserver/model/actor/Player.sendPacket:(Lext/mods/gameserver/network/SystemMessageId;)V
       809: goto          819
       812: aload_1
       813: getstatic     #215                // Field ext/mods/gameserver/network/SystemMessageId.FIGHT_FOR_STRIFE:Lext/mods/gameserver/network/SystemMessageId;
       816: invokevirtual #72                 // Method ext/mods/gameserver/model/actor/Player.sendPacket:(Lext/mods/gameserver/network/SystemMessageId;)V
       819: aload_0
       820: aload_1
       821: iconst_4
       822: aload         5
       824: invokevirtual #176                // Method ext/mods/gameserver/enums/CabalType.getShortName:()Ljava/lang/String;
       827: iconst_0
       828: invokevirtual #38                 // Method showChatWindow:(Lext/mods/gameserver/model/actor/Player;ILjava/lang/String;Z)V
       831: goto          3063
       834: invokestatic  #102                // Method ext/mods/gameserver/data/manager/SevenSignsManager.getInstance:()Lext/mods/gameserver/data/manager/SevenSignsManager;
       837: aload_1
       838: invokevirtual #106                // Method ext/mods/gameserver/model/actor/Player.getObjectId:()I
       841: invokevirtual #107                // Method ext/mods/gameserver/data/manager/SevenSignsManager.getPlayerCabal:(I)Lext/mods/gameserver/enums/CabalType;
       844: getstatic     #111                // Field ext/mods/gameserver/enums/CabalType.NORMAL:Lext/mods/gameserver/enums/CabalType;
       847: if_acmpne     875
       850: aload_0
       851: aload_1
       852: iload         4
       854: aload_0
       855: instanceof    #82                 // class ext/mods/gameserver/model/actor/instance/DawnPriest
       858: ifeq          866
       861: ldc           #84                 // String dawn_no
       863: goto          868
       866: ldc           #86                 // String dusk_no
       868: iconst_0
       869: invokevirtual #38                 // Method showChatWindow:(Lext/mods/gameserver/model/actor/Player;ILjava/lang/String;Z)V
       872: goto          3063
       875: aload_0
       876: aload_1
       877: iload         4
       879: aload_0
       880: instanceof    #82                 // class ext/mods/gameserver/model/actor/instance/DawnPriest
       883: ifeq          891
       886: ldc           #92                 // String dawn
       888: goto          893
       891: ldc           #94                 // String dusk
       893: iconst_0
       894: invokevirtual #38                 // Method showChatWindow:(Lext/mods/gameserver/model/actor/Player;ILjava/lang/String;Z)V
       897: goto          3063
       900: aload_3
       901: invokevirtual #53                 // Method java/util/StringTokenizer.nextToken:()Ljava/lang/String;
       904: invokestatic  #32                 // Method java/lang/Integer.parseInt:(Ljava/lang/String;)I
       907: istore        8
       909: aload_1
       910: invokevirtual #56                 // Method ext/mods/gameserver/model/actor/Player.getInventory:()Lext/mods/gameserver/model/itemcontainer/PcInventory;
       913: sipush        6360
       916: invokevirtual #218                // Method ext/mods/gameserver/model/itemcontainer/PcInventory.getItemByItemId:(I)Lext/mods/gameserver/model/item/instance/ItemInstance;
       919: astore        9
       921: aload_1
       922: invokevirtual #56                 // Method ext/mods/gameserver/model/actor/Player.getInventory:()Lext/mods/gameserver/model/itemcontainer/PcInventory;
       925: sipush        6361
       928: invokevirtual #218                // Method ext/mods/gameserver/model/itemcontainer/PcInventory.getItemByItemId:(I)Lext/mods/gameserver/model/item/instance/ItemInstance;
       931: astore        10
       933: aload_1
       934: invokevirtual #56                 // Method ext/mods/gameserver/model/actor/Player.getInventory:()Lext/mods/gameserver/model/itemcontainer/PcInventory;
       937: sipush        6362
       940: invokevirtual #218                // Method ext/mods/gameserver/model/itemcontainer/PcInventory.getItemByItemId:(I)Lext/mods/gameserver/model/item/instance/ItemInstance;
       943: astore        11
       945: aload         9
       947: ifnonnull     954
       950: iconst_0
       951: goto          959
       954: aload         9
       956: invokevirtual #222                // Method ext/mods/gameserver/model/item/instance/ItemInstance.getCount:()I
       959: istore        12
       961: aload         10
       963: ifnonnull     970
       966: iconst_0
       967: goto          975
       970: aload         10
       972: invokevirtual #222                // Method ext/mods/gameserver/model/item/instance/ItemInstance.getCount:()I
       975: istore        13
       977: aload         11
       979: ifnonnull     986
       982: iconst_0
       983: goto          991
       986: aload         11
       988: invokevirtual #222                // Method ext/mods/gameserver/model/item/instance/ItemInstance.getCount:()I
       991: istore        14
       993: invokestatic  #102                // Method ext/mods/gameserver/data/manager/SevenSignsManager.getInstance:()Lext/mods/gameserver/data/manager/SevenSignsManager;
       996: aload_1
       997: invokevirtual #106                // Method ext/mods/gameserver/model/actor/Player.getObjectId:()I
      1000: invokevirtual #227                // Method ext/mods/gameserver/data/manager/SevenSignsManager.getPlayerContribScore:(I)I
      1003: istore        15
      1005: iconst_0
      1006: istore        16
      1008: iload         15
      1010: getstatic     #231                // Field ext/mods/Config.MAXIMUM_PLAYER_CONTRIB:I
      1013: if_icmpne     1026
      1016: aload_1
      1017: getstatic     #235                // Field ext/mods/gameserver/network/SystemMessageId.CONTRIB_SCORE_EXCEEDED:Lext/mods/gameserver/network/SystemMessageId;
      1020: invokevirtual #72                 // Method ext/mods/gameserver/model/actor/Player.sendPacket:(Lext/mods/gameserver/network/SystemMessageId;)V
      1023: goto          3063
      1026: ldc           #238                // String
      1028: astore        17
      1030: iconst_0
      1031: istore        18
      1033: iconst_0
      1034: istore        19
      1036: iload         8
      1038: tableswitch   { // 1 to 4

                       1: 1068

                       2: 1084

                       3: 1100

                       4: 1116
                 default: 1349
            }
      1068: ldc           #240                // String Blue
      1070: astore        17
      1072: sipush        6360
      1075: istore        19
      1077: iload         12
      1079: istore        18
      1081: goto          1349
      1084: ldc           #242                // String Green
      1086: astore        17
      1088: sipush        6361
      1091: istore        19
      1093: iload         13
      1095: istore        18
      1097: goto          1349
      1100: ldc           #244                // String Red
      1102: astore        17
      1104: sipush        6362
      1107: istore        19
      1109: iload         14
      1111: istore        18
      1113: goto          1349
      1116: iload         15
      1118: istore        20
      1120: getstatic     #231                // Field ext/mods/Config.MAXIMUM_PLAYER_CONTRIB:I
      1123: iload         20
      1125: isub
      1126: bipush        10
      1128: idiv
      1129: istore        21
      1131: iload         21
      1133: iload         14
      1135: if_icmple     1142
      1138: iload         14
      1140: istore        21
      1142: iload         20
      1144: iload         21
      1146: bipush        10
      1148: imul
      1149: iadd
      1150: istore        20
      1152: getstatic     #231                // Field ext/mods/Config.MAXIMUM_PLAYER_CONTRIB:I
      1155: iload         20
      1157: isub
      1158: iconst_5
      1159: idiv
      1160: istore        22
      1162: iload         22
      1164: iload         13
      1166: if_icmple     1173
      1169: iload         13
      1171: istore        22
      1173: iload         20
      1175: iload         22
      1177: iconst_5
      1178: imul
      1179: iadd
      1180: istore        20
      1182: getstatic     #231                // Field ext/mods/Config.MAXIMUM_PLAYER_CONTRIB:I
      1185: iload         20
      1187: isub
      1188: iconst_3
      1189: idiv
      1190: istore        23
      1192: iload         23
      1194: iload         12
      1196: if_icmple     1203
      1199: iload         12
      1201: istore        23
      1203: iload         21
      1205: ifle          1223
      1208: iload         16
      1210: aload_1
      1211: sipush        6362
      1214: iload         21
      1216: iconst_1
      1217: invokevirtual #184                // Method ext/mods/gameserver/model/actor/Player.destroyItemByItemId:(IIZ)Z
      1220: ior
      1221: istore        16
      1223: iload         22
      1225: ifle          1243
      1228: iload         16
      1230: aload_1
      1231: sipush        6361
      1234: iload         22
      1236: iconst_1
      1237: invokevirtual #184                // Method ext/mods/gameserver/model/actor/Player.destroyItemByItemId:(IIZ)Z
      1240: ior
      1241: istore        16
      1243: iload         23
      1245: ifle          1263
      1248: iload         16
      1250: aload_1
      1251: sipush        6360
      1254: iload         23
      1256: iconst_1
      1257: invokevirtual #184                // Method ext/mods/gameserver/model/actor/Player.destroyItemByItemId:(IIZ)Z
      1260: ior
      1261: istore        16
      1263: iload         16
      1265: ifne          1293
      1268: aload_0
      1269: aload_1
      1270: iload         4
      1272: aload_0
      1273: instanceof    #82                 // class ext/mods/gameserver/model/actor/instance/DawnPriest
      1276: ifeq          1284
      1279: ldc           #246                // String dawn_no_stones
      1281: goto          1286
      1284: ldc           #248                // String dusk_no_stones
      1286: iconst_0
      1287: invokevirtual #38                 // Method showChatWindow:(Lext/mods/gameserver/model/actor/Player;ILjava/lang/String;Z)V
      1290: goto          1348
      1293: invokestatic  #102                // Method ext/mods/gameserver/data/manager/SevenSignsManager.getInstance:()Lext/mods/gameserver/data/manager/SevenSignsManager;
      1296: aload_1
      1297: invokevirtual #106                // Method ext/mods/gameserver/model/actor/Player.getObjectId:()I
      1300: iload         23
      1302: iload         22
      1304: iload         21
      1306: invokevirtual #250                // Method ext/mods/gameserver/data/manager/SevenSignsManager.addPlayerStoneContrib:(IIII)I
      1309: istore        15
      1311: aload_1
      1312: getstatic     #254                // Field ext/mods/gameserver/network/SystemMessageId.CONTRIB_SCORE_INCREASED_S1:Lext/mods/gameserver/network/SystemMessageId;
      1315: invokestatic  #257                // Method ext/mods/gameserver/network/serverpackets/SystemMessage.getSystemMessage:(Lext/mods/gameserver/network/SystemMessageId;)Lext/mods/gameserver/network/serverpackets/SystemMessage;
      1318: iload         15
      1320: invokevirtual #263                // Method ext/mods/gameserver/network/serverpackets/SystemMessage.addItemNumber:(I)Lext/mods/gameserver/network/serverpackets/SystemMessage;
      1323: invokevirtual #267                // Method ext/mods/gameserver/model/actor/Player.sendPacket:(Lext/mods/gameserver/network/serverpackets/L2GameServerPacket;)V
      1326: aload_0
      1327: aload_1
      1328: bipush        6
      1330: aload_0
      1331: instanceof    #82                 // class ext/mods/gameserver/model/actor/instance/DawnPriest
      1334: ifeq          1342
      1337: ldc           #92                 // String dawn
      1339: goto          1344
      1342: ldc           #94                 // String dusk
      1344: iconst_0
      1345: invokevirtual #38                 // Method showChatWindow:(Lext/mods/gameserver/model/actor/Player;ILjava/lang/String;Z)V
      1348: return
      1349: new           #270                // class ext/mods/gameserver/network/serverpackets/NpcHtmlMessage
      1352: dup
      1353: aload_0
      1354: invokevirtual #17                 // Method getObjectId:()I
      1357: invokespecial #272                // Method ext/mods/gameserver/network/serverpackets/NpcHtmlMessage."<init>":(I)V
      1360: astore        20
      1362: aload         20
      1364: aload_1
      1365: invokevirtual #275                // Method ext/mods/gameserver/model/actor/Player.getLocale:()Ljava/util/Locale;
      1368: aload_0
      1369: instanceof    #82                 // class ext/mods/gameserver/model/actor/instance/DawnPriest
      1372: ifeq          1381
      1375: ldc_w         #279                // String signs_6_dawn_contribute.htm
      1378: goto          1384
      1381: ldc_w         #281                // String signs_6_dusk_contribute.htm
      1384: invokedynamic #172,  0            // InvokeDynamic #0:makeConcatWithConstants:(Ljava/lang/String;)Ljava/lang/String;
      1389: invokevirtual #283                // Method ext/mods/gameserver/network/serverpackets/NpcHtmlMessage.setFile:(Ljava/util/Locale;Ljava/lang/String;)V
      1392: aload         20
      1394: ldc_w         #287                // String %stoneColor%
      1397: aload         17
      1399: invokevirtual #289                // Method ext/mods/gameserver/network/serverpackets/NpcHtmlMessage.replace:(Ljava/lang/String;Ljava/lang/String;)V
      1402: aload         20
      1404: ldc_w         #293                // String %stoneCount%
      1407: iload         18
      1409: invokevirtual #295                // Method ext/mods/gameserver/network/serverpackets/NpcHtmlMessage.replace:(Ljava/lang/String;I)V
      1412: aload         20
      1414: ldc_w         #298                // String %stoneItemId%
      1417: iload         19
      1419: invokevirtual #295                // Method ext/mods/gameserver/network/serverpackets/NpcHtmlMessage.replace:(Ljava/lang/String;I)V
      1422: aload         20
      1424: ldc_w         #300                // String %objectId%
      1427: aload_0
      1428: invokevirtual #17                 // Method getObjectId:()I
      1431: invokevirtual #295                // Method ext/mods/gameserver/network/serverpackets/NpcHtmlMessage.replace:(Ljava/lang/String;I)V
      1434: aload_1
      1435: aload         20
      1437: invokevirtual #267                // Method ext/mods/gameserver/model/actor/Player.sendPacket:(Lext/mods/gameserver/network/serverpackets/L2GameServerPacket;)V
      1440: goto          3063
      1443: iconst_0
      1444: istore        17
      1446: aload_2
      1447: bipush        13
      1449: invokevirtual #28                 // Method java/lang/String.substring:(I)Ljava/lang/String;
      1452: invokevirtual #46                 // Method java/lang/String.trim:()Ljava/lang/String;
      1455: invokestatic  #32                 // Method java/lang/Integer.parseInt:(Ljava/lang/String;)I
      1458: istore        17
      1460: goto          1474
      1463: astore        18
      1465: aload_0
      1466: aload_1
      1467: ldc_w         #304                // String html/seven_signs/blkmrkt_3.htm
      1470: invokevirtual #153                // Method showChatWindow:(Lext/mods/gameserver/model/actor/Player;Ljava/lang/String;)V
      1473: return
      1474: iload         17
      1476: iconst_1
      1477: if_icmpge     1489
      1480: aload_0
      1481: aload_1
      1482: ldc_w         #304                // String html/seven_signs/blkmrkt_3.htm
      1485: invokevirtual #153                // Method showChatWindow:(Lext/mods/gameserver/model/actor/Player;Ljava/lang/String;)V
      1488: return
      1489: aload_1
      1490: invokevirtual #306                // Method ext/mods/gameserver/model/actor/Player.getAncientAdena:()I
      1493: iload         17
      1495: if_icmpge     1507
      1498: aload_0
      1499: aload_1
      1500: ldc_w         #309                // String html/seven_signs/blkmrkt_4.htm
      1503: invokevirtual #153                // Method showChatWindow:(Lext/mods/gameserver/model/actor/Player;Ljava/lang/String;)V
      1506: return
      1507: ldc_w         #311                // int 2147483647
      1510: aload_1
      1511: invokevirtual #56                 // Method ext/mods/gameserver/model/actor/Player.getInventory:()Lext/mods/gameserver/model/itemcontainer/PcInventory;
      1514: invokevirtual #312                // Method ext/mods/gameserver/model/itemcontainer/PcInventory.getAdena:()I
      1517: isub
      1518: iload         17
      1520: isub
      1521: ifge          1525
      1524: return
      1525: aload_1
      1526: iload         17
      1528: iconst_1
      1529: invokevirtual #313                // Method ext/mods/gameserver/model/actor/Player.reduceAncientAdena:(IZ)Z
      1532: ifeq          1542
      1535: aload_1
      1536: iload         17
      1538: iconst_1
      1539: invokevirtual #316                // Method ext/mods/gameserver/model/actor/Player.addAdena:(IZ)V
      1542: aload_0
      1543: aload_1
      1544: ldc_w         #320                // String html/seven_signs/blkmrkt_5.htm
      1547: invokevirtual #153                // Method showChatWindow:(Lext/mods/gameserver/model/actor/Player;Ljava/lang/String;)V
      1550: goto          3063
      1553: invokestatic  #102                // Method ext/mods/gameserver/data/manager/SevenSignsManager.getInstance:()Lext/mods/gameserver/data/manager/SevenSignsManager;
      1556: invokevirtual #322                // Method ext/mods/gameserver/data/manager/SevenSignsManager.isSealValidationPeriod:()Z
      1559: ifeq          3063
      1562: invokestatic  #102                // Method ext/mods/gameserver/data/manager/SevenSignsManager.getInstance:()Lext/mods/gameserver/data/manager/SevenSignsManager;
      1565: aload_1
      1566: invokevirtual #106                // Method ext/mods/gameserver/model/actor/Player.getObjectId:()I
      1569: invokevirtual #107                // Method ext/mods/gameserver/data/manager/SevenSignsManager.getPlayerCabal:(I)Lext/mods/gameserver/enums/CabalType;
      1572: invokestatic  #102                // Method ext/mods/gameserver/data/manager/SevenSignsManager.getInstance:()Lext/mods/gameserver/data/manager/SevenSignsManager;
      1575: invokevirtual #325                // Method ext/mods/gameserver/data/manager/SevenSignsManager.getWinningCabal:()Lext/mods/gameserver/enums/CabalType;
      1578: if_acmpne     3063
      1581: aload_1
      1582: invokevirtual #56                 // Method ext/mods/gameserver/model/actor/Player.getInventory:()Lext/mods/gameserver/model/itemcontainer/PcInventory;
      1585: iconst_1
      1586: invokevirtual #60                 // Method ext/mods/gameserver/model/itemcontainer/PcInventory.validateCapacity:(I)Z
      1589: ifne          1600
      1592: aload_1
      1593: getstatic     #66                 // Field ext/mods/gameserver/network/SystemMessageId.SLOTS_FULL:Lext/mods/gameserver/network/SystemMessageId;
      1596: invokevirtual #72                 // Method ext/mods/gameserver/model/actor/Player.sendPacket:(Lext/mods/gameserver/network/SystemMessageId;)V
      1599: return
      1600: invokestatic  #102                // Method ext/mods/gameserver/data/manager/SevenSignsManager.getInstance:()Lext/mods/gameserver/data/manager/SevenSignsManager;
      1603: aload_1
      1604: invokevirtual #106                // Method ext/mods/gameserver/model/actor/Player.getObjectId:()I
      1607: invokevirtual #329                // Method ext/mods/gameserver/data/manager/SevenSignsManager.getAncientAdenaReward:(I)I
      1610: istore        18
      1612: iload         18
      1614: ifgt          1642
      1617: aload_0
      1618: aload_1
      1619: bipush        9
      1621: aload_0
      1622: instanceof    #82                 // class ext/mods/gameserver/model/actor/instance/DawnPriest
      1625: ifeq          1634
      1628: ldc_w         #332                // String dawn_b
      1631: goto          1637
      1634: ldc_w         #334                // String dusk_b
      1637: iconst_0
      1638: invokevirtual #38                 // Method showChatWindow:(Lext/mods/gameserver/model/actor/Player;ILjava/lang/String;Z)V
      1641: return
      1642: aload_1
      1643: iload         18
      1645: iconst_1
      1646: invokevirtual #336                // Method ext/mods/gameserver/model/actor/Player.addAncientAdena:(IZ)V
      1649: aload_0
      1650: aload_1
      1651: bipush        9
      1653: aload_0
      1654: instanceof    #82                 // class ext/mods/gameserver/model/actor/instance/DawnPriest
      1657: ifeq          1666
      1660: ldc_w         #339                // String dawn_a
      1663: goto          1669
      1666: ldc_w         #341                // String dusk_a
      1669: iconst_0
      1670: invokevirtual #38                 // Method showChatWindow:(Lext/mods/gameserver/model/actor/Player;ILjava/lang/String;Z)V
      1673: goto          3063
      1676: aload_3
      1677: invokevirtual #53                 // Method java/util/StringTokenizer.nextToken:()Ljava/lang/String;
      1680: invokestatic  #32                 // Method java/lang/Integer.parseInt:(Ljava/lang/String;)I
      1683: istore        18
      1685: aload_3
      1686: invokevirtual #53                 // Method java/util/StringTokenizer.nextToken:()Ljava/lang/String;
      1689: invokestatic  #32                 // Method java/lang/Integer.parseInt:(Ljava/lang/String;)I
      1692: istore        19
      1694: aload_3
      1695: invokevirtual #53                 // Method java/util/StringTokenizer.nextToken:()Ljava/lang/String;
      1698: invokestatic  #32                 // Method java/lang/Integer.parseInt:(Ljava/lang/String;)I
      1701: istore        20
      1703: aload_3
      1704: invokevirtual #53                 // Method java/util/StringTokenizer.nextToken:()Ljava/lang/String;
      1707: invokestatic  #32                 // Method java/lang/Integer.parseInt:(Ljava/lang/String;)I
      1710: istore        21
      1712: iload         21
      1714: ifle          1728
      1717: aload_1
      1718: iload         21
      1720: iconst_1
      1721: invokevirtual #313                // Method ext/mods/gameserver/model/actor/Player.reduceAncientAdena:(IZ)Z
      1724: ifne          1728
      1727: return
      1728: aload_1
      1729: iload         18
      1731: iload         19
      1733: iload         20
      1735: iconst_0
      1736: invokevirtual #343                // Method ext/mods/gameserver/model/actor/Player.teleportTo:(IIII)Z
      1739: pop
      1740: goto          3063
      1743: astore        18
      1745: getstatic     #347                // Field LOGGER:Lext/mods/commons/logging/CLogger;
      1748: ldc_w         #351                // String An error occurred while teleporting a player.
      1751: aload         18
      1753: invokevirtual #353                // Method ext/mods/commons/logging/CLogger.error:(Ljava/lang/Object;Ljava/lang/Throwable;)V
      1756: goto          3063
      1759: aload_0
      1760: aload_1
      1761: iload         4
      1763: aload_0
      1764: instanceof    #82                 // class ext/mods/gameserver/model/actor/instance/DawnPriest
      1767: ifeq          1775
      1770: ldc           #92                 // String dawn
      1772: goto          1777
      1775: ldc           #94                 // String dusk
      1777: iconst_0
      1778: invokevirtual #38                 // Method showChatWindow:(Lext/mods/gameserver/model/actor/Player;ILjava/lang/String;Z)V
      1781: goto          3063
      1784: aload_2
      1785: bipush        14
      1787: invokevirtual #28                 // Method java/lang/String.substring:(I)Ljava/lang/String;
      1790: invokestatic  #32                 // Method java/lang/Integer.parseInt:(Ljava/lang/String;)I
      1793: istore        8
      1795: iconst_0
      1796: istore        18
      1798: iconst_0
      1799: istore        19
      1801: iconst_0
      1802: istore        20
      1804: ldc           #238                // String
      1806: astore        21
      1808: aload_1
      1809: invokevirtual #56                 // Method ext/mods/gameserver/model/actor/Player.getInventory:()Lext/mods/gameserver/model/itemcontainer/PcInventory;
      1812: iconst_1
      1813: invokevirtual #60                 // Method ext/mods/gameserver/model/itemcontainer/PcInventory.validateCapacity:(I)Z
      1816: ifne          1827
      1819: aload_1
      1820: getstatic     #66                 // Field ext/mods/gameserver/network/SystemMessageId.SLOTS_FULL:Lext/mods/gameserver/network/SystemMessageId;
      1823: invokevirtual #72                 // Method ext/mods/gameserver/model/actor/Player.sendPacket:(Lext/mods/gameserver/network/SystemMessageId;)V
      1826: return
      1827: iload         8
      1829: tableswitch   { // 1 to 4

                       1: 1860

                       2: 1876

                       3: 1892

                       4: 1909
                 default: 2113
            }
      1860: ldc_w         #359                // String blue
      1863: astore        21
      1865: sipush        6360
      1868: istore        18
      1870: iconst_3
      1871: istore        20
      1873: goto          2113
      1876: ldc_w         #361                // String green
      1879: astore        21
      1881: sipush        6361
      1884: istore        18
      1886: iconst_5
      1887: istore        20
      1889: goto          2113
      1892: ldc_w         #363                // String red
      1895: astore        21
      1897: sipush        6362
      1900: istore        18
      1902: bipush        10
      1904: istore        20
      1906: goto          2113
      1909: aload_1
      1910: invokevirtual #56                 // Method ext/mods/gameserver/model/actor/Player.getInventory:()Lext/mods/gameserver/model/itemcontainer/PcInventory;
      1913: sipush        6360
      1916: invokevirtual #218                // Method ext/mods/gameserver/model/itemcontainer/PcInventory.getItemByItemId:(I)Lext/mods/gameserver/model/item/instance/ItemInstance;
      1919: astore        22
      1921: aload_1
      1922: invokevirtual #56                 // Method ext/mods/gameserver/model/actor/Player.getInventory:()Lext/mods/gameserver/model/itemcontainer/PcInventory;
      1925: sipush        6361
      1928: invokevirtual #218                // Method ext/mods/gameserver/model/itemcontainer/PcInventory.getItemByItemId:(I)Lext/mods/gameserver/model/item/instance/ItemInstance;
      1931: astore        23
      1933: aload_1
      1934: invokevirtual #56                 // Method ext/mods/gameserver/model/actor/Player.getInventory:()Lext/mods/gameserver/model/itemcontainer/PcInventory;
      1937: sipush        6362
      1940: invokevirtual #218                // Method ext/mods/gameserver/model/itemcontainer/PcInventory.getItemByItemId:(I)Lext/mods/gameserver/model/item/instance/ItemInstance;
      1943: astore        24
      1945: aload         22
      1947: ifnonnull     1954
      1950: iconst_0
      1951: goto          1959
      1954: aload         22
      1956: invokevirtual #222                // Method ext/mods/gameserver/model/item/instance/ItemInstance.getCount:()I
      1959: istore        25
      1961: aload         23
      1963: ifnonnull     1970
      1966: iconst_0
      1967: goto          1975
      1970: aload         23
      1972: invokevirtual #222                // Method ext/mods/gameserver/model/item/instance/ItemInstance.getCount:()I
      1975: istore        26
      1977: aload         24
      1979: ifnonnull     1986
      1982: iconst_0
      1983: goto          1991
      1986: aload         24
      1988: invokevirtual #222                // Method ext/mods/gameserver/model/item/instance/ItemInstance.getCount:()I
      1991: istore        27
      1993: iconst_0
      1994: istore        28
      1996: iload         25
      1998: iload         26
      2000: iload         27
      2002: invokestatic  #365                // Method ext/mods/gameserver/data/manager/SevenSignsManager.calcScore:(III)I
      2005: istore        28
      2007: iload         28
      2009: ifne          2035
      2012: aload_0
      2013: aload_1
      2014: bipush        18
      2016: aload_0
      2017: instanceof    #82                 // class ext/mods/gameserver/model/actor/instance/DawnPriest
      2020: ifeq          2028
      2023: ldc           #246                // String dawn_no_stones
      2025: goto          2030
      2028: ldc           #248                // String dusk_no_stones
      2030: iconst_0
      2031: invokevirtual #38                 // Method showChatWindow:(Lext/mods/gameserver/model/actor/Player;ILjava/lang/String;Z)V
      2034: return
      2035: iload         25
      2037: ifle          2051
      2040: aload_1
      2041: sipush        6360
      2044: iload         25
      2046: iconst_1
      2047: invokevirtual #184                // Method ext/mods/gameserver/model/actor/Player.destroyItemByItemId:(IIZ)Z
      2050: pop
      2051: iload         26
      2053: ifle          2067
      2056: aload_1
      2057: sipush        6361
      2060: iload         26
      2062: iconst_1
      2063: invokevirtual #184                // Method ext/mods/gameserver/model/actor/Player.destroyItemByItemId:(IIZ)Z
      2066: pop
      2067: iload         27
      2069: ifle          2083
      2072: aload_1
      2073: sipush        6362
      2076: iload         27
      2078: iconst_1
      2079: invokevirtual #184                // Method ext/mods/gameserver/model/actor/Player.destroyItemByItemId:(IIZ)Z
      2082: pop
      2083: aload_1
      2084: iload         28
      2086: iconst_1
      2087: invokevirtual #336                // Method ext/mods/gameserver/model/actor/Player.addAncientAdena:(IZ)V
      2090: aload_0
      2091: aload_1
      2092: bipush        18
      2094: aload_0
      2095: instanceof    #82                 // class ext/mods/gameserver/model/actor/instance/DawnPriest
      2098: ifeq          2106
      2101: ldc           #92                 // String dawn
      2103: goto          2108
      2106: ldc           #94                 // String dusk
      2108: iconst_0
      2109: invokevirtual #38                 // Method showChatWindow:(Lext/mods/gameserver/model/actor/Player;ILjava/lang/String;Z)V
      2112: return
      2113: aload_1
      2114: invokevirtual #56                 // Method ext/mods/gameserver/model/actor/Player.getInventory:()Lext/mods/gameserver/model/itemcontainer/PcInventory;
      2117: iload         18
      2119: invokevirtual #218                // Method ext/mods/gameserver/model/itemcontainer/PcInventory.getItemByItemId:(I)Lext/mods/gameserver/model/item/instance/ItemInstance;
      2122: astore        22
      2124: aload         22
      2126: ifnull        2136
      2129: aload         22
      2131: invokevirtual #222                // Method ext/mods/gameserver/model/item/instance/ItemInstance.getCount:()I
      2134: istore        19
      2136: new           #270                // class ext/mods/gameserver/network/serverpackets/NpcHtmlMessage
      2139: dup
      2140: aload_0
      2141: invokevirtual #17                 // Method getObjectId:()I
      2144: invokespecial #272                // Method ext/mods/gameserver/network/serverpackets/NpcHtmlMessage."<init>":(I)V
      2147: astore        23
      2149: aload         23
      2151: aload_1
      2152: invokevirtual #275                // Method ext/mods/gameserver/model/actor/Player.getLocale:()Ljava/util/Locale;
      2155: aload_0
      2156: instanceof    #82                 // class ext/mods/gameserver/model/actor/instance/DawnPriest
      2159: ifeq          2168
      2162: ldc_w         #369                // String signs_17_dawn.htm
      2165: goto          2171
      2168: ldc_w         #371                // String signs_17_dusk.htm
      2171: invokedynamic #172,  0            // InvokeDynamic #0:makeConcatWithConstants:(Ljava/lang/String;)Ljava/lang/String;
      2176: invokevirtual #283                // Method ext/mods/gameserver/network/serverpackets/NpcHtmlMessage.setFile:(Ljava/util/Locale;Ljava/lang/String;)V
      2179: aload         23
      2181: ldc_w         #287                // String %stoneColor%
      2184: aload         21
      2186: invokevirtual #289                // Method ext/mods/gameserver/network/serverpackets/NpcHtmlMessage.replace:(Ljava/lang/String;Ljava/lang/String;)V
      2189: aload         23
      2191: ldc_w         #373                // String %stoneValue%
      2194: iload         20
      2196: invokevirtual #295                // Method ext/mods/gameserver/network/serverpackets/NpcHtmlMessage.replace:(Ljava/lang/String;I)V
      2199: aload         23
      2201: ldc_w         #293                // String %stoneCount%
      2204: iload         19
      2206: invokevirtual #295                // Method ext/mods/gameserver/network/serverpackets/NpcHtmlMessage.replace:(Ljava/lang/String;I)V
      2209: aload         23
      2211: ldc_w         #298                // String %stoneItemId%
      2214: iload         18
      2216: invokevirtual #295                // Method ext/mods/gameserver/network/serverpackets/NpcHtmlMessage.replace:(Ljava/lang/String;I)V
      2219: aload         23
      2221: ldc_w         #300                // String %objectId%
      2224: aload_0
      2225: invokevirtual #17                 // Method getObjectId:()I
      2228: invokevirtual #295                // Method ext/mods/gameserver/network/serverpackets/NpcHtmlMessage.replace:(Ljava/lang/String;I)V
      2231: aload_1
      2232: aload         23
      2234: invokevirtual #267                // Method ext/mods/gameserver/model/actor/Player.sendPacket:(Lext/mods/gameserver/network/serverpackets/L2GameServerPacket;)V
      2237: goto          3063
      2240: aload_3
      2241: invokevirtual #53                 // Method java/util/StringTokenizer.nextToken:()Ljava/lang/String;
      2244: invokestatic  #32                 // Method java/lang/Integer.parseInt:(Ljava/lang/String;)I
      2247: istore        24
      2249: iconst_0
      2250: istore        17
      2252: aload_2
      2253: bipush        19
      2255: invokevirtual #28                 // Method java/lang/String.substring:(I)Ljava/lang/String;
      2258: invokevirtual #46                 // Method java/lang/String.trim:()Ljava/lang/String;
      2261: invokestatic  #32                 // Method java/lang/Integer.parseInt:(Ljava/lang/String;)I
      2264: istore        17
      2266: goto          2296
      2269: astore        25
      2271: aload_0
      2272: aload_1
      2273: bipush        18
      2275: aload_0
      2276: instanceof    #82                 // class ext/mods/gameserver/model/actor/instance/DawnPriest
      2279: ifeq          2288
      2282: ldc_w         #375                // String dawn_failed
      2285: goto          2291
      2288: ldc_w         #377                // String dusk_failed
      2291: iconst_0
      2292: invokevirtual #38                 // Method showChatWindow:(Lext/mods/gameserver/model/actor/Player;ILjava/lang/String;Z)V
      2295: return
      2296: aload_1
      2297: invokevirtual #56                 // Method ext/mods/gameserver/model/actor/Player.getInventory:()Lext/mods/gameserver/model/itemcontainer/PcInventory;
      2300: iload         24
      2302: invokevirtual #218                // Method ext/mods/gameserver/model/itemcontainer/PcInventory.getItemByItemId:(I)Lext/mods/gameserver/model/item/instance/ItemInstance;
      2305: astore        25
      2307: aload         25
      2309: ifnonnull     2335
      2312: aload_0
      2313: aload_1
      2314: bipush        18
      2316: aload_0
      2317: instanceof    #82                 // class ext/mods/gameserver/model/actor/instance/DawnPriest
      2320: ifeq          2328
      2323: ldc           #246                // String dawn_no_stones
      2325: goto          2330
      2328: ldc           #248                // String dusk_no_stones
      2330: iconst_0
      2331: invokevirtual #38                 // Method showChatWindow:(Lext/mods/gameserver/model/actor/Player;ILjava/lang/String;Z)V
      2334: return
      2335: iload         17
      2337: ifle          2350
      2340: iload         17
      2342: aload         25
      2344: invokevirtual #222                // Method ext/mods/gameserver/model/item/instance/ItemInstance.getCount:()I
      2347: if_icmple     2375
      2350: aload_0
      2351: aload_1
      2352: bipush        18
      2354: aload_0
      2355: instanceof    #82                 // class ext/mods/gameserver/model/actor/instance/DawnPriest
      2358: ifeq          2367
      2361: ldc_w         #379                // String dawn_low_stones
      2364: goto          2370
      2367: ldc_w         #381                // String dusk_low_stones
      2370: iconst_0
      2371: invokevirtual #38                 // Method showChatWindow:(Lext/mods/gameserver/model/actor/Player;ILjava/lang/String;Z)V
      2374: return
      2375: iconst_0
      2376: istore        26
      2378: iload         24
      2380: tableswitch   { // 6360 to 6362

                    6360: 2408

                    6361: 2420

                    6362: 2432
                 default: 2441
            }
      2408: iload         17
      2410: iconst_0
      2411: iconst_0
      2412: invokestatic  #365                // Method ext/mods/gameserver/data/manager/SevenSignsManager.calcScore:(III)I
      2415: istore        26
      2417: goto          2441
      2420: iconst_0
      2421: iload         17
      2423: iconst_0
      2424: invokestatic  #365                // Method ext/mods/gameserver/data/manager/SevenSignsManager.calcScore:(III)I
      2427: istore        26
      2429: goto          2441
      2432: iconst_0
      2433: iconst_0
      2434: iload         17
      2436: invokestatic  #365                // Method ext/mods/gameserver/data/manager/SevenSignsManager.calcScore:(III)I
      2439: istore        26
      2441: aload_1
      2442: iload         24
      2444: iload         17
      2446: iconst_1
      2447: invokevirtual #184                // Method ext/mods/gameserver/model/actor/Player.destroyItemByItemId:(IIZ)Z
      2450: ifne          2454
      2453: return
      2454: aload_1
      2455: iload         26
      2457: iconst_1
      2458: invokevirtual #336                // Method ext/mods/gameserver/model/actor/Player.addAncientAdena:(IZ)V
      2461: aload_0
      2462: aload_1
      2463: bipush        18
      2465: aload_0
      2466: instanceof    #82                 // class ext/mods/gameserver/model/actor/instance/DawnPriest
      2469: ifeq          2477
      2472: ldc           #92                 // String dawn
      2474: goto          2479
      2477: ldc           #94                 // String dusk
      2479: iconst_0
      2480: invokevirtual #38                 // Method showChatWindow:(Lext/mods/gameserver/model/actor/Player;ILjava/lang/String;Z)V
      2483: goto          3063
      2486: getstatic     #96                 // Field ext/mods/gameserver/enums/CabalType.VALUES:[Lext/mods/gameserver/enums/CabalType;
      2489: aload_3
      2490: invokevirtual #53                 // Method java/util/StringTokenizer.nextToken:()Ljava/lang/String;
      2493: invokestatic  #32                 // Method java/lang/Integer.parseInt:(Ljava/lang/String;)I
      2496: aaload
      2497: astore        5
      2499: getstatic     #179                // Field ext/mods/gameserver/enums/SealType.VALUES:[Lext/mods/gameserver/enums/SealType;
      2502: aload_3
      2503: invokevirtual #53                 // Method java/util/StringTokenizer.nextToken:()Ljava/lang/String;
      2506: invokestatic  #32                 // Method java/lang/Integer.parseInt:(Ljava/lang/String;)I
      2509: aaload
      2510: astore        7
      2512: aload_0
      2513: aload_1
      2514: iload         4
      2516: aload         7
      2518: invokevirtual #383                // Method ext/mods/gameserver/enums/SealType.getShortName:()Ljava/lang/String;
      2521: aload         5
      2523: invokevirtual #176                // Method ext/mods/gameserver/enums/CabalType.getShortName:()Ljava/lang/String;
      2526: invokedynamic #384,  0            // InvokeDynamic #1:makeConcatWithConstants:(Ljava/lang/String;Ljava/lang/String;)Ljava/lang/String;
      2531: iconst_0
      2532: invokevirtual #38                 // Method showChatWindow:(Lext/mods/gameserver/model/actor/Player;ILjava/lang/String;Z)V
      2535: goto          3063
      2538: new           #387                // class java/lang/StringBuilder
      2541: dup
      2542: invokespecial #389                // Method java/lang/StringBuilder."<init>":()V
      2545: astore        27
      2547: aload_0
      2548: instanceof    #82                 // class ext/mods/gameserver/model/actor/instance/DawnPriest
      2551: ifeq          2566
      2554: aload         27
      2556: ldc_w         #392                // String <html><body>Priest of Dawn:<br><font color=\"LEVEL\">[ Seal Status ]</font><br>
      2559: invokevirtual #394                // Method java/lang/StringBuilder.append:(Ljava/lang/String;)Ljava/lang/StringBuilder;
      2562: pop
      2563: goto          2575
      2566: aload         27
      2568: ldc_w         #398                // String <html><body>Dusk Priestess:<br><font color=\"LEVEL\">[ Status of the Seals ]</font><br>
      2571: invokevirtual #394                // Method java/lang/StringBuilder.append:(Ljava/lang/String;)Ljava/lang/StringBuilder;
      2574: pop
      2575: invokestatic  #102                // Method ext/mods/gameserver/data/manager/SevenSignsManager.getInstance:()Lext/mods/gameserver/data/manager/SevenSignsManager;
      2578: invokevirtual #400                // Method ext/mods/gameserver/data/manager/SevenSignsManager.getSealOwners:()Ljava/util/Map;
      2581: invokeinterface #404,  1          // InterfaceMethod java/util/Map.entrySet:()Ljava/util/Set;
      2586: invokeinterface #410,  1          // InterfaceMethod java/util/Set.iterator:()Ljava/util/Iterator;
      2591: astore        28
      2593: aload         28
      2595: invokeinterface #416,  1          // InterfaceMethod java/util/Iterator.hasNext:()Z
      2600: ifeq          2690
      2603: aload         28
      2605: invokeinterface #421,  1          // InterfaceMethod java/util/Iterator.next:()Ljava/lang/Object;
      2610: checkcast     #425                // class java/util/Map$Entry
      2613: astore        29
      2615: aload         29
      2617: invokeinterface #427,  1          // InterfaceMethod java/util/Map$Entry.getKey:()Ljava/lang/Object;
      2622: checkcast     #180                // class ext/mods/gameserver/enums/SealType
      2625: astore        30
      2627: aload         29
      2629: invokeinterface #430,  1          // InterfaceMethod java/util/Map$Entry.getValue:()Ljava/lang/Object;
      2634: checkcast     #97                 // class ext/mods/gameserver/enums/CabalType
      2637: astore        31
      2639: aload         31
      2641: getstatic     #111                // Field ext/mods/gameserver/enums/CabalType.NORMAL:Lext/mods/gameserver/enums/CabalType;
      2644: if_acmpeq     2671
      2647: aload         27
      2649: aload         30
      2651: invokevirtual #433                // Method ext/mods/gameserver/enums/SealType.getFullName:()Ljava/lang/String;
      2654: aload         31
      2656: invokevirtual #436                // Method ext/mods/gameserver/enums/CabalType.getFullName:()Ljava/lang/String;
      2659: invokedynamic #437,  0            // InvokeDynamic #2:makeConcatWithConstants:(Ljava/lang/String;Ljava/lang/String;)Ljava/lang/String;
      2664: invokevirtual #394                // Method java/lang/StringBuilder.append:(Ljava/lang/String;)Ljava/lang/StringBuilder;
      2667: pop
      2668: goto          2687
      2671: aload         27
      2673: aload         30
      2675: invokevirtual #433                // Method ext/mods/gameserver/enums/SealType.getFullName:()Ljava/lang/String;
      2678: invokedynamic #438,  0            // InvokeDynamic #3:makeConcatWithConstants:(Ljava/lang/String;)Ljava/lang/String;
      2683: invokevirtual #394                // Method java/lang/StringBuilder.append:(Ljava/lang/String;)Ljava/lang/StringBuilder;
      2686: pop
      2687: goto          2593
      2690: aload         27
      2692: aload_0
      2693: invokevirtual #17                 // Method getObjectId:()I
      2696: invokedynamic #439,  0            // InvokeDynamic #4:makeConcatWithConstants:(I)Ljava/lang/String;
      2701: invokevirtual #394                // Method java/lang/StringBuilder.append:(Ljava/lang/String;)Ljava/lang/StringBuilder;
      2704: pop
      2705: new           #270                // class ext/mods/gameserver/network/serverpackets/NpcHtmlMessage
      2708: dup
      2709: aload_0
      2710: invokevirtual #17                 // Method getObjectId:()I
      2713: invokespecial #272                // Method ext/mods/gameserver/network/serverpackets/NpcHtmlMessage."<init>":(I)V
      2716: astore        23
      2718: aload         23
      2720: aload         27
      2722: invokevirtual #441                // Method java/lang/StringBuilder.toString:()Ljava/lang/String;
      2725: invokevirtual #444                // Method ext/mods/gameserver/network/serverpackets/NpcHtmlMessage.setHtml:(Ljava/lang/String;)V
      2728: aload_1
      2729: aload         23
      2731: invokevirtual #267                // Method ext/mods/gameserver/model/actor/Player.sendPacket:(Lext/mods/gameserver/network/serverpackets/L2GameServerPacket;)V
      2734: goto          3063
      2737: aload_3
      2738: invokevirtual #53                 // Method java/util/StringTokenizer.nextToken:()Ljava/lang/String;
      2741: invokestatic  #32                 // Method java/lang/Integer.parseInt:(Ljava/lang/String;)I
      2744: istore        24
      2746: aload_2
      2747: bipush        19
      2749: invokevirtual #28                 // Method java/lang/String.substring:(I)Ljava/lang/String;
      2752: invokevirtual #46                 // Method java/lang/String.trim:()Ljava/lang/String;
      2755: invokestatic  #32                 // Method java/lang/Integer.parseInt:(Ljava/lang/String;)I
      2758: istore        17
      2760: goto          2790
      2763: astore        28
      2765: aload_0
      2766: aload_1
      2767: bipush        6
      2769: aload_0
      2770: instanceof    #82                 // class ext/mods/gameserver/model/actor/instance/DawnPriest
      2773: ifeq          2782
      2776: ldc_w         #447                // String dawn_failure
      2779: goto          2785
      2782: ldc_w         #449                // String dusk_failure
      2785: iconst_0
      2786: invokevirtual #38                 // Method showChatWindow:(Lext/mods/gameserver/model/actor/Player;ILjava/lang/String;Z)V
      2789: return
      2790: iload         17
      2792: aload_1
      2793: invokevirtual #56                 // Method ext/mods/gameserver/model/actor/Player.getInventory:()Lext/mods/gameserver/model/itemcontainer/PcInventory;
      2796: iload         24
      2798: invokevirtual #451                // Method ext/mods/gameserver/model/itemcontainer/PcInventory.getItemCount:(I)I
      2801: invokestatic  #454                // Method java/lang/Math.min:(II)I
      2804: istore        19
      2806: invokestatic  #102                // Method ext/mods/gameserver/data/manager/SevenSignsManager.getInstance:()Lext/mods/gameserver/data/manager/SevenSignsManager;
      2809: aload_1
      2810: invokevirtual #106                // Method ext/mods/gameserver/model/actor/Player.getObjectId:()I
      2813: invokevirtual #227                // Method ext/mods/gameserver/data/manager/SevenSignsManager.getPlayerContribScore:(I)I
      2816: istore        28
      2818: iconst_0
      2819: istore        29
      2821: iload         24
      2823: tableswitch   { // 6360 to 6362

                    6360: 2848

                    6361: 2861

                    6362: 2874
                 default: 2885
            }
      2848: getstatic     #231                // Field ext/mods/Config.MAXIMUM_PLAYER_CONTRIB:I
      2851: iload         28
      2853: isub
      2854: iconst_3
      2855: idiv
      2856: istore        29
      2858: goto          2885
      2861: getstatic     #231                // Field ext/mods/Config.MAXIMUM_PLAYER_CONTRIB:I
      2864: iload         28
      2866: isub
      2867: iconst_5
      2868: idiv
      2869: istore        29
      2871: goto          2885
      2874: getstatic     #231                // Field ext/mods/Config.MAXIMUM_PLAYER_CONTRIB:I
      2877: iload         28
      2879: isub
      2880: bipush        10
      2882: idiv
      2883: istore        29
      2885: iload         19
      2887: iload         29
      2889: invokestatic  #454                // Method java/lang/Math.min:(II)I
      2892: istore        19
      2894: aload_1
      2895: iload         24
      2897: iload         19
      2899: iconst_1
      2900: invokevirtual #184                // Method ext/mods/gameserver/model/actor/Player.destroyItemByItemId:(IIZ)Z
      2903: ifne          2931
      2906: aload_0
      2907: aload_1
      2908: bipush        6
      2910: aload_0
      2911: instanceof    #82                 // class ext/mods/gameserver/model/actor/instance/DawnPriest
      2914: ifeq          2923
      2917: ldc_w         #379                // String dawn_low_stones
      2920: goto          2926
      2923: ldc_w         #381                // String dusk_low_stones
      2926: iconst_0
      2927: invokevirtual #38                 // Method showChatWindow:(Lext/mods/gameserver/model/actor/Player;ILjava/lang/String;Z)V
      2930: return
      2931: iload         24
      2933: tableswitch   { // 6360 to 6362

                    6360: 2960

                    6361: 2979

                    6362: 2998
                 default: 3014
            }
      2960: invokestatic  #102                // Method ext/mods/gameserver/data/manager/SevenSignsManager.getInstance:()Lext/mods/gameserver/data/manager/SevenSignsManager;
      2963: aload_1
      2964: invokevirtual #106                // Method ext/mods/gameserver/model/actor/Player.getObjectId:()I
      2967: iload         19
      2969: iconst_0
      2970: iconst_0
      2971: invokevirtual #250                // Method ext/mods/gameserver/data/manager/SevenSignsManager.addPlayerStoneContrib:(IIII)I
      2974: istore        28
      2976: goto          3014
      2979: invokestatic  #102                // Method ext/mods/gameserver/data/manager/SevenSignsManager.getInstance:()Lext/mods/gameserver/data/manager/SevenSignsManager;
      2982: aload_1
      2983: invokevirtual #106                // Method ext/mods/gameserver/model/actor/Player.getObjectId:()I
      2986: iconst_0
      2987: iload         19
      2989: iconst_0
      2990: invokevirtual #250                // Method ext/mods/gameserver/data/manager/SevenSignsManager.addPlayerStoneContrib:(IIII)I
      2993: istore        28
      2995: goto          3014
      2998: invokestatic  #102                // Method ext/mods/gameserver/data/manager/SevenSignsManager.getInstance:()Lext/mods/gameserver/data/manager/SevenSignsManager;
      3001: aload_1
      3002: invokevirtual #106                // Method ext/mods/gameserver/model/actor/Player.getObjectId:()I
      3005: iconst_0
      3006: iconst_0
      3007: iload         19
      3009: invokevirtual #250                // Method ext/mods/gameserver/data/manager/SevenSignsManager.addPlayerStoneContrib:(IIII)I
      3012: istore        28
      3014: aload_1
      3015: getstatic     #254                // Field ext/mods/gameserver/network/SystemMessageId.CONTRIB_SCORE_INCREASED_S1:Lext/mods/gameserver/network/SystemMessageId;
      3018: invokestatic  #257                // Method ext/mods/gameserver/network/serverpackets/SystemMessage.getSystemMessage:(Lext/mods/gameserver/network/SystemMessageId;)Lext/mods/gameserver/network/serverpackets/SystemMessage;
      3021: iload         28
      3023: invokevirtual #263                // Method ext/mods/gameserver/network/serverpackets/SystemMessage.addItemNumber:(I)Lext/mods/gameserver/network/serverpackets/SystemMessage;
      3026: invokevirtual #267                // Method ext/mods/gameserver/model/actor/Player.sendPacket:(Lext/mods/gameserver/network/serverpackets/L2GameServerPacket;)V
      3029: aload_0
      3030: aload_1
      3031: bipush        6
      3033: aload_0
      3034: instanceof    #82                 // class ext/mods/gameserver/model/actor/instance/DawnPriest
      3037: ifeq          3045
      3040: ldc           #92                 // String dawn
      3042: goto          3047
      3045: ldc           #94                 // String dusk
      3047: iconst_0
      3048: invokevirtual #38                 // Method showChatWindow:(Lext/mods/gameserver/model/actor/Player;ILjava/lang/String;Z)V
      3051: goto          3063
      3054: aload_0
      3055: aload_1
      3056: iload         4
      3058: aconst_null
      3059: iconst_0
      3060: invokevirtual #38                 // Method showChatWindow:(Lext/mods/gameserver/model/actor/Player;ILjava/lang/String;Z)V
      3063: goto          3072
      3066: aload_0
      3067: aload_1
      3068: aload_2
      3069: invokespecial #460                // Method ext/mods/gameserver/model/actor/instance/Folk.onBypassFeedback:(Lext/mods/gameserver/model/actor/Player;Ljava/lang/String;)V
      3072: return
      Exception table:
         from    to  target type
          1446  1460  1463   Class java/lang/Exception
          1676  1727  1743   Class java/lang/Exception
          1728  1740  1743   Class java/lang/Exception
          2252  2266  2269   Class java/lang/Exception
          2737  2760  2763   Class java/lang/Exception
      LineNumberTable:
        line 45: 0
        line 46: 21
        line 48: 22
        line 49: 31
        line 50: 50
        line 52: 59
        line 53: 71
        line 55: 76
        line 56: 85
        line 59: 232
        line 61: 243
        line 62: 250
        line 65: 251
        line 67: 262
        line 68: 284
        line 71: 285
        line 73: 295
        line 74: 317
        line 77: 320
        line 79: 333
        line 81: 349
        line 82: 371
        line 85: 372
        line 87: 378
        line 88: 387
        line 90: 392
        line 91: 414
        line 94: 415
        line 96: 421
        line 98: 445
        line 100: 458
        line 101: 465
        line 104: 466
        line 106: 479
        line 107: 486
        line 112: 487
        line 113: 509
        line 116: 512
        line 117: 541
        line 118: 563
        line 121: 566
        line 122: 579
        line 123: 592
        line 126: 595
        line 127: 608
        line 129: 621
        line 131: 627
        line 133: 651
        line 135: 664
        line 136: 671
        line 139: 672
        line 141: 707
        line 142: 714
        line 146: 715
        line 148: 730
        line 149: 738
        line 151: 748
        line 153: 755
        line 156: 792
        line 157: 799
        line 160: 802
        line 161: 809
        line 164: 812
        line 168: 819
        line 169: 831
        line 172: 834
        line 173: 850
        line 175: 875
        line 176: 897
        line 179: 900
        line 181: 909
        line 182: 921
        line 183: 933
        line 185: 945
        line 186: 961
        line 187: 977
        line 189: 993
        line 190: 1005
        line 192: 1008
        line 193: 1016
        line 196: 1026
        line 197: 1030
        line 198: 1033
        line 200: 1036
        line 203: 1068
        line 204: 1072
        line 205: 1077
        line 206: 1081
        line 209: 1084
        line 210: 1088
        line 211: 1093
        line 212: 1097
        line 215: 1100
        line 216: 1104
        line 217: 1109
        line 218: 1113
        line 221: 1116
        line 222: 1120
        line 223: 1131
        line 224: 1138
        line 226: 1142
        line 227: 1152
        line 228: 1162
        line 229: 1169
        line 231: 1173
        line 232: 1182
        line 233: 1192
        line 234: 1199
        line 236: 1203
        line 237: 1208
        line 239: 1223
        line 240: 1228
        line 242: 1243
        line 243: 1248
        line 245: 1263
        line 246: 1268
        line 249: 1293
        line 250: 1311
        line 252: 1326
        line 254: 1348
        line 257: 1349
        line 258: 1362
        line 259: 1392
        line 260: 1402
        line 261: 1412
        line 262: 1422
        line 263: 1434
        line 265: 1440
        line 268: 1443
        line 271: 1446
        line 277: 1460
        line 273: 1463
        line 275: 1465
        line 276: 1473
        line 279: 1474
        line 281: 1480
        line 282: 1488
        line 285: 1489
        line 287: 1498
        line 288: 1506
        line 291: 1507
        line 292: 1524
        line 294: 1525
        line 295: 1535
        line 297: 1542
        line 298: 1550
        line 301: 1553
        line 303: 1581
        line 305: 1592
        line 306: 1599
        line 309: 1600
        line 310: 1612
        line 312: 1617
        line 313: 1641
        line 316: 1642
        line 318: 1649
        line 319: 1673
        line 325: 1676
        line 326: 1685
        line 327: 1694
        line 329: 1703
        line 330: 1712
        line 331: 1727
        line 333: 1728
        line 338: 1740
        line 335: 1743
        line 337: 1745
        line 339: 1756
        line 342: 1759
        line 343: 1781
        line 346: 1784
        line 348: 1795
        line 349: 1798
        line 350: 1801
        line 352: 1804
        line 354: 1808
        line 356: 1819
        line 357: 1826
        line 360: 1827
        line 363: 1860
        line 364: 1865
        line 365: 1870
        line 366: 1873
        line 369: 1876
        line 370: 1881
        line 371: 1886
        line 372: 1889
        line 375: 1892
        line 376: 1897
        line 377: 1902
        line 378: 1906
        line 381: 1909
        line 382: 1921
        line 383: 1933
        line 385: 1945
        line 386: 1961
        line 387: 1977
        line 388: 1993
        line 390: 1996
        line 392: 2007
        line 394: 2012
        line 395: 2034
        line 398: 2035
        line 399: 2040
        line 401: 2051
        line 402: 2056
        line 404: 2067
        line 405: 2072
        line 407: 2083
        line 409: 2090
        line 410: 2112
        line 413: 2113
        line 414: 2124
        line 415: 2129
        line 417: 2136
        line 418: 2149
        line 419: 2179
        line 420: 2189
        line 421: 2199
        line 422: 2209
        line 423: 2219
        line 424: 2231
        line 425: 2237
        line 428: 2240
        line 429: 2249
        line 432: 2252
        line 438: 2266
        line 434: 2269
        line 436: 2271
        line 437: 2295
        line 440: 2296
        line 441: 2307
        line 443: 2312
        line 444: 2334
        line 447: 2335
        line 449: 2350
        line 450: 2374
        line 453: 2375
        line 454: 2378
        line 457: 2408
        line 458: 2417
        line 461: 2420
        line 462: 2429
        line 465: 2432
        line 469: 2441
        line 470: 2453
        line 472: 2454
        line 474: 2461
        line 475: 2483
        line 478: 2486
        line 479: 2499
        line 481: 2512
        line 482: 2535
        line 485: 2538
        line 487: 2547
        line 488: 2554
        line 490: 2566
        line 492: 2575
        line 494: 2615
        line 495: 2627
        line 497: 2639
        line 498: 2647
        line 500: 2671
        line 501: 2687
        line 503: 2690
        line 505: 2705
        line 506: 2718
        line 507: 2728
        line 508: 2734
        line 513: 2737
        line 515: 2746
        line 521: 2760
        line 517: 2763
        line 519: 2765
        line 520: 2789
        line 523: 2790
        line 525: 2806
        line 527: 2818
        line 528: 2821
        line 531: 2848
        line 532: 2858
        line 535: 2861
        line 536: 2871
        line 539: 2874
        line 543: 2885
        line 545: 2894
        line 547: 2906
        line 548: 2930
        line 551: 2931
        line 554: 2960
        line 555: 2976
        line 558: 2979
        line 559: 2995
        line 562: 2998
        line 566: 3014
        line 568: 3029
        line 569: 3051
        line 572: 3054
        line 575: 3063
        line 577: 3066
        line 578: 3072
      LocalVariableTable:
        Start  Length  Slot  Name   Signature
          445      42     7 hasCastle   Z
          387     100     6 classLevel   I
          333     179     5 cabal   Lext/mods/gameserver/enums/CabalType;
          541      25     6 canPayFee   Z
          579      16     5 cabal   Lext/mods/gameserver/enums/CabalType;
          651      64     8 hasCastle   Z
          608     226     5 cabal   Lext/mods/gameserver/enums/CabalType;
          621     213     7  seal   Lext/mods/gameserver/enums/SealType;
         1120     229    20 tempContribScore   I
         1131     218    21 redContribCount   I
         1162     187    22 greenContribCount   I
         1192     157    23 blueContribCount   I
         1030     410    17 stoneColor   Ljava/lang/String;
         1033     407    18 stoneCount   I
         1036     404    19 stoneId   I
         1362      78    20  html   Lext/mods/gameserver/network/serverpackets/NpcHtmlMessage;
          909     534     8 stoneType   I
          921     522     9 blueStones   Lext/mods/gameserver/model/item/instance/ItemInstance;
          933     510    10 greenStones   Lext/mods/gameserver/model/item/instance/ItemInstance;
          945     498    11 redStones   Lext/mods/gameserver/model/item/instance/ItemInstance;
          961     482    12 blueStoneCount   I
          977     466    13 greenStoneCount   I
          993     450    14 redStoneCount   I
         1005     438    15 contribScore   I
         1008     435    16 stonesFound   Z
         1465       9    18     e   Ljava/lang/Exception;
         1446     107    17 amount   I
         1612      61    18 reward   I
         1685      55    18     x   I
         1694      46    19     y   I
         1703      37    20     z   I
         1712      28    21 ancientAdenaCost   I
         1745      11    18     e   Ljava/lang/Exception;
         1921     192    22 blueStonesAll   Lext/mods/gameserver/model/item/instance/ItemInstance;
         1933     180    23 greenStonesAll   Lext/mods/gameserver/model/item/instance/ItemInstance;
         1945     168    24 redStonesAll   Lext/mods/gameserver/model/item/instance/ItemInstance;
         1961     152    25 blueStoneCountAll   I
         1977     136    26 greenStoneCountAll   I
         1993     120    27 redStoneCountAll   I
         1996     117    28 ancientAdenaRewardAll   I
         1795     445     8 stoneType   I
         1798     442    18 stoneId   I
         1801     439    19 stoneCount   I
         1804     436    20 stoneValue   I
         1808     432    21 stoneColor   Ljava/lang/String;
         2124     116    22 stoneInstance   Lext/mods/gameserver/model/item/instance/ItemInstance;
         2149      91    23  html   Lext/mods/gameserver/network/serverpackets/NpcHtmlMessage;
         2271      25    25     e   Ljava/lang/Exception;
         2252     234    17 amount   I
         2249     237    24 itemId   I
         2307     179    25 convertItem   Lext/mods/gameserver/model/item/instance/ItemInstance;
         2378     108    26 reward   I
         2499      39     5 cabal   Lext/mods/gameserver/enums/CabalType;
         2512      26     7  seal   Lext/mods/gameserver/enums/SealType;
         2627      60    30     s   Lext/mods/gameserver/enums/SealType;
         2639      48    31    so   Lext/mods/gameserver/enums/CabalType;
         2615      72    29 entry   Ljava/util/Map$Entry;
         2718      19    23  html   Lext/mods/gameserver/network/serverpackets/NpcHtmlMessage;
         2547     190    27    sb   Ljava/lang/StringBuilder;
         2760       3    17 amount   I
         2746      17    24 itemId   I
         2765      25    28     e   Ljava/lang/Exception;
         2790     264    17 amount   I
         2806     248    19 stoneCount   I
         2790     264    24 itemId   I
         2818     236    28 score   I
         2821     233    29 maxStoneCountToContribute   I
           71    2992     3    st   Ljava/util/StringTokenizer;
           85    2978     4 value   I
            0    3073     0  this   Lext/mods/gameserver/model/actor/instance/SignsPriest;
            0    3073     1 player   Lext/mods/gameserver/model/actor/Player;
            0    3073     2 command   Ljava/lang/String;
      LocalVariableTypeTable:
        Start  Length  Slot  Name   Signature
         2615      72    29 entry   Ljava/util/Map$Entry<Lext/mods/gameserver/enums/SealType;Lext/mods/gameserver/enums/CabalType;>;
      StackMapTable: number_of_entries = 167
        frame_type = 21 /* same */
        frame_type = 0 /* same */
        frame_type = 27 /* same */
        frame_type = 253 /* append */
          offset_delta = 181
          locals = [ class java/util/StringTokenizer, int ]
        frame_type = 18 /* same */
        frame_type = 255 /* full_frame */
          offset_delta = 26
          locals = [ class ext/mods/gameserver/model/actor/instance/SignsPriest, class ext/mods/gameserver/model/actor/Player, class java/lang/String, class java/util/StringTokenizer, int ]
          stack = [ class ext/mods/gameserver/model/actor/instance/SignsPriest, class ext/mods/gameserver/model/actor/Player, int ]
        frame_type = 255 /* full_frame */
          offset_delta = 1
          locals = [ class ext/mods/gameserver/model/actor/instance/SignsPriest, class ext/mods/gameserver/model/actor/Player, class java/lang/String, class java/util/StringTokenizer, int ]
          stack = [ class ext/mods/gameserver/model/actor/instance/SignsPriest, class ext/mods/gameserver/model/actor/Player, int, class java/lang/String ]
        frame_type = 4 /* same */
        frame_type = 255 /* full_frame */
          offset_delta = 25
          locals = [ class ext/mods/gameserver/model/actor/instance/SignsPriest, class ext/mods/gameserver/model/actor/Player, class java/lang/String, class java/util/StringTokenizer, int ]
          stack = [ class ext/mods/gameserver/model/actor/instance/SignsPriest, class ext/mods/gameserver/model/actor/Player, int ]
        frame_type = 255 /* full_frame */
          offset_delta = 1
          locals = [ class ext/mods/gameserver/model/actor/instance/SignsPriest, class ext/mods/gameserver/model/actor/Player, class java/lang/String, class java/util/StringTokenizer, int ]
          stack = [ class ext/mods/gameserver/model/actor/instance/SignsPriest, class ext/mods/gameserver/model/actor/Player, int, class java/lang/String ]
        frame_type = 6 /* same */
        frame_type = 255 /* full_frame */
          offset_delta = 44
          locals = [ class ext/mods/gameserver/model/actor/instance/SignsPriest, class ext/mods/gameserver/model/actor/Player, class java/lang/String, class java/util/StringTokenizer, int, class ext/mods/gameserver/enums/CabalType ]
          stack = [ class ext/mods/gameserver/model/actor/instance/SignsPriest, class ext/mods/gameserver/model/actor/Player, int ]
        frame_type = 255 /* full_frame */
          offset_delta = 1
          locals = [ class ext/mods/gameserver/model/actor/instance/SignsPriest, class ext/mods/gameserver/model/actor/Player, class java/lang/String, class java/util/StringTokenizer, int, class ext/mods/gameserver/enums/CabalType ]
          stack = [ class ext/mods/gameserver/model/actor/instance/SignsPriest, class ext/mods/gameserver/model/actor/Player, int, class java/lang/String ]
        frame_type = 4 /* same */
        frame_type = 255 /* full_frame */
          offset_delta = 35
          locals = [ class ext/mods/gameserver/model/actor/instance/SignsPriest, class ext/mods/gameserver/model/actor/Player, class java/lang/String, class java/util/StringTokenizer, int, class ext/mods/gameserver/enums/CabalType, int ]
          stack = [ class ext/mods/gameserver/model/actor/instance/SignsPriest, class ext/mods/gameserver/model/actor/Player, int ]
        frame_type = 255 /* full_frame */
          offset_delta = 1
          locals = [ class ext/mods/gameserver/model/actor/instance/SignsPriest, class ext/mods/gameserver/model/actor/Player, class java/lang/String, class java/util/StringTokenizer, int, class ext/mods/gameserver/enums/CabalType, int ]
          stack = [ class ext/mods/gameserver/model/actor/instance/SignsPriest, class ext/mods/gameserver/model/actor/Player, int, class java/lang/String ]
        frame_type = 4 /* same */
        frame_type = 26 /* same */
        frame_type = 64 /* same_locals_1_stack_item */
          stack = [ int ]
        frame_type = 252 /* append */
          offset_delta = 22
          locals = [ int ]
        frame_type = 249 /* chop */
          offset_delta = 20
        frame_type = 255 /* full_frame */
          offset_delta = 15
          locals = [ class ext/mods/gameserver/model/actor/instance/SignsPriest, class ext/mods/gameserver/model/actor/Player, class java/lang/String, class java/util/StringTokenizer, int, class ext/mods/gameserver/enums/CabalType ]
          stack = [ class ext/mods/gameserver/model/actor/instance/SignsPriest, class ext/mods/gameserver/model/actor/Player, int ]
        frame_type = 255 /* full_frame */
          offset_delta = 1
          locals = [ class ext/mods/gameserver/model/actor/instance/SignsPriest, class ext/mods/gameserver/model/actor/Player, class java/lang/String, class java/util/StringTokenizer, int, class ext/mods/gameserver/enums/CabalType ]
          stack = [ class ext/mods/gameserver/model/actor/instance/SignsPriest, class ext/mods/gameserver/model/actor/Player, int, class java/lang/String ]
        frame_type = 250 /* chop */
          offset_delta = 6
        frame_type = 21 /* same */
        frame_type = 3 /* same */
        frame_type = 64 /* same_locals_1_stack_item */
          stack = [ int ]
        frame_type = 255 /* full_frame */
          offset_delta = 13
          locals = [ class ext/mods/gameserver/model/actor/instance/SignsPriest, class ext/mods/gameserver/model/actor/Player, class java/lang/String, class java/util/StringTokenizer, int, top, int ]
          stack = [ class ext/mods/gameserver/model/actor/instance/SignsPriest, class ext/mods/gameserver/model/actor/Player ]
        frame_type = 255 /* full_frame */
          offset_delta = 1
          locals = [ class ext/mods/gameserver/model/actor/instance/SignsPriest, class ext/mods/gameserver/model/actor/Player, class java/lang/String, class java/util/StringTokenizer, int, top, int ]
          stack = [ class ext/mods/gameserver/model/actor/instance/SignsPriest, class ext/mods/gameserver/model/actor/Player, class java/lang/String ]
        frame_type = 249 /* chop */
          offset_delta = 10
        frame_type = 28 /* same */
        frame_type = 254 /* append */
          offset_delta = 52
          locals = [ class ext/mods/gameserver/enums/CabalType, top, class ext/mods/gameserver/enums/SealType ]
        frame_type = 64 /* same_locals_1_stack_item */
          stack = [ int ]
        frame_type = 252 /* append */
          offset_delta = 22
          locals = [ int ]
        frame_type = 250 /* chop */
          offset_delta = 42
        frame_type = 32 /* same */
        frame_type = 6 /* same */
        frame_type = 36 /* same */
        frame_type = 9 /* same */
        frame_type = 9 /* same */
        frame_type = 6 /* same */
        frame_type = 248 /* chop */
          offset_delta = 14
        frame_type = 255 /* full_frame */
          offset_delta = 31
          locals = [ class ext/mods/gameserver/model/actor/instance/SignsPriest, class ext/mods/gameserver/model/actor/Player, class java/lang/String, class java/util/StringTokenizer, int ]
          stack = [ class ext/mods/gameserver/model/actor/instance/SignsPriest, class ext/mods/gameserver/model/actor/Player, int ]
        frame_type = 255 /* full_frame */
          offset_delta = 1
          locals = [ class ext/mods/gameserver/model/actor/instance/SignsPriest, class ext/mods/gameserver/model/actor/Player, class java/lang/String, class java/util/StringTokenizer, int ]
          stack = [ class ext/mods/gameserver/model/actor/instance/SignsPriest, class ext/mods/gameserver/model/actor/Player, int, class java/lang/String ]
        frame_type = 6 /* same */
        frame_type = 255 /* full_frame */
          offset_delta = 15
          locals = [ class ext/mods/gameserver/model/actor/instance/SignsPriest, class ext/mods/gameserver/model/actor/Player, class java/lang/String, class java/util/StringTokenizer, int ]
          stack = [ class ext/mods/gameserver/model/actor/instance/SignsPriest, class ext/mods/gameserver/model/actor/Player, int ]
        frame_type = 255 /* full_frame */
          offset_delta = 1
          locals = [ class ext/mods/gameserver/model/actor/instance/SignsPriest, class ext/mods/gameserver/model/actor/Player, class java/lang/String, class java/util/StringTokenizer, int ]
          stack = [ class ext/mods/gameserver/model/actor/instance/SignsPriest, class ext/mods/gameserver/model/actor/Player, int, class java/lang/String ]
        frame_type = 6 /* same */
        frame_type = 255 /* full_frame */
          offset_delta = 53
          locals = [ class ext/mods/gameserver/model/actor/instance/SignsPriest, class ext/mods/gameserver/model/actor/Player, class java/lang/String, class java/util/StringTokenizer, int, top, top, top, int, class ext/mods/gameserver/model/item/instance/ItemInstance, class ext/mods/gameserver/model/item/instance/ItemInstance, class ext/mods/gameserver/model/item/instance/ItemInstance ]
          stack = []
        frame_type = 68 /* same_locals_1_stack_item */
          stack = [ int ]
        frame_type = 252 /* append */
          offset_delta = 10
          locals = [ int ]
        frame_type = 68 /* same_locals_1_stack_item */
          stack = [ int ]
        frame_type = 252 /* append */
          offset_delta = 10
          locals = [ int ]
        frame_type = 68 /* same_locals_1_stack_item */
          stack = [ int ]
        frame_type = 254 /* append */
          offset_delta = 34
          locals = [ int, int, int ]
        frame_type = 254 /* append */
          offset_delta = 41
          locals = [ class java/lang/String, int, int ]
        frame_type = 15 /* same */
        frame_type = 15 /* same */
        frame_type = 15 /* same */
        frame_type = 253 /* append */
          offset_delta = 25
          locals = [ int, int ]
        frame_type = 252 /* append */
          offset_delta = 30
          locals = [ int ]
        frame_type = 252 /* append */
          offset_delta = 29
          locals = [ int ]
        frame_type = 19 /* same */
        frame_type = 19 /* same */
        frame_type = 19 /* same */
        frame_type = 255 /* full_frame */
          offset_delta = 20
          locals = [ class ext/mods/gameserver/model/actor/instance/SignsPriest, class ext/mods/gameserver/model/actor/Player, class java/lang/String, class java/util/StringTokenizer, int, top, top, top, int, class ext/mods/gameserver/model/item/instance/ItemInstance, class ext/mods/gameserver/model/item/instance/ItemInstance, class ext/mods/gameserver/model/item/instance/ItemInstance, int, int, int, int, int, class java/lang/String, int, int, int, int, int, int ]
          stack = [ class ext/mods/gameserver/model/actor/instance/SignsPriest, class ext/mods/gameserver/model/actor/Player, int ]
        frame_type = 255 /* full_frame */
          offset_delta = 1
          locals = [ class ext/mods/gameserver/model/actor/instance/SignsPriest, class ext/mods/gameserver/model/actor/Player, class java/lang/String, class java/util/StringTokenizer, int, top, top, top, int, class ext/mods/gameserver/model/item/instance/ItemInstance, class ext/mods/gameserver/model/item/instance/ItemInstance, class ext/mods/gameserver/model/item/instance/ItemInstance, int, int, int, int, int, class java/lang/String, int, int, int, int, int, int ]
          stack = [ class ext/mods/gameserver/model/actor/instance/SignsPriest, class ext/mods/gameserver/model/actor/Player, int, class java/lang/String ]
        frame_type = 6 /* same */
        frame_type = 255 /* full_frame */
          offset_delta = 48
          locals = [ class ext/mods/gameserver/model/actor/instance/SignsPriest, class ext/mods/gameserver/model/actor/Player, class java/lang/String, class java/util/StringTokenizer, int, top, top, top, int, class ext/mods/gameserver/model/item/instance/ItemInstance, class ext/mods/gameserver/model/item/instance/ItemInstance, class ext/mods/gameserver/model/item/instance/ItemInstance, int, int, int, int, int, class java/lang/String, int, int, int, int, int, int ]
          stack = [ class ext/mods/gameserver/model/actor/instance/SignsPriest, class ext/mods/gameserver/model/actor/Player, int ]
        frame_type = 255 /* full_frame */
          offset_delta = 1
          locals = [ class ext/mods/gameserver/model/actor/instance/SignsPriest, class ext/mods/gameserver/model/actor/Player, class java/lang/String, class java/util/StringTokenizer, int, top, top, top, int, class ext/mods/gameserver/model/item/instance/ItemInstance, class ext/mods/gameserver/model/item/instance/ItemInstance, class ext/mods/gameserver/model/item/instance/ItemInstance, int, int, int, int, int, class java/lang/String, int, int, int, int, int, int ]
          stack = [ class ext/mods/gameserver/model/actor/instance/SignsPriest, class ext/mods/gameserver/model/actor/Player, int, class java/lang/String ]
        frame_type = 3 /* same */
        frame_type = 255 /* full_frame */
          offset_delta = 0
          locals = [ class ext/mods/gameserver/model/actor/instance/SignsPriest, class ext/mods/gameserver/model/actor/Player, class java/lang/String, class java/util/StringTokenizer, int, top, top, top, int, class ext/mods/gameserver/model/item/instance/ItemInstance, class ext/mods/gameserver/model/item/instance/ItemInstance, class ext/mods/gameserver/model/item/instance/ItemInstance, int, int, int, int, int, class java/lang/String, int, int ]
          stack = []
        frame_type = 255 /* full_frame */
          offset_delta = 31
          locals = [ class ext/mods/gameserver/model/actor/instance/SignsPriest, class ext/mods/gameserver/model/actor/Player, class java/lang/String, class java/util/StringTokenizer, int, top, top, top, int, class ext/mods/gameserver/model/item/instance/ItemInstance, class ext/mods/gameserver/model/item/instance/ItemInstance, class ext/mods/gameserver/model/item/instance/ItemInstance, int, int, int, int, int, class java/lang/String, int, int, class ext/mods/gameserver/network/serverpackets/NpcHtmlMessage ]
          stack = [ class ext/mods/gameserver/network/serverpackets/NpcHtmlMessage, class java/util/Locale ]
        frame_type = 255 /* full_frame */
          offset_delta = 2
          locals = [ class ext/mods/gameserver/model/actor/instance/SignsPriest, class ext/mods/gameserver/model/actor/Player, class java/lang/String, class java/util/StringTokenizer, int, top, top, top, int, class ext/mods/gameserver/model/item/instance/ItemInstance, class ext/mods/gameserver/model/item/instance/ItemInstance, class ext/mods/gameserver/model/item/instance/ItemInstance, int, int, int, int, int, class java/lang/String, int, int, class ext/mods/gameserver/network/serverpackets/NpcHtmlMessage ]
          stack = [ class ext/mods/gameserver/network/serverpackets/NpcHtmlMessage, class java/util/Locale, class java/lang/String ]
        frame_type = 255 /* full_frame */
          offset_delta = 58
          locals = [ class ext/mods/gameserver/model/actor/instance/SignsPriest, class ext/mods/gameserver/model/actor/Player, class java/lang/String, class java/util/StringTokenizer, int ]
          stack = []
        frame_type = 255 /* full_frame */
          offset_delta = 19
          locals = [ class ext/mods/gameserver/model/actor/instance/SignsPriest, class ext/mods/gameserver/model/actor/Player, class java/lang/String, class java/util/StringTokenizer, int, top, top, top, top, top, top, top, top, top, top, top, top, int ]
          stack = [ class java/lang/Exception ]
        frame_type = 10 /* same */
        frame_type = 14 /* same */
        frame_type = 17 /* same */
        frame_type = 17 /* same */
        frame_type = 16 /* same */
        frame_type = 255 /* full_frame */
          offset_delta = 10
          locals = [ class ext/mods/gameserver/model/actor/instance/SignsPriest, class ext/mods/gameserver/model/actor/Player, class java/lang/String, class java/util/StringTokenizer, int ]
          stack = []
        frame_type = 46 /* same */
        frame_type = 255 /* full_frame */
          offset_delta = 33
          locals = [ class ext/mods/gameserver/model/actor/instance/SignsPriest, class ext/mods/gameserver/model/actor/Player, class java/lang/String, class java/util/StringTokenizer, int, top, top, top, top, top, top, top, top, top, top, top, top, top, int ]
          stack = [ class ext/mods/gameserver/model/actor/instance/SignsPriest, class ext/mods/gameserver/model/actor/Player, int ]
        frame_type = 255 /* full_frame */
          offset_delta = 2
          locals = [ class ext/mods/gameserver/model/actor/instance/SignsPriest, class ext/mods/gameserver/model/actor/Player, class java/lang/String, class java/util/StringTokenizer, int, top, top, top, top, top, top, top, top, top, top, top, top, top, int ]
          stack = [ class ext/mods/gameserver/model/actor/instance/SignsPriest, class ext/mods/gameserver/model/actor/Player, int, class java/lang/String ]
        frame_type = 4 /* same */
        frame_type = 255 /* full_frame */
          offset_delta = 23
          locals = [ class ext/mods/gameserver/model/actor/instance/SignsPriest, class ext/mods/gameserver/model/actor/Player, class java/lang/String, class java/util/StringTokenizer, int, top, top, top, top, top, top, top, top, top, top, top, top, top, int ]
          stack = [ class ext/mods/gameserver/model/actor/instance/SignsPriest, class ext/mods/gameserver/model/actor/Player, int ]
        frame_type = 255 /* full_frame */
          offset_delta = 2
          locals = [ class ext/mods/gameserver/model/actor/instance/SignsPriest, class ext/mods/gameserver/model/actor/Player, class java/lang/String, class java/util/StringTokenizer, int, top, top, top, top, top, top, top, top, top, top, top, top, top, int ]
          stack = [ class ext/mods/gameserver/model/actor/instance/SignsPriest, class ext/mods/gameserver/model/actor/Player, int, class java/lang/String ]
        frame_type = 255 /* full_frame */
          offset_delta = 6
          locals = [ class ext/mods/gameserver/model/actor/instance/SignsPriest, class ext/mods/gameserver/model/actor/Player, class java/lang/String, class java/util/StringTokenizer, int ]
          stack = []
        frame_type = 255 /* full_frame */
          offset_delta = 51
          locals = [ class ext/mods/gameserver/model/actor/instance/SignsPriest, class ext/mods/gameserver/model/actor/Player, class java/lang/String, class java/util/StringTokenizer, int, top, top, top, top, top, top, top, top, top, top, top, top, top, int, int, int, int ]
          stack = []
        frame_type = 255 /* full_frame */
          offset_delta = 14
          locals = [ class ext/mods/gameserver/model/actor/instance/SignsPriest, class ext/mods/gameserver/model/actor/Player, class java/lang/String, class java/util/StringTokenizer, int ]
          stack = [ class java/lang/Exception ]
        frame_type = 15 /* same */
        frame_type = 255 /* full_frame */
          offset_delta = 15
          locals = [ class ext/mods/gameserver/model/actor/instance/SignsPriest, class ext/mods/gameserver/model/actor/Player, class java/lang/String, class java/util/StringTokenizer, int ]
          stack = [ class ext/mods/gameserver/model/actor/instance/SignsPriest, class ext/mods/gameserver/model/actor/Player, int ]
        frame_type = 255 /* full_frame */
          offset_delta = 1
          locals = [ class ext/mods/gameserver/model/actor/instance/SignsPriest, class ext/mods/gameserver/model/actor/Player, class java/lang/String, class java/util/StringTokenizer, int ]
          stack = [ class ext/mods/gameserver/model/actor/instance/SignsPriest, class ext/mods/gameserver/model/actor/Player, int, class java/lang/String ]
        frame_type = 6 /* same */
        frame_type = 255 /* full_frame */
          offset_delta = 42
          locals = [ class ext/mods/gameserver/model/actor/instance/SignsPriest, class ext/mods/gameserver/model/actor/Player, class java/lang/String, class java/util/StringTokenizer, int, top, top, top, int, top, top, top, top, top, top, top, top, top, int, int, int, class java/lang/String ]
          stack = []
        frame_type = 32 /* same */
        frame_type = 15 /* same */
        frame_type = 15 /* same */
        frame_type = 16 /* same */
        frame_type = 254 /* append */
          offset_delta = 44
          locals = [ class ext/mods/gameserver/model/item/instance/ItemInstance, class ext/mods/gameserver/model/item/instance/ItemInstance, class ext/mods/gameserver/model/item/instance/ItemInstance ]
        frame_type = 68 /* same_locals_1_stack_item */
          stack = [ int ]
        frame_type = 252 /* append */
          offset_delta = 10
          locals = [ int ]
        frame_type = 68 /* same_locals_1_stack_item */
          stack = [ int ]
        frame_type = 252 /* append */
          offset_delta = 10
          locals = [ int ]
        frame_type = 68 /* same_locals_1_stack_item */
          stack = [ int ]
        frame_type = 255 /* full_frame */
          offset_delta = 36
          locals = [ class ext/mods/gameserver/model/actor/instance/SignsPriest, class ext/mods/gameserver/model/actor/Player, class java/lang/String, class java/util/StringTokenizer, int, top, top, top, int, top, top, top, top, top, top, top, top, top, int, int, int, class java/lang/String, class ext/mods/gameserver/model/item/instance/ItemInstance, class ext/mods/gameserver/model/item/instance/ItemInstance, class ext/mods/gameserver/model/item/instance/ItemInstance, int, int, int, int ]
          stack = [ class ext/mods/gameserver/model/actor/instance/SignsPriest, class ext/mods/gameserver/model/actor/Player, int ]
        frame_type = 255 /* full_frame */
          offset_delta = 1
          locals = [ class ext/mods/gameserver/model/actor/instance/SignsPriest, class ext/mods/gameserver/model/actor/Player, class java/lang/String, class java/util/StringTokenizer, int, top, top, top, int, top, top, top, top, top, top, top, top, top, int, int, int, class java/lang/String, class ext/mods/gameserver/model/item/instance/ItemInstance, class ext/mods/gameserver/model/item/instance/ItemInstance, class ext/mods/gameserver/model/item/instance/ItemInstance, int, int, int, int ]
          stack = [ class ext/mods/gameserver/model/actor/instance/SignsPriest, class ext/mods/gameserver/model/actor/Player, int, class java/lang/String ]
        frame_type = 4 /* same */
        frame_type = 15 /* same */
        frame_type = 15 /* same */
        frame_type = 15 /* same */
        frame_type = 255 /* full_frame */
          offset_delta = 22
          locals = [ class ext/mods/gameserver/model/actor/instance/SignsPriest, class ext/mods/gameserver/model/actor/Player, class java/lang/String, class java/util/StringTokenizer, int, top, top, top, int, top, top, top, top, top, top, top, top, top, int, int, int, class java/lang/String, class ext/mods/gameserver/model/item/instance/ItemInstance, class ext/mods/gameserver/model/item/instance/ItemInstance, class ext/mods/gameserver/model/item/instance/ItemInstance, int, int, int, int ]
          stack = [ class ext/mods/gameserver/model/actor/instance/SignsPriest, class ext/mods/gameserver/model/actor/Player, int ]
        frame_type = 255 /* full_frame */
          offset_delta = 1
          locals = [ class ext/mods/gameserver/model/actor/instance/SignsPriest, class ext/mods/gameserver/model/actor/Player, class java/lang/String, class java/util/StringTokenizer, int, top, top, top, int, top, top, top, top, top, top, top, top, top, int, int, int, class java/lang/String, class ext/mods/gameserver/model/item/instance/ItemInstance, class ext/mods/gameserver/model/item/instance/ItemInstance, class ext/mods/gameserver/model/item/instance/ItemInstance, int, int, int, int ]
          stack = [ class ext/mods/gameserver/model/actor/instance/SignsPriest, class ext/mods/gameserver/model/actor/Player, int, class java/lang/String ]
        frame_type = 255 /* full_frame */
          offset_delta = 4
          locals = [ class ext/mods/gameserver/model/actor/instance/SignsPriest, class ext/mods/gameserver/model/actor/Player, class java/lang/String, class java/util/StringTokenizer, int, top, top, top, int, top, top, top, top, top, top, top, top, top, int, int, int, class java/lang/String ]
          stack = []
        frame_type = 252 /* append */
          offset_delta = 22
          locals = [ class ext/mods/gameserver/model/item/instance/ItemInstance ]
        frame_type = 255 /* full_frame */
          offset_delta = 31
          locals = [ class ext/mods/gameserver/model/actor/instance/SignsPriest, class ext/mods/gameserver/model/actor/Player, class java/lang/String, class java/util/StringTokenizer, int, top, top, top, int, top, top, top, top, top, top, top, top, top, int, int, int, class java/lang/String, class ext/mods/gameserver/model/item/instance/ItemInstance, class ext/mods/gameserver/network/serverpackets/NpcHtmlMessage ]
          stack = [ class ext/mods/gameserver/network/serverpackets/NpcHtmlMessage, class java/util/Locale ]
        frame_type = 255 /* full_frame */
          offset_delta = 2
          locals = [ class ext/mods/gameserver/model/actor/instance/SignsPriest, class ext/mods/gameserver/model/actor/Player, class java/lang/String, class java/util/StringTokenizer, int, top, top, top, int, top, top, top, top, top, top, top, top, top, int, int, int, class java/lang/String, class ext/mods/gameserver/model/item/instance/ItemInstance, class ext/mods/gameserver/network/serverpackets/NpcHtmlMessage ]
          stack = [ class ext/mods/gameserver/network/serverpackets/NpcHtmlMessage, class java/util/Locale, class java/lang/String ]
        frame_type = 255 /* full_frame */
          offset_delta = 68
          locals = [ class ext/mods/gameserver/model/actor/instance/SignsPriest, class ext/mods/gameserver/model/actor/Player, class java/lang/String, class java/util/StringTokenizer, int ]
          stack = []
        frame_type = 255 /* full_frame */
          offset_delta = 28
          locals = [ class ext/mods/gameserver/model/actor/instance/SignsPriest, class ext/mods/gameserver/model/actor/Player, class java/lang/String, class java/util/StringTokenizer, int, top, top, top, top, top, top, top, top, top, top, top, top, int, top, top, top, top, top, top, int ]
          stack = [ class java/lang/Exception ]
        frame_type = 255 /* full_frame */
          offset_delta = 18
          locals = [ class ext/mods/gameserver/model/actor/instance/SignsPriest, class ext/mods/gameserver/model/actor/Player, class java/lang/String, class java/util/StringTokenizer, int, top, top, top, top, top, top, top, top, top, top, top, top, int, top, top, top, top, top, top, int, class java/lang/Exception ]
          stack = [ class ext/mods/gameserver/model/actor/instance/SignsPriest, class ext/mods/gameserver/model/actor/Player, int ]
        frame_type = 255 /* full_frame */
          offset_delta = 2
          locals = [ class ext/mods/gameserver/model/actor/instance/SignsPriest, class ext/mods/gameserver/model/actor/Player, class java/lang/String, class java/util/StringTokenizer, int, top, top, top, top, top, top, top, top, top, top, top, top, int, top, top, top, top, top, top, int, class java/lang/Exception ]
          stack = [ class ext/mods/gameserver/model/actor/instance/SignsPriest, class ext/mods/gameserver/model/actor/Player, int, class java/lang/String ]
        frame_type = 250 /* chop */
          offset_delta = 4
        frame_type = 255 /* full_frame */
          offset_delta = 31
          locals = [ class ext/mods/gameserver/model/actor/instance/SignsPriest, class ext/mods/gameserver/model/actor/Player, class java/lang/String, class java/util/StringTokenizer, int, top, top, top, top, top, top, top, top, top, top, top, top, int, top, top, top, top, top, top, int, class ext/mods/gameserver/model/item/instance/ItemInstance ]
          stack = [ class ext/mods/gameserver/model/actor/instance/SignsPriest, class ext/mods/gameserver/model/actor/Player, int ]
        frame_type = 255 /* full_frame */
          offset_delta = 1
          locals = [ class ext/mods/gameserver/model/actor/instance/SignsPriest, class ext/mods/gameserver/model/actor/Player, class java/lang/String, class java/util/StringTokenizer, int, top, top, top, top, top, top, top, top, top, top, top, top, int, top, top, top, top, top, top, int, class ext/mods/gameserver/model/item/instance/ItemInstance ]
          stack = [ class ext/mods/gameserver/model/actor/instance/SignsPriest, class ext/mods/gameserver/model/actor/Player, int, class java/lang/String ]
        frame_type = 4 /* same */
        frame_type = 14 /* same */
        frame_type = 255 /* full_frame */
          offset_delta = 16
          locals = [ class ext/mods/gameserver/model/actor/instance/SignsPriest, class ext/mods/gameserver/model/actor/Player, class java/lang/String, class java/util/StringTokenizer, int, top, top, top, top, top, top, top, top, top, top, top, top, int, top, top, top, top, top, top, int, class ext/mods/gameserver/model/item/instance/ItemInstance ]
          stack = [ class ext/mods/gameserver/model/actor/instance/SignsPriest, class ext/mods/gameserver/model/actor/Player, int ]
        frame_type = 255 /* full_frame */
          offset_delta = 2
          locals = [ class ext/mods/gameserver/model/actor/instance/SignsPriest, class ext/mods/gameserver/model/actor/Player, class java/lang/String, class java/util/StringTokenizer, int, top, top, top, top, top, top, top, top, top, top, top, top, int, top, top, top, top, top, top, int, class ext/mods/gameserver/model/item/instance/ItemInstance ]
          stack = [ class ext/mods/gameserver/model/actor/instance/SignsPriest, class ext/mods/gameserver/model/actor/Player, int, class java/lang/String ]
        frame_type = 4 /* same */
        frame_type = 252 /* append */
          offset_delta = 32
          locals = [ int ]
        frame_type = 11 /* same */
        frame_type = 11 /* same */
        frame_type = 8 /* same */
        frame_type = 12 /* same */
        frame_type = 255 /* full_frame */
          offset_delta = 22
          locals = [ class ext/mods/gameserver/model/actor/instance/SignsPriest, class ext/mods/gameserver/model/actor/Player, class java/lang/String, class java/util/StringTokenizer, int, top, top, top, top, top, top, top, top, top, top, top, top, int, top, top, top, top, top, top, int, class ext/mods/gameserver/model/item/instance/ItemInstance, int ]
          stack = [ class ext/mods/gameserver/model/actor/instance/SignsPriest, class ext/mods/gameserver/model/actor/Player, int ]
        frame_type = 255 /* full_frame */
          offset_delta = 1
          locals = [ class ext/mods/gameserver/model/actor/instance/SignsPriest, class ext/mods/gameserver/model/actor/Player, class java/lang/String, class java/util/StringTokenizer, int, top, top, top, top, top, top, top, top, top, top, top, top, int, top, top, top, top, top, top, int, class ext/mods/gameserver/model/item/instance/ItemInstance, int ]
          stack = [ class ext/mods/gameserver/model/actor/instance/SignsPriest, class ext/mods/gameserver/model/actor/Player, int, class java/lang/String ]
        frame_type = 255 /* full_frame */
          offset_delta = 6
          locals = [ class ext/mods/gameserver/model/actor/instance/SignsPriest, class ext/mods/gameserver/model/actor/Player, class java/lang/String, class java/util/StringTokenizer, int ]
          stack = []
        frame_type = 51 /* same */
        frame_type = 255 /* full_frame */
          offset_delta = 27
          locals = [ class ext/mods/gameserver/model/actor/instance/SignsPriest, class ext/mods/gameserver/model/actor/Player, class java/lang/String, class java/util/StringTokenizer, int, top, top, top, top, top, top, top, top, top, top, top, top, top, top, top, top, top, top, top, top, top, top, class java/lang/StringBuilder ]
          stack = []
        frame_type = 8 /* same */
        frame_type = 252 /* append */
          offset_delta = 17
          locals = [ class java/util/Iterator ]
        frame_type = 254 /* append */
          offset_delta = 77
          locals = [ class java/util/Map$Entry, class ext/mods/gameserver/enums/SealType, class ext/mods/gameserver/enums/CabalType ]
        frame_type = 248 /* chop */
          offset_delta = 15
        frame_type = 250 /* chop */
          offset_delta = 2
        frame_type = 255 /* full_frame */
          offset_delta = 46
          locals = [ class ext/mods/gameserver/model/actor/instance/SignsPriest, class ext/mods/gameserver/model/actor/Player, class java/lang/String, class java/util/StringTokenizer, int ]
          stack = []
        frame_type = 89 /* same_locals_1_stack_item */
          stack = [ class java/lang/Exception ]
        frame_type = 255 /* full_frame */
          offset_delta = 18
          locals = [ class ext/mods/gameserver/model/actor/instance/SignsPriest, class ext/mods/gameserver/model/actor/Player, class java/lang/String, class java/util/StringTokenizer, int, top, top, top, top, top, top, top, top, top, top, top, top, top, top, top, top, top, top, top, top, top, top, top, class java/lang/Exception ]
          stack = [ class ext/mods/gameserver/model/actor/instance/SignsPriest, class ext/mods/gameserver/model/actor/Player, int ]
        frame_type = 255 /* full_frame */
          offset_delta = 2
          locals = [ class ext/mods/gameserver/model/actor/instance/SignsPriest, class ext/mods/gameserver/model/actor/Player, class java/lang/String, class java/util/StringTokenizer, int, top, top, top, top, top, top, top, top, top, top, top, top, top, top, top, top, top, top, top, top, top, top, top, class java/lang/Exception ]
          stack = [ class ext/mods/gameserver/model/actor/instance/SignsPriest, class ext/mods/gameserver/model/actor/Player, int, class java/lang/String ]
        frame_type = 255 /* full_frame */
          offset_delta = 4
          locals = [ class ext/mods/gameserver/model/actor/instance/SignsPriest, class ext/mods/gameserver/model/actor/Player, class java/lang/String, class java/util/StringTokenizer, int, top, top, top, top, top, top, top, top, top, top, top, top, int, top, top, top, top, top, top, int ]
          stack = []
        frame_type = 255 /* full_frame */
          offset_delta = 57
          locals = [ class ext/mods/gameserver/model/actor/instance/SignsPriest, class ext/mods/gameserver/model/actor/Player, class java/lang/String, class java/util/StringTokenizer, int, top, top, top, top, top, top, top, top, top, top, top, top, int, top, int, top, top, top, top, int, top, top, top, int, int ]
          stack = []
        frame_type = 12 /* same */
        frame_type = 12 /* same */
        frame_type = 10 /* same */
        frame_type = 255 /* full_frame */
          offset_delta = 37
          locals = [ class ext/mods/gameserver/model/actor/instance/SignsPriest, class ext/mods/gameserver/model/actor/Player, class java/lang/String, class java/util/StringTokenizer, int, top, top, top, top, top, top, top, top, top, top, top, top, int, top, int, top, top, top, top, int, top, top, top, int, int ]
          stack = [ class ext/mods/gameserver/model/actor/instance/SignsPriest, class ext/mods/gameserver/model/actor/Player, int ]
        frame_type = 255 /* full_frame */
          offset_delta = 2
          locals = [ class ext/mods/gameserver/model/actor/instance/SignsPriest, class ext/mods/gameserver/model/actor/Player, class java/lang/String, class java/util/StringTokenizer, int, top, top, top, top, top, top, top, top, top, top, top, top, int, top, int, top, top, top, top, int, top, top, top, int, int ]
          stack = [ class ext/mods/gameserver/model/actor/instance/SignsPriest, class ext/mods/gameserver/model/actor/Player, int, class java/lang/String ]
        frame_type = 4 /* same */
        frame_type = 28 /* same */
        frame_type = 18 /* same */
        frame_type = 18 /* same */
        frame_type = 15 /* same */
        frame_type = 255 /* full_frame */
          offset_delta = 30
          locals = [ class ext/mods/gameserver/model/actor/instance/SignsPriest, class ext/mods/gameserver/model/actor/Player, class java/lang/String, class java/util/StringTokenizer, int, top, top, top, top, top, top, top, top, top, top, top, top, int, top, int, top, top, top, top, int, top, top, top, int, int ]
          stack = [ class ext/mods/gameserver/model/actor/instance/SignsPriest, class ext/mods/gameserver/model/actor/Player, int ]
        frame_type = 255 /* full_frame */
          offset_delta = 1
          locals = [ class ext/mods/gameserver/model/actor/instance/SignsPriest, class ext/mods/gameserver/model/actor/Player, class java/lang/String, class java/util/StringTokenizer, int, top, top, top, top, top, top, top, top, top, top, top, top, int, top, int, top, top, top, top, int, top, top, top, int, int ]
          stack = [ class ext/mods/gameserver/model/actor/instance/SignsPriest, class ext/mods/gameserver/model/actor/Player, int, class java/lang/String ]
        frame_type = 255 /* full_frame */
          offset_delta = 6
          locals = [ class ext/mods/gameserver/model/actor/instance/SignsPriest, class ext/mods/gameserver/model/actor/Player, class java/lang/String, class java/util/StringTokenizer, int ]
          stack = []
        frame_type = 249 /* chop */
          offset_delta = 8
        frame_type = 2 /* same */
        frame_type = 5 /* same */

  public void showChatWindow(ext.mods.gameserver.model.actor.Player, int);
    descriptor: (Lext/mods/gameserver/model/actor/Player;I)V
    flags: (0x0001) ACC_PUBLIC
    Code:
      stack=4, locals=8, args_size=3
         0: aload_0
         1: invokevirtual #463                // Method getTemplate:()Lext/mods/gameserver/model/actor/template/NpcTemplate;
         4: invokevirtual #467                // Method ext/mods/gameserver/model/actor/template/NpcTemplate.getNpcId:()I
         7: istore_3
         8: ldc_w         #472                // String html/seven_signs/
        11: astore        4
        13: invokestatic  #102                // Method ext/mods/gameserver/data/manager/SevenSignsManager.getInstance:()Lext/mods/gameserver/data/manager/SevenSignsManager;
        16: aload_1
        17: invokevirtual #106                // Method ext/mods/gameserver/model/actor/Player.getObjectId:()I
        20: invokevirtual #107                // Method ext/mods/gameserver/data/manager/SevenSignsManager.getPlayerCabal:(I)Lext/mods/gameserver/enums/CabalType;
        23: astore        5
        25: invokestatic  #102                // Method ext/mods/gameserver/data/manager/SevenSignsManager.getInstance:()Lext/mods/gameserver/data/manager/SevenSignsManager;
        28: invokevirtual #325                // Method ext/mods/gameserver/data/manager/SevenSignsManager.getWinningCabal:()Lext/mods/gameserver/enums/CabalType;
        31: astore        6
        33: iload_3
        34: lookupswitch  { // 3

                   31092: 68

                   31113: 80

                   31126: 210
                 default: 334
            }
        68: aload         4
        70: invokedynamic #474,  0            // InvokeDynamic #5:makeConcatWithConstants:(Ljava/lang/String;)Ljava/lang/String;
        75: astore        4
        77: goto          343
        80: getstatic     #475                // Field ext/mods/Config.STRICT_SEVENSIGNS:Z
        83: ifeq          198
        86: invokestatic  #102                // Method ext/mods/gameserver/data/manager/SevenSignsManager.getInstance:()Lext/mods/gameserver/data/manager/SevenSignsManager;
        89: getstatic     #478                // Field ext/mods/gameserver/enums/SealType.AVARICE:Lext/mods/gameserver/enums/SealType;
        92: invokevirtual #482                // Method ext/mods/gameserver/data/manager/SevenSignsManager.getSealOwner:(Lext/mods/gameserver/enums/SealType;)Lext/mods/gameserver/enums/CabalType;
        95: astore        7
        97: getstatic     #486                // Field ext/mods/gameserver/model/actor/instance/SignsPriest$1.$SwitchMap$ext$mods$gameserver$enums$CabalType:[I
       100: aload         6
       102: invokevirtual #489                // Method ext/mods/gameserver/enums/CabalType.ordinal:()I
       105: iaload
       106: lookupswitch  { // 2

                       1: 132

                       2: 161
                 default: 190
            }
       132: aload         5
       134: aload         6
       136: if_acmpne     146
       139: aload         5
       141: aload         7
       143: if_acmpeq     198
       146: aload_1
       147: getstatic     #490                // Field ext/mods/gameserver/network/SystemMessageId.CAN_BE_USED_BY_DAWN:Lext/mods/gameserver/network/SystemMessageId;
       150: invokevirtual #72                 // Method ext/mods/gameserver/model/actor/Player.sendPacket:(Lext/mods/gameserver/network/SystemMessageId;)V
       153: aload_1
       154: getstatic     #493                // Field ext/mods/gameserver/network/serverpackets/ActionFailed.STATIC_PACKET:Lext/mods/gameserver/network/serverpackets/ActionFailed;
       157: invokevirtual #267                // Method ext/mods/gameserver/model/actor/Player.sendPacket:(Lext/mods/gameserver/network/serverpackets/L2GameServerPacket;)V
       160: return
       161: aload         5
       163: aload         6
       165: if_acmpne     175
       168: aload         5
       170: aload         7
       172: if_acmpeq     198
       175: aload_1
       176: getstatic     #499                // Field ext/mods/gameserver/network/SystemMessageId.CAN_BE_USED_BY_DUSK:Lext/mods/gameserver/network/SystemMessageId;
       179: invokevirtual #72                 // Method ext/mods/gameserver/model/actor/Player.sendPacket:(Lext/mods/gameserver/network/SystemMessageId;)V
       182: aload_1
       183: getstatic     #493                // Field ext/mods/gameserver/network/serverpackets/ActionFailed.STATIC_PACKET:Lext/mods/gameserver/network/serverpackets/ActionFailed;
       186: invokevirtual #267                // Method ext/mods/gameserver/model/actor/Player.sendPacket:(Lext/mods/gameserver/network/serverpackets/L2GameServerPacket;)V
       189: return
       190: aload_1
       191: getstatic     #502                // Field ext/mods/gameserver/network/SystemMessageId.QUEST_EVENT_PERIOD:Lext/mods/gameserver/network/SystemMessageId;
       194: invokevirtual #72                 // Method ext/mods/gameserver/model/actor/Player.sendPacket:(Lext/mods/gameserver/network/SystemMessageId;)V
       197: return
       198: aload         4
       200: invokedynamic #505,  0            // InvokeDynamic #6:makeConcatWithConstants:(Ljava/lang/String;)Ljava/lang/String;
       205: astore        4
       207: goto          343
       210: getstatic     #475                // Field ext/mods/Config.STRICT_SEVENSIGNS:Z
       213: ifeq          322
       216: invokestatic  #102                // Method ext/mods/gameserver/data/manager/SevenSignsManager.getInstance:()Lext/mods/gameserver/data/manager/SevenSignsManager;
       219: getstatic     #506                // Field ext/mods/gameserver/enums/SealType.GNOSIS:Lext/mods/gameserver/enums/SealType;
       222: invokevirtual #482                // Method ext/mods/gameserver/data/manager/SevenSignsManager.getSealOwner:(Lext/mods/gameserver/enums/SealType;)Lext/mods/gameserver/enums/CabalType;
       225: astore        7
       227: getstatic     #486                // Field ext/mods/gameserver/model/actor/instance/SignsPriest$1.$SwitchMap$ext$mods$gameserver$enums$CabalType:[I
       230: aload         6
       232: invokevirtual #489                // Method ext/mods/gameserver/enums/CabalType.ordinal:()I
       235: iaload
       236: lookupswitch  { // 2

                       1: 264

                       2: 293
                 default: 322
            }
       264: aload         5
       266: aload         6
       268: if_acmpne     278
       271: aload         5
       273: aload         7
       275: if_acmpeq     322
       278: aload_1
       279: getstatic     #490                // Field ext/mods/gameserver/network/SystemMessageId.CAN_BE_USED_BY_DAWN:Lext/mods/gameserver/network/SystemMessageId;
       282: invokevirtual #72                 // Method ext/mods/gameserver/model/actor/Player.sendPacket:(Lext/mods/gameserver/network/SystemMessageId;)V
       285: aload_1
       286: getstatic     #493                // Field ext/mods/gameserver/network/serverpackets/ActionFailed.STATIC_PACKET:Lext/mods/gameserver/network/serverpackets/ActionFailed;
       289: invokevirtual #267                // Method ext/mods/gameserver/model/actor/Player.sendPacket:(Lext/mods/gameserver/network/serverpackets/L2GameServerPacket;)V
       292: return
       293: aload         5
       295: aload         6
       297: if_acmpne     307
       300: aload         5
       302: aload         7
       304: if_acmpeq     322
       307: aload_1
       308: getstatic     #499                // Field ext/mods/gameserver/network/SystemMessageId.CAN_BE_USED_BY_DUSK:Lext/mods/gameserver/network/SystemMessageId;
       311: invokevirtual #72                 // Method ext/mods/gameserver/model/actor/Player.sendPacket:(Lext/mods/gameserver/network/SystemMessageId;)V
       314: aload_1
       315: getstatic     #493                // Field ext/mods/gameserver/network/serverpackets/ActionFailed.STATIC_PACKET:Lext/mods/gameserver/network/serverpackets/ActionFailed;
       318: invokevirtual #267                // Method ext/mods/gameserver/model/actor/Player.sendPacket:(Lext/mods/gameserver/network/serverpackets/L2GameServerPacket;)V
       321: return
       322: aload         4
       324: invokedynamic #509,  0            // InvokeDynamic #7:makeConcatWithConstants:(Ljava/lang/String;)Ljava/lang/String;
       329: astore        4
       331: goto          343
       334: aload_0
       335: aload_1
       336: iload_3
       337: iload_2
       338: invokevirtual #510                // Method getHtmlPath:(Lext/mods/gameserver/model/actor/Player;II)Ljava/lang/String;
       341: astore        4
       343: new           #270                // class ext/mods/gameserver/network/serverpackets/NpcHtmlMessage
       346: dup
       347: aload_0
       348: invokevirtual #17                 // Method getObjectId:()I
       351: invokespecial #272                // Method ext/mods/gameserver/network/serverpackets/NpcHtmlMessage."<init>":(I)V
       354: astore        7
       356: aload         7
       358: aload_1
       359: invokevirtual #275                // Method ext/mods/gameserver/model/actor/Player.getLocale:()Ljava/util/Locale;
       362: aload         4
       364: invokevirtual #283                // Method ext/mods/gameserver/network/serverpackets/NpcHtmlMessage.setFile:(Ljava/util/Locale;Ljava/lang/String;)V
       367: aload         7
       369: ldc_w         #300                // String %objectId%
       372: aload_0
       373: invokevirtual #17                 // Method getObjectId:()I
       376: invokevirtual #295                // Method ext/mods/gameserver/network/serverpackets/NpcHtmlMessage.replace:(Ljava/lang/String;I)V
       379: aload_1
       380: aload         7
       382: invokevirtual #267                // Method ext/mods/gameserver/model/actor/Player.sendPacket:(Lext/mods/gameserver/network/serverpackets/L2GameServerPacket;)V
       385: aload_1
       386: getstatic     #493                // Field ext/mods/gameserver/network/serverpackets/ActionFailed.STATIC_PACKET:Lext/mods/gameserver/network/serverpackets/ActionFailed;
       389: invokevirtual #267                // Method ext/mods/gameserver/model/actor/Player.sendPacket:(Lext/mods/gameserver/network/serverpackets/L2GameServerPacket;)V
       392: return
      LineNumberTable:
        line 583: 0
        line 584: 8
        line 586: 13
        line 587: 25
        line 589: 33
        line 592: 68
        line 593: 77
        line 596: 80
        line 598: 86
        line 599: 97
        line 602: 132
        line 604: 146
        line 605: 153
        line 606: 160
        line 611: 161
        line 613: 175
        line 614: 182
        line 615: 189
        line 620: 190
        line 621: 197
        line 624: 198
        line 625: 207
        line 628: 210
        line 630: 216
        line 631: 227
        line 634: 264
        line 636: 278
        line 637: 285
        line 638: 292
        line 643: 293
        line 645: 307
        line 646: 314
        line 647: 321
        line 652: 322
        line 653: 331
        line 656: 334
        line 660: 343
        line 661: 356
        line 662: 367
        line 663: 379
        line 665: 385
        line 666: 392
      LocalVariableTable:
        Start  Length  Slot  Name   Signature
           97     101     7 sealAvariceOwner   Lext/mods/gameserver/enums/CabalType;
          227      95     7 sealGnosisOwner   Lext/mods/gameserver/enums/CabalType;
            0     393     0  this   Lext/mods/gameserver/model/actor/instance/SignsPriest;
            0     393     1 player   Lext/mods/gameserver/model/actor/Player;
            0     393     2   val   I
            8     385     3 npcId   I
           13     380     4 filename   Ljava/lang/String;
           25     368     5 playerCabal   Lext/mods/gameserver/enums/CabalType;
           33     360     6 winningCabal   Lext/mods/gameserver/enums/CabalType;
          356      37     7  html   Lext/mods/gameserver/network/serverpackets/NpcHtmlMessage;
      StackMapTable: number_of_entries = 16
        frame_type = 255 /* full_frame */
          offset_delta = 68
          locals = [ class ext/mods/gameserver/model/actor/instance/SignsPriest, class ext/mods/gameserver/model/actor/Player, int, int, class java/lang/String, class ext/mods/gameserver/enums/CabalType, class ext/mods/gameserver/enums/CabalType ]
          stack = []
        frame_type = 11 /* same */
        frame_type = 252 /* append */
          offset_delta = 51
          locals = [ class ext/mods/gameserver/enums/CabalType ]
        frame_type = 13 /* same */
        frame_type = 14 /* same */
        frame_type = 13 /* same */
        frame_type = 14 /* same */
        frame_type = 250 /* chop */
          offset_delta = 7
        frame_type = 11 /* same */
        frame_type = 252 /* append */
          offset_delta = 53
          locals = [ class ext/mods/gameserver/enums/CabalType ]
        frame_type = 13 /* same */
        frame_type = 14 /* same */
        frame_type = 13 /* same */
        frame_type = 250 /* chop */
          offset_delta = 14
        frame_type = 11 /* same */
        frame_type = 8 /* same */
}
SourceFile: "SignsPriest.java"
NestMembers:
  ext/mods/gameserver/model/actor/instance/SignsPriest$1
BootstrapMethods:
  0: #628 REF_invokeStatic java/lang/invoke/StringConcatFactory.makeConcatWithConstants:(Ljava/lang/invoke/MethodHandles$Lookup;Ljava/lang/String;Ljava/lang/invoke/MethodType;Ljava/lang/String;[Ljava/lang/Object;)Ljava/lang/invoke/CallSite;
    Method arguments:
      #604 html/seven_signs/\u0001
  1: #628 REF_invokeStatic java/lang/invoke/StringConcatFactory.makeConcatWithConstants:(Ljava/lang/invoke/MethodHandles$Lookup;Ljava/lang/String;Ljava/lang/invoke/MethodType;Ljava/lang/String;[Ljava/lang/Object;)Ljava/lang/invoke/CallSite;
    Method arguments:
      #606 \u0001_\u0001
  2: #628 REF_invokeStatic java/lang/invoke/StringConcatFactory.makeConcatWithConstants:(Ljava/lang/invoke/MethodHandles$Lookup;Ljava/lang/String;Ljava/lang/invoke/MethodType;Ljava/lang/String;[Ljava/lang/Object;)Ljava/lang/invoke/CallSite;
    Method arguments:
      #608 [\u0001: \u0001]<br>
  3: #628 REF_invokeStatic java/lang/invoke/StringConcatFactory.makeConcatWithConstants:(Ljava/lang/invoke/MethodHandles$Lookup;Ljava/lang/String;Ljava/lang/invoke/MethodType;Ljava/lang/String;[Ljava/lang/Object;)Ljava/lang/invoke/CallSite;
    Method arguments:
      #610 [\u0001: Nothingness]<br>
  4: #628 REF_invokeStatic java/lang/invoke/StringConcatFactory.makeConcatWithConstants:(Ljava/lang/invoke/MethodHandles$Lookup;Ljava/lang/String;Ljava/lang/invoke/MethodType;Ljava/lang/String;[Ljava/lang/Object;)Ljava/lang/invoke/CallSite;
    Method arguments:
      #612 <a action=\"bypass -h npc_\u0001_Chat 0\">Go back.</a></body></html>
  5: #628 REF_invokeStatic java/lang/invoke/StringConcatFactory.makeConcatWithConstants:(Ljava/lang/invoke/MethodHandles$Lookup;Ljava/lang/String;Ljava/lang/invoke/MethodType;Ljava/lang/String;[Ljava/lang/Object;)Ljava/lang/invoke/CallSite;
    Method arguments:
      #614 \u0001blkmrkt_1.htm
  6: #628 REF_invokeStatic java/lang/invoke/StringConcatFactory.makeConcatWithConstants:(Ljava/lang/invoke/MethodHandles$Lookup;Ljava/lang/String;Ljava/lang/invoke/MethodType;Ljava/lang/String;[Ljava/lang/Object;)Ljava/lang/invoke/CallSite;
    Method arguments:
      #616 \u0001mammmerch_1.htm
  7: #628 REF_invokeStatic java/lang/invoke/StringConcatFactory.makeConcatWithConstants:(Ljava/lang/invoke/MethodHandles$Lookup;Ljava/lang/String;Ljava/lang/invoke/MethodType;Ljava/lang/String;[Ljava/lang/Object;)Ljava/lang/invoke/CallSite;
    Method arguments:
      #618 \u0001mammblack_1.htm
  8: #628 REF_invokeStatic java/lang/invoke/StringConcatFactory.makeConcatWithConstants:(Ljava/lang/invoke/MethodHandles$Lookup;Ljava/lang/String;Ljava/lang/invoke/MethodType;Ljava/lang/String;[Ljava/lang/Object;)Ljava/lang/invoke/CallSite;
    Method arguments:
      #620 desc_\u0001
  9: #628 REF_invokeStatic java/lang/invoke/StringConcatFactory.makeConcatWithConstants:(Ljava/lang/invoke/MethodHandles$Lookup;Ljava/lang/String;Ljava/lang/invoke/MethodType;Ljava/lang/String;[Ljava/lang/Object;)Ljava/lang/invoke/CallSite;
    Method arguments:
      #622 signs_\u0001
  10: #628 REF_invokeStatic java/lang/invoke/StringConcatFactory.makeConcatWithConstants:(Ljava/lang/invoke/MethodHandles$Lookup;Ljava/lang/String;Ljava/lang/invoke/MethodType;Ljava/lang/String;[Ljava/lang/Object;)Ljava/lang/invoke/CallSite;
    Method arguments:
      #624 \u0001\u0001
  11: #628 REF_invokeStatic java/lang/invoke/StringConcatFactory.makeConcatWithConstants:(Ljava/lang/invoke/MethodHandles$Lookup;Ljava/lang/String;Ljava/lang/invoke/MethodType;Ljava/lang/String;[Ljava/lang/Object;)Ljava/lang/invoke/CallSite;
    Method arguments:
      #626 _\u0001.htm
InnerClasses:
  static #201;                            // class ext/mods/gameserver/model/actor/instance/SignsPriest$1
  public static #635= #425 of #405;       // Entry=class java/util/Map$Entry of class java/util/Map
  public static final #640= #636 of #638; // Lookup=class java/lang/invoke/MethodHandles$Lookup of class java/lang/invoke/MethodHandles
