// Bytecode for: ext.mods.gameserver.handler.skillhandlers.Harvest
// File: ext\mods\gameserver\handler\skillhandlers\Harvest.class

Classfile /c:/Users/User/Desktop/BrProject/bin/main/ext/mods/gameserver/handler/skillhandlers/Harvest.class
  Last modified 9 de jul de 2026; size 4588 bytes
  MD5 checksum 431452e48e1b6f7d9cdd75696341a60a
  Compiled from "Harvest.java"
public class ext.mods.gameserver.handler.skillhandlers.Harvest implements ext.mods.gameserver.handler.ISkillHandler
  minor version: 0
  major version: 69
  flags: (0x0021) ACC_PUBLIC, ACC_SUPER
  this_class: #48                         // ext/mods/gameserver/handler/skillhandlers/Harvest
  super_class: #2                         // java/lang/Object
  interfaces: 1, fields: 1, methods: 5, attributes: 1
Constant pool:
    #1 = Methodref          #2.#3         // java/lang/Object."<init>":()V
    #2 = Class              #4            // java/lang/Object
    #3 = NameAndType        #5:#6         // "<init>":()V
    #4 = Utf8               java/lang/Object
    #5 = Utf8               <init>
    #6 = Utf8               ()V
    #7 = Class              #8            // ext/mods/gameserver/model/actor/Player
    #8 = Utf8               ext/mods/gameserver/model/actor/Player
    #9 = Class              #10           // ext/mods/gameserver/model/actor/instance/Monster
   #10 = Utf8               ext/mods/gameserver/model/actor/instance/Monster
   #11 = Fieldref           #12.#13       // ext/mods/gameserver/network/SystemMessageId.THE_HARVEST_FAILED_BECAUSE_THE_SEED_WAS_NOT_SOWN:Lext/mods/gameserver/network/SystemMessageId;
   #12 = Class              #14           // ext/mods/gameserver/network/SystemMessageId
   #13 = NameAndType        #15:#16       // THE_HARVEST_FAILED_BECAUSE_THE_SEED_WAS_NOT_SOWN:Lext/mods/gameserver/network/SystemMessageId;
   #14 = Utf8               ext/mods/gameserver/network/SystemMessageId
   #15 = Utf8               THE_HARVEST_FAILED_BECAUSE_THE_SEED_WAS_NOT_SOWN
   #16 = Utf8               Lext/mods/gameserver/network/SystemMessageId;
   #17 = Methodref          #7.#18        // ext/mods/gameserver/model/actor/Player.sendPacket:(Lext/mods/gameserver/network/SystemMessageId;)V
   #18 = NameAndType        #19:#20       // sendPacket:(Lext/mods/gameserver/network/SystemMessageId;)V
   #19 = Utf8               sendPacket
   #20 = Utf8               (Lext/mods/gameserver/network/SystemMessageId;)V
   #21 = Methodref          #9.#22        // ext/mods/gameserver/model/actor/instance/Monster.getSeedState:()Lext/mods/gameserver/model/actor/container/monster/SeedState;
   #22 = NameAndType        #23:#24       // getSeedState:()Lext/mods/gameserver/model/actor/container/monster/SeedState;
   #23 = Utf8               getSeedState
   #24 = Utf8               ()Lext/mods/gameserver/model/actor/container/monster/SeedState;
   #25 = Methodref          #26.#27       // ext/mods/gameserver/model/actor/container/monster/SeedState.isSeeded:()Z
   #26 = Class              #28           // ext/mods/gameserver/model/actor/container/monster/SeedState
   #27 = NameAndType        #29:#30       // isSeeded:()Z
   #28 = Utf8               ext/mods/gameserver/model/actor/container/monster/SeedState
   #29 = Utf8               isSeeded
   #30 = Utf8               ()Z
   #31 = Methodref          #26.#32       // ext/mods/gameserver/model/actor/container/monster/SeedState.isHarvested:()Z
   #32 = NameAndType        #33:#30       // isHarvested:()Z
   #33 = Utf8               isHarvested
   #34 = Fieldref           #12.#35       // ext/mods/gameserver/network/SystemMessageId.THE_HARVEST_HAS_FAILED:Lext/mods/gameserver/network/SystemMessageId;
   #35 = NameAndType        #36:#16       // THE_HARVEST_HAS_FAILED:Lext/mods/gameserver/network/SystemMessageId;
   #36 = Utf8               THE_HARVEST_HAS_FAILED
   #37 = Methodref          #26.#38       // ext/mods/gameserver/model/actor/container/monster/SeedState.isAllowedToHarvest:(Lext/mods/gameserver/model/actor/Player;)Z
   #38 = NameAndType        #39:#40       // isAllowedToHarvest:(Lext/mods/gameserver/model/actor/Player;)Z
   #39 = Utf8               isAllowedToHarvest
   #40 = Utf8               (Lext/mods/gameserver/model/actor/Player;)Z
   #41 = Fieldref           #12.#42       // ext/mods/gameserver/network/SystemMessageId.YOU_ARE_NOT_AUTHORIZED_TO_HARVEST:Lext/mods/gameserver/network/SystemMessageId;
   #42 = NameAndType        #43:#16       // YOU_ARE_NOT_AUTHORIZED_TO_HARVEST:Lext/mods/gameserver/network/SystemMessageId;
   #43 = Utf8               YOU_ARE_NOT_AUTHORIZED_TO_HARVEST
   #44 = Methodref          #26.#45       // ext/mods/gameserver/model/actor/container/monster/SeedState.setHarvested:()V
   #45 = NameAndType        #46:#6        // setHarvested:()V
   #46 = Utf8               setHarvested
   #47 = Methodref          #48.#49       // ext/mods/gameserver/handler/skillhandlers/Harvest.calcSuccess:(Lext/mods/gameserver/model/actor/Player;Lext/mods/gameserver/model/actor/Creature;)Z
   #48 = Class              #50           // ext/mods/gameserver/handler/skillhandlers/Harvest
   #49 = NameAndType        #51:#52       // calcSuccess:(Lext/mods/gameserver/model/actor/Player;Lext/mods/gameserver/model/actor/Creature;)Z
   #50 = Utf8               ext/mods/gameserver/handler/skillhandlers/Harvest
   #51 = Utf8               calcSuccess
   #52 = Utf8               (Lext/mods/gameserver/model/actor/Player;Lext/mods/gameserver/model/actor/Creature;)Z
   #53 = Methodref          #26.#54       // ext/mods/gameserver/model/actor/container/monster/SeedState.getHarvestedCrop:()Lext/mods/gameserver/model/holder/IntIntHolder;
   #54 = NameAndType        #55:#56       // getHarvestedCrop:()Lext/mods/gameserver/model/holder/IntIntHolder;
   #55 = Utf8               getHarvestedCrop
   #56 = Utf8               ()Lext/mods/gameserver/model/holder/IntIntHolder;
   #57 = Methodref          #58.#59       // ext/mods/gameserver/model/holder/IntIntHolder.getId:()I
   #58 = Class              #60           // ext/mods/gameserver/model/holder/IntIntHolder
   #59 = NameAndType        #61:#62       // getId:()I
   #60 = Utf8               ext/mods/gameserver/model/holder/IntIntHolder
   #61 = Utf8               getId
   #62 = Utf8               ()I
   #63 = Methodref          #58.#64       // ext/mods/gameserver/model/holder/IntIntHolder.getValue:()I
   #64 = NameAndType        #65:#62       // getValue:()I
   #65 = Utf8               getValue
   #66 = Methodref          #7.#67        // ext/mods/gameserver/model/actor/Player.addEarnedItem:(IIZ)Lext/mods/gameserver/model/item/instance/ItemInstance;
   #67 = NameAndType        #68:#69       // addEarnedItem:(IIZ)Lext/mods/gameserver/model/item/instance/ItemInstance;
   #68 = Utf8               addEarnedItem
   #69 = Utf8               (IIZ)Lext/mods/gameserver/model/item/instance/ItemInstance;
   #70 = Methodref          #7.#71        // ext/mods/gameserver/model/actor/Player.isInParty:()Z
   #71 = NameAndType        #72:#30       // isInParty:()Z
   #72 = Utf8               isInParty
   #73 = Fieldref           #12.#74       // ext/mods/gameserver/network/SystemMessageId.S1_HARVESTED_S3_S2S:Lext/mods/gameserver/network/SystemMessageId;
   #74 = NameAndType        #75:#16       // S1_HARVESTED_S3_S2S:Lext/mods/gameserver/network/SystemMessageId;
   #75 = Utf8               S1_HARVESTED_S3_S2S
   #76 = Methodref          #77.#78       // ext/mods/gameserver/network/serverpackets/SystemMessage.getSystemMessage:(Lext/mods/gameserver/network/SystemMessageId;)Lext/mods/gameserver/network/serverpackets/SystemMessage;
   #77 = Class              #79           // ext/mods/gameserver/network/serverpackets/SystemMessage
   #78 = NameAndType        #80:#81       // getSystemMessage:(Lext/mods/gameserver/network/SystemMessageId;)Lext/mods/gameserver/network/serverpackets/SystemMessage;
   #79 = Utf8               ext/mods/gameserver/network/serverpackets/SystemMessage
   #80 = Utf8               getSystemMessage
   #81 = Utf8               (Lext/mods/gameserver/network/SystemMessageId;)Lext/mods/gameserver/network/serverpackets/SystemMessage;
   #82 = Methodref          #77.#83       // ext/mods/gameserver/network/serverpackets/SystemMessage.addCharName:(Lext/mods/gameserver/model/actor/Creature;)Lext/mods/gameserver/network/serverpackets/SystemMessage;
   #83 = NameAndType        #84:#85       // addCharName:(Lext/mods/gameserver/model/actor/Creature;)Lext/mods/gameserver/network/serverpackets/SystemMessage;
   #84 = Utf8               addCharName
   #85 = Utf8               (Lext/mods/gameserver/model/actor/Creature;)Lext/mods/gameserver/network/serverpackets/SystemMessage;
   #86 = Methodref          #77.#87       // ext/mods/gameserver/network/serverpackets/SystemMessage.addItemName:(I)Lext/mods/gameserver/network/serverpackets/SystemMessage;
   #87 = NameAndType        #88:#89       // addItemName:(I)Lext/mods/gameserver/network/serverpackets/SystemMessage;
   #88 = Utf8               addItemName
   #89 = Utf8               (I)Lext/mods/gameserver/network/serverpackets/SystemMessage;
   #90 = Methodref          #77.#91       // ext/mods/gameserver/network/serverpackets/SystemMessage.addNumber:(I)Lext/mods/gameserver/network/serverpackets/SystemMessage;
   #91 = NameAndType        #92:#89       // addNumber:(I)Lext/mods/gameserver/network/serverpackets/SystemMessage;
   #92 = Utf8               addNumber
   #93 = Fieldref           #12.#94       // ext/mods/gameserver/network/SystemMessageId.S1_HARVESTED_S2S:Lext/mods/gameserver/network/SystemMessageId;
   #94 = NameAndType        #95:#16       // S1_HARVESTED_S2S:Lext/mods/gameserver/network/SystemMessageId;
   #95 = Utf8               S1_HARVESTED_S2S
   #96 = Methodref          #7.#97        // ext/mods/gameserver/model/actor/Player.getParty:()Lext/mods/gameserver/model/group/Party;
   #97 = NameAndType        #98:#99       // getParty:()Lext/mods/gameserver/model/group/Party;
   #98 = Utf8               getParty
   #99 = Utf8               ()Lext/mods/gameserver/model/group/Party;
  #100 = Methodref          #101.#102     // ext/mods/gameserver/model/group/Party.broadcastToPartyMembers:(Lext/mods/gameserver/model/actor/Player;Lext/mods/gameserver/network/serverpackets/L2GameServerPacket;)V
  #101 = Class              #103          // ext/mods/gameserver/model/group/Party
  #102 = NameAndType        #104:#105     // broadcastToPartyMembers:(Lext/mods/gameserver/model/actor/Player;Lext/mods/gameserver/network/serverpackets/L2GameServerPacket;)V
  #103 = Utf8               ext/mods/gameserver/model/group/Party
  #104 = Utf8               broadcastToPartyMembers
  #105 = Utf8               (Lext/mods/gameserver/model/actor/Player;Lext/mods/gameserver/network/serverpackets/L2GameServerPacket;)V
  #106 = Methodref          #7.#107       // ext/mods/gameserver/model/actor/Player.getStatus:()Lext/mods/gameserver/model/actor/status/PlayerStatus;
  #107 = NameAndType        #108:#109     // getStatus:()Lext/mods/gameserver/model/actor/status/PlayerStatus;
  #108 = Utf8               getStatus
  #109 = Utf8               ()Lext/mods/gameserver/model/actor/status/PlayerStatus;
  #110 = Methodref          #111.#112     // ext/mods/gameserver/model/actor/status/PlayerStatus.getLevel:()I
  #111 = Class              #113          // ext/mods/gameserver/model/actor/status/PlayerStatus
  #112 = NameAndType        #114:#62      // getLevel:()I
  #113 = Utf8               ext/mods/gameserver/model/actor/status/PlayerStatus
  #114 = Utf8               getLevel
  #115 = Methodref          #116.#117     // ext/mods/gameserver/model/actor/Creature.getStatus:()Lext/mods/gameserver/model/actor/status/CreatureStatus;
  #116 = Class              #118          // ext/mods/gameserver/model/actor/Creature
  #117 = NameAndType        #108:#119     // getStatus:()Lext/mods/gameserver/model/actor/status/CreatureStatus;
  #118 = Utf8               ext/mods/gameserver/model/actor/Creature
  #119 = Utf8               ()Lext/mods/gameserver/model/actor/status/CreatureStatus;
  #120 = Methodref          #121.#112     // ext/mods/gameserver/model/actor/status/CreatureStatus.getLevel:()I
  #121 = Class              #122          // ext/mods/gameserver/model/actor/status/CreatureStatus
  #122 = Utf8               ext/mods/gameserver/model/actor/status/CreatureStatus
  #123 = Methodref          #124.#125     // java/lang/Math.abs:(I)I
  #124 = Class              #126          // java/lang/Math
  #125 = NameAndType        #127:#128     // abs:(I)I
  #126 = Utf8               java/lang/Math
  #127 = Utf8               abs
  #128 = Utf8               (I)I
  #129 = Methodref          #130.#131     // ext/mods/commons/random/Rnd.get:(I)I
  #130 = Class              #132          // ext/mods/commons/random/Rnd
  #131 = NameAndType        #133:#128     // get:(I)I
  #132 = Utf8               ext/mods/commons/random/Rnd
  #133 = Utf8               get
  #134 = Methodref          #124.#135     // java/lang/Math.max:(II)I
  #135 = NameAndType        #136:#137     // max:(II)I
  #136 = Utf8               max
  #137 = Utf8               (II)I
  #138 = Fieldref           #48.#139      // ext/mods/gameserver/handler/skillhandlers/Harvest.SKILL_IDS:[Lext/mods/gameserver/enums/skills/SkillType;
  #139 = NameAndType        #140:#141     // SKILL_IDS:[Lext/mods/gameserver/enums/skills/SkillType;
  #140 = Utf8               SKILL_IDS
  #141 = Utf8               [Lext/mods/gameserver/enums/skills/SkillType;
  #142 = Class              #143          // ext/mods/gameserver/enums/skills/SkillType
  #143 = Utf8               ext/mods/gameserver/enums/skills/SkillType
  #144 = Fieldref           #142.#145     // ext/mods/gameserver/enums/skills/SkillType.HARVEST:Lext/mods/gameserver/enums/skills/SkillType;
  #145 = NameAndType        #146:#147     // HARVEST:Lext/mods/gameserver/enums/skills/SkillType;
  #146 = Utf8               HARVEST
  #147 = Utf8               Lext/mods/gameserver/enums/skills/SkillType;
  #148 = Class              #149          // ext/mods/gameserver/handler/ISkillHandler
  #149 = Utf8               ext/mods/gameserver/handler/ISkillHandler
  #150 = Utf8               Code
  #151 = Utf8               LineNumberTable
  #152 = Utf8               LocalVariableTable
  #153 = Utf8               this
  #154 = Utf8               Lext/mods/gameserver/handler/skillhandlers/Harvest;
  #155 = Utf8               useSkill
  #156 = Utf8               (Lext/mods/gameserver/model/actor/Creature;Lext/mods/gameserver/skills/L2Skill;[Lext/mods/gameserver/model/WorldObject;Lext/mods/gameserver/model/item/instance/ItemInstance;)V
  #157 = Utf8               player
  #158 = Utf8               Lext/mods/gameserver/model/actor/Player;
  #159 = Utf8               targetMonster
  #160 = Utf8               Lext/mods/gameserver/model/actor/instance/Monster;
  #161 = Utf8               sm
  #162 = Utf8               Lext/mods/gameserver/network/serverpackets/SystemMessage;
  #163 = Utf8               creature
  #164 = Utf8               Lext/mods/gameserver/model/actor/Creature;
  #165 = Utf8               skill
  #166 = Utf8               Lext/mods/gameserver/skills/L2Skill;
  #167 = Utf8               targets
  #168 = Utf8               [Lext/mods/gameserver/model/WorldObject;
  #169 = Utf8               item
  #170 = Utf8               Lext/mods/gameserver/model/item/instance/ItemInstance;
  #171 = Utf8               seedState
  #172 = Utf8               Lext/mods/gameserver/model/actor/container/monster/SeedState;
  #173 = Utf8               crop
  #174 = Utf8               Lext/mods/gameserver/model/holder/IntIntHolder;
  #175 = Utf8               StackMapTable
  #176 = Utf8               target
  #177 = Utf8               rate
  #178 = Utf8               I
  #179 = Utf8               diff
  #180 = Utf8               getSkillIds
  #181 = Utf8               ()[Lext/mods/gameserver/enums/skills/SkillType;
  #182 = Utf8               <clinit>
  #183 = Utf8               SourceFile
  #184 = Utf8               Harvest.java
{
  public ext.mods.gameserver.handler.skillhandlers.Harvest();
    descriptor: ()V
    flags: (0x0001) ACC_PUBLIC
    Code:
      stack=1, locals=1, args_size=1
         0: aload_0
         1: invokespecial #1                  // Method java/lang/Object."<init>":()V
         4: return
      LineNumberTable:
        line 35: 0
      LocalVariableTable:
        Start  Length  Slot  Name   Signature
            0       5     0  this   Lext/mods/gameserver/handler/skillhandlers/Harvest;

  public void useSkill(ext.mods.gameserver.model.actor.Creature, ext.mods.gameserver.skills.L2Skill, ext.mods.gameserver.model.WorldObject[], ext.mods.gameserver.model.item.instance.ItemInstance);
    descriptor: (Lext/mods/gameserver/model/actor/Creature;Lext/mods/gameserver/skills/L2Skill;[Lext/mods/gameserver/model/WorldObject;Lext/mods/gameserver/model/item/instance/ItemInstance;)V
    flags: (0x0001) ACC_PUBLIC
    Code:
      stack=4, locals=10, args_size=5
         0: aload_1
         1: instanceof    #7                  // class ext/mods/gameserver/model/actor/Player
         4: ifeq          16
         7: aload_1
         8: checkcast     #7                  // class ext/mods/gameserver/model/actor/Player
        11: astore        5
        13: goto          17
        16: return
        17: aload_3
        18: iconst_0
        19: aaload
        20: astore        7
        22: aload         7
        24: instanceof    #9                  // class ext/mods/gameserver/model/actor/instance/Monster
        27: ifeq          40
        30: aload         7
        32: checkcast     #9                  // class ext/mods/gameserver/model/actor/instance/Monster
        35: astore        6
        37: goto          49
        40: aload         5
        42: getstatic     #11                 // Field ext/mods/gameserver/network/SystemMessageId.THE_HARVEST_FAILED_BECAUSE_THE_SEED_WAS_NOT_SOWN:Lext/mods/gameserver/network/SystemMessageId;
        45: invokevirtual #17                 // Method ext/mods/gameserver/model/actor/Player.sendPacket:(Lext/mods/gameserver/network/SystemMessageId;)V
        48: return
        49: aload         6
        51: invokevirtual #21                 // Method ext/mods/gameserver/model/actor/instance/Monster.getSeedState:()Lext/mods/gameserver/model/actor/container/monster/SeedState;
        54: astore        7
        56: aload         7
        58: invokevirtual #25                 // Method ext/mods/gameserver/model/actor/container/monster/SeedState.isSeeded:()Z
        61: ifne          73
        64: aload         5
        66: getstatic     #11                 // Field ext/mods/gameserver/network/SystemMessageId.THE_HARVEST_FAILED_BECAUSE_THE_SEED_WAS_NOT_SOWN:Lext/mods/gameserver/network/SystemMessageId;
        69: invokevirtual #17                 // Method ext/mods/gameserver/model/actor/Player.sendPacket:(Lext/mods/gameserver/network/SystemMessageId;)V
        72: return
        73: aload         7
        75: invokevirtual #31                 // Method ext/mods/gameserver/model/actor/container/monster/SeedState.isHarvested:()Z
        78: ifeq          90
        81: aload         5
        83: getstatic     #34                 // Field ext/mods/gameserver/network/SystemMessageId.THE_HARVEST_HAS_FAILED:Lext/mods/gameserver/network/SystemMessageId;
        86: invokevirtual #17                 // Method ext/mods/gameserver/model/actor/Player.sendPacket:(Lext/mods/gameserver/network/SystemMessageId;)V
        89: return
        90: aload         7
        92: aload         5
        94: invokevirtual #37                 // Method ext/mods/gameserver/model/actor/container/monster/SeedState.isAllowedToHarvest:(Lext/mods/gameserver/model/actor/Player;)Z
        97: ifne          109
       100: aload         5
       102: getstatic     #41                 // Field ext/mods/gameserver/network/SystemMessageId.YOU_ARE_NOT_AUTHORIZED_TO_HARVEST:Lext/mods/gameserver/network/SystemMessageId;
       105: invokevirtual #17                 // Method ext/mods/gameserver/model/actor/Player.sendPacket:(Lext/mods/gameserver/network/SystemMessageId;)V
       108: return
       109: aload         7
       111: invokevirtual #44                 // Method ext/mods/gameserver/model/actor/container/monster/SeedState.setHarvested:()V
       114: aload         5
       116: aload         6
       118: invokestatic  #47                 // Method calcSuccess:(Lext/mods/gameserver/model/actor/Player;Lext/mods/gameserver/model/actor/Creature;)Z
       121: ifne          133
       124: aload         5
       126: getstatic     #34                 // Field ext/mods/gameserver/network/SystemMessageId.THE_HARVEST_HAS_FAILED:Lext/mods/gameserver/network/SystemMessageId;
       129: invokevirtual #17                 // Method ext/mods/gameserver/model/actor/Player.sendPacket:(Lext/mods/gameserver/network/SystemMessageId;)V
       132: return
       133: aload         7
       135: invokevirtual #53                 // Method ext/mods/gameserver/model/actor/container/monster/SeedState.getHarvestedCrop:()Lext/mods/gameserver/model/holder/IntIntHolder;
       138: astore        8
       140: aload         5
       142: aload         8
       144: invokevirtual #57                 // Method ext/mods/gameserver/model/holder/IntIntHolder.getId:()I
       147: aload         8
       149: invokevirtual #63                 // Method ext/mods/gameserver/model/holder/IntIntHolder.getValue:()I
       152: iconst_1
       153: invokevirtual #66                 // Method ext/mods/gameserver/model/actor/Player.addEarnedItem:(IIZ)Lext/mods/gameserver/model/item/instance/ItemInstance;
       156: pop
       157: aload         5
       159: invokevirtual #70                 // Method ext/mods/gameserver/model/actor/Player.isInParty:()Z
       162: ifeq          239
       165: aload         8
       167: invokevirtual #63                 // Method ext/mods/gameserver/model/holder/IntIntHolder.getValue:()I
       170: iconst_1
       171: if_icmple     206
       174: getstatic     #73                 // Field ext/mods/gameserver/network/SystemMessageId.S1_HARVESTED_S3_S2S:Lext/mods/gameserver/network/SystemMessageId;
       177: invokestatic  #76                 // Method ext/mods/gameserver/network/serverpackets/SystemMessage.getSystemMessage:(Lext/mods/gameserver/network/SystemMessageId;)Lext/mods/gameserver/network/serverpackets/SystemMessage;
       180: aload         5
       182: invokevirtual #82                 // Method ext/mods/gameserver/network/serverpackets/SystemMessage.addCharName:(Lext/mods/gameserver/model/actor/Creature;)Lext/mods/gameserver/network/serverpackets/SystemMessage;
       185: aload         8
       187: invokevirtual #57                 // Method ext/mods/gameserver/model/holder/IntIntHolder.getId:()I
       190: invokevirtual #86                 // Method ext/mods/gameserver/network/serverpackets/SystemMessage.addItemName:(I)Lext/mods/gameserver/network/serverpackets/SystemMessage;
       193: aload         8
       195: invokevirtual #63                 // Method ext/mods/gameserver/model/holder/IntIntHolder.getValue:()I
       198: invokevirtual #90                 // Method ext/mods/gameserver/network/serverpackets/SystemMessage.addNumber:(I)Lext/mods/gameserver/network/serverpackets/SystemMessage;
       201: astore        9
       203: goto          227
       206: getstatic     #93                 // Field ext/mods/gameserver/network/SystemMessageId.S1_HARVESTED_S2S:Lext/mods/gameserver/network/SystemMessageId;
       209: invokestatic  #76                 // Method ext/mods/gameserver/network/serverpackets/SystemMessage.getSystemMessage:(Lext/mods/gameserver/network/SystemMessageId;)Lext/mods/gameserver/network/serverpackets/SystemMessage;
       212: aload         5
       214: invokevirtual #82                 // Method ext/mods/gameserver/network/serverpackets/SystemMessage.addCharName:(Lext/mods/gameserver/model/actor/Creature;)Lext/mods/gameserver/network/serverpackets/SystemMessage;
       217: aload         8
       219: invokevirtual #57                 // Method ext/mods/gameserver/model/holder/IntIntHolder.getId:()I
       222: invokevirtual #86                 // Method ext/mods/gameserver/network/serverpackets/SystemMessage.addItemName:(I)Lext/mods/gameserver/network/serverpackets/SystemMessage;
       225: astore        9
       227: aload         5
       229: invokevirtual #96                 // Method ext/mods/gameserver/model/actor/Player.getParty:()Lext/mods/gameserver/model/group/Party;
       232: aload         5
       234: aload         9
       236: invokevirtual #100                // Method ext/mods/gameserver/model/group/Party.broadcastToPartyMembers:(Lext/mods/gameserver/model/actor/Player;Lext/mods/gameserver/network/serverpackets/L2GameServerPacket;)V
       239: return
      LineNumberTable:
        line 45: 0
        line 46: 16
        line 48: 17
        line 50: 40
        line 51: 48
        line 54: 49
        line 55: 56
        line 57: 64
        line 58: 72
        line 61: 73
        line 63: 81
        line 64: 89
        line 67: 90
        line 69: 100
        line 70: 108
        line 73: 109
        line 75: 114
        line 77: 124
        line 78: 132
        line 81: 133
        line 82: 140
        line 84: 157
        line 87: 165
        line 88: 174
        line 90: 206
        line 92: 227
        line 94: 239
      LocalVariableTable:
        Start  Length  Slot  Name   Signature
           13       3     5 player   Lext/mods/gameserver/model/actor/Player;
           37       3     6 targetMonster   Lext/mods/gameserver/model/actor/instance/Monster;
          203       3     9    sm   Lext/mods/gameserver/network/serverpackets/SystemMessage;
          227      12     9    sm   Lext/mods/gameserver/network/serverpackets/SystemMessage;
            0     240     0  this   Lext/mods/gameserver/handler/skillhandlers/Harvest;
            0     240     1 creature   Lext/mods/gameserver/model/actor/Creature;
            0     240     2 skill   Lext/mods/gameserver/skills/L2Skill;
            0     240     3 targets   [Lext/mods/gameserver/model/WorldObject;
            0     240     4  item   Lext/mods/gameserver/model/item/instance/ItemInstance;
           17     223     5 player   Lext/mods/gameserver/model/actor/Player;
           49     191     6 targetMonster   Lext/mods/gameserver/model/actor/instance/Monster;
           56     184     7 seedState   Lext/mods/gameserver/model/actor/container/monster/SeedState;
          140     100     8  crop   Lext/mods/gameserver/model/holder/IntIntHolder;
      StackMapTable: number_of_entries = 11
        frame_type = 16 /* same */
        frame_type = 252 /* append */
          offset_delta = 0
          locals = [ class ext/mods/gameserver/model/actor/Player ]
        frame_type = 22 /* same */
        frame_type = 252 /* append */
          offset_delta = 8
          locals = [ class ext/mods/gameserver/model/actor/instance/Monster ]
        frame_type = 252 /* append */
          offset_delta = 23
          locals = [ class ext/mods/gameserver/model/actor/container/monster/SeedState ]
        frame_type = 16 /* same */
        frame_type = 18 /* same */
        frame_type = 23 /* same */
        frame_type = 252 /* append */
          offset_delta = 72
          locals = [ class ext/mods/gameserver/model/holder/IntIntHolder ]
        frame_type = 252 /* append */
          offset_delta = 20
          locals = [ class ext/mods/gameserver/network/serverpackets/SystemMessage ]
        frame_type = 250 /* chop */
          offset_delta = 11

  public ext.mods.gameserver.enums.skills.SkillType[] getSkillIds();
    descriptor: ()[Lext/mods/gameserver/enums/skills/SkillType;
    flags: (0x0001) ACC_PUBLIC
    Code:
      stack=1, locals=1, args_size=1
         0: getstatic     #138                // Field SKILL_IDS:[Lext/mods/gameserver/enums/skills/SkillType;
         3: areturn
      LineNumberTable:
        line 110: 0
      LocalVariableTable:
        Start  Length  Slot  Name   Signature
            0       4     0  this   Lext/mods/gameserver/handler/skillhandlers/Harvest;

  static {};
    descriptor: ()V
    flags: (0x0008) ACC_STATIC
    Code:
      stack=4, locals=0, args_size=0
         0: iconst_1
         1: anewarray     #142                // class ext/mods/gameserver/enums/skills/SkillType
         4: dup
         5: iconst_0
         6: getstatic     #144                // Field ext/mods/gameserver/enums/skills/SkillType.HARVEST:Lext/mods/gameserver/enums/skills/SkillType;
         9: aastore
        10: putstatic     #138                // Field SKILL_IDS:[Lext/mods/gameserver/enums/skills/SkillType;
        13: return
      LineNumberTable:
        line 37: 0
}
SourceFile: "Harvest.java"
