// Bytecode for: ext.mods.gameserver.handler.skillhandlers.Sow
// File: ext\mods\gameserver\handler\skillhandlers\Sow.class

Classfile /c:/Users/User/Desktop/BrProject/bin/main/ext/mods/gameserver/handler/skillhandlers/Sow.class
  Last modified 9 de jul de 2026; size 2932 bytes
  MD5 checksum 9fc228905a9a27ba3a38152e87a140b8
  Compiled from "Sow.java"
public class ext.mods.gameserver.handler.skillhandlers.Sow implements ext.mods.gameserver.handler.ISkillHandler
  minor version: 0
  major version: 69
  flags: (0x0021) ACC_PUBLIC, ACC_SUPER
  this_class: #67                         // ext/mods/gameserver/handler/skillhandlers/Sow
  super_class: #2                         // java/lang/Object
  interfaces: 1, fields: 1, methods: 4, attributes: 1
Constant pool:
    #1 = Methodref          #2.#3         // java/lang/Object."<init>":()V
    #2 = Class              #4            // java/lang/Object
    #3 = NameAndType        #5:#6         // "<init>":()V
    #4 = Utf8               java/lang/Object
    #5 = Utf8               <init>
    #6 = Utf8               ()V
    #7 = Class              #8            // ext/mods/gameserver/model/actor/Player
    #8 = Utf8               ext/mods/gameserver/model/actor/Player
    #9 = Class              #10           // ext/mods/gameserver/model/actor/instance/Monster
   #10 = Utf8               ext/mods/gameserver/model/actor/instance/Monster
   #11 = Methodref          #9.#12        // ext/mods/gameserver/model/actor/instance/Monster.isDead:()Z
   #12 = NameAndType        #13:#14       // isDead:()Z
   #13 = Utf8               isDead
   #14 = Utf8               ()Z
   #15 = Methodref          #9.#16        // ext/mods/gameserver/model/actor/instance/Monster.getSeedState:()Lext/mods/gameserver/model/actor/container/monster/SeedState;
   #16 = NameAndType        #17:#18       // getSeedState:()Lext/mods/gameserver/model/actor/container/monster/SeedState;
   #17 = Utf8               getSeedState
   #18 = Utf8               ()Lext/mods/gameserver/model/actor/container/monster/SeedState;
   #19 = Methodref          #20.#21       // ext/mods/gameserver/model/actor/container/monster/SeedState.isSeeded:()Z
   #20 = Class              #22           // ext/mods/gameserver/model/actor/container/monster/SeedState
   #21 = NameAndType        #23:#14       // isSeeded:()Z
   #22 = Utf8               ext/mods/gameserver/model/actor/container/monster/SeedState
   #23 = Utf8               isSeeded
   #24 = Fieldref           #25.#26       // ext/mods/gameserver/network/SystemMessageId.THE_SEED_HAS_BEEN_SOWN:Lext/mods/gameserver/network/SystemMessageId;
   #25 = Class              #27           // ext/mods/gameserver/network/SystemMessageId
   #26 = NameAndType        #28:#29       // THE_SEED_HAS_BEEN_SOWN:Lext/mods/gameserver/network/SystemMessageId;
   #27 = Utf8               ext/mods/gameserver/network/SystemMessageId
   #28 = Utf8               THE_SEED_HAS_BEEN_SOWN
   #29 = Utf8               Lext/mods/gameserver/network/SystemMessageId;
   #30 = Methodref          #7.#31        // ext/mods/gameserver/model/actor/Player.sendPacket:(Lext/mods/gameserver/network/SystemMessageId;)V
   #31 = NameAndType        #32:#33       // sendPacket:(Lext/mods/gameserver/network/SystemMessageId;)V
   #32 = Utf8               sendPacket
   #33 = Utf8               (Lext/mods/gameserver/network/SystemMessageId;)V
   #34 = Methodref          #35.#36       // ext/mods/gameserver/data/manager/CastleManorManager.getInstance:()Lext/mods/gameserver/data/manager/CastleManorManager;
   #35 = Class              #37           // ext/mods/gameserver/data/manager/CastleManorManager
   #36 = NameAndType        #38:#39       // getInstance:()Lext/mods/gameserver/data/manager/CastleManorManager;
   #37 = Utf8               ext/mods/gameserver/data/manager/CastleManorManager
   #38 = Utf8               getInstance
   #39 = Utf8               ()Lext/mods/gameserver/data/manager/CastleManorManager;
   #40 = Methodref          #41.#42       // ext/mods/gameserver/model/item/instance/ItemInstance.getItemId:()I
   #41 = Class              #43           // ext/mods/gameserver/model/item/instance/ItemInstance
   #42 = NameAndType        #44:#45       // getItemId:()I
   #43 = Utf8               ext/mods/gameserver/model/item/instance/ItemInstance
   #44 = Utf8               getItemId
   #45 = Utf8               ()I
   #46 = Methodref          #35.#47       // ext/mods/gameserver/data/manager/CastleManorManager.getSeed:(I)Lext/mods/gameserver/model/manor/Seed;
   #47 = NameAndType        #48:#49       // getSeed:(I)Lext/mods/gameserver/model/manor/Seed;
   #48 = Utf8               getSeed
   #49 = Utf8               (I)Lext/mods/gameserver/model/manor/Seed;
   #50 = Methodref          #51.#52       // ext/mods/gameserver/skills/Formulas.calcSowSuccess:(Lext/mods/gameserver/model/actor/Player;Lext/mods/gameserver/model/actor/Creature;Lext/mods/gameserver/model/manor/Seed;)Z
   #51 = Class              #53           // ext/mods/gameserver/skills/Formulas
   #52 = NameAndType        #54:#55       // calcSowSuccess:(Lext/mods/gameserver/model/actor/Player;Lext/mods/gameserver/model/actor/Creature;Lext/mods/gameserver/model/manor/Seed;)Z
   #53 = Utf8               ext/mods/gameserver/skills/Formulas
   #54 = Utf8               calcSowSuccess
   #55 = Utf8               (Lext/mods/gameserver/model/actor/Player;Lext/mods/gameserver/model/actor/Creature;Lext/mods/gameserver/model/manor/Seed;)Z
   #56 = Fieldref           #25.#57       // ext/mods/gameserver/network/SystemMessageId.THE_SEED_WAS_NOT_SOWN:Lext/mods/gameserver/network/SystemMessageId;
   #57 = NameAndType        #58:#29       // THE_SEED_WAS_NOT_SOWN:Lext/mods/gameserver/network/SystemMessageId;
   #58 = Utf8               THE_SEED_WAS_NOT_SOWN
   #59 = Methodref          #20.#60       // ext/mods/gameserver/model/actor/container/monster/SeedState.setSeeded:(Lext/mods/gameserver/model/actor/Player;Lext/mods/gameserver/model/manor/Seed;)V
   #60 = NameAndType        #61:#62       // setSeeded:(Lext/mods/gameserver/model/actor/Player;Lext/mods/gameserver/model/manor/Seed;)V
   #61 = Utf8               setSeeded
   #62 = Utf8               (Lext/mods/gameserver/model/actor/Player;Lext/mods/gameserver/model/manor/Seed;)V
   #63 = Fieldref           #25.#64       // ext/mods/gameserver/network/SystemMessageId.THE_SEED_WAS_SUCCESSFULLY_SOWN:Lext/mods/gameserver/network/SystemMessageId;
   #64 = NameAndType        #65:#29       // THE_SEED_WAS_SUCCESSFULLY_SOWN:Lext/mods/gameserver/network/SystemMessageId;
   #65 = Utf8               THE_SEED_WAS_SUCCESSFULLY_SOWN
   #66 = Fieldref           #67.#68       // ext/mods/gameserver/handler/skillhandlers/Sow.SKILL_IDS:[Lext/mods/gameserver/enums/skills/SkillType;
   #67 = Class              #69           // ext/mods/gameserver/handler/skillhandlers/Sow
   #68 = NameAndType        #70:#71       // SKILL_IDS:[Lext/mods/gameserver/enums/skills/SkillType;
   #69 = Utf8               ext/mods/gameserver/handler/skillhandlers/Sow
   #70 = Utf8               SKILL_IDS
   #71 = Utf8               [Lext/mods/gameserver/enums/skills/SkillType;
   #72 = Class              #73           // ext/mods/gameserver/enums/skills/SkillType
   #73 = Utf8               ext/mods/gameserver/enums/skills/SkillType
   #74 = Fieldref           #72.#75       // ext/mods/gameserver/enums/skills/SkillType.SOW:Lext/mods/gameserver/enums/skills/SkillType;
   #75 = NameAndType        #76:#77       // SOW:Lext/mods/gameserver/enums/skills/SkillType;
   #76 = Utf8               SOW
   #77 = Utf8               Lext/mods/gameserver/enums/skills/SkillType;
   #78 = Class              #79           // ext/mods/gameserver/handler/ISkillHandler
   #79 = Utf8               ext/mods/gameserver/handler/ISkillHandler
   #80 = Utf8               Code
   #81 = Utf8               LineNumberTable
   #82 = Utf8               LocalVariableTable
   #83 = Utf8               this
   #84 = Utf8               Lext/mods/gameserver/handler/skillhandlers/Sow;
   #85 = Utf8               useSkill
   #86 = Utf8               (Lext/mods/gameserver/model/actor/Creature;Lext/mods/gameserver/skills/L2Skill;[Lext/mods/gameserver/model/WorldObject;Lext/mods/gameserver/model/item/instance/ItemInstance;)V
   #87 = Utf8               player
   #88 = Utf8               Lext/mods/gameserver/model/actor/Player;
   #89 = Utf8               targetMonster
   #90 = Utf8               Lext/mods/gameserver/model/actor/instance/Monster;
   #91 = Utf8               creature
   #92 = Utf8               Lext/mods/gameserver/model/actor/Creature;
   #93 = Utf8               skill
   #94 = Utf8               Lext/mods/gameserver/skills/L2Skill;
   #95 = Utf8               targets
   #96 = Utf8               [Lext/mods/gameserver/model/WorldObject;
   #97 = Utf8               item
   #98 = Utf8               Lext/mods/gameserver/model/item/instance/ItemInstance;
   #99 = Utf8               seed
  #100 = Utf8               Lext/mods/gameserver/model/manor/Seed;
  #101 = Utf8               StackMapTable
  #102 = Class              #103          // ext/mods/gameserver/model/manor/Seed
  #103 = Utf8               ext/mods/gameserver/model/manor/Seed
  #104 = Utf8               getSkillIds
  #105 = Utf8               ()[Lext/mods/gameserver/enums/skills/SkillType;
  #106 = Utf8               <clinit>
  #107 = Utf8               SourceFile
  #108 = Utf8               Sow.java
{
  public ext.mods.gameserver.handler.skillhandlers.Sow();
    descriptor: ()V
    flags: (0x0001) ACC_PUBLIC
    Code:
      stack=1, locals=1, args_size=1
         0: aload_0
         1: invokespecial #1                  // Method java/lang/Object."<init>":()V
         4: return
      LineNumberTable:
        line 33: 0
      LocalVariableTable:
        Start  Length  Slot  Name   Signature
            0       5     0  this   Lext/mods/gameserver/handler/skillhandlers/Sow;

  public void useSkill(ext.mods.gameserver.model.actor.Creature, ext.mods.gameserver.skills.L2Skill, ext.mods.gameserver.model.WorldObject[], ext.mods.gameserver.model.item.instance.ItemInstance);
    descriptor: (Lext/mods/gameserver/model/actor/Creature;Lext/mods/gameserver/skills/L2Skill;[Lext/mods/gameserver/model/WorldObject;Lext/mods/gameserver/model/item/instance/ItemInstance;)V
    flags: (0x0001) ACC_PUBLIC
    Code:
      stack=3, locals=8, args_size=5
         0: aload         4
         2: ifnull        21
         5: aload_1
         6: instanceof    #7                  // class ext/mods/gameserver/model/actor/Player
         9: ifeq          21
        12: aload_1
        13: checkcast     #7                  // class ext/mods/gameserver/model/actor/Player
        16: astore        5
        18: goto          22
        21: return
        22: aload_3
        23: iconst_0
        24: aaload
        25: astore        7
        27: aload         7
        29: instanceof    #9                  // class ext/mods/gameserver/model/actor/instance/Monster
        32: ifeq          45
        35: aload         7
        37: checkcast     #9                  // class ext/mods/gameserver/model/actor/instance/Monster
        40: astore        6
        42: goto          46
        45: return
        46: aload         6
        48: invokevirtual #11                 // Method ext/mods/gameserver/model/actor/instance/Monster.isDead:()Z
        51: ifeq          55
        54: return
        55: aload         6
        57: invokevirtual #15                 // Method ext/mods/gameserver/model/actor/instance/Monster.getSeedState:()Lext/mods/gameserver/model/actor/container/monster/SeedState;
        60: invokevirtual #19                 // Method ext/mods/gameserver/model/actor/container/monster/SeedState.isSeeded:()Z
        63: ifeq          75
        66: aload         5
        68: getstatic     #24                 // Field ext/mods/gameserver/network/SystemMessageId.THE_SEED_HAS_BEEN_SOWN:Lext/mods/gameserver/network/SystemMessageId;
        71: invokevirtual #30                 // Method ext/mods/gameserver/model/actor/Player.sendPacket:(Lext/mods/gameserver/network/SystemMessageId;)V
        74: return
        75: invokestatic  #34                 // Method ext/mods/gameserver/data/manager/CastleManorManager.getInstance:()Lext/mods/gameserver/data/manager/CastleManorManager;
        78: aload         4
        80: invokevirtual #40                 // Method ext/mods/gameserver/model/item/instance/ItemInstance.getItemId:()I
        83: invokevirtual #46                 // Method ext/mods/gameserver/data/manager/CastleManorManager.getSeed:(I)Lext/mods/gameserver/model/manor/Seed;
        86: astore        7
        88: aload         7
        90: ifnonnull     94
        93: return
        94: aload         5
        96: aload         6
        98: aload         7
       100: invokestatic  #50                 // Method ext/mods/gameserver/skills/Formulas.calcSowSuccess:(Lext/mods/gameserver/model/actor/Player;Lext/mods/gameserver/model/actor/Creature;Lext/mods/gameserver/model/manor/Seed;)Z
       103: ifne          115
       106: aload         5
       108: getstatic     #56                 // Field ext/mods/gameserver/network/SystemMessageId.THE_SEED_WAS_NOT_SOWN:Lext/mods/gameserver/network/SystemMessageId;
       111: invokevirtual #30                 // Method ext/mods/gameserver/model/actor/Player.sendPacket:(Lext/mods/gameserver/network/SystemMessageId;)V
       114: return
       115: aload         6
       117: invokevirtual #15                 // Method ext/mods/gameserver/model/actor/instance/Monster.getSeedState:()Lext/mods/gameserver/model/actor/container/monster/SeedState;
       120: aload         5
       122: aload         7
       124: invokevirtual #59                 // Method ext/mods/gameserver/model/actor/container/monster/SeedState.setSeeded:(Lext/mods/gameserver/model/actor/Player;Lext/mods/gameserver/model/manor/Seed;)V
       127: aload         5
       129: getstatic     #63                 // Field ext/mods/gameserver/network/SystemMessageId.THE_SEED_WAS_SUCCESSFULLY_SOWN:Lext/mods/gameserver/network/SystemMessageId;
       132: invokevirtual #30                 // Method ext/mods/gameserver/model/actor/Player.sendPacket:(Lext/mods/gameserver/network/SystemMessageId;)V
       135: return
      LineNumberTable:
        line 43: 0
        line 44: 21
        line 46: 22
        line 47: 45
        line 49: 46
        line 50: 54
        line 52: 55
        line 54: 66
        line 55: 74
        line 58: 75
        line 59: 88
        line 60: 93
        line 62: 94
        line 64: 106
        line 65: 114
        line 68: 115
        line 70: 127
        line 71: 135
      LocalVariableTable:
        Start  Length  Slot  Name   Signature
           18       3     5 player   Lext/mods/gameserver/model/actor/Player;
           42       3     6 targetMonster   Lext/mods/gameserver/model/actor/instance/Monster;
            0     136     0  this   Lext/mods/gameserver/handler/skillhandlers/Sow;
            0     136     1 creature   Lext/mods/gameserver/model/actor/Creature;
            0     136     2 skill   Lext/mods/gameserver/skills/L2Skill;
            0     136     3 targets   [Lext/mods/gameserver/model/WorldObject;
            0     136     4  item   Lext/mods/gameserver/model/item/instance/ItemInstance;
           22     114     5 player   Lext/mods/gameserver/model/actor/Player;
           46      90     6 targetMonster   Lext/mods/gameserver/model/actor/instance/Monster;
           88      48     7  seed   Lext/mods/gameserver/model/manor/Seed;
      StackMapTable: number_of_entries = 8
        frame_type = 21 /* same */
        frame_type = 252 /* append */
          offset_delta = 0
          locals = [ class ext/mods/gameserver/model/actor/Player ]
        frame_type = 22 /* same */
        frame_type = 252 /* append */
          offset_delta = 0
          locals = [ class ext/mods/gameserver/model/actor/instance/Monster ]
        frame_type = 8 /* same */
        frame_type = 19 /* same */
        frame_type = 252 /* append */
          offset_delta = 18
          locals = [ class ext/mods/gameserver/model/manor/Seed ]
        frame_type = 20 /* same */

  public ext.mods.gameserver.enums.skills.SkillType[] getSkillIds();
    descriptor: ()[Lext/mods/gameserver/enums/skills/SkillType;
    flags: (0x0001) ACC_PUBLIC
    Code:
      stack=1, locals=1, args_size=1
         0: getstatic     #66                 // Field SKILL_IDS:[Lext/mods/gameserver/enums/skills/SkillType;
         3: areturn
      LineNumberTable:
        line 76: 0
      LocalVariableTable:
        Start  Length  Slot  Name   Signature
            0       4     0  this   Lext/mods/gameserver/handler/skillhandlers/Sow;

  static {};
    descriptor: ()V
    flags: (0x0008) ACC_STATIC
    Code:
      stack=4, locals=0, args_size=0
         0: iconst_1
         1: anewarray     #72                 // class ext/mods/gameserver/enums/skills/SkillType
         4: dup
         5: iconst_0
         6: getstatic     #74                 // Field ext/mods/gameserver/enums/skills/SkillType.SOW:Lext/mods/gameserver/enums/skills/SkillType;
         9: aastore
        10: putstatic     #66                 // Field SKILL_IDS:[Lext/mods/gameserver/enums/skills/SkillType;
        13: return
      LineNumberTable:
        line 35: 0
}
SourceFile: "Sow.java"
