// Bytecode for: ext.mods.gameserver.data.manager.CastleManorManager
// File: ext\mods\gameserver\data\manager\CastleManorManager.class

Classfile /c:/Users/User/Desktop/BrProject/bin/main/ext/mods/gameserver/data/manager/CastleManorManager.class
  Last modified 9 de jul de 2026; size 23707 bytes
  MD5 checksum 683a3d726eea8d7242c93a02a39a9fc1
  Compiled from "CastleManorManager.java"
public class ext.mods.gameserver.data.manager.CastleManorManager implements ext.mods.commons.data.xml.IXmlReader
  minor version: 0
  major version: 69
  flags: (0x0021) ACC_PUBLIC, ACC_SUPER
  this_class: #14                         // ext/mods/gameserver/data/manager/CastleManorManager
  super_class: #2                         // java/lang/Object
  interfaces: 1, fields: 15, methods: 35, attributes: 4
Constant pool:
    #1 = Methodref          #2.#3         // java/lang/Object."<init>":()V
    #2 = Class              #4            // java/lang/Object
    #3 = NameAndType        #5:#6         // "<init>":()V
    #4 = Utf8               java/lang/Object
    #5 = Utf8               <init>
    #6 = Utf8               ()V
    #7 = Fieldref           #8.#9         // ext/mods/gameserver/enums/ManorStatus.APPROVED:Lext/mods/gameserver/enums/ManorStatus;
    #8 = Class              #10           // ext/mods/gameserver/enums/ManorStatus
    #9 = NameAndType        #11:#12       // APPROVED:Lext/mods/gameserver/enums/ManorStatus;
   #10 = Utf8               ext/mods/gameserver/enums/ManorStatus
   #11 = Utf8               APPROVED
   #12 = Utf8               Lext/mods/gameserver/enums/ManorStatus;
   #13 = Fieldref           #14.#15       // ext/mods/gameserver/data/manager/CastleManorManager._mode:Lext/mods/gameserver/enums/ManorStatus;
   #14 = Class              #16           // ext/mods/gameserver/data/manager/CastleManorManager
   #15 = NameAndType        #17:#12       // _mode:Lext/mods/gameserver/enums/ManorStatus;
   #16 = Utf8               ext/mods/gameserver/data/manager/CastleManorManager
   #17 = Utf8               _mode
   #18 = Fieldref           #14.#19       // ext/mods/gameserver/data/manager/CastleManorManager._nextModeChange:Ljava/util/Calendar;
   #19 = NameAndType        #20:#21       // _nextModeChange:Ljava/util/Calendar;
   #20 = Utf8               _nextModeChange
   #21 = Utf8               Ljava/util/Calendar;
   #22 = Class              #23           // java/util/HashMap
   #23 = Utf8               java/util/HashMap
   #24 = Methodref          #22.#3        // java/util/HashMap."<init>":()V
   #25 = Fieldref           #14.#26       // ext/mods/gameserver/data/manager/CastleManorManager._seeds:Ljava/util/Map;
   #26 = NameAndType        #27:#28       // _seeds:Ljava/util/Map;
   #27 = Utf8               _seeds
   #28 = Utf8               Ljava/util/Map;
   #29 = Fieldref           #14.#30       // ext/mods/gameserver/data/manager/CastleManorManager._procure:Ljava/util/Map;
   #30 = NameAndType        #31:#28       // _procure:Ljava/util/Map;
   #31 = Utf8               _procure
   #32 = Fieldref           #14.#33       // ext/mods/gameserver/data/manager/CastleManorManager._procureNext:Ljava/util/Map;
   #33 = NameAndType        #34:#28       // _procureNext:Ljava/util/Map;
   #34 = Utf8               _procureNext
   #35 = Fieldref           #14.#36       // ext/mods/gameserver/data/manager/CastleManorManager._production:Ljava/util/Map;
   #36 = NameAndType        #37:#28       // _production:Ljava/util/Map;
   #37 = Utf8               _production
   #38 = Fieldref           #14.#39       // ext/mods/gameserver/data/manager/CastleManorManager._productionNext:Ljava/util/Map;
   #39 = NameAndType        #40:#28       // _productionNext:Ljava/util/Map;
   #40 = Utf8               _productionNext
   #41 = Fieldref           #42.#43       // ext/mods/Config.ALLOW_MANOR:Z
   #42 = Class              #44           // ext/mods/Config
   #43 = NameAndType        #45:#46       // ALLOW_MANOR:Z
   #44 = Utf8               ext/mods/Config
   #45 = Utf8               ALLOW_MANOR
   #46 = Utf8               Z
   #47 = Fieldref           #8.#48        // ext/mods/gameserver/enums/ManorStatus.DISABLED:Lext/mods/gameserver/enums/ManorStatus;
   #48 = NameAndType        #49:#12       // DISABLED:Lext/mods/gameserver/enums/ManorStatus;
   #49 = Utf8               DISABLED
   #50 = Fieldref           #14.#51       // ext/mods/gameserver/data/manager/CastleManorManager.LOGGER:Lext/mods/commons/logging/CLogger;
   #51 = NameAndType        #52:#53       // LOGGER:Lext/mods/commons/logging/CLogger;
   #52 = Utf8               LOGGER
   #53 = Utf8               Lext/mods/commons/logging/CLogger;
   #54 = String             #55           // Manor system is deactivated.
   #55 = Utf8               Manor system is deactivated.
   #56 = Methodref          #57.#58       // ext/mods/commons/logging/CLogger.info:(Ljava/lang/Object;)V
   #57 = Class              #59           // ext/mods/commons/logging/CLogger
   #58 = NameAndType        #60:#61       // info:(Ljava/lang/Object;)V
   #59 = Utf8               ext/mods/commons/logging/CLogger
   #60 = Utf8               info
   #61 = Utf8               (Ljava/lang/Object;)V
   #62 = Methodref          #14.#63       // ext/mods/gameserver/data/manager/CastleManorManager.load:()V
   #63 = NameAndType        #64:#6        // load:()V
   #64 = Utf8               load
   #65 = Methodref          #66.#67       // ext/mods/commons/pool/ConnectionPool.getConnection:()Ljava/sql/Connection;
   #66 = Class              #68           // ext/mods/commons/pool/ConnectionPool
   #67 = NameAndType        #69:#70       // getConnection:()Ljava/sql/Connection;
   #68 = Utf8               ext/mods/commons/pool/ConnectionPool
   #69 = Utf8               getConnection
   #70 = Utf8               ()Ljava/sql/Connection;
   #71 = String             #72           // SELECT * FROM castle_manor_production WHERE castle_id=?
   #72 = Utf8               SELECT * FROM castle_manor_production WHERE castle_id=?
   #73 = InterfaceMethodref #74.#75       // java/sql/Connection.prepareStatement:(Ljava/lang/String;)Ljava/sql/PreparedStatement;
   #74 = Class              #76           // java/sql/Connection
   #75 = NameAndType        #77:#78       // prepareStatement:(Ljava/lang/String;)Ljava/sql/PreparedStatement;
   #76 = Utf8               java/sql/Connection
   #77 = Utf8               prepareStatement
   #78 = Utf8               (Ljava/lang/String;)Ljava/sql/PreparedStatement;
   #79 = String             #80           // SELECT * FROM castle_manor_procure WHERE castle_id=?
   #80 = Utf8               SELECT * FROM castle_manor_procure WHERE castle_id=?
   #81 = Methodref          #82.#83       // ext/mods/gameserver/data/manager/CastleManager.getInstance:()Lext/mods/gameserver/data/manager/CastleManager;
   #82 = Class              #84           // ext/mods/gameserver/data/manager/CastleManager
   #83 = NameAndType        #85:#86       // getInstance:()Lext/mods/gameserver/data/manager/CastleManager;
   #84 = Utf8               ext/mods/gameserver/data/manager/CastleManager
   #85 = Utf8               getInstance
   #86 = Utf8               ()Lext/mods/gameserver/data/manager/CastleManager;
   #87 = Methodref          #82.#88       // ext/mods/gameserver/data/manager/CastleManager.getCastles:()Ljava/util/Collection;
   #88 = NameAndType        #89:#90       // getCastles:()Ljava/util/Collection;
   #89 = Utf8               getCastles
   #90 = Utf8               ()Ljava/util/Collection;
   #91 = InterfaceMethodref #92.#93       // java/util/Collection.iterator:()Ljava/util/Iterator;
   #92 = Class              #94           // java/util/Collection
   #93 = NameAndType        #95:#96       // iterator:()Ljava/util/Iterator;
   #94 = Utf8               java/util/Collection
   #95 = Utf8               iterator
   #96 = Utf8               ()Ljava/util/Iterator;
   #97 = InterfaceMethodref #98.#99       // java/util/Iterator.hasNext:()Z
   #98 = Class              #100          // java/util/Iterator
   #99 = NameAndType        #101:#102     // hasNext:()Z
  #100 = Utf8               java/util/Iterator
  #101 = Utf8               hasNext
  #102 = Utf8               ()Z
  #103 = InterfaceMethodref #98.#104      // java/util/Iterator.next:()Ljava/lang/Object;
  #104 = NameAndType        #105:#106     // next:()Ljava/lang/Object;
  #105 = Utf8               next
  #106 = Utf8               ()Ljava/lang/Object;
  #107 = Class              #108          // ext/mods/gameserver/model/residence/castle/Castle
  #108 = Utf8               ext/mods/gameserver/model/residence/castle/Castle
  #109 = Class              #110          // java/util/ArrayList
  #110 = Utf8               java/util/ArrayList
  #111 = Methodref          #109.#3       // java/util/ArrayList."<init>":()V
  #112 = InterfaceMethodref #113.#114     // java/sql/PreparedStatement.clearParameters:()V
  #113 = Class              #115          // java/sql/PreparedStatement
  #114 = NameAndType        #116:#6       // clearParameters:()V
  #115 = Utf8               java/sql/PreparedStatement
  #116 = Utf8               clearParameters
  #117 = Methodref          #107.#118     // ext/mods/gameserver/model/residence/castle/Castle.getId:()I
  #118 = NameAndType        #119:#120     // getId:()I
  #119 = Utf8               getId
  #120 = Utf8               ()I
  #121 = InterfaceMethodref #113.#122     // java/sql/PreparedStatement.setInt:(II)V
  #122 = NameAndType        #123:#124     // setInt:(II)V
  #123 = Utf8               setInt
  #124 = Utf8               (II)V
  #125 = InterfaceMethodref #113.#126     // java/sql/PreparedStatement.executeQuery:()Ljava/sql/ResultSet;
  #126 = NameAndType        #127:#128     // executeQuery:()Ljava/sql/ResultSet;
  #127 = Utf8               executeQuery
  #128 = Utf8               ()Ljava/sql/ResultSet;
  #129 = InterfaceMethodref #130.#131     // java/sql/ResultSet.next:()Z
  #130 = Class              #132          // java/sql/ResultSet
  #131 = NameAndType        #105:#102     // next:()Z
  #132 = Utf8               java/sql/ResultSet
  #133 = Class              #134          // ext/mods/gameserver/model/manor/SeedProduction
  #134 = Utf8               ext/mods/gameserver/model/manor/SeedProduction
  #135 = String             #136          // seed_id
  #136 = Utf8               seed_id
  #137 = InterfaceMethodref #130.#138     // java/sql/ResultSet.getInt:(Ljava/lang/String;)I
  #138 = NameAndType        #139:#140     // getInt:(Ljava/lang/String;)I
  #139 = Utf8               getInt
  #140 = Utf8               (Ljava/lang/String;)I
  #141 = String             #142          // amount
  #142 = Utf8               amount
  #143 = String             #144          // price
  #144 = Utf8               price
  #145 = String             #146          // start_amount
  #146 = Utf8               start_amount
  #147 = Methodref          #133.#148     // ext/mods/gameserver/model/manor/SeedProduction."<init>":(IIII)V
  #148 = NameAndType        #5:#149       // "<init>":(IIII)V
  #149 = Utf8               (IIII)V
  #150 = String             #151          // next_period
  #151 = Utf8               next_period
  #152 = InterfaceMethodref #130.#153     // java/sql/ResultSet.getBoolean:(Ljava/lang/String;)Z
  #153 = NameAndType        #154:#155     // getBoolean:(Ljava/lang/String;)Z
  #154 = Utf8               getBoolean
  #155 = Utf8               (Ljava/lang/String;)Z
  #156 = InterfaceMethodref #157.#158     // java/util/List.add:(Ljava/lang/Object;)Z
  #157 = Class              #159          // java/util/List
  #158 = NameAndType        #160:#161     // add:(Ljava/lang/Object;)Z
  #159 = Utf8               java/util/List
  #160 = Utf8               add
  #161 = Utf8               (Ljava/lang/Object;)Z
  #162 = InterfaceMethodref #130.#163     // java/sql/ResultSet.close:()V
  #163 = NameAndType        #164:#6       // close:()V
  #164 = Utf8               close
  #165 = Class              #166          // java/lang/Throwable
  #166 = Utf8               java/lang/Throwable
  #167 = Methodref          #165.#168     // java/lang/Throwable.addSuppressed:(Ljava/lang/Throwable;)V
  #168 = NameAndType        #169:#170     // addSuppressed:(Ljava/lang/Throwable;)V
  #169 = Utf8               addSuppressed
  #170 = Utf8               (Ljava/lang/Throwable;)V
  #171 = Methodref          #172.#173     // java/lang/Integer.valueOf:(I)Ljava/lang/Integer;
  #172 = Class              #174          // java/lang/Integer
  #173 = NameAndType        #175:#176     // valueOf:(I)Ljava/lang/Integer;
  #174 = Utf8               java/lang/Integer
  #175 = Utf8               valueOf
  #176 = Utf8               (I)Ljava/lang/Integer;
  #177 = InterfaceMethodref #178.#179     // java/util/Map.put:(Ljava/lang/Object;Ljava/lang/Object;)Ljava/lang/Object;
  #178 = Class              #180          // java/util/Map
  #179 = NameAndType        #181:#182     // put:(Ljava/lang/Object;Ljava/lang/Object;)Ljava/lang/Object;
  #180 = Utf8               java/util/Map
  #181 = Utf8               put
  #182 = Utf8               (Ljava/lang/Object;Ljava/lang/Object;)Ljava/lang/Object;
  #183 = Class              #184          // ext/mods/gameserver/model/manor/CropProcure
  #184 = Utf8               ext/mods/gameserver/model/manor/CropProcure
  #185 = String             #186          // crop_id
  #186 = Utf8               crop_id
  #187 = String             #188          // reward_type
  #188 = Utf8               reward_type
  #189 = Methodref          #183.#190     // ext/mods/gameserver/model/manor/CropProcure."<init>":(IIIII)V
  #190 = NameAndType        #5:#191       // "<init>":(IIIII)V
  #191 = Utf8               (IIIII)V
  #192 = InterfaceMethodref #113.#163     // java/sql/PreparedStatement.close:()V
  #193 = InterfaceMethodref #74.#163      // java/sql/Connection.close:()V
  #194 = Class              #195          // java/lang/Exception
  #195 = Utf8               java/lang/Exception
  #196 = String             #197          // Error restoring manor data.
  #197 = Utf8               Error restoring manor data.
  #198 = Methodref          #57.#199      // ext/mods/commons/logging/CLogger.error:(Ljava/lang/Object;Ljava/lang/Throwable;)V
  #199 = NameAndType        #200:#201     // error:(Ljava/lang/Object;Ljava/lang/Throwable;)V
  #200 = Utf8               error
  #201 = Utf8               (Ljava/lang/Object;Ljava/lang/Throwable;)V
  #202 = Methodref          #203.#204     // java/util/Calendar.getInstance:()Ljava/util/Calendar;
  #203 = Class              #205          // java/util/Calendar
  #204 = NameAndType        #85:#206      // getInstance:()Ljava/util/Calendar;
  #205 = Utf8               java/util/Calendar
  #206 = Utf8               ()Ljava/util/Calendar;
  #207 = Methodref          #203.#208     // java/util/Calendar.get:(I)I
  #208 = NameAndType        #209:#210     // get:(I)I
  #209 = Utf8               get
  #210 = Utf8               (I)I
  #211 = Fieldref           #42.#212      // ext/mods/Config.MANOR_REFRESH_MIN:I
  #212 = NameAndType        #213:#214     // MANOR_REFRESH_MIN:I
  #213 = Utf8               MANOR_REFRESH_MIN
  #214 = Utf8               I
  #215 = Fieldref           #42.#216      // ext/mods/Config.MANOR_MAINTENANCE_MIN:I
  #216 = NameAndType        #217:#214     // MANOR_MAINTENANCE_MIN:I
  #217 = Utf8               MANOR_MAINTENANCE_MIN
  #218 = Fieldref           #42.#219      // ext/mods/Config.MANOR_REFRESH_TIME:I
  #219 = NameAndType        #220:#214     // MANOR_REFRESH_TIME:I
  #220 = Utf8               MANOR_REFRESH_TIME
  #221 = Fieldref           #42.#222      // ext/mods/Config.MANOR_APPROVE_TIME:I
  #222 = NameAndType        #223:#214     // MANOR_APPROVE_TIME:I
  #223 = Utf8               MANOR_APPROVE_TIME
  #224 = Fieldref           #42.#225      // ext/mods/Config.MANOR_APPROVE_MIN:I
  #225 = NameAndType        #226:#214     // MANOR_APPROVE_MIN:I
  #226 = Utf8               MANOR_APPROVE_MIN
  #227 = Fieldref           #8.#228       // ext/mods/gameserver/enums/ManorStatus.MODIFIABLE:Lext/mods/gameserver/enums/ManorStatus;
  #228 = NameAndType        #229:#12      // MODIFIABLE:Lext/mods/gameserver/enums/ManorStatus;
  #229 = Utf8               MODIFIABLE
  #230 = Fieldref           #8.#231       // ext/mods/gameserver/enums/ManorStatus.MAINTENANCE:Lext/mods/gameserver/enums/ManorStatus;
  #231 = NameAndType        #232:#12      // MAINTENANCE:Lext/mods/gameserver/enums/ManorStatus;
  #232 = Utf8               MAINTENANCE
  #233 = Methodref          #14.#234      // ext/mods/gameserver/data/manager/CastleManorManager.scheduleModeChange:()V
  #234 = NameAndType        #235:#6       // scheduleModeChange:()V
  #235 = Utf8               scheduleModeChange
  #236 = InvokeDynamic      #0:#237       // #0:run:(Lext/mods/gameserver/data/manager/CastleManorManager;)Ljava/lang/Runnable;
  #237 = NameAndType        #238:#239     // run:(Lext/mods/gameserver/data/manager/CastleManorManager;)Ljava/lang/Runnable;
  #238 = Utf8               run
  #239 = Utf8               (Lext/mods/gameserver/data/manager/CastleManorManager;)Ljava/lang/Runnable;
  #240 = Fieldref           #42.#241      // ext/mods/Config.MANOR_SAVE_PERIOD_RATE:I
  #241 = NameAndType        #242:#214     // MANOR_SAVE_PERIOD_RATE:I
  #242 = Utf8               MANOR_SAVE_PERIOD_RATE
  #243 = Methodref          #244.#245     // ext/mods/commons/pool/ThreadPool.scheduleAtFixedRate:(Ljava/lang/Runnable;JJ)Ljava/util/concurrent/ScheduledFuture;
  #244 = Class              #246          // ext/mods/commons/pool/ThreadPool
  #245 = NameAndType        #247:#248     // scheduleAtFixedRate:(Ljava/lang/Runnable;JJ)Ljava/util/concurrent/ScheduledFuture;
  #246 = Utf8               ext/mods/commons/pool/ThreadPool
  #247 = Utf8               scheduleAtFixedRate
  #248 = Utf8               (Ljava/lang/Runnable;JJ)Ljava/util/concurrent/ScheduledFuture;
  #249 = String             #250          // Current Manor mode is: {}.
  #250 = Utf8               Current Manor mode is: {}.
  #251 = Methodref          #8.#252       // ext/mods/gameserver/enums/ManorStatus.toString:()Ljava/lang/String;
  #252 = NameAndType        #253:#254     // toString:()Ljava/lang/String;
  #253 = Utf8               toString
  #254 = Utf8               ()Ljava/lang/String;
  #255 = Methodref          #57.#256      // ext/mods/commons/logging/CLogger.debug:(Ljava/lang/Object;[Ljava/lang/Object;)V
  #256 = NameAndType        #257:#258     // debug:(Ljava/lang/Object;[Ljava/lang/Object;)V
  #257 = Utf8               debug
  #258 = Utf8               (Ljava/lang/Object;[Ljava/lang/Object;)V
  #259 = String             #260          // xml/manors.xml
  #260 = Utf8               xml/manors.xml
  #261 = Methodref          #14.#262      // ext/mods/gameserver/data/manager/CastleManorManager.parseDataFile:(Ljava/lang/String;)V
  #262 = NameAndType        #263:#264     // parseDataFile:(Ljava/lang/String;)V
  #263 = Utf8               parseDataFile
  #264 = Utf8               (Ljava/lang/String;)V
  #265 = String             #266          // Loaded {} seeds.
  #266 = Utf8               Loaded {} seeds.
  #267 = InterfaceMethodref #178.#268     // java/util/Map.size:()I
  #268 = NameAndType        #269:#120     // size:()I
  #269 = Utf8               size
  #270 = Methodref          #57.#271      // ext/mods/commons/logging/CLogger.info:(Ljava/lang/Object;[Ljava/lang/Object;)V
  #271 = NameAndType        #60:#258      // info:(Ljava/lang/Object;[Ljava/lang/Object;)V
  #272 = String             #273          // list
  #273 = Utf8               list
  #274 = InvokeDynamic      #1:#275       // #1:accept:(Lext/mods/gameserver/data/manager/CastleManorManager;)Ljava/util/function/Consumer;
  #275 = NameAndType        #276:#277     // accept:(Lext/mods/gameserver/data/manager/CastleManorManager;)Ljava/util/function/Consumer;
  #276 = Utf8               accept
  #277 = Utf8               (Lext/mods/gameserver/data/manager/CastleManorManager;)Ljava/util/function/Consumer;
  #278 = Methodref          #14.#279      // ext/mods/gameserver/data/manager/CastleManorManager.forEach:(Lorg/w3c/dom/Node;Ljava/lang/String;Ljava/util/function/Consumer;)V
  #279 = NameAndType        #280:#281     // forEach:(Lorg/w3c/dom/Node;Ljava/lang/String;Ljava/util/function/Consumer;)V
  #280 = Utf8               forEach
  #281 = Utf8               (Lorg/w3c/dom/Node;Ljava/lang/String;Ljava/util/function/Consumer;)V
  #282 = Methodref          #203.#283     // java/util/Calendar.set:(II)V
  #283 = NameAndType        #284:#124     // set:(II)V
  #284 = Utf8               set
  #285 = Fieldref           #286.#287     // ext/mods/gameserver/data/manager/CastleManorManager$1.$SwitchMap$ext$mods$gameserver$enums$ManorStatus:[I
  #286 = Class              #288          // ext/mods/gameserver/data/manager/CastleManorManager$1
  #287 = NameAndType        #289:#290     // $SwitchMap$ext$mods$gameserver$enums$ManorStatus:[I
  #288 = Utf8               ext/mods/gameserver/data/manager/CastleManorManager$1
  #289 = Utf8               $SwitchMap$ext$mods$gameserver$enums$ManorStatus
  #290 = Utf8               [I
  #291 = Methodref          #8.#292       // ext/mods/gameserver/enums/ManorStatus.ordinal:()I
  #292 = NameAndType        #293:#120     // ordinal:()I
  #293 = Utf8               ordinal
  #294 = Methodref          #203.#295     // java/util/Calendar.before:(Ljava/lang/Object;)Z
  #295 = NameAndType        #296:#161     // before:(Ljava/lang/Object;)Z
  #296 = Utf8               before
  #297 = Methodref          #203.#298     // java/util/Calendar.add:(II)V
  #298 = NameAndType        #160:#124     // add:(II)V
  #299 = InvokeDynamic      #2:#237       // #2:run:(Lext/mods/gameserver/data/manager/CastleManorManager;)Ljava/lang/Runnable;
  #300 = Methodref          #203.#301     // java/util/Calendar.getTimeInMillis:()J
  #301 = NameAndType        #302:#303     // getTimeInMillis:()J
  #302 = Utf8               getTimeInMillis
  #303 = Utf8               ()J
  #304 = Methodref          #305.#306     // java/lang/System.currentTimeMillis:()J
  #305 = Class              #307          // java/lang/System
  #306 = NameAndType        #308:#303     // currentTimeMillis:()J
  #307 = Utf8               java/lang/System
  #308 = Utf8               currentTimeMillis
  #309 = Methodref          #244.#310     // ext/mods/commons/pool/ThreadPool.schedule:(Ljava/lang/Runnable;J)Ljava/util/concurrent/ScheduledFuture;
  #310 = NameAndType        #311:#312     // schedule:(Ljava/lang/Runnable;J)Ljava/util/concurrent/ScheduledFuture;
  #311 = Utf8               schedule
  #312 = Utf8               (Ljava/lang/Runnable;J)Ljava/util/concurrent/ScheduledFuture;
  #313 = Methodref          #314.#315     // ext/mods/gameserver/data/sql/ClanTable.getInstance:()Lext/mods/gameserver/data/sql/ClanTable;
  #314 = Class              #316          // ext/mods/gameserver/data/sql/ClanTable
  #315 = NameAndType        #85:#317      // getInstance:()Lext/mods/gameserver/data/sql/ClanTable;
  #316 = Utf8               ext/mods/gameserver/data/sql/ClanTable
  #317 = Utf8               ()Lext/mods/gameserver/data/sql/ClanTable;
  #318 = Methodref          #107.#319     // ext/mods/gameserver/model/residence/castle/Castle.getOwnerId:()I
  #319 = NameAndType        #320:#120     // getOwnerId:()I
  #320 = Utf8               getOwnerId
  #321 = Methodref          #314.#322     // ext/mods/gameserver/data/sql/ClanTable.getClan:(I)Lext/mods/gameserver/model/pledge/Clan;
  #322 = NameAndType        #323:#324     // getClan:(I)Lext/mods/gameserver/model/pledge/Clan;
  #323 = Utf8               getClan
  #324 = Utf8               (I)Lext/mods/gameserver/model/pledge/Clan;
  #325 = InterfaceMethodref #178.#326     // java/util/Map.get:(Ljava/lang/Object;)Ljava/lang/Object;
  #326 = NameAndType        #209:#327     // get:(Ljava/lang/Object;)Ljava/lang/Object;
  #327 = Utf8               (Ljava/lang/Object;)Ljava/lang/Object;
  #328 = InterfaceMethodref #157.#93      // java/util/List.iterator:()Ljava/util/Iterator;
  #329 = Methodref          #183.#330     // ext/mods/gameserver/model/manor/CropProcure.getStartAmount:()I
  #330 = NameAndType        #331:#120     // getStartAmount:()I
  #331 = Utf8               getStartAmount
  #332 = Methodref          #183.#333     // ext/mods/gameserver/model/manor/CropProcure.getAmount:()I
  #333 = NameAndType        #334:#120     // getAmount:()I
  #334 = Utf8               getAmount
  #335 = Double             0.9d
  #337 = Methodref          #338.#339     // ext/mods/commons/random/Rnd.nextInt:(I)I
  #338 = Class              #340          // ext/mods/commons/random/Rnd
  #339 = NameAndType        #341:#210     // nextInt:(I)I
  #340 = Utf8               ext/mods/commons/random/Rnd
  #341 = Utf8               nextInt
  #342 = Methodref          #183.#118     // ext/mods/gameserver/model/manor/CropProcure.getId:()I
  #343 = Methodref          #14.#344      // ext/mods/gameserver/data/manager/CastleManorManager.getSeedByCrop:(I)Lext/mods/gameserver/model/manor/Seed;
  #344 = NameAndType        #345:#346     // getSeedByCrop:(I)Lext/mods/gameserver/model/manor/Seed;
  #345 = Utf8               getSeedByCrop
  #346 = Utf8               (I)Lext/mods/gameserver/model/manor/Seed;
  #347 = Methodref          #348.#349     // ext/mods/gameserver/model/pledge/Clan.getWarehouse:()Lext/mods/gameserver/model/itemcontainer/ItemContainer;
  #348 = Class              #350          // ext/mods/gameserver/model/pledge/Clan
  #349 = NameAndType        #351:#352     // getWarehouse:()Lext/mods/gameserver/model/itemcontainer/ItemContainer;
  #350 = Utf8               ext/mods/gameserver/model/pledge/Clan
  #351 = Utf8               getWarehouse
  #352 = Utf8               ()Lext/mods/gameserver/model/itemcontainer/ItemContainer;
  #353 = Methodref          #354.#355     // ext/mods/gameserver/model/manor/Seed.getMatureId:()I
  #354 = Class              #356          // ext/mods/gameserver/model/manor/Seed
  #355 = NameAndType        #357:#120     // getMatureId:()I
  #356 = Utf8               ext/mods/gameserver/model/manor/Seed
  #357 = Utf8               getMatureId
  #358 = Methodref          #359.#360     // ext/mods/gameserver/model/itemcontainer/ItemContainer.addItem:(II)Lext/mods/gameserver/model/item/instance/ItemInstance;
  #359 = Class              #361          // ext/mods/gameserver/model/itemcontainer/ItemContainer
  #360 = NameAndType        #362:#363     // addItem:(II)Lext/mods/gameserver/model/item/instance/ItemInstance;
  #361 = Utf8               ext/mods/gameserver/model/itemcontainer/ItemContainer
  #362 = Utf8               addItem
  #363 = Utf8               (II)Lext/mods/gameserver/model/item/instance/ItemInstance;
  #364 = Methodref          #183.#365     // ext/mods/gameserver/model/manor/CropProcure.getPrice:()I
  #365 = NameAndType        #366:#120     // getPrice:()I
  #366 = Utf8               getPrice
  #367 = Methodref          #107.#368     // ext/mods/gameserver/model/residence/castle/Castle.riseSeedIncome:(J)V
  #368 = NameAndType        #369:#370     // riseSeedIncome:(J)V
  #369 = Utf8               riseSeedIncome
  #370 = Utf8               (J)V
  #371 = Methodref          #107.#372     // ext/mods/gameserver/model/residence/castle/Castle.getTreasury:()J
  #372 = NameAndType        #373:#303     // getTreasury:()J
  #373 = Utf8               getTreasury
  #374 = Methodref          #14.#375      // ext/mods/gameserver/data/manager/CastleManorManager.getManorCost:(IZ)J
  #375 = NameAndType        #376:#377     // getManorCost:(IZ)J
  #376 = Utf8               getManorCost
  #377 = Utf8               (IZ)J
  #378 = Methodref          #379.#380     // java/util/Collections.emptyList:()Ljava/util/List;
  #379 = Class              #381          // java/util/Collections
  #380 = NameAndType        #382:#383     // emptyList:()Ljava/util/List;
  #381 = Utf8               java/util/Collections
  #382 = Utf8               emptyList
  #383 = Utf8               ()Ljava/util/List;
  #384 = Methodref          #109.#385     // java/util/ArrayList."<init>":(Ljava/util/Collection;)V
  #385 = NameAndType        #5:#386       // "<init>":(Ljava/util/Collection;)V
  #386 = Utf8               (Ljava/util/Collection;)V
  #387 = Methodref          #133.#330     // ext/mods/gameserver/model/manor/SeedProduction.getStartAmount:()I
  #388 = Methodref          #133.#389     // ext/mods/gameserver/model/manor/SeedProduction.setAmount:(I)V
  #389 = NameAndType        #390:#391     // setAmount:(I)V
  #390 = Utf8               setAmount
  #391 = Utf8               (I)V
  #392 = Methodref          #183.#389     // ext/mods/gameserver/model/manor/CropProcure.setAmount:(I)V
  #393 = Methodref          #14.#394      // ext/mods/gameserver/data/manager/CastleManorManager.storeMe:()Z
  #394 = NameAndType        #395:#102     // storeMe:()Z
  #395 = Utf8               storeMe
  #396 = Methodref          #348.#397     // ext/mods/gameserver/model/pledge/Clan.getLeader:()Lext/mods/gameserver/model/pledge/ClanMember;
  #397 = NameAndType        #398:#399     // getLeader:()Lext/mods/gameserver/model/pledge/ClanMember;
  #398 = Utf8               getLeader
  #399 = Utf8               ()Lext/mods/gameserver/model/pledge/ClanMember;
  #400 = Methodref          #401.#402     // ext/mods/gameserver/model/pledge/ClanMember.isOnline:()Z
  #401 = Class              #403          // ext/mods/gameserver/model/pledge/ClanMember
  #402 = NameAndType        #404:#102     // isOnline:()Z
  #403 = Utf8               ext/mods/gameserver/model/pledge/ClanMember
  #404 = Utf8               isOnline
  #405 = Methodref          #401.#406     // ext/mods/gameserver/model/pledge/ClanMember.getPlayerInstance:()Lext/mods/gameserver/model/actor/Player;
  #406 = NameAndType        #407:#408     // getPlayerInstance:()Lext/mods/gameserver/model/actor/Player;
  #407 = Utf8               getPlayerInstance
  #408 = Utf8               ()Lext/mods/gameserver/model/actor/Player;
  #409 = Fieldref           #410.#411     // ext/mods/gameserver/network/SystemMessageId.THE_MANOR_INFORMATION_HAS_BEEN_UPDATED:Lext/mods/gameserver/network/SystemMessageId;
  #410 = Class              #412          // ext/mods/gameserver/network/SystemMessageId
  #411 = NameAndType        #413:#414     // THE_MANOR_INFORMATION_HAS_BEEN_UPDATED:Lext/mods/gameserver/network/SystemMessageId;
  #412 = Utf8               ext/mods/gameserver/network/SystemMessageId
  #413 = Utf8               THE_MANOR_INFORMATION_HAS_BEEN_UPDATED
  #414 = Utf8               Lext/mods/gameserver/network/SystemMessageId;
  #415 = Methodref          #416.#417     // ext/mods/gameserver/model/actor/Player.sendPacket:(Lext/mods/gameserver/network/SystemMessageId;)V
  #416 = Class              #418          // ext/mods/gameserver/model/actor/Player
  #417 = NameAndType        #419:#420     // sendPacket:(Lext/mods/gameserver/network/SystemMessageId;)V
  #418 = Utf8               ext/mods/gameserver/model/actor/Player
  #419 = Utf8               sendPacket
  #420 = Utf8               (Lext/mods/gameserver/network/SystemMessageId;)V
  #421 = Methodref          #359.#422     // ext/mods/gameserver/model/itemcontainer/ItemContainer.getItemsByItemId:(I)Ljava/util/List;
  #422 = NameAndType        #423:#424     // getItemsByItemId:(I)Ljava/util/List;
  #423 = Utf8               getItemsByItemId
  #424 = Utf8               (I)Ljava/util/List;
  #425 = Methodref          #359.#426     // ext/mods/gameserver/model/itemcontainer/ItemContainer.validateCapacity:(I)Z
  #426 = NameAndType        #427:#428     // validateCapacity:(I)Z
  #427 = Utf8               validateCapacity
  #428 = Utf8               (I)Z
  #429 = Methodref          #107.#430     // ext/mods/gameserver/model/residence/castle/Castle.editTreasury:(JZ)Z
  #430 = NameAndType        #431:#432     // editTreasury:(JZ)Z
  #431 = Utf8               editTreasury
  #432 = Utf8               (JZ)Z
  #433 = InterfaceMethodref #157.#434     // java/util/List.clear:()V
  #434 = NameAndType        #435:#6       // clear:()V
  #435 = Utf8               clear
  #436 = Fieldref           #410.#437     // ext/mods/gameserver/network/SystemMessageId.THE_AMOUNT_IS_NOT_SUFFICIENT_AND_SO_THE_MANOR_IS_NOT_IN_OPERATION:Lext/mods/gameserver/network/SystemMessageId;
  #437 = NameAndType        #438:#414     // THE_AMOUNT_IS_NOT_SUFFICIENT_AND_SO_THE_MANOR_IS_NOT_IN_OPERATION:Lext/mods/gameserver/network/SystemMessageId;
  #438 = Utf8               THE_AMOUNT_IS_NOT_SUFFICIENT_AND_SO_THE_MANOR_IS_NOT_IN_OPERATION
  #439 = String             #440          // Manor mode changed to: {}.
  #440 = Utf8               Manor mode changed to: {}.
  #441 = String             #442          // UPDATE castle_manor_production SET amount = ? WHERE castle_id = ? AND seed_id = ? AND next_period = 0
  #442 = Utf8               UPDATE castle_manor_production SET amount = ? WHERE castle_id = ? AND seed_id = ? AND next_period = 0
  #443 = Methodref          #133.#333     // ext/mods/gameserver/model/manor/SeedProduction.getAmount:()I
  #444 = InterfaceMethodref #113.#445     // java/sql/PreparedStatement.setLong:(IJ)V
  #445 = NameAndType        #446:#447     // setLong:(IJ)V
  #446 = Utf8               setLong
  #447 = Utf8               (IJ)V
  #448 = Methodref          #133.#118     // ext/mods/gameserver/model/manor/SeedProduction.getId:()I
  #449 = InterfaceMethodref #113.#450     // java/sql/PreparedStatement.addBatch:()V
  #450 = NameAndType        #451:#6       // addBatch:()V
  #451 = Utf8               addBatch
  #452 = InterfaceMethodref #113.#453     // java/sql/PreparedStatement.executeBatch:()[I
  #453 = NameAndType        #454:#455     // executeBatch:()[I
  #454 = Utf8               executeBatch
  #455 = Utf8               ()[I
  #456 = String             #457          // Unable to store manor data.
  #457 = Utf8               Unable to store manor data.
  #458 = String             #459          // UPDATE castle_manor_procure SET amount = ? WHERE castle_id = ? AND crop_id = ? AND next_period = 0
  #459 = Utf8               UPDATE castle_manor_procure SET amount = ? WHERE castle_id = ? AND crop_id = ? AND next_period = 0
  #460 = Methodref          #14.#461      // ext/mods/gameserver/data/manager/CastleManorManager.getSeedProduction:(IZ)Ljava/util/List;
  #461 = NameAndType        #462:#463     // getSeedProduction:(IZ)Ljava/util/List;
  #462 = Utf8               getSeedProduction
  #463 = Utf8               (IZ)Ljava/util/List;
  #464 = Methodref          #14.#465      // ext/mods/gameserver/data/manager/CastleManorManager.getCropProcure:(IZ)Ljava/util/List;
  #465 = NameAndType        #466:#463     // getCropProcure:(IZ)Ljava/util/List;
  #466 = Utf8               getCropProcure
  #467 = Methodref          #14.#468      // ext/mods/gameserver/data/manager/CastleManorManager.getSeed:(I)Lext/mods/gameserver/model/manor/Seed;
  #468 = NameAndType        #469:#346     // getSeed:(I)Lext/mods/gameserver/model/manor/Seed;
  #469 = Utf8               getSeed
  #470 = Methodref          #354.#471     // ext/mods/gameserver/model/manor/Seed.getSeedReferencePrice:()I
  #471 = NameAndType        #472:#120     // getSeedReferencePrice:()I
  #472 = Utf8               getSeedReferencePrice
  #473 = String             #474          // TRUNCATE castle_manor_production
  #474 = Utf8               TRUNCATE castle_manor_production
  #475 = String             #476          // INSERT INTO castle_manor_production VALUES (?, ?, ?, ?, ?, ?)
  #476 = Utf8               INSERT INTO castle_manor_production VALUES (?, ?, ?, ?, ?, ?)
  #477 = String             #478          // TRUNCATE castle_manor_procure
  #478 = Utf8               TRUNCATE castle_manor_procure
  #479 = String             #480          // INSERT INTO castle_manor_procure VALUES (?, ?, ?, ?, ?, ?, ?)
  #480 = Utf8               INSERT INTO castle_manor_procure VALUES (?, ?, ?, ?, ?, ?, ?)
  #481 = InterfaceMethodref #113.#482     // java/sql/PreparedStatement.executeUpdate:()I
  #482 = NameAndType        #483:#120     // executeUpdate:()I
  #483 = Utf8               executeUpdate
  #484 = InterfaceMethodref #178.#485     // java/util/Map.entrySet:()Ljava/util/Set;
  #485 = NameAndType        #486:#487     // entrySet:()Ljava/util/Set;
  #486 = Utf8               entrySet
  #487 = Utf8               ()Ljava/util/Set;
  #488 = InterfaceMethodref #489.#93      // java/util/Set.iterator:()Ljava/util/Iterator;
  #489 = Class              #490          // java/util/Set
  #490 = Utf8               java/util/Set
  #491 = Class              #492          // java/util/Map$Entry
  #492 = Utf8               java/util/Map$Entry
  #493 = InterfaceMethodref #491.#494     // java/util/Map$Entry.getValue:()Ljava/lang/Object;
  #494 = NameAndType        #495:#106     // getValue:()Ljava/lang/Object;
  #495 = Utf8               getValue
  #496 = InterfaceMethodref #491.#497     // java/util/Map$Entry.getKey:()Ljava/lang/Object;
  #497 = NameAndType        #498:#106     // getKey:()Ljava/lang/Object;
  #498 = Utf8               getKey
  #499 = Methodref          #172.#500     // java/lang/Integer.intValue:()I
  #500 = NameAndType        #501:#120     // intValue:()I
  #501 = Utf8               intValue
  #502 = Methodref          #133.#365     // ext/mods/gameserver/model/manor/SeedProduction.getPrice:()I
  #503 = InterfaceMethodref #113.#504     // java/sql/PreparedStatement.setBoolean:(IZ)V
  #504 = NameAndType        #505:#506     // setBoolean:(IZ)V
  #505 = Utf8               setBoolean
  #506 = Utf8               (IZ)V
  #507 = Methodref          #183.#508     // ext/mods/gameserver/model/manor/CropProcure.getReward:()I
  #508 = NameAndType        #509:#120     // getReward:()I
  #509 = Utf8               getReward
  #510 = Class              #511          // java/text/SimpleDateFormat
  #511 = Utf8               java/text/SimpleDateFormat
  #512 = String             #513          // dd/MM HH:mm:ss
  #513 = Utf8               dd/MM HH:mm:ss
  #514 = Methodref          #510.#515     // java/text/SimpleDateFormat."<init>":(Ljava/lang/String;)V
  #515 = NameAndType        #5:#264       // "<init>":(Ljava/lang/String;)V
  #516 = Methodref          #203.#517     // java/util/Calendar.getTime:()Ljava/util/Date;
  #517 = NameAndType        #518:#519     // getTime:()Ljava/util/Date;
  #518 = Utf8               getTime
  #519 = Utf8               ()Ljava/util/Date;
  #520 = Methodref          #510.#521     // java/text/SimpleDateFormat.format:(Ljava/util/Date;)Ljava/lang/String;
  #521 = NameAndType        #522:#523     // format:(Ljava/util/Date;)Ljava/lang/String;
  #522 = Utf8               format
  #523 = Utf8               (Ljava/util/Date;)Ljava/lang/String;
  #524 = InterfaceMethodref #178.#525     // java/util/Map.values:()Ljava/util/Collection;
  #525 = NameAndType        #526:#90      // values:()Ljava/util/Collection;
  #526 = Utf8               values
  #527 = Methodref          #354.#528     // ext/mods/gameserver/model/manor/Seed.getCropId:()I
  #528 = NameAndType        #529:#120     // getCropId:()I
  #529 = Utf8               getCropId
  #530 = InterfaceMethodref #157.#531     // java/util/List.contains:(Ljava/lang/Object;)Z
  #531 = NameAndType        #532:#161     // contains:(Ljava/lang/Object;)Z
  #532 = Utf8               contains
  #533 = InterfaceMethodref #92.#534      // java/util/Collection.stream:()Ljava/util/stream/Stream;
  #534 = NameAndType        #535:#536     // stream:()Ljava/util/stream/Stream;
  #535 = Utf8               stream
  #536 = Utf8               ()Ljava/util/stream/Stream;
  #537 = InvokeDynamic      #3:#538       // #3:test:(I)Ljava/util/function/Predicate;
  #538 = NameAndType        #539:#540     // test:(I)Ljava/util/function/Predicate;
  #539 = Utf8               test
  #540 = Utf8               (I)Ljava/util/function/Predicate;
  #541 = InterfaceMethodref #542.#543     // java/util/stream/Stream.filter:(Ljava/util/function/Predicate;)Ljava/util/stream/Stream;
  #542 = Class              #544          // java/util/stream/Stream
  #543 = NameAndType        #545:#546     // filter:(Ljava/util/function/Predicate;)Ljava/util/stream/Stream;
  #544 = Utf8               java/util/stream/Stream
  #545 = Utf8               filter
  #546 = Utf8               (Ljava/util/function/Predicate;)Ljava/util/stream/Stream;
  #547 = Methodref          #548.#549     // java/util/stream/Collectors.toSet:()Ljava/util/stream/Collector;
  #548 = Class              #550          // java/util/stream/Collectors
  #549 = NameAndType        #551:#552     // toSet:()Ljava/util/stream/Collector;
  #550 = Utf8               java/util/stream/Collectors
  #551 = Utf8               toSet
  #552 = Utf8               ()Ljava/util/stream/Collector;
  #553 = InterfaceMethodref #542.#554     // java/util/stream/Stream.collect:(Ljava/util/stream/Collector;)Ljava/lang/Object;
  #554 = NameAndType        #555:#556     // collect:(Ljava/util/stream/Collector;)Ljava/lang/Object;
  #555 = Utf8               collect
  #556 = Utf8               (Ljava/util/stream/Collector;)Ljava/lang/Object;
  #557 = InvokeDynamic      #4:#558       // #4:apply:()Ljava/util/function/Function;
  #558 = NameAndType        #559:#560     // apply:()Ljava/util/function/Function;
  #559 = Utf8               apply
  #560 = Utf8               ()Ljava/util/function/Function;
  #561 = InterfaceMethodref #542.#562     // java/util/stream/Stream.map:(Ljava/util/function/Function;)Ljava/util/stream/Stream;
  #562 = NameAndType        #563:#564     // map:(Ljava/util/function/Function;)Ljava/util/stream/Stream;
  #563 = Utf8               map
  #564 = Utf8               (Ljava/util/function/Function;)Ljava/util/stream/Stream;
  #565 = InvokeDynamic      #5:#566       // #5:test:(II)Ljava/util/function/Predicate;
  #566 = NameAndType        #539:#567     // test:(II)Ljava/util/function/Predicate;
  #567 = Utf8               (II)Ljava/util/function/Predicate;
  #568 = InterfaceMethodref #542.#569     // java/util/stream/Stream.findFirst:()Ljava/util/Optional;
  #569 = NameAndType        #570:#571     // findFirst:()Ljava/util/Optional;
  #570 = Utf8               findFirst
  #571 = Utf8               ()Ljava/util/Optional;
  #572 = Methodref          #573.#574     // java/util/Optional.orElse:(Ljava/lang/Object;)Ljava/lang/Object;
  #573 = Class              #575          // java/util/Optional
  #574 = NameAndType        #576:#327     // orElse:(Ljava/lang/Object;)Ljava/lang/Object;
  #575 = Utf8               java/util/Optional
  #576 = Utf8               orElse
  #577 = InvokeDynamic      #6:#538       // #6:test:(I)Ljava/util/function/Predicate;
  #578 = Methodref          #354.#579     // ext/mods/gameserver/model/manor/Seed.getReward1:()I
  #579 = NameAndType        #580:#120     // getReward1:()I
  #580 = Utf8               getReward1
  #581 = Methodref          #354.#582     // ext/mods/gameserver/model/manor/Seed.getReward2:()I
  #582 = NameAndType        #583:#120     // getReward2:()I
  #583 = Utf8               getReward2
  #584 = Fieldref           #585.#586     // ext/mods/gameserver/data/manager/CastleManorManager$SingletonHolder.INSTANCE:Lext/mods/gameserver/data/manager/CastleManorManager;
  #585 = Class              #587          // ext/mods/gameserver/data/manager/CastleManorManager$SingletonHolder
  #586 = NameAndType        #588:#589     // INSTANCE:Lext/mods/gameserver/data/manager/CastleManorManager;
  #587 = Utf8               ext/mods/gameserver/data/manager/CastleManorManager$SingletonHolder
  #588 = Utf8               INSTANCE
  #589 = Utf8               Lext/mods/gameserver/data/manager/CastleManorManager;
  #590 = Methodref          #354.#591     // ext/mods/gameserver/model/manor/Seed.getCastleId:()I
  #591 = NameAndType        #592:#120     // getCastleId:()I
  #592 = Utf8               getCastleId
  #593 = String             #594          // manor
  #594 = Utf8               manor
  #595 = InvokeDynamic      #7:#275       // #7:accept:(Lext/mods/gameserver/data/manager/CastleManorManager;)Ljava/util/function/Consumer;
  #596 = InterfaceMethodref #597.#598     // org/w3c/dom/Node.getAttributes:()Lorg/w3c/dom/NamedNodeMap;
  #597 = Class              #599          // org/w3c/dom/Node
  #598 = NameAndType        #600:#601     // getAttributes:()Lorg/w3c/dom/NamedNodeMap;
  #599 = Utf8               org/w3c/dom/Node
  #600 = Utf8               getAttributes
  #601 = Utf8               ()Lorg/w3c/dom/NamedNodeMap;
  #602 = String             #603          // id
  #603 = Utf8               id
  #604 = Methodref          #14.#605      // ext/mods/gameserver/data/manager/CastleManorManager.parseInteger:(Lorg/w3c/dom/NamedNodeMap;Ljava/lang/String;)Ljava/lang/Integer;
  #605 = NameAndType        #606:#607     // parseInteger:(Lorg/w3c/dom/NamedNodeMap;Ljava/lang/String;)Ljava/lang/Integer;
  #606 = Utf8               parseInteger
  #607 = Utf8               (Lorg/w3c/dom/NamedNodeMap;Ljava/lang/String;)Ljava/lang/Integer;
  #608 = String             #609          // crop
  #609 = Utf8               crop
  #610 = InvokeDynamic      #8:#611       // #8:accept:(Lext/mods/gameserver/data/manager/CastleManorManager;I)Ljava/util/function/Consumer;
  #611 = NameAndType        #276:#612     // accept:(Lext/mods/gameserver/data/manager/CastleManorManager;I)Ljava/util/function/Consumer;
  #612 = Utf8               (Lext/mods/gameserver/data/manager/CastleManorManager;I)Ljava/util/function/Consumer;
  #613 = Methodref          #14.#614      // ext/mods/gameserver/data/manager/CastleManorManager.parseAttributes:(Lorg/w3c/dom/Node;)Lext/mods/commons/data/StatSet;
  #614 = NameAndType        #615:#616     // parseAttributes:(Lorg/w3c/dom/Node;)Lext/mods/commons/data/StatSet;
  #615 = Utf8               parseAttributes
  #616 = Utf8               (Lorg/w3c/dom/Node;)Lext/mods/commons/data/StatSet;
  #617 = String             #618          // castleId
  #618 = Utf8               castleId
  #619 = Methodref          #620.#621     // ext/mods/commons/data/StatSet.set:(Ljava/lang/String;I)V
  #620 = Class              #622          // ext/mods/commons/data/StatSet
  #621 = NameAndType        #284:#623     // set:(Ljava/lang/String;I)V
  #622 = Utf8               ext/mods/commons/data/StatSet
  #623 = Utf8               (Ljava/lang/String;I)V
  #624 = String             #625          // seedId
  #625 = Utf8               seedId
  #626 = Methodref          #620.#627     // ext/mods/commons/data/StatSet.getInteger:(Ljava/lang/String;)I
  #627 = NameAndType        #628:#140     // getInteger:(Ljava/lang/String;)I
  #628 = Utf8               getInteger
  #629 = Methodref          #354.#630     // ext/mods/gameserver/model/manor/Seed."<init>":(Lext/mods/commons/data/StatSet;)V
  #630 = NameAndType        #5:#631       // "<init>":(Lext/mods/commons/data/StatSet;)V
  #631 = Utf8               (Lext/mods/commons/data/StatSet;)V
  #632 = Class              #633          // ext/mods/commons/data/xml/IXmlReader
  #633 = Utf8               ext/mods/commons/data/xml/IXmlReader
  #634 = Utf8               LOAD_PROCURE
  #635 = Utf8               Ljava/lang/String;
  #636 = Utf8               ConstantValue
  #637 = Utf8               LOAD_PRODUCTION
  #638 = Utf8               UPDATE_PRODUCTION
  #639 = Utf8               UPDATE_PROCURE
  #640 = Utf8               TRUNCATE_PRODUCTS
  #641 = Utf8               INSERT_PRODUCT
  #642 = Utf8               TRUNCATE_PROCURES
  #643 = Utf8               INSERT_CROP
  #644 = Utf8               Signature
  #645 = Utf8               Ljava/util/Map<Ljava/lang/Integer;Lext/mods/gameserver/model/manor/Seed;>;
  #646 = Utf8               Ljava/util/Map<Ljava/lang/Integer;Ljava/util/List<Lext/mods/gameserver/model/manor/CropProcure;>;>;
  #647 = Utf8               Ljava/util/Map<Ljava/lang/Integer;Ljava/util/List<Lext/mods/gameserver/model/manor/SeedProduction;>;>;
  #648 = Utf8               Code
  #649 = Utf8               LineNumberTable
  #650 = Utf8               LocalVariableTable
  #651 = Utf8               sp
  #652 = Utf8               Lext/mods/gameserver/model/manor/SeedProduction;
  #653 = Utf8               rs
  #654 = Utf8               Ljava/sql/ResultSet;
  #655 = Utf8               cp
  #656 = Utf8               Lext/mods/gameserver/model/manor/CropProcure;
  #657 = Utf8               pCurrent
  #658 = Utf8               Ljava/util/List;
  #659 = Utf8               pNext
  #660 = Utf8               current
  #661 = Utf8               castle
  #662 = Utf8               Lext/mods/gameserver/model/residence/castle/Castle;
  #663 = Utf8               stProcure
  #664 = Utf8               Ljava/sql/PreparedStatement;
  #665 = Utf8               stProduction
  #666 = Utf8               con
  #667 = Utf8               Ljava/sql/Connection;
  #668 = Utf8               e
  #669 = Utf8               Ljava/lang/Exception;
  #670 = Utf8               this
  #671 = Utf8               currentTime
  #672 = Utf8               hour
  #673 = Utf8               min
  #674 = Utf8               maintenanceMin
  #675 = Utf8               LocalVariableTypeTable
  #676 = Utf8               Ljava/util/List<Lext/mods/gameserver/model/manor/SeedProduction;>;
  #677 = Utf8               Ljava/util/List<Lext/mods/gameserver/model/manor/CropProcure;>;
  #678 = Utf8               StackMapTable
  #679 = Utf8               parseDocument
  #680 = Utf8               (Lorg/w3c/dom/Document;Ljava/nio/file/Path;)V
  #681 = Utf8               doc
  #682 = Utf8               Lorg/w3c/dom/Document;
  #683 = Utf8               path
  #684 = Utf8               Ljava/nio/file/Path;
  #685 = Utf8               changeMode
  #686 = Utf8               seed
  #687 = Utf8               Lext/mods/gameserver/model/manor/Seed;
  #688 = Utf8               count
  #689 = Utf8               s
  #690 = Utf8               cr
  #691 = Utf8               production
  #692 = Utf8               procure
  #693 = Utf8               owner
  #694 = Utf8               Lext/mods/gameserver/model/pledge/Clan;
  #695 = Utf8               J
  #696 = Utf8               nextProduction
  #697 = Utf8               nextProcure
  #698 = Utf8               clanLeader
  #699 = Utf8               Lext/mods/gameserver/model/pledge/ClanMember;
  #700 = Utf8               manorCost
  #701 = Utf8               slots
  #702 = Utf8               cwh
  #703 = Utf8               Lext/mods/gameserver/model/itemcontainer/ItemContainer;
  #704 = Utf8               setNextSeedProduction
  #705 = Utf8               (Ljava/util/List;I)V
  #706 = Utf8               (Ljava/util/List<Lext/mods/gameserver/model/manor/SeedProduction;>;I)V
  #707 = Utf8               setNextCropProcure
  #708 = Utf8               (Ljava/util/List<Lext/mods/gameserver/model/manor/CropProcure;>;I)V
  #709 = Utf8               updateCurrentProduction
  #710 = Utf8               (ILjava/util/Collection;)V
  #711 = Utf8               ps
  #712 = Utf8               items
  #713 = Utf8               Ljava/util/Collection;
  #714 = Utf8               Ljava/util/Collection<Lext/mods/gameserver/model/manor/SeedProduction;>;
  #715 = Utf8               (ILjava/util/Collection<Lext/mods/gameserver/model/manor/SeedProduction;>;)V
  #716 = Utf8               updateCurrentProcure
  #717 = Utf8               Ljava/util/Collection<Lext/mods/gameserver/model/manor/CropProcure;>;
  #718 = Utf8               (ILjava/util/Collection<Lext/mods/gameserver/model/manor/CropProcure;>;)V
  #719 = Utf8               nextPeriod
  #720 = Utf8               (IZ)Ljava/util/List<Lext/mods/gameserver/model/manor/SeedProduction;>;
  #721 = Utf8               getSeedProduct
  #722 = Utf8               (IIZ)Lext/mods/gameserver/model/manor/SeedProduction;
  #723 = Utf8               (IZ)Ljava/util/List<Lext/mods/gameserver/model/manor/CropProcure;>;
  #724 = Utf8               (IIZ)Lext/mods/gameserver/model/manor/CropProcure;
  #725 = Utf8               cropId
  #726 = Utf8               crops
  #727 = Utf8               total
  #728 = Utf8               entry
  #729 = Utf8               Ljava/util/Map$Entry;
  #730 = Utf8               ip
  #731 = Utf8               dp
  #732 = Utf8               is
  #733 = Utf8               ds
  #734 = Utf8               Ljava/util/Map$Entry<Ljava/lang/Integer;Ljava/util/List<Lext/mods/gameserver/model/manor/SeedProduction;>;>;
  #735 = Utf8               Ljava/util/Map$Entry<Ljava/lang/Integer;Ljava/util/List<Lext/mods/gameserver/model/manor/CropProcure;>;>;
  #736 = Utf8               resetManorData
  #737 = Utf8               isUnderMaintenance
  #738 = Utf8               isManorApproved
  #739 = Utf8               isModifiablePeriod
  #740 = Utf8               getCurrentModeName
  #741 = Utf8               getNextModeChange
  #742 = Utf8               getCrops
  #743 = Utf8               seeds
  #744 = Utf8               cropIds
  #745 = Utf8               Ljava/util/List<Lext/mods/gameserver/model/manor/Seed;>;
  #746 = Utf8               Ljava/util/List<Ljava/lang/Integer;>;
  #747 = Utf8               ()Ljava/util/List<Lext/mods/gameserver/model/manor/Seed;>;
  #748 = Utf8               getSeedsForCastle
  #749 = Utf8               (I)Ljava/util/Set;
  #750 = Utf8               (I)Ljava/util/Set<Lext/mods/gameserver/model/manor/Seed;>;
  #751 = Utf8               getCropIds
  #752 = Utf8               ()Ljava/util/Set<Ljava/lang/Integer;>;
  #753 = Utf8               (II)Lext/mods/gameserver/model/manor/Seed;
  #754 = Utf8               getSeedRewardByCrop
  #755 = Utf8               (II)I
  #756 = Utf8               rewardId
  #757 = Utf8               ()Lext/mods/gameserver/data/manager/CastleManorManager;
  #758 = Utf8               lambda$getSeedByCrop$1
  #759 = Utf8               (ILext/mods/gameserver/model/manor/Seed;)Z
  #760 = Utf8               lambda$getSeedByCrop$0
  #761 = Utf8               (IILext/mods/gameserver/model/manor/Seed;)Z
  #762 = Utf8               lambda$getSeedsForCastle$0
  #763 = Utf8               lambda$parseDocument$0
  #764 = Utf8               (Lorg/w3c/dom/Node;)V
  #765 = Utf8               listNode
  #766 = Utf8               Lorg/w3c/dom/Node;
  #767 = Utf8               lambda$parseDocument$1
  #768 = Utf8               manorNode
  #769 = Utf8               lambda$parseDocument$2
  #770 = Utf8               (ILorg/w3c/dom/Node;)V
  #771 = Utf8               cropNode
  #772 = Utf8               Lext/mods/commons/data/StatSet;
  #773 = Utf8               SourceFile
  #774 = Utf8               CastleManorManager.java
  #775 = Utf8               NestMembers
  #776 = Utf8               BootstrapMethods
  #777 = MethodType         #6            //  ()V
  #778 = MethodHandle       5:#393        // REF_invokeVirtual ext/mods/gameserver/data/manager/CastleManorManager.storeMe:()Z
  #779 = MethodType         #61           //  (Ljava/lang/Object;)V
  #780 = MethodHandle       5:#781        // REF_invokeVirtual ext/mods/gameserver/data/manager/CastleManorManager.lambda$parseDocument$0:(Lorg/w3c/dom/Node;)V
  #781 = Methodref          #14.#782      // ext/mods/gameserver/data/manager/CastleManorManager.lambda$parseDocument$0:(Lorg/w3c/dom/Node;)V
  #782 = NameAndType        #763:#764     // lambda$parseDocument$0:(Lorg/w3c/dom/Node;)V
  #783 = MethodType         #764          //  (Lorg/w3c/dom/Node;)V
  #784 = MethodHandle       5:#785        // REF_invokeVirtual ext/mods/gameserver/data/manager/CastleManorManager.changeMode:()V
  #785 = Methodref          #14.#786      // ext/mods/gameserver/data/manager/CastleManorManager.changeMode:()V
  #786 = NameAndType        #685:#6       // changeMode:()V
  #787 = MethodType         #161          //  (Ljava/lang/Object;)Z
  #788 = MethodHandle       6:#789        // REF_invokeStatic ext/mods/gameserver/data/manager/CastleManorManager.lambda$getSeedsForCastle$0:(ILext/mods/gameserver/model/manor/Seed;)Z
  #789 = Methodref          #14.#790      // ext/mods/gameserver/data/manager/CastleManorManager.lambda$getSeedsForCastle$0:(ILext/mods/gameserver/model/manor/Seed;)Z
  #790 = NameAndType        #762:#759     // lambda$getSeedsForCastle$0:(ILext/mods/gameserver/model/manor/Seed;)Z
  #791 = MethodType         #792          //  (Lext/mods/gameserver/model/manor/Seed;)Z
  #792 = Utf8               (Lext/mods/gameserver/model/manor/Seed;)Z
  #793 = MethodType         #327          //  (Ljava/lang/Object;)Ljava/lang/Object;
  #794 = MethodHandle       5:#527        // REF_invokeVirtual ext/mods/gameserver/model/manor/Seed.getCropId:()I
  #795 = MethodType         #796          //  (Lext/mods/gameserver/model/manor/Seed;)Ljava/lang/Integer;
  #796 = Utf8               (Lext/mods/gameserver/model/manor/Seed;)Ljava/lang/Integer;
  #797 = MethodHandle       6:#798        // REF_invokeStatic ext/mods/gameserver/data/manager/CastleManorManager.lambda$getSeedByCrop$0:(IILext/mods/gameserver/model/manor/Seed;)Z
  #798 = Methodref          #14.#799      // ext/mods/gameserver/data/manager/CastleManorManager.lambda$getSeedByCrop$0:(IILext/mods/gameserver/model/manor/Seed;)Z
  #799 = NameAndType        #760:#761     // lambda$getSeedByCrop$0:(IILext/mods/gameserver/model/manor/Seed;)Z
  #800 = MethodHandle       6:#801        // REF_invokeStatic ext/mods/gameserver/data/manager/CastleManorManager.lambda$getSeedByCrop$1:(ILext/mods/gameserver/model/manor/Seed;)Z
  #801 = Methodref          #14.#802      // ext/mods/gameserver/data/manager/CastleManorManager.lambda$getSeedByCrop$1:(ILext/mods/gameserver/model/manor/Seed;)Z
  #802 = NameAndType        #758:#759     // lambda$getSeedByCrop$1:(ILext/mods/gameserver/model/manor/Seed;)Z
  #803 = MethodHandle       5:#804        // REF_invokeVirtual ext/mods/gameserver/data/manager/CastleManorManager.lambda$parseDocument$1:(Lorg/w3c/dom/Node;)V
  #804 = Methodref          #14.#805      // ext/mods/gameserver/data/manager/CastleManorManager.lambda$parseDocument$1:(Lorg/w3c/dom/Node;)V
  #805 = NameAndType        #767:#764     // lambda$parseDocument$1:(Lorg/w3c/dom/Node;)V
  #806 = MethodHandle       5:#807        // REF_invokeVirtual ext/mods/gameserver/data/manager/CastleManorManager.lambda$parseDocument$2:(ILorg/w3c/dom/Node;)V
  #807 = Methodref          #14.#808      // ext/mods/gameserver/data/manager/CastleManorManager.lambda$parseDocument$2:(ILorg/w3c/dom/Node;)V
  #808 = NameAndType        #769:#770     // lambda$parseDocument$2:(ILorg/w3c/dom/Node;)V
  #809 = MethodHandle       6:#810        // REF_invokeStatic java/lang/invoke/LambdaMetafactory.metafactory:(Ljava/lang/invoke/MethodHandles$Lookup;Ljava/lang/String;Ljava/lang/invoke/MethodType;Ljava/lang/invoke/MethodType;Ljava/lang/invoke/MethodHandle;Ljava/lang/invoke/MethodType;)Ljava/lang/invoke/CallSite;
  #810 = Methodref          #811.#812     // java/lang/invoke/LambdaMetafactory.metafactory:(Ljava/lang/invoke/MethodHandles$Lookup;Ljava/lang/String;Ljava/lang/invoke/MethodType;Ljava/lang/invoke/MethodType;Ljava/lang/invoke/MethodHandle;Ljava/lang/invoke/MethodType;)Ljava/lang/invoke/CallSite;
  #811 = Class              #813          // java/lang/invoke/LambdaMetafactory
  #812 = NameAndType        #814:#815     // metafactory:(Ljava/lang/invoke/MethodHandles$Lookup;Ljava/lang/String;Ljava/lang/invoke/MethodType;Ljava/lang/invoke/MethodType;Ljava/lang/invoke/MethodHandle;Ljava/lang/invoke/MethodType;)Ljava/lang/invoke/CallSite;
  #813 = Utf8               java/lang/invoke/LambdaMetafactory
  #814 = Utf8               metafactory
  #815 = Utf8               (Ljava/lang/invoke/MethodHandles$Lookup;Ljava/lang/String;Ljava/lang/invoke/MethodType;Ljava/lang/invoke/MethodType;Ljava/lang/invoke/MethodHandle;Ljava/lang/invoke/MethodType;)Ljava/lang/invoke/CallSite;
  #816 = Utf8               InnerClasses
  #817 = Utf8               Entry
  #818 = Utf8               SingletonHolder
  #819 = Class              #820          // java/lang/invoke/MethodHandles$Lookup
  #820 = Utf8               java/lang/invoke/MethodHandles$Lookup
  #821 = Class              #822          // java/lang/invoke/MethodHandles
  #822 = Utf8               java/lang/invoke/MethodHandles
  #823 = Utf8               Lookup
{
  protected ext.mods.gameserver.data.manager.CastleManorManager();
    descriptor: ()V
    flags: (0x0004) ACC_PROTECTED
    Code:
      stack=8, locals=13, args_size=1
         0: aload_0
         1: invokespecial #1                  // Method java/lang/Object."<init>":()V
         4: aload_0
         5: getstatic     #7                  // Field ext/mods/gameserver/enums/ManorStatus.APPROVED:Lext/mods/gameserver/enums/ManorStatus;
         8: putfield      #13                 // Field _mode:Lext/mods/gameserver/enums/ManorStatus;
        11: aload_0
        12: aconst_null
        13: putfield      #18                 // Field _nextModeChange:Ljava/util/Calendar;
        16: aload_0
        17: new           #22                 // class java/util/HashMap
        20: dup
        21: invokespecial #24                 // Method java/util/HashMap."<init>":()V
        24: putfield      #25                 // Field _seeds:Ljava/util/Map;
        27: aload_0
        28: new           #22                 // class java/util/HashMap
        31: dup
        32: invokespecial #24                 // Method java/util/HashMap."<init>":()V
        35: putfield      #29                 // Field _procure:Ljava/util/Map;
        38: aload_0
        39: new           #22                 // class java/util/HashMap
        42: dup
        43: invokespecial #24                 // Method java/util/HashMap."<init>":()V
        46: putfield      #32                 // Field _procureNext:Ljava/util/Map;
        49: aload_0
        50: new           #22                 // class java/util/HashMap
        53: dup
        54: invokespecial #24                 // Method java/util/HashMap."<init>":()V
        57: putfield      #35                 // Field _production:Ljava/util/Map;
        60: aload_0
        61: new           #22                 // class java/util/HashMap
        64: dup
        65: invokespecial #24                 // Method java/util/HashMap."<init>":()V
        68: putfield      #38                 // Field _productionNext:Ljava/util/Map;
        71: getstatic     #41                 // Field ext/mods/Config.ALLOW_MANOR:Z
        74: ifne          93
        77: aload_0
        78: getstatic     #47                 // Field ext/mods/gameserver/enums/ManorStatus.DISABLED:Lext/mods/gameserver/enums/ManorStatus;
        81: putfield      #13                 // Field _mode:Lext/mods/gameserver/enums/ManorStatus;
        84: getstatic     #50                 // Field LOGGER:Lext/mods/commons/logging/CLogger;
        87: ldc           #54                 // String Manor system is deactivated.
        89: invokevirtual #56                 // Method ext/mods/commons/logging/CLogger.info:(Ljava/lang/Object;)V
        92: return
        93: aload_0
        94: invokevirtual #62                 // Method load:()V
        97: invokestatic  #65                 // Method ext/mods/commons/pool/ConnectionPool.getConnection:()Ljava/sql/Connection;
       100: astore_1
       101: aload_1
       102: ldc           #71                 // String SELECT * FROM castle_manor_production WHERE castle_id=?
       104: invokeinterface #73,  2           // InterfaceMethod java/sql/Connection.prepareStatement:(Ljava/lang/String;)Ljava/sql/PreparedStatement;
       109: astore_2
       110: aload_1
       111: ldc           #79                 // String SELECT * FROM castle_manor_procure WHERE castle_id=?
       113: invokeinterface #73,  2           // InterfaceMethod java/sql/Connection.prepareStatement:(Ljava/lang/String;)Ljava/sql/PreparedStatement;
       118: astore_3
       119: invokestatic  #81                 // Method ext/mods/gameserver/data/manager/CastleManager.getInstance:()Lext/mods/gameserver/data/manager/CastleManager;
       122: invokevirtual #87                 // Method ext/mods/gameserver/data/manager/CastleManager.getCastles:()Ljava/util/Collection;
       125: invokeinterface #91,  1           // InterfaceMethod java/util/Collection.iterator:()Ljava/util/Iterator;
       130: astore        4
       132: aload         4
       134: invokeinterface #97,  1           // InterfaceMethod java/util/Iterator.hasNext:()Z
       139: ifeq          608
       142: aload         4
       144: invokeinterface #103,  1          // InterfaceMethod java/util/Iterator.next:()Ljava/lang/Object;
       149: checkcast     #107                // class ext/mods/gameserver/model/residence/castle/Castle
       152: astore        5
       154: new           #109                // class java/util/ArrayList
       157: dup
       158: invokespecial #111                // Method java/util/ArrayList."<init>":()V
       161: astore        6
       163: new           #109                // class java/util/ArrayList
       166: dup
       167: invokespecial #111                // Method java/util/ArrayList."<init>":()V
       170: astore        7
       172: aload_2
       173: invokeinterface #112,  1          // InterfaceMethod java/sql/PreparedStatement.clearParameters:()V
       178: aload_2
       179: iconst_1
       180: aload         5
       182: invokevirtual #117                // Method ext/mods/gameserver/model/residence/castle/Castle.getId:()I
       185: invokeinterface #121,  3          // InterfaceMethod java/sql/PreparedStatement.setInt:(II)V
       190: aload_2
       191: invokeinterface #125,  1          // InterfaceMethod java/sql/PreparedStatement.executeQuery:()Ljava/sql/ResultSet;
       196: astore        8
       198: aload         8
       200: invokeinterface #129,  1          // InterfaceMethod java/sql/ResultSet.next:()Z
       205: ifeq          291
       208: new           #133                // class ext/mods/gameserver/model/manor/SeedProduction
       211: dup
       212: aload         8
       214: ldc           #135                // String seed_id
       216: invokeinterface #137,  2          // InterfaceMethod java/sql/ResultSet.getInt:(Ljava/lang/String;)I
       221: aload         8
       223: ldc           #141                // String amount
       225: invokeinterface #137,  2          // InterfaceMethod java/sql/ResultSet.getInt:(Ljava/lang/String;)I
       230: aload         8
       232: ldc           #143                // String price
       234: invokeinterface #137,  2          // InterfaceMethod java/sql/ResultSet.getInt:(Ljava/lang/String;)I
       239: aload         8
       241: ldc           #145                // String start_amount
       243: invokeinterface #137,  2          // InterfaceMethod java/sql/ResultSet.getInt:(Ljava/lang/String;)I
       248: invokespecial #147                // Method ext/mods/gameserver/model/manor/SeedProduction."<init>":(IIII)V
       251: astore        9
       253: aload         8
       255: ldc           #150                // String next_period
       257: invokeinterface #152,  2          // InterfaceMethod java/sql/ResultSet.getBoolean:(Ljava/lang/String;)Z
       262: ifeq          278
       265: aload         7
       267: aload         9
       269: invokeinterface #156,  2          // InterfaceMethod java/util/List.add:(Ljava/lang/Object;)Z
       274: pop
       275: goto          288
       278: aload         6
       280: aload         9
       282: invokeinterface #156,  2          // InterfaceMethod java/util/List.add:(Ljava/lang/Object;)Z
       287: pop
       288: goto          198
       291: aload         8
       293: ifnull        335
       296: aload         8
       298: invokeinterface #162,  1          // InterfaceMethod java/sql/ResultSet.close:()V
       303: goto          335
       306: astore        9
       308: aload         8
       310: ifnull        332
       313: aload         8
       315: invokeinterface #162,  1          // InterfaceMethod java/sql/ResultSet.close:()V
       320: goto          332
       323: astore        10
       325: aload         9
       327: aload         10
       329: invokevirtual #167                // Method java/lang/Throwable.addSuppressed:(Ljava/lang/Throwable;)V
       332: aload         9
       334: athrow
       335: aload_0
       336: getfield      #35                 // Field _production:Ljava/util/Map;
       339: aload         5
       341: invokevirtual #117                // Method ext/mods/gameserver/model/residence/castle/Castle.getId:()I
       344: invokestatic  #171                // Method java/lang/Integer.valueOf:(I)Ljava/lang/Integer;
       347: aload         6
       349: invokeinterface #177,  3          // InterfaceMethod java/util/Map.put:(Ljava/lang/Object;Ljava/lang/Object;)Ljava/lang/Object;
       354: pop
       355: aload_0
       356: getfield      #38                 // Field _productionNext:Ljava/util/Map;
       359: aload         5
       361: invokevirtual #117                // Method ext/mods/gameserver/model/residence/castle/Castle.getId:()I
       364: invokestatic  #171                // Method java/lang/Integer.valueOf:(I)Ljava/lang/Integer;
       367: aload         7
       369: invokeinterface #177,  3          // InterfaceMethod java/util/Map.put:(Ljava/lang/Object;Ljava/lang/Object;)Ljava/lang/Object;
       374: pop
       375: new           #109                // class java/util/ArrayList
       378: dup
       379: invokespecial #111                // Method java/util/ArrayList."<init>":()V
       382: astore        8
       384: new           #109                // class java/util/ArrayList
       387: dup
       388: invokespecial #111                // Method java/util/ArrayList."<init>":()V
       391: astore        9
       393: aload_3
       394: invokeinterface #112,  1          // InterfaceMethod java/sql/PreparedStatement.clearParameters:()V
       399: aload_3
       400: iconst_1
       401: aload         5
       403: invokevirtual #117                // Method ext/mods/gameserver/model/residence/castle/Castle.getId:()I
       406: invokeinterface #121,  3          // InterfaceMethod java/sql/PreparedStatement.setInt:(II)V
       411: aload_3
       412: invokeinterface #125,  1          // InterfaceMethod java/sql/PreparedStatement.executeQuery:()Ljava/sql/ResultSet;
       417: astore        10
       419: aload         10
       421: invokeinterface #129,  1          // InterfaceMethod java/sql/ResultSet.next:()Z
       426: ifeq          521
       429: new           #183                // class ext/mods/gameserver/model/manor/CropProcure
       432: dup
       433: aload         10
       435: ldc           #185                // String crop_id
       437: invokeinterface #137,  2          // InterfaceMethod java/sql/ResultSet.getInt:(Ljava/lang/String;)I
       442: aload         10
       444: ldc           #141                // String amount
       446: invokeinterface #137,  2          // InterfaceMethod java/sql/ResultSet.getInt:(Ljava/lang/String;)I
       451: aload         10
       453: ldc           #187                // String reward_type
       455: invokeinterface #137,  2          // InterfaceMethod java/sql/ResultSet.getInt:(Ljava/lang/String;)I
       460: aload         10
       462: ldc           #145                // String start_amount
       464: invokeinterface #137,  2          // InterfaceMethod java/sql/ResultSet.getInt:(Ljava/lang/String;)I
       469: aload         10
       471: ldc           #143                // String price
       473: invokeinterface #137,  2          // InterfaceMethod java/sql/ResultSet.getInt:(Ljava/lang/String;)I
       478: invokespecial #189                // Method ext/mods/gameserver/model/manor/CropProcure."<init>":(IIIII)V
       481: astore        11
       483: aload         10
       485: ldc           #150                // String next_period
       487: invokeinterface #152,  2          // InterfaceMethod java/sql/ResultSet.getBoolean:(Ljava/lang/String;)Z
       492: ifeq          508
       495: aload         9
       497: aload         11
       499: invokeinterface #156,  2          // InterfaceMethod java/util/List.add:(Ljava/lang/Object;)Z
       504: pop
       505: goto          518
       508: aload         8
       510: aload         11
       512: invokeinterface #156,  2          // InterfaceMethod java/util/List.add:(Ljava/lang/Object;)Z
       517: pop
       518: goto          419
       521: aload         10
       523: ifnull        565
       526: aload         10
       528: invokeinterface #162,  1          // InterfaceMethod java/sql/ResultSet.close:()V
       533: goto          565
       536: astore        11
       538: aload         10
       540: ifnull        562
       543: aload         10
       545: invokeinterface #162,  1          // InterfaceMethod java/sql/ResultSet.close:()V
       550: goto          562
       553: astore        12
       555: aload         11
       557: aload         12
       559: invokevirtual #167                // Method java/lang/Throwable.addSuppressed:(Ljava/lang/Throwable;)V
       562: aload         11
       564: athrow
       565: aload_0
       566: getfield      #29                 // Field _procure:Ljava/util/Map;
       569: aload         5
       571: invokevirtual #117                // Method ext/mods/gameserver/model/residence/castle/Castle.getId:()I
       574: invokestatic  #171                // Method java/lang/Integer.valueOf:(I)Ljava/lang/Integer;
       577: aload         8
       579: invokeinterface #177,  3          // InterfaceMethod java/util/Map.put:(Ljava/lang/Object;Ljava/lang/Object;)Ljava/lang/Object;
       584: pop
       585: aload_0
       586: getfield      #32                 // Field _procureNext:Ljava/util/Map;
       589: aload         5
       591: invokevirtual #117                // Method ext/mods/gameserver/model/residence/castle/Castle.getId:()I
       594: invokestatic  #171                // Method java/lang/Integer.valueOf:(I)Ljava/lang/Integer;
       597: aload         9
       599: invokeinterface #177,  3          // InterfaceMethod java/util/Map.put:(Ljava/lang/Object;Ljava/lang/Object;)Ljava/lang/Object;
       604: pop
       605: goto          132
       608: aload_3
       609: ifnull        648
       612: aload_3
       613: invokeinterface #192,  1          // InterfaceMethod java/sql/PreparedStatement.close:()V
       618: goto          648
       621: astore        4
       623: aload_3
       624: ifnull        645
       627: aload_3
       628: invokeinterface #192,  1          // InterfaceMethod java/sql/PreparedStatement.close:()V
       633: goto          645
       636: astore        5
       638: aload         4
       640: aload         5
       642: invokevirtual #167                // Method java/lang/Throwable.addSuppressed:(Ljava/lang/Throwable;)V
       645: aload         4
       647: athrow
       648: aload_2
       649: ifnull        685
       652: aload_2
       653: invokeinterface #192,  1          // InterfaceMethod java/sql/PreparedStatement.close:()V
       658: goto          685
       661: astore_3
       662: aload_2
       663: ifnull        683
       666: aload_2
       667: invokeinterface #192,  1          // InterfaceMethod java/sql/PreparedStatement.close:()V
       672: goto          683
       675: astore        4
       677: aload_3
       678: aload         4
       680: invokevirtual #167                // Method java/lang/Throwable.addSuppressed:(Ljava/lang/Throwable;)V
       683: aload_3
       684: athrow
       685: aload_1
       686: ifnull        720
       689: aload_1
       690: invokeinterface #193,  1          // InterfaceMethod java/sql/Connection.close:()V
       695: goto          720
       698: astore_2
       699: aload_1
       700: ifnull        718
       703: aload_1
       704: invokeinterface #193,  1          // InterfaceMethod java/sql/Connection.close:()V
       709: goto          718
       712: astore_3
       713: aload_2
       714: aload_3
       715: invokevirtual #167                // Method java/lang/Throwable.addSuppressed:(Ljava/lang/Throwable;)V
       718: aload_2
       719: athrow
       720: goto          733
       723: astore_1
       724: getstatic     #50                 // Field LOGGER:Lext/mods/commons/logging/CLogger;
       727: ldc           #196                // String Error restoring manor data.
       729: aload_1
       730: invokevirtual #198                // Method ext/mods/commons/logging/CLogger.error:(Ljava/lang/Object;Ljava/lang/Throwable;)V
       733: invokestatic  #202                // Method java/util/Calendar.getInstance:()Ljava/util/Calendar;
       736: astore_1
       737: aload_1
       738: bipush        11
       740: invokevirtual #207                // Method java/util/Calendar.get:(I)I
       743: istore_2
       744: aload_1
       745: bipush        12
       747: invokevirtual #207                // Method java/util/Calendar.get:(I)I
       750: istore_3
       751: getstatic     #211                // Field ext/mods/Config.MANOR_REFRESH_MIN:I
       754: getstatic     #215                // Field ext/mods/Config.MANOR_MAINTENANCE_MIN:I
       757: iadd
       758: istore        4
       760: iload_2
       761: getstatic     #218                // Field ext/mods/Config.MANOR_REFRESH_TIME:I
       764: if_icmplt     773
       767: iload_3
       768: iload         4
       770: if_icmpge     794
       773: iload_2
       774: getstatic     #221                // Field ext/mods/Config.MANOR_APPROVE_TIME:I
       777: if_icmplt     794
       780: iload_2
       781: getstatic     #221                // Field ext/mods/Config.MANOR_APPROVE_TIME:I
       784: if_icmpne     804
       787: iload_3
       788: getstatic     #224                // Field ext/mods/Config.MANOR_APPROVE_MIN:I
       791: if_icmpgt     804
       794: aload_0
       795: getstatic     #227                // Field ext/mods/gameserver/enums/ManorStatus.MODIFIABLE:Lext/mods/gameserver/enums/ManorStatus;
       798: putfield      #13                 // Field _mode:Lext/mods/gameserver/enums/ManorStatus;
       801: goto          831
       804: iload_2
       805: getstatic     #218                // Field ext/mods/Config.MANOR_REFRESH_TIME:I
       808: if_icmpne     831
       811: iload_3
       812: getstatic     #211                // Field ext/mods/Config.MANOR_REFRESH_MIN:I
       815: if_icmplt     831
       818: iload_3
       819: iload         4
       821: if_icmpge     831
       824: aload_0
       825: getstatic     #230                // Field ext/mods/gameserver/enums/ManorStatus.MAINTENANCE:Lext/mods/gameserver/enums/ManorStatus;
       828: putfield      #13                 // Field _mode:Lext/mods/gameserver/enums/ManorStatus;
       831: aload_0
       832: invokevirtual #233                // Method scheduleModeChange:()V
       835: aload_0
       836: invokedynamic #236,  0            // InvokeDynamic #0:run:(Lext/mods/gameserver/data/manager/CastleManorManager;)Ljava/lang/Runnable;
       841: getstatic     #240                // Field ext/mods/Config.MANOR_SAVE_PERIOD_RATE:I
       844: i2l
       845: getstatic     #240                // Field ext/mods/Config.MANOR_SAVE_PERIOD_RATE:I
       848: i2l
       849: invokestatic  #243                // Method ext/mods/commons/pool/ThreadPool.scheduleAtFixedRate:(Ljava/lang/Runnable;JJ)Ljava/util/concurrent/ScheduledFuture;
       852: pop
       853: getstatic     #50                 // Field LOGGER:Lext/mods/commons/logging/CLogger;
       856: ldc           #249                // String Current Manor mode is: {}.
       858: iconst_1
       859: anewarray     #2                  // class java/lang/Object
       862: dup
       863: iconst_0
       864: aload_0
       865: getfield      #13                 // Field _mode:Lext/mods/gameserver/enums/ManorStatus;
       868: invokevirtual #251                // Method ext/mods/gameserver/enums/ManorStatus.toString:()Ljava/lang/String;
       871: aastore
       872: invokevirtual #255                // Method ext/mods/commons/logging/CLogger.debug:(Ljava/lang/Object;[Ljava/lang/Object;)V
       875: return
      Exception table:
         from    to  target type
           198   291   306   Class java/lang/Throwable
           313   320   323   Class java/lang/Throwable
           419   521   536   Class java/lang/Throwable
           543   550   553   Class java/lang/Throwable
           119   608   621   Class java/lang/Throwable
           627   633   636   Class java/lang/Throwable
           110   648   661   Class java/lang/Throwable
           666   672   675   Class java/lang/Throwable
           101   685   698   Class java/lang/Throwable
           703   709   712   Class java/lang/Throwable
            97   720   723   Class java/lang/Exception
      LineNumberTable:
        line 84: 0
        line 72: 4
        line 74: 11
        line 76: 16
        line 78: 27
        line 79: 38
        line 80: 49
        line 81: 60
        line 85: 71
        line 87: 77
        line 88: 84
        line 89: 92
        line 92: 93
        line 94: 97
        line 95: 101
        line 96: 110
        line 98: 119
        line 100: 154
        line 101: 163
        line 103: 172
        line 104: 178
        line 106: 190
        line 108: 198
        line 110: 208
        line 111: 253
        line 112: 265
        line 114: 278
        line 115: 288
        line 116: 291
        line 106: 306
        line 117: 335
        line 118: 355
        line 120: 375
        line 121: 384
        line 123: 393
        line 124: 399
        line 126: 411
        line 128: 419
        line 130: 429
        line 131: 483
        line 132: 495
        line 134: 508
        line 135: 518
        line 136: 521
        line 126: 536
        line 137: 565
        line 138: 585
        line 139: 605
        line 140: 608
        line 94: 621
        line 140: 648
        line 94: 661
        line 140: 685
        line 94: 698
        line 144: 720
        line 141: 723
        line 143: 724
        line 146: 733
        line 147: 737
        line 148: 744
        line 149: 751
        line 151: 760
        line 152: 794
        line 153: 804
        line 154: 824
        line 156: 831
        line 158: 835
        line 160: 853
        line 161: 875
      LocalVariableTable:
        Start  Length  Slot  Name   Signature
          253      35     9    sp   Lext/mods/gameserver/model/manor/SeedProduction;
          198     137     8    rs   Ljava/sql/ResultSet;
          483      35    11    cp   Lext/mods/gameserver/model/manor/CropProcure;
          419     146    10    rs   Ljava/sql/ResultSet;
          163     442     6 pCurrent   Ljava/util/List;
          172     433     7 pNext   Ljava/util/List;
          384     221     8 current   Ljava/util/List;
          393     212     9  next   Ljava/util/List;
          154     451     5 castle   Lext/mods/gameserver/model/residence/castle/Castle;
          119     529     3 stProcure   Ljava/sql/PreparedStatement;
          110     575     2 stProduction   Ljava/sql/PreparedStatement;
          101     619     1   con   Ljava/sql/Connection;
          724       9     1     e   Ljava/lang/Exception;
            0     876     0  this   Lext/mods/gameserver/data/manager/CastleManorManager;
          737     139     1 currentTime   Ljava/util/Calendar;
          744     132     2  hour   I
          751     125     3   min   I
          760     116     4 maintenanceMin   I
      LocalVariableTypeTable:
        Start  Length  Slot  Name   Signature
          163     442     6 pCurrent   Ljava/util/List<Lext/mods/gameserver/model/manor/SeedProduction;>;
          172     433     7 pNext   Ljava/util/List<Lext/mods/gameserver/model/manor/SeedProduction;>;
          384     221     8 current   Ljava/util/List<Lext/mods/gameserver/model/manor/CropProcure;>;
          393     212     9  next   Ljava/util/List<Lext/mods/gameserver/model/manor/CropProcure;>;
      StackMapTable: number_of_entries = 37
        frame_type = 255 /* full_frame */
          offset_delta = 93
          locals = [ class ext/mods/gameserver/data/manager/CastleManorManager ]
          stack = []
        frame_type = 255 /* full_frame */
          offset_delta = 38
          locals = [ class ext/mods/gameserver/data/manager/CastleManorManager, class java/sql/Connection, class java/sql/PreparedStatement, class java/sql/PreparedStatement, class java/util/Iterator ]
          stack = []
        frame_type = 255 /* full_frame */
          offset_delta = 65
          locals = [ class ext/mods/gameserver/data/manager/CastleManorManager, class java/sql/Connection, class java/sql/PreparedStatement, class java/sql/PreparedStatement, class java/util/Iterator, class ext/mods/gameserver/model/residence/castle/Castle, class java/util/List, class java/util/List, class java/sql/ResultSet ]
          stack = []
        frame_type = 252 /* append */
          offset_delta = 79
          locals = [ class ext/mods/gameserver/model/manor/SeedProduction ]
        frame_type = 250 /* chop */
          offset_delta = 9
        frame_type = 2 /* same */
        frame_type = 78 /* same_locals_1_stack_item */
          stack = [ class java/lang/Throwable ]
        frame_type = 255 /* full_frame */
          offset_delta = 16
          locals = [ class ext/mods/gameserver/data/manager/CastleManorManager, class java/sql/Connection, class java/sql/PreparedStatement, class java/sql/PreparedStatement, class java/util/Iterator, class ext/mods/gameserver/model/residence/castle/Castle, class java/util/List, class java/util/List, class java/sql/ResultSet, class java/lang/Throwable ]
          stack = [ class java/lang/Throwable ]
        frame_type = 8 /* same */
        frame_type = 249 /* chop */
          offset_delta = 2
        frame_type = 254 /* append */
          offset_delta = 83
          locals = [ class java/util/List, class java/util/List, class java/sql/ResultSet ]
        frame_type = 252 /* append */
          offset_delta = 88
          locals = [ class ext/mods/gameserver/model/manor/CropProcure ]
        frame_type = 250 /* chop */
          offset_delta = 9
        frame_type = 2 /* same */
        frame_type = 78 /* same_locals_1_stack_item */
          stack = [ class java/lang/Throwable ]
        frame_type = 255 /* full_frame */
          offset_delta = 16
          locals = [ class ext/mods/gameserver/data/manager/CastleManorManager, class java/sql/Connection, class java/sql/PreparedStatement, class java/sql/PreparedStatement, class java/util/Iterator, class ext/mods/gameserver/model/residence/castle/Castle, class java/util/List, class java/util/List, class java/util/List, class java/util/List, class java/sql/ResultSet, class java/lang/Throwable ]
          stack = [ class java/lang/Throwable ]
        frame_type = 8 /* same */
        frame_type = 249 /* chop */
          offset_delta = 2
        frame_type = 255 /* full_frame */
          offset_delta = 42
          locals = [ class ext/mods/gameserver/data/manager/CastleManorManager, class java/sql/Connection, class java/sql/PreparedStatement, class java/sql/PreparedStatement ]
          stack = []
        frame_type = 76 /* same_locals_1_stack_item */
          stack = [ class java/lang/Throwable ]
        frame_type = 255 /* full_frame */
          offset_delta = 14
          locals = [ class ext/mods/gameserver/data/manager/CastleManorManager, class java/sql/Connection, class java/sql/PreparedStatement, class java/sql/PreparedStatement, class java/lang/Throwable ]
          stack = [ class java/lang/Throwable ]
        frame_type = 8 /* same */
        frame_type = 249 /* chop */
          offset_delta = 2
        frame_type = 76 /* same_locals_1_stack_item */
          stack = [ class java/lang/Throwable ]
        frame_type = 255 /* full_frame */
          offset_delta = 13
          locals = [ class ext/mods/gameserver/data/manager/CastleManorManager, class java/sql/Connection, class java/sql/PreparedStatement, class java/lang/Throwable ]
          stack = [ class java/lang/Throwable ]
        frame_type = 7 /* same */
        frame_type = 249 /* chop */
          offset_delta = 1
        frame_type = 76 /* same_locals_1_stack_item */
          stack = [ class java/lang/Throwable ]
        frame_type = 255 /* full_frame */
          offset_delta = 13
          locals = [ class ext/mods/gameserver/data/manager/CastleManorManager, class java/sql/Connection, class java/lang/Throwable ]
          stack = [ class java/lang/Throwable ]
        frame_type = 5 /* same */
        frame_type = 249 /* chop */
          offset_delta = 1
        frame_type = 66 /* same_locals_1_stack_item */
          stack = [ class java/lang/Exception ]
        frame_type = 9 /* same */
        frame_type = 255 /* full_frame */
          offset_delta = 39
          locals = [ class ext/mods/gameserver/data/manager/CastleManorManager, class java/util/Calendar, int, int, int ]
          stack = []
        frame_type = 20 /* same */
        frame_type = 9 /* same */
        frame_type = 26 /* same */

  public void load();
    descriptor: ()V
    flags: (0x0001) ACC_PUBLIC
    Code:
      stack=6, locals=1, args_size=1
         0: aload_0
         1: ldc_w         #259                // String xml/manors.xml
         4: invokevirtual #261                // Method parseDataFile:(Ljava/lang/String;)V
         7: getstatic     #50                 // Field LOGGER:Lext/mods/commons/logging/CLogger;
        10: ldc_w         #265                // String Loaded {} seeds.
        13: iconst_1
        14: anewarray     #2                  // class java/lang/Object
        17: dup
        18: iconst_0
        19: aload_0
        20: getfield      #25                 // Field _seeds:Ljava/util/Map;
        23: invokeinterface #267,  1          // InterfaceMethod java/util/Map.size:()I
        28: invokestatic  #171                // Method java/lang/Integer.valueOf:(I)Ljava/lang/Integer;
        31: aastore
        32: invokevirtual #270                // Method ext/mods/commons/logging/CLogger.info:(Ljava/lang/Object;[Ljava/lang/Object;)V
        35: return
      LineNumberTable:
        line 166: 0
        line 167: 7
        line 168: 35
      LocalVariableTable:
        Start  Length  Slot  Name   Signature
            0      36     0  this   Lext/mods/gameserver/data/manager/CastleManorManager;

  public void parseDocument(org.w3c.dom.Document, java.nio.file.Path);
    descriptor: (Lorg/w3c/dom/Document;Ljava/nio/file/Path;)V
    flags: (0x0001) ACC_PUBLIC
    Code:
      stack=4, locals=3, args_size=3
         0: aload_0
         1: aload_1
         2: ldc_w         #272                // String list
         5: aload_0
         6: invokedynamic #274,  0            // InvokeDynamic #1:accept:(Lext/mods/gameserver/data/manager/CastleManorManager;)Ljava/util/function/Consumer;
        11: invokevirtual #278                // Method forEach:(Lorg/w3c/dom/Node;Ljava/lang/String;Ljava/util/function/Consumer;)V
        14: return
      LineNumberTable:
        line 173: 0
        line 184: 14
      LocalVariableTable:
        Start  Length  Slot  Name   Signature
            0      15     0  this   Lext/mods/gameserver/data/manager/CastleManorManager;
            0      15     1   doc   Lorg/w3c/dom/Document;
            0      15     2  path   Ljava/nio/file/Path;

  public final void changeMode();
    descriptor: ()V
    flags: (0x0011) ACC_PUBLIC, ACC_FINAL
    Code:
      stack=6, locals=12, args_size=1
         0: getstatic     #285                // Field ext/mods/gameserver/data/manager/CastleManorManager$1.$SwitchMap$ext$mods$gameserver$enums$ManorStatus:[I
         3: aload_0
         4: getfield      #13                 // Field _mode:Lext/mods/gameserver/enums/ManorStatus;
         7: invokevirtual #291                // Method ext/mods/gameserver/enums/ManorStatus.ordinal:()I
        10: iaload
        11: tableswitch   { // 1 to 3

                       1: 660

                       2: 571

                       3: 36
                 default: 920
            }
        36: aload_0
        37: getstatic     #230                // Field ext/mods/gameserver/enums/ManorStatus.MAINTENANCE:Lext/mods/gameserver/enums/ManorStatus;
        40: putfield      #13                 // Field _mode:Lext/mods/gameserver/enums/ManorStatus;
        43: invokestatic  #81                 // Method ext/mods/gameserver/data/manager/CastleManager.getInstance:()Lext/mods/gameserver/data/manager/CastleManager;
        46: invokevirtual #87                 // Method ext/mods/gameserver/data/manager/CastleManager.getCastles:()Ljava/util/Collection;
        49: invokeinterface #91,  1           // InterfaceMethod java/util/Collection.iterator:()Ljava/util/Iterator;
        54: astore_1
        55: aload_1
        56: invokeinterface #97,  1           // InterfaceMethod java/util/Iterator.hasNext:()Z
        61: ifeq          563
        64: aload_1
        65: invokeinterface #103,  1          // InterfaceMethod java/util/Iterator.next:()Ljava/lang/Object;
        70: checkcast     #107                // class ext/mods/gameserver/model/residence/castle/Castle
        73: astore_2
        74: invokestatic  #313                // Method ext/mods/gameserver/data/sql/ClanTable.getInstance:()Lext/mods/gameserver/data/sql/ClanTable;
        77: aload_2
        78: invokevirtual #318                // Method ext/mods/gameserver/model/residence/castle/Castle.getOwnerId:()I
        81: invokevirtual #321                // Method ext/mods/gameserver/data/sql/ClanTable.getClan:(I)Lext/mods/gameserver/model/pledge/Clan;
        84: astore_3
        85: aload_3
        86: ifnonnull     92
        89: goto          55
        92: lconst_0
        93: lstore        4
        95: aload_0
        96: getfield      #29                 // Field _procure:Ljava/util/Map;
        99: aload_2
       100: invokevirtual #117                // Method ext/mods/gameserver/model/residence/castle/Castle.getId:()I
       103: invokestatic  #171                // Method java/lang/Integer.valueOf:(I)Ljava/lang/Integer;
       106: invokeinterface #325,  2          // InterfaceMethod java/util/Map.get:(Ljava/lang/Object;)Ljava/lang/Object;
       111: checkcast     #157                // class java/util/List
       114: invokeinterface #328,  1          // InterfaceMethod java/util/List.iterator:()Ljava/util/Iterator;
       119: astore        6
       121: aload         6
       123: invokeinterface #97,  1           // InterfaceMethod java/util/Iterator.hasNext:()Z
       128: ifeq          266
       131: aload         6
       133: invokeinterface #103,  1          // InterfaceMethod java/util/Iterator.next:()Ljava/lang/Object;
       138: checkcast     #183                // class ext/mods/gameserver/model/manor/CropProcure
       141: astore        7
       143: aload         7
       145: invokevirtual #329                // Method ext/mods/gameserver/model/manor/CropProcure.getStartAmount:()I
       148: ifle          263
       151: aload         7
       153: invokevirtual #329                // Method ext/mods/gameserver/model/manor/CropProcure.getStartAmount:()I
       156: aload         7
       158: invokevirtual #332                // Method ext/mods/gameserver/model/manor/CropProcure.getAmount:()I
       161: if_icmpeq     238
       164: aload         7
       166: invokevirtual #329                // Method ext/mods/gameserver/model/manor/CropProcure.getStartAmount:()I
       169: aload         7
       171: invokevirtual #332                // Method ext/mods/gameserver/model/manor/CropProcure.getAmount:()I
       174: isub
       175: i2d
       176: ldc2_w        #335                // double 0.9d
       179: dmul
       180: d2i
       181: istore        8
       183: iload         8
       185: iconst_1
       186: if_icmpge     202
       189: bipush        99
       191: invokestatic  #337                // Method ext/mods/commons/random/Rnd.nextInt:(I)I
       194: bipush        90
       196: if_icmpge     202
       199: iconst_1
       200: istore        8
       202: iload         8
       204: ifle          238
       207: aload_0
       208: aload         7
       210: invokevirtual #342                // Method ext/mods/gameserver/model/manor/CropProcure.getId:()I
       213: invokevirtual #343                // Method getSeedByCrop:(I)Lext/mods/gameserver/model/manor/Seed;
       216: astore        9
       218: aload         9
       220: ifnull        238
       223: aload_3
       224: invokevirtual #347                // Method ext/mods/gameserver/model/pledge/Clan.getWarehouse:()Lext/mods/gameserver/model/itemcontainer/ItemContainer;
       227: aload         9
       229: invokevirtual #353                // Method ext/mods/gameserver/model/manor/Seed.getMatureId:()I
       232: iload         8
       234: invokevirtual #358                // Method ext/mods/gameserver/model/itemcontainer/ItemContainer.addItem:(II)Lext/mods/gameserver/model/item/instance/ItemInstance;
       237: pop
       238: aload         7
       240: invokevirtual #332                // Method ext/mods/gameserver/model/manor/CropProcure.getAmount:()I
       243: ifle          263
       246: lload         4
       248: aload         7
       250: invokevirtual #332                // Method ext/mods/gameserver/model/manor/CropProcure.getAmount:()I
       253: aload         7
       255: invokevirtual #364                // Method ext/mods/gameserver/model/manor/CropProcure.getPrice:()I
       258: imul
       259: i2l
       260: ladd
       261: lstore        4
       263: goto          121
       266: aload_2
       267: lload         4
       269: invokevirtual #367                // Method ext/mods/gameserver/model/residence/castle/Castle.riseSeedIncome:(J)V
       272: aload_0
       273: getfield      #38                 // Field _productionNext:Ljava/util/Map;
       276: aload_2
       277: invokevirtual #117                // Method ext/mods/gameserver/model/residence/castle/Castle.getId:()I
       280: invokestatic  #171                // Method java/lang/Integer.valueOf:(I)Ljava/lang/Integer;
       283: invokeinterface #325,  2          // InterfaceMethod java/util/Map.get:(Ljava/lang/Object;)Ljava/lang/Object;
       288: checkcast     #157                // class java/util/List
       291: astore        6
       293: aload_0
       294: getfield      #32                 // Field _procureNext:Ljava/util/Map;
       297: aload_2
       298: invokevirtual #117                // Method ext/mods/gameserver/model/residence/castle/Castle.getId:()I
       301: invokestatic  #171                // Method java/lang/Integer.valueOf:(I)Ljava/lang/Integer;
       304: invokeinterface #325,  2          // InterfaceMethod java/util/Map.get:(Ljava/lang/Object;)Ljava/lang/Object;
       309: checkcast     #157                // class java/util/List
       312: astore        7
       314: aload_0
       315: getfield      #35                 // Field _production:Ljava/util/Map;
       318: aload_2
       319: invokevirtual #117                // Method ext/mods/gameserver/model/residence/castle/Castle.getId:()I
       322: invokestatic  #171                // Method java/lang/Integer.valueOf:(I)Ljava/lang/Integer;
       325: aload         6
       327: invokeinterface #177,  3          // InterfaceMethod java/util/Map.put:(Ljava/lang/Object;Ljava/lang/Object;)Ljava/lang/Object;
       332: pop
       333: aload_0
       334: getfield      #29                 // Field _procure:Ljava/util/Map;
       337: aload_2
       338: invokevirtual #117                // Method ext/mods/gameserver/model/residence/castle/Castle.getId:()I
       341: invokestatic  #171                // Method java/lang/Integer.valueOf:(I)Ljava/lang/Integer;
       344: aload         7
       346: invokeinterface #177,  3          // InterfaceMethod java/util/Map.put:(Ljava/lang/Object;Ljava/lang/Object;)Ljava/lang/Object;
       351: pop
       352: aload_2
       353: invokevirtual #371                // Method ext/mods/gameserver/model/residence/castle/Castle.getTreasury:()J
       356: aload_0
       357: aload_2
       358: invokevirtual #117                // Method ext/mods/gameserver/model/residence/castle/Castle.getId:()I
       361: iconst_0
       362: invokevirtual #374                // Method getManorCost:(IZ)J
       365: lcmp
       366: ifge          412
       369: aload_0
       370: getfield      #38                 // Field _productionNext:Ljava/util/Map;
       373: aload_2
       374: invokevirtual #117                // Method ext/mods/gameserver/model/residence/castle/Castle.getId:()I
       377: invokestatic  #171                // Method java/lang/Integer.valueOf:(I)Ljava/lang/Integer;
       380: invokestatic  #378                // Method java/util/Collections.emptyList:()Ljava/util/List;
       383: invokeinterface #177,  3          // InterfaceMethod java/util/Map.put:(Ljava/lang/Object;Ljava/lang/Object;)Ljava/lang/Object;
       388: pop
       389: aload_0
       390: getfield      #32                 // Field _procureNext:Ljava/util/Map;
       393: aload_2
       394: invokevirtual #117                // Method ext/mods/gameserver/model/residence/castle/Castle.getId:()I
       397: invokestatic  #171                // Method java/lang/Integer.valueOf:(I)Ljava/lang/Integer;
       400: invokestatic  #378                // Method java/util/Collections.emptyList:()Ljava/util/List;
       403: invokeinterface #177,  3          // InterfaceMethod java/util/Map.put:(Ljava/lang/Object;Ljava/lang/Object;)Ljava/lang/Object;
       408: pop
       409: goto          560
       412: new           #109                // class java/util/ArrayList
       415: dup
       416: aload         6
       418: invokespecial #384                // Method java/util/ArrayList."<init>":(Ljava/util/Collection;)V
       421: astore        8
       423: aload         8
       425: invokeinterface #328,  1          // InterfaceMethod java/util/List.iterator:()Ljava/util/Iterator;
       430: astore        9
       432: aload         9
       434: invokeinterface #97,  1           // InterfaceMethod java/util/Iterator.hasNext:()Z
       439: ifeq          467
       442: aload         9
       444: invokeinterface #103,  1          // InterfaceMethod java/util/Iterator.next:()Ljava/lang/Object;
       449: checkcast     #133                // class ext/mods/gameserver/model/manor/SeedProduction
       452: astore        10
       454: aload         10
       456: aload         10
       458: invokevirtual #387                // Method ext/mods/gameserver/model/manor/SeedProduction.getStartAmount:()I
       461: invokevirtual #388                // Method ext/mods/gameserver/model/manor/SeedProduction.setAmount:(I)V
       464: goto          432
       467: aload_0
       468: getfield      #38                 // Field _productionNext:Ljava/util/Map;
       471: aload_2
       472: invokevirtual #117                // Method ext/mods/gameserver/model/residence/castle/Castle.getId:()I
       475: invokestatic  #171                // Method java/lang/Integer.valueOf:(I)Ljava/lang/Integer;
       478: aload         8
       480: invokeinterface #177,  3          // InterfaceMethod java/util/Map.put:(Ljava/lang/Object;Ljava/lang/Object;)Ljava/lang/Object;
       485: pop
       486: new           #109                // class java/util/ArrayList
       489: dup
       490: aload         7
       492: invokespecial #384                // Method java/util/ArrayList."<init>":(Ljava/util/Collection;)V
       495: astore        9
       497: aload         9
       499: invokeinterface #328,  1          // InterfaceMethod java/util/List.iterator:()Ljava/util/Iterator;
       504: astore        10
       506: aload         10
       508: invokeinterface #97,  1           // InterfaceMethod java/util/Iterator.hasNext:()Z
       513: ifeq          541
       516: aload         10
       518: invokeinterface #103,  1          // InterfaceMethod java/util/Iterator.next:()Ljava/lang/Object;
       523: checkcast     #183                // class ext/mods/gameserver/model/manor/CropProcure
       526: astore        11
       528: aload         11
       530: aload         11
       532: invokevirtual #329                // Method ext/mods/gameserver/model/manor/CropProcure.getStartAmount:()I
       535: invokevirtual #392                // Method ext/mods/gameserver/model/manor/CropProcure.setAmount:(I)V
       538: goto          506
       541: aload_0
       542: getfield      #32                 // Field _procureNext:Ljava/util/Map;
       545: aload_2
       546: invokevirtual #117                // Method ext/mods/gameserver/model/residence/castle/Castle.getId:()I
       549: invokestatic  #171                // Method java/lang/Integer.valueOf:(I)Ljava/lang/Integer;
       552: aload         9
       554: invokeinterface #177,  3          // InterfaceMethod java/util/Map.put:(Ljava/lang/Object;Ljava/lang/Object;)Ljava/lang/Object;
       559: pop
       560: goto          55
       563: aload_0
       564: invokevirtual #393                // Method storeMe:()Z
       567: pop
       568: goto          920
       571: invokestatic  #81                 // Method ext/mods/gameserver/data/manager/CastleManager.getInstance:()Lext/mods/gameserver/data/manager/CastleManager;
       574: invokevirtual #87                 // Method ext/mods/gameserver/data/manager/CastleManager.getCastles:()Ljava/util/Collection;
       577: invokeinterface #91,  1           // InterfaceMethod java/util/Collection.iterator:()Ljava/util/Iterator;
       582: astore_1
       583: aload_1
       584: invokeinterface #97,  1           // InterfaceMethod java/util/Iterator.hasNext:()Z
       589: ifeq          650
       592: aload_1
       593: invokeinterface #103,  1          // InterfaceMethod java/util/Iterator.next:()Ljava/lang/Object;
       598: checkcast     #107                // class ext/mods/gameserver/model/residence/castle/Castle
       601: astore_2
       602: invokestatic  #313                // Method ext/mods/gameserver/data/sql/ClanTable.getInstance:()Lext/mods/gameserver/data/sql/ClanTable;
       605: aload_2
       606: invokevirtual #318                // Method ext/mods/gameserver/model/residence/castle/Castle.getOwnerId:()I
       609: invokevirtual #321                // Method ext/mods/gameserver/data/sql/ClanTable.getClan:(I)Lext/mods/gameserver/model/pledge/Clan;
       612: astore_3
       613: aload_3
       614: ifnull        647
       617: aload_3
       618: invokevirtual #396                // Method ext/mods/gameserver/model/pledge/Clan.getLeader:()Lext/mods/gameserver/model/pledge/ClanMember;
       621: astore        4
       623: aload         4
       625: ifnull        647
       628: aload         4
       630: invokevirtual #400                // Method ext/mods/gameserver/model/pledge/ClanMember.isOnline:()Z
       633: ifeq          647
       636: aload         4
       638: invokevirtual #405                // Method ext/mods/gameserver/model/pledge/ClanMember.getPlayerInstance:()Lext/mods/gameserver/model/actor/Player;
       641: getstatic     #409                // Field ext/mods/gameserver/network/SystemMessageId.THE_MANOR_INFORMATION_HAS_BEEN_UPDATED:Lext/mods/gameserver/network/SystemMessageId;
       644: invokevirtual #415                // Method ext/mods/gameserver/model/actor/Player.sendPacket:(Lext/mods/gameserver/network/SystemMessageId;)V
       647: goto          583
       650: aload_0
       651: getstatic     #227                // Field ext/mods/gameserver/enums/ManorStatus.MODIFIABLE:Lext/mods/gameserver/enums/ManorStatus;
       654: putfield      #13                 // Field _mode:Lext/mods/gameserver/enums/ManorStatus;
       657: goto          920
       660: aload_0
       661: getstatic     #7                  // Field ext/mods/gameserver/enums/ManorStatus.APPROVED:Lext/mods/gameserver/enums/ManorStatus;
       664: putfield      #13                 // Field _mode:Lext/mods/gameserver/enums/ManorStatus;
       667: invokestatic  #81                 // Method ext/mods/gameserver/data/manager/CastleManager.getInstance:()Lext/mods/gameserver/data/manager/CastleManager;
       670: invokevirtual #87                 // Method ext/mods/gameserver/data/manager/CastleManager.getCastles:()Ljava/util/Collection;
       673: invokeinterface #91,  1           // InterfaceMethod java/util/Collection.iterator:()Ljava/util/Iterator;
       678: astore_1
       679: aload_1
       680: invokeinterface #97,  1           // InterfaceMethod java/util/Iterator.hasNext:()Z
       685: ifeq          920
       688: aload_1
       689: invokeinterface #103,  1          // InterfaceMethod java/util/Iterator.next:()Ljava/lang/Object;
       694: checkcast     #107                // class ext/mods/gameserver/model/residence/castle/Castle
       697: astore_2
       698: invokestatic  #313                // Method ext/mods/gameserver/data/sql/ClanTable.getInstance:()Lext/mods/gameserver/data/sql/ClanTable;
       701: aload_2
       702: invokevirtual #318                // Method ext/mods/gameserver/model/residence/castle/Castle.getOwnerId:()I
       705: invokevirtual #321                // Method ext/mods/gameserver/data/sql/ClanTable.getClan:(I)Lext/mods/gameserver/model/pledge/Clan;
       708: astore_3
       709: aload_3
       710: ifnonnull     716
       713: goto          679
       716: iconst_0
       717: istore        4
       719: aload_3
       720: invokevirtual #347                // Method ext/mods/gameserver/model/pledge/Clan.getWarehouse:()Lext/mods/gameserver/model/itemcontainer/ItemContainer;
       723: astore        5
       725: aload_0
       726: getfield      #32                 // Field _procureNext:Ljava/util/Map;
       729: aload_2
       730: invokevirtual #117                // Method ext/mods/gameserver/model/residence/castle/Castle.getId:()I
       733: invokestatic  #171                // Method java/lang/Integer.valueOf:(I)Ljava/lang/Integer;
       736: invokeinterface #325,  2          // InterfaceMethod java/util/Map.get:(Ljava/lang/Object;)Ljava/lang/Object;
       741: checkcast     #157                // class java/util/List
       744: invokeinterface #328,  1          // InterfaceMethod java/util/List.iterator:()Ljava/util/Iterator;
       749: astore        6
       751: aload         6
       753: invokeinterface #97,  1           // InterfaceMethod java/util/Iterator.hasNext:()Z
       758: ifeq          807
       761: aload         6
       763: invokeinterface #103,  1          // InterfaceMethod java/util/Iterator.next:()Ljava/lang/Object;
       768: checkcast     #183                // class ext/mods/gameserver/model/manor/CropProcure
       771: astore        7
       773: aload         7
       775: invokevirtual #329                // Method ext/mods/gameserver/model/manor/CropProcure.getStartAmount:()I
       778: ifle          804
       781: aload         5
       783: aload_0
       784: aload         7
       786: invokevirtual #342                // Method ext/mods/gameserver/model/manor/CropProcure.getId:()I
       789: invokevirtual #343                // Method getSeedByCrop:(I)Lext/mods/gameserver/model/manor/Seed;
       792: invokevirtual #353                // Method ext/mods/gameserver/model/manor/Seed.getMatureId:()I
       795: invokevirtual #421                // Method ext/mods/gameserver/model/itemcontainer/ItemContainer.getItemsByItemId:(I)Ljava/util/List;
       798: ifnonnull     804
       801: iinc          4, 1
       804: goto          751
       807: aload         5
       809: iload         4
       811: invokevirtual #425                // Method ext/mods/gameserver/model/itemcontainer/ItemContainer.validateCapacity:(I)Z
       814: ifne          917
       817: aload_0
       818: aload_2
       819: invokevirtual #117                // Method ext/mods/gameserver/model/residence/castle/Castle.getId:()I
       822: iconst_1
       823: invokevirtual #374                // Method getManorCost:(IZ)J
       826: lstore        6
       828: aload_2
       829: lload         6
       831: lneg
       832: iconst_1
       833: invokevirtual #429                // Method ext/mods/gameserver/model/residence/castle/Castle.editTreasury:(JZ)Z
       836: ifne          917
       839: aload_0
       840: getfield      #38                 // Field _productionNext:Ljava/util/Map;
       843: aload_2
       844: invokevirtual #117                // Method ext/mods/gameserver/model/residence/castle/Castle.getId:()I
       847: invokestatic  #171                // Method java/lang/Integer.valueOf:(I)Ljava/lang/Integer;
       850: invokeinterface #325,  2          // InterfaceMethod java/util/Map.get:(Ljava/lang/Object;)Ljava/lang/Object;
       855: checkcast     #157                // class java/util/List
       858: invokeinterface #433,  1          // InterfaceMethod java/util/List.clear:()V
       863: aload_0
       864: getfield      #32                 // Field _procureNext:Ljava/util/Map;
       867: aload_2
       868: invokevirtual #117                // Method ext/mods/gameserver/model/residence/castle/Castle.getId:()I
       871: invokestatic  #171                // Method java/lang/Integer.valueOf:(I)Ljava/lang/Integer;
       874: invokeinterface #325,  2          // InterfaceMethod java/util/Map.get:(Ljava/lang/Object;)Ljava/lang/Object;
       879: checkcast     #157                // class java/util/List
       882: invokeinterface #433,  1          // InterfaceMethod java/util/List.clear:()V
       887: aload_3
       888: invokevirtual #396                // Method ext/mods/gameserver/model/pledge/Clan.getLeader:()Lext/mods/gameserver/model/pledge/ClanMember;
       891: astore        8
       893: aload         8
       895: ifnull        917
       898: aload         8
       900: invokevirtual #400                // Method ext/mods/gameserver/model/pledge/ClanMember.isOnline:()Z
       903: ifeq          917
       906: aload         8
       908: invokevirtual #405                // Method ext/mods/gameserver/model/pledge/ClanMember.getPlayerInstance:()Lext/mods/gameserver/model/actor/Player;
       911: getstatic     #436                // Field ext/mods/gameserver/network/SystemMessageId.THE_AMOUNT_IS_NOT_SUFFICIENT_AND_SO_THE_MANOR_IS_NOT_IN_OPERATION:Lext/mods/gameserver/network/SystemMessageId;
       914: invokevirtual #415                // Method ext/mods/gameserver/model/actor/Player.sendPacket:(Lext/mods/gameserver/network/SystemMessageId;)V
       917: goto          679
       920: aload_0
       921: invokevirtual #233                // Method scheduleModeChange:()V
       924: getstatic     #50                 // Field LOGGER:Lext/mods/commons/logging/CLogger;
       927: ldc_w         #439                // String Manor mode changed to: {}.
       930: iconst_1
       931: anewarray     #2                  // class java/lang/Object
       934: dup
       935: iconst_0
       936: aload_0
       937: getfield      #13                 // Field _mode:Lext/mods/gameserver/enums/ManorStatus;
       940: invokevirtual #251                // Method ext/mods/gameserver/enums/ManorStatus.toString:()Ljava/lang/String;
       943: aastore
       944: invokevirtual #255                // Method ext/mods/commons/logging/CLogger.debug:(Ljava/lang/Object;[Ljava/lang/Object;)V
       947: return
      LineNumberTable:
        line 218: 0
        line 221: 36
        line 223: 43
        line 225: 74
        line 226: 85
        line 227: 89
        line 229: 92
        line 231: 95
        line 233: 143
        line 235: 151
        line 237: 164
        line 238: 183
        line 239: 199
        line 241: 202
        line 243: 207
        line 244: 218
        line 245: 223
        line 249: 238
        line 250: 246
        line 252: 263
        line 254: 266
        line 256: 272
        line 257: 293
        line 259: 314
        line 260: 333
        line 262: 352
        line 264: 369
        line 265: 389
        line 269: 412
        line 270: 423
        line 271: 454
        line 273: 467
        line 275: 486
        line 276: 497
        line 277: 528
        line 279: 541
        line 281: 560
        line 283: 563
        line 284: 568
        line 287: 571
        line 289: 602
        line 290: 613
        line 292: 617
        line 293: 623
        line 294: 636
        line 296: 647
        line 297: 650
        line 298: 657
        line 301: 660
        line 303: 667
        line 305: 698
        line 306: 709
        line 307: 713
        line 309: 716
        line 310: 719
        line 312: 725
        line 314: 773
        line 315: 801
        line 316: 804
        line 318: 807
        line 320: 817
        line 321: 828
        line 323: 839
        line 324: 863
        line 326: 887
        line 327: 893
        line 328: 906
        line 331: 917
        line 334: 920
        line 336: 924
        line 337: 947
      LocalVariableTable:
        Start  Length  Slot  Name   Signature
          218      20     9  seed   Lext/mods/gameserver/model/manor/Seed;
          183      55     8 count   I
          143     120     7  crop   Lext/mods/gameserver/model/manor/CropProcure;
          454      10    10     s   Lext/mods/gameserver/model/manor/SeedProduction;
          528      10    11    cr   Lext/mods/gameserver/model/manor/CropProcure;
          423     137     8 production   Ljava/util/List;
          497      63     9 procure   Ljava/util/List;
           85     475     3 owner   Lext/mods/gameserver/model/pledge/Clan;
           95     465     4 amount   J
          293     267     6 nextProduction   Ljava/util/List;
          314     246     7 nextProcure   Ljava/util/List;
           74     486     2 castle   Lext/mods/gameserver/model/residence/castle/Castle;
          623      24     4 clanLeader   Lext/mods/gameserver/model/pledge/ClanMember;
          613      34     3 owner   Lext/mods/gameserver/model/pledge/Clan;
          602      45     2 castle   Lext/mods/gameserver/model/residence/castle/Castle;
          773      31     7  crop   Lext/mods/gameserver/model/manor/CropProcure;
          893      24     8 clanLeader   Lext/mods/gameserver/model/pledge/ClanMember;
          828      89     6 manorCost   J
          709     208     3 owner   Lext/mods/gameserver/model/pledge/Clan;
          719     198     4 slots   I
          725     192     5   cwh   Lext/mods/gameserver/model/itemcontainer/ItemContainer;
          698     219     2 castle   Lext/mods/gameserver/model/residence/castle/Castle;
            0     948     0  this   Lext/mods/gameserver/data/manager/CastleManorManager;
      LocalVariableTypeTable:
        Start  Length  Slot  Name   Signature
          423     137     8 production   Ljava/util/List<Lext/mods/gameserver/model/manor/SeedProduction;>;
          497      63     9 procure   Ljava/util/List<Lext/mods/gameserver/model/manor/CropProcure;>;
          293     267     6 nextProduction   Ljava/util/List<Lext/mods/gameserver/model/manor/SeedProduction;>;
          314     246     7 nextProcure   Ljava/util/List<Lext/mods/gameserver/model/manor/CropProcure;>;
      StackMapTable: number_of_entries = 27
        frame_type = 36 /* same */
        frame_type = 252 /* append */
          offset_delta = 18
          locals = [ class java/util/Iterator ]
        frame_type = 253 /* append */
          offset_delta = 36
          locals = [ class ext/mods/gameserver/model/residence/castle/Castle, class ext/mods/gameserver/model/pledge/Clan ]
        frame_type = 253 /* append */
          offset_delta = 28
          locals = [ long, class java/util/Iterator ]
        frame_type = 253 /* append */
          offset_delta = 80
          locals = [ class ext/mods/gameserver/model/manor/CropProcure, int ]
        frame_type = 250 /* chop */
          offset_delta = 35
        frame_type = 250 /* chop */
          offset_delta = 24
        frame_type = 250 /* chop */
          offset_delta = 2
        frame_type = 253 /* append */
          offset_delta = 145
          locals = [ class java/util/List, class java/util/List ]
        frame_type = 253 /* append */
          offset_delta = 19
          locals = [ class java/util/List, class java/util/Iterator ]
        frame_type = 250 /* chop */
          offset_delta = 34
        frame_type = 253 /* append */
          offset_delta = 38
          locals = [ class java/util/List, class java/util/Iterator ]
        frame_type = 250 /* chop */
          offset_delta = 34
        frame_type = 255 /* full_frame */
          offset_delta = 18
          locals = [ class ext/mods/gameserver/data/manager/CastleManorManager, class java/util/Iterator ]
          stack = []
        frame_type = 250 /* chop */
          offset_delta = 2
        frame_type = 7 /* same */
        frame_type = 252 /* append */
          offset_delta = 11
          locals = [ class java/util/Iterator ]
        frame_type = 63 /* same */
        frame_type = 250 /* chop */
          offset_delta = 2
        frame_type = 9 /* same */
        frame_type = 252 /* append */
          offset_delta = 18
          locals = [ class java/util/Iterator ]
        frame_type = 253 /* append */
          offset_delta = 36
          locals = [ class ext/mods/gameserver/model/residence/castle/Castle, class ext/mods/gameserver/model/pledge/Clan ]
        frame_type = 254 /* append */
          offset_delta = 34
          locals = [ int, class ext/mods/gameserver/model/itemcontainer/ItemContainer, class java/util/Iterator ]
        frame_type = 52 /* same */
        frame_type = 250 /* chop */
          offset_delta = 2
        frame_type = 255 /* full_frame */
          offset_delta = 109
          locals = [ class ext/mods/gameserver/data/manager/CastleManorManager, class java/util/Iterator ]
          stack = []
        frame_type = 250 /* chop */
          offset_delta = 2

  public final void setNextSeedProduction(java.util.List<ext.mods.gameserver.model.manor.SeedProduction>, int);
    descriptor: (Ljava/util/List;I)V
    flags: (0x0011) ACC_PUBLIC, ACC_FINAL
    Code:
      stack=3, locals=3, args_size=3
         0: aload_0
         1: getfield      #38                 // Field _productionNext:Ljava/util/Map;
         4: iload_2
         5: invokestatic  #171                // Method java/lang/Integer.valueOf:(I)Ljava/lang/Integer;
         8: aload_1
         9: invokeinterface #177,  3          // InterfaceMethod java/util/Map.put:(Ljava/lang/Object;Ljava/lang/Object;)Ljava/lang/Object;
        14: pop
        15: return
      LineNumberTable:
        line 341: 0
        line 342: 15
      LocalVariableTable:
        Start  Length  Slot  Name   Signature
            0      16     0  this   Lext/mods/gameserver/data/manager/CastleManorManager;
            0      16     1  list   Ljava/util/List;
            0      16     2 castleId   I
      LocalVariableTypeTable:
        Start  Length  Slot  Name   Signature
            0      16     1  list   Ljava/util/List<Lext/mods/gameserver/model/manor/SeedProduction;>;
    Signature: #706                         // (Ljava/util/List<Lext/mods/gameserver/model/manor/SeedProduction;>;I)V

  public final void setNextCropProcure(java.util.List<ext.mods.gameserver.model.manor.CropProcure>, int);
    descriptor: (Ljava/util/List;I)V
    flags: (0x0011) ACC_PUBLIC, ACC_FINAL
    Code:
      stack=3, locals=3, args_size=3
         0: aload_0
         1: getfield      #32                 // Field _procureNext:Ljava/util/Map;
         4: iload_2
         5: invokestatic  #171                // Method java/lang/Integer.valueOf:(I)Ljava/lang/Integer;
         8: aload_1
         9: invokeinterface #177,  3          // InterfaceMethod java/util/Map.put:(Ljava/lang/Object;Ljava/lang/Object;)Ljava/lang/Object;
        14: pop
        15: return
      LineNumberTable:
        line 346: 0
        line 347: 15
      LocalVariableTable:
        Start  Length  Slot  Name   Signature
            0      16     0  this   Lext/mods/gameserver/data/manager/CastleManorManager;
            0      16     1  list   Ljava/util/List;
            0      16     2 castleId   I
      LocalVariableTypeTable:
        Start  Length  Slot  Name   Signature
            0      16     1  list   Ljava/util/List<Lext/mods/gameserver/model/manor/CropProcure;>;
    Signature: #708                         // (Ljava/util/List<Lext/mods/gameserver/model/manor/CropProcure;>;I)V

  public static final void updateCurrentProduction(int, java.util.Collection<ext.mods.gameserver.model.manor.SeedProduction>);
    descriptor: (ILjava/util/Collection;)V
    flags: (0x0019) ACC_PUBLIC, ACC_STATIC, ACC_FINAL
    Code:
      stack=4, locals=6, args_size=2
         0: invokestatic  #65                 // Method ext/mods/commons/pool/ConnectionPool.getConnection:()Ljava/sql/Connection;
         3: astore_2
         4: aload_2
         5: ldc_w         #441                // String UPDATE castle_manor_production SET amount = ? WHERE castle_id = ? AND seed_id = ? AND next_period = 0
         8: invokeinterface #73,  2           // InterfaceMethod java/sql/Connection.prepareStatement:(Ljava/lang/String;)Ljava/sql/PreparedStatement;
        13: astore_3
        14: aload_1
        15: invokeinterface #91,  1           // InterfaceMethod java/util/Collection.iterator:()Ljava/util/Iterator;
        20: astore        4
        22: aload         4
        24: invokeinterface #97,  1           // InterfaceMethod java/util/Iterator.hasNext:()Z
        29: ifeq          86
        32: aload         4
        34: invokeinterface #103,  1          // InterfaceMethod java/util/Iterator.next:()Ljava/lang/Object;
        39: checkcast     #133                // class ext/mods/gameserver/model/manor/SeedProduction
        42: astore        5
        44: aload_3
        45: iconst_1
        46: aload         5
        48: invokevirtual #443                // Method ext/mods/gameserver/model/manor/SeedProduction.getAmount:()I
        51: i2l
        52: invokeinterface #444,  4          // InterfaceMethod java/sql/PreparedStatement.setLong:(IJ)V
        57: aload_3
        58: iconst_2
        59: iload_0
        60: invokeinterface #121,  3          // InterfaceMethod java/sql/PreparedStatement.setInt:(II)V
        65: aload_3
        66: iconst_3
        67: aload         5
        69: invokevirtual #448                // Method ext/mods/gameserver/model/manor/SeedProduction.getId:()I
        72: invokeinterface #121,  3          // InterfaceMethod java/sql/PreparedStatement.setInt:(II)V
        77: aload_3
        78: invokeinterface #449,  1          // InterfaceMethod java/sql/PreparedStatement.addBatch:()V
        83: goto          22
        86: aload_3
        87: invokeinterface #452,  1          // InterfaceMethod java/sql/PreparedStatement.executeBatch:()[I
        92: pop
        93: aload_3
        94: ifnull        133
        97: aload_3
        98: invokeinterface #192,  1          // InterfaceMethod java/sql/PreparedStatement.close:()V
       103: goto          133
       106: astore        4
       108: aload_3
       109: ifnull        130
       112: aload_3
       113: invokeinterface #192,  1          // InterfaceMethod java/sql/PreparedStatement.close:()V
       118: goto          130
       121: astore        5
       123: aload         4
       125: aload         5
       127: invokevirtual #167                // Method java/lang/Throwable.addSuppressed:(Ljava/lang/Throwable;)V
       130: aload         4
       132: athrow
       133: aload_2
       134: ifnull        170
       137: aload_2
       138: invokeinterface #193,  1          // InterfaceMethod java/sql/Connection.close:()V
       143: goto          170
       146: astore_3
       147: aload_2
       148: ifnull        168
       151: aload_2
       152: invokeinterface #193,  1          // InterfaceMethod java/sql/Connection.close:()V
       157: goto          168
       160: astore        4
       162: aload_3
       163: aload         4
       165: invokevirtual #167                // Method java/lang/Throwable.addSuppressed:(Ljava/lang/Throwable;)V
       168: aload_3
       169: athrow
       170: goto          184
       173: astore_2
       174: getstatic     #50                 // Field LOGGER:Lext/mods/commons/logging/CLogger;
       177: ldc_w         #456                // String Unable to store manor data.
       180: aload_2
       181: invokevirtual #198                // Method ext/mods/commons/logging/CLogger.error:(Ljava/lang/Object;Ljava/lang/Throwable;)V
       184: return
      Exception table:
         from    to  target type
            14    93   106   Class java/lang/Throwable
           112   118   121   Class java/lang/Throwable
             4   133   146   Class java/lang/Throwable
           151   157   160   Class java/lang/Throwable
             0   170   173   Class java/lang/Exception
      LineNumberTable:
        line 351: 0
        line 352: 4
        line 354: 14
        line 356: 44
        line 357: 57
        line 358: 65
        line 359: 77
        line 360: 83
        line 361: 86
        line 362: 93
        line 351: 106
        line 362: 133
        line 351: 146
        line 366: 170
        line 363: 173
        line 365: 174
        line 367: 184
      LocalVariableTable:
        Start  Length  Slot  Name   Signature
           44      39     5    sp   Lext/mods/gameserver/model/manor/SeedProduction;
           14     119     3    ps   Ljava/sql/PreparedStatement;
            4     166     2   con   Ljava/sql/Connection;
          174      10     2     e   Ljava/lang/Exception;
            0     185     0 castleId   I
            0     185     1 items   Ljava/util/Collection;
      LocalVariableTypeTable:
        Start  Length  Slot  Name   Signature
            0     185     1 items   Ljava/util/Collection<Lext/mods/gameserver/model/manor/SeedProduction;>;
      StackMapTable: number_of_entries = 12
        frame_type = 254 /* append */
          offset_delta = 22
          locals = [ class java/sql/Connection, class java/sql/PreparedStatement, class java/util/Iterator ]
        frame_type = 250 /* chop */
          offset_delta = 63
        frame_type = 83 /* same_locals_1_stack_item */
          stack = [ class java/lang/Throwable ]
        frame_type = 255 /* full_frame */
          offset_delta = 14
          locals = [ int, class java/util/Collection, class java/sql/Connection, class java/sql/PreparedStatement, class java/lang/Throwable ]
          stack = [ class java/lang/Throwable ]
        frame_type = 8 /* same */
        frame_type = 249 /* chop */
          offset_delta = 2
        frame_type = 76 /* same_locals_1_stack_item */
          stack = [ class java/lang/Throwable ]
        frame_type = 255 /* full_frame */
          offset_delta = 13
          locals = [ int, class java/util/Collection, class java/sql/Connection, class java/lang/Throwable ]
          stack = [ class java/lang/Throwable ]
        frame_type = 7 /* same */
        frame_type = 249 /* chop */
          offset_delta = 1
        frame_type = 66 /* same_locals_1_stack_item */
          stack = [ class java/lang/Exception ]
        frame_type = 10 /* same */
    Signature: #715                         // (ILjava/util/Collection<Lext/mods/gameserver/model/manor/SeedProduction;>;)V

  public static final void updateCurrentProcure(int, java.util.Collection<ext.mods.gameserver.model.manor.CropProcure>);
    descriptor: (ILjava/util/Collection;)V
    flags: (0x0019) ACC_PUBLIC, ACC_STATIC, ACC_FINAL
    Code:
      stack=4, locals=6, args_size=2
         0: invokestatic  #65                 // Method ext/mods/commons/pool/ConnectionPool.getConnection:()Ljava/sql/Connection;
         3: astore_2
         4: aload_2
         5: ldc_w         #458                // String UPDATE castle_manor_procure SET amount = ? WHERE castle_id = ? AND crop_id = ? AND next_period = 0
         8: invokeinterface #73,  2           // InterfaceMethod java/sql/Connection.prepareStatement:(Ljava/lang/String;)Ljava/sql/PreparedStatement;
        13: astore_3
        14: aload_1
        15: invokeinterface #91,  1           // InterfaceMethod java/util/Collection.iterator:()Ljava/util/Iterator;
        20: astore        4
        22: aload         4
        24: invokeinterface #97,  1           // InterfaceMethod java/util/Iterator.hasNext:()Z
        29: ifeq          86
        32: aload         4
        34: invokeinterface #103,  1          // InterfaceMethod java/util/Iterator.next:()Ljava/lang/Object;
        39: checkcast     #183                // class ext/mods/gameserver/model/manor/CropProcure
        42: astore        5
        44: aload_3
        45: iconst_1
        46: aload         5
        48: invokevirtual #332                // Method ext/mods/gameserver/model/manor/CropProcure.getAmount:()I
        51: i2l
        52: invokeinterface #444,  4          // InterfaceMethod java/sql/PreparedStatement.setLong:(IJ)V
        57: aload_3
        58: iconst_2
        59: iload_0
        60: invokeinterface #121,  3          // InterfaceMethod java/sql/PreparedStatement.setInt:(II)V
        65: aload_3
        66: iconst_3
        67: aload         5
        69: invokevirtual #342                // Method ext/mods/gameserver/model/manor/CropProcure.getId:()I
        72: invokeinterface #121,  3          // InterfaceMethod java/sql/PreparedStatement.setInt:(II)V
        77: aload_3
        78: invokeinterface #449,  1          // InterfaceMethod java/sql/PreparedStatement.addBatch:()V
        83: goto          22
        86: aload_3
        87: invokeinterface #452,  1          // InterfaceMethod java/sql/PreparedStatement.executeBatch:()[I
        92: pop
        93: aload_3
        94: ifnull        133
        97: aload_3
        98: invokeinterface #192,  1          // InterfaceMethod java/sql/PreparedStatement.close:()V
       103: goto          133
       106: astore        4
       108: aload_3
       109: ifnull        130
       112: aload_3
       113: invokeinterface #192,  1          // InterfaceMethod java/sql/PreparedStatement.close:()V
       118: goto          130
       121: astore        5
       123: aload         4
       125: aload         5
       127: invokevirtual #167                // Method java/lang/Throwable.addSuppressed:(Ljava/lang/Throwable;)V
       130: aload         4
       132: athrow
       133: aload_2
       134: ifnull        170
       137: aload_2
       138: invokeinterface #193,  1          // InterfaceMethod java/sql/Connection.close:()V
       143: goto          170
       146: astore_3
       147: aload_2
       148: ifnull        168
       151: aload_2
       152: invokeinterface #193,  1          // InterfaceMethod java/sql/Connection.close:()V
       157: goto          168
       160: astore        4
       162: aload_3
       163: aload         4
       165: invokevirtual #167                // Method java/lang/Throwable.addSuppressed:(Ljava/lang/Throwable;)V
       168: aload_3
       169: athrow
       170: goto          184
       173: astore_2
       174: getstatic     #50                 // Field LOGGER:Lext/mods/commons/logging/CLogger;
       177: ldc_w         #456                // String Unable to store manor data.
       180: aload_2
       181: invokevirtual #198                // Method ext/mods/commons/logging/CLogger.error:(Ljava/lang/Object;Ljava/lang/Throwable;)V
       184: return
      Exception table:
         from    to  target type
            14    93   106   Class java/lang/Throwable
           112   118   121   Class java/lang/Throwable
             4   133   146   Class java/lang/Throwable
           151   157   160   Class java/lang/Throwable
             0   170   173   Class java/lang/Exception
      LineNumberTable:
        line 371: 0
        line 372: 4
        line 374: 14
        line 376: 44
        line 377: 57
        line 378: 65
        line 379: 77
        line 380: 83
        line 381: 86
        line 382: 93
        line 371: 106
        line 382: 133
        line 371: 146
        line 386: 170
        line 383: 173
        line 385: 174
        line 387: 184
      LocalVariableTable:
        Start  Length  Slot  Name   Signature
           44      39     5    sp   Lext/mods/gameserver/model/manor/CropProcure;
           14     119     3    ps   Ljava/sql/PreparedStatement;
            4     166     2   con   Ljava/sql/Connection;
          174      10     2     e   Ljava/lang/Exception;
            0     185     0 castleId   I
            0     185     1 items   Ljava/util/Collection;
      LocalVariableTypeTable:
        Start  Length  Slot  Name   Signature
            0     185     1 items   Ljava/util/Collection<Lext/mods/gameserver/model/manor/CropProcure;>;
      StackMapTable: number_of_entries = 12
        frame_type = 254 /* append */
          offset_delta = 22
          locals = [ class java/sql/Connection, class java/sql/PreparedStatement, class java/util/Iterator ]
        frame_type = 250 /* chop */
          offset_delta = 63
        frame_type = 83 /* same_locals_1_stack_item */
          stack = [ class java/lang/Throwable ]
        frame_type = 255 /* full_frame */
          offset_delta = 14
          locals = [ int, class java/util/Collection, class java/sql/Connection, class java/sql/PreparedStatement, class java/lang/Throwable ]
          stack = [ class java/lang/Throwable ]
        frame_type = 8 /* same */
        frame_type = 249 /* chop */
          offset_delta = 2
        frame_type = 76 /* same_locals_1_stack_item */
          stack = [ class java/lang/Throwable ]
        frame_type = 255 /* full_frame */
          offset_delta = 13
          locals = [ int, class java/util/Collection, class java/sql/Connection, class java/lang/Throwable ]
          stack = [ class java/lang/Throwable ]
        frame_type = 7 /* same */
        frame_type = 249 /* chop */
          offset_delta = 1
        frame_type = 66 /* same_locals_1_stack_item */
          stack = [ class java/lang/Exception ]
        frame_type = 10 /* same */
    Signature: #718                         // (ILjava/util/Collection<Lext/mods/gameserver/model/manor/CropProcure;>;)V

  public final java.util.List<ext.mods.gameserver.model.manor.SeedProduction> getSeedProduction(int, boolean);
    descriptor: (IZ)Ljava/util/List;
    flags: (0x0011) ACC_PUBLIC, ACC_FINAL
    Code:
      stack=2, locals=3, args_size=3
         0: iload_2
         1: ifeq          23
         4: aload_0
         5: getfield      #38                 // Field _productionNext:Ljava/util/Map;
         8: iload_1
         9: invokestatic  #171                // Method java/lang/Integer.valueOf:(I)Ljava/lang/Integer;
        12: invokeinterface #325,  2          // InterfaceMethod java/util/Map.get:(Ljava/lang/Object;)Ljava/lang/Object;
        17: checkcast     #157                // class java/util/List
        20: goto          39
        23: aload_0
        24: getfield      #35                 // Field _production:Ljava/util/Map;
        27: iload_1
        28: invokestatic  #171                // Method java/lang/Integer.valueOf:(I)Ljava/lang/Integer;
        31: invokeinterface #325,  2          // InterfaceMethod java/util/Map.get:(Ljava/lang/Object;)Ljava/lang/Object;
        36: checkcast     #157                // class java/util/List
        39: areturn
      LineNumberTable:
        line 391: 0
      LocalVariableTable:
        Start  Length  Slot  Name   Signature
            0      40     0  this   Lext/mods/gameserver/data/manager/CastleManorManager;
            0      40     1 castleId   I
            0      40     2 nextPeriod   Z
      StackMapTable: number_of_entries = 2
        frame_type = 23 /* same */
        frame_type = 79 /* same_locals_1_stack_item */
          stack = [ class java/util/List ]
    Signature: #720                         // (IZ)Ljava/util/List<Lext/mods/gameserver/model/manor/SeedProduction;>;

  public final ext.mods.gameserver.model.manor.SeedProduction getSeedProduct(int, int, boolean);
    descriptor: (IIZ)Lext/mods/gameserver/model/manor/SeedProduction;
    flags: (0x0011) ACC_PUBLIC, ACC_FINAL
    Code:
      stack=3, locals=6, args_size=4
         0: aload_0
         1: iload_1
         2: iload_3
         3: invokevirtual #460                // Method getSeedProduction:(IZ)Ljava/util/List;
         6: invokeinterface #328,  1          // InterfaceMethod java/util/List.iterator:()Ljava/util/Iterator;
        11: astore        4
        13: aload         4
        15: invokeinterface #97,  1           // InterfaceMethod java/util/Iterator.hasNext:()Z
        20: ifeq          50
        23: aload         4
        25: invokeinterface #103,  1          // InterfaceMethod java/util/Iterator.next:()Ljava/lang/Object;
        30: checkcast     #133                // class ext/mods/gameserver/model/manor/SeedProduction
        33: astore        5
        35: aload         5
        37: invokevirtual #448                // Method ext/mods/gameserver/model/manor/SeedProduction.getId:()I
        40: iload_2
        41: if_icmpne     47
        44: aload         5
        46: areturn
        47: goto          13
        50: aconst_null
        51: areturn
      LineNumberTable:
        line 396: 0
        line 398: 35
        line 399: 44
        line 400: 47
        line 401: 50
      LocalVariableTable:
        Start  Length  Slot  Name   Signature
           35      12     5    sp   Lext/mods/gameserver/model/manor/SeedProduction;
            0      52     0  this   Lext/mods/gameserver/data/manager/CastleManorManager;
            0      52     1 castleId   I
            0      52     2 seedId   I
            0      52     3 nextPeriod   Z
      StackMapTable: number_of_entries = 3
        frame_type = 252 /* append */
          offset_delta = 13
          locals = [ class java/util/Iterator ]
        frame_type = 33 /* same */
        frame_type = 250 /* chop */
          offset_delta = 2

  public final java.util.List<ext.mods.gameserver.model.manor.CropProcure> getCropProcure(int, boolean);
    descriptor: (IZ)Ljava/util/List;
    flags: (0x0011) ACC_PUBLIC, ACC_FINAL
    Code:
      stack=2, locals=3, args_size=3
         0: iload_2
         1: ifeq          23
         4: aload_0
         5: getfield      #32                 // Field _procureNext:Ljava/util/Map;
         8: iload_1
         9: invokestatic  #171                // Method java/lang/Integer.valueOf:(I)Ljava/lang/Integer;
        12: invokeinterface #325,  2          // InterfaceMethod java/util/Map.get:(Ljava/lang/Object;)Ljava/lang/Object;
        17: checkcast     #157                // class java/util/List
        20: goto          39
        23: aload_0
        24: getfield      #29                 // Field _procure:Ljava/util/Map;
        27: iload_1
        28: invokestatic  #171                // Method java/lang/Integer.valueOf:(I)Ljava/lang/Integer;
        31: invokeinterface #325,  2          // InterfaceMethod java/util/Map.get:(Ljava/lang/Object;)Ljava/lang/Object;
        36: checkcast     #157                // class java/util/List
        39: areturn
      LineNumberTable:
        line 406: 0
      LocalVariableTable:
        Start  Length  Slot  Name   Signature
            0      40     0  this   Lext/mods/gameserver/data/manager/CastleManorManager;
            0      40     1 castleId   I
            0      40     2 nextPeriod   Z
      StackMapTable: number_of_entries = 2
        frame_type = 23 /* same */
        frame_type = 79 /* same_locals_1_stack_item */
          stack = [ class java/util/List ]
    Signature: #723                         // (IZ)Ljava/util/List<Lext/mods/gameserver/model/manor/CropProcure;>;

  public final ext.mods.gameserver.model.manor.CropProcure getCropProcure(int, int, boolean);
    descriptor: (IIZ)Lext/mods/gameserver/model/manor/CropProcure;
    flags: (0x0011) ACC_PUBLIC, ACC_FINAL
    Code:
      stack=3, locals=7, args_size=4
         0: aload_0
         1: iload_1
         2: iload_3
         3: invokevirtual #464                // Method getCropProcure:(IZ)Ljava/util/List;
         6: astore        4
         8: aload         4
        10: ifnonnull     15
        13: aconst_null
        14: areturn
        15: aload         4
        17: invokeinterface #328,  1          // InterfaceMethod java/util/List.iterator:()Ljava/util/Iterator;
        22: astore        5
        24: aload         5
        26: invokeinterface #97,  1           // InterfaceMethod java/util/Iterator.hasNext:()Z
        31: ifeq          61
        34: aload         5
        36: invokeinterface #103,  1          // InterfaceMethod java/util/Iterator.next:()Ljava/lang/Object;
        41: checkcast     #183                // class ext/mods/gameserver/model/manor/CropProcure
        44: astore        6
        46: aload         6
        48: invokevirtual #342                // Method ext/mods/gameserver/model/manor/CropProcure.getId:()I
        51: iload_2
        52: if_icmpne     58
        55: aload         6
        57: areturn
        58: goto          24
        61: aconst_null
        62: areturn
      LineNumberTable:
        line 411: 0
        line 412: 8
        line 413: 13
        line 415: 15
        line 417: 46
        line 418: 55
        line 419: 58
        line 420: 61
      LocalVariableTable:
        Start  Length  Slot  Name   Signature
           46      12     6    cp   Lext/mods/gameserver/model/manor/CropProcure;
            0      63     0  this   Lext/mods/gameserver/data/manager/CastleManorManager;
            0      63     1 castleId   I
            0      63     2 cropId   I
            0      63     3 nextPeriod   Z
            8      55     4 crops   Ljava/util/List;
      LocalVariableTypeTable:
        Start  Length  Slot  Name   Signature
            8      55     4 crops   Ljava/util/List<Lext/mods/gameserver/model/manor/CropProcure;>;
      StackMapTable: number_of_entries = 4
        frame_type = 252 /* append */
          offset_delta = 15
          locals = [ class java/util/List ]
        frame_type = 252 /* append */
          offset_delta = 8
          locals = [ class java/util/Iterator ]
        frame_type = 33 /* same */
        frame_type = 250 /* chop */
          offset_delta = 2

  public final long getManorCost(int, boolean);
    descriptor: (IZ)J
    flags: (0x0011) ACC_PUBLIC, ACC_FINAL
    Code:
      stack=4, locals=10, args_size=3
         0: aload_0
         1: iload_1
         2: iload_2
         3: invokevirtual #464                // Method getCropProcure:(IZ)Ljava/util/List;
         6: astore_3
         7: aload_0
         8: iload_1
         9: iload_2
        10: invokevirtual #460                // Method getSeedProduction:(IZ)Ljava/util/List;
        13: astore        4
        15: lconst_0
        16: lstore        5
        18: aload         4
        20: invokeinterface #328,  1          // InterfaceMethod java/util/List.iterator:()Ljava/util/Iterator;
        25: astore        7
        27: aload         7
        29: invokeinterface #97,  1           // InterfaceMethod java/util/Iterator.hasNext:()Z
        34: ifeq          89
        37: aload         7
        39: invokeinterface #103,  1          // InterfaceMethod java/util/Iterator.next:()Ljava/lang/Object;
        44: checkcast     #133                // class ext/mods/gameserver/model/manor/SeedProduction
        47: astore        8
        49: aload_0
        50: aload         8
        52: invokevirtual #448                // Method ext/mods/gameserver/model/manor/SeedProduction.getId:()I
        55: invokevirtual #467                // Method getSeed:(I)Lext/mods/gameserver/model/manor/Seed;
        58: astore        9
        60: lload         5
        62: aload         9
        64: ifnonnull     71
        67: lconst_1
        68: goto          83
        71: aload         9
        73: invokevirtual #470                // Method ext/mods/gameserver/model/manor/Seed.getSeedReferencePrice:()I
        76: aload         8
        78: invokevirtual #387                // Method ext/mods/gameserver/model/manor/SeedProduction.getStartAmount:()I
        81: imul
        82: i2l
        83: ladd
        84: lstore        5
        86: goto          27
        89: aload_3
        90: invokeinterface #328,  1          // InterfaceMethod java/util/List.iterator:()Ljava/util/Iterator;
        95: astore        7
        97: aload         7
        99: invokeinterface #97,  1           // InterfaceMethod java/util/Iterator.hasNext:()Z
       104: ifeq          139
       107: aload         7
       109: invokeinterface #103,  1          // InterfaceMethod java/util/Iterator.next:()Ljava/lang/Object;
       114: checkcast     #183                // class ext/mods/gameserver/model/manor/CropProcure
       117: astore        8
       119: lload         5
       121: aload         8
       123: invokevirtual #364                // Method ext/mods/gameserver/model/manor/CropProcure.getPrice:()I
       126: aload         8
       128: invokevirtual #329                // Method ext/mods/gameserver/model/manor/CropProcure.getStartAmount:()I
       131: imul
       132: i2l
       133: ladd
       134: lstore        5
       136: goto          97
       139: lload         5
       141: lreturn
      LineNumberTable:
        line 425: 0
        line 426: 7
        line 428: 15
        line 429: 18
        line 431: 49
        line 432: 60
        line 433: 86
        line 434: 89
        line 436: 119
        line 437: 136
        line 438: 139
      LocalVariableTable:
        Start  Length  Slot  Name   Signature
           60      26     9     s   Lext/mods/gameserver/model/manor/Seed;
           49      37     8  seed   Lext/mods/gameserver/model/manor/SeedProduction;
          119      17     8  crop   Lext/mods/gameserver/model/manor/CropProcure;
            0     142     0  this   Lext/mods/gameserver/data/manager/CastleManorManager;
            0     142     1 castleId   I
            0     142     2 nextPeriod   Z
            7     135     3 procure   Ljava/util/List;
           15     127     4 production   Ljava/util/List;
           18     124     5 total   J
      LocalVariableTypeTable:
        Start  Length  Slot  Name   Signature
            7     135     3 procure   Ljava/util/List<Lext/mods/gameserver/model/manor/CropProcure;>;
           15     127     4 production   Ljava/util/List<Lext/mods/gameserver/model/manor/SeedProduction;>;
      StackMapTable: number_of_entries = 6
        frame_type = 255 /* full_frame */
          offset_delta = 27
          locals = [ class ext/mods/gameserver/data/manager/CastleManorManager, int, int, class java/util/List, class java/util/List, long, class java/util/Iterator ]
          stack = []
        frame_type = 255 /* full_frame */
          offset_delta = 43
          locals = [ class ext/mods/gameserver/data/manager/CastleManorManager, int, int, class java/util/List, class java/util/List, long, class java/util/Iterator, class ext/mods/gameserver/model/manor/SeedProduction, class ext/mods/gameserver/model/manor/Seed ]
          stack = [ long ]
        frame_type = 255 /* full_frame */
          offset_delta = 11
          locals = [ class ext/mods/gameserver/data/manager/CastleManorManager, int, int, class java/util/List, class java/util/List, long, class java/util/Iterator, class ext/mods/gameserver/model/manor/SeedProduction, class ext/mods/gameserver/model/manor/Seed ]
          stack = [ long, long ]
        frame_type = 248 /* chop */
          offset_delta = 5
        frame_type = 252 /* append */
          offset_delta = 7
          locals = [ class java/util/Iterator ]
        frame_type = 250 /* chop */
          offset_delta = 41

  public final boolean storeMe();
    descriptor: ()Z
    flags: (0x0011) ACC_PUBLIC, ACC_FINAL
    Code:
      stack=4, locals=10, args_size=1
         0: invokestatic  #65                 // Method ext/mods/commons/pool/ConnectionPool.getConnection:()Ljava/sql/Connection;
         3: astore_1
         4: aload_1
         5: ldc_w         #473                // String TRUNCATE castle_manor_production
         8: invokeinterface #73,  2           // InterfaceMethod java/sql/Connection.prepareStatement:(Ljava/lang/String;)Ljava/sql/PreparedStatement;
        13: astore_2
        14: aload_1
        15: ldc_w         #475                // String INSERT INTO castle_manor_production VALUES (?, ?, ?, ?, ?, ?)
        18: invokeinterface #73,  2           // InterfaceMethod java/sql/Connection.prepareStatement:(Ljava/lang/String;)Ljava/sql/PreparedStatement;
        23: astore_3
        24: aload_1
        25: ldc_w         #477                // String TRUNCATE castle_manor_procure
        28: invokeinterface #73,  2           // InterfaceMethod java/sql/Connection.prepareStatement:(Ljava/lang/String;)Ljava/sql/PreparedStatement;
        33: astore        4
        35: aload_1
        36: ldc_w         #479                // String INSERT INTO castle_manor_procure VALUES (?, ?, ?, ?, ?, ?, ?)
        39: invokeinterface #73,  2           // InterfaceMethod java/sql/Connection.prepareStatement:(Ljava/lang/String;)Ljava/sql/PreparedStatement;
        44: astore        5
        46: aload_2
        47: invokeinterface #481,  1          // InterfaceMethod java/sql/PreparedStatement.executeUpdate:()I
        52: pop
        53: aload_0
        54: getfield      #35                 // Field _production:Ljava/util/Map;
        57: invokeinterface #484,  1          // InterfaceMethod java/util/Map.entrySet:()Ljava/util/Set;
        62: invokeinterface #488,  1          // InterfaceMethod java/util/Set.iterator:()Ljava/util/Iterator;
        67: astore        6
        69: aload         6
        71: invokeinterface #97,  1           // InterfaceMethod java/util/Iterator.hasNext:()Z
        76: ifeq          222
        79: aload         6
        81: invokeinterface #103,  1          // InterfaceMethod java/util/Iterator.next:()Ljava/lang/Object;
        86: checkcast     #491                // class java/util/Map$Entry
        89: astore        7
        91: aload         7
        93: invokeinterface #493,  1          // InterfaceMethod java/util/Map$Entry.getValue:()Ljava/lang/Object;
        98: checkcast     #157                // class java/util/List
       101: invokeinterface #328,  1          // InterfaceMethod java/util/List.iterator:()Ljava/util/Iterator;
       106: astore        8
       108: aload         8
       110: invokeinterface #97,  1           // InterfaceMethod java/util/Iterator.hasNext:()Z
       115: ifeq          219
       118: aload         8
       120: invokeinterface #103,  1          // InterfaceMethod java/util/Iterator.next:()Ljava/lang/Object;
       125: checkcast     #133                // class ext/mods/gameserver/model/manor/SeedProduction
       128: astore        9
       130: aload_3
       131: iconst_1
       132: aload         7
       134: invokeinterface #496,  1          // InterfaceMethod java/util/Map$Entry.getKey:()Ljava/lang/Object;
       139: checkcast     #172                // class java/lang/Integer
       142: invokevirtual #499                // Method java/lang/Integer.intValue:()I
       145: invokeinterface #121,  3          // InterfaceMethod java/sql/PreparedStatement.setInt:(II)V
       150: aload_3
       151: iconst_2
       152: aload         9
       154: invokevirtual #448                // Method ext/mods/gameserver/model/manor/SeedProduction.getId:()I
       157: invokeinterface #121,  3          // InterfaceMethod java/sql/PreparedStatement.setInt:(II)V
       162: aload_3
       163: iconst_3
       164: aload         9
       166: invokevirtual #443                // Method ext/mods/gameserver/model/manor/SeedProduction.getAmount:()I
       169: i2l
       170: invokeinterface #444,  4          // InterfaceMethod java/sql/PreparedStatement.setLong:(IJ)V
       175: aload_3
       176: iconst_4
       177: aload         9
       179: invokevirtual #387                // Method ext/mods/gameserver/model/manor/SeedProduction.getStartAmount:()I
       182: i2l
       183: invokeinterface #444,  4          // InterfaceMethod java/sql/PreparedStatement.setLong:(IJ)V
       188: aload_3
       189: iconst_5
       190: aload         9
       192: invokevirtual #502                // Method ext/mods/gameserver/model/manor/SeedProduction.getPrice:()I
       195: i2l
       196: invokeinterface #444,  4          // InterfaceMethod java/sql/PreparedStatement.setLong:(IJ)V
       201: aload_3
       202: bipush        6
       204: iconst_0
       205: invokeinterface #503,  3          // InterfaceMethod java/sql/PreparedStatement.setBoolean:(IZ)V
       210: aload_3
       211: invokeinterface #449,  1          // InterfaceMethod java/sql/PreparedStatement.addBatch:()V
       216: goto          108
       219: goto          69
       222: aload_0
       223: getfield      #38                 // Field _productionNext:Ljava/util/Map;
       226: invokeinterface #484,  1          // InterfaceMethod java/util/Map.entrySet:()Ljava/util/Set;
       231: invokeinterface #488,  1          // InterfaceMethod java/util/Set.iterator:()Ljava/util/Iterator;
       236: astore        6
       238: aload         6
       240: invokeinterface #97,  1           // InterfaceMethod java/util/Iterator.hasNext:()Z
       245: ifeq          391
       248: aload         6
       250: invokeinterface #103,  1          // InterfaceMethod java/util/Iterator.next:()Ljava/lang/Object;
       255: checkcast     #491                // class java/util/Map$Entry
       258: astore        7
       260: aload         7
       262: invokeinterface #493,  1          // InterfaceMethod java/util/Map$Entry.getValue:()Ljava/lang/Object;
       267: checkcast     #157                // class java/util/List
       270: invokeinterface #328,  1          // InterfaceMethod java/util/List.iterator:()Ljava/util/Iterator;
       275: astore        8
       277: aload         8
       279: invokeinterface #97,  1           // InterfaceMethod java/util/Iterator.hasNext:()Z
       284: ifeq          388
       287: aload         8
       289: invokeinterface #103,  1          // InterfaceMethod java/util/Iterator.next:()Ljava/lang/Object;
       294: checkcast     #133                // class ext/mods/gameserver/model/manor/SeedProduction
       297: astore        9
       299: aload_3
       300: iconst_1
       301: aload         7
       303: invokeinterface #496,  1          // InterfaceMethod java/util/Map$Entry.getKey:()Ljava/lang/Object;
       308: checkcast     #172                // class java/lang/Integer
       311: invokevirtual #499                // Method java/lang/Integer.intValue:()I
       314: invokeinterface #121,  3          // InterfaceMethod java/sql/PreparedStatement.setInt:(II)V
       319: aload_3
       320: iconst_2
       321: aload         9
       323: invokevirtual #448                // Method ext/mods/gameserver/model/manor/SeedProduction.getId:()I
       326: invokeinterface #121,  3          // InterfaceMethod java/sql/PreparedStatement.setInt:(II)V
       331: aload_3
       332: iconst_3
       333: aload         9
       335: invokevirtual #443                // Method ext/mods/gameserver/model/manor/SeedProduction.getAmount:()I
       338: i2l
       339: invokeinterface #444,  4          // InterfaceMethod java/sql/PreparedStatement.setLong:(IJ)V
       344: aload_3
       345: iconst_4
       346: aload         9
       348: invokevirtual #387                // Method ext/mods/gameserver/model/manor/SeedProduction.getStartAmount:()I
       351: i2l
       352: invokeinterface #444,  4          // InterfaceMethod java/sql/PreparedStatement.setLong:(IJ)V
       357: aload_3
       358: iconst_5
       359: aload         9
       361: invokevirtual #502                // Method ext/mods/gameserver/model/manor/SeedProduction.getPrice:()I
       364: i2l
       365: invokeinterface #444,  4          // InterfaceMethod java/sql/PreparedStatement.setLong:(IJ)V
       370: aload_3
       371: bipush        6
       373: iconst_1
       374: invokeinterface #503,  3          // InterfaceMethod java/sql/PreparedStatement.setBoolean:(IZ)V
       379: aload_3
       380: invokeinterface #449,  1          // InterfaceMethod java/sql/PreparedStatement.addBatch:()V
       385: goto          277
       388: goto          238
       391: aload_3
       392: invokeinterface #452,  1          // InterfaceMethod java/sql/PreparedStatement.executeBatch:()[I
       397: pop
       398: aload         4
       400: invokeinterface #481,  1          // InterfaceMethod java/sql/PreparedStatement.executeUpdate:()I
       405: pop
       406: aload_0
       407: getfield      #29                 // Field _procure:Ljava/util/Map;
       410: invokeinterface #484,  1          // InterfaceMethod java/util/Map.entrySet:()Ljava/util/Set;
       415: invokeinterface #488,  1          // InterfaceMethod java/util/Set.iterator:()Ljava/util/Iterator;
       420: astore        6
       422: aload         6
       424: invokeinterface #97,  1           // InterfaceMethod java/util/Iterator.hasNext:()Z
       429: ifeq          596
       432: aload         6
       434: invokeinterface #103,  1          // InterfaceMethod java/util/Iterator.next:()Ljava/lang/Object;
       439: checkcast     #491                // class java/util/Map$Entry
       442: astore        7
       444: aload         7
       446: invokeinterface #493,  1          // InterfaceMethod java/util/Map$Entry.getValue:()Ljava/lang/Object;
       451: checkcast     #157                // class java/util/List
       454: invokeinterface #328,  1          // InterfaceMethod java/util/List.iterator:()Ljava/util/Iterator;
       459: astore        8
       461: aload         8
       463: invokeinterface #97,  1           // InterfaceMethod java/util/Iterator.hasNext:()Z
       468: ifeq          593
       471: aload         8
       473: invokeinterface #103,  1          // InterfaceMethod java/util/Iterator.next:()Ljava/lang/Object;
       478: checkcast     #183                // class ext/mods/gameserver/model/manor/CropProcure
       481: astore        9
       483: aload         5
       485: iconst_1
       486: aload         7
       488: invokeinterface #496,  1          // InterfaceMethod java/util/Map$Entry.getKey:()Ljava/lang/Object;
       493: checkcast     #172                // class java/lang/Integer
       496: invokevirtual #499                // Method java/lang/Integer.intValue:()I
       499: invokeinterface #121,  3          // InterfaceMethod java/sql/PreparedStatement.setInt:(II)V
       504: aload         5
       506: iconst_2
       507: aload         9
       509: invokevirtual #342                // Method ext/mods/gameserver/model/manor/CropProcure.getId:()I
       512: invokeinterface #121,  3          // InterfaceMethod java/sql/PreparedStatement.setInt:(II)V
       517: aload         5
       519: iconst_3
       520: aload         9
       522: invokevirtual #332                // Method ext/mods/gameserver/model/manor/CropProcure.getAmount:()I
       525: i2l
       526: invokeinterface #444,  4          // InterfaceMethod java/sql/PreparedStatement.setLong:(IJ)V
       531: aload         5
       533: iconst_4
       534: aload         9
       536: invokevirtual #329                // Method ext/mods/gameserver/model/manor/CropProcure.getStartAmount:()I
       539: i2l
       540: invokeinterface #444,  4          // InterfaceMethod java/sql/PreparedStatement.setLong:(IJ)V
       545: aload         5
       547: iconst_5
       548: aload         9
       550: invokevirtual #364                // Method ext/mods/gameserver/model/manor/CropProcure.getPrice:()I
       553: i2l
       554: invokeinterface #444,  4          // InterfaceMethod java/sql/PreparedStatement.setLong:(IJ)V
       559: aload         5
       561: bipush        6
       563: aload         9
       565: invokevirtual #507                // Method ext/mods/gameserver/model/manor/CropProcure.getReward:()I
       568: invokeinterface #121,  3          // InterfaceMethod java/sql/PreparedStatement.setInt:(II)V
       573: aload         5
       575: bipush        7
       577: iconst_0
       578: invokeinterface #503,  3          // InterfaceMethod java/sql/PreparedStatement.setBoolean:(IZ)V
       583: aload         5
       585: invokeinterface #449,  1          // InterfaceMethod java/sql/PreparedStatement.addBatch:()V
       590: goto          461
       593: goto          422
       596: aload_0
       597: getfield      #32                 // Field _procureNext:Ljava/util/Map;
       600: invokeinterface #484,  1          // InterfaceMethod java/util/Map.entrySet:()Ljava/util/Set;
       605: invokeinterface #488,  1          // InterfaceMethod java/util/Set.iterator:()Ljava/util/Iterator;
       610: astore        6
       612: aload         6
       614: invokeinterface #97,  1           // InterfaceMethod java/util/Iterator.hasNext:()Z
       619: ifeq          786
       622: aload         6
       624: invokeinterface #103,  1          // InterfaceMethod java/util/Iterator.next:()Ljava/lang/Object;
       629: checkcast     #491                // class java/util/Map$Entry
       632: astore        7
       634: aload         7
       636: invokeinterface #493,  1          // InterfaceMethod java/util/Map$Entry.getValue:()Ljava/lang/Object;
       641: checkcast     #157                // class java/util/List
       644: invokeinterface #328,  1          // InterfaceMethod java/util/List.iterator:()Ljava/util/Iterator;
       649: astore        8
       651: aload         8
       653: invokeinterface #97,  1           // InterfaceMethod java/util/Iterator.hasNext:()Z
       658: ifeq          783
       661: aload         8
       663: invokeinterface #103,  1          // InterfaceMethod java/util/Iterator.next:()Ljava/lang/Object;
       668: checkcast     #183                // class ext/mods/gameserver/model/manor/CropProcure
       671: astore        9
       673: aload         5
       675: iconst_1
       676: aload         7
       678: invokeinterface #496,  1          // InterfaceMethod java/util/Map$Entry.getKey:()Ljava/lang/Object;
       683: checkcast     #172                // class java/lang/Integer
       686: invokevirtual #499                // Method java/lang/Integer.intValue:()I
       689: invokeinterface #121,  3          // InterfaceMethod java/sql/PreparedStatement.setInt:(II)V
       694: aload         5
       696: iconst_2
       697: aload         9
       699: invokevirtual #342                // Method ext/mods/gameserver/model/manor/CropProcure.getId:()I
       702: invokeinterface #121,  3          // InterfaceMethod java/sql/PreparedStatement.setInt:(II)V
       707: aload         5
       709: iconst_3
       710: aload         9
       712: invokevirtual #332                // Method ext/mods/gameserver/model/manor/CropProcure.getAmount:()I
       715: i2l
       716: invokeinterface #444,  4          // InterfaceMethod java/sql/PreparedStatement.setLong:(IJ)V
       721: aload         5
       723: iconst_4
       724: aload         9
       726: invokevirtual #329                // Method ext/mods/gameserver/model/manor/CropProcure.getStartAmount:()I
       729: i2l
       730: invokeinterface #444,  4          // InterfaceMethod java/sql/PreparedStatement.setLong:(IJ)V
       735: aload         5
       737: iconst_5
       738: aload         9
       740: invokevirtual #364                // Method ext/mods/gameserver/model/manor/CropProcure.getPrice:()I
       743: i2l
       744: invokeinterface #444,  4          // InterfaceMethod java/sql/PreparedStatement.setLong:(IJ)V
       749: aload         5
       751: bipush        6
       753: aload         9
       755: invokevirtual #507                // Method ext/mods/gameserver/model/manor/CropProcure.getReward:()I
       758: invokeinterface #121,  3          // InterfaceMethod java/sql/PreparedStatement.setInt:(II)V
       763: aload         5
       765: bipush        7
       767: iconst_1
       768: invokeinterface #503,  3          // InterfaceMethod java/sql/PreparedStatement.setBoolean:(IZ)V
       773: aload         5
       775: invokeinterface #449,  1          // InterfaceMethod java/sql/PreparedStatement.addBatch:()V
       780: goto          651
       783: goto          612
       786: aload         5
       788: invokeinterface #452,  1          // InterfaceMethod java/sql/PreparedStatement.executeBatch:()[I
       793: pop
       794: iconst_1
       795: istore        6
       797: aload         5
       799: ifnull        809
       802: aload         5
       804: invokeinterface #192,  1          // InterfaceMethod java/sql/PreparedStatement.close:()V
       809: aload         4
       811: ifnull        821
       814: aload         4
       816: invokeinterface #192,  1          // InterfaceMethod java/sql/PreparedStatement.close:()V
       821: aload_3
       822: ifnull        831
       825: aload_3
       826: invokeinterface #192,  1          // InterfaceMethod java/sql/PreparedStatement.close:()V
       831: aload_2
       832: ifnull        841
       835: aload_2
       836: invokeinterface #192,  1          // InterfaceMethod java/sql/PreparedStatement.close:()V
       841: aload_1
       842: ifnull        851
       845: aload_1
       846: invokeinterface #193,  1          // InterfaceMethod java/sql/Connection.close:()V
       851: iload         6
       853: ireturn
       854: astore        6
       856: aload         5
       858: ifnull        880
       861: aload         5
       863: invokeinterface #192,  1          // InterfaceMethod java/sql/PreparedStatement.close:()V
       868: goto          880
       871: astore        7
       873: aload         6
       875: aload         7
       877: invokevirtual #167                // Method java/lang/Throwable.addSuppressed:(Ljava/lang/Throwable;)V
       880: aload         6
       882: athrow
       883: astore        5
       885: aload         4
       887: ifnull        909
       890: aload         4
       892: invokeinterface #192,  1          // InterfaceMethod java/sql/PreparedStatement.close:()V
       897: goto          909
       900: astore        6
       902: aload         5
       904: aload         6
       906: invokevirtual #167                // Method java/lang/Throwable.addSuppressed:(Ljava/lang/Throwable;)V
       909: aload         5
       911: athrow
       912: astore        4
       914: aload_3
       915: ifnull        936
       918: aload_3
       919: invokeinterface #192,  1          // InterfaceMethod java/sql/PreparedStatement.close:()V
       924: goto          936
       927: astore        5
       929: aload         4
       931: aload         5
       933: invokevirtual #167                // Method java/lang/Throwable.addSuppressed:(Ljava/lang/Throwable;)V
       936: aload         4
       938: athrow
       939: astore_3
       940: aload_2
       941: ifnull        961
       944: aload_2
       945: invokeinterface #192,  1          // InterfaceMethod java/sql/PreparedStatement.close:()V
       950: goto          961
       953: astore        4
       955: aload_3
       956: aload         4
       958: invokevirtual #167                // Method java/lang/Throwable.addSuppressed:(Ljava/lang/Throwable;)V
       961: aload_3
       962: athrow
       963: astore_2
       964: aload_1
       965: ifnull        983
       968: aload_1
       969: invokeinterface #193,  1          // InterfaceMethod java/sql/Connection.close:()V
       974: goto          983
       977: astore_3
       978: aload_2
       979: aload_3
       980: invokevirtual #167                // Method java/lang/Throwable.addSuppressed:(Ljava/lang/Throwable;)V
       983: aload_2
       984: athrow
       985: astore_1
       986: getstatic     #50                 // Field LOGGER:Lext/mods/commons/logging/CLogger;
       989: ldc_w         #456                // String Unable to store manor data.
       992: aload_1
       993: invokevirtual #198                // Method ext/mods/commons/logging/CLogger.error:(Ljava/lang/Object;Ljava/lang/Throwable;)V
       996: iconst_0
       997: ireturn
      Exception table:
         from    to  target type
            46   797   854   Class java/lang/Throwable
           861   868   871   Class java/lang/Throwable
            35   809   883   Class java/lang/Throwable
           854   883   883   Class java/lang/Throwable
           890   897   900   Class java/lang/Throwable
            24   821   912   Class java/lang/Throwable
           854   912   912   Class java/lang/Throwable
           918   924   927   Class java/lang/Throwable
            14   831   939   Class java/lang/Throwable
           854   939   939   Class java/lang/Throwable
           944   950   953   Class java/lang/Throwable
             4   841   963   Class java/lang/Throwable
           854   963   963   Class java/lang/Throwable
           968   974   977   Class java/lang/Throwable
             0   851   985   Class java/lang/Exception
           854   985   985   Class java/lang/Exception
      LineNumberTable:
        line 443: 0
        line 444: 4
        line 445: 14
        line 446: 24
        line 447: 35
        line 449: 46
        line 451: 53
        line 453: 91
        line 455: 130
        line 456: 150
        line 457: 162
        line 458: 175
        line 459: 188
        line 460: 201
        line 461: 210
        line 462: 216
        line 463: 219
        line 465: 222
        line 467: 260
        line 469: 299
        line 470: 319
        line 471: 331
        line 472: 344
        line 473: 357
        line 474: 370
        line 475: 379
        line 476: 385
        line 477: 388
        line 479: 391
        line 481: 398
        line 483: 406
        line 485: 444
        line 487: 483
        line 488: 504
        line 489: 517
        line 490: 531
        line 491: 545
        line 492: 559
        line 493: 573
        line 494: 583
        line 495: 590
        line 496: 593
        line 498: 596
        line 500: 634
        line 502: 673
        line 503: 694
        line 504: 707
        line 505: 721
        line 506: 735
        line 507: 749
        line 508: 763
        line 509: 773
        line 510: 780
        line 511: 783
        line 513: 786
        line 515: 794
        line 516: 797
        line 515: 851
        line 443: 854
        line 517: 985
        line 519: 986
        line 520: 996
      LocalVariableTable:
        Start  Length  Slot  Name   Signature
          130      86     9    sp   Lext/mods/gameserver/model/manor/SeedProduction;
           91     128     7 entry   Ljava/util/Map$Entry;
          299      86     9    sp   Lext/mods/gameserver/model/manor/SeedProduction;
          260     128     7 entry   Ljava/util/Map$Entry;
          483     107     9    cp   Lext/mods/gameserver/model/manor/CropProcure;
          444     149     7 entry   Ljava/util/Map$Entry;
          673     107     9    cp   Lext/mods/gameserver/model/manor/CropProcure;
          634     149     7 entry   Ljava/util/Map$Entry;
           46     837     5    ip   Ljava/sql/PreparedStatement;
           35     877     4    dp   Ljava/sql/PreparedStatement;
           24     915     3    is   Ljava/sql/PreparedStatement;
           14     949     2    ds   Ljava/sql/PreparedStatement;
            4     981     1   con   Ljava/sql/Connection;
          986      12     1     e   Ljava/lang/Exception;
            0     998     0  this   Lext/mods/gameserver/data/manager/CastleManorManager;
      LocalVariableTypeTable:
        Start  Length  Slot  Name   Signature
           91     128     7 entry   Ljava/util/Map$Entry<Ljava/lang/Integer;Ljava/util/List<Lext/mods/gameserver/model/manor/SeedProduction;>;>;
          260     128     7 entry   Ljava/util/Map$Entry<Ljava/lang/Integer;Ljava/util/List<Lext/mods/gameserver/model/manor/SeedProduction;>;>;
          444     149     7 entry   Ljava/util/Map$Entry<Ljava/lang/Integer;Ljava/util/List<Lext/mods/gameserver/model/manor/CropProcure;>;>;
          634     149     7 entry   Ljava/util/Map$Entry<Ljava/lang/Integer;Ljava/util/List<Lext/mods/gameserver/model/manor/CropProcure;>;>;
      StackMapTable: number_of_entries = 37
        frame_type = 255 /* full_frame */
          offset_delta = 69
          locals = [ class ext/mods/gameserver/data/manager/CastleManorManager, class java/sql/Connection, class java/sql/PreparedStatement, class java/sql/PreparedStatement, class java/sql/PreparedStatement, class java/sql/PreparedStatement, class java/util/Iterator ]
          stack = []
        frame_type = 253 /* append */
          offset_delta = 38
          locals = [ class java/util/Map$Entry, class java/util/Iterator ]
        frame_type = 249 /* chop */
          offset_delta = 110
        frame_type = 250 /* chop */
          offset_delta = 2
        frame_type = 252 /* append */
          offset_delta = 15
          locals = [ class java/util/Iterator ]
        frame_type = 253 /* append */
          offset_delta = 38
          locals = [ class java/util/Map$Entry, class java/util/Iterator ]
        frame_type = 249 /* chop */
          offset_delta = 110
        frame_type = 250 /* chop */
          offset_delta = 2
        frame_type = 252 /* append */
          offset_delta = 30
          locals = [ class java/util/Iterator ]
        frame_type = 253 /* append */
          offset_delta = 38
          locals = [ class java/util/Map$Entry, class java/util/Iterator ]
        frame_type = 249 /* chop */
          offset_delta = 131
        frame_type = 250 /* chop */
          offset_delta = 2
        frame_type = 252 /* append */
          offset_delta = 15
          locals = [ class java/util/Iterator ]
        frame_type = 253 /* append */
          offset_delta = 38
          locals = [ class java/util/Map$Entry, class java/util/Iterator ]
        frame_type = 249 /* chop */
          offset_delta = 131
        frame_type = 250 /* chop */
          offset_delta = 2
        frame_type = 252 /* append */
          offset_delta = 22
          locals = [ int ]
        frame_type = 11 /* same */
        frame_type = 9 /* same */
        frame_type = 9 /* same */
        frame_type = 9 /* same */
        frame_type = 255 /* full_frame */
          offset_delta = 2
          locals = [ class ext/mods/gameserver/data/manager/CastleManorManager, class java/sql/Connection, class java/sql/PreparedStatement, class java/sql/PreparedStatement, class java/sql/PreparedStatement, class java/sql/PreparedStatement ]
          stack = [ class java/lang/Throwable ]
        frame_type = 255 /* full_frame */
          offset_delta = 16
          locals = [ class ext/mods/gameserver/data/manager/CastleManorManager, class java/sql/Connection, class java/sql/PreparedStatement, class java/sql/PreparedStatement, class java/sql/PreparedStatement, class java/sql/PreparedStatement, class java/lang/Throwable ]
          stack = [ class java/lang/Throwable ]
        frame_type = 8 /* same */
        frame_type = 255 /* full_frame */
          offset_delta = 2
          locals = [ class ext/mods/gameserver/data/manager/CastleManorManager, class java/sql/Connection, class java/sql/PreparedStatement, class java/sql/PreparedStatement, class java/sql/PreparedStatement ]
          stack = [ class java/lang/Throwable ]
        frame_type = 255 /* full_frame */
          offset_delta = 16
          locals = [ class ext/mods/gameserver/data/manager/CastleManorManager, class java/sql/Connection, class java/sql/PreparedStatement, class java/sql/PreparedStatement, class java/sql/PreparedStatement, class java/lang/Throwable ]
          stack = [ class java/lang/Throwable ]
        frame_type = 8 /* same */
        frame_type = 255 /* full_frame */
          offset_delta = 2
          locals = [ class ext/mods/gameserver/data/manager/CastleManorManager, class java/sql/Connection, class java/sql/PreparedStatement, class java/sql/PreparedStatement ]
          stack = [ class java/lang/Throwable ]
        frame_type = 255 /* full_frame */
          offset_delta = 14
          locals = [ class ext/mods/gameserver/data/manager/CastleManorManager, class java/sql/Connection, class java/sql/PreparedStatement, class java/sql/PreparedStatement, class java/lang/Throwable ]
          stack = [ class java/lang/Throwable ]
        frame_type = 8 /* same */
        frame_type = 255 /* full_frame */
          offset_delta = 2
          locals = [ class ext/mods/gameserver/data/manager/CastleManorManager, class java/sql/Connection, class java/sql/PreparedStatement ]
          stack = [ class java/lang/Throwable ]
        frame_type = 255 /* full_frame */
          offset_delta = 13
          locals = [ class ext/mods/gameserver/data/manager/CastleManorManager, class java/sql/Connection, class java/sql/PreparedStatement, class java/lang/Throwable ]
          stack = [ class java/lang/Throwable ]
        frame_type = 7 /* same */
        frame_type = 255 /* full_frame */
          offset_delta = 1
          locals = [ class ext/mods/gameserver/data/manager/CastleManorManager, class java/sql/Connection ]
          stack = [ class java/lang/Throwable ]
        frame_type = 255 /* full_frame */
          offset_delta = 13
          locals = [ class ext/mods/gameserver/data/manager/CastleManorManager, class java/sql/Connection, class java/lang/Throwable ]
          stack = [ class java/lang/Throwable ]
        frame_type = 5 /* same */
        frame_type = 255 /* full_frame */
          offset_delta = 1
          locals = [ class ext/mods/gameserver/data/manager/CastleManorManager ]
          stack = [ class java/lang/Exception ]

  public final void resetManorData(int);
    descriptor: (I)V
    flags: (0x0011) ACC_PUBLIC, ACC_FINAL
    Code:
      stack=2, locals=2, args_size=2
         0: aload_0
         1: getfield      #13                 // Field _mode:Lext/mods/gameserver/enums/ManorStatus;
         4: getstatic     #47                 // Field ext/mods/gameserver/enums/ManorStatus.DISABLED:Lext/mods/gameserver/enums/ManorStatus;
         7: if_acmpne     11
        10: return
        11: aload_0
        12: getfield      #29                 // Field _procure:Ljava/util/Map;
        15: iload_1
        16: invokestatic  #171                // Method java/lang/Integer.valueOf:(I)Ljava/lang/Integer;
        19: invokeinterface #325,  2          // InterfaceMethod java/util/Map.get:(Ljava/lang/Object;)Ljava/lang/Object;
        24: checkcast     #157                // class java/util/List
        27: invokeinterface #433,  1          // InterfaceMethod java/util/List.clear:()V
        32: aload_0
        33: getfield      #32                 // Field _procureNext:Ljava/util/Map;
        36: iload_1
        37: invokestatic  #171                // Method java/lang/Integer.valueOf:(I)Ljava/lang/Integer;
        40: invokeinterface #325,  2          // InterfaceMethod java/util/Map.get:(Ljava/lang/Object;)Ljava/lang/Object;
        45: checkcast     #157                // class java/util/List
        48: invokeinterface #433,  1          // InterfaceMethod java/util/List.clear:()V
        53: aload_0
        54: getfield      #35                 // Field _production:Ljava/util/Map;
        57: iload_1
        58: invokestatic  #171                // Method java/lang/Integer.valueOf:(I)Ljava/lang/Integer;
        61: invokeinterface #325,  2          // InterfaceMethod java/util/Map.get:(Ljava/lang/Object;)Ljava/lang/Object;
        66: checkcast     #157                // class java/util/List
        69: invokeinterface #433,  1          // InterfaceMethod java/util/List.clear:()V
        74: aload_0
        75: getfield      #38                 // Field _productionNext:Ljava/util/Map;
        78: iload_1
        79: invokestatic  #171                // Method java/lang/Integer.valueOf:(I)Ljava/lang/Integer;
        82: invokeinterface #325,  2          // InterfaceMethod java/util/Map.get:(Ljava/lang/Object;)Ljava/lang/Object;
        87: checkcast     #157                // class java/util/List
        90: invokeinterface #433,  1          // InterfaceMethod java/util/List.clear:()V
        95: return
      LineNumberTable:
        line 526: 0
        line 527: 10
        line 529: 11
        line 530: 32
        line 531: 53
        line 532: 74
        line 533: 95
      LocalVariableTable:
        Start  Length  Slot  Name   Signature
            0      96     0  this   Lext/mods/gameserver/data/manager/CastleManorManager;
            0      96     1 castleId   I
      StackMapTable: number_of_entries = 1
        frame_type = 11 /* same */

  public final boolean isUnderMaintenance();
    descriptor: ()Z
    flags: (0x0011) ACC_PUBLIC, ACC_FINAL
    Code:
      stack=2, locals=1, args_size=1
         0: aload_0
         1: getfield      #13                 // Field _mode:Lext/mods/gameserver/enums/ManorStatus;
         4: getstatic     #230                // Field ext/mods/gameserver/enums/ManorStatus.MAINTENANCE:Lext/mods/gameserver/enums/ManorStatus;
         7: if_acmpne     14
        10: iconst_1
        11: goto          15
        14: iconst_0
        15: ireturn
      LineNumberTable:
        line 537: 0
      LocalVariableTable:
        Start  Length  Slot  Name   Signature
            0      16     0  this   Lext/mods/gameserver/data/manager/CastleManorManager;
      StackMapTable: number_of_entries = 2
        frame_type = 14 /* same */
        frame_type = 64 /* same_locals_1_stack_item */
          stack = [ int ]

  public final boolean isManorApproved();
    descriptor: ()Z
    flags: (0x0011) ACC_PUBLIC, ACC_FINAL
    Code:
      stack=2, locals=1, args_size=1
         0: aload_0
         1: getfield      #13                 // Field _mode:Lext/mods/gameserver/enums/ManorStatus;
         4: getstatic     #7                  // Field ext/mods/gameserver/enums/ManorStatus.APPROVED:Lext/mods/gameserver/enums/ManorStatus;
         7: if_acmpne     14
        10: iconst_1
        11: goto          15
        14: iconst_0
        15: ireturn
      LineNumberTable:
        line 542: 0
      LocalVariableTable:
        Start  Length  Slot  Name   Signature
            0      16     0  this   Lext/mods/gameserver/data/manager/CastleManorManager;
      StackMapTable: number_of_entries = 2
        frame_type = 14 /* same */
        frame_type = 64 /* same_locals_1_stack_item */
          stack = [ int ]

  public final boolean isModifiablePeriod();
    descriptor: ()Z
    flags: (0x0011) ACC_PUBLIC, ACC_FINAL
    Code:
      stack=2, locals=1, args_size=1
         0: aload_0
         1: getfield      #13                 // Field _mode:Lext/mods/gameserver/enums/ManorStatus;
         4: getstatic     #227                // Field ext/mods/gameserver/enums/ManorStatus.MODIFIABLE:Lext/mods/gameserver/enums/ManorStatus;
         7: if_acmpne     14
        10: iconst_1
        11: goto          15
        14: iconst_0
        15: ireturn
      LineNumberTable:
        line 547: 0
      LocalVariableTable:
        Start  Length  Slot  Name   Signature
            0      16     0  this   Lext/mods/gameserver/data/manager/CastleManorManager;
      StackMapTable: number_of_entries = 2
        frame_type = 14 /* same */
        frame_type = 64 /* same_locals_1_stack_item */
          stack = [ int ]

  public final java.lang.String getCurrentModeName();
    descriptor: ()Ljava/lang/String;
    flags: (0x0011) ACC_PUBLIC, ACC_FINAL
    Code:
      stack=1, locals=1, args_size=1
         0: aload_0
         1: getfield      #13                 // Field _mode:Lext/mods/gameserver/enums/ManorStatus;
         4: invokevirtual #251                // Method ext/mods/gameserver/enums/ManorStatus.toString:()Ljava/lang/String;
         7: areturn
      LineNumberTable:
        line 552: 0
      LocalVariableTable:
        Start  Length  Slot  Name   Signature
            0       8     0  this   Lext/mods/gameserver/data/manager/CastleManorManager;

  public final java.lang.String getNextModeChange();
    descriptor: ()Ljava/lang/String;
    flags: (0x0011) ACC_PUBLIC, ACC_FINAL
    Code:
      stack=3, locals=1, args_size=1
         0: new           #510                // class java/text/SimpleDateFormat
         3: dup
         4: ldc_w         #512                // String dd/MM HH:mm:ss
         7: invokespecial #514                // Method java/text/SimpleDateFormat."<init>":(Ljava/lang/String;)V
        10: aload_0
        11: getfield      #18                 // Field _nextModeChange:Ljava/util/Calendar;
        14: invokevirtual #516                // Method java/util/Calendar.getTime:()Ljava/util/Date;
        17: invokevirtual #520                // Method java/text/SimpleDateFormat.format:(Ljava/util/Date;)Ljava/lang/String;
        20: areturn
      LineNumberTable:
        line 557: 0
      LocalVariableTable:
        Start  Length  Slot  Name   Signature
            0      21     0  this   Lext/mods/gameserver/data/manager/CastleManorManager;

  public final java.util.List<ext.mods.gameserver.model.manor.Seed> getCrops();
    descriptor: ()Ljava/util/List;
    flags: (0x0011) ACC_PUBLIC, ACC_FINAL
    Code:
      stack=2, locals=5, args_size=1
         0: new           #109                // class java/util/ArrayList
         3: dup
         4: invokespecial #111                // Method java/util/ArrayList."<init>":()V
         7: astore_1
         8: new           #109                // class java/util/ArrayList
        11: dup
        12: invokespecial #111                // Method java/util/ArrayList."<init>":()V
        15: astore_2
        16: aload_0
        17: getfield      #25                 // Field _seeds:Ljava/util/Map;
        20: invokeinterface #524,  1          // InterfaceMethod java/util/Map.values:()Ljava/util/Collection;
        25: invokeinterface #91,  1           // InterfaceMethod java/util/Collection.iterator:()Ljava/util/Iterator;
        30: astore_3
        31: aload_3
        32: invokeinterface #97,  1           // InterfaceMethod java/util/Iterator.hasNext:()Z
        37: ifeq          95
        40: aload_3
        41: invokeinterface #103,  1          // InterfaceMethod java/util/Iterator.next:()Ljava/lang/Object;
        46: checkcast     #354                // class ext/mods/gameserver/model/manor/Seed
        49: astore        4
        51: aload_2
        52: aload         4
        54: invokevirtual #527                // Method ext/mods/gameserver/model/manor/Seed.getCropId:()I
        57: invokestatic  #171                // Method java/lang/Integer.valueOf:(I)Ljava/lang/Integer;
        60: invokeinterface #530,  2          // InterfaceMethod java/util/List.contains:(Ljava/lang/Object;)Z
        65: ifne          92
        68: aload_1
        69: aload         4
        71: invokeinterface #156,  2          // InterfaceMethod java/util/List.add:(Ljava/lang/Object;)Z
        76: pop
        77: aload_2
        78: aload         4
        80: invokevirtual #527                // Method ext/mods/gameserver/model/manor/Seed.getCropId:()I
        83: invokestatic  #171                // Method java/lang/Integer.valueOf:(I)Ljava/lang/Integer;
        86: invokeinterface #156,  2          // InterfaceMethod java/util/List.add:(Ljava/lang/Object;)Z
        91: pop
        92: goto          31
        95: aload_2
        96: invokeinterface #433,  1          // InterfaceMethod java/util/List.clear:()V
       101: aload_1
       102: areturn
      LineNumberTable:
        line 562: 0
        line 563: 8
        line 564: 16
        line 566: 51
        line 568: 68
        line 569: 77
        line 571: 92
        line 572: 95
        line 573: 101
      LocalVariableTable:
        Start  Length  Slot  Name   Signature
           51      41     4  seed   Lext/mods/gameserver/model/manor/Seed;
            0     103     0  this   Lext/mods/gameserver/data/manager/CastleManorManager;
            8      95     1 seeds   Ljava/util/List;
           16      87     2 cropIds   Ljava/util/List;
      LocalVariableTypeTable:
        Start  Length  Slot  Name   Signature
            8      95     1 seeds   Ljava/util/List<Lext/mods/gameserver/model/manor/Seed;>;
           16      87     2 cropIds   Ljava/util/List<Ljava/lang/Integer;>;
      StackMapTable: number_of_entries = 3
        frame_type = 254 /* append */
          offset_delta = 31
          locals = [ class java/util/List, class java/util/List, class java/util/Iterator ]
        frame_type = 60 /* same */
        frame_type = 250 /* chop */
          offset_delta = 2
    Signature: #747                         // ()Ljava/util/List<Lext/mods/gameserver/model/manor/Seed;>;

  public final java.util.Set<ext.mods.gameserver.model.manor.Seed> getSeedsForCastle(int);
    descriptor: (I)Ljava/util/Set;
    flags: (0x0011) ACC_PUBLIC, ACC_FINAL
    Code:
      stack=2, locals=2, args_size=2
         0: aload_0
         1: getfield      #25                 // Field _seeds:Ljava/util/Map;
         4: invokeinterface #524,  1          // InterfaceMethod java/util/Map.values:()Ljava/util/Collection;
         9: invokeinterface #533,  1          // InterfaceMethod java/util/Collection.stream:()Ljava/util/stream/Stream;
        14: iload_1
        15: invokedynamic #537,  0            // InvokeDynamic #3:test:(I)Ljava/util/function/Predicate;
        20: invokeinterface #541,  2          // InterfaceMethod java/util/stream/Stream.filter:(Ljava/util/function/Predicate;)Ljava/util/stream/Stream;
        25: invokestatic  #547                // Method java/util/stream/Collectors.toSet:()Ljava/util/stream/Collector;
        28: invokeinterface #553,  2          // InterfaceMethod java/util/stream/Stream.collect:(Ljava/util/stream/Collector;)Ljava/lang/Object;
        33: checkcast     #489                // class java/util/Set
        36: areturn
      LineNumberTable:
        line 578: 0
      LocalVariableTable:
        Start  Length  Slot  Name   Signature
            0      37     0  this   Lext/mods/gameserver/data/manager/CastleManorManager;
            0      37     1 castleId   I
    Signature: #750                         // (I)Ljava/util/Set<Lext/mods/gameserver/model/manor/Seed;>;

  public final java.util.Set<java.lang.Integer> getCropIds();
    descriptor: ()Ljava/util/Set;
    flags: (0x0011) ACC_PUBLIC, ACC_FINAL
    Code:
      stack=2, locals=1, args_size=1
         0: aload_0
         1: getfield      #25                 // Field _seeds:Ljava/util/Map;
         4: invokeinterface #524,  1          // InterfaceMethod java/util/Map.values:()Ljava/util/Collection;
         9: invokeinterface #533,  1          // InterfaceMethod java/util/Collection.stream:()Ljava/util/stream/Stream;
        14: invokedynamic #557,  0            // InvokeDynamic #4:apply:()Ljava/util/function/Function;
        19: invokeinterface #561,  2          // InterfaceMethod java/util/stream/Stream.map:(Ljava/util/function/Function;)Ljava/util/stream/Stream;
        24: invokestatic  #547                // Method java/util/stream/Collectors.toSet:()Ljava/util/stream/Collector;
        27: invokeinterface #553,  2          // InterfaceMethod java/util/stream/Stream.collect:(Ljava/util/stream/Collector;)Ljava/lang/Object;
        32: checkcast     #489                // class java/util/Set
        35: areturn
      LineNumberTable:
        line 583: 0
      LocalVariableTable:
        Start  Length  Slot  Name   Signature
            0      36     0  this   Lext/mods/gameserver/data/manager/CastleManorManager;
    Signature: #752                         // ()Ljava/util/Set<Ljava/lang/Integer;>;

  public final ext.mods.gameserver.model.manor.Seed getSeed(int);
    descriptor: (I)Lext/mods/gameserver/model/manor/Seed;
    flags: (0x0011) ACC_PUBLIC, ACC_FINAL
    Code:
      stack=2, locals=2, args_size=2
         0: aload_0
         1: getfield      #25                 // Field _seeds:Ljava/util/Map;
         4: iload_1
         5: invokestatic  #171                // Method java/lang/Integer.valueOf:(I)Ljava/lang/Integer;
         8: invokeinterface #325,  2          // InterfaceMethod java/util/Map.get:(Ljava/lang/Object;)Ljava/lang/Object;
        13: checkcast     #354                // class ext/mods/gameserver/model/manor/Seed
        16: areturn
      LineNumberTable:
        line 588: 0
      LocalVariableTable:
        Start  Length  Slot  Name   Signature
            0      17     0  this   Lext/mods/gameserver/data/manager/CastleManorManager;
            0      17     1 seedId   I

  public final ext.mods.gameserver.model.manor.Seed getSeedByCrop(int, int);
    descriptor: (II)Lext/mods/gameserver/model/manor/Seed;
    flags: (0x0011) ACC_PUBLIC, ACC_FINAL
    Code:
      stack=3, locals=3, args_size=3
         0: aload_0
         1: getfield      #25                 // Field _seeds:Ljava/util/Map;
         4: invokeinterface #524,  1          // InterfaceMethod java/util/Map.values:()Ljava/util/Collection;
         9: invokeinterface #533,  1          // InterfaceMethod java/util/Collection.stream:()Ljava/util/stream/Stream;
        14: iload_2
        15: iload_1
        16: invokedynamic #565,  0            // InvokeDynamic #5:test:(II)Ljava/util/function/Predicate;
        21: invokeinterface #541,  2          // InterfaceMethod java/util/stream/Stream.filter:(Ljava/util/function/Predicate;)Ljava/util/stream/Stream;
        26: invokeinterface #568,  1          // InterfaceMethod java/util/stream/Stream.findFirst:()Ljava/util/Optional;
        31: aconst_null
        32: invokevirtual #572                // Method java/util/Optional.orElse:(Ljava/lang/Object;)Ljava/lang/Object;
        35: checkcast     #354                // class ext/mods/gameserver/model/manor/Seed
        38: areturn
      LineNumberTable:
        line 593: 0
      LocalVariableTable:
        Start  Length  Slot  Name   Signature
            0      39     0  this   Lext/mods/gameserver/data/manager/CastleManorManager;
            0      39     1 cropId   I
            0      39     2 castleId   I

  public final ext.mods.gameserver.model.manor.Seed getSeedByCrop(int);
    descriptor: (I)Lext/mods/gameserver/model/manor/Seed;
    flags: (0x0011) ACC_PUBLIC, ACC_FINAL
    Code:
      stack=2, locals=2, args_size=2
         0: aload_0
         1: getfield      #25                 // Field _seeds:Ljava/util/Map;
         4: invokeinterface #524,  1          // InterfaceMethod java/util/Map.values:()Ljava/util/Collection;
         9: invokeinterface #533,  1          // InterfaceMethod java/util/Collection.stream:()Ljava/util/stream/Stream;
        14: iload_1
        15: invokedynamic #577,  0            // InvokeDynamic #6:test:(I)Ljava/util/function/Predicate;
        20: invokeinterface #541,  2          // InterfaceMethod java/util/stream/Stream.filter:(Ljava/util/function/Predicate;)Ljava/util/stream/Stream;
        25: invokeinterface #568,  1          // InterfaceMethod java/util/stream/Stream.findFirst:()Ljava/util/Optional;
        30: aconst_null
        31: invokevirtual #572                // Method java/util/Optional.orElse:(Ljava/lang/Object;)Ljava/lang/Object;
        34: checkcast     #354                // class ext/mods/gameserver/model/manor/Seed
        37: areturn
      LineNumberTable:
        line 598: 0
      LocalVariableTable:
        Start  Length  Slot  Name   Signature
            0      38     0  this   Lext/mods/gameserver/data/manager/CastleManorManager;
            0      38     1 cropId   I

  public final int getSeedRewardByCrop(int, int);
    descriptor: (II)I
    flags: (0x0011) ACC_PUBLIC, ACC_FINAL
    Code:
      stack=2, locals=4, args_size=3
         0: aload_0
         1: iload_1
         2: invokevirtual #343                // Method getSeedByCrop:(I)Lext/mods/gameserver/model/manor/Seed;
         5: astore_3
         6: aload_3
         7: ifnull        27
        10: iload_2
        11: iconst_1
        12: if_icmpne     22
        15: aload_3
        16: invokevirtual #578                // Method ext/mods/gameserver/model/manor/Seed.getReward1:()I
        19: goto          26
        22: aload_3
        23: invokevirtual #581                // Method ext/mods/gameserver/model/manor/Seed.getReward2:()I
        26: ireturn
        27: iconst_0
        28: ireturn
      LineNumberTable:
        line 603: 0
        line 604: 6
        line 605: 10
        line 607: 27
      LocalVariableTable:
        Start  Length  Slot  Name   Signature
            0      29     0  this   Lext/mods/gameserver/data/manager/CastleManorManager;
            0      29     1 cropId   I
            0      29     2 rewardId   I
            6      23     3  seed   Lext/mods/gameserver/model/manor/Seed;
      StackMapTable: number_of_entries = 3
        frame_type = 252 /* append */
          offset_delta = 22
          locals = [ class ext/mods/gameserver/model/manor/Seed ]
        frame_type = 67 /* same_locals_1_stack_item */
          stack = [ int ]
        frame_type = 0 /* same */

  public static final ext.mods.gameserver.data.manager.CastleManorManager getInstance();
    descriptor: ()Lext/mods/gameserver/data/manager/CastleManorManager;
    flags: (0x0019) ACC_PUBLIC, ACC_STATIC, ACC_FINAL
    Code:
      stack=1, locals=0, args_size=0
         0: getstatic     #584                // Field ext/mods/gameserver/data/manager/CastleManorManager$SingletonHolder.INSTANCE:Lext/mods/gameserver/data/manager/CastleManorManager;
         3: areturn
      LineNumberTable:
        line 612: 0
}
SourceFile: "CastleManorManager.java"
NestMembers:
  ext/mods/gameserver/data/manager/CastleManorManager$1
  ext/mods/gameserver/data/manager/CastleManorManager$SingletonHolder
BootstrapMethods:
  0: #809 REF_invokeStatic java/lang/invoke/LambdaMetafactory.metafactory:(Ljava/lang/invoke/MethodHandles$Lookup;Ljava/lang/String;Ljava/lang/invoke/MethodType;Ljava/lang/invoke/MethodType;Ljava/lang/invoke/MethodHandle;Ljava/lang/invoke/MethodType;)Ljava/lang/invoke/CallSite;
    Method arguments:
      #777 ()V
      #778 REF_invokeVirtual ext/mods/gameserver/data/manager/CastleManorManager.storeMe:()Z
      #777 ()V
  1: #809 REF_invokeStatic java/lang/invoke/LambdaMetafactory.metafactory:(Ljava/lang/invoke/MethodHandles$Lookup;Ljava/lang/String;Ljava/lang/invoke/MethodType;Ljava/lang/invoke/MethodType;Ljava/lang/invoke/MethodHandle;Ljava/lang/invoke/MethodType;)Ljava/lang/invoke/CallSite;
    Method arguments:
      #779 (Ljava/lang/Object;)V
      #780 REF_invokeVirtual ext/mods/gameserver/data/manager/CastleManorManager.lambda$parseDocument$0:(Lorg/w3c/dom/Node;)V
      #783 (Lorg/w3c/dom/Node;)V
  2: #809 REF_invokeStatic java/lang/invoke/LambdaMetafactory.metafactory:(Ljava/lang/invoke/MethodHandles$Lookup;Ljava/lang/String;Ljava/lang/invoke/MethodType;Ljava/lang/invoke/MethodType;Ljava/lang/invoke/MethodHandle;Ljava/lang/invoke/MethodType;)Ljava/lang/invoke/CallSite;
    Method arguments:
      #777 ()V
      #784 REF_invokeVirtual ext/mods/gameserver/data/manager/CastleManorManager.changeMode:()V
      #777 ()V
  3: #809 REF_invokeStatic java/lang/invoke/LambdaMetafactory.metafactory:(Ljava/lang/invoke/MethodHandles$Lookup;Ljava/lang/String;Ljava/lang/invoke/MethodType;Ljava/lang/invoke/MethodType;Ljava/lang/invoke/MethodHandle;Ljava/lang/invoke/MethodType;)Ljava/lang/invoke/CallSite;
    Method arguments:
      #787 (Ljava/lang/Object;)Z
      #788 REF_invokeStatic ext/mods/gameserver/data/manager/CastleManorManager.lambda$getSeedsForCastle$0:(ILext/mods/gameserver/model/manor/Seed;)Z
      #791 (Lext/mods/gameserver/model/manor/Seed;)Z
  4: #809 REF_invokeStatic java/lang/invoke/LambdaMetafactory.metafactory:(Ljava/lang/invoke/MethodHandles$Lookup;Ljava/lang/String;Ljava/lang/invoke/MethodType;Ljava/lang/invoke/MethodType;Ljava/lang/invoke/MethodHandle;Ljava/lang/invoke/MethodType;)Ljava/lang/invoke/CallSite;
    Method arguments:
      #793 (Ljava/lang/Object;)Ljava/lang/Object;
      #794 REF_invokeVirtual ext/mods/gameserver/model/manor/Seed.getCropId:()I
      #795 (Lext/mods/gameserver/model/manor/Seed;)Ljava/lang/Integer;
  5: #809 REF_invokeStatic java/lang/invoke/LambdaMetafactory.metafactory:(Ljava/lang/invoke/MethodHandles$Lookup;Ljava/lang/String;Ljava/lang/invoke/MethodType;Ljava/lang/invoke/MethodType;Ljava/lang/invoke/MethodHandle;Ljava/lang/invoke/MethodType;)Ljava/lang/invoke/CallSite;
    Method arguments:
      #787 (Ljava/lang/Object;)Z
      #797 REF_invokeStatic ext/mods/gameserver/data/manager/CastleManorManager.lambda$getSeedByCrop$0:(IILext/mods/gameserver/model/manor/Seed;)Z
      #791 (Lext/mods/gameserver/model/manor/Seed;)Z
  6: #809 REF_invokeStatic java/lang/invoke/LambdaMetafactory.metafactory:(Ljava/lang/invoke/MethodHandles$Lookup;Ljava/lang/String;Ljava/lang/invoke/MethodType;Ljava/lang/invoke/MethodType;Ljava/lang/invoke/MethodHandle;Ljava/lang/invoke/MethodType;)Ljava/lang/invoke/CallSite;
    Method arguments:
      #787 (Ljava/lang/Object;)Z
      #800 REF_invokeStatic ext/mods/gameserver/data/manager/CastleManorManager.lambda$getSeedByCrop$1:(ILext/mods/gameserver/model/manor/Seed;)Z
      #791 (Lext/mods/gameserver/model/manor/Seed;)Z
  7: #809 REF_invokeStatic java/lang/invoke/LambdaMetafactory.metafactory:(Ljava/lang/invoke/MethodHandles$Lookup;Ljava/lang/String;Ljava/lang/invoke/MethodType;Ljava/lang/invoke/MethodType;Ljava/lang/invoke/MethodHandle;Ljava/lang/invoke/MethodType;)Ljava/lang/invoke/CallSite;
    Method arguments:
      #779 (Ljava/lang/Object;)V
      #803 REF_invokeVirtual ext/mods/gameserver/data/manager/CastleManorManager.lambda$parseDocument$1:(Lorg/w3c/dom/Node;)V
      #783 (Lorg/w3c/dom/Node;)V
  8: #809 REF_invokeStatic java/lang/invoke/LambdaMetafactory.metafactory:(Ljava/lang/invoke/MethodHandles$Lookup;Ljava/lang/String;Ljava/lang/invoke/MethodType;Ljava/lang/invoke/MethodType;Ljava/lang/invoke/MethodHandle;Ljava/lang/invoke/MethodType;)Ljava/lang/invoke/CallSite;
    Method arguments:
      #779 (Ljava/lang/Object;)V
      #806 REF_invokeVirtual ext/mods/gameserver/data/manager/CastleManorManager.lambda$parseDocument$2:(ILorg/w3c/dom/Node;)V
      #783 (Lorg/w3c/dom/Node;)V
InnerClasses:
  static #286;                            // class ext/mods/gameserver/data/manager/CastleManorManager$1
  public static #817= #491 of #178;       // Entry=class java/util/Map$Entry of class java/util/Map
  public static final #823= #819 of #821; // Lookup=class java/lang/invoke/MethodHandles$Lookup of class java/lang/invoke/MethodHandles
