// Bytecode for: ext.mods.gameserver.data.manager.LotteryManager$FinishLottery
// File: ext\mods\gameserver\data\manager\LotteryManager$FinishLottery.class

Classfile /c:/Users/User/Desktop/BrProject/bin/main/ext/mods/gameserver/data/manager/LotteryManager$FinishLottery.class
  Last modified 9 de jul de 2026; size 5607 bytes
  MD5 checksum 5dbe5156d9bdfe1ee2c3ca01352dec79
  Compiled from "LotteryManager.java"
class ext.mods.gameserver.data.manager.LotteryManager$FinishLottery implements java.lang.Runnable
  minor version: 0
  major version: 69
  flags: (0x0020) ACC_SUPER
  this_class: #10                         // ext/mods/gameserver/data/manager/LotteryManager$FinishLottery
  super_class: #16                        // java/lang/Object
  interfaces: 1, fields: 1, methods: 2, attributes: 3
Constant pool:
    #1 = Class              #2            // ext/mods/gameserver/data/manager/LotteryManager
    #2 = Utf8               ext/mods/gameserver/data/manager/LotteryManager
    #3 = Methodref          #4.#5         // java/util/Objects.requireNonNull:(Ljava/lang/Object;)Ljava/lang/Object;
    #4 = Class              #6            // java/util/Objects
    #5 = NameAndType        #7:#8         // requireNonNull:(Ljava/lang/Object;)Ljava/lang/Object;
    #6 = Utf8               java/util/Objects
    #7 = Utf8               requireNonNull
    #8 = Utf8               (Ljava/lang/Object;)Ljava/lang/Object;
    #9 = Fieldref           #10.#11       // ext/mods/gameserver/data/manager/LotteryManager$FinishLottery.this$0:Lext/mods/gameserver/data/manager/LotteryManager;
   #10 = Class              #12           // ext/mods/gameserver/data/manager/LotteryManager$FinishLottery
   #11 = NameAndType        #13:#14       // this$0:Lext/mods/gameserver/data/manager/LotteryManager;
   #12 = Utf8               ext/mods/gameserver/data/manager/LotteryManager$FinishLottery
   #13 = Utf8               this$0
   #14 = Utf8               Lext/mods/gameserver/data/manager/LotteryManager;
   #15 = Methodref          #16.#17       // java/lang/Object."<init>":()V
   #16 = Class              #18           // java/lang/Object
   #17 = NameAndType        #19:#20       // "<init>":()V
   #18 = Utf8               java/lang/Object
   #19 = Utf8               <init>
   #20 = Utf8               ()V
   #21 = Methodref          #22.#23       // ext/mods/commons/random/Rnd.get:(I)I
   #22 = Class              #24           // ext/mods/commons/random/Rnd
   #23 = NameAndType        #25:#26       // get:(I)I
   #24 = Utf8               ext/mods/commons/random/Rnd
   #25 = Utf8               get
   #26 = Utf8               (I)I
   #27 = Double             2.0d
   #29 = Methodref          #30.#31       // java/lang/Math.pow:(DD)D
   #30 = Class              #32           // java/lang/Math
   #31 = NameAndType        #33:#34       // pow:(DD)D
   #32 = Utf8               java/lang/Math
   #33 = Utf8               pow
   #34 = Utf8               (DD)D
   #35 = Methodref          #36.#37       // ext/mods/commons/pool/ConnectionPool.getConnection:()Ljava/sql/Connection;
   #36 = Class              #38           // ext/mods/commons/pool/ConnectionPool
   #37 = NameAndType        #39:#40       // getConnection:()Ljava/sql/Connection;
   #38 = Utf8               ext/mods/commons/pool/ConnectionPool
   #39 = Utf8               getConnection
   #40 = Utf8               ()Ljava/sql/Connection;
   #41 = String             #42           // SELECT enchant_level, custom_type2 FROM items WHERE item_id = 4442 AND custom_type1 = ?
   #42 = Utf8               SELECT enchant_level, custom_type2 FROM items WHERE item_id = 4442 AND custom_type1 = ?
   #43 = InterfaceMethodref #44.#45       // java/sql/Connection.prepareStatement:(Ljava/lang/String;)Ljava/sql/PreparedStatement;
   #44 = Class              #46           // java/sql/Connection
   #45 = NameAndType        #47:#48       // prepareStatement:(Ljava/lang/String;)Ljava/sql/PreparedStatement;
   #46 = Utf8               java/sql/Connection
   #47 = Utf8               prepareStatement
   #48 = Utf8               (Ljava/lang/String;)Ljava/sql/PreparedStatement;
   #49 = Methodref          #1.#50        // ext/mods/gameserver/data/manager/LotteryManager.getId:()I
   #50 = NameAndType        #51:#52       // getId:()I
   #51 = Utf8               getId
   #52 = Utf8               ()I
   #53 = InterfaceMethodref #54.#55       // java/sql/PreparedStatement.setInt:(II)V
   #54 = Class              #56           // java/sql/PreparedStatement
   #55 = NameAndType        #57:#58       // setInt:(II)V
   #56 = Utf8               java/sql/PreparedStatement
   #57 = Utf8               setInt
   #58 = Utf8               (II)V
   #59 = InterfaceMethodref #54.#60       // java/sql/PreparedStatement.executeQuery:()Ljava/sql/ResultSet;
   #60 = NameAndType        #61:#62       // executeQuery:()Ljava/sql/ResultSet;
   #61 = Utf8               executeQuery
   #62 = Utf8               ()Ljava/sql/ResultSet;
   #63 = InterfaceMethodref #64.#65       // java/sql/ResultSet.next:()Z
   #64 = Class              #66           // java/sql/ResultSet
   #65 = NameAndType        #67:#68       // next:()Z
   #66 = Utf8               java/sql/ResultSet
   #67 = Utf8               next
   #68 = Utf8               ()Z
   #69 = String             #70           // enchant_level
   #70 = Utf8               enchant_level
   #71 = InterfaceMethodref #64.#72       // java/sql/ResultSet.getInt:(Ljava/lang/String;)I
   #72 = NameAndType        #73:#74       // getInt:(Ljava/lang/String;)I
   #73 = Utf8               getInt
   #74 = Utf8               (Ljava/lang/String;)I
   #75 = String             #76           // custom_type2
   #76 = Utf8               custom_type2
   #77 = InterfaceMethodref #64.#78       // java/sql/ResultSet.close:()V
   #78 = NameAndType        #79:#20       // close:()V
   #79 = Utf8               close
   #80 = Class              #81           // java/lang/Throwable
   #81 = Utf8               java/lang/Throwable
   #82 = Methodref          #80.#83       // java/lang/Throwable.addSuppressed:(Ljava/lang/Throwable;)V
   #83 = NameAndType        #84:#85       // addSuppressed:(Ljava/lang/Throwable;)V
   #84 = Utf8               addSuppressed
   #85 = Utf8               (Ljava/lang/Throwable;)V
   #86 = InterfaceMethodref #54.#78       // java/sql/PreparedStatement.close:()V
   #87 = InterfaceMethodref #44.#78       // java/sql/Connection.close:()V
   #88 = Class              #89           // java/lang/Exception
   #89 = Utf8               java/lang/Exception
   #90 = Fieldref           #1.#91        // ext/mods/gameserver/data/manager/LotteryManager.LOGGER:Lext/mods/commons/logging/CLogger;
   #91 = NameAndType        #92:#93       // LOGGER:Lext/mods/commons/logging/CLogger;
   #92 = Utf8               LOGGER
   #93 = Utf8               Lext/mods/commons/logging/CLogger;
   #94 = String             #95           // Couldn\'t restore lottery data.
   #95 = Utf8               Couldn\'t restore lottery data.
   #96 = Methodref          #97.#98       // ext/mods/commons/logging/CLogger.error:(Ljava/lang/Object;Ljava/lang/Throwable;)V
   #97 = Class              #99           // ext/mods/commons/logging/CLogger
   #98 = NameAndType        #100:#101     // error:(Ljava/lang/Object;Ljava/lang/Throwable;)V
   #99 = Utf8               ext/mods/commons/logging/CLogger
  #100 = Utf8               error
  #101 = Utf8               (Ljava/lang/Object;Ljava/lang/Throwable;)V
  #102 = Fieldref           #103.#104     // ext/mods/Config.LOTTERY_2_AND_1_NUMBER_PRIZE:I
  #103 = Class              #105          // ext/mods/Config
  #104 = NameAndType        #106:#107     // LOTTERY_2_AND_1_NUMBER_PRIZE:I
  #105 = Utf8               ext/mods/Config
  #106 = Utf8               LOTTERY_2_AND_1_NUMBER_PRIZE
  #107 = Utf8               I
  #108 = Methodref          #1.#109       // ext/mods/gameserver/data/manager/LotteryManager.getPrize:()I
  #109 = NameAndType        #110:#52      // getPrize:()I
  #110 = Utf8               getPrize
  #111 = Fieldref           #103.#112     // ext/mods/Config.LOTTERY_5_NUMBER_RATE:D
  #112 = NameAndType        #113:#114     // LOTTERY_5_NUMBER_RATE:D
  #113 = Utf8               LOTTERY_5_NUMBER_RATE
  #114 = Utf8               D
  #115 = Fieldref           #103.#116     // ext/mods/Config.LOTTERY_4_NUMBER_RATE:D
  #116 = NameAndType        #117:#114     // LOTTERY_4_NUMBER_RATE:D
  #117 = Utf8               LOTTERY_4_NUMBER_RATE
  #118 = Fieldref           #103.#119     // ext/mods/Config.LOTTERY_3_NUMBER_RATE:D
  #119 = NameAndType        #120:#114     // LOTTERY_3_NUMBER_RATE:D
  #120 = Utf8               LOTTERY_3_NUMBER_RATE
  #121 = Fieldref           #103.#122     // ext/mods/Config.LOTTERY_PRIZE:I
  #122 = NameAndType        #123:#107     // LOTTERY_PRIZE:I
  #123 = Utf8               LOTTERY_PRIZE
  #124 = Fieldref           #125.#126     // ext/mods/gameserver/network/SystemMessageId.AMOUNT_FOR_WINNER_S1_IS_S2_ADENA_WE_HAVE_S3_PRIZE_WINNER:Lext/mods/gameserver/network/SystemMessageId;
  #125 = Class              #127          // ext/mods/gameserver/network/SystemMessageId
  #126 = NameAndType        #128:#129     // AMOUNT_FOR_WINNER_S1_IS_S2_ADENA_WE_HAVE_S3_PRIZE_WINNER:Lext/mods/gameserver/network/SystemMessageId;
  #127 = Utf8               ext/mods/gameserver/network/SystemMessageId
  #128 = Utf8               AMOUNT_FOR_WINNER_S1_IS_S2_ADENA_WE_HAVE_S3_PRIZE_WINNER
  #129 = Utf8               Lext/mods/gameserver/network/SystemMessageId;
  #130 = Methodref          #131.#132     // ext/mods/gameserver/network/serverpackets/SystemMessage.getSystemMessage:(Lext/mods/gameserver/network/SystemMessageId;)Lext/mods/gameserver/network/serverpackets/SystemMessage;
  #131 = Class              #133          // ext/mods/gameserver/network/serverpackets/SystemMessage
  #132 = NameAndType        #134:#135     // getSystemMessage:(Lext/mods/gameserver/network/SystemMessageId;)Lext/mods/gameserver/network/serverpackets/SystemMessage;
  #133 = Utf8               ext/mods/gameserver/network/serverpackets/SystemMessage
  #134 = Utf8               getSystemMessage
  #135 = Utf8               (Lext/mods/gameserver/network/SystemMessageId;)Lext/mods/gameserver/network/serverpackets/SystemMessage;
  #136 = Methodref          #131.#137     // ext/mods/gameserver/network/serverpackets/SystemMessage.addNumber:(I)Lext/mods/gameserver/network/serverpackets/SystemMessage;
  #137 = NameAndType        #138:#139     // addNumber:(I)Lext/mods/gameserver/network/serverpackets/SystemMessage;
  #138 = Utf8               addNumber
  #139 = Utf8               (I)Lext/mods/gameserver/network/serverpackets/SystemMessage;
  #140 = Methodref          #141.#142     // ext/mods/gameserver/model/World.toAllOnlinePlayers:(Lext/mods/gameserver/network/serverpackets/L2GameServerPacket;)V
  #141 = Class              #143          // ext/mods/gameserver/model/World
  #142 = NameAndType        #144:#145     // toAllOnlinePlayers:(Lext/mods/gameserver/network/serverpackets/L2GameServerPacket;)V
  #143 = Utf8               ext/mods/gameserver/model/World
  #144 = Utf8               toAllOnlinePlayers
  #145 = Utf8               (Lext/mods/gameserver/network/serverpackets/L2GameServerPacket;)V
  #146 = Fieldref           #125.#147     // ext/mods/gameserver/network/SystemMessageId.AMOUNT_FOR_LOTTERY_S1_IS_S2_ADENA_NO_WINNER:Lext/mods/gameserver/network/SystemMessageId;
  #147 = NameAndType        #148:#129     // AMOUNT_FOR_LOTTERY_S1_IS_S2_ADENA_NO_WINNER:Lext/mods/gameserver/network/SystemMessageId;
  #148 = Utf8               AMOUNT_FOR_LOTTERY_S1_IS_S2_ADENA_NO_WINNER
  #149 = String             #150          // UPDATE games SET finished=1, prize=?, newprize=?, number1=?, number2=?, prize1=?, prize2=?, prize3=? WHERE id=1 AND idnr=?
  #150 = Utf8               UPDATE games SET finished=1, prize=?, newprize=?, number1=?, number2=?, prize1=?, prize2=?, prize3=? WHERE id=1 AND idnr=?
  #151 = InterfaceMethodref #54.#152      // java/sql/PreparedStatement.execute:()Z
  #152 = NameAndType        #153:#68      // execute:()Z
  #153 = Utf8               execute
  #154 = String             #155          // Couldn\'t store finished lottery data.
  #155 = Utf8               Couldn\'t store finished lottery data.
  #156 = Class              #157          // ext/mods/gameserver/data/manager/LotteryManager$StartLottery
  #157 = Utf8               ext/mods/gameserver/data/manager/LotteryManager$StartLottery
  #158 = Methodref          #156.#159     // ext/mods/gameserver/data/manager/LotteryManager$StartLottery."<init>":(Lext/mods/gameserver/data/manager/LotteryManager;)V
  #159 = NameAndType        #19:#160      // "<init>":(Lext/mods/gameserver/data/manager/LotteryManager;)V
  #160 = Utf8               (Lext/mods/gameserver/data/manager/LotteryManager;)V
  #161 = Long               60000l
  #163 = Methodref          #164.#165     // ext/mods/commons/pool/ThreadPool.schedule:(Ljava/lang/Runnable;J)Ljava/util/concurrent/ScheduledFuture;
  #164 = Class              #166          // ext/mods/commons/pool/ThreadPool
  #165 = NameAndType        #167:#168     // schedule:(Ljava/lang/Runnable;J)Ljava/util/concurrent/ScheduledFuture;
  #166 = Utf8               ext/mods/commons/pool/ThreadPool
  #167 = Utf8               schedule
  #168 = Utf8               (Ljava/lang/Runnable;J)Ljava/util/concurrent/ScheduledFuture;
  #169 = Fieldref           #1.#170       // ext/mods/gameserver/data/manager/LotteryManager._number:I
  #170 = NameAndType        #171:#107     // _number:I
  #171 = Utf8               _number
  #172 = Fieldref           #1.#173       // ext/mods/gameserver/data/manager/LotteryManager._isStarted:Z
  #173 = NameAndType        #174:#175     // _isStarted:Z
  #174 = Utf8               _isStarted
  #175 = Utf8               Z
  #176 = Class              #177          // java/lang/Runnable
  #177 = Utf8               java/lang/Runnable
  #178 = Utf8               Code
  #179 = Utf8               LineNumberTable
  #180 = Utf8               LocalVariableTable
  #181 = Utf8               this
  #182 = Utf8               Lext/mods/gameserver/data/manager/LotteryManager$FinishLottery;
  #183 = Utf8               MethodParameters
  #184 = Utf8               run
  #185 = Utf8               j
  #186 = Utf8               found
  #187 = Utf8               i
  #188 = Utf8               val
  #189 = Utf8               val2
  #190 = Utf8               curenchant
  #191 = Utf8               curtype2
  #192 = Utf8               count
  #193 = Utf8               rs
  #194 = Utf8               Ljava/sql/ResultSet;
  #195 = Utf8               ps
  #196 = Utf8               Ljava/sql/PreparedStatement;
  #197 = Utf8               con
  #198 = Utf8               Ljava/sql/Connection;
  #199 = Utf8               e
  #200 = Utf8               Ljava/lang/Exception;
  #201 = Utf8               luckynums
  #202 = Utf8               [I
  #203 = Utf8               luckynum
  #204 = Utf8               enchant
  #205 = Utf8               type2
  #206 = Utf8               count1
  #207 = Utf8               count2
  #208 = Utf8               count3
  #209 = Utf8               count4
  #210 = Utf8               prize4
  #211 = Utf8               prize1
  #212 = Utf8               prize2
  #213 = Utf8               prize3
  #214 = Utf8               newPrize
  #215 = Utf8               StackMapTable
  #216 = Class              #202          // "[I"
  #217 = Utf8               SourceFile
  #218 = Utf8               LotteryManager.java
  #219 = Utf8               NestHost
  #220 = Utf8               InnerClasses
  #221 = Utf8               FinishLottery
  #222 = Utf8               StartLottery
{
  final ext.mods.gameserver.data.manager.LotteryManager this$0;
    descriptor: Lext/mods/gameserver/data/manager/LotteryManager;
    flags: (0x1010) ACC_FINAL, ACC_SYNTHETIC

  protected ext.mods.gameserver.data.manager.LotteryManager$FinishLottery(ext.mods.gameserver.data.manager.LotteryManager);
    descriptor: (Lext/mods/gameserver/data/manager/LotteryManager;)V
    flags: (0x0004) ACC_PROTECTED
    Code:
      stack=3, locals=2, args_size=2
         0: aload_0
         1: aload_1
         2: dup
         3: invokestatic  #3                  // Method java/util/Objects.requireNonNull:(Ljava/lang/Object;)Ljava/lang/Object;
         6: pop
         7: putfield      #9                  // Field this$0:Lext/mods/gameserver/data/manager/LotteryManager;
        10: aload_0
        11: invokespecial #15                 // Method java/lang/Object."<init>":()V
        14: return
      LineNumberTable:
        line 339: 0
        line 340: 14
      LocalVariableTable:
        Start  Length  Slot  Name   Signature
            0      15     0  this   Lext/mods/gameserver/data/manager/LotteryManager$FinishLottery;
    MethodParameters:
      Name                           Flags
      <no name>                      final synthetic

  public void run();
    descriptor: ()V
    flags: (0x0001) ACC_PUBLIC
    Code:
      stack=6, locals=18, args_size=1
         0: iconst_5
         1: newarray       int
         3: astore_1
         4: iconst_0
         5: istore_2
         6: iconst_0
         7: istore_3
         8: iload_3
         9: iconst_5
        10: if_icmpge     71
        13: iconst_1
        14: istore        4
        16: iload         4
        18: ifeq          61
        21: bipush        20
        23: invokestatic  #21                 // Method ext/mods/commons/random/Rnd.get:(I)I
        26: iconst_1
        27: iadd
        28: istore_2
        29: iconst_0
        30: istore        4
        32: iconst_0
        33: istore        5
        35: iload         5
        37: iload_3
        38: if_icmpge     58
        41: aload_1
        42: iload         5
        44: iaload
        45: iload_2
        46: if_icmpne     52
        49: iconst_1
        50: istore        4
        52: iinc          5, 1
        55: goto          35
        58: goto          16
        61: aload_1
        62: iload_3
        63: iload_2
        64: iastore
        65: iinc          3, 1
        68: goto          8
        71: iconst_0
        72: istore_3
        73: iconst_0
        74: istore        4
        76: iconst_0
        77: istore        5
        79: iload         5
        81: iconst_5
        82: if_icmpge     142
        85: aload_1
        86: iload         5
        88: iaload
        89: bipush        17
        91: if_icmpge     115
        94: iload_3
        95: i2d
        96: ldc2_w        #27                 // double 2.0d
        99: aload_1
       100: iload         5
       102: iaload
       103: iconst_1
       104: isub
       105: i2d
       106: invokestatic  #29                 // Method java/lang/Math.pow:(DD)D
       109: dadd
       110: d2i
       111: istore_3
       112: goto          136
       115: iload         4
       117: i2d
       118: ldc2_w        #27                 // double 2.0d
       121: aload_1
       122: iload         5
       124: iaload
       125: bipush        17
       127: isub
       128: i2d
       129: invokestatic  #29                 // Method java/lang/Math.pow:(DD)D
       132: dadd
       133: d2i
       134: istore        4
       136: iinc          5, 1
       139: goto          79
       142: iconst_0
       143: istore        5
       145: iconst_0
       146: istore        6
       148: iconst_0
       149: istore        7
       151: iconst_0
       152: istore        8
       154: invokestatic  #35                 // Method ext/mods/commons/pool/ConnectionPool.getConnection:()Ljava/sql/Connection;
       157: astore        9
       159: aload         9
       161: ldc           #41                 // String SELECT enchant_level, custom_type2 FROM items WHERE item_id = 4442 AND custom_type1 = ?
       163: invokeinterface #43,  2           // InterfaceMethod java/sql/Connection.prepareStatement:(Ljava/lang/String;)Ljava/sql/PreparedStatement;
       168: astore        10
       170: aload         10
       172: iconst_1
       173: aload_0
       174: getfield      #9                  // Field this$0:Lext/mods/gameserver/data/manager/LotteryManager;
       177: invokevirtual #49                 // Method ext/mods/gameserver/data/manager/LotteryManager.getId:()I
       180: invokeinterface #53,  3           // InterfaceMethod java/sql/PreparedStatement.setInt:(II)V
       185: aload         10
       187: invokeinterface #59,  1           // InterfaceMethod java/sql/PreparedStatement.executeQuery:()Ljava/sql/ResultSet;
       192: astore        11
       194: aload         11
       196: invokeinterface #63,  1           // InterfaceMethod java/sql/ResultSet.next:()Z
       201: ifeq          364
       204: aload         11
       206: ldc           #69                 // String enchant_level
       208: invokeinterface #71,  2           // InterfaceMethod java/sql/ResultSet.getInt:(Ljava/lang/String;)I
       213: iload_3
       214: iand
       215: istore        12
       217: aload         11
       219: ldc           #75                 // String custom_type2
       221: invokeinterface #71,  2           // InterfaceMethod java/sql/ResultSet.getInt:(Ljava/lang/String;)I
       226: iload         4
       228: iand
       229: istore        13
       231: iload         12
       233: ifne          244
       236: iload         13
       238: ifne          244
       241: goto          194
       244: iconst_0
       245: istore        14
       247: iconst_1
       248: istore        15
       250: iload         15
       252: bipush        16
       254: if_icmpgt     317
       257: iload         12
       259: iconst_2
       260: idiv
       261: istore        16
       263: iload         16
       265: i2d
       266: iload         12
       268: i2d
       269: ldc2_w        #27                 // double 2.0d
       272: ddiv
       273: dcmpl
       274: ifeq          280
       277: iinc          14, 1
       280: iload         13
       282: iconst_2
       283: idiv
       284: istore        17
       286: iload         17
       288: i2d
       289: iload         13
       291: i2d
       292: ldc2_w        #27                 // double 2.0d
       295: ddiv
       296: dcmpl
       297: ifeq          303
       300: iinc          14, 1
       303: iload         16
       305: istore        12
       307: iload         17
       309: istore        13
       311: iinc          15, 1
       314: goto          250
       317: iload         14
       319: iconst_5
       320: if_icmpne     329
       323: iinc          5, 1
       326: goto          361
       329: iload         14
       331: iconst_4
       332: if_icmpne     341
       335: iinc          6, 1
       338: goto          361
       341: iload         14
       343: iconst_3
       344: if_icmpne     353
       347: iinc          7, 1
       350: goto          361
       353: iload         14
       355: ifle          361
       358: iinc          8, 1
       361: goto          194
       364: aload         11
       366: ifnull        408
       369: aload         11
       371: invokeinterface #77,  1           // InterfaceMethod java/sql/ResultSet.close:()V
       376: goto          408
       379: astore        12
       381: aload         11
       383: ifnull        405
       386: aload         11
       388: invokeinterface #77,  1           // InterfaceMethod java/sql/ResultSet.close:()V
       393: goto          405
       396: astore        13
       398: aload         12
       400: aload         13
       402: invokevirtual #82                 // Method java/lang/Throwable.addSuppressed:(Ljava/lang/Throwable;)V
       405: aload         12
       407: athrow
       408: aload         10
       410: ifnull        452
       413: aload         10
       415: invokeinterface #86,  1           // InterfaceMethod java/sql/PreparedStatement.close:()V
       420: goto          452
       423: astore        11
       425: aload         10
       427: ifnull        449
       430: aload         10
       432: invokeinterface #86,  1           // InterfaceMethod java/sql/PreparedStatement.close:()V
       437: goto          449
       440: astore        12
       442: aload         11
       444: aload         12
       446: invokevirtual #82                 // Method java/lang/Throwable.addSuppressed:(Ljava/lang/Throwable;)V
       449: aload         11
       451: athrow
       452: aload         9
       454: ifnull        496
       457: aload         9
       459: invokeinterface #87,  1           // InterfaceMethod java/sql/Connection.close:()V
       464: goto          496
       467: astore        10
       469: aload         9
       471: ifnull        493
       474: aload         9
       476: invokeinterface #87,  1           // InterfaceMethod java/sql/Connection.close:()V
       481: goto          493
       484: astore        11
       486: aload         10
       488: aload         11
       490: invokevirtual #82                 // Method java/lang/Throwable.addSuppressed:(Ljava/lang/Throwable;)V
       493: aload         10
       495: athrow
       496: goto          511
       499: astore        9
       501: getstatic     #90                 // Field ext/mods/gameserver/data/manager/LotteryManager.LOGGER:Lext/mods/commons/logging/CLogger;
       504: ldc           #94                 // String Couldn\'t restore lottery data.
       506: aload         9
       508: invokevirtual #96                 // Method ext/mods/commons/logging/CLogger.error:(Ljava/lang/Object;Ljava/lang/Throwable;)V
       511: iload         8
       513: getstatic     #102                // Field ext/mods/Config.LOTTERY_2_AND_1_NUMBER_PRIZE:I
       516: imul
       517: istore        9
       519: iconst_0
       520: istore        10
       522: iconst_0
       523: istore        11
       525: iconst_0
       526: istore        12
       528: iload         5
       530: ifle          555
       533: aload_0
       534: getfield      #9                  // Field this$0:Lext/mods/gameserver/data/manager/LotteryManager;
       537: invokevirtual #108                // Method ext/mods/gameserver/data/manager/LotteryManager.getPrize:()I
       540: iload         9
       542: isub
       543: i2d
       544: getstatic     #111                // Field ext/mods/Config.LOTTERY_5_NUMBER_RATE:D
       547: dmul
       548: iload         5
       550: i2d
       551: ddiv
       552: d2i
       553: istore        10
       555: iload         6
       557: ifle          582
       560: aload_0
       561: getfield      #9                  // Field this$0:Lext/mods/gameserver/data/manager/LotteryManager;
       564: invokevirtual #108                // Method ext/mods/gameserver/data/manager/LotteryManager.getPrize:()I
       567: iload         9
       569: isub
       570: i2d
       571: getstatic     #115                // Field ext/mods/Config.LOTTERY_4_NUMBER_RATE:D
       574: dmul
       575: iload         6
       577: i2d
       578: ddiv
       579: d2i
       580: istore        11
       582: iload         7
       584: ifle          609
       587: aload_0
       588: getfield      #9                  // Field this$0:Lext/mods/gameserver/data/manager/LotteryManager;
       591: invokevirtual #108                // Method ext/mods/gameserver/data/manager/LotteryManager.getPrize:()I
       594: iload         9
       596: isub
       597: i2d
       598: getstatic     #118                // Field ext/mods/Config.LOTTERY_3_NUMBER_RATE:D
       601: dmul
       602: iload         7
       604: i2d
       605: ddiv
       606: d2i
       607: istore        12
       609: getstatic     #121                // Field ext/mods/Config.LOTTERY_PRIZE:I
       612: aload_0
       613: getfield      #9                  // Field this$0:Lext/mods/gameserver/data/manager/LotteryManager;
       616: invokevirtual #108                // Method ext/mods/gameserver/data/manager/LotteryManager.getPrize:()I
       619: iadd
       620: iload         10
       622: iload         11
       624: iadd
       625: iload         12
       627: iadd
       628: iload         9
       630: iadd
       631: isub
       632: istore        13
       634: iload         5
       636: ifle          676
       639: getstatic     #124                // Field ext/mods/gameserver/network/SystemMessageId.AMOUNT_FOR_WINNER_S1_IS_S2_ADENA_WE_HAVE_S3_PRIZE_WINNER:Lext/mods/gameserver/network/SystemMessageId;
       642: invokestatic  #130                // Method ext/mods/gameserver/network/serverpackets/SystemMessage.getSystemMessage:(Lext/mods/gameserver/network/SystemMessageId;)Lext/mods/gameserver/network/serverpackets/SystemMessage;
       645: aload_0
       646: getfield      #9                  // Field this$0:Lext/mods/gameserver/data/manager/LotteryManager;
       649: invokevirtual #49                 // Method ext/mods/gameserver/data/manager/LotteryManager.getId:()I
       652: invokevirtual #136                // Method ext/mods/gameserver/network/serverpackets/SystemMessage.addNumber:(I)Lext/mods/gameserver/network/serverpackets/SystemMessage;
       655: aload_0
       656: getfield      #9                  // Field this$0:Lext/mods/gameserver/data/manager/LotteryManager;
       659: invokevirtual #108                // Method ext/mods/gameserver/data/manager/LotteryManager.getPrize:()I
       662: invokevirtual #136                // Method ext/mods/gameserver/network/serverpackets/SystemMessage.addNumber:(I)Lext/mods/gameserver/network/serverpackets/SystemMessage;
       665: iload         5
       667: invokevirtual #136                // Method ext/mods/gameserver/network/serverpackets/SystemMessage.addNumber:(I)Lext/mods/gameserver/network/serverpackets/SystemMessage;
       670: invokestatic  #140                // Method ext/mods/gameserver/model/World.toAllOnlinePlayers:(Lext/mods/gameserver/network/serverpackets/L2GameServerPacket;)V
       673: goto          705
       676: getstatic     #146                // Field ext/mods/gameserver/network/SystemMessageId.AMOUNT_FOR_LOTTERY_S1_IS_S2_ADENA_NO_WINNER:Lext/mods/gameserver/network/SystemMessageId;
       679: invokestatic  #130                // Method ext/mods/gameserver/network/serverpackets/SystemMessage.getSystemMessage:(Lext/mods/gameserver/network/SystemMessageId;)Lext/mods/gameserver/network/serverpackets/SystemMessage;
       682: aload_0
       683: getfield      #9                  // Field this$0:Lext/mods/gameserver/data/manager/LotteryManager;
       686: invokevirtual #49                 // Method ext/mods/gameserver/data/manager/LotteryManager.getId:()I
       689: invokevirtual #136                // Method ext/mods/gameserver/network/serverpackets/SystemMessage.addNumber:(I)Lext/mods/gameserver/network/serverpackets/SystemMessage;
       692: aload_0
       693: getfield      #9                  // Field this$0:Lext/mods/gameserver/data/manager/LotteryManager;
       696: invokevirtual #108                // Method ext/mods/gameserver/data/manager/LotteryManager.getPrize:()I
       699: invokevirtual #136                // Method ext/mods/gameserver/network/serverpackets/SystemMessage.addNumber:(I)Lext/mods/gameserver/network/serverpackets/SystemMessage;
       702: invokestatic  #140                // Method ext/mods/gameserver/model/World.toAllOnlinePlayers:(Lext/mods/gameserver/network/serverpackets/L2GameServerPacket;)V
       705: invokestatic  #35                 // Method ext/mods/commons/pool/ConnectionPool.getConnection:()Ljava/sql/Connection;
       708: astore        14
       710: aload         14
       712: ldc           #149                // String UPDATE games SET finished=1, prize=?, newprize=?, number1=?, number2=?, prize1=?, prize2=?, prize3=? WHERE id=1 AND idnr=?
       714: invokeinterface #43,  2           // InterfaceMethod java/sql/Connection.prepareStatement:(Ljava/lang/String;)Ljava/sql/PreparedStatement;
       719: astore        15
       721: aload         15
       723: iconst_1
       724: aload_0
       725: getfield      #9                  // Field this$0:Lext/mods/gameserver/data/manager/LotteryManager;
       728: invokevirtual #108                // Method ext/mods/gameserver/data/manager/LotteryManager.getPrize:()I
       731: invokeinterface #53,  3           // InterfaceMethod java/sql/PreparedStatement.setInt:(II)V
       736: aload         15
       738: iconst_2
       739: iload         13
       741: invokeinterface #53,  3           // InterfaceMethod java/sql/PreparedStatement.setInt:(II)V
       746: aload         15
       748: iconst_3
       749: iload_3
       750: invokeinterface #53,  3           // InterfaceMethod java/sql/PreparedStatement.setInt:(II)V
       755: aload         15
       757: iconst_4
       758: iload         4
       760: invokeinterface #53,  3           // InterfaceMethod java/sql/PreparedStatement.setInt:(II)V
       765: aload         15
       767: iconst_5
       768: iload         10
       770: invokeinterface #53,  3           // InterfaceMethod java/sql/PreparedStatement.setInt:(II)V
       775: aload         15
       777: bipush        6
       779: iload         11
       781: invokeinterface #53,  3           // InterfaceMethod java/sql/PreparedStatement.setInt:(II)V
       786: aload         15
       788: bipush        7
       790: iload         12
       792: invokeinterface #53,  3           // InterfaceMethod java/sql/PreparedStatement.setInt:(II)V
       797: aload         15
       799: bipush        8
       801: aload_0
       802: getfield      #9                  // Field this$0:Lext/mods/gameserver/data/manager/LotteryManager;
       805: invokevirtual #49                 // Method ext/mods/gameserver/data/manager/LotteryManager.getId:()I
       808: invokeinterface #53,  3           // InterfaceMethod java/sql/PreparedStatement.setInt:(II)V
       813: aload         15
       815: invokeinterface #151,  1          // InterfaceMethod java/sql/PreparedStatement.execute:()Z
       820: pop
       821: aload         15
       823: ifnull        865
       826: aload         15
       828: invokeinterface #86,  1           // InterfaceMethod java/sql/PreparedStatement.close:()V
       833: goto          865
       836: astore        16
       838: aload         15
       840: ifnull        862
       843: aload         15
       845: invokeinterface #86,  1           // InterfaceMethod java/sql/PreparedStatement.close:()V
       850: goto          862
       853: astore        17
       855: aload         16
       857: aload         17
       859: invokevirtual #82                 // Method java/lang/Throwable.addSuppressed:(Ljava/lang/Throwable;)V
       862: aload         16
       864: athrow
       865: aload         14
       867: ifnull        909
       870: aload         14
       872: invokeinterface #87,  1           // InterfaceMethod java/sql/Connection.close:()V
       877: goto          909
       880: astore        15
       882: aload         14
       884: ifnull        906
       887: aload         14
       889: invokeinterface #87,  1           // InterfaceMethod java/sql/Connection.close:()V
       894: goto          906
       897: astore        16
       899: aload         15
       901: aload         16
       903: invokevirtual #82                 // Method java/lang/Throwable.addSuppressed:(Ljava/lang/Throwable;)V
       906: aload         15
       908: athrow
       909: goto          924
       912: astore        14
       914: getstatic     #90                 // Field ext/mods/gameserver/data/manager/LotteryManager.LOGGER:Lext/mods/commons/logging/CLogger;
       917: ldc           #154                // String Couldn\'t store finished lottery data.
       919: aload         14
       921: invokevirtual #96                 // Method ext/mods/commons/logging/CLogger.error:(Ljava/lang/Object;Ljava/lang/Throwable;)V
       924: new           #156                // class ext/mods/gameserver/data/manager/LotteryManager$StartLottery
       927: dup
       928: aload_0
       929: getfield      #9                  // Field this$0:Lext/mods/gameserver/data/manager/LotteryManager;
       932: invokespecial #158                // Method ext/mods/gameserver/data/manager/LotteryManager$StartLottery."<init>":(Lext/mods/gameserver/data/manager/LotteryManager;)V
       935: ldc2_w        #161                // long 60000l
       938: invokestatic  #163                // Method ext/mods/commons/pool/ThreadPool.schedule:(Ljava/lang/Runnable;J)Ljava/util/concurrent/ScheduledFuture;
       941: pop
       942: aload_0
       943: getfield      #9                  // Field this$0:Lext/mods/gameserver/data/manager/LotteryManager;
       946: dup
       947: getfield      #169                // Field ext/mods/gameserver/data/manager/LotteryManager._number:I
       950: iconst_1
       951: iadd
       952: putfield      #169                // Field ext/mods/gameserver/data/manager/LotteryManager._number:I
       955: aload_0
       956: getfield      #9                  // Field this$0:Lext/mods/gameserver/data/manager/LotteryManager;
       959: iconst_0
       960: putfield      #172                // Field ext/mods/gameserver/data/manager/LotteryManager._isStarted:Z
       963: return
      Exception table:
         from    to  target type
           194   364   379   Class java/lang/Throwable
           386   393   396   Class java/lang/Throwable
           170   408   423   Class java/lang/Throwable
           430   437   440   Class java/lang/Throwable
           159   452   467   Class java/lang/Throwable
           474   481   484   Class java/lang/Throwable
           154   496   499   Class java/lang/Exception
           721   821   836   Class java/lang/Throwable
           843   850   853   Class java/lang/Throwable
           710   865   880   Class java/lang/Throwable
           887   894   897   Class java/lang/Throwable
           705   909   912   Class java/lang/Exception
      LineNumberTable:
        line 345: 0
        line 346: 4
        line 348: 6
        line 350: 13
        line 352: 16
        line 354: 21
        line 355: 29
        line 357: 32
        line 358: 41
        line 359: 49
        line 357: 52
        line 362: 61
        line 348: 65
        line 365: 71
        line 366: 73
        line 368: 76
        line 370: 85
        line 371: 94
        line 373: 115
        line 368: 136
        line 376: 142
        line 377: 145
        line 378: 148
        line 379: 151
        line 381: 154
        line 382: 159
        line 384: 170
        line 386: 185
        line 388: 194
        line 390: 204
        line 391: 217
        line 393: 231
        line 394: 241
        line 396: 244
        line 398: 247
        line 400: 257
        line 402: 263
        line 403: 277
        line 405: 280
        line 407: 286
        line 408: 300
        line 410: 303
        line 411: 307
        line 398: 311
        line 414: 317
        line 415: 323
        line 416: 329
        line 417: 335
        line 418: 341
        line 419: 347
        line 420: 353
        line 421: 358
        line 422: 361
        line 423: 364
        line 386: 379
        line 424: 408
        line 381: 423
        line 424: 452
        line 381: 467
        line 428: 496
        line 425: 499
        line 427: 501
        line 430: 511
        line 431: 519
        line 432: 522
        line 433: 525
        line 435: 528
        line 436: 533
        line 438: 555
        line 439: 560
        line 441: 582
        line 442: 587
        line 444: 609
        line 446: 634
        line 447: 639
        line 449: 676
        line 451: 705
        line 452: 710
        line 454: 721
        line 455: 736
        line 456: 746
        line 457: 755
        line 458: 765
        line 459: 775
        line 460: 786
        line 461: 797
        line 462: 813
        line 463: 821
        line 451: 836
        line 463: 865
        line 451: 880
        line 467: 909
        line 464: 912
        line 466: 914
        line 469: 924
        line 470: 942
        line 472: 955
        line 473: 963
      LocalVariableTable:
        Start  Length  Slot  Name   Signature
           35      23     5     j   I
           16      49     4 found   Z
            8      63     3     i   I
           79      63     5     i   I
          263      48    16   val   I
          286      25    17  val2   I
          250      67    15     i   I
          217     144    12 curenchant   I
          231     130    13 curtype2   I
          247     114    14 count   I
          194     214    11    rs   Ljava/sql/ResultSet;
          170     282    10    ps   Ljava/sql/PreparedStatement;
          159     337     9   con   Ljava/sql/Connection;
          501      10     9     e   Ljava/lang/Exception;
          721     144    15    ps   Ljava/sql/PreparedStatement;
          710     199    14   con   Ljava/sql/Connection;
          914      10    14     e   Ljava/lang/Exception;
            0     964     0  this   Lext/mods/gameserver/data/manager/LotteryManager$FinishLottery;
            4     960     1 luckynums   [I
            6     958     2 luckynum   I
           73     891     3 enchant   I
           76     888     4 type2   I
          145     819     5 count1   I
          148     816     6 count2   I
          151     813     7 count3   I
          154     810     8 count4   I
          519     445     9 prize4   I
          522     442    10 prize1   I
          525     439    11 prize2   I
          528     436    12 prize3   I
          634     330    13 newPrize   I
      StackMapTable: number_of_entries = 51
        frame_type = 254 /* append */
          offset_delta = 8
          locals = [ class "[I", int, int ]
        frame_type = 252 /* append */
          offset_delta = 7
          locals = [ int ]
        frame_type = 252 /* append */
          offset_delta = 18
          locals = [ int ]
        frame_type = 16 /* same */
        frame_type = 250 /* chop */
          offset_delta = 5
        frame_type = 2 /* same */
        frame_type = 249 /* chop */
          offset_delta = 9
        frame_type = 254 /* append */
          offset_delta = 7
          locals = [ int, int, int ]
        frame_type = 35 /* same */
        frame_type = 20 /* same */
        frame_type = 250 /* chop */
          offset_delta = 5
        frame_type = 255 /* full_frame */
          offset_delta = 51
          locals = [ class ext/mods/gameserver/data/manager/LotteryManager$FinishLottery, class "[I", int, int, int, int, int, int, int, class java/sql/Connection, class java/sql/PreparedStatement, class java/sql/ResultSet ]
          stack = []
        frame_type = 253 /* append */
          offset_delta = 49
          locals = [ int, int ]
        frame_type = 253 /* append */
          offset_delta = 5
          locals = [ int, int ]
        frame_type = 252 /* append */
          offset_delta = 29
          locals = [ int ]
        frame_type = 252 /* append */
          offset_delta = 22
          locals = [ int ]
        frame_type = 248 /* chop */
          offset_delta = 13
        frame_type = 11 /* same */
        frame_type = 11 /* same */
        frame_type = 11 /* same */
        frame_type = 248 /* chop */
          offset_delta = 7
        frame_type = 2 /* same */
        frame_type = 78 /* same_locals_1_stack_item */
          stack = [ class java/lang/Throwable ]
        frame_type = 255 /* full_frame */
          offset_delta = 16
          locals = [ class ext/mods/gameserver/data/manager/LotteryManager$FinishLottery, class "[I", int, int, int, int, int, int, int, class java/sql/Connection, class java/sql/PreparedStatement, class java/sql/ResultSet, class java/lang/Throwable ]
          stack = [ class java/lang/Throwable ]
        frame_type = 8 /* same */
        frame_type = 249 /* chop */
          offset_delta = 2
        frame_type = 78 /* same_locals_1_stack_item */
          stack = [ class java/lang/Throwable ]
        frame_type = 255 /* full_frame */
          offset_delta = 16
          locals = [ class ext/mods/gameserver/data/manager/LotteryManager$FinishLottery, class "[I", int, int, int, int, int, int, int, class java/sql/Connection, class java/sql/PreparedStatement, class java/lang/Throwable ]
          stack = [ class java/lang/Throwable ]
        frame_type = 8 /* same */
        frame_type = 249 /* chop */
          offset_delta = 2
        frame_type = 78 /* same_locals_1_stack_item */
          stack = [ class java/lang/Throwable ]
        frame_type = 255 /* full_frame */
          offset_delta = 16
          locals = [ class ext/mods/gameserver/data/manager/LotteryManager$FinishLottery, class "[I", int, int, int, int, int, int, int, class java/sql/Connection, class java/lang/Throwable ]
          stack = [ class java/lang/Throwable ]
        frame_type = 8 /* same */
        frame_type = 249 /* chop */
          offset_delta = 2
        frame_type = 66 /* same_locals_1_stack_item */
          stack = [ class java/lang/Exception ]
        frame_type = 11 /* same */
        frame_type = 255 /* full_frame */
          offset_delta = 43
          locals = [ class ext/mods/gameserver/data/manager/LotteryManager$FinishLottery, class "[I", int, int, int, int, int, int, int, int, int, int, int ]
          stack = []
        frame_type = 26 /* same */
        frame_type = 26 /* same */
        frame_type = 252 /* append */
          offset_delta = 66
          locals = [ int ]
        frame_type = 28 /* same */
        frame_type = 255 /* full_frame */
          offset_delta = 130
          locals = [ class ext/mods/gameserver/data/manager/LotteryManager$FinishLottery, class "[I", int, int, int, int, int, int, int, int, int, int, int, int, class java/sql/Connection, class java/sql/PreparedStatement ]
          stack = [ class java/lang/Throwable ]
        frame_type = 255 /* full_frame */
          offset_delta = 16
          locals = [ class ext/mods/gameserver/data/manager/LotteryManager$FinishLottery, class "[I", int, int, int, int, int, int, int, int, int, int, int, int, class java/sql/Connection, class java/sql/PreparedStatement, class java/lang/Throwable ]
          stack = [ class java/lang/Throwable ]
        frame_type = 8 /* same */
        frame_type = 249 /* chop */
          offset_delta = 2
        frame_type = 78 /* same_locals_1_stack_item */
          stack = [ class java/lang/Throwable ]
        frame_type = 255 /* full_frame */
          offset_delta = 16
          locals = [ class ext/mods/gameserver/data/manager/LotteryManager$FinishLottery, class "[I", int, int, int, int, int, int, int, int, int, int, int, int, class java/sql/Connection, class java/lang/Throwable ]
          stack = [ class java/lang/Throwable ]
        frame_type = 8 /* same */
        frame_type = 249 /* chop */
          offset_delta = 2
        frame_type = 66 /* same_locals_1_stack_item */
          stack = [ class java/lang/Exception ]
        frame_type = 11 /* same */
}
SourceFile: "LotteryManager.java"
NestHost: class ext/mods/gameserver/data/manager/LotteryManager
