// Bytecode for: ext.mods.gameserver.data.manager.PcCafeManager
// File: ext\mods\gameserver\data\manager\PcCafeManager.class

Classfile /c:/Users/User/Desktop/BrProject/bin/main/ext/mods/gameserver/data/manager/PcCafeManager.class
  Last modified 9 de jul de 2026; size 7029 bytes
  MD5 checksum e666928cbc3a518def1dc6f50e6e9189
  Compiled from "PcCafeManager.java"
public class ext.mods.gameserver.data.manager.PcCafeManager
  minor version: 0
  major version: 69
  flags: (0x0021) ACC_PUBLIC, ACC_SUPER
  this_class: #13                         // ext/mods/gameserver/data/manager/PcCafeManager
  super_class: #2                         // java/lang/Object
  interfaces: 0, fields: 14, methods: 12, attributes: 4
Constant pool:
    #1 = Methodref          #2.#3         // java/lang/Object."<init>":()V
    #2 = Class              #4            // java/lang/Object
    #3 = NameAndType        #5:#6         // "<init>":()V
    #4 = Utf8               java/lang/Object
    #5 = Utf8               <init>
    #6 = Utf8               ()V
    #7 = Methodref          #8.#9         // ext/mods/gameserver/custom/data/PcCafeData.getInstance:()Lext/mods/gameserver/custom/data/PcCafeData;
    #8 = Class              #10           // ext/mods/gameserver/custom/data/PcCafeData
    #9 = NameAndType        #11:#12       // getInstance:()Lext/mods/gameserver/custom/data/PcCafeData;
   #10 = Utf8               ext/mods/gameserver/custom/data/PcCafeData
   #11 = Utf8               getInstance
   #12 = Utf8               ()Lext/mods/gameserver/custom/data/PcCafeData;
   #13 = Class              #14           // ext/mods/gameserver/data/manager/PcCafeManager
   #14 = Utf8               ext/mods/gameserver/data/manager/PcCafeManager
   #15 = String             #16           // enable_timer_bonus
   #16 = Utf8               enable_timer_bonus
   #17 = Methodref          #8.#18        // ext/mods/gameserver/custom/data/PcCafeData.getCafeBool:(Ljava/lang/String;Z)Z
   #18 = NameAndType        #19:#20       // getCafeBool:(Ljava/lang/String;Z)Z
   #19 = Utf8               getCafeBool
   #20 = Utf8               (Ljava/lang/String;Z)Z
   #21 = InvokeDynamic      #0:#22        // #0:run:(Lext/mods/gameserver/data/manager/PcCafeManager;)Ljava/lang/Runnable;
   #22 = NameAndType        #23:#24       // run:(Lext/mods/gameserver/data/manager/PcCafeManager;)Ljava/lang/Runnable;
   #23 = Utf8               run
   #24 = Utf8               (Lext/mods/gameserver/data/manager/PcCafeManager;)Ljava/lang/Runnable;
   #25 = Fieldref           #26.#27       // java/util/concurrent/TimeUnit.MINUTES:Ljava/util/concurrent/TimeUnit;
   #26 = Class              #28           // java/util/concurrent/TimeUnit
   #27 = NameAndType        #29:#30       // MINUTES:Ljava/util/concurrent/TimeUnit;
   #28 = Utf8               java/util/concurrent/TimeUnit
   #29 = Utf8               MINUTES
   #30 = Utf8               Ljava/util/concurrent/TimeUnit;
   #31 = Long               15l
   #33 = Methodref          #26.#34       // java/util/concurrent/TimeUnit.toMillis:(J)J
   #34 = NameAndType        #35:#36       // toMillis:(J)J
   #35 = Utf8               toMillis
   #36 = Utf8               (J)J
   #37 = Methodref          #38.#39       // ext/mods/commons/pool/ThreadPool.scheduleAtFixedRate:(Ljava/lang/Runnable;JJ)Ljava/util/concurrent/ScheduledFuture;
   #38 = Class              #40           // ext/mods/commons/pool/ThreadPool
   #39 = NameAndType        #41:#42       // scheduleAtFixedRate:(Ljava/lang/Runnable;JJ)Ljava/util/concurrent/ScheduledFuture;
   #40 = Utf8               ext/mods/commons/pool/ThreadPool
   #41 = Utf8               scheduleAtFixedRate
   #42 = Utf8               (Ljava/lang/Runnable;JJ)Ljava/util/concurrent/ScheduledFuture;
   #43 = String             #44           // enable
   #44 = Utf8               enable
   #45 = Methodref          #8.#46        // ext/mods/gameserver/custom/data/PcCafeData.getCafeInt:(Ljava/lang/String;I)I
   #46 = NameAndType        #47:#48       // getCafeInt:(Ljava/lang/String;I)I
   #47 = Utf8               getCafeInt
   #48 = Utf8               (Ljava/lang/String;I)I
   #49 = Methodref          #13.#50       // ext/mods/gameserver/data/manager/PcCafeManager.enableEvent:()I
   #50 = NameAndType        #51:#52       // enableEvent:()I
   #51 = Utf8               enableEvent
   #52 = Utf8               ()I
   #53 = Methodref          #54.#55       // ext/mods/gameserver/model/World.getInstance:()Lext/mods/gameserver/model/World;
   #54 = Class              #56           // ext/mods/gameserver/model/World
   #55 = NameAndType        #11:#57       // getInstance:()Lext/mods/gameserver/model/World;
   #56 = Utf8               ext/mods/gameserver/model/World
   #57 = Utf8               ()Lext/mods/gameserver/model/World;
   #58 = Methodref          #54.#59       // ext/mods/gameserver/model/World.getPlayers:()Ljava/util/Collection;
   #59 = NameAndType        #60:#61       // getPlayers:()Ljava/util/Collection;
   #60 = Utf8               getPlayers
   #61 = Utf8               ()Ljava/util/Collection;
   #62 = InterfaceMethodref #63.#64       // java/util/Collection.iterator:()Ljava/util/Iterator;
   #63 = Class              #65           // java/util/Collection
   #64 = NameAndType        #66:#67       // iterator:()Ljava/util/Iterator;
   #65 = Utf8               java/util/Collection
   #66 = Utf8               iterator
   #67 = Utf8               ()Ljava/util/Iterator;
   #68 = InterfaceMethodref #69.#70       // java/util/Iterator.hasNext:()Z
   #69 = Class              #71           // java/util/Iterator
   #70 = NameAndType        #72:#73       // hasNext:()Z
   #71 = Utf8               java/util/Iterator
   #72 = Utf8               hasNext
   #73 = Utf8               ()Z
   #74 = InterfaceMethodref #69.#75       // java/util/Iterator.next:()Ljava/lang/Object;
   #75 = NameAndType        #76:#77       // next:()Ljava/lang/Object;
   #76 = Utf8               next
   #77 = Utf8               ()Ljava/lang/Object;
   #78 = Class              #79           // ext/mods/gameserver/model/actor/Player
   #79 = Utf8               ext/mods/gameserver/model/actor/Player
   #80 = Methodref          #13.#81       // ext/mods/gameserver/data/manager/PcCafeManager.isEventEnabled:()Z
   #81 = NameAndType        #82:#73       // isEventEnabled:()Z
   #82 = Utf8               isEventEnabled
   #83 = Methodref          #78.#84       // ext/mods/gameserver/model/actor/Player.getClient:()Lext/mods/gameserver/network/GameClient;
   #84 = NameAndType        #85:#86       // getClient:()Lext/mods/gameserver/network/GameClient;
   #85 = Utf8               getClient
   #86 = Utf8               ()Lext/mods/gameserver/network/GameClient;
   #87 = Methodref          #88.#89       // ext/mods/gameserver/network/GameClient.isDetached:()Z
   #88 = Class              #90           // ext/mods/gameserver/network/GameClient
   #89 = NameAndType        #91:#73       // isDetached:()Z
   #90 = Utf8               ext/mods/gameserver/network/GameClient
   #91 = Utf8               isDetached
   #92 = String             #93           // timer_points
   #93 = Utf8               timer_points
   #94 = Methodref          #95.#96       // ext/mods/commons/random/Rnd.get:(I)I
   #95 = Class              #97           // ext/mods/commons/random/Rnd
   #96 = NameAndType        #98:#99       // get:(I)I
   #97 = Utf8               ext/mods/commons/random/Rnd
   #98 = Utf8               get
   #99 = Utf8               (I)I
  #100 = String             #101          // timer_double_points_probability
  #101 = Utf8               timer_double_points_probability
  #102 = Methodref          #78.#103      // ext/mods/gameserver/model/actor/Player.increasePcCafePoints:(IZ)V
  #103 = NameAndType        #104:#105     // increasePcCafePoints:(IZ)V
  #104 = Utf8               increasePcCafePoints
  #105 = Utf8               (IZ)V
  #106 = String             #107          // enable_daily_bonus
  #107 = Utf8               enable_daily_bonus
  #108 = Methodref          #78.#109      // ext/mods/gameserver/model/actor/Player.getMemos:()Lext/mods/gameserver/model/memo/PlayerMemo;
  #109 = NameAndType        #110:#111     // getMemos:()Lext/mods/gameserver/model/memo/PlayerMemo;
  #110 = Utf8               getMemos
  #111 = Utf8               ()Lext/mods/gameserver/model/memo/PlayerMemo;
  #112 = String             #113          // cafe_points_today
  #113 = Utf8               cafe_points_today
  #114 = Methodref          #115.#116     // ext/mods/gameserver/model/memo/PlayerMemo.getBool:(Ljava/lang/String;Z)Z
  #115 = Class              #117          // ext/mods/gameserver/model/memo/PlayerMemo
  #116 = NameAndType        #118:#20      // getBool:(Ljava/lang/String;Z)Z
  #117 = Utf8               ext/mods/gameserver/model/memo/PlayerMemo
  #118 = Utf8               getBool
  #119 = Methodref          #115.#120     // ext/mods/gameserver/model/memo/PlayerMemo.set:(Ljava/lang/String;Z)V
  #120 = NameAndType        #121:#122     // set:(Ljava/lang/String;Z)V
  #121 = Utf8               set
  #122 = Utf8               (Ljava/lang/String;Z)V
  #123 = String             #124          // daily_bonus_points
  #124 = Utf8               daily_bonus_points
  #125 = Methodref          #78.#126      // ext/mods/gameserver/model/actor/Player.increasePcCafePoints:(I)V
  #126 = NameAndType        #104:#127     // increasePcCafePoints:(I)V
  #127 = Utf8               (I)V
  #128 = Class              #129          // ext/mods/gameserver/network/serverpackets/ExPCCafePointInfo
  #129 = Utf8               ext/mods/gameserver/network/serverpackets/ExPCCafePointInfo
  #130 = Methodref          #78.#131      // ext/mods/gameserver/model/actor/Player.getPcCafePoints:()I
  #131 = NameAndType        #132:#52      // getPcCafePoints:()I
  #132 = Utf8               getPcCafePoints
  #133 = Fieldref           #134.#135     // ext/mods/gameserver/enums/PcCafeConsumeType.NORMAL:Lext/mods/gameserver/enums/PcCafeConsumeType;
  #134 = Class              #136          // ext/mods/gameserver/enums/PcCafeConsumeType
  #135 = NameAndType        #137:#138     // NORMAL:Lext/mods/gameserver/enums/PcCafeConsumeType;
  #136 = Utf8               ext/mods/gameserver/enums/PcCafeConsumeType
  #137 = Utf8               NORMAL
  #138 = Utf8               Lext/mods/gameserver/enums/PcCafeConsumeType;
  #139 = Methodref          #128.#140     // ext/mods/gameserver/network/serverpackets/ExPCCafePointInfo."<init>":(IILext/mods/gameserver/enums/PcCafeConsumeType;)V
  #140 = NameAndType        #5:#141       // "<init>":(IILext/mods/gameserver/enums/PcCafeConsumeType;)V
  #141 = Utf8               (IILext/mods/gameserver/enums/PcCafeConsumeType;)V
  #142 = Methodref          #78.#143      // ext/mods/gameserver/model/actor/Player.sendPacket:(Lext/mods/gameserver/network/serverpackets/L2GameServerPacket;)V
  #143 = NameAndType        #144:#145     // sendPacket:(Lext/mods/gameserver/network/serverpackets/L2GameServerPacket;)V
  #144 = Utf8               sendPacket
  #145 = Utf8               (Lext/mods/gameserver/network/serverpackets/L2GameServerPacket;)V
  #146 = String             #147          // enable_farming_bonus
  #147 = Utf8               enable_farming_bonus
  #148 = Methodref          #78.#149      // ext/mods/gameserver/model/actor/Player.getTarget:()Lext/mods/gameserver/model/WorldObject;
  #149 = NameAndType        #150:#151     // getTarget:()Lext/mods/gameserver/model/WorldObject;
  #150 = Utf8               getTarget
  #151 = Utf8               ()Lext/mods/gameserver/model/WorldObject;
  #152 = Class              #153          // ext/mods/gameserver/model/actor/Creature
  #153 = Utf8               ext/mods/gameserver/model/actor/Creature
  #154 = Methodref          #152.#155     // ext/mods/gameserver/model/actor/Creature.getStatus:()Lext/mods/gameserver/model/actor/status/CreatureStatus;
  #155 = NameAndType        #156:#157     // getStatus:()Lext/mods/gameserver/model/actor/status/CreatureStatus;
  #156 = Utf8               getStatus
  #157 = Utf8               ()Lext/mods/gameserver/model/actor/status/CreatureStatus;
  #158 = Methodref          #159.#160     // ext/mods/gameserver/model/actor/status/CreatureStatus.getLevel:()I
  #159 = Class              #161          // ext/mods/gameserver/model/actor/status/CreatureStatus
  #160 = NameAndType        #162:#52      // getLevel:()I
  #161 = Utf8               ext/mods/gameserver/model/actor/status/CreatureStatus
  #162 = Utf8               getLevel
  #163 = Methodref          #78.#164      // ext/mods/gameserver/model/actor/Player.getStatus:()Lext/mods/gameserver/model/actor/status/PlayerStatus;
  #164 = NameAndType        #156:#165     // getStatus:()Lext/mods/gameserver/model/actor/status/PlayerStatus;
  #165 = Utf8               ()Lext/mods/gameserver/model/actor/status/PlayerStatus;
  #166 = Methodref          #167.#160     // ext/mods/gameserver/model/actor/status/PlayerStatus.getLevel:()I
  #167 = Class              #168          // ext/mods/gameserver/model/actor/status/PlayerStatus
  #168 = Utf8               ext/mods/gameserver/model/actor/status/PlayerStatus
  #169 = String             #170          // farming_bonus_level_diff
  #170 = Utf8               farming_bonus_level_diff
  #171 = String             #172          // farming_bonus_points
  #172 = Utf8               farming_bonus_points
  #173 = Methodref          #174.#175     // ext/mods/commons/pool/ConnectionPool.getConnection:()Ljava/sql/Connection;
  #174 = Class              #176          // ext/mods/commons/pool/ConnectionPool
  #175 = NameAndType        #177:#178     // getConnection:()Ljava/sql/Connection;
  #176 = Utf8               ext/mods/commons/pool/ConnectionPool
  #177 = Utf8               getConnection
  #178 = Utf8               ()Ljava/sql/Connection;
  #179 = String             #180          // DELETE FROM character_memo WHERE var=\'cafe_points_today\'
  #180 = Utf8               DELETE FROM character_memo WHERE var=\'cafe_points_today\'
  #181 = InterfaceMethodref #182.#183     // java/sql/Connection.prepareStatement:(Ljava/lang/String;)Ljava/sql/PreparedStatement;
  #182 = Class              #184          // java/sql/Connection
  #183 = NameAndType        #185:#186     // prepareStatement:(Ljava/lang/String;)Ljava/sql/PreparedStatement;
  #184 = Utf8               java/sql/Connection
  #185 = Utf8               prepareStatement
  #186 = Utf8               (Ljava/lang/String;)Ljava/sql/PreparedStatement;
  #187 = InterfaceMethodref #188.#189     // java/sql/PreparedStatement.executeUpdate:()I
  #188 = Class              #190          // java/sql/PreparedStatement
  #189 = NameAndType        #191:#52      // executeUpdate:()I
  #190 = Utf8               java/sql/PreparedStatement
  #191 = Utf8               executeUpdate
  #192 = InterfaceMethodref #188.#193     // java/sql/PreparedStatement.close:()V
  #193 = NameAndType        #194:#6       // close:()V
  #194 = Utf8               close
  #195 = Class              #196          // java/lang/Throwable
  #196 = Utf8               java/lang/Throwable
  #197 = Methodref          #195.#198     // java/lang/Throwable.addSuppressed:(Ljava/lang/Throwable;)V
  #198 = NameAndType        #199:#200     // addSuppressed:(Ljava/lang/Throwable;)V
  #199 = Utf8               addSuppressed
  #200 = Utf8               (Ljava/lang/Throwable;)V
  #201 = InterfaceMethodref #182.#193     // java/sql/Connection.close:()V
  #202 = Class              #203          // java/lang/Exception
  #203 = Utf8               java/lang/Exception
  #204 = Fieldref           #13.#205      // ext/mods/gameserver/data/manager/PcCafeManager.LOGGER:Lext/mods/commons/logging/CLogger;
  #205 = NameAndType        #206:#207     // LOGGER:Lext/mods/commons/logging/CLogger;
  #206 = Utf8               LOGGER
  #207 = Utf8               Lext/mods/commons/logging/CLogger;
  #208 = String             #209          // Failed to reset daily login pc points.
  #209 = Utf8               Failed to reset daily login pc points.
  #210 = Methodref          #211.#212     // ext/mods/commons/logging/CLogger.error:(Ljava/lang/Object;Ljava/lang/Throwable;)V
  #211 = Class              #213          // ext/mods/commons/logging/CLogger
  #212 = NameAndType        #214:#215     // error:(Ljava/lang/Object;Ljava/lang/Throwable;)V
  #213 = Utf8               ext/mods/commons/logging/CLogger
  #214 = Utf8               error
  #215 = Utf8               (Ljava/lang/Object;Ljava/lang/Throwable;)V
  #216 = InterfaceMethodref #63.#217      // java/util/Collection.stream:()Ljava/util/stream/Stream;
  #217 = NameAndType        #218:#219     // stream:()Ljava/util/stream/Stream;
  #218 = Utf8               stream
  #219 = Utf8               ()Ljava/util/stream/Stream;
  #220 = InvokeDynamic      #1:#221       // #1:accept:()Ljava/util/function/Consumer;
  #221 = NameAndType        #222:#223     // accept:()Ljava/util/function/Consumer;
  #222 = Utf8               accept
  #223 = Utf8               ()Ljava/util/function/Consumer;
  #224 = InterfaceMethodref #225.#226     // java/util/stream/Stream.forEach:(Ljava/util/function/Consumer;)V
  #225 = Class              #227          // java/util/stream/Stream
  #226 = NameAndType        #228:#229     // forEach:(Ljava/util/function/Consumer;)V
  #227 = Utf8               java/util/stream/Stream
  #228 = Utf8               forEach
  #229 = Utf8               (Ljava/util/function/Consumer;)V
  #230 = String             #231          // enable_pvp_bonus
  #231 = Utf8               enable_pvp_bonus
  #232 = String             #233          // pvp_bonus_points
  #233 = Utf8               pvp_bonus_points
  #234 = Fieldref           #235.#236     // ext/mods/gameserver/data/manager/PcCafeManager$SingletonHolder.INSTANCE:Lext/mods/gameserver/data/manager/PcCafeManager;
  #235 = Class              #237          // ext/mods/gameserver/data/manager/PcCafeManager$SingletonHolder
  #236 = NameAndType        #238:#239     // INSTANCE:Lext/mods/gameserver/data/manager/PcCafeManager;
  #237 = Utf8               ext/mods/gameserver/data/manager/PcCafeManager$SingletonHolder
  #238 = Utf8               INSTANCE
  #239 = Utf8               Lext/mods/gameserver/data/manager/PcCafeManager;
  #240 = Methodref          #115.#241     // ext/mods/gameserver/model/memo/PlayerMemo.remove:(Ljava/lang/Object;)Ljava/lang/Object;
  #241 = NameAndType        #242:#243     // remove:(Ljava/lang/Object;)Ljava/lang/Object;
  #242 = Utf8               remove
  #243 = Utf8               (Ljava/lang/Object;)Ljava/lang/Object;
  #244 = Methodref          #13.#245      // ext/mods/gameserver/data/manager/PcCafeManager.rewardPoint:()V
  #245 = NameAndType        #246:#6       // rewardPoint:()V
  #246 = Utf8               rewardPoint
  #247 = Methodref          #248.#249     // java/lang/Class.getName:()Ljava/lang/String;
  #248 = Class              #250          // java/lang/Class
  #249 = NameAndType        #251:#252     // getName:()Ljava/lang/String;
  #250 = Utf8               java/lang/Class
  #251 = Utf8               getName
  #252 = Utf8               ()Ljava/lang/String;
  #253 = Methodref          #211.#254     // ext/mods/commons/logging/CLogger."<init>":(Ljava/lang/String;)V
  #254 = NameAndType        #5:#255       // "<init>":(Ljava/lang/String;)V
  #255 = Utf8               (Ljava/lang/String;)V
  #256 = Utf8               CLEAR_MEMO
  #257 = Utf8               Ljava/lang/String;
  #258 = Utf8               ConstantValue
  #259 = Utf8               ENABLE
  #260 = Utf8               ENABLE_TIMER_BONUS
  #261 = Utf8               TIMER_POINTS
  #262 = Utf8               DOUBLE_POINTS_PROBABILITY
  #263 = Utf8               ENABLE_DAILY_BONUS
  #264 = Utf8               DAILY_BONUS_POINTS
  #265 = Utf8               DAILY_POINTS
  #266 = Utf8               ENABLE_FARMING_BONUS
  #267 = Utf8               FARMING_BONUS_POINTS
  #268 = Utf8               FARMING_BONUS_LEVEL_DIFF
  #269 = Utf8               ENABLE_PVP_BONUS
  #270 = Utf8               PVP_BONUS_POINTS
  #271 = Utf8               Code
  #272 = Utf8               LineNumberTable
  #273 = Utf8               LocalVariableTable
  #274 = Utf8               this
  #275 = Utf8               StackMapTable
  #276 = Utf8               timerPoints
  #277 = Utf8               I
  #278 = Utf8               doublePoints
  #279 = Utf8               Z
  #280 = Utf8               player
  #281 = Utf8               Lext/mods/gameserver/model/actor/Player;
  #282 = Utf8               onPlayerLogin
  #283 = Utf8               (Lext/mods/gameserver/model/actor/Player;)V
  #284 = Utf8               onAttackableKill
  #285 = Utf8               target
  #286 = Utf8               Lext/mods/gameserver/model/actor/Creature;
  #287 = Utf8               levelDiff
  #288 = Utf8               maxLevelDiff
  #289 = Utf8               onReset
  #290 = Utf8               ps
  #291 = Utf8               Ljava/sql/PreparedStatement;
  #292 = Utf8               con
  #293 = Utf8               Ljava/sql/Connection;
  #294 = Utf8               e
  #295 = Utf8               Ljava/lang/Exception;
  #296 = Utf8               onPlayerPvPKill
  #297 = Utf8               ()Lext/mods/gameserver/data/manager/PcCafeManager;
  #298 = Utf8               lambda$onReset$0
  #299 = Utf8               lambda$new$0
  #300 = Utf8               <clinit>
  #301 = Utf8               SourceFile
  #302 = Utf8               PcCafeManager.java
  #303 = Utf8               NestMembers
  #304 = Utf8               BootstrapMethods
  #305 = MethodType         #6            //  ()V
  #306 = MethodHandle       5:#307        // REF_invokeVirtual ext/mods/gameserver/data/manager/PcCafeManager.lambda$new$0:()V
  #307 = Methodref          #13.#308      // ext/mods/gameserver/data/manager/PcCafeManager.lambda$new$0:()V
  #308 = NameAndType        #299:#6       // lambda$new$0:()V
  #309 = MethodType         #310          //  (Ljava/lang/Object;)V
  #310 = Utf8               (Ljava/lang/Object;)V
  #311 = MethodHandle       6:#312        // REF_invokeStatic ext/mods/gameserver/data/manager/PcCafeManager.lambda$onReset$0:(Lext/mods/gameserver/model/actor/Player;)V
  #312 = Methodref          #13.#313      // ext/mods/gameserver/data/manager/PcCafeManager.lambda$onReset$0:(Lext/mods/gameserver/model/actor/Player;)V
  #313 = NameAndType        #298:#283     // lambda$onReset$0:(Lext/mods/gameserver/model/actor/Player;)V
  #314 = MethodType         #283          //  (Lext/mods/gameserver/model/actor/Player;)V
  #315 = MethodHandle       6:#316        // REF_invokeStatic java/lang/invoke/LambdaMetafactory.metafactory:(Ljava/lang/invoke/MethodHandles$Lookup;Ljava/lang/String;Ljava/lang/invoke/MethodType;Ljava/lang/invoke/MethodType;Ljava/lang/invoke/MethodHandle;Ljava/lang/invoke/MethodType;)Ljava/lang/invoke/CallSite;
  #316 = Methodref          #317.#318     // java/lang/invoke/LambdaMetafactory.metafactory:(Ljava/lang/invoke/MethodHandles$Lookup;Ljava/lang/String;Ljava/lang/invoke/MethodType;Ljava/lang/invoke/MethodType;Ljava/lang/invoke/MethodHandle;Ljava/lang/invoke/MethodType;)Ljava/lang/invoke/CallSite;
  #317 = Class              #319          // java/lang/invoke/LambdaMetafactory
  #318 = NameAndType        #320:#321     // metafactory:(Ljava/lang/invoke/MethodHandles$Lookup;Ljava/lang/String;Ljava/lang/invoke/MethodType;Ljava/lang/invoke/MethodType;Ljava/lang/invoke/MethodHandle;Ljava/lang/invoke/MethodType;)Ljava/lang/invoke/CallSite;
  #319 = Utf8               java/lang/invoke/LambdaMetafactory
  #320 = Utf8               metafactory
  #321 = Utf8               (Ljava/lang/invoke/MethodHandles$Lookup;Ljava/lang/String;Ljava/lang/invoke/MethodType;Ljava/lang/invoke/MethodType;Ljava/lang/invoke/MethodHandle;Ljava/lang/invoke/MethodType;)Ljava/lang/invoke/CallSite;
  #322 = Utf8               InnerClasses
  #323 = Utf8               SingletonHolder
  #324 = Class              #325          // java/lang/invoke/MethodHandles$Lookup
  #325 = Utf8               java/lang/invoke/MethodHandles$Lookup
  #326 = Class              #327          // java/lang/invoke/MethodHandles
  #327 = Utf8               java/lang/invoke/MethodHandles
  #328 = Utf8               Lookup
{
  public static final ext.mods.commons.logging.CLogger LOGGER;
    descriptor: Lext/mods/commons/logging/CLogger;
    flags: (0x0019) ACC_PUBLIC, ACC_STATIC, ACC_FINAL

  protected ext.mods.gameserver.data.manager.PcCafeManager();
    descriptor: ()V
    flags: (0x0004) ACC_PROTECTED
    Code:
      stack=6, locals=1, args_size=1
         0: aload_0
         1: invokespecial #1                  // Method java/lang/Object."<init>":()V
         4: invokestatic  #7                  // Method ext/mods/gameserver/custom/data/PcCafeData.getInstance:()Lext/mods/gameserver/custom/data/PcCafeData;
         7: ldc           #15                 // String enable_timer_bonus
         9: iconst_0
        10: invokevirtual #17                 // Method ext/mods/gameserver/custom/data/PcCafeData.getCafeBool:(Ljava/lang/String;Z)Z
        13: ifeq          44
        16: aload_0
        17: invokedynamic #21,  0             // InvokeDynamic #0:run:(Lext/mods/gameserver/data/manager/PcCafeManager;)Ljava/lang/Runnable;
        22: getstatic     #25                 // Field java/util/concurrent/TimeUnit.MINUTES:Ljava/util/concurrent/TimeUnit;
        25: ldc2_w        #31                 // long 15l
        28: invokevirtual #33                 // Method java/util/concurrent/TimeUnit.toMillis:(J)J
        31: getstatic     #25                 // Field java/util/concurrent/TimeUnit.MINUTES:Ljava/util/concurrent/TimeUnit;
        34: ldc2_w        #31                 // long 15l
        37: invokevirtual #33                 // Method java/util/concurrent/TimeUnit.toMillis:(J)J
        40: invokestatic  #37                 // Method ext/mods/commons/pool/ThreadPool.scheduleAtFixedRate:(Ljava/lang/Runnable;JJ)Ljava/util/concurrent/ScheduledFuture;
        43: pop
        44: return
      LineNumberTable:
        line 56: 0
        line 57: 4
        line 58: 16
        line 59: 44
      LocalVariableTable:
        Start  Length  Slot  Name   Signature
            0      45     0  this   Lext/mods/gameserver/data/manager/PcCafeManager;
      StackMapTable: number_of_entries = 1
        frame_type = 255 /* full_frame */
          offset_delta = 44
          locals = [ class ext/mods/gameserver/data/manager/PcCafeManager ]
          stack = []

  public int enableEvent();
    descriptor: ()I
    flags: (0x0001) ACC_PUBLIC
    Code:
      stack=3, locals=1, args_size=1
         0: invokestatic  #7                  // Method ext/mods/gameserver/custom/data/PcCafeData.getInstance:()Lext/mods/gameserver/custom/data/PcCafeData;
         3: ldc           #43                 // String enable
         5: iconst_1
         6: invokevirtual #45                 // Method ext/mods/gameserver/custom/data/PcCafeData.getCafeInt:(Ljava/lang/String;I)I
         9: ireturn
      LineNumberTable:
        line 63: 0
      LocalVariableTable:
        Start  Length  Slot  Name   Signature
            0      10     0  this   Lext/mods/gameserver/data/manager/PcCafeManager;

  public void onPlayerLogin(ext.mods.gameserver.model.actor.Player);
    descriptor: (Lext/mods/gameserver/model/actor/Player;)V
    flags: (0x0001) ACC_PUBLIC
    Code:
      stack=6, locals=2, args_size=2
         0: aload_0
         1: invokevirtual #80                 // Method isEventEnabled:()Z
         4: ifeq          57
         7: invokestatic  #7                  // Method ext/mods/gameserver/custom/data/PcCafeData.getInstance:()Lext/mods/gameserver/custom/data/PcCafeData;
        10: ldc           #106                // String enable_daily_bonus
        12: iconst_0
        13: invokevirtual #17                 // Method ext/mods/gameserver/custom/data/PcCafeData.getCafeBool:(Ljava/lang/String;Z)Z
        16: ifeq          57
        19: aload_1
        20: invokevirtual #108                // Method ext/mods/gameserver/model/actor/Player.getMemos:()Lext/mods/gameserver/model/memo/PlayerMemo;
        23: ldc           #112                // String cafe_points_today
        25: iconst_0
        26: invokevirtual #114                // Method ext/mods/gameserver/model/memo/PlayerMemo.getBool:(Ljava/lang/String;Z)Z
        29: ifne          57
        32: aload_1
        33: invokevirtual #108                // Method ext/mods/gameserver/model/actor/Player.getMemos:()Lext/mods/gameserver/model/memo/PlayerMemo;
        36: ldc           #112                // String cafe_points_today
        38: iconst_1
        39: invokevirtual #119                // Method ext/mods/gameserver/model/memo/PlayerMemo.set:(Ljava/lang/String;Z)V
        42: aload_1
        43: invokestatic  #7                  // Method ext/mods/gameserver/custom/data/PcCafeData.getInstance:()Lext/mods/gameserver/custom/data/PcCafeData;
        46: ldc           #123                // String daily_bonus_points
        48: sipush        1000
        51: invokevirtual #45                 // Method ext/mods/gameserver/custom/data/PcCafeData.getCafeInt:(Ljava/lang/String;I)I
        54: invokevirtual #125                // Method ext/mods/gameserver/model/actor/Player.increasePcCafePoints:(I)V
        57: aload_1
        58: new           #128                // class ext/mods/gameserver/network/serverpackets/ExPCCafePointInfo
        61: dup
        62: aload_1
        63: invokevirtual #130                // Method ext/mods/gameserver/model/actor/Player.getPcCafePoints:()I
        66: iconst_0
        67: getstatic     #133                // Field ext/mods/gameserver/enums/PcCafeConsumeType.NORMAL:Lext/mods/gameserver/enums/PcCafeConsumeType;
        70: invokespecial #139                // Method ext/mods/gameserver/network/serverpackets/ExPCCafePointInfo."<init>":(IILext/mods/gameserver/enums/PcCafeConsumeType;)V
        73: invokevirtual #142                // Method ext/mods/gameserver/model/actor/Player.sendPacket:(Lext/mods/gameserver/network/serverpackets/L2GameServerPacket;)V
        76: return
      LineNumberTable:
        line 86: 0
        line 88: 19
        line 90: 32
        line 91: 42
        line 95: 57
        line 96: 76
      LocalVariableTable:
        Start  Length  Slot  Name   Signature
            0      77     0  this   Lext/mods/gameserver/data/manager/PcCafeManager;
            0      77     1 player   Lext/mods/gameserver/model/actor/Player;
      StackMapTable: number_of_entries = 1
        frame_type = 57 /* same */

  public void onAttackableKill(ext.mods.gameserver.model.actor.Player);
    descriptor: (Lext/mods/gameserver/model/actor/Player;)V
    flags: (0x0001) ACC_PUBLIC
    Code:
      stack=4, locals=5, args_size=2
         0: aload_0
         1: invokevirtual #80                 // Method isEventEnabled:()Z
         4: ifeq          92
         7: invokestatic  #7                  // Method ext/mods/gameserver/custom/data/PcCafeData.getInstance:()Lext/mods/gameserver/custom/data/PcCafeData;
        10: ldc           #146                // String enable_farming_bonus
        12: iconst_0
        13: invokevirtual #17                 // Method ext/mods/gameserver/custom/data/PcCafeData.getCafeBool:(Ljava/lang/String;Z)Z
        16: ifeq          92
        19: aload_1
        20: ifnonnull     24
        23: return
        24: aload_1
        25: invokevirtual #148                // Method ext/mods/gameserver/model/actor/Player.getTarget:()Lext/mods/gameserver/model/WorldObject;
        28: checkcast     #152                // class ext/mods/gameserver/model/actor/Creature
        31: astore_2
        32: aload_2
        33: ifnonnull     37
        36: return
        37: aload_2
        38: invokevirtual #154                // Method ext/mods/gameserver/model/actor/Creature.getStatus:()Lext/mods/gameserver/model/actor/status/CreatureStatus;
        41: invokevirtual #158                // Method ext/mods/gameserver/model/actor/status/CreatureStatus.getLevel:()I
        44: aload_1
        45: invokevirtual #163                // Method ext/mods/gameserver/model/actor/Player.getStatus:()Lext/mods/gameserver/model/actor/status/PlayerStatus;
        48: invokevirtual #166                // Method ext/mods/gameserver/model/actor/status/PlayerStatus.getLevel:()I
        51: isub
        52: istore_3
        53: invokestatic  #7                  // Method ext/mods/gameserver/custom/data/PcCafeData.getInstance:()Lext/mods/gameserver/custom/data/PcCafeData;
        56: ldc           #169                // String farming_bonus_level_diff
        58: bipush        11
        60: invokevirtual #45                 // Method ext/mods/gameserver/custom/data/PcCafeData.getCafeInt:(Ljava/lang/String;I)I
        63: istore        4
        65: iload_3
        66: iload         4
        68: ineg
        69: if_icmple     92
        72: iload_3
        73: iload         4
        75: if_icmpge     92
        78: aload_1
        79: invokestatic  #7                  // Method ext/mods/gameserver/custom/data/PcCafeData.getInstance:()Lext/mods/gameserver/custom/data/PcCafeData;
        82: ldc           #171                // String farming_bonus_points
        84: bipush        50
        86: invokevirtual #45                 // Method ext/mods/gameserver/custom/data/PcCafeData.getCafeInt:(Ljava/lang/String;I)I
        89: invokevirtual #125                // Method ext/mods/gameserver/model/actor/Player.increasePcCafePoints:(I)V
        92: return
      LineNumberTable:
        line 100: 0
        line 102: 19
        line 103: 23
        line 105: 24
        line 106: 32
        line 107: 36
        line 109: 37
        line 110: 53
        line 111: 65
        line 112: 78
        line 114: 92
      LocalVariableTable:
        Start  Length  Slot  Name   Signature
           32      60     2 target   Lext/mods/gameserver/model/actor/Creature;
           53      39     3 levelDiff   I
           65      27     4 maxLevelDiff   I
            0      93     0  this   Lext/mods/gameserver/data/manager/PcCafeManager;
            0      93     1 player   Lext/mods/gameserver/model/actor/Player;
      StackMapTable: number_of_entries = 3
        frame_type = 24 /* same */
        frame_type = 252 /* append */
          offset_delta = 12
          locals = [ class ext/mods/gameserver/model/actor/Creature ]
        frame_type = 250 /* chop */
          offset_delta = 54

  public void onReset();
    descriptor: ()V
    flags: (0x0001) ACC_PUBLIC
    Code:
      stack=3, locals=5, args_size=1
         0: invokestatic  #173                // Method ext/mods/commons/pool/ConnectionPool.getConnection:()Ljava/sql/Connection;
         3: astore_1
         4: aload_1
         5: ldc           #179                // String DELETE FROM character_memo WHERE var=\'cafe_points_today\'
         7: invokeinterface #181,  2          // InterfaceMethod java/sql/Connection.prepareStatement:(Ljava/lang/String;)Ljava/sql/PreparedStatement;
        12: astore_2
        13: aload_2
        14: invokeinterface #187,  1          // InterfaceMethod java/sql/PreparedStatement.executeUpdate:()I
        19: pop
        20: aload_2
        21: ifnull        57
        24: aload_2
        25: invokeinterface #192,  1          // InterfaceMethod java/sql/PreparedStatement.close:()V
        30: goto          57
        33: astore_3
        34: aload_2
        35: ifnull        55
        38: aload_2
        39: invokeinterface #192,  1          // InterfaceMethod java/sql/PreparedStatement.close:()V
        44: goto          55
        47: astore        4
        49: aload_3
        50: aload         4
        52: invokevirtual #197                // Method java/lang/Throwable.addSuppressed:(Ljava/lang/Throwable;)V
        55: aload_3
        56: athrow
        57: aload_1
        58: ifnull        92
        61: aload_1
        62: invokeinterface #201,  1          // InterfaceMethod java/sql/Connection.close:()V
        67: goto          92
        70: astore_2
        71: aload_1
        72: ifnull        90
        75: aload_1
        76: invokeinterface #201,  1          // InterfaceMethod java/sql/Connection.close:()V
        81: goto          90
        84: astore_3
        85: aload_2
        86: aload_3
        87: invokevirtual #197                // Method java/lang/Throwable.addSuppressed:(Ljava/lang/Throwable;)V
        90: aload_2
        91: athrow
        92: goto          105
        95: astore_1
        96: getstatic     #204                // Field LOGGER:Lext/mods/commons/logging/CLogger;
        99: ldc           #208                // String Failed to reset daily login pc points.
       101: aload_1
       102: invokevirtual #210                // Method ext/mods/commons/logging/CLogger.error:(Ljava/lang/Object;Ljava/lang/Throwable;)V
       105: invokestatic  #53                 // Method ext/mods/gameserver/model/World.getInstance:()Lext/mods/gameserver/model/World;
       108: invokevirtual #58                 // Method ext/mods/gameserver/model/World.getPlayers:()Ljava/util/Collection;
       111: invokeinterface #216,  1          // InterfaceMethod java/util/Collection.stream:()Ljava/util/stream/Stream;
       116: invokedynamic #220,  0            // InvokeDynamic #1:accept:()Ljava/util/function/Consumer;
       121: invokeinterface #224,  2          // InterfaceMethod java/util/stream/Stream.forEach:(Ljava/util/function/Consumer;)V
       126: return
      Exception table:
         from    to  target type
            13    20    33   Class java/lang/Throwable
            38    44    47   Class java/lang/Throwable
             4    57    70   Class java/lang/Throwable
            75    81    84   Class java/lang/Throwable
             0    92    95   Class java/lang/Exception
      LineNumberTable:
        line 118: 0
        line 119: 4
        line 121: 13
        line 122: 20
        line 118: 33
        line 122: 57
        line 118: 70
        line 126: 92
        line 123: 95
        line 125: 96
        line 128: 105
        line 129: 126
      LocalVariableTable:
        Start  Length  Slot  Name   Signature
           13      44     2    ps   Ljava/sql/PreparedStatement;
            4      88     1   con   Ljava/sql/Connection;
           96       9     1     e   Ljava/lang/Exception;
            0     127     0  this   Lext/mods/gameserver/data/manager/PcCafeManager;
      StackMapTable: number_of_entries = 10
        frame_type = 255 /* full_frame */
          offset_delta = 33
          locals = [ class ext/mods/gameserver/data/manager/PcCafeManager, class java/sql/Connection, class java/sql/PreparedStatement ]
          stack = [ class java/lang/Throwable ]
        frame_type = 255 /* full_frame */
          offset_delta = 13
          locals = [ class ext/mods/gameserver/data/manager/PcCafeManager, class java/sql/Connection, class java/sql/PreparedStatement, class java/lang/Throwable ]
          stack = [ class java/lang/Throwable ]
        frame_type = 7 /* same */
        frame_type = 249 /* chop */
          offset_delta = 1
        frame_type = 76 /* same_locals_1_stack_item */
          stack = [ class java/lang/Throwable ]
        frame_type = 255 /* full_frame */
          offset_delta = 13
          locals = [ class ext/mods/gameserver/data/manager/PcCafeManager, class java/sql/Connection, class java/lang/Throwable ]
          stack = [ class java/lang/Throwable ]
        frame_type = 5 /* same */
        frame_type = 249 /* chop */
          offset_delta = 1
        frame_type = 66 /* same_locals_1_stack_item */
          stack = [ class java/lang/Exception ]
        frame_type = 9 /* same */

  public void onPlayerPvPKill(ext.mods.gameserver.model.actor.Player);
    descriptor: (Lext/mods/gameserver/model/actor/Player;)V
    flags: (0x0001) ACC_PUBLIC
    Code:
      stack=4, locals=2, args_size=2
         0: aload_0
         1: invokevirtual #80                 // Method isEventEnabled:()Z
         4: ifeq          33
         7: invokestatic  #7                  // Method ext/mods/gameserver/custom/data/PcCafeData.getInstance:()Lext/mods/gameserver/custom/data/PcCafeData;
        10: ldc           #230                // String enable_pvp_bonus
        12: iconst_0
        13: invokevirtual #17                 // Method ext/mods/gameserver/custom/data/PcCafeData.getCafeBool:(Ljava/lang/String;Z)Z
        16: ifeq          33
        19: aload_1
        20: invokestatic  #7                  // Method ext/mods/gameserver/custom/data/PcCafeData.getInstance:()Lext/mods/gameserver/custom/data/PcCafeData;
        23: ldc           #232                // String pvp_bonus_points
        25: bipush        100
        27: invokevirtual #45                 // Method ext/mods/gameserver/custom/data/PcCafeData.getCafeInt:(Ljava/lang/String;I)I
        30: invokevirtual #125                // Method ext/mods/gameserver/model/actor/Player.increasePcCafePoints:(I)V
        33: return
      LineNumberTable:
        line 133: 0
        line 134: 19
        line 135: 33
      LocalVariableTable:
        Start  Length  Slot  Name   Signature
            0      34     0  this   Lext/mods/gameserver/data/manager/PcCafeManager;
            0      34     1 player   Lext/mods/gameserver/model/actor/Player;
      StackMapTable: number_of_entries = 1
        frame_type = 33 /* same */

  public static final ext.mods.gameserver.data.manager.PcCafeManager getInstance();
    descriptor: ()Lext/mods/gameserver/data/manager/PcCafeManager;
    flags: (0x0019) ACC_PUBLIC, ACC_STATIC, ACC_FINAL
    Code:
      stack=1, locals=0, args_size=0
         0: getstatic     #234                // Field ext/mods/gameserver/data/manager/PcCafeManager$SingletonHolder.INSTANCE:Lext/mods/gameserver/data/manager/PcCafeManager;
         3: areturn
      LineNumberTable:
        line 139: 0

  static {};
    descriptor: ()V
    flags: (0x0008) ACC_STATIC
    Code:
      stack=3, locals=0, args_size=0
         0: new           #211                // class ext/mods/commons/logging/CLogger
         3: dup
         4: ldc           #13                 // class ext/mods/gameserver/data/manager/PcCafeManager
         6: invokevirtual #247                // Method java/lang/Class.getName:()Ljava/lang/String;
         9: invokespecial #253                // Method ext/mods/commons/logging/CLogger."<init>":(Ljava/lang/String;)V
        12: putstatic     #204                // Field LOGGER:Lext/mods/commons/logging/CLogger;
        15: return
      LineNumberTable:
        line 38: 0
}
SourceFile: "PcCafeManager.java"
NestMembers:
  ext/mods/gameserver/data/manager/PcCafeManager$SingletonHolder
BootstrapMethods:
  0: #315 REF_invokeStatic java/lang/invoke/LambdaMetafactory.metafactory:(Ljava/lang/invoke/MethodHandles$Lookup;Ljava/lang/String;Ljava/lang/invoke/MethodType;Ljava/lang/invoke/MethodType;Ljava/lang/invoke/MethodHandle;Ljava/lang/invoke/MethodType;)Ljava/lang/invoke/CallSite;
    Method arguments:
      #305 ()V
      #306 REF_invokeVirtual ext/mods/gameserver/data/manager/PcCafeManager.lambda$new$0:()V
      #305 ()V
  1: #315 REF_invokeStatic java/lang/invoke/LambdaMetafactory.metafactory:(Ljava/lang/invoke/MethodHandles$Lookup;Ljava/lang/String;Ljava/lang/invoke/MethodType;Ljava/lang/invoke/MethodType;Ljava/lang/invoke/MethodHandle;Ljava/lang/invoke/MethodType;)Ljava/lang/invoke/CallSite;
    Method arguments:
      #309 (Ljava/lang/Object;)V
      #311 REF_invokeStatic ext/mods/gameserver/data/manager/PcCafeManager.lambda$onReset$0:(Lext/mods/gameserver/model/actor/Player;)V
      #314 (Lext/mods/gameserver/model/actor/Player;)V
InnerClasses:
  public static final #328= #324 of #326; // Lookup=class java/lang/invoke/MethodHandles$Lookup of class java/lang/invoke/MethodHandles
