// Bytecode for: ext.mods.gameserver.data.manager.SevenSignsManager
// File: ext\mods\gameserver\data\manager\SevenSignsManager.class

Classfile /c:/Users/User/Desktop/BrProject/bin/main/ext/mods/gameserver/data/manager/SevenSignsManager.class
  Last modified 9 de jul de 2026; size 22830 bytes
  MD5 checksum 21182cde01a79b85faa3e417bdeeefc7
  Compiled from "SevenSignsManager.java"
public class ext.mods.gameserver.data.manager.SevenSignsManager
  minor version: 0
  major version: 69
  flags: (0x0021) ACC_PUBLIC, ACC_SUPER
  this_class: #3                          // ext/mods/gameserver/data/manager/SevenSignsManager
  super_class: #6                         // java/lang/Object
  interfaces: 0, fields: 33, methods: 42, attributes: 3
Constant pool:
    #1 = Class              #2            // java/util/Calendar
    #2 = Utf8               java/util/Calendar
    #3 = Class              #4            // ext/mods/gameserver/data/manager/SevenSignsManager
    #4 = Utf8               ext/mods/gameserver/data/manager/SevenSignsManager
    #5 = Methodref          #6.#7         // java/lang/Object."<init>":()V
    #6 = Class              #8            // java/lang/Object
    #7 = NameAndType        #9:#10        // "<init>":()V
    #8 = Utf8               java/lang/Object
    #9 = Utf8               <init>
   #10 = Utf8               ()V
   #11 = Methodref          #1.#12        // java/util/Calendar.getInstance:()Ljava/util/Calendar;
   #12 = NameAndType        #13:#14       // getInstance:()Ljava/util/Calendar;
   #13 = Utf8               getInstance
   #14 = Utf8               ()Ljava/util/Calendar;
   #15 = Fieldref           #3.#16        // ext/mods/gameserver/data/manager/SevenSignsManager._nextPeriodChange:Ljava/util/Calendar;
   #16 = NameAndType        #17:#18       // _nextPeriodChange:Ljava/util/Calendar;
   #17 = Utf8               _nextPeriodChange
   #18 = Utf8               Ljava/util/Calendar;
   #19 = Fieldref           #3.#20        // ext/mods/gameserver/data/manager/SevenSignsManager._lastSave:Ljava/util/Calendar;
   #20 = NameAndType        #21:#18       // _lastSave:Ljava/util/Calendar;
   #21 = Utf8               _lastSave
   #22 = Class              #23           // java/util/HashMap
   #23 = Utf8               java/util/HashMap
   #24 = Methodref          #22.#7        // java/util/HashMap."<init>":()V
   #25 = Fieldref           #3.#26        // ext/mods/gameserver/data/manager/SevenSignsManager._playersData:Ljava/util/Map;
   #26 = NameAndType        #27:#28       // _playersData:Ljava/util/Map;
   #27 = Utf8               _playersData
   #28 = Utf8               Ljava/util/Map;
   #29 = Class              #30           // java/util/EnumMap
   #30 = Utf8               java/util/EnumMap
   #31 = Class              #32           // ext/mods/gameserver/enums/SealType
   #32 = Utf8               ext/mods/gameserver/enums/SealType
   #33 = Methodref          #29.#34       // java/util/EnumMap."<init>":(Ljava/lang/Class;)V
   #34 = NameAndType        #9:#35        // "<init>":(Ljava/lang/Class;)V
   #35 = Utf8               (Ljava/lang/Class;)V
   #36 = Fieldref           #3.#37        // ext/mods/gameserver/data/manager/SevenSignsManager._sealOwners:Ljava/util/Map;
   #37 = NameAndType        #38:#28       // _sealOwners:Ljava/util/Map;
   #38 = Utf8               _sealOwners
   #39 = Fieldref           #3.#40        // ext/mods/gameserver/data/manager/SevenSignsManager._duskScores:Ljava/util/Map;
   #40 = NameAndType        #41:#28       // _duskScores:Ljava/util/Map;
   #41 = Utf8               _duskScores
   #42 = Fieldref           #3.#43        // ext/mods/gameserver/data/manager/SevenSignsManager._dawnScores:Ljava/util/Map;
   #43 = NameAndType        #44:#28       // _dawnScores:Ljava/util/Map;
   #44 = Utf8               _dawnScores
   #45 = Methodref          #3.#46        // ext/mods/gameserver/data/manager/SevenSignsManager.restoreSevenSignsData:()V
   #46 = NameAndType        #47:#10       // restoreSevenSignsData:()V
   #47 = Utf8               restoreSevenSignsData
   #48 = Fieldref           #3.#49        // ext/mods/gameserver/data/manager/SevenSignsManager.LOGGER:Lext/mods/commons/logging/CLogger;
   #49 = NameAndType        #50:#51       // LOGGER:Lext/mods/commons/logging/CLogger;
   #50 = Utf8               LOGGER
   #51 = Utf8               Lext/mods/commons/logging/CLogger;
   #52 = String             #53           // Currently on {} period.
   #53 = Utf8               Currently on {} period.
   #54 = Fieldref           #3.#55        // ext/mods/gameserver/data/manager/SevenSignsManager._activePeriod:Lext/mods/gameserver/enums/PeriodType;
   #55 = NameAndType        #56:#57       // _activePeriod:Lext/mods/gameserver/enums/PeriodType;
   #56 = Utf8               _activePeriod
   #57 = Utf8               Lext/mods/gameserver/enums/PeriodType;
   #58 = Methodref          #59.#60       // ext/mods/gameserver/enums/PeriodType.getName:()Ljava/lang/String;
   #59 = Class              #61           // ext/mods/gameserver/enums/PeriodType
   #60 = NameAndType        #62:#63       // getName:()Ljava/lang/String;
   #61 = Utf8               ext/mods/gameserver/enums/PeriodType
   #62 = Utf8               getName
   #63 = Utf8               ()Ljava/lang/String;
   #64 = Methodref          #65.#66       // ext/mods/commons/logging/CLogger.info:(Ljava/lang/Object;[Ljava/lang/Object;)V
   #65 = Class              #67           // ext/mods/commons/logging/CLogger
   #66 = NameAndType        #68:#69       // info:(Ljava/lang/Object;[Ljava/lang/Object;)V
   #67 = Utf8               ext/mods/commons/logging/CLogger
   #68 = Utf8               info
   #69 = Utf8               (Ljava/lang/Object;[Ljava/lang/Object;)V
   #70 = Methodref          #3.#71        // ext/mods/gameserver/data/manager/SevenSignsManager.initializeSeals:()V
   #71 = NameAndType        #72:#10       // initializeSeals:()V
   #72 = Utf8               initializeSeals
   #73 = Methodref          #3.#74        // ext/mods/gameserver/data/manager/SevenSignsManager.isNextPeriodChangeInPast:()Z
   #74 = NameAndType        #75:#76       // isNextPeriodChangeInPast:()Z
   #75 = Utf8               isNextPeriodChangeInPast
   #76 = Utf8               ()Z
   #77 = String             #78           // Next Seven Signs period is already computed.
   #78 = Utf8               Next Seven Signs period is already computed.
   #79 = Methodref          #65.#80       // ext/mods/commons/logging/CLogger.info:(Ljava/lang/Object;)V
   #80 = NameAndType        #68:#81       // info:(Ljava/lang/Object;)V
   #81 = Utf8               (Ljava/lang/Object;)V
   #82 = Methodref          #3.#83        // ext/mods/gameserver/data/manager/SevenSignsManager.setCalendarForNextPeriodChange:()V
   #83 = NameAndType        #84:#10       // setCalendarForNextPeriodChange:()V
   #84 = Utf8               setCalendarForNextPeriodChange
   #85 = Methodref          #3.#86        // ext/mods/gameserver/data/manager/SevenSignsManager.getMilliToPeriodChange:()J
   #86 = NameAndType        #87:#88       // getMilliToPeriodChange:()J
   #87 = Utf8               getMilliToPeriodChange
   #88 = Utf8               ()J
   #89 = Class              #90           // ext/mods/gameserver/data/manager/SevenSignsManager$SevenSignsPeriodChange
   #90 = Utf8               ext/mods/gameserver/data/manager/SevenSignsManager$SevenSignsPeriodChange
   #91 = Methodref          #89.#92       // ext/mods/gameserver/data/manager/SevenSignsManager$SevenSignsPeriodChange."<init>":(Lext/mods/gameserver/data/manager/SevenSignsManager;)V
   #92 = NameAndType        #9:#93        // "<init>":(Lext/mods/gameserver/data/manager/SevenSignsManager;)V
   #93 = Utf8               (Lext/mods/gameserver/data/manager/SevenSignsManager;)V
   #94 = Methodref          #95.#96       // ext/mods/commons/pool/ThreadPool.schedule:(Ljava/lang/Runnable;J)Ljava/util/concurrent/ScheduledFuture;
   #95 = Class              #97           // ext/mods/commons/pool/ThreadPool
   #96 = NameAndType        #98:#99       // schedule:(Ljava/lang/Runnable;J)Ljava/util/concurrent/ScheduledFuture;
   #97 = Utf8               ext/mods/commons/pool/ThreadPool
   #98 = Utf8               schedule
   #99 = Utf8               (Ljava/lang/Runnable;J)Ljava/util/concurrent/ScheduledFuture;
  #100 = Long               1000l
  #102 = Long               60l
  #104 = Double             60.0d
  #106 = Methodref          #107.#108     // java/lang/Math.floor:(D)D
  #107 = Class              #109          // java/lang/Math
  #108 = NameAndType        #110:#111     // floor:(D)D
  #109 = Utf8               java/lang/Math
  #110 = Utf8               floor
  #111 = Utf8               (D)D
  #112 = Double             24.0d
  #114 = String             #115          // Next Seven Signs period begins in {} days, {} hours and {} mins.
  #115 = Utf8               Next Seven Signs period begins in {} days, {} hours and {} mins.
  #116 = Methodref          #117.#118     // java/lang/Integer.valueOf:(I)Ljava/lang/Integer;
  #117 = Class              #119          // java/lang/Integer
  #118 = NameAndType        #120:#121     // valueOf:(I)Ljava/lang/Integer;
  #119 = Utf8               java/lang/Integer
  #120 = Utf8               valueOf
  #121 = Utf8               (I)Ljava/lang/Integer;
  #122 = Fieldref           #123.#124     // ext/mods/gameserver/data/manager/SevenSignsManager$1.$SwitchMap$ext$mods$gameserver$enums$PeriodType:[I
  #123 = Class              #125          // ext/mods/gameserver/data/manager/SevenSignsManager$1
  #124 = NameAndType        #126:#127     // $SwitchMap$ext$mods$gameserver$enums$PeriodType:[I
  #125 = Utf8               ext/mods/gameserver/data/manager/SevenSignsManager$1
  #126 = Utf8               $SwitchMap$ext$mods$gameserver$enums$PeriodType
  #127 = Utf8               [I
  #128 = Methodref          #59.#129      // ext/mods/gameserver/enums/PeriodType.ordinal:()I
  #129 = NameAndType        #130:#131     // ordinal:()I
  #130 = Utf8               ordinal
  #131 = Utf8               ()I
  #132 = Methodref          #1.#133       // java/util/Calendar.set:(II)V
  #133 = NameAndType        #134:#135     // set:(II)V
  #134 = Utf8               set
  #135 = Utf8               (II)V
  #136 = Methodref          #1.#137       // java/util/Calendar.before:(Ljava/lang/Object;)Z
  #137 = NameAndType        #138:#139     // before:(Ljava/lang/Object;)Z
  #138 = Utf8               before
  #139 = Utf8               (Ljava/lang/Object;)Z
  #140 = Methodref          #1.#141       // java/util/Calendar.add:(II)V
  #141 = NameAndType        #142:#135     // add:(II)V
  #142 = Utf8               add
  #143 = Methodref          #1.#144       // java/util/Calendar.getTimeInMillis:()J
  #144 = NameAndType        #145:#88      // getTimeInMillis:()J
  #145 = Utf8               getTimeInMillis
  #146 = Long               900000l
  #148 = Methodref          #1.#149       // java/util/Calendar.setTimeInMillis:(J)V
  #149 = NameAndType        #150:#151     // setTimeInMillis:(J)V
  #150 = Utf8               setTimeInMillis
  #151 = Utf8               (J)V
  #152 = Long               7l
  #154 = Fieldref           #3.#155       // ext/mods/gameserver/data/manager/SevenSignsManager._currentCycle:I
  #155 = NameAndType        #156:#157     // _currentCycle:I
  #156 = Utf8               _currentCycle
  #157 = Utf8               I
  #158 = Methodref          #1.#159       // java/util/Calendar.get:(I)I
  #159 = NameAndType        #160:#161     // get:(I)I
  #160 = Utf8               get
  #161 = Utf8               (I)I
  #162 = Methodref          #163.#164     // java/lang/System.currentTimeMillis:()J
  #163 = Class              #165          // java/lang/System
  #164 = NameAndType        #166:#88      // currentTimeMillis:()J
  #165 = Utf8               java/lang/System
  #166 = Utf8               currentTimeMillis
  #167 = Methodref          #3.#168       // ext/mods/gameserver/data/manager/SevenSignsManager.getDaysToPeriodChange:()I
  #168 = NameAndType        #169:#131     // getDaysToPeriodChange:()I
  #169 = Utf8               getDaysToPeriodChange
  #170 = Integer            900000
  #171 = String             #172          // Next Seven Signs period change set to {}.
  #172 = Utf8               Next Seven Signs period change set to {}.
  #173 = Methodref          #1.#174       // java/util/Calendar.getTime:()Ljava/util/Date;
  #174 = NameAndType        #175:#176     // getTime:()Ljava/util/Date;
  #175 = Utf8               getTime
  #176 = Utf8               ()Ljava/util/Date;
  #177 = Fieldref           #59.#178      // ext/mods/gameserver/enums/PeriodType.RECRUITING:Lext/mods/gameserver/enums/PeriodType;
  #178 = NameAndType        #179:#57      // RECRUITING:Lext/mods/gameserver/enums/PeriodType;
  #179 = Utf8               RECRUITING
  #180 = Fieldref           #59.#181      // ext/mods/gameserver/enums/PeriodType.SEAL_VALIDATION:Lext/mods/gameserver/enums/PeriodType;
  #181 = NameAndType        #182:#57      // SEAL_VALIDATION:Lext/mods/gameserver/enums/PeriodType;
  #182 = Utf8               SEAL_VALIDATION
  #183 = Fieldref           #59.#184      // ext/mods/gameserver/enums/PeriodType.RESULTS:Lext/mods/gameserver/enums/PeriodType;
  #184 = NameAndType        #185:#57      // RESULTS:Lext/mods/gameserver/enums/PeriodType;
  #185 = Utf8               RESULTS
  #186 = Fieldref           #3.#187       // ext/mods/gameserver/data/manager/SevenSignsManager._dawnStoneScore:D
  #187 = NameAndType        #188:#189     // _dawnStoneScore:D
  #188 = Utf8               _dawnStoneScore
  #189 = Utf8               D
  #190 = Fieldref           #3.#191       // ext/mods/gameserver/data/manager/SevenSignsManager._duskStoneScore:D
  #191 = NameAndType        #192:#189     // _duskStoneScore:D
  #192 = Utf8               _duskStoneScore
  #193 = Fieldref           #123.#194     // ext/mods/gameserver/data/manager/SevenSignsManager$1.$SwitchMap$ext$mods$gameserver$enums$CabalType:[I
  #194 = NameAndType        #195:#127     // $SwitchMap$ext$mods$gameserver$enums$CabalType:[I
  #195 = Utf8               $SwitchMap$ext$mods$gameserver$enums$CabalType
  #196 = Methodref          #197.#129     // ext/mods/gameserver/enums/CabalType.ordinal:()I
  #197 = Class              #198          // ext/mods/gameserver/enums/CabalType
  #198 = Utf8               ext/mods/gameserver/enums/CabalType
  #199 = Float              500.0f
  #200 = Methodref          #107.#201     // java/lang/Math.round:(F)I
  #201 = NameAndType        #202:#203     // round:(F)I
  #202 = Utf8               round
  #203 = Utf8               (F)I
  #204 = Methodref          #3.#205       // ext/mods/gameserver/data/manager/SevenSignsManager.getCurrentFestivalScore:(Lext/mods/gameserver/enums/CabalType;)I
  #205 = NameAndType        #206:#207     // getCurrentFestivalScore:(Lext/mods/gameserver/enums/CabalType;)I
  #206 = Utf8               getCurrentFestivalScore
  #207 = Utf8               (Lext/mods/gameserver/enums/CabalType;)I
  #208 = Methodref          #209.#210     // ext/mods/gameserver/data/manager/FestivalOfDarknessManager.getInstance:()Lext/mods/gameserver/data/manager/FestivalOfDarknessManager;
  #209 = Class              #211          // ext/mods/gameserver/data/manager/FestivalOfDarknessManager
  #210 = NameAndType        #13:#212      // getInstance:()Lext/mods/gameserver/data/manager/FestivalOfDarknessManager;
  #211 = Utf8               ext/mods/gameserver/data/manager/FestivalOfDarknessManager
  #212 = Utf8               ()Lext/mods/gameserver/data/manager/FestivalOfDarknessManager;
  #213 = Methodref          #209.#214     // ext/mods/gameserver/data/manager/FestivalOfDarknessManager.getFestivalScore:(Lext/mods/gameserver/enums/CabalType;)I
  #214 = NameAndType        #215:#207     // getFestivalScore:(Lext/mods/gameserver/enums/CabalType;)I
  #215 = Utf8               getFestivalScore
  #216 = Fieldref           #197.#217     // ext/mods/gameserver/enums/CabalType.DUSK:Lext/mods/gameserver/enums/CabalType;
  #217 = NameAndType        #218:#219     // DUSK:Lext/mods/gameserver/enums/CabalType;
  #218 = Utf8               DUSK
  #219 = Utf8               Lext/mods/gameserver/enums/CabalType;
  #220 = Methodref          #3.#221       // ext/mods/gameserver/data/manager/SevenSignsManager.getCurrentScore:(Lext/mods/gameserver/enums/CabalType;)I
  #221 = NameAndType        #222:#207     // getCurrentScore:(Lext/mods/gameserver/enums/CabalType;)I
  #222 = Utf8               getCurrentScore
  #223 = Fieldref           #197.#224     // ext/mods/gameserver/enums/CabalType.DAWN:Lext/mods/gameserver/enums/CabalType;
  #224 = NameAndType        #225:#219     // DAWN:Lext/mods/gameserver/enums/CabalType;
  #225 = Utf8               DAWN
  #226 = Fieldref           #197.#227     // ext/mods/gameserver/enums/CabalType.NORMAL:Lext/mods/gameserver/enums/CabalType;
  #227 = NameAndType        #228:#219     // NORMAL:Lext/mods/gameserver/enums/CabalType;
  #228 = Utf8               NORMAL
  #229 = InterfaceMethodref #230.#231     // java/util/Map.get:(Ljava/lang/Object;)Ljava/lang/Object;
  #230 = Class              #232          // java/util/Map
  #231 = NameAndType        #160:#233     // get:(Ljava/lang/Object;)Ljava/lang/Object;
  #232 = Utf8               java/util/Map
  #233 = Utf8               (Ljava/lang/Object;)Ljava/lang/Object;
  #234 = Methodref          #117.#235     // java/lang/Integer.intValue:()I
  #235 = NameAndType        #236:#131     // intValue:()I
  #236 = Utf8               intValue
  #237 = InterfaceMethodref #230.#238     // java/util/Map.values:()Ljava/util/Collection;
  #238 = NameAndType        #239:#240     // values:()Ljava/util/Collection;
  #239 = Utf8               values
  #240 = Utf8               ()Ljava/util/Collection;
  #241 = InterfaceMethodref #242.#243     // java/util/Collection.iterator:()Ljava/util/Iterator;
  #242 = Class              #244          // java/util/Collection
  #243 = NameAndType        #245:#246     // iterator:()Ljava/util/Iterator;
  #244 = Utf8               java/util/Collection
  #245 = Utf8               iterator
  #246 = Utf8               ()Ljava/util/Iterator;
  #247 = InterfaceMethodref #248.#249     // java/util/Iterator.hasNext:()Z
  #248 = Class              #250          // java/util/Iterator
  #249 = NameAndType        #251:#76      // hasNext:()Z
  #250 = Utf8               java/util/Iterator
  #251 = Utf8               hasNext
  #252 = InterfaceMethodref #248.#253     // java/util/Iterator.next:()Ljava/lang/Object;
  #253 = NameAndType        #254:#255     // next:()Ljava/lang/Object;
  #254 = Utf8               next
  #255 = Utf8               ()Ljava/lang/Object;
  #256 = Class              #257          // ext/mods/commons/data/StatSet
  #257 = Utf8               ext/mods/commons/data/StatSet
  #258 = String             #259          // cabal
  #259 = Utf8               cabal
  #260 = Methodref          #256.#261     // ext/mods/commons/data/StatSet.getEnum:(Ljava/lang/String;Ljava/lang/Class;)Ljava/lang/Enum;
  #261 = NameAndType        #262:#263     // getEnum:(Ljava/lang/String;Ljava/lang/Class;)Ljava/lang/Enum;
  #262 = Utf8               getEnum
  #263 = Utf8               (Ljava/lang/String;Ljava/lang/Class;)Ljava/lang/Enum;
  #264 = String             #265          // red_stones
  #265 = Utf8               red_stones
  #266 = Methodref          #256.#267     // ext/mods/commons/data/StatSet.getInteger:(Ljava/lang/String;)I
  #267 = NameAndType        #268:#269     // getInteger:(Ljava/lang/String;)I
  #268 = Utf8               getInteger
  #269 = Utf8               (Ljava/lang/String;)I
  #270 = String             #271          // green_stones
  #271 = Utf8               green_stones
  #272 = String             #273          // blue_stones
  #273 = Utf8               blue_stones
  #274 = String             #275          // contribution_score
  #275 = Utf8               contribution_score
  #276 = String             #277          // ancient_adena_amount
  #277 = Utf8               ancient_adena_amount
  #278 = Fieldref           #31.#279      // ext/mods/gameserver/enums/SealType.NONE:Lext/mods/gameserver/enums/SealType;
  #279 = NameAndType        #280:#281     // NONE:Lext/mods/gameserver/enums/SealType;
  #280 = Utf8               NONE
  #281 = Utf8               Lext/mods/gameserver/enums/SealType;
  #282 = String             #283          // seal
  #283 = Utf8               seal
  #284 = Methodref          #285.#286     // ext/mods/commons/pool/ConnectionPool.getConnection:()Ljava/sql/Connection;
  #285 = Class              #287          // ext/mods/commons/pool/ConnectionPool
  #286 = NameAndType        #288:#289     // getConnection:()Ljava/sql/Connection;
  #287 = Utf8               ext/mods/commons/pool/ConnectionPool
  #288 = Utf8               getConnection
  #289 = Utf8               ()Ljava/sql/Connection;
  #290 = String             #291          // SELECT char_obj_id, cabal, seal, red_stones, green_stones, blue_stones, ancient_adena_amount, contribution_score FROM seven_signs
  #291 = Utf8               SELECT char_obj_id, cabal, seal, red_stones, green_stones, blue_stones, ancient_adena_amount, contribution_score FROM seven_signs
  #292 = InterfaceMethodref #293.#294     // java/sql/Connection.prepareStatement:(Ljava/lang/String;)Ljava/sql/PreparedStatement;
  #293 = Class              #295          // java/sql/Connection
  #294 = NameAndType        #296:#297     // prepareStatement:(Ljava/lang/String;)Ljava/sql/PreparedStatement;
  #295 = Utf8               java/sql/Connection
  #296 = Utf8               prepareStatement
  #297 = Utf8               (Ljava/lang/String;)Ljava/sql/PreparedStatement;
  #298 = InterfaceMethodref #299.#300     // java/sql/PreparedStatement.executeQuery:()Ljava/sql/ResultSet;
  #299 = Class              #301          // java/sql/PreparedStatement
  #300 = NameAndType        #302:#303     // executeQuery:()Ljava/sql/ResultSet;
  #301 = Utf8               java/sql/PreparedStatement
  #302 = Utf8               executeQuery
  #303 = Utf8               ()Ljava/sql/ResultSet;
  #304 = InterfaceMethodref #305.#306     // java/sql/ResultSet.next:()Z
  #305 = Class              #307          // java/sql/ResultSet
  #306 = NameAndType        #254:#76      // next:()Z
  #307 = Utf8               java/sql/ResultSet
  #308 = String             #309          // char_obj_id
  #309 = Utf8               char_obj_id
  #310 = InterfaceMethodref #305.#311     // java/sql/ResultSet.getInt:(Ljava/lang/String;)I
  #311 = NameAndType        #312:#269     // getInt:(Ljava/lang/String;)I
  #312 = Utf8               getInt
  #313 = Methodref          #256.#7       // ext/mods/commons/data/StatSet."<init>":()V
  #314 = Methodref          #256.#315     // ext/mods/commons/data/StatSet.set:(Ljava/lang/String;I)V
  #315 = NameAndType        #134:#316     // set:(Ljava/lang/String;I)V
  #316 = Utf8               (Ljava/lang/String;I)V
  #317 = InterfaceMethodref #305.#318     // java/sql/ResultSet.getString:(Ljava/lang/String;)Ljava/lang/String;
  #318 = NameAndType        #319:#320     // getString:(Ljava/lang/String;)Ljava/lang/String;
  #319 = Utf8               getString
  #320 = Utf8               (Ljava/lang/String;)Ljava/lang/String;
  #321 = Methodref          #322.#323     // java/lang/Enum.valueOf:(Ljava/lang/Class;Ljava/lang/String;)Ljava/lang/Enum;
  #322 = Class              #324          // java/lang/Enum
  #323 = NameAndType        #120:#325     // valueOf:(Ljava/lang/Class;Ljava/lang/String;)Ljava/lang/Enum;
  #324 = Utf8               java/lang/Enum
  #325 = Utf8               (Ljava/lang/Class;Ljava/lang/String;)Ljava/lang/Enum;
  #326 = Methodref          #256.#327     // ext/mods/commons/data/StatSet.set:(Ljava/lang/String;Ljava/lang/Enum;)V
  #327 = NameAndType        #134:#328     // set:(Ljava/lang/String;Ljava/lang/Enum;)V
  #328 = Utf8               (Ljava/lang/String;Ljava/lang/Enum;)V
  #329 = InterfaceMethodref #305.#330     // java/sql/ResultSet.getDouble:(Ljava/lang/String;)D
  #330 = NameAndType        #331:#332     // getDouble:(Ljava/lang/String;)D
  #331 = Utf8               getDouble
  #332 = Utf8               (Ljava/lang/String;)D
  #333 = Methodref          #256.#334     // ext/mods/commons/data/StatSet.set:(Ljava/lang/String;D)V
  #334 = NameAndType        #134:#335     // set:(Ljava/lang/String;D)V
  #335 = Utf8               (Ljava/lang/String;D)V
  #336 = InterfaceMethodref #230.#337     // java/util/Map.put:(Ljava/lang/Object;Ljava/lang/Object;)Ljava/lang/Object;
  #337 = NameAndType        #338:#339     // put:(Ljava/lang/Object;Ljava/lang/Object;)Ljava/lang/Object;
  #338 = Utf8               put
  #339 = Utf8               (Ljava/lang/Object;Ljava/lang/Object;)Ljava/lang/Object;
  #340 = InterfaceMethodref #305.#341     // java/sql/ResultSet.close:()V
  #341 = NameAndType        #342:#10      // close:()V
  #342 = Utf8               close
  #343 = Class              #344          // java/lang/Throwable
  #344 = Utf8               java/lang/Throwable
  #345 = Methodref          #343.#346     // java/lang/Throwable.addSuppressed:(Ljava/lang/Throwable;)V
  #346 = NameAndType        #347:#348     // addSuppressed:(Ljava/lang/Throwable;)V
  #347 = Utf8               addSuppressed
  #348 = Utf8               (Ljava/lang/Throwable;)V
  #349 = InterfaceMethodref #299.#341     // java/sql/PreparedStatement.close:()V
  #350 = String             #351          // SELECT * FROM seven_signs_status WHERE id=0
  #351 = Utf8               SELECT * FROM seven_signs_status WHERE id=0
  #352 = String             #353          // current_cycle
  #353 = Utf8               current_cycle
  #354 = String             #355          // active_period
  #355 = Utf8               active_period
  #356 = String             #357          // previous_winner
  #357 = Utf8               previous_winner
  #358 = Fieldref           #3.#359       // ext/mods/gameserver/data/manager/SevenSignsManager._previousWinner:Lext/mods/gameserver/enums/CabalType;
  #359 = NameAndType        #360:#219     // _previousWinner:Lext/mods/gameserver/enums/CabalType;
  #360 = Utf8               _previousWinner
  #361 = String             #362          // dawn_stone_score
  #362 = Utf8               dawn_stone_score
  #363 = String             #364          // dusk_stone_score
  #364 = Utf8               dusk_stone_score
  #365 = Fieldref           #31.#366      // ext/mods/gameserver/enums/SealType.AVARICE:Lext/mods/gameserver/enums/SealType;
  #366 = NameAndType        #367:#281     // AVARICE:Lext/mods/gameserver/enums/SealType;
  #367 = Utf8               AVARICE
  #368 = String             #369          // avarice_owner
  #369 = Utf8               avarice_owner
  #370 = Fieldref           #31.#371      // ext/mods/gameserver/enums/SealType.GNOSIS:Lext/mods/gameserver/enums/SealType;
  #371 = NameAndType        #372:#281     // GNOSIS:Lext/mods/gameserver/enums/SealType;
  #372 = Utf8               GNOSIS
  #373 = String             #374          // gnosis_owner
  #374 = Utf8               gnosis_owner
  #375 = Fieldref           #31.#376      // ext/mods/gameserver/enums/SealType.STRIFE:Lext/mods/gameserver/enums/SealType;
  #376 = NameAndType        #377:#281     // STRIFE:Lext/mods/gameserver/enums/SealType;
  #377 = Utf8               STRIFE
  #378 = String             #379          // strife_owner
  #379 = Utf8               strife_owner
  #380 = String             #381          // avarice_dawn_score
  #381 = Utf8               avarice_dawn_score
  #382 = String             #383          // gnosis_dawn_score
  #383 = Utf8               gnosis_dawn_score
  #384 = String             #385          // strife_dawn_score
  #385 = Utf8               strife_dawn_score
  #386 = String             #387          // avarice_dusk_score
  #387 = Utf8               avarice_dusk_score
  #388 = String             #389          // gnosis_dusk_score
  #389 = Utf8               gnosis_dusk_score
  #390 = String             #391          // strife_dusk_score
  #391 = Utf8               strife_dusk_score
  #392 = String             #393          // date
  #393 = Utf8               date
  #394 = InterfaceMethodref #305.#395     // java/sql/ResultSet.getLong:(Ljava/lang/String;)J
  #395 = NameAndType        #396:#397     // getLong:(Ljava/lang/String;)J
  #396 = Utf8               getLong
  #397 = Utf8               (Ljava/lang/String;)J
  #398 = InterfaceMethodref #293.#341     // java/sql/Connection.close:()V
  #399 = Class              #400          // java/lang/Exception
  #400 = Utf8               java/lang/Exception
  #401 = String             #402          // Couldn\'t load Seven Signs data.
  #402 = Utf8               Couldn\'t load Seven Signs data.
  #403 = Methodref          #65.#404      // ext/mods/commons/logging/CLogger.error:(Ljava/lang/Object;Ljava/lang/Throwable;)V
  #404 = NameAndType        #405:#406     // error:(Ljava/lang/Object;Ljava/lang/Throwable;)V
  #405 = Utf8               error
  #406 = Utf8               (Ljava/lang/Object;Ljava/lang/Throwable;)V
  #407 = String             #408          // UPDATE seven_signs SET cabal=?, seal=?, red_stones=?, green_stones=?, blue_stones=?, ancient_adena_amount=?, contribution_score=? WHERE char_obj_id=?
  #408 = Utf8               UPDATE seven_signs SET cabal=?, seal=?, red_stones=?, green_stones=?, blue_stones=?, ancient_adena_amount=?, contribution_score=? WHERE char_obj_id=?
  #409 = Methodref          #256.#318     // ext/mods/commons/data/StatSet.getString:(Ljava/lang/String;)Ljava/lang/String;
  #410 = InterfaceMethodref #299.#411     // java/sql/PreparedStatement.setString:(ILjava/lang/String;)V
  #411 = NameAndType        #412:#413     // setString:(ILjava/lang/String;)V
  #412 = Utf8               setString
  #413 = Utf8               (ILjava/lang/String;)V
  #414 = InterfaceMethodref #299.#415     // java/sql/PreparedStatement.setInt:(II)V
  #415 = NameAndType        #416:#135     // setInt:(II)V
  #416 = Utf8               setInt
  #417 = Methodref          #256.#330     // ext/mods/commons/data/StatSet.getDouble:(Ljava/lang/String;)D
  #418 = InterfaceMethodref #299.#419     // java/sql/PreparedStatement.setDouble:(ID)V
  #419 = NameAndType        #420:#421     // setDouble:(ID)V
  #420 = Utf8               setDouble
  #421 = Utf8               (ID)V
  #422 = InterfaceMethodref #299.#423     // java/sql/PreparedStatement.addBatch:()V
  #423 = NameAndType        #424:#10      // addBatch:()V
  #424 = Utf8               addBatch
  #425 = InterfaceMethodref #299.#426     // java/sql/PreparedStatement.executeBatch:()[I
  #426 = NameAndType        #427:#428     // executeBatch:()[I
  #427 = Utf8               executeBatch
  #428 = Utf8               ()[I
  #429 = String             #430          // Couldn\'t save Seven Signs player data.
  #430 = Utf8               Couldn\'t save Seven Signs player data.
  #431 = String             #432          // UPDATE seven_signs_status SET current_cycle=?, active_period=?, previous_winner=?, dawn_stone_score=?, dawn_festival_score=?, dusk_stone_score=?, dusk_festival_score=?, avarice_owner=?, gnosis_owner=?, strife_owner=?, avarice_dawn_score=?, gnosis_dawn_score=?, strife_dawn_score=?, avarice_dusk_score=?, gnosis_dusk_score=?, strife_dusk_score=?, festival_cycle=?, accumulated_bonus0=?, accumulated_bonus1=?, accumulated_bonus2=?,accumulated_bonus3=?, accumulated_bonus4=?, date=? WHERE id=0
  #432 = Utf8               UPDATE seven_signs_status SET current_cycle=?, active_period=?, previous_winner=?, dawn_stone_score=?, dawn_festival_score=?, dusk_stone_score=?, dusk_festival_score=?, avarice_owner=?, gnosis_owner=?, strife_owner=?, avarice_dawn_score=?, gnosis_dawn_score=?, strife_dawn_score=?, avarice_dusk_score=?, gnosis_dusk_score=?, strife_dusk_score=?, festival_cycle=?, accumulated_bonus0=?, accumulated_bonus1=?, accumulated_bonus2=?,accumulated_bonus3=?, accumulated_bonus4=?, date=? WHERE id=0
  #433 = Methodref          #59.#434      // ext/mods/gameserver/enums/PeriodType.toString:()Ljava/lang/String;
  #434 = NameAndType        #435:#63      // toString:()Ljava/lang/String;
  #435 = Utf8               toString
  #436 = Methodref          #197.#434     // ext/mods/gameserver/enums/CabalType.toString:()Ljava/lang/String;
  #437 = Methodref          #209.#438     // ext/mods/gameserver/data/manager/FestivalOfDarknessManager.getCurrentFestivalCycle:()I
  #438 = NameAndType        #439:#131     // getCurrentFestivalCycle:()I
  #439 = Utf8               getCurrentFestivalCycle
  #440 = Methodref          #209.#441     // ext/mods/gameserver/data/manager/FestivalOfDarknessManager.getAccumulatedBonus:(I)I
  #441 = NameAndType        #442:#161     // getAccumulatedBonus:(I)I
  #442 = Utf8               getAccumulatedBonus
  #443 = InterfaceMethodref #299.#444     // java/sql/PreparedStatement.setLong:(IJ)V
  #444 = NameAndType        #445:#446     // setLong:(IJ)V
  #445 = Utf8               setLong
  #446 = Utf8               (IJ)V
  #447 = InterfaceMethodref #299.#448     // java/sql/PreparedStatement.execute:()Z
  #448 = NameAndType        #449:#76      // execute:()Z
  #449 = Utf8               execute
  #450 = String             #451          // Couldn\'t save Seven Signs status data.
  #451 = Utf8               Couldn\'t save Seven Signs status data.
  #452 = String             #453          // INSERT INTO seven_signs (char_obj_id, cabal, seal) VALUES (?,?,?)
  #453 = Utf8               INSERT INTO seven_signs (char_obj_id, cabal, seal) VALUES (?,?,?)
  #454 = Methodref          #31.#434      // ext/mods/gameserver/enums/SealType.toString:()Ljava/lang/String;
  #455 = String             #456          // Couldn\'t save Seven Signs player info data.
  #456 = Utf8               Couldn\'t save Seven Signs player info data.
  #457 = Methodref          #3.#458       // ext/mods/gameserver/data/manager/SevenSignsManager.calcScore:(III)I
  #458 = NameAndType        #459:#460     // calcScore:(III)I
  #459 = Utf8               calcScore
  #460 = Utf8               (III)I
  #461 = Fieldref           #462.#463     // ext/mods/Config.MAXIMUM_PLAYER_CONTRIB:I
  #462 = Class              #464          // ext/mods/Config
  #463 = NameAndType        #465:#157     // MAXIMUM_PLAYER_CONTRIB:I
  #464 = Utf8               ext/mods/Config
  #465 = Utf8               MAXIMUM_PLAYER_CONTRIB
  #466 = Methodref          #3.#467       // ext/mods/gameserver/data/manager/SevenSignsManager.getPlayerCabal:(I)Lext/mods/gameserver/enums/CabalType;
  #467 = NameAndType        #468:#469     // getPlayerCabal:(I)Lext/mods/gameserver/enums/CabalType;
  #468 = Utf8               getPlayerCabal
  #469 = Utf8               (I)Lext/mods/gameserver/enums/CabalType;
  #470 = InterfaceMethodref #230.#471     // java/util/Map.entrySet:()Ljava/util/Set;
  #471 = NameAndType        #472:#473     // entrySet:()Ljava/util/Set;
  #472 = Utf8               entrySet
  #473 = Utf8               ()Ljava/util/Set;
  #474 = InterfaceMethodref #475.#243     // java/util/Set.iterator:()Ljava/util/Iterator;
  #475 = Class              #476          // java/util/Set
  #476 = Utf8               java/util/Set
  #477 = Class              #478          // java/util/Map$Entry
  #478 = Utf8               java/util/Map$Entry
  #479 = InterfaceMethodref #477.#480     // java/util/Map$Entry.getKey:()Ljava/lang/Object;
  #480 = NameAndType        #481:#255     // getKey:()Ljava/lang/Object;
  #481 = Utf8               getKey
  #482 = InterfaceMethodref #477.#483     // java/util/Map$Entry.getValue:()Ljava/lang/Object;
  #483 = NameAndType        #484:#255     // getValue:()Ljava/lang/Object;
  #484 = Utf8               getValue
  #485 = Methodref          #3.#486       // ext/mods/gameserver/data/manager/SevenSignsManager.isSealValidationPeriod:()Z
  #486 = NameAndType        #487:#76      // isSealValidationPeriod:()Z
  #487 = Utf8               isSealValidationPeriod
  #488 = String             #489          // The {} have won {}.
  #489 = Utf8               The {} have won {}.
  #490 = Methodref          #197.#491     // ext/mods/gameserver/enums/CabalType.getFullName:()Ljava/lang/String;
  #491 = NameAndType        #492:#63      // getFullName:()Ljava/lang/String;
  #492 = Utf8               getFullName
  #493 = Methodref          #31.#491      // ext/mods/gameserver/enums/SealType.getFullName:()Ljava/lang/String;
  #494 = String             #495          // The {} is currently owned by {}.
  #495 = Utf8               The {} is currently owned by {}.
  #496 = String             #497          // The {} remains unclaimed.
  #497 = Utf8               The {} remains unclaimed.
  #498 = InterfaceMethodref #230.#499     // java/util/Map.keySet:()Ljava/util/Set;
  #499 = NameAndType        #500:#473     // keySet:()Ljava/util/Set;
  #500 = Utf8               keySet
  #501 = Methodref          #3.#502       // ext/mods/gameserver/data/manager/SevenSignsManager.getSealProportion:(Lext/mods/gameserver/enums/SealType;Lext/mods/gameserver/enums/CabalType;)I
  #502 = NameAndType        #503:#504     // getSealProportion:(Lext/mods/gameserver/enums/SealType;Lext/mods/gameserver/enums/CabalType;)I
  #503 = Utf8               getSealProportion
  #504 = Utf8               (Lext/mods/gameserver/enums/SealType;Lext/mods/gameserver/enums/CabalType;)I
  #505 = Methodref          #3.#506       // ext/mods/gameserver/data/manager/SevenSignsManager.getTotalMembers:(Lext/mods/gameserver/enums/CabalType;)I
  #506 = NameAndType        #507:#207     // getTotalMembers:(Lext/mods/gameserver/enums/CabalType;)I
  #507 = Utf8               getTotalMembers
  #508 = Methodref          #107.#509     // java/lang/Math.max:(II)I
  #509 = NameAndType        #510:#511     // max:(II)I
  #510 = Utf8               max
  #511 = Utf8               (II)I
  #512 = Float              100.0f
  #513 = Methodref          #3.#514       // ext/mods/gameserver/data/manager/SevenSignsManager.getWinningCabal:()Lext/mods/gameserver/enums/CabalType;
  #514 = NameAndType        #515:#516     // getWinningCabal:()Lext/mods/gameserver/enums/CabalType;
  #515 = Utf8               getWinningCabal
  #516 = Utf8               ()Lext/mods/gameserver/enums/CabalType;
  #517 = Fieldref           #123.#518     // ext/mods/gameserver/data/manager/SevenSignsManager$1.$SwitchMap$ext$mods$gameserver$enums$SealType:[I
  #518 = NameAndType        #519:#127     // $SwitchMap$ext$mods$gameserver$enums$SealType:[I
  #519 = Utf8               $SwitchMap$ext$mods$gameserver$enums$SealType
  #520 = Methodref          #31.#129      // ext/mods/gameserver/enums/SealType.ordinal:()I
  #521 = Fieldref           #522.#523     // ext/mods/gameserver/network/SystemMessageId.DAWN_OBTAINED_AVARICE:Lext/mods/gameserver/network/SystemMessageId;
  #522 = Class              #524          // ext/mods/gameserver/network/SystemMessageId
  #523 = NameAndType        #525:#526     // DAWN_OBTAINED_AVARICE:Lext/mods/gameserver/network/SystemMessageId;
  #524 = Utf8               ext/mods/gameserver/network/SystemMessageId
  #525 = Utf8               DAWN_OBTAINED_AVARICE
  #526 = Utf8               Lext/mods/gameserver/network/SystemMessageId;
  #527 = Methodref          #528.#529     // ext/mods/gameserver/network/serverpackets/SystemMessage.getSystemMessage:(Lext/mods/gameserver/network/SystemMessageId;)Lext/mods/gameserver/network/serverpackets/SystemMessage;
  #528 = Class              #530          // ext/mods/gameserver/network/serverpackets/SystemMessage
  #529 = NameAndType        #531:#532     // getSystemMessage:(Lext/mods/gameserver/network/SystemMessageId;)Lext/mods/gameserver/network/serverpackets/SystemMessage;
  #530 = Utf8               ext/mods/gameserver/network/serverpackets/SystemMessage
  #531 = Utf8               getSystemMessage
  #532 = Utf8               (Lext/mods/gameserver/network/SystemMessageId;)Lext/mods/gameserver/network/serverpackets/SystemMessage;
  #533 = Methodref          #534.#535     // ext/mods/gameserver/model/World.toAllOnlinePlayers:(Lext/mods/gameserver/network/serverpackets/L2GameServerPacket;)V
  #534 = Class              #536          // ext/mods/gameserver/model/World
  #535 = NameAndType        #537:#538     // toAllOnlinePlayers:(Lext/mods/gameserver/network/serverpackets/L2GameServerPacket;)V
  #536 = Utf8               ext/mods/gameserver/model/World
  #537 = Utf8               toAllOnlinePlayers
  #538 = Utf8               (Lext/mods/gameserver/network/serverpackets/L2GameServerPacket;)V
  #539 = Fieldref           #522.#540     // ext/mods/gameserver/network/SystemMessageId.DUSK_OBTAINED_AVARICE:Lext/mods/gameserver/network/SystemMessageId;
  #540 = NameAndType        #541:#526     // DUSK_OBTAINED_AVARICE:Lext/mods/gameserver/network/SystemMessageId;
  #541 = Utf8               DUSK_OBTAINED_AVARICE
  #542 = Fieldref           #522.#543     // ext/mods/gameserver/network/SystemMessageId.DAWN_OBTAINED_GNOSIS:Lext/mods/gameserver/network/SystemMessageId;
  #543 = NameAndType        #544:#526     // DAWN_OBTAINED_GNOSIS:Lext/mods/gameserver/network/SystemMessageId;
  #544 = Utf8               DAWN_OBTAINED_GNOSIS
  #545 = Fieldref           #522.#546     // ext/mods/gameserver/network/SystemMessageId.DUSK_OBTAINED_GNOSIS:Lext/mods/gameserver/network/SystemMessageId;
  #546 = NameAndType        #547:#526     // DUSK_OBTAINED_GNOSIS:Lext/mods/gameserver/network/SystemMessageId;
  #547 = Utf8               DUSK_OBTAINED_GNOSIS
  #548 = Fieldref           #522.#549     // ext/mods/gameserver/network/SystemMessageId.DAWN_OBTAINED_STRIFE:Lext/mods/gameserver/network/SystemMessageId;
  #549 = NameAndType        #550:#526     // DAWN_OBTAINED_STRIFE:Lext/mods/gameserver/network/SystemMessageId;
  #550 = Utf8               DAWN_OBTAINED_STRIFE
  #551 = Fieldref           #522.#552     // ext/mods/gameserver/network/SystemMessageId.DUSK_OBTAINED_STRIFE:Lext/mods/gameserver/network/SystemMessageId;
  #552 = NameAndType        #553:#526     // DUSK_OBTAINED_STRIFE:Lext/mods/gameserver/network/SystemMessageId;
  #553 = Utf8               DUSK_OBTAINED_STRIFE
  #554 = Methodref          #555.#556     // ext/mods/gameserver/data/manager/CastleManager.getInstance:()Lext/mods/gameserver/data/manager/CastleManager;
  #555 = Class              #557          // ext/mods/gameserver/data/manager/CastleManager
  #556 = NameAndType        #13:#558      // getInstance:()Lext/mods/gameserver/data/manager/CastleManager;
  #557 = Utf8               ext/mods/gameserver/data/manager/CastleManager
  #558 = Utf8               ()Lext/mods/gameserver/data/manager/CastleManager;
  #559 = Methodref          #555.#560     // ext/mods/gameserver/data/manager/CastleManager.validateTaxes:(Lext/mods/gameserver/enums/CabalType;)V
  #560 = NameAndType        #561:#562     // validateTaxes:(Lext/mods/gameserver/enums/CabalType;)V
  #561 = Utf8               validateTaxes
  #562 = Utf8               (Lext/mods/gameserver/enums/CabalType;)V
  #563 = Methodref          #534.#564     // ext/mods/gameserver/model/World.getInstance:()Lext/mods/gameserver/model/World;
  #564 = NameAndType        #13:#565      // getInstance:()Lext/mods/gameserver/model/World;
  #565 = Utf8               ()Lext/mods/gameserver/model/World;
  #566 = Methodref          #534.#567     // ext/mods/gameserver/model/World.getPlayers:()Ljava/util/Collection;
  #567 = NameAndType        #568:#240     // getPlayers:()Ljava/util/Collection;
  #568 = Utf8               getPlayers
  #569 = Class              #570          // ext/mods/gameserver/model/actor/Player
  #570 = Utf8               ext/mods/gameserver/model/actor/Player
  #571 = Methodref          #569.#572     // ext/mods/gameserver/model/actor/Player.isGM:()Z
  #572 = NameAndType        #573:#76      // isGM:()Z
  #573 = Utf8               isGM
  #574 = Methodref          #569.#575     // ext/mods/gameserver/model/actor/Player.isIn7sDungeon:()Z
  #575 = NameAndType        #576:#76      // isIn7sDungeon:()Z
  #576 = Utf8               isIn7sDungeon
  #577 = Methodref          #569.#578     // ext/mods/gameserver/model/actor/Player.getObjectId:()I
  #578 = NameAndType        #579:#131     // getObjectId:()I
  #579 = Utf8               getObjectId
  #580 = Methodref          #3.#581       // ext/mods/gameserver/data/manager/SevenSignsManager.isCompResultsPeriod:()Z
  #581 = NameAndType        #582:#76      // isCompResultsPeriod:()Z
  #582 = Utf8               isCompResultsPeriod
  #583 = Fieldref           #584.#585     // ext/mods/gameserver/enums/RestartType.TOWN:Lext/mods/gameserver/enums/RestartType;
  #584 = Class              #586          // ext/mods/gameserver/enums/RestartType
  #585 = NameAndType        #587:#588     // TOWN:Lext/mods/gameserver/enums/RestartType;
  #586 = Utf8               ext/mods/gameserver/enums/RestartType
  #587 = Utf8               TOWN
  #588 = Utf8               Lext/mods/gameserver/enums/RestartType;
  #589 = Methodref          #569.#590     // ext/mods/gameserver/model/actor/Player.teleportTo:(Lext/mods/gameserver/enums/RestartType;)V
  #590 = NameAndType        #591:#592     // teleportTo:(Lext/mods/gameserver/enums/RestartType;)V
  #591 = Utf8               teleportTo
  #592 = Utf8               (Lext/mods/gameserver/enums/RestartType;)V
  #593 = Methodref          #569.#594     // ext/mods/gameserver/model/actor/Player.setIsIn7sDungeon:(Z)V
  #594 = NameAndType        #595:#596     // setIsIn7sDungeon:(Z)V
  #595 = Utf8               setIsIn7sDungeon
  #596 = Utf8               (Z)V
  #597 = Fieldref           #598.#599     // ext/mods/gameserver/data/SkillTable$FrequentSkill.THE_VICTOR_OF_WAR:Lext/mods/gameserver/data/SkillTable$FrequentSkill;
  #598 = Class              #600          // ext/mods/gameserver/data/SkillTable$FrequentSkill
  #599 = NameAndType        #601:#602     // THE_VICTOR_OF_WAR:Lext/mods/gameserver/data/SkillTable$FrequentSkill;
  #600 = Utf8               ext/mods/gameserver/data/SkillTable$FrequentSkill
  #601 = Utf8               THE_VICTOR_OF_WAR
  #602 = Utf8               Lext/mods/gameserver/data/SkillTable$FrequentSkill;
  #603 = Methodref          #598.#604     // ext/mods/gameserver/data/SkillTable$FrequentSkill.getSkill:()Lext/mods/gameserver/skills/L2Skill;
  #604 = NameAndType        #605:#606     // getSkill:()Lext/mods/gameserver/skills/L2Skill;
  #605 = Utf8               getSkill
  #606 = Utf8               ()Lext/mods/gameserver/skills/L2Skill;
  #607 = Methodref          #569.#608     // ext/mods/gameserver/model/actor/Player.addSkill:(Lext/mods/gameserver/skills/L2Skill;Z)Z
  #608 = NameAndType        #609:#610     // addSkill:(Lext/mods/gameserver/skills/L2Skill;Z)Z
  #609 = Utf8               addSkill
  #610 = Utf8               (Lext/mods/gameserver/skills/L2Skill;Z)Z
  #611 = Fieldref           #598.#612     // ext/mods/gameserver/data/SkillTable$FrequentSkill.THE_VANQUISHED_OF_WAR:Lext/mods/gameserver/data/SkillTable$FrequentSkill;
  #612 = NameAndType        #613:#602     // THE_VANQUISHED_OF_WAR:Lext/mods/gameserver/data/SkillTable$FrequentSkill;
  #613 = Utf8               THE_VANQUISHED_OF_WAR
  #614 = Methodref          #615.#616     // ext/mods/gameserver/skills/L2Skill.getId:()I
  #615 = Class              #617          // ext/mods/gameserver/skills/L2Skill
  #616 = NameAndType        #618:#131     // getId:()I
  #617 = Utf8               ext/mods/gameserver/skills/L2Skill
  #618 = Utf8               getId
  #619 = Methodref          #569.#620     // ext/mods/gameserver/model/actor/Player.removeSkill:(IZ)Lext/mods/gameserver/skills/L2Skill;
  #620 = NameAndType        #621:#622     // removeSkill:(IZ)Lext/mods/gameserver/skills/L2Skill;
  #621 = Utf8               removeSkill
  #622 = Utf8               (IZ)Lext/mods/gameserver/skills/L2Skill;
  #623 = Long               10l
  #625 = Fieldref           #462.#626     // ext/mods/Config.CATACOMBS_IN_ANY_PERIOD:Z
  #626 = NameAndType        #627:#628     // CATACOMBS_IN_ANY_PERIOD:Z
  #627 = Utf8               CATACOMBS_IN_ANY_PERIOD
  #628 = Utf8               Z
  #629 = Fieldref           #630.#631     // ext/mods/gameserver/data/manager/SevenSignsManager$SingletonHolder.INSTANCE:Lext/mods/gameserver/data/manager/SevenSignsManager;
  #630 = Class              #632          // ext/mods/gameserver/data/manager/SevenSignsManager$SingletonHolder
  #631 = NameAndType        #633:#634     // INSTANCE:Lext/mods/gameserver/data/manager/SevenSignsManager;
  #632 = Utf8               ext/mods/gameserver/data/manager/SevenSignsManager$SingletonHolder
  #633 = Utf8               INSTANCE
  #634 = Utf8               Lext/mods/gameserver/data/manager/SevenSignsManager;
  #635 = Methodref          #636.#60      // java/lang/Class.getName:()Ljava/lang/String;
  #636 = Class              #637          // java/lang/Class
  #637 = Utf8               java/lang/Class
  #638 = Methodref          #65.#639      // ext/mods/commons/logging/CLogger."<init>":(Ljava/lang/String;)V
  #639 = NameAndType        #9:#640       // "<init>":(Ljava/lang/String;)V
  #640 = Utf8               (Ljava/lang/String;)V
  #641 = Utf8               LOAD_DATA
  #642 = Utf8               Ljava/lang/String;
  #643 = Utf8               ConstantValue
  #644 = Utf8               LOAD_STATUS
  #645 = Utf8               INSERT_PLAYER
  #646 = Utf8               UPDATE_PLAYER
  #647 = Utf8               UPDATE_STATUS
  #648 = Utf8               SEVEN_SIGNS_HTML_PATH
  #649 = String             #650          // html/seven_signs/
  #650 = Utf8               html/seven_signs/
  #651 = Utf8               PERIOD_START_HOUR
  #652 = Integer            18
  #653 = Utf8               PERIOD_START_MINS
  #654 = Integer            0
  #655 = Utf8               PERIOD_START_DAY
  #656 = Integer            2
  #657 = Utf8               PERIOD_MINOR_LENGTH
  #658 = Utf8               PERIOD_MAJOR_LENGTH
  #659 = Integer            603900000
  #660 = Utf8               RECORD_SEVEN_SIGNS_ID
  #661 = Integer            5707
  #662 = Utf8               CERTIFICATE_OF_APPROVAL_ID
  #663 = Integer            6388
  #664 = Utf8               RECORD_SEVEN_SIGNS_COST
  #665 = Integer            500
  #666 = Utf8               ADENA_JOIN_DAWN_COST
  #667 = Integer            50000
  #668 = Utf8               SEAL_STONE_BLUE_ID
  #669 = Integer            6360
  #670 = Utf8               SEAL_STONE_GREEN_ID
  #671 = Integer            6361
  #672 = Utf8               SEAL_STONE_RED_ID
  #673 = Integer            6362
  #674 = Utf8               SEAL_STONE_BLUE_VALUE
  #675 = Integer            3
  #676 = Utf8               SEAL_STONE_GREEN_VALUE
  #677 = Integer            5
  #678 = Utf8               SEAL_STONE_RED_VALUE
  #679 = Integer            10
  #680 = Utf8               Signature
  #681 = Utf8               Ljava/util/Map<Ljava/lang/Integer;Lext/mods/commons/data/StatSet;>;
  #682 = Utf8               Ljava/util/Map<Lext/mods/gameserver/enums/SealType;Lext/mods/gameserver/enums/CabalType;>;
  #683 = Utf8               Ljava/util/Map<Lext/mods/gameserver/enums/SealType;Ljava/lang/Integer;>;
  #684 = Utf8               Code
  #685 = Utf8               LineNumberTable
  #686 = Utf8               LocalVariableTable
  #687 = Utf8               this
  #688 = Utf8               milliToChange
  #689 = Utf8               J
  #690 = Utf8               numSecs
  #691 = Utf8               countDown
  #692 = Utf8               numMins
  #693 = Utf8               numHours
  #694 = Utf8               numDays
  #695 = Utf8               StackMapTable
  #696 = Utf8               lastPeriodChange
  #697 = Utf8               blueCount
  #698 = Utf8               greenCount
  #699 = Utf8               redCount
  #700 = Utf8               getCurrentCycle
  #701 = Utf8               getCurrentPeriod
  #702 = Utf8               ()Lext/mods/gameserver/enums/PeriodType;
  #703 = Utf8               daysToChange
  #704 = Utf8               isRecruitingPeriod
  #705 = Utf8               totalStoneScore
  #706 = Utf8               getCurrentStoneScore
  #707 = Utf8               (Lext/mods/gameserver/enums/CabalType;)D
  #708 = Utf8               duskScore
  #709 = Utf8               dawnScore
  #710 = Utf8               getLosingCabal
  #711 = Utf8               getSealOwner
  #712 = Utf8               (Lext/mods/gameserver/enums/SealType;)Lext/mods/gameserver/enums/CabalType;
  #713 = Utf8               getSealOwners
  #714 = Utf8               ()Ljava/util/Map;
  #715 = Utf8               ()Ljava/util/Map<Lext/mods/gameserver/enums/SealType;Lext/mods/gameserver/enums/CabalType;>;
  #716 = Utf8               Lext/mods/commons/data/StatSet;
  #717 = Utf8               cabalMembers
  #718 = Utf8               getPlayerStoneContrib
  #719 = Utf8               objectId
  #720 = Utf8               getPlayerContribScore
  #721 = Utf8               getPlayerAdenaCollect
  #722 = Utf8               getPlayerSeal
  #723 = Utf8               (I)Lext/mods/gameserver/enums/SealType;
  #724 = Utf8               rs
  #725 = Utf8               Ljava/sql/ResultSet;
  #726 = Utf8               ps
  #727 = Utf8               Ljava/sql/PreparedStatement;
  #728 = Utf8               con
  #729 = Utf8               Ljava/sql/Connection;
  #730 = Utf8               e
  #731 = Utf8               Ljava/lang/Exception;
  #732 = Utf8               saveSevenSignsData
  #733 = Utf8               saveSevenSignsStatus
  #734 = Utf8               i
  #735 = Utf8               resetPlayerData
  #736 = Utf8               setPlayerInfo
  #737 = Utf8               (ILext/mods/gameserver/enums/CabalType;Lext/mods/gameserver/enums/SealType;)Lext/mods/gameserver/enums/CabalType;
  #738 = Utf8               getAncientAdenaReward
  #739 = Utf8               rewardAmount
  #740 = Utf8               addPlayerStoneContrib
  #741 = Utf8               (IIII)I
  #742 = Utf8               contribScore
  #743 = Utf8               totalAncientAdena
  #744 = Utf8               totalContribScore
  #745 = Utf8               currentSeal
  #746 = Utf8               sealOwner
  #747 = Utf8               sealEntry
  #748 = Utf8               Ljava/util/Map$Entry;
  #749 = Utf8               LocalVariableTypeTable
  #750 = Utf8               Ljava/util/Map$Entry<Lext/mods/gameserver/enums/SealType;Lext/mods/gameserver/enums/CabalType;>;
  #751 = Utf8               resetSeals
  #752 = Utf8               calcNewSealOwners
  #753 = Utf8               prevSealOwner
  #754 = Utf8               dawnProportion
  #755 = Utf8               totalDawnMembers
  #756 = Utf8               dawnPercent
  #757 = Utf8               duskProportion
  #758 = Utf8               totalDuskMembers
  #759 = Utf8               duskPercent
  #760 = Utf8               newSealOwner
  #761 = Utf8               teleLosingCabalFromDungeons
  #762 = Utf8               playerCabal
  #763 = Utf8               player
  #764 = Utf8               Lext/mods/gameserver/model/actor/Player;
  #765 = Utf8               winningCabal
  #766 = Utf8               giveSosEffect
  #767 = Utf8               strifeOwner
  #768 = Utf8               removeSosEffect
  #769 = Utf8               changePeriod
  #770 = Utf8               allowCatacombsInAnyPeriod
  #771 = Utf8               ()Lext/mods/gameserver/data/manager/SevenSignsManager;
  #772 = Utf8               <clinit>
  #773 = Utf8               SourceFile
  #774 = Utf8               SevenSignsManager.java
  #775 = Utf8               NestMembers
  #776 = Utf8               InnerClasses
  #777 = Utf8               SevenSignsPeriodChange
  #778 = Utf8               Entry
  #779 = Class              #780          // ext/mods/gameserver/data/SkillTable
  #780 = Utf8               ext/mods/gameserver/data/SkillTable
  #781 = Utf8               FrequentSkill
  #782 = Utf8               SingletonHolder
{
  public static final java.lang.String SEVEN_SIGNS_HTML_PATH;
    descriptor: Ljava/lang/String;
    flags: (0x0019) ACC_PUBLIC, ACC_STATIC, ACC_FINAL
    ConstantValue: String html/seven_signs/

  public static final int PERIOD_START_HOUR;
    descriptor: I
    flags: (0x0019) ACC_PUBLIC, ACC_STATIC, ACC_FINAL
    ConstantValue: int 18

  public static final int PERIOD_START_MINS;
    descriptor: I
    flags: (0x0019) ACC_PUBLIC, ACC_STATIC, ACC_FINAL
    ConstantValue: int 0

  public static final int PERIOD_START_DAY;
    descriptor: I
    flags: (0x0019) ACC_PUBLIC, ACC_STATIC, ACC_FINAL
    ConstantValue: int 2

  public static final int PERIOD_MINOR_LENGTH;
    descriptor: I
    flags: (0x0019) ACC_PUBLIC, ACC_STATIC, ACC_FINAL
    ConstantValue: int 900000

  public static final int PERIOD_MAJOR_LENGTH;
    descriptor: I
    flags: (0x0019) ACC_PUBLIC, ACC_STATIC, ACC_FINAL
    ConstantValue: int 603900000

  public static final int RECORD_SEVEN_SIGNS_ID;
    descriptor: I
    flags: (0x0019) ACC_PUBLIC, ACC_STATIC, ACC_FINAL
    ConstantValue: int 5707

  public static final int CERTIFICATE_OF_APPROVAL_ID;
    descriptor: I
    flags: (0x0019) ACC_PUBLIC, ACC_STATIC, ACC_FINAL
    ConstantValue: int 6388

  public static final int RECORD_SEVEN_SIGNS_COST;
    descriptor: I
    flags: (0x0019) ACC_PUBLIC, ACC_STATIC, ACC_FINAL
    ConstantValue: int 500

  public static final int ADENA_JOIN_DAWN_COST;
    descriptor: I
    flags: (0x0019) ACC_PUBLIC, ACC_STATIC, ACC_FINAL
    ConstantValue: int 50000

  public static final int SEAL_STONE_BLUE_ID;
    descriptor: I
    flags: (0x0019) ACC_PUBLIC, ACC_STATIC, ACC_FINAL
    ConstantValue: int 6360

  public static final int SEAL_STONE_GREEN_ID;
    descriptor: I
    flags: (0x0019) ACC_PUBLIC, ACC_STATIC, ACC_FINAL
    ConstantValue: int 6361

  public static final int SEAL_STONE_RED_ID;
    descriptor: I
    flags: (0x0019) ACC_PUBLIC, ACC_STATIC, ACC_FINAL
    ConstantValue: int 6362

  public static final int SEAL_STONE_BLUE_VALUE;
    descriptor: I
    flags: (0x0019) ACC_PUBLIC, ACC_STATIC, ACC_FINAL
    ConstantValue: int 3

  public static final int SEAL_STONE_GREEN_VALUE;
    descriptor: I
    flags: (0x0019) ACC_PUBLIC, ACC_STATIC, ACC_FINAL
    ConstantValue: int 5

  public static final int SEAL_STONE_RED_VALUE;
    descriptor: I
    flags: (0x0019) ACC_PUBLIC, ACC_STATIC, ACC_FINAL
    ConstantValue: int 10

  protected ext.mods.gameserver.enums.PeriodType _activePeriod;
    descriptor: Lext/mods/gameserver/enums/PeriodType;
    flags: (0x0004) ACC_PROTECTED

  protected int _currentCycle;
    descriptor: I
    flags: (0x0004) ACC_PROTECTED

  protected double _dawnStoneScore;
    descriptor: D
    flags: (0x0004) ACC_PROTECTED

  protected double _duskStoneScore;
    descriptor: D
    flags: (0x0004) ACC_PROTECTED

  protected ext.mods.gameserver.enums.CabalType _previousWinner;
    descriptor: Lext/mods/gameserver/enums/CabalType;
    flags: (0x0004) ACC_PROTECTED

  protected ext.mods.gameserver.data.manager.SevenSignsManager();
    descriptor: ()V
    flags: (0x0004) ACC_PROTECTED
    Code:
      stack=6, locals=10, args_size=1
         0: aload_0
         1: invokespecial #5                  // Method java/lang/Object."<init>":()V
         4: aload_0
         5: invokestatic  #11                 // Method java/util/Calendar.getInstance:()Ljava/util/Calendar;
         8: putfield      #15                 // Field _nextPeriodChange:Ljava/util/Calendar;
        11: aload_0
        12: invokestatic  #11                 // Method java/util/Calendar.getInstance:()Ljava/util/Calendar;
        15: putfield      #19                 // Field _lastSave:Ljava/util/Calendar;
        18: aload_0
        19: new           #22                 // class java/util/HashMap
        22: dup
        23: invokespecial #24                 // Method java/util/HashMap."<init>":()V
        26: putfield      #25                 // Field _playersData:Ljava/util/Map;
        29: aload_0
        30: new           #29                 // class java/util/EnumMap
        33: dup
        34: ldc           #31                 // class ext/mods/gameserver/enums/SealType
        36: invokespecial #33                 // Method java/util/EnumMap."<init>":(Ljava/lang/Class;)V
        39: putfield      #36                 // Field _sealOwners:Ljava/util/Map;
        42: aload_0
        43: new           #29                 // class java/util/EnumMap
        46: dup
        47: ldc           #31                 // class ext/mods/gameserver/enums/SealType
        49: invokespecial #33                 // Method java/util/EnumMap."<init>":(Ljava/lang/Class;)V
        52: putfield      #39                 // Field _duskScores:Ljava/util/Map;
        55: aload_0
        56: new           #29                 // class java/util/EnumMap
        59: dup
        60: ldc           #31                 // class ext/mods/gameserver/enums/SealType
        62: invokespecial #33                 // Method java/util/EnumMap."<init>":(Ljava/lang/Class;)V
        65: putfield      #42                 // Field _dawnScores:Ljava/util/Map;
        68: aload_0
        69: invokevirtual #45                 // Method restoreSevenSignsData:()V
        72: getstatic     #48                 // Field LOGGER:Lext/mods/commons/logging/CLogger;
        75: ldc           #52                 // String Currently on {} period.
        77: iconst_1
        78: anewarray     #6                  // class java/lang/Object
        81: dup
        82: iconst_0
        83: aload_0
        84: getfield      #54                 // Field _activePeriod:Lext/mods/gameserver/enums/PeriodType;
        87: invokevirtual #58                 // Method ext/mods/gameserver/enums/PeriodType.getName:()Ljava/lang/String;
        90: aastore
        91: invokevirtual #64                 // Method ext/mods/commons/logging/CLogger.info:(Ljava/lang/Object;[Ljava/lang/Object;)V
        94: aload_0
        95: invokevirtual #70                 // Method initializeSeals:()V
        98: lconst_0
        99: lstore_1
       100: aload_0
       101: invokevirtual #73                 // Method isNextPeriodChangeInPast:()Z
       104: ifeq          118
       107: getstatic     #48                 // Field LOGGER:Lext/mods/commons/logging/CLogger;
       110: ldc           #77                 // String Next Seven Signs period is already computed.
       112: invokevirtual #79                 // Method ext/mods/commons/logging/CLogger.info:(Ljava/lang/Object;)V
       115: goto          127
       118: aload_0
       119: invokevirtual #82                 // Method setCalendarForNextPeriodChange:()V
       122: aload_0
       123: invokevirtual #85                 // Method getMilliToPeriodChange:()J
       126: lstore_1
       127: new           #89                 // class ext/mods/gameserver/data/manager/SevenSignsManager$SevenSignsPeriodChange
       130: dup
       131: aload_0
       132: invokespecial #91                 // Method ext/mods/gameserver/data/manager/SevenSignsManager$SevenSignsPeriodChange."<init>":(Lext/mods/gameserver/data/manager/SevenSignsManager;)V
       135: lload_1
       136: invokestatic  #94                 // Method ext/mods/commons/pool/ThreadPool.schedule:(Ljava/lang/Runnable;J)Ljava/util/concurrent/ScheduledFuture;
       139: pop
       140: lload_1
       141: ldc2_w        #100                // long 1000l
       144: ldiv
       145: ldc2_w        #102                // long 60l
       148: lrem
       149: l2d
       150: dstore_3
       151: lload_1
       152: ldc2_w        #100                // long 1000l
       155: ldiv
       156: l2d
       157: dload_3
       158: dsub
       159: ldc2_w        #104                // double 60.0d
       162: ddiv
       163: dstore        5
       165: dload         5
       167: ldc2_w        #104                // double 60.0d
       170: drem
       171: invokestatic  #106                // Method java/lang/Math.floor:(D)D
       174: d2i
       175: istore        7
       177: dload         5
       179: iload         7
       181: i2d
       182: dsub
       183: ldc2_w        #104                // double 60.0d
       186: ddiv
       187: dstore        5
       189: dload         5
       191: ldc2_w        #112                // double 24.0d
       194: drem
       195: invokestatic  #106                // Method java/lang/Math.floor:(D)D
       198: d2i
       199: istore        8
       201: dload         5
       203: iload         8
       205: i2d
       206: dsub
       207: ldc2_w        #112                // double 24.0d
       210: ddiv
       211: invokestatic  #106                // Method java/lang/Math.floor:(D)D
       214: d2i
       215: istore        9
       217: getstatic     #48                 // Field LOGGER:Lext/mods/commons/logging/CLogger;
       220: ldc           #114                // String Next Seven Signs period begins in {} days, {} hours and {} mins.
       222: iconst_3
       223: anewarray     #6                  // class java/lang/Object
       226: dup
       227: iconst_0
       228: iload         9
       230: invokestatic  #116                // Method java/lang/Integer.valueOf:(I)Ljava/lang/Integer;
       233: aastore
       234: dup
       235: iconst_1
       236: iload         8
       238: invokestatic  #116                // Method java/lang/Integer.valueOf:(I)Ljava/lang/Integer;
       241: aastore
       242: dup
       243: iconst_2
       244: iload         7
       246: invokestatic  #116                // Method java/lang/Integer.valueOf:(I)Ljava/lang/Integer;
       249: aastore
       250: invokevirtual #64                 // Method ext/mods/commons/logging/CLogger.info:(Ljava/lang/Object;[Ljava/lang/Object;)V
       253: return
      LineNumberTable:
        line 94: 0
        line 79: 4
        line 80: 11
        line 88: 18
        line 89: 29
        line 90: 42
        line 91: 55
        line 95: 68
        line 97: 72
        line 98: 94
        line 100: 98
        line 101: 100
        line 102: 107
        line 105: 118
        line 106: 122
        line 109: 127
        line 111: 140
        line 112: 151
        line 113: 165
        line 114: 177
        line 115: 189
        line 116: 201
        line 118: 217
        line 119: 253
      LocalVariableTable:
        Start  Length  Slot  Name   Signature
            0     254     0  this   Lext/mods/gameserver/data/manager/SevenSignsManager;
          100     154     1 milliToChange   J
          151     103     3 numSecs   D
          165      89     5 countDown   D
          177      77     7 numMins   I
          201      53     8 numHours   I
          217      37     9 numDays   I
      StackMapTable: number_of_entries = 2
        frame_type = 255 /* full_frame */
          offset_delta = 118
          locals = [ class ext/mods/gameserver/data/manager/SevenSignsManager, long ]
          stack = []
        frame_type = 8 /* same */

  public static int calcScore(int, int, int);
    descriptor: (III)I
    flags: (0x0009) ACC_PUBLIC, ACC_STATIC
    Code:
      stack=3, locals=3, args_size=3
         0: iload_0
         1: iconst_3
         2: imul
         3: iload_1
         4: iconst_5
         5: imul
         6: iadd
         7: iload_2
         8: bipush        10
        10: imul
        11: iadd
        12: ireturn
      LineNumberTable:
        line 145: 0
      LocalVariableTable:
        Start  Length  Slot  Name   Signature
            0      13     0 blueCount   I
            0      13     1 greenCount   I
            0      13     2 redCount   I

  public final int getCurrentCycle();
    descriptor: ()I
    flags: (0x0011) ACC_PUBLIC, ACC_FINAL
    Code:
      stack=1, locals=1, args_size=1
         0: aload_0
         1: getfield      #154                // Field _currentCycle:I
         4: ireturn
      LineNumberTable:
        line 150: 0
      LocalVariableTable:
        Start  Length  Slot  Name   Signature
            0       5     0  this   Lext/mods/gameserver/data/manager/SevenSignsManager;

  public final ext.mods.gameserver.enums.PeriodType getCurrentPeriod();
    descriptor: ()Lext/mods/gameserver/enums/PeriodType;
    flags: (0x0011) ACC_PUBLIC, ACC_FINAL
    Code:
      stack=1, locals=1, args_size=1
         0: aload_0
         1: getfield      #54                 // Field _activePeriod:Lext/mods/gameserver/enums/PeriodType;
         4: areturn
      LineNumberTable:
        line 155: 0
      LocalVariableTable:
        Start  Length  Slot  Name   Signature
            0       5     0  this   Lext/mods/gameserver/data/manager/SevenSignsManager;

  public final long getMilliToPeriodChange();
    descriptor: ()J
    flags: (0x0011) ACC_PUBLIC, ACC_FINAL
    Code:
      stack=4, locals=1, args_size=1
         0: aload_0
         1: getfield      #15                 // Field _nextPeriodChange:Ljava/util/Calendar;
         4: invokevirtual #143                // Method java/util/Calendar.getTimeInMillis:()J
         7: invokestatic  #162                // Method java/lang/System.currentTimeMillis:()J
        10: lsub
        11: lreturn
      LineNumberTable:
        line 170: 0
      LocalVariableTable:
        Start  Length  Slot  Name   Signature
            0      12     0  this   Lext/mods/gameserver/data/manager/SevenSignsManager;

  protected void setCalendarForNextPeriodChange();
    descriptor: ()V
    flags: (0x0004) ACC_PROTECTED
    Code:
      stack=6, locals=2, args_size=1
         0: getstatic     #122                // Field ext/mods/gameserver/data/manager/SevenSignsManager$1.$SwitchMap$ext$mods$gameserver$enums$PeriodType:[I
         3: aload_0
         4: getfield      #54                 // Field _activePeriod:Lext/mods/gameserver/enums/PeriodType;
         7: invokevirtual #128                // Method ext/mods/gameserver/enums/PeriodType.ordinal:()I
        10: iaload
        11: tableswitch   { // 1 to 4

                       1: 40

                       2: 40

                       3: 150

                       4: 150
                 default: 161
            }
        40: aload_0
        41: invokevirtual #167                // Method getDaysToPeriodChange:()I
        44: istore_1
        45: iload_1
        46: bipush        7
        48: if_icmpne     93
        51: aload_0
        52: getfield      #15                 // Field _nextPeriodChange:Ljava/util/Calendar;
        55: bipush        11
        57: invokevirtual #158                // Method java/util/Calendar.get:(I)I
        60: bipush        18
        62: if_icmplt     91
        65: aload_0
        66: getfield      #15                 // Field _nextPeriodChange:Ljava/util/Calendar;
        69: bipush        11
        71: invokevirtual #158                // Method java/util/Calendar.get:(I)I
        74: bipush        18
        76: if_icmpne     93
        79: aload_0
        80: getfield      #15                 // Field _nextPeriodChange:Ljava/util/Calendar;
        83: bipush        12
        85: invokevirtual #158                // Method java/util/Calendar.get:(I)I
        88: ifge          93
        91: iconst_0
        92: istore_1
        93: iload_1
        94: ifle          106
        97: aload_0
        98: getfield      #15                 // Field _nextPeriodChange:Ljava/util/Calendar;
       101: iconst_5
       102: iload_1
       103: invokevirtual #140                // Method java/util/Calendar.add:(II)V
       106: aload_0
       107: getfield      #15                 // Field _nextPeriodChange:Ljava/util/Calendar;
       110: bipush        11
       112: bipush        18
       114: invokevirtual #132                // Method java/util/Calendar.set:(II)V
       117: aload_0
       118: getfield      #15                 // Field _nextPeriodChange:Ljava/util/Calendar;
       121: bipush        12
       123: iconst_0
       124: invokevirtual #132                // Method java/util/Calendar.set:(II)V
       127: aload_0
       128: getfield      #15                 // Field _nextPeriodChange:Ljava/util/Calendar;
       131: bipush        13
       133: iconst_0
       134: invokevirtual #132                // Method java/util/Calendar.set:(II)V
       137: aload_0
       138: getfield      #15                 // Field _nextPeriodChange:Ljava/util/Calendar;
       141: bipush        14
       143: iconst_0
       144: invokevirtual #132                // Method java/util/Calendar.set:(II)V
       147: goto          161
       150: aload_0
       151: getfield      #15                 // Field _nextPeriodChange:Ljava/util/Calendar;
       154: bipush        14
       156: ldc           #170                // int 900000
       158: invokevirtual #140                // Method java/util/Calendar.add:(II)V
       161: getstatic     #48                 // Field LOGGER:Lext/mods/commons/logging/CLogger;
       164: ldc           #171                // String Next Seven Signs period change set to {}.
       166: iconst_1
       167: anewarray     #6                  // class java/lang/Object
       170: dup
       171: iconst_0
       172: aload_0
       173: getfield      #15                 // Field _nextPeriodChange:Ljava/util/Calendar;
       176: invokevirtual #173                // Method java/util/Calendar.getTime:()Ljava/util/Date;
       179: aastore
       180: invokevirtual #64                 // Method ext/mods/commons/logging/CLogger.info:(Ljava/lang/Object;[Ljava/lang/Object;)V
       183: return
      LineNumberTable:
        line 179: 0
        line 182: 40
        line 184: 45
        line 185: 91
        line 187: 93
        line 188: 97
        line 190: 106
        line 191: 117
        line 192: 127
        line 193: 137
        line 194: 147
        line 197: 150
        line 200: 161
        line 201: 183
      LocalVariableTable:
        Start  Length  Slot  Name   Signature
           45     105     1 daysToChange   I
            0     184     0  this   Lext/mods/gameserver/data/manager/SevenSignsManager;
      StackMapTable: number_of_entries = 6
        frame_type = 40 /* same */
        frame_type = 252 /* append */
          offset_delta = 50
          locals = [ int ]
        frame_type = 1 /* same */
        frame_type = 12 /* same */
        frame_type = 250 /* chop */
          offset_delta = 43
        frame_type = 10 /* same */

  public final boolean isRecruitingPeriod();
    descriptor: ()Z
    flags: (0x0011) ACC_PUBLIC, ACC_FINAL
    Code:
      stack=2, locals=1, args_size=1
         0: aload_0
         1: getfield      #54                 // Field _activePeriod:Lext/mods/gameserver/enums/PeriodType;
         4: getstatic     #177                // Field ext/mods/gameserver/enums/PeriodType.RECRUITING:Lext/mods/gameserver/enums/PeriodType;
         7: if_acmpne     14
        10: iconst_1
        11: goto          15
        14: iconst_0
        15: ireturn
      LineNumberTable:
        line 205: 0
      LocalVariableTable:
        Start  Length  Slot  Name   Signature
            0      16     0  this   Lext/mods/gameserver/data/manager/SevenSignsManager;
      StackMapTable: number_of_entries = 2
        frame_type = 14 /* same */
        frame_type = 64 /* same_locals_1_stack_item */
          stack = [ int ]

  public final boolean isSealValidationPeriod();
    descriptor: ()Z
    flags: (0x0011) ACC_PUBLIC, ACC_FINAL
    Code:
      stack=2, locals=1, args_size=1
         0: aload_0
         1: getfield      #54                 // Field _activePeriod:Lext/mods/gameserver/enums/PeriodType;
         4: getstatic     #180                // Field ext/mods/gameserver/enums/PeriodType.SEAL_VALIDATION:Lext/mods/gameserver/enums/PeriodType;
         7: if_acmpne     14
        10: iconst_1
        11: goto          15
        14: iconst_0
        15: ireturn
      LineNumberTable:
        line 210: 0
      LocalVariableTable:
        Start  Length  Slot  Name   Signature
            0      16     0  this   Lext/mods/gameserver/data/manager/SevenSignsManager;
      StackMapTable: number_of_entries = 2
        frame_type = 14 /* same */
        frame_type = 64 /* same_locals_1_stack_item */
          stack = [ int ]

  public final boolean isCompResultsPeriod();
    descriptor: ()Z
    flags: (0x0011) ACC_PUBLIC, ACC_FINAL
    Code:
      stack=2, locals=1, args_size=1
         0: aload_0
         1: getfield      #54                 // Field _activePeriod:Lext/mods/gameserver/enums/PeriodType;
         4: getstatic     #183                // Field ext/mods/gameserver/enums/PeriodType.RESULTS:Lext/mods/gameserver/enums/PeriodType;
         7: if_acmpne     14
        10: iconst_1
        11: goto          15
        14: iconst_0
        15: ireturn
      LineNumberTable:
        line 215: 0
      LocalVariableTable:
        Start  Length  Slot  Name   Signature
            0      16     0  this   Lext/mods/gameserver/data/manager/SevenSignsManager;
      StackMapTable: number_of_entries = 2
        frame_type = 14 /* same */
        frame_type = 64 /* same_locals_1_stack_item */
          stack = [ int ]

  public final int getCurrentScore(ext.mods.gameserver.enums.CabalType);
    descriptor: (Lext/mods/gameserver/enums/CabalType;)I
    flags: (0x0011) ACC_PUBLIC, ACC_FINAL
    Code:
      stack=4, locals=4, args_size=2
         0: aload_0
         1: getfield      #186                // Field _dawnStoneScore:D
         4: aload_0
         5: getfield      #190                // Field _duskStoneScore:D
         8: dadd
         9: dstore_2
        10: getstatic     #193                // Field ext/mods/gameserver/data/manager/SevenSignsManager$1.$SwitchMap$ext$mods$gameserver$enums$CabalType:[I
        13: aload_1
        14: invokevirtual #196                // Method ext/mods/gameserver/enums/CabalType.ordinal:()I
        17: iaload
        18: lookupswitch  { // 2

                       1: 44

                       2: 75
                 default: 106
            }
        44: aload_0
        45: getfield      #186                // Field _dawnStoneScore:D
        48: dload_2
        49: d2f
        50: fconst_0
        51: fcmpl
        52: ifne          59
        55: dconst_1
        56: goto          60
        59: dload_2
        60: ddiv
        61: d2f
        62: ldc           #199                // float 500.0f
        64: fmul
        65: invokestatic  #200                // Method java/lang/Math.round:(F)I
        68: aload_0
        69: aload_1
        70: invokevirtual #204                // Method getCurrentFestivalScore:(Lext/mods/gameserver/enums/CabalType;)I
        73: iadd
        74: ireturn
        75: aload_0
        76: getfield      #190                // Field _duskStoneScore:D
        79: dload_2
        80: d2f
        81: fconst_0
        82: fcmpl
        83: ifne          90
        86: dconst_1
        87: goto          91
        90: dload_2
        91: ddiv
        92: d2f
        93: ldc           #199                // float 500.0f
        95: fmul
        96: invokestatic  #200                // Method java/lang/Math.round:(F)I
        99: aload_0
       100: aload_1
       101: invokevirtual #204                // Method getCurrentFestivalScore:(Lext/mods/gameserver/enums/CabalType;)I
       104: iadd
       105: ireturn
       106: iconst_0
       107: ireturn
      LineNumberTable:
        line 220: 0
        line 222: 10
        line 225: 44
        line 228: 75
        line 231: 106
      LocalVariableTable:
        Start  Length  Slot  Name   Signature
            0     108     0  this   Lext/mods/gameserver/data/manager/SevenSignsManager;
            0     108     1 cabal   Lext/mods/gameserver/enums/CabalType;
           10      98     2 totalStoneScore   D
      StackMapTable: number_of_entries = 7
        frame_type = 252 /* append */
          offset_delta = 44
          locals = [ double ]
        frame_type = 78 /* same_locals_1_stack_item */
          stack = [ double ]
        frame_type = 255 /* full_frame */
          offset_delta = 0
          locals = [ class ext/mods/gameserver/data/manager/SevenSignsManager, class ext/mods/gameserver/enums/CabalType, double ]
          stack = [ double, double ]
        frame_type = 14 /* same */
        frame_type = 78 /* same_locals_1_stack_item */
          stack = [ double ]
        frame_type = 255 /* full_frame */
          offset_delta = 0
          locals = [ class ext/mods/gameserver/data/manager/SevenSignsManager, class ext/mods/gameserver/enums/CabalType, double ]
          stack = [ double, double ]
        frame_type = 14 /* same */

  public final double getCurrentStoneScore(ext.mods.gameserver.enums.CabalType);
    descriptor: (Lext/mods/gameserver/enums/CabalType;)D
    flags: (0x0011) ACC_PUBLIC, ACC_FINAL
    Code:
      stack=2, locals=2, args_size=2
         0: getstatic     #193                // Field ext/mods/gameserver/data/manager/SevenSignsManager$1.$SwitchMap$ext$mods$gameserver$enums$CabalType:[I
         3: aload_1
         4: invokevirtual #196                // Method ext/mods/gameserver/enums/CabalType.ordinal:()I
         7: iaload
         8: lookupswitch  { // 2

                       1: 36

                       2: 41
                 default: 46
            }
        36: aload_0
        37: getfield      #186                // Field _dawnStoneScore:D
        40: dreturn
        41: aload_0
        42: getfield      #190                // Field _duskStoneScore:D
        45: dreturn
        46: dconst_0
        47: dreturn
      LineNumberTable:
        line 236: 0
        line 239: 36
        line 242: 41
        line 245: 46
      LocalVariableTable:
        Start  Length  Slot  Name   Signature
            0      48     0  this   Lext/mods/gameserver/data/manager/SevenSignsManager;
            0      48     1 cabal   Lext/mods/gameserver/enums/CabalType;
      StackMapTable: number_of_entries = 3
        frame_type = 36 /* same */
        frame_type = 4 /* same */
        frame_type = 4 /* same */

  public final int getCurrentFestivalScore(ext.mods.gameserver.enums.CabalType);
    descriptor: (Lext/mods/gameserver/enums/CabalType;)I
    flags: (0x0011) ACC_PUBLIC, ACC_FINAL
    Code:
      stack=2, locals=2, args_size=2
         0: invokestatic  #208                // Method ext/mods/gameserver/data/manager/FestivalOfDarknessManager.getInstance:()Lext/mods/gameserver/data/manager/FestivalOfDarknessManager;
         3: aload_1
         4: invokevirtual #213                // Method ext/mods/gameserver/data/manager/FestivalOfDarknessManager.getFestivalScore:(Lext/mods/gameserver/enums/CabalType;)I
         7: ireturn
      LineNumberTable:
        line 250: 0
      LocalVariableTable:
        Start  Length  Slot  Name   Signature
            0       8     0  this   Lext/mods/gameserver/data/manager/SevenSignsManager;
            0       8     1 cabal   Lext/mods/gameserver/enums/CabalType;

  public final ext.mods.gameserver.enums.CabalType getWinningCabal();
    descriptor: ()Lext/mods/gameserver/enums/CabalType;
    flags: (0x0011) ACC_PUBLIC, ACC_FINAL
    Code:
      stack=2, locals=3, args_size=1
         0: aload_0
         1: getstatic     #216                // Field ext/mods/gameserver/enums/CabalType.DUSK:Lext/mods/gameserver/enums/CabalType;
         4: invokevirtual #220                // Method getCurrentScore:(Lext/mods/gameserver/enums/CabalType;)I
         7: istore_1
         8: aload_0
         9: getstatic     #223                // Field ext/mods/gameserver/enums/CabalType.DAWN:Lext/mods/gameserver/enums/CabalType;
        12: invokevirtual #220                // Method getCurrentScore:(Lext/mods/gameserver/enums/CabalType;)I
        15: istore_2
        16: iload_1
        17: iload_2
        18: if_icmpne     25
        21: getstatic     #226                // Field ext/mods/gameserver/enums/CabalType.NORMAL:Lext/mods/gameserver/enums/CabalType;
        24: areturn
        25: iload_1
        26: iload_2
        27: if_icmple     34
        30: getstatic     #216                // Field ext/mods/gameserver/enums/CabalType.DUSK:Lext/mods/gameserver/enums/CabalType;
        33: areturn
        34: getstatic     #223                // Field ext/mods/gameserver/enums/CabalType.DAWN:Lext/mods/gameserver/enums/CabalType;
        37: areturn
      LineNumberTable:
        line 255: 0
        line 256: 8
        line 258: 16
        line 259: 21
        line 261: 25
        line 262: 30
        line 264: 34
      LocalVariableTable:
        Start  Length  Slot  Name   Signature
            0      38     0  this   Lext/mods/gameserver/data/manager/SevenSignsManager;
            8      30     1 duskScore   I
           16      22     2 dawnScore   I
      StackMapTable: number_of_entries = 2
        frame_type = 253 /* append */
          offset_delta = 25
          locals = [ int, int ]
        frame_type = 8 /* same */

  public final ext.mods.gameserver.enums.CabalType getLosingCabal();
    descriptor: ()Lext/mods/gameserver/enums/CabalType;
    flags: (0x0011) ACC_PUBLIC, ACC_FINAL
    Code:
      stack=2, locals=3, args_size=1
         0: aload_0
         1: getstatic     #216                // Field ext/mods/gameserver/enums/CabalType.DUSK:Lext/mods/gameserver/enums/CabalType;
         4: invokevirtual #220                // Method getCurrentScore:(Lext/mods/gameserver/enums/CabalType;)I
         7: istore_1
         8: aload_0
         9: getstatic     #223                // Field ext/mods/gameserver/enums/CabalType.DAWN:Lext/mods/gameserver/enums/CabalType;
        12: invokevirtual #220                // Method getCurrentScore:(Lext/mods/gameserver/enums/CabalType;)I
        15: istore_2
        16: iload_1
        17: iload_2
        18: if_icmpne     25
        21: getstatic     #226                // Field ext/mods/gameserver/enums/CabalType.NORMAL:Lext/mods/gameserver/enums/CabalType;
        24: areturn
        25: iload_1
        26: iload_2
        27: if_icmple     34
        30: getstatic     #223                // Field ext/mods/gameserver/enums/CabalType.DAWN:Lext/mods/gameserver/enums/CabalType;
        33: areturn
        34: getstatic     #216                // Field ext/mods/gameserver/enums/CabalType.DUSK:Lext/mods/gameserver/enums/CabalType;
        37: areturn
      LineNumberTable:
        line 269: 0
        line 270: 8
        line 272: 16
        line 273: 21
        line 275: 25
        line 276: 30
        line 278: 34
      LocalVariableTable:
        Start  Length  Slot  Name   Signature
            0      38     0  this   Lext/mods/gameserver/data/manager/SevenSignsManager;
            8      30     1 duskScore   I
           16      22     2 dawnScore   I
      StackMapTable: number_of_entries = 2
        frame_type = 253 /* append */
          offset_delta = 25
          locals = [ int, int ]
        frame_type = 8 /* same */

  public final ext.mods.gameserver.enums.CabalType getSealOwner(ext.mods.gameserver.enums.SealType);
    descriptor: (Lext/mods/gameserver/enums/SealType;)Lext/mods/gameserver/enums/CabalType;
    flags: (0x0011) ACC_PUBLIC, ACC_FINAL
    Code:
      stack=2, locals=2, args_size=2
         0: aload_0
         1: getfield      #36                 // Field _sealOwners:Ljava/util/Map;
         4: aload_1
         5: invokeinterface #229,  2          // InterfaceMethod java/util/Map.get:(Ljava/lang/Object;)Ljava/lang/Object;
        10: checkcast     #197                // class ext/mods/gameserver/enums/CabalType
        13: areturn
      LineNumberTable:
        line 283: 0
      LocalVariableTable:
        Start  Length  Slot  Name   Signature
            0      14     0  this   Lext/mods/gameserver/data/manager/SevenSignsManager;
            0      14     1  seal   Lext/mods/gameserver/enums/SealType;

  public final java.util.Map<ext.mods.gameserver.enums.SealType, ext.mods.gameserver.enums.CabalType> getSealOwners();
    descriptor: ()Ljava/util/Map;
    flags: (0x0011) ACC_PUBLIC, ACC_FINAL
    Code:
      stack=1, locals=1, args_size=1
         0: aload_0
         1: getfield      #36                 // Field _sealOwners:Ljava/util/Map;
         4: areturn
      LineNumberTable:
        line 288: 0
      LocalVariableTable:
        Start  Length  Slot  Name   Signature
            0       5     0  this   Lext/mods/gameserver/data/manager/SevenSignsManager;
    Signature: #715                         // ()Ljava/util/Map<Lext/mods/gameserver/enums/SealType;Lext/mods/gameserver/enums/CabalType;>;

  public final int getSealProportion(ext.mods.gameserver.enums.SealType, ext.mods.gameserver.enums.CabalType);
    descriptor: (Lext/mods/gameserver/enums/SealType;Lext/mods/gameserver/enums/CabalType;)I
    flags: (0x0011) ACC_PUBLIC, ACC_FINAL
    Code:
      stack=2, locals=3, args_size=3
         0: getstatic     #193                // Field ext/mods/gameserver/data/manager/SevenSignsManager$1.$SwitchMap$ext$mods$gameserver$enums$CabalType:[I
         3: aload_2
         4: invokevirtual #196                // Method ext/mods/gameserver/enums/CabalType.ordinal:()I
         7: iaload
         8: lookupswitch  { // 2

                       1: 36

                       2: 53
                 default: 70
            }
        36: aload_0
        37: getfield      #42                 // Field _dawnScores:Ljava/util/Map;
        40: aload_1
        41: invokeinterface #229,  2          // InterfaceMethod java/util/Map.get:(Ljava/lang/Object;)Ljava/lang/Object;
        46: checkcast     #117                // class java/lang/Integer
        49: invokevirtual #234                // Method java/lang/Integer.intValue:()I
        52: ireturn
        53: aload_0
        54: getfield      #39                 // Field _duskScores:Ljava/util/Map;
        57: aload_1
        58: invokeinterface #229,  2          // InterfaceMethod java/util/Map.get:(Ljava/lang/Object;)Ljava/lang/Object;
        63: checkcast     #117                // class java/lang/Integer
        66: invokevirtual #234                // Method java/lang/Integer.intValue:()I
        69: ireturn
        70: iconst_0
        71: ireturn
      LineNumberTable:
        line 293: 0
        line 296: 36
        line 299: 53
        line 302: 70
      LocalVariableTable:
        Start  Length  Slot  Name   Signature
            0      72     0  this   Lext/mods/gameserver/data/manager/SevenSignsManager;
            0      72     1  seal   Lext/mods/gameserver/enums/SealType;
            0      72     2 cabal   Lext/mods/gameserver/enums/CabalType;
      StackMapTable: number_of_entries = 3
        frame_type = 36 /* same */
        frame_type = 16 /* same */
        frame_type = 16 /* same */

  public final int getTotalMembers(ext.mods.gameserver.enums.CabalType);
    descriptor: (Lext/mods/gameserver/enums/CabalType;)I
    flags: (0x0011) ACC_PUBLIC, ACC_FINAL
    Code:
      stack=3, locals=5, args_size=2
         0: iconst_0
         1: istore_2
         2: aload_0
         3: getfield      #25                 // Field _playersData:Ljava/util/Map;
         6: invokeinterface #237,  1          // InterfaceMethod java/util/Map.values:()Ljava/util/Collection;
        11: invokeinterface #241,  1          // InterfaceMethod java/util/Collection.iterator:()Ljava/util/Iterator;
        16: astore_3
        17: aload_3
        18: invokeinterface #247,  1          // InterfaceMethod java/util/Iterator.hasNext:()Z
        23: ifeq          57
        26: aload_3
        27: invokeinterface #252,  1          // InterfaceMethod java/util/Iterator.next:()Ljava/lang/Object;
        32: checkcast     #256                // class ext/mods/commons/data/StatSet
        35: astore        4
        37: aload         4
        39: ldc_w         #258                // String cabal
        42: ldc           #197                // class ext/mods/gameserver/enums/CabalType
        44: invokevirtual #260                // Method ext/mods/commons/data/StatSet.getEnum:(Ljava/lang/String;Ljava/lang/Class;)Ljava/lang/Enum;
        47: aload_1
        48: if_acmpne     54
        51: iinc          2, 1
        54: goto          17
        57: iload_2
        58: ireturn
      LineNumberTable:
        line 307: 0
        line 309: 2
        line 310: 37
        line 311: 51
        line 310: 54
        line 313: 57
      LocalVariableTable:
        Start  Length  Slot  Name   Signature
           37      17     4   set   Lext/mods/commons/data/StatSet;
            0      59     0  this   Lext/mods/gameserver/data/manager/SevenSignsManager;
            0      59     1 cabal   Lext/mods/gameserver/enums/CabalType;
            2      57     2 cabalMembers   I
      StackMapTable: number_of_entries = 3
        frame_type = 253 /* append */
          offset_delta = 17
          locals = [ int, class java/util/Iterator ]
        frame_type = 36 /* same */
        frame_type = 250 /* chop */
          offset_delta = 2

  public int getPlayerStoneContrib(int);
    descriptor: (I)I
    flags: (0x0001) ACC_PUBLIC
    Code:
      stack=3, locals=3, args_size=2
         0: aload_0
         1: getfield      #25                 // Field _playersData:Ljava/util/Map;
         4: iload_1
         5: invokestatic  #116                // Method java/lang/Integer.valueOf:(I)Ljava/lang/Integer;
         8: invokeinterface #229,  2          // InterfaceMethod java/util/Map.get:(Ljava/lang/Object;)Ljava/lang/Object;
        13: checkcast     #256                // class ext/mods/commons/data/StatSet
        16: astore_2
        17: aload_2
        18: ifnonnull     23
        21: iconst_0
        22: ireturn
        23: aload_2
        24: ldc_w         #264                // String red_stones
        27: invokevirtual #266                // Method ext/mods/commons/data/StatSet.getInteger:(Ljava/lang/String;)I
        30: aload_2
        31: ldc_w         #270                // String green_stones
        34: invokevirtual #266                // Method ext/mods/commons/data/StatSet.getInteger:(Ljava/lang/String;)I
        37: iadd
        38: aload_2
        39: ldc_w         #272                // String blue_stones
        42: invokevirtual #266                // Method ext/mods/commons/data/StatSet.getInteger:(Ljava/lang/String;)I
        45: iadd
        46: ireturn
      LineNumberTable:
        line 318: 0
        line 319: 17
        line 320: 21
        line 322: 23
      LocalVariableTable:
        Start  Length  Slot  Name   Signature
            0      47     0  this   Lext/mods/gameserver/data/manager/SevenSignsManager;
            0      47     1 objectId   I
           17      30     2   set   Lext/mods/commons/data/StatSet;
      StackMapTable: number_of_entries = 1
        frame_type = 252 /* append */
          offset_delta = 23
          locals = [ class ext/mods/commons/data/StatSet ]

  public int getPlayerContribScore(int);
    descriptor: (I)I
    flags: (0x0001) ACC_PUBLIC
    Code:
      stack=2, locals=3, args_size=2
         0: aload_0
         1: getfield      #25                 // Field _playersData:Ljava/util/Map;
         4: iload_1
         5: invokestatic  #116                // Method java/lang/Integer.valueOf:(I)Ljava/lang/Integer;
         8: invokeinterface #229,  2          // InterfaceMethod java/util/Map.get:(Ljava/lang/Object;)Ljava/lang/Object;
        13: checkcast     #256                // class ext/mods/commons/data/StatSet
        16: astore_2
        17: aload_2
        18: ifnonnull     23
        21: iconst_0
        22: ireturn
        23: aload_2
        24: ldc_w         #274                // String contribution_score
        27: invokevirtual #266                // Method ext/mods/commons/data/StatSet.getInteger:(Ljava/lang/String;)I
        30: ireturn
      LineNumberTable:
        line 327: 0
        line 328: 17
        line 329: 21
        line 331: 23
      LocalVariableTable:
        Start  Length  Slot  Name   Signature
            0      31     0  this   Lext/mods/gameserver/data/manager/SevenSignsManager;
            0      31     1 objectId   I
           17      14     2   set   Lext/mods/commons/data/StatSet;
      StackMapTable: number_of_entries = 1
        frame_type = 252 /* append */
          offset_delta = 23
          locals = [ class ext/mods/commons/data/StatSet ]

  public int getPlayerAdenaCollect(int);
    descriptor: (I)I
    flags: (0x0001) ACC_PUBLIC
    Code:
      stack=2, locals=3, args_size=2
         0: aload_0
         1: getfield      #25                 // Field _playersData:Ljava/util/Map;
         4: iload_1
         5: invokestatic  #116                // Method java/lang/Integer.valueOf:(I)Ljava/lang/Integer;
         8: invokeinterface #229,  2          // InterfaceMethod java/util/Map.get:(Ljava/lang/Object;)Ljava/lang/Object;
        13: checkcast     #256                // class ext/mods/commons/data/StatSet
        16: astore_2
        17: aload_2
        18: ifnonnull     23
        21: iconst_0
        22: ireturn
        23: aload_2
        24: ldc_w         #276                // String ancient_adena_amount
        27: invokevirtual #266                // Method ext/mods/commons/data/StatSet.getInteger:(Ljava/lang/String;)I
        30: ireturn
      LineNumberTable:
        line 336: 0
        line 337: 17
        line 338: 21
        line 340: 23
      LocalVariableTable:
        Start  Length  Slot  Name   Signature
            0      31     0  this   Lext/mods/gameserver/data/manager/SevenSignsManager;
            0      31     1 objectId   I
           17      14     2   set   Lext/mods/commons/data/StatSet;
      StackMapTable: number_of_entries = 1
        frame_type = 252 /* append */
          offset_delta = 23
          locals = [ class ext/mods/commons/data/StatSet ]

  public ext.mods.gameserver.enums.SealType getPlayerSeal(int);
    descriptor: (I)Lext/mods/gameserver/enums/SealType;
    flags: (0x0001) ACC_PUBLIC
    Code:
      stack=3, locals=3, args_size=2
         0: aload_0
         1: getfield      #25                 // Field _playersData:Ljava/util/Map;
         4: iload_1
         5: invokestatic  #116                // Method java/lang/Integer.valueOf:(I)Ljava/lang/Integer;
         8: invokeinterface #229,  2          // InterfaceMethod java/util/Map.get:(Ljava/lang/Object;)Ljava/lang/Object;
        13: checkcast     #256                // class ext/mods/commons/data/StatSet
        16: astore_2
        17: aload_2
        18: ifnonnull     25
        21: getstatic     #278                // Field ext/mods/gameserver/enums/SealType.NONE:Lext/mods/gameserver/enums/SealType;
        24: areturn
        25: aload_2
        26: ldc_w         #282                // String seal
        29: ldc           #31                 // class ext/mods/gameserver/enums/SealType
        31: invokevirtual #260                // Method ext/mods/commons/data/StatSet.getEnum:(Ljava/lang/String;Ljava/lang/Class;)Ljava/lang/Enum;
        34: checkcast     #31                 // class ext/mods/gameserver/enums/SealType
        37: areturn
      LineNumberTable:
        line 345: 0
        line 346: 17
        line 347: 21
        line 349: 25
      LocalVariableTable:
        Start  Length  Slot  Name   Signature
            0      38     0  this   Lext/mods/gameserver/data/manager/SevenSignsManager;
            0      38     1 objectId   I
           17      21     2   set   Lext/mods/commons/data/StatSet;
      StackMapTable: number_of_entries = 1
        frame_type = 252 /* append */
          offset_delta = 25
          locals = [ class ext/mods/commons/data/StatSet ]

  public ext.mods.gameserver.enums.CabalType getPlayerCabal(int);
    descriptor: (I)Lext/mods/gameserver/enums/CabalType;
    flags: (0x0001) ACC_PUBLIC
    Code:
      stack=3, locals=3, args_size=2
         0: aload_0
         1: getfield      #25                 // Field _playersData:Ljava/util/Map;
         4: iload_1
         5: invokestatic  #116                // Method java/lang/Integer.valueOf:(I)Ljava/lang/Integer;
         8: invokeinterface #229,  2          // InterfaceMethod java/util/Map.get:(Ljava/lang/Object;)Ljava/lang/Object;
        13: checkcast     #256                // class ext/mods/commons/data/StatSet
        16: astore_2
        17: aload_2
        18: ifnonnull     25
        21: getstatic     #226                // Field ext/mods/gameserver/enums/CabalType.NORMAL:Lext/mods/gameserver/enums/CabalType;
        24: areturn
        25: aload_2
        26: ldc_w         #258                // String cabal
        29: ldc           #197                // class ext/mods/gameserver/enums/CabalType
        31: invokevirtual #260                // Method ext/mods/commons/data/StatSet.getEnum:(Ljava/lang/String;Ljava/lang/Class;)Ljava/lang/Enum;
        34: checkcast     #197                // class ext/mods/gameserver/enums/CabalType
        37: areturn
      LineNumberTable:
        line 354: 0
        line 355: 17
        line 356: 21
        line 358: 25
      LocalVariableTable:
        Start  Length  Slot  Name   Signature
            0      38     0  this   Lext/mods/gameserver/data/manager/SevenSignsManager;
            0      38     1 objectId   I
           17      21     2   set   Lext/mods/commons/data/StatSet;
      StackMapTable: number_of_entries = 1
        frame_type = 252 /* append */
          offset_delta = 25
          locals = [ class ext/mods/commons/data/StatSet ]

  protected void restoreSevenSignsData();
    descriptor: ()V
    flags: (0x0004) ACC_PROTECTED
    Code:
      stack=5, locals=6, args_size=1
         0: invokestatic  #284                // Method ext/mods/commons/pool/ConnectionPool.getConnection:()Ljava/sql/Connection;
         3: astore_1
         4: aload_1
         5: ldc_w         #290                // String SELECT char_obj_id, cabal, seal, red_stones, green_stones, blue_stones, ancient_adena_amount, contribution_score FROM seven_signs
         8: invokeinterface #292,  2          // InterfaceMethod java/sql/Connection.prepareStatement:(Ljava/lang/String;)Ljava/sql/PreparedStatement;
        13: astore_2
        14: aload_2
        15: invokeinterface #298,  1          // InterfaceMethod java/sql/PreparedStatement.executeQuery:()Ljava/sql/ResultSet;
        20: astore_3
        21: aload_3
        22: invokeinterface #304,  1          // InterfaceMethod java/sql/ResultSet.next:()Z
        27: ifeq          209
        30: aload_3
        31: ldc_w         #308                // String char_obj_id
        34: invokeinterface #310,  2          // InterfaceMethod java/sql/ResultSet.getInt:(Ljava/lang/String;)I
        39: istore        4
        41: new           #256                // class ext/mods/commons/data/StatSet
        44: dup
        45: invokespecial #313                // Method ext/mods/commons/data/StatSet."<init>":()V
        48: astore        5
        50: aload         5
        52: ldc_w         #308                // String char_obj_id
        55: iload         4
        57: invokevirtual #314                // Method ext/mods/commons/data/StatSet.set:(Ljava/lang/String;I)V
        60: aload         5
        62: ldc_w         #258                // String cabal
        65: ldc           #197                // class ext/mods/gameserver/enums/CabalType
        67: aload_3
        68: ldc_w         #258                // String cabal
        71: invokeinterface #317,  2          // InterfaceMethod java/sql/ResultSet.getString:(Ljava/lang/String;)Ljava/lang/String;
        76: invokestatic  #321                // Method java/lang/Enum.valueOf:(Ljava/lang/Class;Ljava/lang/String;)Ljava/lang/Enum;
        79: invokevirtual #326                // Method ext/mods/commons/data/StatSet.set:(Ljava/lang/String;Ljava/lang/Enum;)V
        82: aload         5
        84: ldc_w         #282                // String seal
        87: ldc           #31                 // class ext/mods/gameserver/enums/SealType
        89: aload_3
        90: ldc_w         #282                // String seal
        93: invokeinterface #317,  2          // InterfaceMethod java/sql/ResultSet.getString:(Ljava/lang/String;)Ljava/lang/String;
        98: invokestatic  #321                // Method java/lang/Enum.valueOf:(Ljava/lang/Class;Ljava/lang/String;)Ljava/lang/Enum;
       101: invokevirtual #326                // Method ext/mods/commons/data/StatSet.set:(Ljava/lang/String;Ljava/lang/Enum;)V
       104: aload         5
       106: ldc_w         #264                // String red_stones
       109: aload_3
       110: ldc_w         #264                // String red_stones
       113: invokeinterface #310,  2          // InterfaceMethod java/sql/ResultSet.getInt:(Ljava/lang/String;)I
       118: invokevirtual #314                // Method ext/mods/commons/data/StatSet.set:(Ljava/lang/String;I)V
       121: aload         5
       123: ldc_w         #270                // String green_stones
       126: aload_3
       127: ldc_w         #270                // String green_stones
       130: invokeinterface #310,  2          // InterfaceMethod java/sql/ResultSet.getInt:(Ljava/lang/String;)I
       135: invokevirtual #314                // Method ext/mods/commons/data/StatSet.set:(Ljava/lang/String;I)V
       138: aload         5
       140: ldc_w         #272                // String blue_stones
       143: aload_3
       144: ldc_w         #272                // String blue_stones
       147: invokeinterface #310,  2          // InterfaceMethod java/sql/ResultSet.getInt:(Ljava/lang/String;)I
       152: invokevirtual #314                // Method ext/mods/commons/data/StatSet.set:(Ljava/lang/String;I)V
       155: aload         5
       157: ldc_w         #276                // String ancient_adena_amount
       160: aload_3
       161: ldc_w         #276                // String ancient_adena_amount
       164: invokeinterface #329,  2          // InterfaceMethod java/sql/ResultSet.getDouble:(Ljava/lang/String;)D
       169: invokevirtual #333                // Method ext/mods/commons/data/StatSet.set:(Ljava/lang/String;D)V
       172: aload         5
       174: ldc_w         #274                // String contribution_score
       177: aload_3
       178: ldc_w         #274                // String contribution_score
       181: invokeinterface #329,  2          // InterfaceMethod java/sql/ResultSet.getDouble:(Ljava/lang/String;)D
       186: invokevirtual #333                // Method ext/mods/commons/data/StatSet.set:(Ljava/lang/String;D)V
       189: aload_0
       190: getfield      #25                 // Field _playersData:Ljava/util/Map;
       193: iload         4
       195: invokestatic  #116                // Method java/lang/Integer.valueOf:(I)Ljava/lang/Integer;
       198: aload         5
       200: invokeinterface #336,  3          // InterfaceMethod java/util/Map.put:(Ljava/lang/Object;Ljava/lang/Object;)Ljava/lang/Object;
       205: pop
       206: goto          21
       209: aload_3
       210: ifnull        249
       213: aload_3
       214: invokeinterface #340,  1          // InterfaceMethod java/sql/ResultSet.close:()V
       219: goto          249
       222: astore        4
       224: aload_3
       225: ifnull        246
       228: aload_3
       229: invokeinterface #340,  1          // InterfaceMethod java/sql/ResultSet.close:()V
       234: goto          246
       237: astore        5
       239: aload         4
       241: aload         5
       243: invokevirtual #345                // Method java/lang/Throwable.addSuppressed:(Ljava/lang/Throwable;)V
       246: aload         4
       248: athrow
       249: aload_2
       250: ifnull        286
       253: aload_2
       254: invokeinterface #349,  1          // InterfaceMethod java/sql/PreparedStatement.close:()V
       259: goto          286
       262: astore_3
       263: aload_2
       264: ifnull        284
       267: aload_2
       268: invokeinterface #349,  1          // InterfaceMethod java/sql/PreparedStatement.close:()V
       273: goto          284
       276: astore        4
       278: aload_3
       279: aload         4
       281: invokevirtual #345                // Method java/lang/Throwable.addSuppressed:(Ljava/lang/Throwable;)V
       284: aload_3
       285: athrow
       286: aload_1
       287: ldc_w         #350                // String SELECT * FROM seven_signs_status WHERE id=0
       290: invokeinterface #292,  2          // InterfaceMethod java/sql/Connection.prepareStatement:(Ljava/lang/String;)Ljava/sql/PreparedStatement;
       295: astore_2
       296: aload_2
       297: invokeinterface #298,  1          // InterfaceMethod java/sql/PreparedStatement.executeQuery:()Ljava/sql/ResultSet;
       302: astore_3
       303: aload_3
       304: invokeinterface #304,  1          // InterfaceMethod java/sql/ResultSet.next:()Z
       309: ifeq          652
       312: aload_0
       313: aload_3
       314: ldc_w         #352                // String current_cycle
       317: invokeinterface #310,  2          // InterfaceMethod java/sql/ResultSet.getInt:(Ljava/lang/String;)I
       322: putfield      #154                // Field _currentCycle:I
       325: aload_0
       326: ldc           #59                 // class ext/mods/gameserver/enums/PeriodType
       328: aload_3
       329: ldc_w         #354                // String active_period
       332: invokeinterface #317,  2          // InterfaceMethod java/sql/ResultSet.getString:(Ljava/lang/String;)Ljava/lang/String;
       337: invokestatic  #321                // Method java/lang/Enum.valueOf:(Ljava/lang/Class;Ljava/lang/String;)Ljava/lang/Enum;
       340: checkcast     #59                 // class ext/mods/gameserver/enums/PeriodType
       343: putfield      #54                 // Field _activePeriod:Lext/mods/gameserver/enums/PeriodType;
       346: aload_0
       347: ldc           #197                // class ext/mods/gameserver/enums/CabalType
       349: aload_3
       350: ldc_w         #356                // String previous_winner
       353: invokeinterface #317,  2          // InterfaceMethod java/sql/ResultSet.getString:(Ljava/lang/String;)Ljava/lang/String;
       358: invokestatic  #321                // Method java/lang/Enum.valueOf:(Ljava/lang/Class;Ljava/lang/String;)Ljava/lang/Enum;
       361: checkcast     #197                // class ext/mods/gameserver/enums/CabalType
       364: putfield      #358                // Field _previousWinner:Lext/mods/gameserver/enums/CabalType;
       367: aload_0
       368: aload_3
       369: ldc_w         #361                // String dawn_stone_score
       372: invokeinterface #329,  2          // InterfaceMethod java/sql/ResultSet.getDouble:(Ljava/lang/String;)D
       377: putfield      #186                // Field _dawnStoneScore:D
       380: aload_0
       381: aload_3
       382: ldc_w         #363                // String dusk_stone_score
       385: invokeinterface #329,  2          // InterfaceMethod java/sql/ResultSet.getDouble:(Ljava/lang/String;)D
       390: putfield      #190                // Field _duskStoneScore:D
       393: aload_0
       394: getfield      #36                 // Field _sealOwners:Ljava/util/Map;
       397: getstatic     #365                // Field ext/mods/gameserver/enums/SealType.AVARICE:Lext/mods/gameserver/enums/SealType;
       400: ldc           #197                // class ext/mods/gameserver/enums/CabalType
       402: aload_3
       403: ldc_w         #368                // String avarice_owner
       406: invokeinterface #317,  2          // InterfaceMethod java/sql/ResultSet.getString:(Ljava/lang/String;)Ljava/lang/String;
       411: invokestatic  #321                // Method java/lang/Enum.valueOf:(Ljava/lang/Class;Ljava/lang/String;)Ljava/lang/Enum;
       414: checkcast     #197                // class ext/mods/gameserver/enums/CabalType
       417: invokeinterface #336,  3          // InterfaceMethod java/util/Map.put:(Ljava/lang/Object;Ljava/lang/Object;)Ljava/lang/Object;
       422: pop
       423: aload_0
       424: getfield      #36                 // Field _sealOwners:Ljava/util/Map;
       427: getstatic     #370                // Field ext/mods/gameserver/enums/SealType.GNOSIS:Lext/mods/gameserver/enums/SealType;
       430: ldc           #197                // class ext/mods/gameserver/enums/CabalType
       432: aload_3
       433: ldc_w         #373                // String gnosis_owner
       436: invokeinterface #317,  2          // InterfaceMethod java/sql/ResultSet.getString:(Ljava/lang/String;)Ljava/lang/String;
       441: invokestatic  #321                // Method java/lang/Enum.valueOf:(Ljava/lang/Class;Ljava/lang/String;)Ljava/lang/Enum;
       444: checkcast     #197                // class ext/mods/gameserver/enums/CabalType
       447: invokeinterface #336,  3          // InterfaceMethod java/util/Map.put:(Ljava/lang/Object;Ljava/lang/Object;)Ljava/lang/Object;
       452: pop
       453: aload_0
       454: getfield      #36                 // Field _sealOwners:Ljava/util/Map;
       457: getstatic     #375                // Field ext/mods/gameserver/enums/SealType.STRIFE:Lext/mods/gameserver/enums/SealType;
       460: ldc           #197                // class ext/mods/gameserver/enums/CabalType
       462: aload_3
       463: ldc_w         #378                // String strife_owner
       466: invokeinterface #317,  2          // InterfaceMethod java/sql/ResultSet.getString:(Ljava/lang/String;)Ljava/lang/String;
       471: invokestatic  #321                // Method java/lang/Enum.valueOf:(Ljava/lang/Class;Ljava/lang/String;)Ljava/lang/Enum;
       474: checkcast     #197                // class ext/mods/gameserver/enums/CabalType
       477: invokeinterface #336,  3          // InterfaceMethod java/util/Map.put:(Ljava/lang/Object;Ljava/lang/Object;)Ljava/lang/Object;
       482: pop
       483: aload_0
       484: getfield      #42                 // Field _dawnScores:Ljava/util/Map;
       487: getstatic     #365                // Field ext/mods/gameserver/enums/SealType.AVARICE:Lext/mods/gameserver/enums/SealType;
       490: aload_3
       491: ldc_w         #380                // String avarice_dawn_score
       494: invokeinterface #310,  2          // InterfaceMethod java/sql/ResultSet.getInt:(Ljava/lang/String;)I
       499: invokestatic  #116                // Method java/lang/Integer.valueOf:(I)Ljava/lang/Integer;
       502: invokeinterface #336,  3          // InterfaceMethod java/util/Map.put:(Ljava/lang/Object;Ljava/lang/Object;)Ljava/lang/Object;
       507: pop
       508: aload_0
       509: getfield      #42                 // Field _dawnScores:Ljava/util/Map;
       512: getstatic     #370                // Field ext/mods/gameserver/enums/SealType.GNOSIS:Lext/mods/gameserver/enums/SealType;
       515: aload_3
       516: ldc_w         #382                // String gnosis_dawn_score
       519: invokeinterface #310,  2          // InterfaceMethod java/sql/ResultSet.getInt:(Ljava/lang/String;)I
       524: invokestatic  #116                // Method java/lang/Integer.valueOf:(I)Ljava/lang/Integer;
       527: invokeinterface #336,  3          // InterfaceMethod java/util/Map.put:(Ljava/lang/Object;Ljava/lang/Object;)Ljava/lang/Object;
       532: pop
       533: aload_0
       534: getfield      #42                 // Field _dawnScores:Ljava/util/Map;
       537: getstatic     #375                // Field ext/mods/gameserver/enums/SealType.STRIFE:Lext/mods/gameserver/enums/SealType;
       540: aload_3
       541: ldc_w         #384                // String strife_dawn_score
       544: invokeinterface #310,  2          // InterfaceMethod java/sql/ResultSet.getInt:(Ljava/lang/String;)I
       549: invokestatic  #116                // Method java/lang/Integer.valueOf:(I)Ljava/lang/Integer;
       552: invokeinterface #336,  3          // InterfaceMethod java/util/Map.put:(Ljava/lang/Object;Ljava/lang/Object;)Ljava/lang/Object;
       557: pop
       558: aload_0
       559: getfield      #39                 // Field _duskScores:Ljava/util/Map;
       562: getstatic     #365                // Field ext/mods/gameserver/enums/SealType.AVARICE:Lext/mods/gameserver/enums/SealType;
       565: aload_3
       566: ldc_w         #386                // String avarice_dusk_score
       569: invokeinterface #310,  2          // InterfaceMethod java/sql/ResultSet.getInt:(Ljava/lang/String;)I
       574: invokestatic  #116                // Method java/lang/Integer.valueOf:(I)Ljava/lang/Integer;
       577: invokeinterface #336,  3          // InterfaceMethod java/util/Map.put:(Ljava/lang/Object;Ljava/lang/Object;)Ljava/lang/Object;
       582: pop
       583: aload_0
       584: getfield      #39                 // Field _duskScores:Ljava/util/Map;
       587: getstatic     #370                // Field ext/mods/gameserver/enums/SealType.GNOSIS:Lext/mods/gameserver/enums/SealType;
       590: aload_3
       591: ldc_w         #388                // String gnosis_dusk_score
       594: invokeinterface #310,  2          // InterfaceMethod java/sql/ResultSet.getInt:(Ljava/lang/String;)I
       599: invokestatic  #116                // Method java/lang/Integer.valueOf:(I)Ljava/lang/Integer;
       602: invokeinterface #336,  3          // InterfaceMethod java/util/Map.put:(Ljava/lang/Object;Ljava/lang/Object;)Ljava/lang/Object;
       607: pop
       608: aload_0
       609: getfield      #39                 // Field _duskScores:Ljava/util/Map;
       612: getstatic     #375                // Field ext/mods/gameserver/enums/SealType.STRIFE:Lext/mods/gameserver/enums/SealType;
       615: aload_3
       616: ldc_w         #390                // String strife_dusk_score
       619: invokeinterface #310,  2          // InterfaceMethod java/sql/ResultSet.getInt:(Ljava/lang/String;)I
       624: invokestatic  #116                // Method java/lang/Integer.valueOf:(I)Ljava/lang/Integer;
       627: invokeinterface #336,  3          // InterfaceMethod java/util/Map.put:(Ljava/lang/Object;Ljava/lang/Object;)Ljava/lang/Object;
       632: pop
       633: aload_0
       634: getfield      #19                 // Field _lastSave:Ljava/util/Calendar;
       637: aload_3
       638: ldc_w         #392                // String date
       641: invokeinterface #394,  2          // InterfaceMethod java/sql/ResultSet.getLong:(Ljava/lang/String;)J
       646: invokevirtual #148                // Method java/util/Calendar.setTimeInMillis:(J)V
       649: goto          303
       652: aload_3
       653: ifnull        692
       656: aload_3
       657: invokeinterface #340,  1          // InterfaceMethod java/sql/ResultSet.close:()V
       662: goto          692
       665: astore        4
       667: aload_3
       668: ifnull        689
       671: aload_3
       672: invokeinterface #340,  1          // InterfaceMethod java/sql/ResultSet.close:()V
       677: goto          689
       680: astore        5
       682: aload         4
       684: aload         5
       686: invokevirtual #345                // Method java/lang/Throwable.addSuppressed:(Ljava/lang/Throwable;)V
       689: aload         4
       691: athrow
       692: aload_2
       693: ifnull        729
       696: aload_2
       697: invokeinterface #349,  1          // InterfaceMethod java/sql/PreparedStatement.close:()V
       702: goto          729
       705: astore_3
       706: aload_2
       707: ifnull        727
       710: aload_2
       711: invokeinterface #349,  1          // InterfaceMethod java/sql/PreparedStatement.close:()V
       716: goto          727
       719: astore        4
       721: aload_3
       722: aload         4
       724: invokevirtual #345                // Method java/lang/Throwable.addSuppressed:(Ljava/lang/Throwable;)V
       727: aload_3
       728: athrow
       729: aload_1
       730: ifnull        764
       733: aload_1
       734: invokeinterface #398,  1          // InterfaceMethod java/sql/Connection.close:()V
       739: goto          764
       742: astore_2
       743: aload_1
       744: ifnull        762
       747: aload_1
       748: invokeinterface #398,  1          // InterfaceMethod java/sql/Connection.close:()V
       753: goto          762
       756: astore_3
       757: aload_2
       758: aload_3
       759: invokevirtual #345                // Method java/lang/Throwable.addSuppressed:(Ljava/lang/Throwable;)V
       762: aload_2
       763: athrow
       764: goto          778
       767: astore_1
       768: getstatic     #48                 // Field LOGGER:Lext/mods/commons/logging/CLogger;
       771: ldc_w         #401                // String Couldn\'t load Seven Signs data.
       774: aload_1
       775: invokevirtual #403                // Method ext/mods/commons/logging/CLogger.error:(Ljava/lang/Object;Ljava/lang/Throwable;)V
       778: return
      Exception table:
         from    to  target type
            21   209   222   Class java/lang/Throwable
           228   234   237   Class java/lang/Throwable
            14   249   262   Class java/lang/Throwable
           267   273   276   Class java/lang/Throwable
           303   652   665   Class java/lang/Throwable
           671   677   680   Class java/lang/Throwable
           296   692   705   Class java/lang/Throwable
           710   716   719   Class java/lang/Throwable
             4   729   742   Class java/lang/Throwable
           747   753   756   Class java/lang/Throwable
             0   764   767   Class java/lang/Exception
      LineNumberTable:
        line 366: 0
        line 368: 4
        line 369: 14
        line 371: 21
        line 373: 30
        line 375: 41
        line 376: 50
        line 377: 60
        line 378: 82
        line 379: 104
        line 380: 121
        line 381: 138
        line 382: 155
        line 383: 172
        line 385: 189
        line 386: 206
        line 387: 209
        line 368: 222
        line 387: 249
        line 368: 262
        line 389: 286
        line 390: 296
        line 392: 303
        line 394: 312
        line 395: 325
        line 396: 346
        line 398: 367
        line 399: 380
        line 401: 393
        line 402: 423
        line 403: 453
        line 405: 483
        line 406: 508
        line 407: 533
        line 409: 558
        line 410: 583
        line 411: 608
        line 413: 633
        line 415: 652
        line 389: 665
        line 415: 692
        line 389: 705
        line 416: 729
        line 366: 742
        line 420: 764
        line 417: 767
        line 419: 768
        line 421: 778
      LocalVariableTable:
        Start  Length  Slot  Name   Signature
           41     165     4 objectId   I
           50     156     5   set   Lext/mods/commons/data/StatSet;
           21     228     3    rs   Ljava/sql/ResultSet;
           14     272     2    ps   Ljava/sql/PreparedStatement;
          303     389     3    rs   Ljava/sql/ResultSet;
          296     433     2    ps   Ljava/sql/PreparedStatement;
            4     760     1   con   Ljava/sql/Connection;
          768      10     1     e   Ljava/lang/Exception;
            0     779     0  this   Lext/mods/gameserver/data/manager/SevenSignsManager;
      StackMapTable: number_of_entries = 26
        frame_type = 254 /* append */
          offset_delta = 21
          locals = [ class java/sql/Connection, class java/sql/PreparedStatement, class java/sql/ResultSet ]
        frame_type = 251 /* same_frame_extended */
          offset_delta = 187
        frame_type = 76 /* same_locals_1_stack_item */
          stack = [ class java/lang/Throwable ]
        frame_type = 255 /* full_frame */
          offset_delta = 14
          locals = [ class ext/mods/gameserver/data/manager/SevenSignsManager, class java/sql/Connection, class java/sql/PreparedStatement, class java/sql/ResultSet, class java/lang/Throwable ]
          stack = [ class java/lang/Throwable ]
        frame_type = 8 /* same */
        frame_type = 249 /* chop */
          offset_delta = 2
        frame_type = 76 /* same_locals_1_stack_item */
          stack = [ class java/lang/Throwable ]
        frame_type = 255 /* full_frame */
          offset_delta = 13
          locals = [ class ext/mods/gameserver/data/manager/SevenSignsManager, class java/sql/Connection, class java/sql/PreparedStatement, class java/lang/Throwable ]
          stack = [ class java/lang/Throwable ]
        frame_type = 7 /* same */
        frame_type = 249 /* chop */
          offset_delta = 1
        frame_type = 253 /* append */
          offset_delta = 16
          locals = [ class java/sql/PreparedStatement, class java/sql/ResultSet ]
        frame_type = 251 /* same_frame_extended */
          offset_delta = 348
        frame_type = 76 /* same_locals_1_stack_item */
          stack = [ class java/lang/Throwable ]
        frame_type = 255 /* full_frame */
          offset_delta = 14
          locals = [ class ext/mods/gameserver/data/manager/SevenSignsManager, class java/sql/Connection, class java/sql/PreparedStatement, class java/sql/ResultSet, class java/lang/Throwable ]
          stack = [ class java/lang/Throwable ]
        frame_type = 8 /* same */
        frame_type = 249 /* chop */
          offset_delta = 2
        frame_type = 76 /* same_locals_1_stack_item */
          stack = [ class java/lang/Throwable ]
        frame_type = 255 /* full_frame */
          offset_delta = 13
          locals = [ class ext/mods/gameserver/data/manager/SevenSignsManager, class java/sql/Connection, class java/sql/PreparedStatement, class java/lang/Throwable ]
          stack = [ class java/lang/Throwable ]
        frame_type = 7 /* same */
        frame_type = 249 /* chop */
          offset_delta = 1
        frame_type = 76 /* same_locals_1_stack_item */
          stack = [ class java/lang/Throwable ]
        frame_type = 255 /* full_frame */
          offset_delta = 13
          locals = [ class ext/mods/gameserver/data/manager/SevenSignsManager, class java/sql/Connection, class java/lang/Throwable ]
          stack = [ class java/lang/Throwable ]
        frame_type = 5 /* same */
        frame_type = 249 /* chop */
          offset_delta = 1
        frame_type = 66 /* same_locals_1_stack_item */
          stack = [ class java/lang/Exception ]
        frame_type = 10 /* same */

  public void saveSevenSignsData();
    descriptor: ()V
    flags: (0x0001) ACC_PUBLIC
    Code:
      stack=4, locals=5, args_size=1
         0: invokestatic  #284                // Method ext/mods/commons/pool/ConnectionPool.getConnection:()Ljava/sql/Connection;
         3: astore_1
         4: aload_1
         5: ldc_w         #407                // String UPDATE seven_signs SET cabal=?, seal=?, red_stones=?, green_stones=?, blue_stones=?, ancient_adena_amount=?, contribution_score=? WHERE char_obj_id=?
         8: invokeinterface #292,  2          // InterfaceMethod java/sql/Connection.prepareStatement:(Ljava/lang/String;)Ljava/sql/PreparedStatement;
        13: astore_2
        14: aload_0
        15: getfield      #25                 // Field _playersData:Ljava/util/Map;
        18: invokeinterface #237,  1          // InterfaceMethod java/util/Map.values:()Ljava/util/Collection;
        23: invokeinterface #241,  1          // InterfaceMethod java/util/Collection.iterator:()Ljava/util/Iterator;
        28: astore_3
        29: aload_3
        30: invokeinterface #247,  1          // InterfaceMethod java/util/Iterator.hasNext:()Z
        35: ifeq          181
        38: aload_3
        39: invokeinterface #252,  1          // InterfaceMethod java/util/Iterator.next:()Ljava/lang/Object;
        44: checkcast     #256                // class ext/mods/commons/data/StatSet
        47: astore        4
        49: aload_2
        50: iconst_1
        51: aload         4
        53: ldc_w         #258                // String cabal
        56: invokevirtual #409                // Method ext/mods/commons/data/StatSet.getString:(Ljava/lang/String;)Ljava/lang/String;
        59: invokeinterface #410,  3          // InterfaceMethod java/sql/PreparedStatement.setString:(ILjava/lang/String;)V
        64: aload_2
        65: iconst_2
        66: aload         4
        68: ldc_w         #282                // String seal
        71: invokevirtual #409                // Method ext/mods/commons/data/StatSet.getString:(Ljava/lang/String;)Ljava/lang/String;
        74: invokeinterface #410,  3          // InterfaceMethod java/sql/PreparedStatement.setString:(ILjava/lang/String;)V
        79: aload_2
        80: iconst_3
        81: aload         4
        83: ldc_w         #264                // String red_stones
        86: invokevirtual #266                // Method ext/mods/commons/data/StatSet.getInteger:(Ljava/lang/String;)I
        89: invokeinterface #414,  3          // InterfaceMethod java/sql/PreparedStatement.setInt:(II)V
        94: aload_2
        95: iconst_4
        96: aload         4
        98: ldc_w         #270                // String green_stones
       101: invokevirtual #266                // Method ext/mods/commons/data/StatSet.getInteger:(Ljava/lang/String;)I
       104: invokeinterface #414,  3          // InterfaceMethod java/sql/PreparedStatement.setInt:(II)V
       109: aload_2
       110: iconst_5
       111: aload         4
       113: ldc_w         #272                // String blue_stones
       116: invokevirtual #266                // Method ext/mods/commons/data/StatSet.getInteger:(Ljava/lang/String;)I
       119: invokeinterface #414,  3          // InterfaceMethod java/sql/PreparedStatement.setInt:(II)V
       124: aload_2
       125: bipush        6
       127: aload         4
       129: ldc_w         #276                // String ancient_adena_amount
       132: invokevirtual #417                // Method ext/mods/commons/data/StatSet.getDouble:(Ljava/lang/String;)D
       135: invokeinterface #418,  4          // InterfaceMethod java/sql/PreparedStatement.setDouble:(ID)V
       140: aload_2
       141: bipush        7
       143: aload         4
       145: ldc_w         #274                // String contribution_score
       148: invokevirtual #417                // Method ext/mods/commons/data/StatSet.getDouble:(Ljava/lang/String;)D
       151: invokeinterface #418,  4          // InterfaceMethod java/sql/PreparedStatement.setDouble:(ID)V
       156: aload_2
       157: bipush        8
       159: aload         4
       161: ldc_w         #308                // String char_obj_id
       164: invokevirtual #266                // Method ext/mods/commons/data/StatSet.getInteger:(Ljava/lang/String;)I
       167: invokeinterface #414,  3          // InterfaceMethod java/sql/PreparedStatement.setInt:(II)V
       172: aload_2
       173: invokeinterface #422,  1          // InterfaceMethod java/sql/PreparedStatement.addBatch:()V
       178: goto          29
       181: aload_2
       182: invokeinterface #425,  1          // InterfaceMethod java/sql/PreparedStatement.executeBatch:()[I
       187: pop
       188: aload_2
       189: ifnull        225
       192: aload_2
       193: invokeinterface #349,  1          // InterfaceMethod java/sql/PreparedStatement.close:()V
       198: goto          225
       201: astore_3
       202: aload_2
       203: ifnull        223
       206: aload_2
       207: invokeinterface #349,  1          // InterfaceMethod java/sql/PreparedStatement.close:()V
       212: goto          223
       215: astore        4
       217: aload_3
       218: aload         4
       220: invokevirtual #345                // Method java/lang/Throwable.addSuppressed:(Ljava/lang/Throwable;)V
       223: aload_3
       224: athrow
       225: aload_1
       226: ifnull        260
       229: aload_1
       230: invokeinterface #398,  1          // InterfaceMethod java/sql/Connection.close:()V
       235: goto          260
       238: astore_2
       239: aload_1
       240: ifnull        258
       243: aload_1
       244: invokeinterface #398,  1          // InterfaceMethod java/sql/Connection.close:()V
       249: goto          258
       252: astore_3
       253: aload_2
       254: aload_3
       255: invokevirtual #345                // Method java/lang/Throwable.addSuppressed:(Ljava/lang/Throwable;)V
       258: aload_2
       259: athrow
       260: goto          274
       263: astore_1
       264: getstatic     #48                 // Field LOGGER:Lext/mods/commons/logging/CLogger;
       267: ldc_w         #429                // String Couldn\'t save Seven Signs player data.
       270: aload_1
       271: invokevirtual #403                // Method ext/mods/commons/logging/CLogger.error:(Ljava/lang/Object;Ljava/lang/Throwable;)V
       274: return
      Exception table:
         from    to  target type
            14   188   201   Class java/lang/Throwable
           206   212   215   Class java/lang/Throwable
             4   225   238   Class java/lang/Throwable
           243   249   252   Class java/lang/Throwable
             0   260   263   Class java/lang/Exception
      LineNumberTable:
        line 429: 0
        line 430: 4
        line 432: 14
        line 434: 49
        line 435: 64
        line 436: 79
        line 437: 94
        line 438: 109
        line 439: 124
        line 440: 140
        line 441: 156
        line 442: 172
        line 443: 178
        line 444: 181
        line 445: 188
        line 429: 201
        line 445: 225
        line 429: 238
        line 449: 260
        line 446: 263
        line 448: 264
        line 450: 274
      LocalVariableTable:
        Start  Length  Slot  Name   Signature
           49     129     4   set   Lext/mods/commons/data/StatSet;
           14     211     2    ps   Ljava/sql/PreparedStatement;
            4     256     1   con   Ljava/sql/Connection;
          264      10     1     e   Ljava/lang/Exception;
            0     275     0  this   Lext/mods/gameserver/data/manager/SevenSignsManager;
      StackMapTable: number_of_entries = 12
        frame_type = 254 /* append */
          offset_delta = 29
          locals = [ class java/sql/Connection, class java/sql/PreparedStatement, class java/util/Iterator ]
        frame_type = 250 /* chop */
          offset_delta = 151
        frame_type = 83 /* same_locals_1_stack_item */
          stack = [ class java/lang/Throwable ]
        frame_type = 255 /* full_frame */
          offset_delta = 13
          locals = [ class ext/mods/gameserver/data/manager/SevenSignsManager, class java/sql/Connection, class java/sql/PreparedStatement, class java/lang/Throwable ]
          stack = [ class java/lang/Throwable ]
        frame_type = 7 /* same */
        frame_type = 249 /* chop */
          offset_delta = 1
        frame_type = 76 /* same_locals_1_stack_item */
          stack = [ class java/lang/Throwable ]
        frame_type = 255 /* full_frame */
          offset_delta = 13
          locals = [ class ext/mods/gameserver/data/manager/SevenSignsManager, class java/sql/Connection, class java/lang/Throwable ]
          stack = [ class java/lang/Throwable ]
        frame_type = 5 /* same */
        frame_type = 249 /* chop */
          offset_delta = 1
        frame_type = 66 /* same_locals_1_stack_item */
          stack = [ class java/lang/Exception ]
        frame_type = 10 /* same */

  public final void saveSevenSignsStatus();
    descriptor: ()V
    flags: (0x0011) ACC_PUBLIC, ACC_FINAL
    Code:
      stack=4, locals=5, args_size=1
         0: invokestatic  #284                // Method ext/mods/commons/pool/ConnectionPool.getConnection:()Ljava/sql/Connection;
         3: astore_1
         4: aload_1
         5: ldc_w         #431                // String UPDATE seven_signs_status SET current_cycle=?, active_period=?, previous_winner=?, dawn_stone_score=?, dawn_festival_score=?, dusk_stone_score=?, dusk_festival_score=?, avarice_owner=?, gnosis_owner=?, strife_owner=?, avarice_dawn_score=?, gnosis_dawn_score=?, strife_dawn_score=?, avarice_dusk_score=?, gnosis_dusk_score=?, strife_dusk_score=?, festival_cycle=?, accumulated_bonus0=?, accumulated_bonus1=?, accumulated_bonus2=?,accumulated_bonus3=?, accumulated_bonus4=?, date=? WHERE id=0
         8: invokeinterface #292,  2          // InterfaceMethod java/sql/Connection.prepareStatement:(Ljava/lang/String;)Ljava/sql/PreparedStatement;
        13: astore_2
        14: aload_2
        15: iconst_1
        16: aload_0
        17: getfield      #154                // Field _currentCycle:I
        20: invokeinterface #414,  3          // InterfaceMethod java/sql/PreparedStatement.setInt:(II)V
        25: aload_2
        26: iconst_2
        27: aload_0
        28: getfield      #54                 // Field _activePeriod:Lext/mods/gameserver/enums/PeriodType;
        31: invokevirtual #433                // Method ext/mods/gameserver/enums/PeriodType.toString:()Ljava/lang/String;
        34: invokeinterface #410,  3          // InterfaceMethod java/sql/PreparedStatement.setString:(ILjava/lang/String;)V
        39: aload_2
        40: iconst_3
        41: aload_0
        42: getfield      #358                // Field _previousWinner:Lext/mods/gameserver/enums/CabalType;
        45: invokevirtual #436                // Method ext/mods/gameserver/enums/CabalType.toString:()Ljava/lang/String;
        48: invokeinterface #410,  3          // InterfaceMethod java/sql/PreparedStatement.setString:(ILjava/lang/String;)V
        53: aload_2
        54: iconst_4
        55: aload_0
        56: getfield      #186                // Field _dawnStoneScore:D
        59: invokeinterface #418,  4          // InterfaceMethod java/sql/PreparedStatement.setDouble:(ID)V
        64: aload_2
        65: iconst_5
        66: iconst_0
        67: invokeinterface #414,  3          // InterfaceMethod java/sql/PreparedStatement.setInt:(II)V
        72: aload_2
        73: bipush        6
        75: aload_0
        76: getfield      #190                // Field _duskStoneScore:D
        79: invokeinterface #418,  4          // InterfaceMethod java/sql/PreparedStatement.setDouble:(ID)V
        84: aload_2
        85: bipush        7
        87: iconst_0
        88: invokeinterface #414,  3          // InterfaceMethod java/sql/PreparedStatement.setInt:(II)V
        93: aload_2
        94: bipush        8
        96: aload_0
        97: getfield      #36                 // Field _sealOwners:Ljava/util/Map;
       100: getstatic     #365                // Field ext/mods/gameserver/enums/SealType.AVARICE:Lext/mods/gameserver/enums/SealType;
       103: invokeinterface #229,  2          // InterfaceMethod java/util/Map.get:(Ljava/lang/Object;)Ljava/lang/Object;
       108: checkcast     #197                // class ext/mods/gameserver/enums/CabalType
       111: invokevirtual #436                // Method ext/mods/gameserver/enums/CabalType.toString:()Ljava/lang/String;
       114: invokeinterface #410,  3          // InterfaceMethod java/sql/PreparedStatement.setString:(ILjava/lang/String;)V
       119: aload_2
       120: bipush        9
       122: aload_0
       123: getfield      #36                 // Field _sealOwners:Ljava/util/Map;
       126: getstatic     #370                // Field ext/mods/gameserver/enums/SealType.GNOSIS:Lext/mods/gameserver/enums/SealType;
       129: invokeinterface #229,  2          // InterfaceMethod java/util/Map.get:(Ljava/lang/Object;)Ljava/lang/Object;
       134: checkcast     #197                // class ext/mods/gameserver/enums/CabalType
       137: invokevirtual #436                // Method ext/mods/gameserver/enums/CabalType.toString:()Ljava/lang/String;
       140: invokeinterface #410,  3          // InterfaceMethod java/sql/PreparedStatement.setString:(ILjava/lang/String;)V
       145: aload_2
       146: bipush        10
       148: aload_0
       149: getfield      #36                 // Field _sealOwners:Ljava/util/Map;
       152: getstatic     #375                // Field ext/mods/gameserver/enums/SealType.STRIFE:Lext/mods/gameserver/enums/SealType;
       155: invokeinterface #229,  2          // InterfaceMethod java/util/Map.get:(Ljava/lang/Object;)Ljava/lang/Object;
       160: checkcast     #197                // class ext/mods/gameserver/enums/CabalType
       163: invokevirtual #436                // Method ext/mods/gameserver/enums/CabalType.toString:()Ljava/lang/String;
       166: invokeinterface #410,  3          // InterfaceMethod java/sql/PreparedStatement.setString:(ILjava/lang/String;)V
       171: aload_2
       172: bipush        11
       174: aload_0
       175: getfield      #42                 // Field _dawnScores:Ljava/util/Map;
       178: getstatic     #365                // Field ext/mods/gameserver/enums/SealType.AVARICE:Lext/mods/gameserver/enums/SealType;
       181: invokeinterface #229,  2          // InterfaceMethod java/util/Map.get:(Ljava/lang/Object;)Ljava/lang/Object;
       186: checkcast     #117                // class java/lang/Integer
       189: invokevirtual #234                // Method java/lang/Integer.intValue:()I
       192: invokeinterface #414,  3          // InterfaceMethod java/sql/PreparedStatement.setInt:(II)V
       197: aload_2
       198: bipush        12
       200: aload_0
       201: getfield      #42                 // Field _dawnScores:Ljava/util/Map;
       204: getstatic     #370                // Field ext/mods/gameserver/enums/SealType.GNOSIS:Lext/mods/gameserver/enums/SealType;
       207: invokeinterface #229,  2          // InterfaceMethod java/util/Map.get:(Ljava/lang/Object;)Ljava/lang/Object;
       212: checkcast     #117                // class java/lang/Integer
       215: invokevirtual #234                // Method java/lang/Integer.intValue:()I
       218: invokeinterface #414,  3          // InterfaceMethod java/sql/PreparedStatement.setInt:(II)V
       223: aload_2
       224: bipush        13
       226: aload_0
       227: getfield      #42                 // Field _dawnScores:Ljava/util/Map;
       230: getstatic     #375                // Field ext/mods/gameserver/enums/SealType.STRIFE:Lext/mods/gameserver/enums/SealType;
       233: invokeinterface #229,  2          // InterfaceMethod java/util/Map.get:(Ljava/lang/Object;)Ljava/lang/Object;
       238: checkcast     #117                // class java/lang/Integer
       241: invokevirtual #234                // Method java/lang/Integer.intValue:()I
       244: invokeinterface #414,  3          // InterfaceMethod java/sql/PreparedStatement.setInt:(II)V
       249: aload_2
       250: bipush        14
       252: aload_0
       253: getfield      #39                 // Field _duskScores:Ljava/util/Map;
       256: getstatic     #365                // Field ext/mods/gameserver/enums/SealType.AVARICE:Lext/mods/gameserver/enums/SealType;
       259: invokeinterface #229,  2          // InterfaceMethod java/util/Map.get:(Ljava/lang/Object;)Ljava/lang/Object;
       264: checkcast     #117                // class java/lang/Integer
       267: invokevirtual #234                // Method java/lang/Integer.intValue:()I
       270: invokeinterface #414,  3          // InterfaceMethod java/sql/PreparedStatement.setInt:(II)V
       275: aload_2
       276: bipush        15
       278: aload_0
       279: getfield      #39                 // Field _duskScores:Ljava/util/Map;
       282: getstatic     #370                // Field ext/mods/gameserver/enums/SealType.GNOSIS:Lext/mods/gameserver/enums/SealType;
       285: invokeinterface #229,  2          // InterfaceMethod java/util/Map.get:(Ljava/lang/Object;)Ljava/lang/Object;
       290: checkcast     #117                // class java/lang/Integer
       293: invokevirtual #234                // Method java/lang/Integer.intValue:()I
       296: invokeinterface #414,  3          // InterfaceMethod java/sql/PreparedStatement.setInt:(II)V
       301: aload_2
       302: bipush        16
       304: aload_0
       305: getfield      #39                 // Field _duskScores:Ljava/util/Map;
       308: getstatic     #375                // Field ext/mods/gameserver/enums/SealType.STRIFE:Lext/mods/gameserver/enums/SealType;
       311: invokeinterface #229,  2          // InterfaceMethod java/util/Map.get:(Ljava/lang/Object;)Ljava/lang/Object;
       316: checkcast     #117                // class java/lang/Integer
       319: invokevirtual #234                // Method java/lang/Integer.intValue:()I
       322: invokeinterface #414,  3          // InterfaceMethod java/sql/PreparedStatement.setInt:(II)V
       327: aload_2
       328: bipush        17
       330: invokestatic  #208                // Method ext/mods/gameserver/data/manager/FestivalOfDarknessManager.getInstance:()Lext/mods/gameserver/data/manager/FestivalOfDarknessManager;
       333: invokevirtual #437                // Method ext/mods/gameserver/data/manager/FestivalOfDarknessManager.getCurrentFestivalCycle:()I
       336: invokeinterface #414,  3          // InterfaceMethod java/sql/PreparedStatement.setInt:(II)V
       341: iconst_0
       342: istore_3
       343: iload_3
       344: iconst_5
       345: if_icmpge     371
       348: aload_2
       349: bipush        18
       351: iload_3
       352: iadd
       353: invokestatic  #208                // Method ext/mods/gameserver/data/manager/FestivalOfDarknessManager.getInstance:()Lext/mods/gameserver/data/manager/FestivalOfDarknessManager;
       356: iload_3
       357: invokevirtual #440                // Method ext/mods/gameserver/data/manager/FestivalOfDarknessManager.getAccumulatedBonus:(I)I
       360: invokeinterface #414,  3          // InterfaceMethod java/sql/PreparedStatement.setInt:(II)V
       365: iinc          3, 1
       368: goto          343
       371: aload_0
       372: invokestatic  #11                 // Method java/util/Calendar.getInstance:()Ljava/util/Calendar;
       375: putfield      #19                 // Field _lastSave:Ljava/util/Calendar;
       378: aload_2
       379: bipush        23
       381: aload_0
       382: getfield      #19                 // Field _lastSave:Ljava/util/Calendar;
       385: invokevirtual #143                // Method java/util/Calendar.getTimeInMillis:()J
       388: invokeinterface #443,  4          // InterfaceMethod java/sql/PreparedStatement.setLong:(IJ)V
       393: aload_2
       394: invokeinterface #447,  1          // InterfaceMethod java/sql/PreparedStatement.execute:()Z
       399: pop
       400: aload_2
       401: ifnull        437
       404: aload_2
       405: invokeinterface #349,  1          // InterfaceMethod java/sql/PreparedStatement.close:()V
       410: goto          437
       413: astore_3
       414: aload_2
       415: ifnull        435
       418: aload_2
       419: invokeinterface #349,  1          // InterfaceMethod java/sql/PreparedStatement.close:()V
       424: goto          435
       427: astore        4
       429: aload_3
       430: aload         4
       432: invokevirtual #345                // Method java/lang/Throwable.addSuppressed:(Ljava/lang/Throwable;)V
       435: aload_3
       436: athrow
       437: aload_1
       438: ifnull        472
       441: aload_1
       442: invokeinterface #398,  1          // InterfaceMethod java/sql/Connection.close:()V
       447: goto          472
       450: astore_2
       451: aload_1
       452: ifnull        470
       455: aload_1
       456: invokeinterface #398,  1          // InterfaceMethod java/sql/Connection.close:()V
       461: goto          470
       464: astore_3
       465: aload_2
       466: aload_3
       467: invokevirtual #345                // Method java/lang/Throwable.addSuppressed:(Ljava/lang/Throwable;)V
       470: aload_2
       471: athrow
       472: goto          486
       475: astore_1
       476: getstatic     #48                 // Field LOGGER:Lext/mods/commons/logging/CLogger;
       479: ldc_w         #450                // String Couldn\'t save Seven Signs status data.
       482: aload_1
       483: invokevirtual #403                // Method ext/mods/commons/logging/CLogger.error:(Ljava/lang/Object;Ljava/lang/Throwable;)V
       486: return
      Exception table:
         from    to  target type
            14   400   413   Class java/lang/Throwable
           418   424   427   Class java/lang/Throwable
             4   437   450   Class java/lang/Throwable
           455   461   464   Class java/lang/Throwable
             0   472   475   Class java/lang/Exception
      LineNumberTable:
        line 454: 0
        line 455: 4
        line 457: 14
        line 458: 25
        line 459: 39
        line 460: 53
        line 461: 64
        line 462: 72
        line 463: 84
        line 464: 93
        line 465: 119
        line 466: 145
        line 467: 171
        line 468: 197
        line 469: 223
        line 470: 249
        line 471: 275
        line 472: 301
        line 473: 327
        line 475: 341
        line 476: 348
        line 475: 365
        line 478: 371
        line 479: 378
        line 480: 393
        line 481: 400
        line 454: 413
        line 481: 437
        line 454: 450
        line 485: 472
        line 482: 475
        line 484: 476
        line 486: 486
      LocalVariableTable:
        Start  Length  Slot  Name   Signature
          343      28     3     i   I
           14     423     2    ps   Ljava/sql/PreparedStatement;
            4     468     1   con   Ljava/sql/Connection;
          476      10     1     e   Ljava/lang/Exception;
            0     487     0  this   Lext/mods/gameserver/data/manager/SevenSignsManager;
      StackMapTable: number_of_entries = 12
        frame_type = 254 /* append */
          offset_delta = 343
          locals = [ class java/sql/Connection, class java/sql/PreparedStatement, int ]
        frame_type = 250 /* chop */
          offset_delta = 27
        frame_type = 105 /* same_locals_1_stack_item */
          stack = [ class java/lang/Throwable ]
        frame_type = 255 /* full_frame */
          offset_delta = 13
          locals = [ class ext/mods/gameserver/data/manager/SevenSignsManager, class java/sql/Connection, class java/sql/PreparedStatement, class java/lang/Throwable ]
          stack = [ class java/lang/Throwable ]
        frame_type = 7 /* same */
        frame_type = 249 /* chop */
          offset_delta = 1
        frame_type = 76 /* same_locals_1_stack_item */
          stack = [ class java/lang/Throwable ]
        frame_type = 255 /* full_frame */
          offset_delta = 13
          locals = [ class ext/mods/gameserver/data/manager/SevenSignsManager, class java/sql/Connection, class java/lang/Throwable ]
          stack = [ class java/lang/Throwable ]
        frame_type = 5 /* same */
        frame_type = 249 /* chop */
          offset_delta = 1
        frame_type = 66 /* same_locals_1_stack_item */
          stack = [ class java/lang/Exception ]
        frame_type = 10 /* same */

  protected void resetPlayerData();
    descriptor: ()V
    flags: (0x0004) ACC_PROTECTED
    Code:
      stack=3, locals=3, args_size=1
         0: aload_0
         1: getfield      #25                 // Field _playersData:Ljava/util/Map;
         4: invokeinterface #237,  1          // InterfaceMethod java/util/Map.values:()Ljava/util/Collection;
         9: invokeinterface #241,  1          // InterfaceMethod java/util/Collection.iterator:()Ljava/util/Iterator;
        14: astore_1
        15: aload_1
        16: invokeinterface #247,  1          // InterfaceMethod java/util/Iterator.hasNext:()Z
        21: ifeq          65
        24: aload_1
        25: invokeinterface #252,  1          // InterfaceMethod java/util/Iterator.next:()Ljava/lang/Object;
        30: checkcast     #256                // class ext/mods/commons/data/StatSet
        33: astore_2
        34: aload_2
        35: ldc_w         #258                // String cabal
        38: getstatic     #226                // Field ext/mods/gameserver/enums/CabalType.NORMAL:Lext/mods/gameserver/enums/CabalType;
        41: invokevirtual #326                // Method ext/mods/commons/data/StatSet.set:(Ljava/lang/String;Ljava/lang/Enum;)V
        44: aload_2
        45: ldc_w         #282                // String seal
        48: getstatic     #278                // Field ext/mods/gameserver/enums/SealType.NONE:Lext/mods/gameserver/enums/SealType;
        51: invokevirtual #326                // Method ext/mods/commons/data/StatSet.set:(Ljava/lang/String;Ljava/lang/Enum;)V
        54: aload_2
        55: ldc_w         #274                // String contribution_score
        58: iconst_0
        59: invokevirtual #314                // Method ext/mods/commons/data/StatSet.set:(Ljava/lang/String;I)V
        62: goto          15
        65: return
      LineNumberTable:
        line 494: 0
        line 496: 34
        line 497: 44
        line 498: 54
        line 499: 62
        line 500: 65
      LocalVariableTable:
        Start  Length  Slot  Name   Signature
           34      28     2   set   Lext/mods/commons/data/StatSet;
            0      66     0  this   Lext/mods/gameserver/data/manager/SevenSignsManager;
      StackMapTable: number_of_entries = 2
        frame_type = 252 /* append */
          offset_delta = 15
          locals = [ class java/util/Iterator ]
        frame_type = 250 /* chop */
          offset_delta = 49

  public ext.mods.gameserver.enums.CabalType setPlayerInfo(int, ext.mods.gameserver.enums.CabalType, ext.mods.gameserver.enums.SealType);
    descriptor: (ILext/mods/gameserver/enums/CabalType;Lext/mods/gameserver/enums/SealType;)Lext/mods/gameserver/enums/CabalType;
    flags: (0x0001) ACC_PUBLIC
    Code:
      stack=4, locals=9, args_size=4
         0: aload_0
         1: getfield      #25                 // Field _playersData:Ljava/util/Map;
         4: iload_1
         5: invokestatic  #116                // Method java/lang/Integer.valueOf:(I)Ljava/lang/Integer;
         8: invokeinterface #229,  2          // InterfaceMethod java/util/Map.get:(Ljava/lang/Object;)Ljava/lang/Object;
        13: checkcast     #256                // class ext/mods/commons/data/StatSet
        16: astore        4
        18: aload         4
        20: ifnull        44
        23: aload         4
        25: ldc_w         #258                // String cabal
        28: aload_2
        29: invokevirtual #326                // Method ext/mods/commons/data/StatSet.set:(Ljava/lang/String;Ljava/lang/Enum;)V
        32: aload         4
        34: ldc_w         #282                // String seal
        37: aload_3
        38: invokevirtual #326                // Method ext/mods/commons/data/StatSet.set:(Ljava/lang/String;Ljava/lang/Enum;)V
        41: goto          303
        44: new           #256                // class ext/mods/commons/data/StatSet
        47: dup
        48: invokespecial #313                // Method ext/mods/commons/data/StatSet."<init>":()V
        51: astore        4
        53: aload         4
        55: ldc_w         #308                // String char_obj_id
        58: iload_1
        59: invokevirtual #314                // Method ext/mods/commons/data/StatSet.set:(Ljava/lang/String;I)V
        62: aload         4
        64: ldc_w         #258                // String cabal
        67: aload_2
        68: invokevirtual #326                // Method ext/mods/commons/data/StatSet.set:(Ljava/lang/String;Ljava/lang/Enum;)V
        71: aload         4
        73: ldc_w         #282                // String seal
        76: aload_3
        77: invokevirtual #326                // Method ext/mods/commons/data/StatSet.set:(Ljava/lang/String;Ljava/lang/Enum;)V
        80: aload         4
        82: ldc_w         #264                // String red_stones
        85: iconst_0
        86: invokevirtual #314                // Method ext/mods/commons/data/StatSet.set:(Ljava/lang/String;I)V
        89: aload         4
        91: ldc_w         #270                // String green_stones
        94: iconst_0
        95: invokevirtual #314                // Method ext/mods/commons/data/StatSet.set:(Ljava/lang/String;I)V
        98: aload         4
       100: ldc_w         #272                // String blue_stones
       103: iconst_0
       104: invokevirtual #314                // Method ext/mods/commons/data/StatSet.set:(Ljava/lang/String;I)V
       107: aload         4
       109: ldc_w         #276                // String ancient_adena_amount
       112: iconst_0
       113: invokevirtual #314                // Method ext/mods/commons/data/StatSet.set:(Ljava/lang/String;I)V
       116: aload         4
       118: ldc_w         #274                // String contribution_score
       121: iconst_0
       122: invokevirtual #314                // Method ext/mods/commons/data/StatSet.set:(Ljava/lang/String;I)V
       125: aload_0
       126: getfield      #25                 // Field _playersData:Ljava/util/Map;
       129: iload_1
       130: invokestatic  #116                // Method java/lang/Integer.valueOf:(I)Ljava/lang/Integer;
       133: aload         4
       135: invokeinterface #336,  3          // InterfaceMethod java/util/Map.put:(Ljava/lang/Object;Ljava/lang/Object;)Ljava/lang/Object;
       140: pop
       141: invokestatic  #284                // Method ext/mods/commons/pool/ConnectionPool.getConnection:()Ljava/sql/Connection;
       144: astore        5
       146: aload         5
       148: ldc_w         #452                // String INSERT INTO seven_signs (char_obj_id, cabal, seal) VALUES (?,?,?)
       151: invokeinterface #292,  2          // InterfaceMethod java/sql/Connection.prepareStatement:(Ljava/lang/String;)Ljava/sql/PreparedStatement;
       156: astore        6
       158: aload         6
       160: iconst_1
       161: iload_1
       162: invokeinterface #414,  3          // InterfaceMethod java/sql/PreparedStatement.setInt:(II)V
       167: aload         6
       169: iconst_2
       170: aload_2
       171: invokevirtual #436                // Method ext/mods/gameserver/enums/CabalType.toString:()Ljava/lang/String;
       174: invokeinterface #410,  3          // InterfaceMethod java/sql/PreparedStatement.setString:(ILjava/lang/String;)V
       179: aload         6
       181: iconst_3
       182: aload_3
       183: invokevirtual #454                // Method ext/mods/gameserver/enums/SealType.toString:()Ljava/lang/String;
       186: invokeinterface #410,  3          // InterfaceMethod java/sql/PreparedStatement.setString:(ILjava/lang/String;)V
       191: aload         6
       193: invokeinterface #447,  1          // InterfaceMethod java/sql/PreparedStatement.execute:()Z
       198: pop
       199: aload         6
       201: ifnull        243
       204: aload         6
       206: invokeinterface #349,  1          // InterfaceMethod java/sql/PreparedStatement.close:()V
       211: goto          243
       214: astore        7
       216: aload         6
       218: ifnull        240
       221: aload         6
       223: invokeinterface #349,  1          // InterfaceMethod java/sql/PreparedStatement.close:()V
       228: goto          240
       231: astore        8
       233: aload         7
       235: aload         8
       237: invokevirtual #345                // Method java/lang/Throwable.addSuppressed:(Ljava/lang/Throwable;)V
       240: aload         7
       242: athrow
       243: aload         5
       245: ifnull        287
       248: aload         5
       250: invokeinterface #398,  1          // InterfaceMethod java/sql/Connection.close:()V
       255: goto          287
       258: astore        6
       260: aload         5
       262: ifnull        284
       265: aload         5
       267: invokeinterface #398,  1          // InterfaceMethod java/sql/Connection.close:()V
       272: goto          284
       275: astore        7
       277: aload         6
       279: aload         7
       281: invokevirtual #345                // Method java/lang/Throwable.addSuppressed:(Ljava/lang/Throwable;)V
       284: aload         6
       286: athrow
       287: goto          303
       290: astore        5
       292: getstatic     #48                 // Field LOGGER:Lext/mods/commons/logging/CLogger;
       295: ldc_w         #455                // String Couldn\'t save Seven Signs player info data.
       298: aload         5
       300: invokevirtual #403                // Method ext/mods/commons/logging/CLogger.error:(Ljava/lang/Object;Ljava/lang/Throwable;)V
       303: aload_2
       304: getstatic     #223                // Field ext/mods/gameserver/enums/CabalType.DAWN:Lext/mods/gameserver/enums/CabalType;
       307: if_acmpne     345
       310: aload_0
       311: getfield      #42                 // Field _dawnScores:Ljava/util/Map;
       314: aload_3
       315: aload_0
       316: getfield      #42                 // Field _dawnScores:Ljava/util/Map;
       319: aload_3
       320: invokeinterface #229,  2          // InterfaceMethod java/util/Map.get:(Ljava/lang/Object;)Ljava/lang/Object;
       325: checkcast     #117                // class java/lang/Integer
       328: invokevirtual #234                // Method java/lang/Integer.intValue:()I
       331: iconst_1
       332: iadd
       333: invokestatic  #116                // Method java/lang/Integer.valueOf:(I)Ljava/lang/Integer;
       336: invokeinterface #336,  3          // InterfaceMethod java/util/Map.put:(Ljava/lang/Object;Ljava/lang/Object;)Ljava/lang/Object;
       341: pop
       342: goto          377
       345: aload_0
       346: getfield      #39                 // Field _duskScores:Ljava/util/Map;
       349: aload_3
       350: aload_0
       351: getfield      #39                 // Field _duskScores:Ljava/util/Map;
       354: aload_3
       355: invokeinterface #229,  2          // InterfaceMethod java/util/Map.get:(Ljava/lang/Object;)Ljava/lang/Object;
       360: checkcast     #117                // class java/lang/Integer
       363: invokevirtual #234                // Method java/lang/Integer.intValue:()I
       366: iconst_1
       367: iadd
       368: invokestatic  #116                // Method java/lang/Integer.valueOf:(I)Ljava/lang/Integer;
       371: invokeinterface #336,  3          // InterfaceMethod java/util/Map.put:(Ljava/lang/Object;Ljava/lang/Object;)Ljava/lang/Object;
       376: pop
       377: aload_2
       378: areturn
      Exception table:
         from    to  target type
           158   199   214   Class java/lang/Throwable
           221   228   231   Class java/lang/Throwable
           146   243   258   Class java/lang/Throwable
           265   272   275   Class java/lang/Throwable
           141   287   290   Class java/lang/Exception
      LineNumberTable:
        line 512: 0
        line 513: 18
        line 515: 23
        line 516: 32
        line 520: 44
        line 521: 53
        line 522: 62
        line 523: 71
        line 524: 80
        line 525: 89
        line 526: 98
        line 527: 107
        line 528: 116
        line 530: 125
        line 532: 141
        line 533: 146
        line 535: 158
        line 536: 167
        line 537: 179
        line 538: 191
        line 539: 199
        line 532: 214
        line 539: 243
        line 532: 258
        line 543: 287
        line 540: 290
        line 542: 292
        line 546: 303
        line 547: 310
        line 549: 345
        line 551: 377
      LocalVariableTable:
        Start  Length  Slot  Name   Signature
          158      85     6    ps   Ljava/sql/PreparedStatement;
          146     141     5   con   Ljava/sql/Connection;
          292      11     5     e   Ljava/lang/Exception;
            0     379     0  this   Lext/mods/gameserver/data/manager/SevenSignsManager;
            0     379     1 objectId   I
            0     379     2 cabal   Lext/mods/gameserver/enums/CabalType;
            0     379     3  seal   Lext/mods/gameserver/enums/SealType;
           18     361     4   set   Lext/mods/commons/data/StatSet;
      StackMapTable: number_of_entries = 13
        frame_type = 252 /* append */
          offset_delta = 44
          locals = [ class ext/mods/commons/data/StatSet ]
        frame_type = 255 /* full_frame */
          offset_delta = 169
          locals = [ class ext/mods/gameserver/data/manager/SevenSignsManager, int, class ext/mods/gameserver/enums/CabalType, class ext/mods/gameserver/enums/SealType, class ext/mods/commons/data/StatSet, class java/sql/Connection, class java/sql/PreparedStatement ]
          stack = [ class java/lang/Throwable ]
        frame_type = 255 /* full_frame */
          offset_delta = 16
          locals = [ class ext/mods/gameserver/data/manager/SevenSignsManager, int, class ext/mods/gameserver/enums/CabalType, class ext/mods/gameserver/enums/SealType, class ext/mods/commons/data/StatSet, class java/sql/Connection, class java/sql/PreparedStatement, class java/lang/Throwable ]
          stack = [ class java/lang/Throwable ]
        frame_type = 8 /* same */
        frame_type = 249 /* chop */
          offset_delta = 2
        frame_type = 78 /* same_locals_1_stack_item */
          stack = [ class java/lang/Throwable ]
        frame_type = 255 /* full_frame */
          offset_delta = 16
          locals = [ class ext/mods/gameserver/data/manager/SevenSignsManager, int, class ext/mods/gameserver/enums/CabalType, class ext/mods/gameserver/enums/SealType, class ext/mods/commons/data/StatSet, class java/sql/Connection, class java/lang/Throwable ]
          stack = [ class java/lang/Throwable ]
        frame_type = 8 /* same */
        frame_type = 249 /* chop */
          offset_delta = 2
        frame_type = 66 /* same_locals_1_stack_item */
          stack = [ class java/lang/Exception ]
        frame_type = 12 /* same */
        frame_type = 41 /* same */
        frame_type = 31 /* same */

  public int getAncientAdenaReward(int);
    descriptor: (I)I
    flags: (0x0001) ACC_PUBLIC
    Code:
      stack=3, locals=4, args_size=2
         0: aload_0
         1: getfield      #25                 // Field _playersData:Ljava/util/Map;
         4: iload_1
         5: invokestatic  #116                // Method java/lang/Integer.valueOf:(I)Ljava/lang/Integer;
         8: invokeinterface #229,  2          // InterfaceMethod java/util/Map.get:(Ljava/lang/Object;)Ljava/lang/Object;
        13: checkcast     #256                // class ext/mods/commons/data/StatSet
        16: astore_2
        17: aload_2
        18: ldc_w         #276                // String ancient_adena_amount
        21: invokevirtual #266                // Method ext/mods/commons/data/StatSet.getInteger:(Ljava/lang/String;)I
        24: istore_3
        25: aload_2
        26: ldc_w         #264                // String red_stones
        29: iconst_0
        30: invokevirtual #314                // Method ext/mods/commons/data/StatSet.set:(Ljava/lang/String;I)V
        33: aload_2
        34: ldc_w         #270                // String green_stones
        37: iconst_0
        38: invokevirtual #314                // Method ext/mods/commons/data/StatSet.set:(Ljava/lang/String;I)V
        41: aload_2
        42: ldc_w         #272                // String blue_stones
        45: iconst_0
        46: invokevirtual #314                // Method ext/mods/commons/data/StatSet.set:(Ljava/lang/String;I)V
        49: aload_2
        50: ldc_w         #276                // String ancient_adena_amount
        53: iconst_0
        54: invokevirtual #314                // Method ext/mods/commons/data/StatSet.set:(Ljava/lang/String;I)V
        57: iload_3
        58: ireturn
      LineNumberTable:
        line 560: 0
        line 561: 17
        line 563: 25
        line 564: 33
        line 565: 41
        line 566: 49
        line 568: 57
      LocalVariableTable:
        Start  Length  Slot  Name   Signature
            0      59     0  this   Lext/mods/gameserver/data/manager/SevenSignsManager;
            0      59     1 objectId   I
           17      42     2   set   Lext/mods/commons/data/StatSet;
           25      34     3 rewardAmount   I

  public int addPlayerStoneContrib(int, int, int, int);
    descriptor: (IIII)I
    flags: (0x0001) ACC_PUBLIC
    Code:
      stack=5, locals=9, args_size=5
         0: aload_0
         1: getfield      #25                 // Field _playersData:Ljava/util/Map;
         4: iload_1
         5: invokestatic  #116                // Method java/lang/Integer.valueOf:(I)Ljava/lang/Integer;
         8: invokeinterface #229,  2          // InterfaceMethod java/util/Map.get:(Ljava/lang/Object;)Ljava/lang/Object;
        13: checkcast     #256                // class ext/mods/commons/data/StatSet
        16: astore        5
        18: iload_2
        19: iload_3
        20: iload         4
        22: invokestatic  #457                // Method calcScore:(III)I
        25: istore        6
        27: aload         5
        29: ldc_w         #276                // String ancient_adena_amount
        32: invokevirtual #266                // Method ext/mods/commons/data/StatSet.getInteger:(Ljava/lang/String;)I
        35: iload         6
        37: iadd
        38: istore        7
        40: aload         5
        42: ldc_w         #274                // String contribution_score
        45: invokevirtual #266                // Method ext/mods/commons/data/StatSet.getInteger:(Ljava/lang/String;)I
        48: iload         6
        50: iadd
        51: istore        8
        53: iload         8
        55: getstatic     #461                // Field ext/mods/Config.MAXIMUM_PLAYER_CONTRIB:I
        58: if_icmple     63
        61: iconst_m1
        62: ireturn
        63: aload         5
        65: ldc_w         #264                // String red_stones
        68: aload         5
        70: ldc_w         #264                // String red_stones
        73: invokevirtual #266                // Method ext/mods/commons/data/StatSet.getInteger:(Ljava/lang/String;)I
        76: iload         4
        78: iadd
        79: invokevirtual #314                // Method ext/mods/commons/data/StatSet.set:(Ljava/lang/String;I)V
        82: aload         5
        84: ldc_w         #270                // String green_stones
        87: aload         5
        89: ldc_w         #270                // String green_stones
        92: invokevirtual #266                // Method ext/mods/commons/data/StatSet.getInteger:(Ljava/lang/String;)I
        95: iload_3
        96: iadd
        97: invokevirtual #314                // Method ext/mods/commons/data/StatSet.set:(Ljava/lang/String;I)V
       100: aload         5
       102: ldc_w         #272                // String blue_stones
       105: aload         5
       107: ldc_w         #272                // String blue_stones
       110: invokevirtual #266                // Method ext/mods/commons/data/StatSet.getInteger:(Ljava/lang/String;)I
       113: iload_2
       114: iadd
       115: invokevirtual #314                // Method ext/mods/commons/data/StatSet.set:(Ljava/lang/String;I)V
       118: aload         5
       120: ldc_w         #276                // String ancient_adena_amount
       123: iload         7
       125: invokevirtual #314                // Method ext/mods/commons/data/StatSet.set:(Ljava/lang/String;I)V
       128: aload         5
       130: ldc_w         #274                // String contribution_score
       133: iload         8
       135: invokevirtual #314                // Method ext/mods/commons/data/StatSet.set:(Ljava/lang/String;I)V
       138: getstatic     #193                // Field ext/mods/gameserver/data/manager/SevenSignsManager$1.$SwitchMap$ext$mods$gameserver$enums$CabalType:[I
       141: aload_0
       142: iload_1
       143: invokevirtual #466                // Method getPlayerCabal:(I)Lext/mods/gameserver/enums/CabalType;
       146: invokevirtual #196                // Method ext/mods/gameserver/enums/CabalType.ordinal:()I
       149: iaload
       150: lookupswitch  { // 2

                       1: 176

                       2: 191
                 default: 203
            }
       176: aload_0
       177: dup
       178: getfield      #186                // Field _dawnStoneScore:D
       181: iload         6
       183: i2d
       184: dadd
       185: putfield      #186                // Field _dawnStoneScore:D
       188: goto          203
       191: aload_0
       192: dup
       193: getfield      #190                // Field _duskStoneScore:D
       196: iload         6
       198: i2d
       199: dadd
       200: putfield      #190                // Field _duskStoneScore:D
       203: iload         6
       205: ireturn
      LineNumberTable:
        line 582: 0
        line 584: 18
        line 585: 27
        line 586: 40
        line 588: 53
        line 589: 61
        line 591: 63
        line 592: 82
        line 593: 100
        line 594: 118
        line 595: 128
        line 597: 138
        line 600: 176
        line 601: 188
        line 604: 191
        line 608: 203
      LocalVariableTable:
        Start  Length  Slot  Name   Signature
            0     206     0  this   Lext/mods/gameserver/data/manager/SevenSignsManager;
            0     206     1 objectId   I
            0     206     2 blueCount   I
            0     206     3 greenCount   I
            0     206     4 redCount   I
           18     188     5   set   Lext/mods/commons/data/StatSet;
           27     179     6 contribScore   I
           40     166     7 totalAncientAdena   I
           53     153     8 totalContribScore   I
      StackMapTable: number_of_entries = 4
        frame_type = 255 /* full_frame */
          offset_delta = 63
          locals = [ class ext/mods/gameserver/data/manager/SevenSignsManager, int, int, int, int, class ext/mods/commons/data/StatSet, int, int, int ]
          stack = []
        frame_type = 251 /* same_frame_extended */
          offset_delta = 112
        frame_type = 14 /* same */
        frame_type = 11 /* same */

  protected void initializeSeals();
    descriptor: ()V
    flags: (0x0004) ACC_PROTECTED
    Code:
      stack=6, locals=5, args_size=1
         0: aload_0
         1: getfield      #36                 // Field _sealOwners:Ljava/util/Map;
         4: invokeinterface #470,  1          // InterfaceMethod java/util/Map.entrySet:()Ljava/util/Set;
         9: invokeinterface #474,  1          // InterfaceMethod java/util/Set.iterator:()Ljava/util/Iterator;
        14: astore_1
        15: aload_1
        16: invokeinterface #247,  1          // InterfaceMethod java/util/Iterator.hasNext:()Z
        21: ifeq          155
        24: aload_1
        25: invokeinterface #252,  1          // InterfaceMethod java/util/Iterator.next:()Ljava/lang/Object;
        30: checkcast     #477                // class java/util/Map$Entry
        33: astore_2
        34: aload_2
        35: invokeinterface #479,  1          // InterfaceMethod java/util/Map$Entry.getKey:()Ljava/lang/Object;
        40: checkcast     #31                 // class ext/mods/gameserver/enums/SealType
        43: astore_3
        44: aload_2
        45: invokeinterface #482,  1          // InterfaceMethod java/util/Map$Entry.getValue:()Ljava/lang/Object;
        50: checkcast     #197                // class ext/mods/gameserver/enums/CabalType
        53: astore        4
        55: aload         4
        57: getstatic     #226                // Field ext/mods/gameserver/enums/CabalType.NORMAL:Lext/mods/gameserver/enums/CabalType;
        60: if_acmpeq     132
        63: aload_0
        64: invokevirtual #485                // Method isSealValidationPeriod:()Z
        67: ifeq          101
        70: getstatic     #48                 // Field LOGGER:Lext/mods/commons/logging/CLogger;
        73: ldc_w         #488                // String The {} have won {}.
        76: iconst_2
        77: anewarray     #6                  // class java/lang/Object
        80: dup
        81: iconst_0
        82: aload         4
        84: invokevirtual #490                // Method ext/mods/gameserver/enums/CabalType.getFullName:()Ljava/lang/String;
        87: aastore
        88: dup
        89: iconst_1
        90: aload_3
        91: invokevirtual #493                // Method ext/mods/gameserver/enums/SealType.getFullName:()Ljava/lang/String;
        94: aastore
        95: invokevirtual #64                 // Method ext/mods/commons/logging/CLogger.info:(Ljava/lang/Object;[Ljava/lang/Object;)V
        98: goto          152
       101: getstatic     #48                 // Field LOGGER:Lext/mods/commons/logging/CLogger;
       104: ldc_w         #494                // String The {} is currently owned by {}.
       107: iconst_2
       108: anewarray     #6                  // class java/lang/Object
       111: dup
       112: iconst_0
       113: aload_3
       114: invokevirtual #493                // Method ext/mods/gameserver/enums/SealType.getFullName:()Ljava/lang/String;
       117: aastore
       118: dup
       119: iconst_1
       120: aload         4
       122: invokevirtual #490                // Method ext/mods/gameserver/enums/CabalType.getFullName:()Ljava/lang/String;
       125: aastore
       126: invokevirtual #64                 // Method ext/mods/commons/logging/CLogger.info:(Ljava/lang/Object;[Ljava/lang/Object;)V
       129: goto          152
       132: getstatic     #48                 // Field LOGGER:Lext/mods/commons/logging/CLogger;
       135: ldc_w         #496                // String The {} remains unclaimed.
       138: iconst_1
       139: anewarray     #6                  // class java/lang/Object
       142: dup
       143: iconst_0
       144: aload_3
       145: invokevirtual #493                // Method ext/mods/gameserver/enums/SealType.getFullName:()Ljava/lang/String;
       148: aastore
       149: invokevirtual #64                 // Method ext/mods/commons/logging/CLogger.info:(Ljava/lang/Object;[Ljava/lang/Object;)V
       152: goto          15
       155: return
      LineNumberTable:
        line 616: 0
        line 618: 34
        line 619: 44
        line 621: 55
        line 623: 63
        line 624: 70
        line 626: 101
        line 629: 132
        line 630: 152
        line 631: 155
      LocalVariableTable:
        Start  Length  Slot  Name   Signature
           44     108     3 currentSeal   Lext/mods/gameserver/enums/SealType;
           55      97     4 sealOwner   Lext/mods/gameserver/enums/CabalType;
           34     118     2 sealEntry   Ljava/util/Map$Entry;
            0     156     0  this   Lext/mods/gameserver/data/manager/SevenSignsManager;
      LocalVariableTypeTable:
        Start  Length  Slot  Name   Signature
           34     118     2 sealEntry   Ljava/util/Map$Entry<Lext/mods/gameserver/enums/SealType;Lext/mods/gameserver/enums/CabalType;>;
      StackMapTable: number_of_entries = 5
        frame_type = 252 /* append */
          offset_delta = 15
          locals = [ class java/util/Iterator ]
        frame_type = 254 /* append */
          offset_delta = 85
          locals = [ class java/util/Map$Entry, class ext/mods/gameserver/enums/SealType, class ext/mods/gameserver/enums/CabalType ]
        frame_type = 30 /* same */
        frame_type = 248 /* chop */
          offset_delta = 19
        frame_type = 250 /* chop */
          offset_delta = 2

  protected void resetSeals();
    descriptor: ()V
    flags: (0x0004) ACC_PROTECTED
    Code:
      stack=3, locals=1, args_size=1
         0: aload_0
         1: getfield      #42                 // Field _dawnScores:Ljava/util/Map;
         4: getstatic     #365                // Field ext/mods/gameserver/enums/SealType.AVARICE:Lext/mods/gameserver/enums/SealType;
         7: iconst_0
         8: invokestatic  #116                // Method java/lang/Integer.valueOf:(I)Ljava/lang/Integer;
        11: invokeinterface #336,  3          // InterfaceMethod java/util/Map.put:(Ljava/lang/Object;Ljava/lang/Object;)Ljava/lang/Object;
        16: pop
        17: aload_0
        18: getfield      #42                 // Field _dawnScores:Ljava/util/Map;
        21: getstatic     #370                // Field ext/mods/gameserver/enums/SealType.GNOSIS:Lext/mods/gameserver/enums/SealType;
        24: iconst_0
        25: invokestatic  #116                // Method java/lang/Integer.valueOf:(I)Ljava/lang/Integer;
        28: invokeinterface #336,  3          // InterfaceMethod java/util/Map.put:(Ljava/lang/Object;Ljava/lang/Object;)Ljava/lang/Object;
        33: pop
        34: aload_0
        35: getfield      #42                 // Field _dawnScores:Ljava/util/Map;
        38: getstatic     #375                // Field ext/mods/gameserver/enums/SealType.STRIFE:Lext/mods/gameserver/enums/SealType;
        41: iconst_0
        42: invokestatic  #116                // Method java/lang/Integer.valueOf:(I)Ljava/lang/Integer;
        45: invokeinterface #336,  3          // InterfaceMethod java/util/Map.put:(Ljava/lang/Object;Ljava/lang/Object;)Ljava/lang/Object;
        50: pop
        51: aload_0
        52: getfield      #39                 // Field _duskScores:Ljava/util/Map;
        55: getstatic     #365                // Field ext/mods/gameserver/enums/SealType.AVARICE:Lext/mods/gameserver/enums/SealType;
        58: iconst_0
        59: invokestatic  #116                // Method java/lang/Integer.valueOf:(I)Ljava/lang/Integer;
        62: invokeinterface #336,  3          // InterfaceMethod java/util/Map.put:(Ljava/lang/Object;Ljava/lang/Object;)Ljava/lang/Object;
        67: pop
        68: aload_0
        69: getfield      #39                 // Field _duskScores:Ljava/util/Map;
        72: getstatic     #370                // Field ext/mods/gameserver/enums/SealType.GNOSIS:Lext/mods/gameserver/enums/SealType;
        75: iconst_0
        76: invokestatic  #116                // Method java/lang/Integer.valueOf:(I)Ljava/lang/Integer;
        79: invokeinterface #336,  3          // InterfaceMethod java/util/Map.put:(Ljava/lang/Object;Ljava/lang/Object;)Ljava/lang/Object;
        84: pop
        85: aload_0
        86: getfield      #39                 // Field _duskScores:Ljava/util/Map;
        89: getstatic     #375                // Field ext/mods/gameserver/enums/SealType.STRIFE:Lext/mods/gameserver/enums/SealType;
        92: iconst_0
        93: invokestatic  #116                // Method java/lang/Integer.valueOf:(I)Ljava/lang/Integer;
        96: invokeinterface #336,  3          // InterfaceMethod java/util/Map.put:(Ljava/lang/Object;Ljava/lang/Object;)Ljava/lang/Object;
       101: pop
       102: return
      LineNumberTable:
        line 638: 0
        line 639: 17
        line 640: 34
        line 642: 51
        line 643: 68
        line 644: 85
        line 645: 102
      LocalVariableTable:
        Start  Length  Slot  Name   Signature
            0     103     0  this   Lext/mods/gameserver/data/manager/SevenSignsManager;

  protected void calcNewSealOwners();
    descriptor: ()V
    flags: (0x0004) ACC_PROTECTED
    Code:
      stack=3, locals=11, args_size=1
         0: aload_0
         1: getfield      #42                 // Field _dawnScores:Ljava/util/Map;
         4: invokeinterface #498,  1          // InterfaceMethod java/util/Map.keySet:()Ljava/util/Set;
         9: invokeinterface #474,  1          // InterfaceMethod java/util/Set.iterator:()Ljava/util/Iterator;
        14: astore_1
        15: aload_1
        16: invokeinterface #247,  1          // InterfaceMethod java/util/Iterator.hasNext:()Z
        21: ifeq          596
        24: aload_1
        25: invokeinterface #252,  1          // InterfaceMethod java/util/Iterator.next:()Ljava/lang/Object;
        30: checkcast     #31                 // class ext/mods/gameserver/enums/SealType
        33: astore_2
        34: aload_0
        35: getfield      #36                 // Field _sealOwners:Ljava/util/Map;
        38: aload_2
        39: invokeinterface #229,  2          // InterfaceMethod java/util/Map.get:(Ljava/lang/Object;)Ljava/lang/Object;
        44: checkcast     #197                // class ext/mods/gameserver/enums/CabalType
        47: astore_3
        48: aload_0
        49: aload_2
        50: getstatic     #223                // Field ext/mods/gameserver/enums/CabalType.DAWN:Lext/mods/gameserver/enums/CabalType;
        53: invokevirtual #501                // Method getSealProportion:(Lext/mods/gameserver/enums/SealType;Lext/mods/gameserver/enums/CabalType;)I
        56: istore        4
        58: iconst_1
        59: aload_0
        60: getstatic     #223                // Field ext/mods/gameserver/enums/CabalType.DAWN:Lext/mods/gameserver/enums/CabalType;
        63: invokevirtual #505                // Method getTotalMembers:(Lext/mods/gameserver/enums/CabalType;)I
        66: invokestatic  #508                // Method java/lang/Math.max:(II)I
        69: istore        5
        71: iload         4
        73: i2f
        74: iload         5
        76: i2f
        77: fdiv
        78: ldc_w         #512                // float 100.0f
        81: fmul
        82: invokestatic  #200                // Method java/lang/Math.round:(F)I
        85: istore        6
        87: aload_0
        88: aload_2
        89: getstatic     #216                // Field ext/mods/gameserver/enums/CabalType.DUSK:Lext/mods/gameserver/enums/CabalType;
        92: invokevirtual #501                // Method getSealProportion:(Lext/mods/gameserver/enums/SealType;Lext/mods/gameserver/enums/CabalType;)I
        95: istore        7
        97: iconst_1
        98: aload_0
        99: getstatic     #216                // Field ext/mods/gameserver/enums/CabalType.DUSK:Lext/mods/gameserver/enums/CabalType;
       102: invokevirtual #505                // Method getTotalMembers:(Lext/mods/gameserver/enums/CabalType;)I
       105: invokestatic  #508                // Method java/lang/Math.max:(II)I
       108: istore        8
       110: iload         7
       112: i2f
       113: iload         8
       115: i2f
       116: fdiv
       117: ldc_w         #512                // float 100.0f
       120: fmul
       121: invokestatic  #200                // Method java/lang/Math.round:(F)I
       124: istore        9
       126: getstatic     #226                // Field ext/mods/gameserver/enums/CabalType.NORMAL:Lext/mods/gameserver/enums/CabalType;
       129: astore        10
       131: getstatic     #193                // Field ext/mods/gameserver/data/manager/SevenSignsManager$1.$SwitchMap$ext$mods$gameserver$enums$CabalType:[I
       134: aload_3
       135: invokevirtual #196                // Method ext/mods/gameserver/enums/CabalType.ordinal:()I
       138: iaload
       139: tableswitch   { // 1 to 3

                       1: 230

                       2: 328

                       3: 164
                 default: 421
            }
       164: getstatic     #193                // Field ext/mods/gameserver/data/manager/SevenSignsManager$1.$SwitchMap$ext$mods$gameserver$enums$CabalType:[I
       167: aload_0
       168: invokevirtual #513                // Method getWinningCabal:()Lext/mods/gameserver/enums/CabalType;
       171: invokevirtual #196                // Method ext/mods/gameserver/enums/CabalType.ordinal:()I
       174: iaload
       175: lookupswitch  { // 2

                       1: 200

                       2: 215
                 default: 227
            }
       200: iload         6
       202: bipush        35
       204: if_icmplt     227
       207: getstatic     #223                // Field ext/mods/gameserver/enums/CabalType.DAWN:Lext/mods/gameserver/enums/CabalType;
       210: astore        10
       212: goto          227
       215: iload         9
       217: bipush        35
       219: if_icmplt     227
       222: getstatic     #216                // Field ext/mods/gameserver/enums/CabalType.DUSK:Lext/mods/gameserver/enums/CabalType;
       225: astore        10
       227: goto          421
       230: getstatic     #193                // Field ext/mods/gameserver/data/manager/SevenSignsManager$1.$SwitchMap$ext$mods$gameserver$enums$CabalType:[I
       233: aload_0
       234: invokevirtual #513                // Method getWinningCabal:()Lext/mods/gameserver/enums/CabalType;
       237: invokevirtual #196                // Method ext/mods/gameserver/enums/CabalType.ordinal:()I
       240: iaload
       241: tableswitch   { // 1 to 3

                       1: 283

                       2: 298

                       3: 268
                 default: 325
            }
       268: iload         6
       270: bipush        10
       272: if_icmplt     325
       275: getstatic     #223                // Field ext/mods/gameserver/enums/CabalType.DAWN:Lext/mods/gameserver/enums/CabalType;
       278: astore        10
       280: goto          325
       283: iload         6
       285: bipush        10
       287: if_icmplt     325
       290: getstatic     #223                // Field ext/mods/gameserver/enums/CabalType.DAWN:Lext/mods/gameserver/enums/CabalType;
       293: astore        10
       295: goto          325
       298: iload         9
       300: bipush        35
       302: if_icmplt     313
       305: getstatic     #216                // Field ext/mods/gameserver/enums/CabalType.DUSK:Lext/mods/gameserver/enums/CabalType;
       308: astore        10
       310: goto          325
       313: iload         6
       315: bipush        10
       317: if_icmplt     325
       320: getstatic     #223                // Field ext/mods/gameserver/enums/CabalType.DAWN:Lext/mods/gameserver/enums/CabalType;
       323: astore        10
       325: goto          421
       328: getstatic     #193                // Field ext/mods/gameserver/data/manager/SevenSignsManager$1.$SwitchMap$ext$mods$gameserver$enums$CabalType:[I
       331: aload_0
       332: invokevirtual #513                // Method getWinningCabal:()Lext/mods/gameserver/enums/CabalType;
       335: invokevirtual #196                // Method ext/mods/gameserver/enums/CabalType.ordinal:()I
       338: iaload
       339: tableswitch   { // 1 to 3

                       1: 379

                       2: 409

                       3: 364
                 default: 421
            }
       364: iload         9
       366: bipush        10
       368: if_icmplt     421
       371: getstatic     #216                // Field ext/mods/gameserver/enums/CabalType.DUSK:Lext/mods/gameserver/enums/CabalType;
       374: astore        10
       376: goto          421
       379: iload         6
       381: bipush        35
       383: if_icmplt     394
       386: getstatic     #223                // Field ext/mods/gameserver/enums/CabalType.DAWN:Lext/mods/gameserver/enums/CabalType;
       389: astore        10
       391: goto          421
       394: iload         9
       396: bipush        10
       398: if_icmplt     421
       401: getstatic     #216                // Field ext/mods/gameserver/enums/CabalType.DUSK:Lext/mods/gameserver/enums/CabalType;
       404: astore        10
       406: goto          421
       409: iload         9
       411: bipush        10
       413: if_icmplt     421
       416: getstatic     #216                // Field ext/mods/gameserver/enums/CabalType.DUSK:Lext/mods/gameserver/enums/CabalType;
       419: astore        10
       421: aload_0
       422: getfield      #36                 // Field _sealOwners:Ljava/util/Map;
       425: aload_2
       426: aload         10
       428: invokeinterface #336,  3          // InterfaceMethod java/util/Map.put:(Ljava/lang/Object;Ljava/lang/Object;)Ljava/lang/Object;
       433: pop
       434: getstatic     #517                // Field ext/mods/gameserver/data/manager/SevenSignsManager$1.$SwitchMap$ext$mods$gameserver$enums$SealType:[I
       437: aload_2
       438: invokevirtual #520                // Method ext/mods/gameserver/enums/SealType.ordinal:()I
       441: iaload
       442: tableswitch   { // 1 to 3

                       1: 468

                       2: 508

                       3: 548
                 default: 593
            }
       468: aload         10
       470: getstatic     #223                // Field ext/mods/gameserver/enums/CabalType.DAWN:Lext/mods/gameserver/enums/CabalType;
       473: if_acmpne     488
       476: getstatic     #521                // Field ext/mods/gameserver/network/SystemMessageId.DAWN_OBTAINED_AVARICE:Lext/mods/gameserver/network/SystemMessageId;
       479: invokestatic  #527                // Method ext/mods/gameserver/network/serverpackets/SystemMessage.getSystemMessage:(Lext/mods/gameserver/network/SystemMessageId;)Lext/mods/gameserver/network/serverpackets/SystemMessage;
       482: invokestatic  #533                // Method ext/mods/gameserver/model/World.toAllOnlinePlayers:(Lext/mods/gameserver/network/serverpackets/L2GameServerPacket;)V
       485: goto          593
       488: aload         10
       490: getstatic     #216                // Field ext/mods/gameserver/enums/CabalType.DUSK:Lext/mods/gameserver/enums/CabalType;
       493: if_acmpne     593
       496: getstatic     #539                // Field ext/mods/gameserver/network/SystemMessageId.DUSK_OBTAINED_AVARICE:Lext/mods/gameserver/network/SystemMessageId;
       499: invokestatic  #527                // Method ext/mods/gameserver/network/serverpackets/SystemMessage.getSystemMessage:(Lext/mods/gameserver/network/SystemMessageId;)Lext/mods/gameserver/network/serverpackets/SystemMessage;
       502: invokestatic  #533                // Method ext/mods/gameserver/model/World.toAllOnlinePlayers:(Lext/mods/gameserver/network/serverpackets/L2GameServerPacket;)V
       505: goto          593
       508: aload         10
       510: getstatic     #223                // Field ext/mods/gameserver/enums/CabalType.DAWN:Lext/mods/gameserver/enums/CabalType;
       513: if_acmpne     528
       516: getstatic     #542                // Field ext/mods/gameserver/network/SystemMessageId.DAWN_OBTAINED_GNOSIS:Lext/mods/gameserver/network/SystemMessageId;
       519: invokestatic  #527                // Method ext/mods/gameserver/network/serverpackets/SystemMessage.getSystemMessage:(Lext/mods/gameserver/network/SystemMessageId;)Lext/mods/gameserver/network/serverpackets/SystemMessage;
       522: invokestatic  #533                // Method ext/mods/gameserver/model/World.toAllOnlinePlayers:(Lext/mods/gameserver/network/serverpackets/L2GameServerPacket;)V
       525: goto          593
       528: aload         10
       530: getstatic     #216                // Field ext/mods/gameserver/enums/CabalType.DUSK:Lext/mods/gameserver/enums/CabalType;
       533: if_acmpne     593
       536: getstatic     #545                // Field ext/mods/gameserver/network/SystemMessageId.DUSK_OBTAINED_GNOSIS:Lext/mods/gameserver/network/SystemMessageId;
       539: invokestatic  #527                // Method ext/mods/gameserver/network/serverpackets/SystemMessage.getSystemMessage:(Lext/mods/gameserver/network/SystemMessageId;)Lext/mods/gameserver/network/serverpackets/SystemMessage;
       542: invokestatic  #533                // Method ext/mods/gameserver/model/World.toAllOnlinePlayers:(Lext/mods/gameserver/network/serverpackets/L2GameServerPacket;)V
       545: goto          593
       548: aload         10
       550: getstatic     #223                // Field ext/mods/gameserver/enums/CabalType.DAWN:Lext/mods/gameserver/enums/CabalType;
       553: if_acmpne     568
       556: getstatic     #548                // Field ext/mods/gameserver/network/SystemMessageId.DAWN_OBTAINED_STRIFE:Lext/mods/gameserver/network/SystemMessageId;
       559: invokestatic  #527                // Method ext/mods/gameserver/network/serverpackets/SystemMessage.getSystemMessage:(Lext/mods/gameserver/network/SystemMessageId;)Lext/mods/gameserver/network/serverpackets/SystemMessage;
       562: invokestatic  #533                // Method ext/mods/gameserver/model/World.toAllOnlinePlayers:(Lext/mods/gameserver/network/serverpackets/L2GameServerPacket;)V
       565: goto          585
       568: aload         10
       570: getstatic     #216                // Field ext/mods/gameserver/enums/CabalType.DUSK:Lext/mods/gameserver/enums/CabalType;
       573: if_acmpne     585
       576: getstatic     #551                // Field ext/mods/gameserver/network/SystemMessageId.DUSK_OBTAINED_STRIFE:Lext/mods/gameserver/network/SystemMessageId;
       579: invokestatic  #527                // Method ext/mods/gameserver/network/serverpackets/SystemMessage.getSystemMessage:(Lext/mods/gameserver/network/SystemMessageId;)Lext/mods/gameserver/network/serverpackets/SystemMessage;
       582: invokestatic  #533                // Method ext/mods/gameserver/model/World.toAllOnlinePlayers:(Lext/mods/gameserver/network/serverpackets/L2GameServerPacket;)V
       585: invokestatic  #554                // Method ext/mods/gameserver/data/manager/CastleManager.getInstance:()Lext/mods/gameserver/data/manager/CastleManager;
       588: aload         10
       590: invokevirtual #559                // Method ext/mods/gameserver/data/manager/CastleManager.validateTaxes:(Lext/mods/gameserver/enums/CabalType;)V
       593: goto          15
       596: return
      LineNumberTable:
        line 653: 0
        line 655: 34
        line 657: 48
        line 658: 58
        line 659: 71
        line 661: 87
        line 662: 97
        line 663: 110
        line 665: 126
        line 667: 131
        line 670: 164
        line 673: 200
        line 674: 207
        line 678: 215
        line 679: 222
        line 682: 227
        line 685: 230
        line 688: 268
        line 689: 275
        line 693: 283
        line 694: 290
        line 698: 298
        line 699: 305
        line 700: 313
        line 701: 320
        line 704: 325
        line 707: 328
        line 710: 364
        line 711: 371
        line 715: 379
        line 716: 386
        line 717: 394
        line 718: 401
        line 722: 409
        line 723: 416
        line 729: 421
        line 731: 434
        line 734: 468
        line 735: 476
        line 736: 488
        line 737: 496
        line 741: 508
        line 742: 516
        line 743: 528
        line 744: 536
        line 748: 548
        line 749: 556
        line 750: 568
        line 751: 576
        line 753: 585
        line 756: 593
        line 757: 596
      LocalVariableTable:
        Start  Length  Slot  Name   Signature
           48     545     3 prevSealOwner   Lext/mods/gameserver/enums/CabalType;
           58     535     4 dawnProportion   I
           71     522     5 totalDawnMembers   I
           87     506     6 dawnPercent   I
           97     496     7 duskProportion   I
          110     483     8 totalDuskMembers   I
          126     467     9 duskPercent   I
          131     462    10 newSealOwner   Lext/mods/gameserver/enums/CabalType;
           34     559     2  seal   Lext/mods/gameserver/enums/SealType;
            0     597     0  this   Lext/mods/gameserver/data/manager/SevenSignsManager;
      StackMapTable: number_of_entries = 26
        frame_type = 252 /* append */
          offset_delta = 15
          locals = [ class java/util/Iterator ]
        frame_type = 255 /* full_frame */
          offset_delta = 148
          locals = [ class ext/mods/gameserver/data/manager/SevenSignsManager, class java/util/Iterator, class ext/mods/gameserver/enums/SealType, class ext/mods/gameserver/enums/CabalType, int, int, int, int, int, int, class ext/mods/gameserver/enums/CabalType ]
          stack = []
        frame_type = 35 /* same */
        frame_type = 14 /* same */
        frame_type = 11 /* same */
        frame_type = 2 /* same */
        frame_type = 37 /* same */
        frame_type = 14 /* same */
        frame_type = 14 /* same */
        frame_type = 14 /* same */
        frame_type = 11 /* same */
        frame_type = 2 /* same */
        frame_type = 35 /* same */
        frame_type = 14 /* same */
        frame_type = 14 /* same */
        frame_type = 14 /* same */
        frame_type = 11 /* same */
        frame_type = 46 /* same */
        frame_type = 19 /* same */
        frame_type = 19 /* same */
        frame_type = 19 /* same */
        frame_type = 19 /* same */
        frame_type = 19 /* same */
        frame_type = 16 /* same */
        frame_type = 255 /* full_frame */
          offset_delta = 7
          locals = [ class ext/mods/gameserver/data/manager/SevenSignsManager, class java/util/Iterator ]
          stack = []
        frame_type = 250 /* chop */
          offset_delta = 2

  protected void teleLosingCabalFromDungeons(ext.mods.gameserver.enums.CabalType);
    descriptor: (Lext/mods/gameserver/enums/CabalType;)V
    flags: (0x0004) ACC_PROTECTED
    Code:
      stack=3, locals=6, args_size=2
         0: invokestatic  #563                // Method ext/mods/gameserver/model/World.getInstance:()Lext/mods/gameserver/model/World;
         3: invokevirtual #566                // Method ext/mods/gameserver/model/World.getPlayers:()Ljava/util/Collection;
         6: invokeinterface #241,  1          // InterfaceMethod java/util/Collection.iterator:()Ljava/util/Iterator;
        11: astore_2
        12: aload_2
        13: invokeinterface #247,  1          // InterfaceMethod java/util/Iterator.hasNext:()Z
        18: ifeq          138
        21: aload_2
        22: invokeinterface #252,  1          // InterfaceMethod java/util/Iterator.next:()Ljava/lang/Object;
        27: checkcast     #569                // class ext/mods/gameserver/model/actor/Player
        30: astore_3
        31: aload_3
        32: invokevirtual #571                // Method ext/mods/gameserver/model/actor/Player.isGM:()Z
        35: ifne          12
        38: aload_3
        39: invokevirtual #574                // Method ext/mods/gameserver/model/actor/Player.isIn7sDungeon:()Z
        42: ifne          48
        45: goto          12
        48: aload_0
        49: getfield      #25                 // Field _playersData:Ljava/util/Map;
        52: aload_3
        53: invokevirtual #577                // Method ext/mods/gameserver/model/actor/Player.getObjectId:()I
        56: invokestatic  #116                // Method java/lang/Integer.valueOf:(I)Ljava/lang/Integer;
        59: invokeinterface #229,  2          // InterfaceMethod java/util/Map.get:(Ljava/lang/Object;)Ljava/lang/Object;
        64: checkcast     #256                // class ext/mods/commons/data/StatSet
        67: astore        4
        69: aload         4
        71: ifnull        123
        74: aload         4
        76: ldc_w         #258                // String cabal
        79: ldc           #197                // class ext/mods/gameserver/enums/CabalType
        81: invokevirtual #260                // Method ext/mods/commons/data/StatSet.getEnum:(Ljava/lang/String;Ljava/lang/Class;)Ljava/lang/Enum;
        84: checkcast     #197                // class ext/mods/gameserver/enums/CabalType
        87: astore        5
        89: aload_0
        90: invokevirtual #485                // Method isSealValidationPeriod:()Z
        93: ifne          103
        96: aload_0
        97: invokevirtual #580                // Method isCompResultsPeriod:()Z
       100: ifeq          112
       103: aload         5
       105: aload_1
       106: if_acmpne     123
       109: goto          12
       112: aload         5
       114: getstatic     #226                // Field ext/mods/gameserver/enums/CabalType.NORMAL:Lext/mods/gameserver/enums/CabalType;
       117: if_acmpne     123
       120: goto          12
       123: aload_3
       124: getstatic     #583                // Field ext/mods/gameserver/enums/RestartType.TOWN:Lext/mods/gameserver/enums/RestartType;
       127: invokevirtual #589                // Method ext/mods/gameserver/model/actor/Player.teleportTo:(Lext/mods/gameserver/enums/RestartType;)V
       130: aload_3
       131: iconst_0
       132: invokevirtual #593                // Method ext/mods/gameserver/model/actor/Player.setIsIn7sDungeon:(Z)V
       135: goto          12
       138: return
      LineNumberTable:
        line 766: 0
        line 768: 31
        line 769: 45
        line 771: 48
        line 772: 69
        line 774: 74
        line 775: 89
        line 777: 103
        line 778: 109
        line 780: 112
        line 781: 120
        line 784: 123
        line 785: 130
        line 786: 135
        line 787: 138
      LocalVariableTable:
        Start  Length  Slot  Name   Signature
           89      34     5 playerCabal   Lext/mods/gameserver/enums/CabalType;
           69      66     4   set   Lext/mods/commons/data/StatSet;
           31     104     3 player   Lext/mods/gameserver/model/actor/Player;
            0     139     0  this   Lext/mods/gameserver/data/manager/SevenSignsManager;
            0     139     1 winningCabal   Lext/mods/gameserver/enums/CabalType;
      StackMapTable: number_of_entries = 6
        frame_type = 252 /* append */
          offset_delta = 12
          locals = [ class java/util/Iterator ]
        frame_type = 252 /* append */
          offset_delta = 35
          locals = [ class ext/mods/gameserver/model/actor/Player ]
        frame_type = 253 /* append */
          offset_delta = 54
          locals = [ class ext/mods/commons/data/StatSet, class ext/mods/gameserver/enums/CabalType ]
        frame_type = 8 /* same */
        frame_type = 250 /* chop */
          offset_delta = 10
        frame_type = 248 /* chop */
          offset_delta = 14

  public void giveSosEffect(ext.mods.gameserver.enums.CabalType);
    descriptor: (Lext/mods/gameserver/enums/CabalType;)V
    flags: (0x0001) ACC_PUBLIC
    Code:
      stack=3, locals=5, args_size=2
         0: invokestatic  #563                // Method ext/mods/gameserver/model/World.getInstance:()Lext/mods/gameserver/model/World;
         3: invokevirtual #566                // Method ext/mods/gameserver/model/World.getPlayers:()Ljava/util/Collection;
         6: invokeinterface #241,  1          // InterfaceMethod java/util/Collection.iterator:()Ljava/util/Iterator;
        11: astore_2
        12: aload_2
        13: invokeinterface #247,  1          // InterfaceMethod java/util/Iterator.hasNext:()Z
        18: ifeq          85
        21: aload_2
        22: invokeinterface #252,  1          // InterfaceMethod java/util/Iterator.next:()Ljava/lang/Object;
        27: checkcast     #569                // class ext/mods/gameserver/model/actor/Player
        30: astore_3
        31: aload_0
        32: aload_3
        33: invokevirtual #577                // Method ext/mods/gameserver/model/actor/Player.getObjectId:()I
        36: invokevirtual #466                // Method getPlayerCabal:(I)Lext/mods/gameserver/enums/CabalType;
        39: astore        4
        41: aload         4
        43: getstatic     #226                // Field ext/mods/gameserver/enums/CabalType.NORMAL:Lext/mods/gameserver/enums/CabalType;
        46: if_acmpeq     82
        49: aload         4
        51: aload_1
        52: if_acmpne     70
        55: aload_3
        56: getstatic     #597                // Field ext/mods/gameserver/data/SkillTable$FrequentSkill.THE_VICTOR_OF_WAR:Lext/mods/gameserver/data/SkillTable$FrequentSkill;
        59: invokevirtual #603                // Method ext/mods/gameserver/data/SkillTable$FrequentSkill.getSkill:()Lext/mods/gameserver/skills/L2Skill;
        62: iconst_0
        63: invokevirtual #607                // Method ext/mods/gameserver/model/actor/Player.addSkill:(Lext/mods/gameserver/skills/L2Skill;Z)Z
        66: pop
        67: goto          82
        70: aload_3
        71: getstatic     #611                // Field ext/mods/gameserver/data/SkillTable$FrequentSkill.THE_VANQUISHED_OF_WAR:Lext/mods/gameserver/data/SkillTable$FrequentSkill;
        74: invokevirtual #603                // Method ext/mods/gameserver/data/SkillTable$FrequentSkill.getSkill:()Lext/mods/gameserver/skills/L2Skill;
        77: iconst_0
        78: invokevirtual #607                // Method ext/mods/gameserver/model/actor/Player.addSkill:(Lext/mods/gameserver/skills/L2Skill;Z)Z
        81: pop
        82: goto          12
        85: return
      LineNumberTable:
        line 894: 0
        line 896: 31
        line 897: 41
        line 899: 49
        line 900: 55
        line 902: 70
        line 904: 82
        line 905: 85
      LocalVariableTable:
        Start  Length  Slot  Name   Signature
           41      41     4 cabal   Lext/mods/gameserver/enums/CabalType;
           31      51     3 player   Lext/mods/gameserver/model/actor/Player;
            0      86     0  this   Lext/mods/gameserver/data/manager/SevenSignsManager;
            0      86     1 strifeOwner   Lext/mods/gameserver/enums/CabalType;
      StackMapTable: number_of_entries = 4
        frame_type = 252 /* append */
          offset_delta = 12
          locals = [ class java/util/Iterator ]
        frame_type = 253 /* append */
          offset_delta = 57
          locals = [ class ext/mods/gameserver/model/actor/Player, class ext/mods/gameserver/enums/CabalType ]
        frame_type = 249 /* chop */
          offset_delta = 11
        frame_type = 250 /* chop */
          offset_delta = 2

  public void removeSosEffect();
    descriptor: ()V
    flags: (0x0001) ACC_PUBLIC
    Code:
      stack=3, locals=3, args_size=1
         0: invokestatic  #563                // Method ext/mods/gameserver/model/World.getInstance:()Lext/mods/gameserver/model/World;
         3: invokevirtual #566                // Method ext/mods/gameserver/model/World.getPlayers:()Ljava/util/Collection;
         6: invokeinterface #241,  1          // InterfaceMethod java/util/Collection.iterator:()Ljava/util/Iterator;
        11: astore_1
        12: aload_1
        13: invokeinterface #247,  1          // InterfaceMethod java/util/Iterator.hasNext:()Z
        18: ifeq          64
        21: aload_1
        22: invokeinterface #252,  1          // InterfaceMethod java/util/Iterator.next:()Ljava/lang/Object;
        27: checkcast     #569                // class ext/mods/gameserver/model/actor/Player
        30: astore_2
        31: aload_2
        32: getstatic     #597                // Field ext/mods/gameserver/data/SkillTable$FrequentSkill.THE_VICTOR_OF_WAR:Lext/mods/gameserver/data/SkillTable$FrequentSkill;
        35: invokevirtual #603                // Method ext/mods/gameserver/data/SkillTable$FrequentSkill.getSkill:()Lext/mods/gameserver/skills/L2Skill;
        38: invokevirtual #614                // Method ext/mods/gameserver/skills/L2Skill.getId:()I
        41: iconst_0
        42: invokevirtual #619                // Method ext/mods/gameserver/model/actor/Player.removeSkill:(IZ)Lext/mods/gameserver/skills/L2Skill;
        45: pop
        46: aload_2
        47: getstatic     #611                // Field ext/mods/gameserver/data/SkillTable$FrequentSkill.THE_VANQUISHED_OF_WAR:Lext/mods/gameserver/data/SkillTable$FrequentSkill;
        50: invokevirtual #603                // Method ext/mods/gameserver/data/SkillTable$FrequentSkill.getSkill:()Lext/mods/gameserver/skills/L2Skill;
        53: invokevirtual #614                // Method ext/mods/gameserver/skills/L2Skill.getId:()I
        56: iconst_0
        57: invokevirtual #619                // Method ext/mods/gameserver/model/actor/Player.removeSkill:(IZ)Lext/mods/gameserver/skills/L2Skill;
        60: pop
        61: goto          12
        64: return
      LineNumberTable:
        line 912: 0
        line 914: 31
        line 915: 46
        line 916: 61
        line 917: 64
      LocalVariableTable:
        Start  Length  Slot  Name   Signature
           31      30     2 player   Lext/mods/gameserver/model/actor/Player;
            0      65     0  this   Lext/mods/gameserver/data/manager/SevenSignsManager;
      StackMapTable: number_of_entries = 2
        frame_type = 252 /* append */
          offset_delta = 12
          locals = [ class java/util/Iterator ]
        frame_type = 250 /* chop */
          offset_delta = 51

  public void changePeriod();
    descriptor: ()V
    flags: (0x0001) ACC_PUBLIC
    Code:
      stack=3, locals=1, args_size=1
         0: new           #89                 // class ext/mods/gameserver/data/manager/SevenSignsManager$SevenSignsPeriodChange
         3: dup
         4: aload_0
         5: invokespecial #91                 // Method ext/mods/gameserver/data/manager/SevenSignsManager$SevenSignsPeriodChange."<init>":(Lext/mods/gameserver/data/manager/SevenSignsManager;)V
         8: ldc2_w        #623                // long 10l
        11: invokestatic  #94                 // Method ext/mods/commons/pool/ThreadPool.schedule:(Ljava/lang/Runnable;J)Ljava/util/concurrent/ScheduledFuture;
        14: pop
        15: return
      LineNumberTable:
        line 921: 0
        line 922: 15
      LocalVariableTable:
        Start  Length  Slot  Name   Signature
            0      16     0  this   Lext/mods/gameserver/data/manager/SevenSignsManager;

  public boolean allowCatacombsInAnyPeriod();
    descriptor: ()Z
    flags: (0x0001) ACC_PUBLIC
    Code:
      stack=1, locals=1, args_size=1
         0: getstatic     #625                // Field ext/mods/Config.CATACOMBS_IN_ANY_PERIOD:Z
         3: ireturn
      LineNumberTable:
        line 926: 0
      LocalVariableTable:
        Start  Length  Slot  Name   Signature
            0       4     0  this   Lext/mods/gameserver/data/manager/SevenSignsManager;

  public static ext.mods.gameserver.data.manager.SevenSignsManager getInstance();
    descriptor: ()Lext/mods/gameserver/data/manager/SevenSignsManager;
    flags: (0x0009) ACC_PUBLIC, ACC_STATIC
    Code:
      stack=1, locals=0, args_size=0
         0: getstatic     #629                // Field ext/mods/gameserver/data/manager/SevenSignsManager$SingletonHolder.INSTANCE:Lext/mods/gameserver/data/manager/SevenSignsManager;
         3: areturn
      LineNumberTable:
        line 931: 0

  static {};
    descriptor: ()V
    flags: (0x0008) ACC_STATIC
    Code:
      stack=3, locals=0, args_size=0
         0: new           #65                 // class ext/mods/commons/logging/CLogger
         3: dup
         4: ldc           #3                  // class ext/mods/gameserver/data/manager/SevenSignsManager
         6: invokevirtual #635                // Method java/lang/Class.getName:()Ljava/lang/String;
         9: invokespecial #638                // Method ext/mods/commons/logging/CLogger."<init>":(Ljava/lang/String;)V
        12: putstatic     #48                 // Field LOGGER:Lext/mods/commons/logging/CLogger;
        15: return
      LineNumberTable:
        line 49: 0
}
SourceFile: "SevenSignsManager.java"
NestMembers:
  ext/mods/gameserver/data/manager/SevenSignsManager$1
  ext/mods/gameserver/data/manager/SevenSignsManager$SingletonHolder
  ext/mods/gameserver/data/manager/SevenSignsManager$SevenSignsPeriodChange
InnerClasses:
  protected #777= #89 of #3;              // SevenSignsPeriodChange=class ext/mods/gameserver/data/manager/SevenSignsManager$SevenSignsPeriodChange of class ext/mods/gameserver/data/manager/SevenSignsManager
  static #123;                            // class ext/mods/gameserver/data/manager/SevenSignsManager$1
  public static #778= #477 of #230;       // Entry=class java/util/Map$Entry of class java/util/Map
  public static final #781= #598 of #779; // FrequentSkill=class ext/mods/gameserver/data/SkillTable$FrequentSkill of class ext/mods/gameserver/data/SkillTable
