// Bytecode for: ext.mods.gameserver.data.manager.SevenSignsManager$SevenSignsPeriodChange
// File: ext\mods\gameserver\data\manager\SevenSignsManager$SevenSignsPeriodChange.class

Classfile /c:/Users/User/Desktop/BrProject/bin/main/ext/mods/gameserver/data/manager/SevenSignsManager$SevenSignsPeriodChange.class
  Last modified 9 de jul de 2026; size 5151 bytes
  MD5 checksum 3a54751f8b4485dbe36e967ccac07a83
  Compiled from "SevenSignsManager.java"
public class ext.mods.gameserver.data.manager.SevenSignsManager$SevenSignsPeriodChange implements java.lang.Runnable
  minor version: 0
  major version: 69
  flags: (0x0021) ACC_PUBLIC, ACC_SUPER
  this_class: #8                          // ext/mods/gameserver/data/manager/SevenSignsManager$SevenSignsPeriodChange
  super_class: #14                        // java/lang/Object
  interfaces: 1, fields: 1, methods: 2, attributes: 3
Constant pool:
    #1 = Methodref          #2.#3         // java/util/Objects.requireNonNull:(Ljava/lang/Object;)Ljava/lang/Object;
    #2 = Class              #4            // java/util/Objects
    #3 = NameAndType        #5:#6         // requireNonNull:(Ljava/lang/Object;)Ljava/lang/Object;
    #4 = Utf8               java/util/Objects
    #5 = Utf8               requireNonNull
    #6 = Utf8               (Ljava/lang/Object;)Ljava/lang/Object;
    #7 = Fieldref           #8.#9         // ext/mods/gameserver/data/manager/SevenSignsManager$SevenSignsPeriodChange.this$0:Lext/mods/gameserver/data/manager/SevenSignsManager;
    #8 = Class              #10           // ext/mods/gameserver/data/manager/SevenSignsManager$SevenSignsPeriodChange
    #9 = NameAndType        #11:#12       // this$0:Lext/mods/gameserver/data/manager/SevenSignsManager;
   #10 = Utf8               ext/mods/gameserver/data/manager/SevenSignsManager$SevenSignsPeriodChange
   #11 = Utf8               this$0
   #12 = Utf8               Lext/mods/gameserver/data/manager/SevenSignsManager;
   #13 = Methodref          #14.#15       // java/lang/Object."<init>":()V
   #14 = Class              #16           // java/lang/Object
   #15 = NameAndType        #17:#18       // "<init>":()V
   #16 = Utf8               java/lang/Object
   #17 = Utf8               <init>
   #18 = Utf8               ()V
   #19 = Fieldref           #20.#21       // ext/mods/gameserver/data/manager/SevenSignsManager._activePeriod:Lext/mods/gameserver/enums/PeriodType;
   #20 = Class              #22           // ext/mods/gameserver/data/manager/SevenSignsManager
   #21 = NameAndType        #23:#24       // _activePeriod:Lext/mods/gameserver/enums/PeriodType;
   #22 = Utf8               ext/mods/gameserver/data/manager/SevenSignsManager
   #23 = Utf8               _activePeriod
   #24 = Utf8               Lext/mods/gameserver/enums/PeriodType;
   #25 = Fieldref           #26.#27       // ext/mods/gameserver/enums/PeriodType.VALUES:[Lext/mods/gameserver/enums/PeriodType;
   #26 = Class              #28           // ext/mods/gameserver/enums/PeriodType
   #27 = NameAndType        #29:#30       // VALUES:[Lext/mods/gameserver/enums/PeriodType;
   #28 = Utf8               ext/mods/gameserver/enums/PeriodType
   #29 = Utf8               VALUES
   #30 = Utf8               [Lext/mods/gameserver/enums/PeriodType;
   #31 = Methodref          #26.#32       // ext/mods/gameserver/enums/PeriodType.ordinal:()I
   #32 = NameAndType        #33:#34       // ordinal:()I
   #33 = Utf8               ordinal
   #34 = Utf8               ()I
   #35 = Fieldref           #36.#37       // ext/mods/gameserver/data/manager/SevenSignsManager$1.$SwitchMap$ext$mods$gameserver$enums$PeriodType:[I
   #36 = Class              #38           // ext/mods/gameserver/data/manager/SevenSignsManager$1
   #37 = NameAndType        #39:#40       // $SwitchMap$ext$mods$gameserver$enums$PeriodType:[I
   #38 = Utf8               ext/mods/gameserver/data/manager/SevenSignsManager$1
   #39 = Utf8               $SwitchMap$ext$mods$gameserver$enums$PeriodType
   #40 = Utf8               [I
   #41 = Methodref          #42.#43       // ext/mods/gameserver/data/manager/FestivalOfDarknessManager.getInstance:()Lext/mods/gameserver/data/manager/FestivalOfDarknessManager;
   #42 = Class              #44           // ext/mods/gameserver/data/manager/FestivalOfDarknessManager
   #43 = NameAndType        #45:#46       // getInstance:()Lext/mods/gameserver/data/manager/FestivalOfDarknessManager;
   #44 = Utf8               ext/mods/gameserver/data/manager/FestivalOfDarknessManager
   #45 = Utf8               getInstance
   #46 = Utf8               ()Lext/mods/gameserver/data/manager/FestivalOfDarknessManager;
   #47 = Methodref          #42.#48       // ext/mods/gameserver/data/manager/FestivalOfDarknessManager.startFestivalManager:()V
   #48 = NameAndType        #49:#18       // startFestivalManager:()V
   #49 = Utf8               startFestivalManager
   #50 = Methodref          #51.#52       // ext/mods/gameserver/data/manager/CastleManager.getInstance:()Lext/mods/gameserver/data/manager/CastleManager;
   #51 = Class              #53           // ext/mods/gameserver/data/manager/CastleManager
   #52 = NameAndType        #45:#54       // getInstance:()Lext/mods/gameserver/data/manager/CastleManager;
   #53 = Utf8               ext/mods/gameserver/data/manager/CastleManager
   #54 = Utf8               ()Lext/mods/gameserver/data/manager/CastleManager;
   #55 = Methodref          #51.#56       // ext/mods/gameserver/data/manager/CastleManager.resetCertificates:()V
   #56 = NameAndType        #57:#18       // resetCertificates:()V
   #57 = Utf8               resetCertificates
   #58 = Class              #59           // ext/mods/gameserver/network/serverpackets/PlaySound
   #59 = Utf8               ext/mods/gameserver/network/serverpackets/PlaySound
   #60 = String             #61           // SSQ_Neutral_01
   #61 = Utf8               SSQ_Neutral_01
   #62 = Methodref          #58.#63       // ext/mods/gameserver/network/serverpackets/PlaySound."<init>":(ILjava/lang/String;)V
   #63 = NameAndType        #17:#64       // "<init>":(ILjava/lang/String;)V
   #64 = Utf8               (ILjava/lang/String;)V
   #65 = Methodref          #66.#67       // ext/mods/gameserver/model/World.toAllOnlinePlayers:(Lext/mods/gameserver/network/serverpackets/L2GameServerPacket;)V
   #66 = Class              #68           // ext/mods/gameserver/model/World
   #67 = NameAndType        #69:#70       // toAllOnlinePlayers:(Lext/mods/gameserver/network/serverpackets/L2GameServerPacket;)V
   #68 = Utf8               ext/mods/gameserver/model/World
   #69 = Utf8               toAllOnlinePlayers
   #70 = Utf8               (Lext/mods/gameserver/network/serverpackets/L2GameServerPacket;)V
   #71 = Fieldref           #72.#73       // ext/mods/gameserver/network/SystemMessageId.QUEST_EVENT_PERIOD_BEGUN:Lext/mods/gameserver/network/SystemMessageId;
   #72 = Class              #74           // ext/mods/gameserver/network/SystemMessageId
   #73 = NameAndType        #75:#76       // QUEST_EVENT_PERIOD_BEGUN:Lext/mods/gameserver/network/SystemMessageId;
   #74 = Utf8               ext/mods/gameserver/network/SystemMessageId
   #75 = Utf8               QUEST_EVENT_PERIOD_BEGUN
   #76 = Utf8               Lext/mods/gameserver/network/SystemMessageId;
   #77 = Methodref          #78.#79       // ext/mods/gameserver/network/serverpackets/SystemMessage.getSystemMessage:(Lext/mods/gameserver/network/SystemMessageId;)Lext/mods/gameserver/network/serverpackets/SystemMessage;
   #78 = Class              #80           // ext/mods/gameserver/network/serverpackets/SystemMessage
   #79 = NameAndType        #81:#82       // getSystemMessage:(Lext/mods/gameserver/network/SystemMessageId;)Lext/mods/gameserver/network/serverpackets/SystemMessage;
   #80 = Utf8               ext/mods/gameserver/network/serverpackets/SystemMessage
   #81 = Utf8               getSystemMessage
   #82 = Utf8               (Lext/mods/gameserver/network/SystemMessageId;)Lext/mods/gameserver/network/serverpackets/SystemMessage;
   #83 = Fieldref           #72.#84       // ext/mods/gameserver/network/SystemMessageId.QUEST_EVENT_PERIOD_ENDED:Lext/mods/gameserver/network/SystemMessageId;
   #84 = NameAndType        #85:#76       // QUEST_EVENT_PERIOD_ENDED:Lext/mods/gameserver/network/SystemMessageId;
   #85 = Utf8               QUEST_EVENT_PERIOD_ENDED
   #86 = Methodref          #20.#87       // ext/mods/gameserver/data/manager/SevenSignsManager.getWinningCabal:()Lext/mods/gameserver/enums/CabalType;
   #87 = NameAndType        #88:#89       // getWinningCabal:()Lext/mods/gameserver/enums/CabalType;
   #88 = Utf8               getWinningCabal
   #89 = Utf8               ()Lext/mods/gameserver/enums/CabalType;
   #90 = Methodref          #42.#91       // ext/mods/gameserver/data/manager/FestivalOfDarknessManager.rewardHighestRanked:()V
   #91 = NameAndType        #92:#18       // rewardHighestRanked:()V
   #92 = Utf8               rewardHighestRanked
   #93 = Methodref          #20.#94       // ext/mods/gameserver/data/manager/SevenSignsManager.calcNewSealOwners:()V
   #94 = NameAndType        #95:#18       // calcNewSealOwners:()V
   #95 = Utf8               calcNewSealOwners
   #96 = Fieldref           #36.#97       // ext/mods/gameserver/data/manager/SevenSignsManager$1.$SwitchMap$ext$mods$gameserver$enums$CabalType:[I
   #97 = NameAndType        #98:#40       // $SwitchMap$ext$mods$gameserver$enums$CabalType:[I
   #98 = Utf8               $SwitchMap$ext$mods$gameserver$enums$CabalType
   #99 = Methodref          #100.#32      // ext/mods/gameserver/enums/CabalType.ordinal:()I
  #100 = Class              #101          // ext/mods/gameserver/enums/CabalType
  #101 = Utf8               ext/mods/gameserver/enums/CabalType
  #102 = Fieldref           #72.#103      // ext/mods/gameserver/network/SystemMessageId.DAWN_WON:Lext/mods/gameserver/network/SystemMessageId;
  #103 = NameAndType        #104:#76      // DAWN_WON:Lext/mods/gameserver/network/SystemMessageId;
  #104 = Utf8               DAWN_WON
  #105 = Fieldref           #72.#106      // ext/mods/gameserver/network/SystemMessageId.DUSK_WON:Lext/mods/gameserver/network/SystemMessageId;
  #106 = NameAndType        #107:#76      // DUSK_WON:Lext/mods/gameserver/network/SystemMessageId;
  #107 = Utf8               DUSK_WON
  #108 = Fieldref           #20.#109      // ext/mods/gameserver/data/manager/SevenSignsManager._previousWinner:Lext/mods/gameserver/enums/CabalType;
  #109 = NameAndType        #110:#111     // _previousWinner:Lext/mods/gameserver/enums/CabalType;
  #110 = Utf8               _previousWinner
  #111 = Utf8               Lext/mods/gameserver/enums/CabalType;
  #112 = Methodref          #20.#113      // ext/mods/gameserver/data/manager/SevenSignsManager.initializeSeals:()V
  #113 = NameAndType        #114:#18      // initializeSeals:()V
  #114 = Utf8               initializeSeals
  #115 = Fieldref           #116.#117     // ext/mods/gameserver/enums/SealType.STRIFE:Lext/mods/gameserver/enums/SealType;
  #116 = Class              #118          // ext/mods/gameserver/enums/SealType
  #117 = NameAndType        #119:#120     // STRIFE:Lext/mods/gameserver/enums/SealType;
  #118 = Utf8               ext/mods/gameserver/enums/SealType
  #119 = Utf8               STRIFE
  #120 = Utf8               Lext/mods/gameserver/enums/SealType;
  #121 = Methodref          #20.#122      // ext/mods/gameserver/data/manager/SevenSignsManager.getSealOwner:(Lext/mods/gameserver/enums/SealType;)Lext/mods/gameserver/enums/CabalType;
  #122 = NameAndType        #123:#124     // getSealOwner:(Lext/mods/gameserver/enums/SealType;)Lext/mods/gameserver/enums/CabalType;
  #123 = Utf8               getSealOwner
  #124 = Utf8               (Lext/mods/gameserver/enums/SealType;)Lext/mods/gameserver/enums/CabalType;
  #125 = Methodref          #20.#126      // ext/mods/gameserver/data/manager/SevenSignsManager.giveSosEffect:(Lext/mods/gameserver/enums/CabalType;)V
  #126 = NameAndType        #127:#128     // giveSosEffect:(Lext/mods/gameserver/enums/CabalType;)V
  #127 = Utf8               giveSosEffect
  #128 = Utf8               (Lext/mods/gameserver/enums/CabalType;)V
  #129 = Fieldref           #100.#130     // ext/mods/gameserver/enums/CabalType.DAWN:Lext/mods/gameserver/enums/CabalType;
  #130 = NameAndType        #131:#111     // DAWN:Lext/mods/gameserver/enums/CabalType;
  #131 = Utf8               DAWN
  #132 = String             #133          // SSQ_Dawn_01
  #133 = Utf8               SSQ_Dawn_01
  #134 = String             #135          // SSQ_Dusk_01
  #135 = Utf8               SSQ_Dusk_01
  #136 = Fieldref           #72.#137      // ext/mods/gameserver/network/SystemMessageId.SEAL_VALIDATION_PERIOD_BEGUN:Lext/mods/gameserver/network/SystemMessageId;
  #137 = NameAndType        #138:#76      // SEAL_VALIDATION_PERIOD_BEGUN:Lext/mods/gameserver/network/SystemMessageId;
  #138 = Utf8               SEAL_VALIDATION_PERIOD_BEGUN
  #139 = Fieldref           #20.#140      // ext/mods/gameserver/data/manager/SevenSignsManager.LOGGER:Lext/mods/commons/logging/CLogger;
  #140 = NameAndType        #141:#142     // LOGGER:Lext/mods/commons/logging/CLogger;
  #141 = Utf8               LOGGER
  #142 = Utf8               Lext/mods/commons/logging/CLogger;
  #143 = String             #144          // The {} have won the competition with {} points.
  #144 = Utf8               The {} have won the competition with {} points.
  #145 = Methodref          #100.#146     // ext/mods/gameserver/enums/CabalType.getFullName:()Ljava/lang/String;
  #146 = NameAndType        #147:#148     // getFullName:()Ljava/lang/String;
  #147 = Utf8               getFullName
  #148 = Utf8               ()Ljava/lang/String;
  #149 = Methodref          #20.#150      // ext/mods/gameserver/data/manager/SevenSignsManager.getCurrentScore:(Lext/mods/gameserver/enums/CabalType;)I
  #150 = NameAndType        #151:#152     // getCurrentScore:(Lext/mods/gameserver/enums/CabalType;)I
  #151 = Utf8               getCurrentScore
  #152 = Utf8               (Lext/mods/gameserver/enums/CabalType;)I
  #153 = Methodref          #154.#155     // java/lang/Integer.valueOf:(I)Ljava/lang/Integer;
  #154 = Class              #156          // java/lang/Integer
  #155 = NameAndType        #157:#158     // valueOf:(I)Ljava/lang/Integer;
  #156 = Utf8               java/lang/Integer
  #157 = Utf8               valueOf
  #158 = Utf8               (I)Ljava/lang/Integer;
  #159 = Methodref          #160.#161     // ext/mods/commons/logging/CLogger.info:(Ljava/lang/Object;[Ljava/lang/Object;)V
  #160 = Class              #162          // ext/mods/commons/logging/CLogger
  #161 = NameAndType        #163:#164     // info:(Ljava/lang/Object;[Ljava/lang/Object;)V
  #162 = Utf8               ext/mods/commons/logging/CLogger
  #163 = Utf8               info
  #164 = Utf8               (Ljava/lang/Object;[Ljava/lang/Object;)V
  #165 = Fieldref           #26.#166      // ext/mods/gameserver/enums/PeriodType.RECRUITING:Lext/mods/gameserver/enums/PeriodType;
  #166 = NameAndType        #167:#24      // RECRUITING:Lext/mods/gameserver/enums/PeriodType;
  #167 = Utf8               RECRUITING
  #168 = Fieldref           #72.#169      // ext/mods/gameserver/network/SystemMessageId.SEAL_VALIDATION_PERIOD_ENDED:Lext/mods/gameserver/network/SystemMessageId;
  #169 = NameAndType        #170:#76      // SEAL_VALIDATION_PERIOD_ENDED:Lext/mods/gameserver/network/SystemMessageId;
  #170 = Utf8               SEAL_VALIDATION_PERIOD_ENDED
  #171 = Methodref          #20.#172      // ext/mods/gameserver/data/manager/SevenSignsManager.removeSosEffect:()V
  #172 = NameAndType        #173:#18      // removeSosEffect:()V
  #173 = Utf8               removeSosEffect
  #174 = Methodref          #20.#175      // ext/mods/gameserver/data/manager/SevenSignsManager.resetPlayerData:()V
  #175 = NameAndType        #176:#18      // resetPlayerData:()V
  #176 = Utf8               resetPlayerData
  #177 = Methodref          #20.#178      // ext/mods/gameserver/data/manager/SevenSignsManager.resetSeals:()V
  #178 = NameAndType        #179:#18      // resetSeals:()V
  #179 = Utf8               resetSeals
  #180 = Fieldref           #20.#181      // ext/mods/gameserver/data/manager/SevenSignsManager._currentCycle:I
  #181 = NameAndType        #182:#183     // _currentCycle:I
  #182 = Utf8               _currentCycle
  #183 = Utf8               I
  #184 = Methodref          #42.#185      // ext/mods/gameserver/data/manager/FestivalOfDarknessManager.resetFestivalData:(Z)V
  #185 = NameAndType        #186:#187     // resetFestivalData:(Z)V
  #186 = Utf8               resetFestivalData
  #187 = Utf8               (Z)V
  #188 = Fieldref           #20.#189      // ext/mods/gameserver/data/manager/SevenSignsManager._dawnStoneScore:D
  #189 = NameAndType        #190:#191     // _dawnStoneScore:D
  #190 = Utf8               _dawnStoneScore
  #191 = Utf8               D
  #192 = Fieldref           #20.#193      // ext/mods/gameserver/data/manager/SevenSignsManager._duskStoneScore:D
  #193 = NameAndType        #194:#191     // _duskStoneScore:D
  #194 = Utf8               _duskStoneScore
  #195 = Methodref          #20.#196      // ext/mods/gameserver/data/manager/SevenSignsManager.saveSevenSignsData:()V
  #196 = NameAndType        #197:#18      // saveSevenSignsData:()V
  #197 = Utf8               saveSevenSignsData
  #198 = Methodref          #20.#199      // ext/mods/gameserver/data/manager/SevenSignsManager.saveSevenSignsStatus:()V
  #199 = NameAndType        #200:#18      // saveSevenSignsStatus:()V
  #200 = Utf8               saveSevenSignsStatus
  #201 = Fieldref           #202.#203     // ext/mods/Config.CATACOMBS_IN_ANY_PERIOD:Z
  #202 = Class              #204          // ext/mods/Config
  #203 = NameAndType        #205:#206     // CATACOMBS_IN_ANY_PERIOD:Z
  #204 = Utf8               ext/mods/Config
  #205 = Utf8               CATACOMBS_IN_ANY_PERIOD
  #206 = Utf8               Z
  #207 = Methodref          #20.#208      // ext/mods/gameserver/data/manager/SevenSignsManager.teleLosingCabalFromDungeons:(Lext/mods/gameserver/enums/CabalType;)V
  #208 = NameAndType        #209:#128     // teleLosingCabalFromDungeons:(Lext/mods/gameserver/enums/CabalType;)V
  #209 = Utf8               teleLosingCabalFromDungeons
  #210 = Methodref          #211.#212     // ext/mods/gameserver/network/serverpackets/SSQInfo.sendSky:()Lext/mods/gameserver/network/serverpackets/SSQInfo;
  #211 = Class              #213          // ext/mods/gameserver/network/serverpackets/SSQInfo
  #212 = NameAndType        #214:#215     // sendSky:()Lext/mods/gameserver/network/serverpackets/SSQInfo;
  #213 = Utf8               ext/mods/gameserver/network/serverpackets/SSQInfo
  #214 = Utf8               sendSky
  #215 = Utf8               ()Lext/mods/gameserver/network/serverpackets/SSQInfo;
  #216 = Methodref          #217.#218     // ext/mods/gameserver/data/manager/SpawnManager.getInstance:()Lext/mods/gameserver/data/manager/SpawnManager;
  #217 = Class              #219          // ext/mods/gameserver/data/manager/SpawnManager
  #218 = NameAndType        #45:#220      // getInstance:()Lext/mods/gameserver/data/manager/SpawnManager;
  #219 = Utf8               ext/mods/gameserver/data/manager/SpawnManager
  #220 = Utf8               ()Lext/mods/gameserver/data/manager/SpawnManager;
  #221 = Methodref          #217.#222     // ext/mods/gameserver/data/manager/SpawnManager.notifySevenSignsChange:()V
  #222 = NameAndType        #223:#18      // notifySevenSignsChange:()V
  #223 = Utf8               notifySevenSignsChange
  #224 = String             #225          // The {} period of Seven Signs has begun.
  #225 = Utf8               The {} period of Seven Signs has begun.
  #226 = Methodref          #26.#227      // ext/mods/gameserver/enums/PeriodType.getName:()Ljava/lang/String;
  #227 = NameAndType        #228:#148     // getName:()Ljava/lang/String;
  #228 = Utf8               getName
  #229 = Methodref          #20.#230      // ext/mods/gameserver/data/manager/SevenSignsManager.setCalendarForNextPeriodChange:()V
  #230 = NameAndType        #231:#18      // setCalendarForNextPeriodChange:()V
  #231 = Utf8               setCalendarForNextPeriodChange
  #232 = Methodref          #8.#233       // ext/mods/gameserver/data/manager/SevenSignsManager$SevenSignsPeriodChange."<init>":(Lext/mods/gameserver/data/manager/SevenSignsManager;)V
  #233 = NameAndType        #17:#234      // "<init>":(Lext/mods/gameserver/data/manager/SevenSignsManager;)V
  #234 = Utf8               (Lext/mods/gameserver/data/manager/SevenSignsManager;)V
  #235 = Methodref          #20.#236      // ext/mods/gameserver/data/manager/SevenSignsManager.getMilliToPeriodChange:()J
  #236 = NameAndType        #237:#238     // getMilliToPeriodChange:()J
  #237 = Utf8               getMilliToPeriodChange
  #238 = Utf8               ()J
  #239 = Methodref          #240.#241     // ext/mods/commons/pool/ThreadPool.schedule:(Ljava/lang/Runnable;J)Ljava/util/concurrent/ScheduledFuture;
  #240 = Class              #242          // ext/mods/commons/pool/ThreadPool
  #241 = NameAndType        #243:#244     // schedule:(Ljava/lang/Runnable;J)Ljava/util/concurrent/ScheduledFuture;
  #242 = Utf8               ext/mods/commons/pool/ThreadPool
  #243 = Utf8               schedule
  #244 = Utf8               (Ljava/lang/Runnable;J)Ljava/util/concurrent/ScheduledFuture;
  #245 = Class              #246          // java/lang/Runnable
  #246 = Utf8               java/lang/Runnable
  #247 = Utf8               Code
  #248 = Utf8               LineNumberTable
  #249 = Utf8               LocalVariableTable
  #250 = Utf8               this
  #251 = Utf8               Lext/mods/gameserver/data/manager/SevenSignsManager$SevenSignsPeriodChange;
  #252 = Utf8               MethodParameters
  #253 = Utf8               run
  #254 = Utf8               winningCabal
  #255 = Utf8               periodEnded
  #256 = Utf8               StackMapTable
  #257 = Class              #258          // java/lang/String
  #258 = Utf8               java/lang/String
  #259 = Utf8               SourceFile
  #260 = Utf8               SevenSignsManager.java
  #261 = Utf8               NestHost
  #262 = Utf8               InnerClasses
  #263 = Utf8               SevenSignsPeriodChange
{
  final ext.mods.gameserver.data.manager.SevenSignsManager this$0;
    descriptor: Lext/mods/gameserver/data/manager/SevenSignsManager;
    flags: (0x1010) ACC_FINAL, ACC_SYNTHETIC

  protected ext.mods.gameserver.data.manager.SevenSignsManager$SevenSignsPeriodChange(ext.mods.gameserver.data.manager.SevenSignsManager);
    descriptor: (Lext/mods/gameserver/data/manager/SevenSignsManager;)V
    flags: (0x0004) ACC_PROTECTED
    Code:
      stack=3, locals=2, args_size=2
         0: aload_0
         1: aload_1
         2: dup
         3: invokestatic  #1                  // Method java/util/Objects.requireNonNull:(Ljava/lang/Object;)Ljava/lang/Object;
         6: pop
         7: putfield      #7                  // Field this$0:Lext/mods/gameserver/data/manager/SevenSignsManager;
        10: aload_0
        11: invokespecial #13                 // Method java/lang/Object."<init>":()V
        14: return
      LineNumberTable:
        line 792: 0
      LocalVariableTable:
        Start  Length  Slot  Name   Signature
            0      15     0  this   Lext/mods/gameserver/data/manager/SevenSignsManager$SevenSignsPeriodChange;
            0      15     1 this$0   Lext/mods/gameserver/data/manager/SevenSignsManager;
    MethodParameters:
      Name                           Flags
      <no name>                      final mandated

  public void run();
    descriptor: ()V
    flags: (0x0001) ACC_PUBLIC
    Code:
      stack=7, locals=3, args_size=1
         0: aload_0
         1: getfield      #7                  // Field this$0:Lext/mods/gameserver/data/manager/SevenSignsManager;
         4: getfield      #19                 // Field ext/mods/gameserver/data/manager/SevenSignsManager._activePeriod:Lext/mods/gameserver/enums/PeriodType;
         7: astore_1
         8: aload_0
         9: getfield      #7                  // Field this$0:Lext/mods/gameserver/data/manager/SevenSignsManager;
        12: getstatic     #25                 // Field ext/mods/gameserver/enums/PeriodType.VALUES:[Lext/mods/gameserver/enums/PeriodType;
        15: aload_0
        16: getfield      #7                  // Field this$0:Lext/mods/gameserver/data/manager/SevenSignsManager;
        19: getfield      #19                 // Field ext/mods/gameserver/data/manager/SevenSignsManager._activePeriod:Lext/mods/gameserver/enums/PeriodType;
        22: invokevirtual #31                 // Method ext/mods/gameserver/enums/PeriodType.ordinal:()I
        25: iconst_1
        26: iadd
        27: getstatic     #25                 // Field ext/mods/gameserver/enums/PeriodType.VALUES:[Lext/mods/gameserver/enums/PeriodType;
        30: arraylength
        31: irem
        32: aaload
        33: putfield      #19                 // Field ext/mods/gameserver/data/manager/SevenSignsManager._activePeriod:Lext/mods/gameserver/enums/PeriodType;
        36: getstatic     #35                 // Field ext/mods/gameserver/data/manager/SevenSignsManager$1.$SwitchMap$ext$mods$gameserver$enums$PeriodType:[I
        39: aload_1
        40: invokevirtual #31                 // Method ext/mods/gameserver/enums/PeriodType.ordinal:()I
        43: iaload
        44: tableswitch   { // 1 to 4

                       1: 336

                       2: 113

                       3: 76

                       4: 224
                 default: 425
            }
        76: invokestatic  #41                 // Method ext/mods/gameserver/data/manager/FestivalOfDarknessManager.getInstance:()Lext/mods/gameserver/data/manager/FestivalOfDarknessManager;
        79: invokevirtual #47                 // Method ext/mods/gameserver/data/manager/FestivalOfDarknessManager.startFestivalManager:()V
        82: invokestatic  #50                 // Method ext/mods/gameserver/data/manager/CastleManager.getInstance:()Lext/mods/gameserver/data/manager/CastleManager;
        85: invokevirtual #55                 // Method ext/mods/gameserver/data/manager/CastleManager.resetCertificates:()V
        88: new           #58                 // class ext/mods/gameserver/network/serverpackets/PlaySound
        91: dup
        92: iconst_0
        93: ldc           #60                 // String SSQ_Neutral_01
        95: invokespecial #62                 // Method ext/mods/gameserver/network/serverpackets/PlaySound."<init>":(ILjava/lang/String;)V
        98: invokestatic  #65                 // Method ext/mods/gameserver/model/World.toAllOnlinePlayers:(Lext/mods/gameserver/network/serverpackets/L2GameServerPacket;)V
       101: getstatic     #71                 // Field ext/mods/gameserver/network/SystemMessageId.QUEST_EVENT_PERIOD_BEGUN:Lext/mods/gameserver/network/SystemMessageId;
       104: invokestatic  #77                 // Method ext/mods/gameserver/network/serverpackets/SystemMessage.getSystemMessage:(Lext/mods/gameserver/network/SystemMessageId;)Lext/mods/gameserver/network/serverpackets/SystemMessage;
       107: invokestatic  #65                 // Method ext/mods/gameserver/model/World.toAllOnlinePlayers:(Lext/mods/gameserver/network/serverpackets/L2GameServerPacket;)V
       110: goto          425
       113: new           #58                 // class ext/mods/gameserver/network/serverpackets/PlaySound
       116: dup
       117: iconst_0
       118: ldc           #60                 // String SSQ_Neutral_01
       120: invokespecial #62                 // Method ext/mods/gameserver/network/serverpackets/PlaySound."<init>":(ILjava/lang/String;)V
       123: invokestatic  #65                 // Method ext/mods/gameserver/model/World.toAllOnlinePlayers:(Lext/mods/gameserver/network/serverpackets/L2GameServerPacket;)V
       126: getstatic     #83                 // Field ext/mods/gameserver/network/SystemMessageId.QUEST_EVENT_PERIOD_ENDED:Lext/mods/gameserver/network/SystemMessageId;
       129: invokestatic  #77                 // Method ext/mods/gameserver/network/serverpackets/SystemMessage.getSystemMessage:(Lext/mods/gameserver/network/SystemMessageId;)Lext/mods/gameserver/network/serverpackets/SystemMessage;
       132: invokestatic  #65                 // Method ext/mods/gameserver/model/World.toAllOnlinePlayers:(Lext/mods/gameserver/network/serverpackets/L2GameServerPacket;)V
       135: aload_0
       136: getfield      #7                  // Field this$0:Lext/mods/gameserver/data/manager/SevenSignsManager;
       139: invokevirtual #86                 // Method ext/mods/gameserver/data/manager/SevenSignsManager.getWinningCabal:()Lext/mods/gameserver/enums/CabalType;
       142: astore_2
       143: invokestatic  #41                 // Method ext/mods/gameserver/data/manager/FestivalOfDarknessManager.getInstance:()Lext/mods/gameserver/data/manager/FestivalOfDarknessManager;
       146: invokevirtual #90                 // Method ext/mods/gameserver/data/manager/FestivalOfDarknessManager.rewardHighestRanked:()V
       149: aload_0
       150: getfield      #7                  // Field this$0:Lext/mods/gameserver/data/manager/SevenSignsManager;
       153: invokevirtual #93                 // Method ext/mods/gameserver/data/manager/SevenSignsManager.calcNewSealOwners:()V
       156: getstatic     #96                 // Field ext/mods/gameserver/data/manager/SevenSignsManager$1.$SwitchMap$ext$mods$gameserver$enums$CabalType:[I
       159: aload_2
       160: invokevirtual #99                 // Method ext/mods/gameserver/enums/CabalType.ordinal:()I
       163: iaload
       164: lookupswitch  { // 2

                       1: 192

                       2: 204
                 default: 213
            }
       192: getstatic     #102                // Field ext/mods/gameserver/network/SystemMessageId.DAWN_WON:Lext/mods/gameserver/network/SystemMessageId;
       195: invokestatic  #77                 // Method ext/mods/gameserver/network/serverpackets/SystemMessage.getSystemMessage:(Lext/mods/gameserver/network/SystemMessageId;)Lext/mods/gameserver/network/serverpackets/SystemMessage;
       198: invokestatic  #65                 // Method ext/mods/gameserver/model/World.toAllOnlinePlayers:(Lext/mods/gameserver/network/serverpackets/L2GameServerPacket;)V
       201: goto          213
       204: getstatic     #105                // Field ext/mods/gameserver/network/SystemMessageId.DUSK_WON:Lext/mods/gameserver/network/SystemMessageId;
       207: invokestatic  #77                 // Method ext/mods/gameserver/network/serverpackets/SystemMessage.getSystemMessage:(Lext/mods/gameserver/network/SystemMessageId;)Lext/mods/gameserver/network/serverpackets/SystemMessage;
       210: invokestatic  #65                 // Method ext/mods/gameserver/model/World.toAllOnlinePlayers:(Lext/mods/gameserver/network/serverpackets/L2GameServerPacket;)V
       213: aload_0
       214: getfield      #7                  // Field this$0:Lext/mods/gameserver/data/manager/SevenSignsManager;
       217: aload_2
       218: putfield      #108                // Field ext/mods/gameserver/data/manager/SevenSignsManager._previousWinner:Lext/mods/gameserver/enums/CabalType;
       221: goto          425
       224: aload_0
       225: getfield      #7                  // Field this$0:Lext/mods/gameserver/data/manager/SevenSignsManager;
       228: invokevirtual #112                // Method ext/mods/gameserver/data/manager/SevenSignsManager.initializeSeals:()V
       231: aload_0
       232: getfield      #7                  // Field this$0:Lext/mods/gameserver/data/manager/SevenSignsManager;
       235: aload_0
       236: getfield      #7                  // Field this$0:Lext/mods/gameserver/data/manager/SevenSignsManager;
       239: getstatic     #115                // Field ext/mods/gameserver/enums/SealType.STRIFE:Lext/mods/gameserver/enums/SealType;
       242: invokevirtual #121                // Method ext/mods/gameserver/data/manager/SevenSignsManager.getSealOwner:(Lext/mods/gameserver/enums/SealType;)Lext/mods/gameserver/enums/CabalType;
       245: invokevirtual #125                // Method ext/mods/gameserver/data/manager/SevenSignsManager.giveSosEffect:(Lext/mods/gameserver/enums/CabalType;)V
       248: new           #58                 // class ext/mods/gameserver/network/serverpackets/PlaySound
       251: dup
       252: iconst_0
       253: aload_0
       254: getfield      #7                  // Field this$0:Lext/mods/gameserver/data/manager/SevenSignsManager;
       257: getfield      #108                // Field ext/mods/gameserver/data/manager/SevenSignsManager._previousWinner:Lext/mods/gameserver/enums/CabalType;
       260: getstatic     #129                // Field ext/mods/gameserver/enums/CabalType.DAWN:Lext/mods/gameserver/enums/CabalType;
       263: if_acmpne     271
       266: ldc           #132                // String SSQ_Dawn_01
       268: goto          273
       271: ldc           #134                // String SSQ_Dusk_01
       273: invokespecial #62                 // Method ext/mods/gameserver/network/serverpackets/PlaySound."<init>":(ILjava/lang/String;)V
       276: invokestatic  #65                 // Method ext/mods/gameserver/model/World.toAllOnlinePlayers:(Lext/mods/gameserver/network/serverpackets/L2GameServerPacket;)V
       279: getstatic     #136                // Field ext/mods/gameserver/network/SystemMessageId.SEAL_VALIDATION_PERIOD_BEGUN:Lext/mods/gameserver/network/SystemMessageId;
       282: invokestatic  #77                 // Method ext/mods/gameserver/network/serverpackets/SystemMessage.getSystemMessage:(Lext/mods/gameserver/network/SystemMessageId;)Lext/mods/gameserver/network/serverpackets/SystemMessage;
       285: invokestatic  #65                 // Method ext/mods/gameserver/model/World.toAllOnlinePlayers:(Lext/mods/gameserver/network/serverpackets/L2GameServerPacket;)V
       288: getstatic     #139                // Field ext/mods/gameserver/data/manager/SevenSignsManager.LOGGER:Lext/mods/commons/logging/CLogger;
       291: ldc           #143                // String The {} have won the competition with {} points.
       293: iconst_2
       294: anewarray     #14                 // class java/lang/Object
       297: dup
       298: iconst_0
       299: aload_0
       300: getfield      #7                  // Field this$0:Lext/mods/gameserver/data/manager/SevenSignsManager;
       303: getfield      #108                // Field ext/mods/gameserver/data/manager/SevenSignsManager._previousWinner:Lext/mods/gameserver/enums/CabalType;
       306: invokevirtual #145                // Method ext/mods/gameserver/enums/CabalType.getFullName:()Ljava/lang/String;
       309: aastore
       310: dup
       311: iconst_1
       312: aload_0
       313: getfield      #7                  // Field this$0:Lext/mods/gameserver/data/manager/SevenSignsManager;
       316: aload_0
       317: getfield      #7                  // Field this$0:Lext/mods/gameserver/data/manager/SevenSignsManager;
       320: getfield      #108                // Field ext/mods/gameserver/data/manager/SevenSignsManager._previousWinner:Lext/mods/gameserver/enums/CabalType;
       323: invokevirtual #149                // Method ext/mods/gameserver/data/manager/SevenSignsManager.getCurrentScore:(Lext/mods/gameserver/enums/CabalType;)I
       326: invokestatic  #153                // Method java/lang/Integer.valueOf:(I)Ljava/lang/Integer;
       329: aastore
       330: invokevirtual #159                // Method ext/mods/commons/logging/CLogger.info:(Ljava/lang/Object;[Ljava/lang/Object;)V
       333: goto          425
       336: aload_0
       337: getfield      #7                  // Field this$0:Lext/mods/gameserver/data/manager/SevenSignsManager;
       340: getstatic     #165                // Field ext/mods/gameserver/enums/PeriodType.RECRUITING:Lext/mods/gameserver/enums/PeriodType;
       343: putfield      #19                 // Field ext/mods/gameserver/data/manager/SevenSignsManager._activePeriod:Lext/mods/gameserver/enums/PeriodType;
       346: new           #58                 // class ext/mods/gameserver/network/serverpackets/PlaySound
       349: dup
       350: iconst_0
       351: ldc           #60                 // String SSQ_Neutral_01
       353: invokespecial #62                 // Method ext/mods/gameserver/network/serverpackets/PlaySound."<init>":(ILjava/lang/String;)V
       356: invokestatic  #65                 // Method ext/mods/gameserver/model/World.toAllOnlinePlayers:(Lext/mods/gameserver/network/serverpackets/L2GameServerPacket;)V
       359: getstatic     #168                // Field ext/mods/gameserver/network/SystemMessageId.SEAL_VALIDATION_PERIOD_ENDED:Lext/mods/gameserver/network/SystemMessageId;
       362: invokestatic  #77                 // Method ext/mods/gameserver/network/serverpackets/SystemMessage.getSystemMessage:(Lext/mods/gameserver/network/SystemMessageId;)Lext/mods/gameserver/network/serverpackets/SystemMessage;
       365: invokestatic  #65                 // Method ext/mods/gameserver/model/World.toAllOnlinePlayers:(Lext/mods/gameserver/network/serverpackets/L2GameServerPacket;)V
       368: aload_0
       369: getfield      #7                  // Field this$0:Lext/mods/gameserver/data/manager/SevenSignsManager;
       372: invokevirtual #171                // Method ext/mods/gameserver/data/manager/SevenSignsManager.removeSosEffect:()V
       375: aload_0
       376: getfield      #7                  // Field this$0:Lext/mods/gameserver/data/manager/SevenSignsManager;
       379: invokevirtual #174                // Method ext/mods/gameserver/data/manager/SevenSignsManager.resetPlayerData:()V
       382: aload_0
       383: getfield      #7                  // Field this$0:Lext/mods/gameserver/data/manager/SevenSignsManager;
       386: invokevirtual #177                // Method ext/mods/gameserver/data/manager/SevenSignsManager.resetSeals:()V
       389: aload_0
       390: getfield      #7                  // Field this$0:Lext/mods/gameserver/data/manager/SevenSignsManager;
       393: dup
       394: getfield      #180                // Field ext/mods/gameserver/data/manager/SevenSignsManager._currentCycle:I
       397: iconst_1
       398: iadd
       399: putfield      #180                // Field ext/mods/gameserver/data/manager/SevenSignsManager._currentCycle:I
       402: invokestatic  #41                 // Method ext/mods/gameserver/data/manager/FestivalOfDarknessManager.getInstance:()Lext/mods/gameserver/data/manager/FestivalOfDarknessManager;
       405: iconst_0
       406: invokevirtual #184                // Method ext/mods/gameserver/data/manager/FestivalOfDarknessManager.resetFestivalData:(Z)V
       409: aload_0
       410: getfield      #7                  // Field this$0:Lext/mods/gameserver/data/manager/SevenSignsManager;
       413: dconst_0
       414: putfield      #188                // Field ext/mods/gameserver/data/manager/SevenSignsManager._dawnStoneScore:D
       417: aload_0
       418: getfield      #7                  // Field this$0:Lext/mods/gameserver/data/manager/SevenSignsManager;
       421: dconst_0
       422: putfield      #192                // Field ext/mods/gameserver/data/manager/SevenSignsManager._duskStoneScore:D
       425: aload_0
       426: getfield      #7                  // Field this$0:Lext/mods/gameserver/data/manager/SevenSignsManager;
       429: invokevirtual #195                // Method ext/mods/gameserver/data/manager/SevenSignsManager.saveSevenSignsData:()V
       432: aload_0
       433: getfield      #7                  // Field this$0:Lext/mods/gameserver/data/manager/SevenSignsManager;
       436: invokevirtual #198                // Method ext/mods/gameserver/data/manager/SevenSignsManager.saveSevenSignsStatus:()V
       439: getstatic     #201                // Field ext/mods/Config.CATACOMBS_IN_ANY_PERIOD:Z
       442: ifne          459
       445: aload_0
       446: getfield      #7                  // Field this$0:Lext/mods/gameserver/data/manager/SevenSignsManager;
       449: aload_0
       450: getfield      #7                  // Field this$0:Lext/mods/gameserver/data/manager/SevenSignsManager;
       453: invokevirtual #86                 // Method ext/mods/gameserver/data/manager/SevenSignsManager.getWinningCabal:()Lext/mods/gameserver/enums/CabalType;
       456: invokevirtual #207                // Method ext/mods/gameserver/data/manager/SevenSignsManager.teleLosingCabalFromDungeons:(Lext/mods/gameserver/enums/CabalType;)V
       459: invokestatic  #210                // Method ext/mods/gameserver/network/serverpackets/SSQInfo.sendSky:()Lext/mods/gameserver/network/serverpackets/SSQInfo;
       462: invokestatic  #65                 // Method ext/mods/gameserver/model/World.toAllOnlinePlayers:(Lext/mods/gameserver/network/serverpackets/L2GameServerPacket;)V
       465: invokestatic  #216                // Method ext/mods/gameserver/data/manager/SpawnManager.getInstance:()Lext/mods/gameserver/data/manager/SpawnManager;
       468: invokevirtual #221                // Method ext/mods/gameserver/data/manager/SpawnManager.notifySevenSignsChange:()V
       471: getstatic     #139                // Field ext/mods/gameserver/data/manager/SevenSignsManager.LOGGER:Lext/mods/commons/logging/CLogger;
       474: ldc           #224                // String The {} period of Seven Signs has begun.
       476: iconst_1
       477: anewarray     #14                 // class java/lang/Object
       480: dup
       481: iconst_0
       482: aload_0
       483: getfield      #7                  // Field this$0:Lext/mods/gameserver/data/manager/SevenSignsManager;
       486: getfield      #19                 // Field ext/mods/gameserver/data/manager/SevenSignsManager._activePeriod:Lext/mods/gameserver/enums/PeriodType;
       489: invokevirtual #226                // Method ext/mods/gameserver/enums/PeriodType.getName:()Ljava/lang/String;
       492: aastore
       493: invokevirtual #159                // Method ext/mods/commons/logging/CLogger.info:(Ljava/lang/Object;[Ljava/lang/Object;)V
       496: aload_0
       497: getfield      #7                  // Field this$0:Lext/mods/gameserver/data/manager/SevenSignsManager;
       500: invokevirtual #229                // Method ext/mods/gameserver/data/manager/SevenSignsManager.setCalendarForNextPeriodChange:()V
       503: new           #8                  // class ext/mods/gameserver/data/manager/SevenSignsManager$SevenSignsPeriodChange
       506: dup
       507: aload_0
       508: getfield      #7                  // Field this$0:Lext/mods/gameserver/data/manager/SevenSignsManager;
       511: invokespecial #232                // Method "<init>":(Lext/mods/gameserver/data/manager/SevenSignsManager;)V
       514: aload_0
       515: getfield      #7                  // Field this$0:Lext/mods/gameserver/data/manager/SevenSignsManager;
       518: invokevirtual #235                // Method ext/mods/gameserver/data/manager/SevenSignsManager.getMilliToPeriodChange:()J
       521: invokestatic  #239                // Method ext/mods/commons/pool/ThreadPool.schedule:(Ljava/lang/Runnable;J)Ljava/util/concurrent/ScheduledFuture;
       524: pop
       525: return
      LineNumberTable:
        line 797: 0
        line 799: 8
        line 801: 36
        line 804: 76
        line 806: 82
        line 808: 88
        line 810: 101
        line 811: 110
        line 814: 113
        line 816: 126
        line 818: 135
        line 820: 143
        line 822: 149
        line 824: 156
        line 827: 192
        line 828: 201
        line 831: 204
        line 835: 213
        line 836: 221
        line 839: 224
        line 841: 231
        line 843: 248
        line 845: 279
        line 847: 288
        line 848: 333
        line 851: 336
        line 853: 346
        line 855: 359
        line 857: 368
        line 859: 375
        line 860: 382
        line 862: 389
        line 864: 402
        line 866: 409
        line 867: 417
        line 871: 425
        line 872: 432
        line 874: 439
        line 875: 445
        line 877: 459
        line 878: 465
        line 880: 471
        line 882: 496
        line 884: 503
        line 885: 525
      LocalVariableTable:
        Start  Length  Slot  Name   Signature
          143      81     2 winningCabal   Lext/mods/gameserver/enums/CabalType;
            0     526     0  this   Lext/mods/gameserver/data/manager/SevenSignsManager$SevenSignsPeriodChange;
            8     518     1 periodEnded   Lext/mods/gameserver/enums/PeriodType;
      StackMapTable: number_of_entries = 11
        frame_type = 252 /* append */
          offset_delta = 76
          locals = [ class ext/mods/gameserver/enums/PeriodType ]
        frame_type = 36 /* same */
        frame_type = 252 /* append */
          offset_delta = 78
          locals = [ class ext/mods/gameserver/enums/CabalType ]
        frame_type = 11 /* same */
        frame_type = 8 /* same */
        frame_type = 250 /* chop */
          offset_delta = 10
        frame_type = 255 /* full_frame */
          offset_delta = 46
          locals = [ class ext/mods/gameserver/data/manager/SevenSignsManager$SevenSignsPeriodChange, class ext/mods/gameserver/enums/PeriodType ]
          stack = [ uninitialized 248, uninitialized 248, int ]
        frame_type = 255 /* full_frame */
          offset_delta = 1
          locals = [ class ext/mods/gameserver/data/manager/SevenSignsManager$SevenSignsPeriodChange, class ext/mods/gameserver/enums/PeriodType ]
          stack = [ uninitialized 248, uninitialized 248, int, class java/lang/String ]
        frame_type = 62 /* same */
        frame_type = 251 /* same_frame_extended */
          offset_delta = 88
        frame_type = 33 /* same */
}
SourceFile: "SevenSignsManager.java"
NestHost: class ext/mods/gameserver/data/manager/SevenSignsManager
InnerClasses:
  protected #263= #8 of #20;              // SevenSignsPeriodChange=class ext/mods/gameserver/data/manager/SevenSignsManager$SevenSignsPeriodChange of class ext/mods/gameserver/data/manager/SevenSignsManager
  static #36;                             // class ext/mods/gameserver/data/manager/SevenSignsManager$1
