// Bytecode for: ext.mods.commons.gui.actions.PlayerActions
// File: ext\mods\commons\gui\actions\PlayerActions.class

Classfile /c:/Users/User/Desktop/BrProject/bin/main/ext/mods/commons/gui/actions/PlayerActions.class
  Last modified 9 de jul de 2026; size 6214 bytes
  MD5 checksum 9f9d14096dd7c3b96272584247b80337
  Compiled from "PlayerActions.java"
public class ext.mods.commons.gui.actions.PlayerActions
  minor version: 0
  major version: 69
  flags: (0x0021) ACC_PUBLIC, ACC_SUPER
  this_class: #67                         // ext/mods/commons/gui/actions/PlayerActions
  super_class: #2                         // java/lang/Object
  interfaces: 0, fields: 0, methods: 7, attributes: 3
Constant pool:
    #1 = Methodref          #2.#3         // java/lang/Object."<init>":()V
    #2 = Class              #4            // java/lang/Object
    #3 = NameAndType        #5:#6         // "<init>":()V
    #4 = Utf8               java/lang/Object
    #5 = Utf8               <init>
    #6 = Utf8               ()V
    #7 = String             #8            // Enter player name:
    #8 = Utf8               Enter player name:
    #9 = String             #10           // Admin Player
   #10 = Utf8               Admin Player
   #11 = Class              #12           // javax/swing/JOptionPane
   #12 = Utf8               javax/swing/JOptionPane
   #13 = Methodref          #11.#14       // javax/swing/JOptionPane.showInputDialog:(Ljava/awt/Component;Ljava/lang/Object;Ljava/lang/String;I)Ljava/lang/String;
   #14 = NameAndType        #15:#16       // showInputDialog:(Ljava/awt/Component;Ljava/lang/Object;Ljava/lang/String;I)Ljava/lang/String;
   #15 = Utf8               showInputDialog
   #16 = Utf8               (Ljava/awt/Component;Ljava/lang/Object;Ljava/lang/String;I)Ljava/lang/String;
   #17 = Methodref          #18.#19       // java/lang/String.trim:()Ljava/lang/String;
   #18 = Class              #20           // java/lang/String
   #19 = NameAndType        #21:#22       // trim:()Ljava/lang/String;
   #20 = Utf8               java/lang/String
   #21 = Utf8               trim
   #22 = Utf8               ()Ljava/lang/String;
   #23 = Methodref          #18.#24       // java/lang/String.isEmpty:()Z
   #24 = NameAndType        #25:#26       // isEmpty:()Z
   #25 = Utf8               isEmpty
   #26 = Utf8               ()Z
   #27 = String             #28           //  -1 | Banned | No access
   #28 = Utf8                -1 | Banned | No access
   #29 = String             #30           //  0 | User | Normal player
   #30 = Utf8                0 | User | Normal player
   #31 = String             #32           //  1 | Chat Moderator | Moderates chat only
   #32 = Utf8                1 | Chat Moderator | Moderates chat only
   #33 = String             #34           //  2 | Test GM | Test GM
   #34 = Utf8                2 | Test GM | Test GM
   #35 = String             #36           //  3 | General GM | General GM
   #36 = Utf8                3 | General GM | General GM
   #37 = String             #38           //  4 | Support GM | Support GM
   #38 = Utf8                4 | Support GM | Support GM
   #39 = String             #40           //  5 | Event GM | Event GM
   #40 = Utf8                5 | Event GM | Event GM
   #41 = String             #42           //  6 | Head GM | Head GM
   #42 = Utf8                6 | Head GM | Head GM
   #43 = String             #44           //  7 | Admin | Administrator
   #44 = Utf8                7 | Admin | Administrator
   #45 = String             #46           //  8 | Master | Owner/Master
   #46 = Utf8                8 | Master | Owner/Master
   #47 = String             #48           // Select the new access level:
   #48 = Utf8               Select the new access level:
   #49 = String             #50           // Change Access Level
   #50 = Utf8               Change Access Level
   #51 = Methodref          #11.#52       // javax/swing/JOptionPane.showInputDialog:(Ljava/awt/Component;Ljava/lang/Object;Ljava/lang/String;ILjavax/swing/Icon;[Ljava/lang/Object;Ljava/lang/Object;)Ljava/lang/Object;
   #52 = NameAndType        #15:#53       // showInputDialog:(Ljava/awt/Component;Ljava/lang/Object;Ljava/lang/String;ILjavax/swing/Icon;[Ljava/lang/Object;Ljava/lang/Object;)Ljava/lang/Object;
   #53 = Utf8               (Ljava/awt/Component;Ljava/lang/Object;Ljava/lang/String;ILjavax/swing/Icon;[Ljava/lang/Object;Ljava/lang/Object;)Ljava/lang/Object;
   #54 = String             #55           // \\|
   #55 = Utf8               \\|
   #56 = Methodref          #18.#57       // java/lang/String.split:(Ljava/lang/String;)[Ljava/lang/String;
   #57 = NameAndType        #58:#59       // split:(Ljava/lang/String;)[Ljava/lang/String;
   #58 = Utf8               split
   #59 = Utf8               (Ljava/lang/String;)[Ljava/lang/String;
   #60 = Methodref          #61.#62       // java/lang/Integer.parseInt:(Ljava/lang/String;)I
   #61 = Class              #63           // java/lang/Integer
   #62 = NameAndType        #64:#65       // parseInt:(Ljava/lang/String;)I
   #63 = Utf8               java/lang/Integer
   #64 = Utf8               parseInt
   #65 = Utf8               (Ljava/lang/String;)I
   #66 = Methodref          #67.#68       // ext/mods/commons/gui/actions/PlayerActions.adminPlayer:(Ljava/lang/String;I)V
   #67 = Class              #69           // ext/mods/commons/gui/actions/PlayerActions
   #68 = NameAndType        #70:#71       // adminPlayer:(Ljava/lang/String;I)V
   #69 = Utf8               ext/mods/commons/gui/actions/PlayerActions
   #70 = Utf8               adminPlayer
   #71 = Utf8               (Ljava/lang/String;I)V
   #72 = InvokeDynamic      #0:#73        // #0:makeConcatWithConstants:(Ljava/lang/String;Ljava/lang/String;)Ljava/lang/String;
   #73 = NameAndType        #74:#75       // makeConcatWithConstants:(Ljava/lang/String;Ljava/lang/String;)Ljava/lang/String;
   #74 = Utf8               makeConcatWithConstants
   #75 = Utf8               (Ljava/lang/String;Ljava/lang/String;)Ljava/lang/String;
   #76 = String             #77           // Success
   #77 = Utf8               Success
   #78 = Methodref          #11.#79       // javax/swing/JOptionPane.showMessageDialog:(Ljava/awt/Component;Ljava/lang/Object;Ljava/lang/String;I)V
   #79 = NameAndType        #80:#81       // showMessageDialog:(Ljava/awt/Component;Ljava/lang/Object;Ljava/lang/String;I)V
   #80 = Utf8               showMessageDialog
   #81 = Utf8               (Ljava/awt/Component;Ljava/lang/Object;Ljava/lang/String;I)V
   #82 = Class              #83           // java/lang/NumberFormatException
   #83 = Utf8               java/lang/NumberFormatException
   #84 = String             #85           // Error parsing level!
   #85 = Utf8               Error parsing level!
   #86 = String             #87           // Error
   #87 = Utf8               Error
   #88 = String             #89           // Repair Player
   #89 = Utf8               Repair Player
   #90 = Methodref          #67.#91       // ext/mods/commons/gui/actions/PlayerActions.handlerRepair:(Ljava/lang/String;)V
   #91 = NameAndType        #92:#93       // handlerRepair:(Ljava/lang/String;)V
   #92 = Utf8               handlerRepair
   #93 = Utf8               (Ljava/lang/String;)V
   #94 = String             #95           // Invalid player name! Please enter a valid name.
   #95 = Utf8               Invalid player name! Please enter a valid name.
   #96 = Methodref          #97.#98       // ext/mods/gameserver/model/World.getInstance:()Lext/mods/gameserver/model/World;
   #97 = Class              #99           // ext/mods/gameserver/model/World
   #98 = NameAndType        #100:#101     // getInstance:()Lext/mods/gameserver/model/World;
   #99 = Utf8               ext/mods/gameserver/model/World
  #100 = Utf8               getInstance
  #101 = Utf8               ()Lext/mods/gameserver/model/World;
  #102 = Methodref          #97.#103      // ext/mods/gameserver/model/World.getPlayer:(Ljava/lang/String;)Lext/mods/gameserver/model/actor/Player;
  #103 = NameAndType        #104:#105     // getPlayer:(Ljava/lang/String;)Lext/mods/gameserver/model/actor/Player;
  #104 = Utf8               getPlayer
  #105 = Utf8               (Ljava/lang/String;)Lext/mods/gameserver/model/actor/Player;
  #106 = Methodref          #67.#107      // ext/mods/commons/gui/actions/PlayerActions.onLineRepair:(Lext/mods/gameserver/model/actor/Player;)V
  #107 = NameAndType        #108:#109     // onLineRepair:(Lext/mods/gameserver/model/actor/Player;)V
  #108 = Utf8               onLineRepair
  #109 = Utf8               (Lext/mods/gameserver/model/actor/Player;)V
  #110 = Methodref          #111.#112     // ext/mods/commons/pool/ConnectionPool.getConnection:()Ljava/sql/Connection;
  #111 = Class              #113          // ext/mods/commons/pool/ConnectionPool
  #112 = NameAndType        #114:#115     // getConnection:()Ljava/sql/Connection;
  #113 = Utf8               ext/mods/commons/pool/ConnectionPool
  #114 = Utf8               getConnection
  #115 = Utf8               ()Ljava/sql/Connection;
  #116 = String             #117          // UPDATE characters SET x=?, y=?, z=? WHERE char_name=?
  #117 = Utf8               UPDATE characters SET x=?, y=?, z=? WHERE char_name=?
  #118 = InterfaceMethodref #119.#120     // java/sql/Connection.prepareStatement:(Ljava/lang/String;)Ljava/sql/PreparedStatement;
  #119 = Class              #121          // java/sql/Connection
  #120 = NameAndType        #122:#123     // prepareStatement:(Ljava/lang/String;)Ljava/sql/PreparedStatement;
  #121 = Utf8               java/sql/Connection
  #122 = Utf8               prepareStatement
  #123 = Utf8               (Ljava/lang/String;)Ljava/sql/PreparedStatement;
  #124 = Integer            83345
  #125 = InterfaceMethodref #126.#127     // java/sql/PreparedStatement.setInt:(II)V
  #126 = Class              #128          // java/sql/PreparedStatement
  #127 = NameAndType        #129:#130     // setInt:(II)V
  #128 = Utf8               java/sql/PreparedStatement
  #129 = Utf8               setInt
  #130 = Utf8               (II)V
  #131 = Integer            148144
  #132 = InterfaceMethodref #126.#133     // java/sql/PreparedStatement.setString:(ILjava/lang/String;)V
  #133 = NameAndType        #134:#135     // setString:(ILjava/lang/String;)V
  #134 = Utf8               setString
  #135 = Utf8               (ILjava/lang/String;)V
  #136 = InterfaceMethodref #126.#137     // java/sql/PreparedStatement.executeUpdate:()I
  #137 = NameAndType        #138:#139     // executeUpdate:()I
  #138 = Utf8               executeUpdate
  #139 = Utf8               ()I
  #140 = Fieldref           #141.#142     // java/lang/System.out:Ljava/io/PrintStream;
  #141 = Class              #143          // java/lang/System
  #142 = NameAndType        #144:#145     // out:Ljava/io/PrintStream;
  #143 = Utf8               java/lang/System
  #144 = Utf8               out
  #145 = Utf8               Ljava/io/PrintStream;
  #146 = InvokeDynamic      #1:#147       // #1:makeConcatWithConstants:(Ljava/lang/String;)Ljava/lang/String;
  #147 = NameAndType        #74:#148      // makeConcatWithConstants:(Ljava/lang/String;)Ljava/lang/String;
  #148 = Utf8               (Ljava/lang/String;)Ljava/lang/String;
  #149 = Methodref          #150.#151     // java/io/PrintStream.println:(Ljava/lang/String;)V
  #150 = Class              #152          // java/io/PrintStream
  #151 = NameAndType        #153:#93      // println:(Ljava/lang/String;)V
  #152 = Utf8               java/io/PrintStream
  #153 = Utf8               println
  #154 = InterfaceMethodref #126.#155     // java/sql/PreparedStatement.close:()V
  #155 = NameAndType        #156:#6       // close:()V
  #156 = Utf8               close
  #157 = Class              #158          // java/lang/Throwable
  #158 = Utf8               java/lang/Throwable
  #159 = Methodref          #157.#160     // java/lang/Throwable.addSuppressed:(Ljava/lang/Throwable;)V
  #160 = NameAndType        #161:#162     // addSuppressed:(Ljava/lang/Throwable;)V
  #161 = Utf8               addSuppressed
  #162 = Utf8               (Ljava/lang/Throwable;)V
  #163 = InterfaceMethodref #119.#155     // java/sql/Connection.close:()V
  #164 = Class              #165          // java/lang/Exception
  #165 = Utf8               java/lang/Exception
  #166 = Methodref          #164.#167     // java/lang/Exception.printStackTrace:()V
  #167 = NameAndType        #168:#6       // printStackTrace:()V
  #168 = Utf8               printStackTrace
  #169 = Methodref          #170.#171     // ext/mods/gameserver/model/actor/Player.isInCombat:()Z
  #170 = Class              #172          // ext/mods/gameserver/model/actor/Player
  #171 = NameAndType        #173:#26      // isInCombat:()Z
  #172 = Utf8               ext/mods/gameserver/model/actor/Player
  #173 = Utf8               isInCombat
  #174 = Methodref          #170.#175     // ext/mods/gameserver/model/actor/Player.abortAll:(Z)V
  #175 = NameAndType        #176:#177     // abortAll:(Z)V
  #176 = Utf8               abortAll
  #177 = Utf8               (Z)V
  #178 = Fieldref           #179.#180     // ext/mods/gameserver/enums/RestartType.TOWN:Lext/mods/gameserver/enums/RestartType;
  #179 = Class              #181          // ext/mods/gameserver/enums/RestartType
  #180 = NameAndType        #182:#183     // TOWN:Lext/mods/gameserver/enums/RestartType;
  #181 = Utf8               ext/mods/gameserver/enums/RestartType
  #182 = Utf8               TOWN
  #183 = Utf8               Lext/mods/gameserver/enums/RestartType;
  #184 = Methodref          #170.#185     // ext/mods/gameserver/model/actor/Player.teleportTo:(Lext/mods/gameserver/enums/RestartType;)V
  #185 = NameAndType        #186:#187     // teleportTo:(Lext/mods/gameserver/enums/RestartType;)V
  #186 = Utf8               teleportTo
  #187 = Utf8               (Lext/mods/gameserver/enums/RestartType;)V
  #188 = String             #189          // Admin repair you characters, you move town
  #189 = Utf8               Admin repair you characters, you move town
  #190 = Methodref          #170.#191     // ext/mods/gameserver/model/actor/Player.sendMessage:(Ljava/lang/String;)V
  #191 = NameAndType        #192:#93      // sendMessage:(Ljava/lang/String;)V
  #192 = Utf8               sendMessage
  #193 = Methodref          #170.#194     // ext/mods/gameserver/model/actor/Player.getName:()Ljava/lang/String;
  #194 = NameAndType        #195:#22      // getName:()Ljava/lang/String;
  #195 = Utf8               getName
  #196 = InvokeDynamic      #2:#147       // #2:makeConcatWithConstants:(Ljava/lang/String;)Ljava/lang/String;
  #197 = Methodref          #67.#198      // ext/mods/commons/gui/actions/PlayerActions.onLineChange:(Lext/mods/gameserver/model/actor/Player;I)V
  #198 = NameAndType        #199:#200     // onLineChange:(Lext/mods/gameserver/model/actor/Player;I)V
  #199 = Utf8               onLineChange
  #200 = Utf8               (Lext/mods/gameserver/model/actor/Player;I)V
  #201 = String             #202          // UPDATE characters SET accesslevel=? WHERE char_name=?
  #202 = Utf8               UPDATE characters SET accesslevel=? WHERE char_name=?
  #203 = InterfaceMethodref #126.#204     // java/sql/PreparedStatement.execute:()Z
  #204 = NameAndType        #205:#26      // execute:()Z
  #205 = Utf8               execute
  #206 = InterfaceMethodref #126.#207     // java/sql/PreparedStatement.getUpdateCount:()I
  #207 = NameAndType        #208:#139     // getUpdateCount:()I
  #208 = Utf8               getUpdateCount
  #209 = InvokeDynamic      #3:#210       // #3:makeConcatWithConstants:(Ljava/lang/String;I)Ljava/lang/String;
  #210 = NameAndType        #74:#211      // makeConcatWithConstants:(Ljava/lang/String;I)Ljava/lang/String;
  #211 = Utf8               (Ljava/lang/String;I)Ljava/lang/String;
  #212 = String             #213          //
  #213 = Utf8
  #214 = Methodref          #170.#215     // ext/mods/gameserver/model/actor/Player.setTitle:(Ljava/lang/String;)V
  #215 = NameAndType        #216:#93      // setTitle:(Ljava/lang/String;)V
  #216 = Utf8               setTitle
  #217 = Methodref          #170.#218     // ext/mods/gameserver/model/actor/Player.setAccessLevel:(I)V
  #218 = NameAndType        #219:#220     // setAccessLevel:(I)V
  #219 = Utf8               setAccessLevel
  #220 = Utf8               (I)V
  #221 = Methodref          #170.#222     // ext/mods/gameserver/model/actor/Player.logout:(Z)V
  #222 = NameAndType        #223:#177     // logout:(Z)V
  #223 = Utf8               logout
  #224 = InvokeDynamic      #4:#225       // #4:makeConcatWithConstants:(I)Ljava/lang/String;
  #225 = NameAndType        #74:#226      // makeConcatWithConstants:(I)Ljava/lang/String;
  #226 = Utf8               (I)Ljava/lang/String;
  #227 = Utf8               Code
  #228 = Utf8               LineNumberTable
  #229 = Utf8               LocalVariableTable
  #230 = Utf8               this
  #231 = Utf8               Lext/mods/commons/gui/actions/PlayerActions;
  #232 = Utf8               changeAccess
  #233 = Utf8               (Ljavax/swing/JFrame;)V
  #234 = Utf8               level
  #235 = Utf8               I
  #236 = Utf8               e
  #237 = Utf8               Ljava/lang/NumberFormatException;
  #238 = Utf8               parent
  #239 = Utf8               Ljavax/swing/JFrame;
  #240 = Utf8               playerName
  #241 = Utf8               Ljava/lang/String;
  #242 = Utf8               accessOptions
  #243 = Utf8               [Ljava/lang/String;
  #244 = Utf8               selected
  #245 = Utf8               StackMapTable
  #246 = Class              #247          // javax/swing/JFrame
  #247 = Utf8               javax/swing/JFrame
  #248 = Class              #243          // "[Ljava/lang/String;"
  #249 = Utf8               repairPlayer
  #250 = Utf8               ps
  #251 = Utf8               Ljava/sql/PreparedStatement;
  #252 = Utf8               con
  #253 = Utf8               Ljava/sql/Connection;
  #254 = Utf8               Ljava/lang/Exception;
  #255 = Utf8               player
  #256 = Utf8               Lext/mods/gameserver/model/actor/Player;
  #257 = Utf8               name
  #258 = Utf8               adminLevel
  #259 = Utf8               SourceFile
  #260 = Utf8               PlayerActions.java
  #261 = Utf8               BootstrapMethods
  #262 = String             #263          // Access level of \u0001 changed to: \u0001
  #263 = Utf8               Access level of \u0001 changed to: \u0001
  #264 = String             #265          // Repair player name: [\u0001] Teleport to fixed location
  #265 = Utf8               Repair player name: [\u0001] Teleport to fixed location
  #266 = String             #267          // Repair player name: [\u0001] Teleport to town
  #267 = Utf8               Repair player name: [\u0001] Teleport to town
  #268 = String             #269          // Change Status player name: [\u0001] accesslevel: \u0001
  #269 = Utf8               Change Status player name: [\u0001] accesslevel: \u0001
  #270 = String             #271          // Your access level has been changed to \u0001.
  #271 = Utf8               Your access level has been changed to \u0001.
  #272 = MethodHandle       6:#273        // REF_invokeStatic java/lang/invoke/StringConcatFactory.makeConcatWithConstants:(Ljava/lang/invoke/MethodHandles$Lookup;Ljava/lang/String;Ljava/lang/invoke/MethodType;Ljava/lang/String;[Ljava/lang/Object;)Ljava/lang/invoke/CallSite;
  #273 = Methodref          #274.#275     // java/lang/invoke/StringConcatFactory.makeConcatWithConstants:(Ljava/lang/invoke/MethodHandles$Lookup;Ljava/lang/String;Ljava/lang/invoke/MethodType;Ljava/lang/String;[Ljava/lang/Object;)Ljava/lang/invoke/CallSite;
  #274 = Class              #276          // java/lang/invoke/StringConcatFactory
  #275 = NameAndType        #74:#277      // makeConcatWithConstants:(Ljava/lang/invoke/MethodHandles$Lookup;Ljava/lang/String;Ljava/lang/invoke/MethodType;Ljava/lang/String;[Ljava/lang/Object;)Ljava/lang/invoke/CallSite;
  #276 = Utf8               java/lang/invoke/StringConcatFactory
  #277 = Utf8               (Ljava/lang/invoke/MethodHandles$Lookup;Ljava/lang/String;Ljava/lang/invoke/MethodType;Ljava/lang/String;[Ljava/lang/Object;)Ljava/lang/invoke/CallSite;
  #278 = Utf8               InnerClasses
  #279 = Class              #280          // java/lang/invoke/MethodHandles$Lookup
  #280 = Utf8               java/lang/invoke/MethodHandles$Lookup
  #281 = Class              #282          // java/lang/invoke/MethodHandles
  #282 = Utf8               java/lang/invoke/MethodHandles
  #283 = Utf8               Lookup
{
  public ext.mods.commons.gui.actions.PlayerActions();
    descriptor: ()V
    flags: (0x0001) ACC_PUBLIC
    Code:
      stack=1, locals=1, args_size=1
         0: aload_0
         1: invokespecial #1                  // Method java/lang/Object."<init>":()V
         4: return
      LineNumberTable:
        line 29: 0
      LocalVariableTable:
        Start  Length  Slot  Name   Signature
            0       5     0  this   Lext/mods/commons/gui/actions/PlayerActions;

  public static void changeAccess(javax.swing.JFrame);
    descriptor: (Ljavax/swing/JFrame;)V
    flags: (0x0009) ACC_PUBLIC, ACC_STATIC
    Code:
      stack=8, locals=5, args_size=1
         0: aload_0
         1: ldc           #7                  // String Enter player name:
         3: ldc           #9                  // String Admin Player
         5: iconst_3
         6: invokestatic  #13                 // Method javax/swing/JOptionPane.showInputDialog:(Ljava/awt/Component;Ljava/lang/Object;Ljava/lang/String;I)Ljava/lang/String;
         9: astore_1
        10: aload_1
        11: ifnull        24
        14: aload_1
        15: invokevirtual #17                 // Method java/lang/String.trim:()Ljava/lang/String;
        18: invokevirtual #23                 // Method java/lang/String.isEmpty:()Z
        21: ifeq          25
        24: return
        25: bipush        10
        27: anewarray     #18                 // class java/lang/String
        30: dup
        31: iconst_0
        32: ldc           #27                 // String  -1 | Banned | No access
        34: aastore
        35: dup
        36: iconst_1
        37: ldc           #29                 // String  0 | User | Normal player
        39: aastore
        40: dup
        41: iconst_2
        42: ldc           #31                 // String  1 | Chat Moderator | Moderates chat only
        44: aastore
        45: dup
        46: iconst_3
        47: ldc           #33                 // String  2 | Test GM | Test GM
        49: aastore
        50: dup
        51: iconst_4
        52: ldc           #35                 // String  3 | General GM | General GM
        54: aastore
        55: dup
        56: iconst_5
        57: ldc           #37                 // String  4 | Support GM | Support GM
        59: aastore
        60: dup
        61: bipush        6
        63: ldc           #39                 // String  5 | Event GM | Event GM
        65: aastore
        66: dup
        67: bipush        7
        69: ldc           #41                 // String  6 | Head GM | Head GM
        71: aastore
        72: dup
        73: bipush        8
        75: ldc           #43                 // String  7 | Admin | Administrator
        77: aastore
        78: dup
        79: bipush        9
        81: ldc           #45                 // String  8 | Master | Owner/Master
        83: aastore
        84: astore_2
        85: aload_0
        86: ldc           #47                 // String Select the new access level:
        88: ldc           #49                 // String Change Access Level
        90: iconst_3
        91: aconst_null
        92: aload_2
        93: aload_2
        94: iconst_1
        95: aaload
        96: invokestatic  #51                 // Method javax/swing/JOptionPane.showInputDialog:(Ljava/awt/Component;Ljava/lang/Object;Ljava/lang/String;ILjavax/swing/Icon;[Ljava/lang/Object;Ljava/lang/Object;)Ljava/lang/Object;
        99: checkcast     #18                 // class java/lang/String
       102: astore_3
       103: aload_3
       104: ifnull        160
       107: aload_3
       108: invokevirtual #17                 // Method java/lang/String.trim:()Ljava/lang/String;
       111: ldc           #54                 // String \\|
       113: invokevirtual #56                 // Method java/lang/String.split:(Ljava/lang/String;)[Ljava/lang/String;
       116: iconst_0
       117: aaload
       118: invokevirtual #17                 // Method java/lang/String.trim:()Ljava/lang/String;
       121: invokestatic  #60                 // Method java/lang/Integer.parseInt:(Ljava/lang/String;)I
       124: istore        4
       126: aload_1
       127: iload         4
       129: invokestatic  #66                 // Method adminPlayer:(Ljava/lang/String;I)V
       132: aload_0
       133: aload_1
       134: aload_3
       135: invokedynamic #72,  0             // InvokeDynamic #0:makeConcatWithConstants:(Ljava/lang/String;Ljava/lang/String;)Ljava/lang/String;
       140: ldc           #76                 // String Success
       142: iconst_1
       143: invokestatic  #78                 // Method javax/swing/JOptionPane.showMessageDialog:(Ljava/awt/Component;Ljava/lang/Object;Ljava/lang/String;I)V
       146: goto          160
       149: astore        4
       151: aload_0
       152: ldc           #84                 // String Error parsing level!
       154: ldc           #86                 // String Error
       156: iconst_0
       157: invokestatic  #78                 // Method javax/swing/JOptionPane.showMessageDialog:(Ljava/awt/Component;Ljava/lang/Object;Ljava/lang/String;I)V
       160: return
      Exception table:
         from    to  target type
           107   146   149   Class java/lang/NumberFormatException
      LineNumberTable:
        line 36: 0
        line 38: 10
        line 39: 24
        line 42: 25
        line 46: 85
        line 48: 103
        line 50: 107
        line 51: 126
        line 52: 132
        line 55: 146
        line 53: 149
        line 54: 151
        line 57: 160
      LocalVariableTable:
        Start  Length  Slot  Name   Signature
          126      20     4 level   I
          151       9     4     e   Ljava/lang/NumberFormatException;
            0     161     0 parent   Ljavax/swing/JFrame;
           10     151     1 playerName   Ljava/lang/String;
           85      76     2 accessOptions   [Ljava/lang/String;
          103      58     3 selected   Ljava/lang/String;
      StackMapTable: number_of_entries = 4
        frame_type = 252 /* append */
          offset_delta = 24
          locals = [ class java/lang/String ]
        frame_type = 0 /* same */
        frame_type = 255 /* full_frame */
          offset_delta = 123
          locals = [ class javax/swing/JFrame, class java/lang/String, class "[Ljava/lang/String;", class java/lang/String ]
          stack = [ class java/lang/NumberFormatException ]
        frame_type = 10 /* same */

  public static void repairPlayer(javax.swing.JFrame);
    descriptor: (Ljavax/swing/JFrame;)V
    flags: (0x0009) ACC_PUBLIC, ACC_STATIC
    Code:
      stack=4, locals=3, args_size=1
         0: aload_0
         1: ldc           #7                  // String Enter player name:
         3: ldc           #88                 // String Repair Player
         5: iconst_3
         6: invokestatic  #13                 // Method javax/swing/JOptionPane.showInputDialog:(Ljava/awt/Component;Ljava/lang/Object;Ljava/lang/String;I)Ljava/lang/String;
         9: astore_1
        10: aload_1
        11: ifnull        38
        14: aload_1
        15: invokevirtual #23                 // Method java/lang/String.isEmpty:()Z
        18: ifne          38
        21: aload_1
        22: invokestatic  #90                 // Method handlerRepair:(Ljava/lang/String;)V
        25: goto          38
        28: astore_2
        29: aload_0
        30: ldc           #94                 // String Invalid player name! Please enter a valid name.
        32: ldc           #86                 // String Error
        34: iconst_0
        35: invokestatic  #78                 // Method javax/swing/JOptionPane.showMessageDialog:(Ljava/awt/Component;Ljava/lang/Object;Ljava/lang/String;I)V
        38: return
      Exception table:
         from    to  target type
            21    25    28   Class java/lang/NumberFormatException
      LineNumberTable:
        line 64: 0
        line 65: 10
        line 67: 21
        line 70: 25
        line 68: 28
        line 69: 29
        line 72: 38
      LocalVariableTable:
        Start  Length  Slot  Name   Signature
           29       9     2     e   Ljava/lang/NumberFormatException;
            0      39     0 parent   Ljavax/swing/JFrame;
           10      29     1 playerName   Ljava/lang/String;
      StackMapTable: number_of_entries = 2
        frame_type = 255 /* full_frame */
          offset_delta = 28
          locals = [ class javax/swing/JFrame, class java/lang/String ]
          stack = [ class java/lang/NumberFormatException ]
        frame_type = 9 /* same */
}
SourceFile: "PlayerActions.java"
BootstrapMethods:
  0: #272 REF_invokeStatic java/lang/invoke/StringConcatFactory.makeConcatWithConstants:(Ljava/lang/invoke/MethodHandles$Lookup;Ljava/lang/String;Ljava/lang/invoke/MethodType;Ljava/lang/String;[Ljava/lang/Object;)Ljava/lang/invoke/CallSite;
    Method arguments:
      #262 Access level of \u0001 changed to: \u0001
  1: #272 REF_invokeStatic java/lang/invoke/StringConcatFactory.makeConcatWithConstants:(Ljava/lang/invoke/MethodHandles$Lookup;Ljava/lang/String;Ljava/lang/invoke/MethodType;Ljava/lang/String;[Ljava/lang/Object;)Ljava/lang/invoke/CallSite;
    Method arguments:
      #264 Repair player name: [\u0001] Teleport to fixed location
  2: #272 REF_invokeStatic java/lang/invoke/StringConcatFactory.makeConcatWithConstants:(Ljava/lang/invoke/MethodHandles$Lookup;Ljava/lang/String;Ljava/lang/invoke/MethodType;Ljava/lang/String;[Ljava/lang/Object;)Ljava/lang/invoke/CallSite;
    Method arguments:
      #266 Repair player name: [\u0001] Teleport to town
  3: #272 REF_invokeStatic java/lang/invoke/StringConcatFactory.makeConcatWithConstants:(Ljava/lang/invoke/MethodHandles$Lookup;Ljava/lang/String;Ljava/lang/invoke/MethodType;Ljava/lang/String;[Ljava/lang/Object;)Ljava/lang/invoke/CallSite;
    Method arguments:
      #268 Change Status player name: [\u0001] accesslevel: \u0001
  4: #272 REF_invokeStatic java/lang/invoke/StringConcatFactory.makeConcatWithConstants:(Ljava/lang/invoke/MethodHandles$Lookup;Ljava/lang/String;Ljava/lang/invoke/MethodType;Ljava/lang/String;[Ljava/lang/Object;)Ljava/lang/invoke/CallSite;
    Method arguments:
      #270 Your access level has been changed to \u0001.
InnerClasses:
  public static final #283= #279 of #281; // Lookup=class java/lang/invoke/MethodHandles$Lookup of class java/lang/invoke/MethodHandles
