// Bytecode for: ext.mods.commons.gui.actions.ReloadActions
// File: ext\mods\commons\gui\actions\ReloadActions.class

Classfile /c:/Users/User/Desktop/BrProject/bin/main/ext/mods/commons/gui/actions/ReloadActions.class
  Last modified 9 de jul de 2026; size 3709 bytes
  MD5 checksum c66655fc77514de8fbfa8eac4bdaeed7
  Compiled from "ReloadActions.java"
public class ext.mods.commons.gui.actions.ReloadActions
  minor version: 0
  major version: 69
  flags: (0x0021) ACC_PUBLIC, ACC_SUPER
  this_class: #12                         // ext/mods/commons/gui/actions/ReloadActions
  super_class: #2                         // java/lang/Object
  interfaces: 0, fields: 1, methods: 11, attributes: 1
Constant pool:
    #1 = Methodref          #2.#3         // java/lang/Object."<init>":()V
    #2 = Class              #4            // java/lang/Object
    #3 = NameAndType        #5:#6         // "<init>":()V
    #4 = Utf8               java/lang/Object
    #5 = Utf8               <init>
    #6 = Utf8               ()V
    #7 = String             #8            // Select an option
    #8 = Utf8               Select an option
    #9 = Class              #10           // javax/swing/JOptionPane
   #10 = Utf8               javax/swing/JOptionPane
   #11 = Fieldref           #12.#13       // ext/mods/commons/gui/actions/ReloadActions.confirmOptions:[Ljava/lang/String;
   #12 = Class              #14           // ext/mods/commons/gui/actions/ReloadActions
   #13 = NameAndType        #15:#16       // confirmOptions:[Ljava/lang/String;
   #14 = Utf8               ext/mods/commons/gui/actions/ReloadActions
   #15 = Utf8               confirmOptions
   #16 = Utf8               [Ljava/lang/String;
   #17 = Methodref          #9.#18        // javax/swing/JOptionPane.showOptionDialog:(Ljava/awt/Component;Ljava/lang/Object;Ljava/lang/String;IILjavax/swing/Icon;[Ljava/lang/Object;Ljava/lang/Object;)I
   #18 = NameAndType        #19:#20       // showOptionDialog:(Ljava/awt/Component;Ljava/lang/Object;Ljava/lang/String;IILjavax/swing/Icon;[Ljava/lang/Object;Ljava/lang/Object;)I
   #19 = Utf8               showOptionDialog
   #20 = Utf8               (Ljava/awt/Component;Ljava/lang/Object;Ljava/lang/String;IILjavax/swing/Icon;[Ljava/lang/Object;Ljava/lang/Object;)I
   #21 = String             #22           // Reload admin access levels?
   #22 = Utf8               Reload admin access levels?
   #23 = Methodref          #12.#24       // ext/mods/commons/gui/actions/ReloadActions.confirm:(Ljavax/swing/JFrame;Ljava/lang/String;)Z
   #24 = NameAndType        #25:#26       // confirm:(Ljavax/swing/JFrame;Ljava/lang/String;)Z
   #25 = Utf8               confirm
   #26 = Utf8               (Ljavax/swing/JFrame;Ljava/lang/String;)Z
   #27 = Methodref          #28.#29       // ext/mods/gameserver/data/xml/AdminData.getInstance:()Lext/mods/gameserver/data/xml/AdminData;
   #28 = Class              #30           // ext/mods/gameserver/data/xml/AdminData
   #29 = NameAndType        #31:#32       // getInstance:()Lext/mods/gameserver/data/xml/AdminData;
   #30 = Utf8               ext/mods/gameserver/data/xml/AdminData
   #31 = Utf8               getInstance
   #32 = Utf8               ()Lext/mods/gameserver/data/xml/AdminData;
   #33 = Methodref          #28.#34       // ext/mods/gameserver/data/xml/AdminData.reload:()V
   #34 = NameAndType        #35:#6        // reload:()V
   #35 = Utf8               reload
   #36 = Fieldref           #37.#38       // java/lang/System.out:Ljava/io/PrintStream;
   #37 = Class              #39           // java/lang/System
   #38 = NameAndType        #40:#41       // out:Ljava/io/PrintStream;
   #39 = Utf8               java/lang/System
   #40 = Utf8               out
   #41 = Utf8               Ljava/io/PrintStream;
   #42 = String             #43           // Admin access levels have been reloaded.
   #43 = Utf8               Admin access levels have been reloaded.
   #44 = Methodref          #45.#46       // java/io/PrintStream.println:(Ljava/lang/String;)V
   #45 = Class              #47           // java/io/PrintStream
   #46 = NameAndType        #48:#49       // println:(Ljava/lang/String;)V
   #47 = Utf8               java/io/PrintStream
   #48 = Utf8               println
   #49 = Utf8               (Ljava/lang/String;)V
   #50 = String             #51           // Reload buylists?
   #51 = Utf8               Reload buylists?
   #52 = Methodref          #53.#54       // ext/mods/gameserver/data/manager/BuyListManager.getInstance:()Lext/mods/gameserver/data/manager/BuyListManager;
   #53 = Class              #55           // ext/mods/gameserver/data/manager/BuyListManager
   #54 = NameAndType        #31:#56       // getInstance:()Lext/mods/gameserver/data/manager/BuyListManager;
   #55 = Utf8               ext/mods/gameserver/data/manager/BuyListManager
   #56 = Utf8               ()Lext/mods/gameserver/data/manager/BuyListManager;
   #57 = Methodref          #53.#34       // ext/mods/gameserver/data/manager/BuyListManager.reload:()V
   #58 = String             #59           // Buylists have been reloaded.
   #59 = Utf8               Buylists have been reloaded.
   #60 = String             #61           // Reload configs?
   #61 = Utf8               Reload configs?
   #62 = Methodref          #63.#64       // ext/mods/Config.loadGameServer:()V
   #63 = Class              #65           // ext/mods/Config
   #64 = NameAndType        #66:#6        // loadGameServer:()V
   #65 = Utf8               ext/mods/Config
   #66 = Utf8               loadGameServer
   #67 = String             #68           // Configs files have been reloaded.
   #68 = Utf8               Configs files have been reloaded.
   #69 = String             #70           // Reload Random Farm Event?
   #70 = Utf8               Reload Random Farm Event?
   #71 = Methodref          #72.#73       // ext/mods/Crypta/RandomManager.getInstance:()Lext/mods/Crypta/RandomManager;
   #72 = Class              #74           // ext/mods/Crypta/RandomManager
   #73 = NameAndType        #31:#75       // getInstance:()Lext/mods/Crypta/RandomManager;
   #74 = Utf8               ext/mods/Crypta/RandomManager
   #75 = Utf8               ()Lext/mods/Crypta/RandomManager;
   #76 = String             #77           // AdminGui: RandomManager is not available.
   #77 = Utf8               AdminGui: RandomManager is not available.
   #78 = Methodref          #72.#34       // ext/mods/Crypta/RandomManager.reload:()V
   #79 = String             #80           // Random Farm Mod has been reloaded.
   #80 = Utf8               Random Farm Mod has been reloaded.
   #81 = Class              #82           // java/lang/Exception
   #82 = Utf8               java/lang/Exception
   #83 = String             #84           // AdminGui: Error accessing RandomManager.
   #84 = Utf8               AdminGui: Error accessing RandomManager.
   #85 = Methodref          #81.#86       // java/lang/Exception.printStackTrace:()V
   #86 = NameAndType        #87:#6        // printStackTrace:()V
   #87 = Utf8               printStackTrace
   #88 = String             #89           // Reload Items data files?
   #89 = Utf8               Reload Items data files?
   #90 = Methodref          #91.#92       // ext/mods/gameserver/data/xml/ItemData.getInstance:()Lext/mods/gameserver/data/xml/ItemData;
   #91 = Class              #93           // ext/mods/gameserver/data/xml/ItemData
   #92 = NameAndType        #31:#94       // getInstance:()Lext/mods/gameserver/data/xml/ItemData;
   #93 = Utf8               ext/mods/gameserver/data/xml/ItemData
   #94 = Utf8               ()Lext/mods/gameserver/data/xml/ItemData;
   #95 = Methodref          #91.#34       // ext/mods/gameserver/data/xml/ItemData.reload:()V
   #96 = String             #97           // Items\' templates have been reloaded.
   #97 = Utf8               Items\' templates have been reloaded.
   #98 = String             #99           // Reload multisells?
   #99 = Utf8               Reload multisells?
  #100 = Methodref          #101.#102     // ext/mods/gameserver/data/xml/MultisellData.getInstance:()Lext/mods/gameserver/data/xml/MultisellData;
  #101 = Class              #103          // ext/mods/gameserver/data/xml/MultisellData
  #102 = NameAndType        #31:#104      // getInstance:()Lext/mods/gameserver/data/xml/MultisellData;
  #103 = Utf8               ext/mods/gameserver/data/xml/MultisellData
  #104 = Utf8               ()Lext/mods/gameserver/data/xml/MultisellData;
  #105 = Methodref          #101.#34      // ext/mods/gameserver/data/xml/MultisellData.reload:()V
  #106 = String             #107          // The multisell instance has been reloaded.
  #107 = Utf8               The multisell instance has been reloaded.
  #108 = String             #109          // Reload Skills data files?
  #109 = Utf8               Reload Skills data files?
  #110 = Methodref          #111.#112     // ext/mods/gameserver/data/SkillTable.getInstance:()Lext/mods/gameserver/data/SkillTable;
  #111 = Class              #113          // ext/mods/gameserver/data/SkillTable
  #112 = NameAndType        #31:#114      // getInstance:()Lext/mods/gameserver/data/SkillTable;
  #113 = Utf8               ext/mods/gameserver/data/SkillTable
  #114 = Utf8               ()Lext/mods/gameserver/data/SkillTable;
  #115 = Methodref          #111.#34      // ext/mods/gameserver/data/SkillTable.reload:()V
  #116 = String             #117          // Skills\' XMLs have been reloaded.
  #117 = Utf8               Skills\' XMLs have been reloaded.
  #118 = String             #119          // Reload Zone Data files?
  #119 = Utf8               Reload Zone Data files?
  #120 = Methodref          #121.#122     // ext/mods/gameserver/data/manager/ZoneManager.getInstance:()Lext/mods/gameserver/data/manager/ZoneManager;
  #121 = Class              #123          // ext/mods/gameserver/data/manager/ZoneManager
  #122 = NameAndType        #31:#124      // getInstance:()Lext/mods/gameserver/data/manager/ZoneManager;
  #123 = Utf8               ext/mods/gameserver/data/manager/ZoneManager
  #124 = Utf8               ()Lext/mods/gameserver/data/manager/ZoneManager;
  #125 = Methodref          #121.#34      // ext/mods/gameserver/data/manager/ZoneManager.reload:()V
  #126 = String             #127          // Zones have been reloaded.
  #127 = Utf8               Zones have been reloaded.
  #128 = Class              #129          // java/lang/String
  #129 = Utf8               java/lang/String
  #130 = String             #131          // Reload
  #131 = Utf8               Reload
  #132 = String             #133          // Cancel
  #133 = Utf8               Cancel
  #134 = Utf8               Code
  #135 = Utf8               LineNumberTable
  #136 = Utf8               LocalVariableTable
  #137 = Utf8               this
  #138 = Utf8               Lext/mods/commons/gui/actions/ReloadActions;
  #139 = Utf8               parent
  #140 = Utf8               Ljavax/swing/JFrame;
  #141 = Utf8               message
  #142 = Utf8               Ljava/lang/String;
  #143 = Utf8               StackMapTable
  #144 = Utf8               reloadAccess
  #145 = Utf8               (Ljavax/swing/JFrame;)V
  #146 = Utf8               reloadBuylists
  #147 = Utf8               reloadConfigs
  #148 = Utf8               reloadFarmEvent
  #149 = Utf8               e
  #150 = Utf8               Ljava/lang/Exception;
  #151 = Utf8               RandomManagerIntance
  #152 = Utf8               Ljava/lang/Object;
  #153 = Utf8               reloadItems
  #154 = Utf8               reloadMultisells
  #155 = Utf8               reloadSkills
  #156 = Utf8               reloadZones
  #157 = Utf8               <clinit>
  #158 = Utf8               SourceFile
  #159 = Utf8               ReloadActions.java
{
  public ext.mods.commons.gui.actions.ReloadActions();
    descriptor: ()V
    flags: (0x0001) ACC_PUBLIC
    Code:
      stack=1, locals=1, args_size=1
         0: aload_0
         1: invokespecial #1                  // Method java/lang/Object."<init>":()V
         4: return
      LineNumberTable:
        line 31: 0
      LocalVariableTable:
        Start  Length  Slot  Name   Signature
            0       5     0  this   Lext/mods/commons/gui/actions/ReloadActions;

  public static void reloadAccess(javax.swing.JFrame);
    descriptor: (Ljavax/swing/JFrame;)V
    flags: (0x0009) ACC_PUBLIC, ACC_STATIC
    Code:
      stack=2, locals=1, args_size=1
         0: aload_0
         1: ldc           #21                 // String Reload admin access levels?
         3: invokestatic  #23                 // Method confirm:(Ljavax/swing/JFrame;Ljava/lang/String;)Z
         6: ifeq          23
         9: invokestatic  #27                 // Method ext/mods/gameserver/data/xml/AdminData.getInstance:()Lext/mods/gameserver/data/xml/AdminData;
        12: invokevirtual #33                 // Method ext/mods/gameserver/data/xml/AdminData.reload:()V
        15: getstatic     #36                 // Field java/lang/System.out:Ljava/io/PrintStream;
        18: ldc           #42                 // String Admin access levels have been reloaded.
        20: invokevirtual #44                 // Method java/io/PrintStream.println:(Ljava/lang/String;)V
        23: return
      LineNumberTable:
        line 40: 0
        line 41: 9
        line 42: 15
        line 44: 23
      LocalVariableTable:
        Start  Length  Slot  Name   Signature
            0      24     0 parent   Ljavax/swing/JFrame;
      StackMapTable: number_of_entries = 1
        frame_type = 23 /* same */

  public static void reloadBuylists(javax.swing.JFrame);
    descriptor: (Ljavax/swing/JFrame;)V
    flags: (0x0009) ACC_PUBLIC, ACC_STATIC
    Code:
      stack=2, locals=1, args_size=1
         0: aload_0
         1: ldc           #50                 // String Reload buylists?
         3: invokestatic  #23                 // Method confirm:(Ljavax/swing/JFrame;Ljava/lang/String;)Z
         6: ifeq          23
         9: invokestatic  #52                 // Method ext/mods/gameserver/data/manager/BuyListManager.getInstance:()Lext/mods/gameserver/data/manager/BuyListManager;
        12: invokevirtual #57                 // Method ext/mods/gameserver/data/manager/BuyListManager.reload:()V
        15: getstatic     #36                 // Field java/lang/System.out:Ljava/io/PrintStream;
        18: ldc           #58                 // String Buylists have been reloaded.
        20: invokevirtual #44                 // Method java/io/PrintStream.println:(Ljava/lang/String;)V
        23: return
      LineNumberTable:
        line 47: 0
        line 48: 9
        line 49: 15
        line 51: 23
      LocalVariableTable:
        Start  Length  Slot  Name   Signature
            0      24     0 parent   Ljavax/swing/JFrame;
      StackMapTable: number_of_entries = 1
        frame_type = 23 /* same */

  public static void reloadConfigs(javax.swing.JFrame);
    descriptor: (Ljavax/swing/JFrame;)V
    flags: (0x0009) ACC_PUBLIC, ACC_STATIC
    Code:
      stack=2, locals=1, args_size=1
         0: aload_0
         1: ldc           #60                 // String Reload configs?
         3: invokestatic  #23                 // Method confirm:(Ljavax/swing/JFrame;Ljava/lang/String;)Z
         6: ifeq          20
         9: invokestatic  #62                 // Method ext/mods/Config.loadGameServer:()V
        12: getstatic     #36                 // Field java/lang/System.out:Ljava/io/PrintStream;
        15: ldc           #67                 // String Configs files have been reloaded.
        17: invokevirtual #44                 // Method java/io/PrintStream.println:(Ljava/lang/String;)V
        20: return
      LineNumberTable:
        line 54: 0
        line 55: 9
        line 56: 12
        line 58: 20
      LocalVariableTable:
        Start  Length  Slot  Name   Signature
            0      21     0 parent   Ljavax/swing/JFrame;
      StackMapTable: number_of_entries = 1
        frame_type = 20 /* same */

  public static void reloadFarmEvent(javax.swing.JFrame);
    descriptor: (Ljavax/swing/JFrame;)V
    flags: (0x0009) ACC_PUBLIC, ACC_STATIC
    Code:
      stack=2, locals=3, args_size=1
         0: aload_0
         1: ldc           #69                 // String Reload Random Farm Event?
         3: invokestatic  #23                 // Method confirm:(Ljavax/swing/JFrame;Ljava/lang/String;)Z
         6: ifeq          57
         9: invokestatic  #71                 // Method ext/mods/Crypta/RandomManager.getInstance:()Lext/mods/Crypta/RandomManager;
        12: astore_1
        13: aload_1
        14: ifnonnull     26
        17: getstatic     #36                 // Field java/lang/System.out:Ljava/io/PrintStream;
        20: ldc           #76                 // String AdminGui: RandomManager is not available.
        22: invokevirtual #44                 // Method java/io/PrintStream.println:(Ljava/lang/String;)V
        25: return
        26: invokestatic  #71                 // Method ext/mods/Crypta/RandomManager.getInstance:()Lext/mods/Crypta/RandomManager;
        29: invokevirtual #78                 // Method ext/mods/Crypta/RandomManager.reload:()V
        32: getstatic     #36                 // Field java/lang/System.out:Ljava/io/PrintStream;
        35: ldc           #79                 // String Random Farm Mod has been reloaded.
        37: invokevirtual #44                 // Method java/io/PrintStream.println:(Ljava/lang/String;)V
        40: goto          57
        43: astore_2
        44: getstatic     #36                 // Field java/lang/System.out:Ljava/io/PrintStream;
        47: ldc           #83                 // String AdminGui: Error accessing RandomManager.
        49: invokevirtual #44                 // Method java/io/PrintStream.println:(Ljava/lang/String;)V
        52: aload_2
        53: invokevirtual #85                 // Method java/lang/Exception.printStackTrace:()V
        56: return
        57: return
      Exception table:
         from    to  target type
            26    40    43   Class java/lang/Exception
      LineNumberTable:
        line 61: 0
        line 63: 9
        line 64: 13
        line 66: 17
        line 67: 25
        line 72: 26
        line 73: 32
        line 80: 40
        line 75: 43
        line 77: 44
        line 78: 52
        line 79: 56
        line 83: 57
      LocalVariableTable:
        Start  Length  Slot  Name   Signature
           44      13     2     e   Ljava/lang/Exception;
           13      44     1 RandomManagerIntance   Ljava/lang/Object;
            0      58     0 parent   Ljavax/swing/JFrame;
      StackMapTable: number_of_entries = 3
        frame_type = 252 /* append */
          offset_delta = 26
          locals = [ class java/lang/Object ]
        frame_type = 80 /* same_locals_1_stack_item */
          stack = [ class java/lang/Exception ]
        frame_type = 250 /* chop */
          offset_delta = 13

  public static void reloadItems(javax.swing.JFrame);
    descriptor: (Ljavax/swing/JFrame;)V
    flags: (0x0009) ACC_PUBLIC, ACC_STATIC
    Code:
      stack=2, locals=1, args_size=1
         0: aload_0
         1: ldc           #88                 // String Reload Items data files?
         3: invokestatic  #23                 // Method confirm:(Ljavax/swing/JFrame;Ljava/lang/String;)Z
         6: ifeq          23
         9: invokestatic  #90                 // Method ext/mods/gameserver/data/xml/ItemData.getInstance:()Lext/mods/gameserver/data/xml/ItemData;
        12: invokevirtual #95                 // Method ext/mods/gameserver/data/xml/ItemData.reload:()V
        15: getstatic     #36                 // Field java/lang/System.out:Ljava/io/PrintStream;
        18: ldc           #96                 // String Items\' templates have been reloaded.
        20: invokevirtual #44                 // Method java/io/PrintStream.println:(Ljava/lang/String;)V
        23: return
      LineNumberTable:
        line 86: 0
        line 87: 9
        line 88: 15
        line 90: 23
      LocalVariableTable:
        Start  Length  Slot  Name   Signature
            0      24     0 parent   Ljavax/swing/JFrame;
      StackMapTable: number_of_entries = 1
        frame_type = 23 /* same */

  public static void reloadMultisells(javax.swing.JFrame);
    descriptor: (Ljavax/swing/JFrame;)V
    flags: (0x0009) ACC_PUBLIC, ACC_STATIC
    Code:
      stack=2, locals=1, args_size=1
         0: aload_0
         1: ldc           #98                 // String Reload multisells?
         3: invokestatic  #23                 // Method confirm:(Ljavax/swing/JFrame;Ljava/lang/String;)Z
         6: ifeq          23
         9: invokestatic  #100                // Method ext/mods/gameserver/data/xml/MultisellData.getInstance:()Lext/mods/gameserver/data/xml/MultisellData;
        12: invokevirtual #105                // Method ext/mods/gameserver/data/xml/MultisellData.reload:()V
        15: getstatic     #36                 // Field java/lang/System.out:Ljava/io/PrintStream;
        18: ldc           #106                // String The multisell instance has been reloaded.
        20: invokevirtual #44                 // Method java/io/PrintStream.println:(Ljava/lang/String;)V
        23: return
      LineNumberTable:
        line 93: 0
        line 94: 9
        line 95: 15
        line 97: 23
      LocalVariableTable:
        Start  Length  Slot  Name   Signature
            0      24     0 parent   Ljavax/swing/JFrame;
      StackMapTable: number_of_entries = 1
        frame_type = 23 /* same */

  public static void reloadSkills(javax.swing.JFrame);
    descriptor: (Ljavax/swing/JFrame;)V
    flags: (0x0009) ACC_PUBLIC, ACC_STATIC
    Code:
      stack=2, locals=1, args_size=1
         0: aload_0
         1: ldc           #108                // String Reload Skills data files?
         3: invokestatic  #23                 // Method confirm:(Ljavax/swing/JFrame;Ljava/lang/String;)Z
         6: ifeq          23
         9: invokestatic  #110                // Method ext/mods/gameserver/data/SkillTable.getInstance:()Lext/mods/gameserver/data/SkillTable;
        12: invokevirtual #115                // Method ext/mods/gameserver/data/SkillTable.reload:()V
        15: getstatic     #36                 // Field java/lang/System.out:Ljava/io/PrintStream;
        18: ldc           #116                // String Skills\' XMLs have been reloaded.
        20: invokevirtual #44                 // Method java/io/PrintStream.println:(Ljava/lang/String;)V
        23: return
      LineNumberTable:
        line 100: 0
        line 101: 9
        line 102: 15
        line 104: 23
      LocalVariableTable:
        Start  Length  Slot  Name   Signature
            0      24     0 parent   Ljavax/swing/JFrame;
      StackMapTable: number_of_entries = 1
        frame_type = 23 /* same */

  public static void reloadZones(javax.swing.JFrame);
    descriptor: (Ljavax/swing/JFrame;)V
    flags: (0x0009) ACC_PUBLIC, ACC_STATIC
    Code:
      stack=2, locals=1, args_size=1
         0: aload_0
         1: ldc           #118                // String Reload Zone Data files?
         3: invokestatic  #23                 // Method confirm:(Ljavax/swing/JFrame;Ljava/lang/String;)Z
         6: ifeq          23
         9: invokestatic  #120                // Method ext/mods/gameserver/data/manager/ZoneManager.getInstance:()Lext/mods/gameserver/data/manager/ZoneManager;
        12: invokevirtual #125                // Method ext/mods/gameserver/data/manager/ZoneManager.reload:()V
        15: getstatic     #36                 // Field java/lang/System.out:Ljava/io/PrintStream;
        18: ldc           #126                // String Zones have been reloaded.
        20: invokevirtual #44                 // Method java/io/PrintStream.println:(Ljava/lang/String;)V
        23: return
      LineNumberTable:
        line 107: 0
        line 108: 9
        line 109: 15
        line 111: 23
      LocalVariableTable:
        Start  Length  Slot  Name   Signature
            0      24     0 parent   Ljavax/swing/JFrame;
      StackMapTable: number_of_entries = 1
        frame_type = 23 /* same */

  static {};
    descriptor: ()V
    flags: (0x0008) ACC_STATIC
    Code:
      stack=4, locals=0, args_size=0
         0: iconst_2
         1: anewarray     #128                // class java/lang/String
         4: dup
         5: iconst_0
         6: ldc           #130                // String Reload
         8: aastore
         9: dup
        10: iconst_1
        11: ldc           #132                // String Cancel
        13: aastore
        14: putstatic     #11                 // Field confirmOptions:[Ljava/lang/String;
        17: return
      LineNumberTable:
        line 33: 0
}
SourceFile: "ReloadActions.java"
