// Bytecode for: ext.mods.commons.gui.actions.ServerActions
// File: ext\mods\commons\gui\actions\ServerActions.class

Classfile /c:/Users/User/Desktop/BrProject/bin/main/ext/mods/commons/gui/actions/ServerActions.class
  Last modified 9 de jul de 2026; size 2771 bytes
  MD5 checksum 7fe4235e45b1bb4ae4c42dae967f3a18
  Compiled from "ServerActions.java"
public class ext.mods.commons.gui.actions.ServerActions
  minor version: 0
  major version: 69
  flags: (0x0021) ACC_PUBLIC, ACC_SUPER
  this_class: #14                         // ext/mods/commons/gui/actions/ServerActions
  super_class: #2                         // java/lang/Object
  interfaces: 0, fields: 3, methods: 7, attributes: 1
Constant pool:
    #1 = Methodref          #2.#3         // java/lang/Object."<init>":()V
    #2 = Class              #4            // java/lang/Object
    #3 = NameAndType        #5:#6         // "<init>":()V
    #4 = Utf8               java/lang/Object
    #5 = Utf8               <init>
    #6 = Utf8               ()V
    #7 = String             #8            // Shutdown GameServer?
    #8 = Utf8               Shutdown GameServer?
    #9 = String             #10           // Select an option
   #10 = Utf8               Select an option
   #11 = Class              #12           // javax/swing/JOptionPane
   #12 = Utf8               javax/swing/JOptionPane
   #13 = Fieldref           #14.#15       // ext/mods/commons/gui/actions/ServerActions.shutdownOptions:[Ljava/lang/String;
   #14 = Class              #16           // ext/mods/commons/gui/actions/ServerActions
   #15 = NameAndType        #17:#18       // shutdownOptions:[Ljava/lang/String;
   #16 = Utf8               ext/mods/commons/gui/actions/ServerActions
   #17 = Utf8               shutdownOptions
   #18 = Utf8               [Ljava/lang/String;
   #19 = Methodref          #11.#20       // javax/swing/JOptionPane.showOptionDialog:(Ljava/awt/Component;Ljava/lang/Object;Ljava/lang/String;IILjavax/swing/Icon;[Ljava/lang/Object;Ljava/lang/Object;)I
   #20 = NameAndType        #21:#22       // showOptionDialog:(Ljava/awt/Component;Ljava/lang/Object;Ljava/lang/String;IILjavax/swing/Icon;[Ljava/lang/Object;Ljava/lang/Object;)I
   #21 = Utf8               showOptionDialog
   #22 = Utf8               (Ljava/awt/Component;Ljava/lang/Object;Ljava/lang/String;IILjavax/swing/Icon;[Ljava/lang/Object;Ljava/lang/Object;)I
   #23 = String             #24           // Shutdown delay in seconds
   #24 = Utf8               Shutdown delay in seconds
   #25 = String             #26           // Input
   #26 = Utf8               Input
   #27 = String             #28           // 600
   #28 = Utf8               600
   #29 = Methodref          #11.#30       // javax/swing/JOptionPane.showInputDialog:(Ljava/awt/Component;Ljava/lang/Object;Ljava/lang/String;ILjavax/swing/Icon;[Ljava/lang/Object;Ljava/lang/Object;)Ljava/lang/Object;
   #30 = NameAndType        #31:#32       // showInputDialog:(Ljava/awt/Component;Ljava/lang/Object;Ljava/lang/String;ILjavax/swing/Icon;[Ljava/lang/Object;Ljava/lang/Object;)Ljava/lang/Object;
   #31 = Utf8               showInputDialog
   #32 = Utf8               (Ljava/awt/Component;Ljava/lang/Object;Ljava/lang/String;ILjavax/swing/Icon;[Ljava/lang/Object;Ljava/lang/Object;)Ljava/lang/Object;
   #33 = Class              #34           // java/lang/String
   #34 = Utf8               java/lang/String
   #35 = Methodref          #33.#36       // java/lang/String.trim:()Ljava/lang/String;
   #36 = NameAndType        #37:#38       // trim:()Ljava/lang/String;
   #37 = Utf8               trim
   #38 = Utf8               ()Ljava/lang/String;
   #39 = Methodref          #40.#41       // ext/mods/commons/gui/GuiUtils.isDigit:(Ljava/lang/String;)Z
   #40 = Class              #42           // ext/mods/commons/gui/GuiUtils
   #41 = NameAndType        #43:#44       // isDigit:(Ljava/lang/String;)Z
   #42 = Utf8               ext/mods/commons/gui/GuiUtils
   #43 = Utf8               isDigit
   #44 = Utf8               (Ljava/lang/String;)Z
   #45 = Methodref          #46.#47       // java/lang/Integer.parseInt:(Ljava/lang/String;)I
   #46 = Class              #48           // java/lang/Integer
   #47 = NameAndType        #49:#50       // parseInt:(Ljava/lang/String;)I
   #48 = Utf8               java/lang/Integer
   #49 = Utf8               parseInt
   #50 = Utf8               (Ljava/lang/String;)I
   #51 = Methodref          #52.#53       // ext/mods/gameserver/Shutdown.getInstance:()Lext/mods/gameserver/Shutdown;
   #52 = Class              #54           // ext/mods/gameserver/Shutdown
   #53 = NameAndType        #55:#56       // getInstance:()Lext/mods/gameserver/Shutdown;
   #54 = Utf8               ext/mods/gameserver/Shutdown
   #55 = Utf8               getInstance
   #56 = Utf8               ()Lext/mods/gameserver/Shutdown;
   #57 = Methodref          #52.#58       // ext/mods/gameserver/Shutdown.startShutdown:(Lext/mods/gameserver/model/actor/Player;IZ)V
   #58 = NameAndType        #59:#60       // startShutdown:(Lext/mods/gameserver/model/actor/Player;IZ)V
   #59 = Utf8               startShutdown
   #60 = Utf8               (Lext/mods/gameserver/model/actor/Player;IZ)V
   #61 = String             #62           // Restart GameServer?
   #62 = Utf8               Restart GameServer?
   #63 = Fieldref           #14.#64       // ext/mods/commons/gui/actions/ServerActions.restartOptions:[Ljava/lang/String;
   #64 = NameAndType        #65:#18       // restartOptions:[Ljava/lang/String;
   #65 = Utf8               restartOptions
   #66 = String             #67           // Restart delay in seconds
   #67 = Utf8               Restart delay in seconds
   #68 = String             #69           // Abort server shutdown?
   #69 = Utf8               Abort server shutdown?
   #70 = Fieldref           #14.#71       // ext/mods/commons/gui/actions/ServerActions.abortOptions:[Ljava/lang/String;
   #71 = NameAndType        #72:#18       // abortOptions:[Ljava/lang/String;
   #72 = Utf8               abortOptions
   #73 = Methodref          #52.#74       // ext/mods/gameserver/Shutdown.abort:(Lext/mods/gameserver/model/actor/Player;)V
   #74 = NameAndType        #75:#76       // abort:(Lext/mods/gameserver/model/actor/Player;)V
   #75 = Utf8               abort
   #76 = Utf8               (Lext/mods/gameserver/model/actor/Player;)V
   #77 = String             #78           // Announce message
   #78 = Utf8               Announce message
   #79 = String             #80           //
   #80 = Utf8
   #81 = Methodref          #33.#82       // java/lang/String.isEmpty:()Z
   #82 = NameAndType        #83:#84       // isEmpty:()Z
   #83 = Utf8               isEmpty
   #84 = Utf8               ()Z
   #85 = Methodref          #86.#87       // ext/mods/gameserver/model/World.announceToOnlinePlayers:(Ljava/lang/String;Z)V
   #86 = Class              #88           // ext/mods/gameserver/model/World
   #87 = NameAndType        #89:#90       // announceToOnlinePlayers:(Ljava/lang/String;Z)V
   #88 = Utf8               ext/mods/gameserver/model/World
   #89 = Utf8               announceToOnlinePlayers
   #90 = Utf8               (Ljava/lang/String;Z)V
   #91 = String             #92           // Critical announce message
   #92 = Utf8               Critical announce message
   #93 = String             #94           // Shutdown
   #94 = Utf8               Shutdown
   #95 = String             #96           // Cancel
   #96 = Utf8               Cancel
   #97 = String             #98           // Restart
   #98 = Utf8               Restart
   #99 = String             #100          // Abort
  #100 = Utf8               Abort
  #101 = Utf8               Code
  #102 = Utf8               LineNumberTable
  #103 = Utf8               LocalVariableTable
  #104 = Utf8               this
  #105 = Utf8               Lext/mods/commons/gui/actions/ServerActions;
  #106 = Utf8               shutdown
  #107 = Utf8               (Ljavax/swing/JFrame;)V
  #108 = Utf8               delay
  #109 = Utf8               I
  #110 = Utf8               input
  #111 = Utf8               Ljava/lang/String;
  #112 = Utf8               answer
  #113 = Utf8               Ljava/lang/Object;
  #114 = Utf8               parent
  #115 = Utf8               Ljavax/swing/JFrame;
  #116 = Utf8               StackMapTable
  #117 = Utf8               restart
  #118 = Utf8               normalAnnounce
  #119 = Utf8               message
  #120 = Utf8               criticalAnnounce
  #121 = Utf8               <clinit>
  #122 = Utf8               SourceFile
  #123 = Utf8               ServerActions.java
{
  public ext.mods.commons.gui.actions.ServerActions();
    descriptor: ()V
    flags: (0x0001) ACC_PUBLIC
    Code:
      stack=1, locals=1, args_size=1
         0: aload_0
         1: invokespecial #1                  // Method java/lang/Object."<init>":()V
         4: return
      LineNumberTable:
        line 26: 0
      LocalVariableTable:
        Start  Length  Slot  Name   Signature
            0       5     0  this   Lext/mods/commons/gui/actions/ServerActions;

  public static void shutdown(javax.swing.JFrame);
    descriptor: (Ljavax/swing/JFrame;)V
    flags: (0x0009) ACC_PUBLIC, ACC_STATIC
    Code:
      stack=9, locals=4, args_size=1
         0: aload_0
         1: ldc           #7                  // String Shutdown GameServer?
         3: ldc           #9                  // String Select an option
         5: iconst_0
         6: iconst_3
         7: aconst_null
         8: getstatic     #13                 // Field shutdownOptions:[Ljava/lang/String;
        11: getstatic     #13                 // Field shutdownOptions:[Ljava/lang/String;
        14: iconst_1
        15: aaload
        16: invokestatic  #19                 // Method javax/swing/JOptionPane.showOptionDialog:(Ljava/awt/Component;Ljava/lang/Object;Ljava/lang/String;IILjavax/swing/Icon;[Ljava/lang/Object;Ljava/lang/Object;)I
        19: ifne          73
        22: aload_0
        23: ldc           #23                 // String Shutdown delay in seconds
        25: ldc           #25                 // String Input
        27: iconst_1
        28: aconst_null
        29: aconst_null
        30: ldc           #27                 // String 600
        32: invokestatic  #29                 // Method javax/swing/JOptionPane.showInputDialog:(Ljava/awt/Component;Ljava/lang/Object;Ljava/lang/String;ILjavax/swing/Icon;[Ljava/lang/Object;Ljava/lang/Object;)Ljava/lang/Object;
        35: astore_1
        36: aload_1
        37: ifnull        73
        40: aload_1
        41: checkcast     #33                 // class java/lang/String
        44: invokevirtual #35                 // Method java/lang/String.trim:()Ljava/lang/String;
        47: astore_2
        48: aload_2
        49: invokestatic  #39                 // Method ext/mods/commons/gui/GuiUtils.isDigit:(Ljava/lang/String;)Z
        52: ifeq          73
        55: aload_2
        56: invokestatic  #45                 // Method java/lang/Integer.parseInt:(Ljava/lang/String;)I
        59: istore_3
        60: iload_3
        61: ifle          73
        64: invokestatic  #51                 // Method ext/mods/gameserver/Shutdown.getInstance:()Lext/mods/gameserver/Shutdown;
        67: aconst_null
        68: iload_3
        69: iconst_0
        70: invokevirtual #57                 // Method ext/mods/gameserver/Shutdown.startShutdown:(Lext/mods/gameserver/model/actor/Player;IZ)V
        73: return
      LineNumberTable:
        line 37: 0
        line 38: 22
        line 39: 36
        line 40: 40
        line 41: 48
        line 42: 55
        line 43: 60
        line 44: 64
        line 49: 73
      LocalVariableTable:
        Start  Length  Slot  Name   Signature
           60      13     3 delay   I
           48      25     2 input   Ljava/lang/String;
           36      37     1 answer   Ljava/lang/Object;
            0      74     0 parent   Ljavax/swing/JFrame;
      StackMapTable: number_of_entries = 1
        frame_type = 251 /* same_frame_extended */
          offset_delta = 73

  public static void restart(javax.swing.JFrame);
    descriptor: (Ljavax/swing/JFrame;)V
    flags: (0x0009) ACC_PUBLIC, ACC_STATIC
    Code:
      stack=9, locals=4, args_size=1
         0: aload_0
         1: ldc           #61                 // String Restart GameServer?
         3: ldc           #9                  // String Select an option
         5: iconst_0
         6: iconst_3
         7: aconst_null
         8: getstatic     #63                 // Field restartOptions:[Ljava/lang/String;
        11: getstatic     #63                 // Field restartOptions:[Ljava/lang/String;
        14: iconst_1
        15: aaload
        16: invokestatic  #19                 // Method javax/swing/JOptionPane.showOptionDialog:(Ljava/awt/Component;Ljava/lang/Object;Ljava/lang/String;IILjavax/swing/Icon;[Ljava/lang/Object;Ljava/lang/Object;)I
        19: ifne          73
        22: aload_0
        23: ldc           #66                 // String Restart delay in seconds
        25: ldc           #25                 // String Input
        27: iconst_1
        28: aconst_null
        29: aconst_null
        30: ldc           #27                 // String 600
        32: invokestatic  #29                 // Method javax/swing/JOptionPane.showInputDialog:(Ljava/awt/Component;Ljava/lang/Object;Ljava/lang/String;ILjavax/swing/Icon;[Ljava/lang/Object;Ljava/lang/Object;)Ljava/lang/Object;
        35: astore_1
        36: aload_1
        37: ifnull        73
        40: aload_1
        41: checkcast     #33                 // class java/lang/String
        44: invokevirtual #35                 // Method java/lang/String.trim:()Ljava/lang/String;
        47: astore_2
        48: aload_2
        49: invokestatic  #39                 // Method ext/mods/commons/gui/GuiUtils.isDigit:(Ljava/lang/String;)Z
        52: ifeq          73
        55: aload_2
        56: invokestatic  #45                 // Method java/lang/Integer.parseInt:(Ljava/lang/String;)I
        59: istore_3
        60: iload_3
        61: ifle          73
        64: invokestatic  #51                 // Method ext/mods/gameserver/Shutdown.getInstance:()Lext/mods/gameserver/Shutdown;
        67: aconst_null
        68: iload_3
        69: iconst_1
        70: invokevirtual #57                 // Method ext/mods/gameserver/Shutdown.startShutdown:(Lext/mods/gameserver/model/actor/Player;IZ)V
        73: return
      LineNumberTable:
        line 56: 0
        line 57: 22
        line 58: 36
        line 59: 40
        line 60: 48
        line 61: 55
        line 62: 60
        line 63: 64
        line 68: 73
      LocalVariableTable:
        Start  Length  Slot  Name   Signature
           60      13     3 delay   I
           48      25     2 input   Ljava/lang/String;
           36      37     1 answer   Ljava/lang/Object;
            0      74     0 parent   Ljavax/swing/JFrame;
      StackMapTable: number_of_entries = 1
        frame_type = 251 /* same_frame_extended */
          offset_delta = 73

  public static void abort(javax.swing.JFrame);
    descriptor: (Ljavax/swing/JFrame;)V
    flags: (0x0009) ACC_PUBLIC, ACC_STATIC
    Code:
      stack=9, locals=1, args_size=1
         0: aload_0
         1: ldc           #68                 // String Abort server shutdown?
         3: ldc           #9                  // String Select an option
         5: iconst_0
         6: iconst_3
         7: aconst_null
         8: getstatic     #70                 // Field abortOptions:[Ljava/lang/String;
        11: getstatic     #70                 // Field abortOptions:[Ljava/lang/String;
        14: iconst_1
        15: aaload
        16: invokestatic  #19                 // Method javax/swing/JOptionPane.showOptionDialog:(Ljava/awt/Component;Ljava/lang/Object;Ljava/lang/String;IILjavax/swing/Icon;[Ljava/lang/Object;Ljava/lang/Object;)I
        19: ifne          29
        22: invokestatic  #51                 // Method ext/mods/gameserver/Shutdown.getInstance:()Lext/mods/gameserver/Shutdown;
        25: aconst_null
        26: invokevirtual #73                 // Method ext/mods/gameserver/Shutdown.abort:(Lext/mods/gameserver/model/actor/Player;)V
        29: return
      LineNumberTable:
        line 75: 0
        line 76: 22
        line 78: 29
      LocalVariableTable:
        Start  Length  Slot  Name   Signature
            0      30     0 parent   Ljavax/swing/JFrame;
      StackMapTable: number_of_entries = 1
        frame_type = 29 /* same */

  public static void normalAnnounce(javax.swing.JFrame);
    descriptor: (Ljavax/swing/JFrame;)V
    flags: (0x0009) ACC_PUBLIC, ACC_STATIC
    Code:
      stack=7, locals=3, args_size=1
         0: aload_0
         1: ldc           #77                 // String Announce message
         3: ldc           #25                 // String Input
         5: iconst_1
         6: aconst_null
         7: aconst_null
         8: ldc           #79                 // String
        10: invokestatic  #29                 // Method javax/swing/JOptionPane.showInputDialog:(Ljava/awt/Component;Ljava/lang/Object;Ljava/lang/String;ILjavax/swing/Icon;[Ljava/lang/Object;Ljava/lang/Object;)Ljava/lang/Object;
        13: astore_1
        14: aload_1
        15: ifnull        38
        18: aload_1
        19: checkcast     #33                 // class java/lang/String
        22: invokevirtual #35                 // Method java/lang/String.trim:()Ljava/lang/String;
        25: astore_2
        26: aload_2
        27: invokevirtual #81                 // Method java/lang/String.isEmpty:()Z
        30: ifne          38
        33: aload_2
        34: iconst_0
        35: invokestatic  #85                 // Method ext/mods/gameserver/model/World.announceToOnlinePlayers:(Ljava/lang/String;Z)V
        38: return
      LineNumberTable:
        line 85: 0
        line 86: 14
        line 87: 18
        line 88: 26
        line 89: 33
        line 92: 38
      LocalVariableTable:
        Start  Length  Slot  Name   Signature
           26      12     2 message   Ljava/lang/String;
            0      39     0 parent   Ljavax/swing/JFrame;
           14      25     1 input   Ljava/lang/Object;
      StackMapTable: number_of_entries = 1
        frame_type = 252 /* append */
          offset_delta = 38
          locals = [ class java/lang/Object ]

  public static void criticalAnnounce(javax.swing.JFrame);
    descriptor: (Ljavax/swing/JFrame;)V
    flags: (0x0009) ACC_PUBLIC, ACC_STATIC
    Code:
      stack=7, locals=3, args_size=1
         0: aload_0
         1: ldc           #91                 // String Critical announce message
         3: ldc           #25                 // String Input
         5: iconst_1
         6: aconst_null
         7: aconst_null
         8: ldc           #79                 // String
        10: invokestatic  #29                 // Method javax/swing/JOptionPane.showInputDialog:(Ljava/awt/Component;Ljava/lang/Object;Ljava/lang/String;ILjavax/swing/Icon;[Ljava/lang/Object;Ljava/lang/Object;)Ljava/lang/Object;
        13: astore_1
        14: aload_1
        15: ifnull        38
        18: aload_1
        19: checkcast     #33                 // class java/lang/String
        22: invokevirtual #35                 // Method java/lang/String.trim:()Ljava/lang/String;
        25: astore_2
        26: aload_2
        27: invokevirtual #81                 // Method java/lang/String.isEmpty:()Z
        30: ifne          38
        33: aload_2
        34: iconst_1
        35: invokestatic  #85                 // Method ext/mods/gameserver/model/World.announceToOnlinePlayers:(Ljava/lang/String;Z)V
        38: return
      LineNumberTable:
        line 99: 0
        line 100: 14
        line 101: 18
        line 102: 26
        line 103: 33
        line 106: 38
      LocalVariableTable:
        Start  Length  Slot  Name   Signature
           26      12     2 message   Ljava/lang/String;
            0      39     0 parent   Ljavax/swing/JFrame;
           14      25     1 input   Ljava/lang/Object;
      StackMapTable: number_of_entries = 1
        frame_type = 252 /* append */
          offset_delta = 38
          locals = [ class java/lang/Object ]

  static {};
    descriptor: ()V
    flags: (0x0008) ACC_STATIC
    Code:
      stack=4, locals=0, args_size=0
         0: iconst_2
         1: anewarray     #33                 // class java/lang/String
         4: dup
         5: iconst_0
         6: ldc           #93                 // String Shutdown
         8: aastore
         9: dup
        10: iconst_1
        11: ldc           #95                 // String Cancel
        13: aastore
        14: putstatic     #13                 // Field shutdownOptions:[Ljava/lang/String;
        17: iconst_2
        18: anewarray     #33                 // class java/lang/String
        21: dup
        22: iconst_0
        23: ldc           #97                 // String Restart
        25: aastore
        26: dup
        27: iconst_1
        28: ldc           #95                 // String Cancel
        30: aastore
        31: putstatic     #63                 // Field restartOptions:[Ljava/lang/String;
        34: iconst_2
        35: anewarray     #33                 // class java/lang/String
        38: dup
        39: iconst_0
        40: ldc           #99                 // String Abort
        42: aastore
        43: dup
        44: iconst_1
        45: ldc           #95                 // String Cancel
        47: aastore
        48: putstatic     #70                 // Field abortOptions:[Ljava/lang/String;
        51: return
      LineNumberTable:
        line 28: 0
        line 29: 17
        line 30: 34
}
SourceFile: "ServerActions.java"
