// Bytecode for: ext.mods.gameserver.data.sql.OfflineTradersTable
// File: ext\mods\gameserver\data\sql\OfflineTradersTable.class

Classfile /c:/Users/User/Desktop/BrProject/bin/main/ext/mods/gameserver/data/sql/OfflineTradersTable.class
  Last modified 9 de jul de 2026; size 14184 bytes
  MD5 checksum a6a983f583f187a9313180b78d077906
  Compiled from "OfflineTradersTable.java"
public final class ext.mods.gameserver.data.sql.OfflineTradersTable
  minor version: 0
  major version: 69
  flags: (0x0031) ACC_PUBLIC, ACC_FINAL, ACC_SUPER
  this_class: #25                         // ext/mods/gameserver/data/sql/OfflineTradersTable
  super_class: #2                         // java/lang/Object
  interfaces: 0, fields: 7, methods: 9, attributes: 4
Constant pool:
    #1 = Methodref          #2.#3         // java/lang/Object."<init>":()V
    #2 = Class              #4            // java/lang/Object
    #3 = NameAndType        #5:#6         // "<init>":()V
    #4 = Utf8               java/lang/Object
    #5 = Utf8               <init>
    #6 = Utf8               ()V
    #7 = Fieldref           #8.#9         // ext/mods/Config.RESTORE_OFFLINERS:Z
    #8 = Class              #10           // ext/mods/Config
    #9 = NameAndType        #11:#12       // RESTORE_OFFLINERS:Z
   #10 = Utf8               ext/mods/Config
   #11 = Utf8               RESTORE_OFFLINERS
   #12 = Utf8               Z
   #13 = Fieldref           #8.#14        // ext/mods/Config.OFFLINE_TRADE_ENABLE:Z
   #14 = NameAndType        #15:#12       // OFFLINE_TRADE_ENABLE:Z
   #15 = Utf8               OFFLINE_TRADE_ENABLE
   #16 = Fieldref           #8.#17        // ext/mods/Config.OFFLINE_CRAFT_ENABLE:Z
   #17 = NameAndType        #18:#12       // OFFLINE_CRAFT_ENABLE:Z
   #18 = Utf8               OFFLINE_CRAFT_ENABLE
   #19 = Methodref          #20.#21       // ext/mods/commons/pool/ConnectionPool.getConnection:()Ljava/sql/Connection;
   #20 = Class              #22           // ext/mods/commons/pool/ConnectionPool
   #21 = NameAndType        #23:#24       // getConnection:()Ljava/sql/Connection;
   #22 = Utf8               ext/mods/commons/pool/ConnectionPool
   #23 = Utf8               getConnection
   #24 = Utf8               ()Ljava/sql/Connection;
   #25 = Class              #26           // ext/mods/gameserver/data/sql/OfflineTradersTable
   #26 = Utf8               ext/mods/gameserver/data/sql/OfflineTradersTable
   #27 = String             #28           // INSERT INTO character_offline_trade (`charId`,`time`,`type`,`title`) VALUES (?,?,?,?)
   #28 = Utf8               INSERT INTO character_offline_trade (`charId`,`time`,`type`,`title`) VALUES (?,?,?,?)
   #29 = InterfaceMethodref #30.#31       // java/sql/Connection.prepareStatement:(Ljava/lang/String;)Ljava/sql/PreparedStatement;
   #30 = Class              #32           // java/sql/Connection
   #31 = NameAndType        #33:#34       // prepareStatement:(Ljava/lang/String;)Ljava/sql/PreparedStatement;
   #32 = Utf8               java/sql/Connection
   #33 = Utf8               prepareStatement
   #34 = Utf8               (Ljava/lang/String;)Ljava/sql/PreparedStatement;
   #35 = String             #36           // INSERT INTO character_offline_trade_items (`charId`,`item`,`count`,`price`,`enchant`) VALUES (?,?,?,?,?)
   #36 = Utf8               INSERT INTO character_offline_trade_items (`charId`,`item`,`count`,`price`,`enchant`) VALUES (?,?,?,?,?)
   #37 = InterfaceMethodref #30.#38       // java/sql/Connection.createStatement:()Ljava/sql/Statement;
   #38 = NameAndType        #39:#40       // createStatement:()Ljava/sql/Statement;
   #39 = Utf8               createStatement
   #40 = Utf8               ()Ljava/sql/Statement;
   #41 = String             #42           // DELETE FROM character_offline_trade
   #42 = Utf8               DELETE FROM character_offline_trade
   #43 = InterfaceMethodref #44.#45       // java/sql/Statement.execute:(Ljava/lang/String;)Z
   #44 = Class              #46           // java/sql/Statement
   #45 = NameAndType        #47:#48       // execute:(Ljava/lang/String;)Z
   #46 = Utf8               java/sql/Statement
   #47 = Utf8               execute
   #48 = Utf8               (Ljava/lang/String;)Z
   #49 = String             #50           // DELETE FROM character_offline_trade_items
   #50 = Utf8               DELETE FROM character_offline_trade_items
   #51 = InterfaceMethodref #44.#52       // java/sql/Statement.close:()V
   #52 = NameAndType        #53:#6        // close:()V
   #53 = Utf8               close
   #54 = Class              #55           // java/lang/Throwable
   #55 = Utf8               java/lang/Throwable
   #56 = Methodref          #54.#57       // java/lang/Throwable.addSuppressed:(Ljava/lang/Throwable;)V
   #57 = NameAndType        #58:#59       // addSuppressed:(Ljava/lang/Throwable;)V
   #58 = Utf8               addSuppressed
   #59 = Utf8               (Ljava/lang/Throwable;)V
   #60 = Methodref          #61.#62       // ext/mods/gameserver/model/World.getInstance:()Lext/mods/gameserver/model/World;
   #61 = Class              #63           // ext/mods/gameserver/model/World
   #62 = NameAndType        #64:#65       // getInstance:()Lext/mods/gameserver/model/World;
   #63 = Utf8               ext/mods/gameserver/model/World
   #64 = Utf8               getInstance
   #65 = Utf8               ()Lext/mods/gameserver/model/World;
   #66 = Methodref          #61.#67       // ext/mods/gameserver/model/World.getPlayers:()Ljava/util/Collection;
   #67 = NameAndType        #68:#69       // getPlayers:()Ljava/util/Collection;
   #68 = Utf8               getPlayers
   #69 = Utf8               ()Ljava/util/Collection;
   #70 = InterfaceMethodref #71.#72       // java/util/Collection.iterator:()Ljava/util/Iterator;
   #71 = Class              #73           // java/util/Collection
   #72 = NameAndType        #74:#75       // iterator:()Ljava/util/Iterator;
   #73 = Utf8               java/util/Collection
   #74 = Utf8               iterator
   #75 = Utf8               ()Ljava/util/Iterator;
   #76 = InterfaceMethodref #77.#78       // java/util/Iterator.hasNext:()Z
   #77 = Class              #79           // java/util/Iterator
   #78 = NameAndType        #80:#81       // hasNext:()Z
   #79 = Utf8               java/util/Iterator
   #80 = Utf8               hasNext
   #81 = Utf8               ()Z
   #82 = InterfaceMethodref #77.#83       // java/util/Iterator.next:()Ljava/lang/Object;
   #83 = NameAndType        #84:#85       // next:()Ljava/lang/Object;
   #84 = Utf8               next
   #85 = Utf8               ()Ljava/lang/Object;
   #86 = Class              #87           // ext/mods/gameserver/model/actor/Player
   #87 = Utf8               ext/mods/gameserver/model/actor/Player
   #88 = Methodref          #86.#89       // ext/mods/gameserver/model/actor/Player.getOperateType:()Lext/mods/gameserver/enums/actors/OperateType;
   #89 = NameAndType        #90:#91       // getOperateType:()Lext/mods/gameserver/enums/actors/OperateType;
   #90 = Utf8               getOperateType
   #91 = Utf8               ()Lext/mods/gameserver/enums/actors/OperateType;
   #92 = Fieldref           #93.#94       // ext/mods/gameserver/enums/actors/OperateType.NONE:Lext/mods/gameserver/enums/actors/OperateType;
   #93 = Class              #95           // ext/mods/gameserver/enums/actors/OperateType
   #94 = NameAndType        #96:#97       // NONE:Lext/mods/gameserver/enums/actors/OperateType;
   #95 = Utf8               ext/mods/gameserver/enums/actors/OperateType
   #96 = Utf8               NONE
   #97 = Utf8               Lext/mods/gameserver/enums/actors/OperateType;
   #98 = Methodref          #86.#99       // ext/mods/gameserver/model/actor/Player.getClient:()Lext/mods/gameserver/network/GameClient;
   #99 = NameAndType        #100:#101     // getClient:()Lext/mods/gameserver/network/GameClient;
  #100 = Utf8               getClient
  #101 = Utf8               ()Lext/mods/gameserver/network/GameClient;
  #102 = Methodref          #103.#104     // ext/mods/gameserver/network/GameClient.isDetached:()Z
  #103 = Class              #105          // ext/mods/gameserver/network/GameClient
  #104 = NameAndType        #106:#81      // isDetached:()Z
  #105 = Utf8               ext/mods/gameserver/network/GameClient
  #106 = Utf8               isDetached
  #107 = Methodref          #86.#108      // ext/mods/gameserver/model/actor/Player.getObjectId:()I
  #108 = NameAndType        #109:#110     // getObjectId:()I
  #109 = Utf8               getObjectId
  #110 = Utf8               ()I
  #111 = InterfaceMethodref #112.#113     // java/sql/PreparedStatement.setInt:(II)V
  #112 = Class              #114          // java/sql/PreparedStatement
  #113 = NameAndType        #115:#116     // setInt:(II)V
  #114 = Utf8               java/sql/PreparedStatement
  #115 = Utf8               setInt
  #116 = Utf8               (II)V
  #117 = Methodref          #86.#118      // ext/mods/gameserver/model/actor/Player.getOfflineStartTime:()J
  #118 = NameAndType        #119:#120     // getOfflineStartTime:()J
  #119 = Utf8               getOfflineStartTime
  #120 = Utf8               ()J
  #121 = InterfaceMethodref #112.#122     // java/sql/PreparedStatement.setLong:(IJ)V
  #122 = NameAndType        #123:#124     // setLong:(IJ)V
  #123 = Utf8               setLong
  #124 = Utf8               (IJ)V
  #125 = Methodref          #86.#126      // ext/mods/gameserver/model/actor/Player.isSellingBuffs:()Z
  #126 = NameAndType        #127:#81      // isSellingBuffs:()Z
  #127 = Utf8               isSellingBuffs
  #128 = Fieldref           #93.#129      // ext/mods/gameserver/enums/actors/OperateType.SELL_BUFFS:Lext/mods/gameserver/enums/actors/OperateType;
  #129 = NameAndType        #130:#97      // SELL_BUFFS:Lext/mods/gameserver/enums/actors/OperateType;
  #130 = Utf8               SELL_BUFFS
  #131 = Methodref          #93.#132      // ext/mods/gameserver/enums/actors/OperateType.getId:()I
  #132 = NameAndType        #133:#110     // getId:()I
  #133 = Utf8               getId
  #134 = Fieldref           #135.#136     // ext/mods/gameserver/data/sql/OfflineTradersTable$1.$SwitchMap$ext$mods$gameserver$enums$actors$OperateType:[I
  #135 = Class              #137          // ext/mods/gameserver/data/sql/OfflineTradersTable$1
  #136 = NameAndType        #138:#139     // $SwitchMap$ext$mods$gameserver$enums$actors$OperateType:[I
  #137 = Utf8               ext/mods/gameserver/data/sql/OfflineTradersTable$1
  #138 = Utf8               $SwitchMap$ext$mods$gameserver$enums$actors$OperateType
  #139 = Utf8               [I
  #140 = Methodref          #93.#141      // ext/mods/gameserver/enums/actors/OperateType.ordinal:()I
  #141 = NameAndType        #142:#110     // ordinal:()I
  #142 = Utf8               ordinal
  #143 = Methodref          #86.#144      // ext/mods/gameserver/model/actor/Player.getBuyList:()Lext/mods/gameserver/model/trade/TradeList;
  #144 = NameAndType        #145:#146     // getBuyList:()Lext/mods/gameserver/model/trade/TradeList;
  #145 = Utf8               getBuyList
  #146 = Utf8               ()Lext/mods/gameserver/model/trade/TradeList;
  #147 = Methodref          #148.#149     // ext/mods/gameserver/model/trade/TradeList.getTitle:()Ljava/lang/String;
  #148 = Class              #150          // ext/mods/gameserver/model/trade/TradeList
  #149 = NameAndType        #151:#152     // getTitle:()Ljava/lang/String;
  #150 = Utf8               ext/mods/gameserver/model/trade/TradeList
  #151 = Utf8               getTitle
  #152 = Utf8               ()Ljava/lang/String;
  #153 = InterfaceMethodref #112.#154     // java/sql/PreparedStatement.setString:(ILjava/lang/String;)V
  #154 = NameAndType        #155:#156     // setString:(ILjava/lang/String;)V
  #155 = Utf8               setString
  #156 = Utf8               (ILjava/lang/String;)V
  #157 = Methodref          #148.#72      // ext/mods/gameserver/model/trade/TradeList.iterator:()Ljava/util/Iterator;
  #158 = Class              #159          // ext/mods/gameserver/model/trade/TradeItem
  #159 = Utf8               ext/mods/gameserver/model/trade/TradeItem
  #160 = Methodref          #158.#161     // ext/mods/gameserver/model/trade/TradeItem.getItem:()Lext/mods/gameserver/model/item/kind/Item;
  #161 = NameAndType        #162:#163     // getItem:()Lext/mods/gameserver/model/item/kind/Item;
  #162 = Utf8               getItem
  #163 = Utf8               ()Lext/mods/gameserver/model/item/kind/Item;
  #164 = Methodref          #165.#166     // ext/mods/gameserver/model/item/kind/Item.getItemId:()I
  #165 = Class              #167          // ext/mods/gameserver/model/item/kind/Item
  #166 = NameAndType        #168:#110     // getItemId:()I
  #167 = Utf8               ext/mods/gameserver/model/item/kind/Item
  #168 = Utf8               getItemId
  #169 = Methodref          #158.#170     // ext/mods/gameserver/model/trade/TradeItem.getQuantity:()I
  #170 = NameAndType        #171:#110     // getQuantity:()I
  #171 = Utf8               getQuantity
  #172 = Methodref          #158.#173     // ext/mods/gameserver/model/trade/TradeItem.getPrice:()I
  #173 = NameAndType        #174:#110     // getPrice:()I
  #174 = Utf8               getPrice
  #175 = Methodref          #158.#176     // ext/mods/gameserver/model/trade/TradeItem.getEnchant:()I
  #176 = NameAndType        #177:#110     // getEnchant:()I
  #177 = Utf8               getEnchant
  #178 = InterfaceMethodref #112.#179     // java/sql/PreparedStatement.addBatch:()V
  #179 = NameAndType        #180:#6       // addBatch:()V
  #180 = Utf8               addBatch
  #181 = Methodref          #86.#182      // ext/mods/gameserver/model/actor/Player.getSellList:()Lext/mods/gameserver/model/trade/TradeList;
  #182 = NameAndType        #183:#146     // getSellList:()Lext/mods/gameserver/model/trade/TradeList;
  #183 = Utf8               getSellList
  #184 = Methodref          #148.#185     // ext/mods/gameserver/model/trade/TradeList.updateItems:(Z)V
  #185 = NameAndType        #186:#187     // updateItems:(Z)V
  #186 = Utf8               updateItems
  #187 = Utf8               (Z)V
  #188 = Methodref          #86.#189      // ext/mods/gameserver/model/actor/Player.getSellingBuffs:()Ljava/util/List;
  #189 = NameAndType        #190:#191     // getSellingBuffs:()Ljava/util/List;
  #190 = Utf8               getSellingBuffs
  #191 = Utf8               ()Ljava/util/List;
  #192 = InterfaceMethodref #193.#72      // java/util/List.iterator:()Ljava/util/Iterator;
  #193 = Class              #194          // java/util/List
  #194 = Utf8               java/util/List
  #195 = Class              #196          // ext/mods/gameserver/model/SellBuffHolder
  #196 = Utf8               ext/mods/gameserver/model/SellBuffHolder
  #197 = Methodref          #195.#198     // ext/mods/gameserver/model/SellBuffHolder.getSkillId:()I
  #198 = NameAndType        #199:#110     // getSkillId:()I
  #199 = Utf8               getSkillId
  #200 = Methodref          #195.#201     // ext/mods/gameserver/model/SellBuffHolder.getSkillLvl:()I
  #201 = NameAndType        #202:#110     // getSkillLvl:()I
  #202 = Utf8               getSkillLvl
  #203 = Methodref          #195.#173     // ext/mods/gameserver/model/SellBuffHolder.getPrice:()I
  #204 = Methodref          #158.#108     // ext/mods/gameserver/model/trade/TradeItem.getObjectId:()I
  #205 = Methodref          #86.#206      // ext/mods/gameserver/model/actor/Player.getManufactureList:()Lext/mods/gameserver/model/craft/ManufactureList;
  #206 = NameAndType        #207:#208     // getManufactureList:()Lext/mods/gameserver/model/craft/ManufactureList;
  #207 = Utf8               getManufactureList
  #208 = Utf8               ()Lext/mods/gameserver/model/craft/ManufactureList;
  #209 = Methodref          #210.#211     // ext/mods/gameserver/model/craft/ManufactureList.getStoreName:()Ljava/lang/String;
  #210 = Class              #212          // ext/mods/gameserver/model/craft/ManufactureList
  #211 = NameAndType        #213:#152     // getStoreName:()Ljava/lang/String;
  #212 = Utf8               ext/mods/gameserver/model/craft/ManufactureList
  #213 = Utf8               getStoreName
  #214 = Methodref          #210.#72      // ext/mods/gameserver/model/craft/ManufactureList.iterator:()Ljava/util/Iterator;
  #215 = Class              #216          // ext/mods/gameserver/model/records/ManufactureItem
  #216 = Utf8               ext/mods/gameserver/model/records/ManufactureItem
  #217 = Methodref          #215.#218     // ext/mods/gameserver/model/records/ManufactureItem.recipeId:()I
  #218 = NameAndType        #219:#110     // recipeId:()I
  #219 = Utf8               recipeId
  #220 = Methodref          #215.#221     // ext/mods/gameserver/model/records/ManufactureItem.cost:()I
  #221 = NameAndType        #222:#110     // cost:()I
  #222 = Utf8               cost
  #223 = InterfaceMethodref #112.#224     // java/sql/PreparedStatement.executeBatch:()[I
  #224 = NameAndType        #225:#226     // executeBatch:()[I
  #225 = Utf8               executeBatch
  #226 = Utf8               ()[I
  #227 = InterfaceMethodref #112.#228     // java/sql/PreparedStatement.execute:()Z
  #228 = NameAndType        #47:#81       // execute:()Z
  #229 = Class              #230          // java/lang/Exception
  #230 = Utf8               java/lang/Exception
  #231 = Fieldref           #25.#232      // ext/mods/gameserver/data/sql/OfflineTradersTable.LOGGER:Lext/mods/commons/logging/CLogger;
  #232 = NameAndType        #233:#234     // LOGGER:Lext/mods/commons/logging/CLogger;
  #233 = Utf8               LOGGER
  #234 = Utf8               Lext/mods/commons/logging/CLogger;
  #235 = InvokeDynamic      #0:#236       // #0:makeConcatWithConstants:(I)Ljava/lang/String;
  #236 = NameAndType        #237:#238     // makeConcatWithConstants:(I)Ljava/lang/String;
  #237 = Utf8               makeConcatWithConstants
  #238 = Utf8               (I)Ljava/lang/String;
  #239 = Methodref          #240.#241     // ext/mods/commons/logging/CLogger.error:(Ljava/lang/Object;Ljava/lang/Throwable;)V
  #240 = Class              #242          // ext/mods/commons/logging/CLogger
  #241 = NameAndType        #243:#244     // error:(Ljava/lang/Object;Ljava/lang/Throwable;)V
  #242 = Utf8               ext/mods/commons/logging/CLogger
  #243 = Utf8               error
  #244 = Utf8               (Ljava/lang/Object;Ljava/lang/Throwable;)V
  #245 = String             #246          // Offline stored.
  #246 = Utf8               Offline stored.
  #247 = Methodref          #240.#248     // ext/mods/commons/logging/CLogger.info:(Ljava/lang/Object;)V
  #248 = NameAndType        #249:#250     // info:(Ljava/lang/Object;)V
  #249 = Utf8               info
  #250 = Utf8               (Ljava/lang/Object;)V
  #251 = InterfaceMethodref #112.#52      // java/sql/PreparedStatement.close:()V
  #252 = InterfaceMethodref #30.#52       // java/sql/Connection.close:()V
  #253 = String             #254          // Error while saving offline:
  #254 = Utf8               Error while saving offline:
  #255 = String             #256          // error while saving offline traders.
  #256 = Utf8               error while saving offline traders.
  #257 = String             #258          // error while clear table offline traders.
  #258 = Utf8               error while clear table offline traders.
  #259 = String             #260          // SELECT * FROM character_offline_trade
  #260 = Utf8               SELECT * FROM character_offline_trade
  #261 = InterfaceMethodref #44.#262      // java/sql/Statement.executeQuery:(Ljava/lang/String;)Ljava/sql/ResultSet;
  #262 = NameAndType        #263:#264     // executeQuery:(Ljava/lang/String;)Ljava/sql/ResultSet;
  #263 = Utf8               executeQuery
  #264 = Utf8               (Ljava/lang/String;)Ljava/sql/ResultSet;
  #265 = InterfaceMethodref #266.#267     // java/sql/ResultSet.next:()Z
  #266 = Class              #268          // java/sql/ResultSet
  #267 = NameAndType        #84:#81       // next:()Z
  #268 = Utf8               java/sql/ResultSet
  #269 = String             #270          // time
  #270 = Utf8               time
  #271 = InterfaceMethodref #266.#272     // java/sql/ResultSet.getLong:(Ljava/lang/String;)J
  #272 = NameAndType        #273:#274     // getLong:(Ljava/lang/String;)J
  #273 = Utf8               getLong
  #274 = Utf8               (Ljava/lang/String;)J
  #275 = Fieldref           #8.#276       // ext/mods/Config.OFFLINE_MAX_DAYS:I
  #276 = NameAndType        #277:#278     // OFFLINE_MAX_DAYS:I
  #277 = Utf8               OFFLINE_MAX_DAYS
  #278 = Utf8               I
  #279 = Methodref          #25.#280      // ext/mods/gameserver/data/sql/OfflineTradersTable.isExpired:(J)Z
  #280 = NameAndType        #281:#282     // isExpired:(J)Z
  #281 = Utf8               isExpired
  #282 = Utf8               (J)Z
  #283 = String             #284          // type
  #284 = Utf8               type
  #285 = InterfaceMethodref #266.#286     // java/sql/ResultSet.getInt:(Ljava/lang/String;)I
  #286 = NameAndType        #287:#288     // getInt:(Ljava/lang/String;)I
  #287 = Utf8               getInt
  #288 = Utf8               (Ljava/lang/String;)I
  #289 = Methodref          #25.#290      // ext/mods/gameserver/data/sql/OfflineTradersTable.getType:(I)Lext/mods/gameserver/enums/actors/OperateType;
  #290 = NameAndType        #291:#292     // getType:(I)Lext/mods/gameserver/enums/actors/OperateType;
  #291 = Utf8               getType
  #292 = Utf8               (I)Lext/mods/gameserver/enums/actors/OperateType;
  #293 = Fieldref           #93.#294      // ext/mods/gameserver/enums/actors/OperateType.PACKAGE_SELL:Lext/mods/gameserver/enums/actors/OperateType;
  #294 = NameAndType        #295:#97      // PACKAGE_SELL:Lext/mods/gameserver/enums/actors/OperateType;
  #295 = Utf8               PACKAGE_SELL
  #296 = String             #297          // charId
  #297 = Utf8               charId
  #298 = Methodref          #86.#299      // ext/mods/gameserver/model/actor/Player.restore:(IZ)Lext/mods/gameserver/model/actor/Player;
  #299 = NameAndType        #300:#301     // restore:(IZ)Lext/mods/gameserver/model/actor/Player;
  #300 = Utf8               restore
  #301 = Utf8               (IZ)Lext/mods/gameserver/model/actor/Player;
  #302 = Methodref          #103.#303     // ext/mods/gameserver/network/GameClient."<init>":(Lext/mods/commons/mmocore/MMOConnection;)V
  #303 = NameAndType        #5:#304       // "<init>":(Lext/mods/commons/mmocore/MMOConnection;)V
  #304 = Utf8               (Lext/mods/commons/mmocore/MMOConnection;)V
  #305 = Methodref          #103.#306     // ext/mods/gameserver/network/GameClient.spawnOffline:(Lext/mods/gameserver/model/actor/Player;)V
  #306 = NameAndType        #307:#308     // spawnOffline:(Lext/mods/gameserver/model/actor/Player;)V
  #307 = Utf8               spawnOffline
  #308 = Utf8               (Lext/mods/gameserver/model/actor/Player;)V
  #309 = Methodref          #86.#310      // ext/mods/gameserver/model/actor/Player.setOfflineStartTime:(J)V
  #310 = NameAndType        #311:#312     // setOfflineStartTime:(J)V
  #311 = Utf8               setOfflineStartTime
  #312 = Utf8               (J)V
  #313 = Methodref          #86.#314      // ext/mods/gameserver/model/actor/Player.sitDown:()Z
  #314 = NameAndType        #315:#81      // sitDown:()Z
  #315 = Utf8               sitDown
  #316 = Methodref          #86.#317      // ext/mods/gameserver/model/actor/Player.setSellingBuffs:(Z)V
  #317 = NameAndType        #318:#187     // setSellingBuffs:(Z)V
  #318 = Utf8               setSellingBuffs
  #319 = String             #320          // title
  #320 = Utf8               title
  #321 = InterfaceMethodref #266.#322     // java/sql/ResultSet.getString:(Ljava/lang/String;)Ljava/lang/String;
  #322 = NameAndType        #323:#324     // getString:(Ljava/lang/String;)Ljava/lang/String;
  #323 = Utf8               getString
  #324 = Utf8               (Ljava/lang/String;)Ljava/lang/String;
  #325 = String             #326          // SELECT * FROM character_offline_trade_items WHERE charId = ?
  #326 = Utf8               SELECT * FROM character_offline_trade_items WHERE charId = ?
  #327 = InterfaceMethodref #112.#328     // java/sql/PreparedStatement.executeQuery:()Ljava/sql/ResultSet;
  #328 = NameAndType        #263:#329     // executeQuery:()Ljava/sql/ResultSet;
  #329 = Utf8               ()Ljava/sql/ResultSet;
  #330 = InterfaceMethodref #266.#331     // java/sql/ResultSet.getInt:(I)I
  #331 = NameAndType        #287:#332     // getInt:(I)I
  #332 = Utf8               (I)I
  #333 = Methodref          #148.#334     // ext/mods/gameserver/model/trade/TradeList.addItemByItemId:(IIII)Lext/mods/gameserver/model/trade/TradeItem;
  #334 = NameAndType        #335:#336     // addItemByItemId:(IIII)Lext/mods/gameserver/model/trade/TradeItem;
  #335 = Utf8               addItemByItemId
  #336 = Utf8               (IIII)Lext/mods/gameserver/model/trade/TradeItem;
  #337 = Methodref          #148.#338     // ext/mods/gameserver/model/trade/TradeList.setTitle:(Ljava/lang/String;)V
  #338 = NameAndType        #339:#340     // setTitle:(Ljava/lang/String;)V
  #339 = Utf8               setTitle
  #340 = Utf8               (Ljava/lang/String;)V
  #341 = String             #342          // item
  #342 = Utf8               item
  #343 = String             #344          // count
  #344 = Utf8               count
  #345 = String             #346          // price
  #346 = Utf8               price
  #347 = Methodref          #195.#348     // ext/mods/gameserver/model/SellBuffHolder."<init>":(III)V
  #348 = NameAndType        #5:#349       // "<init>":(III)V
  #349 = Utf8               (III)V
  #350 = InterfaceMethodref #193.#351     // java/util/List.add:(Ljava/lang/Object;)Z
  #351 = NameAndType        #352:#353     // add:(Ljava/lang/Object;)Z
  #352 = Utf8               add
  #353 = Utf8               (Ljava/lang/Object;)Z
  #354 = Methodref          #148.#355     // ext/mods/gameserver/model/trade/TradeList.addItem:(III)Lext/mods/gameserver/model/trade/TradeItem;
  #355 = NameAndType        #356:#357     // addItem:(III)Lext/mods/gameserver/model/trade/TradeItem;
  #356 = Utf8               addItem
  #357 = Utf8               (III)Lext/mods/gameserver/model/trade/TradeItem;
  #358 = Methodref          #148.#359     // ext/mods/gameserver/model/trade/TradeList.setPackaged:(Z)V
  #359 = NameAndType        #360:#187     // setPackaged:(Z)V
  #360 = Utf8               setPackaged
  #361 = Methodref          #215.#362     // ext/mods/gameserver/model/records/ManufactureItem."<init>":(II)V
  #362 = NameAndType        #5:#116       // "<init>":(II)V
  #363 = Methodref          #210.#351     // ext/mods/gameserver/model/craft/ManufactureList.add:(Ljava/lang/Object;)Z
  #364 = Methodref          #210.#365     // ext/mods/gameserver/model/craft/ManufactureList.setStoreName:(Ljava/lang/String;)V
  #365 = NameAndType        #366:#340     // setStoreName:(Ljava/lang/String;)V
  #366 = Utf8               setStoreName
  #367 = InterfaceMethodref #266.#52      // java/sql/ResultSet.close:()V
  #368 = Fieldref           #8.#369       // ext/mods/Config.OFFLINE_SLEEP_EFFECT:Z
  #369 = NameAndType        #370:#12      // OFFLINE_SLEEP_EFFECT:Z
  #370 = Utf8               OFFLINE_SLEEP_EFFECT
  #371 = String             #372          // 0x80
  #372 = Utf8               0x80
  #373 = Methodref          #374.#375     // java/lang/Integer.decode:(Ljava/lang/String;)Ljava/lang/Integer;
  #374 = Class              #376          // java/lang/Integer
  #375 = NameAndType        #377:#378     // decode:(Ljava/lang/String;)Ljava/lang/Integer;
  #376 = Utf8               java/lang/Integer
  #377 = Utf8               decode
  #378 = Utf8               (Ljava/lang/String;)Ljava/lang/Integer;
  #379 = Methodref          #374.#380     // java/lang/Integer.intValue:()I
  #380 = NameAndType        #381:#110     // intValue:()I
  #381 = Utf8               intValue
  #382 = Methodref          #86.#383      // ext/mods/gameserver/model/actor/Player.startAbnormalEffect:(I)V
  #383 = NameAndType        #384:#385     // startAbnormalEffect:(I)V
  #384 = Utf8               startAbnormalEffect
  #385 = Utf8               (I)V
  #386 = Methodref          #86.#387      // ext/mods/gameserver/model/actor/Player.broadcastUserInfo:()V
  #387 = NameAndType        #388:#6       // broadcastUserInfo:()V
  #388 = Utf8               broadcastUserInfo
  #389 = Methodref          #86.#390      // ext/mods/gameserver/model/actor/Player.setOperateType:(Lext/mods/gameserver/enums/actors/OperateType;)V
  #390 = NameAndType        #391:#392     // setOperateType:(Lext/mods/gameserver/enums/actors/OperateType;)V
  #391 = Utf8               setOperateType
  #392 = Utf8               (Lext/mods/gameserver/enums/actors/OperateType;)V
  #393 = Methodref          #86.#394      // ext/mods/gameserver/model/actor/Player.restoreEffects:()V
  #394 = NameAndType        #395:#6       // restoreEffects:()V
  #395 = Utf8               restoreEffects
  #396 = Methodref          #86.#397      // ext/mods/gameserver/model/actor/Player.broadcastTitleInfo:()V
  #397 = NameAndType        #398:#6       // broadcastTitleInfo:()V
  #398 = Utf8               broadcastTitleInfo
  #399 = String             #400          // Error loading offline {}({}).
  #400 = Utf8               Error loading offline {}({}).
  #401 = Methodref          #86.#402      // ext/mods/gameserver/model/actor/Player.getName:()Ljava/lang/String;
  #402 = NameAndType        #403:#152     // getName:()Ljava/lang/String;
  #403 = Utf8               getName
  #404 = Methodref          #374.#405     // java/lang/Integer.valueOf:(I)Ljava/lang/Integer;
  #405 = NameAndType        #406:#407     // valueOf:(I)Ljava/lang/Integer;
  #406 = Utf8               valueOf
  #407 = Utf8               (I)Ljava/lang/Integer;
  #408 = Methodref          #240.#409     // ext/mods/commons/logging/CLogger.warn:(Ljava/lang/Object;Ljava/lang/Throwable;[Ljava/lang/Object;)V
  #409 = NameAndType        #410:#411     // warn:(Ljava/lang/Object;Ljava/lang/Throwable;[Ljava/lang/Object;)V
  #410 = Utf8               warn
  #411 = Utf8               (Ljava/lang/Object;Ljava/lang/Throwable;[Ljava/lang/Object;)V
  #412 = Methodref          #86.#413      // ext/mods/gameserver/model/actor/Player.logout:(Z)V
  #413 = NameAndType        #414:#187     // logout:(Z)V
  #414 = Utf8               logout
  #415 = InvokeDynamic      #1:#236       // #1:makeConcatWithConstants:(I)Ljava/lang/String;
  #416 = String             #417          // Error while loading offline:
  #417 = Utf8               Error while loading offline:
  #418 = Methodref          #240.#419     // ext/mods/commons/logging/CLogger.warn:(Ljava/lang/Object;Ljava/lang/Throwable;)V
  #419 = NameAndType        #410:#244     // warn:(Ljava/lang/Object;Ljava/lang/Throwable;)V
  #420 = Methodref          #93.#421      // ext/mods/gameserver/enums/actors/OperateType.values:()[Lext/mods/gameserver/enums/actors/OperateType;
  #421 = NameAndType        #422:#423     // values:()[Lext/mods/gameserver/enums/actors/OperateType;
  #422 = Utf8               values
  #423 = Utf8               ()[Lext/mods/gameserver/enums/actors/OperateType;
  #424 = String             #425          // Wrong OperateType id \'{}\' not found.
  #425 = Utf8               Wrong OperateType id \'{}\' not found.
  #426 = Methodref          #240.#427     // ext/mods/commons/logging/CLogger.warn:(Ljava/lang/Object;[Ljava/lang/Object;)V
  #427 = NameAndType        #410:#428     // warn:(Ljava/lang/Object;[Ljava/lang/Object;)V
  #428 = Utf8               (Ljava/lang/Object;[Ljava/lang/Object;)V
  #429 = Methodref          #430.#431     // java/util/Calendar.getInstance:()Ljava/util/Calendar;
  #430 = Class              #432          // java/util/Calendar
  #431 = NameAndType        #64:#433      // getInstance:()Ljava/util/Calendar;
  #432 = Utf8               java/util/Calendar
  #433 = Utf8               ()Ljava/util/Calendar;
  #434 = Methodref          #430.#435     // java/util/Calendar.setTimeInMillis:(J)V
  #435 = NameAndType        #436:#312     // setTimeInMillis:(J)V
  #436 = Utf8               setTimeInMillis
  #437 = Methodref          #430.#438     // java/util/Calendar.add:(II)V
  #438 = NameAndType        #352:#116     // add:(II)V
  #439 = Methodref          #430.#440     // java/util/Calendar.getTimeInMillis:()J
  #440 = NameAndType        #441:#120     // getTimeInMillis:()J
  #441 = Utf8               getTimeInMillis
  #442 = Methodref          #443.#444     // java/lang/System.currentTimeMillis:()J
  #443 = Class              #445          // java/lang/System
  #444 = NameAndType        #446:#120     // currentTimeMillis:()J
  #445 = Utf8               java/lang/System
  #446 = Utf8               currentTimeMillis
  #447 = Methodref          #86.#448      // ext/mods/gameserver/model/actor/Player.isInOlympiadMode:()Z
  #448 = NameAndType        #449:#81      // isInOlympiadMode:()Z
  #449 = Utf8               isInOlympiadMode
  #450 = Methodref          #86.#451      // ext/mods/gameserver/model/actor/Player.isInJail:()Z
  #451 = NameAndType        #452:#81      // isInJail:()Z
  #452 = Utf8               isInJail
  #453 = Methodref          #86.#454      // ext/mods/gameserver/model/actor/Player.getBoatInfo:()Lext/mods/gameserver/model/actor/container/player/BoatInfo;
  #454 = NameAndType        #455:#456     // getBoatInfo:()Lext/mods/gameserver/model/actor/container/player/BoatInfo;
  #455 = Utf8               getBoatInfo
  #456 = Utf8               ()Lext/mods/gameserver/model/actor/container/player/BoatInfo;
  #457 = Methodref          #458.#459     // ext/mods/gameserver/model/actor/container/player/BoatInfo.getBoat:()Lext/mods/gameserver/model/actor/Boat;
  #458 = Class              #460          // ext/mods/gameserver/model/actor/container/player/BoatInfo
  #459 = NameAndType        #461:#462     // getBoat:()Lext/mods/gameserver/model/actor/Boat;
  #460 = Utf8               ext/mods/gameserver/model/actor/container/player/BoatInfo
  #461 = Utf8               getBoat
  #462 = Utf8               ()Lext/mods/gameserver/model/actor/Boat;
  #463 = Fieldref           #8.#464       // ext/mods/Config.OFFLINE_MODE_IN_PEACE_ZONE:Z
  #464 = NameAndType        #465:#12      // OFFLINE_MODE_IN_PEACE_ZONE:Z
  #465 = Utf8               OFFLINE_MODE_IN_PEACE_ZONE
  #466 = Fieldref           #467.#468     // ext/mods/gameserver/enums/ZoneId.PEACE:Lext/mods/gameserver/enums/ZoneId;
  #467 = Class              #469          // ext/mods/gameserver/enums/ZoneId
  #468 = NameAndType        #470:#471     // PEACE:Lext/mods/gameserver/enums/ZoneId;
  #469 = Utf8               ext/mods/gameserver/enums/ZoneId
  #470 = Utf8               PEACE
  #471 = Utf8               Lext/mods/gameserver/enums/ZoneId;
  #472 = Methodref          #86.#473      // ext/mods/gameserver/model/actor/Player.isInsideZone:(Lext/mods/gameserver/enums/ZoneId;)Z
  #473 = NameAndType        #474:#475     // isInsideZone:(Lext/mods/gameserver/enums/ZoneId;)Z
  #474 = Utf8               isInsideZone
  #475 = Utf8               (Lext/mods/gameserver/enums/ZoneId;)Z
  #476 = Fieldref           #477.#478     // ext/mods/gameserver/data/sql/OfflineTradersTable$SingletonHolder.INSTANCE:Lext/mods/gameserver/data/sql/OfflineTradersTable;
  #477 = Class              #479          // ext/mods/gameserver/data/sql/OfflineTradersTable$SingletonHolder
  #478 = NameAndType        #480:#481     // INSTANCE:Lext/mods/gameserver/data/sql/OfflineTradersTable;
  #479 = Utf8               ext/mods/gameserver/data/sql/OfflineTradersTable$SingletonHolder
  #480 = Utf8               INSTANCE
  #481 = Utf8               Lext/mods/gameserver/data/sql/OfflineTradersTable;
  #482 = Methodref          #483.#402     // java/lang/Class.getName:()Ljava/lang/String;
  #483 = Class              #484          // java/lang/Class
  #484 = Utf8               java/lang/Class
  #485 = Methodref          #240.#486     // ext/mods/commons/logging/CLogger."<init>":(Ljava/lang/String;)V
  #486 = NameAndType        #5:#340       // "<init>":(Ljava/lang/String;)V
  #487 = Utf8               SAVE_OFFLINE_STATUS
  #488 = Utf8               Ljava/lang/String;
  #489 = Utf8               ConstantValue
  #490 = Utf8               SAVE_ITEMS
  #491 = Utf8               CLEAR_OFFLINE_TABLE
  #492 = Utf8               CLEAR_OFFLINE_TABLE_ITEMS
  #493 = Utf8               LOAD_OFFLINE_STATUS
  #494 = Utf8               LOAD_OFFLINE_ITEMS
  #495 = Utf8               Code
  #496 = Utf8               LineNumberTable
  #497 = Utf8               LocalVariableTable
  #498 = Utf8               this
  #499 = Utf8               store
  #500 = Utf8               stm
  #501 = Utf8               Ljava/sql/Statement;
  #502 = Utf8               i
  #503 = Utf8               Lext/mods/gameserver/model/trade/TradeItem;
  #504 = Utf8               holder
  #505 = Utf8               Lext/mods/gameserver/model/SellBuffHolder;
  #506 = Utf8               Lext/mods/gameserver/model/records/ManufactureItem;
  #507 = Utf8               e
  #508 = Utf8               Ljava/lang/Exception;
  #509 = Utf8               player
  #510 = Utf8               Lext/mods/gameserver/model/actor/Player;
  #511 = Utf8               Ljava/sql/PreparedStatement;
  #512 = Utf8               offline
  #513 = Utf8               con
  #514 = Utf8               Ljava/sql/Connection;
  #515 = Utf8               StackMapTable
  #516 = Utf8               saveOfflineTraders
  #517 = Utf8               ps4
  #518 = Utf8               ps3
  #519 = Utf8               ps2
  #520 = Utf8               ps
  #521 = Utf8               Ljava/sql/ResultSet;
  #522 = Utf8               J
  #523 = Utf8               oType
  #524 = Utf8               isSellBuff
  #525 = Utf8               client
  #526 = Utf8               Lext/mods/gameserver/network/GameClient;
  #527 = Utf8               stm2
  #528 = Utf8               rs
  #529 = Class              #530          // java/lang/String
  #530 = Utf8               java/lang/String
  #531 = Utf8               id
  #532 = Class              #533          // "[Lext/mods/gameserver/enums/actors/OperateType;"
  #533 = Utf8               [Lext/mods/gameserver/enums/actors/OperateType;
  #534 = Utf8               cal
  #535 = Utf8               Ljava/util/Calendar;
  #536 = Utf8               offlineMode
  #537 = Utf8               (Lext/mods/gameserver/model/actor/Player;)Z
  #538 = Utf8               ()Lext/mods/gameserver/data/sql/OfflineTradersTable;
  #539 = Utf8               <clinit>
  #540 = Utf8               SourceFile
  #541 = Utf8               OfflineTradersTable.java
  #542 = Utf8               NestMembers
  #543 = Utf8               BootstrapMethods
  #544 = String             #545          // Error while saving offline: \u0001
  #545 = Utf8               Error while saving offline: \u0001
  #546 = String             #547          // Loaded \u0001 offline.
  #547 = Utf8               Loaded \u0001 offline.
  #548 = MethodHandle       6:#549        // REF_invokeStatic java/lang/invoke/StringConcatFactory.makeConcatWithConstants:(Ljava/lang/invoke/MethodHandles$Lookup;Ljava/lang/String;Ljava/lang/invoke/MethodType;Ljava/lang/String;[Ljava/lang/Object;)Ljava/lang/invoke/CallSite;
  #549 = Methodref          #550.#551     // java/lang/invoke/StringConcatFactory.makeConcatWithConstants:(Ljava/lang/invoke/MethodHandles$Lookup;Ljava/lang/String;Ljava/lang/invoke/MethodType;Ljava/lang/String;[Ljava/lang/Object;)Ljava/lang/invoke/CallSite;
  #550 = Class              #552          // java/lang/invoke/StringConcatFactory
  #551 = NameAndType        #237:#553     // makeConcatWithConstants:(Ljava/lang/invoke/MethodHandles$Lookup;Ljava/lang/String;Ljava/lang/invoke/MethodType;Ljava/lang/String;[Ljava/lang/Object;)Ljava/lang/invoke/CallSite;
  #552 = Utf8               java/lang/invoke/StringConcatFactory
  #553 = Utf8               (Ljava/lang/invoke/MethodHandles$Lookup;Ljava/lang/String;Ljava/lang/invoke/MethodType;Ljava/lang/String;[Ljava/lang/Object;)Ljava/lang/invoke/CallSite;
  #554 = Utf8               InnerClasses
  #555 = Utf8               SingletonHolder
  #556 = Class              #557          // java/lang/invoke/MethodHandles$Lookup
  #557 = Utf8               java/lang/invoke/MethodHandles$Lookup
  #558 = Class              #559          // java/lang/invoke/MethodHandles
  #559 = Utf8               java/lang/invoke/MethodHandles
  #560 = Utf8               Lookup
{
  public ext.mods.gameserver.data.sql.OfflineTradersTable();
    descriptor: ()V
    flags: (0x0001) ACC_PUBLIC
    Code:
      stack=1, locals=1, args_size=1
         0: aload_0
         1: invokespecial #1                  // Method java/lang/Object."<init>":()V
         4: return
      LineNumberTable:
        line 39: 0
      LocalVariableTable:
        Start  Length  Slot  Name   Signature
            0       5     0  this   Lext/mods/gameserver/data/sql/OfflineTradersTable;

  public void store();
    descriptor: ()V
    flags: (0x0001) ACC_PUBLIC
    Code:
      stack=4, locals=8, args_size=1
         0: getstatic     #7                  // Field ext/mods/Config.RESTORE_OFFLINERS:Z
         3: ifeq          18
         6: getstatic     #13                 // Field ext/mods/Config.OFFLINE_TRADE_ENABLE:Z
         9: ifne          19
        12: getstatic     #16                 // Field ext/mods/Config.OFFLINE_CRAFT_ENABLE:Z
        15: ifne          19
        18: return
        19: invokestatic  #19                 // Method ext/mods/commons/pool/ConnectionPool.getConnection:()Ljava/sql/Connection;
        22: astore_1
        23: aload_1
        24: ldc           #27                 // String INSERT INTO character_offline_trade (`charId`,`time`,`type`,`title`) VALUES (?,?,?,?)
        26: invokeinterface #29,  2           // InterfaceMethod java/sql/Connection.prepareStatement:(Ljava/lang/String;)Ljava/sql/PreparedStatement;
        31: astore_2
        32: aload_1
        33: ldc           #35                 // String INSERT INTO character_offline_trade_items (`charId`,`item`,`count`,`price`,`enchant`) VALUES (?,?,?,?,?)
        35: invokeinterface #29,  2           // InterfaceMethod java/sql/Connection.prepareStatement:(Ljava/lang/String;)Ljava/sql/PreparedStatement;
        40: astore_3
        41: aload_1
        42: invokeinterface #37,  1           // InterfaceMethod java/sql/Connection.createStatement:()Ljava/sql/Statement;
        47: astore        4
        49: aload         4
        51: ldc           #41                 // String DELETE FROM character_offline_trade
        53: invokeinterface #43,  2           // InterfaceMethod java/sql/Statement.execute:(Ljava/lang/String;)Z
        58: pop
        59: aload         4
        61: ldc           #49                 // String DELETE FROM character_offline_trade_items
        63: invokeinterface #43,  2           // InterfaceMethod java/sql/Statement.execute:(Ljava/lang/String;)Z
        68: pop
        69: aload         4
        71: ifnull        113
        74: aload         4
        76: invokeinterface #51,  1           // InterfaceMethod java/sql/Statement.close:()V
        81: goto          113
        84: astore        5
        86: aload         4
        88: ifnull        110
        91: aload         4
        93: invokeinterface #51,  1           // InterfaceMethod java/sql/Statement.close:()V
        98: goto          110
       101: astore        6
       103: aload         5
       105: aload         6
       107: invokevirtual #56                 // Method java/lang/Throwable.addSuppressed:(Ljava/lang/Throwable;)V
       110: aload         5
       112: athrow
       113: invokestatic  #60                 // Method ext/mods/gameserver/model/World.getInstance:()Lext/mods/gameserver/model/World;
       116: invokevirtual #66                 // Method ext/mods/gameserver/model/World.getPlayers:()Ljava/util/Collection;
       119: invokeinterface #70,  1           // InterfaceMethod java/util/Collection.iterator:()Ljava/util/Iterator;
       124: astore        4
       126: aload         4
       128: invokeinterface #76,  1           // InterfaceMethod java/util/Iterator.hasNext:()Z
       133: ifeq          820
       136: aload         4
       138: invokeinterface #82,  1           // InterfaceMethod java/util/Iterator.next:()Ljava/lang/Object;
       143: checkcast     #86                 // class ext/mods/gameserver/model/actor/Player
       146: astore        5
       148: aload         5
       150: invokevirtual #88                 // Method ext/mods/gameserver/model/actor/Player.getOperateType:()Lext/mods/gameserver/enums/actors/OperateType;
       153: getstatic     #92                 // Field ext/mods/gameserver/enums/actors/OperateType.NONE:Lext/mods/gameserver/enums/actors/OperateType;
       156: if_acmpeq     794
       159: aload         5
       161: invokevirtual #98                 // Method ext/mods/gameserver/model/actor/Player.getClient:()Lext/mods/gameserver/network/GameClient;
       164: ifnull        178
       167: aload         5
       169: invokevirtual #98                 // Method ext/mods/gameserver/model/actor/Player.getClient:()Lext/mods/gameserver/network/GameClient;
       172: invokevirtual #102                // Method ext/mods/gameserver/network/GameClient.isDetached:()Z
       175: ifeq          794
       178: aload_2
       179: iconst_1
       180: aload         5
       182: invokevirtual #107                // Method ext/mods/gameserver/model/actor/Player.getObjectId:()I
       185: invokeinterface #111,  3          // InterfaceMethod java/sql/PreparedStatement.setInt:(II)V
       190: aload_2
       191: iconst_2
       192: aload         5
       194: invokevirtual #117                // Method ext/mods/gameserver/model/actor/Player.getOfflineStartTime:()J
       197: invokeinterface #121,  4          // InterfaceMethod java/sql/PreparedStatement.setLong:(IJ)V
       202: aload_2
       203: iconst_3
       204: aload         5
       206: invokevirtual #125                // Method ext/mods/gameserver/model/actor/Player.isSellingBuffs:()Z
       209: ifeq          221
       212: getstatic     #128                // Field ext/mods/gameserver/enums/actors/OperateType.SELL_BUFFS:Lext/mods/gameserver/enums/actors/OperateType;
       215: invokevirtual #131                // Method ext/mods/gameserver/enums/actors/OperateType.getId:()I
       218: goto          229
       221: aload         5
       223: invokevirtual #88                 // Method ext/mods/gameserver/model/actor/Player.getOperateType:()Lext/mods/gameserver/enums/actors/OperateType;
       226: invokevirtual #131                // Method ext/mods/gameserver/enums/actors/OperateType.getId:()I
       229: invokeinterface #111,  3          // InterfaceMethod java/sql/PreparedStatement.setInt:(II)V
       234: getstatic     #134                // Field ext/mods/gameserver/data/sql/OfflineTradersTable$1.$SwitchMap$ext$mods$gameserver$enums$actors$OperateType:[I
       237: aload         5
       239: invokevirtual #88                 // Method ext/mods/gameserver/model/actor/Player.getOperateType:()Lext/mods/gameserver/enums/actors/OperateType;
       242: invokevirtual #140                // Method ext/mods/gameserver/enums/actors/OperateType.ordinal:()I
       245: iaload
       246: tableswitch   { // 1 to 4

                       1: 276

                       2: 410

                       3: 410

                       4: 662
                 default: 780
            }
       276: getstatic     #13                 // Field ext/mods/Config.OFFLINE_TRADE_ENABLE:Z
       279: ifne          285
       282: goto          126
       285: aload_2
       286: iconst_4
       287: aload         5
       289: invokevirtual #143                // Method ext/mods/gameserver/model/actor/Player.getBuyList:()Lext/mods/gameserver/model/trade/TradeList;
       292: invokevirtual #147                // Method ext/mods/gameserver/model/trade/TradeList.getTitle:()Ljava/lang/String;
       295: invokeinterface #153,  3          // InterfaceMethod java/sql/PreparedStatement.setString:(ILjava/lang/String;)V
       300: aload         5
       302: invokevirtual #143                // Method ext/mods/gameserver/model/actor/Player.getBuyList:()Lext/mods/gameserver/model/trade/TradeList;
       305: invokevirtual #157                // Method ext/mods/gameserver/model/trade/TradeList.iterator:()Ljava/util/Iterator;
       308: astore        6
       310: aload         6
       312: invokeinterface #76,  1           // InterfaceMethod java/util/Iterator.hasNext:()Z
       317: ifeq          407
       320: aload         6
       322: invokeinterface #82,  1           // InterfaceMethod java/util/Iterator.next:()Ljava/lang/Object;
       327: checkcast     #158                // class ext/mods/gameserver/model/trade/TradeItem
       330: astore        7
       332: aload_3
       333: iconst_1
       334: aload         5
       336: invokevirtual #107                // Method ext/mods/gameserver/model/actor/Player.getObjectId:()I
       339: invokeinterface #111,  3          // InterfaceMethod java/sql/PreparedStatement.setInt:(II)V
       344: aload_3
       345: iconst_2
       346: aload         7
       348: invokevirtual #160                // Method ext/mods/gameserver/model/trade/TradeItem.getItem:()Lext/mods/gameserver/model/item/kind/Item;
       351: invokevirtual #164                // Method ext/mods/gameserver/model/item/kind/Item.getItemId:()I
       354: invokeinterface #111,  3          // InterfaceMethod java/sql/PreparedStatement.setInt:(II)V
       359: aload_3
       360: iconst_3
       361: aload         7
       363: invokevirtual #169                // Method ext/mods/gameserver/model/trade/TradeItem.getQuantity:()I
       366: i2l
       367: invokeinterface #121,  4          // InterfaceMethod java/sql/PreparedStatement.setLong:(IJ)V
       372: aload_3
       373: iconst_4
       374: aload         7
       376: invokevirtual #172                // Method ext/mods/gameserver/model/trade/TradeItem.getPrice:()I
       379: i2l
       380: invokeinterface #121,  4          // InterfaceMethod java/sql/PreparedStatement.setLong:(IJ)V
       385: aload_3
       386: iconst_5
       387: aload         7
       389: invokevirtual #175                // Method ext/mods/gameserver/model/trade/TradeItem.getEnchant:()I
       392: i2l
       393: invokeinterface #121,  4          // InterfaceMethod java/sql/PreparedStatement.setLong:(IJ)V
       398: aload_3
       399: invokeinterface #178,  1          // InterfaceMethod java/sql/PreparedStatement.addBatch:()V
       404: goto          310
       407: goto          780
       410: getstatic     #13                 // Field ext/mods/Config.OFFLINE_TRADE_ENABLE:Z
       413: ifne          419
       416: goto          126
       419: aload_2
       420: iconst_4
       421: aload         5
       423: invokevirtual #181                // Method ext/mods/gameserver/model/actor/Player.getSellList:()Lext/mods/gameserver/model/trade/TradeList;
       426: invokevirtual #147                // Method ext/mods/gameserver/model/trade/TradeList.getTitle:()Ljava/lang/String;
       429: invokeinterface #153,  3          // InterfaceMethod java/sql/PreparedStatement.setString:(ILjava/lang/String;)V
       434: aload         5
       436: invokevirtual #181                // Method ext/mods/gameserver/model/actor/Player.getSellList:()Lext/mods/gameserver/model/trade/TradeList;
       439: iconst_0
       440: invokevirtual #184                // Method ext/mods/gameserver/model/trade/TradeList.updateItems:(Z)V
       443: aload         5
       445: invokevirtual #125                // Method ext/mods/gameserver/model/actor/Player.isSellingBuffs:()Z
       448: ifeq          555
       451: aload         5
       453: invokevirtual #188                // Method ext/mods/gameserver/model/actor/Player.getSellingBuffs:()Ljava/util/List;
       456: invokeinterface #192,  1          // InterfaceMethod java/util/List.iterator:()Ljava/util/Iterator;
       461: astore        6
       463: aload         6
       465: invokeinterface #76,  1           // InterfaceMethod java/util/Iterator.hasNext:()Z
       470: ifeq          552
       473: aload         6
       475: invokeinterface #82,  1           // InterfaceMethod java/util/Iterator.next:()Ljava/lang/Object;
       480: checkcast     #195                // class ext/mods/gameserver/model/SellBuffHolder
       483: astore        7
       485: aload_3
       486: iconst_1
       487: aload         5
       489: invokevirtual #107                // Method ext/mods/gameserver/model/actor/Player.getObjectId:()I
       492: invokeinterface #111,  3          // InterfaceMethod java/sql/PreparedStatement.setInt:(II)V
       497: aload_3
       498: iconst_2
       499: aload         7
       501: invokevirtual #197                // Method ext/mods/gameserver/model/SellBuffHolder.getSkillId:()I
       504: invokeinterface #111,  3          // InterfaceMethod java/sql/PreparedStatement.setInt:(II)V
       509: aload_3
       510: iconst_3
       511: aload         7
       513: invokevirtual #200                // Method ext/mods/gameserver/model/SellBuffHolder.getSkillLvl:()I
       516: i2l
       517: invokeinterface #121,  4          // InterfaceMethod java/sql/PreparedStatement.setLong:(IJ)V
       522: aload_3
       523: iconst_4
       524: aload         7
       526: invokevirtual #203                // Method ext/mods/gameserver/model/SellBuffHolder.getPrice:()I
       529: i2l
       530: invokeinterface #121,  4          // InterfaceMethod java/sql/PreparedStatement.setLong:(IJ)V
       535: aload_3
       536: iconst_5
       537: lconst_0
       538: invokeinterface #121,  4          // InterfaceMethod java/sql/PreparedStatement.setLong:(IJ)V
       543: aload_3
       544: invokeinterface #178,  1          // InterfaceMethod java/sql/PreparedStatement.addBatch:()V
       549: goto          463
       552: goto          780
       555: aload         5
       557: invokevirtual #181                // Method ext/mods/gameserver/model/actor/Player.getSellList:()Lext/mods/gameserver/model/trade/TradeList;
       560: invokevirtual #157                // Method ext/mods/gameserver/model/trade/TradeList.iterator:()Ljava/util/Iterator;
       563: astore        6
       565: aload         6
       567: invokeinterface #76,  1           // InterfaceMethod java/util/Iterator.hasNext:()Z
       572: ifeq          659
       575: aload         6
       577: invokeinterface #82,  1           // InterfaceMethod java/util/Iterator.next:()Ljava/lang/Object;
       582: checkcast     #158                // class ext/mods/gameserver/model/trade/TradeItem
       585: astore        7
       587: aload_3
       588: iconst_1
       589: aload         5
       591: invokevirtual #107                // Method ext/mods/gameserver/model/actor/Player.getObjectId:()I
       594: invokeinterface #111,  3          // InterfaceMethod java/sql/PreparedStatement.setInt:(II)V
       599: aload_3
       600: iconst_2
       601: aload         7
       603: invokevirtual #204                // Method ext/mods/gameserver/model/trade/TradeItem.getObjectId:()I
       606: invokeinterface #111,  3          // InterfaceMethod java/sql/PreparedStatement.setInt:(II)V
       611: aload_3
       612: iconst_3
       613: aload         7
       615: invokevirtual #169                // Method ext/mods/gameserver/model/trade/TradeItem.getQuantity:()I
       618: i2l
       619: invokeinterface #121,  4          // InterfaceMethod java/sql/PreparedStatement.setLong:(IJ)V
       624: aload_3
       625: iconst_4
       626: aload         7
       628: invokevirtual #172                // Method ext/mods/gameserver/model/trade/TradeItem.getPrice:()I
       631: i2l
       632: invokeinterface #121,  4          // InterfaceMethod java/sql/PreparedStatement.setLong:(IJ)V
       637: aload_3
       638: iconst_5
       639: aload         7
       641: invokevirtual #175                // Method ext/mods/gameserver/model/trade/TradeItem.getEnchant:()I
       644: i2l
       645: invokeinterface #121,  4          // InterfaceMethod java/sql/PreparedStatement.setLong:(IJ)V
       650: aload_3
       651: invokeinterface #178,  1          // InterfaceMethod java/sql/PreparedStatement.addBatch:()V
       656: goto          565
       659: goto          780
       662: getstatic     #16                 // Field ext/mods/Config.OFFLINE_CRAFT_ENABLE:Z
       665: ifne          671
       668: goto          126
       671: aload_2
       672: iconst_4
       673: aload         5
       675: invokevirtual #205                // Method ext/mods/gameserver/model/actor/Player.getManufactureList:()Lext/mods/gameserver/model/craft/ManufactureList;
       678: invokevirtual #209                // Method ext/mods/gameserver/model/craft/ManufactureList.getStoreName:()Ljava/lang/String;
       681: invokeinterface #153,  3          // InterfaceMethod java/sql/PreparedStatement.setString:(ILjava/lang/String;)V
       686: aload         5
       688: invokevirtual #205                // Method ext/mods/gameserver/model/actor/Player.getManufactureList:()Lext/mods/gameserver/model/craft/ManufactureList;
       691: invokevirtual #214                // Method ext/mods/gameserver/model/craft/ManufactureList.iterator:()Ljava/util/Iterator;
       694: astore        6
       696: aload         6
       698: invokeinterface #76,  1           // InterfaceMethod java/util/Iterator.hasNext:()Z
       703: ifeq          780
       706: aload         6
       708: invokeinterface #82,  1           // InterfaceMethod java/util/Iterator.next:()Ljava/lang/Object;
       713: checkcast     #215                // class ext/mods/gameserver/model/records/ManufactureItem
       716: astore        7
       718: aload_3
       719: iconst_1
       720: aload         5
       722: invokevirtual #107                // Method ext/mods/gameserver/model/actor/Player.getObjectId:()I
       725: invokeinterface #111,  3          // InterfaceMethod java/sql/PreparedStatement.setInt:(II)V
       730: aload_3
       731: iconst_2
       732: aload         7
       734: invokevirtual #217                // Method ext/mods/gameserver/model/records/ManufactureItem.recipeId:()I
       737: invokeinterface #111,  3          // InterfaceMethod java/sql/PreparedStatement.setInt:(II)V
       742: aload_3
       743: iconst_3
       744: lconst_0
       745: invokeinterface #121,  4          // InterfaceMethod java/sql/PreparedStatement.setLong:(IJ)V
       750: aload_3
       751: iconst_4
       752: aload         7
       754: invokevirtual #220                // Method ext/mods/gameserver/model/records/ManufactureItem.cost:()I
       757: i2l
       758: invokeinterface #121,  4          // InterfaceMethod java/sql/PreparedStatement.setLong:(IJ)V
       763: aload_3
       764: iconst_5
       765: lconst_0
       766: invokeinterface #121,  4          // InterfaceMethod java/sql/PreparedStatement.setLong:(IJ)V
       771: aload_3
       772: invokeinterface #178,  1          // InterfaceMethod java/sql/PreparedStatement.addBatch:()V
       777: goto          696
       780: aload_3
       781: invokeinterface #223,  1          // InterfaceMethod java/sql/PreparedStatement.executeBatch:()[I
       786: pop
       787: aload_2
       788: invokeinterface #227,  1          // InterfaceMethod java/sql/PreparedStatement.execute:()Z
       793: pop
       794: goto          817
       797: astore        6
       799: getstatic     #231                // Field LOGGER:Lext/mods/commons/logging/CLogger;
       802: aload         5
       804: invokevirtual #107                // Method ext/mods/gameserver/model/actor/Player.getObjectId:()I
       807: invokedynamic #235,  0            // InvokeDynamic #0:makeConcatWithConstants:(I)Ljava/lang/String;
       812: aload         6
       814: invokevirtual #239                // Method ext/mods/commons/logging/CLogger.error:(Ljava/lang/Object;Ljava/lang/Throwable;)V
       817: goto          126
       820: getstatic     #231                // Field LOGGER:Lext/mods/commons/logging/CLogger;
       823: ldc           #245                // String Offline stored.
       825: invokevirtual #247                // Method ext/mods/commons/logging/CLogger.info:(Ljava/lang/Object;)V
       828: aload_3
       829: ifnull        868
       832: aload_3
       833: invokeinterface #251,  1          // InterfaceMethod java/sql/PreparedStatement.close:()V
       838: goto          868
       841: astore        4
       843: aload_3
       844: ifnull        865
       847: aload_3
       848: invokeinterface #251,  1          // InterfaceMethod java/sql/PreparedStatement.close:()V
       853: goto          865
       856: astore        5
       858: aload         4
       860: aload         5
       862: invokevirtual #56                 // Method java/lang/Throwable.addSuppressed:(Ljava/lang/Throwable;)V
       865: aload         4
       867: athrow
       868: aload_2
       869: ifnull        905
       872: aload_2
       873: invokeinterface #251,  1          // InterfaceMethod java/sql/PreparedStatement.close:()V
       878: goto          905
       881: astore_3
       882: aload_2
       883: ifnull        903
       886: aload_2
       887: invokeinterface #251,  1          // InterfaceMethod java/sql/PreparedStatement.close:()V
       892: goto          903
       895: astore        4
       897: aload_3
       898: aload         4
       900: invokevirtual #56                 // Method java/lang/Throwable.addSuppressed:(Ljava/lang/Throwable;)V
       903: aload_3
       904: athrow
       905: aload_1
       906: ifnull        940
       909: aload_1
       910: invokeinterface #252,  1          // InterfaceMethod java/sql/Connection.close:()V
       915: goto          940
       918: astore_2
       919: aload_1
       920: ifnull        938
       923: aload_1
       924: invokeinterface #252,  1          // InterfaceMethod java/sql/Connection.close:()V
       929: goto          938
       932: astore_3
       933: aload_2
       934: aload_3
       935: invokevirtual #56                 // Method java/lang/Throwable.addSuppressed:(Ljava/lang/Throwable;)V
       938: aload_2
       939: athrow
       940: goto          953
       943: astore_1
       944: getstatic     #231                // Field LOGGER:Lext/mods/commons/logging/CLogger;
       947: ldc           #253                // String Error while saving offline:
       949: aload_1
       950: invokevirtual #239                // Method ext/mods/commons/logging/CLogger.error:(Ljava/lang/Object;Ljava/lang/Throwable;)V
       953: return
      Exception table:
         from    to  target type
            49    69    84   Class java/lang/Throwable
            91    98   101   Class java/lang/Throwable
           148   282   797   Class java/lang/Exception
           285   416   797   Class java/lang/Exception
           419   668   797   Class java/lang/Exception
           671   794   797   Class java/lang/Exception
            41   828   841   Class java/lang/Throwable
           847   853   856   Class java/lang/Throwable
            32   868   881   Class java/lang/Throwable
           886   892   895   Class java/lang/Throwable
            23   905   918   Class java/lang/Throwable
           923   929   932   Class java/lang/Throwable
            19   940   943   Class java/lang/Exception
      LineNumberTable:
        line 52: 0
        line 53: 18
        line 55: 19
        line 56: 23
        line 57: 32
        line 59: 41
        line 61: 49
        line 62: 59
        line 63: 69
        line 59: 84
        line 65: 113
        line 69: 148
        line 71: 178
        line 72: 190
        line 73: 202
        line 75: 234
        line 78: 276
        line 79: 282
        line 81: 285
        line 82: 300
        line 84: 332
        line 85: 344
        line 86: 359
        line 87: 372
        line 88: 385
        line 89: 398
        line 90: 404
        line 91: 407
        line 95: 410
        line 96: 416
        line 98: 419
        line 99: 434
        line 100: 443
        line 102: 451
        line 104: 485
        line 105: 497
        line 106: 509
        line 107: 522
        line 108: 535
        line 109: 543
        line 110: 549
        line 114: 555
        line 116: 587
        line 117: 599
        line 118: 611
        line 119: 624
        line 120: 637
        line 121: 650
        line 122: 656
        line 124: 659
        line 127: 662
        line 128: 668
        line 130: 671
        line 131: 686
        line 133: 718
        line 134: 730
        line 135: 742
        line 136: 750
        line 137: 763
        line 138: 771
        line 139: 777
        line 143: 780
        line 144: 787
        line 150: 794
        line 147: 797
        line 149: 799
        line 151: 817
        line 153: 820
        line 154: 828
        line 55: 841
        line 154: 868
        line 55: 881
        line 154: 905
        line 55: 918
        line 158: 940
        line 155: 943
        line 157: 944
        line 159: 953
      LocalVariableTable:
        Start  Length  Slot  Name   Signature
           49      64     4   stm   Ljava/sql/Statement;
          332      72     7     i   Lext/mods/gameserver/model/trade/TradeItem;
          485      64     7 holder   Lext/mods/gameserver/model/SellBuffHolder;
          587      69     7     i   Lext/mods/gameserver/model/trade/TradeItem;
          718      59     7     i   Lext/mods/gameserver/model/records/ManufactureItem;
          799      18     6     e   Ljava/lang/Exception;
          148     669     5 player   Lext/mods/gameserver/model/actor/Player;
           41     827     3  item   Ljava/sql/PreparedStatement;
           32     873     2 offline   Ljava/sql/PreparedStatement;
           23     917     1   con   Ljava/sql/Connection;
          944       9     1     e   Ljava/lang/Exception;
            0     954     0  this   Lext/mods/gameserver/data/sql/OfflineTradersTable;
      StackMapTable: number_of_entries = 43
        frame_type = 18 /* same */
        frame_type = 0 /* same */
        frame_type = 255 /* full_frame */
          offset_delta = 64
          locals = [ class ext/mods/gameserver/data/sql/OfflineTradersTable, class java/sql/Connection, class java/sql/PreparedStatement, class java/sql/PreparedStatement, class java/sql/Statement ]
          stack = [ class java/lang/Throwable ]
        frame_type = 255 /* full_frame */
          offset_delta = 16
          locals = [ class ext/mods/gameserver/data/sql/OfflineTradersTable, class java/sql/Connection, class java/sql/PreparedStatement, class java/sql/PreparedStatement, class java/sql/Statement, class java/lang/Throwable ]
          stack = [ class java/lang/Throwable ]
        frame_type = 8 /* same */
        frame_type = 249 /* chop */
          offset_delta = 2
        frame_type = 252 /* append */
          offset_delta = 12
          locals = [ class java/util/Iterator ]
        frame_type = 252 /* append */
          offset_delta = 51
          locals = [ class ext/mods/gameserver/model/actor/Player ]
        frame_type = 255 /* full_frame */
          offset_delta = 42
          locals = [ class ext/mods/gameserver/data/sql/OfflineTradersTable, class java/sql/Connection, class java/sql/PreparedStatement, class java/sql/PreparedStatement, class java/util/Iterator, class ext/mods/gameserver/model/actor/Player ]
          stack = [ class java/sql/PreparedStatement, int ]
        frame_type = 255 /* full_frame */
          offset_delta = 7
          locals = [ class ext/mods/gameserver/data/sql/OfflineTradersTable, class java/sql/Connection, class java/sql/PreparedStatement, class java/sql/PreparedStatement, class java/util/Iterator, class ext/mods/gameserver/model/actor/Player ]
          stack = [ class java/sql/PreparedStatement, int, int ]
        frame_type = 46 /* same */
        frame_type = 8 /* same */
        frame_type = 252 /* append */
          offset_delta = 24
          locals = [ class java/util/Iterator ]
        frame_type = 250 /* chop */
          offset_delta = 96
        frame_type = 2 /* same */
        frame_type = 8 /* same */
        frame_type = 252 /* append */
          offset_delta = 43
          locals = [ class java/util/Iterator ]
        frame_type = 250 /* chop */
          offset_delta = 88
        frame_type = 2 /* same */
        frame_type = 252 /* append */
          offset_delta = 9
          locals = [ class java/util/Iterator ]
        frame_type = 250 /* chop */
          offset_delta = 93
        frame_type = 2 /* same */
        frame_type = 8 /* same */
        frame_type = 252 /* append */
          offset_delta = 24
          locals = [ class java/util/Iterator ]
        frame_type = 250 /* chop */
          offset_delta = 83
        frame_type = 13 /* same */
        frame_type = 66 /* same_locals_1_stack_item */
          stack = [ class java/lang/Exception ]
        frame_type = 250 /* chop */
          offset_delta = 19
        frame_type = 250 /* chop */
          offset_delta = 2
        frame_type = 84 /* same_locals_1_stack_item */
          stack = [ class java/lang/Throwable ]
        frame_type = 255 /* full_frame */
          offset_delta = 14
          locals = [ class ext/mods/gameserver/data/sql/OfflineTradersTable, class java/sql/Connection, class java/sql/PreparedStatement, class java/sql/PreparedStatement, class java/lang/Throwable ]
          stack = [ class java/lang/Throwable ]
        frame_type = 8 /* same */
        frame_type = 249 /* chop */
          offset_delta = 2
        frame_type = 76 /* same_locals_1_stack_item */
          stack = [ class java/lang/Throwable ]
        frame_type = 255 /* full_frame */
          offset_delta = 13
          locals = [ class ext/mods/gameserver/data/sql/OfflineTradersTable, class java/sql/Connection, class java/sql/PreparedStatement, class java/lang/Throwable ]
          stack = [ class java/lang/Throwable ]
        frame_type = 7 /* same */
        frame_type = 249 /* chop */
          offset_delta = 1
        frame_type = 76 /* same_locals_1_stack_item */
          stack = [ class java/lang/Throwable ]
        frame_type = 255 /* full_frame */
          offset_delta = 13
          locals = [ class ext/mods/gameserver/data/sql/OfflineTradersTable, class java/sql/Connection, class java/lang/Throwable ]
          stack = [ class java/lang/Throwable ]
        frame_type = 5 /* same */
        frame_type = 249 /* chop */
          offset_delta = 1
        frame_type = 66 /* same_locals_1_stack_item */
          stack = [ class java/lang/Exception ]
        frame_type = 9 /* same */

  public void saveOfflineTraders(ext.mods.gameserver.model.actor.Player);
    descriptor: (Lext/mods/gameserver/model/actor/Player;)V
    flags: (0x0001) ACC_PUBLIC
    Code:
      stack=4, locals=9, args_size=2
         0: invokestatic  #19                 // Method ext/mods/commons/pool/ConnectionPool.getConnection:()Ljava/sql/Connection;
         3: astore_2
         4: aload_2
         5: ldc           #41                 // String DELETE FROM character_offline_trade
         7: invokeinterface #29,  2           // InterfaceMethod java/sql/Connection.prepareStatement:(Ljava/lang/String;)Ljava/sql/PreparedStatement;
        12: astore_3
        13: aload_2
        14: ldc           #49                 // String DELETE FROM character_offline_trade_items
        16: invokeinterface #29,  2           // InterfaceMethod java/sql/Connection.prepareStatement:(Ljava/lang/String;)Ljava/sql/PreparedStatement;
        21: astore        4
        23: aload_3
        24: invokeinterface #227,  1          // InterfaceMethod java/sql/PreparedStatement.execute:()Z
        29: pop
        30: aload         4
        32: invokeinterface #227,  1          // InterfaceMethod java/sql/PreparedStatement.execute:()Z
        37: pop
        38: aload_2
        39: ldc           #27                 // String INSERT INTO character_offline_trade (`charId`,`time`,`type`,`title`) VALUES (?,?,?,?)
        41: invokeinterface #29,  2           // InterfaceMethod java/sql/Connection.prepareStatement:(Ljava/lang/String;)Ljava/sql/PreparedStatement;
        46: astore        5
        48: aload_2
        49: ldc           #35                 // String INSERT INTO character_offline_trade_items (`charId`,`item`,`count`,`price`,`enchant`) VALUES (?,?,?,?,?)
        51: invokeinterface #29,  2           // InterfaceMethod java/sql/Connection.prepareStatement:(Ljava/lang/String;)Ljava/sql/PreparedStatement;
        56: astore        6
        58: aload         5
        60: iconst_1
        61: aload_1
        62: invokevirtual #107                // Method ext/mods/gameserver/model/actor/Player.getObjectId:()I
        65: invokeinterface #111,  3          // InterfaceMethod java/sql/PreparedStatement.setInt:(II)V
        70: aload         5
        72: iconst_2
        73: aload_1
        74: invokevirtual #117                // Method ext/mods/gameserver/model/actor/Player.getOfflineStartTime:()J
        77: invokeinterface #121,  4          // InterfaceMethod java/sql/PreparedStatement.setLong:(IJ)V
        82: aload         5
        84: iconst_3
        85: aload_1
        86: invokevirtual #125                // Method ext/mods/gameserver/model/actor/Player.isSellingBuffs:()Z
        89: ifeq          101
        92: getstatic     #128                // Field ext/mods/gameserver/enums/actors/OperateType.SELL_BUFFS:Lext/mods/gameserver/enums/actors/OperateType;
        95: invokevirtual #131                // Method ext/mods/gameserver/enums/actors/OperateType.getId:()I
        98: goto          108
       101: aload_1
       102: invokevirtual #88                 // Method ext/mods/gameserver/model/actor/Player.getOperateType:()Lext/mods/gameserver/enums/actors/OperateType;
       105: invokevirtual #131                // Method ext/mods/gameserver/enums/actors/OperateType.getId:()I
       108: invokeinterface #111,  3          // InterfaceMethod java/sql/PreparedStatement.setInt:(II)V
       113: getstatic     #134                // Field ext/mods/gameserver/data/sql/OfflineTradersTable$1.$SwitchMap$ext$mods$gameserver$enums$actors$OperateType:[I
       116: aload_1
       117: invokevirtual #88                 // Method ext/mods/gameserver/model/actor/Player.getOperateType:()Lext/mods/gameserver/enums/actors/OperateType;
       120: invokevirtual #140                // Method ext/mods/gameserver/enums/actors/OperateType.ordinal:()I
       123: iaload
       124: tableswitch   { // 1 to 4

                       1: 156

                       2: 285

                       3: 285

                       4: 534
                 default: 647
            }
       156: aload         5
       158: iconst_4
       159: aload_1
       160: invokevirtual #143                // Method ext/mods/gameserver/model/actor/Player.getBuyList:()Lext/mods/gameserver/model/trade/TradeList;
       163: invokevirtual #147                // Method ext/mods/gameserver/model/trade/TradeList.getTitle:()Ljava/lang/String;
       166: invokeinterface #153,  3          // InterfaceMethod java/sql/PreparedStatement.setString:(ILjava/lang/String;)V
       171: aload_1
       172: invokevirtual #143                // Method ext/mods/gameserver/model/actor/Player.getBuyList:()Lext/mods/gameserver/model/trade/TradeList;
       175: invokevirtual #157                // Method ext/mods/gameserver/model/trade/TradeList.iterator:()Ljava/util/Iterator;
       178: astore        7
       180: aload         7
       182: invokeinterface #76,  1           // InterfaceMethod java/util/Iterator.hasNext:()Z
       187: ifeq          282
       190: aload         7
       192: invokeinterface #82,  1           // InterfaceMethod java/util/Iterator.next:()Ljava/lang/Object;
       197: checkcast     #158                // class ext/mods/gameserver/model/trade/TradeItem
       200: astore        8
       202: aload         6
       204: iconst_1
       205: aload_1
       206: invokevirtual #107                // Method ext/mods/gameserver/model/actor/Player.getObjectId:()I
       209: invokeinterface #111,  3          // InterfaceMethod java/sql/PreparedStatement.setInt:(II)V
       214: aload         6
       216: iconst_2
       217: aload         8
       219: invokevirtual #160                // Method ext/mods/gameserver/model/trade/TradeItem.getItem:()Lext/mods/gameserver/model/item/kind/Item;
       222: invokevirtual #164                // Method ext/mods/gameserver/model/item/kind/Item.getItemId:()I
       225: invokeinterface #111,  3          // InterfaceMethod java/sql/PreparedStatement.setInt:(II)V
       230: aload         6
       232: iconst_3
       233: aload         8
       235: invokevirtual #169                // Method ext/mods/gameserver/model/trade/TradeItem.getQuantity:()I
       238: i2l
       239: invokeinterface #121,  4          // InterfaceMethod java/sql/PreparedStatement.setLong:(IJ)V
       244: aload         6
       246: iconst_4
       247: aload         8
       249: invokevirtual #172                // Method ext/mods/gameserver/model/trade/TradeItem.getPrice:()I
       252: i2l
       253: invokeinterface #121,  4          // InterfaceMethod java/sql/PreparedStatement.setLong:(IJ)V
       258: aload         6
       260: iconst_5
       261: aload         8
       263: invokevirtual #175                // Method ext/mods/gameserver/model/trade/TradeItem.getEnchant:()I
       266: i2l
       267: invokeinterface #121,  4          // InterfaceMethod java/sql/PreparedStatement.setLong:(IJ)V
       272: aload         6
       274: invokeinterface #178,  1          // InterfaceMethod java/sql/PreparedStatement.addBatch:()V
       279: goto          180
       282: goto          647
       285: aload         5
       287: iconst_4
       288: aload_1
       289: invokevirtual #181                // Method ext/mods/gameserver/model/actor/Player.getSellList:()Lext/mods/gameserver/model/trade/TradeList;
       292: invokevirtual #147                // Method ext/mods/gameserver/model/trade/TradeList.getTitle:()Ljava/lang/String;
       295: invokeinterface #153,  3          // InterfaceMethod java/sql/PreparedStatement.setString:(ILjava/lang/String;)V
       300: aload_1
       301: invokevirtual #181                // Method ext/mods/gameserver/model/actor/Player.getSellList:()Lext/mods/gameserver/model/trade/TradeList;
       304: iconst_0
       305: invokevirtual #184                // Method ext/mods/gameserver/model/trade/TradeList.updateItems:(Z)V
       308: aload_1
       309: invokevirtual #125                // Method ext/mods/gameserver/model/actor/Player.isSellingBuffs:()Z
       312: ifeq          423
       315: aload_1
       316: invokevirtual #188                // Method ext/mods/gameserver/model/actor/Player.getSellingBuffs:()Ljava/util/List;
       319: invokeinterface #192,  1          // InterfaceMethod java/util/List.iterator:()Ljava/util/Iterator;
       324: astore        7
       326: aload         7
       328: invokeinterface #76,  1           // InterfaceMethod java/util/Iterator.hasNext:()Z
       333: ifeq          420
       336: aload         7
       338: invokeinterface #82,  1           // InterfaceMethod java/util/Iterator.next:()Ljava/lang/Object;
       343: checkcast     #195                // class ext/mods/gameserver/model/SellBuffHolder
       346: astore        8
       348: aload         6
       350: iconst_1
       351: aload_1
       352: invokevirtual #107                // Method ext/mods/gameserver/model/actor/Player.getObjectId:()I
       355: invokeinterface #111,  3          // InterfaceMethod java/sql/PreparedStatement.setInt:(II)V
       360: aload         6
       362: iconst_2
       363: aload         8
       365: invokevirtual #197                // Method ext/mods/gameserver/model/SellBuffHolder.getSkillId:()I
       368: invokeinterface #111,  3          // InterfaceMethod java/sql/PreparedStatement.setInt:(II)V
       373: aload         6
       375: iconst_3
       376: aload         8
       378: invokevirtual #200                // Method ext/mods/gameserver/model/SellBuffHolder.getSkillLvl:()I
       381: i2l
       382: invokeinterface #121,  4          // InterfaceMethod java/sql/PreparedStatement.setLong:(IJ)V
       387: aload         6
       389: iconst_4
       390: aload         8
       392: invokevirtual #203                // Method ext/mods/gameserver/model/SellBuffHolder.getPrice:()I
       395: i2l
       396: invokeinterface #121,  4          // InterfaceMethod java/sql/PreparedStatement.setLong:(IJ)V
       401: aload         6
       403: iconst_5
       404: lconst_0
       405: invokeinterface #121,  4          // InterfaceMethod java/sql/PreparedStatement.setLong:(IJ)V
       410: aload         6
       412: invokeinterface #178,  1          // InterfaceMethod java/sql/PreparedStatement.addBatch:()V
       417: goto          326
       420: goto          647
       423: aload_1
       424: invokevirtual #181                // Method ext/mods/gameserver/model/actor/Player.getSellList:()Lext/mods/gameserver/model/trade/TradeList;
       427: invokevirtual #157                // Method ext/mods/gameserver/model/trade/TradeList.iterator:()Ljava/util/Iterator;
       430: astore        7
       432: aload         7
       434: invokeinterface #76,  1           // InterfaceMethod java/util/Iterator.hasNext:()Z
       439: ifeq          531
       442: aload         7
       444: invokeinterface #82,  1           // InterfaceMethod java/util/Iterator.next:()Ljava/lang/Object;
       449: checkcast     #158                // class ext/mods/gameserver/model/trade/TradeItem
       452: astore        8
       454: aload         6
       456: iconst_1
       457: aload_1
       458: invokevirtual #107                // Method ext/mods/gameserver/model/actor/Player.getObjectId:()I
       461: invokeinterface #111,  3          // InterfaceMethod java/sql/PreparedStatement.setInt:(II)V
       466: aload         6
       468: iconst_2
       469: aload         8
       471: invokevirtual #204                // Method ext/mods/gameserver/model/trade/TradeItem.getObjectId:()I
       474: invokeinterface #111,  3          // InterfaceMethod java/sql/PreparedStatement.setInt:(II)V
       479: aload         6
       481: iconst_3
       482: aload         8
       484: invokevirtual #169                // Method ext/mods/gameserver/model/trade/TradeItem.getQuantity:()I
       487: i2l
       488: invokeinterface #121,  4          // InterfaceMethod java/sql/PreparedStatement.setLong:(IJ)V
       493: aload         6
       495: iconst_4
       496: aload         8
       498: invokevirtual #172                // Method ext/mods/gameserver/model/trade/TradeItem.getPrice:()I
       501: i2l
       502: invokeinterface #121,  4          // InterfaceMethod java/sql/PreparedStatement.setLong:(IJ)V
       507: aload         6
       509: iconst_5
       510: aload         8
       512: invokevirtual #175                // Method ext/mods/gameserver/model/trade/TradeItem.getEnchant:()I
       515: i2l
       516: invokeinterface #121,  4          // InterfaceMethod java/sql/PreparedStatement.setLong:(IJ)V
       521: aload         6
       523: invokeinterface #178,  1          // InterfaceMethod java/sql/PreparedStatement.addBatch:()V
       528: goto          432
       531: goto          647
       534: aload         5
       536: iconst_4
       537: aload_1
       538: invokevirtual #205                // Method ext/mods/gameserver/model/actor/Player.getManufactureList:()Lext/mods/gameserver/model/craft/ManufactureList;
       541: invokevirtual #209                // Method ext/mods/gameserver/model/craft/ManufactureList.getStoreName:()Ljava/lang/String;
       544: invokeinterface #153,  3          // InterfaceMethod java/sql/PreparedStatement.setString:(ILjava/lang/String;)V
       549: aload_1
       550: invokevirtual #205                // Method ext/mods/gameserver/model/actor/Player.getManufactureList:()Lext/mods/gameserver/model/craft/ManufactureList;
       553: invokevirtual #214                // Method ext/mods/gameserver/model/craft/ManufactureList.iterator:()Ljava/util/Iterator;
       556: astore        7
       558: aload         7
       560: invokeinterface #76,  1           // InterfaceMethod java/util/Iterator.hasNext:()Z
       565: ifeq          647
       568: aload         7
       570: invokeinterface #82,  1           // InterfaceMethod java/util/Iterator.next:()Ljava/lang/Object;
       575: checkcast     #215                // class ext/mods/gameserver/model/records/ManufactureItem
       578: astore        8
       580: aload         6
       582: iconst_1
       583: aload_1
       584: invokevirtual #107                // Method ext/mods/gameserver/model/actor/Player.getObjectId:()I
       587: invokeinterface #111,  3          // InterfaceMethod java/sql/PreparedStatement.setInt:(II)V
       592: aload         6
       594: iconst_2
       595: aload         8
       597: invokevirtual #217                // Method ext/mods/gameserver/model/records/ManufactureItem.recipeId:()I
       600: invokeinterface #111,  3          // InterfaceMethod java/sql/PreparedStatement.setInt:(II)V
       605: aload         6
       607: iconst_3
       608: lconst_0
       609: invokeinterface #121,  4          // InterfaceMethod java/sql/PreparedStatement.setLong:(IJ)V
       614: aload         6
       616: iconst_4
       617: aload         8
       619: invokevirtual #220                // Method ext/mods/gameserver/model/records/ManufactureItem.cost:()I
       622: i2l
       623: invokeinterface #121,  4          // InterfaceMethod java/sql/PreparedStatement.setLong:(IJ)V
       628: aload         6
       630: iconst_5
       631: lconst_0
       632: invokeinterface #121,  4          // InterfaceMethod java/sql/PreparedStatement.setLong:(IJ)V
       637: aload         6
       639: invokeinterface #178,  1          // InterfaceMethod java/sql/PreparedStatement.addBatch:()V
       644: goto          558
       647: aload         6
       649: invokeinterface #223,  1          // InterfaceMethod java/sql/PreparedStatement.executeBatch:()[I
       654: pop
       655: aload         5
       657: invokeinterface #227,  1          // InterfaceMethod java/sql/PreparedStatement.execute:()Z
       662: pop
       663: aload         6
       665: ifnull        707
       668: aload         6
       670: invokeinterface #251,  1          // InterfaceMethod java/sql/PreparedStatement.close:()V
       675: goto          707
       678: astore        7
       680: aload         6
       682: ifnull        704
       685: aload         6
       687: invokeinterface #251,  1          // InterfaceMethod java/sql/PreparedStatement.close:()V
       692: goto          704
       695: astore        8
       697: aload         7
       699: aload         8
       701: invokevirtual #56                 // Method java/lang/Throwable.addSuppressed:(Ljava/lang/Throwable;)V
       704: aload         7
       706: athrow
       707: aload         5
       709: ifnull        751
       712: aload         5
       714: invokeinterface #251,  1          // InterfaceMethod java/sql/PreparedStatement.close:()V
       719: goto          751
       722: astore        6
       724: aload         5
       726: ifnull        748
       729: aload         5
       731: invokeinterface #251,  1          // InterfaceMethod java/sql/PreparedStatement.close:()V
       736: goto          748
       739: astore        7
       741: aload         6
       743: aload         7
       745: invokevirtual #56                 // Method java/lang/Throwable.addSuppressed:(Ljava/lang/Throwable;)V
       748: aload         6
       750: athrow
       751: goto          766
       754: astore        5
       756: getstatic     #231                // Field LOGGER:Lext/mods/commons/logging/CLogger;
       759: ldc           #255                // String error while saving offline traders.
       761: aload         5
       763: invokevirtual #239                // Method ext/mods/commons/logging/CLogger.error:(Ljava/lang/Object;Ljava/lang/Throwable;)V
       766: aload         4
       768: ifnull        810
       771: aload         4
       773: invokeinterface #251,  1          // InterfaceMethod java/sql/PreparedStatement.close:()V
       778: goto          810
       781: astore        5
       783: aload         4
       785: ifnull        807
       788: aload         4
       790: invokeinterface #251,  1          // InterfaceMethod java/sql/PreparedStatement.close:()V
       795: goto          807
       798: astore        6
       800: aload         5
       802: aload         6
       804: invokevirtual #56                 // Method java/lang/Throwable.addSuppressed:(Ljava/lang/Throwable;)V
       807: aload         5
       809: athrow
       810: aload_3
       811: ifnull        850
       814: aload_3
       815: invokeinterface #251,  1          // InterfaceMethod java/sql/PreparedStatement.close:()V
       820: goto          850
       823: astore        4
       825: aload_3
       826: ifnull        847
       829: aload_3
       830: invokeinterface #251,  1          // InterfaceMethod java/sql/PreparedStatement.close:()V
       835: goto          847
       838: astore        5
       840: aload         4
       842: aload         5
       844: invokevirtual #56                 // Method java/lang/Throwable.addSuppressed:(Ljava/lang/Throwable;)V
       847: aload         4
       849: athrow
       850: aload_2
       851: ifnull        887
       854: aload_2
       855: invokeinterface #252,  1          // InterfaceMethod java/sql/Connection.close:()V
       860: goto          887
       863: astore_3
       864: aload_2
       865: ifnull        885
       868: aload_2
       869: invokeinterface #252,  1          // InterfaceMethod java/sql/Connection.close:()V
       874: goto          885
       877: astore        4
       879: aload_3
       880: aload         4
       882: invokevirtual #56                 // Method java/lang/Throwable.addSuppressed:(Ljava/lang/Throwable;)V
       885: aload_3
       886: athrow
       887: goto          901
       890: astore_2
       891: getstatic     #231                // Field LOGGER:Lext/mods/commons/logging/CLogger;
       894: ldc_w         #257                // String error while clear table offline traders.
       897: aload_2
       898: invokevirtual #239                // Method ext/mods/commons/logging/CLogger.error:(Ljava/lang/Object;Ljava/lang/Throwable;)V
       901: return
      Exception table:
         from    to  target type
            58   663   678   Class java/lang/Throwable
           685   692   695   Class java/lang/Throwable
            48   707   722   Class java/lang/Throwable
           729   736   739   Class java/lang/Throwable
            38   751   754   Class java/lang/Exception
            23   766   781   Class java/lang/Throwable
           788   795   798   Class java/lang/Throwable
            13   810   823   Class java/lang/Throwable
           829   835   838   Class java/lang/Throwable
             4   850   863   Class java/lang/Throwable
           868   874   877   Class java/lang/Throwable
             0   887   890   Class java/lang/Exception
      LineNumberTable:
        line 163: 0
        line 164: 4
        line 165: 13
        line 167: 23
        line 168: 30
        line 170: 38
        line 171: 48
        line 173: 58
        line 174: 70
        line 175: 82
        line 177: 113
        line 180: 156
        line 181: 171
        line 183: 202
        line 184: 214
        line 185: 230
        line 186: 244
        line 187: 258
        line 188: 272
        line 189: 279
        line 190: 282
        line 194: 285
        line 195: 300
        line 196: 308
        line 198: 315
        line 200: 348
        line 201: 360
        line 202: 373
        line 203: 387
        line 204: 401
        line 205: 410
        line 206: 417
        line 210: 423
        line 212: 454
        line 213: 466
        line 214: 479
        line 215: 493
        line 216: 507
        line 217: 521
        line 218: 528
        line 220: 531
        line 223: 534
        line 224: 549
        line 226: 580
        line 227: 592
        line 228: 605
        line 229: 614
        line 230: 628
        line 231: 637
        line 232: 644
        line 236: 647
        line 237: 655
        line 238: 663
        line 170: 678
        line 238: 707
        line 170: 722
        line 242: 751
        line 239: 754
        line 241: 756
        line 243: 766
        line 163: 781
        line 243: 810
        line 163: 823
        line 243: 850
        line 163: 863
        line 247: 887
        line 244: 890
        line 246: 891
        line 248: 901
      LocalVariableTable:
        Start  Length  Slot  Name   Signature
          202      77     8     i   Lext/mods/gameserver/model/trade/TradeItem;
          348      69     8 holder   Lext/mods/gameserver/model/SellBuffHolder;
          454      74     8     i   Lext/mods/gameserver/model/trade/TradeItem;
          580      64     8     i   Lext/mods/gameserver/model/records/ManufactureItem;
           58     649     6   ps4   Ljava/sql/PreparedStatement;
           48     703     5   ps3   Ljava/sql/PreparedStatement;
          756      10     5     e   Ljava/lang/Exception;
           23     787     4   ps2   Ljava/sql/PreparedStatement;
           13     837     3    ps   Ljava/sql/PreparedStatement;
            4     883     2   con   Ljava/sql/Connection;
          891      10     2     e   Ljava/lang/Exception;
            0     902     0  this   Lext/mods/gameserver/data/sql/OfflineTradersTable;
            0     902     1 player   Lext/mods/gameserver/model/actor/Player;
      StackMapTable: number_of_entries = 38
        frame_type = 255 /* full_frame */
          offset_delta = 101
          locals = [ class ext/mods/gameserver/data/sql/OfflineTradersTable, class ext/mods/gameserver/model/actor/Player, class java/sql/Connection, class java/sql/PreparedStatement, class java/sql/PreparedStatement, class java/sql/PreparedStatement, class java/sql/PreparedStatement ]
          stack = [ class java/sql/PreparedStatement, int ]
        frame_type = 255 /* full_frame */
          offset_delta = 6
          locals = [ class ext/mods/gameserver/data/sql/OfflineTradersTable, class ext/mods/gameserver/model/actor/Player, class java/sql/Connection, class java/sql/PreparedStatement, class java/sql/PreparedStatement, class java/sql/PreparedStatement, class java/sql/PreparedStatement ]
          stack = [ class java/sql/PreparedStatement, int, int ]
        frame_type = 47 /* same */
        frame_type = 252 /* append */
          offset_delta = 23
          locals = [ class java/util/Iterator ]
        frame_type = 250 /* chop */
          offset_delta = 101
        frame_type = 2 /* same */
        frame_type = 252 /* append */
          offset_delta = 40
          locals = [ class java/util/Iterator ]
        frame_type = 250 /* chop */
          offset_delta = 93
        frame_type = 2 /* same */
        frame_type = 252 /* append */
          offset_delta = 8
          locals = [ class java/util/Iterator ]
        frame_type = 250 /* chop */
          offset_delta = 98
        frame_type = 2 /* same */
        frame_type = 252 /* append */
          offset_delta = 23
          locals = [ class java/util/Iterator ]
        frame_type = 250 /* chop */
          offset_delta = 88
        frame_type = 94 /* same_locals_1_stack_item */
          stack = [ class java/lang/Throwable ]
        frame_type = 255 /* full_frame */
          offset_delta = 16
          locals = [ class ext/mods/gameserver/data/sql/OfflineTradersTable, class ext/mods/gameserver/model/actor/Player, class java/sql/Connection, class java/sql/PreparedStatement, class java/sql/PreparedStatement, class java/sql/PreparedStatement, class java/sql/PreparedStatement, class java/lang/Throwable ]
          stack = [ class java/lang/Throwable ]
        frame_type = 8 /* same */
        frame_type = 249 /* chop */
          offset_delta = 2
        frame_type = 78 /* same_locals_1_stack_item */
          stack = [ class java/lang/Throwable ]
        frame_type = 255 /* full_frame */
          offset_delta = 16
          locals = [ class ext/mods/gameserver/data/sql/OfflineTradersTable, class ext/mods/gameserver/model/actor/Player, class java/sql/Connection, class java/sql/PreparedStatement, class java/sql/PreparedStatement, class java/sql/PreparedStatement, class java/lang/Throwable ]
          stack = [ class java/lang/Throwable ]
        frame_type = 8 /* same */
        frame_type = 249 /* chop */
          offset_delta = 2
        frame_type = 66 /* same_locals_1_stack_item */
          stack = [ class java/lang/Exception ]
        frame_type = 11 /* same */
        frame_type = 78 /* same_locals_1_stack_item */
          stack = [ class java/lang/Throwable ]
        frame_type = 255 /* full_frame */
          offset_delta = 16
          locals = [ class ext/mods/gameserver/data/sql/OfflineTradersTable, class ext/mods/gameserver/model/actor/Player, class java/sql/Connection, class java/sql/PreparedStatement, class java/sql/PreparedStatement, class java/lang/Throwable ]
          stack = [ class java/lang/Throwable ]
        frame_type = 8 /* same */
        frame_type = 249 /* chop */
          offset_delta = 2
        frame_type = 76 /* same_locals_1_stack_item */
          stack = [ class java/lang/Throwable ]
        frame_type = 255 /* full_frame */
          offset_delta = 14
          locals = [ class ext/mods/gameserver/data/sql/OfflineTradersTable, class ext/mods/gameserver/model/actor/Player, class java/sql/Connection, class java/sql/PreparedStatement, class java/lang/Throwable ]
          stack = [ class java/lang/Throwable ]
        frame_type = 8 /* same */
        frame_type = 249 /* chop */
          offset_delta = 2
        frame_type = 76 /* same_locals_1_stack_item */
          stack = [ class java/lang/Throwable ]
        frame_type = 255 /* full_frame */
          offset_delta = 13
          locals = [ class ext/mods/gameserver/data/sql/OfflineTradersTable, class ext/mods/gameserver/model/actor/Player, class java/sql/Connection, class java/lang/Throwable ]
          stack = [ class java/lang/Throwable ]
        frame_type = 7 /* same */
        frame_type = 249 /* chop */
          offset_delta = 1
        frame_type = 66 /* same_locals_1_stack_item */
          stack = [ class java/lang/Exception ]
        frame_type = 10 /* same */

  public void restore();
    descriptor: ()V
    flags: (0x0001) ACC_PUBLIC
    Code:
      stack=7, locals=17, args_size=1
         0: getstatic     #7                  // Field ext/mods/Config.RESTORE_OFFLINERS:Z
         3: ifeq          18
         6: getstatic     #13                 // Field ext/mods/Config.OFFLINE_TRADE_ENABLE:Z
         9: ifne          19
        12: getstatic     #16                 // Field ext/mods/Config.OFFLINE_CRAFT_ENABLE:Z
        15: ifne          19
        18: return
        19: iconst_0
        20: istore_1
        21: invokestatic  #19                 // Method ext/mods/commons/pool/ConnectionPool.getConnection:()Ljava/sql/Connection;
        24: astore_2
        25: aload_2
        26: invokeinterface #37,  1           // InterfaceMethod java/sql/Connection.createStatement:()Ljava/sql/Statement;
        31: astore_3
        32: aload_3
        33: ldc_w         #259                // String SELECT * FROM character_offline_trade
        36: invokeinterface #261,  2          // InterfaceMethod java/sql/Statement.executeQuery:(Ljava/lang/String;)Ljava/sql/ResultSet;
        41: astore        4
        43: aload         4
        45: invokeinterface #265,  1          // InterfaceMethod java/sql/ResultSet.next:()Z
        50: ifeq          749
        53: aload         4
        55: ldc_w         #269                // String time
        58: invokeinterface #271,  2          // InterfaceMethod java/sql/ResultSet.getLong:(Ljava/lang/String;)J
        63: lstore        5
        65: getstatic     #275                // Field ext/mods/Config.OFFLINE_MAX_DAYS:I
        68: ifle          83
        71: aload_0
        72: lload         5
        74: invokevirtual #279                // Method isExpired:(J)Z
        77: ifeq          83
        80: goto          43
        83: aload_0
        84: aload         4
        86: ldc_w         #283                // String type
        89: invokeinterface #285,  2          // InterfaceMethod java/sql/ResultSet.getInt:(Ljava/lang/String;)I
        94: invokevirtual #289                // Method getType:(I)Lext/mods/gameserver/enums/actors/OperateType;
        97: astore        7
        99: iconst_0
       100: istore        8
       102: aload         7
       104: getstatic     #128                // Field ext/mods/gameserver/enums/actors/OperateType.SELL_BUFFS:Lext/mods/gameserver/enums/actors/OperateType;
       107: if_acmpne     113
       110: iconst_1
       111: istore        8
       113: iload         8
       115: ifeq          124
       118: getstatic     #293                // Field ext/mods/gameserver/enums/actors/OperateType.PACKAGE_SELL:Lext/mods/gameserver/enums/actors/OperateType;
       121: goto          126
       124: aload         7
       126: astore        9
       128: aload         9
       130: ifnull        43
       133: aload         9
       135: getstatic     #92                 // Field ext/mods/gameserver/enums/actors/OperateType.NONE:Lext/mods/gameserver/enums/actors/OperateType;
       138: if_acmpne     144
       141: goto          43
       144: aload         4
       146: ldc_w         #296                // String charId
       149: invokeinterface #285,  2          // InterfaceMethod java/sql/ResultSet.getInt:(Ljava/lang/String;)I
       154: iconst_1
       155: invokestatic  #298                // Method ext/mods/gameserver/model/actor/Player.restore:(IZ)Lext/mods/gameserver/model/actor/Player;
       158: astore        10
       160: aload         10
       162: ifnonnull     168
       165: goto          43
       168: new           #103                // class ext/mods/gameserver/network/GameClient
       171: dup
       172: aconst_null
       173: invokespecial #302                // Method ext/mods/gameserver/network/GameClient."<init>":(Lext/mods/commons/mmocore/MMOConnection;)V
       176: astore        11
       178: aload         11
       180: aload         10
       182: invokevirtual #305                // Method ext/mods/gameserver/network/GameClient.spawnOffline:(Lext/mods/gameserver/model/actor/Player;)V
       185: aload         10
       187: lload         5
       189: invokevirtual #309                // Method ext/mods/gameserver/model/actor/Player.setOfflineStartTime:(J)V
       192: aload         10
       194: invokevirtual #313                // Method ext/mods/gameserver/model/actor/Player.sitDown:()Z
       197: pop
       198: iload         8
       200: ifeq          209
       203: aload         10
       205: iconst_1
       206: invokevirtual #316                // Method ext/mods/gameserver/model/actor/Player.setSellingBuffs:(Z)V
       209: aload         4
       211: ldc_w         #319                // String title
       214: invokeinterface #321,  2          // InterfaceMethod java/sql/ResultSet.getString:(Ljava/lang/String;)Ljava/lang/String;
       219: astore        12
       221: aload_2
       222: ldc_w         #325                // String SELECT * FROM character_offline_trade_items WHERE charId = ?
       225: invokeinterface #29,  2           // InterfaceMethod java/sql/Connection.prepareStatement:(Ljava/lang/String;)Ljava/sql/PreparedStatement;
       230: astore        13
       232: aload         13
       234: iconst_1
       235: aload         10
       237: invokevirtual #107                // Method ext/mods/gameserver/model/actor/Player.getObjectId:()I
       240: invokeinterface #111,  3          // InterfaceMethod java/sql/PreparedStatement.setInt:(II)V
       245: aload         13
       247: invokeinterface #327,  1          // InterfaceMethod java/sql/PreparedStatement.executeQuery:()Ljava/sql/ResultSet;
       252: astore        14
       254: getstatic     #134                // Field ext/mods/gameserver/data/sql/OfflineTradersTable$1.$SwitchMap$ext$mods$gameserver$enums$actors$OperateType:[I
       257: aload         9
       259: invokevirtual #140                // Method ext/mods/gameserver/enums/actors/OperateType.ordinal:()I
       262: iaload
       263: tableswitch   { // 1 to 4

                       1: 292

                       2: 359

                       3: 359

                       4: 508
                 default: 563
            }
       292: aload         14
       294: invokeinterface #265,  1          // InterfaceMethod java/sql/ResultSet.next:()Z
       299: ifeq          346
       302: aload         10
       304: invokevirtual #143                // Method ext/mods/gameserver/model/actor/Player.getBuyList:()Lext/mods/gameserver/model/trade/TradeList;
       307: aload         14
       309: iconst_2
       310: invokeinterface #330,  2          // InterfaceMethod java/sql/ResultSet.getInt:(I)I
       315: aload         14
       317: iconst_3
       318: invokeinterface #330,  2          // InterfaceMethod java/sql/ResultSet.getInt:(I)I
       323: aload         14
       325: iconst_4
       326: invokeinterface #330,  2          // InterfaceMethod java/sql/ResultSet.getInt:(I)I
       331: aload         14
       333: iconst_5
       334: invokeinterface #330,  2          // InterfaceMethod java/sql/ResultSet.getInt:(I)I
       339: invokevirtual #333                // Method ext/mods/gameserver/model/trade/TradeList.addItemByItemId:(IIII)Lext/mods/gameserver/model/trade/TradeItem;
       342: pop
       343: goto          292
       346: aload         10
       348: invokevirtual #143                // Method ext/mods/gameserver/model/actor/Player.getBuyList:()Lext/mods/gameserver/model/trade/TradeList;
       351: aload         12
       353: invokevirtual #337                // Method ext/mods/gameserver/model/trade/TradeList.setTitle:(Ljava/lang/String;)V
       356: goto          563
       359: aload         10
       361: invokevirtual #125                // Method ext/mods/gameserver/model/actor/Player.isSellingBuffs:()Z
       364: ifeq          428
       367: aload         14
       369: invokeinterface #265,  1          // InterfaceMethod java/sql/ResultSet.next:()Z
       374: ifeq          474
       377: aload         10
       379: invokevirtual #188                // Method ext/mods/gameserver/model/actor/Player.getSellingBuffs:()Ljava/util/List;
       382: new           #195                // class ext/mods/gameserver/model/SellBuffHolder
       385: dup
       386: aload         14
       388: ldc_w         #341                // String item
       391: invokeinterface #285,  2          // InterfaceMethod java/sql/ResultSet.getInt:(Ljava/lang/String;)I
       396: aload         14
       398: ldc_w         #343                // String count
       401: invokeinterface #285,  2          // InterfaceMethod java/sql/ResultSet.getInt:(Ljava/lang/String;)I
       406: aload         14
       408: ldc_w         #345                // String price
       411: invokeinterface #285,  2          // InterfaceMethod java/sql/ResultSet.getInt:(Ljava/lang/String;)I
       416: invokespecial #347                // Method ext/mods/gameserver/model/SellBuffHolder."<init>":(III)V
       419: invokeinterface #350,  2          // InterfaceMethod java/util/List.add:(Ljava/lang/Object;)Z
       424: pop
       425: goto          367
       428: aload         14
       430: invokeinterface #265,  1          // InterfaceMethod java/sql/ResultSet.next:()Z
       435: ifeq          474
       438: aload         10
       440: invokevirtual #181                // Method ext/mods/gameserver/model/actor/Player.getSellList:()Lext/mods/gameserver/model/trade/TradeList;
       443: aload         14
       445: iconst_2
       446: invokeinterface #330,  2          // InterfaceMethod java/sql/ResultSet.getInt:(I)I
       451: aload         14
       453: iconst_3
       454: invokeinterface #330,  2          // InterfaceMethod java/sql/ResultSet.getInt:(I)I
       459: aload         14
       461: iconst_4
       462: invokeinterface #330,  2          // InterfaceMethod java/sql/ResultSet.getInt:(I)I
       467: invokevirtual #354                // Method ext/mods/gameserver/model/trade/TradeList.addItem:(III)Lext/mods/gameserver/model/trade/TradeItem;
       470: pop
       471: goto          428
       474: aload         10
       476: invokevirtual #181                // Method ext/mods/gameserver/model/actor/Player.getSellList:()Lext/mods/gameserver/model/trade/TradeList;
       479: aload         12
       481: invokevirtual #337                // Method ext/mods/gameserver/model/trade/TradeList.setTitle:(Ljava/lang/String;)V
       484: aload         10
       486: invokevirtual #181                // Method ext/mods/gameserver/model/actor/Player.getSellList:()Lext/mods/gameserver/model/trade/TradeList;
       489: aload         9
       491: getstatic     #293                // Field ext/mods/gameserver/enums/actors/OperateType.PACKAGE_SELL:Lext/mods/gameserver/enums/actors/OperateType;
       494: if_acmpne     501
       497: iconst_1
       498: goto          502
       501: iconst_0
       502: invokevirtual #358                // Method ext/mods/gameserver/model/trade/TradeList.setPackaged:(Z)V
       505: goto          563
       508: aload         14
       510: invokeinterface #265,  1          // InterfaceMethod java/sql/ResultSet.next:()Z
       515: ifeq          553
       518: aload         10
       520: invokevirtual #205                // Method ext/mods/gameserver/model/actor/Player.getManufactureList:()Lext/mods/gameserver/model/craft/ManufactureList;
       523: new           #215                // class ext/mods/gameserver/model/records/ManufactureItem
       526: dup
       527: aload         14
       529: iconst_2
       530: invokeinterface #330,  2          // InterfaceMethod java/sql/ResultSet.getInt:(I)I
       535: aload         14
       537: iconst_4
       538: invokeinterface #330,  2          // InterfaceMethod java/sql/ResultSet.getInt:(I)I
       543: invokespecial #361                // Method ext/mods/gameserver/model/records/ManufactureItem."<init>":(II)V
       546: invokevirtual #363                // Method ext/mods/gameserver/model/craft/ManufactureList.add:(Ljava/lang/Object;)Z
       549: pop
       550: goto          508
       553: aload         10
       555: invokevirtual #205                // Method ext/mods/gameserver/model/actor/Player.getManufactureList:()Lext/mods/gameserver/model/craft/ManufactureList;
       558: aload         12
       560: invokevirtual #364                // Method ext/mods/gameserver/model/craft/ManufactureList.setStoreName:(Ljava/lang/String;)V
       563: aload         14
       565: ifnull        607
       568: aload         14
       570: invokeinterface #367,  1          // InterfaceMethod java/sql/ResultSet.close:()V
       575: goto          607
       578: astore        15
       580: aload         14
       582: ifnull        604
       585: aload         14
       587: invokeinterface #367,  1          // InterfaceMethod java/sql/ResultSet.close:()V
       592: goto          604
       595: astore        16
       597: aload         15
       599: aload         16
       601: invokevirtual #56                 // Method java/lang/Throwable.addSuppressed:(Ljava/lang/Throwable;)V
       604: aload         15
       606: athrow
       607: getstatic     #368                // Field ext/mods/Config.OFFLINE_SLEEP_EFFECT:Z
       610: ifeq          632
       613: aload         10
       615: ldc_w         #371                // String 0x80
       618: invokestatic  #373                // Method java/lang/Integer.decode:(Ljava/lang/String;)Ljava/lang/Integer;
       621: invokevirtual #379                // Method java/lang/Integer.intValue:()I
       624: invokevirtual #382                // Method ext/mods/gameserver/model/actor/Player.startAbnormalEffect:(I)V
       627: aload         10
       629: invokevirtual #386                // Method ext/mods/gameserver/model/actor/Player.broadcastUserInfo:()V
       632: aload         10
       634: aload         9
       636: invokevirtual #389                // Method ext/mods/gameserver/model/actor/Player.setOperateType:(Lext/mods/gameserver/enums/actors/OperateType;)V
       639: aload         10
       641: invokevirtual #393                // Method ext/mods/gameserver/model/actor/Player.restoreEffects:()V
       644: aload         10
       646: invokevirtual #386                // Method ext/mods/gameserver/model/actor/Player.broadcastUserInfo:()V
       649: aload         10
       651: invokevirtual #396                // Method ext/mods/gameserver/model/actor/Player.broadcastTitleInfo:()V
       654: iinc          1, 1
       657: aload         13
       659: ifnull        701
       662: aload         13
       664: invokeinterface #251,  1          // InterfaceMethod java/sql/PreparedStatement.close:()V
       669: goto          701
       672: astore        14
       674: aload         13
       676: ifnull        698
       679: aload         13
       681: invokeinterface #251,  1          // InterfaceMethod java/sql/PreparedStatement.close:()V
       686: goto          698
       689: astore        15
       691: aload         14
       693: aload         15
       695: invokevirtual #56                 // Method java/lang/Throwable.addSuppressed:(Ljava/lang/Throwable;)V
       698: aload         14
       700: athrow
       701: goto          746
       704: astore        13
       706: getstatic     #231                // Field LOGGER:Lext/mods/commons/logging/CLogger;
       709: ldc_w         #399                // String Error loading offline {}({}).
       712: aload         13
       714: iconst_2
       715: anewarray     #2                  // class java/lang/Object
       718: dup
       719: iconst_0
       720: aload         10
       722: invokevirtual #401                // Method ext/mods/gameserver/model/actor/Player.getName:()Ljava/lang/String;
       725: aastore
       726: dup
       727: iconst_1
       728: aload         10
       730: invokevirtual #107                // Method ext/mods/gameserver/model/actor/Player.getObjectId:()I
       733: invokestatic  #404                // Method java/lang/Integer.valueOf:(I)Ljava/lang/Integer;
       736: aastore
       737: invokevirtual #408                // Method ext/mods/commons/logging/CLogger.warn:(Ljava/lang/Object;Ljava/lang/Throwable;[Ljava/lang/Object;)V
       740: aload         10
       742: iconst_1
       743: invokevirtual #412                // Method ext/mods/gameserver/model/actor/Player.logout:(Z)V
       746: goto          43
       749: getstatic     #231                // Field LOGGER:Lext/mods/commons/logging/CLogger;
       752: iload_1
       753: invokedynamic #415,  0            // InvokeDynamic #1:makeConcatWithConstants:(I)Ljava/lang/String;
       758: invokevirtual #247                // Method ext/mods/commons/logging/CLogger.info:(Ljava/lang/Object;)V
       761: aload_2
       762: invokeinterface #37,  1           // InterfaceMethod java/sql/Connection.createStatement:()Ljava/sql/Statement;
       767: astore        5
       769: aload         5
       771: ldc           #41                 // String DELETE FROM character_offline_trade
       773: invokeinterface #43,  2           // InterfaceMethod java/sql/Statement.execute:(Ljava/lang/String;)Z
       778: pop
       779: aload         5
       781: ldc           #49                 // String DELETE FROM character_offline_trade_items
       783: invokeinterface #43,  2           // InterfaceMethod java/sql/Statement.execute:(Ljava/lang/String;)Z
       788: pop
       789: aload         5
       791: ifnull        833
       794: aload         5
       796: invokeinterface #51,  1           // InterfaceMethod java/sql/Statement.close:()V
       801: goto          833
       804: astore        6
       806: aload         5
       808: ifnull        830
       811: aload         5
       813: invokeinterface #51,  1           // InterfaceMethod java/sql/Statement.close:()V
       818: goto          830
       821: astore        7
       823: aload         6
       825: aload         7
       827: invokevirtual #56                 // Method java/lang/Throwable.addSuppressed:(Ljava/lang/Throwable;)V
       830: aload         6
       832: athrow
       833: aload         4
       835: ifnull        877
       838: aload         4
       840: invokeinterface #367,  1          // InterfaceMethod java/sql/ResultSet.close:()V
       845: goto          877
       848: astore        5
       850: aload         4
       852: ifnull        874
       855: aload         4
       857: invokeinterface #367,  1          // InterfaceMethod java/sql/ResultSet.close:()V
       862: goto          874
       865: astore        6
       867: aload         5
       869: aload         6
       871: invokevirtual #56                 // Method java/lang/Throwable.addSuppressed:(Ljava/lang/Throwable;)V
       874: aload         5
       876: athrow
       877: aload_3
       878: ifnull        917
       881: aload_3
       882: invokeinterface #51,  1           // InterfaceMethod java/sql/Statement.close:()V
       887: goto          917
       890: astore        4
       892: aload_3
       893: ifnull        914
       896: aload_3
       897: invokeinterface #51,  1           // InterfaceMethod java/sql/Statement.close:()V
       902: goto          914
       905: astore        5
       907: aload         4
       909: aload         5
       911: invokevirtual #56                 // Method java/lang/Throwable.addSuppressed:(Ljava/lang/Throwable;)V
       914: aload         4
       916: athrow
       917: aload_2
       918: ifnull        954
       921: aload_2
       922: invokeinterface #252,  1          // InterfaceMethod java/sql/Connection.close:()V
       927: goto          954
       930: astore_3
       931: aload_2
       932: ifnull        952
       935: aload_2
       936: invokeinterface #252,  1          // InterfaceMethod java/sql/Connection.close:()V
       941: goto          952
       944: astore        4
       946: aload_3
       947: aload         4
       949: invokevirtual #56                 // Method java/lang/Throwable.addSuppressed:(Ljava/lang/Throwable;)V
       952: aload_3
       953: athrow
       954: goto          968
       957: astore_2
       958: getstatic     #231                // Field LOGGER:Lext/mods/commons/logging/CLogger;
       961: ldc_w         #416                // String Error while loading offline:
       964: aload_2
       965: invokevirtual #418                // Method ext/mods/commons/logging/CLogger.warn:(Ljava/lang/Object;Ljava/lang/Throwable;)V
       968: return
      Exception table:
         from    to  target type
           254   563   578   Class java/lang/Throwable
           585   592   595   Class java/lang/Throwable
           232   657   672   Class java/lang/Throwable
           679   686   689   Class java/lang/Throwable
           221   701   704   Class java/lang/Exception
           769   789   804   Class java/lang/Throwable
           811   818   821   Class java/lang/Throwable
            43   833   848   Class java/lang/Throwable
           855   862   865   Class java/lang/Throwable
            32   877   890   Class java/lang/Throwable
           896   902   905   Class java/lang/Throwable
            25   917   930   Class java/lang/Throwable
           935   941   944   Class java/lang/Throwable
            21   954   957   Class java/lang/Exception
      LineNumberTable:
        line 252: 0
        line 253: 18
        line 255: 19
        line 257: 21
        line 258: 25
        line 259: 32
        line 262: 43
        line 264: 53
        line 265: 65
        line 266: 80
        line 268: 83
        line 269: 99
        line 270: 102
        line 271: 110
        line 273: 113
        line 274: 128
        line 275: 141
        line 277: 144
        line 278: 160
        line 279: 165
        line 281: 168
        line 282: 178
        line 283: 185
        line 284: 192
        line 286: 198
        line 287: 203
        line 289: 209
        line 291: 221
        line 293: 232
        line 294: 245
        line 296: 254
        line 299: 292
        line 300: 302
        line 302: 346
        line 303: 356
        line 306: 359
        line 308: 367
        line 309: 377
        line 313: 428
        line 314: 438
        line 317: 474
        line 318: 484
        line 319: 505
        line 321: 508
        line 322: 518
        line 324: 553
        line 327: 563
        line 294: 578
        line 329: 607
        line 331: 613
        line 332: 627
        line 335: 632
        line 336: 639
        line 337: 644
        line 338: 649
        line 340: 654
        line 341: 657
        line 291: 672
        line 347: 701
        line 342: 704
        line 345: 706
        line 346: 740
        line 348: 746
        line 350: 749
        line 352: 761
        line 354: 769
        line 355: 779
        line 356: 789
        line 352: 804
        line 357: 833
        line 257: 848
        line 357: 877
        line 257: 890
        line 357: 917
        line 257: 930
        line 361: 954
        line 358: 957
        line 360: 958
        line 362: 968
      LocalVariableTable:
        Start  Length  Slot  Name   Signature
          254     353    14  item   Ljava/sql/ResultSet;
          232     469    13    ps   Ljava/sql/PreparedStatement;
          706      40    13     e   Ljava/lang/Exception;
           65     681     5  time   J
           99     647     7 oType   Lext/mods/gameserver/enums/actors/OperateType;
          102     644     8 isSellBuff   Z
          128     618     9  type   Lext/mods/gameserver/enums/actors/OperateType;
          160     586    10 player   Lext/mods/gameserver/model/actor/Player;
          178     568    11 client   Lext/mods/gameserver/network/GameClient;
          221     525    12 title   Ljava/lang/String;
          769      64     5  stm2   Ljava/sql/Statement;
           43     834     4    rs   Ljava/sql/ResultSet;
           32     885     3   stm   Ljava/sql/Statement;
           25     929     2   con   Ljava/sql/Connection;
          958      10     2     e   Ljava/lang/Exception;
            0     969     0  this   Lext/mods/gameserver/data/sql/OfflineTradersTable;
           21     948     1 count   I
      StackMapTable: number_of_entries = 51
        frame_type = 18 /* same */
        frame_type = 0 /* same */
        frame_type = 255 /* full_frame */
          offset_delta = 23
          locals = [ class ext/mods/gameserver/data/sql/OfflineTradersTable, int, class java/sql/Connection, class java/sql/Statement, class java/sql/ResultSet ]
          stack = []
        frame_type = 252 /* append */
          offset_delta = 39
          locals = [ long ]
        frame_type = 253 /* append */
          offset_delta = 29
          locals = [ class ext/mods/gameserver/enums/actors/OperateType, int ]
        frame_type = 10 /* same */
        frame_type = 65 /* same_locals_1_stack_item */
          stack = [ class ext/mods/gameserver/enums/actors/OperateType ]
        frame_type = 252 /* append */
          offset_delta = 17
          locals = [ class ext/mods/gameserver/enums/actors/OperateType ]
        frame_type = 252 /* append */
          offset_delta = 23
          locals = [ class ext/mods/gameserver/model/actor/Player ]
        frame_type = 252 /* append */
          offset_delta = 40
          locals = [ class ext/mods/gameserver/network/GameClient ]
        frame_type = 254 /* append */
          offset_delta = 82
          locals = [ class java/lang/String, class java/sql/PreparedStatement, class java/sql/ResultSet ]
        frame_type = 53 /* same */
        frame_type = 12 /* same */
        frame_type = 7 /* same */
        frame_type = 60 /* same */
        frame_type = 45 /* same */
        frame_type = 90 /* same_locals_1_stack_item */
          stack = [ class ext/mods/gameserver/model/trade/TradeList ]
        frame_type = 255 /* full_frame */
          offset_delta = 0
          locals = [ class ext/mods/gameserver/data/sql/OfflineTradersTable, int, class java/sql/Connection, class java/sql/Statement, class java/sql/ResultSet, long, class ext/mods/gameserver/enums/actors/OperateType, int, class ext/mods/gameserver/enums/actors/OperateType, class ext/mods/gameserver/model/actor/Player, class ext/mods/gameserver/network/GameClient, class java/lang/String, class java/sql/PreparedStatement, class java/sql/ResultSet ]
          stack = [ class ext/mods/gameserver/model/trade/TradeList, int ]
        frame_type = 5 /* same */
        frame_type = 44 /* same */
        frame_type = 9 /* same */
        frame_type = 78 /* same_locals_1_stack_item */
          stack = [ class java/lang/Throwable ]
        frame_type = 255 /* full_frame */
          offset_delta = 16
          locals = [ class ext/mods/gameserver/data/sql/OfflineTradersTable, int, class java/sql/Connection, class java/sql/Statement, class java/sql/ResultSet, long, class ext/mods/gameserver/enums/actors/OperateType, int, class ext/mods/gameserver/enums/actors/OperateType, class ext/mods/gameserver/model/actor/Player, class ext/mods/gameserver/network/GameClient, class java/lang/String, class java/sql/PreparedStatement, class java/sql/ResultSet, class java/lang/Throwable ]
          stack = [ class java/lang/Throwable ]
        frame_type = 8 /* same */
        frame_type = 249 /* chop */
          offset_delta = 2
        frame_type = 24 /* same */
        frame_type = 103 /* same_locals_1_stack_item */
          stack = [ class java/lang/Throwable ]
        frame_type = 255 /* full_frame */
          offset_delta = 16
          locals = [ class ext/mods/gameserver/data/sql/OfflineTradersTable, int, class java/sql/Connection, class java/sql/Statement, class java/sql/ResultSet, long, class ext/mods/gameserver/enums/actors/OperateType, int, class ext/mods/gameserver/enums/actors/OperateType, class ext/mods/gameserver/model/actor/Player, class ext/mods/gameserver/network/GameClient, class java/lang/String, class java/sql/PreparedStatement, class java/lang/Throwable ]
          stack = [ class java/lang/Throwable ]
        frame_type = 8 /* same */
        frame_type = 249 /* chop */
          offset_delta = 2
        frame_type = 66 /* same_locals_1_stack_item */
          stack = [ class java/lang/Exception ]
        frame_type = 255 /* full_frame */
          offset_delta = 41
          locals = [ class ext/mods/gameserver/data/sql/OfflineTradersTable, int, class java/sql/Connection, class java/sql/Statement, class java/sql/ResultSet ]
          stack = []
        frame_type = 2 /* same */
        frame_type = 255 /* full_frame */
          offset_delta = 54
          locals = [ class ext/mods/gameserver/data/sql/OfflineTradersTable, int, class java/sql/Connection, class java/sql/Statement, class java/sql/ResultSet, class java/sql/Statement ]
          stack = [ class java/lang/Throwable ]
        frame_type = 255 /* full_frame */
          offset_delta = 16
          locals = [ class ext/mods/gameserver/data/sql/OfflineTradersTable, int, class java/sql/Connection, class java/sql/Statement, class java/sql/ResultSet, class java/sql/Statement, class java/lang/Throwable ]
          stack = [ class java/lang/Throwable ]
        frame_type = 8 /* same */
        frame_type = 249 /* chop */
          offset_delta = 2
        frame_type = 78 /* same_locals_1_stack_item */
          stack = [ class java/lang/Throwable ]
        frame_type = 255 /* full_frame */
          offset_delta = 16
          locals = [ class ext/mods/gameserver/data/sql/OfflineTradersTable, int, class java/sql/Connection, class java/sql/Statement, class java/sql/ResultSet, class java/lang/Throwable ]
          stack = [ class java/lang/Throwable ]
        frame_type = 8 /* same */
        frame_type = 249 /* chop */
          offset_delta = 2
        frame_type = 76 /* same_locals_1_stack_item */
          stack = [ class java/lang/Throwable ]
        frame_type = 255 /* full_frame */
          offset_delta = 14
          locals = [ class ext/mods/gameserver/data/sql/OfflineTradersTable, int, class java/sql/Connection, class java/sql/Statement, class java/lang/Throwable ]
          stack = [ class java/lang/Throwable ]
        frame_type = 8 /* same */
        frame_type = 249 /* chop */
          offset_delta = 2
        frame_type = 76 /* same_locals_1_stack_item */
          stack = [ class java/lang/Throwable ]
        frame_type = 255 /* full_frame */
          offset_delta = 13
          locals = [ class ext/mods/gameserver/data/sql/OfflineTradersTable, int, class java/sql/Connection, class java/lang/Throwable ]
          stack = [ class java/lang/Throwable ]
        frame_type = 7 /* same */
        frame_type = 249 /* chop */
          offset_delta = 1
        frame_type = 66 /* same_locals_1_stack_item */
          stack = [ class java/lang/Exception ]
        frame_type = 10 /* same */

  protected ext.mods.gameserver.enums.actors.OperateType getType(int);
    descriptor: (I)Lext/mods/gameserver/enums/actors/OperateType;
    flags: (0x0004) ACC_PROTECTED
    Code:
      stack=6, locals=6, args_size=2
         0: invokestatic  #420                // Method ext/mods/gameserver/enums/actors/OperateType.values:()[Lext/mods/gameserver/enums/actors/OperateType;
         3: astore_2
         4: aload_2
         5: arraylength
         6: istore_3
         7: iconst_0
         8: istore        4
        10: iload         4
        12: iload_3
        13: if_icmpge     40
        16: aload_2
        17: iload         4
        19: aaload
        20: astore        5
        22: aload         5
        24: invokevirtual #131                // Method ext/mods/gameserver/enums/actors/OperateType.getId:()I
        27: iload_1
        28: if_icmpne     34
        31: aload         5
        33: areturn
        34: iinc          4, 1
        37: goto          10
        40: getstatic     #231                // Field LOGGER:Lext/mods/commons/logging/CLogger;
        43: ldc_w         #424                // String Wrong OperateType id \'{}\' not found.
        46: iconst_1
        47: anewarray     #2                  // class java/lang/Object
        50: dup
        51: iconst_0
        52: iload_1
        53: invokestatic  #404                // Method java/lang/Integer.valueOf:(I)Ljava/lang/Integer;
        56: aastore
        57: invokevirtual #426                // Method ext/mods/commons/logging/CLogger.warn:(Ljava/lang/Object;[Ljava/lang/Object;)V
        60: aconst_null
        61: areturn
      LineNumberTable:
        line 366: 0
        line 367: 22
        line 368: 31
        line 366: 34
        line 370: 40
        line 371: 60
      LocalVariableTable:
        Start  Length  Slot  Name   Signature
           22      12     5  type   Lext/mods/gameserver/enums/actors/OperateType;
            0      62     0  this   Lext/mods/gameserver/data/sql/OfflineTradersTable;
            0      62     1    id   I
      StackMapTable: number_of_entries = 3
        frame_type = 254 /* append */
          offset_delta = 10
          locals = [ class "[Lext/mods/gameserver/enums/actors/OperateType;", int, int ]
        frame_type = 23 /* same */
        frame_type = 248 /* chop */
          offset_delta = 5

  protected boolean isExpired(long);
    descriptor: (J)Z
    flags: (0x0004) ACC_PROTECTED
    Code:
      stack=4, locals=4, args_size=2
         0: invokestatic  #429                // Method java/util/Calendar.getInstance:()Ljava/util/Calendar;
         3: astore_3
         4: aload_3
         5: lload_1
         6: invokevirtual #434                // Method java/util/Calendar.setTimeInMillis:(J)V
         9: aload_3
        10: bipush        6
        12: getstatic     #275                // Field ext/mods/Config.OFFLINE_MAX_DAYS:I
        15: invokevirtual #437                // Method java/util/Calendar.add:(II)V
        18: aload_3
        19: invokevirtual #439                // Method java/util/Calendar.getTimeInMillis:()J
        22: invokestatic  #442                // Method java/lang/System.currentTimeMillis:()J
        25: lcmp
        26: ifgt          33
        29: iconst_1
        30: goto          34
        33: iconst_0
        34: ireturn
      LineNumberTable:
        line 376: 0
        line 377: 4
        line 378: 9
        line 379: 18
      LocalVariableTable:
        Start  Length  Slot  Name   Signature
            0      35     0  this   Lext/mods/gameserver/data/sql/OfflineTradersTable;
            0      35     1  time   J
            4      31     3   cal   Ljava/util/Calendar;
      StackMapTable: number_of_entries = 2
        frame_type = 252 /* append */
          offset_delta = 33
          locals = [ class java/util/Calendar ]
        frame_type = 64 /* same_locals_1_stack_item */
          stack = [ int ]

  public static boolean offlineMode(ext.mods.gameserver.model.actor.Player);
    descriptor: (Lext/mods/gameserver/model/actor/Player;)Z
    flags: (0x0009) ACC_PUBLIC, ACC_STATIC
    Code:
      stack=2, locals=1, args_size=1
         0: aload_0
         1: invokevirtual #447                // Method ext/mods/gameserver/model/actor/Player.isInOlympiadMode:()Z
         4: ifne          24
         7: aload_0
         8: invokevirtual #450                // Method ext/mods/gameserver/model/actor/Player.isInJail:()Z
        11: ifne          24
        14: aload_0
        15: invokevirtual #453                // Method ext/mods/gameserver/model/actor/Player.getBoatInfo:()Lext/mods/gameserver/model/actor/container/player/BoatInfo;
        18: invokevirtual #457                // Method ext/mods/gameserver/model/actor/container/player/BoatInfo.getBoat:()Lext/mods/gameserver/model/actor/Boat;
        21: ifnull        26
        24: iconst_0
        25: ireturn
        26: getstatic     #463                // Field ext/mods/Config.OFFLINE_MODE_IN_PEACE_ZONE:Z
        29: ifeq          44
        32: aload_0
        33: getstatic     #466                // Field ext/mods/gameserver/enums/ZoneId.PEACE:Lext/mods/gameserver/enums/ZoneId;
        36: invokevirtual #472                // Method ext/mods/gameserver/model/actor/Player.isInsideZone:(Lext/mods/gameserver/enums/ZoneId;)Z
        39: ifne          44
        42: iconst_0
        43: ireturn
        44: getstatic     #134                // Field ext/mods/gameserver/data/sql/OfflineTradersTable$1.$SwitchMap$ext$mods$gameserver$enums$actors$OperateType:[I
        47: aload_0
        48: invokevirtual #88                 // Method ext/mods/gameserver/model/actor/Player.getOperateType:()Lext/mods/gameserver/enums/actors/OperateType;
        51: invokevirtual #140                // Method ext/mods/gameserver/enums/actors/OperateType.ordinal:()I
        54: iaload
        55: tableswitch   { // 1 to 4

                       1: 84

                       2: 84

                       3: 84

                       4: 88
                 default: 92
            }
        84: getstatic     #13                 // Field ext/mods/Config.OFFLINE_TRADE_ENABLE:Z
        87: ireturn
        88: getstatic     #16                 // Field ext/mods/Config.OFFLINE_CRAFT_ENABLE:Z
        91: ireturn
        92: iconst_0
        93: ireturn
      LineNumberTable:
        line 384: 0
        line 385: 24
        line 387: 26
        line 388: 42
        line 390: 44
        line 395: 84
        line 397: 88
        line 400: 92
      LocalVariableTable:
        Start  Length  Slot  Name   Signature
            0      94     0 player   Lext/mods/gameserver/model/actor/Player;
      StackMapTable: number_of_entries = 6
        frame_type = 24 /* same */
        frame_type = 1 /* same */
        frame_type = 17 /* same */
        frame_type = 39 /* same */
        frame_type = 3 /* same */
        frame_type = 3 /* same */

  public static final ext.mods.gameserver.data.sql.OfflineTradersTable getInstance();
    descriptor: ()Lext/mods/gameserver/data/sql/OfflineTradersTable;
    flags: (0x0019) ACC_PUBLIC, ACC_STATIC, ACC_FINAL
    Code:
      stack=1, locals=0, args_size=0
         0: getstatic     #476                // Field ext/mods/gameserver/data/sql/OfflineTradersTable$SingletonHolder.INSTANCE:Lext/mods/gameserver/data/sql/OfflineTradersTable;
         3: areturn
      LineNumberTable:
        line 405: 0

  static {};
    descriptor: ()V
    flags: (0x0008) ACC_STATIC
    Code:
      stack=3, locals=0, args_size=0
         0: new           #240                // class ext/mods/commons/logging/CLogger
         3: dup
         4: ldc           #25                 // class ext/mods/gameserver/data/sql/OfflineTradersTable
         6: invokevirtual #482                // Method java/lang/Class.getName:()Ljava/lang/String;
         9: invokespecial #485                // Method ext/mods/commons/logging/CLogger."<init>":(Ljava/lang/String;)V
        12: putstatic     #231                // Field LOGGER:Lext/mods/commons/logging/CLogger;
        15: return
      LineNumberTable:
        line 41: 0
}
SourceFile: "OfflineTradersTable.java"
NestMembers:
  ext/mods/gameserver/data/sql/OfflineTradersTable$1
  ext/mods/gameserver/data/sql/OfflineTradersTable$SingletonHolder
BootstrapMethods:
  0: #548 REF_invokeStatic java/lang/invoke/StringConcatFactory.makeConcatWithConstants:(Ljava/lang/invoke/MethodHandles$Lookup;Ljava/lang/String;Ljava/lang/invoke/MethodType;Ljava/lang/String;[Ljava/lang/Object;)Ljava/lang/invoke/CallSite;
    Method arguments:
      #544 Error while saving offline: \u0001
  1: #548 REF_invokeStatic java/lang/invoke/StringConcatFactory.makeConcatWithConstants:(Ljava/lang/invoke/MethodHandles$Lookup;Ljava/lang/String;Ljava/lang/invoke/MethodType;Ljava/lang/String;[Ljava/lang/Object;)Ljava/lang/invoke/CallSite;
    Method arguments:
      #546 Loaded \u0001 offline.
InnerClasses:
  static #135;                            // class ext/mods/gameserver/data/sql/OfflineTradersTable$1
  public static final #560= #556 of #558; // Lookup=class java/lang/invoke/MethodHandles$Lookup of class java/lang/invoke/MethodHandles
