// Bytecode for: ext.mods.gameserver.data.sql.PlayerInfoTable
// File: ext\mods\gameserver\data\sql\PlayerInfoTable.class

Classfile /c:/Users/User/Desktop/BrProject/bin/main/ext/mods/gameserver/data/sql/PlayerInfoTable.class
  Last modified 9 de jul de 2026; size 6538 bytes
  MD5 checksum 9fedc2eedb3b653ed7fdeb476e2be18d
  Compiled from "PlayerInfoTable.java"
public final class ext.mods.gameserver.data.sql.PlayerInfoTable
  minor version: 0
  major version: 69
  flags: (0x0031) ACC_PUBLIC, ACC_FINAL, ACC_SUPER
  this_class: #11                         // ext/mods/gameserver/data/sql/PlayerInfoTable
  super_class: #2                         // java/lang/Object
  interfaces: 0, fields: 3, methods: 12, attributes: 4
Constant pool:
    #1 = Methodref          #2.#3         // java/lang/Object."<init>":()V
    #2 = Class              #4            // java/lang/Object
    #3 = NameAndType        #5:#6         // "<init>":()V
    #4 = Utf8               java/lang/Object
    #5 = Utf8               <init>
    #6 = Utf8               ()V
    #7 = Class              #8            // java/util/concurrent/ConcurrentHashMap
    #8 = Utf8               java/util/concurrent/ConcurrentHashMap
    #9 = Methodref          #7.#3         // java/util/concurrent/ConcurrentHashMap."<init>":()V
   #10 = Fieldref           #11.#12       // ext/mods/gameserver/data/sql/PlayerInfoTable._infos:Ljava/util/Map;
   #11 = Class              #13           // ext/mods/gameserver/data/sql/PlayerInfoTable
   #12 = NameAndType        #14:#15       // _infos:Ljava/util/Map;
   #13 = Utf8               ext/mods/gameserver/data/sql/PlayerInfoTable
   #14 = Utf8               _infos
   #15 = Utf8               Ljava/util/Map;
   #16 = Methodref          #17.#18       // ext/mods/commons/pool/ConnectionPool.getConnection:()Ljava/sql/Connection;
   #17 = Class              #19           // ext/mods/commons/pool/ConnectionPool
   #18 = NameAndType        #20:#21       // getConnection:()Ljava/sql/Connection;
   #19 = Utf8               ext/mods/commons/pool/ConnectionPool
   #20 = Utf8               getConnection
   #21 = Utf8               ()Ljava/sql/Connection;
   #22 = String             #23           // SELECT account_name, obj_Id, char_name, accesslevel FROM characters
   #23 = Utf8               SELECT account_name, obj_Id, char_name, accesslevel FROM characters
   #24 = InterfaceMethodref #25.#26       // java/sql/Connection.prepareStatement:(Ljava/lang/String;)Ljava/sql/PreparedStatement;
   #25 = Class              #27           // java/sql/Connection
   #26 = NameAndType        #28:#29       // prepareStatement:(Ljava/lang/String;)Ljava/sql/PreparedStatement;
   #27 = Utf8               java/sql/Connection
   #28 = Utf8               prepareStatement
   #29 = Utf8               (Ljava/lang/String;)Ljava/sql/PreparedStatement;
   #30 = InterfaceMethodref #31.#32       // java/sql/PreparedStatement.executeQuery:()Ljava/sql/ResultSet;
   #31 = Class              #33           // java/sql/PreparedStatement
   #32 = NameAndType        #34:#35       // executeQuery:()Ljava/sql/ResultSet;
   #33 = Utf8               java/sql/PreparedStatement
   #34 = Utf8               executeQuery
   #35 = Utf8               ()Ljava/sql/ResultSet;
   #36 = InterfaceMethodref #37.#38       // java/sql/ResultSet.next:()Z
   #37 = Class              #39           // java/sql/ResultSet
   #38 = NameAndType        #40:#41       // next:()Z
   #39 = Utf8               java/sql/ResultSet
   #40 = Utf8               next
   #41 = Utf8               ()Z
   #42 = String             #43           // obj_Id
   #43 = Utf8               obj_Id
   #44 = InterfaceMethodref #37.#45       // java/sql/ResultSet.getInt:(Ljava/lang/String;)I
   #45 = NameAndType        #46:#47       // getInt:(Ljava/lang/String;)I
   #46 = Utf8               getInt
   #47 = Utf8               (Ljava/lang/String;)I
   #48 = Methodref          #49.#50       // java/lang/Integer.valueOf:(I)Ljava/lang/Integer;
   #49 = Class              #51           // java/lang/Integer
   #50 = NameAndType        #52:#53       // valueOf:(I)Ljava/lang/Integer;
   #51 = Utf8               java/lang/Integer
   #52 = Utf8               valueOf
   #53 = Utf8               (I)Ljava/lang/Integer;
   #54 = Class              #55           // ext/mods/gameserver/data/sql/PlayerInfoTable$PlayerInfo
   #55 = Utf8               ext/mods/gameserver/data/sql/PlayerInfoTable$PlayerInfo
   #56 = String             #57           // account_name
   #57 = Utf8               account_name
   #58 = InterfaceMethodref #37.#59       // java/sql/ResultSet.getString:(Ljava/lang/String;)Ljava/lang/String;
   #59 = NameAndType        #60:#61       // getString:(Ljava/lang/String;)Ljava/lang/String;
   #60 = Utf8               getString
   #61 = Utf8               (Ljava/lang/String;)Ljava/lang/String;
   #62 = String             #63           // char_name
   #63 = Utf8               char_name
   #64 = String             #65           // accesslevel
   #65 = Utf8               accesslevel
   #66 = Methodref          #54.#67       // ext/mods/gameserver/data/sql/PlayerInfoTable$PlayerInfo."<init>":(Lext/mods/gameserver/data/sql/PlayerInfoTable;Ljava/lang/String;Ljava/lang/String;I)V
   #67 = NameAndType        #5:#68        // "<init>":(Lext/mods/gameserver/data/sql/PlayerInfoTable;Ljava/lang/String;Ljava/lang/String;I)V
   #68 = Utf8               (Lext/mods/gameserver/data/sql/PlayerInfoTable;Ljava/lang/String;Ljava/lang/String;I)V
   #69 = InterfaceMethodref #70.#71       // java/util/Map.put:(Ljava/lang/Object;Ljava/lang/Object;)Ljava/lang/Object;
   #70 = Class              #72           // java/util/Map
   #71 = NameAndType        #73:#74       // put:(Ljava/lang/Object;Ljava/lang/Object;)Ljava/lang/Object;
   #72 = Utf8               java/util/Map
   #73 = Utf8               put
   #74 = Utf8               (Ljava/lang/Object;Ljava/lang/Object;)Ljava/lang/Object;
   #75 = InterfaceMethodref #37.#76       // java/sql/ResultSet.close:()V
   #76 = NameAndType        #77:#6        // close:()V
   #77 = Utf8               close
   #78 = Class              #79           // java/lang/Throwable
   #79 = Utf8               java/lang/Throwable
   #80 = Methodref          #78.#81       // java/lang/Throwable.addSuppressed:(Ljava/lang/Throwable;)V
   #81 = NameAndType        #82:#83       // addSuppressed:(Ljava/lang/Throwable;)V
   #82 = Utf8               addSuppressed
   #83 = Utf8               (Ljava/lang/Throwable;)V
   #84 = InterfaceMethodref #31.#76       // java/sql/PreparedStatement.close:()V
   #85 = InterfaceMethodref #25.#76       // java/sql/Connection.close:()V
   #86 = Class              #87           // java/lang/Exception
   #87 = Utf8               java/lang/Exception
   #88 = Fieldref           #11.#89       // ext/mods/gameserver/data/sql/PlayerInfoTable.LOGGER:Lext/mods/commons/logging/CLogger;
   #89 = NameAndType        #90:#91       // LOGGER:Lext/mods/commons/logging/CLogger;
   #90 = Utf8               LOGGER
   #91 = Utf8               Lext/mods/commons/logging/CLogger;
   #92 = String             #93           // Couldn\'t load player infos.
   #93 = Utf8               Couldn\'t load player infos.
   #94 = Methodref          #95.#96       // ext/mods/commons/logging/CLogger.error:(Ljava/lang/Object;Ljava/lang/Throwable;)V
   #95 = Class              #97           // ext/mods/commons/logging/CLogger
   #96 = NameAndType        #98:#99       // error:(Ljava/lang/Object;Ljava/lang/Throwable;)V
   #97 = Utf8               ext/mods/commons/logging/CLogger
   #98 = Utf8               error
   #99 = Utf8               (Ljava/lang/Object;Ljava/lang/Throwable;)V
  #100 = String             #101          // Loaded {} player infos.
  #101 = Utf8               Loaded {} player infos.
  #102 = InterfaceMethodref #70.#103      // java/util/Map.size:()I
  #103 = NameAndType        #104:#105     // size:()I
  #104 = Utf8               size
  #105 = Utf8               ()I
  #106 = Methodref          #95.#107      // ext/mods/commons/logging/CLogger.info:(Ljava/lang/Object;[Ljava/lang/Object;)V
  #107 = NameAndType        #108:#109     // info:(Ljava/lang/Object;[Ljava/lang/Object;)V
  #108 = Utf8               info
  #109 = Utf8               (Ljava/lang/Object;[Ljava/lang/Object;)V
  #110 = InterfaceMethodref #70.#111      // java/util/Map.putIfAbsent:(Ljava/lang/Object;Ljava/lang/Object;)Ljava/lang/Object;
  #111 = NameAndType        #112:#74      // putIfAbsent:(Ljava/lang/Object;Ljava/lang/Object;)Ljava/lang/Object;
  #112 = Utf8               putIfAbsent
  #113 = Methodref          #114.#115     // ext/mods/gameserver/model/actor/Player.getObjectId:()I
  #114 = Class              #116          // ext/mods/gameserver/model/actor/Player
  #115 = NameAndType        #117:#105     // getObjectId:()I
  #116 = Utf8               ext/mods/gameserver/model/actor/Player
  #117 = Utf8               getObjectId
  #118 = InterfaceMethodref #70.#119      // java/util/Map.get:(Ljava/lang/Object;)Ljava/lang/Object;
  #119 = NameAndType        #120:#121     // get:(Ljava/lang/Object;)Ljava/lang/Object;
  #120 = Utf8               get
  #121 = Utf8               (Ljava/lang/Object;)Ljava/lang/Object;
  #122 = Methodref          #114.#123     // ext/mods/gameserver/model/actor/Player.getAccessLevel:()Lext/mods/gameserver/model/AccessLevel;
  #123 = NameAndType        #124:#125     // getAccessLevel:()Lext/mods/gameserver/model/AccessLevel;
  #124 = Utf8               getAccessLevel
  #125 = Utf8               ()Lext/mods/gameserver/model/AccessLevel;
  #126 = Methodref          #127.#128     // ext/mods/gameserver/model/AccessLevel.getLevel:()I
  #127 = Class              #129          // ext/mods/gameserver/model/AccessLevel
  #128 = NameAndType        #130:#105     // getLevel:()I
  #129 = Utf8               ext/mods/gameserver/model/AccessLevel
  #130 = Utf8               getLevel
  #131 = Methodref          #54.#132      // ext/mods/gameserver/data/sql/PlayerInfoTable$PlayerInfo.setAccessLevel:(I)V
  #132 = NameAndType        #133:#134     // setAccessLevel:(I)V
  #133 = Utf8               setAccessLevel
  #134 = Utf8               (I)V
  #135 = Methodref          #114.#136     // ext/mods/gameserver/model/actor/Player.getName:()Ljava/lang/String;
  #136 = NameAndType        #137:#138     // getName:()Ljava/lang/String;
  #137 = Utf8               getName
  #138 = Utf8               ()Ljava/lang/String;
  #139 = Methodref          #54.#140      // ext/mods/gameserver/data/sql/PlayerInfoTable$PlayerInfo.getPlayerName:()Ljava/lang/String;
  #140 = NameAndType        #141:#138     // getPlayerName:()Ljava/lang/String;
  #141 = Utf8               getPlayerName
  #142 = Methodref          #143.#144     // java/lang/String.equalsIgnoreCase:(Ljava/lang/String;)Z
  #143 = Class              #145          // java/lang/String
  #144 = NameAndType        #146:#147     // equalsIgnoreCase:(Ljava/lang/String;)Z
  #145 = Utf8               java/lang/String
  #146 = Utf8               equalsIgnoreCase
  #147 = Utf8               (Ljava/lang/String;)Z
  #148 = Methodref          #54.#149      // ext/mods/gameserver/data/sql/PlayerInfoTable$PlayerInfo.setPlayerName:(Ljava/lang/String;)V
  #149 = NameAndType        #150:#151     // setPlayerName:(Ljava/lang/String;)V
  #150 = Utf8               setPlayerName
  #151 = Utf8               (Ljava/lang/String;)V
  #152 = InterfaceMethodref #70.#153      // java/util/Map.containsKey:(Ljava/lang/Object;)Z
  #153 = NameAndType        #154:#155     // containsKey:(Ljava/lang/Object;)Z
  #154 = Utf8               containsKey
  #155 = Utf8               (Ljava/lang/Object;)Z
  #156 = InterfaceMethodref #70.#157      // java/util/Map.remove:(Ljava/lang/Object;)Ljava/lang/Object;
  #157 = NameAndType        #158:#121     // remove:(Ljava/lang/Object;)Ljava/lang/Object;
  #158 = Utf8               remove
  #159 = Methodref          #143.#160     // java/lang/String.isEmpty:()Z
  #160 = NameAndType        #161:#41      // isEmpty:()Z
  #161 = Utf8               isEmpty
  #162 = InterfaceMethodref #70.#163      // java/util/Map.entrySet:()Ljava/util/Set;
  #163 = NameAndType        #164:#165     // entrySet:()Ljava/util/Set;
  #164 = Utf8               entrySet
  #165 = Utf8               ()Ljava/util/Set;
  #166 = InterfaceMethodref #167.#168     // java/util/Set.stream:()Ljava/util/stream/Stream;
  #167 = Class              #169          // java/util/Set
  #168 = NameAndType        #170:#171     // stream:()Ljava/util/stream/Stream;
  #169 = Utf8               java/util/Set
  #170 = Utf8               stream
  #171 = Utf8               ()Ljava/util/stream/Stream;
  #172 = InvokeDynamic      #0:#173       // #0:test:(Ljava/lang/String;)Ljava/util/function/Predicate;
  #173 = NameAndType        #174:#175     // test:(Ljava/lang/String;)Ljava/util/function/Predicate;
  #174 = Utf8               test
  #175 = Utf8               (Ljava/lang/String;)Ljava/util/function/Predicate;
  #176 = InterfaceMethodref #177.#178     // java/util/stream/Stream.filter:(Ljava/util/function/Predicate;)Ljava/util/stream/Stream;
  #177 = Class              #179          // java/util/stream/Stream
  #178 = NameAndType        #180:#181     // filter:(Ljava/util/function/Predicate;)Ljava/util/stream/Stream;
  #179 = Utf8               java/util/stream/Stream
  #180 = Utf8               filter
  #181 = Utf8               (Ljava/util/function/Predicate;)Ljava/util/stream/Stream;
  #182 = InvokeDynamic      #1:#183       // #1:apply:()Ljava/util/function/Function;
  #183 = NameAndType        #184:#185     // apply:()Ljava/util/function/Function;
  #184 = Utf8               apply
  #185 = Utf8               ()Ljava/util/function/Function;
  #186 = InterfaceMethodref #177.#187     // java/util/stream/Stream.map:(Ljava/util/function/Function;)Ljava/util/stream/Stream;
  #187 = NameAndType        #188:#189     // map:(Ljava/util/function/Function;)Ljava/util/stream/Stream;
  #188 = Utf8               map
  #189 = Utf8               (Ljava/util/function/Function;)Ljava/util/stream/Stream;
  #190 = InterfaceMethodref #177.#191     // java/util/stream/Stream.findFirst:()Ljava/util/Optional;
  #191 = NameAndType        #192:#193     // findFirst:()Ljava/util/Optional;
  #192 = Utf8               findFirst
  #193 = Utf8               ()Ljava/util/Optional;
  #194 = Methodref          #195.#196     // java/util/Optional.orElse:(Ljava/lang/Object;)Ljava/lang/Object;
  #195 = Class              #197          // java/util/Optional
  #196 = NameAndType        #198:#121     // orElse:(Ljava/lang/Object;)Ljava/lang/Object;
  #197 = Utf8               java/util/Optional
  #198 = Utf8               orElse
  #199 = Methodref          #49.#200      // java/lang/Integer.intValue:()I
  #200 = NameAndType        #201:#105     // intValue:()I
  #201 = Utf8               intValue
  #202 = Methodref          #54.#203      // ext/mods/gameserver/data/sql/PlayerInfoTable$PlayerInfo.getAccessLevel:()I
  #203 = NameAndType        #124:#105     // getAccessLevel:()I
  #204 = InvokeDynamic      #2:#173       // #2:test:(Ljava/lang/String;)Ljava/util/function/Predicate;
  #205 = InterfaceMethodref #177.#206     // java/util/stream/Stream.count:()J
  #206 = NameAndType        #207:#208     // count:()J
  #207 = Utf8               count
  #208 = Utf8               ()J
  #209 = Fieldref           #210.#211     // ext/mods/gameserver/data/sql/PlayerInfoTable$SingletonHolder.INSTANCE:Lext/mods/gameserver/data/sql/PlayerInfoTable;
  #210 = Class              #212          // ext/mods/gameserver/data/sql/PlayerInfoTable$SingletonHolder
  #211 = NameAndType        #213:#214     // INSTANCE:Lext/mods/gameserver/data/sql/PlayerInfoTable;
  #212 = Utf8               ext/mods/gameserver/data/sql/PlayerInfoTable$SingletonHolder
  #213 = Utf8               INSTANCE
  #214 = Utf8               Lext/mods/gameserver/data/sql/PlayerInfoTable;
  #215 = InterfaceMethodref #216.#217     // java/util/Map$Entry.getValue:()Ljava/lang/Object;
  #216 = Class              #218          // java/util/Map$Entry
  #217 = NameAndType        #219:#220     // getValue:()Ljava/lang/Object;
  #218 = Utf8               java/util/Map$Entry
  #219 = Utf8               getValue
  #220 = Utf8               ()Ljava/lang/Object;
  #221 = Methodref          #54.#222      // ext/mods/gameserver/data/sql/PlayerInfoTable$PlayerInfo.getAccountName:()Ljava/lang/String;
  #222 = NameAndType        #223:#138     // getAccountName:()Ljava/lang/String;
  #223 = Utf8               getAccountName
  #224 = Methodref          #225.#136     // java/lang/Class.getName:()Ljava/lang/String;
  #225 = Class              #226          // java/lang/Class
  #226 = Utf8               java/lang/Class
  #227 = Methodref          #95.#228      // ext/mods/commons/logging/CLogger."<init>":(Ljava/lang/String;)V
  #228 = NameAndType        #5:#151       // "<init>":(Ljava/lang/String;)V
  #229 = Utf8               LOAD_DATA
  #230 = Utf8               Ljava/lang/String;
  #231 = Utf8               ConstantValue
  #232 = Utf8               Signature
  #233 = Utf8               Ljava/util/Map<Ljava/lang/Integer;Lext/mods/gameserver/data/sql/PlayerInfoTable$PlayerInfo;>;
  #234 = Utf8               Code
  #235 = Utf8               LineNumberTable
  #236 = Utf8               LocalVariableTable
  #237 = Utf8               rs
  #238 = Utf8               Ljava/sql/ResultSet;
  #239 = Utf8               ps
  #240 = Utf8               Ljava/sql/PreparedStatement;
  #241 = Utf8               con
  #242 = Utf8               Ljava/sql/Connection;
  #243 = Utf8               e
  #244 = Utf8               Ljava/lang/Exception;
  #245 = Utf8               this
  #246 = Utf8               StackMapTable
  #247 = Utf8               addPlayer
  #248 = Utf8               (ILjava/lang/String;Ljava/lang/String;I)V
  #249 = Utf8               objectId
  #250 = Utf8               I
  #251 = Utf8               accountName
  #252 = Utf8               playerName
  #253 = Utf8               accessLevel
  #254 = Utf8               updatePlayerData
  #255 = Utf8               (Lext/mods/gameserver/model/actor/Player;Z)V
  #256 = Utf8               player
  #257 = Utf8               Lext/mods/gameserver/model/actor/Player;
  #258 = Utf8               onlyAccessLevel
  #259 = Utf8               Z
  #260 = Utf8               data
  #261 = Utf8               Lext/mods/gameserver/data/sql/PlayerInfoTable$PlayerInfo;
  #262 = Utf8               removePlayer
  #263 = Utf8               objId
  #264 = Utf8               getPlayerObjectId
  #265 = Utf8               (I)Ljava/lang/String;
  #266 = Utf8               getPlayerAccessLevel
  #267 = Utf8               (I)I
  #268 = Utf8               getCharactersInAcc
  #269 = Utf8               getInstance
  #270 = Utf8               ()Lext/mods/gameserver/data/sql/PlayerInfoTable;
  #271 = Utf8               lambda$getCharactersInAcc$0
  #272 = Utf8               (Ljava/lang/String;Ljava/util/Map$Entry;)Z
  #273 = Utf8               m
  #274 = Utf8               Ljava/util/Map$Entry;
  #275 = Utf8               lambda$getPlayerObjectId$0
  #276 = Utf8               <clinit>
  #277 = Utf8               SourceFile
  #278 = Utf8               PlayerInfoTable.java
  #279 = Utf8               NestMembers
  #280 = Utf8               BootstrapMethods
  #281 = MethodType         #155          //  (Ljava/lang/Object;)Z
  #282 = MethodHandle       6:#283        // REF_invokeStatic ext/mods/gameserver/data/sql/PlayerInfoTable.lambda$getPlayerObjectId$0:(Ljava/lang/String;Ljava/util/Map$Entry;)Z
  #283 = Methodref          #11.#284      // ext/mods/gameserver/data/sql/PlayerInfoTable.lambda$getPlayerObjectId$0:(Ljava/lang/String;Ljava/util/Map$Entry;)Z
  #284 = NameAndType        #275:#272     // lambda$getPlayerObjectId$0:(Ljava/lang/String;Ljava/util/Map$Entry;)Z
  #285 = MethodType         #286          //  (Ljava/util/Map$Entry;)Z
  #286 = Utf8               (Ljava/util/Map$Entry;)Z
  #287 = MethodType         #121          //  (Ljava/lang/Object;)Ljava/lang/Object;
  #288 = MethodHandle       9:#289        // REF_invokeInterface java/util/Map$Entry.getKey:()Ljava/lang/Object;
  #289 = InterfaceMethodref #216.#290     // java/util/Map$Entry.getKey:()Ljava/lang/Object;
  #290 = NameAndType        #291:#220     // getKey:()Ljava/lang/Object;
  #291 = Utf8               getKey
  #292 = MethodType         #293          //  (Ljava/util/Map$Entry;)Ljava/lang/Integer;
  #293 = Utf8               (Ljava/util/Map$Entry;)Ljava/lang/Integer;
  #294 = MethodHandle       6:#295        // REF_invokeStatic ext/mods/gameserver/data/sql/PlayerInfoTable.lambda$getCharactersInAcc$0:(Ljava/lang/String;Ljava/util/Map$Entry;)Z
  #295 = Methodref          #11.#296      // ext/mods/gameserver/data/sql/PlayerInfoTable.lambda$getCharactersInAcc$0:(Ljava/lang/String;Ljava/util/Map$Entry;)Z
  #296 = NameAndType        #271:#272     // lambda$getCharactersInAcc$0:(Ljava/lang/String;Ljava/util/Map$Entry;)Z
  #297 = MethodHandle       6:#298        // REF_invokeStatic java/lang/invoke/LambdaMetafactory.metafactory:(Ljava/lang/invoke/MethodHandles$Lookup;Ljava/lang/String;Ljava/lang/invoke/MethodType;Ljava/lang/invoke/MethodType;Ljava/lang/invoke/MethodHandle;Ljava/lang/invoke/MethodType;)Ljava/lang/invoke/CallSite;
  #298 = Methodref          #299.#300     // java/lang/invoke/LambdaMetafactory.metafactory:(Ljava/lang/invoke/MethodHandles$Lookup;Ljava/lang/String;Ljava/lang/invoke/MethodType;Ljava/lang/invoke/MethodType;Ljava/lang/invoke/MethodHandle;Ljava/lang/invoke/MethodType;)Ljava/lang/invoke/CallSite;
  #299 = Class              #301          // java/lang/invoke/LambdaMetafactory
  #300 = NameAndType        #302:#303     // metafactory:(Ljava/lang/invoke/MethodHandles$Lookup;Ljava/lang/String;Ljava/lang/invoke/MethodType;Ljava/lang/invoke/MethodType;Ljava/lang/invoke/MethodHandle;Ljava/lang/invoke/MethodType;)Ljava/lang/invoke/CallSite;
  #301 = Utf8               java/lang/invoke/LambdaMetafactory
  #302 = Utf8               metafactory
  #303 = Utf8               (Ljava/lang/invoke/MethodHandles$Lookup;Ljava/lang/String;Ljava/lang/invoke/MethodType;Ljava/lang/invoke/MethodType;Ljava/lang/invoke/MethodHandle;Ljava/lang/invoke/MethodType;)Ljava/lang/invoke/CallSite;
  #304 = Utf8               InnerClasses
  #305 = Utf8               PlayerInfo
  #306 = Utf8               SingletonHolder
  #307 = Utf8               Entry
  #308 = Class              #309          // java/lang/invoke/MethodHandles$Lookup
  #309 = Utf8               java/lang/invoke/MethodHandles$Lookup
  #310 = Class              #311          // java/lang/invoke/MethodHandles
  #311 = Utf8               java/lang/invoke/MethodHandles
  #312 = Utf8               Lookup
{
  protected ext.mods.gameserver.data.sql.PlayerInfoTable();
    descriptor: ()V
    flags: (0x0004) ACC_PROTECTED
    Code:
      stack=9, locals=6, args_size=1
         0: aload_0
         1: invokespecial #1                  // Method java/lang/Object."<init>":()V
         4: aload_0
         5: new           #7                  // class java/util/concurrent/ConcurrentHashMap
         8: dup
         9: invokespecial #9                  // Method java/util/concurrent/ConcurrentHashMap."<init>":()V
        12: putfield      #10                 // Field _infos:Ljava/util/Map;
        15: invokestatic  #16                 // Method ext/mods/commons/pool/ConnectionPool.getConnection:()Ljava/sql/Connection;
        18: astore_1
        19: aload_1
        20: ldc           #22                 // String SELECT account_name, obj_Id, char_name, accesslevel FROM characters
        22: invokeinterface #24,  2           // InterfaceMethod java/sql/Connection.prepareStatement:(Ljava/lang/String;)Ljava/sql/PreparedStatement;
        27: astore_2
        28: aload_2
        29: invokeinterface #30,  1           // InterfaceMethod java/sql/PreparedStatement.executeQuery:()Ljava/sql/ResultSet;
        34: astore_3
        35: aload_3
        36: invokeinterface #36,  1           // InterfaceMethod java/sql/ResultSet.next:()Z
        41: ifeq          100
        44: aload_0
        45: getfield      #10                 // Field _infos:Ljava/util/Map;
        48: aload_3
        49: ldc           #42                 // String obj_Id
        51: invokeinterface #44,  2           // InterfaceMethod java/sql/ResultSet.getInt:(Ljava/lang/String;)I
        56: invokestatic  #48                 // Method java/lang/Integer.valueOf:(I)Ljava/lang/Integer;
        59: new           #54                 // class ext/mods/gameserver/data/sql/PlayerInfoTable$PlayerInfo
        62: dup
        63: aload_0
        64: aload_3
        65: ldc           #56                 // String account_name
        67: invokeinterface #58,  2           // InterfaceMethod java/sql/ResultSet.getString:(Ljava/lang/String;)Ljava/lang/String;
        72: aload_3
        73: ldc           #62                 // String char_name
        75: invokeinterface #58,  2           // InterfaceMethod java/sql/ResultSet.getString:(Ljava/lang/String;)Ljava/lang/String;
        80: aload_3
        81: ldc           #64                 // String accesslevel
        83: invokeinterface #44,  2           // InterfaceMethod java/sql/ResultSet.getInt:(Ljava/lang/String;)I
        88: invokespecial #66                 // Method ext/mods/gameserver/data/sql/PlayerInfoTable$PlayerInfo."<init>":(Lext/mods/gameserver/data/sql/PlayerInfoTable;Ljava/lang/String;Ljava/lang/String;I)V
        91: invokeinterface #69,  3           // InterfaceMethod java/util/Map.put:(Ljava/lang/Object;Ljava/lang/Object;)Ljava/lang/Object;
        96: pop
        97: goto          35
       100: aload_3
       101: ifnull        140
       104: aload_3
       105: invokeinterface #75,  1           // InterfaceMethod java/sql/ResultSet.close:()V
       110: goto          140
       113: astore        4
       115: aload_3
       116: ifnull        137
       119: aload_3
       120: invokeinterface #75,  1           // InterfaceMethod java/sql/ResultSet.close:()V
       125: goto          137
       128: astore        5
       130: aload         4
       132: aload         5
       134: invokevirtual #80                 // Method java/lang/Throwable.addSuppressed:(Ljava/lang/Throwable;)V
       137: aload         4
       139: athrow
       140: aload_2
       141: ifnull        177
       144: aload_2
       145: invokeinterface #84,  1           // InterfaceMethod java/sql/PreparedStatement.close:()V
       150: goto          177
       153: astore_3
       154: aload_2
       155: ifnull        175
       158: aload_2
       159: invokeinterface #84,  1           // InterfaceMethod java/sql/PreparedStatement.close:()V
       164: goto          175
       167: astore        4
       169: aload_3
       170: aload         4
       172: invokevirtual #80                 // Method java/lang/Throwable.addSuppressed:(Ljava/lang/Throwable;)V
       175: aload_3
       176: athrow
       177: aload_1
       178: ifnull        212
       181: aload_1
       182: invokeinterface #85,  1           // InterfaceMethod java/sql/Connection.close:()V
       187: goto          212
       190: astore_2
       191: aload_1
       192: ifnull        210
       195: aload_1
       196: invokeinterface #85,  1           // InterfaceMethod java/sql/Connection.close:()V
       201: goto          210
       204: astore_3
       205: aload_2
       206: aload_3
       207: invokevirtual #80                 // Method java/lang/Throwable.addSuppressed:(Ljava/lang/Throwable;)V
       210: aload_2
       211: athrow
       212: goto          225
       215: astore_1
       216: getstatic     #88                 // Field LOGGER:Lext/mods/commons/logging/CLogger;
       219: ldc           #92                 // String Couldn\'t load player infos.
       221: aload_1
       222: invokevirtual #94                 // Method ext/mods/commons/logging/CLogger.error:(Ljava/lang/Object;Ljava/lang/Throwable;)V
       225: getstatic     #88                 // Field LOGGER:Lext/mods/commons/logging/CLogger;
       228: ldc           #100                // String Loaded {} player infos.
       230: iconst_1
       231: anewarray     #2                  // class java/lang/Object
       234: dup
       235: iconst_0
       236: aload_0
       237: getfield      #10                 // Field _infos:Ljava/util/Map;
       240: invokeinterface #102,  1          // InterfaceMethod java/util/Map.size:()I
       245: invokestatic  #48                 // Method java/lang/Integer.valueOf:(I)Ljava/lang/Integer;
       248: aastore
       249: invokevirtual #106                // Method ext/mods/commons/logging/CLogger.info:(Ljava/lang/Object;[Ljava/lang/Object;)V
       252: return
      Exception table:
         from    to  target type
            35   100   113   Class java/lang/Throwable
           119   125   128   Class java/lang/Throwable
            28   140   153   Class java/lang/Throwable
           158   164   167   Class java/lang/Throwable
            19   177   190   Class java/lang/Throwable
           195   201   204   Class java/lang/Throwable
            15   212   215   Class java/lang/Exception
      LineNumberTable:
        line 47: 0
        line 44: 4
        line 48: 15
        line 49: 19
        line 50: 28
        line 52: 35
        line 53: 44
        line 54: 100
        line 48: 113
        line 54: 140
        line 48: 153
        line 54: 177
        line 48: 190
        line 58: 212
        line 55: 215
        line 57: 216
        line 60: 225
        line 61: 252
      LocalVariableTable:
        Start  Length  Slot  Name   Signature
           35     105     3    rs   Ljava/sql/ResultSet;
           28     149     2    ps   Ljava/sql/PreparedStatement;
           19     193     1   con   Ljava/sql/Connection;
          216       9     1     e   Ljava/lang/Exception;
            0     253     0  this   Lext/mods/gameserver/data/sql/PlayerInfoTable;
      StackMapTable: number_of_entries = 16
        frame_type = 255 /* full_frame */
          offset_delta = 35
          locals = [ class ext/mods/gameserver/data/sql/PlayerInfoTable, class java/sql/Connection, class java/sql/PreparedStatement, class java/sql/ResultSet ]
          stack = []
        frame_type = 251 /* same_frame_extended */
          offset_delta = 64
        frame_type = 76 /* same_locals_1_stack_item */
          stack = [ class java/lang/Throwable ]
        frame_type = 255 /* full_frame */
          offset_delta = 14
          locals = [ class ext/mods/gameserver/data/sql/PlayerInfoTable, class java/sql/Connection, class java/sql/PreparedStatement, class java/sql/ResultSet, class java/lang/Throwable ]
          stack = [ class java/lang/Throwable ]
        frame_type = 8 /* same */
        frame_type = 249 /* chop */
          offset_delta = 2
        frame_type = 76 /* same_locals_1_stack_item */
          stack = [ class java/lang/Throwable ]
        frame_type = 255 /* full_frame */
          offset_delta = 13
          locals = [ class ext/mods/gameserver/data/sql/PlayerInfoTable, class java/sql/Connection, class java/sql/PreparedStatement, class java/lang/Throwable ]
          stack = [ class java/lang/Throwable ]
        frame_type = 7 /* same */
        frame_type = 249 /* chop */
          offset_delta = 1
        frame_type = 76 /* same_locals_1_stack_item */
          stack = [ class java/lang/Throwable ]
        frame_type = 255 /* full_frame */
          offset_delta = 13
          locals = [ class ext/mods/gameserver/data/sql/PlayerInfoTable, class java/sql/Connection, class java/lang/Throwable ]
          stack = [ class java/lang/Throwable ]
        frame_type = 5 /* same */
        frame_type = 249 /* chop */
          offset_delta = 1
        frame_type = 66 /* same_locals_1_stack_item */
          stack = [ class java/lang/Exception ]
        frame_type = 9 /* same */

  public final void addPlayer(int, java.lang.String, java.lang.String, int);
    descriptor: (ILjava/lang/String;Ljava/lang/String;I)V
    flags: (0x0011) ACC_PUBLIC, ACC_FINAL
    Code:
      stack=8, locals=5, args_size=5
         0: aload_0
         1: getfield      #10                 // Field _infos:Ljava/util/Map;
         4: iload_1
         5: invokestatic  #48                 // Method java/lang/Integer.valueOf:(I)Ljava/lang/Integer;
         8: new           #54                 // class ext/mods/gameserver/data/sql/PlayerInfoTable$PlayerInfo
        11: dup
        12: aload_0
        13: aload_2
        14: aload_3
        15: iload         4
        17: invokespecial #66                 // Method ext/mods/gameserver/data/sql/PlayerInfoTable$PlayerInfo."<init>":(Lext/mods/gameserver/data/sql/PlayerInfoTable;Ljava/lang/String;Ljava/lang/String;I)V
        20: invokeinterface #110,  3          // InterfaceMethod java/util/Map.putIfAbsent:(Ljava/lang/Object;Ljava/lang/Object;)Ljava/lang/Object;
        25: pop
        26: return
      LineNumberTable:
        line 72: 0
        line 73: 26
      LocalVariableTable:
        Start  Length  Slot  Name   Signature
            0      27     0  this   Lext/mods/gameserver/data/sql/PlayerInfoTable;
            0      27     1 objectId   I
            0      27     2 accountName   Ljava/lang/String;
            0      27     3 playerName   Ljava/lang/String;
            0      27     4 accessLevel   I

  public final void updatePlayerData(ext.mods.gameserver.model.actor.Player, boolean);
    descriptor: (Lext/mods/gameserver/model/actor/Player;Z)V
    flags: (0x0011) ACC_PUBLIC, ACC_FINAL
    Code:
      stack=2, locals=5, args_size=3
         0: aload_1
         1: ifnonnull     5
         4: return
         5: aload_0
         6: getfield      #10                 // Field _infos:Ljava/util/Map;
         9: aload_1
        10: invokevirtual #113                // Method ext/mods/gameserver/model/actor/Player.getObjectId:()I
        13: invokestatic  #48                 // Method java/lang/Integer.valueOf:(I)Ljava/lang/Integer;
        16: invokeinterface #118,  2          // InterfaceMethod java/util/Map.get:(Ljava/lang/Object;)Ljava/lang/Object;
        21: checkcast     #54                 // class ext/mods/gameserver/data/sql/PlayerInfoTable$PlayerInfo
        24: astore_3
        25: aload_3
        26: ifnull        71
        29: iload_2
        30: ifeq          47
        33: aload_3
        34: aload_1
        35: invokevirtual #122                // Method ext/mods/gameserver/model/actor/Player.getAccessLevel:()Lext/mods/gameserver/model/AccessLevel;
        38: invokevirtual #126                // Method ext/mods/gameserver/model/AccessLevel.getLevel:()I
        41: invokevirtual #131                // Method ext/mods/gameserver/data/sql/PlayerInfoTable$PlayerInfo.setAccessLevel:(I)V
        44: goto          71
        47: aload_1
        48: invokevirtual #135                // Method ext/mods/gameserver/model/actor/Player.getName:()Ljava/lang/String;
        51: astore        4
        53: aload_3
        54: invokevirtual #139                // Method ext/mods/gameserver/data/sql/PlayerInfoTable$PlayerInfo.getPlayerName:()Ljava/lang/String;
        57: aload         4
        59: invokevirtual #142                // Method java/lang/String.equalsIgnoreCase:(Ljava/lang/String;)Z
        62: ifne          71
        65: aload_3
        66: aload         4
        68: invokevirtual #148                // Method ext/mods/gameserver/data/sql/PlayerInfoTable$PlayerInfo.setPlayerName:(Ljava/lang/String;)V
        71: return
      LineNumberTable:
        line 82: 0
        line 83: 4
        line 85: 5
        line 86: 25
        line 88: 29
        line 89: 33
        line 92: 47
        line 93: 53
        line 94: 65
        line 97: 71
      LocalVariableTable:
        Start  Length  Slot  Name   Signature
           53      18     4 playerName   Ljava/lang/String;
            0      72     0  this   Lext/mods/gameserver/data/sql/PlayerInfoTable;
            0      72     1 player   Lext/mods/gameserver/model/actor/Player;
            0      72     2 onlyAccessLevel   Z
           25      47     3  data   Lext/mods/gameserver/data/sql/PlayerInfoTable$PlayerInfo;
      StackMapTable: number_of_entries = 3
        frame_type = 5 /* same */
        frame_type = 252 /* append */
          offset_delta = 41
          locals = [ class ext/mods/gameserver/data/sql/PlayerInfoTable$PlayerInfo ]
        frame_type = 23 /* same */

  public final void removePlayer(int);
    descriptor: (I)V
    flags: (0x0011) ACC_PUBLIC, ACC_FINAL
    Code:
      stack=2, locals=2, args_size=2
         0: aload_0
         1: getfield      #10                 // Field _infos:Ljava/util/Map;
         4: iload_1
         5: invokestatic  #48                 // Method java/lang/Integer.valueOf:(I)Ljava/lang/Integer;
         8: invokeinterface #152,  2          // InterfaceMethod java/util/Map.containsKey:(Ljava/lang/Object;)Z
        13: ifeq          30
        16: aload_0
        17: getfield      #10                 // Field _infos:Ljava/util/Map;
        20: iload_1
        21: invokestatic  #48                 // Method java/lang/Integer.valueOf:(I)Ljava/lang/Integer;
        24: invokeinterface #156,  2          // InterfaceMethod java/util/Map.remove:(Ljava/lang/Object;)Ljava/lang/Object;
        29: pop
        30: return
      LineNumberTable:
        line 105: 0
        line 106: 16
        line 107: 30
      LocalVariableTable:
        Start  Length  Slot  Name   Signature
            0      31     0  this   Lext/mods/gameserver/data/sql/PlayerInfoTable;
            0      31     1 objId   I
      StackMapTable: number_of_entries = 1
        frame_type = 30 /* same */

  public final int getPlayerObjectId(java.lang.String);
    descriptor: (Ljava/lang/String;)I
    flags: (0x0011) ACC_PUBLIC, ACC_FINAL
    Code:
      stack=2, locals=2, args_size=2
         0: aload_1
         1: ifnull        11
         4: aload_1
         5: invokevirtual #159                // Method java/lang/String.isEmpty:()Z
         8: ifeq          13
        11: iconst_m1
        12: ireturn
        13: aload_0
        14: getfield      #10                 // Field _infos:Ljava/util/Map;
        17: invokeinterface #162,  1          // InterfaceMethod java/util/Map.entrySet:()Ljava/util/Set;
        22: invokeinterface #166,  1          // InterfaceMethod java/util/Set.stream:()Ljava/util/stream/Stream;
        27: aload_1
        28: invokedynamic #172,  0            // InvokeDynamic #0:test:(Ljava/lang/String;)Ljava/util/function/Predicate;
        33: invokeinterface #176,  2          // InterfaceMethod java/util/stream/Stream.filter:(Ljava/util/function/Predicate;)Ljava/util/stream/Stream;
        38: invokedynamic #182,  0            // InvokeDynamic #1:apply:()Ljava/util/function/Function;
        43: invokeinterface #186,  2          // InterfaceMethod java/util/stream/Stream.map:(Ljava/util/function/Function;)Ljava/util/stream/Stream;
        48: invokeinterface #190,  1          // InterfaceMethod java/util/stream/Stream.findFirst:()Ljava/util/Optional;
        53: iconst_m1
        54: invokestatic  #48                 // Method java/lang/Integer.valueOf:(I)Ljava/lang/Integer;
        57: invokevirtual #194                // Method java/util/Optional.orElse:(Ljava/lang/Object;)Ljava/lang/Object;
        60: checkcast     #49                 // class java/lang/Integer
        63: invokevirtual #199                // Method java/lang/Integer.intValue:()I
        66: ireturn
      LineNumberTable:
        line 116: 0
        line 117: 11
        line 119: 13
      LocalVariableTable:
        Start  Length  Slot  Name   Signature
            0      67     0  this   Lext/mods/gameserver/data/sql/PlayerInfoTable;
            0      67     1 playerName   Ljava/lang/String;
      StackMapTable: number_of_entries = 2
        frame_type = 11 /* same */
        frame_type = 1 /* same */

  public final java.lang.String getPlayerName(int);
    descriptor: (I)Ljava/lang/String;
    flags: (0x0011) ACC_PUBLIC, ACC_FINAL
    Code:
      stack=2, locals=3, args_size=2
         0: aload_0
         1: getfield      #10                 // Field _infos:Ljava/util/Map;
         4: iload_1
         5: invokestatic  #48                 // Method java/lang/Integer.valueOf:(I)Ljava/lang/Integer;
         8: invokeinterface #118,  2          // InterfaceMethod java/util/Map.get:(Ljava/lang/Object;)Ljava/lang/Object;
        13: checkcast     #54                 // class ext/mods/gameserver/data/sql/PlayerInfoTable$PlayerInfo
        16: astore_2
        17: aload_2
        18: ifnull        28
        21: aload_2
        22: invokevirtual #139                // Method ext/mods/gameserver/data/sql/PlayerInfoTable$PlayerInfo.getPlayerName:()Ljava/lang/String;
        25: goto          29
        28: aconst_null
        29: areturn
      LineNumberTable:
        line 129: 0
        line 130: 17
      LocalVariableTable:
        Start  Length  Slot  Name   Signature
            0      30     0  this   Lext/mods/gameserver/data/sql/PlayerInfoTable;
            0      30     1 objId   I
           17      13     2  data   Lext/mods/gameserver/data/sql/PlayerInfoTable$PlayerInfo;
      StackMapTable: number_of_entries = 2
        frame_type = 252 /* append */
          offset_delta = 28
          locals = [ class ext/mods/gameserver/data/sql/PlayerInfoTable$PlayerInfo ]
        frame_type = 64 /* same_locals_1_stack_item */
          stack = [ class java/lang/String ]

  public final int getPlayerAccessLevel(int);
    descriptor: (I)I
    flags: (0x0011) ACC_PUBLIC, ACC_FINAL
    Code:
      stack=2, locals=3, args_size=2
         0: aload_0
         1: getfield      #10                 // Field _infos:Ljava/util/Map;
         4: iload_1
         5: invokestatic  #48                 // Method java/lang/Integer.valueOf:(I)Ljava/lang/Integer;
         8: invokeinterface #118,  2          // InterfaceMethod java/util/Map.get:(Ljava/lang/Object;)Ljava/lang/Object;
        13: checkcast     #54                 // class ext/mods/gameserver/data/sql/PlayerInfoTable$PlayerInfo
        16: astore_2
        17: aload_2
        18: ifnull        28
        21: aload_2
        22: invokevirtual #202                // Method ext/mods/gameserver/data/sql/PlayerInfoTable$PlayerInfo.getAccessLevel:()I
        25: goto          29
        28: iconst_0
        29: ireturn
      LineNumberTable:
        line 140: 0
        line 141: 17
      LocalVariableTable:
        Start  Length  Slot  Name   Signature
            0      30     0  this   Lext/mods/gameserver/data/sql/PlayerInfoTable;
            0      30     1 objId   I
           17      13     2  data   Lext/mods/gameserver/data/sql/PlayerInfoTable$PlayerInfo;
      StackMapTable: number_of_entries = 2
        frame_type = 252 /* append */
          offset_delta = 28
          locals = [ class ext/mods/gameserver/data/sql/PlayerInfoTable$PlayerInfo ]
        frame_type = 64 /* same_locals_1_stack_item */
          stack = [ int ]

  public final int getCharactersInAcc(java.lang.String);
    descriptor: (Ljava/lang/String;)I
    flags: (0x0011) ACC_PUBLIC, ACC_FINAL
    Code:
      stack=2, locals=2, args_size=2
         0: aload_0
         1: getfield      #10                 // Field _infos:Ljava/util/Map;
         4: invokeinterface #162,  1          // InterfaceMethod java/util/Map.entrySet:()Ljava/util/Set;
         9: invokeinterface #166,  1          // InterfaceMethod java/util/Set.stream:()Ljava/util/stream/Stream;
        14: aload_1
        15: invokedynamic #204,  0            // InvokeDynamic #2:test:(Ljava/lang/String;)Ljava/util/function/Predicate;
        20: invokeinterface #176,  2          // InterfaceMethod java/util/stream/Stream.filter:(Ljava/util/function/Predicate;)Ljava/util/stream/Stream;
        25: invokeinterface #205,  1          // InterfaceMethod java/util/stream/Stream.count:()J
        30: l2i
        31: ireturn
      LineNumberTable:
        line 151: 0
      LocalVariableTable:
        Start  Length  Slot  Name   Signature
            0      32     0  this   Lext/mods/gameserver/data/sql/PlayerInfoTable;
            0      32     1 accountName   Ljava/lang/String;

  public static final ext.mods.gameserver.data.sql.PlayerInfoTable getInstance();
    descriptor: ()Lext/mods/gameserver/data/sql/PlayerInfoTable;
    flags: (0x0019) ACC_PUBLIC, ACC_STATIC, ACC_FINAL
    Code:
      stack=1, locals=0, args_size=0
         0: getstatic     #209                // Field ext/mods/gameserver/data/sql/PlayerInfoTable$SingletonHolder.INSTANCE:Lext/mods/gameserver/data/sql/PlayerInfoTable;
         3: areturn
      LineNumberTable:
        line 198: 0

  static {};
    descriptor: ()V
    flags: (0x0008) ACC_STATIC
    Code:
      stack=3, locals=0, args_size=0
         0: new           #95                 // class ext/mods/commons/logging/CLogger
         3: dup
         4: ldc           #11                 // class ext/mods/gameserver/data/sql/PlayerInfoTable
         6: invokevirtual #224                // Method java/lang/Class.getName:()Ljava/lang/String;
         9: invokespecial #227                // Method ext/mods/commons/logging/CLogger."<init>":(Ljava/lang/String;)V
        12: putstatic     #88                 // Field LOGGER:Lext/mods/commons/logging/CLogger;
        15: return
      LineNumberTable:
        line 40: 0
}
SourceFile: "PlayerInfoTable.java"
NestMembers:
  ext/mods/gameserver/data/sql/PlayerInfoTable$SingletonHolder
  ext/mods/gameserver/data/sql/PlayerInfoTable$PlayerInfo
BootstrapMethods:
  0: #297 REF_invokeStatic java/lang/invoke/LambdaMetafactory.metafactory:(Ljava/lang/invoke/MethodHandles$Lookup;Ljava/lang/String;Ljava/lang/invoke/MethodType;Ljava/lang/invoke/MethodType;Ljava/lang/invoke/MethodHandle;Ljava/lang/invoke/MethodType;)Ljava/lang/invoke/CallSite;
    Method arguments:
      #281 (Ljava/lang/Object;)Z
      #282 REF_invokeStatic ext/mods/gameserver/data/sql/PlayerInfoTable.lambda$getPlayerObjectId$0:(Ljava/lang/String;Ljava/util/Map$Entry;)Z
      #285 (Ljava/util/Map$Entry;)Z
  1: #297 REF_invokeStatic java/lang/invoke/LambdaMetafactory.metafactory:(Ljava/lang/invoke/MethodHandles$Lookup;Ljava/lang/String;Ljava/lang/invoke/MethodType;Ljava/lang/invoke/MethodType;Ljava/lang/invoke/MethodHandle;Ljava/lang/invoke/MethodType;)Ljava/lang/invoke/CallSite;
    Method arguments:
      #287 (Ljava/lang/Object;)Ljava/lang/Object;
      #288 REF_invokeInterface java/util/Map$Entry.getKey:()Ljava/lang/Object;
      #292 (Ljava/util/Map$Entry;)Ljava/lang/Integer;
  2: #297 REF_invokeStatic java/lang/invoke/LambdaMetafactory.metafactory:(Ljava/lang/invoke/MethodHandles$Lookup;Ljava/lang/String;Ljava/lang/invoke/MethodType;Ljava/lang/invoke/MethodType;Ljava/lang/invoke/MethodHandle;Ljava/lang/invoke/MethodType;)Ljava/lang/invoke/CallSite;
    Method arguments:
      #281 (Ljava/lang/Object;)Z
      #294 REF_invokeStatic ext/mods/gameserver/data/sql/PlayerInfoTable.lambda$getCharactersInAcc$0:(Ljava/lang/String;Ljava/util/Map$Entry;)Z
      #285 (Ljava/util/Map$Entry;)Z
InnerClasses:
  public static #307= #216 of #70;        // Entry=class java/util/Map$Entry of class java/util/Map
  public static final #312= #308 of #310; // Lookup=class java/lang/invoke/MethodHandles$Lookup of class java/lang/invoke/MethodHandles
