// Bytecode for: ext.mods.gameserver.enums.items.ItemLocation
// File: ext\mods\gameserver\enums\items\ItemLocation.class

Classfile /c:/Users/User/Desktop/BrProject/bin/main/ext/mods/gameserver/enums/items/ItemLocation.class
  Last modified 9 de jul de 2026; size 1521 bytes
  MD5 checksum 35b5df8d1fe42b84602c695f9619afe9
  Compiled from "ItemLocation.java"
public final class ext.mods.gameserver.enums.items.ItemLocation extends java.lang.Enum<ext.mods.gameserver.enums.items.ItemLocation>
  minor version: 0
  major version: 69
  flags: (0x4031) ACC_PUBLIC, ACC_FINAL, ACC_SUPER, ACC_ENUM
  this_class: #1                          // ext/mods/gameserver/enums/items/ItemLocation
  super_class: #38                        // java/lang/Enum
  interfaces: 0, fields: 9, methods: 5, attributes: 2
Constant pool:
   #1 = Class              #2             // ext/mods/gameserver/enums/items/ItemLocation
   #2 = Utf8               ext/mods/gameserver/enums/items/ItemLocation
   #3 = Fieldref           #1.#4          // ext/mods/gameserver/enums/items/ItemLocation.VOID:Lext/mods/gameserver/enums/items/ItemLocation;
   #4 = NameAndType        #5:#6          // VOID:Lext/mods/gameserver/enums/items/ItemLocation;
   #5 = Utf8               VOID
   #6 = Utf8               Lext/mods/gameserver/enums/items/ItemLocation;
   #7 = Fieldref           #1.#8          // ext/mods/gameserver/enums/items/ItemLocation.INVENTORY:Lext/mods/gameserver/enums/items/ItemLocation;
   #8 = NameAndType        #9:#6          // INVENTORY:Lext/mods/gameserver/enums/items/ItemLocation;
   #9 = Utf8               INVENTORY
  #10 = Fieldref           #1.#11         // ext/mods/gameserver/enums/items/ItemLocation.PAPERDOLL:Lext/mods/gameserver/enums/items/ItemLocation;
  #11 = NameAndType        #12:#6         // PAPERDOLL:Lext/mods/gameserver/enums/items/ItemLocation;
  #12 = Utf8               PAPERDOLL
  #13 = Fieldref           #1.#14         // ext/mods/gameserver/enums/items/ItemLocation.WAREHOUSE:Lext/mods/gameserver/enums/items/ItemLocation;
  #14 = NameAndType        #15:#6         // WAREHOUSE:Lext/mods/gameserver/enums/items/ItemLocation;
  #15 = Utf8               WAREHOUSE
  #16 = Fieldref           #1.#17         // ext/mods/gameserver/enums/items/ItemLocation.CLANWH:Lext/mods/gameserver/enums/items/ItemLocation;
  #17 = NameAndType        #18:#6         // CLANWH:Lext/mods/gameserver/enums/items/ItemLocation;
  #18 = Utf8               CLANWH
  #19 = Fieldref           #1.#20         // ext/mods/gameserver/enums/items/ItemLocation.PET:Lext/mods/gameserver/enums/items/ItemLocation;
  #20 = NameAndType        #21:#6         // PET:Lext/mods/gameserver/enums/items/ItemLocation;
  #21 = Utf8               PET
  #22 = Fieldref           #1.#23         // ext/mods/gameserver/enums/items/ItemLocation.PET_EQUIP:Lext/mods/gameserver/enums/items/ItemLocation;
  #23 = NameAndType        #24:#6         // PET_EQUIP:Lext/mods/gameserver/enums/items/ItemLocation;
  #24 = Utf8               PET_EQUIP
  #25 = Fieldref           #1.#26         // ext/mods/gameserver/enums/items/ItemLocation.FREIGHT:Lext/mods/gameserver/enums/items/ItemLocation;
  #26 = NameAndType        #27:#6         // FREIGHT:Lext/mods/gameserver/enums/items/ItemLocation;
  #27 = Utf8               FREIGHT
  #28 = Fieldref           #1.#29         // ext/mods/gameserver/enums/items/ItemLocation.$VALUES:[Lext/mods/gameserver/enums/items/ItemLocation;
  #29 = NameAndType        #30:#31        // $VALUES:[Lext/mods/gameserver/enums/items/ItemLocation;
  #30 = Utf8               $VALUES
  #31 = Utf8               [Lext/mods/gameserver/enums/items/ItemLocation;
  #32 = Methodref          #33.#34        // "[Lext/mods/gameserver/enums/items/ItemLocation;".clone:()Ljava/lang/Object;
  #33 = Class              #31            // "[Lext/mods/gameserver/enums/items/ItemLocation;"
  #34 = NameAndType        #35:#36        // clone:()Ljava/lang/Object;
  #35 = Utf8               clone
  #36 = Utf8               ()Ljava/lang/Object;
  #37 = Methodref          #38.#39        // java/lang/Enum.valueOf:(Ljava/lang/Class;Ljava/lang/String;)Ljava/lang/Enum;
  #38 = Class              #40            // java/lang/Enum
  #39 = NameAndType        #41:#42        // valueOf:(Ljava/lang/Class;Ljava/lang/String;)Ljava/lang/Enum;
  #40 = Utf8               java/lang/Enum
  #41 = Utf8               valueOf
  #42 = Utf8               (Ljava/lang/Class;Ljava/lang/String;)Ljava/lang/Enum;
  #43 = Methodref          #38.#44        // java/lang/Enum."<init>":(Ljava/lang/String;I)V
  #44 = NameAndType        #45:#46        // "<init>":(Ljava/lang/String;I)V
  #45 = Utf8               <init>
  #46 = Utf8               (Ljava/lang/String;I)V
  #47 = String             #5             // VOID
  #48 = Methodref          #1.#44         // ext/mods/gameserver/enums/items/ItemLocation."<init>":(Ljava/lang/String;I)V
  #49 = String             #9             // INVENTORY
  #50 = String             #12            // PAPERDOLL
  #51 = String             #15            // WAREHOUSE
  #52 = String             #18            // CLANWH
  #53 = String             #21            // PET
  #54 = String             #24            // PET_EQUIP
  #55 = String             #27            // FREIGHT
  #56 = Methodref          #1.#57         // ext/mods/gameserver/enums/items/ItemLocation.$values:()[Lext/mods/gameserver/enums/items/ItemLocation;
  #57 = NameAndType        #58:#59        // $values:()[Lext/mods/gameserver/enums/items/ItemLocation;
  #58 = Utf8               $values
  #59 = Utf8               ()[Lext/mods/gameserver/enums/items/ItemLocation;
  #60 = Utf8               values
  #61 = Utf8               Code
  #62 = Utf8               LineNumberTable
  #63 = Utf8               (Ljava/lang/String;)Lext/mods/gameserver/enums/items/ItemLocation;
  #64 = Utf8               LocalVariableTable
  #65 = Utf8               name
  #66 = Utf8               Ljava/lang/String;
  #67 = Utf8               MethodParameters
  #68 = Utf8               this
  #69 = Utf8               Signature
  #70 = Utf8               ()V
  #71 = Utf8               <clinit>
  #72 = Utf8               Ljava/lang/Enum<Lext/mods/gameserver/enums/items/ItemLocation;>;
  #73 = Utf8               SourceFile
  #74 = Utf8               ItemLocation.java
{
  public static final ext.mods.gameserver.enums.items.ItemLocation VOID;
    descriptor: Lext/mods/gameserver/enums/items/ItemLocation;
    flags: (0x4019) ACC_PUBLIC, ACC_STATIC, ACC_FINAL, ACC_ENUM

  public static final ext.mods.gameserver.enums.items.ItemLocation INVENTORY;
    descriptor: Lext/mods/gameserver/enums/items/ItemLocation;
    flags: (0x4019) ACC_PUBLIC, ACC_STATIC, ACC_FINAL, ACC_ENUM

  public static final ext.mods.gameserver.enums.items.ItemLocation PAPERDOLL;
    descriptor: Lext/mods/gameserver/enums/items/ItemLocation;
    flags: (0x4019) ACC_PUBLIC, ACC_STATIC, ACC_FINAL, ACC_ENUM

  public static final ext.mods.gameserver.enums.items.ItemLocation WAREHOUSE;
    descriptor: Lext/mods/gameserver/enums/items/ItemLocation;
    flags: (0x4019) ACC_PUBLIC, ACC_STATIC, ACC_FINAL, ACC_ENUM

  public static final ext.mods.gameserver.enums.items.ItemLocation CLANWH;
    descriptor: Lext/mods/gameserver/enums/items/ItemLocation;
    flags: (0x4019) ACC_PUBLIC, ACC_STATIC, ACC_FINAL, ACC_ENUM

  public static final ext.mods.gameserver.enums.items.ItemLocation PET;
    descriptor: Lext/mods/gameserver/enums/items/ItemLocation;
    flags: (0x4019) ACC_PUBLIC, ACC_STATIC, ACC_FINAL, ACC_ENUM

  public static final ext.mods.gameserver.enums.items.ItemLocation PET_EQUIP;
    descriptor: Lext/mods/gameserver/enums/items/ItemLocation;
    flags: (0x4019) ACC_PUBLIC, ACC_STATIC, ACC_FINAL, ACC_ENUM

  public static final ext.mods.gameserver.enums.items.ItemLocation FREIGHT;
    descriptor: Lext/mods/gameserver/enums/items/ItemLocation;
    flags: (0x4019) ACC_PUBLIC, ACC_STATIC, ACC_FINAL, ACC_ENUM

  public static ext.mods.gameserver.enums.items.ItemLocation[] values();
    descriptor: ()[Lext/mods/gameserver/enums/items/ItemLocation;
    flags: (0x0009) ACC_PUBLIC, ACC_STATIC
    Code:
      stack=1, locals=0, args_size=0
         0: getstatic     #28                 // Field $VALUES:[Lext/mods/gameserver/enums/items/ItemLocation;
         3: invokevirtual #32                 // Method "[Lext/mods/gameserver/enums/items/ItemLocation;".clone:()Ljava/lang/Object;
         6: checkcast     #33                 // class "[Lext/mods/gameserver/enums/items/ItemLocation;"
         9: areturn
      LineNumberTable:
        line 20: 0

  public static ext.mods.gameserver.enums.items.ItemLocation valueOf(java.lang.String);
    descriptor: (Ljava/lang/String;)Lext/mods/gameserver/enums/items/ItemLocation;
    flags: (0x0009) ACC_PUBLIC, ACC_STATIC
    Code:
      stack=2, locals=1, args_size=1
         0: ldc           #1                  // class ext/mods/gameserver/enums/items/ItemLocation
         2: aload_0
         3: invokestatic  #37                 // Method java/lang/Enum.valueOf:(Ljava/lang/Class;Ljava/lang/String;)Ljava/lang/Enum;
         6: checkcast     #1                  // class ext/mods/gameserver/enums/items/ItemLocation
         9: areturn
      LineNumberTable:
        line 20: 0
      LocalVariableTable:
        Start  Length  Slot  Name   Signature
            0      10     0  name   Ljava/lang/String;
    MethodParameters:
      Name                           Flags
      <no name>                      mandated

  static {};
    descriptor: ()V
    flags: (0x0008) ACC_STATIC
    Code:
      stack=4, locals=0, args_size=0
         0: new           #1                  // class ext/mods/gameserver/enums/items/ItemLocation
         3: dup
         4: ldc           #47                 // String VOID
         6: iconst_0
         7: invokespecial #48                 // Method "<init>":(Ljava/lang/String;I)V
        10: putstatic     #3                  // Field VOID:Lext/mods/gameserver/enums/items/ItemLocation;
        13: new           #1                  // class ext/mods/gameserver/enums/items/ItemLocation
        16: dup
        17: ldc           #49                 // String INVENTORY
        19: iconst_1
        20: invokespecial #48                 // Method "<init>":(Ljava/lang/String;I)V
        23: putstatic     #7                  // Field INVENTORY:Lext/mods/gameserver/enums/items/ItemLocation;
        26: new           #1                  // class ext/mods/gameserver/enums/items/ItemLocation
        29: dup
        30: ldc           #50                 // String PAPERDOLL
        32: iconst_2
        33: invokespecial #48                 // Method "<init>":(Ljava/lang/String;I)V
        36: putstatic     #10                 // Field PAPERDOLL:Lext/mods/gameserver/enums/items/ItemLocation;
        39: new           #1                  // class ext/mods/gameserver/enums/items/ItemLocation
        42: dup
        43: ldc           #51                 // String WAREHOUSE
        45: iconst_3
        46: invokespecial #48                 // Method "<init>":(Ljava/lang/String;I)V
        49: putstatic     #13                 // Field WAREHOUSE:Lext/mods/gameserver/enums/items/ItemLocation;
        52: new           #1                  // class ext/mods/gameserver/enums/items/ItemLocation
        55: dup
        56: ldc           #52                 // String CLANWH
        58: iconst_4
        59: invokespecial #48                 // Method "<init>":(Ljava/lang/String;I)V
        62: putstatic     #16                 // Field CLANWH:Lext/mods/gameserver/enums/items/ItemLocation;
        65: new           #1                  // class ext/mods/gameserver/enums/items/ItemLocation
        68: dup
        69: ldc           #53                 // String PET
        71: iconst_5
        72: invokespecial #48                 // Method "<init>":(Ljava/lang/String;I)V
        75: putstatic     #19                 // Field PET:Lext/mods/gameserver/enums/items/ItemLocation;
        78: new           #1                  // class ext/mods/gameserver/enums/items/ItemLocation
        81: dup
        82: ldc           #54                 // String PET_EQUIP
        84: bipush        6
        86: invokespecial #48                 // Method "<init>":(Ljava/lang/String;I)V
        89: putstatic     #22                 // Field PET_EQUIP:Lext/mods/gameserver/enums/items/ItemLocation;
        92: new           #1                  // class ext/mods/gameserver/enums/items/ItemLocation
        95: dup
        96: ldc           #55                 // String FREIGHT
        98: bipush        7
       100: invokespecial #48                 // Method "<init>":(Ljava/lang/String;I)V
       103: putstatic     #25                 // Field FREIGHT:Lext/mods/gameserver/enums/items/ItemLocation;
       106: invokestatic  #56                 // Method $values:()[Lext/mods/gameserver/enums/items/ItemLocation;
       109: putstatic     #28                 // Field $VALUES:[Lext/mods/gameserver/enums/items/ItemLocation;
       112: return
      LineNumberTable:
        line 22: 0
        line 23: 13
        line 24: 26
        line 25: 39
        line 26: 52
        line 27: 65
        line 28: 78
        line 29: 92
        line 20: 106
}
Signature: #72                          // Ljava/lang/Enum<Lext/mods/gameserver/enums/items/ItemLocation;>;
SourceFile: "ItemLocation.java"
