// Bytecode for: ext.mods.gameserver.enums.items.TicketType
// File: ext\mods\gameserver\enums\items\TicketType.class

Classfile /c:/Users/User/Desktop/BrProject/bin/main/ext/mods/gameserver/enums/items/TicketType.class
  Last modified 9 de jul de 2026; size 1387 bytes
  MD5 checksum 323b9560a8ca5e0758eb5dd4ae342967
  Compiled from "TicketType.java"
public final class ext.mods.gameserver.enums.items.TicketType extends java.lang.Enum<ext.mods.gameserver.enums.items.TicketType>
  minor version: 0
  major version: 69
  flags: (0x4031) ACC_PUBLIC, ACC_FINAL, ACC_SUPER, ACC_ENUM
  this_class: #1                          // ext/mods/gameserver/enums/items/TicketType
  super_class: #32                        // java/lang/Enum
  interfaces: 0, fields: 7, methods: 5, attributes: 2
Constant pool:
   #1 = Class              #2             // ext/mods/gameserver/enums/items/TicketType
   #2 = Utf8               ext/mods/gameserver/enums/items/TicketType
   #3 = Fieldref           #1.#4          // ext/mods/gameserver/enums/items/TicketType.SWORD:Lext/mods/gameserver/enums/items/TicketType;
   #4 = NameAndType        #5:#6          // SWORD:Lext/mods/gameserver/enums/items/TicketType;
   #5 = Utf8               SWORD
   #6 = Utf8               Lext/mods/gameserver/enums/items/TicketType;
   #7 = Fieldref           #1.#8          // ext/mods/gameserver/enums/items/TicketType.POLE:Lext/mods/gameserver/enums/items/TicketType;
   #8 = NameAndType        #9:#6          // POLE:Lext/mods/gameserver/enums/items/TicketType;
   #9 = Utf8               POLE
  #10 = Fieldref           #1.#11         // ext/mods/gameserver/enums/items/TicketType.BOW:Lext/mods/gameserver/enums/items/TicketType;
  #11 = NameAndType        #12:#6         // BOW:Lext/mods/gameserver/enums/items/TicketType;
  #12 = Utf8               BOW
  #13 = Fieldref           #1.#14         // ext/mods/gameserver/enums/items/TicketType.CLERIC:Lext/mods/gameserver/enums/items/TicketType;
  #14 = NameAndType        #15:#6         // CLERIC:Lext/mods/gameserver/enums/items/TicketType;
  #15 = Utf8               CLERIC
  #16 = Fieldref           #1.#17         // ext/mods/gameserver/enums/items/TicketType.WIZARD:Lext/mods/gameserver/enums/items/TicketType;
  #17 = NameAndType        #18:#6         // WIZARD:Lext/mods/gameserver/enums/items/TicketType;
  #18 = Utf8               WIZARD
  #19 = Fieldref           #1.#20         // ext/mods/gameserver/enums/items/TicketType.TELEPORTER:Lext/mods/gameserver/enums/items/TicketType;
  #20 = NameAndType        #21:#6         // TELEPORTER:Lext/mods/gameserver/enums/items/TicketType;
  #21 = Utf8               TELEPORTER
  #22 = Fieldref           #1.#23         // ext/mods/gameserver/enums/items/TicketType.$VALUES:[Lext/mods/gameserver/enums/items/TicketType;
  #23 = NameAndType        #24:#25        // $VALUES:[Lext/mods/gameserver/enums/items/TicketType;
  #24 = Utf8               $VALUES
  #25 = Utf8               [Lext/mods/gameserver/enums/items/TicketType;
  #26 = Methodref          #27.#28        // "[Lext/mods/gameserver/enums/items/TicketType;".clone:()Ljava/lang/Object;
  #27 = Class              #25            // "[Lext/mods/gameserver/enums/items/TicketType;"
  #28 = NameAndType        #29:#30        // clone:()Ljava/lang/Object;
  #29 = Utf8               clone
  #30 = Utf8               ()Ljava/lang/Object;
  #31 = Methodref          #32.#33        // java/lang/Enum.valueOf:(Ljava/lang/Class;Ljava/lang/String;)Ljava/lang/Enum;
  #32 = Class              #34            // java/lang/Enum
  #33 = NameAndType        #35:#36        // valueOf:(Ljava/lang/Class;Ljava/lang/String;)Ljava/lang/Enum;
  #34 = Utf8               java/lang/Enum
  #35 = Utf8               valueOf
  #36 = Utf8               (Ljava/lang/Class;Ljava/lang/String;)Ljava/lang/Enum;
  #37 = Methodref          #32.#38        // java/lang/Enum."<init>":(Ljava/lang/String;I)V
  #38 = NameAndType        #39:#40        // "<init>":(Ljava/lang/String;I)V
  #39 = Utf8               <init>
  #40 = Utf8               (Ljava/lang/String;I)V
  #41 = String             #5             // SWORD
  #42 = Methodref          #1.#38         // ext/mods/gameserver/enums/items/TicketType."<init>":(Ljava/lang/String;I)V
  #43 = String             #9             // POLE
  #44 = String             #12            // BOW
  #45 = String             #15            // CLERIC
  #46 = String             #18            // WIZARD
  #47 = String             #21            // TELEPORTER
  #48 = Methodref          #1.#49         // ext/mods/gameserver/enums/items/TicketType.$values:()[Lext/mods/gameserver/enums/items/TicketType;
  #49 = NameAndType        #50:#51        // $values:()[Lext/mods/gameserver/enums/items/TicketType;
  #50 = Utf8               $values
  #51 = Utf8               ()[Lext/mods/gameserver/enums/items/TicketType;
  #52 = Utf8               values
  #53 = Utf8               Code
  #54 = Utf8               LineNumberTable
  #55 = Utf8               (Ljava/lang/String;)Lext/mods/gameserver/enums/items/TicketType;
  #56 = Utf8               LocalVariableTable
  #57 = Utf8               name
  #58 = Utf8               Ljava/lang/String;
  #59 = Utf8               MethodParameters
  #60 = Utf8               this
  #61 = Utf8               Signature
  #62 = Utf8               ()V
  #63 = Utf8               <clinit>
  #64 = Utf8               Ljava/lang/Enum<Lext/mods/gameserver/enums/items/TicketType;>;
  #65 = Utf8               SourceFile
  #66 = Utf8               TicketType.java
{
  public static final ext.mods.gameserver.enums.items.TicketType SWORD;
    descriptor: Lext/mods/gameserver/enums/items/TicketType;
    flags: (0x4019) ACC_PUBLIC, ACC_STATIC, ACC_FINAL, ACC_ENUM

  public static final ext.mods.gameserver.enums.items.TicketType POLE;
    descriptor: Lext/mods/gameserver/enums/items/TicketType;
    flags: (0x4019) ACC_PUBLIC, ACC_STATIC, ACC_FINAL, ACC_ENUM

  public static final ext.mods.gameserver.enums.items.TicketType BOW;
    descriptor: Lext/mods/gameserver/enums/items/TicketType;
    flags: (0x4019) ACC_PUBLIC, ACC_STATIC, ACC_FINAL, ACC_ENUM

  public static final ext.mods.gameserver.enums.items.TicketType CLERIC;
    descriptor: Lext/mods/gameserver/enums/items/TicketType;
    flags: (0x4019) ACC_PUBLIC, ACC_STATIC, ACC_FINAL, ACC_ENUM

  public static final ext.mods.gameserver.enums.items.TicketType WIZARD;
    descriptor: Lext/mods/gameserver/enums/items/TicketType;
    flags: (0x4019) ACC_PUBLIC, ACC_STATIC, ACC_FINAL, ACC_ENUM

  public static final ext.mods.gameserver.enums.items.TicketType TELEPORTER;
    descriptor: Lext/mods/gameserver/enums/items/TicketType;
    flags: (0x4019) ACC_PUBLIC, ACC_STATIC, ACC_FINAL, ACC_ENUM

  public static ext.mods.gameserver.enums.items.TicketType[] values();
    descriptor: ()[Lext/mods/gameserver/enums/items/TicketType;
    flags: (0x0009) ACC_PUBLIC, ACC_STATIC
    Code:
      stack=1, locals=0, args_size=0
         0: getstatic     #22                 // Field $VALUES:[Lext/mods/gameserver/enums/items/TicketType;
         3: invokevirtual #26                 // Method "[Lext/mods/gameserver/enums/items/TicketType;".clone:()Ljava/lang/Object;
         6: checkcast     #27                 // class "[Lext/mods/gameserver/enums/items/TicketType;"
         9: areturn
      LineNumberTable:
        line 20: 0

  public static ext.mods.gameserver.enums.items.TicketType valueOf(java.lang.String);
    descriptor: (Ljava/lang/String;)Lext/mods/gameserver/enums/items/TicketType;
    flags: (0x0009) ACC_PUBLIC, ACC_STATIC
    Code:
      stack=2, locals=1, args_size=1
         0: ldc           #1                  // class ext/mods/gameserver/enums/items/TicketType
         2: aload_0
         3: invokestatic  #31                 // Method java/lang/Enum.valueOf:(Ljava/lang/Class;Ljava/lang/String;)Ljava/lang/Enum;
         6: checkcast     #1                  // class ext/mods/gameserver/enums/items/TicketType
         9: areturn
      LineNumberTable:
        line 20: 0
      LocalVariableTable:
        Start  Length  Slot  Name   Signature
            0      10     0  name   Ljava/lang/String;
    MethodParameters:
      Name                           Flags
      <no name>                      mandated

  static {};
    descriptor: ()V
    flags: (0x0008) ACC_STATIC
    Code:
      stack=4, locals=0, args_size=0
         0: new           #1                  // class ext/mods/gameserver/enums/items/TicketType
         3: dup
         4: ldc           #41                 // String SWORD
         6: iconst_0
         7: invokespecial #42                 // Method "<init>":(Ljava/lang/String;I)V
        10: putstatic     #3                  // Field SWORD:Lext/mods/gameserver/enums/items/TicketType;
        13: new           #1                  // class ext/mods/gameserver/enums/items/TicketType
        16: dup
        17: ldc           #43                 // String POLE
        19: iconst_1
        20: invokespecial #42                 // Method "<init>":(Ljava/lang/String;I)V
        23: putstatic     #7                  // Field POLE:Lext/mods/gameserver/enums/items/TicketType;
        26: new           #1                  // class ext/mods/gameserver/enums/items/TicketType
        29: dup
        30: ldc           #44                 // String BOW
        32: iconst_2
        33: invokespecial #42                 // Method "<init>":(Ljava/lang/String;I)V
        36: putstatic     #10                 // Field BOW:Lext/mods/gameserver/enums/items/TicketType;
        39: new           #1                  // class ext/mods/gameserver/enums/items/TicketType
        42: dup
        43: ldc           #45                 // String CLERIC
        45: iconst_3
        46: invokespecial #42                 // Method "<init>":(Ljava/lang/String;I)V
        49: putstatic     #13                 // Field CLERIC:Lext/mods/gameserver/enums/items/TicketType;
        52: new           #1                  // class ext/mods/gameserver/enums/items/TicketType
        55: dup
        56: ldc           #46                 // String WIZARD
        58: iconst_4
        59: invokespecial #42                 // Method "<init>":(Ljava/lang/String;I)V
        62: putstatic     #16                 // Field WIZARD:Lext/mods/gameserver/enums/items/TicketType;
        65: new           #1                  // class ext/mods/gameserver/enums/items/TicketType
        68: dup
        69: ldc           #47                 // String TELEPORTER
        71: iconst_5
        72: invokespecial #42                 // Method "<init>":(Ljava/lang/String;I)V
        75: putstatic     #19                 // Field TELEPORTER:Lext/mods/gameserver/enums/items/TicketType;
        78: invokestatic  #48                 // Method $values:()[Lext/mods/gameserver/enums/items/TicketType;
        81: putstatic     #22                 // Field $VALUES:[Lext/mods/gameserver/enums/items/TicketType;
        84: return
      LineNumberTable:
        line 22: 0
        line 23: 13
        line 24: 26
        line 25: 39
        line 26: 52
        line 27: 65
        line 20: 78
}
Signature: #64                          // Ljava/lang/Enum<Lext/mods/gameserver/enums/items/TicketType;>;
SourceFile: "TicketType.java"
