// Bytecode for: ext.mods.gameserver.geoengine.pathfinding.serialization.L2BRSerializer$Companion
// File: ext\mods\gameserver\geoengine\pathfinding\serialization\L2BRSerializer$Companion.class

Classfile /c:/Users/User/Desktop/BrProject/bin/main/ext/mods/gameserver/geoengine/pathfinding/serialization/L2BRSerializer$Companion.class
  Last modified 9 de jul de 2026; size 1298 bytes
  MD5 checksum 3e82b5f7a71d6c9183aade556d325f80
  Compiled from "L2BRSerializer.kt"
public final class ext.mods.gameserver.geoengine.pathfinding.serialization.L2BRSerializer$Companion
  minor version: 0
  major version: 69
  flags: (0x0031) ACC_PUBLIC, ACC_FINAL, ACC_SUPER
  this_class: #2                          // ext/mods/gameserver/geoengine/pathfinding/serialization/L2BRSerializer$Companion
  super_class: #4                         // java/lang/Object
  interfaces: 0, fields: 0, methods: 3, attributes: 3
Constant pool:
   #1 = Utf8               ext/mods/gameserver/geoengine/pathfinding/serialization/L2BRSerializer$Companion
   #2 = Class              #1             // ext/mods/gameserver/geoengine/pathfinding/serialization/L2BRSerializer$Companion
   #3 = Utf8               java/lang/Object
   #4 = Class              #3             // java/lang/Object
   #5 = Utf8               <init>
   #6 = Utf8               ()V
   #7 = NameAndType        #5:#6          // "<init>":()V
   #8 = Methodref          #4.#7          // java/lang/Object."<init>":()V
   #9 = Utf8               this
  #10 = Utf8               Lext/mods/gameserver/geoengine/pathfinding/serialization/L2BRSerializer$Companion;
  #11 = Utf8               getMAGIC
  #12 = Utf8               ()J
  #13 = Utf8               ext/mods/gameserver/geoengine/pathfinding/serialization/L2BRSerializer
  #14 = Class              #13            // ext/mods/gameserver/geoengine/pathfinding/serialization/L2BRSerializer
  #15 = Utf8               access$getMAGIC$cp
  #16 = NameAndType        #15:#12        // access$getMAGIC$cp:()J
  #17 = Methodref          #14.#16        // ext/mods/gameserver/geoengine/pathfinding/serialization/L2BRSerializer.access$getMAGIC$cp:()J
  #18 = Utf8               (Lkotlin/jvm/internal/DefaultConstructorMarker;)V
  #19 = Methodref          #2.#7          // ext/mods/gameserver/geoengine/pathfinding/serialization/L2BRSerializer$Companion."<init>":()V
  #20 = Utf8               $constructor_marker
  #21 = Utf8               Lkotlin/jvm/internal/DefaultConstructorMarker;
  #22 = Utf8               Lkotlin/Metadata;
  #23 = Utf8               mv
  #24 = Integer            2
  #25 = Integer            3
  #26 = Integer            0
  #27 = Utf8               k
  #28 = Integer            1
  #29 = Utf8               xi
  #30 = Integer            48
  #31 = Utf8               d1
  #32 = Utf8               \u0000(\n\u0002\u0018\u0002\n\u0002\u0010\u0000\n\u0002\b\u0003\n\u0002\u0010\b\n\u0002\b\u0003\n\u0002\u0010\u000e\n\u0000\n\u0002\u0010\t\n\u0002\b\u0003\n\u0002\u0010\n\n\u0000\b\u0086\u0003\u0018\u00002\u00020\u0001B\t\b\u0002¢\u0006\u0004\b\u0002\u0010\u0003R\u000e\u0010\u0004\u001a\u00020\u0005X\u0086T¢\u0006\u0002\n\u0000R\u000e\u0010\u0006\u001a\u00020\u0005X\u0086T¢\u0006\u0002\n\u0000R\u000e\u0010\u0007\u001a\u00020\u0005X\u0086T¢\u0006\u0002\n\u0000R\u000e\u0010\b\u001a\u00020\tX\u0086T¢\u0006\u0002\n\u0000R\u0014\u0010\n\u001a\u00020\u000bX\u0086D¢\u0006\b\n\u0000\u001a\u0004\b\f\u0010\rR\u000e\u0010\u000e\u001a\u00020\u000fX\u0086T¢\u0006\u0002\n\u0000¨\u0006\u0010
  #33 = Utf8               d2
  #34 = Utf8
  #35 = Utf8               HEADER_SIZE
  #36 = Utf8               INDEX_ENTRY_SIZE
  #37 = Utf8               ZSTD_LEVEL
  #38 = Utf8               MAGIC_STRING
  #39 = Utf8               MAGIC
  #40 = Utf8               VERSION
  #41 = Utf8               Brproject
  #42 = Utf8               Companion
  #43 = Utf8               L2BRSerializer.kt
  #44 = Utf8               Code
  #45 = Utf8               LineNumberTable
  #46 = Utf8               LocalVariableTable
  #47 = Utf8               InnerClasses
  #48 = Utf8               SourceFile
  #49 = Utf8               RuntimeVisibleAnnotations
{
  public final long getMAGIC();
    descriptor: ()J
    flags: (0x0011) ACC_PUBLIC, ACC_FINAL
    Code:
      stack=2, locals=1, args_size=1
         0: invokestatic  #17                 // Method ext/mods/gameserver/geoengine/pathfinding/serialization/L2BRSerializer.access$getMAGIC$cp:()J
         3: lreturn
      LineNumberTable:
        line 41: 0
      LocalVariableTable:
        Start  Length  Slot  Name   Signature
            0       4     0  this   Lext/mods/gameserver/geoengine/pathfinding/serialization/L2BRSerializer$Companion;

  public ext.mods.gameserver.geoengine.pathfinding.serialization.L2BRSerializer$Companion(kotlin.jvm.internal.DefaultConstructorMarker);
    descriptor: (Lkotlin/jvm/internal/DefaultConstructorMarker;)V
    flags: (0x1001) ACC_PUBLIC, ACC_SYNTHETIC
    Code:
      stack=1, locals=2, args_size=2
         0: aload_0
         1: invokespecial #19                 // Method "<init>":()V
         4: return
      LocalVariableTable:
        Start  Length  Slot  Name   Signature
            0       5     0  this   Lext/mods/gameserver/geoengine/pathfinding/serialization/L2BRSerializer$Companion;
            0       5     1 $constructor_marker   Lkotlin/jvm/internal/DefaultConstructorMarker;
}
InnerClasses:
  public static final #42= #2 of #14;     // Companion=class ext/mods/gameserver/geoengine/pathfinding/serialization/L2BRSerializer$Companion of class ext/mods/gameserver/geoengine/pathfinding/serialization/L2BRSerializer
SourceFile: "L2BRSerializer.kt"
RuntimeVisibleAnnotations:
  0: #22(#23=[I#24,I#25,I#26],#27=I#28,#29=I#30,#31=[s#32],#33=[s#10,s#34,s#5,s#6,s#35,s#34,s#36,s#37,s#38,s#34,s#39,s#34,s#11,s#12,s#40,s#34,s#41])
    kotlin.Metadata(
      mv=[2,3,0]
      k=1
      xi=48
      d1=["\u0000(\n\u0002\u0018\u0002\n\u0002\u0010\u0000\n\u0002\b\u0003\n\u0002\u0010\b\n\u0002\b\u0003\n\u0002\u0010\u000e\n\u0000\n\u0002\u0010\t\n\u0002\b\u0003\n\u0002\u0010\n\n\u0000\b\u0086\u0003\u0018\u00002\u00020\u0001B\t\b\u0002¢\u0006\u0004\b\u0002\u0010\u0003R\u000e\u0010\u0004\u001a\u00020\u0005X\u0086T¢\u0006\u0002\n\u0000R\u000e\u0010\u0006\u001a\u00020\u0005X\u0086T¢\u0006\u0002\n\u0000R\u000e\u0010\u0007\u001a\u00020\u0005X\u0086T¢\u0006\u0002\n\u0000R\u000e\u0010\b\u001a\u00020\tX\u0086T¢\u0006\u0002\n\u0000R\u0014\u0010\n\u001a\u00020\u000bX\u0086D¢\u0006\b\n\u0000\u001a\u0004\b\f\u0010\rR\u000e\u0010\u000e\u001a\u00020\u000fX\u0086T¢\u0006\u0002\n\u0000¨\u0006\u0010"]
      d2=["Lext/mods/gameserver/geoengine/pathfinding/serialization/L2BRSerializer$Companion;","","<init>","()V","HEADER_SIZE","","INDEX_ENTRY_SIZE","ZSTD_LEVEL","MAGIC_STRING","","MAGIC","","getMAGIC","()J","VERSION","","Brproject"]
    )
