// Bytecode for: ext.mods.gameserver.handler.voicedcommandhandlers.Pix
// File: ext\mods\gameserver\handler\voicedcommandhandlers\Pix.class

Classfile /c:/Users/User/Desktop/BrProject/bin/main/ext/mods/gameserver/handler/voicedcommandhandlers/Pix.class
  Last modified 9 de jul de 2026; size 1255 bytes
  MD5 checksum 76ab75bfb29d93a1779f5e9237b81a6c
  Compiled from "Pix.java"
public class ext.mods.gameserver.handler.voicedcommandhandlers.Pix implements ext.mods.gameserver.handler.IVoicedCommandHandler
  minor version: 0
  major version: 69
  flags: (0x0021) ACC_PUBLIC, ACC_SUPER
  this_class: #26                         // ext/mods/gameserver/handler/voicedcommandhandlers/Pix
  super_class: #2                         // java/lang/Object
  interfaces: 1, fields: 1, methods: 4, attributes: 1
Constant pool:
   #1 = Methodref          #2.#3          // java/lang/Object."<init>":()V
   #2 = Class              #4             // java/lang/Object
   #3 = NameAndType        #5:#6          // "<init>":()V
   #4 = Utf8               java/lang/Object
   #5 = Utf8               <init>
   #6 = Utf8               ()V
   #7 = String             #8             // pay
   #8 = Utf8               pay
   #9 = Methodref          #10.#11        // java/lang/String.equalsIgnoreCase:(Ljava/lang/String;)Z
  #10 = Class              #12            // java/lang/String
  #11 = NameAndType        #13:#14        // equalsIgnoreCase:(Ljava/lang/String;)Z
  #12 = Utf8               java/lang/String
  #13 = Utf8               equalsIgnoreCase
  #14 = Utf8               (Ljava/lang/String;)Z
  #15 = String             #16            // en
  #16 = Utf8               en
  #17 = String             #18            // pt
  #18 = Utf8               pt
  #19 = Methodref          #20.#21        // ext/mods/donation/DonationPixAccess.openShop:(Lext/mods/gameserver/model/actor/Player;Ljava/lang/String;)Z
  #20 = Class              #22            // ext/mods/donation/DonationPixAccess
  #21 = NameAndType        #23:#24        // openShop:(Lext/mods/gameserver/model/actor/Player;Ljava/lang/String;)Z
  #22 = Utf8               ext/mods/donation/DonationPixAccess
  #23 = Utf8               openShop
  #24 = Utf8               (Lext/mods/gameserver/model/actor/Player;Ljava/lang/String;)Z
  #25 = Fieldref           #26.#27        // ext/mods/gameserver/handler/voicedcommandhandlers/Pix.VOICED_COMMANDS:[Ljava/lang/String;
  #26 = Class              #28            // ext/mods/gameserver/handler/voicedcommandhandlers/Pix
  #27 = NameAndType        #29:#30        // VOICED_COMMANDS:[Ljava/lang/String;
  #28 = Utf8               ext/mods/gameserver/handler/voicedcommandhandlers/Pix
  #29 = Utf8               VOICED_COMMANDS
  #30 = Utf8               [Ljava/lang/String;
  #31 = String             #32            // pix
  #32 = Utf8               pix
  #33 = Class              #34            // ext/mods/gameserver/handler/IVoicedCommandHandler
  #34 = Utf8               ext/mods/gameserver/handler/IVoicedCommandHandler
  #35 = Utf8               Code
  #36 = Utf8               LineNumberTable
  #37 = Utf8               LocalVariableTable
  #38 = Utf8               this
  #39 = Utf8               Lext/mods/gameserver/handler/voicedcommandhandlers/Pix;
  #40 = Utf8               useVoicedCommand
  #41 = Utf8               (Ljava/lang/String;Lext/mods/gameserver/model/actor/Player;Ljava/lang/String;)Z
  #42 = Utf8               command
  #43 = Utf8               Ljava/lang/String;
  #44 = Utf8               player
  #45 = Utf8               Lext/mods/gameserver/model/actor/Player;
  #46 = Utf8               target
  #47 = Utf8               StackMapTable
  #48 = Class              #49            // ext/mods/gameserver/model/actor/Player
  #49 = Utf8               ext/mods/gameserver/model/actor/Player
  #50 = Utf8               getVoicedCommandList
  #51 = Utf8               ()[Ljava/lang/String;
  #52 = Utf8               <clinit>
  #53 = Utf8               SourceFile
  #54 = Utf8               Pix.java
{
  public ext.mods.gameserver.handler.voicedcommandhandlers.Pix();
    descriptor: ()V
    flags: (0x0001) ACC_PUBLIC
    Code:
      stack=1, locals=1, args_size=1
         0: aload_0
         1: invokespecial #1                  // Method java/lang/Object."<init>":()V
         4: return
      LineNumberTable:
        line 13: 0
      LocalVariableTable:
        Start  Length  Slot  Name   Signature
            0       5     0  this   Lext/mods/gameserver/handler/voicedcommandhandlers/Pix;

  public boolean useVoicedCommand(java.lang.String, ext.mods.gameserver.model.actor.Player, java.lang.String);
    descriptor: (Ljava/lang/String;Lext/mods/gameserver/model/actor/Player;Ljava/lang/String;)Z
    flags: (0x0001) ACC_PUBLIC
    Code:
      stack=3, locals=4, args_size=4
         0: aload_2
         1: ldc           #7                  // String pay
         3: aload_1
         4: invokevirtual #9                  // Method java/lang/String.equalsIgnoreCase:(Ljava/lang/String;)Z
         7: ifeq          15
        10: ldc           #15                 // String en
        12: goto          17
        15: ldc           #17                 // String pt
        17: invokestatic  #19                 // Method ext/mods/donation/DonationPixAccess.openShop:(Lext/mods/gameserver/model/actor/Player;Ljava/lang/String;)Z
        20: ireturn
      LineNumberTable:
        line 24: 0
      LocalVariableTable:
        Start  Length  Slot  Name   Signature
            0      21     0  this   Lext/mods/gameserver/handler/voicedcommandhandlers/Pix;
            0      21     1 command   Ljava/lang/String;
            0      21     2 player   Lext/mods/gameserver/model/actor/Player;
            0      21     3 target   Ljava/lang/String;
      StackMapTable: number_of_entries = 2
        frame_type = 79 /* same_locals_1_stack_item */
          stack = [ class ext/mods/gameserver/model/actor/Player ]
        frame_type = 255 /* full_frame */
          offset_delta = 1
          locals = [ class ext/mods/gameserver/handler/voicedcommandhandlers/Pix, class java/lang/String, class ext/mods/gameserver/model/actor/Player, class java/lang/String ]
          stack = [ class ext/mods/gameserver/model/actor/Player, class java/lang/String ]

  public java.lang.String[] getVoicedCommandList();
    descriptor: ()[Ljava/lang/String;
    flags: (0x0001) ACC_PUBLIC
    Code:
      stack=1, locals=1, args_size=1
         0: getstatic     #25                 // Field VOICED_COMMANDS:[Ljava/lang/String;
         3: areturn
      LineNumberTable:
        line 30: 0
      LocalVariableTable:
        Start  Length  Slot  Name   Signature
            0       4     0  this   Lext/mods/gameserver/handler/voicedcommandhandlers/Pix;

  static {};
    descriptor: ()V
    flags: (0x0008) ACC_STATIC
    Code:
      stack=4, locals=0, args_size=0
         0: iconst_2
         1: anewarray     #10                 // class java/lang/String
         4: dup
         5: iconst_0
         6: ldc           #31                 // String pix
         8: aastore
         9: dup
        10: iconst_1
        11: ldc           #7                  // String pay
        13: aastore
        14: putstatic     #25                 // Field VOICED_COMMANDS:[Ljava/lang/String;
        17: return
      LineNumberTable:
        line 15: 0
}
SourceFile: "Pix.java"
