// Bytecode for: ext.mods.gameserver.network.clientpackets.RequestBuySeed
// File: ext\mods\gameserver\network\clientpackets\RequestBuySeed.class

Classfile /c:/Users/User/Desktop/BrProject/bin/main/ext/mods/gameserver/network/clientpackets/RequestBuySeed.class
  Last modified 9 de jul de 2026; size 6513 bytes
  MD5 checksum 74d12b87f8effc801c1f23f8b78b0610
  Compiled from "RequestBuySeed.java"
public class ext.mods.gameserver.network.clientpackets.RequestBuySeed extends ext.mods.gameserver.network.clientpackets.L2GameClientPacket
  minor version: 0
  major version: 69
  flags: (0x0021) ACC_PUBLIC, ACC_SUPER
  this_class: #8                          // ext/mods/gameserver/network/clientpackets/RequestBuySeed
  super_class: #2                         // ext/mods/gameserver/network/clientpackets/L2GameClientPacket
  interfaces: 0, fields: 3, methods: 3, attributes: 1
Constant pool:
    #1 = Methodref          #2.#3         // ext/mods/gameserver/network/clientpackets/L2GameClientPacket."<init>":()V
    #2 = Class              #4            // ext/mods/gameserver/network/clientpackets/L2GameClientPacket
    #3 = NameAndType        #5:#6         // "<init>":()V
    #4 = Utf8               ext/mods/gameserver/network/clientpackets/L2GameClientPacket
    #5 = Utf8               <init>
    #6 = Utf8               ()V
    #7 = Methodref          #8.#9         // ext/mods/gameserver/network/clientpackets/RequestBuySeed.readD:()I
    #8 = Class              #10           // ext/mods/gameserver/network/clientpackets/RequestBuySeed
    #9 = NameAndType        #11:#12       // readD:()I
   #10 = Utf8               ext/mods/gameserver/network/clientpackets/RequestBuySeed
   #11 = Utf8               readD
   #12 = Utf8               ()I
   #13 = Fieldref           #8.#14        // ext/mods/gameserver/network/clientpackets/RequestBuySeed._manorId:I
   #14 = NameAndType        #15:#16       // _manorId:I
   #15 = Utf8               _manorId
   #16 = Utf8               I
   #17 = Fieldref           #18.#19       // ext/mods/Config.MAX_ITEM_IN_PACKET:I
   #18 = Class              #20           // ext/mods/Config
   #19 = NameAndType        #21:#16       // MAX_ITEM_IN_PACKET:I
   #20 = Utf8               ext/mods/Config
   #21 = Utf8               MAX_ITEM_IN_PACKET
   #22 = Fieldref           #8.#23        // ext/mods/gameserver/network/clientpackets/RequestBuySeed._buf:Ljava/nio/ByteBuffer;
   #23 = NameAndType        #24:#25       // _buf:Ljava/nio/ByteBuffer;
   #24 = Utf8               _buf
   #25 = Utf8               Ljava/nio/ByteBuffer;
   #26 = Methodref          #27.#28       // java/nio/ByteBuffer.remaining:()I
   #27 = Class              #29           // java/nio/ByteBuffer
   #28 = NameAndType        #30:#12       // remaining:()I
   #29 = Utf8               java/nio/ByteBuffer
   #30 = Utf8               remaining
   #31 = Class              #32           // java/util/ArrayList
   #32 = Utf8               java/util/ArrayList
   #33 = Methodref          #31.#34       // java/util/ArrayList."<init>":(I)V
   #34 = NameAndType        #5:#35        // "<init>":(I)V
   #35 = Utf8               (I)V
   #36 = Fieldref           #8.#37        // ext/mods/gameserver/network/clientpackets/RequestBuySeed._items:Ljava/util/List;
   #37 = NameAndType        #38:#39       // _items:Ljava/util/List;
   #38 = Utf8               _items
   #39 = Utf8               Ljava/util/List;
   #40 = Class              #41           // ext/mods/gameserver/model/holder/IntIntHolder
   #41 = Utf8               ext/mods/gameserver/model/holder/IntIntHolder
   #42 = Methodref          #40.#43       // ext/mods/gameserver/model/holder/IntIntHolder."<init>":(II)V
   #43 = NameAndType        #5:#44        // "<init>":(II)V
   #44 = Utf8               (II)V
   #45 = InterfaceMethodref #46.#47       // java/util/List.add:(Ljava/lang/Object;)Z
   #46 = Class              #48           // java/util/List
   #47 = NameAndType        #49:#50       // add:(Ljava/lang/Object;)Z
   #48 = Utf8               java/util/List
   #49 = Utf8               add
   #50 = Utf8               (Ljava/lang/Object;)Z
   #51 = Methodref          #8.#52        // ext/mods/gameserver/network/clientpackets/RequestBuySeed.getClient:()Lext/mods/commons/mmocore/MMOClient;
   #52 = NameAndType        #53:#54       // getClient:()Lext/mods/commons/mmocore/MMOClient;
   #53 = Utf8               getClient
   #54 = Utf8               ()Lext/mods/commons/mmocore/MMOClient;
   #55 = Class              #56           // ext/mods/gameserver/network/GameClient
   #56 = Utf8               ext/mods/gameserver/network/GameClient
   #57 = Fieldref           #58.#59       // ext/mods/gameserver/enums/FloodProtector.MANOR:Lext/mods/gameserver/enums/FloodProtector;
   #58 = Class              #60           // ext/mods/gameserver/enums/FloodProtector
   #59 = NameAndType        #61:#62       // MANOR:Lext/mods/gameserver/enums/FloodProtector;
   #60 = Utf8               ext/mods/gameserver/enums/FloodProtector
   #61 = Utf8               MANOR
   #62 = Utf8               Lext/mods/gameserver/enums/FloodProtector;
   #63 = Methodref          #55.#64       // ext/mods/gameserver/network/GameClient.performAction:(Lext/mods/gameserver/enums/FloodProtector;)Z
   #64 = NameAndType        #65:#66       // performAction:(Lext/mods/gameserver/enums/FloodProtector;)Z
   #65 = Utf8               performAction
   #66 = Utf8               (Lext/mods/gameserver/enums/FloodProtector;)Z
   #67 = Methodref          #55.#68       // ext/mods/gameserver/network/GameClient.getPlayer:()Lext/mods/gameserver/model/actor/Player;
   #68 = NameAndType        #69:#70       // getPlayer:()Lext/mods/gameserver/model/actor/Player;
   #69 = Utf8               getPlayer
   #70 = Utf8               ()Lext/mods/gameserver/model/actor/Player;
   #71 = Fieldref           #72.#73       // ext/mods/gameserver/network/serverpackets/ActionFailed.STATIC_PACKET:Lext/mods/gameserver/network/serverpackets/ActionFailed;
   #72 = Class              #74           // ext/mods/gameserver/network/serverpackets/ActionFailed
   #73 = NameAndType        #75:#76       // STATIC_PACKET:Lext/mods/gameserver/network/serverpackets/ActionFailed;
   #74 = Utf8               ext/mods/gameserver/network/serverpackets/ActionFailed
   #75 = Utf8               STATIC_PACKET
   #76 = Utf8               Lext/mods/gameserver/network/serverpackets/ActionFailed;
   #77 = Methodref          #8.#78        // ext/mods/gameserver/network/clientpackets/RequestBuySeed.sendPacket:(Lext/mods/gameserver/network/serverpackets/L2GameServerPacket;)V
   #78 = NameAndType        #79:#80       // sendPacket:(Lext/mods/gameserver/network/serverpackets/L2GameServerPacket;)V
   #79 = Utf8               sendPacket
   #80 = Utf8               (Lext/mods/gameserver/network/serverpackets/L2GameServerPacket;)V
   #81 = Methodref          #82.#83       // ext/mods/gameserver/data/manager/CastleManorManager.getInstance:()Lext/mods/gameserver/data/manager/CastleManorManager;
   #82 = Class              #84           // ext/mods/gameserver/data/manager/CastleManorManager
   #83 = NameAndType        #85:#86       // getInstance:()Lext/mods/gameserver/data/manager/CastleManorManager;
   #84 = Utf8               ext/mods/gameserver/data/manager/CastleManorManager
   #85 = Utf8               getInstance
   #86 = Utf8               ()Lext/mods/gameserver/data/manager/CastleManorManager;
   #87 = Methodref          #82.#88       // ext/mods/gameserver/data/manager/CastleManorManager.isUnderMaintenance:()Z
   #88 = NameAndType        #89:#90       // isUnderMaintenance:()Z
   #89 = Utf8               isUnderMaintenance
   #90 = Utf8               ()Z
   #91 = Methodref          #92.#93       // ext/mods/gameserver/data/manager/CastleManager.getInstance:()Lext/mods/gameserver/data/manager/CastleManager;
   #92 = Class              #94           // ext/mods/gameserver/data/manager/CastleManager
   #93 = NameAndType        #85:#95       // getInstance:()Lext/mods/gameserver/data/manager/CastleManager;
   #94 = Utf8               ext/mods/gameserver/data/manager/CastleManager
   #95 = Utf8               ()Lext/mods/gameserver/data/manager/CastleManager;
   #96 = Methodref          #92.#97       // ext/mods/gameserver/data/manager/CastleManager.getCastleById:(I)Lext/mods/gameserver/model/residence/castle/Castle;
   #97 = NameAndType        #98:#99       // getCastleById:(I)Lext/mods/gameserver/model/residence/castle/Castle;
   #98 = Utf8               getCastleById
   #99 = Utf8               (I)Lext/mods/gameserver/model/residence/castle/Castle;
  #100 = Methodref          #101.#102     // ext/mods/gameserver/model/actor/Player.getCurrentFolk:()Lext/mods/gameserver/model/actor/instance/Folk;
  #101 = Class              #103          // ext/mods/gameserver/model/actor/Player
  #102 = NameAndType        #104:#105     // getCurrentFolk:()Lext/mods/gameserver/model/actor/instance/Folk;
  #103 = Utf8               ext/mods/gameserver/model/actor/Player
  #104 = Utf8               getCurrentFolk
  #105 = Utf8               ()Lext/mods/gameserver/model/actor/instance/Folk;
  #106 = Class              #107          // ext/mods/gameserver/model/actor/instance/ManorManagerNpc
  #107 = Utf8               ext/mods/gameserver/model/actor/instance/ManorManagerNpc
  #108 = Methodref          #101.#109     // ext/mods/gameserver/model/actor/Player.getAI:()Lext/mods/gameserver/model/actor/ai/type/PlayerAI;
  #109 = NameAndType        #110:#111     // getAI:()Lext/mods/gameserver/model/actor/ai/type/PlayerAI;
  #110 = Utf8               getAI
  #111 = Utf8               ()Lext/mods/gameserver/model/actor/ai/type/PlayerAI;
  #112 = Methodref          #113.#114     // ext/mods/gameserver/model/actor/ai/type/PlayerAI.canDoInteract:(Lext/mods/gameserver/model/WorldObject;)Z
  #113 = Class              #115          // ext/mods/gameserver/model/actor/ai/type/PlayerAI
  #114 = NameAndType        #116:#117     // canDoInteract:(Lext/mods/gameserver/model/WorldObject;)Z
  #115 = Utf8               ext/mods/gameserver/model/actor/ai/type/PlayerAI
  #116 = Utf8               canDoInteract
  #117 = Utf8               (Lext/mods/gameserver/model/WorldObject;)Z
  #118 = Methodref          #119.#120     // ext/mods/gameserver/model/actor/instance/Folk.getCastle:()Lext/mods/gameserver/model/residence/castle/Castle;
  #119 = Class              #121          // ext/mods/gameserver/model/actor/instance/Folk
  #120 = NameAndType        #122:#123     // getCastle:()Lext/mods/gameserver/model/residence/castle/Castle;
  #121 = Utf8               ext/mods/gameserver/model/actor/instance/Folk
  #122 = Utf8               getCastle
  #123 = Utf8               ()Lext/mods/gameserver/model/residence/castle/Castle;
  #124 = Class              #125          // java/util/HashMap
  #125 = Utf8               java/util/HashMap
  #126 = Methodref          #124.#3       // java/util/HashMap."<init>":()V
  #127 = InterfaceMethodref #46.#128      // java/util/List.iterator:()Ljava/util/Iterator;
  #128 = NameAndType        #129:#130     // iterator:()Ljava/util/Iterator;
  #129 = Utf8               iterator
  #130 = Utf8               ()Ljava/util/Iterator;
  #131 = InterfaceMethodref #132.#133     // java/util/Iterator.hasNext:()Z
  #132 = Class              #134          // java/util/Iterator
  #133 = NameAndType        #135:#90      // hasNext:()Z
  #134 = Utf8               java/util/Iterator
  #135 = Utf8               hasNext
  #136 = InterfaceMethodref #132.#137     // java/util/Iterator.next:()Ljava/lang/Object;
  #137 = NameAndType        #138:#139     // next:()Ljava/lang/Object;
  #138 = Utf8               next
  #139 = Utf8               ()Ljava/lang/Object;
  #140 = Methodref          #40.#141      // ext/mods/gameserver/model/holder/IntIntHolder.getId:()I
  #141 = NameAndType        #142:#12      // getId:()I
  #142 = Utf8               getId
  #143 = Methodref          #82.#144      // ext/mods/gameserver/data/manager/CastleManorManager.getSeedProduct:(IIZ)Lext/mods/gameserver/model/manor/SeedProduction;
  #144 = NameAndType        #145:#146     // getSeedProduct:(IIZ)Lext/mods/gameserver/model/manor/SeedProduction;
  #145 = Utf8               getSeedProduct
  #146 = Utf8               (IIZ)Lext/mods/gameserver/model/manor/SeedProduction;
  #147 = Methodref          #148.#149     // ext/mods/gameserver/model/manor/SeedProduction.getPrice:()I
  #148 = Class              #150          // ext/mods/gameserver/model/manor/SeedProduction
  #149 = NameAndType        #151:#12      // getPrice:()I
  #150 = Utf8               ext/mods/gameserver/model/manor/SeedProduction
  #151 = Utf8               getPrice
  #152 = Methodref          #148.#153     // ext/mods/gameserver/model/manor/SeedProduction.getAmount:()I
  #153 = NameAndType        #154:#12      // getAmount:()I
  #154 = Utf8               getAmount
  #155 = Methodref          #40.#156      // ext/mods/gameserver/model/holder/IntIntHolder.getValue:()I
  #156 = NameAndType        #157:#12      // getValue:()I
  #157 = Utf8               getValue
  #158 = Class              #159          // java/lang/Integer
  #159 = Utf8               java/lang/Integer
  #160 = Integer            2147483647
  #161 = Long               2147483647l
  #163 = Methodref          #164.#165     // ext/mods/gameserver/data/xml/ItemData.getInstance:()Lext/mods/gameserver/data/xml/ItemData;
  #164 = Class              #166          // ext/mods/gameserver/data/xml/ItemData
  #165 = NameAndType        #85:#167      // getInstance:()Lext/mods/gameserver/data/xml/ItemData;
  #166 = Utf8               ext/mods/gameserver/data/xml/ItemData
  #167 = Utf8               ()Lext/mods/gameserver/data/xml/ItemData;
  #168 = Methodref          #164.#169     // ext/mods/gameserver/data/xml/ItemData.getTemplate:(I)Lext/mods/gameserver/model/item/kind/Item;
  #169 = NameAndType        #170:#171     // getTemplate:(I)Lext/mods/gameserver/model/item/kind/Item;
  #170 = Utf8               getTemplate
  #171 = Utf8               (I)Lext/mods/gameserver/model/item/kind/Item;
  #172 = Methodref          #173.#174     // ext/mods/gameserver/model/item/kind/Item.getWeight:()I
  #173 = Class              #175          // ext/mods/gameserver/model/item/kind/Item
  #174 = NameAndType        #176:#12      // getWeight:()I
  #175 = Utf8               ext/mods/gameserver/model/item/kind/Item
  #176 = Utf8               getWeight
  #177 = Methodref          #173.#178     // ext/mods/gameserver/model/item/kind/Item.isStackable:()Z
  #178 = NameAndType        #179:#90      // isStackable:()Z
  #179 = Utf8               isStackable
  #180 = Methodref          #101.#181     // ext/mods/gameserver/model/actor/Player.getInventory:()Lext/mods/gameserver/model/itemcontainer/PcInventory;
  #181 = NameAndType        #182:#183     // getInventory:()Lext/mods/gameserver/model/itemcontainer/PcInventory;
  #182 = Utf8               getInventory
  #183 = Utf8               ()Lext/mods/gameserver/model/itemcontainer/PcInventory;
  #184 = Methodref          #185.#186     // ext/mods/gameserver/model/itemcontainer/PcInventory.getItemByItemId:(I)Lext/mods/gameserver/model/item/instance/ItemInstance;
  #185 = Class              #187          // ext/mods/gameserver/model/itemcontainer/PcInventory
  #186 = NameAndType        #188:#189     // getItemByItemId:(I)Lext/mods/gameserver/model/item/instance/ItemInstance;
  #187 = Utf8               ext/mods/gameserver/model/itemcontainer/PcInventory
  #188 = Utf8               getItemByItemId
  #189 = Utf8               (I)Lext/mods/gameserver/model/item/instance/ItemInstance;
  #190 = Methodref          #158.#191     // java/lang/Integer.valueOf:(I)Ljava/lang/Integer;
  #191 = NameAndType        #192:#193     // valueOf:(I)Ljava/lang/Integer;
  #192 = Utf8               valueOf
  #193 = Utf8               (I)Ljava/lang/Integer;
  #194 = InterfaceMethodref #195.#196     // java/util/Map.put:(Ljava/lang/Object;Ljava/lang/Object;)Ljava/lang/Object;
  #195 = Class              #197          // java/util/Map
  #196 = NameAndType        #198:#199     // put:(Ljava/lang/Object;Ljava/lang/Object;)Ljava/lang/Object;
  #197 = Utf8               java/util/Map
  #198 = Utf8               put
  #199 = Utf8               (Ljava/lang/Object;Ljava/lang/Object;)Ljava/lang/Object;
  #200 = Methodref          #185.#201     // ext/mods/gameserver/model/itemcontainer/PcInventory.validateWeight:(I)Z
  #201 = NameAndType        #202:#203     // validateWeight:(I)Z
  #202 = Utf8               validateWeight
  #203 = Utf8               (I)Z
  #204 = Fieldref           #205.#206     // ext/mods/gameserver/network/SystemMessageId.WEIGHT_LIMIT_EXCEEDED:Lext/mods/gameserver/network/SystemMessageId;
  #205 = Class              #207          // ext/mods/gameserver/network/SystemMessageId
  #206 = NameAndType        #208:#209     // WEIGHT_LIMIT_EXCEEDED:Lext/mods/gameserver/network/SystemMessageId;
  #207 = Utf8               ext/mods/gameserver/network/SystemMessageId
  #208 = Utf8               WEIGHT_LIMIT_EXCEEDED
  #209 = Utf8               Lext/mods/gameserver/network/SystemMessageId;
  #210 = Methodref          #211.#212     // ext/mods/gameserver/network/serverpackets/SystemMessage.getSystemMessage:(Lext/mods/gameserver/network/SystemMessageId;)Lext/mods/gameserver/network/serverpackets/SystemMessage;
  #211 = Class              #213          // ext/mods/gameserver/network/serverpackets/SystemMessage
  #212 = NameAndType        #214:#215     // getSystemMessage:(Lext/mods/gameserver/network/SystemMessageId;)Lext/mods/gameserver/network/serverpackets/SystemMessage;
  #213 = Utf8               ext/mods/gameserver/network/serverpackets/SystemMessage
  #214 = Utf8               getSystemMessage
  #215 = Utf8               (Lext/mods/gameserver/network/SystemMessageId;)Lext/mods/gameserver/network/serverpackets/SystemMessage;
  #216 = Methodref          #185.#217     // ext/mods/gameserver/model/itemcontainer/PcInventory.validateCapacity:(I)Z
  #217 = NameAndType        #218:#203     // validateCapacity:(I)Z
  #218 = Utf8               validateCapacity
  #219 = Fieldref           #205.#220     // ext/mods/gameserver/network/SystemMessageId.SLOTS_FULL:Lext/mods/gameserver/network/SystemMessageId;
  #220 = NameAndType        #221:#209     // SLOTS_FULL:Lext/mods/gameserver/network/SystemMessageId;
  #221 = Utf8               SLOTS_FULL
  #222 = Methodref          #101.#223     // ext/mods/gameserver/model/actor/Player.getAdena:()I
  #223 = NameAndType        #224:#12      // getAdena:()I
  #224 = Utf8               getAdena
  #225 = Fieldref           #205.#226     // ext/mods/gameserver/network/SystemMessageId.YOU_NOT_ENOUGH_ADENA:Lext/mods/gameserver/network/SystemMessageId;
  #226 = NameAndType        #227:#209     // YOU_NOT_ENOUGH_ADENA:Lext/mods/gameserver/network/SystemMessageId;
  #227 = Utf8               YOU_NOT_ENOUGH_ADENA
  #228 = InterfaceMethodref #195.#229     // java/util/Map.get:(Ljava/lang/Object;)Ljava/lang/Object;
  #229 = NameAndType        #230:#231     // get:(Ljava/lang/Object;)Ljava/lang/Object;
  #230 = Utf8               get
  #231 = Utf8               (Ljava/lang/Object;)Ljava/lang/Object;
  #232 = Methodref          #148.#233     // ext/mods/gameserver/model/manor/SeedProduction.decreaseAmount:(I)Z
  #233 = NameAndType        #234:#203     // decreaseAmount:(I)Z
  #234 = Utf8               decreaseAmount
  #235 = Methodref          #101.#236     // ext/mods/gameserver/model/actor/Player.reduceAdena:(IZ)Z
  #236 = NameAndType        #237:#238     // reduceAdena:(IZ)Z
  #237 = Utf8               reduceAdena
  #238 = Utf8               (IZ)Z
  #239 = Methodref          #101.#240     // ext/mods/gameserver/model/actor/Player.addItem:(IIZ)Lext/mods/gameserver/model/item/instance/ItemInstance;
  #240 = NameAndType        #241:#242     // addItem:(IIZ)Lext/mods/gameserver/model/item/instance/ItemInstance;
  #241 = Utf8               addItem
  #242 = Utf8               (IIZ)Lext/mods/gameserver/model/item/instance/ItemInstance;
  #243 = Methodref          #244.#245     // ext/mods/gameserver/model/residence/castle/Castle.riseSeedIncome:(J)V
  #244 = Class              #246          // ext/mods/gameserver/model/residence/castle/Castle
  #245 = NameAndType        #247:#248     // riseSeedIncome:(J)V
  #246 = Utf8               ext/mods/gameserver/model/residence/castle/Castle
  #247 = Utf8               riseSeedIncome
  #248 = Utf8               (J)V
  #249 = Fieldref           #205.#250     // ext/mods/gameserver/network/SystemMessageId.S1_DISAPPEARED_ADENA:Lext/mods/gameserver/network/SystemMessageId;
  #250 = NameAndType        #251:#209     // S1_DISAPPEARED_ADENA:Lext/mods/gameserver/network/SystemMessageId;
  #251 = Utf8               S1_DISAPPEARED_ADENA
  #252 = Methodref          #211.#253     // ext/mods/gameserver/network/serverpackets/SystemMessage.addItemNumber:(I)Lext/mods/gameserver/network/serverpackets/SystemMessage;
  #253 = NameAndType        #254:#255     // addItemNumber:(I)Lext/mods/gameserver/network/serverpackets/SystemMessage;
  #254 = Utf8               addItemNumber
  #255 = Utf8               (I)Lext/mods/gameserver/network/serverpackets/SystemMessage;
  #256 = Methodref          #101.#78      // ext/mods/gameserver/model/actor/Player.sendPacket:(Lext/mods/gameserver/network/serverpackets/L2GameServerPacket;)V
  #257 = Utf8               BATCH_LENGTH
  #258 = Utf8               ConstantValue
  #259 = Integer            8
  #260 = Utf8               Signature
  #261 = Utf8               Ljava/util/List<Lext/mods/gameserver/model/holder/IntIntHolder;>;
  #262 = Utf8               Code
  #263 = Utf8               LineNumberTable
  #264 = Utf8               LocalVariableTable
  #265 = Utf8               this
  #266 = Utf8               Lext/mods/gameserver/network/clientpackets/RequestBuySeed;
  #267 = Utf8               readImpl
  #268 = Utf8               itemId
  #269 = Utf8               cnt
  #270 = Utf8               i
  #271 = Utf8               count
  #272 = Utf8               StackMapTable
  #273 = Utf8               runImpl
  #274 = Utf8               sp
  #275 = Utf8               Lext/mods/gameserver/model/manor/SeedProduction;
  #276 = Utf8               template
  #277 = Utf8               Lext/mods/gameserver/model/item/kind/Item;
  #278 = Utf8               ih
  #279 = Utf8               Lext/mods/gameserver/model/holder/IntIntHolder;
  #280 = Utf8               price
  #281 = Utf8               player
  #282 = Utf8               Lext/mods/gameserver/model/actor/Player;
  #283 = Utf8               manor
  #284 = Utf8               Lext/mods/gameserver/data/manager/CastleManorManager;
  #285 = Utf8               castle
  #286 = Utf8               Lext/mods/gameserver/model/residence/castle/Castle;
  #287 = Utf8               folk
  #288 = Utf8               Lext/mods/gameserver/model/actor/instance/Folk;
  #289 = Utf8               totalPrice
  #290 = Utf8               J
  #291 = Utf8               slots
  #292 = Utf8               totalWeight
  #293 = Utf8               _productInfo
  #294 = Utf8               Ljava/util/Map;
  #295 = Utf8               LocalVariableTypeTable
  #296 = Utf8               Ljava/util/Map<Ljava/lang/Integer;Lext/mods/gameserver/model/manor/SeedProduction;>;
  #297 = Utf8               SourceFile
  #298 = Utf8               RequestBuySeed.java
{
  public ext.mods.gameserver.network.clientpackets.RequestBuySeed();
    descriptor: ()V
    flags: (0x0001) ACC_PUBLIC
    Code:
      stack=1, locals=1, args_size=1
         0: aload_0
         1: invokespecial #1                  // Method ext/mods/gameserver/network/clientpackets/L2GameClientPacket."<init>":()V
         4: return
      LineNumberTable:
        line 41: 0
      LocalVariableTable:
        Start  Length  Slot  Name   Signature
            0       5     0  this   Lext/mods/gameserver/network/clientpackets/RequestBuySeed;

  protected void readImpl();
    descriptor: ()V
    flags: (0x0004) ACC_PROTECTED
    Code:
      stack=5, locals=5, args_size=1
         0: aload_0
         1: aload_0
         2: invokevirtual #7                  // Method readD:()I
         5: putfield      #13                 // Field _manorId:I
         8: aload_0
         9: invokevirtual #7                  // Method readD:()I
        12: istore_1
        13: iload_1
        14: ifle          38
        17: iload_1
        18: getstatic     #17                 // Field ext/mods/Config.MAX_ITEM_IN_PACKET:I
        21: if_icmpgt     38
        24: iload_1
        25: bipush        8
        27: imul
        28: aload_0
        29: getfield      #22                 // Field _buf:Ljava/nio/ByteBuffer;
        32: invokevirtual #26                 // Method java/nio/ByteBuffer.remaining:()I
        35: if_icmpeq     39
        38: return
        39: aload_0
        40: new           #31                 // class java/util/ArrayList
        43: dup
        44: iload_1
        45: invokespecial #33                 // Method java/util/ArrayList."<init>":(I)V
        48: putfield      #36                 // Field _items:Ljava/util/List;
        51: iconst_0
        52: istore_2
        53: iload_2
        54: iload_1
        55: if_icmpge     112
        58: aload_0
        59: invokevirtual #7                  // Method readD:()I
        62: istore_3
        63: aload_0
        64: invokevirtual #7                  // Method readD:()I
        67: istore        4
        69: iload         4
        71: iconst_1
        72: if_icmplt     80
        75: iload_3
        76: iconst_1
        77: if_icmpge     86
        80: aload_0
        81: aconst_null
        82: putfield      #36                 // Field _items:Ljava/util/List;
        85: return
        86: aload_0
        87: getfield      #36                 // Field _items:Ljava/util/List;
        90: new           #40                 // class ext/mods/gameserver/model/holder/IntIntHolder
        93: dup
        94: iload_3
        95: iload         4
        97: invokespecial #42                 // Method ext/mods/gameserver/model/holder/IntIntHolder."<init>":(II)V
       100: invokeinterface #45,  2           // InterfaceMethod java/util/List.add:(Ljava/lang/Object;)Z
       105: pop
       106: iinc          2, 1
       109: goto          53
       112: return
      LineNumberTable:
        line 51: 0
        line 53: 8
        line 54: 13
        line 55: 38
        line 57: 39
        line 58: 51
        line 60: 58
        line 61: 63
        line 63: 69
        line 65: 80
        line 66: 85
        line 69: 86
        line 58: 106
        line 71: 112
      LocalVariableTable:
        Start  Length  Slot  Name   Signature
           63      43     3 itemId   I
           69      37     4   cnt   I
           53      59     2     i   I
            0     113     0  this   Lext/mods/gameserver/network/clientpackets/RequestBuySeed;
           13     100     1 count   I
      StackMapTable: number_of_entries = 6
        frame_type = 252 /* append */
          offset_delta = 38
          locals = [ int ]
        frame_type = 0 /* same */
        frame_type = 252 /* append */
          offset_delta = 13
          locals = [ int ]
        frame_type = 253 /* append */
          offset_delta = 26
          locals = [ int, int ]
        frame_type = 5 /* same */
        frame_type = 248 /* chop */
          offset_delta = 25

  protected void runImpl();
    descriptor: ()V
    flags: (0x0004) ACC_PROTECTED
    Code:
      stack=4, locals=14, args_size=1
         0: aload_0
         1: invokevirtual #51                 // Method getClient:()Lext/mods/commons/mmocore/MMOClient;
         4: checkcast     #55                 // class ext/mods/gameserver/network/GameClient
         7: getstatic     #57                 // Field ext/mods/gameserver/enums/FloodProtector.MANOR:Lext/mods/gameserver/enums/FloodProtector;
        10: invokevirtual #63                 // Method ext/mods/gameserver/network/GameClient.performAction:(Lext/mods/gameserver/enums/FloodProtector;)Z
        13: ifne          17
        16: return
        17: aload_0
        18: invokevirtual #51                 // Method getClient:()Lext/mods/commons/mmocore/MMOClient;
        21: checkcast     #55                 // class ext/mods/gameserver/network/GameClient
        24: invokevirtual #67                 // Method ext/mods/gameserver/network/GameClient.getPlayer:()Lext/mods/gameserver/model/actor/Player;
        27: astore_1
        28: aload_1
        29: ifnonnull     33
        32: return
        33: aload_0
        34: getfield      #36                 // Field _items:Ljava/util/List;
        37: ifnonnull     48
        40: aload_0
        41: getstatic     #71                 // Field ext/mods/gameserver/network/serverpackets/ActionFailed.STATIC_PACKET:Lext/mods/gameserver/network/serverpackets/ActionFailed;
        44: invokevirtual #77                 // Method sendPacket:(Lext/mods/gameserver/network/serverpackets/L2GameServerPacket;)V
        47: return
        48: invokestatic  #81                 // Method ext/mods/gameserver/data/manager/CastleManorManager.getInstance:()Lext/mods/gameserver/data/manager/CastleManorManager;
        51: astore_2
        52: aload_2
        53: invokevirtual #87                 // Method ext/mods/gameserver/data/manager/CastleManorManager.isUnderMaintenance:()Z
        56: ifeq          67
        59: aload_0
        60: getstatic     #71                 // Field ext/mods/gameserver/network/serverpackets/ActionFailed.STATIC_PACKET:Lext/mods/gameserver/network/serverpackets/ActionFailed;
        63: invokevirtual #77                 // Method sendPacket:(Lext/mods/gameserver/network/serverpackets/L2GameServerPacket;)V
        66: return
        67: invokestatic  #91                 // Method ext/mods/gameserver/data/manager/CastleManager.getInstance:()Lext/mods/gameserver/data/manager/CastleManager;
        70: aload_0
        71: getfield      #13                 // Field _manorId:I
        74: invokevirtual #96                 // Method ext/mods/gameserver/data/manager/CastleManager.getCastleById:(I)Lext/mods/gameserver/model/residence/castle/Castle;
        77: astore_3
        78: aload_3
        79: ifnonnull     90
        82: aload_0
        83: getstatic     #71                 // Field ext/mods/gameserver/network/serverpackets/ActionFailed.STATIC_PACKET:Lext/mods/gameserver/network/serverpackets/ActionFailed;
        86: invokevirtual #77                 // Method sendPacket:(Lext/mods/gameserver/network/serverpackets/L2GameServerPacket;)V
        89: return
        90: aload_1
        91: invokevirtual #100                // Method ext/mods/gameserver/model/actor/Player.getCurrentFolk:()Lext/mods/gameserver/model/actor/instance/Folk;
        94: astore        4
        96: aload         4
        98: instanceof    #106                // class ext/mods/gameserver/model/actor/instance/ManorManagerNpc
       101: ifeq          125
       104: aload_1
       105: invokevirtual #108                // Method ext/mods/gameserver/model/actor/Player.getAI:()Lext/mods/gameserver/model/actor/ai/type/PlayerAI;
       108: aload         4
       110: invokevirtual #112                // Method ext/mods/gameserver/model/actor/ai/type/PlayerAI.canDoInteract:(Lext/mods/gameserver/model/WorldObject;)Z
       113: ifeq          125
       116: aload         4
       118: invokevirtual #118                // Method ext/mods/gameserver/model/actor/instance/Folk.getCastle:()Lext/mods/gameserver/model/residence/castle/Castle;
       121: aload_3
       122: if_acmpeq     133
       125: aload_0
       126: getstatic     #71                 // Field ext/mods/gameserver/network/serverpackets/ActionFailed.STATIC_PACKET:Lext/mods/gameserver/network/serverpackets/ActionFailed;
       129: invokevirtual #77                 // Method sendPacket:(Lext/mods/gameserver/network/serverpackets/L2GameServerPacket;)V
       132: return
       133: lconst_0
       134: lstore        5
       136: iconst_0
       137: istore        7
       139: iconst_0
       140: istore        8
       142: new           #124                // class java/util/HashMap
       145: dup
       146: invokespecial #126                // Method java/util/HashMap."<init>":()V
       149: astore        9
       151: aload_0
       152: getfield      #36                 // Field _items:Ljava/util/List;
       155: invokeinterface #127,  1          // InterfaceMethod java/util/List.iterator:()Ljava/util/Iterator;
       160: astore        10
       162: aload         10
       164: invokeinterface #131,  1          // InterfaceMethod java/util/Iterator.hasNext:()Z
       169: ifeq          373
       172: aload         10
       174: invokeinterface #136,  1          // InterfaceMethod java/util/Iterator.next:()Ljava/lang/Object;
       179: checkcast     #40                 // class ext/mods/gameserver/model/holder/IntIntHolder
       182: astore        11
       184: aload_2
       185: aload_0
       186: getfield      #13                 // Field _manorId:I
       189: aload         11
       191: invokevirtual #140                // Method ext/mods/gameserver/model/holder/IntIntHolder.getId:()I
       194: iconst_0
       195: invokevirtual #143                // Method ext/mods/gameserver/data/manager/CastleManorManager.getSeedProduct:(IIZ)Lext/mods/gameserver/model/manor/SeedProduction;
       198: astore        12
       200: aload         12
       202: ifnull        242
       205: aload         12
       207: invokevirtual #147                // Method ext/mods/gameserver/model/manor/SeedProduction.getPrice:()I
       210: ifle          242
       213: aload         12
       215: invokevirtual #152                // Method ext/mods/gameserver/model/manor/SeedProduction.getAmount:()I
       218: aload         11
       220: invokevirtual #155                // Method ext/mods/gameserver/model/holder/IntIntHolder.getValue:()I
       223: if_icmplt     242
       226: ldc           #160                // int 2147483647
       228: aload         11
       230: invokevirtual #155                // Method ext/mods/gameserver/model/holder/IntIntHolder.getValue:()I
       233: idiv
       234: aload         12
       236: invokevirtual #147                // Method ext/mods/gameserver/model/manor/SeedProduction.getPrice:()I
       239: if_icmpge     250
       242: aload_0
       243: getstatic     #71                 // Field ext/mods/gameserver/network/serverpackets/ActionFailed.STATIC_PACKET:Lext/mods/gameserver/network/serverpackets/ActionFailed;
       246: invokevirtual #77                 // Method sendPacket:(Lext/mods/gameserver/network/serverpackets/L2GameServerPacket;)V
       249: return
       250: lload         5
       252: aload         12
       254: invokevirtual #147                // Method ext/mods/gameserver/model/manor/SeedProduction.getPrice:()I
       257: aload         11
       259: invokevirtual #155                // Method ext/mods/gameserver/model/holder/IntIntHolder.getValue:()I
       262: imul
       263: i2l
       264: ladd
       265: lstore        5
       267: lload         5
       269: ldc2_w        #161                // long 2147483647l
       272: lcmp
       273: ifle          284
       276: aload_0
       277: getstatic     #71                 // Field ext/mods/gameserver/network/serverpackets/ActionFailed.STATIC_PACKET:Lext/mods/gameserver/network/serverpackets/ActionFailed;
       280: invokevirtual #77                 // Method sendPacket:(Lext/mods/gameserver/network/serverpackets/L2GameServerPacket;)V
       283: return
       284: invokestatic  #163                // Method ext/mods/gameserver/data/xml/ItemData.getInstance:()Lext/mods/gameserver/data/xml/ItemData;
       287: aload         11
       289: invokevirtual #140                // Method ext/mods/gameserver/model/holder/IntIntHolder.getId:()I
       292: invokevirtual #168                // Method ext/mods/gameserver/data/xml/ItemData.getTemplate:(I)Lext/mods/gameserver/model/item/kind/Item;
       295: astore        13
       297: iload         8
       299: aload         11
       301: invokevirtual #155                // Method ext/mods/gameserver/model/holder/IntIntHolder.getValue:()I
       304: aload         13
       306: invokevirtual #172                // Method ext/mods/gameserver/model/item/kind/Item.getWeight:()I
       309: imul
       310: iadd
       311: istore        8
       313: aload         13
       315: invokevirtual #177                // Method ext/mods/gameserver/model/item/kind/Item.isStackable:()Z
       318: ifne          334
       321: iload         7
       323: aload         11
       325: invokevirtual #155                // Method ext/mods/gameserver/model/holder/IntIntHolder.getValue:()I
       328: iadd
       329: istore        7
       331: goto          352
       334: aload_1
       335: invokevirtual #180                // Method ext/mods/gameserver/model/actor/Player.getInventory:()Lext/mods/gameserver/model/itemcontainer/PcInventory;
       338: aload         11
       340: invokevirtual #140                // Method ext/mods/gameserver/model/holder/IntIntHolder.getId:()I
       343: invokevirtual #184                // Method ext/mods/gameserver/model/itemcontainer/PcInventory.getItemByItemId:(I)Lext/mods/gameserver/model/item/instance/ItemInstance;
       346: ifnonnull     352
       349: iinc          7, 1
       352: aload         9
       354: aload         11
       356: invokevirtual #140                // Method ext/mods/gameserver/model/holder/IntIntHolder.getId:()I
       359: invokestatic  #190                // Method java/lang/Integer.valueOf:(I)Ljava/lang/Integer;
       362: aload         12
       364: invokeinterface #194,  3          // InterfaceMethod java/util/Map.put:(Ljava/lang/Object;Ljava/lang/Object;)Ljava/lang/Object;
       369: pop
       370: goto          162
       373: aload_1
       374: invokevirtual #180                // Method ext/mods/gameserver/model/actor/Player.getInventory:()Lext/mods/gameserver/model/itemcontainer/PcInventory;
       377: iload         8
       379: invokevirtual #200                // Method ext/mods/gameserver/model/itemcontainer/PcInventory.validateWeight:(I)Z
       382: ifne          396
       385: aload_0
       386: getstatic     #204                // Field ext/mods/gameserver/network/SystemMessageId.WEIGHT_LIMIT_EXCEEDED:Lext/mods/gameserver/network/SystemMessageId;
       389: invokestatic  #210                // Method ext/mods/gameserver/network/serverpackets/SystemMessage.getSystemMessage:(Lext/mods/gameserver/network/SystemMessageId;)Lext/mods/gameserver/network/serverpackets/SystemMessage;
       392: invokevirtual #77                 // Method sendPacket:(Lext/mods/gameserver/network/serverpackets/L2GameServerPacket;)V
       395: return
       396: aload_1
       397: invokevirtual #180                // Method ext/mods/gameserver/model/actor/Player.getInventory:()Lext/mods/gameserver/model/itemcontainer/PcInventory;
       400: iload         7
       402: invokevirtual #216                // Method ext/mods/gameserver/model/itemcontainer/PcInventory.validateCapacity:(I)Z
       405: ifne          419
       408: aload_0
       409: getstatic     #219                // Field ext/mods/gameserver/network/SystemMessageId.SLOTS_FULL:Lext/mods/gameserver/network/SystemMessageId;
       412: invokestatic  #210                // Method ext/mods/gameserver/network/serverpackets/SystemMessage.getSystemMessage:(Lext/mods/gameserver/network/SystemMessageId;)Lext/mods/gameserver/network/serverpackets/SystemMessage;
       415: invokevirtual #77                 // Method sendPacket:(Lext/mods/gameserver/network/serverpackets/L2GameServerPacket;)V
       418: return
       419: lload         5
       421: lconst_0
       422: lcmp
       423: iflt          437
       426: aload_1
       427: invokevirtual #222                // Method ext/mods/gameserver/model/actor/Player.getAdena:()I
       430: i2l
       431: lload         5
       433: lcmp
       434: ifge          448
       437: aload_0
       438: getstatic     #225                // Field ext/mods/gameserver/network/SystemMessageId.YOU_NOT_ENOUGH_ADENA:Lext/mods/gameserver/network/SystemMessageId;
       441: invokestatic  #210                // Method ext/mods/gameserver/network/serverpackets/SystemMessage.getSystemMessage:(Lext/mods/gameserver/network/SystemMessageId;)Lext/mods/gameserver/network/serverpackets/SystemMessage;
       444: invokevirtual #77                 // Method sendPacket:(Lext/mods/gameserver/network/serverpackets/L2GameServerPacket;)V
       447: return
       448: aload_0
       449: getfield      #36                 // Field _items:Ljava/util/List;
       452: invokeinterface #127,  1          // InterfaceMethod java/util/List.iterator:()Ljava/util/Iterator;
       457: astore        10
       459: aload         10
       461: invokeinterface #131,  1          // InterfaceMethod java/util/Iterator.hasNext:()Z
       466: ifeq          567
       469: aload         10
       471: invokeinterface #136,  1          // InterfaceMethod java/util/Iterator.next:()Ljava/lang/Object;
       476: checkcast     #40                 // class ext/mods/gameserver/model/holder/IntIntHolder
       479: astore        11
       481: aload         9
       483: aload         11
       485: invokevirtual #140                // Method ext/mods/gameserver/model/holder/IntIntHolder.getId:()I
       488: invokestatic  #190                // Method java/lang/Integer.valueOf:(I)Ljava/lang/Integer;
       491: invokeinterface #228,  2          // InterfaceMethod java/util/Map.get:(Ljava/lang/Object;)Ljava/lang/Object;
       496: checkcast     #148                // class ext/mods/gameserver/model/manor/SeedProduction
       499: astore        12
       501: aload         12
       503: invokevirtual #147                // Method ext/mods/gameserver/model/manor/SeedProduction.getPrice:()I
       506: aload         11
       508: invokevirtual #155                // Method ext/mods/gameserver/model/holder/IntIntHolder.getValue:()I
       511: imul
       512: istore        13
       514: aload         12
       516: aload         11
       518: invokevirtual #155                // Method ext/mods/gameserver/model/holder/IntIntHolder.getValue:()I
       521: invokevirtual #232                // Method ext/mods/gameserver/model/manor/SeedProduction.decreaseAmount:(I)Z
       524: ifeq          537
       527: aload_1
       528: iload         13
       530: iconst_0
       531: invokevirtual #235                // Method ext/mods/gameserver/model/actor/Player.reduceAdena:(IZ)Z
       534: ifne          548
       537: lload         5
       539: iload         13
       541: i2l
       542: lsub
       543: lstore        5
       545: goto          459
       548: aload_1
       549: aload         11
       551: invokevirtual #140                // Method ext/mods/gameserver/model/holder/IntIntHolder.getId:()I
       554: aload         11
       556: invokevirtual #155                // Method ext/mods/gameserver/model/holder/IntIntHolder.getValue:()I
       559: iconst_1
       560: invokevirtual #239                // Method ext/mods/gameserver/model/actor/Player.addItem:(IIZ)Lext/mods/gameserver/model/item/instance/ItemInstance;
       563: pop
       564: goto          459
       567: lload         5
       569: lconst_0
       570: lcmp
       571: ifle          596
       574: aload_3
       575: lload         5
       577: invokevirtual #243                // Method ext/mods/gameserver/model/residence/castle/Castle.riseSeedIncome:(J)V
       580: aload_1
       581: getstatic     #249                // Field ext/mods/gameserver/network/SystemMessageId.S1_DISAPPEARED_ADENA:Lext/mods/gameserver/network/SystemMessageId;
       584: invokestatic  #210                // Method ext/mods/gameserver/network/serverpackets/SystemMessage.getSystemMessage:(Lext/mods/gameserver/network/SystemMessageId;)Lext/mods/gameserver/network/serverpackets/SystemMessage;
       587: lload         5
       589: l2i
       590: invokevirtual #252                // Method ext/mods/gameserver/network/serverpackets/SystemMessage.addItemNumber:(I)Lext/mods/gameserver/network/serverpackets/SystemMessage;
       593: invokevirtual #256                // Method ext/mods/gameserver/model/actor/Player.sendPacket:(Lext/mods/gameserver/network/serverpackets/L2GameServerPacket;)V
       596: return
      LineNumberTable:
        line 76: 0
        line 77: 16
        line 79: 17
        line 80: 28
        line 81: 32
        line 83: 33
        line 85: 40
        line 86: 47
        line 89: 48
        line 90: 52
        line 92: 59
        line 93: 66
        line 96: 67
        line 97: 78
        line 99: 82
        line 100: 89
        line 103: 90
        line 104: 96
        line 106: 125
        line 107: 132
        line 110: 133
        line 111: 136
        line 112: 139
        line 114: 142
        line 116: 151
        line 118: 184
        line 119: 200
        line 121: 242
        line 122: 249
        line 125: 250
        line 126: 267
        line 128: 276
        line 129: 283
        line 132: 284
        line 133: 297
        line 135: 313
        line 136: 321
        line 137: 334
        line 138: 349
        line 140: 352
        line 141: 370
        line 143: 373
        line 145: 385
        line 146: 395
        line 149: 396
        line 151: 408
        line 152: 418
        line 155: 419
        line 157: 437
        line 158: 447
        line 161: 448
        line 163: 481
        line 164: 501
        line 166: 514
        line 168: 537
        line 169: 545
        line 172: 548
        line 173: 564
        line 175: 567
        line 177: 574
        line 178: 580
        line 180: 596
      LocalVariableTable:
        Start  Length  Slot  Name   Signature
          200     170    12    sp   Lext/mods/gameserver/model/manor/SeedProduction;
          297      73    13 template   Lext/mods/gameserver/model/item/kind/Item;
          184     186    11    ih   Lext/mods/gameserver/model/holder/IntIntHolder;
          501      63    12    sp   Lext/mods/gameserver/model/manor/SeedProduction;
          514      50    13 price   I
          481      83    11     i   Lext/mods/gameserver/model/holder/IntIntHolder;
            0     597     0  this   Lext/mods/gameserver/network/clientpackets/RequestBuySeed;
           28     569     1 player   Lext/mods/gameserver/model/actor/Player;
           52     545     2 manor   Lext/mods/gameserver/data/manager/CastleManorManager;
           78     519     3 castle   Lext/mods/gameserver/model/residence/castle/Castle;
           96     501     4  folk   Lext/mods/gameserver/model/actor/instance/Folk;
          136     461     5 totalPrice   J
          139     458     7 slots   I
          142     455     8 totalWeight   I
          151     446     9 _productInfo   Ljava/util/Map;
      LocalVariableTypeTable:
        Start  Length  Slot  Name   Signature
          151     446     9 _productInfo   Ljava/util/Map<Ljava/lang/Integer;Lext/mods/gameserver/model/manor/SeedProduction;>;
      StackMapTable: number_of_entries = 23
        frame_type = 17 /* same */
        frame_type = 252 /* append */
          offset_delta = 15
          locals = [ class ext/mods/gameserver/model/actor/Player ]
        frame_type = 14 /* same */
        frame_type = 252 /* append */
          offset_delta = 18
          locals = [ class ext/mods/gameserver/data/manager/CastleManorManager ]
        frame_type = 252 /* append */
          offset_delta = 22
          locals = [ class ext/mods/gameserver/model/residence/castle/Castle ]
        frame_type = 252 /* append */
          offset_delta = 34
          locals = [ class ext/mods/gameserver/model/actor/instance/Folk ]
        frame_type = 7 /* same */
        frame_type = 255 /* full_frame */
          offset_delta = 28
          locals = [ class ext/mods/gameserver/network/clientpackets/RequestBuySeed, class ext/mods/gameserver/model/actor/Player, class ext/mods/gameserver/data/manager/CastleManorManager, class ext/mods/gameserver/model/residence/castle/Castle, class ext/mods/gameserver/model/actor/instance/Folk, long, int, int, class java/util/Map, class java/util/Iterator ]
          stack = []
        frame_type = 253 /* append */
          offset_delta = 79
          locals = [ class ext/mods/gameserver/model/holder/IntIntHolder, class ext/mods/gameserver/model/manor/SeedProduction ]
        frame_type = 7 /* same */
        frame_type = 33 /* same */
        frame_type = 252 /* append */
          offset_delta = 49
          locals = [ class ext/mods/gameserver/model/item/kind/Item ]
        frame_type = 17 /* same */
        frame_type = 255 /* full_frame */
          offset_delta = 20
          locals = [ class ext/mods/gameserver/network/clientpackets/RequestBuySeed, class ext/mods/gameserver/model/actor/Player, class ext/mods/gameserver/data/manager/CastleManorManager, class ext/mods/gameserver/model/residence/castle/Castle, class ext/mods/gameserver/model/actor/instance/Folk, long, int, int, class java/util/Map ]
          stack = []
        frame_type = 22 /* same */
        frame_type = 22 /* same */
        frame_type = 17 /* same */
        frame_type = 10 /* same */
        frame_type = 252 /* append */
          offset_delta = 10
          locals = [ class java/util/Iterator ]
        frame_type = 254 /* append */
          offset_delta = 77
          locals = [ class ext/mods/gameserver/model/holder/IntIntHolder, class ext/mods/gameserver/model/manor/SeedProduction, int ]
        frame_type = 10 /* same */
        frame_type = 255 /* full_frame */
          offset_delta = 18
          locals = [ class ext/mods/gameserver/network/clientpackets/RequestBuySeed, class ext/mods/gameserver/model/actor/Player, class ext/mods/gameserver/data/manager/CastleManorManager, class ext/mods/gameserver/model/residence/castle/Castle, class ext/mods/gameserver/model/actor/instance/Folk, long, int, int, class java/util/Map ]
          stack = []
        frame_type = 28 /* same */
}
SourceFile: "RequestBuySeed.java"
