// Bytecode for: ext.mods.gameserver.enums.petitions.PetitionType
// File: ext\mods\gameserver\enums\petitions\PetitionType.class

Classfile /c:/Users/User/Desktop/BrProject/bin/main/ext/mods/gameserver/enums/petitions/PetitionType.class
  Last modified 9 de jul de 2026; size 1736 bytes
  MD5 checksum bf3f92b913ac49c1619270dda17b8a66
  Compiled from "PetitionType.java"
public final class ext.mods.gameserver.enums.petitions.PetitionType extends java.lang.Enum<ext.mods.gameserver.enums.petitions.PetitionType>
  minor version: 0
  major version: 69
  flags: (0x4031) ACC_PUBLIC, ACC_FINAL, ACC_SUPER, ACC_ENUM
  this_class: #1                          // ext/mods/gameserver/enums/petitions/PetitionType
  super_class: #44                        // java/lang/Enum
  interfaces: 0, fields: 12, methods: 5, attributes: 2
Constant pool:
   #1 = Class              #2             // ext/mods/gameserver/enums/petitions/PetitionType
   #2 = Utf8               ext/mods/gameserver/enums/petitions/PetitionType
   #3 = Fieldref           #1.#4          // ext/mods/gameserver/enums/petitions/PetitionType.NONE:Lext/mods/gameserver/enums/petitions/PetitionType;
   #4 = NameAndType        #5:#6          // NONE:Lext/mods/gameserver/enums/petitions/PetitionType;
   #5 = Utf8               NONE
   #6 = Utf8               Lext/mods/gameserver/enums/petitions/PetitionType;
   #7 = Fieldref           #1.#8          // ext/mods/gameserver/enums/petitions/PetitionType.IMMOBILITY:Lext/mods/gameserver/enums/petitions/PetitionType;
   #8 = NameAndType        #9:#6          // IMMOBILITY:Lext/mods/gameserver/enums/petitions/PetitionType;
   #9 = Utf8               IMMOBILITY
  #10 = Fieldref           #1.#11         // ext/mods/gameserver/enums/petitions/PetitionType.RECOVERY_RELATED:Lext/mods/gameserver/enums/petitions/PetitionType;
  #11 = NameAndType        #12:#6         // RECOVERY_RELATED:Lext/mods/gameserver/enums/petitions/PetitionType;
  #12 = Utf8               RECOVERY_RELATED
  #13 = Fieldref           #1.#14         // ext/mods/gameserver/enums/petitions/PetitionType.BUG_REPORT:Lext/mods/gameserver/enums/petitions/PetitionType;
  #14 = NameAndType        #15:#6         // BUG_REPORT:Lext/mods/gameserver/enums/petitions/PetitionType;
  #15 = Utf8               BUG_REPORT
  #16 = Fieldref           #1.#17         // ext/mods/gameserver/enums/petitions/PetitionType.QUEST_RELATED:Lext/mods/gameserver/enums/petitions/PetitionType;
  #17 = NameAndType        #18:#6         // QUEST_RELATED:Lext/mods/gameserver/enums/petitions/PetitionType;
  #18 = Utf8               QUEST_RELATED
  #19 = Fieldref           #1.#20         // ext/mods/gameserver/enums/petitions/PetitionType.BAD_USER:Lext/mods/gameserver/enums/petitions/PetitionType;
  #20 = NameAndType        #21:#6         // BAD_USER:Lext/mods/gameserver/enums/petitions/PetitionType;
  #21 = Utf8               BAD_USER
  #22 = Fieldref           #1.#23         // ext/mods/gameserver/enums/petitions/PetitionType.SUGGESTIONS:Lext/mods/gameserver/enums/petitions/PetitionType;
  #23 = NameAndType        #24:#6         // SUGGESTIONS:Lext/mods/gameserver/enums/petitions/PetitionType;
  #24 = Utf8               SUGGESTIONS
  #25 = Fieldref           #1.#26         // ext/mods/gameserver/enums/petitions/PetitionType.GAME_TIP:Lext/mods/gameserver/enums/petitions/PetitionType;
  #26 = NameAndType        #27:#6         // GAME_TIP:Lext/mods/gameserver/enums/petitions/PetitionType;
  #27 = Utf8               GAME_TIP
  #28 = Fieldref           #1.#29         // ext/mods/gameserver/enums/petitions/PetitionType.OPERATION_RELATED:Lext/mods/gameserver/enums/petitions/PetitionType;
  #29 = NameAndType        #30:#6         // OPERATION_RELATED:Lext/mods/gameserver/enums/petitions/PetitionType;
  #30 = Utf8               OPERATION_RELATED
  #31 = Fieldref           #1.#32         // ext/mods/gameserver/enums/petitions/PetitionType.OTHER:Lext/mods/gameserver/enums/petitions/PetitionType;
  #32 = NameAndType        #33:#6         // OTHER:Lext/mods/gameserver/enums/petitions/PetitionType;
  #33 = Utf8               OTHER
  #34 = Fieldref           #1.#35         // ext/mods/gameserver/enums/petitions/PetitionType.$VALUES:[Lext/mods/gameserver/enums/petitions/PetitionType;
  #35 = NameAndType        #36:#37        // $VALUES:[Lext/mods/gameserver/enums/petitions/PetitionType;
  #36 = Utf8               $VALUES
  #37 = Utf8               [Lext/mods/gameserver/enums/petitions/PetitionType;
  #38 = Methodref          #39.#40        // "[Lext/mods/gameserver/enums/petitions/PetitionType;".clone:()Ljava/lang/Object;
  #39 = Class              #37            // "[Lext/mods/gameserver/enums/petitions/PetitionType;"
  #40 = NameAndType        #41:#42        // clone:()Ljava/lang/Object;
  #41 = Utf8               clone
  #42 = Utf8               ()Ljava/lang/Object;
  #43 = Methodref          #44.#45        // java/lang/Enum.valueOf:(Ljava/lang/Class;Ljava/lang/String;)Ljava/lang/Enum;
  #44 = Class              #46            // java/lang/Enum
  #45 = NameAndType        #47:#48        // valueOf:(Ljava/lang/Class;Ljava/lang/String;)Ljava/lang/Enum;
  #46 = Utf8               java/lang/Enum
  #47 = Utf8               valueOf
  #48 = Utf8               (Ljava/lang/Class;Ljava/lang/String;)Ljava/lang/Enum;
  #49 = Methodref          #44.#50        // java/lang/Enum."<init>":(Ljava/lang/String;I)V
  #50 = NameAndType        #51:#52        // "<init>":(Ljava/lang/String;I)V
  #51 = Utf8               <init>
  #52 = Utf8               (Ljava/lang/String;I)V
  #53 = String             #5             // NONE
  #54 = Methodref          #1.#50         // ext/mods/gameserver/enums/petitions/PetitionType."<init>":(Ljava/lang/String;I)V
  #55 = String             #9             // IMMOBILITY
  #56 = String             #12            // RECOVERY_RELATED
  #57 = String             #15            // BUG_REPORT
  #58 = String             #18            // QUEST_RELATED
  #59 = String             #21            // BAD_USER
  #60 = String             #24            // SUGGESTIONS
  #61 = String             #27            // GAME_TIP
  #62 = String             #30            // OPERATION_RELATED
  #63 = String             #33            // OTHER
  #64 = Methodref          #1.#65         // ext/mods/gameserver/enums/petitions/PetitionType.$values:()[Lext/mods/gameserver/enums/petitions/PetitionType;
  #65 = NameAndType        #66:#67        // $values:()[Lext/mods/gameserver/enums/petitions/PetitionType;
  #66 = Utf8               $values
  #67 = Utf8               ()[Lext/mods/gameserver/enums/petitions/PetitionType;
  #68 = Methodref          #1.#69         // ext/mods/gameserver/enums/petitions/PetitionType.values:()[Lext/mods/gameserver/enums/petitions/PetitionType;
  #69 = NameAndType        #70:#67        // values:()[Lext/mods/gameserver/enums/petitions/PetitionType;
  #70 = Utf8               values
  #71 = Fieldref           #1.#72         // ext/mods/gameserver/enums/petitions/PetitionType.VALUES:[Lext/mods/gameserver/enums/petitions/PetitionType;
  #72 = NameAndType        #73:#37        // VALUES:[Lext/mods/gameserver/enums/petitions/PetitionType;
  #73 = Utf8               VALUES
  #74 = Utf8               Code
  #75 = Utf8               LineNumberTable
  #76 = Utf8               (Ljava/lang/String;)Lext/mods/gameserver/enums/petitions/PetitionType;
  #77 = Utf8               LocalVariableTable
  #78 = Utf8               name
  #79 = Utf8               Ljava/lang/String;
  #80 = Utf8               MethodParameters
  #81 = Utf8               this
  #82 = Utf8               Signature
  #83 = Utf8               ()V
  #84 = Utf8               <clinit>
  #85 = Utf8               Ljava/lang/Enum<Lext/mods/gameserver/enums/petitions/PetitionType;>;
  #86 = Utf8               SourceFile
  #87 = Utf8               PetitionType.java
{
  public static final ext.mods.gameserver.enums.petitions.PetitionType NONE;
    descriptor: Lext/mods/gameserver/enums/petitions/PetitionType;
    flags: (0x4019) ACC_PUBLIC, ACC_STATIC, ACC_FINAL, ACC_ENUM

  public static final ext.mods.gameserver.enums.petitions.PetitionType IMMOBILITY;
    descriptor: Lext/mods/gameserver/enums/petitions/PetitionType;
    flags: (0x4019) ACC_PUBLIC, ACC_STATIC, ACC_FINAL, ACC_ENUM

  public static final ext.mods.gameserver.enums.petitions.PetitionType RECOVERY_RELATED;
    descriptor: Lext/mods/gameserver/enums/petitions/PetitionType;
    flags: (0x4019) ACC_PUBLIC, ACC_STATIC, ACC_FINAL, ACC_ENUM

  public static final ext.mods.gameserver.enums.petitions.PetitionType BUG_REPORT;
    descriptor: Lext/mods/gameserver/enums/petitions/PetitionType;
    flags: (0x4019) ACC_PUBLIC, ACC_STATIC, ACC_FINAL, ACC_ENUM

  public static final ext.mods.gameserver.enums.petitions.PetitionType QUEST_RELATED;
    descriptor: Lext/mods/gameserver/enums/petitions/PetitionType;
    flags: (0x4019) ACC_PUBLIC, ACC_STATIC, ACC_FINAL, ACC_ENUM

  public static final ext.mods.gameserver.enums.petitions.PetitionType BAD_USER;
    descriptor: Lext/mods/gameserver/enums/petitions/PetitionType;
    flags: (0x4019) ACC_PUBLIC, ACC_STATIC, ACC_FINAL, ACC_ENUM

  public static final ext.mods.gameserver.enums.petitions.PetitionType SUGGESTIONS;
    descriptor: Lext/mods/gameserver/enums/petitions/PetitionType;
    flags: (0x4019) ACC_PUBLIC, ACC_STATIC, ACC_FINAL, ACC_ENUM

  public static final ext.mods.gameserver.enums.petitions.PetitionType GAME_TIP;
    descriptor: Lext/mods/gameserver/enums/petitions/PetitionType;
    flags: (0x4019) ACC_PUBLIC, ACC_STATIC, ACC_FINAL, ACC_ENUM

  public static final ext.mods.gameserver.enums.petitions.PetitionType OPERATION_RELATED;
    descriptor: Lext/mods/gameserver/enums/petitions/PetitionType;
    flags: (0x4019) ACC_PUBLIC, ACC_STATIC, ACC_FINAL, ACC_ENUM

  public static final ext.mods.gameserver.enums.petitions.PetitionType OTHER;
    descriptor: Lext/mods/gameserver/enums/petitions/PetitionType;
    flags: (0x4019) ACC_PUBLIC, ACC_STATIC, ACC_FINAL, ACC_ENUM

  public static final ext.mods.gameserver.enums.petitions.PetitionType[] VALUES;
    descriptor: [Lext/mods/gameserver/enums/petitions/PetitionType;
    flags: (0x0019) ACC_PUBLIC, ACC_STATIC, ACC_FINAL

  public static ext.mods.gameserver.enums.petitions.PetitionType[] values();
    descriptor: ()[Lext/mods/gameserver/enums/petitions/PetitionType;
    flags: (0x0009) ACC_PUBLIC, ACC_STATIC
    Code:
      stack=1, locals=0, args_size=0
         0: getstatic     #34                 // Field $VALUES:[Lext/mods/gameserver/enums/petitions/PetitionType;
         3: invokevirtual #38                 // Method "[Lext/mods/gameserver/enums/petitions/PetitionType;".clone:()Ljava/lang/Object;
         6: checkcast     #39                 // class "[Lext/mods/gameserver/enums/petitions/PetitionType;"
         9: areturn
      LineNumberTable:
        line 20: 0

  public static ext.mods.gameserver.enums.petitions.PetitionType valueOf(java.lang.String);
    descriptor: (Ljava/lang/String;)Lext/mods/gameserver/enums/petitions/PetitionType;
    flags: (0x0009) ACC_PUBLIC, ACC_STATIC
    Code:
      stack=2, locals=1, args_size=1
         0: ldc           #1                  // class ext/mods/gameserver/enums/petitions/PetitionType
         2: aload_0
         3: invokestatic  #43                 // Method java/lang/Enum.valueOf:(Ljava/lang/Class;Ljava/lang/String;)Ljava/lang/Enum;
         6: checkcast     #1                  // class ext/mods/gameserver/enums/petitions/PetitionType
         9: areturn
      LineNumberTable:
        line 20: 0
      LocalVariableTable:
        Start  Length  Slot  Name   Signature
            0      10     0  name   Ljava/lang/String;
    MethodParameters:
      Name                           Flags
      <no name>                      mandated

  static {};
    descriptor: ()V
    flags: (0x0008) ACC_STATIC
    Code:
      stack=4, locals=0, args_size=0
         0: new           #1                  // class ext/mods/gameserver/enums/petitions/PetitionType
         3: dup
         4: ldc           #53                 // String NONE
         6: iconst_0
         7: invokespecial #54                 // Method "<init>":(Ljava/lang/String;I)V
        10: putstatic     #3                  // Field NONE:Lext/mods/gameserver/enums/petitions/PetitionType;
        13: new           #1                  // class ext/mods/gameserver/enums/petitions/PetitionType
        16: dup
        17: ldc           #55                 // String IMMOBILITY
        19: iconst_1
        20: invokespecial #54                 // Method "<init>":(Ljava/lang/String;I)V
        23: putstatic     #7                  // Field IMMOBILITY:Lext/mods/gameserver/enums/petitions/PetitionType;
        26: new           #1                  // class ext/mods/gameserver/enums/petitions/PetitionType
        29: dup
        30: ldc           #56                 // String RECOVERY_RELATED
        32: iconst_2
        33: invokespecial #54                 // Method "<init>":(Ljava/lang/String;I)V
        36: putstatic     #10                 // Field RECOVERY_RELATED:Lext/mods/gameserver/enums/petitions/PetitionType;
        39: new           #1                  // class ext/mods/gameserver/enums/petitions/PetitionType
        42: dup
        43: ldc           #57                 // String BUG_REPORT
        45: iconst_3
        46: invokespecial #54                 // Method "<init>":(Ljava/lang/String;I)V
        49: putstatic     #13                 // Field BUG_REPORT:Lext/mods/gameserver/enums/petitions/PetitionType;
        52: new           #1                  // class ext/mods/gameserver/enums/petitions/PetitionType
        55: dup
        56: ldc           #58                 // String QUEST_RELATED
        58: iconst_4
        59: invokespecial #54                 // Method "<init>":(Ljava/lang/String;I)V
        62: putstatic     #16                 // Field QUEST_RELATED:Lext/mods/gameserver/enums/petitions/PetitionType;
        65: new           #1                  // class ext/mods/gameserver/enums/petitions/PetitionType
        68: dup
        69: ldc           #59                 // String BAD_USER
        71: iconst_5
        72: invokespecial #54                 // Method "<init>":(Ljava/lang/String;I)V
        75: putstatic     #19                 // Field BAD_USER:Lext/mods/gameserver/enums/petitions/PetitionType;
        78: new           #1                  // class ext/mods/gameserver/enums/petitions/PetitionType
        81: dup
        82: ldc           #60                 // String SUGGESTIONS
        84: bipush        6
        86: invokespecial #54                 // Method "<init>":(Ljava/lang/String;I)V
        89: putstatic     #22                 // Field SUGGESTIONS:Lext/mods/gameserver/enums/petitions/PetitionType;
        92: new           #1                  // class ext/mods/gameserver/enums/petitions/PetitionType
        95: dup
        96: ldc           #61                 // String GAME_TIP
        98: bipush        7
       100: invokespecial #54                 // Method "<init>":(Ljava/lang/String;I)V
       103: putstatic     #25                 // Field GAME_TIP:Lext/mods/gameserver/enums/petitions/PetitionType;
       106: new           #1                  // class ext/mods/gameserver/enums/petitions/PetitionType
       109: dup
       110: ldc           #62                 // String OPERATION_RELATED
       112: bipush        8
       114: invokespecial #54                 // Method "<init>":(Ljava/lang/String;I)V
       117: putstatic     #28                 // Field OPERATION_RELATED:Lext/mods/gameserver/enums/petitions/PetitionType;
       120: new           #1                  // class ext/mods/gameserver/enums/petitions/PetitionType
       123: dup
       124: ldc           #63                 // String OTHER
       126: bipush        9
       128: invokespecial #54                 // Method "<init>":(Ljava/lang/String;I)V
       131: putstatic     #31                 // Field OTHER:Lext/mods/gameserver/enums/petitions/PetitionType;
       134: invokestatic  #64                 // Method $values:()[Lext/mods/gameserver/enums/petitions/PetitionType;
       137: putstatic     #34                 // Field $VALUES:[Lext/mods/gameserver/enums/petitions/PetitionType;
       140: invokestatic  #68                 // Method values:()[Lext/mods/gameserver/enums/petitions/PetitionType;
       143: putstatic     #71                 // Field VALUES:[Lext/mods/gameserver/enums/petitions/PetitionType;
       146: return
      LineNumberTable:
        line 22: 0
        line 23: 13
        line 24: 26
        line 25: 39
        line 26: 52
        line 27: 65
        line 28: 78
        line 29: 92
        line 30: 106
        line 31: 120
        line 20: 134
        line 33: 140
}
Signature: #85                          // Ljava/lang/Enum<Lext/mods/gameserver/enums/petitions/PetitionType;>;
SourceFile: "PetitionType.java"
