// Bytecode for: ext.mods.gameserver.enums.petitions.PetitionRate
// File: ext\mods\gameserver\enums\petitions\PetitionRate.class

Classfile /c:/Users/User/Desktop/BrProject/bin/main/ext/mods/gameserver/enums/petitions/PetitionRate.class
  Last modified 9 de jul de 2026; size 1716 bytes
  MD5 checksum da3dbfcf8f355eb7d529da862fc037a3
  Compiled from "PetitionRate.java"
public final class ext.mods.gameserver.enums.petitions.PetitionRate extends java.lang.Enum<ext.mods.gameserver.enums.petitions.PetitionRate>
  minor version: 0
  major version: 69
  flags: (0x4031) ACC_PUBLIC, ACC_FINAL, ACC_SUPER, ACC_ENUM
  this_class: #1                          // ext/mods/gameserver/enums/petitions/PetitionRate
  super_class: #29                        // java/lang/Enum
  interfaces: 0, fields: 8, methods: 6, attributes: 2
Constant pool:
   #1 = Class              #2             // ext/mods/gameserver/enums/petitions/PetitionRate
   #2 = Utf8               ext/mods/gameserver/enums/petitions/PetitionRate
   #3 = Fieldref           #1.#4          // ext/mods/gameserver/enums/petitions/PetitionRate.VERY_GOOD:Lext/mods/gameserver/enums/petitions/PetitionRate;
   #4 = NameAndType        #5:#6          // VERY_GOOD:Lext/mods/gameserver/enums/petitions/PetitionRate;
   #5 = Utf8               VERY_GOOD
   #6 = Utf8               Lext/mods/gameserver/enums/petitions/PetitionRate;
   #7 = Fieldref           #1.#8          // ext/mods/gameserver/enums/petitions/PetitionRate.GOOD:Lext/mods/gameserver/enums/petitions/PetitionRate;
   #8 = NameAndType        #9:#6          // GOOD:Lext/mods/gameserver/enums/petitions/PetitionRate;
   #9 = Utf8               GOOD
  #10 = Fieldref           #1.#11         // ext/mods/gameserver/enums/petitions/PetitionRate.FAIR:Lext/mods/gameserver/enums/petitions/PetitionRate;
  #11 = NameAndType        #12:#6         // FAIR:Lext/mods/gameserver/enums/petitions/PetitionRate;
  #12 = Utf8               FAIR
  #13 = Fieldref           #1.#14         // ext/mods/gameserver/enums/petitions/PetitionRate.POOR:Lext/mods/gameserver/enums/petitions/PetitionRate;
  #14 = NameAndType        #15:#6         // POOR:Lext/mods/gameserver/enums/petitions/PetitionRate;
  #15 = Utf8               POOR
  #16 = Fieldref           #1.#17         // ext/mods/gameserver/enums/petitions/PetitionRate.VERY_POOR:Lext/mods/gameserver/enums/petitions/PetitionRate;
  #17 = NameAndType        #18:#6         // VERY_POOR:Lext/mods/gameserver/enums/petitions/PetitionRate;
  #18 = Utf8               VERY_POOR
  #19 = Fieldref           #1.#20         // ext/mods/gameserver/enums/petitions/PetitionRate.$VALUES:[Lext/mods/gameserver/enums/petitions/PetitionRate;
  #20 = NameAndType        #21:#22        // $VALUES:[Lext/mods/gameserver/enums/petitions/PetitionRate;
  #21 = Utf8               $VALUES
  #22 = Utf8               [Lext/mods/gameserver/enums/petitions/PetitionRate;
  #23 = Methodref          #24.#25        // "[Lext/mods/gameserver/enums/petitions/PetitionRate;".clone:()Ljava/lang/Object;
  #24 = Class              #22            // "[Lext/mods/gameserver/enums/petitions/PetitionRate;"
  #25 = NameAndType        #26:#27        // clone:()Ljava/lang/Object;
  #26 = Utf8               clone
  #27 = Utf8               ()Ljava/lang/Object;
  #28 = Methodref          #29.#30        // java/lang/Enum.valueOf:(Ljava/lang/Class;Ljava/lang/String;)Ljava/lang/Enum;
  #29 = Class              #31            // java/lang/Enum
  #30 = NameAndType        #32:#33        // valueOf:(Ljava/lang/Class;Ljava/lang/String;)Ljava/lang/Enum;
  #31 = Utf8               java/lang/Enum
  #32 = Utf8               valueOf
  #33 = Utf8               (Ljava/lang/Class;Ljava/lang/String;)Ljava/lang/Enum;
  #34 = Methodref          #29.#35        // java/lang/Enum."<init>":(Ljava/lang/String;I)V
  #35 = NameAndType        #36:#37        // "<init>":(Ljava/lang/String;I)V
  #36 = Utf8               <init>
  #37 = Utf8               (Ljava/lang/String;I)V
  #38 = Fieldref           #1.#39         // ext/mods/gameserver/enums/petitions/PetitionRate._desc:Ljava/lang/String;
  #39 = NameAndType        #40:#41        // _desc:Ljava/lang/String;
  #40 = Utf8               _desc
  #41 = Utf8               Ljava/lang/String;
  #42 = String             #5             // VERY_GOOD
  #43 = String             #44            // Very Good
  #44 = Utf8               Very Good
  #45 = Methodref          #1.#46         // ext/mods/gameserver/enums/petitions/PetitionRate."<init>":(Ljava/lang/String;ILjava/lang/String;)V
  #46 = NameAndType        #36:#47        // "<init>":(Ljava/lang/String;ILjava/lang/String;)V
  #47 = Utf8               (Ljava/lang/String;ILjava/lang/String;)V
  #48 = String             #9             // GOOD
  #49 = String             #50            // Good
  #50 = Utf8               Good
  #51 = String             #12            // FAIR
  #52 = String             #53            // Fair
  #53 = Utf8               Fair
  #54 = String             #15            // POOR
  #55 = String             #56            // Poor
  #56 = Utf8               Poor
  #57 = String             #18            // VERY_POOR
  #58 = String             #59            // Very Poor
  #59 = Utf8               Very Poor
  #60 = Methodref          #1.#61         // ext/mods/gameserver/enums/petitions/PetitionRate.$values:()[Lext/mods/gameserver/enums/petitions/PetitionRate;
  #61 = NameAndType        #62:#63        // $values:()[Lext/mods/gameserver/enums/petitions/PetitionRate;
  #62 = Utf8               $values
  #63 = Utf8               ()[Lext/mods/gameserver/enums/petitions/PetitionRate;
  #64 = Methodref          #1.#65         // ext/mods/gameserver/enums/petitions/PetitionRate.values:()[Lext/mods/gameserver/enums/petitions/PetitionRate;
  #65 = NameAndType        #66:#63        // values:()[Lext/mods/gameserver/enums/petitions/PetitionRate;
  #66 = Utf8               values
  #67 = Fieldref           #1.#68         // ext/mods/gameserver/enums/petitions/PetitionRate.VALUES:[Lext/mods/gameserver/enums/petitions/PetitionRate;
  #68 = NameAndType        #69:#22        // VALUES:[Lext/mods/gameserver/enums/petitions/PetitionRate;
  #69 = Utf8               VALUES
  #70 = Utf8               Code
  #71 = Utf8               LineNumberTable
  #72 = Utf8               (Ljava/lang/String;)Lext/mods/gameserver/enums/petitions/PetitionRate;
  #73 = Utf8               LocalVariableTable
  #74 = Utf8               name
  #75 = Utf8               MethodParameters
  #76 = Utf8               this
  #77 = Utf8               desc
  #78 = Utf8               Signature
  #79 = Utf8               (Ljava/lang/String;)V
  #80 = Utf8               getDesc
  #81 = Utf8               ()Ljava/lang/String;
  #82 = Utf8               <clinit>
  #83 = Utf8               ()V
  #84 = Utf8               Ljava/lang/Enum<Lext/mods/gameserver/enums/petitions/PetitionRate;>;
  #85 = Utf8               SourceFile
  #86 = Utf8               PetitionRate.java
{
  public static final ext.mods.gameserver.enums.petitions.PetitionRate VERY_GOOD;
    descriptor: Lext/mods/gameserver/enums/petitions/PetitionRate;
    flags: (0x4019) ACC_PUBLIC, ACC_STATIC, ACC_FINAL, ACC_ENUM

  public static final ext.mods.gameserver.enums.petitions.PetitionRate GOOD;
    descriptor: Lext/mods/gameserver/enums/petitions/PetitionRate;
    flags: (0x4019) ACC_PUBLIC, ACC_STATIC, ACC_FINAL, ACC_ENUM

  public static final ext.mods.gameserver.enums.petitions.PetitionRate FAIR;
    descriptor: Lext/mods/gameserver/enums/petitions/PetitionRate;
    flags: (0x4019) ACC_PUBLIC, ACC_STATIC, ACC_FINAL, ACC_ENUM

  public static final ext.mods.gameserver.enums.petitions.PetitionRate POOR;
    descriptor: Lext/mods/gameserver/enums/petitions/PetitionRate;
    flags: (0x4019) ACC_PUBLIC, ACC_STATIC, ACC_FINAL, ACC_ENUM

  public static final ext.mods.gameserver.enums.petitions.PetitionRate VERY_POOR;
    descriptor: Lext/mods/gameserver/enums/petitions/PetitionRate;
    flags: (0x4019) ACC_PUBLIC, ACC_STATIC, ACC_FINAL, ACC_ENUM

  public static final ext.mods.gameserver.enums.petitions.PetitionRate[] VALUES;
    descriptor: [Lext/mods/gameserver/enums/petitions/PetitionRate;
    flags: (0x0019) ACC_PUBLIC, ACC_STATIC, ACC_FINAL

  public static ext.mods.gameserver.enums.petitions.PetitionRate[] values();
    descriptor: ()[Lext/mods/gameserver/enums/petitions/PetitionRate;
    flags: (0x0009) ACC_PUBLIC, ACC_STATIC
    Code:
      stack=1, locals=0, args_size=0
         0: getstatic     #19                 // Field $VALUES:[Lext/mods/gameserver/enums/petitions/PetitionRate;
         3: invokevirtual #23                 // Method "[Lext/mods/gameserver/enums/petitions/PetitionRate;".clone:()Ljava/lang/Object;
         6: checkcast     #24                 // class "[Lext/mods/gameserver/enums/petitions/PetitionRate;"
         9: areturn
      LineNumberTable:
        line 20: 0

  public static ext.mods.gameserver.enums.petitions.PetitionRate valueOf(java.lang.String);
    descriptor: (Ljava/lang/String;)Lext/mods/gameserver/enums/petitions/PetitionRate;
    flags: (0x0009) ACC_PUBLIC, ACC_STATIC
    Code:
      stack=2, locals=1, args_size=1
         0: ldc           #1                  // class ext/mods/gameserver/enums/petitions/PetitionRate
         2: aload_0
         3: invokestatic  #28                 // Method java/lang/Enum.valueOf:(Ljava/lang/Class;Ljava/lang/String;)Ljava/lang/Enum;
         6: checkcast     #1                  // class ext/mods/gameserver/enums/petitions/PetitionRate
         9: areturn
      LineNumberTable:
        line 20: 0
      LocalVariableTable:
        Start  Length  Slot  Name   Signature
            0      10     0  name   Ljava/lang/String;
    MethodParameters:
      Name                           Flags
      <no name>                      mandated

  public java.lang.String getDesc();
    descriptor: ()Ljava/lang/String;
    flags: (0x0001) ACC_PUBLIC
    Code:
      stack=1, locals=1, args_size=1
         0: aload_0
         1: getfield      #38                 // Field _desc:Ljava/lang/String;
         4: areturn
      LineNumberTable:
        line 39: 0
      LocalVariableTable:
        Start  Length  Slot  Name   Signature
            0       5     0  this   Lext/mods/gameserver/enums/petitions/PetitionRate;

  static {};
    descriptor: ()V
    flags: (0x0008) ACC_STATIC
    Code:
      stack=5, locals=0, args_size=0
         0: new           #1                  // class ext/mods/gameserver/enums/petitions/PetitionRate
         3: dup
         4: ldc           #42                 // String VERY_GOOD
         6: iconst_0
         7: ldc           #43                 // String Very Good
         9: invokespecial #45                 // Method "<init>":(Ljava/lang/String;ILjava/lang/String;)V
        12: putstatic     #3                  // Field VERY_GOOD:Lext/mods/gameserver/enums/petitions/PetitionRate;
        15: new           #1                  // class ext/mods/gameserver/enums/petitions/PetitionRate
        18: dup
        19: ldc           #48                 // String GOOD
        21: iconst_1
        22: ldc           #49                 // String Good
        24: invokespecial #45                 // Method "<init>":(Ljava/lang/String;ILjava/lang/String;)V
        27: putstatic     #7                  // Field GOOD:Lext/mods/gameserver/enums/petitions/PetitionRate;
        30: new           #1                  // class ext/mods/gameserver/enums/petitions/PetitionRate
        33: dup
        34: ldc           #51                 // String FAIR
        36: iconst_2
        37: ldc           #52                 // String Fair
        39: invokespecial #45                 // Method "<init>":(Ljava/lang/String;ILjava/lang/String;)V
        42: putstatic     #10                 // Field FAIR:Lext/mods/gameserver/enums/petitions/PetitionRate;
        45: new           #1                  // class ext/mods/gameserver/enums/petitions/PetitionRate
        48: dup
        49: ldc           #54                 // String POOR
        51: iconst_3
        52: ldc           #55                 // String Poor
        54: invokespecial #45                 // Method "<init>":(Ljava/lang/String;ILjava/lang/String;)V
        57: putstatic     #13                 // Field POOR:Lext/mods/gameserver/enums/petitions/PetitionRate;
        60: new           #1                  // class ext/mods/gameserver/enums/petitions/PetitionRate
        63: dup
        64: ldc           #57                 // String VERY_POOR
        66: iconst_4
        67: ldc           #58                 // String Very Poor
        69: invokespecial #45                 // Method "<init>":(Ljava/lang/String;ILjava/lang/String;)V
        72: putstatic     #16                 // Field VERY_POOR:Lext/mods/gameserver/enums/petitions/PetitionRate;
        75: invokestatic  #60                 // Method $values:()[Lext/mods/gameserver/enums/petitions/PetitionRate;
        78: putstatic     #19                 // Field $VALUES:[Lext/mods/gameserver/enums/petitions/PetitionRate;
        81: invokestatic  #64                 // Method values:()[Lext/mods/gameserver/enums/petitions/PetitionRate;
        84: putstatic     #67                 // Field VALUES:[Lext/mods/gameserver/enums/petitions/PetitionRate;
        87: return
      LineNumberTable:
        line 22: 0
        line 23: 15
        line 24: 30
        line 25: 45
        line 26: 60
        line 20: 75
        line 28: 81
}
Signature: #84                          // Ljava/lang/Enum<Lext/mods/gameserver/enums/petitions/PetitionRate;>;
SourceFile: "PetitionRate.java"
