// Bytecode for: ext.mods.gameserver.GameServer$Companion
// File: ext\mods\gameserver\GameServer$Companion.class

Classfile /c:/Users/User/Desktop/BrProject/bin/main/ext/mods/gameserver/GameServer$Companion.class
  Last modified 9 de jul de 2026; size 11745 bytes
  MD5 checksum 544c4cf7539ff1493ee881f9bf7096a3
  Compiled from "GameServer.kt"
public final class ext.mods.gameserver.GameServer$Companion
  minor version: 0
  major version: 69
  flags: (0x0031) ACC_PUBLIC, ACC_FINAL, ACC_SUPER
  this_class: #2                          // ext/mods/gameserver/GameServer$Companion
  super_class: #4                         // java/lang/Object
  interfaces: 0, fields: 0, methods: 12, attributes: 4
Constant pool:
    #1 = Utf8               ext/mods/gameserver/GameServer$Companion
    #2 = Class              #1            // ext/mods/gameserver/GameServer$Companion
    #3 = Utf8               java/lang/Object
    #4 = Class              #3            // java/lang/Object
    #5 = Utf8               <init>
    #6 = Utf8               ()V
    #7 = NameAndType        #5:#6         // "<init>":()V
    #8 = Methodref          #4.#7         // java/lang/Object."<init>":()V
    #9 = Utf8               this
   #10 = Utf8               Lext/mods/gameserver/GameServer$Companion;
   #11 = Utf8               getInstance
   #12 = Utf8               ()Lext/mods/gameserver/GameServer;
   #13 = Utf8               Lorg/jetbrains/annotations/Nullable;
   #14 = Utf8               ext/mods/gameserver/GameServer
   #15 = Class              #14           // ext/mods/gameserver/GameServer
   #16 = Utf8               access$getInstance$cp
   #17 = NameAndType        #16:#12       // access$getInstance$cp:()Lext/mods/gameserver/GameServer;
   #18 = Methodref          #15.#17       // ext/mods/gameserver/GameServer.access$getInstance$cp:()Lext/mods/gameserver/GameServer;
   #19 = Utf8               getInstance$annotations
   #20 = Utf8               Lkotlin/jvm/JvmStatic;
   #21 = Utf8               main
   #22 = Utf8               ([Ljava/lang/String;)V
   #23 = Utf8               Lorg/jetbrains/annotations/NotNull;
   #24 = Utf8               true
   #25 = String             #24           // true
   #26 = Utf8               brproject.safe.graphics
   #27 = String             #26           // brproject.safe.graphics
   #28 = Utf8               java/lang/System
   #29 = Class              #28           // java/lang/System
   #30 = Utf8               getProperty
   #31 = Utf8               (Ljava/lang/String;)Ljava/lang/String;
   #32 = NameAndType        #30:#31       // getProperty:(Ljava/lang/String;)Ljava/lang/String;
   #33 = Methodref          #29.#32       // java/lang/System.getProperty:(Ljava/lang/String;)Ljava/lang/String;
   #34 = Utf8               kotlin/text/StringsKt
   #35 = Class              #34           // kotlin/text/StringsKt
   #36 = Utf8               equals
   #37 = Utf8               (Ljava/lang/String;Ljava/lang/String;Z)Z
   #38 = NameAndType        #36:#37       // equals:(Ljava/lang/String;Ljava/lang/String;Z)Z
   #39 = Methodref          #35.#38       // kotlin/text/StringsKt.equals:(Ljava/lang/String;Ljava/lang/String;Z)Z
   #40 = Utf8               sun.java2d.opengl
   #41 = String             #40           // sun.java2d.opengl
   #42 = Utf8               false
   #43 = String             #42           // false
   #44 = Utf8               setProperty
   #45 = Utf8               (Ljava/lang/String;Ljava/lang/String;)Ljava/lang/String;
   #46 = NameAndType        #44:#45       // setProperty:(Ljava/lang/String;Ljava/lang/String;)Ljava/lang/String;
   #47 = Methodref          #29.#46       // java/lang/System.setProperty:(Ljava/lang/String;Ljava/lang/String;)Ljava/lang/String;
   #48 = Utf8               sun.java2d.d3d
   #49 = String             #48           // sun.java2d.d3d
   #50 = Utf8               sun.java2d.pmoffscreen
   #51 = String             #50           // sun.java2d.pmoffscreen
   #52 = Utf8               ext/mods/commons/Team
   #53 = Class              #52           // ext/mods/commons/Team
   #54 = Utf8               infoGameServer
   #55 = NameAndType        #54:#6        // infoGameServer:()V
   #56 = Methodref          #53.#55       // ext/mods/commons/Team.infoGameServer:()V
   #57 = Utf8               ext/mods/commons/util/JvmOptimizer
   #58 = Class              #57           // ext/mods/commons/util/JvmOptimizer
   #59 = Utf8               initialize
   #60 = NameAndType        #59:#6        // initialize:()V
   #61 = Methodref          #58.#60       // ext/mods/commons/util/JvmOptimizer.initialize:()V
   #62 = NameAndType        #5:#22        // "<init>":([Ljava/lang/String;)V
   #63 = Methodref          #15.#62       // ext/mods/gameserver/GameServer."<init>":([Ljava/lang/String;)V
   #64 = Utf8               args
   #65 = Utf8               [Ljava/lang/String;
   #66 = Utf8               createDirectories
   #67 = Utf8               java/lang/Exception
   #68 = Class              #67           // java/lang/Exception
   #69 = Utf8               log
   #70 = String             #69           // log
   #71 = Utf8               createDirectory
   #72 = Utf8               (Ljava/lang/String;)V
   #73 = NameAndType        #71:#72       // createDirectory:(Ljava/lang/String;)V
   #74 = Methodref          #2.#73        // ext/mods/gameserver/GameServer$Companion.createDirectory:(Ljava/lang/String;)V
   #75 = Utf8               log/drop
   #76 = String             #75           // log/drop
   #77 = Utf8               log/chat
   #78 = String             #77           // log/chat
   #79 = Utf8               log/console
   #80 = String             #79           // log/console
   #81 = Utf8               log/error
   #82 = String             #81           // log/error
   #83 = Utf8               log/gmaudit
   #84 = String             #83           // log/gmaudit
   #85 = Utf8               log/item
   #86 = String             #85           // log/item
   #87 = Utf8               crests
   #88 = String             #87           // crests
   #89 = Utf8               createDataDirectory
   #90 = NameAndType        #89:#72       // createDataDirectory:(Ljava/lang/String;)V
   #91 = Methodref          #2.#90        // ext/mods/gameserver/GameServer$Companion.createDataDirectory:(Ljava/lang/String;)V
   #92 = Utf8               access$getLOGGER$cp
   #93 = Utf8               ()Lext/mods/commons/logging/CLogger;
   #94 = NameAndType        #92:#93       // access$getLOGGER$cp:()Lext/mods/commons/logging/CLogger;
   #95 = Methodref          #15.#94       // ext/mods/gameserver/GameServer.access$getLOGGER$cp:()Lext/mods/commons/logging/CLogger;
   #96 = Utf8               Failed to create directories.
   #97 = String             #96           // Failed to create directories.
   #98 = Utf8               java/lang/Throwable
   #99 = Class              #98           // java/lang/Throwable
  #100 = Utf8               ext/mods/commons/logging/CLogger
  #101 = Class              #100          // ext/mods/commons/logging/CLogger
  #102 = Utf8               error
  #103 = Utf8               (Ljava/lang/Object;Ljava/lang/Throwable;)V
  #104 = NameAndType        #102:#103     // error:(Ljava/lang/Object;Ljava/lang/Throwable;)V
  #105 = Methodref          #101.#104     // ext/mods/commons/logging/CLogger.error:(Ljava/lang/Object;Ljava/lang/Throwable;)V
  #106 = Utf8               e
  #107 = Utf8               Ljava/lang/Exception;
  #108 = Utf8               ext/mods/Config
  #109 = Class              #108          // ext/mods/Config
  #110 = Utf8               BASE_PATH
  #111 = Utf8               Ljava/nio/file/Path;
  #112 = NameAndType        #110:#111     // BASE_PATH:Ljava/nio/file/Path;
  #113 = Fieldref           #109.#112     // ext/mods/Config.BASE_PATH:Ljava/nio/file/Path;
  #114 = Utf8               DEV_MODE
  #115 = Utf8               Z
  #116 = NameAndType        #114:#115     // DEV_MODE:Z
  #117 = Fieldref           #109.#116     // ext/mods/Config.DEV_MODE:Z
  #118 = Utf8               dev
  #119 = String             #118          // dev
  #120 = Utf8               java/nio/file/Path
  #121 = Class              #120          // java/nio/file/Path
  #122 = Utf8               resolve
  #123 = Utf8               (Ljava/lang/String;)Ljava/nio/file/Path;
  #124 = NameAndType        #122:#123     // resolve:(Ljava/lang/String;)Ljava/nio/file/Path;
  #125 = InterfaceMethodref #121.#124     // java/nio/file/Path.resolve:(Ljava/lang/String;)Ljava/nio/file/Path;
  #126 = Utf8               game
  #127 = String             #126          // game
  #128 = Utf8               toFile
  #129 = Utf8               ()Ljava/io/File;
  #130 = NameAndType        #128:#129     // toFile:()Ljava/io/File;
  #131 = InterfaceMethodref #121.#130     // java/nio/file/Path.toFile:()Ljava/io/File;
  #132 = Utf8               java/io/File
  #133 = Class              #132          // java/io/File
  #134 = Utf8               mkdirs
  #135 = Utf8               ()Z
  #136 = NameAndType        #134:#135     // mkdirs:()Z
  #137 = Methodref          #133.#136     // java/io/File.mkdirs:()Z
  #138 = Utf8               p
  #139 = Utf8               path
  #140 = Utf8               Ljava/lang/String;
  #141 = Utf8               DATA_PATH
  #142 = NameAndType        #141:#111     // DATA_PATH:Ljava/nio/file/Path;
  #143 = Fieldref           #109.#142     // ext/mods/Config.DATA_PATH:Ljava/nio/file/Path;
  #144 = Utf8               getTimeUntilMidnight
  #145 = Utf8               ()J
  #146 = Utf8               currentTimeMillis
  #147 = NameAndType        #146:#145     // currentTimeMillis:()J
  #148 = Methodref          #29.#147      // java/lang/System.currentTimeMillis:()J
  #149 = Integer            86400000
  #150 = Utf8               now
  #151 = Utf8               J
  #152 = Utf8               tomorrowMidnight
  #153 = Utf8               customMods
  #154 = Utf8               Custom Mods: initialization...
  #155 = String             #154          // Custom Mods: initialization...
  #156 = Utf8               ext/mods/commons/lang/StringUtil
  #157 = Class              #156          // ext/mods/commons/lang/StringUtil
  #158 = Utf8               printSection
  #159 = NameAndType        #158:#72      // printSection:(Ljava/lang/String;)V
  #160 = Methodref          #157.#159     // ext/mods/commons/lang/StringUtil.printSection:(Ljava/lang/String;)V
  #161 = Utf8               ext/mods/gameserver/custom/data/BalanceData
  #162 = Class              #161          // ext/mods/gameserver/custom/data/BalanceData
  #163 = Utf8               ()Lext/mods/gameserver/custom/data/BalanceData;
  #164 = NameAndType        #11:#163      // getInstance:()Lext/mods/gameserver/custom/data/BalanceData;
  #165 = Methodref          #162.#164     // ext/mods/gameserver/custom/data/BalanceData.getInstance:()Lext/mods/gameserver/custom/data/BalanceData;
  #166 = Utf8               init
  #167 = NameAndType        #166:#6       // init:()V
  #168 = Methodref          #162.#167     // ext/mods/gameserver/custom/data/BalanceData.init:()V
  #169 = Utf8               ext/mods/gameserver/custom/data/RatesData
  #170 = Class              #169          // ext/mods/gameserver/custom/data/RatesData
  #171 = Utf8               ()Lext/mods/gameserver/custom/data/RatesData;
  #172 = NameAndType        #11:#171      // getInstance:()Lext/mods/gameserver/custom/data/RatesData;
  #173 = Methodref          #170.#172     // ext/mods/gameserver/custom/data/RatesData.getInstance:()Lext/mods/gameserver/custom/data/RatesData;
  #174 = Utf8               OFFLINE_TRADE_ENABLE
  #175 = NameAndType        #174:#115     // OFFLINE_TRADE_ENABLE:Z
  #176 = Fieldref           #109.#175     // ext/mods/Config.OFFLINE_TRADE_ENABLE:Z
  #177 = Utf8               OFFLINE_CRAFT_ENABLE
  #178 = NameAndType        #177:#115     // OFFLINE_CRAFT_ENABLE:Z
  #179 = Fieldref           #109.#178     // ext/mods/Config.OFFLINE_CRAFT_ENABLE:Z
  #180 = Utf8               RESTORE_OFFLINERS
  #181 = NameAndType        #180:#115     // RESTORE_OFFLINERS:Z
  #182 = Fieldref           #109.#181     // ext/mods/Config.RESTORE_OFFLINERS:Z
  #183 = Utf8               ext/mods/gameserver/data/sql/OfflineTradersTable
  #184 = Class              #183          // ext/mods/gameserver/data/sql/OfflineTradersTable
  #185 = Utf8               ()Lext/mods/gameserver/data/sql/OfflineTradersTable;
  #186 = NameAndType        #11:#185      // getInstance:()Lext/mods/gameserver/data/sql/OfflineTradersTable;
  #187 = Methodref          #184.#186     // ext/mods/gameserver/data/sql/OfflineTradersTable.getInstance:()Lext/mods/gameserver/data/sql/OfflineTradersTable;
  #188 = Utf8               restore
  #189 = NameAndType        #188:#6       // restore:()V
  #190 = Methodref          #184.#189     // ext/mods/gameserver/data/sql/OfflineTradersTable.restore:()V
  #191 = Utf8               ext/mods/gameserver/data/manager/CoupleManager
  #192 = Class              #191          // ext/mods/gameserver/data/manager/CoupleManager
  #193 = Utf8               ()Lext/mods/gameserver/data/manager/CoupleManager;
  #194 = NameAndType        #11:#193      // getInstance:()Lext/mods/gameserver/data/manager/CoupleManager;
  #195 = Methodref          #192.#194     // ext/mods/gameserver/data/manager/CoupleManager.getInstance:()Lext/mods/gameserver/data/manager/CoupleManager;
  #196 = Utf8               ext/mods/gameserver/custom/data/EventsData
  #197 = Class              #196          // ext/mods/gameserver/custom/data/EventsData
  #198 = Utf8               ()Lext/mods/gameserver/custom/data/EventsData;
  #199 = NameAndType        #11:#198      // getInstance:()Lext/mods/gameserver/custom/data/EventsData;
  #200 = Methodref          #197.#199     // ext/mods/gameserver/custom/data/EventsData.getInstance:()Lext/mods/gameserver/custom/data/EventsData;
  #201 = Utf8               ext/mods/gameserver/data/manager/EventsDropManager
  #202 = Class              #201          // ext/mods/gameserver/data/manager/EventsDropManager
  #203 = Utf8               ()Lext/mods/gameserver/data/manager/EventsDropManager;
  #204 = NameAndType        #11:#203      // getInstance:()Lext/mods/gameserver/data/manager/EventsDropManager;
  #205 = Methodref          #202.#204     // ext/mods/gameserver/data/manager/EventsDropManager.getInstance:()Lext/mods/gameserver/data/manager/EventsDropManager;
  #206 = Utf8               ext/mods/gameserver/model/entity/events/capturetheflag/CTFManager
  #207 = Class              #206          // ext/mods/gameserver/model/entity/events/capturetheflag/CTFManager
  #208 = Utf8               ()Lext/mods/gameserver/model/entity/events/capturetheflag/CTFManager;
  #209 = NameAndType        #11:#208      // getInstance:()Lext/mods/gameserver/model/entity/events/capturetheflag/CTFManager;
  #210 = Methodref          #207.#209     // ext/mods/gameserver/model/entity/events/capturetheflag/CTFManager.getInstance:()Lext/mods/gameserver/model/entity/events/capturetheflag/CTFManager;
  #211 = Utf8               ext/mods/gameserver/model/entity/events/deathmatch/DMManager
  #212 = Class              #211          // ext/mods/gameserver/model/entity/events/deathmatch/DMManager
  #213 = Utf8               ()Lext/mods/gameserver/model/entity/events/deathmatch/DMManager;
  #214 = NameAndType        #11:#213      // getInstance:()Lext/mods/gameserver/model/entity/events/deathmatch/DMManager;
  #215 = Methodref          #212.#214     // ext/mods/gameserver/model/entity/events/deathmatch/DMManager.getInstance:()Lext/mods/gameserver/model/entity/events/deathmatch/DMManager;
  #216 = Utf8               ext/mods/gameserver/model/entity/events/lastman/LMManager
  #217 = Class              #216          // ext/mods/gameserver/model/entity/events/lastman/LMManager
  #218 = Utf8               ()Lext/mods/gameserver/model/entity/events/lastman/LMManager;
  #219 = NameAndType        #11:#218      // getInstance:()Lext/mods/gameserver/model/entity/events/lastman/LMManager;
  #220 = Methodref          #217.#219     // ext/mods/gameserver/model/entity/events/lastman/LMManager.getInstance:()Lext/mods/gameserver/model/entity/events/lastman/LMManager;
  #221 = Utf8               ext/mods/gameserver/model/entity/events/teamvsteam/TvTManager
  #222 = Class              #221          // ext/mods/gameserver/model/entity/events/teamvsteam/TvTManager
  #223 = Utf8               ()Lext/mods/gameserver/model/entity/events/teamvsteam/TvTManager;
  #224 = NameAndType        #11:#223      // getInstance:()Lext/mods/gameserver/model/entity/events/teamvsteam/TvTManager;
  #225 = Methodref          #222.#224     // ext/mods/gameserver/model/entity/events/teamvsteam/TvTManager.getInstance:()Lext/mods/gameserver/model/entity/events/teamvsteam/TvTManager;
  #226 = Utf8               ext/mods/gameserver/custom/data/EnchantData
  #227 = Class              #226          // ext/mods/gameserver/custom/data/EnchantData
  #228 = Utf8               ()Lext/mods/gameserver/custom/data/EnchantData;
  #229 = NameAndType        #11:#228      // getInstance:()Lext/mods/gameserver/custom/data/EnchantData;
  #230 = Methodref          #227.#229     // ext/mods/gameserver/custom/data/EnchantData.getInstance:()Lext/mods/gameserver/custom/data/EnchantData;
  #231 = Utf8               ext/mods/gameserver/data/manager/AntiFeedManager
  #232 = Class              #231          // ext/mods/gameserver/data/manager/AntiFeedManager
  #233 = Utf8               ()Lext/mods/gameserver/data/manager/AntiFeedManager;
  #234 = NameAndType        #11:#233      // getInstance:()Lext/mods/gameserver/data/manager/AntiFeedManager;
  #235 = Methodref          #232.#234     // ext/mods/gameserver/data/manager/AntiFeedManager.getInstance:()Lext/mods/gameserver/data/manager/AntiFeedManager;
  #236 = Utf8               registerEvent
  #237 = Utf8               (I)V
  #238 = NameAndType        #236:#237     // registerEvent:(I)V
  #239 = Methodref          #232.#238     // ext/mods/gameserver/data/manager/AntiFeedManager.registerEvent:(I)V
  #240 = Utf8               ext/mods/gameserver/data/manager/PcCafeManager
  #241 = Class              #240          // ext/mods/gameserver/data/manager/PcCafeManager
  #242 = Utf8               ()Lext/mods/gameserver/data/manager/PcCafeManager;
  #243 = NameAndType        #11:#242      // getInstance:()Lext/mods/gameserver/data/manager/PcCafeManager;
  #244 = Methodref          #241.#243     // ext/mods/gameserver/data/manager/PcCafeManager.getInstance:()Lext/mods/gameserver/data/manager/PcCafeManager;
  #245 = Utf8               CapsuleBox - Terius
  #246 = String             #245          // CapsuleBox - Terius
  #247 = Utf8               ext/mods/CapsuleBox/CapsuleBoxData
  #248 = Class              #247          // ext/mods/CapsuleBox/CapsuleBoxData
  #249 = Utf8               ()Lext/mods/CapsuleBox/CapsuleBoxData;
  #250 = NameAndType        #11:#249      // getInstance:()Lext/mods/CapsuleBox/CapsuleBoxData;
  #251 = Methodref          #248.#250     // ext/mods/CapsuleBox/CapsuleBoxData.getInstance:()Lext/mods/CapsuleBox/CapsuleBoxData;
  #252 = Utf8               ext/mods/gameserver/data/xml/StaticSpawnData
  #253 = Class              #252          // ext/mods/gameserver/data/xml/StaticSpawnData
  #254 = Utf8               ()Lext/mods/gameserver/data/xml/StaticSpawnData;
  #255 = NameAndType        #11:#254      // getInstance:()Lext/mods/gameserver/data/xml/StaticSpawnData;
  #256 = Methodref          #253.#255     // ext/mods/gameserver/data/xml/StaticSpawnData.getInstance:()Lext/mods/gameserver/data/xml/StaticSpawnData;
  #257 = Utf8               ext/mods/gameserver/handler/voicedcommandhandlers/Raid
  #258 = Class              #257          // ext/mods/gameserver/handler/voicedcommandhandlers/Raid
  #259 = Utf8               load
  #260 = NameAndType        #259:#6       // load:()V
  #261 = Methodref          #258.#260     // ext/mods/gameserver/handler/voicedcommandhandlers/Raid.load:()V
  #262 = Utf8               ext/mods/gameserver/handler/voicedcommandhandlers/Epic
  #263 = Class              #262          // ext/mods/gameserver/handler/voicedcommandhandlers/Epic
  #264 = Methodref          #263.#260     // ext/mods/gameserver/handler/voicedcommandhandlers/Epic.load:()V
  #265 = Utf8               ext/mods/gameserver/communitybbs/custom/AuctionBBSManager
  #266 = Class              #265          // ext/mods/gameserver/communitybbs/custom/AuctionBBSManager
  #267 = Utf8               ()Lext/mods/gameserver/communitybbs/custom/AuctionBBSManager;
  #268 = NameAndType        #11:#267      // getInstance:()Lext/mods/gameserver/communitybbs/custom/AuctionBBSManager;
  #269 = Methodref          #266.#268     // ext/mods/gameserver/communitybbs/custom/AuctionBBSManager.getInstance:()Lext/mods/gameserver/communitybbs/custom/AuctionBBSManager;
  #270 = Methodref          #266.#260     // ext/mods/gameserver/communitybbs/custom/AuctionBBSManager.load:()V
  #271 = Utf8               ext/mods/gameserver/custom/data/AuctionCurrencies
  #272 = Class              #271          // ext/mods/gameserver/custom/data/AuctionCurrencies
  #273 = Utf8               ()Lext/mods/gameserver/custom/data/AuctionCurrencies;
  #274 = NameAndType        #11:#273      // getInstance:()Lext/mods/gameserver/custom/data/AuctionCurrencies;
  #275 = Methodref          #272.#274     // ext/mods/gameserver/custom/data/AuctionCurrencies.getInstance:()Lext/mods/gameserver/custom/data/AuctionCurrencies;
  #276 = Utf8               ext/mods/gameserver/model/entity/autofarm/AutoFarmManager
  #277 = Class              #276          // ext/mods/gameserver/model/entity/autofarm/AutoFarmManager
  #278 = Utf8               ()Lext/mods/gameserver/model/entity/autofarm/AutoFarmManager;
  #279 = NameAndType        #11:#278      // getInstance:()Lext/mods/gameserver/model/entity/autofarm/AutoFarmManager;
  #280 = Methodref          #277.#279     // ext/mods/gameserver/model/entity/autofarm/AutoFarmManager.getInstance:()Lext/mods/gameserver/model/entity/autofarm/AutoFarmManager;
  #281 = Utf8               ext/mods/gameserver/model/entity/autofarm/AutoFarmTask
  #282 = Class              #281          // ext/mods/gameserver/model/entity/autofarm/AutoFarmTask
  #283 = Utf8               ()Lext/mods/gameserver/model/entity/autofarm/AutoFarmTask;
  #284 = NameAndType        #11:#283      // getInstance:()Lext/mods/gameserver/model/entity/autofarm/AutoFarmTask;
  #285 = Methodref          #282.#284     // ext/mods/gameserver/model/entity/autofarm/AutoFarmTask.getInstance:()Lext/mods/gameserver/model/entity/autofarm/AutoFarmTask;
  #286 = Utf8               SELLBUFF_ENABLED
  #287 = NameAndType        #286:#115     // SELLBUFF_ENABLED:Z
  #288 = Fieldref           #109.#287     // ext/mods/Config.SELLBUFF_ENABLED:Z
  #289 = Utf8               ext/mods/gameserver/data/manager/SellBuffsManager
  #290 = Class              #289          // ext/mods/gameserver/data/manager/SellBuffsManager
  #291 = Utf8               ()Lext/mods/gameserver/data/manager/SellBuffsManager;
  #292 = NameAndType        #11:#291      // getInstance:()Lext/mods/gameserver/data/manager/SellBuffsManager;
  #293 = Methodref          #290.#292     // ext/mods/gameserver/data/manager/SellBuffsManager.getInstance:()Lext/mods/gameserver/data/manager/SellBuffsManager;
  #294 = Utf8               ext/mods/gameserver/custom/data/DonateData
  #295 = Class              #294          // ext/mods/gameserver/custom/data/DonateData
  #296 = Utf8               ()Lext/mods/gameserver/custom/data/DonateData;
  #297 = NameAndType        #11:#296      // getInstance:()Lext/mods/gameserver/custom/data/DonateData;
  #298 = Methodref          #295.#297     // ext/mods/gameserver/custom/data/DonateData.getInstance:()Lext/mods/gameserver/custom/data/DonateData;
  #299 = Utf8               ENABLE_PIX_MOD
  #300 = NameAndType        #299:#115     // ENABLE_PIX_MOD:Z
  #301 = Fieldref           #109.#300     // ext/mods/Config.ENABLE_PIX_MOD:Z
  #302 = Utf8               DONATION_ENABLED
  #303 = NameAndType        #302:#115     // DONATION_ENABLED:Z
  #304 = Fieldref           #109.#303     // ext/mods/Config.DONATION_ENABLED:Z
  #305 = Utf8               net/sf/donationmanager/DonationManager
  #306 = Class              #305          // net/sf/donationmanager/DonationManager
  #307 = Utf8               ()Lnet/sf/donationmanager/DonationManager;
  #308 = NameAndType        #11:#307      // getInstance:()Lnet/sf/donationmanager/DonationManager;
  #309 = Methodref          #306.#308     // net/sf/donationmanager/DonationManager.getInstance:()Lnet/sf/donationmanager/DonationManager;
  #310 = Utf8               ext/mods/gameserver/custom/data/MissionData
  #311 = Class              #310          // ext/mods/gameserver/custom/data/MissionData
  #312 = Utf8               ()Lext/mods/gameserver/custom/data/MissionData;
  #313 = NameAndType        #11:#312      // getInstance:()Lext/mods/gameserver/custom/data/MissionData;
  #314 = Methodref          #311.#313     // ext/mods/gameserver/custom/data/MissionData.getInstance:()Lext/mods/gameserver/custom/data/MissionData;
  #315 = Utf8               ext/mods/gameserver/custom/data/PvPData
  #316 = Class              #315          // ext/mods/gameserver/custom/data/PvPData
  #317 = Utf8               ()Lext/mods/gameserver/custom/data/PvPData;
  #318 = NameAndType        #11:#317      // getInstance:()Lext/mods/gameserver/custom/data/PvPData;
  #319 = Methodref          #316.#318     // ext/mods/gameserver/custom/data/PvPData.getInstance:()Lext/mods/gameserver/custom/data/PvPData;
  #320 = Utf8               ext/mods/Crypta/AgathionData
  #321 = Class              #320          // ext/mods/Crypta/AgathionData
  #322 = Utf8               ()Lext/mods/Crypta/AgathionData;
  #323 = NameAndType        #11:#322      // getInstance:()Lext/mods/Crypta/AgathionData;
  #324 = Methodref          #321.#323     // ext/mods/Crypta/AgathionData.getInstance:()Lext/mods/Crypta/AgathionData;
  #325 = Utf8               ext/mods/gameserver/custom/data/PolymorphData
  #326 = Class              #325          // ext/mods/gameserver/custom/data/PolymorphData
  #327 = Utf8               ()Lext/mods/gameserver/custom/data/PolymorphData;
  #328 = NameAndType        #11:#327      // getInstance:()Lext/mods/gameserver/custom/data/PolymorphData;
  #329 = Methodref          #326.#328     // ext/mods/gameserver/custom/data/PolymorphData.getInstance:()Lext/mods/gameserver/custom/data/PolymorphData;
  #330 = Utf8               ext/mods/gameserver/custom/data/RaidDropAnnounceData
  #331 = Class              #330          // ext/mods/gameserver/custom/data/RaidDropAnnounceData
  #332 = Utf8               ()Lext/mods/gameserver/custom/data/RaidDropAnnounceData;
  #333 = NameAndType        #11:#332      // getInstance:()Lext/mods/gameserver/custom/data/RaidDropAnnounceData;
  #334 = Methodref          #331.#333     // ext/mods/gameserver/custom/data/RaidDropAnnounceData.getInstance:()Lext/mods/gameserver/custom/data/RaidDropAnnounceData;
  #335 = Utf8               ext/mods/gameserver/custom/data/EquipGradeRestrictionData
  #336 = Class              #335          // ext/mods/gameserver/custom/data/EquipGradeRestrictionData
  #337 = Utf8               ()Lext/mods/gameserver/custom/data/EquipGradeRestrictionData;
  #338 = NameAndType        #11:#337      // getInstance:()Lext/mods/gameserver/custom/data/EquipGradeRestrictionData;
  #339 = Methodref          #336.#338     // ext/mods/gameserver/custom/data/EquipGradeRestrictionData.getInstance:()Lext/mods/gameserver/custom/data/EquipGradeRestrictionData;
  #340 = Utf8               ext/mods/gameserver/custom/data/BossHpAnnounceData
  #341 = Class              #340          // ext/mods/gameserver/custom/data/BossHpAnnounceData
  #342 = Utf8               ()Lext/mods/gameserver/custom/data/BossHpAnnounceData;
  #343 = NameAndType        #11:#342      // getInstance:()Lext/mods/gameserver/custom/data/BossHpAnnounceData;
  #344 = Methodref          #341.#343     // ext/mods/gameserver/custom/data/BossHpAnnounceData.getInstance:()Lext/mods/gameserver/custom/data/BossHpAnnounceData;
  #345 = Utf8               ext/mods/BossZerg/BossZergManager
  #346 = Class              #345          // ext/mods/BossZerg/BossZergManager
  #347 = Utf8               ()Lext/mods/BossZerg/BossZergManager;
  #348 = NameAndType        #11:#347      // getInstance:()Lext/mods/BossZerg/BossZergManager;
  #349 = Methodref          #346.#348     // ext/mods/BossZerg/BossZergManager.getInstance:()Lext/mods/BossZerg/BossZergManager;
  #350 = Utf8               ext/mods/FarmEventRandom/RandomData
  #351 = Class              #350          // ext/mods/FarmEventRandom/RandomData
  #352 = Utf8               ()Lext/mods/FarmEventRandom/RandomData;
  #353 = NameAndType        #11:#352      // getInstance:()Lext/mods/FarmEventRandom/RandomData;
  #354 = Methodref          #351.#353     // ext/mods/FarmEventRandom/RandomData.getInstance:()Lext/mods/FarmEventRandom/RandomData;
  #355 = Utf8               ext/mods/Crypta/RandomManager
  #356 = Class              #355          // ext/mods/Crypta/RandomManager
  #357 = Utf8               ()Lext/mods/Crypta/RandomManager;
  #358 = NameAndType        #11:#357      // getInstance:()Lext/mods/Crypta/RandomManager;
  #359 = Methodref          #356.#358     // ext/mods/Crypta/RandomManager.getInstance:()Lext/mods/Crypta/RandomManager;
  #360 = Utf8               start
  #361 = NameAndType        #360:#6       // start:()V
  #362 = Methodref          #356.#361     // ext/mods/Crypta/RandomManager.start:()V
  #363 = Utf8               ext/mods/dungeon/data/DungeonData
  #364 = Class              #363          // ext/mods/dungeon/data/DungeonData
  #365 = Utf8               ()Lext/mods/dungeon/data/DungeonData;
  #366 = NameAndType        #11:#365      // getInstance:()Lext/mods/dungeon/data/DungeonData;
  #367 = Methodref          #364.#366     // ext/mods/dungeon/data/DungeonData.getInstance:()Lext/mods/dungeon/data/DungeonData;
  #368 = Utf8               ext/mods/roulette/RouletteData
  #369 = Class              #368          // ext/mods/roulette/RouletteData
  #370 = Utf8               ()Lext/mods/roulette/RouletteData;
  #371 = NameAndType        #11:#370      // getInstance:()Lext/mods/roulette/RouletteData;
  #372 = Methodref          #369.#371     // ext/mods/roulette/RouletteData.getInstance:()Lext/mods/roulette/RouletteData;
  #373 = Utf8               ext/mods/playergod/data/PlayerGodData
  #374 = Class              #373          // ext/mods/playergod/data/PlayerGodData
  #375 = Utf8               ()Lext/mods/playergod/data/PlayerGodData;
  #376 = NameAndType        #11:#375      // getInstance:()Lext/mods/playergod/data/PlayerGodData;
  #377 = Methodref          #374.#376     // ext/mods/playergod/data/PlayerGodData.getInstance:()Lext/mods/playergod/data/PlayerGodData;
  #378 = Utf8               ext/mods/dressme/DressMeData
  #379 = Class              #378          // ext/mods/dressme/DressMeData
  #380 = Utf8               ()Lext/mods/dressme/DressMeData;
  #381 = NameAndType        #11:#380      // getInstance:()Lext/mods/dressme/DressMeData;
  #382 = Methodref          #379.#381     // ext/mods/dressme/DressMeData.getInstance:()Lext/mods/dressme/DressMeData;
  #383 = Utf8               ext/mods/tour/TourData
  #384 = Class              #383          // ext/mods/tour/TourData
  #385 = Utf8               ()Lext/mods/tour/TourData;
  #386 = NameAndType        #11:#385      // getInstance:()Lext/mods/tour/TourData;
  #387 = Methodref          #384.#386     // ext/mods/tour/TourData.getInstance:()Lext/mods/tour/TourData;
  #388 = Utf8               ext/mods/levelupmaker/LevelUpMakerManager
  #389 = Class              #388          // ext/mods/levelupmaker/LevelUpMakerManager
  #390 = Utf8               ()Lext/mods/levelupmaker/LevelUpMakerManager;
  #391 = NameAndType        #11:#390      // getInstance:()Lext/mods/levelupmaker/LevelUpMakerManager;
  #392 = Methodref          #389.#391     // ext/mods/levelupmaker/LevelUpMakerManager.getInstance:()Lext/mods/levelupmaker/LevelUpMakerManager;
  #393 = Methodref          #389.#167     // ext/mods/levelupmaker/LevelUpMakerManager.init:()V
  #394 = Utf8               ext/mods/email/task/EmailDeliveryTask
  #395 = Class              #394          // ext/mods/email/task/EmailDeliveryTask
  #396 = Utf8               ()Lext/mods/email/task/EmailDeliveryTask;
  #397 = NameAndType        #11:#396      // getInstance:()Lext/mods/email/task/EmailDeliveryTask;
  #398 = Methodref          #395.#397     // ext/mods/email/task/EmailDeliveryTask.getInstance:()Lext/mods/email/task/EmailDeliveryTask;
  #399 = Utf8               loadAllPending
  #400 = NameAndType        #399:#6       // loadAllPending:()V
  #401 = Methodref          #395.#400     // ext/mods/email/task/EmailDeliveryTask.loadAllPending:()V
  #402 = Utf8               ext/mods/fakeplayer/FakePlayerManager
  #403 = Class              #402          // ext/mods/fakeplayer/FakePlayerManager
  #404 = Utf8               ()Lext/mods/fakeplayer/FakePlayerManager;
  #405 = NameAndType        #11:#404      // getInstance:()Lext/mods/fakeplayer/FakePlayerManager;
  #406 = Methodref          #403.#405     // ext/mods/fakeplayer/FakePlayerManager.getInstance:()Lext/mods/fakeplayer/FakePlayerManager;
  #407 = Utf8               initialise
  #408 = NameAndType        #407:#6       // initialise:()V
  #409 = Methodref          #403.#408     // ext/mods/fakeplayer/FakePlayerManager.initialise:()V
  #410 = Utf8               ALLOW_GUARD_SYSTEM
  #411 = NameAndType        #410:#115     // ALLOW_GUARD_SYSTEM:Z
  #412 = Fieldref           #109.#411     // ext/mods/Config.ALLOW_GUARD_SYSTEM:Z
  #413 = Utf8               ext/mods/protection/hwid/hwid
  #414 = Class              #413          // ext/mods/protection/hwid/hwid
  #415 = Utf8               Init
  #416 = NameAndType        #415:#6       // Init:()V
  #417 = Methodref          #414.#416     // ext/mods/protection/hwid/hwid.Init:()V
  #418 = Utf8               Hwid Manager is disabled.
  #419 = String             #418          // Hwid Manager is disabled.
  #420 = Utf8               info
  #421 = Utf8               (Ljava/lang/Object;)V
  #422 = NameAndType        #420:#421     // info:(Ljava/lang/Object;)V
  #423 = Methodref          #101.#422     // ext/mods/commons/logging/CLogger.info:(Ljava/lang/Object;)V
  #424 = Utf8               ext/mods/sellBuffEngine/BuffShopConfigs
  #425 = Class              #424          // ext/mods/sellBuffEngine/BuffShopConfigs
  #426 = Utf8               ()Lext/mods/sellBuffEngine/BuffShopConfigs;
  #427 = NameAndType        #11:#426      // getInstance:()Lext/mods/sellBuffEngine/BuffShopConfigs;
  #428 = Methodref          #425.#427     // ext/mods/sellBuffEngine/BuffShopConfigs.getInstance:()Lext/mods/sellBuffEngine/BuffShopConfigs;
  #429 = Utf8               loadConfigs
  #430 = NameAndType        #429:#6       // loadConfigs:()V
  #431 = Methodref          #425.#430     // ext/mods/sellBuffEngine/BuffShopConfigs.loadConfigs:()V
  #432 = Utf8               ext/mods/sellBuffEngine/BuffShopManager
  #433 = Class              #432          // ext/mods/sellBuffEngine/BuffShopManager
  #434 = Utf8               ()Lext/mods/sellBuffEngine/BuffShopManager;
  #435 = NameAndType        #11:#434      // getInstance:()Lext/mods/sellBuffEngine/BuffShopManager;
  #436 = Methodref          #433.#435     // ext/mods/sellBuffEngine/BuffShopManager.getInstance:()Lext/mods/sellBuffEngine/BuffShopManager;
  #437 = Utf8               restoreOfflineTraders
  #438 = NameAndType        #437:#6       // restoreOfflineTraders:()V
  #439 = Methodref          #433.#438     // ext/mods/sellBuffEngine/BuffShopManager.restoreOfflineTraders:()V
  #440 = Utf8               getMessage
  #441 = Utf8               ()Ljava/lang/String;
  #442 = NameAndType        #440:#441     // getMessage:()Ljava/lang/String;
  #443 = Methodref          #68.#442      // java/lang/Exception.getMessage:()Ljava/lang/String;
  #444 = Utf8               Failed to initialize Buff Shop System: \u0001
  #445 = String             #444          // Failed to initialize Buff Shop System: \u0001
  #446 = Utf8               java/lang/invoke/StringConcatFactory
  #447 = Class              #446          // java/lang/invoke/StringConcatFactory
  #448 = Utf8               makeConcatWithConstants
  #449 = Utf8               (Ljava/lang/invoke/MethodHandles$Lookup;Ljava/lang/String;Ljava/lang/invoke/MethodType;Ljava/lang/String;[Ljava/lang/Object;)Ljava/lang/invoke/CallSite;
  #450 = NameAndType        #448:#449     // makeConcatWithConstants:(Ljava/lang/invoke/MethodHandles$Lookup;Ljava/lang/String;Ljava/lang/invoke/MethodType;Ljava/lang/String;[Ljava/lang/Object;)Ljava/lang/invoke/CallSite;
  #451 = Methodref          #447.#450     // java/lang/invoke/StringConcatFactory.makeConcatWithConstants:(Ljava/lang/invoke/MethodHandles$Lookup;Ljava/lang/String;Ljava/lang/invoke/MethodType;Ljava/lang/String;[Ljava/lang/Object;)Ljava/lang/invoke/CallSite;
  #452 = MethodHandle       6:#451        // REF_invokeStatic java/lang/invoke/StringConcatFactory.makeConcatWithConstants:(Ljava/lang/invoke/MethodHandles$Lookup;Ljava/lang/String;Ljava/lang/invoke/MethodType;Ljava/lang/String;[Ljava/lang/Object;)Ljava/lang/invoke/CallSite;
  #453 = NameAndType        #448:#31      // makeConcatWithConstants:(Ljava/lang/String;)Ljava/lang/String;
  #454 = InvokeDynamic      #0:#453       // #0:makeConcatWithConstants:(Ljava/lang/String;)Ljava/lang/String;
  #455 = NameAndType        #102:#421     // error:(Ljava/lang/Object;)V
  #456 = Methodref          #101.#455     // ext/mods/commons/logging/CLogger.error:(Ljava/lang/Object;)V
  #457 = Utf8               ext/mods/quests/QuestData
  #458 = Class              #457          // ext/mods/quests/QuestData
  #459 = Utf8               ()Lext/mods/quests/QuestData;
  #460 = NameAndType        #11:#459      // getInstance:()Lext/mods/quests/QuestData;
  #461 = Methodref          #458.#460     // ext/mods/quests/QuestData.getInstance:()Lext/mods/quests/QuestData;
  #462 = Utf8               ext/mods/Crypta/BattleBossData
  #463 = Class              #462          // ext/mods/Crypta/BattleBossData
  #464 = Utf8               ()Lext/mods/Crypta/BattleBossData;
  #465 = NameAndType        #11:#464      // getInstance:()Lext/mods/Crypta/BattleBossData;
  #466 = Methodref          #463.#465     // ext/mods/Crypta/BattleBossData.getInstance:()Lext/mods/Crypta/BattleBossData;
  #467 = Utf8               ext/mods/battlerboss/tasks/BattleBossCountDownTask
  #468 = Class              #467          // ext/mods/battlerboss/tasks/BattleBossCountDownTask
  #469 = Utf8               ()Lext/mods/battlerboss/tasks/BattleBossCountDownTask;
  #470 = NameAndType        #11:#469      // getInstance:()Lext/mods/battlerboss/tasks/BattleBossCountDownTask;
  #471 = Methodref          #468.#470     // ext/mods/battlerboss/tasks/BattleBossCountDownTask.getInstance:()Lext/mods/battlerboss/tasks/BattleBossCountDownTask;
  #472 = Methodref          #468.#361     // ext/mods/battlerboss/tasks/BattleBossCountDownTask.start:()V
  #473 = Utf8               [Brproject Ext Mods]
  #474 = String             #473          // [Brproject Ext Mods]
  #475 = Utf8               ext/mods/extensions/ExtensionLoader
  #476 = Class              #475          // ext/mods/extensions/ExtensionLoader
  #477 = Utf8               loadExtensions
  #478 = NameAndType        #477:#6       // loadExtensions:()V
  #479 = Methodref          #476.#478     // ext/mods/extensions/ExtensionLoader.loadExtensions:()V
  #480 = Utf8               ext/mods/extensions/listener/manager/GameListenerManager
  #481 = Class              #480          // ext/mods/extensions/listener/manager/GameListenerManager
  #482 = Utf8               ()Lext/mods/extensions/listener/manager/GameListenerManager;
  #483 = NameAndType        #11:#482      // getInstance:()Lext/mods/extensions/listener/manager/GameListenerManager;
  #484 = Methodref          #481.#483     // ext/mods/extensions/listener/manager/GameListenerManager.getInstance:()Lext/mods/extensions/listener/manager/GameListenerManager;
  #485 = Utf8               notifyStart
  #486 = NameAndType        #485:#6       // notifyStart:()V
  #487 = Methodref          #481.#486     // ext/mods/extensions/listener/manager/GameListenerManager.notifyStart:()V
  #488 = Utf8               ext/mods/gameserver/listener/AgathionTeleportListener
  #489 = Class              #488          // ext/mods/gameserver/listener/AgathionTeleportListener
  #490 = Methodref          #489.#7       // ext/mods/gameserver/listener/AgathionTeleportListener."<init>":()V
  #491 = Utf8               ext/mods/extensions/listener/manager/PlayerListenerManager
  #492 = Class              #491          // ext/mods/extensions/listener/manager/PlayerListenerManager
  #493 = Utf8               ()Lext/mods/extensions/listener/manager/PlayerListenerManager;
  #494 = NameAndType        #11:#493      // getInstance:()Lext/mods/extensions/listener/manager/PlayerListenerManager;
  #495 = Methodref          #492.#494     // ext/mods/extensions/listener/manager/PlayerListenerManager.getInstance:()Lext/mods/extensions/listener/manager/PlayerListenerManager;
  #496 = Utf8               ext/mods/extensions/listener/actor/player/OnTeleportListener
  #497 = Class              #496          // ext/mods/extensions/listener/actor/player/OnTeleportListener
  #498 = Utf8               registerTeleportListener
  #499 = Utf8               (Lext/mods/extensions/listener/actor/player/OnTeleportListener;)V
  #500 = NameAndType        #498:#499     // registerTeleportListener:(Lext/mods/extensions/listener/actor/player/OnTeleportListener;)V
  #501 = Methodref          #492.#500     // ext/mods/extensions/listener/manager/PlayerListenerManager.registerTeleportListener:(Lext/mods/extensions/listener/actor/player/OnTeleportListener;)V
  #502 = Utf8               Failed to initialize AgathionTeleportListener: \u0001
  #503 = String             #502          // Failed to initialize AgathionTeleportListener: \u0001
  #504 = InvokeDynamic      #1:#453       // #1:makeConcatWithConstants:(Ljava/lang/String;)Ljava/lang/String;
  #505 = Utf8               agathionListener
  #506 = Utf8               Lext/mods/gameserver/listener/AgathionTeleportListener;
  #507 = Utf8               access$createDirectories
  #508 = Utf8               (Lext/mods/gameserver/GameServer$Companion;)V
  #509 = NameAndType        #66:#6        // createDirectories:()V
  #510 = Methodref          #2.#509       // ext/mods/gameserver/GameServer$Companion.createDirectories:()V
  #511 = Utf8               $this
  #512 = Utf8               access$getTimeUntilMidnight
  #513 = Utf8               (Lext/mods/gameserver/GameServer$Companion;)J
  #514 = NameAndType        #144:#145     // getTimeUntilMidnight:()J
  #515 = Methodref          #2.#514       // ext/mods/gameserver/GameServer$Companion.getTimeUntilMidnight:()J
  #516 = Utf8               (Lkotlin/jvm/internal/DefaultConstructorMarker;)V
  #517 = Methodref          #2.#7         // ext/mods/gameserver/GameServer$Companion."<init>":()V
  #518 = Utf8               $constructor_marker
  #519 = Utf8               Lkotlin/jvm/internal/DefaultConstructorMarker;
  #520 = Utf8               Lkotlin/Metadata;
  #521 = Utf8               mv
  #522 = Integer            2
  #523 = Integer            3
  #524 = Integer            0
  #525 = Utf8               k
  #526 = Integer            1
  #527 = Utf8               xi
  #528 = Integer            48
  #529 = Utf8               d1
  #530 = Utf8               \u00004\n\u0002\u0018\u0002\n\u0002\u0010\u0000\n\u0002\b\u0003\n\u0002\u0018\u0002\n\u0000\n\u0002\u0018\u0002\n\u0002\b\u0005\n\u0002\u0010\u0002\n\u0000\n\u0002\u0010\u0011\n\u0002\u0010\u000e\n\u0002\b\u0006\n\u0002\u0010\t\n\u0002\b\u0002\b\u0086\u0003\u0018\u00002\u00020\u0001B\t\b\u0002Â˘\u0006\u0004\b\u0002\u0010\u0003J\u001b\u0010\f\u001a\u00020\r2\f\u0010\u000e\u001a\b\u0012\u0004\u0012\u00020\u00100\u000fH\u0007Â˘\u0006\u0002\u0010\u0011J\b\u0010\u0012\u001a\u00020\rH\u0002J\u0010\u0010\u0013\u001a\u00020\r2\u0006\u0010\u0014\u001a\u00020\u0010H\u0002J\u0010\u0010\u0015\u001a\u00020\r2\u0006\u0010\u0014\u001a\u00020\u0010H\u0002J\b\u0010\u0016\u001a\u00020\u0017H\u0002J\b\u0010\u0018\u001a\u00020\rH\u0007R\u000e\u0010\u0004\u001a\u00020\u0005X\u0082\u0004Â˘\u0006\u0002\n\u0000R*\u0010\b\u001a\u0004\u0018\u00010\u00072\b\u0010\u0006\u001a\u0004\u0018\u00010\u00078\u0006@BX\u0087\u000eÂ˘\u0006\u000e\n\u0000\u0012\u0004\b\t\u0010\u0003\u001a\u0004\b\n\u0010\u000bÂ¨\u0006\u0019
  #531 = Utf8               d2
  #532 = Utf8
  #533 = Utf8               LOGGER
  #534 = Utf8               Lext/mods/commons/logging/CLogger;
  #535 = Utf8               value
  #536 = Utf8               Lext/mods/gameserver/GameServer;
  #537 = Utf8               instance
  #538 = Utf8               Brproject
  #539 = Utf8               Companion
  #540 = Utf8               GameServer.kt
  #541 = Utf8               Code
  #542 = Utf8               LineNumberTable
  #543 = Utf8               LocalVariableTable
  #544 = Utf8               RuntimeInvisibleAnnotations
  #545 = Utf8               Deprecated
  #546 = Utf8               RuntimeVisibleAnnotations
  #547 = Utf8               StackMapTable
  #548 = Utf8               RuntimeInvisibleParameterAnnotations
  #549 = Utf8               InnerClasses
  #550 = Utf8               SourceFile
  #551 = Utf8               BootstrapMethods
{
  public final ext.mods.gameserver.GameServer getInstance();
    descriptor: ()Lext/mods/gameserver/GameServer;
    flags: (0x0011) ACC_PUBLIC, ACC_FINAL
    Code:
      stack=1, locals=1, args_size=1
         0: invokestatic  #18                 // Method ext/mods/gameserver/GameServer.access$getInstance$cp:()Lext/mods/gameserver/GameServer;
         3: areturn
      LineNumberTable:
        line 222: 0
      LocalVariableTable:
        Start  Length  Slot  Name   Signature
            0       4     0  this   Lext/mods/gameserver/GameServer$Companion;
    RuntimeInvisibleAnnotations:
      0: #13()
        org.jetbrains.annotations.Nullable

  public static void getInstance$annotations();
    descriptor: ()V
    flags: (0x1009) ACC_PUBLIC, ACC_STATIC, ACC_SYNTHETIC
    Code:
      stack=0, locals=0, args_size=0
         0: return
    Deprecated: true
    RuntimeVisibleAnnotations:
      0: #20()
        kotlin.jvm.JvmStatic

  public final void main(java.lang.String[]);
    descriptor: ([Ljava/lang/String;)V
    flags: (0x0011) ACC_PUBLIC, ACC_FINAL
    Code:
      stack=3, locals=2, args_size=2
         0: ldc           #25                 // String true
         2: ldc           #27                 // String brproject.safe.graphics
         4: invokestatic  #33                 // Method java/lang/System.getProperty:(Ljava/lang/String;)Ljava/lang/String;
         7: iconst_1
         8: invokestatic  #39                 // Method kotlin/text/StringsKt.equals:(Ljava/lang/String;Ljava/lang/String;Z)Z
        11: ifeq          38
        14: ldc           #41                 // String sun.java2d.opengl
        16: ldc           #43                 // String false
        18: invokestatic  #47                 // Method java/lang/System.setProperty:(Ljava/lang/String;Ljava/lang/String;)Ljava/lang/String;
        21: pop
        22: ldc           #49                 // String sun.java2d.d3d
        24: ldc           #43                 // String false
        26: invokestatic  #47                 // Method java/lang/System.setProperty:(Ljava/lang/String;Ljava/lang/String;)Ljava/lang/String;
        29: pop
        30: ldc           #51                 // String sun.java2d.pmoffscreen
        32: ldc           #43                 // String false
        34: invokestatic  #47                 // Method java/lang/System.setProperty:(Ljava/lang/String;Ljava/lang/String;)Ljava/lang/String;
        37: pop
        38: invokestatic  #56                 // Method ext/mods/commons/Team.infoGameServer:()V
        41: invokestatic  #61                 // Method ext/mods/commons/util/JvmOptimizer.initialize:()V
        44: new           #15                 // class ext/mods/gameserver/GameServer
        47: dup
        48: aload_1
        49: invokespecial #63                 // Method ext/mods/gameserver/GameServer."<init>":([Ljava/lang/String;)V
        52: pop
        53: return
      StackMapTable: number_of_entries = 1
        frame_type = 38 /* same */
      LineNumberTable:
        line 226: 0
        line 227: 14
        line 228: 22
        line 229: 30
        line 231: 38
        line 232: 41
        line 233: 44
        line 234: 53
      LocalVariableTable:
        Start  Length  Slot  Name   Signature
            0      54     0  this   Lext/mods/gameserver/GameServer$Companion;
            0      54     1  args   [Ljava/lang/String;
    RuntimeVisibleAnnotations:
      0: #20()
        kotlin.jvm.JvmStatic
    RuntimeInvisibleParameterAnnotations:
      parameter 0:
        0: #23()
          org.jetbrains.annotations.NotNull

  public final void customMods();
    descriptor: ()V
    flags: (0x0011) ACC_PUBLIC, ACC_FINAL
    Code:
      stack=2, locals=2, args_size=1
         0: ldc           #155                // String Custom Mods: initialization...
         2: invokestatic  #160                // Method ext/mods/commons/lang/StringUtil.printSection:(Ljava/lang/String;)V
         5: invokestatic  #165                // Method ext/mods/gameserver/custom/data/BalanceData.getInstance:()Lext/mods/gameserver/custom/data/BalanceData;
         8: invokevirtual #168                // Method ext/mods/gameserver/custom/data/BalanceData.init:()V
        11: invokestatic  #173                // Method ext/mods/gameserver/custom/data/RatesData.getInstance:()Lext/mods/gameserver/custom/data/RatesData;
        14: pop
        15: getstatic     #176                // Field ext/mods/Config.OFFLINE_TRADE_ENABLE:Z
        18: ifne          27
        21: getstatic     #179                // Field ext/mods/Config.OFFLINE_CRAFT_ENABLE:Z
        24: ifeq          39
        27: getstatic     #182                // Field ext/mods/Config.RESTORE_OFFLINERS:Z
        30: ifeq          39
        33: invokestatic  #187                // Method ext/mods/gameserver/data/sql/OfflineTradersTable.getInstance:()Lext/mods/gameserver/data/sql/OfflineTradersTable;
        36: invokevirtual #190                // Method ext/mods/gameserver/data/sql/OfflineTradersTable.restore:()V
        39: invokestatic  #195                // Method ext/mods/gameserver/data/manager/CoupleManager.getInstance:()Lext/mods/gameserver/data/manager/CoupleManager;
        42: pop
        43: invokestatic  #200                // Method ext/mods/gameserver/custom/data/EventsData.getInstance:()Lext/mods/gameserver/custom/data/EventsData;
        46: pop
        47: invokestatic  #205                // Method ext/mods/gameserver/data/manager/EventsDropManager.getInstance:()Lext/mods/gameserver/data/manager/EventsDropManager;
        50: pop
        51: invokestatic  #210                // Method ext/mods/gameserver/model/entity/events/capturetheflag/CTFManager.getInstance:()Lext/mods/gameserver/model/entity/events/capturetheflag/CTFManager;
        54: pop
        55: invokestatic  #215                // Method ext/mods/gameserver/model/entity/events/deathmatch/DMManager.getInstance:()Lext/mods/gameserver/model/entity/events/deathmatch/DMManager;
        58: pop
        59: invokestatic  #220                // Method ext/mods/gameserver/model/entity/events/lastman/LMManager.getInstance:()Lext/mods/gameserver/model/entity/events/lastman/LMManager;
        62: pop
        63: invokestatic  #225                // Method ext/mods/gameserver/model/entity/events/teamvsteam/TvTManager.getInstance:()Lext/mods/gameserver/model/entity/events/teamvsteam/TvTManager;
        66: pop
        67: invokestatic  #230                // Method ext/mods/gameserver/custom/data/EnchantData.getInstance:()Lext/mods/gameserver/custom/data/EnchantData;
        70: pop
        71: invokestatic  #235                // Method ext/mods/gameserver/data/manager/AntiFeedManager.getInstance:()Lext/mods/gameserver/data/manager/AntiFeedManager;
        74: iconst_0
        75: invokevirtual #239                // Method ext/mods/gameserver/data/manager/AntiFeedManager.registerEvent:(I)V
        78: invokestatic  #244                // Method ext/mods/gameserver/data/manager/PcCafeManager.getInstance:()Lext/mods/gameserver/data/manager/PcCafeManager;
        81: pop
        82: ldc           #246                // String CapsuleBox - Terius
        84: invokestatic  #160                // Method ext/mods/commons/lang/StringUtil.printSection:(Ljava/lang/String;)V
        87: invokestatic  #251                // Method ext/mods/CapsuleBox/CapsuleBoxData.getInstance:()Lext/mods/CapsuleBox/CapsuleBoxData;
        90: pop
        91: invokestatic  #256                // Method ext/mods/gameserver/data/xml/StaticSpawnData.getInstance:()Lext/mods/gameserver/data/xml/StaticSpawnData;
        94: pop
        95: invokestatic  #261                // Method ext/mods/gameserver/handler/voicedcommandhandlers/Raid.load:()V
        98: invokestatic  #264                // Method ext/mods/gameserver/handler/voicedcommandhandlers/Epic.load:()V
       101: invokestatic  #269                // Method ext/mods/gameserver/communitybbs/custom/AuctionBBSManager.getInstance:()Lext/mods/gameserver/communitybbs/custom/AuctionBBSManager;
       104: invokevirtual #270                // Method ext/mods/gameserver/communitybbs/custom/AuctionBBSManager.load:()V
       107: invokestatic  #275                // Method ext/mods/gameserver/custom/data/AuctionCurrencies.getInstance:()Lext/mods/gameserver/custom/data/AuctionCurrencies;
       110: pop
       111: invokestatic  #280                // Method ext/mods/gameserver/model/entity/autofarm/AutoFarmManager.getInstance:()Lext/mods/gameserver/model/entity/autofarm/AutoFarmManager;
       114: pop
       115: invokestatic  #285                // Method ext/mods/gameserver/model/entity/autofarm/AutoFarmTask.getInstance:()Lext/mods/gameserver/model/entity/autofarm/AutoFarmTask;
       118: pop
       119: getstatic     #288                // Field ext/mods/Config.SELLBUFF_ENABLED:Z
       122: ifeq          129
       125: invokestatic  #293                // Method ext/mods/gameserver/data/manager/SellBuffsManager.getInstance:()Lext/mods/gameserver/data/manager/SellBuffsManager;
       128: pop
       129: invokestatic  #298                // Method ext/mods/gameserver/custom/data/DonateData.getInstance:()Lext/mods/gameserver/custom/data/DonateData;
       132: pop
       133: getstatic     #301                // Field ext/mods/Config.ENABLE_PIX_MOD:Z
       136: ifeq          149
       139: getstatic     #304                // Field ext/mods/Config.DONATION_ENABLED:Z
       142: ifeq          149
       145: invokestatic  #309                // Method net/sf/donationmanager/DonationManager.getInstance:()Lnet/sf/donationmanager/DonationManager;
       148: pop
       149: invokestatic  #314                // Method ext/mods/gameserver/custom/data/MissionData.getInstance:()Lext/mods/gameserver/custom/data/MissionData;
       152: pop
       153: invokestatic  #319                // Method ext/mods/gameserver/custom/data/PvPData.getInstance:()Lext/mods/gameserver/custom/data/PvPData;
       156: pop
       157: invokestatic  #324                // Method ext/mods/Crypta/AgathionData.getInstance:()Lext/mods/Crypta/AgathionData;
       160: pop
       161: invokestatic  #329                // Method ext/mods/gameserver/custom/data/PolymorphData.getInstance:()Lext/mods/gameserver/custom/data/PolymorphData;
       164: pop
       165: invokestatic  #334                // Method ext/mods/gameserver/custom/data/RaidDropAnnounceData.getInstance:()Lext/mods/gameserver/custom/data/RaidDropAnnounceData;
       168: pop
       169: invokestatic  #339                // Method ext/mods/gameserver/custom/data/EquipGradeRestrictionData.getInstance:()Lext/mods/gameserver/custom/data/EquipGradeRestrictionData;
       172: pop
       173: invokestatic  #344                // Method ext/mods/gameserver/custom/data/BossHpAnnounceData.getInstance:()Lext/mods/gameserver/custom/data/BossHpAnnounceData;
       176: pop
       177: invokestatic  #349                // Method ext/mods/BossZerg/BossZergManager.getInstance:()Lext/mods/BossZerg/BossZergManager;
       180: pop
       181: invokestatic  #354                // Method ext/mods/FarmEventRandom/RandomData.getInstance:()Lext/mods/FarmEventRandom/RandomData;
       184: pop
       185: invokestatic  #359                // Method ext/mods/Crypta/RandomManager.getInstance:()Lext/mods/Crypta/RandomManager;
       188: invokevirtual #362                // Method ext/mods/Crypta/RandomManager.start:()V
       191: invokestatic  #367                // Method ext/mods/dungeon/data/DungeonData.getInstance:()Lext/mods/dungeon/data/DungeonData;
       194: pop
       195: invokestatic  #372                // Method ext/mods/roulette/RouletteData.getInstance:()Lext/mods/roulette/RouletteData;
       198: pop
       199: invokestatic  #377                // Method ext/mods/playergod/data/PlayerGodData.getInstance:()Lext/mods/playergod/data/PlayerGodData;
       202: pop
       203: invokestatic  #382                // Method ext/mods/dressme/DressMeData.getInstance:()Lext/mods/dressme/DressMeData;
       206: pop
       207: invokestatic  #387                // Method ext/mods/tour/TourData.getInstance:()Lext/mods/tour/TourData;
       210: pop
       211: invokestatic  #392                // Method ext/mods/levelupmaker/LevelUpMakerManager.getInstance:()Lext/mods/levelupmaker/LevelUpMakerManager;
       214: invokevirtual #393                // Method ext/mods/levelupmaker/LevelUpMakerManager.init:()V
       217: invokestatic  #398                // Method ext/mods/email/task/EmailDeliveryTask.getInstance:()Lext/mods/email/task/EmailDeliveryTask;
       220: invokevirtual #401                // Method ext/mods/email/task/EmailDeliveryTask.loadAllPending:()V
       223: invokestatic  #406                // Method ext/mods/fakeplayer/FakePlayerManager.getInstance:()Lext/mods/fakeplayer/FakePlayerManager;
       226: invokevirtual #409                // Method ext/mods/fakeplayer/FakePlayerManager.initialise:()V
       229: getstatic     #412                // Field ext/mods/Config.ALLOW_GUARD_SYSTEM:Z
       232: ifeq          241
       235: invokestatic  #417                // Method ext/mods/protection/hwid/hwid.Init:()V
       238: goto          250
       241: invokestatic  #95                 // Method ext/mods/gameserver/GameServer.access$getLOGGER$cp:()Lext/mods/commons/logging/CLogger;
       244: ldc_w         #419                // String Hwid Manager is disabled.
       247: invokevirtual #423                // Method ext/mods/commons/logging/CLogger.info:(Ljava/lang/Object;)V
       250: nop
       251: invokestatic  #428                // Method ext/mods/sellBuffEngine/BuffShopConfigs.getInstance:()Lext/mods/sellBuffEngine/BuffShopConfigs;
       254: invokevirtual #431                // Method ext/mods/sellBuffEngine/BuffShopConfigs.loadConfigs:()V
       257: invokestatic  #436                // Method ext/mods/sellBuffEngine/BuffShopManager.getInstance:()Lext/mods/sellBuffEngine/BuffShopManager;
       260: invokevirtual #439                // Method ext/mods/sellBuffEngine/BuffShopManager.restoreOfflineTraders:()V
       263: goto          282
       266: astore_1
       267: invokestatic  #95                 // Method ext/mods/gameserver/GameServer.access$getLOGGER$cp:()Lext/mods/commons/logging/CLogger;
       270: aload_1
       271: invokevirtual #443                // Method java/lang/Exception.getMessage:()Ljava/lang/String;
       274: invokedynamic #454,  0            // InvokeDynamic #0:makeConcatWithConstants:(Ljava/lang/String;)Ljava/lang/String;
       279: invokevirtual #456                // Method ext/mods/commons/logging/CLogger.error:(Ljava/lang/Object;)V
       282: invokestatic  #461                // Method ext/mods/quests/QuestData.getInstance:()Lext/mods/quests/QuestData;
       285: pop
       286: invokestatic  #466                // Method ext/mods/Crypta/BattleBossData.getInstance:()Lext/mods/Crypta/BattleBossData;
       289: pop
       290: invokestatic  #471                // Method ext/mods/battlerboss/tasks/BattleBossCountDownTask.getInstance:()Lext/mods/battlerboss/tasks/BattleBossCountDownTask;
       293: invokevirtual #472                // Method ext/mods/battlerboss/tasks/BattleBossCountDownTask.start:()V
       296: ldc_w         #474                // String [Brproject Ext Mods]
       299: invokestatic  #160                // Method ext/mods/commons/lang/StringUtil.printSection:(Ljava/lang/String;)V
       302: invokestatic  #479                // Method ext/mods/extensions/ExtensionLoader.loadExtensions:()V
       305: invokestatic  #484                // Method ext/mods/extensions/listener/manager/GameListenerManager.getInstance:()Lext/mods/extensions/listener/manager/GameListenerManager;
       308: invokevirtual #487                // Method ext/mods/extensions/listener/manager/GameListenerManager.notifyStart:()V
       311: nop
       312: new           #489                // class ext/mods/gameserver/listener/AgathionTeleportListener
       315: dup
       316: invokespecial #490                // Method ext/mods/gameserver/listener/AgathionTeleportListener."<init>":()V
       319: astore_1
       320: invokestatic  #495                // Method ext/mods/extensions/listener/manager/PlayerListenerManager.getInstance:()Lext/mods/extensions/listener/manager/PlayerListenerManager;
       323: aload_1
       324: checkcast     #497                // class ext/mods/extensions/listener/actor/player/OnTeleportListener
       327: invokevirtual #501                // Method ext/mods/extensions/listener/manager/PlayerListenerManager.registerTeleportListener:(Lext/mods/extensions/listener/actor/player/OnTeleportListener;)V
       330: goto          349
       333: astore_1
       334: invokestatic  #95                 // Method ext/mods/gameserver/GameServer.access$getLOGGER$cp:()Lext/mods/commons/logging/CLogger;
       337: aload_1
       338: invokevirtual #443                // Method java/lang/Exception.getMessage:()Ljava/lang/String;
       341: invokedynamic #504,  0            // InvokeDynamic #1:makeConcatWithConstants:(Ljava/lang/String;)Ljava/lang/String;
       346: invokevirtual #456                // Method ext/mods/commons/logging/CLogger.error:(Ljava/lang/Object;)V
       349: return
      Exception table:
         from    to  target type
           250   263   266   Class java/lang/Exception
           311   330   333   Class java/lang/Exception
      StackMapTable: number_of_entries = 10
        frame_type = 27 /* same */
        frame_type = 11 /* same */
        frame_type = 251 /* same_frame_extended */
          offset_delta = 89
        frame_type = 19 /* same */
        frame_type = 251 /* same_frame_extended */
          offset_delta = 91
        frame_type = 8 /* same */
        frame_type = 79 /* same_locals_1_stack_item */
          stack = [ class java/lang/Exception ]
        frame_type = 15 /* same */
        frame_type = 114 /* same_locals_1_stack_item */
          stack = [ class java/lang/Exception ]
        frame_type = 252 /* append */
          offset_delta = 15
          locals = [ class java/lang/Object ]
      LineNumberTable:
        line 264: 0
        line 265: 5
        line 266: 11
        line 267: 15
        line 268: 33
        line 270: 39
        line 271: 43
        line 272: 47
        line 273: 51
        line 274: 55
        line 275: 59
        line 276: 63
        line 277: 67
        line 278: 71
        line 279: 78
        line 280: 82
        line 281: 87
        line 282: 91
        line 283: 95
        line 284: 98
        line 285: 101
        line 286: 107
        line 287: 111
        line 288: 115
        line 289: 119
        line 290: 129
        line 291: 133
        line 292: 145
        line 293: 149
        line 294: 153
        line 295: 157
        line 296: 161
        line 297: 165
        line 298: 169
        line 299: 173
        line 300: 177
        line 301: 181
        line 302: 185
        line 304: 191
        line 305: 195
        line 306: 199
        line 307: 203
        line 308: 207
        line 309: 211
        line 310: 217
        line 311: 223
        line 312: 229
        line 313: 235
        line 315: 241
        line 317: 250
        line 318: 251
        line 319: 257
        line 320: 266
        line 321: 267
        line 323: 282
        line 324: 286
        line 325: 290
        line 326: 296
        line 327: 302
        line 328: 305
        line 329: 311
        line 330: 312
        line 331: 320
        line 332: 333
        line 333: 334
        line 335: 349
      LocalVariableTable:
        Start  Length  Slot  Name   Signature
          267      15     1     e   Ljava/lang/Exception;
          320      10     1 agathionListener   Lext/mods/gameserver/listener/AgathionTeleportListener;
          334      15     1     e   Ljava/lang/Exception;
            0     350     0  this   Lext/mods/gameserver/GameServer$Companion;
    RuntimeVisibleAnnotations:
      0: #20()
        kotlin.jvm.JvmStatic

  public static final void access$createDirectories(ext.mods.gameserver.GameServer$Companion);
    descriptor: (Lext/mods/gameserver/GameServer$Companion;)V
    flags: (0x1019) ACC_PUBLIC, ACC_STATIC, ACC_FINAL, ACC_SYNTHETIC
    Code:
      stack=1, locals=1, args_size=1
         0: aload_0
         1: invokespecial #510                // Method createDirectories:()V
         4: return
      LineNumberTable:
        line 219: 1
      LocalVariableTable:
        Start  Length  Slot  Name   Signature
            0       5     0 $this   Lext/mods/gameserver/GameServer$Companion;

  public static final long access$getTimeUntilMidnight(ext.mods.gameserver.GameServer$Companion);
    descriptor: (Lext/mods/gameserver/GameServer$Companion;)J
    flags: (0x1019) ACC_PUBLIC, ACC_STATIC, ACC_FINAL, ACC_SYNTHETIC
    Code:
      stack=2, locals=1, args_size=1
         0: aload_0
         1: invokespecial #515                // Method getTimeUntilMidnight:()J
         4: lreturn
      LineNumberTable:
        line 219: 1
      LocalVariableTable:
        Start  Length  Slot  Name   Signature
            0       5     0 $this   Lext/mods/gameserver/GameServer$Companion;

  public ext.mods.gameserver.GameServer$Companion(kotlin.jvm.internal.DefaultConstructorMarker);
    descriptor: (Lkotlin/jvm/internal/DefaultConstructorMarker;)V
    flags: (0x1001) ACC_PUBLIC, ACC_SYNTHETIC
    Code:
      stack=1, locals=2, args_size=2
         0: aload_0
         1: invokespecial #517                // Method "<init>":()V
         4: return
      LocalVariableTable:
        Start  Length  Slot  Name   Signature
            0       5     0  this   Lext/mods/gameserver/GameServer$Companion;
            0       5     1 $constructor_marker   Lkotlin/jvm/internal/DefaultConstructorMarker;
}
InnerClasses:
  public static final #539= #2 of #15;    // Companion=class ext/mods/gameserver/GameServer$Companion of class ext/mods/gameserver/GameServer
SourceFile: "GameServer.kt"
RuntimeVisibleAnnotations:
  0: #520(#521=[I#522,I#523,I#524],#525=I#526,#527=I#528,#529=[s#530],#531=[s#10,s#532,s#5,s#6,s#533,s#534,s#535,s#536,s#537,s#19,s#11,s#12,s#21,s#532,s#64,s#532,s#532,s#22,s#66,s#71,s#139,s#89,s#144,s#532,s#153,s#538])
    kotlin.Metadata(
      mv=[2,3,0]
      k=1
      xi=48
      d1=["\u00004\n\u0002\u0018\u0002\n\u0002\u0010\u0000\n\u0002\b\u0003\n\u0002\u0018\u0002\n\u0000\n\u0002\u0018\u0002\n\u0002\b\u0005\n\u0002\u0010\u0002\n\u0000\n\u0002\u0010\u0011\n\u0002\u0010\u000e\n\u0002\b\u0006\n\u0002\u0010\t\n\u0002\b\u0002\b\u0086\u0003\u0018\u00002\u00020\u0001B\t\b\u0002Â˘\u0006\u0004\b\u0002\u0010\u0003J\u001b\u0010\f\u001a\u00020\r2\f\u0010\u000e\u001a\b\u0012\u0004\u0012\u00020\u00100\u000fH\u0007Â˘\u0006\u0002\u0010\u0011J\b\u0010\u0012\u001a\u00020\rH\u0002J\u0010\u0010\u0013\u001a\u00020\r2\u0006\u0010\u0014\u001a\u00020\u0010H\u0002J\u0010\u0010\u0015\u001a\u00020\r2\u0006\u0010\u0014\u001a\u00020\u0010H\u0002J\b\u0010\u0016\u001a\u00020\u0017H\u0002J\b\u0010\u0018\u001a\u00020\rH\u0007R\u000e\u0010\u0004\u001a\u00020\u0005X\u0082\u0004Â˘\u0006\u0002\n\u0000R*\u0010\b\u001a\u0004\u0018\u00010\u00072\b\u0010\u0006\u001a\u0004\u0018\u00010\u00078\u0006@BX\u0087\u000eÂ˘\u0006\u000e\n\u0000\u0012\u0004\b\t\u0010\u0003\u001a\u0004\b\n\u0010\u000bÂ¨\u0006\u0019"]
      d2=["Lext/mods/gameserver/GameServer$Companion;","","<init>","()V","LOGGER","Lext/mods/commons/logging/CLogger;","value","Lext/mods/gameserver/GameServer;","instance","getInstance$annotations","getInstance","()Lext/mods/gameserver/GameServer;","main","","args","","","([Ljava/lang/String;)V","createDirectories","createDirectory","path","createDataDirectory","getTimeUntilMidnight","","customMods","Brproject"]
    )
BootstrapMethods:
  0: #452 REF_invokeStatic java/lang/invoke/StringConcatFactory.makeConcatWithConstants:(Ljava/lang/invoke/MethodHandles$Lookup;Ljava/lang/String;Ljava/lang/invoke/MethodType;Ljava/lang/String;[Ljava/lang/Object;)Ljava/lang/invoke/CallSite;
    Method arguments:
      #445 Failed to initialize Buff Shop System: \u0001
  1: #452 REF_invokeStatic java/lang/invoke/StringConcatFactory.makeConcatWithConstants:(Ljava/lang/invoke/MethodHandles$Lookup;Ljava/lang/String;Ljava/lang/invoke/MethodType;Ljava/lang/String;[Ljava/lang/Object;)Ljava/lang/invoke/CallSite;
    Method arguments:
      #503 Failed to initialize AgathionTeleportListener: \u0001
