// Bytecode for: ext.mods.gameserver.handler.itemhandlers.SummonItems
// File: ext\mods\gameserver\handler\itemhandlers\SummonItems.class

Classfile /c:/Users/User/Desktop/BrProject/bin/main/ext/mods/gameserver/handler/itemhandlers/SummonItems.class
  Last modified 9 de jul de 2026; size 6561 bytes
  MD5 checksum 50b7c89f9a2099e7a0853c873096034e
  Compiled from "SummonItems.java"
public class ext.mods.gameserver.handler.itemhandlers.SummonItems implements ext.mods.gameserver.handler.IItemHandler
  minor version: 0
  major version: 69
  flags: (0x0021) ACC_PUBLIC, ACC_SUPER
  this_class: #270                        // ext/mods/gameserver/handler/itemhandlers/SummonItems
  super_class: #2                         // java/lang/Object
  interfaces: 1, fields: 0, methods: 2, attributes: 1
Constant pool:
    #1 = Methodref          #2.#3         // java/lang/Object."<init>":()V
    #2 = Class              #4            // java/lang/Object
    #3 = NameAndType        #5:#6         // "<init>":()V
    #4 = Utf8               java/lang/Object
    #5 = Utf8               <init>
    #6 = Utf8               ()V
    #7 = Class              #8            // ext/mods/gameserver/model/actor/Player
    #8 = Utf8               ext/mods/gameserver/model/actor/Player
    #9 = Methodref          #10.#11       // ext/mods/gameserver/model/entity/events/capturetheflag/CTFEvent.getInstance:()Lext/mods/gameserver/model/entity/events/capturetheflag/CTFEvent;
   #10 = Class              #12           // ext/mods/gameserver/model/entity/events/capturetheflag/CTFEvent
   #11 = NameAndType        #13:#14       // getInstance:()Lext/mods/gameserver/model/entity/events/capturetheflag/CTFEvent;
   #12 = Utf8               ext/mods/gameserver/model/entity/events/capturetheflag/CTFEvent
   #13 = Utf8               getInstance
   #14 = Utf8               ()Lext/mods/gameserver/model/entity/events/capturetheflag/CTFEvent;
   #15 = Methodref          #10.#16       // ext/mods/gameserver/model/entity/events/capturetheflag/CTFEvent.isStarted:()Z
   #16 = NameAndType        #17:#18       // isStarted:()Z
   #17 = Utf8               isStarted
   #18 = Utf8               ()Z
   #19 = Methodref          #20.#21       // ext/mods/gameserver/model/actor/Playable.getObjectId:()I
   #20 = Class              #22           // ext/mods/gameserver/model/actor/Playable
   #21 = NameAndType        #23:#24       // getObjectId:()I
   #22 = Utf8               ext/mods/gameserver/model/actor/Playable
   #23 = Utf8               getObjectId
   #24 = Utf8               ()I
   #25 = Methodref          #10.#26       // ext/mods/gameserver/model/entity/events/capturetheflag/CTFEvent.onItemSummon:(I)Z
   #26 = NameAndType        #27:#28       // onItemSummon:(I)Z
   #27 = Utf8               onItemSummon
   #28 = Utf8               (I)Z
   #29 = Methodref          #30.#31       // ext/mods/gameserver/model/entity/events/deathmatch/DMEvent.getInstance:()Lext/mods/gameserver/model/entity/events/deathmatch/DMEvent;
   #30 = Class              #32           // ext/mods/gameserver/model/entity/events/deathmatch/DMEvent
   #31 = NameAndType        #13:#33       // getInstance:()Lext/mods/gameserver/model/entity/events/deathmatch/DMEvent;
   #32 = Utf8               ext/mods/gameserver/model/entity/events/deathmatch/DMEvent
   #33 = Utf8               ()Lext/mods/gameserver/model/entity/events/deathmatch/DMEvent;
   #34 = Methodref          #30.#16       // ext/mods/gameserver/model/entity/events/deathmatch/DMEvent.isStarted:()Z
   #35 = Methodref          #30.#26       // ext/mods/gameserver/model/entity/events/deathmatch/DMEvent.onItemSummon:(I)Z
   #36 = Methodref          #37.#38       // ext/mods/gameserver/model/entity/events/lastman/LMEvent.getInstance:()Lext/mods/gameserver/model/entity/events/lastman/LMEvent;
   #37 = Class              #39           // ext/mods/gameserver/model/entity/events/lastman/LMEvent
   #38 = NameAndType        #13:#40       // getInstance:()Lext/mods/gameserver/model/entity/events/lastman/LMEvent;
   #39 = Utf8               ext/mods/gameserver/model/entity/events/lastman/LMEvent
   #40 = Utf8               ()Lext/mods/gameserver/model/entity/events/lastman/LMEvent;
   #41 = Methodref          #37.#16       // ext/mods/gameserver/model/entity/events/lastman/LMEvent.isStarted:()Z
   #42 = Methodref          #37.#26       // ext/mods/gameserver/model/entity/events/lastman/LMEvent.onItemSummon:(I)Z
   #43 = Methodref          #44.#45       // ext/mods/gameserver/model/entity/events/teamvsteam/TvTEvent.getInstance:()Lext/mods/gameserver/model/entity/events/teamvsteam/TvTEvent;
   #44 = Class              #46           // ext/mods/gameserver/model/entity/events/teamvsteam/TvTEvent
   #45 = NameAndType        #13:#47       // getInstance:()Lext/mods/gameserver/model/entity/events/teamvsteam/TvTEvent;
   #46 = Utf8               ext/mods/gameserver/model/entity/events/teamvsteam/TvTEvent
   #47 = Utf8               ()Lext/mods/gameserver/model/entity/events/teamvsteam/TvTEvent;
   #48 = Methodref          #44.#16       // ext/mods/gameserver/model/entity/events/teamvsteam/TvTEvent.isStarted:()Z
   #49 = Methodref          #44.#26       // ext/mods/gameserver/model/entity/events/teamvsteam/TvTEvent.onItemSummon:(I)Z
   #50 = Methodref          #7.#51        // ext/mods/gameserver/model/actor/Player.isSitting:()Z
   #51 = NameAndType        #52:#18       // isSitting:()Z
   #52 = Utf8               isSitting
   #53 = Fieldref           #54.#55       // ext/mods/gameserver/network/SystemMessageId.CANT_MOVE_SITTING:Lext/mods/gameserver/network/SystemMessageId;
   #54 = Class              #56           // ext/mods/gameserver/network/SystemMessageId
   #55 = NameAndType        #57:#58       // CANT_MOVE_SITTING:Lext/mods/gameserver/network/SystemMessageId;
   #56 = Utf8               ext/mods/gameserver/network/SystemMessageId
   #57 = Utf8               CANT_MOVE_SITTING
   #58 = Utf8               Lext/mods/gameserver/network/SystemMessageId;
   #59 = Methodref          #7.#60        // ext/mods/gameserver/model/actor/Player.sendPacket:(Lext/mods/gameserver/network/SystemMessageId;)V
   #60 = NameAndType        #61:#62       // sendPacket:(Lext/mods/gameserver/network/SystemMessageId;)V
   #61 = Utf8               sendPacket
   #62 = Utf8               (Lext/mods/gameserver/network/SystemMessageId;)V
   #63 = Methodref          #7.#64        // ext/mods/gameserver/model/actor/Player.isInObserverMode:()Z
   #64 = NameAndType        #65:#18       // isInObserverMode:()Z
   #65 = Utf8               isInObserverMode
   #66 = Methodref          #7.#67        // ext/mods/gameserver/model/actor/Player.isAllSkillsDisabled:()Z
   #67 = NameAndType        #68:#18       // isAllSkillsDisabled:()Z
   #68 = Utf8               isAllSkillsDisabled
   #69 = Methodref          #7.#70        // ext/mods/gameserver/model/actor/Player.getCast:()Lext/mods/gameserver/model/actor/cast/PlayerCast;
   #70 = NameAndType        #71:#72       // getCast:()Lext/mods/gameserver/model/actor/cast/PlayerCast;
   #71 = Utf8               getCast
   #72 = Utf8               ()Lext/mods/gameserver/model/actor/cast/PlayerCast;
   #73 = Methodref          #74.#75       // ext/mods/gameserver/model/actor/cast/PlayerCast.isCastingNow:()Z
   #74 = Class              #76           // ext/mods/gameserver/model/actor/cast/PlayerCast
   #75 = NameAndType        #77:#18       // isCastingNow:()Z
   #76 = Utf8               ext/mods/gameserver/model/actor/cast/PlayerCast
   #77 = Utf8               isCastingNow
   #78 = Methodref          #79.#80       // ext/mods/gameserver/data/xml/SummonItemData.getInstance:()Lext/mods/gameserver/data/xml/SummonItemData;
   #79 = Class              #81           // ext/mods/gameserver/data/xml/SummonItemData
   #80 = NameAndType        #13:#82       // getInstance:()Lext/mods/gameserver/data/xml/SummonItemData;
   #81 = Utf8               ext/mods/gameserver/data/xml/SummonItemData
   #82 = Utf8               ()Lext/mods/gameserver/data/xml/SummonItemData;
   #83 = Methodref          #84.#85       // ext/mods/gameserver/model/item/instance/ItemInstance.getItemId:()I
   #84 = Class              #86           // ext/mods/gameserver/model/item/instance/ItemInstance
   #85 = NameAndType        #87:#24       // getItemId:()I
   #86 = Utf8               ext/mods/gameserver/model/item/instance/ItemInstance
   #87 = Utf8               getItemId
   #88 = Methodref          #79.#89       // ext/mods/gameserver/data/xml/SummonItemData.getSummonItem:(I)Lext/mods/gameserver/model/holder/IntIntHolder;
   #89 = NameAndType        #90:#91       // getSummonItem:(I)Lext/mods/gameserver/model/holder/IntIntHolder;
   #90 = Utf8               getSummonItem
   #91 = Utf8               (I)Lext/mods/gameserver/model/holder/IntIntHolder;
   #92 = Methodref          #7.#93        // ext/mods/gameserver/model/actor/Player.getSummon:()Lext/mods/gameserver/model/actor/Summon;
   #93 = NameAndType        #94:#95       // getSummon:()Lext/mods/gameserver/model/actor/Summon;
   #94 = Utf8               getSummon
   #95 = Utf8               ()Lext/mods/gameserver/model/actor/Summon;
   #96 = Methodref          #7.#97        // ext/mods/gameserver/model/actor/Player.isMounted:()Z
   #97 = NameAndType        #98:#18       // isMounted:()Z
   #98 = Utf8               isMounted
   #99 = Methodref          #100.#101     // ext/mods/gameserver/model/holder/IntIntHolder.getValue:()I
  #100 = Class              #102          // ext/mods/gameserver/model/holder/IntIntHolder
  #101 = NameAndType        #103:#24      // getValue:()I
  #102 = Utf8               ext/mods/gameserver/model/holder/IntIntHolder
  #103 = Utf8               getValue
  #104 = Fieldref           #54.#105      // ext/mods/gameserver/network/SystemMessageId.SUMMON_ONLY_ONE:Lext/mods/gameserver/network/SystemMessageId;
  #105 = NameAndType        #106:#58      // SUMMON_ONLY_ONE:Lext/mods/gameserver/network/SystemMessageId;
  #106 = Utf8               SUMMON_ONLY_ONE
  #107 = Methodref          #7.#108       // ext/mods/gameserver/model/actor/Player.getAttack:()Lext/mods/gameserver/model/actor/attack/PlayerAttack;
  #108 = NameAndType        #109:#110     // getAttack:()Lext/mods/gameserver/model/actor/attack/PlayerAttack;
  #109 = Utf8               getAttack
  #110 = Utf8               ()Lext/mods/gameserver/model/actor/attack/PlayerAttack;
  #111 = Methodref          #112.#113     // ext/mods/gameserver/model/actor/attack/PlayerAttack.isAttackingNow:()Z
  #112 = Class              #114          // ext/mods/gameserver/model/actor/attack/PlayerAttack
  #113 = NameAndType        #115:#18      // isAttackingNow:()Z
  #114 = Utf8               ext/mods/gameserver/model/actor/attack/PlayerAttack
  #115 = Utf8               isAttackingNow
  #116 = Methodref          #7.#117       // ext/mods/gameserver/model/actor/Player.isInCombat:()Z
  #117 = NameAndType        #118:#18      // isInCombat:()Z
  #118 = Utf8               isInCombat
  #119 = Fieldref           #54.#120      // ext/mods/gameserver/network/SystemMessageId.YOU_CANNOT_SUMMON_IN_COMBAT:Lext/mods/gameserver/network/SystemMessageId;
  #120 = NameAndType        #121:#58      // YOU_CANNOT_SUMMON_IN_COMBAT:Lext/mods/gameserver/network/SystemMessageId;
  #121 = Utf8               YOU_CANNOT_SUMMON_IN_COMBAT
  #122 = Methodref          #7.#123       // ext/mods/gameserver/model/actor/Player.isInBoat:()Z
  #123 = NameAndType        #124:#18      // isInBoat:()Z
  #124 = Utf8               isInBoat
  #125 = Fieldref           #54.#126      // ext/mods/gameserver/network/SystemMessageId.NOT_CALL_PET_FROM_THIS_LOCATION:Lext/mods/gameserver/network/SystemMessageId;
  #126 = NameAndType        #127:#58      // NOT_CALL_PET_FROM_THIS_LOCATION:Lext/mods/gameserver/network/SystemMessageId;
  #127 = Utf8               NOT_CALL_PET_FROM_THIS_LOCATION
  #128 = Methodref          #129.#130     // ext/mods/gameserver/data/xml/NpcData.getInstance:()Lext/mods/gameserver/data/xml/NpcData;
  #129 = Class              #131          // ext/mods/gameserver/data/xml/NpcData
  #130 = NameAndType        #13:#132      // getInstance:()Lext/mods/gameserver/data/xml/NpcData;
  #131 = Utf8               ext/mods/gameserver/data/xml/NpcData
  #132 = Utf8               ()Lext/mods/gameserver/data/xml/NpcData;
  #133 = Methodref          #100.#134     // ext/mods/gameserver/model/holder/IntIntHolder.getId:()I
  #134 = NameAndType        #135:#24      // getId:()I
  #135 = Utf8               getId
  #136 = Methodref          #129.#137     // ext/mods/gameserver/data/xml/NpcData.getTemplate:(I)Lext/mods/gameserver/model/actor/template/NpcTemplate;
  #137 = NameAndType        #138:#139     // getTemplate:(I)Lext/mods/gameserver/model/actor/template/NpcTemplate;
  #138 = Utf8               getTemplate
  #139 = Utf8               (I)Lext/mods/gameserver/model/actor/template/NpcTemplate;
  #140 = Class              #141          // ext/mods/gameserver/model/actor/instance/ChristmasTree
  #141 = Utf8               ext/mods/gameserver/model/actor/instance/ChristmasTree
  #142 = Methodref          #7.#143       // ext/mods/gameserver/model/actor/Player.getKnownTypeInRadius:(Ljava/lang/Class;I)Ljava/util/List;
  #143 = NameAndType        #144:#145     // getKnownTypeInRadius:(Ljava/lang/Class;I)Ljava/util/List;
  #144 = Utf8               getKnownTypeInRadius
  #145 = Utf8               (Ljava/lang/Class;I)Ljava/util/List;
  #146 = InterfaceMethodref #147.#148     // java/util/List.isEmpty:()Z
  #147 = Class              #149          // java/util/List
  #148 = NameAndType        #150:#18      // isEmpty:()Z
  #149 = Utf8               java/util/List
  #150 = Utf8               isEmpty
  #151 = Fieldref           #54.#152      // ext/mods/gameserver/network/SystemMessageId.CANNOT_SUMMON_S1_AGAIN:Lext/mods/gameserver/network/SystemMessageId;
  #152 = NameAndType        #153:#58      // CANNOT_SUMMON_S1_AGAIN:Lext/mods/gameserver/network/SystemMessageId;
  #153 = Utf8               CANNOT_SUMMON_S1_AGAIN
  #154 = Methodref          #155.#156     // ext/mods/gameserver/network/serverpackets/SystemMessage.getSystemMessage:(Lext/mods/gameserver/network/SystemMessageId;)Lext/mods/gameserver/network/serverpackets/SystemMessage;
  #155 = Class              #157          // ext/mods/gameserver/network/serverpackets/SystemMessage
  #156 = NameAndType        #158:#159     // getSystemMessage:(Lext/mods/gameserver/network/SystemMessageId;)Lext/mods/gameserver/network/serverpackets/SystemMessage;
  #157 = Utf8               ext/mods/gameserver/network/serverpackets/SystemMessage
  #158 = Utf8               getSystemMessage
  #159 = Utf8               (Lext/mods/gameserver/network/SystemMessageId;)Lext/mods/gameserver/network/serverpackets/SystemMessage;
  #160 = InterfaceMethodref #147.#161     // java/util/List.get:(I)Ljava/lang/Object;
  #161 = NameAndType        #162:#163     // get:(I)Ljava/lang/Object;
  #162 = Utf8               get
  #163 = Utf8               (I)Ljava/lang/Object;
  #164 = Class              #165          // ext/mods/gameserver/model/actor/Creature
  #165 = Utf8               ext/mods/gameserver/model/actor/Creature
  #166 = Methodref          #155.#167     // ext/mods/gameserver/network/serverpackets/SystemMessage.addCharName:(Lext/mods/gameserver/model/actor/Creature;)Lext/mods/gameserver/network/serverpackets/SystemMessage;
  #167 = NameAndType        #168:#169     // addCharName:(Lext/mods/gameserver/model/actor/Creature;)Lext/mods/gameserver/network/serverpackets/SystemMessage;
  #168 = Utf8               addCharName
  #169 = Utf8               (Lext/mods/gameserver/model/actor/Creature;)Lext/mods/gameserver/network/serverpackets/SystemMessage;
  #170 = Methodref          #7.#171       // ext/mods/gameserver/model/actor/Player.sendPacket:(Lext/mods/gameserver/network/serverpackets/L2GameServerPacket;)V
  #171 = NameAndType        #61:#172      // sendPacket:(Lext/mods/gameserver/network/serverpackets/L2GameServerPacket;)V
  #172 = Utf8               (Lext/mods/gameserver/network/serverpackets/L2GameServerPacket;)V
  #173 = Methodref          #7.#174       // ext/mods/gameserver/model/actor/Player.destroyItem:(Lext/mods/gameserver/model/item/instance/ItemInstance;IZ)Z
  #174 = NameAndType        #175:#176     // destroyItem:(Lext/mods/gameserver/model/item/instance/ItemInstance;IZ)Z
  #175 = Utf8               destroyItem
  #176 = Utf8               (Lext/mods/gameserver/model/item/instance/ItemInstance;IZ)Z
  #177 = Methodref          #7.#178       // ext/mods/gameserver/model/actor/Player.getMove:()Lext/mods/gameserver/model/actor/move/PlayerMove;
  #178 = NameAndType        #179:#180     // getMove:()Lext/mods/gameserver/model/actor/move/PlayerMove;
  #179 = Utf8               getMove
  #180 = Utf8               ()Lext/mods/gameserver/model/actor/move/PlayerMove;
  #181 = Methodref          #182.#183     // ext/mods/gameserver/model/actor/move/PlayerMove.stop:()V
  #182 = Class              #184          // ext/mods/gameserver/model/actor/move/PlayerMove
  #183 = NameAndType        #185:#6       // stop:()V
  #184 = Utf8               ext/mods/gameserver/model/actor/move/PlayerMove
  #185 = Utf8               stop
  #186 = Class              #187          // ext/mods/gameserver/model/spawn/Spawn
  #187 = Utf8               ext/mods/gameserver/model/spawn/Spawn
  #188 = Methodref          #186.#189     // ext/mods/gameserver/model/spawn/Spawn."<init>":(Lext/mods/gameserver/model/actor/template/NpcTemplate;)V
  #189 = NameAndType        #5:#190       // "<init>":(Lext/mods/gameserver/model/actor/template/NpcTemplate;)V
  #190 = Utf8               (Lext/mods/gameserver/model/actor/template/NpcTemplate;)V
  #191 = Methodref          #7.#192       // ext/mods/gameserver/model/actor/Player.getPosition:()Lext/mods/gameserver/model/location/SpawnLocation;
  #192 = NameAndType        #193:#194     // getPosition:()Lext/mods/gameserver/model/location/SpawnLocation;
  #193 = Utf8               getPosition
  #194 = Utf8               ()Lext/mods/gameserver/model/location/SpawnLocation;
  #195 = Methodref          #186.#196     // ext/mods/gameserver/model/spawn/Spawn.setLoc:(Lext/mods/gameserver/model/location/SpawnLocation;)V
  #196 = NameAndType        #197:#198     // setLoc:(Lext/mods/gameserver/model/location/SpawnLocation;)V
  #197 = Utf8               setLoc
  #198 = Utf8               (Lext/mods/gameserver/model/location/SpawnLocation;)V
  #199 = Methodref          #186.#200     // ext/mods/gameserver/model/spawn/Spawn.doSpawn:(Z)Lext/mods/gameserver/model/actor/Npc;
  #200 = NameAndType        #201:#202     // doSpawn:(Z)Lext/mods/gameserver/model/actor/Npc;
  #201 = Utf8               doSpawn
  #202 = Utf8               (Z)Lext/mods/gameserver/model/actor/Npc;
  #203 = Methodref          #7.#204       // ext/mods/gameserver/model/actor/Player.getName:()Ljava/lang/String;
  #204 = NameAndType        #205:#206     // getName:()Ljava/lang/String;
  #205 = Utf8               getName
  #206 = Utf8               ()Ljava/lang/String;
  #207 = Methodref          #208.#209     // ext/mods/gameserver/model/actor/Npc.setTitle:(Ljava/lang/String;)V
  #208 = Class              #210          // ext/mods/gameserver/model/actor/Npc
  #209 = NameAndType        #211:#212     // setTitle:(Ljava/lang/String;)V
  #210 = Utf8               ext/mods/gameserver/model/actor/Npc
  #211 = Utf8               setTitle
  #212 = Utf8               (Ljava/lang/String;)V
  #213 = Methodref          #208.#214     // ext/mods/gameserver/model/actor/Npc.setWalkOrRun:(Z)V
  #214 = NameAndType        #215:#216     // setWalkOrRun:(Z)V
  #215 = Utf8               setWalkOrRun
  #216 = Utf8               (Z)V
  #217 = Methodref          #218.#219     // ext/mods/gameserver/model/actor/template/NpcTemplate.getNpcId:()I
  #218 = Class              #220          // ext/mods/gameserver/model/actor/template/NpcTemplate
  #219 = NameAndType        #221:#24      // getNpcId:()I
  #220 = Utf8               ext/mods/gameserver/model/actor/template/NpcTemplate
  #221 = Utf8               getNpcId
  #222 = Methodref          #7.#223       // ext/mods/gameserver/model/actor/Player.getMissions:()Lext/mods/gameserver/model/actor/container/player/MissionList;
  #223 = NameAndType        #224:#225     // getMissions:()Lext/mods/gameserver/model/actor/container/player/MissionList;
  #224 = Utf8               getMissions
  #225 = Utf8               ()Lext/mods/gameserver/model/actor/container/player/MissionList;
  #226 = Fieldref           #227.#228     // ext/mods/gameserver/enums/actors/MissionType.SPAWN_CHRISTMAS_TREE:Lext/mods/gameserver/enums/actors/MissionType;
  #227 = Class              #229          // ext/mods/gameserver/enums/actors/MissionType
  #228 = NameAndType        #230:#231     // SPAWN_CHRISTMAS_TREE:Lext/mods/gameserver/enums/actors/MissionType;
  #229 = Utf8               ext/mods/gameserver/enums/actors/MissionType
  #230 = Utf8               SPAWN_CHRISTMAS_TREE
  #231 = Utf8               Lext/mods/gameserver/enums/actors/MissionType;
  #232 = Methodref          #233.#234     // ext/mods/gameserver/model/actor/container/player/MissionList.update:(Lext/mods/gameserver/enums/actors/MissionType;)V
  #233 = Class              #235          // ext/mods/gameserver/model/actor/container/player/MissionList
  #234 = NameAndType        #236:#237     // update:(Lext/mods/gameserver/enums/actors/MissionType;)V
  #235 = Utf8               ext/mods/gameserver/model/actor/container/player/MissionList
  #236 = Utf8               update
  #237 = Utf8               (Lext/mods/gameserver/enums/actors/MissionType;)V
  #238 = Class              #239          // java/lang/Exception
  #239 = Utf8               java/lang/Exception
  #240 = Fieldref           #54.#241      // ext/mods/gameserver/network/SystemMessageId.TARGET_CANT_FOUND:Lext/mods/gameserver/network/SystemMessageId;
  #241 = NameAndType        #242:#58      // TARGET_CANT_FOUND:Lext/mods/gameserver/network/SystemMessageId;
  #242 = Utf8               TARGET_CANT_FOUND
  #243 = Methodref          #7.#244       // ext/mods/gameserver/model/actor/Player.getAI:()Lext/mods/gameserver/model/actor/ai/type/PlayerAI;
  #244 = NameAndType        #245:#246     // getAI:()Lext/mods/gameserver/model/actor/ai/type/PlayerAI;
  #245 = Utf8               getAI
  #246 = Utf8               ()Lext/mods/gameserver/model/actor/ai/type/PlayerAI;
  #247 = Methodref          #248.#249     // ext/mods/gameserver/data/SkillTable.getInstance:()Lext/mods/gameserver/data/SkillTable;
  #248 = Class              #250          // ext/mods/gameserver/data/SkillTable
  #249 = NameAndType        #13:#251      // getInstance:()Lext/mods/gameserver/data/SkillTable;
  #250 = Utf8               ext/mods/gameserver/data/SkillTable
  #251 = Utf8               ()Lext/mods/gameserver/data/SkillTable;
  #252 = Methodref          #248.#253     // ext/mods/gameserver/data/SkillTable.getInfo:(II)Lext/mods/gameserver/skills/L2Skill;
  #253 = NameAndType        #254:#255     // getInfo:(II)Lext/mods/gameserver/skills/L2Skill;
  #254 = Utf8               getInfo
  #255 = Utf8               (II)Lext/mods/gameserver/skills/L2Skill;
  #256 = Methodref          #84.#21       // ext/mods/gameserver/model/item/instance/ItemInstance.getObjectId:()I
  #257 = Methodref          #258.#259     // ext/mods/gameserver/model/actor/ai/type/PlayerAI.tryToCast:(Lext/mods/gameserver/model/actor/Creature;Lext/mods/gameserver/skills/L2Skill;ZZI)V
  #258 = Class              #260          // ext/mods/gameserver/model/actor/ai/type/PlayerAI
  #259 = NameAndType        #261:#262     // tryToCast:(Lext/mods/gameserver/model/actor/Creature;Lext/mods/gameserver/skills/L2Skill;ZZI)V
  #260 = Utf8               ext/mods/gameserver/model/actor/ai/type/PlayerAI
  #261 = Utf8               tryToCast
  #262 = Utf8               (Lext/mods/gameserver/model/actor/Creature;Lext/mods/gameserver/skills/L2Skill;ZZI)V
  #263 = Fieldref           #54.#264      // ext/mods/gameserver/network/SystemMessageId.SUMMON_A_PET:Lext/mods/gameserver/network/SystemMessageId;
  #264 = NameAndType        #265:#58      // SUMMON_A_PET:Lext/mods/gameserver/network/SystemMessageId;
  #265 = Utf8               SUMMON_A_PET
  #266 = Methodref          #7.#267       // ext/mods/gameserver/model/actor/Player.mount:(II)Z
  #267 = NameAndType        #268:#269     // mount:(II)Z
  #268 = Utf8               mount
  #269 = Utf8               (II)Z
  #270 = Class              #271          // ext/mods/gameserver/handler/itemhandlers/SummonItems
  #271 = Utf8               ext/mods/gameserver/handler/itemhandlers/SummonItems
  #272 = Class              #273          // ext/mods/gameserver/handler/IItemHandler
  #273 = Utf8               ext/mods/gameserver/handler/IItemHandler
  #274 = Utf8               Code
  #275 = Utf8               LineNumberTable
  #276 = Utf8               LocalVariableTable
  #277 = Utf8               this
  #278 = Utf8               Lext/mods/gameserver/handler/itemhandlers/SummonItems;
  #279 = Utf8               useItem
  #280 = Utf8               (Lext/mods/gameserver/model/actor/Playable;Lext/mods/gameserver/model/item/instance/ItemInstance;Z)V
  #281 = Utf8               player
  #282 = Utf8               Lext/mods/gameserver/model/actor/Player;
  #283 = Utf8               spawn
  #284 = Utf8               Lext/mods/gameserver/model/spawn/Spawn;
  #285 = Utf8               npc
  #286 = Utf8               Lext/mods/gameserver/model/actor/Npc;
  #287 = Utf8               e
  #288 = Utf8               Ljava/lang/Exception;
  #289 = Utf8               trees
  #290 = Utf8               Ljava/util/List;
  #291 = Utf8               playable
  #292 = Utf8               Lext/mods/gameserver/model/actor/Playable;
  #293 = Utf8               item
  #294 = Utf8               Lext/mods/gameserver/model/item/instance/ItemInstance;
  #295 = Utf8               forceUse
  #296 = Utf8               Z
  #297 = Utf8               sitem
  #298 = Utf8               Lext/mods/gameserver/model/holder/IntIntHolder;
  #299 = Utf8               npcTemplate
  #300 = Utf8               Lext/mods/gameserver/model/actor/template/NpcTemplate;
  #301 = Utf8               LocalVariableTypeTable
  #302 = Utf8               Ljava/util/List<Lext/mods/gameserver/model/actor/instance/ChristmasTree;>;
  #303 = Utf8               StackMapTable
  #304 = Utf8               SourceFile
  #305 = Utf8               SummonItems.java
{
  public ext.mods.gameserver.handler.itemhandlers.SummonItems();
    descriptor: ()V
    flags: (0x0001) ACC_PUBLIC
    Code:
      stack=1, locals=1, args_size=1
         0: aload_0
         1: invokespecial #1                  // Method java/lang/Object."<init>":()V
         4: return
      LineNumberTable:
        line 42: 0
      LocalVariableTable:
        Start  Length  Slot  Name   Signature
            0       5     0  this   Lext/mods/gameserver/handler/itemhandlers/SummonItems;

  public void useItem(ext.mods.gameserver.model.actor.Playable, ext.mods.gameserver.model.item.instance.ItemInstance, boolean);
    descriptor: (Lext/mods/gameserver/model/actor/Playable;Lext/mods/gameserver/model/item/instance/ItemInstance;Z)V
    flags: (0x0001) ACC_PUBLIC
    Code:
      stack=6, locals=10, args_size=4
         0: aload_1
         1: instanceof    #7                  // class ext/mods/gameserver/model/actor/Player
         4: ifeq          16
         7: aload_1
         8: checkcast     #7                  // class ext/mods/gameserver/model/actor/Player
        11: astore        4
        13: goto          17
        16: return
        17: invokestatic  #9                  // Method ext/mods/gameserver/model/entity/events/capturetheflag/CTFEvent.getInstance:()Lext/mods/gameserver/model/entity/events/capturetheflag/CTFEvent;
        20: invokevirtual #15                 // Method ext/mods/gameserver/model/entity/events/capturetheflag/CTFEvent.isStarted:()Z
        23: ifeq          39
        26: invokestatic  #9                  // Method ext/mods/gameserver/model/entity/events/capturetheflag/CTFEvent.getInstance:()Lext/mods/gameserver/model/entity/events/capturetheflag/CTFEvent;
        29: aload_1
        30: invokevirtual #19                 // Method ext/mods/gameserver/model/actor/Playable.getObjectId:()I
        33: invokevirtual #25                 // Method ext/mods/gameserver/model/entity/events/capturetheflag/CTFEvent.onItemSummon:(I)Z
        36: ifne          105
        39: invokestatic  #29                 // Method ext/mods/gameserver/model/entity/events/deathmatch/DMEvent.getInstance:()Lext/mods/gameserver/model/entity/events/deathmatch/DMEvent;
        42: invokevirtual #34                 // Method ext/mods/gameserver/model/entity/events/deathmatch/DMEvent.isStarted:()Z
        45: ifeq          61
        48: invokestatic  #29                 // Method ext/mods/gameserver/model/entity/events/deathmatch/DMEvent.getInstance:()Lext/mods/gameserver/model/entity/events/deathmatch/DMEvent;
        51: aload_1
        52: invokevirtual #19                 // Method ext/mods/gameserver/model/actor/Playable.getObjectId:()I
        55: invokevirtual #35                 // Method ext/mods/gameserver/model/entity/events/deathmatch/DMEvent.onItemSummon:(I)Z
        58: ifne          105
        61: invokestatic  #36                 // Method ext/mods/gameserver/model/entity/events/lastman/LMEvent.getInstance:()Lext/mods/gameserver/model/entity/events/lastman/LMEvent;
        64: invokevirtual #41                 // Method ext/mods/gameserver/model/entity/events/lastman/LMEvent.isStarted:()Z
        67: ifeq          83
        70: invokestatic  #36                 // Method ext/mods/gameserver/model/entity/events/lastman/LMEvent.getInstance:()Lext/mods/gameserver/model/entity/events/lastman/LMEvent;
        73: aload_1
        74: invokevirtual #19                 // Method ext/mods/gameserver/model/actor/Playable.getObjectId:()I
        77: invokevirtual #42                 // Method ext/mods/gameserver/model/entity/events/lastman/LMEvent.onItemSummon:(I)Z
        80: ifne          105
        83: invokestatic  #43                 // Method ext/mods/gameserver/model/entity/events/teamvsteam/TvTEvent.getInstance:()Lext/mods/gameserver/model/entity/events/teamvsteam/TvTEvent;
        86: invokevirtual #48                 // Method ext/mods/gameserver/model/entity/events/teamvsteam/TvTEvent.isStarted:()Z
        89: ifeq          106
        92: invokestatic  #43                 // Method ext/mods/gameserver/model/entity/events/teamvsteam/TvTEvent.getInstance:()Lext/mods/gameserver/model/entity/events/teamvsteam/TvTEvent;
        95: aload_1
        96: invokevirtual #19                 // Method ext/mods/gameserver/model/actor/Playable.getObjectId:()I
        99: invokevirtual #49                 // Method ext/mods/gameserver/model/entity/events/teamvsteam/TvTEvent.onItemSummon:(I)Z
       102: ifeq          106
       105: return
       106: aload         4
       108: invokevirtual #50                 // Method ext/mods/gameserver/model/actor/Player.isSitting:()Z
       111: ifeq          123
       114: aload         4
       116: getstatic     #53                 // Field ext/mods/gameserver/network/SystemMessageId.CANT_MOVE_SITTING:Lext/mods/gameserver/network/SystemMessageId;
       119: invokevirtual #59                 // Method ext/mods/gameserver/model/actor/Player.sendPacket:(Lext/mods/gameserver/network/SystemMessageId;)V
       122: return
       123: aload         4
       125: invokevirtual #63                 // Method ext/mods/gameserver/model/actor/Player.isInObserverMode:()Z
       128: ifeq          132
       131: return
       132: aload         4
       134: invokevirtual #66                 // Method ext/mods/gameserver/model/actor/Player.isAllSkillsDisabled:()Z
       137: ifne          151
       140: aload         4
       142: invokevirtual #69                 // Method ext/mods/gameserver/model/actor/Player.getCast:()Lext/mods/gameserver/model/actor/cast/PlayerCast;
       145: invokevirtual #73                 // Method ext/mods/gameserver/model/actor/cast/PlayerCast.isCastingNow:()Z
       148: ifeq          152
       151: return
       152: invokestatic  #78                 // Method ext/mods/gameserver/data/xml/SummonItemData.getInstance:()Lext/mods/gameserver/data/xml/SummonItemData;
       155: aload_2
       156: invokevirtual #83                 // Method ext/mods/gameserver/model/item/instance/ItemInstance.getItemId:()I
       159: invokevirtual #88                 // Method ext/mods/gameserver/data/xml/SummonItemData.getSummonItem:(I)Lext/mods/gameserver/model/holder/IntIntHolder;
       162: astore        5
       164: aload         4
       166: invokevirtual #92                 // Method ext/mods/gameserver/model/actor/Player.getSummon:()Lext/mods/gameserver/model/actor/Summon;
       169: ifnonnull     180
       172: aload         4
       174: invokevirtual #96                 // Method ext/mods/gameserver/model/actor/Player.isMounted:()Z
       177: ifeq          197
       180: aload         5
       182: invokevirtual #99                 // Method ext/mods/gameserver/model/holder/IntIntHolder.getValue:()I
       185: ifle          197
       188: aload         4
       190: getstatic     #104                // Field ext/mods/gameserver/network/SystemMessageId.SUMMON_ONLY_ONE:Lext/mods/gameserver/network/SystemMessageId;
       193: invokevirtual #59                 // Method ext/mods/gameserver/model/actor/Player.sendPacket:(Lext/mods/gameserver/network/SystemMessageId;)V
       196: return
       197: aload         4
       199: invokevirtual #107                // Method ext/mods/gameserver/model/actor/Player.getAttack:()Lext/mods/gameserver/model/actor/attack/PlayerAttack;
       202: invokevirtual #111                // Method ext/mods/gameserver/model/actor/attack/PlayerAttack.isAttackingNow:()Z
       205: ifne          216
       208: aload         4
       210: invokevirtual #116                // Method ext/mods/gameserver/model/actor/Player.isInCombat:()Z
       213: ifeq          225
       216: aload         4
       218: getstatic     #119                // Field ext/mods/gameserver/network/SystemMessageId.YOU_CANNOT_SUMMON_IN_COMBAT:Lext/mods/gameserver/network/SystemMessageId;
       221: invokevirtual #59                 // Method ext/mods/gameserver/model/actor/Player.sendPacket:(Lext/mods/gameserver/network/SystemMessageId;)V
       224: return
       225: aload         4
       227: invokevirtual #122                // Method ext/mods/gameserver/model/actor/Player.isInBoat:()Z
       230: ifeq          242
       233: aload         4
       235: getstatic     #125                // Field ext/mods/gameserver/network/SystemMessageId.NOT_CALL_PET_FROM_THIS_LOCATION:Lext/mods/gameserver/network/SystemMessageId;
       238: invokevirtual #59                 // Method ext/mods/gameserver/model/actor/Player.sendPacket:(Lext/mods/gameserver/network/SystemMessageId;)V
       241: return
       242: invokestatic  #128                // Method ext/mods/gameserver/data/xml/NpcData.getInstance:()Lext/mods/gameserver/data/xml/NpcData;
       245: aload         5
       247: invokevirtual #133                // Method ext/mods/gameserver/model/holder/IntIntHolder.getId:()I
       250: invokevirtual #136                // Method ext/mods/gameserver/data/xml/NpcData.getTemplate:(I)Lext/mods/gameserver/model/actor/template/NpcTemplate;
       253: astore        6
       255: aload         6
       257: ifnonnull     261
       260: return
       261: aload         5
       263: invokevirtual #99                 // Method ext/mods/gameserver/model/holder/IntIntHolder.getValue:()I
       266: tableswitch   { // 0 to 2

                       0: 292

                       1: 443

                       2: 480
                 default: 503
            }
       292: aload         4
       294: ldc           #140                // class ext/mods/gameserver/model/actor/instance/ChristmasTree
       296: sipush        1200
       299: invokevirtual #142                // Method ext/mods/gameserver/model/actor/Player.getKnownTypeInRadius:(Ljava/lang/Class;I)Ljava/util/List;
       302: astore        7
       304: aload         7
       306: invokeinterface #146,  1          // InterfaceMethod java/util/List.isEmpty:()Z
       311: ifne          340
       314: aload         4
       316: getstatic     #151                // Field ext/mods/gameserver/network/SystemMessageId.CANNOT_SUMMON_S1_AGAIN:Lext/mods/gameserver/network/SystemMessageId;
       319: invokestatic  #154                // Method ext/mods/gameserver/network/serverpackets/SystemMessage.getSystemMessage:(Lext/mods/gameserver/network/SystemMessageId;)Lext/mods/gameserver/network/serverpackets/SystemMessage;
       322: aload         7
       324: iconst_0
       325: invokeinterface #160,  2          // InterfaceMethod java/util/List.get:(I)Ljava/lang/Object;
       330: checkcast     #164                // class ext/mods/gameserver/model/actor/Creature
       333: invokevirtual #166                // Method ext/mods/gameserver/network/serverpackets/SystemMessage.addCharName:(Lext/mods/gameserver/model/actor/Creature;)Lext/mods/gameserver/network/serverpackets/SystemMessage;
       336: invokevirtual #170                // Method ext/mods/gameserver/model/actor/Player.sendPacket:(Lext/mods/gameserver/network/serverpackets/L2GameServerPacket;)V
       339: return
       340: aload         4
       342: aload_2
       343: iconst_1
       344: iconst_0
       345: invokevirtual #173                // Method ext/mods/gameserver/model/actor/Player.destroyItem:(Lext/mods/gameserver/model/item/instance/ItemInstance;IZ)Z
       348: ifne          352
       351: return
       352: aload         4
       354: invokevirtual #177                // Method ext/mods/gameserver/model/actor/Player.getMove:()Lext/mods/gameserver/model/actor/move/PlayerMove;
       357: invokevirtual #181                // Method ext/mods/gameserver/model/actor/move/PlayerMove.stop:()V
       360: new           #186                // class ext/mods/gameserver/model/spawn/Spawn
       363: dup
       364: aload         6
       366: invokespecial #188                // Method ext/mods/gameserver/model/spawn/Spawn."<init>":(Lext/mods/gameserver/model/actor/template/NpcTemplate;)V
       369: astore        8
       371: aload         8
       373: aload         4
       375: invokevirtual #191                // Method ext/mods/gameserver/model/actor/Player.getPosition:()Lext/mods/gameserver/model/location/SpawnLocation;
       378: invokevirtual #195                // Method ext/mods/gameserver/model/spawn/Spawn.setLoc:(Lext/mods/gameserver/model/location/SpawnLocation;)V
       381: aload         8
       383: iconst_1
       384: invokevirtual #199                // Method ext/mods/gameserver/model/spawn/Spawn.doSpawn:(Z)Lext/mods/gameserver/model/actor/Npc;
       387: astore        9
       389: aload         9
       391: aload         4
       393: invokevirtual #203                // Method ext/mods/gameserver/model/actor/Player.getName:()Ljava/lang/String;
       396: invokevirtual #207                // Method ext/mods/gameserver/model/actor/Npc.setTitle:(Ljava/lang/String;)V
       399: aload         9
       401: iconst_0
       402: invokevirtual #213                // Method ext/mods/gameserver/model/actor/Npc.setWalkOrRun:(Z)V
       405: aload         6
       407: invokevirtual #217                // Method ext/mods/gameserver/model/actor/template/NpcTemplate.getNpcId:()I
       410: sipush        13007
       413: if_icmpne     427
       416: aload         4
       418: invokevirtual #222                // Method ext/mods/gameserver/model/actor/Player.getMissions:()Lext/mods/gameserver/model/actor/container/player/MissionList;
       421: getstatic     #226                // Field ext/mods/gameserver/enums/actors/MissionType.SPAWN_CHRISTMAS_TREE:Lext/mods/gameserver/enums/actors/MissionType;
       424: invokevirtual #232                // Method ext/mods/gameserver/model/actor/container/player/MissionList.update:(Lext/mods/gameserver/enums/actors/MissionType;)V
       427: goto          503
       430: astore        8
       432: aload         4
       434: getstatic     #240                // Field ext/mods/gameserver/network/SystemMessageId.TARGET_CANT_FOUND:Lext/mods/gameserver/network/SystemMessageId;
       437: invokevirtual #59                 // Method ext/mods/gameserver/model/actor/Player.sendPacket:(Lext/mods/gameserver/network/SystemMessageId;)V
       440: goto          503
       443: aload         4
       445: invokevirtual #243                // Method ext/mods/gameserver/model/actor/Player.getAI:()Lext/mods/gameserver/model/actor/ai/type/PlayerAI;
       448: aload         4
       450: invokestatic  #247                // Method ext/mods/gameserver/data/SkillTable.getInstance:()Lext/mods/gameserver/data/SkillTable;
       453: sipush        2046
       456: iconst_1
       457: invokevirtual #252                // Method ext/mods/gameserver/data/SkillTable.getInfo:(II)Lext/mods/gameserver/skills/L2Skill;
       460: iconst_0
       461: iconst_0
       462: aload_2
       463: invokevirtual #256                // Method ext/mods/gameserver/model/item/instance/ItemInstance.getObjectId:()I
       466: invokevirtual #257                // Method ext/mods/gameserver/model/actor/ai/type/PlayerAI.tryToCast:(Lext/mods/gameserver/model/actor/Creature;Lext/mods/gameserver/skills/L2Skill;ZZI)V
       469: aload         4
       471: getstatic     #263                // Field ext/mods/gameserver/network/SystemMessageId.SUMMON_A_PET:Lext/mods/gameserver/network/SystemMessageId;
       474: invokevirtual #59                 // Method ext/mods/gameserver/model/actor/Player.sendPacket:(Lext/mods/gameserver/network/SystemMessageId;)V
       477: goto          503
       480: aload         4
       482: invokevirtual #177                // Method ext/mods/gameserver/model/actor/Player.getMove:()Lext/mods/gameserver/model/actor/move/PlayerMove;
       485: invokevirtual #181                // Method ext/mods/gameserver/model/actor/move/PlayerMove.stop:()V
       488: aload         4
       490: aload         5
       492: invokevirtual #133                // Method ext/mods/gameserver/model/holder/IntIntHolder.getId:()I
       495: aload_2
       496: invokevirtual #256                // Method ext/mods/gameserver/model/item/instance/ItemInstance.getObjectId:()I
       499: invokevirtual #266                // Method ext/mods/gameserver/model/actor/Player.mount:(II)Z
       502: pop
       503: return
      Exception table:
         from    to  target type
           360   427   430   Class java/lang/Exception
      LineNumberTable:
        line 47: 0
        line 48: 16
        line 50: 17
        line 51: 105
        line 53: 106
        line 55: 114
        line 56: 122
        line 59: 123
        line 60: 131
        line 62: 132
        line 63: 151
        line 65: 152
        line 67: 164
        line 69: 188
        line 70: 196
        line 73: 197
        line 75: 216
        line 76: 224
        line 79: 225
        line 81: 233
        line 82: 241
        line 85: 242
        line 86: 255
        line 87: 260
        line 89: 261
        line 92: 292
        line 93: 304
        line 95: 314
        line 96: 339
        line 99: 340
        line 100: 351
        line 102: 352
        line 106: 360
        line 107: 371
        line 109: 381
        line 110: 389
        line 111: 399
        line 113: 405
        line 114: 416
        line 119: 427
        line 116: 430
        line 118: 432
        line 120: 440
        line 123: 443
        line 124: 469
        line 125: 477
        line 128: 480
        line 129: 488
        line 132: 503
      LocalVariableTable:
        Start  Length  Slot  Name   Signature
           13       3     4 player   Lext/mods/gameserver/model/actor/Player;
          371      56     8 spawn   Lext/mods/gameserver/model/spawn/Spawn;
          389      38     9   npc   Lext/mods/gameserver/model/actor/Npc;
          432       8     8     e   Ljava/lang/Exception;
          304     139     7 trees   Ljava/util/List;
            0     504     0  this   Lext/mods/gameserver/handler/itemhandlers/SummonItems;
            0     504     1 playable   Lext/mods/gameserver/model/actor/Playable;
            0     504     2  item   Lext/mods/gameserver/model/item/instance/ItemInstance;
            0     504     3 forceUse   Z
           17     487     4 player   Lext/mods/gameserver/model/actor/Player;
          164     340     5 sitem   Lext/mods/gameserver/model/holder/IntIntHolder;
          255     249     6 npcTemplate   Lext/mods/gameserver/model/actor/template/NpcTemplate;
      LocalVariableTypeTable:
        Start  Length  Slot  Name   Signature
          304     139     7 trees   Ljava/util/List<Lext/mods/gameserver/model/actor/instance/ChristmasTree;>;
      StackMapTable: number_of_entries = 25
        frame_type = 16 /* same */
        frame_type = 252 /* append */
          offset_delta = 0
          locals = [ class ext/mods/gameserver/model/actor/Player ]
        frame_type = 21 /* same */
        frame_type = 21 /* same */
        frame_type = 21 /* same */
        frame_type = 21 /* same */
        frame_type = 0 /* same */
        frame_type = 16 /* same */
        frame_type = 8 /* same */
        frame_type = 18 /* same */
        frame_type = 0 /* same */
        frame_type = 252 /* append */
          offset_delta = 27
          locals = [ class ext/mods/gameserver/model/holder/IntIntHolder ]
        frame_type = 16 /* same */
        frame_type = 18 /* same */
        frame_type = 8 /* same */
        frame_type = 16 /* same */
        frame_type = 252 /* append */
          offset_delta = 18
          locals = [ class ext/mods/gameserver/model/actor/template/NpcTemplate ]
        frame_type = 30 /* same */
        frame_type = 252 /* append */
          offset_delta = 47
          locals = [ class java/util/List ]
        frame_type = 11 /* same */
        frame_type = 251 /* same_frame_extended */
          offset_delta = 74
        frame_type = 66 /* same_locals_1_stack_item */
          stack = [ class java/lang/Exception ]
        frame_type = 250 /* chop */
          offset_delta = 12
        frame_type = 36 /* same */
        frame_type = 22 /* same */
}
SourceFile: "SummonItems.java"
