// Bytecode for: ext.mods.gameserver.handler.chathandlers.ChatPartyRoomCommander
// File: ext\mods\gameserver\handler\chathandlers\ChatPartyRoomCommander.class

Classfile /c:/Users/User/Desktop/BrProject/bin/main/ext/mods/gameserver/handler/chathandlers/ChatPartyRoomCommander.class
  Last modified 9 de jul de 2026; size 2011 bytes
  MD5 checksum 09e13427016eb232b135a785fffe6e4c
  Compiled from "ChatPartyRoomCommander.java"
public class ext.mods.gameserver.handler.chathandlers.ChatPartyRoomCommander implements ext.mods.gameserver.handler.IChatHandler
  minor version: 0
  major version: 69
  flags: (0x0021) ACC_PUBLIC, ACC_SUPER
  this_class: #35                         // ext/mods/gameserver/handler/chathandlers/ChatPartyRoomCommander
  super_class: #2                         // java/lang/Object
  interfaces: 1, fields: 1, methods: 4, attributes: 1
Constant pool:
   #1 = Methodref          #2.#3          // java/lang/Object."<init>":()V
   #2 = Class              #4             // java/lang/Object
   #3 = NameAndType        #5:#6          // "<init>":()V
   #4 = Utf8               java/lang/Object
   #5 = Utf8               <init>
   #6 = Utf8               ()V
   #7 = Methodref          #8.#9          // ext/mods/gameserver/model/actor/Player.getParty:()Lext/mods/gameserver/model/group/Party;
   #8 = Class              #10            // ext/mods/gameserver/model/actor/Player
   #9 = NameAndType        #11:#12        // getParty:()Lext/mods/gameserver/model/group/Party;
  #10 = Utf8               ext/mods/gameserver/model/actor/Player
  #11 = Utf8               getParty
  #12 = Utf8               ()Lext/mods/gameserver/model/group/Party;
  #13 = Methodref          #14.#15        // ext/mods/gameserver/model/group/Party.getCommandChannel:()Lext/mods/gameserver/model/group/CommandChannel;
  #14 = Class              #16            // ext/mods/gameserver/model/group/Party
  #15 = NameAndType        #17:#18        // getCommandChannel:()Lext/mods/gameserver/model/group/CommandChannel;
  #16 = Utf8               ext/mods/gameserver/model/group/Party
  #17 = Utf8               getCommandChannel
  #18 = Utf8               ()Lext/mods/gameserver/model/group/CommandChannel;
  #19 = Methodref          #20.#21        // ext/mods/gameserver/model/group/CommandChannel.isLeader:(Lext/mods/gameserver/model/actor/Player;)Z
  #20 = Class              #22            // ext/mods/gameserver/model/group/CommandChannel
  #21 = NameAndType        #23:#24        // isLeader:(Lext/mods/gameserver/model/actor/Player;)Z
  #22 = Utf8               ext/mods/gameserver/model/group/CommandChannel
  #23 = Utf8               isLeader
  #24 = Utf8               (Lext/mods/gameserver/model/actor/Player;)Z
  #25 = Class              #26            // ext/mods/gameserver/network/serverpackets/CreatureSay
  #26 = Utf8               ext/mods/gameserver/network/serverpackets/CreatureSay
  #27 = Methodref          #25.#28        // ext/mods/gameserver/network/serverpackets/CreatureSay."<init>":(Lext/mods/gameserver/model/actor/Creature;Lext/mods/gameserver/enums/SayType;Ljava/lang/String;)V
  #28 = NameAndType        #5:#29         // "<init>":(Lext/mods/gameserver/model/actor/Creature;Lext/mods/gameserver/enums/SayType;Ljava/lang/String;)V
  #29 = Utf8               (Lext/mods/gameserver/model/actor/Creature;Lext/mods/gameserver/enums/SayType;Ljava/lang/String;)V
  #30 = Methodref          #20.#31        // ext/mods/gameserver/model/group/CommandChannel.broadcastCreatureSay:(Lext/mods/gameserver/network/serverpackets/CreatureSay;Lext/mods/gameserver/model/actor/Player;)V
  #31 = NameAndType        #32:#33        // broadcastCreatureSay:(Lext/mods/gameserver/network/serverpackets/CreatureSay;Lext/mods/gameserver/model/actor/Player;)V
  #32 = Utf8               broadcastCreatureSay
  #33 = Utf8               (Lext/mods/gameserver/network/serverpackets/CreatureSay;Lext/mods/gameserver/model/actor/Player;)V
  #34 = Fieldref           #35.#36        // ext/mods/gameserver/handler/chathandlers/ChatPartyRoomCommander.COMMAND_IDS:[Lext/mods/gameserver/enums/SayType;
  #35 = Class              #37            // ext/mods/gameserver/handler/chathandlers/ChatPartyRoomCommander
  #36 = NameAndType        #38:#39        // COMMAND_IDS:[Lext/mods/gameserver/enums/SayType;
  #37 = Utf8               ext/mods/gameserver/handler/chathandlers/ChatPartyRoomCommander
  #38 = Utf8               COMMAND_IDS
  #39 = Utf8               [Lext/mods/gameserver/enums/SayType;
  #40 = Class              #41            // ext/mods/gameserver/enums/SayType
  #41 = Utf8               ext/mods/gameserver/enums/SayType
  #42 = Fieldref           #40.#43        // ext/mods/gameserver/enums/SayType.PARTYROOM_COMMANDER:Lext/mods/gameserver/enums/SayType;
  #43 = NameAndType        #44:#45        // PARTYROOM_COMMANDER:Lext/mods/gameserver/enums/SayType;
  #44 = Utf8               PARTYROOM_COMMANDER
  #45 = Utf8               Lext/mods/gameserver/enums/SayType;
  #46 = Class              #47            // ext/mods/gameserver/handler/IChatHandler
  #47 = Utf8               ext/mods/gameserver/handler/IChatHandler
  #48 = Utf8               Code
  #49 = Utf8               LineNumberTable
  #50 = Utf8               LocalVariableTable
  #51 = Utf8               this
  #52 = Utf8               Lext/mods/gameserver/handler/chathandlers/ChatPartyRoomCommander;
  #53 = Utf8               handleChat
  #54 = Utf8               (Lext/mods/gameserver/enums/SayType;Lext/mods/gameserver/model/actor/Player;Ljava/lang/String;Ljava/lang/String;)V
  #55 = Utf8               type
  #56 = Utf8               player
  #57 = Utf8               Lext/mods/gameserver/model/actor/Player;
  #58 = Utf8               target
  #59 = Utf8               Ljava/lang/String;
  #60 = Utf8               text
  #61 = Utf8               party
  #62 = Utf8               Lext/mods/gameserver/model/group/Party;
  #63 = Utf8               channel
  #64 = Utf8               Lext/mods/gameserver/model/group/CommandChannel;
  #65 = Utf8               StackMapTable
  #66 = Utf8               getChatTypeList
  #67 = Utf8               ()[Lext/mods/gameserver/enums/SayType;
  #68 = Utf8               <clinit>
  #69 = Utf8               SourceFile
  #70 = Utf8               ChatPartyRoomCommander.java
{
  public ext.mods.gameserver.handler.chathandlers.ChatPartyRoomCommander();
    descriptor: ()V
    flags: (0x0001) ACC_PUBLIC
    Code:
      stack=1, locals=1, args_size=1
         0: aload_0
         1: invokespecial #1                  // Method java/lang/Object."<init>":()V
         4: return
      LineNumberTable:
        line 27: 0
      LocalVariableTable:
        Start  Length  Slot  Name   Signature
            0       5     0  this   Lext/mods/gameserver/handler/chathandlers/ChatPartyRoomCommander;

  public void handleChat(ext.mods.gameserver.enums.SayType, ext.mods.gameserver.model.actor.Player, java.lang.String, java.lang.String);
    descriptor: (Lext/mods/gameserver/enums/SayType;Lext/mods/gameserver/model/actor/Player;Ljava/lang/String;Ljava/lang/String;)V
    flags: (0x0001) ACC_PUBLIC
    Code:
      stack=6, locals=7, args_size=5
         0: aload_2
         1: invokevirtual #7                  // Method ext/mods/gameserver/model/actor/Player.getParty:()Lext/mods/gameserver/model/group/Party;
         4: astore        5
         6: aload         5
         8: ifnonnull     12
        11: return
        12: aload         5
        14: invokevirtual #13                 // Method ext/mods/gameserver/model/group/Party.getCommandChannel:()Lext/mods/gameserver/model/group/CommandChannel;
        17: astore        6
        19: aload         6
        21: ifnull        33
        24: aload         6
        26: aload_2
        27: invokevirtual #19                 // Method ext/mods/gameserver/model/group/CommandChannel.isLeader:(Lext/mods/gameserver/model/actor/Player;)Z
        30: ifne          34
        33: return
        34: aload         6
        36: new           #25                 // class ext/mods/gameserver/network/serverpackets/CreatureSay
        39: dup
        40: aload_2
        41: aload_1
        42: aload         4
        44: invokespecial #27                 // Method ext/mods/gameserver/network/serverpackets/CreatureSay."<init>":(Lext/mods/gameserver/model/actor/Creature;Lext/mods/gameserver/enums/SayType;Ljava/lang/String;)V
        47: aload_2
        48: invokevirtual #30                 // Method ext/mods/gameserver/model/group/CommandChannel.broadcastCreatureSay:(Lext/mods/gameserver/network/serverpackets/CreatureSay;Lext/mods/gameserver/model/actor/Player;)V
        51: return
      LineNumberTable:
        line 37: 0
        line 38: 6
        line 39: 11
        line 41: 12
        line 42: 19
        line 43: 33
        line 45: 34
        line 46: 51
      LocalVariableTable:
        Start  Length  Slot  Name   Signature
            0      52     0  this   Lext/mods/gameserver/handler/chathandlers/ChatPartyRoomCommander;
            0      52     1  type   Lext/mods/gameserver/enums/SayType;
            0      52     2 player   Lext/mods/gameserver/model/actor/Player;
            0      52     3 target   Ljava/lang/String;
            0      52     4  text   Ljava/lang/String;
            6      46     5 party   Lext/mods/gameserver/model/group/Party;
           19      33     6 channel   Lext/mods/gameserver/model/group/CommandChannel;
      StackMapTable: number_of_entries = 3
        frame_type = 252 /* append */
          offset_delta = 12
          locals = [ class ext/mods/gameserver/model/group/Party ]
        frame_type = 252 /* append */
          offset_delta = 20
          locals = [ class ext/mods/gameserver/model/group/CommandChannel ]
        frame_type = 0 /* same */

  public ext.mods.gameserver.enums.SayType[] getChatTypeList();
    descriptor: ()[Lext/mods/gameserver/enums/SayType;
    flags: (0x0001) ACC_PUBLIC
    Code:
      stack=1, locals=1, args_size=1
         0: getstatic     #34                 // Field COMMAND_IDS:[Lext/mods/gameserver/enums/SayType;
         3: areturn
      LineNumberTable:
        line 51: 0
      LocalVariableTable:
        Start  Length  Slot  Name   Signature
            0       4     0  this   Lext/mods/gameserver/handler/chathandlers/ChatPartyRoomCommander;

  static {};
    descriptor: ()V
    flags: (0x0008) ACC_STATIC
    Code:
      stack=4, locals=0, args_size=0
         0: iconst_1
         1: anewarray     #40                 // class ext/mods/gameserver/enums/SayType
         4: dup
         5: iconst_0
         6: getstatic     #42                 // Field ext/mods/gameserver/enums/SayType.PARTYROOM_COMMANDER:Lext/mods/gameserver/enums/SayType;
         9: aastore
        10: putstatic     #34                 // Field COMMAND_IDS:[Lext/mods/gameserver/enums/SayType;
        13: return
      LineNumberTable:
        line 29: 0
}
SourceFile: "ChatPartyRoomCommander.java"
