// Bytecode for: ext.mods.FarmEventRandom.holder.RamdomConfig
// File: ext\mods\FarmEventRandom\holder\RamdomConfig.class

Classfile /c:/Users/User/Desktop/BrProject/bin/main/ext/mods/FarmEventRandom/holder/RamdomConfig.class
  Last modified 9 de jul de 2026; size 5503 bytes
  MD5 checksum 2e362c816e0cd204934e261b51785824
  Compiled from "RamdomConfig.java"
public class ext.mods.FarmEventRandom.holder.RamdomConfig
  minor version: 0
  major version: 69
  flags: (0x0021) ACC_PUBLIC, ACC_SUPER
  this_class: #16                         // ext/mods/FarmEventRandom/holder/RamdomConfig
  super_class: #2                         // java/lang/Object
  interfaces: 0, fields: 8, methods: 13, attributes: 3
Constant pool:
    #1 = Methodref          #2.#3         // java/lang/Object."<init>":()V
    #2 = Class              #4            // java/lang/Object
    #3 = NameAndType        #5:#6         // "<init>":()V
    #4 = Utf8               java/lang/Object
    #5 = Utf8               <init>
    #6 = Utf8               ()V
    #7 = String             #8            // enable
    #8 = Utf8               enable
    #9 = Methodref          #10.#11       // ext/mods/commons/data/StatSet.getBool:(Ljava/lang/String;Z)Z
   #10 = Class              #12           // ext/mods/commons/data/StatSet
   #11 = NameAndType        #13:#14       // getBool:(Ljava/lang/String;Z)Z
   #12 = Utf8               ext/mods/commons/data/StatSet
   #13 = Utf8               getBool
   #14 = Utf8               (Ljava/lang/String;Z)Z
   #15 = Fieldref           #16.#17       // ext/mods/FarmEventRandom/holder/RamdomConfig._enabled:Z
   #16 = Class              #18           // ext/mods/FarmEventRandom/holder/RamdomConfig
   #17 = NameAndType        #19:#20       // _enabled:Z
   #18 = Utf8               ext/mods/FarmEventRandom/holder/RamdomConfig
   #19 = Utf8               _enabled
   #20 = Utf8               Z
   #21 = String             #22           // name
   #22 = Utf8               name
   #23 = String             #24           // [Unnamed Event]
   #24 = Utf8               [Unnamed Event]
   #25 = Methodref          #10.#26       // ext/mods/commons/data/StatSet.getString:(Ljava/lang/String;Ljava/lang/String;)Ljava/lang/String;
   #26 = NameAndType        #27:#28       // getString:(Ljava/lang/String;Ljava/lang/String;)Ljava/lang/String;
   #27 = Utf8               getString
   #28 = Utf8               (Ljava/lang/String;Ljava/lang/String;)Ljava/lang/String;
   #29 = Fieldref           #16.#30       // ext/mods/FarmEventRandom/holder/RamdomConfig._eventName:Ljava/lang/String;
   #30 = NameAndType        #31:#32       // _eventName:Ljava/lang/String;
   #31 = Utf8               _eventName
   #32 = Utf8               Ljava/lang/String;
   #33 = String             #34           // prepareMinutes
   #34 = Utf8               prepareMinutes
   #35 = Methodref          #10.#36       // ext/mods/commons/data/StatSet.getInteger:(Ljava/lang/String;I)I
   #36 = NameAndType        #37:#38       // getInteger:(Ljava/lang/String;I)I
   #37 = Utf8               getInteger
   #38 = Utf8               (Ljava/lang/String;I)I
   #39 = Fieldref           #16.#40       // ext/mods/FarmEventRandom/holder/RamdomConfig._preparation:I
   #40 = NameAndType        #41:#42       // _preparation:I
   #41 = Utf8               _preparation
   #42 = Utf8               I
   #43 = String             #44           // intervalHours
   #44 = Utf8               intervalHours
   #45 = Fieldref           #16.#46       // ext/mods/FarmEventRandom/holder/RamdomConfig._interval:I
   #46 = NameAndType        #47:#42       // _interval:I
   #47 = Utf8               _interval
   #48 = String             #49           // select
   #49 = Utf8               select
   #50 = Fieldref           #16.#51       // ext/mods/FarmEventRandom/holder/RamdomConfig._zoneValue:I
   #51 = NameAndType        #52:#42       // _zoneValue:I
   #52 = Utf8               _zoneValue
   #53 = String             #54           // announceEnd
   #54 = Utf8               announceEnd
   #55 = Fieldref           #16.#56       // ext/mods/FarmEventRandom/holder/RamdomConfig._announceEndMinutes:I
   #56 = NameAndType        #57:#42       // _announceEndMinutes:I
   #57 = Utf8               _announceEndMinutes
   #58 = String             #59           // days
   #59 = Utf8               days
   #60 = String             #61           // 0,1,2,3,4,5,6
   #61 = Utf8               0,1,2,3,4,5,6
   #62 = String             #63           // ,
   #63 = Utf8               ,
   #64 = Methodref          #65.#66       // java/lang/String.split:(Ljava/lang/String;)[Ljava/lang/String;
   #65 = Class              #67           // java/lang/String
   #66 = NameAndType        #68:#69       // split:(Ljava/lang/String;)[Ljava/lang/String;
   #67 = Utf8               java/lang/String
   #68 = Utf8               split
   #69 = Utf8               (Ljava/lang/String;)[Ljava/lang/String;
   #70 = Methodref          #71.#72       // java/util/Arrays.stream:([Ljava/lang/Object;)Ljava/util/stream/Stream;
   #71 = Class              #73           // java/util/Arrays
   #72 = NameAndType        #74:#75       // stream:([Ljava/lang/Object;)Ljava/util/stream/Stream;
   #73 = Utf8               java/util/Arrays
   #74 = Utf8               stream
   #75 = Utf8               ([Ljava/lang/Object;)Ljava/util/stream/Stream;
   #76 = InvokeDynamic      #0:#77        // #0:apply:()Ljava/util/function/Function;
   #77 = NameAndType        #78:#79       // apply:()Ljava/util/function/Function;
   #78 = Utf8               apply
   #79 = Utf8               ()Ljava/util/function/Function;
   #80 = InterfaceMethodref #81.#82       // java/util/stream/Stream.map:(Ljava/util/function/Function;)Ljava/util/stream/Stream;
   #81 = Class              #83           // java/util/stream/Stream
   #82 = NameAndType        #84:#85       // map:(Ljava/util/function/Function;)Ljava/util/stream/Stream;
   #83 = Utf8               java/util/stream/Stream
   #84 = Utf8               map
   #85 = Utf8               (Ljava/util/function/Function;)Ljava/util/stream/Stream;
   #86 = InvokeDynamic      #1:#77        // #1:apply:()Ljava/util/function/Function;
   #87 = Methodref          #88.#89       // java/util/stream/Collectors.toSet:()Ljava/util/stream/Collector;
   #88 = Class              #90           // java/util/stream/Collectors
   #89 = NameAndType        #91:#92       // toSet:()Ljava/util/stream/Collector;
   #90 = Utf8               java/util/stream/Collectors
   #91 = Utf8               toSet
   #92 = Utf8               ()Ljava/util/stream/Collector;
   #93 = InterfaceMethodref #81.#94       // java/util/stream/Stream.collect:(Ljava/util/stream/Collector;)Ljava/lang/Object;
   #94 = NameAndType        #95:#96       // collect:(Ljava/util/stream/Collector;)Ljava/lang/Object;
   #95 = Utf8               collect
   #96 = Utf8               (Ljava/util/stream/Collector;)Ljava/lang/Object;
   #97 = Class              #98           // java/util/Set
   #98 = Utf8               java/util/Set
   #99 = Fieldref           #16.#100      // ext/mods/FarmEventRandom/holder/RamdomConfig._activeDays:Ljava/util/Set;
  #100 = NameAndType        #101:#102     // _activeDays:Ljava/util/Set;
  #101 = Utf8               _activeDays
  #102 = Utf8               Ljava/util/Set;
  #103 = String             #104          // times
  #104 = Utf8               times
  #105 = String             #106          //
  #106 = Utf8
  #107 = String             #108          // H:mm
  #108 = Utf8               H:mm
  #109 = Methodref          #110.#111     // java/time/format/DateTimeFormatter.ofPattern:(Ljava/lang/String;)Ljava/time/format/DateTimeFormatter;
  #110 = Class              #112          // java/time/format/DateTimeFormatter
  #111 = NameAndType        #113:#114     // ofPattern:(Ljava/lang/String;)Ljava/time/format/DateTimeFormatter;
  #112 = Utf8               java/time/format/DateTimeFormatter
  #113 = Utf8               ofPattern
  #114 = Utf8               (Ljava/lang/String;)Ljava/time/format/DateTimeFormatter;
  #115 = String             #116          // ;
  #116 = Utf8               ;
  #117 = InvokeDynamic      #2:#118       // #2:test:()Ljava/util/function/Predicate;
  #118 = NameAndType        #119:#120     // test:()Ljava/util/function/Predicate;
  #119 = Utf8               test
  #120 = Utf8               ()Ljava/util/function/Predicate;
  #121 = InterfaceMethodref #81.#122      // java/util/stream/Stream.filter:(Ljava/util/function/Predicate;)Ljava/util/stream/Stream;
  #122 = NameAndType        #123:#124     // filter:(Ljava/util/function/Predicate;)Ljava/util/stream/Stream;
  #123 = Utf8               filter
  #124 = Utf8               (Ljava/util/function/Predicate;)Ljava/util/stream/Stream;
  #125 = InvokeDynamic      #3:#126       // #3:apply:(Ljava/time/format/DateTimeFormatter;)Ljava/util/function/Function;
  #126 = NameAndType        #78:#127      // apply:(Ljava/time/format/DateTimeFormatter;)Ljava/util/function/Function;
  #127 = Utf8               (Ljava/time/format/DateTimeFormatter;)Ljava/util/function/Function;
  #128 = Methodref          #88.#129      // java/util/stream/Collectors.toList:()Ljava/util/stream/Collector;
  #129 = NameAndType        #130:#92      // toList:()Ljava/util/stream/Collector;
  #130 = Utf8               toList
  #131 = Class              #132          // java/util/List
  #132 = Utf8               java/util/List
  #133 = Fieldref           #16.#134      // ext/mods/FarmEventRandom/holder/RamdomConfig._activeTimes:Ljava/util/List;
  #134 = NameAndType        #135:#136     // _activeTimes:Ljava/util/List;
  #135 = Utf8               _activeTimes
  #136 = Utf8               Ljava/util/List;
  #137 = Methodref          #138.#139     // java/time/LocalDateTime.now:()Ljava/time/LocalDateTime;
  #138 = Class              #140          // java/time/LocalDateTime
  #139 = NameAndType        #141:#142     // now:()Ljava/time/LocalDateTime;
  #140 = Utf8               java/time/LocalDateTime
  #141 = Utf8               now
  #142 = Utf8               ()Ljava/time/LocalDateTime;
  #143 = Methodref          #138.#144     // java/time/LocalDateTime.getDayOfWeek:()Ljava/time/DayOfWeek;
  #144 = NameAndType        #145:#146     // getDayOfWeek:()Ljava/time/DayOfWeek;
  #145 = Utf8               getDayOfWeek
  #146 = Utf8               ()Ljava/time/DayOfWeek;
  #147 = Methodref          #148.#149     // java/time/DayOfWeek.getValue:()I
  #148 = Class              #150          // java/time/DayOfWeek
  #149 = NameAndType        #151:#152     // getValue:()I
  #150 = Utf8               java/time/DayOfWeek
  #151 = Utf8               getValue
  #152 = Utf8               ()I
  #153 = Methodref          #138.#154     // java/time/LocalDateTime.toLocalTime:()Ljava/time/LocalTime;
  #154 = NameAndType        #155:#156     // toLocalTime:()Ljava/time/LocalTime;
  #155 = Utf8               toLocalTime
  #156 = Utf8               ()Ljava/time/LocalTime;
  #157 = Methodref          #158.#159     // java/time/LocalTime.withSecond:(I)Ljava/time/LocalTime;
  #158 = Class              #160          // java/time/LocalTime
  #159 = NameAndType        #161:#162     // withSecond:(I)Ljava/time/LocalTime;
  #160 = Utf8               java/time/LocalTime
  #161 = Utf8               withSecond
  #162 = Utf8               (I)Ljava/time/LocalTime;
  #163 = Methodref          #158.#164     // java/time/LocalTime.withNano:(I)Ljava/time/LocalTime;
  #164 = NameAndType        #165:#162     // withNano:(I)Ljava/time/LocalTime;
  #165 = Utf8               withNano
  #166 = Methodref          #167.#168     // java/lang/Integer.valueOf:(I)Ljava/lang/Integer;
  #167 = Class              #169          // java/lang/Integer
  #168 = NameAndType        #170:#171     // valueOf:(I)Ljava/lang/Integer;
  #169 = Utf8               java/lang/Integer
  #170 = Utf8               valueOf
  #171 = Utf8               (I)Ljava/lang/Integer;
  #172 = InterfaceMethodref #97.#173      // java/util/Set.contains:(Ljava/lang/Object;)Z
  #173 = NameAndType        #174:#175     // contains:(Ljava/lang/Object;)Z
  #174 = Utf8               contains
  #175 = Utf8               (Ljava/lang/Object;)Z
  #176 = InterfaceMethodref #131.#177     // java/util/List.stream:()Ljava/util/stream/Stream;
  #177 = NameAndType        #74:#178      // stream:()Ljava/util/stream/Stream;
  #178 = Utf8               ()Ljava/util/stream/Stream;
  #179 = InvokeDynamic      #4:#180       // #4:test:(Ljava/time/LocalTime;)Ljava/util/function/Predicate;
  #180 = NameAndType        #119:#181     // test:(Ljava/time/LocalTime;)Ljava/util/function/Predicate;
  #181 = Utf8               (Ljava/time/LocalTime;)Ljava/util/function/Predicate;
  #182 = InterfaceMethodref #81.#183      // java/util/stream/Stream.anyMatch:(Ljava/util/function/Predicate;)Z
  #183 = NameAndType        #184:#185     // anyMatch:(Ljava/util/function/Predicate;)Z
  #184 = Utf8               anyMatch
  #185 = Utf8               (Ljava/util/function/Predicate;)Z
  #186 = Methodref          #158.#187     // java/time/LocalTime.equals:(Ljava/lang/Object;)Z
  #187 = NameAndType        #188:#175     // equals:(Ljava/lang/Object;)Z
  #188 = Utf8               equals
  #189 = Methodref          #158.#190     // java/time/LocalTime.parse:(Ljava/lang/CharSequence;Ljava/time/format/DateTimeFormatter;)Ljava/time/LocalTime;
  #190 = NameAndType        #191:#192     // parse:(Ljava/lang/CharSequence;Ljava/time/format/DateTimeFormatter;)Ljava/time/LocalTime;
  #191 = Utf8               parse
  #192 = Utf8               (Ljava/lang/CharSequence;Ljava/time/format/DateTimeFormatter;)Ljava/time/LocalTime;
  #193 = Methodref          #65.#194      // java/lang/String.isEmpty:()Z
  #194 = NameAndType        #195:#196     // isEmpty:()Z
  #195 = Utf8               isEmpty
  #196 = Utf8               ()Z
  #197 = Utf8               Signature
  #198 = Utf8               Ljava/util/Set<Ljava/lang/Integer;>;
  #199 = Utf8               Ljava/util/List<Ljava/time/LocalTime;>;
  #200 = Utf8               (Lext/mods/commons/data/StatSet;)V
  #201 = Utf8               Code
  #202 = Utf8               LineNumberTable
  #203 = Utf8               LocalVariableTable
  #204 = Utf8               this
  #205 = Utf8               Lext/mods/FarmEventRandom/holder/RamdomConfig;
  #206 = Utf8               set
  #207 = Utf8               Lext/mods/commons/data/StatSet;
  #208 = Utf8               timeFmt
  #209 = Utf8               Ljava/time/format/DateTimeFormatter;
  #210 = Utf8               isEnabled
  #211 = Utf8               getName
  #212 = Utf8               ()Ljava/lang/String;
  #213 = Utf8               getInterval
  #214 = Utf8               getPrepareMinutes
  #215 = Utf8               getZoneValue
  #216 = Utf8               getActiveDays
  #217 = Utf8               ()Ljava/util/Set;
  #218 = Utf8               ()Ljava/util/Set<Ljava/lang/Integer;>;
  #219 = Utf8               getActiveTimes
  #220 = Utf8               ()Ljava/util/List;
  #221 = Utf8               ()Ljava/util/List<Ljava/time/LocalTime;>;
  #222 = Utf8               getAnnounceEndMinutes
  #223 = Utf8               isTimeToRun
  #224 = Utf8               Ljava/time/LocalDateTime;
  #225 = Utf8               currentDay
  #226 = Utf8               currentTime
  #227 = Utf8               Ljava/time/LocalTime;
  #228 = Utf8               StackMapTable
  #229 = Utf8               lambda$isTimeToRun$0
  #230 = Utf8               (Ljava/time/LocalTime;Ljava/time/LocalTime;)Z
  #231 = Utf8               time
  #232 = Utf8               lambda$new$1
  #233 = Utf8               (Ljava/time/format/DateTimeFormatter;Ljava/lang/String;)Ljava/time/LocalTime;
  #234 = Utf8               lambda$new$0
  #235 = Utf8               (Ljava/lang/String;)Z
  #236 = Utf8               s
  #237 = Utf8               SourceFile
  #238 = Utf8               RamdomConfig.java
  #239 = Utf8               BootstrapMethods
  #240 = MethodType         #241          //  (Ljava/lang/Object;)Ljava/lang/Object;
  #241 = Utf8               (Ljava/lang/Object;)Ljava/lang/Object;
  #242 = MethodHandle       5:#243        // REF_invokeVirtual java/lang/String.trim:()Ljava/lang/String;
  #243 = Methodref          #65.#244      // java/lang/String.trim:()Ljava/lang/String;
  #244 = NameAndType        #245:#212     // trim:()Ljava/lang/String;
  #245 = Utf8               trim
  #246 = MethodType         #247          //  (Ljava/lang/String;)Ljava/lang/String;
  #247 = Utf8               (Ljava/lang/String;)Ljava/lang/String;
  #248 = MethodHandle       6:#249        // REF_invokeStatic java/lang/Integer.parseInt:(Ljava/lang/String;)I
  #249 = Methodref          #167.#250     // java/lang/Integer.parseInt:(Ljava/lang/String;)I
  #250 = NameAndType        #251:#252     // parseInt:(Ljava/lang/String;)I
  #251 = Utf8               parseInt
  #252 = Utf8               (Ljava/lang/String;)I
  #253 = MethodType         #254          //  (Ljava/lang/String;)Ljava/lang/Integer;
  #254 = Utf8               (Ljava/lang/String;)Ljava/lang/Integer;
  #255 = MethodType         #175          //  (Ljava/lang/Object;)Z
  #256 = MethodHandle       6:#257        // REF_invokeStatic ext/mods/FarmEventRandom/holder/RamdomConfig.lambda$new$0:(Ljava/lang/String;)Z
  #257 = Methodref          #16.#258      // ext/mods/FarmEventRandom/holder/RamdomConfig.lambda$new$0:(Ljava/lang/String;)Z
  #258 = NameAndType        #234:#235     // lambda$new$0:(Ljava/lang/String;)Z
  #259 = MethodType         #235          //  (Ljava/lang/String;)Z
  #260 = MethodHandle       6:#261        // REF_invokeStatic ext/mods/FarmEventRandom/holder/RamdomConfig.lambda$new$1:(Ljava/time/format/DateTimeFormatter;Ljava/lang/String;)Ljava/time/LocalTime;
  #261 = Methodref          #16.#262      // ext/mods/FarmEventRandom/holder/RamdomConfig.lambda$new$1:(Ljava/time/format/DateTimeFormatter;Ljava/lang/String;)Ljava/time/LocalTime;
  #262 = NameAndType        #232:#233     // lambda$new$1:(Ljava/time/format/DateTimeFormatter;Ljava/lang/String;)Ljava/time/LocalTime;
  #263 = MethodType         #264          //  (Ljava/lang/String;)Ljava/time/LocalTime;
  #264 = Utf8               (Ljava/lang/String;)Ljava/time/LocalTime;
  #265 = MethodHandle       6:#266        // REF_invokeStatic ext/mods/FarmEventRandom/holder/RamdomConfig.lambda$isTimeToRun$0:(Ljava/time/LocalTime;Ljava/time/LocalTime;)Z
  #266 = Methodref          #16.#267      // ext/mods/FarmEventRandom/holder/RamdomConfig.lambda$isTimeToRun$0:(Ljava/time/LocalTime;Ljava/time/LocalTime;)Z
  #267 = NameAndType        #229:#230     // lambda$isTimeToRun$0:(Ljava/time/LocalTime;Ljava/time/LocalTime;)Z
  #268 = MethodType         #269          //  (Ljava/time/LocalTime;)Z
  #269 = Utf8               (Ljava/time/LocalTime;)Z
  #270 = MethodHandle       6:#271        // REF_invokeStatic java/lang/invoke/LambdaMetafactory.metafactory:(Ljava/lang/invoke/MethodHandles$Lookup;Ljava/lang/String;Ljava/lang/invoke/MethodType;Ljava/lang/invoke/MethodType;Ljava/lang/invoke/MethodHandle;Ljava/lang/invoke/MethodType;)Ljava/lang/invoke/CallSite;
  #271 = Methodref          #272.#273     // java/lang/invoke/LambdaMetafactory.metafactory:(Ljava/lang/invoke/MethodHandles$Lookup;Ljava/lang/String;Ljava/lang/invoke/MethodType;Ljava/lang/invoke/MethodType;Ljava/lang/invoke/MethodHandle;Ljava/lang/invoke/MethodType;)Ljava/lang/invoke/CallSite;
  #272 = Class              #274          // java/lang/invoke/LambdaMetafactory
  #273 = NameAndType        #275:#276     // metafactory:(Ljava/lang/invoke/MethodHandles$Lookup;Ljava/lang/String;Ljava/lang/invoke/MethodType;Ljava/lang/invoke/MethodType;Ljava/lang/invoke/MethodHandle;Ljava/lang/invoke/MethodType;)Ljava/lang/invoke/CallSite;
  #274 = Utf8               java/lang/invoke/LambdaMetafactory
  #275 = Utf8               metafactory
  #276 = Utf8               (Ljava/lang/invoke/MethodHandles$Lookup;Ljava/lang/String;Ljava/lang/invoke/MethodType;Ljava/lang/invoke/MethodType;Ljava/lang/invoke/MethodHandle;Ljava/lang/invoke/MethodType;)Ljava/lang/invoke/CallSite;
  #277 = Utf8               InnerClasses
  #278 = Class              #279          // java/lang/invoke/MethodHandles$Lookup
  #279 = Utf8               java/lang/invoke/MethodHandles$Lookup
  #280 = Class              #281          // java/lang/invoke/MethodHandles
  #281 = Utf8               java/lang/invoke/MethodHandles
  #282 = Utf8               Lookup
{
  public ext.mods.FarmEventRandom.holder.RamdomConfig(ext.mods.commons.data.StatSet);
    descriptor: (Lext/mods/commons/data/StatSet;)V
    flags: (0x0001) ACC_PUBLIC
    Code:
      stack=4, locals=5, args_size=2
         0: aload_0
         1: invokespecial #1                  // Method java/lang/Object."<init>":()V
         4: aload_0
         5: aload_1
         6: ldc           #7                  // String enable
         8: iconst_0
         9: invokevirtual #9                  // Method ext/mods/commons/data/StatSet.getBool:(Ljava/lang/String;Z)Z
        12: putfield      #15                 // Field _enabled:Z
        15: aload_0
        16: aload_1
        17: ldc           #21                 // String name
        19: ldc           #23                 // String [Unnamed Event]
        21: invokevirtual #25                 // Method ext/mods/commons/data/StatSet.getString:(Ljava/lang/String;Ljava/lang/String;)Ljava/lang/String;
        24: putfield      #29                 // Field _eventName:Ljava/lang/String;
        27: aload_0
        28: aload_1
        29: ldc           #33                 // String prepareMinutes
        31: iconst_5
        32: invokevirtual #35                 // Method ext/mods/commons/data/StatSet.getInteger:(Ljava/lang/String;I)I
        35: putfield      #39                 // Field _preparation:I
        38: aload_0
        39: aload_1
        40: ldc           #43                 // String intervalHours
        42: bipush        6
        44: invokevirtual #35                 // Method ext/mods/commons/data/StatSet.getInteger:(Ljava/lang/String;I)I
        47: putfield      #45                 // Field _interval:I
        50: aload_0
        51: aload_1
        52: ldc           #48                 // String select
        54: iconst_1
        55: invokevirtual #35                 // Method ext/mods/commons/data/StatSet.getInteger:(Ljava/lang/String;I)I
        58: putfield      #50                 // Field _zoneValue:I
        61: aload_0
        62: aload_1
        63: ldc           #53                 // String announceEnd
        65: iconst_5
        66: invokevirtual #35                 // Method ext/mods/commons/data/StatSet.getInteger:(Ljava/lang/String;I)I
        69: putfield      #55                 // Field _announceEndMinutes:I
        72: aload_1
        73: ldc           #58                 // String days
        75: ldc           #60                 // String 0,1,2,3,4,5,6
        77: invokevirtual #25                 // Method ext/mods/commons/data/StatSet.getString:(Ljava/lang/String;Ljava/lang/String;)Ljava/lang/String;
        80: astore_2
        81: aload_0
        82: aload_2
        83: ldc           #62                 // String ,
        85: invokevirtual #64                 // Method java/lang/String.split:(Ljava/lang/String;)[Ljava/lang/String;
        88: invokestatic  #70                 // Method java/util/Arrays.stream:([Ljava/lang/Object;)Ljava/util/stream/Stream;
        91: invokedynamic #76,  0             // InvokeDynamic #0:apply:()Ljava/util/function/Function;
        96: invokeinterface #80,  2           // InterfaceMethod java/util/stream/Stream.map:(Ljava/util/function/Function;)Ljava/util/stream/Stream;
       101: invokedynamic #86,  0             // InvokeDynamic #1:apply:()Ljava/util/function/Function;
       106: invokeinterface #80,  2           // InterfaceMethod java/util/stream/Stream.map:(Ljava/util/function/Function;)Ljava/util/stream/Stream;
       111: invokestatic  #87                 // Method java/util/stream/Collectors.toSet:()Ljava/util/stream/Collector;
       114: invokeinterface #93,  2           // InterfaceMethod java/util/stream/Stream.collect:(Ljava/util/stream/Collector;)Ljava/lang/Object;
       119: checkcast     #97                 // class java/util/Set
       122: putfield      #99                 // Field _activeDays:Ljava/util/Set;
       125: aload_1
       126: ldc           #103                // String times
       128: ldc           #105                // String
       130: invokevirtual #25                 // Method ext/mods/commons/data/StatSet.getString:(Ljava/lang/String;Ljava/lang/String;)Ljava/lang/String;
       133: astore_3
       134: ldc           #107                // String H:mm
       136: invokestatic  #109                // Method java/time/format/DateTimeFormatter.ofPattern:(Ljava/lang/String;)Ljava/time/format/DateTimeFormatter;
       139: astore        4
       141: aload_0
       142: aload_3
       143: ldc           #115                // String ;
       145: invokevirtual #64                 // Method java/lang/String.split:(Ljava/lang/String;)[Ljava/lang/String;
       148: invokestatic  #70                 // Method java/util/Arrays.stream:([Ljava/lang/Object;)Ljava/util/stream/Stream;
       151: invokedynamic #76,  0             // InvokeDynamic #0:apply:()Ljava/util/function/Function;
       156: invokeinterface #80,  2           // InterfaceMethod java/util/stream/Stream.map:(Ljava/util/function/Function;)Ljava/util/stream/Stream;
       161: invokedynamic #117,  0            // InvokeDynamic #2:test:()Ljava/util/function/Predicate;
       166: invokeinterface #121,  2          // InterfaceMethod java/util/stream/Stream.filter:(Ljava/util/function/Predicate;)Ljava/util/stream/Stream;
       171: aload         4
       173: invokedynamic #125,  0            // InvokeDynamic #3:apply:(Ljava/time/format/DateTimeFormatter;)Ljava/util/function/Function;
       178: invokeinterface #80,  2           // InterfaceMethod java/util/stream/Stream.map:(Ljava/util/function/Function;)Ljava/util/stream/Stream;
       183: invokestatic  #128                // Method java/util/stream/Collectors.toList:()Ljava/util/stream/Collector;
       186: invokeinterface #93,  2           // InterfaceMethod java/util/stream/Stream.collect:(Ljava/util/stream/Collector;)Ljava/lang/Object;
       191: checkcast     #131                // class java/util/List
       194: putfield      #133                // Field _activeTimes:Ljava/util/List;
       197: return
      LineNumberTable:
        line 43: 0
        line 44: 4
        line 45: 15
        line 46: 27
        line 47: 38
        line 48: 50
        line 50: 61
        line 52: 72
        line 53: 81
        line 55: 125
        line 56: 134
        line 57: 141
        line 58: 197
      LocalVariableTable:
        Start  Length  Slot  Name   Signature
            0     198     0  this   Lext/mods/FarmEventRandom/holder/RamdomConfig;
            0     198     1   set   Lext/mods/commons/data/StatSet;
           81     117     2  days   Ljava/lang/String;
          134      64     3 times   Ljava/lang/String;
          141      57     4 timeFmt   Ljava/time/format/DateTimeFormatter;

  public boolean isEnabled();
    descriptor: ()Z
    flags: (0x0001) ACC_PUBLIC
    Code:
      stack=1, locals=1, args_size=1
         0: aload_0
         1: getfield      #15                 // Field _enabled:Z
         4: ireturn
      LineNumberTable:
        line 60: 0
      LocalVariableTable:
        Start  Length  Slot  Name   Signature
            0       5     0  this   Lext/mods/FarmEventRandom/holder/RamdomConfig;

  public java.lang.String getName();
    descriptor: ()Ljava/lang/String;
    flags: (0x0001) ACC_PUBLIC
    Code:
      stack=1, locals=1, args_size=1
         0: aload_0
         1: getfield      #29                 // Field _eventName:Ljava/lang/String;
         4: areturn
      LineNumberTable:
        line 61: 0
      LocalVariableTable:
        Start  Length  Slot  Name   Signature
            0       5     0  this   Lext/mods/FarmEventRandom/holder/RamdomConfig;

  public int getInterval();
    descriptor: ()I
    flags: (0x0001) ACC_PUBLIC
    Code:
      stack=1, locals=1, args_size=1
         0: aload_0
         1: getfield      #45                 // Field _interval:I
         4: ireturn
      LineNumberTable:
        line 62: 0
      LocalVariableTable:
        Start  Length  Slot  Name   Signature
            0       5     0  this   Lext/mods/FarmEventRandom/holder/RamdomConfig;

  public int getPrepareMinutes();
    descriptor: ()I
    flags: (0x0001) ACC_PUBLIC
    Code:
      stack=1, locals=1, args_size=1
         0: aload_0
         1: getfield      #39                 // Field _preparation:I
         4: ireturn
      LineNumberTable:
        line 63: 0
      LocalVariableTable:
        Start  Length  Slot  Name   Signature
            0       5     0  this   Lext/mods/FarmEventRandom/holder/RamdomConfig;

  public int getZoneValue();
    descriptor: ()I
    flags: (0x0001) ACC_PUBLIC
    Code:
      stack=1, locals=1, args_size=1
         0: aload_0
         1: getfield      #50                 // Field _zoneValue:I
         4: ireturn
      LineNumberTable:
        line 64: 0
      LocalVariableTable:
        Start  Length  Slot  Name   Signature
            0       5     0  this   Lext/mods/FarmEventRandom/holder/RamdomConfig;

  public java.util.Set<java.lang.Integer> getActiveDays();
    descriptor: ()Ljava/util/Set;
    flags: (0x0001) ACC_PUBLIC
    Code:
      stack=1, locals=1, args_size=1
         0: aload_0
         1: getfield      #99                 // Field _activeDays:Ljava/util/Set;
         4: areturn
      LineNumberTable:
        line 65: 0
      LocalVariableTable:
        Start  Length  Slot  Name   Signature
            0       5     0  this   Lext/mods/FarmEventRandom/holder/RamdomConfig;
    Signature: #218                         // ()Ljava/util/Set<Ljava/lang/Integer;>;

  public java.util.List<java.time.LocalTime> getActiveTimes();
    descriptor: ()Ljava/util/List;
    flags: (0x0001) ACC_PUBLIC
    Code:
      stack=1, locals=1, args_size=1
         0: aload_0
         1: getfield      #133                // Field _activeTimes:Ljava/util/List;
         4: areturn
      LineNumberTable:
        line 66: 0
      LocalVariableTable:
        Start  Length  Slot  Name   Signature
            0       5     0  this   Lext/mods/FarmEventRandom/holder/RamdomConfig;
    Signature: #221                         // ()Ljava/util/List<Ljava/time/LocalTime;>;

  public int getAnnounceEndMinutes();
    descriptor: ()I
    flags: (0x0001) ACC_PUBLIC
    Code:
      stack=1, locals=1, args_size=1
         0: aload_0
         1: getfield      #55                 // Field _announceEndMinutes:I
         4: ireturn
      LineNumberTable:
        line 73: 0
      LocalVariableTable:
        Start  Length  Slot  Name   Signature
            0       5     0  this   Lext/mods/FarmEventRandom/holder/RamdomConfig;

  public boolean isTimeToRun();
    descriptor: ()Z
    flags: (0x0001) ACC_PUBLIC
    Code:
      stack=2, locals=4, args_size=1
         0: invokestatic  #137                // Method java/time/LocalDateTime.now:()Ljava/time/LocalDateTime;
         3: astore_1
         4: aload_1
         5: invokevirtual #143                // Method java/time/LocalDateTime.getDayOfWeek:()Ljava/time/DayOfWeek;
         8: invokevirtual #147                // Method java/time/DayOfWeek.getValue:()I
        11: bipush        7
        13: irem
        14: istore_2
        15: aload_1
        16: invokevirtual #153                // Method java/time/LocalDateTime.toLocalTime:()Ljava/time/LocalTime;
        19: iconst_0
        20: invokevirtual #157                // Method java/time/LocalTime.withSecond:(I)Ljava/time/LocalTime;
        23: iconst_0
        24: invokevirtual #163                // Method java/time/LocalTime.withNano:(I)Ljava/time/LocalTime;
        27: astore_3
        28: aload_0
        29: getfield      #99                 // Field _activeDays:Ljava/util/Set;
        32: iload_2
        33: invokestatic  #166                // Method java/lang/Integer.valueOf:(I)Ljava/lang/Integer;
        36: invokeinterface #172,  2          // InterfaceMethod java/util/Set.contains:(Ljava/lang/Object;)Z
        41: ifne          46
        44: iconst_0
        45: ireturn
        46: aload_0
        47: getfield      #133                // Field _activeTimes:Ljava/util/List;
        50: invokeinterface #176,  1          // InterfaceMethod java/util/List.stream:()Ljava/util/stream/Stream;
        55: aload_3
        56: invokedynamic #179,  0            // InvokeDynamic #4:test:(Ljava/time/LocalTime;)Ljava/util/function/Predicate;
        61: invokeinterface #182,  2          // InterfaceMethod java/util/stream/Stream.anyMatch:(Ljava/util/function/Predicate;)Z
        66: ireturn
      LineNumberTable:
        line 78: 0
        line 79: 4
        line 80: 15
        line 82: 28
        line 83: 44
        line 85: 46
      LocalVariableTable:
        Start  Length  Slot  Name   Signature
            0      67     0  this   Lext/mods/FarmEventRandom/holder/RamdomConfig;
            4      63     1   now   Ljava/time/LocalDateTime;
           15      52     2 currentDay   I
           28      39     3 currentTime   Ljava/time/LocalTime;
      StackMapTable: number_of_entries = 1
        frame_type = 254 /* append */
          offset_delta = 46
          locals = [ class java/time/LocalDateTime, int, class java/time/LocalTime ]
}
SourceFile: "RamdomConfig.java"
BootstrapMethods:
  0: #270 REF_invokeStatic java/lang/invoke/LambdaMetafactory.metafactory:(Ljava/lang/invoke/MethodHandles$Lookup;Ljava/lang/String;Ljava/lang/invoke/MethodType;Ljava/lang/invoke/MethodType;Ljava/lang/invoke/MethodHandle;Ljava/lang/invoke/MethodType;)Ljava/lang/invoke/CallSite;
    Method arguments:
      #240 (Ljava/lang/Object;)Ljava/lang/Object;
      #242 REF_invokeVirtual java/lang/String.trim:()Ljava/lang/String;
      #246 (Ljava/lang/String;)Ljava/lang/String;
  1: #270 REF_invokeStatic java/lang/invoke/LambdaMetafactory.metafactory:(Ljava/lang/invoke/MethodHandles$Lookup;Ljava/lang/String;Ljava/lang/invoke/MethodType;Ljava/lang/invoke/MethodType;Ljava/lang/invoke/MethodHandle;Ljava/lang/invoke/MethodType;)Ljava/lang/invoke/CallSite;
    Method arguments:
      #240 (Ljava/lang/Object;)Ljava/lang/Object;
      #248 REF_invokeStatic java/lang/Integer.parseInt:(Ljava/lang/String;)I
      #253 (Ljava/lang/String;)Ljava/lang/Integer;
  2: #270 REF_invokeStatic java/lang/invoke/LambdaMetafactory.metafactory:(Ljava/lang/invoke/MethodHandles$Lookup;Ljava/lang/String;Ljava/lang/invoke/MethodType;Ljava/lang/invoke/MethodType;Ljava/lang/invoke/MethodHandle;Ljava/lang/invoke/MethodType;)Ljava/lang/invoke/CallSite;
    Method arguments:
      #255 (Ljava/lang/Object;)Z
      #256 REF_invokeStatic ext/mods/FarmEventRandom/holder/RamdomConfig.lambda$new$0:(Ljava/lang/String;)Z
      #259 (Ljava/lang/String;)Z
  3: #270 REF_invokeStatic java/lang/invoke/LambdaMetafactory.metafactory:(Ljava/lang/invoke/MethodHandles$Lookup;Ljava/lang/String;Ljava/lang/invoke/MethodType;Ljava/lang/invoke/MethodType;Ljava/lang/invoke/MethodHandle;Ljava/lang/invoke/MethodType;)Ljava/lang/invoke/CallSite;
    Method arguments:
      #240 (Ljava/lang/Object;)Ljava/lang/Object;
      #260 REF_invokeStatic ext/mods/FarmEventRandom/holder/RamdomConfig.lambda$new$1:(Ljava/time/format/DateTimeFormatter;Ljava/lang/String;)Ljava/time/LocalTime;
      #263 (Ljava/lang/String;)Ljava/time/LocalTime;
  4: #270 REF_invokeStatic java/lang/invoke/LambdaMetafactory.metafactory:(Ljava/lang/invoke/MethodHandles$Lookup;Ljava/lang/String;Ljava/lang/invoke/MethodType;Ljava/lang/invoke/MethodType;Ljava/lang/invoke/MethodHandle;Ljava/lang/invoke/MethodType;)Ljava/lang/invoke/CallSite;
    Method arguments:
      #255 (Ljava/lang/Object;)Z
      #265 REF_invokeStatic ext/mods/FarmEventRandom/holder/RamdomConfig.lambda$isTimeToRun$0:(Ljava/time/LocalTime;Ljava/time/LocalTime;)Z
      #268 (Ljava/time/LocalTime;)Z
InnerClasses:
  public static final #282= #278 of #280; // Lookup=class java/lang/invoke/MethodHandles$Lookup of class java/lang/invoke/MethodHandles
