// Bytecode for: ext.mods.FarmEventRandom.holder.RandomZoneData
// File: ext\mods\FarmEventRandom\holder\RandomZoneData.class

Classfile /c:/Users/User/Desktop/BrProject/bin/main/ext/mods/FarmEventRandom/holder/RandomZoneData.class
  Last modified 9 de jul de 2026; size 6392 bytes
  MD5 checksum 8c68998906a5a5485d5711088cc03a50
  Compiled from "RandomZoneData.java"
public class ext.mods.FarmEventRandom.holder.RandomZoneData
  minor version: 0
  major version: 69
  flags: (0x0021) ACC_PUBLIC, ACC_SUPER
  this_class: #11                         // ext/mods/FarmEventRandom/holder/RandomZoneData
  super_class: #2                         // java/lang/Object
  interfaces: 0, fields: 20, methods: 22, attributes: 3
Constant pool:
    #1 = Methodref          #2.#3         // java/lang/Object."<init>":()V
    #2 = Class              #4            // java/lang/Object
    #3 = NameAndType        #5:#6         // "<init>":()V
    #4 = Utf8               java/lang/Object
    #5 = Utf8               <init>
    #6 = Utf8               ()V
    #7 = Class              #8            // java/util/ArrayList
    #8 = Utf8               java/util/ArrayList
    #9 = Methodref          #7.#3         // java/util/ArrayList."<init>":()V
   #10 = Fieldref           #11.#12       // ext/mods/FarmEventRandom/holder/RandomZoneData._customSpawns:Ljava/util/List;
   #11 = Class              #13           // ext/mods/FarmEventRandom/holder/RandomZoneData
   #12 = NameAndType        #14:#15       // _customSpawns:Ljava/util/List;
   #13 = Utf8               ext/mods/FarmEventRandom/holder/RandomZoneData
   #14 = Utf8               _customSpawns
   #15 = Utf8               Ljava/util/List;
   #16 = String             #17           // zoneId
   #17 = Utf8               zoneId
   #18 = Methodref          #19.#20       // ext/mods/commons/data/StatSet.getInteger:(Ljava/lang/String;)I
   #19 = Class              #21           // ext/mods/commons/data/StatSet
   #20 = NameAndType        #22:#23       // getInteger:(Ljava/lang/String;)I
   #21 = Utf8               ext/mods/commons/data/StatSet
   #22 = Utf8               getInteger
   #23 = Utf8               (Ljava/lang/String;)I
   #24 = Fieldref           #11.#25       // ext/mods/FarmEventRandom/holder/RandomZoneData._zoneId:I
   #25 = NameAndType        #26:#27       // _zoneId:I
   #26 = Utf8               _zoneId
   #27 = Utf8               I
   #28 = String             #29           // useOriginals
   #29 = Utf8               useOriginals
   #30 = Methodref          #19.#31       // ext/mods/commons/data/StatSet.getBool:(Ljava/lang/String;Z)Z
   #31 = NameAndType        #32:#33       // getBool:(Ljava/lang/String;Z)Z
   #32 = Utf8               getBool
   #33 = Utf8               (Ljava/lang/String;Z)Z
   #34 = Fieldref           #11.#35       // ext/mods/FarmEventRandom/holder/RandomZoneData._useOriginals:Z
   #35 = NameAndType        #36:#37       // _useOriginals:Z
   #36 = Utf8               _useOriginals
   #37 = Utf8               Z
   #38 = String             #39           // active
   #39 = Utf8               active
   #40 = Fieldref           #11.#41       // ext/mods/FarmEventRandom/holder/RandomZoneData._active:Z
   #41 = NameAndType        #42:#37       // _active:Z
   #42 = Utf8               _active
   #43 = String             #44           // DropsOriginals
   #44 = Utf8               DropsOriginals
   #45 = Fieldref           #11.#46       // ext/mods/FarmEventRandom/holder/RandomZoneData._dropsOriginals:Z
   #46 = NameAndType        #47:#37       // _dropsOriginals:Z
   #47 = Utf8               _dropsOriginals
   #48 = String             #49           // rateXp
   #49 = Utf8               rateXp
   #50 = Methodref          #19.#51       // ext/mods/commons/data/StatSet.getDouble:(Ljava/lang/String;D)D
   #51 = NameAndType        #52:#53       // getDouble:(Ljava/lang/String;D)D
   #52 = Utf8               getDouble
   #53 = Utf8               (Ljava/lang/String;D)D
   #54 = Fieldref           #11.#55       // ext/mods/FarmEventRandom/holder/RandomZoneData._rateXp:D
   #55 = NameAndType        #56:#57       // _rateXp:D
   #56 = Utf8               _rateXp
   #57 = Utf8               D
   #58 = String             #59           // rateSp
   #59 = Utf8               rateSp
   #60 = Fieldref           #11.#61       // ext/mods/FarmEventRandom/holder/RandomZoneData._rateSp:D
   #61 = NameAndType        #62:#57       // _rateSp:D
   #62 = Utf8               _rateSp
   #63 = String             #64           // rateAdena
   #64 = Utf8               rateAdena
   #65 = Fieldref           #11.#66       // ext/mods/FarmEventRandom/holder/RandomZoneData._rateAdena:D
   #66 = NameAndType        #67:#57       // _rateAdena:D
   #67 = Utf8               _rateAdena
   #68 = String             #69           // title
   #69 = Utf8               title
   #70 = String             #71           // [Farm Event]
   #71 = Utf8               [Farm Event]
   #72 = Methodref          #19.#73       // ext/mods/commons/data/StatSet.getString:(Ljava/lang/String;Ljava/lang/String;)Ljava/lang/String;
   #73 = NameAndType        #74:#75       // getString:(Ljava/lang/String;Ljava/lang/String;)Ljava/lang/String;
   #74 = Utf8               getString
   #75 = Utf8               (Ljava/lang/String;Ljava/lang/String;)Ljava/lang/String;
   #76 = Fieldref           #11.#77       // ext/mods/FarmEventRandom/holder/RandomZoneData._defaultTitle:Ljava/lang/String;
   #77 = NameAndType        #78:#79       // _defaultTitle:Ljava/lang/String;
   #78 = Utf8               _defaultTitle
   #79 = Utf8               Ljava/lang/String;
   #80 = String             #81           // respawnDelay
   #81 = Utf8               respawnDelay
   #82 = Methodref          #19.#83       // ext/mods/commons/data/StatSet.getInteger:(Ljava/lang/String;I)I
   #83 = NameAndType        #22:#84       // getInteger:(Ljava/lang/String;I)I
   #84 = Utf8               (Ljava/lang/String;I)I
   #85 = Fieldref           #11.#86       // ext/mods/FarmEventRandom/holder/RandomZoneData._defaultRespawnDelay:I
   #86 = NameAndType        #87:#27       // _defaultRespawnDelay:I
   #87 = Utf8               _defaultRespawnDelay
   #88 = Fieldref           #11.#89       // ext/mods/FarmEventRandom/holder/RandomZoneData._defaultDrops:Ljava/util/List;
   #89 = NameAndType        #90:#15       // _defaultDrops:Ljava/util/List;
   #90 = Utf8               _defaultDrops
   #91 = String             #92           // drops
   #92 = Utf8               drops
   #93 = String             #94           //
   #94 = Utf8
   #95 = Methodref          #96.#97       // java/lang/String.isEmpty:()Z
   #96 = Class              #98           // java/lang/String
   #97 = NameAndType        #99:#100      // isEmpty:()Z
   #98 = Utf8               java/lang/String
   #99 = Utf8               isEmpty
  #100 = Utf8               ()Z
  #101 = String             #102          // ;
  #102 = Utf8               ;
  #103 = Methodref          #96.#104      // java/lang/String.split:(Ljava/lang/String;)[Ljava/lang/String;
  #104 = NameAndType        #105:#106     // split:(Ljava/lang/String;)[Ljava/lang/String;
  #105 = Utf8               split
  #106 = Utf8               (Ljava/lang/String;)[Ljava/lang/String;
  #107 = String             #108          // -
  #108 = Utf8               -
  #109 = Methodref          #110.#111     // java/lang/Integer.parseInt:(Ljava/lang/String;)I
  #110 = Class              #112          // java/lang/Integer
  #111 = NameAndType        #113:#23      // parseInt:(Ljava/lang/String;)I
  #112 = Utf8               java/lang/Integer
  #113 = Utf8               parseInt
  #114 = Class              #115          // ext/mods/FarmEventRandom/holder/DropHolder
  #115 = Utf8               ext/mods/FarmEventRandom/holder/DropHolder
  #116 = Methodref          #114.#117     // ext/mods/FarmEventRandom/holder/DropHolder."<init>":(III)V
  #117 = NameAndType        #5:#118       // "<init>":(III)V
  #118 = Utf8               (III)V
  #119 = InterfaceMethodref #120.#121     // java/util/List.add:(Ljava/lang/Object;)Z
  #120 = Class              #122          // java/util/List
  #121 = NameAndType        #123:#124     // add:(Ljava/lang/Object;)Z
  #122 = Utf8               java/util/List
  #123 = Utf8               add
  #124 = Utf8               (Ljava/lang/Object;)Z
  #125 = Class              #126          // java/lang/NumberFormatException
  #126 = Utf8               java/lang/NumberFormatException
  #127 = Fieldref           #11.#128      // ext/mods/FarmEventRandom/holder/RandomZoneData.LOGGER:Lext/mods/commons/logging/CLogger;
  #128 = NameAndType        #129:#130     // LOGGER:Lext/mods/commons/logging/CLogger;
  #129 = Utf8               LOGGER
  #130 = Utf8               Lext/mods/commons/logging/CLogger;
  #131 = InvokeDynamic      #0:#132       // #0:makeConcatWithConstants:(Ljava/lang/String;)Ljava/lang/String;
  #132 = NameAndType        #133:#134     // makeConcatWithConstants:(Ljava/lang/String;)Ljava/lang/String;
  #133 = Utf8               makeConcatWithConstants
  #134 = Utf8               (Ljava/lang/String;)Ljava/lang/String;
  #135 = Methodref          #136.#137     // ext/mods/commons/logging/CLogger.error:(Ljava/lang/Object;Ljava/lang/Throwable;)V
  #136 = Class              #138          // ext/mods/commons/logging/CLogger
  #137 = NameAndType        #139:#140     // error:(Ljava/lang/Object;Ljava/lang/Throwable;)V
  #138 = Utf8               ext/mods/commons/logging/CLogger
  #139 = Utf8               error
  #140 = Utf8               (Ljava/lang/Object;Ljava/lang/Throwable;)V
  #141 = String             #142          // isVip
  #142 = Utf8               isVip
  #143 = Fieldref           #11.#144      // ext/mods/FarmEventRandom/holder/RandomZoneData._isVip:Z
  #144 = NameAndType        #145:#37      // _isVip:Z
  #145 = Utf8               _isVip
  #146 = String             #147          // isPartyZone
  #147 = Utf8               isPartyZone
  #148 = Fieldref           #11.#149      // ext/mods/FarmEventRandom/holder/RandomZoneData._isPartyZone:Z
  #149 = NameAndType        #150:#37      // _isPartyZone:Z
  #150 = Utf8               _isPartyZone
  #151 = String             #152          // minPartySize
  #152 = Utf8               minPartySize
  #153 = Fieldref           #11.#154      // ext/mods/FarmEventRandom/holder/RandomZoneData._minPartySize:I
  #154 = NameAndType        #155:#27      // _minPartySize:I
  #155 = Utf8               _minPartySize
  #156 = String             #157          // DWARVEN_Only
  #157 = Utf8               DWARVEN_Only
  #158 = Fieldref           #11.#159      // ext/mods/FarmEventRandom/holder/RandomZoneData._dwarvenOnly:Z
  #159 = NameAndType        #160:#37      // _dwarvenOnly:Z
  #160 = Utf8               _dwarvenOnly
  #161 = String             #162          // Enchanter_Zone
  #162 = Utf8               Enchanter_Zone
  #163 = Fieldref           #11.#164      // ext/mods/FarmEventRandom/holder/RandomZoneData._enchanterZone:Z
  #164 = NameAndType        #165:#37      // _enchanterZone:Z
  #165 = Utf8               _enchanterZone
  #166 = String             #167          // enchantChance
  #167 = Utf8               enchantChance
  #168 = Fieldref           #11.#169      // ext/mods/FarmEventRandom/holder/RandomZoneData._enchantChance:D
  #169 = NameAndType        #170:#57      // _enchantChance:D
  #170 = Utf8               _enchantChance
  #171 = String             #172          // maxEnchant
  #172 = Utf8               maxEnchant
  #173 = Fieldref           #11.#174      // ext/mods/FarmEventRandom/holder/RandomZoneData._maxEnchant:I
  #174 = NameAndType        #175:#27      // _maxEnchant:I
  #175 = Utf8               _maxEnchant
  #176 = String             #177          // spawnLocation
  #177 = Utf8               spawnLocation
  #178 = String             #179          // ,
  #179 = Utf8               ,
  #180 = Methodref          #96.#181      // java/lang/String.trim:()Ljava/lang/String;
  #181 = NameAndType        #182:#183     // trim:()Ljava/lang/String;
  #182 = Utf8               trim
  #183 = Utf8               ()Ljava/lang/String;
  #184 = Class              #185          // ext/mods/gameserver/model/location/Location
  #185 = Utf8               ext/mods/gameserver/model/location/Location
  #186 = Methodref          #184.#117     // ext/mods/gameserver/model/location/Location."<init>":(III)V
  #187 = InvokeDynamic      #1:#188       // #1:makeConcatWithConstants:(ILjava/lang/String;)Ljava/lang/String;
  #188 = NameAndType        #133:#189     // makeConcatWithConstants:(ILjava/lang/String;)Ljava/lang/String;
  #189 = Utf8               (ILjava/lang/String;)Ljava/lang/String;
  #190 = Methodref          #136.#191     // ext/mods/commons/logging/CLogger.warn:(Ljava/lang/Object;)V
  #191 = NameAndType        #192:#193     // warn:(Ljava/lang/Object;)V
  #192 = Utf8               warn
  #193 = Utf8               (Ljava/lang/Object;)V
  #194 = InvokeDynamic      #2:#188       // #2:makeConcatWithConstants:(ILjava/lang/String;)Ljava/lang/String;
  #195 = Fieldref           #11.#196      // ext/mods/FarmEventRandom/holder/RandomZoneData._spawnLocation:Lext/mods/gameserver/model/location/Location;
  #196 = NameAndType        #197:#198     // _spawnLocation:Lext/mods/gameserver/model/location/Location;
  #197 = Utf8               _spawnLocation
  #198 = Utf8               Lext/mods/gameserver/model/location/Location;
  #199 = Methodref          #200.#201     // java/lang/Class.getName:()Ljava/lang/String;
  #200 = Class              #202          // java/lang/Class
  #201 = NameAndType        #203:#183     // getName:()Ljava/lang/String;
  #202 = Utf8               java/lang/Class
  #203 = Utf8               getName
  #204 = Methodref          #136.#205     // ext/mods/commons/logging/CLogger."<init>":(Ljava/lang/String;)V
  #205 = NameAndType        #5:#206       // "<init>":(Ljava/lang/String;)V
  #206 = Utf8               (Ljava/lang/String;)V
  #207 = Utf8               Signature
  #208 = Utf8               Ljava/util/List<Lext/mods/FarmEventRandom/holder/DropHolder;>;
  #209 = Utf8               Ljava/util/List<Lext/mods/FarmEventRandom/holder/RandomSpawnHolder;>;
  #210 = Utf8               (Lext/mods/commons/data/StatSet;)V
  #211 = Utf8               Code
  #212 = Utf8               LineNumberTable
  #213 = Utf8               LocalVariableTable
  #214 = Utf8               itemId
  #215 = Utf8               count
  #216 = Utf8               chance
  #217 = Utf8               e
  #218 = Utf8               Ljava/lang/NumberFormatException;
  #219 = Utf8               vals
  #220 = Utf8               [Ljava/lang/String;
  #221 = Utf8               part
  #222 = Utf8               x
  #223 = Utf8               y
  #224 = Utf8               z
  #225 = Utf8               coords
  #226 = Utf8               this
  #227 = Utf8               Lext/mods/FarmEventRandom/holder/RandomZoneData;
  #228 = Utf8               set
  #229 = Utf8               Lext/mods/commons/data/StatSet;
  #230 = Utf8               dropsStr
  #231 = Utf8               tempSpawnLocation
  #232 = Utf8               spawnLocStr
  #233 = Utf8               StackMapTable
  #234 = Class              #220          // "[Ljava/lang/String;"
  #235 = Utf8               getZoneId
  #236 = Utf8               ()I
  #237 = Utf8               isActive
  #238 = Utf8               dropsOriginals
  #239 = Utf8               getRateXp
  #240 = Utf8               ()D
  #241 = Utf8               getRateSp
  #242 = Utf8               getRateAdena
  #243 = Utf8               getDefaultTitle
  #244 = Utf8               getDefaultRespawnDelay
  #245 = Utf8               getDefaultDrops
  #246 = Utf8               ()Ljava/util/List;
  #247 = Utf8               ()Ljava/util/List<Lext/mods/FarmEventRandom/holder/DropHolder;>;
  #248 = Utf8               addCustomSpawn
  #249 = Utf8               (Lext/mods/FarmEventRandom/holder/RandomSpawnHolder;)V
  #250 = Utf8               spawn
  #251 = Utf8               Lext/mods/FarmEventRandom/holder/RandomSpawnHolder;
  #252 = Utf8               getCustomSpawns
  #253 = Utf8               ()Ljava/util/List<Lext/mods/FarmEventRandom/holder/RandomSpawnHolder;>;
  #254 = Utf8               getMinPartySize
  #255 = Utf8               isDwarvenOnly
  #256 = Utf8               isEnchanterZone
  #257 = Utf8               getEnchantChance
  #258 = Utf8               getMaxEnchant
  #259 = Utf8               getSpawnLocation
  #260 = Utf8               ()Lext/mods/gameserver/model/location/Location;
  #261 = Utf8               <clinit>
  #262 = Utf8               SourceFile
  #263 = Utf8               RandomZoneData.java
  #264 = Utf8               BootstrapMethods
  #265 = String             #266          // [RandomZoneData] Erro ao ler drop padrão: \u0001
  #266 = Utf8               [RandomZoneData] Erro ao ler drop padrão: \u0001
  #267 = String             #268          // [RandomZoneData] Formato inválido para spawnLocation na zona \u0001. Esperado: \'x,y,z\'. Recebido: \'\u0001\'
  #268 = Utf8               [RandomZoneData] Formato inválido para spawnLocation na zona \u0001. Esperado: \'x,y,z\'. Recebido: \'\u0001\'
  #269 = String             #270          // [RandomZoneData] Erro ao parsear spawnLocation na zona \u0001: \u0001
  #270 = Utf8               [RandomZoneData] Erro ao parsear spawnLocation na zona \u0001: \u0001
  #271 = MethodHandle       6:#272        // REF_invokeStatic java/lang/invoke/StringConcatFactory.makeConcatWithConstants:(Ljava/lang/invoke/MethodHandles$Lookup;Ljava/lang/String;Ljava/lang/invoke/MethodType;Ljava/lang/String;[Ljava/lang/Object;)Ljava/lang/invoke/CallSite;
  #272 = Methodref          #273.#274     // java/lang/invoke/StringConcatFactory.makeConcatWithConstants:(Ljava/lang/invoke/MethodHandles$Lookup;Ljava/lang/String;Ljava/lang/invoke/MethodType;Ljava/lang/String;[Ljava/lang/Object;)Ljava/lang/invoke/CallSite;
  #273 = Class              #275          // java/lang/invoke/StringConcatFactory
  #274 = NameAndType        #133:#276     // makeConcatWithConstants:(Ljava/lang/invoke/MethodHandles$Lookup;Ljava/lang/String;Ljava/lang/invoke/MethodType;Ljava/lang/String;[Ljava/lang/Object;)Ljava/lang/invoke/CallSite;
  #275 = Utf8               java/lang/invoke/StringConcatFactory
  #276 = Utf8               (Ljava/lang/invoke/MethodHandles$Lookup;Ljava/lang/String;Ljava/lang/invoke/MethodType;Ljava/lang/String;[Ljava/lang/Object;)Ljava/lang/invoke/CallSite;
  #277 = Utf8               InnerClasses
  #278 = Class              #279          // java/lang/invoke/MethodHandles$Lookup
  #279 = Utf8               java/lang/invoke/MethodHandles$Lookup
  #280 = Class              #281          // java/lang/invoke/MethodHandles
  #281 = Utf8               java/lang/invoke/MethodHandles
  #282 = Utf8               Lookup
{
  public ext.mods.FarmEventRandom.holder.RandomZoneData(ext.mods.commons.data.StatSet);
    descriptor: (Lext/mods/commons/data/StatSet;)V
    flags: (0x0001) ACC_PUBLIC
    Code:
      stack=6, locals=11, args_size=2
         0: aload_0
         1: invokespecial #1                  // Method java/lang/Object."<init>":()V
         4: aload_0
         5: new           #7                  // class java/util/ArrayList
         8: dup
         9: invokespecial #9                  // Method java/util/ArrayList."<init>":()V
        12: putfield      #10                 // Field _customSpawns:Ljava/util/List;
        15: aload_0
        16: aload_1
        17: ldc           #16                 // String zoneId
        19: invokevirtual #18                 // Method ext/mods/commons/data/StatSet.getInteger:(Ljava/lang/String;)I
        22: putfield      #24                 // Field _zoneId:I
        25: aload_0
        26: aload_1
        27: ldc           #28                 // String useOriginals
        29: iconst_0
        30: invokevirtual #30                 // Method ext/mods/commons/data/StatSet.getBool:(Ljava/lang/String;Z)Z
        33: putfield      #34                 // Field _useOriginals:Z
        36: aload_0
        37: aload_1
        38: ldc           #38                 // String active
        40: iconst_1
        41: invokevirtual #30                 // Method ext/mods/commons/data/StatSet.getBool:(Ljava/lang/String;Z)Z
        44: putfield      #40                 // Field _active:Z
        47: aload_0
        48: aload_1
        49: ldc           #43                 // String DropsOriginals
        51: iconst_0
        52: invokevirtual #30                 // Method ext/mods/commons/data/StatSet.getBool:(Ljava/lang/String;Z)Z
        55: putfield      #45                 // Field _dropsOriginals:Z
        58: aload_0
        59: aload_1
        60: ldc           #48                 // String rateXp
        62: dconst_1
        63: invokevirtual #50                 // Method ext/mods/commons/data/StatSet.getDouble:(Ljava/lang/String;D)D
        66: putfield      #54                 // Field _rateXp:D
        69: aload_0
        70: aload_1
        71: ldc           #58                 // String rateSp
        73: dconst_1
        74: invokevirtual #50                 // Method ext/mods/commons/data/StatSet.getDouble:(Ljava/lang/String;D)D
        77: putfield      #60                 // Field _rateSp:D
        80: aload_0
        81: aload_1
        82: ldc           #63                 // String rateAdena
        84: dconst_1
        85: invokevirtual #50                 // Method ext/mods/commons/data/StatSet.getDouble:(Ljava/lang/String;D)D
        88: putfield      #65                 // Field _rateAdena:D
        91: aload_0
        92: aload_1
        93: ldc           #68                 // String title
        95: ldc           #70                 // String [Farm Event]
        97: invokevirtual #72                 // Method ext/mods/commons/data/StatSet.getString:(Ljava/lang/String;Ljava/lang/String;)Ljava/lang/String;
       100: putfield      #76                 // Field _defaultTitle:Ljava/lang/String;
       103: aload_0
       104: aload_1
       105: ldc           #80                 // String respawnDelay
       107: iconst_m1
       108: invokevirtual #82                 // Method ext/mods/commons/data/StatSet.getInteger:(Ljava/lang/String;I)I
       111: putfield      #85                 // Field _defaultRespawnDelay:I
       114: aload_0
       115: new           #7                  // class java/util/ArrayList
       118: dup
       119: invokespecial #9                  // Method java/util/ArrayList."<init>":()V
       122: putfield      #88                 // Field _defaultDrops:Ljava/util/List;
       125: aload_1
       126: ldc           #91                 // String drops
       128: ldc           #93                 // String
       130: invokevirtual #72                 // Method ext/mods/commons/data/StatSet.getString:(Ljava/lang/String;Ljava/lang/String;)Ljava/lang/String;
       133: astore_2
       134: aload_2
       135: invokevirtual #95                 // Method java/lang/String.isEmpty:()Z
       138: ifne          260
       141: aload_2
       142: ldc           #101                // String ;
       144: invokevirtual #103                // Method java/lang/String.split:(Ljava/lang/String;)[Ljava/lang/String;
       147: astore_3
       148: aload_3
       149: arraylength
       150: istore        4
       152: iconst_0
       153: istore        5
       155: iload         5
       157: iload         4
       159: if_icmpge     260
       162: aload_3
       163: iload         5
       165: aaload
       166: astore        6
       168: aload         6
       170: ldc           #107                // String -
       172: invokevirtual #103                // Method java/lang/String.split:(Ljava/lang/String;)[Ljava/lang/String;
       175: astore        7
       177: aload         7
       179: arraylength
       180: iconst_3
       181: if_icmplt     254
       184: aload         7
       186: iconst_0
       187: aaload
       188: invokestatic  #109                // Method java/lang/Integer.parseInt:(Ljava/lang/String;)I
       191: istore        8
       193: aload         7
       195: iconst_1
       196: aaload
       197: invokestatic  #109                // Method java/lang/Integer.parseInt:(Ljava/lang/String;)I
       200: istore        9
       202: aload         7
       204: iconst_2
       205: aaload
       206: invokestatic  #109                // Method java/lang/Integer.parseInt:(Ljava/lang/String;)I
       209: istore        10
       211: aload_0
       212: getfield      #88                 // Field _defaultDrops:Ljava/util/List;
       215: new           #114                // class ext/mods/FarmEventRandom/holder/DropHolder
       218: dup
       219: iload         8
       221: iload         9
       223: iload         10
       225: invokespecial #116                // Method ext/mods/FarmEventRandom/holder/DropHolder."<init>":(III)V
       228: invokeinterface #119,  2          // InterfaceMethod java/util/List.add:(Ljava/lang/Object;)Z
       233: pop
       234: goto          254
       237: astore        8
       239: getstatic     #127                // Field LOGGER:Lext/mods/commons/logging/CLogger;
       242: aload         6
       244: invokedynamic #131,  0            // InvokeDynamic #0:makeConcatWithConstants:(Ljava/lang/String;)Ljava/lang/String;
       249: aload         8
       251: invokevirtual #135                // Method ext/mods/commons/logging/CLogger.error:(Ljava/lang/Object;Ljava/lang/Throwable;)V
       254: iinc          5, 1
       257: goto          155
       260: aload_0
       261: aload_1
       262: ldc           #141                // String isVip
       264: iconst_0
       265: invokevirtual #30                 // Method ext/mods/commons/data/StatSet.getBool:(Ljava/lang/String;Z)Z
       268: putfield      #143                // Field _isVip:Z
       271: aload_0
       272: aload_1
       273: ldc           #146                // String isPartyZone
       275: iconst_0
       276: invokevirtual #30                 // Method ext/mods/commons/data/StatSet.getBool:(Ljava/lang/String;Z)Z
       279: putfield      #148                // Field _isPartyZone:Z
       282: aload_0
       283: aload_1
       284: ldc           #151                // String minPartySize
       286: iconst_2
       287: invokevirtual #82                 // Method ext/mods/commons/data/StatSet.getInteger:(Ljava/lang/String;I)I
       290: putfield      #153                // Field _minPartySize:I
       293: aload_0
       294: aload_1
       295: ldc           #156                // String DWARVEN_Only
       297: iconst_0
       298: invokevirtual #30                 // Method ext/mods/commons/data/StatSet.getBool:(Ljava/lang/String;Z)Z
       301: putfield      #158                // Field _dwarvenOnly:Z
       304: aload_0
       305: aload_1
       306: ldc           #161                // String Enchanter_Zone
       308: iconst_0
       309: invokevirtual #30                 // Method ext/mods/commons/data/StatSet.getBool:(Ljava/lang/String;Z)Z
       312: putfield      #163                // Field _enchanterZone:Z
       315: aload_0
       316: aload_1
       317: ldc           #166                // String enchantChance
       319: dconst_0
       320: invokevirtual #50                 // Method ext/mods/commons/data/StatSet.getDouble:(Ljava/lang/String;D)D
       323: putfield      #168                // Field _enchantChance:D
       326: aload_0
       327: aload_1
       328: ldc           #171                // String maxEnchant
       330: bipush        15
       332: invokevirtual #82                 // Method ext/mods/commons/data/StatSet.getInteger:(Ljava/lang/String;I)I
       335: putfield      #173                // Field _maxEnchant:I
       338: aconst_null
       339: astore_3
       340: aload_1
       341: ldc           #176                // String spawnLocation
       343: ldc           #93                 // String
       345: invokevirtual #72                 // Method ext/mods/commons/data/StatSet.getString:(Ljava/lang/String;Ljava/lang/String;)Ljava/lang/String;
       348: astore        4
       350: aload         4
       352: invokevirtual #95                 // Method java/lang/String.isEmpty:()Z
       355: ifne          468
       358: aload         4
       360: ldc           #178                // String ,
       362: invokevirtual #103                // Method java/lang/String.split:(Ljava/lang/String;)[Ljava/lang/String;
       365: astore        5
       367: aload         5
       369: arraylength
       370: iconst_3
       371: if_icmpne     427
       374: aload         5
       376: iconst_0
       377: aaload
       378: invokevirtual #180                // Method java/lang/String.trim:()Ljava/lang/String;
       381: invokestatic  #109                // Method java/lang/Integer.parseInt:(Ljava/lang/String;)I
       384: istore        6
       386: aload         5
       388: iconst_1
       389: aaload
       390: invokevirtual #180                // Method java/lang/String.trim:()Ljava/lang/String;
       393: invokestatic  #109                // Method java/lang/Integer.parseInt:(Ljava/lang/String;)I
       396: istore        7
       398: aload         5
       400: iconst_2
       401: aaload
       402: invokevirtual #180                // Method java/lang/String.trim:()Ljava/lang/String;
       405: invokestatic  #109                // Method java/lang/Integer.parseInt:(Ljava/lang/String;)I
       408: istore        8
       410: new           #184                // class ext/mods/gameserver/model/location/Location
       413: dup
       414: iload         6
       416: iload         7
       418: iload         8
       420: invokespecial #186                // Method ext/mods/gameserver/model/location/Location."<init>":(III)V
       423: astore_3
       424: goto          444
       427: getstatic     #127                // Field LOGGER:Lext/mods/commons/logging/CLogger;
       430: aload_0
       431: getfield      #24                 // Field _zoneId:I
       434: aload         4
       436: invokedynamic #187,  0            // InvokeDynamic #1:makeConcatWithConstants:(ILjava/lang/String;)Ljava/lang/String;
       441: invokevirtual #190                // Method ext/mods/commons/logging/CLogger.warn:(Ljava/lang/Object;)V
       444: goto          468
       447: astore        5
       449: getstatic     #127                // Field LOGGER:Lext/mods/commons/logging/CLogger;
       452: aload_0
       453: getfield      #24                 // Field _zoneId:I
       456: aload         4
       458: invokedynamic #194,  0            // InvokeDynamic #2:makeConcatWithConstants:(ILjava/lang/String;)Ljava/lang/String;
       463: aload         5
       465: invokevirtual #135                // Method ext/mods/commons/logging/CLogger.error:(Ljava/lang/Object;Ljava/lang/Throwable;)V
       468: aload_0
       469: aload_3
       470: putfield      #195                // Field _spawnLocation:Lext/mods/gameserver/model/location/Location;
       473: return
      Exception table:
         from    to  target type
           184   234   237   Class java/lang/NumberFormatException
           358   444   447   Class java/lang/NumberFormatException
      LineNumberTable:
        line 62: 0
        line 50: 4
        line 63: 15
        line 64: 25
        line 65: 36
        line 67: 47
        line 68: 58
        line 69: 69
        line 70: 80
        line 72: 91
        line 73: 103
        line 75: 114
        line 76: 125
        line 77: 134
        line 79: 141
        line 81: 168
        line 82: 177
        line 85: 184
        line 86: 193
        line 87: 202
        line 88: 211
        line 91: 234
        line 89: 237
        line 90: 239
        line 79: 254
        line 96: 260
        line 97: 271
        line 98: 282
        line 99: 293
        line 100: 304
        line 101: 315
        line 102: 326
        line 104: 338
        line 105: 340
        line 106: 350
        line 110: 358
        line 111: 367
        line 113: 374
        line 114: 386
        line 115: 398
        line 116: 410
        line 117: 424
        line 120: 427
        line 126: 444
        line 123: 447
        line 125: 449
        line 128: 468
        line 129: 473
      LocalVariableTable:
        Start  Length  Slot  Name   Signature
          193      41     8 itemId   I
          202      32     9 count   I
          211      23    10 chance   I
          239      15     8     e   Ljava/lang/NumberFormatException;
          177      77     7  vals   [Ljava/lang/String;
          168      86     6  part   Ljava/lang/String;
          386      38     6     x   I
          398      26     7     y   I
          410      14     8     z   I
          367      77     5 coords   [Ljava/lang/String;
          449      19     5     e   Ljava/lang/NumberFormatException;
            0     474     0  this   Lext/mods/FarmEventRandom/holder/RandomZoneData;
            0     474     1   set   Lext/mods/commons/data/StatSet;
          134     340     2 dropsStr   Ljava/lang/String;
          340     134     3 tempSpawnLocation   Lext/mods/gameserver/model/location/Location;
          350     124     4 spawnLocStr   Ljava/lang/String;
      StackMapTable: number_of_entries = 8
        frame_type = 255 /* full_frame */
          offset_delta = 155
          locals = [ class ext/mods/FarmEventRandom/holder/RandomZoneData, class ext/mods/commons/data/StatSet, class java/lang/String, class "[Ljava/lang/String;", int, int ]
          stack = []
        frame_type = 255 /* full_frame */
          offset_delta = 81
          locals = [ class ext/mods/FarmEventRandom/holder/RandomZoneData, class ext/mods/commons/data/StatSet, class java/lang/String, class "[Ljava/lang/String;", int, int, class java/lang/String, class "[Ljava/lang/String;" ]
          stack = [ class java/lang/NumberFormatException ]
        frame_type = 249 /* chop */
          offset_delta = 16
        frame_type = 248 /* chop */
          offset_delta = 5
        frame_type = 254 /* append */
          offset_delta = 166
          locals = [ class ext/mods/gameserver/model/location/Location, class java/lang/String, class "[Ljava/lang/String;" ]
        frame_type = 250 /* chop */
          offset_delta = 16
        frame_type = 66 /* same_locals_1_stack_item */
          stack = [ class java/lang/NumberFormatException ]
        frame_type = 20 /* same */

  public int getZoneId();
    descriptor: ()I
    flags: (0x0001) ACC_PUBLIC
    Code:
      stack=1, locals=1, args_size=1
         0: aload_0
         1: getfield      #24                 // Field _zoneId:I
         4: ireturn
      LineNumberTable:
        line 131: 0
      LocalVariableTable:
        Start  Length  Slot  Name   Signature
            0       5     0  this   Lext/mods/FarmEventRandom/holder/RandomZoneData;

  public boolean useOriginals();
    descriptor: ()Z
    flags: (0x0001) ACC_PUBLIC
    Code:
      stack=1, locals=1, args_size=1
         0: aload_0
         1: getfield      #34                 // Field _useOriginals:Z
         4: ireturn
      LineNumberTable:
        line 132: 0
      LocalVariableTable:
        Start  Length  Slot  Name   Signature
            0       5     0  this   Lext/mods/FarmEventRandom/holder/RandomZoneData;

  public boolean isActive();
    descriptor: ()Z
    flags: (0x0001) ACC_PUBLIC
    Code:
      stack=1, locals=1, args_size=1
         0: aload_0
         1: getfield      #40                 // Field _active:Z
         4: ireturn
      LineNumberTable:
        line 133: 0
      LocalVariableTable:
        Start  Length  Slot  Name   Signature
            0       5     0  this   Lext/mods/FarmEventRandom/holder/RandomZoneData;

  public boolean dropsOriginals();
    descriptor: ()Z
    flags: (0x0001) ACC_PUBLIC
    Code:
      stack=1, locals=1, args_size=1
         0: aload_0
         1: getfield      #45                 // Field _dropsOriginals:Z
         4: ireturn
      LineNumberTable:
        line 134: 0
      LocalVariableTable:
        Start  Length  Slot  Name   Signature
            0       5     0  this   Lext/mods/FarmEventRandom/holder/RandomZoneData;

  public double getRateXp();
    descriptor: ()D
    flags: (0x0001) ACC_PUBLIC
    Code:
      stack=2, locals=1, args_size=1
         0: aload_0
         1: getfield      #54                 // Field _rateXp:D
         4: dreturn
      LineNumberTable:
        line 135: 0
      LocalVariableTable:
        Start  Length  Slot  Name   Signature
            0       5     0  this   Lext/mods/FarmEventRandom/holder/RandomZoneData;

  public double getRateSp();
    descriptor: ()D
    flags: (0x0001) ACC_PUBLIC
    Code:
      stack=2, locals=1, args_size=1
         0: aload_0
         1: getfield      #60                 // Field _rateSp:D
         4: dreturn
      LineNumberTable:
        line 136: 0
      LocalVariableTable:
        Start  Length  Slot  Name   Signature
            0       5     0  this   Lext/mods/FarmEventRandom/holder/RandomZoneData;

  public double getRateAdena();
    descriptor: ()D
    flags: (0x0001) ACC_PUBLIC
    Code:
      stack=2, locals=1, args_size=1
         0: aload_0
         1: getfield      #65                 // Field _rateAdena:D
         4: dreturn
      LineNumberTable:
        line 137: 0
      LocalVariableTable:
        Start  Length  Slot  Name   Signature
            0       5     0  this   Lext/mods/FarmEventRandom/holder/RandomZoneData;

  public java.lang.String getDefaultTitle();
    descriptor: ()Ljava/lang/String;
    flags: (0x0001) ACC_PUBLIC
    Code:
      stack=1, locals=1, args_size=1
         0: aload_0
         1: getfield      #76                 // Field _defaultTitle:Ljava/lang/String;
         4: areturn
      LineNumberTable:
        line 138: 0
      LocalVariableTable:
        Start  Length  Slot  Name   Signature
            0       5     0  this   Lext/mods/FarmEventRandom/holder/RandomZoneData;

  public int getDefaultRespawnDelay();
    descriptor: ()I
    flags: (0x0001) ACC_PUBLIC
    Code:
      stack=1, locals=1, args_size=1
         0: aload_0
         1: getfield      #85                 // Field _defaultRespawnDelay:I
         4: ireturn
      LineNumberTable:
        line 139: 0
      LocalVariableTable:
        Start  Length  Slot  Name   Signature
            0       5     0  this   Lext/mods/FarmEventRandom/holder/RandomZoneData;

  public java.util.List<ext.mods.FarmEventRandom.holder.DropHolder> getDefaultDrops();
    descriptor: ()Ljava/util/List;
    flags: (0x0001) ACC_PUBLIC
    Code:
      stack=1, locals=1, args_size=1
         0: aload_0
         1: getfield      #88                 // Field _defaultDrops:Ljava/util/List;
         4: areturn
      LineNumberTable:
        line 140: 0
      LocalVariableTable:
        Start  Length  Slot  Name   Signature
            0       5     0  this   Lext/mods/FarmEventRandom/holder/RandomZoneData;
    Signature: #247                         // ()Ljava/util/List<Lext/mods/FarmEventRandom/holder/DropHolder;>;

  public void addCustomSpawn(ext.mods.FarmEventRandom.holder.RandomSpawnHolder);
    descriptor: (Lext/mods/FarmEventRandom/holder/RandomSpawnHolder;)V
    flags: (0x0001) ACC_PUBLIC
    Code:
      stack=2, locals=2, args_size=2
         0: aload_0
         1: getfield      #10                 // Field _customSpawns:Ljava/util/List;
         4: aload_1
         5: invokeinterface #119,  2          // InterfaceMethod java/util/List.add:(Ljava/lang/Object;)Z
        10: pop
        11: return
      LineNumberTable:
        line 141: 0
      LocalVariableTable:
        Start  Length  Slot  Name   Signature
            0      12     0  this   Lext/mods/FarmEventRandom/holder/RandomZoneData;
            0      12     1 spawn   Lext/mods/FarmEventRandom/holder/RandomSpawnHolder;

  public java.util.List<ext.mods.FarmEventRandom.holder.RandomSpawnHolder> getCustomSpawns();
    descriptor: ()Ljava/util/List;
    flags: (0x0001) ACC_PUBLIC
    Code:
      stack=1, locals=1, args_size=1
         0: aload_0
         1: getfield      #10                 // Field _customSpawns:Ljava/util/List;
         4: areturn
      LineNumberTable:
        line 142: 0
      LocalVariableTable:
        Start  Length  Slot  Name   Signature
            0       5     0  this   Lext/mods/FarmEventRandom/holder/RandomZoneData;
    Signature: #253                         // ()Ljava/util/List<Lext/mods/FarmEventRandom/holder/RandomSpawnHolder;>;

  public boolean isVip();
    descriptor: ()Z
    flags: (0x0001) ACC_PUBLIC
    Code:
      stack=1, locals=1, args_size=1
         0: aload_0
         1: getfield      #143                // Field _isVip:Z
         4: ireturn
      LineNumberTable:
        line 147: 0
      LocalVariableTable:
        Start  Length  Slot  Name   Signature
            0       5     0  this   Lext/mods/FarmEventRandom/holder/RandomZoneData;

  public boolean isPartyZone();
    descriptor: ()Z
    flags: (0x0001) ACC_PUBLIC
    Code:
      stack=1, locals=1, args_size=1
         0: aload_0
         1: getfield      #148                // Field _isPartyZone:Z
         4: ireturn
      LineNumberTable:
        line 152: 0
      LocalVariableTable:
        Start  Length  Slot  Name   Signature
            0       5     0  this   Lext/mods/FarmEventRandom/holder/RandomZoneData;

  public int getMinPartySize();
    descriptor: ()I
    flags: (0x0001) ACC_PUBLIC
    Code:
      stack=1, locals=1, args_size=1
         0: aload_0
         1: getfield      #153                // Field _minPartySize:I
         4: ireturn
      LineNumberTable:
        line 157: 0
      LocalVariableTable:
        Start  Length  Slot  Name   Signature
            0       5     0  this   Lext/mods/FarmEventRandom/holder/RandomZoneData;

  public boolean isDwarvenOnly();
    descriptor: ()Z
    flags: (0x0001) ACC_PUBLIC
    Code:
      stack=1, locals=1, args_size=1
         0: aload_0
         1: getfield      #158                // Field _dwarvenOnly:Z
         4: ireturn
      LineNumberTable:
        line 162: 0
      LocalVariableTable:
        Start  Length  Slot  Name   Signature
            0       5     0  this   Lext/mods/FarmEventRandom/holder/RandomZoneData;

  public boolean isEnchanterZone();
    descriptor: ()Z
    flags: (0x0001) ACC_PUBLIC
    Code:
      stack=1, locals=1, args_size=1
         0: aload_0
         1: getfield      #163                // Field _enchanterZone:Z
         4: ireturn
      LineNumberTable:
        line 167: 0
      LocalVariableTable:
        Start  Length  Slot  Name   Signature
            0       5     0  this   Lext/mods/FarmEventRandom/holder/RandomZoneData;

  public double getEnchantChance();
    descriptor: ()D
    flags: (0x0001) ACC_PUBLIC
    Code:
      stack=2, locals=1, args_size=1
         0: aload_0
         1: getfield      #168                // Field _enchantChance:D
         4: dreturn
      LineNumberTable:
        line 172: 0
      LocalVariableTable:
        Start  Length  Slot  Name   Signature
            0       5     0  this   Lext/mods/FarmEventRandom/holder/RandomZoneData;

  public int getMaxEnchant();
    descriptor: ()I
    flags: (0x0001) ACC_PUBLIC
    Code:
      stack=1, locals=1, args_size=1
         0: aload_0
         1: getfield      #173                // Field _maxEnchant:I
         4: ireturn
      LineNumberTable:
        line 177: 0
      LocalVariableTable:
        Start  Length  Slot  Name   Signature
            0       5     0  this   Lext/mods/FarmEventRandom/holder/RandomZoneData;

  public ext.mods.gameserver.model.location.Location getSpawnLocation();
    descriptor: ()Lext/mods/gameserver/model/location/Location;
    flags: (0x0001) ACC_PUBLIC
    Code:
      stack=1, locals=1, args_size=1
         0: aload_0
         1: getfield      #195                // Field _spawnLocation:Lext/mods/gameserver/model/location/Location;
         4: areturn
      LineNumberTable:
        line 182: 0
      LocalVariableTable:
        Start  Length  Slot  Name   Signature
            0       5     0  this   Lext/mods/FarmEventRandom/holder/RandomZoneData;

  static {};
    descriptor: ()V
    flags: (0x0008) ACC_STATIC
    Code:
      stack=3, locals=0, args_size=0
         0: new           #136                // class ext/mods/commons/logging/CLogger
         3: dup
         4: ldc           #11                 // class ext/mods/FarmEventRandom/holder/RandomZoneData
         6: invokevirtual #199                // Method java/lang/Class.getName:()Ljava/lang/String;
         9: invokespecial #204                // Method ext/mods/commons/logging/CLogger."<init>":(Ljava/lang/String;)V
        12: putstatic     #127                // Field LOGGER:Lext/mods/commons/logging/CLogger;
        15: return
      LineNumberTable:
        line 35: 0
}
SourceFile: "RandomZoneData.java"
BootstrapMethods:
  0: #271 REF_invokeStatic java/lang/invoke/StringConcatFactory.makeConcatWithConstants:(Ljava/lang/invoke/MethodHandles$Lookup;Ljava/lang/String;Ljava/lang/invoke/MethodType;Ljava/lang/String;[Ljava/lang/Object;)Ljava/lang/invoke/CallSite;
    Method arguments:
      #265 [RandomZoneData] Erro ao ler drop padrão: \u0001
  1: #271 REF_invokeStatic java/lang/invoke/StringConcatFactory.makeConcatWithConstants:(Ljava/lang/invoke/MethodHandles$Lookup;Ljava/lang/String;Ljava/lang/invoke/MethodType;Ljava/lang/String;[Ljava/lang/Object;)Ljava/lang/invoke/CallSite;
    Method arguments:
      #267 [RandomZoneData] Formato inválido para spawnLocation na zona \u0001. Esperado: \'x,y,z\'. Recebido: \'\u0001\'
  2: #271 REF_invokeStatic java/lang/invoke/StringConcatFactory.makeConcatWithConstants:(Ljava/lang/invoke/MethodHandles$Lookup;Ljava/lang/String;Ljava/lang/invoke/MethodType;Ljava/lang/String;[Ljava/lang/Object;)Ljava/lang/invoke/CallSite;
    Method arguments:
      #269 [RandomZoneData] Erro ao parsear spawnLocation na zona \u0001: \u0001
InnerClasses:
  public static final #282= #278 of #280; // Lookup=class java/lang/invoke/MethodHandles$Lookup of class java/lang/invoke/MethodHandles
