// Bytecode for: ext.mods.gameserver.enums.CabalType
// File: ext\mods\gameserver\enums\CabalType.class

Classfile /c:/Users/User/Desktop/BrProject/bin/main/ext/mods/gameserver/enums/CabalType.class
  Last modified 9 de jul de 2026; size 1740 bytes
  MD5 checksum 8301f11519e14a3d2bb4d1ee0b23dba1
  Compiled from "CabalType.java"
public final class ext.mods.gameserver.enums.CabalType extends java.lang.Enum<ext.mods.gameserver.enums.CabalType>
  minor version: 0
  major version: 69
  flags: (0x4031) ACC_PUBLIC, ACC_FINAL, ACC_SUPER, ACC_ENUM
  this_class: #1                          // ext/mods/gameserver/enums/CabalType
  super_class: #23                        // java/lang/Enum
  interfaces: 0, fields: 7, methods: 7, attributes: 2
Constant pool:
   #1 = Class              #2             // ext/mods/gameserver/enums/CabalType
   #2 = Utf8               ext/mods/gameserver/enums/CabalType
   #3 = Fieldref           #1.#4          // ext/mods/gameserver/enums/CabalType.NORMAL:Lext/mods/gameserver/enums/CabalType;
   #4 = NameAndType        #5:#6          // NORMAL:Lext/mods/gameserver/enums/CabalType;
   #5 = Utf8               NORMAL
   #6 = Utf8               Lext/mods/gameserver/enums/CabalType;
   #7 = Fieldref           #1.#8          // ext/mods/gameserver/enums/CabalType.DUSK:Lext/mods/gameserver/enums/CabalType;
   #8 = NameAndType        #9:#6          // DUSK:Lext/mods/gameserver/enums/CabalType;
   #9 = Utf8               DUSK
  #10 = Fieldref           #1.#11         // ext/mods/gameserver/enums/CabalType.DAWN:Lext/mods/gameserver/enums/CabalType;
  #11 = NameAndType        #12:#6         // DAWN:Lext/mods/gameserver/enums/CabalType;
  #12 = Utf8               DAWN
  #13 = Fieldref           #1.#14         // ext/mods/gameserver/enums/CabalType.$VALUES:[Lext/mods/gameserver/enums/CabalType;
  #14 = NameAndType        #15:#16        // $VALUES:[Lext/mods/gameserver/enums/CabalType;
  #15 = Utf8               $VALUES
  #16 = Utf8               [Lext/mods/gameserver/enums/CabalType;
  #17 = Methodref          #18.#19        // "[Lext/mods/gameserver/enums/CabalType;".clone:()Ljava/lang/Object;
  #18 = Class              #16            // "[Lext/mods/gameserver/enums/CabalType;"
  #19 = NameAndType        #20:#21        // clone:()Ljava/lang/Object;
  #20 = Utf8               clone
  #21 = Utf8               ()Ljava/lang/Object;
  #22 = Methodref          #23.#24        // java/lang/Enum.valueOf:(Ljava/lang/Class;Ljava/lang/String;)Ljava/lang/Enum;
  #23 = Class              #25            // java/lang/Enum
  #24 = NameAndType        #26:#27        // valueOf:(Ljava/lang/Class;Ljava/lang/String;)Ljava/lang/Enum;
  #25 = Utf8               java/lang/Enum
  #26 = Utf8               valueOf
  #27 = Utf8               (Ljava/lang/Class;Ljava/lang/String;)Ljava/lang/Enum;
  #28 = Methodref          #23.#29        // java/lang/Enum."<init>":(Ljava/lang/String;I)V
  #29 = NameAndType        #30:#31        // "<init>":(Ljava/lang/String;I)V
  #30 = Utf8               <init>
  #31 = Utf8               (Ljava/lang/String;I)V
  #32 = Fieldref           #1.#33         // ext/mods/gameserver/enums/CabalType._shortName:Ljava/lang/String;
  #33 = NameAndType        #34:#35        // _shortName:Ljava/lang/String;
  #34 = Utf8               _shortName
  #35 = Utf8               Ljava/lang/String;
  #36 = Fieldref           #1.#37         // ext/mods/gameserver/enums/CabalType._fullName:Ljava/lang/String;
  #37 = NameAndType        #38:#35        // _fullName:Ljava/lang/String;
  #38 = Utf8               _fullName
  #39 = String             #5             // NORMAL
  #40 = String             #41            // No Cabal
  #41 = Utf8               No Cabal
  #42 = Methodref          #1.#43         // ext/mods/gameserver/enums/CabalType."<init>":(Ljava/lang/String;ILjava/lang/String;Ljava/lang/String;)V
  #43 = NameAndType        #30:#44        // "<init>":(Ljava/lang/String;ILjava/lang/String;Ljava/lang/String;)V
  #44 = Utf8               (Ljava/lang/String;ILjava/lang/String;Ljava/lang/String;)V
  #45 = String             #9             // DUSK
  #46 = String             #47            // dusk
  #47 = Utf8               dusk
  #48 = String             #49            // Revolutionaries of Dusk
  #49 = Utf8               Revolutionaries of Dusk
  #50 = String             #12            // DAWN
  #51 = String             #52            // dawn
  #52 = Utf8               dawn
  #53 = String             #54            // Lords of Dawn
  #54 = Utf8               Lords of Dawn
  #55 = Methodref          #1.#56         // ext/mods/gameserver/enums/CabalType.$values:()[Lext/mods/gameserver/enums/CabalType;
  #56 = NameAndType        #57:#58        // $values:()[Lext/mods/gameserver/enums/CabalType;
  #57 = Utf8               $values
  #58 = Utf8               ()[Lext/mods/gameserver/enums/CabalType;
  #59 = Methodref          #1.#60         // ext/mods/gameserver/enums/CabalType.values:()[Lext/mods/gameserver/enums/CabalType;
  #60 = NameAndType        #61:#58        // values:()[Lext/mods/gameserver/enums/CabalType;
  #61 = Utf8               values
  #62 = Fieldref           #1.#63         // ext/mods/gameserver/enums/CabalType.VALUES:[Lext/mods/gameserver/enums/CabalType;
  #63 = NameAndType        #64:#16        // VALUES:[Lext/mods/gameserver/enums/CabalType;
  #64 = Utf8               VALUES
  #65 = Utf8               Code
  #66 = Utf8               LineNumberTable
  #67 = Utf8               (Ljava/lang/String;)Lext/mods/gameserver/enums/CabalType;
  #68 = Utf8               LocalVariableTable
  #69 = Utf8               name
  #70 = Utf8               MethodParameters
  #71 = Utf8               this
  #72 = Utf8               shortName
  #73 = Utf8               fullName
  #74 = Utf8               Signature
  #75 = Utf8               (Ljava/lang/String;Ljava/lang/String;)V
  #76 = Utf8               getShortName
  #77 = Utf8               ()Ljava/lang/String;
  #78 = Utf8               getFullName
  #79 = Utf8               <clinit>
  #80 = Utf8               ()V
  #81 = Utf8               Ljava/lang/Enum<Lext/mods/gameserver/enums/CabalType;>;
  #82 = Utf8               SourceFile
  #83 = Utf8               CabalType.java
{
  public static final ext.mods.gameserver.enums.CabalType NORMAL;
    descriptor: Lext/mods/gameserver/enums/CabalType;
    flags: (0x4019) ACC_PUBLIC, ACC_STATIC, ACC_FINAL, ACC_ENUM

  public static final ext.mods.gameserver.enums.CabalType DUSK;
    descriptor: Lext/mods/gameserver/enums/CabalType;
    flags: (0x4019) ACC_PUBLIC, ACC_STATIC, ACC_FINAL, ACC_ENUM

  public static final ext.mods.gameserver.enums.CabalType DAWN;
    descriptor: Lext/mods/gameserver/enums/CabalType;
    flags: (0x4019) ACC_PUBLIC, ACC_STATIC, ACC_FINAL, ACC_ENUM

  public static final ext.mods.gameserver.enums.CabalType[] VALUES;
    descriptor: [Lext/mods/gameserver/enums/CabalType;
    flags: (0x0019) ACC_PUBLIC, ACC_STATIC, ACC_FINAL

  public static ext.mods.gameserver.enums.CabalType[] values();
    descriptor: ()[Lext/mods/gameserver/enums/CabalType;
    flags: (0x0009) ACC_PUBLIC, ACC_STATIC
    Code:
      stack=1, locals=0, args_size=0
         0: getstatic     #13                 // Field $VALUES:[Lext/mods/gameserver/enums/CabalType;
         3: invokevirtual #17                 // Method "[Lext/mods/gameserver/enums/CabalType;".clone:()Ljava/lang/Object;
         6: checkcast     #18                 // class "[Lext/mods/gameserver/enums/CabalType;"
         9: areturn
      LineNumberTable:
        line 20: 0

  public static ext.mods.gameserver.enums.CabalType valueOf(java.lang.String);
    descriptor: (Ljava/lang/String;)Lext/mods/gameserver/enums/CabalType;
    flags: (0x0009) ACC_PUBLIC, ACC_STATIC
    Code:
      stack=2, locals=1, args_size=1
         0: ldc           #1                  // class ext/mods/gameserver/enums/CabalType
         2: aload_0
         3: invokestatic  #22                 // Method java/lang/Enum.valueOf:(Ljava/lang/Class;Ljava/lang/String;)Ljava/lang/Enum;
         6: checkcast     #1                  // class ext/mods/gameserver/enums/CabalType
         9: areturn
      LineNumberTable:
        line 20: 0
      LocalVariableTable:
        Start  Length  Slot  Name   Signature
            0      10     0  name   Ljava/lang/String;
    MethodParameters:
      Name                           Flags
      <no name>                      mandated

  public java.lang.String getShortName();
    descriptor: ()Ljava/lang/String;
    flags: (0x0001) ACC_PUBLIC
    Code:
      stack=1, locals=1, args_size=1
         0: aload_0
         1: getfield      #32                 // Field _shortName:Ljava/lang/String;
         4: areturn
      LineNumberTable:
        line 37: 0
      LocalVariableTable:
        Start  Length  Slot  Name   Signature
            0       5     0  this   Lext/mods/gameserver/enums/CabalType;

  public java.lang.String getFullName();
    descriptor: ()Ljava/lang/String;
    flags: (0x0001) ACC_PUBLIC
    Code:
      stack=1, locals=1, args_size=1
         0: aload_0
         1: getfield      #36                 // Field _fullName:Ljava/lang/String;
         4: areturn
      LineNumberTable:
        line 42: 0
      LocalVariableTable:
        Start  Length  Slot  Name   Signature
            0       5     0  this   Lext/mods/gameserver/enums/CabalType;

  static {};
    descriptor: ()V
    flags: (0x0008) ACC_STATIC
    Code:
      stack=6, locals=0, args_size=0
         0: new           #1                  // class ext/mods/gameserver/enums/CabalType
         3: dup
         4: ldc           #39                 // String NORMAL
         6: iconst_0
         7: ldc           #40                 // String No Cabal
         9: ldc           #40                 // String No Cabal
        11: invokespecial #42                 // Method "<init>":(Ljava/lang/String;ILjava/lang/String;Ljava/lang/String;)V
        14: putstatic     #3                  // Field NORMAL:Lext/mods/gameserver/enums/CabalType;
        17: new           #1                  // class ext/mods/gameserver/enums/CabalType
        20: dup
        21: ldc           #45                 // String DUSK
        23: iconst_1
        24: ldc           #46                 // String dusk
        26: ldc           #48                 // String Revolutionaries of Dusk
        28: invokespecial #42                 // Method "<init>":(Ljava/lang/String;ILjava/lang/String;Ljava/lang/String;)V
        31: putstatic     #7                  // Field DUSK:Lext/mods/gameserver/enums/CabalType;
        34: new           #1                  // class ext/mods/gameserver/enums/CabalType
        37: dup
        38: ldc           #50                 // String DAWN
        40: iconst_2
        41: ldc           #51                 // String dawn
        43: ldc           #53                 // String Lords of Dawn
        45: invokespecial #42                 // Method "<init>":(Ljava/lang/String;ILjava/lang/String;Ljava/lang/String;)V
        48: putstatic     #10                 // Field DAWN:Lext/mods/gameserver/enums/CabalType;
        51: invokestatic  #55                 // Method $values:()[Lext/mods/gameserver/enums/CabalType;
        54: putstatic     #13                 // Field $VALUES:[Lext/mods/gameserver/enums/CabalType;
        57: invokestatic  #59                 // Method values:()[Lext/mods/gameserver/enums/CabalType;
        60: putstatic     #62                 // Field VALUES:[Lext/mods/gameserver/enums/CabalType;
        63: return
      LineNumberTable:
        line 22: 0
        line 23: 17
        line 24: 34
        line 20: 51
        line 45: 57
}
Signature: #81                          // Ljava/lang/Enum<Lext/mods/gameserver/enums/CabalType;>;
SourceFile: "CabalType.java"
