// Bytecode for: ext.mods.gameserver.enums.MakerSpawnTime
// File: ext\mods\gameserver\enums\MakerSpawnTime.class

Classfile /c:/Users/User/Desktop/BrProject/bin/main/ext/mods/gameserver/enums/MakerSpawnTime.class
  Last modified 9 de jul de 2026; size 2213 bytes
  MD5 checksum 863fe37db059138da8da5c16a9d5cf4a
  Compiled from "MakerSpawnTime.java"
public final class ext.mods.gameserver.enums.MakerSpawnTime extends java.lang.Enum<ext.mods.gameserver.enums.MakerSpawnTime>
  minor version: 0
  major version: 69
  flags: (0x4031) ACC_PUBLIC, ACC_FINAL, ACC_SUPER, ACC_ENUM
  this_class: #1                          // ext/mods/gameserver/enums/MakerSpawnTime
  super_class: #35                        // java/lang/Enum
  interfaces: 0, fields: 10, methods: 7, attributes: 2
Constant pool:
    #1 = Class              #2            // ext/mods/gameserver/enums/MakerSpawnTime
    #2 = Utf8               ext/mods/gameserver/enums/MakerSpawnTime
    #3 = Fieldref           #1.#4         // ext/mods/gameserver/enums/MakerSpawnTime.AGIT_BR_START:Lext/mods/gameserver/enums/MakerSpawnTime;
    #4 = NameAndType        #5:#6         // AGIT_BR_START:Lext/mods/gameserver/enums/MakerSpawnTime;
    #5 = Utf8               AGIT_BR_START
    #6 = Utf8               Lext/mods/gameserver/enums/MakerSpawnTime;
    #7 = Fieldref           #1.#8         // ext/mods/gameserver/enums/MakerSpawnTime.AGIT_FINAL_START:Lext/mods/gameserver/enums/MakerSpawnTime;
    #8 = NameAndType        #9:#6         // AGIT_FINAL_START:Lext/mods/gameserver/enums/MakerSpawnTime;
    #9 = Utf8               AGIT_FINAL_START
   #10 = Fieldref           #1.#11        // ext/mods/gameserver/enums/MakerSpawnTime.AGIT_DEF_START:Lext/mods/gameserver/enums/MakerSpawnTime;
   #11 = NameAndType        #12:#6        // AGIT_DEF_START:Lext/mods/gameserver/enums/MakerSpawnTime;
   #12 = Utf8               AGIT_DEF_START
   #13 = Fieldref           #1.#14        // ext/mods/gameserver/enums/MakerSpawnTime.AGIT_ATK_START:Lext/mods/gameserver/enums/MakerSpawnTime;
   #14 = NameAndType        #15:#6        // AGIT_ATK_START:Lext/mods/gameserver/enums/MakerSpawnTime;
   #15 = Utf8               AGIT_ATK_START
   #16 = Fieldref           #1.#17        // ext/mods/gameserver/enums/MakerSpawnTime.SIEGE_START:Lext/mods/gameserver/enums/MakerSpawnTime;
   #17 = NameAndType        #18:#6        // SIEGE_START:Lext/mods/gameserver/enums/MakerSpawnTime;
   #18 = Utf8               SIEGE_START
   #19 = Fieldref           #1.#20        // ext/mods/gameserver/enums/MakerSpawnTime.PC_SIEGE_START:Lext/mods/gameserver/enums/MakerSpawnTime;
   #20 = NameAndType        #21:#6        // PC_SIEGE_START:Lext/mods/gameserver/enums/MakerSpawnTime;
   #21 = Utf8               PC_SIEGE_START
   #22 = Fieldref           #1.#23        // ext/mods/gameserver/enums/MakerSpawnTime.DOOR_OPEN:Lext/mods/gameserver/enums/MakerSpawnTime;
   #23 = NameAndType        #24:#6        // DOOR_OPEN:Lext/mods/gameserver/enums/MakerSpawnTime;
   #24 = Utf8               DOOR_OPEN
   #25 = Fieldref           #1.#26        // ext/mods/gameserver/enums/MakerSpawnTime.$VALUES:[Lext/mods/gameserver/enums/MakerSpawnTime;
   #26 = NameAndType        #27:#28       // $VALUES:[Lext/mods/gameserver/enums/MakerSpawnTime;
   #27 = Utf8               $VALUES
   #28 = Utf8               [Lext/mods/gameserver/enums/MakerSpawnTime;
   #29 = Methodref          #30.#31       // "[Lext/mods/gameserver/enums/MakerSpawnTime;".clone:()Ljava/lang/Object;
   #30 = Class              #28           // "[Lext/mods/gameserver/enums/MakerSpawnTime;"
   #31 = NameAndType        #32:#33       // clone:()Ljava/lang/Object;
   #32 = Utf8               clone
   #33 = Utf8               ()Ljava/lang/Object;
   #34 = Methodref          #35.#36       // java/lang/Enum.valueOf:(Ljava/lang/Class;Ljava/lang/String;)Ljava/lang/Enum;
   #35 = Class              #37           // java/lang/Enum
   #36 = NameAndType        #38:#39       // valueOf:(Ljava/lang/Class;Ljava/lang/String;)Ljava/lang/Enum;
   #37 = Utf8               java/lang/Enum
   #38 = Utf8               valueOf
   #39 = Utf8               (Ljava/lang/Class;Ljava/lang/String;)Ljava/lang/Enum;
   #40 = Methodref          #35.#41       // java/lang/Enum."<init>":(Ljava/lang/String;I)V
   #41 = NameAndType        #42:#43       // "<init>":(Ljava/lang/String;I)V
   #42 = Utf8               <init>
   #43 = Utf8               (Ljava/lang/String;I)V
   #44 = Fieldref           #1.#45        // ext/mods/gameserver/enums/MakerSpawnTime._name:Ljava/lang/String;
   #45 = NameAndType        #46:#47       // _name:Ljava/lang/String;
   #46 = Utf8               _name
   #47 = Utf8               Ljava/lang/String;
   #48 = Fieldref           #1.#49        // ext/mods/gameserver/enums/MakerSpawnTime.VALUES:[Lext/mods/gameserver/enums/MakerSpawnTime;
   #49 = NameAndType        #50:#28       // VALUES:[Lext/mods/gameserver/enums/MakerSpawnTime;
   #50 = Utf8               VALUES
   #51 = Methodref          #1.#52        // ext/mods/gameserver/enums/MakerSpawnTime.getName:()Ljava/lang/String;
   #52 = NameAndType        #53:#54       // getName:()Ljava/lang/String;
   #53 = Utf8               getName
   #54 = Utf8               ()Ljava/lang/String;
   #55 = Methodref          #56.#57       // java/lang/String.equalsIgnoreCase:(Ljava/lang/String;)Z
   #56 = Class              #58           // java/lang/String
   #57 = NameAndType        #59:#60       // equalsIgnoreCase:(Ljava/lang/String;)Z
   #58 = Utf8               java/lang/String
   #59 = Utf8               equalsIgnoreCase
   #60 = Utf8               (Ljava/lang/String;)Z
   #61 = String             #5            // AGIT_BR_START
   #62 = String             #63           // agit_battle_royal_start
   #63 = Utf8               agit_battle_royal_start
   #64 = Methodref          #1.#65        // ext/mods/gameserver/enums/MakerSpawnTime."<init>":(Ljava/lang/String;ILjava/lang/String;)V
   #65 = NameAndType        #42:#66       // "<init>":(Ljava/lang/String;ILjava/lang/String;)V
   #66 = Utf8               (Ljava/lang/String;ILjava/lang/String;)V
   #67 = String             #9            // AGIT_FINAL_START
   #68 = String             #69           // agit_final_start
   #69 = Utf8               agit_final_start
   #70 = String             #12           // AGIT_DEF_START
   #71 = String             #72           // agit_defend_warfare_start
   #72 = Utf8               agit_defend_warfare_start
   #73 = String             #15           // AGIT_ATK_START
   #74 = String             #75           // agit_attack_warfare_start
   #75 = Utf8               agit_attack_warfare_start
   #76 = String             #18           // SIEGE_START
   #77 = String             #78           // siege_warfare_start
   #78 = Utf8               siege_warfare_start
   #79 = String             #21           // PC_SIEGE_START
   #80 = String             #81           // pc_siege_warfare_start
   #81 = Utf8               pc_siege_warfare_start
   #82 = String             #24           // DOOR_OPEN
   #83 = String             #84           // door_open
   #84 = Utf8               door_open
   #85 = Methodref          #1.#86        // ext/mods/gameserver/enums/MakerSpawnTime.$values:()[Lext/mods/gameserver/enums/MakerSpawnTime;
   #86 = NameAndType        #87:#88       // $values:()[Lext/mods/gameserver/enums/MakerSpawnTime;
   #87 = Utf8               $values
   #88 = Utf8               ()[Lext/mods/gameserver/enums/MakerSpawnTime;
   #89 = Methodref          #1.#90        // ext/mods/gameserver/enums/MakerSpawnTime.values:()[Lext/mods/gameserver/enums/MakerSpawnTime;
   #90 = NameAndType        #91:#88       // values:()[Lext/mods/gameserver/enums/MakerSpawnTime;
   #91 = Utf8               values
   #92 = Utf8               Code
   #93 = Utf8               LineNumberTable
   #94 = Utf8               (Ljava/lang/String;)Lext/mods/gameserver/enums/MakerSpawnTime;
   #95 = Utf8               LocalVariableTable
   #96 = Utf8               name
   #97 = Utf8               MethodParameters
   #98 = Utf8               this
   #99 = Utf8               Signature
  #100 = Utf8               (Ljava/lang/String;)V
  #101 = Utf8               getEnumByName
  #102 = Utf8               mst
  #103 = Utf8               StackMapTable
  #104 = Utf8               <clinit>
  #105 = Utf8               ()V
  #106 = Utf8               Ljava/lang/Enum<Lext/mods/gameserver/enums/MakerSpawnTime;>;
  #107 = Utf8               SourceFile
  #108 = Utf8               MakerSpawnTime.java
{
  public static final ext.mods.gameserver.enums.MakerSpawnTime AGIT_BR_START;
    descriptor: Lext/mods/gameserver/enums/MakerSpawnTime;
    flags: (0x4019) ACC_PUBLIC, ACC_STATIC, ACC_FINAL, ACC_ENUM

  public static final ext.mods.gameserver.enums.MakerSpawnTime AGIT_FINAL_START;
    descriptor: Lext/mods/gameserver/enums/MakerSpawnTime;
    flags: (0x4019) ACC_PUBLIC, ACC_STATIC, ACC_FINAL, ACC_ENUM

  public static final ext.mods.gameserver.enums.MakerSpawnTime AGIT_DEF_START;
    descriptor: Lext/mods/gameserver/enums/MakerSpawnTime;
    flags: (0x4019) ACC_PUBLIC, ACC_STATIC, ACC_FINAL, ACC_ENUM

  public static final ext.mods.gameserver.enums.MakerSpawnTime AGIT_ATK_START;
    descriptor: Lext/mods/gameserver/enums/MakerSpawnTime;
    flags: (0x4019) ACC_PUBLIC, ACC_STATIC, ACC_FINAL, ACC_ENUM

  public static final ext.mods.gameserver.enums.MakerSpawnTime SIEGE_START;
    descriptor: Lext/mods/gameserver/enums/MakerSpawnTime;
    flags: (0x4019) ACC_PUBLIC, ACC_STATIC, ACC_FINAL, ACC_ENUM

  public static final ext.mods.gameserver.enums.MakerSpawnTime PC_SIEGE_START;
    descriptor: Lext/mods/gameserver/enums/MakerSpawnTime;
    flags: (0x4019) ACC_PUBLIC, ACC_STATIC, ACC_FINAL, ACC_ENUM

  public static final ext.mods.gameserver.enums.MakerSpawnTime DOOR_OPEN;
    descriptor: Lext/mods/gameserver/enums/MakerSpawnTime;
    flags: (0x4019) ACC_PUBLIC, ACC_STATIC, ACC_FINAL, ACC_ENUM

  public static final ext.mods.gameserver.enums.MakerSpawnTime[] VALUES;
    descriptor: [Lext/mods/gameserver/enums/MakerSpawnTime;
    flags: (0x0019) ACC_PUBLIC, ACC_STATIC, ACC_FINAL

  public static ext.mods.gameserver.enums.MakerSpawnTime[] values();
    descriptor: ()[Lext/mods/gameserver/enums/MakerSpawnTime;
    flags: (0x0009) ACC_PUBLIC, ACC_STATIC
    Code:
      stack=1, locals=0, args_size=0
         0: getstatic     #25                 // Field $VALUES:[Lext/mods/gameserver/enums/MakerSpawnTime;
         3: invokevirtual #29                 // Method "[Lext/mods/gameserver/enums/MakerSpawnTime;".clone:()Ljava/lang/Object;
         6: checkcast     #30                 // class "[Lext/mods/gameserver/enums/MakerSpawnTime;"
         9: areturn
      LineNumberTable:
        line 20: 0

  public static ext.mods.gameserver.enums.MakerSpawnTime valueOf(java.lang.String);
    descriptor: (Ljava/lang/String;)Lext/mods/gameserver/enums/MakerSpawnTime;
    flags: (0x0009) ACC_PUBLIC, ACC_STATIC
    Code:
      stack=2, locals=1, args_size=1
         0: ldc           #1                  // class ext/mods/gameserver/enums/MakerSpawnTime
         2: aload_0
         3: invokestatic  #34                 // Method java/lang/Enum.valueOf:(Ljava/lang/Class;Ljava/lang/String;)Ljava/lang/Enum;
         6: checkcast     #1                  // class ext/mods/gameserver/enums/MakerSpawnTime
         9: areturn
      LineNumberTable:
        line 20: 0
      LocalVariableTable:
        Start  Length  Slot  Name   Signature
            0      10     0  name   Ljava/lang/String;
    MethodParameters:
      Name                           Flags
      <no name>                      mandated

  public java.lang.String getName();
    descriptor: ()Ljava/lang/String;
    flags: (0x0001) ACC_PUBLIC
    Code:
      stack=1, locals=1, args_size=1
         0: aload_0
         1: getfield      #44                 // Field _name:Ljava/lang/String;
         4: areturn
      LineNumberTable:
        line 39: 0
      LocalVariableTable:
        Start  Length  Slot  Name   Signature
            0       5     0  this   Lext/mods/gameserver/enums/MakerSpawnTime;

  public static ext.mods.gameserver.enums.MakerSpawnTime getEnumByName(java.lang.String);
    descriptor: (Ljava/lang/String;)Lext/mods/gameserver/enums/MakerSpawnTime;
    flags: (0x0009) ACC_PUBLIC, ACC_STATIC
    Code:
      stack=2, locals=5, args_size=1
         0: getstatic     #48                 // Field VALUES:[Lext/mods/gameserver/enums/MakerSpawnTime;
         3: astore_1
         4: aload_1
         5: arraylength
         6: istore_2
         7: iconst_0
         8: istore_3
         9: iload_3
        10: iload_2
        11: if_icmpge     40
        14: aload_1
        15: iload_3
        16: aaload
        17: astore        4
        19: aload         4
        21: invokevirtual #51                 // Method getName:()Ljava/lang/String;
        24: aload_0
        25: invokevirtual #55                 // Method java/lang/String.equalsIgnoreCase:(Ljava/lang/String;)Z
        28: ifeq          34
        31: aload         4
        33: areturn
        34: iinc          3, 1
        37: goto          9
        40: aconst_null
        41: areturn
      LineNumberTable:
        line 46: 0
        line 48: 19
        line 49: 31
        line 46: 34
        line 51: 40
      LocalVariableTable:
        Start  Length  Slot  Name   Signature
           19      15     4   mst   Lext/mods/gameserver/enums/MakerSpawnTime;
            0      42     0  name   Ljava/lang/String;
      StackMapTable: number_of_entries = 3
        frame_type = 254 /* append */
          offset_delta = 9
          locals = [ class "[Lext/mods/gameserver/enums/MakerSpawnTime;", int, int ]
        frame_type = 24 /* same */
        frame_type = 248 /* chop */
          offset_delta = 5

  static {};
    descriptor: ()V
    flags: (0x0008) ACC_STATIC
    Code:
      stack=5, locals=0, args_size=0
         0: new           #1                  // class ext/mods/gameserver/enums/MakerSpawnTime
         3: dup
         4: ldc           #61                 // String AGIT_BR_START
         6: iconst_0
         7: ldc           #62                 // String agit_battle_royal_start
         9: invokespecial #64                 // Method "<init>":(Ljava/lang/String;ILjava/lang/String;)V
        12: putstatic     #3                  // Field AGIT_BR_START:Lext/mods/gameserver/enums/MakerSpawnTime;
        15: new           #1                  // class ext/mods/gameserver/enums/MakerSpawnTime
        18: dup
        19: ldc           #67                 // String AGIT_FINAL_START
        21: iconst_1
        22: ldc           #68                 // String agit_final_start
        24: invokespecial #64                 // Method "<init>":(Ljava/lang/String;ILjava/lang/String;)V
        27: putstatic     #7                  // Field AGIT_FINAL_START:Lext/mods/gameserver/enums/MakerSpawnTime;
        30: new           #1                  // class ext/mods/gameserver/enums/MakerSpawnTime
        33: dup
        34: ldc           #70                 // String AGIT_DEF_START
        36: iconst_2
        37: ldc           #71                 // String agit_defend_warfare_start
        39: invokespecial #64                 // Method "<init>":(Ljava/lang/String;ILjava/lang/String;)V
        42: putstatic     #10                 // Field AGIT_DEF_START:Lext/mods/gameserver/enums/MakerSpawnTime;
        45: new           #1                  // class ext/mods/gameserver/enums/MakerSpawnTime
        48: dup
        49: ldc           #73                 // String AGIT_ATK_START
        51: iconst_3
        52: ldc           #74                 // String agit_attack_warfare_start
        54: invokespecial #64                 // Method "<init>":(Ljava/lang/String;ILjava/lang/String;)V
        57: putstatic     #13                 // Field AGIT_ATK_START:Lext/mods/gameserver/enums/MakerSpawnTime;
        60: new           #1                  // class ext/mods/gameserver/enums/MakerSpawnTime
        63: dup
        64: ldc           #76                 // String SIEGE_START
        66: iconst_4
        67: ldc           #77                 // String siege_warfare_start
        69: invokespecial #64                 // Method "<init>":(Ljava/lang/String;ILjava/lang/String;)V
        72: putstatic     #16                 // Field SIEGE_START:Lext/mods/gameserver/enums/MakerSpawnTime;
        75: new           #1                  // class ext/mods/gameserver/enums/MakerSpawnTime
        78: dup
        79: ldc           #79                 // String PC_SIEGE_START
        81: iconst_5
        82: ldc           #80                 // String pc_siege_warfare_start
        84: invokespecial #64                 // Method "<init>":(Ljava/lang/String;ILjava/lang/String;)V
        87: putstatic     #19                 // Field PC_SIEGE_START:Lext/mods/gameserver/enums/MakerSpawnTime;
        90: new           #1                  // class ext/mods/gameserver/enums/MakerSpawnTime
        93: dup
        94: ldc           #82                 // String DOOR_OPEN
        96: bipush        6
        98: ldc           #83                 // String door_open
       100: invokespecial #64                 // Method "<init>":(Ljava/lang/String;ILjava/lang/String;)V
       103: putstatic     #22                 // Field DOOR_OPEN:Lext/mods/gameserver/enums/MakerSpawnTime;
       106: invokestatic  #85                 // Method $values:()[Lext/mods/gameserver/enums/MakerSpawnTime;
       109: putstatic     #25                 // Field $VALUES:[Lext/mods/gameserver/enums/MakerSpawnTime;
       112: invokestatic  #89                 // Method values:()[Lext/mods/gameserver/enums/MakerSpawnTime;
       115: putstatic     #48                 // Field VALUES:[Lext/mods/gameserver/enums/MakerSpawnTime;
       118: return
      LineNumberTable:
        line 22: 0
        line 23: 15
        line 24: 30
        line 25: 45
        line 26: 60
        line 27: 75
        line 28: 90
        line 20: 106
        line 42: 112
}
Signature: #106                         // Ljava/lang/Enum<Lext/mods/gameserver/enums/MakerSpawnTime;>;
SourceFile: "MakerSpawnTime.java"
