// Bytecode for: ext.mods.gameserver.enums.Paperdoll
// File: ext\mods\gameserver\enums\Paperdoll.class

Classfile /c:/Users/User/Desktop/BrProject/bin/main/ext/mods/gameserver/enums/Paperdoll.class
  Last modified 9 de jul de 2026; size 2862 bytes
  MD5 checksum 6dffa90a7c497be3ff0e6c6426d707c8
  Compiled from "Paperdoll.java"
public final class ext.mods.gameserver.enums.Paperdoll extends java.lang.Enum<ext.mods.gameserver.enums.Paperdoll>
  minor version: 0
  major version: 69
  flags: (0x4031) ACC_PUBLIC, ACC_FINAL, ACC_SUPER, ACC_ENUM
  this_class: #1                          // ext/mods/gameserver/enums/Paperdoll
  super_class: #71                        // java/lang/Enum
  interfaces: 0, fields: 23, methods: 8, attributes: 2
Constant pool:
    #1 = Class              #2            // ext/mods/gameserver/enums/Paperdoll
    #2 = Utf8               ext/mods/gameserver/enums/Paperdoll
    #3 = Fieldref           #1.#4         // ext/mods/gameserver/enums/Paperdoll.NULL:Lext/mods/gameserver/enums/Paperdoll;
    #4 = NameAndType        #5:#6         // NULL:Lext/mods/gameserver/enums/Paperdoll;
    #5 = Utf8               NULL
    #6 = Utf8               Lext/mods/gameserver/enums/Paperdoll;
    #7 = Fieldref           #1.#8         // ext/mods/gameserver/enums/Paperdoll.UNDER:Lext/mods/gameserver/enums/Paperdoll;
    #8 = NameAndType        #9:#6         // UNDER:Lext/mods/gameserver/enums/Paperdoll;
    #9 = Utf8               UNDER
   #10 = Fieldref           #1.#11        // ext/mods/gameserver/enums/Paperdoll.LEAR:Lext/mods/gameserver/enums/Paperdoll;
   #11 = NameAndType        #12:#6        // LEAR:Lext/mods/gameserver/enums/Paperdoll;
   #12 = Utf8               LEAR
   #13 = Fieldref           #1.#14        // ext/mods/gameserver/enums/Paperdoll.REAR:Lext/mods/gameserver/enums/Paperdoll;
   #14 = NameAndType        #15:#6        // REAR:Lext/mods/gameserver/enums/Paperdoll;
   #15 = Utf8               REAR
   #16 = Fieldref           #1.#17        // ext/mods/gameserver/enums/Paperdoll.NECK:Lext/mods/gameserver/enums/Paperdoll;
   #17 = NameAndType        #18:#6        // NECK:Lext/mods/gameserver/enums/Paperdoll;
   #18 = Utf8               NECK
   #19 = Fieldref           #1.#20        // ext/mods/gameserver/enums/Paperdoll.LFINGER:Lext/mods/gameserver/enums/Paperdoll;
   #20 = NameAndType        #21:#6        // LFINGER:Lext/mods/gameserver/enums/Paperdoll;
   #21 = Utf8               LFINGER
   #22 = Fieldref           #1.#23        // ext/mods/gameserver/enums/Paperdoll.RFINGER:Lext/mods/gameserver/enums/Paperdoll;
   #23 = NameAndType        #24:#6        // RFINGER:Lext/mods/gameserver/enums/Paperdoll;
   #24 = Utf8               RFINGER
   #25 = Fieldref           #1.#26        // ext/mods/gameserver/enums/Paperdoll.HEAD:Lext/mods/gameserver/enums/Paperdoll;
   #26 = NameAndType        #27:#6        // HEAD:Lext/mods/gameserver/enums/Paperdoll;
   #27 = Utf8               HEAD
   #28 = Fieldref           #1.#29        // ext/mods/gameserver/enums/Paperdoll.RHAND:Lext/mods/gameserver/enums/Paperdoll;
   #29 = NameAndType        #30:#6        // RHAND:Lext/mods/gameserver/enums/Paperdoll;
   #30 = Utf8               RHAND
   #31 = Fieldref           #1.#32        // ext/mods/gameserver/enums/Paperdoll.LHAND:Lext/mods/gameserver/enums/Paperdoll;
   #32 = NameAndType        #33:#6        // LHAND:Lext/mods/gameserver/enums/Paperdoll;
   #33 = Utf8               LHAND
   #34 = Fieldref           #1.#35        // ext/mods/gameserver/enums/Paperdoll.LRHAND:Lext/mods/gameserver/enums/Paperdoll;
   #35 = NameAndType        #36:#6        // LRHAND:Lext/mods/gameserver/enums/Paperdoll;
   #36 = Utf8               LRHAND
   #37 = Fieldref           #1.#38        // ext/mods/gameserver/enums/Paperdoll.GLOVES:Lext/mods/gameserver/enums/Paperdoll;
   #38 = NameAndType        #39:#6        // GLOVES:Lext/mods/gameserver/enums/Paperdoll;
   #39 = Utf8               GLOVES
   #40 = Fieldref           #1.#41        // ext/mods/gameserver/enums/Paperdoll.CHEST:Lext/mods/gameserver/enums/Paperdoll;
   #41 = NameAndType        #42:#6        // CHEST:Lext/mods/gameserver/enums/Paperdoll;
   #42 = Utf8               CHEST
   #43 = Fieldref           #1.#44        // ext/mods/gameserver/enums/Paperdoll.LEGS:Lext/mods/gameserver/enums/Paperdoll;
   #44 = NameAndType        #45:#6        // LEGS:Lext/mods/gameserver/enums/Paperdoll;
   #45 = Utf8               LEGS
   #46 = Fieldref           #1.#47        // ext/mods/gameserver/enums/Paperdoll.FEET:Lext/mods/gameserver/enums/Paperdoll;
   #47 = NameAndType        #48:#6        // FEET:Lext/mods/gameserver/enums/Paperdoll;
   #48 = Utf8               FEET
   #49 = Fieldref           #1.#50        // ext/mods/gameserver/enums/Paperdoll.CLOAK:Lext/mods/gameserver/enums/Paperdoll;
   #50 = NameAndType        #51:#6        // CLOAK:Lext/mods/gameserver/enums/Paperdoll;
   #51 = Utf8               CLOAK
   #52 = Fieldref           #1.#53        // ext/mods/gameserver/enums/Paperdoll.FACE:Lext/mods/gameserver/enums/Paperdoll;
   #53 = NameAndType        #54:#6        // FACE:Lext/mods/gameserver/enums/Paperdoll;
   #54 = Utf8               FACE
   #55 = Fieldref           #1.#56        // ext/mods/gameserver/enums/Paperdoll.HAIR:Lext/mods/gameserver/enums/Paperdoll;
   #56 = NameAndType        #57:#6        // HAIR:Lext/mods/gameserver/enums/Paperdoll;
   #57 = Utf8               HAIR
   #58 = Fieldref           #1.#59        // ext/mods/gameserver/enums/Paperdoll.HAIRALL:Lext/mods/gameserver/enums/Paperdoll;
   #59 = NameAndType        #60:#6        // HAIRALL:Lext/mods/gameserver/enums/Paperdoll;
   #60 = Utf8               HAIRALL
   #61 = Fieldref           #1.#62        // ext/mods/gameserver/enums/Paperdoll.$VALUES:[Lext/mods/gameserver/enums/Paperdoll;
   #62 = NameAndType        #63:#64       // $VALUES:[Lext/mods/gameserver/enums/Paperdoll;
   #63 = Utf8               $VALUES
   #64 = Utf8               [Lext/mods/gameserver/enums/Paperdoll;
   #65 = Methodref          #66.#67       // "[Lext/mods/gameserver/enums/Paperdoll;".clone:()Ljava/lang/Object;
   #66 = Class              #64           // "[Lext/mods/gameserver/enums/Paperdoll;"
   #67 = NameAndType        #68:#69       // clone:()Ljava/lang/Object;
   #68 = Utf8               clone
   #69 = Utf8               ()Ljava/lang/Object;
   #70 = Methodref          #71.#72       // java/lang/Enum.valueOf:(Ljava/lang/Class;Ljava/lang/String;)Ljava/lang/Enum;
   #71 = Class              #73           // java/lang/Enum
   #72 = NameAndType        #74:#75       // valueOf:(Ljava/lang/Class;Ljava/lang/String;)Ljava/lang/Enum;
   #73 = Utf8               java/lang/Enum
   #74 = Utf8               valueOf
   #75 = Utf8               (Ljava/lang/Class;Ljava/lang/String;)Ljava/lang/Enum;
   #76 = Methodref          #71.#77       // java/lang/Enum."<init>":(Ljava/lang/String;I)V
   #77 = NameAndType        #78:#79       // "<init>":(Ljava/lang/String;I)V
   #78 = Utf8               <init>
   #79 = Utf8               (Ljava/lang/String;I)V
   #80 = Fieldref           #1.#81        // ext/mods/gameserver/enums/Paperdoll._id:I
   #81 = NameAndType        #82:#83       // _id:I
   #82 = Utf8               _id
   #83 = Utf8               I
   #84 = Fieldref           #1.#85        // ext/mods/gameserver/enums/Paperdoll.VALUES:[Lext/mods/gameserver/enums/Paperdoll;
   #85 = NameAndType        #86:#64       // VALUES:[Lext/mods/gameserver/enums/Paperdoll;
   #86 = Utf8               VALUES
   #87 = Methodref          #1.#88        // ext/mods/gameserver/enums/Paperdoll.toString:()Ljava/lang/String;
   #88 = NameAndType        #89:#90       // toString:()Ljava/lang/String;
   #89 = Utf8               toString
   #90 = Utf8               ()Ljava/lang/String;
   #91 = Methodref          #92.#93       // java/lang/String.equalsIgnoreCase:(Ljava/lang/String;)Z
   #92 = Class              #94           // java/lang/String
   #93 = NameAndType        #95:#96       // equalsIgnoreCase:(Ljava/lang/String;)Z
   #94 = Utf8               java/lang/String
   #95 = Utf8               equalsIgnoreCase
   #96 = Utf8               (Ljava/lang/String;)Z
   #97 = Methodref          #1.#98        // ext/mods/gameserver/enums/Paperdoll.getId:()I
   #98 = NameAndType        #99:#100      // getId:()I
   #99 = Utf8               getId
  #100 = Utf8               ()I
  #101 = String             #5            // NULL
  #102 = Methodref          #1.#103       // ext/mods/gameserver/enums/Paperdoll."<init>":(Ljava/lang/String;II)V
  #103 = NameAndType        #78:#104      // "<init>":(Ljava/lang/String;II)V
  #104 = Utf8               (Ljava/lang/String;II)V
  #105 = String             #9            // UNDER
  #106 = String             #12           // LEAR
  #107 = String             #15           // REAR
  #108 = String             #18           // NECK
  #109 = String             #21           // LFINGER
  #110 = String             #24           // RFINGER
  #111 = String             #27           // HEAD
  #112 = String             #30           // RHAND
  #113 = String             #33           // LHAND
  #114 = String             #36           // LRHAND
  #115 = String             #39           // GLOVES
  #116 = String             #42           // CHEST
  #117 = String             #45           // LEGS
  #118 = String             #48           // FEET
  #119 = String             #51           // CLOAK
  #120 = String             #54           // FACE
  #121 = String             #57           // HAIR
  #122 = String             #60           // HAIRALL
  #123 = Methodref          #1.#124       // ext/mods/gameserver/enums/Paperdoll.$values:()[Lext/mods/gameserver/enums/Paperdoll;
  #124 = NameAndType        #125:#126     // $values:()[Lext/mods/gameserver/enums/Paperdoll;
  #125 = Utf8               $values
  #126 = Utf8               ()[Lext/mods/gameserver/enums/Paperdoll;
  #127 = Methodref          #1.#128       // ext/mods/gameserver/enums/Paperdoll.values:()[Lext/mods/gameserver/enums/Paperdoll;
  #128 = NameAndType        #129:#126     // values:()[Lext/mods/gameserver/enums/Paperdoll;
  #129 = Utf8               values
  #130 = Utf8               TOTAL_SLOTS
  #131 = Utf8               ConstantValue
  #132 = Integer            18
  #133 = Utf8               Code
  #134 = Utf8               LineNumberTable
  #135 = Utf8               (Ljava/lang/String;)Lext/mods/gameserver/enums/Paperdoll;
  #136 = Utf8               LocalVariableTable
  #137 = Utf8               name
  #138 = Utf8               Ljava/lang/String;
  #139 = Utf8               MethodParameters
  #140 = Utf8               this
  #141 = Utf8               id
  #142 = Utf8               Signature
  #143 = Utf8               (I)V
  #144 = Utf8               getEnumByName
  #145 = Utf8               paperdoll
  #146 = Utf8               StackMapTable
  #147 = Utf8               getEnumById
  #148 = Utf8               (I)Lext/mods/gameserver/enums/Paperdoll;
  #149 = Utf8               <clinit>
  #150 = Utf8               ()V
  #151 = Utf8               Ljava/lang/Enum<Lext/mods/gameserver/enums/Paperdoll;>;
  #152 = Utf8               SourceFile
  #153 = Utf8               Paperdoll.java
{
  public static final ext.mods.gameserver.enums.Paperdoll NULL;
    descriptor: Lext/mods/gameserver/enums/Paperdoll;
    flags: (0x4019) ACC_PUBLIC, ACC_STATIC, ACC_FINAL, ACC_ENUM

  public static final ext.mods.gameserver.enums.Paperdoll UNDER;
    descriptor: Lext/mods/gameserver/enums/Paperdoll;
    flags: (0x4019) ACC_PUBLIC, ACC_STATIC, ACC_FINAL, ACC_ENUM

  public static final ext.mods.gameserver.enums.Paperdoll LEAR;
    descriptor: Lext/mods/gameserver/enums/Paperdoll;
    flags: (0x4019) ACC_PUBLIC, ACC_STATIC, ACC_FINAL, ACC_ENUM

  public static final ext.mods.gameserver.enums.Paperdoll REAR;
    descriptor: Lext/mods/gameserver/enums/Paperdoll;
    flags: (0x4019) ACC_PUBLIC, ACC_STATIC, ACC_FINAL, ACC_ENUM

  public static final ext.mods.gameserver.enums.Paperdoll NECK;
    descriptor: Lext/mods/gameserver/enums/Paperdoll;
    flags: (0x4019) ACC_PUBLIC, ACC_STATIC, ACC_FINAL, ACC_ENUM

  public static final ext.mods.gameserver.enums.Paperdoll LFINGER;
    descriptor: Lext/mods/gameserver/enums/Paperdoll;
    flags: (0x4019) ACC_PUBLIC, ACC_STATIC, ACC_FINAL, ACC_ENUM

  public static final ext.mods.gameserver.enums.Paperdoll RFINGER;
    descriptor: Lext/mods/gameserver/enums/Paperdoll;
    flags: (0x4019) ACC_PUBLIC, ACC_STATIC, ACC_FINAL, ACC_ENUM

  public static final ext.mods.gameserver.enums.Paperdoll HEAD;
    descriptor: Lext/mods/gameserver/enums/Paperdoll;
    flags: (0x4019) ACC_PUBLIC, ACC_STATIC, ACC_FINAL, ACC_ENUM

  public static final ext.mods.gameserver.enums.Paperdoll RHAND;
    descriptor: Lext/mods/gameserver/enums/Paperdoll;
    flags: (0x4019) ACC_PUBLIC, ACC_STATIC, ACC_FINAL, ACC_ENUM

  public static final ext.mods.gameserver.enums.Paperdoll LHAND;
    descriptor: Lext/mods/gameserver/enums/Paperdoll;
    flags: (0x4019) ACC_PUBLIC, ACC_STATIC, ACC_FINAL, ACC_ENUM

  public static final ext.mods.gameserver.enums.Paperdoll LRHAND;
    descriptor: Lext/mods/gameserver/enums/Paperdoll;
    flags: (0x4019) ACC_PUBLIC, ACC_STATIC, ACC_FINAL, ACC_ENUM

  public static final ext.mods.gameserver.enums.Paperdoll GLOVES;
    descriptor: Lext/mods/gameserver/enums/Paperdoll;
    flags: (0x4019) ACC_PUBLIC, ACC_STATIC, ACC_FINAL, ACC_ENUM

  public static final ext.mods.gameserver.enums.Paperdoll CHEST;
    descriptor: Lext/mods/gameserver/enums/Paperdoll;
    flags: (0x4019) ACC_PUBLIC, ACC_STATIC, ACC_FINAL, ACC_ENUM

  public static final ext.mods.gameserver.enums.Paperdoll LEGS;
    descriptor: Lext/mods/gameserver/enums/Paperdoll;
    flags: (0x4019) ACC_PUBLIC, ACC_STATIC, ACC_FINAL, ACC_ENUM

  public static final ext.mods.gameserver.enums.Paperdoll FEET;
    descriptor: Lext/mods/gameserver/enums/Paperdoll;
    flags: (0x4019) ACC_PUBLIC, ACC_STATIC, ACC_FINAL, ACC_ENUM

  public static final ext.mods.gameserver.enums.Paperdoll CLOAK;
    descriptor: Lext/mods/gameserver/enums/Paperdoll;
    flags: (0x4019) ACC_PUBLIC, ACC_STATIC, ACC_FINAL, ACC_ENUM

  public static final ext.mods.gameserver.enums.Paperdoll FACE;
    descriptor: Lext/mods/gameserver/enums/Paperdoll;
    flags: (0x4019) ACC_PUBLIC, ACC_STATIC, ACC_FINAL, ACC_ENUM

  public static final ext.mods.gameserver.enums.Paperdoll HAIR;
    descriptor: Lext/mods/gameserver/enums/Paperdoll;
    flags: (0x4019) ACC_PUBLIC, ACC_STATIC, ACC_FINAL, ACC_ENUM

  public static final ext.mods.gameserver.enums.Paperdoll HAIRALL;
    descriptor: Lext/mods/gameserver/enums/Paperdoll;
    flags: (0x4019) ACC_PUBLIC, ACC_STATIC, ACC_FINAL, ACC_ENUM

  public static final ext.mods.gameserver.enums.Paperdoll[] VALUES;
    descriptor: [Lext/mods/gameserver/enums/Paperdoll;
    flags: (0x0019) ACC_PUBLIC, ACC_STATIC, ACC_FINAL

  public static final int TOTAL_SLOTS;
    descriptor: I
    flags: (0x0019) ACC_PUBLIC, ACC_STATIC, ACC_FINAL
    ConstantValue: int 18

  public static ext.mods.gameserver.enums.Paperdoll[] values();
    descriptor: ()[Lext/mods/gameserver/enums/Paperdoll;
    flags: (0x0009) ACC_PUBLIC, ACC_STATIC
    Code:
      stack=1, locals=0, args_size=0
         0: getstatic     #61                 // Field $VALUES:[Lext/mods/gameserver/enums/Paperdoll;
         3: invokevirtual #65                 // Method "[Lext/mods/gameserver/enums/Paperdoll;".clone:()Ljava/lang/Object;
         6: checkcast     #66                 // class "[Lext/mods/gameserver/enums/Paperdoll;"
         9: areturn
      LineNumberTable:
        line 20: 0

  public static ext.mods.gameserver.enums.Paperdoll valueOf(java.lang.String);
    descriptor: (Ljava/lang/String;)Lext/mods/gameserver/enums/Paperdoll;
    flags: (0x0009) ACC_PUBLIC, ACC_STATIC
    Code:
      stack=2, locals=1, args_size=1
         0: ldc           #1                  // class ext/mods/gameserver/enums/Paperdoll
         2: aload_0
         3: invokestatic  #70                 // Method java/lang/Enum.valueOf:(Ljava/lang/Class;Ljava/lang/String;)Ljava/lang/Enum;
         6: checkcast     #1                  // class ext/mods/gameserver/enums/Paperdoll
         9: areturn
      LineNumberTable:
        line 20: 0
      LocalVariableTable:
        Start  Length  Slot  Name   Signature
            0      10     0  name   Ljava/lang/String;
    MethodParameters:
      Name                           Flags
      <no name>                      mandated

  public int getId();
    descriptor: ()I
    flags: (0x0001) ACC_PUBLIC
    Code:
      stack=1, locals=1, args_size=1
         0: aload_0
         1: getfield      #80                 // Field _id:I
         4: ireturn
      LineNumberTable:
        line 54: 0
      LocalVariableTable:
        Start  Length  Slot  Name   Signature
            0       5     0  this   Lext/mods/gameserver/enums/Paperdoll;

  public static ext.mods.gameserver.enums.Paperdoll getEnumByName(java.lang.String);
    descriptor: (Ljava/lang/String;)Lext/mods/gameserver/enums/Paperdoll;
    flags: (0x0009) ACC_PUBLIC, ACC_STATIC
    Code:
      stack=2, locals=5, args_size=1
         0: getstatic     #84                 // Field VALUES:[Lext/mods/gameserver/enums/Paperdoll;
         3: astore_1
         4: aload_1
         5: arraylength
         6: istore_2
         7: iconst_0
         8: istore_3
         9: iload_3
        10: iload_2
        11: if_icmpge     40
        14: aload_1
        15: iload_3
        16: aaload
        17: astore        4
        19: aload         4
        21: invokevirtual #87                 // Method toString:()Ljava/lang/String;
        24: aload_0
        25: invokevirtual #91                 // Method java/lang/String.equalsIgnoreCase:(Ljava/lang/String;)Z
        28: ifeq          34
        31: aload         4
        33: areturn
        34: iinc          3, 1
        37: goto          9
        40: getstatic     #3                  // Field NULL:Lext/mods/gameserver/enums/Paperdoll;
        43: areturn
      LineNumberTable:
        line 59: 0
        line 61: 19
        line 62: 31
        line 59: 34
        line 64: 40
      LocalVariableTable:
        Start  Length  Slot  Name   Signature
           19      15     4 paperdoll   Lext/mods/gameserver/enums/Paperdoll;
            0      44     0  name   Ljava/lang/String;
      StackMapTable: number_of_entries = 3
        frame_type = 254 /* append */
          offset_delta = 9
          locals = [ class "[Lext/mods/gameserver/enums/Paperdoll;", int, int ]
        frame_type = 24 /* same */
        frame_type = 248 /* chop */
          offset_delta = 5

  public static ext.mods.gameserver.enums.Paperdoll getEnumById(int);
    descriptor: (I)Lext/mods/gameserver/enums/Paperdoll;
    flags: (0x0009) ACC_PUBLIC, ACC_STATIC
    Code:
      stack=2, locals=5, args_size=1
         0: getstatic     #84                 // Field VALUES:[Lext/mods/gameserver/enums/Paperdoll;
         3: astore_1
         4: aload_1
         5: arraylength
         6: istore_2
         7: iconst_0
         8: istore_3
         9: iload_3
        10: iload_2
        11: if_icmpge     37
        14: aload_1
        15: iload_3
        16: aaload
        17: astore        4
        19: aload         4
        21: invokevirtual #97                 // Method getId:()I
        24: iload_0
        25: if_icmpne     31
        28: aload         4
        30: areturn
        31: iinc          3, 1
        34: goto          9
        37: getstatic     #3                  // Field NULL:Lext/mods/gameserver/enums/Paperdoll;
        40: areturn
      LineNumberTable:
        line 69: 0
        line 71: 19
        line 72: 28
        line 69: 31
        line 74: 37
      LocalVariableTable:
        Start  Length  Slot  Name   Signature
           19      12     4 paperdoll   Lext/mods/gameserver/enums/Paperdoll;
            0      41     0    id   I
      StackMapTable: number_of_entries = 3
        frame_type = 254 /* append */
          offset_delta = 9
          locals = [ class "[Lext/mods/gameserver/enums/Paperdoll;", int, int ]
        frame_type = 21 /* same */
        frame_type = 248 /* chop */
          offset_delta = 5

  static {};
    descriptor: ()V
    flags: (0x0008) ACC_STATIC
    Code:
      stack=5, locals=0, args_size=0
         0: new           #1                  // class ext/mods/gameserver/enums/Paperdoll
         3: dup
         4: ldc           #101                // String NULL
         6: iconst_0
         7: iconst_m1
         8: invokespecial #102                // Method "<init>":(Ljava/lang/String;II)V
        11: putstatic     #3                  // Field NULL:Lext/mods/gameserver/enums/Paperdoll;
        14: new           #1                  // class ext/mods/gameserver/enums/Paperdoll
        17: dup
        18: ldc           #105                // String UNDER
        20: iconst_1
        21: iconst_0
        22: invokespecial #102                // Method "<init>":(Ljava/lang/String;II)V
        25: putstatic     #7                  // Field UNDER:Lext/mods/gameserver/enums/Paperdoll;
        28: new           #1                  // class ext/mods/gameserver/enums/Paperdoll
        31: dup
        32: ldc           #106                // String LEAR
        34: iconst_2
        35: iconst_1
        36: invokespecial #102                // Method "<init>":(Ljava/lang/String;II)V
        39: putstatic     #10                 // Field LEAR:Lext/mods/gameserver/enums/Paperdoll;
        42: new           #1                  // class ext/mods/gameserver/enums/Paperdoll
        45: dup
        46: ldc           #107                // String REAR
        48: iconst_3
        49: iconst_2
        50: invokespecial #102                // Method "<init>":(Ljava/lang/String;II)V
        53: putstatic     #13                 // Field REAR:Lext/mods/gameserver/enums/Paperdoll;
        56: new           #1                  // class ext/mods/gameserver/enums/Paperdoll
        59: dup
        60: ldc           #108                // String NECK
        62: iconst_4
        63: iconst_3
        64: invokespecial #102                // Method "<init>":(Ljava/lang/String;II)V
        67: putstatic     #16                 // Field NECK:Lext/mods/gameserver/enums/Paperdoll;
        70: new           #1                  // class ext/mods/gameserver/enums/Paperdoll
        73: dup
        74: ldc           #109                // String LFINGER
        76: iconst_5
        77: iconst_4
        78: invokespecial #102                // Method "<init>":(Ljava/lang/String;II)V
        81: putstatic     #19                 // Field LFINGER:Lext/mods/gameserver/enums/Paperdoll;
        84: new           #1                  // class ext/mods/gameserver/enums/Paperdoll
        87: dup
        88: ldc           #110                // String RFINGER
        90: bipush        6
        92: iconst_5
        93: invokespecial #102                // Method "<init>":(Ljava/lang/String;II)V
        96: putstatic     #22                 // Field RFINGER:Lext/mods/gameserver/enums/Paperdoll;
        99: new           #1                  // class ext/mods/gameserver/enums/Paperdoll
       102: dup
       103: ldc           #111                // String HEAD
       105: bipush        7
       107: bipush        6
       109: invokespecial #102                // Method "<init>":(Ljava/lang/String;II)V
       112: putstatic     #25                 // Field HEAD:Lext/mods/gameserver/enums/Paperdoll;
       115: new           #1                  // class ext/mods/gameserver/enums/Paperdoll
       118: dup
       119: ldc           #112                // String RHAND
       121: bipush        8
       123: bipush        7
       125: invokespecial #102                // Method "<init>":(Ljava/lang/String;II)V
       128: putstatic     #28                 // Field RHAND:Lext/mods/gameserver/enums/Paperdoll;
       131: new           #1                  // class ext/mods/gameserver/enums/Paperdoll
       134: dup
       135: ldc           #113                // String LHAND
       137: bipush        9
       139: bipush        8
       141: invokespecial #102                // Method "<init>":(Ljava/lang/String;II)V
       144: putstatic     #31                 // Field LHAND:Lext/mods/gameserver/enums/Paperdoll;
       147: new           #1                  // class ext/mods/gameserver/enums/Paperdoll
       150: dup
       151: ldc           #114                // String LRHAND
       153: bipush        10
       155: bipush        9
       157: invokespecial #102                // Method "<init>":(Ljava/lang/String;II)V
       160: putstatic     #34                 // Field LRHAND:Lext/mods/gameserver/enums/Paperdoll;
       163: new           #1                  // class ext/mods/gameserver/enums/Paperdoll
       166: dup
       167: ldc           #115                // String GLOVES
       169: bipush        11
       171: bipush        10
       173: invokespecial #102                // Method "<init>":(Ljava/lang/String;II)V
       176: putstatic     #37                 // Field GLOVES:Lext/mods/gameserver/enums/Paperdoll;
       179: new           #1                  // class ext/mods/gameserver/enums/Paperdoll
       182: dup
       183: ldc           #116                // String CHEST
       185: bipush        12
       187: bipush        11
       189: invokespecial #102                // Method "<init>":(Ljava/lang/String;II)V
       192: putstatic     #40                 // Field CHEST:Lext/mods/gameserver/enums/Paperdoll;
       195: new           #1                  // class ext/mods/gameserver/enums/Paperdoll
       198: dup
       199: ldc           #117                // String LEGS
       201: bipush        13
       203: bipush        12
       205: invokespecial #102                // Method "<init>":(Ljava/lang/String;II)V
       208: putstatic     #43                 // Field LEGS:Lext/mods/gameserver/enums/Paperdoll;
       211: new           #1                  // class ext/mods/gameserver/enums/Paperdoll
       214: dup
       215: ldc           #118                // String FEET
       217: bipush        14
       219: bipush        13
       221: invokespecial #102                // Method "<init>":(Ljava/lang/String;II)V
       224: putstatic     #46                 // Field FEET:Lext/mods/gameserver/enums/Paperdoll;
       227: new           #1                  // class ext/mods/gameserver/enums/Paperdoll
       230: dup
       231: ldc           #119                // String CLOAK
       233: bipush        15
       235: bipush        14
       237: invokespecial #102                // Method "<init>":(Ljava/lang/String;II)V
       240: putstatic     #49                 // Field CLOAK:Lext/mods/gameserver/enums/Paperdoll;
       243: new           #1                  // class ext/mods/gameserver/enums/Paperdoll
       246: dup
       247: ldc           #120                // String FACE
       249: bipush        16
       251: bipush        15
       253: invokespecial #102                // Method "<init>":(Ljava/lang/String;II)V
       256: putstatic     #52                 // Field FACE:Lext/mods/gameserver/enums/Paperdoll;
       259: new           #1                  // class ext/mods/gameserver/enums/Paperdoll
       262: dup
       263: ldc           #121                // String HAIR
       265: bipush        17
       267: bipush        16
       269: invokespecial #102                // Method "<init>":(Ljava/lang/String;II)V
       272: putstatic     #55                 // Field HAIR:Lext/mods/gameserver/enums/Paperdoll;
       275: new           #1                  // class ext/mods/gameserver/enums/Paperdoll
       278: dup
       279: ldc           #122                // String HAIRALL
       281: bipush        18
       283: bipush        17
       285: invokespecial #102                // Method "<init>":(Ljava/lang/String;II)V
       288: putstatic     #58                 // Field HAIRALL:Lext/mods/gameserver/enums/Paperdoll;
       291: invokestatic  #123                // Method $values:()[Lext/mods/gameserver/enums/Paperdoll;
       294: putstatic     #61                 // Field $VALUES:[Lext/mods/gameserver/enums/Paperdoll;
       297: invokestatic  #127                // Method values:()[Lext/mods/gameserver/enums/Paperdoll;
       300: putstatic     #84                 // Field VALUES:[Lext/mods/gameserver/enums/Paperdoll;
       303: return
      LineNumberTable:
        line 22: 0
        line 23: 14
        line 24: 28
        line 25: 42
        line 26: 56
        line 27: 70
        line 28: 84
        line 29: 99
        line 30: 115
        line 31: 131
        line 32: 147
        line 33: 163
        line 34: 179
        line 35: 195
        line 36: 211
        line 37: 227
        line 38: 243
        line 39: 259
        line 40: 275
        line 20: 291
        line 42: 297
}
Signature: #151                         // Ljava/lang/Enum<Lext/mods/gameserver/enums/Paperdoll;>;
SourceFile: "Paperdoll.java"
