// Bytecode for: ext.mods.gameserver.enums.SayType
// File: ext\mods\gameserver\enums\SayType.class

Classfile /c:/Users/User/Desktop/BrProject/bin/main/ext/mods/gameserver/enums/SayType.class
  Last modified 9 de jul de 2026; size 2147 bytes
  MD5 checksum b8d11f8431761ce98f3ea519b0f54e7b
  Compiled from "SayType.java"
public final class ext.mods.gameserver.enums.SayType extends java.lang.Enum<ext.mods.gameserver.enums.SayType>
  minor version: 0
  major version: 69
  flags: (0x4031) ACC_PUBLIC, ACC_FINAL, ACC_SUPER, ACC_ENUM
  this_class: #1                          // ext/mods/gameserver/enums/SayType
  super_class: #71                        // java/lang/Enum
  interfaces: 0, fields: 21, methods: 5, attributes: 2
Constant pool:
    #1 = Class              #2            // ext/mods/gameserver/enums/SayType
    #2 = Utf8               ext/mods/gameserver/enums/SayType
    #3 = Fieldref           #1.#4         // ext/mods/gameserver/enums/SayType.ALL:Lext/mods/gameserver/enums/SayType;
    #4 = NameAndType        #5:#6         // ALL:Lext/mods/gameserver/enums/SayType;
    #5 = Utf8               ALL
    #6 = Utf8               Lext/mods/gameserver/enums/SayType;
    #7 = Fieldref           #1.#8         // ext/mods/gameserver/enums/SayType.SHOUT:Lext/mods/gameserver/enums/SayType;
    #8 = NameAndType        #9:#6         // SHOUT:Lext/mods/gameserver/enums/SayType;
    #9 = Utf8               SHOUT
   #10 = Fieldref           #1.#11        // ext/mods/gameserver/enums/SayType.TELL:Lext/mods/gameserver/enums/SayType;
   #11 = NameAndType        #12:#6        // TELL:Lext/mods/gameserver/enums/SayType;
   #12 = Utf8               TELL
   #13 = Fieldref           #1.#14        // ext/mods/gameserver/enums/SayType.PARTY:Lext/mods/gameserver/enums/SayType;
   #14 = NameAndType        #15:#6        // PARTY:Lext/mods/gameserver/enums/SayType;
   #15 = Utf8               PARTY
   #16 = Fieldref           #1.#17        // ext/mods/gameserver/enums/SayType.CLAN:Lext/mods/gameserver/enums/SayType;
   #17 = NameAndType        #18:#6        // CLAN:Lext/mods/gameserver/enums/SayType;
   #18 = Utf8               CLAN
   #19 = Fieldref           #1.#20        // ext/mods/gameserver/enums/SayType.GM:Lext/mods/gameserver/enums/SayType;
   #20 = NameAndType        #21:#6        // GM:Lext/mods/gameserver/enums/SayType;
   #21 = Utf8               GM
   #22 = Fieldref           #1.#23        // ext/mods/gameserver/enums/SayType.PETITION_PLAYER:Lext/mods/gameserver/enums/SayType;
   #23 = NameAndType        #24:#6        // PETITION_PLAYER:Lext/mods/gameserver/enums/SayType;
   #24 = Utf8               PETITION_PLAYER
   #25 = Fieldref           #1.#26        // ext/mods/gameserver/enums/SayType.PETITION_GM:Lext/mods/gameserver/enums/SayType;
   #26 = NameAndType        #27:#6        // PETITION_GM:Lext/mods/gameserver/enums/SayType;
   #27 = Utf8               PETITION_GM
   #28 = Fieldref           #1.#29        // ext/mods/gameserver/enums/SayType.TRADE:Lext/mods/gameserver/enums/SayType;
   #29 = NameAndType        #30:#6        // TRADE:Lext/mods/gameserver/enums/SayType;
   #30 = Utf8               TRADE
   #31 = Fieldref           #1.#32        // ext/mods/gameserver/enums/SayType.ALLIANCE:Lext/mods/gameserver/enums/SayType;
   #32 = NameAndType        #33:#6        // ALLIANCE:Lext/mods/gameserver/enums/SayType;
   #33 = Utf8               ALLIANCE
   #34 = Fieldref           #1.#35        // ext/mods/gameserver/enums/SayType.ANNOUNCEMENT:Lext/mods/gameserver/enums/SayType;
   #35 = NameAndType        #36:#6        // ANNOUNCEMENT:Lext/mods/gameserver/enums/SayType;
   #36 = Utf8               ANNOUNCEMENT
   #37 = Fieldref           #1.#38        // ext/mods/gameserver/enums/SayType.BOAT:Lext/mods/gameserver/enums/SayType;
   #38 = NameAndType        #39:#6        // BOAT:Lext/mods/gameserver/enums/SayType;
   #39 = Utf8               BOAT
   #40 = Fieldref           #1.#41        // ext/mods/gameserver/enums/SayType.L2FRIEND:Lext/mods/gameserver/enums/SayType;
   #41 = NameAndType        #42:#6        // L2FRIEND:Lext/mods/gameserver/enums/SayType;
   #42 = Utf8               L2FRIEND
   #43 = Fieldref           #1.#44        // ext/mods/gameserver/enums/SayType.MSNCHAT:Lext/mods/gameserver/enums/SayType;
   #44 = NameAndType        #45:#6        // MSNCHAT:Lext/mods/gameserver/enums/SayType;
   #45 = Utf8               MSNCHAT
   #46 = Fieldref           #1.#47        // ext/mods/gameserver/enums/SayType.PARTYMATCH_ROOM:Lext/mods/gameserver/enums/SayType;
   #47 = NameAndType        #48:#6        // PARTYMATCH_ROOM:Lext/mods/gameserver/enums/SayType;
   #48 = Utf8               PARTYMATCH_ROOM
   #49 = Fieldref           #1.#50        // ext/mods/gameserver/enums/SayType.PARTYROOM_COMMANDER:Lext/mods/gameserver/enums/SayType;
   #50 = NameAndType        #51:#6        // PARTYROOM_COMMANDER:Lext/mods/gameserver/enums/SayType;
   #51 = Utf8               PARTYROOM_COMMANDER
   #52 = Fieldref           #1.#53        // ext/mods/gameserver/enums/SayType.PARTYROOM_ALL:Lext/mods/gameserver/enums/SayType;
   #53 = NameAndType        #54:#6        // PARTYROOM_ALL:Lext/mods/gameserver/enums/SayType;
   #54 = Utf8               PARTYROOM_ALL
   #55 = Fieldref           #1.#56        // ext/mods/gameserver/enums/SayType.HERO_VOICE:Lext/mods/gameserver/enums/SayType;
   #56 = NameAndType        #57:#6        // HERO_VOICE:Lext/mods/gameserver/enums/SayType;
   #57 = Utf8               HERO_VOICE
   #58 = Fieldref           #1.#59        // ext/mods/gameserver/enums/SayType.CRITICAL_ANNOUNCE:Lext/mods/gameserver/enums/SayType;
   #59 = NameAndType        #60:#6        // CRITICAL_ANNOUNCE:Lext/mods/gameserver/enums/SayType;
   #60 = Utf8               CRITICAL_ANNOUNCE
   #61 = Fieldref           #1.#62        // ext/mods/gameserver/enums/SayType.$VALUES:[Lext/mods/gameserver/enums/SayType;
   #62 = NameAndType        #63:#64       // $VALUES:[Lext/mods/gameserver/enums/SayType;
   #63 = Utf8               $VALUES
   #64 = Utf8               [Lext/mods/gameserver/enums/SayType;
   #65 = Methodref          #66.#67       // "[Lext/mods/gameserver/enums/SayType;".clone:()Ljava/lang/Object;
   #66 = Class              #64           // "[Lext/mods/gameserver/enums/SayType;"
   #67 = NameAndType        #68:#69       // clone:()Ljava/lang/Object;
   #68 = Utf8               clone
   #69 = Utf8               ()Ljava/lang/Object;
   #70 = Methodref          #71.#72       // java/lang/Enum.valueOf:(Ljava/lang/Class;Ljava/lang/String;)Ljava/lang/Enum;
   #71 = Class              #73           // java/lang/Enum
   #72 = NameAndType        #74:#75       // valueOf:(Ljava/lang/Class;Ljava/lang/String;)Ljava/lang/Enum;
   #73 = Utf8               java/lang/Enum
   #74 = Utf8               valueOf
   #75 = Utf8               (Ljava/lang/Class;Ljava/lang/String;)Ljava/lang/Enum;
   #76 = Methodref          #71.#77       // java/lang/Enum."<init>":(Ljava/lang/String;I)V
   #77 = NameAndType        #78:#79       // "<init>":(Ljava/lang/String;I)V
   #78 = Utf8               <init>
   #79 = Utf8               (Ljava/lang/String;I)V
   #80 = String             #5            // ALL
   #81 = Methodref          #1.#77        // ext/mods/gameserver/enums/SayType."<init>":(Ljava/lang/String;I)V
   #82 = String             #9            // SHOUT
   #83 = String             #12           // TELL
   #84 = String             #15           // PARTY
   #85 = String             #18           // CLAN
   #86 = String             #21           // GM
   #87 = String             #24           // PETITION_PLAYER
   #88 = String             #27           // PETITION_GM
   #89 = String             #30           // TRADE
   #90 = String             #33           // ALLIANCE
   #91 = String             #36           // ANNOUNCEMENT
   #92 = String             #39           // BOAT
   #93 = String             #42           // L2FRIEND
   #94 = String             #45           // MSNCHAT
   #95 = String             #48           // PARTYMATCH_ROOM
   #96 = String             #51           // PARTYROOM_COMMANDER
   #97 = String             #54           // PARTYROOM_ALL
   #98 = String             #57           // HERO_VOICE
   #99 = String             #60           // CRITICAL_ANNOUNCE
  #100 = Methodref          #1.#101       // ext/mods/gameserver/enums/SayType.$values:()[Lext/mods/gameserver/enums/SayType;
  #101 = NameAndType        #102:#103     // $values:()[Lext/mods/gameserver/enums/SayType;
  #102 = Utf8               $values
  #103 = Utf8               ()[Lext/mods/gameserver/enums/SayType;
  #104 = Methodref          #1.#105       // ext/mods/gameserver/enums/SayType.values:()[Lext/mods/gameserver/enums/SayType;
  #105 = NameAndType        #106:#103     // values:()[Lext/mods/gameserver/enums/SayType;
  #106 = Utf8               values
  #107 = Fieldref           #1.#108       // ext/mods/gameserver/enums/SayType.VALUES:[Lext/mods/gameserver/enums/SayType;
  #108 = NameAndType        #109:#64      // VALUES:[Lext/mods/gameserver/enums/SayType;
  #109 = Utf8               VALUES
  #110 = Utf8               Code
  #111 = Utf8               LineNumberTable
  #112 = Utf8               (Ljava/lang/String;)Lext/mods/gameserver/enums/SayType;
  #113 = Utf8               LocalVariableTable
  #114 = Utf8               name
  #115 = Utf8               Ljava/lang/String;
  #116 = Utf8               MethodParameters
  #117 = Utf8               this
  #118 = Utf8               Signature
  #119 = Utf8               ()V
  #120 = Utf8               <clinit>
  #121 = Utf8               Ljava/lang/Enum<Lext/mods/gameserver/enums/SayType;>;
  #122 = Utf8               SourceFile
  #123 = Utf8               SayType.java
{
  public static final ext.mods.gameserver.enums.SayType ALL;
    descriptor: Lext/mods/gameserver/enums/SayType;
    flags: (0x4019) ACC_PUBLIC, ACC_STATIC, ACC_FINAL, ACC_ENUM

  public static final ext.mods.gameserver.enums.SayType SHOUT;
    descriptor: Lext/mods/gameserver/enums/SayType;
    flags: (0x4019) ACC_PUBLIC, ACC_STATIC, ACC_FINAL, ACC_ENUM

  public static final ext.mods.gameserver.enums.SayType TELL;
    descriptor: Lext/mods/gameserver/enums/SayType;
    flags: (0x4019) ACC_PUBLIC, ACC_STATIC, ACC_FINAL, ACC_ENUM

  public static final ext.mods.gameserver.enums.SayType PARTY;
    descriptor: Lext/mods/gameserver/enums/SayType;
    flags: (0x4019) ACC_PUBLIC, ACC_STATIC, ACC_FINAL, ACC_ENUM

  public static final ext.mods.gameserver.enums.SayType CLAN;
    descriptor: Lext/mods/gameserver/enums/SayType;
    flags: (0x4019) ACC_PUBLIC, ACC_STATIC, ACC_FINAL, ACC_ENUM

  public static final ext.mods.gameserver.enums.SayType GM;
    descriptor: Lext/mods/gameserver/enums/SayType;
    flags: (0x4019) ACC_PUBLIC, ACC_STATIC, ACC_FINAL, ACC_ENUM

  public static final ext.mods.gameserver.enums.SayType PETITION_PLAYER;
    descriptor: Lext/mods/gameserver/enums/SayType;
    flags: (0x4019) ACC_PUBLIC, ACC_STATIC, ACC_FINAL, ACC_ENUM

  public static final ext.mods.gameserver.enums.SayType PETITION_GM;
    descriptor: Lext/mods/gameserver/enums/SayType;
    flags: (0x4019) ACC_PUBLIC, ACC_STATIC, ACC_FINAL, ACC_ENUM

  public static final ext.mods.gameserver.enums.SayType TRADE;
    descriptor: Lext/mods/gameserver/enums/SayType;
    flags: (0x4019) ACC_PUBLIC, ACC_STATIC, ACC_FINAL, ACC_ENUM

  public static final ext.mods.gameserver.enums.SayType ALLIANCE;
    descriptor: Lext/mods/gameserver/enums/SayType;
    flags: (0x4019) ACC_PUBLIC, ACC_STATIC, ACC_FINAL, ACC_ENUM

  public static final ext.mods.gameserver.enums.SayType ANNOUNCEMENT;
    descriptor: Lext/mods/gameserver/enums/SayType;
    flags: (0x4019) ACC_PUBLIC, ACC_STATIC, ACC_FINAL, ACC_ENUM

  public static final ext.mods.gameserver.enums.SayType BOAT;
    descriptor: Lext/mods/gameserver/enums/SayType;
    flags: (0x4019) ACC_PUBLIC, ACC_STATIC, ACC_FINAL, ACC_ENUM

  public static final ext.mods.gameserver.enums.SayType L2FRIEND;
    descriptor: Lext/mods/gameserver/enums/SayType;
    flags: (0x4019) ACC_PUBLIC, ACC_STATIC, ACC_FINAL, ACC_ENUM

  public static final ext.mods.gameserver.enums.SayType MSNCHAT;
    descriptor: Lext/mods/gameserver/enums/SayType;
    flags: (0x4019) ACC_PUBLIC, ACC_STATIC, ACC_FINAL, ACC_ENUM

  public static final ext.mods.gameserver.enums.SayType PARTYMATCH_ROOM;
    descriptor: Lext/mods/gameserver/enums/SayType;
    flags: (0x4019) ACC_PUBLIC, ACC_STATIC, ACC_FINAL, ACC_ENUM

  public static final ext.mods.gameserver.enums.SayType PARTYROOM_COMMANDER;
    descriptor: Lext/mods/gameserver/enums/SayType;
    flags: (0x4019) ACC_PUBLIC, ACC_STATIC, ACC_FINAL, ACC_ENUM

  public static final ext.mods.gameserver.enums.SayType PARTYROOM_ALL;
    descriptor: Lext/mods/gameserver/enums/SayType;
    flags: (0x4019) ACC_PUBLIC, ACC_STATIC, ACC_FINAL, ACC_ENUM

  public static final ext.mods.gameserver.enums.SayType HERO_VOICE;
    descriptor: Lext/mods/gameserver/enums/SayType;
    flags: (0x4019) ACC_PUBLIC, ACC_STATIC, ACC_FINAL, ACC_ENUM

  public static final ext.mods.gameserver.enums.SayType CRITICAL_ANNOUNCE;
    descriptor: Lext/mods/gameserver/enums/SayType;
    flags: (0x4019) ACC_PUBLIC, ACC_STATIC, ACC_FINAL, ACC_ENUM

  public static final ext.mods.gameserver.enums.SayType[] VALUES;
    descriptor: [Lext/mods/gameserver/enums/SayType;
    flags: (0x0019) ACC_PUBLIC, ACC_STATIC, ACC_FINAL

  public static ext.mods.gameserver.enums.SayType[] values();
    descriptor: ()[Lext/mods/gameserver/enums/SayType;
    flags: (0x0009) ACC_PUBLIC, ACC_STATIC
    Code:
      stack=1, locals=0, args_size=0
         0: getstatic     #61                 // Field $VALUES:[Lext/mods/gameserver/enums/SayType;
         3: invokevirtual #65                 // Method "[Lext/mods/gameserver/enums/SayType;".clone:()Ljava/lang/Object;
         6: checkcast     #66                 // class "[Lext/mods/gameserver/enums/SayType;"
         9: areturn
      LineNumberTable:
        line 20: 0

  public static ext.mods.gameserver.enums.SayType valueOf(java.lang.String);
    descriptor: (Ljava/lang/String;)Lext/mods/gameserver/enums/SayType;
    flags: (0x0009) ACC_PUBLIC, ACC_STATIC
    Code:
      stack=2, locals=1, args_size=1
         0: ldc           #1                  // class ext/mods/gameserver/enums/SayType
         2: aload_0
         3: invokestatic  #70                 // Method java/lang/Enum.valueOf:(Ljava/lang/Class;Ljava/lang/String;)Ljava/lang/Enum;
         6: checkcast     #1                  // class ext/mods/gameserver/enums/SayType
         9: areturn
      LineNumberTable:
        line 20: 0
      LocalVariableTable:
        Start  Length  Slot  Name   Signature
            0      10     0  name   Ljava/lang/String;
    MethodParameters:
      Name                           Flags
      <no name>                      mandated

  static {};
    descriptor: ()V
    flags: (0x0008) ACC_STATIC
    Code:
      stack=4, locals=0, args_size=0
         0: new           #1                  // class ext/mods/gameserver/enums/SayType
         3: dup
         4: ldc           #80                 // String ALL
         6: iconst_0
         7: invokespecial #81                 // Method "<init>":(Ljava/lang/String;I)V
        10: putstatic     #3                  // Field ALL:Lext/mods/gameserver/enums/SayType;
        13: new           #1                  // class ext/mods/gameserver/enums/SayType
        16: dup
        17: ldc           #82                 // String SHOUT
        19: iconst_1
        20: invokespecial #81                 // Method "<init>":(Ljava/lang/String;I)V
        23: putstatic     #7                  // Field SHOUT:Lext/mods/gameserver/enums/SayType;
        26: new           #1                  // class ext/mods/gameserver/enums/SayType
        29: dup
        30: ldc           #83                 // String TELL
        32: iconst_2
        33: invokespecial #81                 // Method "<init>":(Ljava/lang/String;I)V
        36: putstatic     #10                 // Field TELL:Lext/mods/gameserver/enums/SayType;
        39: new           #1                  // class ext/mods/gameserver/enums/SayType
        42: dup
        43: ldc           #84                 // String PARTY
        45: iconst_3
        46: invokespecial #81                 // Method "<init>":(Ljava/lang/String;I)V
        49: putstatic     #13                 // Field PARTY:Lext/mods/gameserver/enums/SayType;
        52: new           #1                  // class ext/mods/gameserver/enums/SayType
        55: dup
        56: ldc           #85                 // String CLAN
        58: iconst_4
        59: invokespecial #81                 // Method "<init>":(Ljava/lang/String;I)V
        62: putstatic     #16                 // Field CLAN:Lext/mods/gameserver/enums/SayType;
        65: new           #1                  // class ext/mods/gameserver/enums/SayType
        68: dup
        69: ldc           #86                 // String GM
        71: iconst_5
        72: invokespecial #81                 // Method "<init>":(Ljava/lang/String;I)V
        75: putstatic     #19                 // Field GM:Lext/mods/gameserver/enums/SayType;
        78: new           #1                  // class ext/mods/gameserver/enums/SayType
        81: dup
        82: ldc           #87                 // String PETITION_PLAYER
        84: bipush        6
        86: invokespecial #81                 // Method "<init>":(Ljava/lang/String;I)V
        89: putstatic     #22                 // Field PETITION_PLAYER:Lext/mods/gameserver/enums/SayType;
        92: new           #1                  // class ext/mods/gameserver/enums/SayType
        95: dup
        96: ldc           #88                 // String PETITION_GM
        98: bipush        7
       100: invokespecial #81                 // Method "<init>":(Ljava/lang/String;I)V
       103: putstatic     #25                 // Field PETITION_GM:Lext/mods/gameserver/enums/SayType;
       106: new           #1                  // class ext/mods/gameserver/enums/SayType
       109: dup
       110: ldc           #89                 // String TRADE
       112: bipush        8
       114: invokespecial #81                 // Method "<init>":(Ljava/lang/String;I)V
       117: putstatic     #28                 // Field TRADE:Lext/mods/gameserver/enums/SayType;
       120: new           #1                  // class ext/mods/gameserver/enums/SayType
       123: dup
       124: ldc           #90                 // String ALLIANCE
       126: bipush        9
       128: invokespecial #81                 // Method "<init>":(Ljava/lang/String;I)V
       131: putstatic     #31                 // Field ALLIANCE:Lext/mods/gameserver/enums/SayType;
       134: new           #1                  // class ext/mods/gameserver/enums/SayType
       137: dup
       138: ldc           #91                 // String ANNOUNCEMENT
       140: bipush        10
       142: invokespecial #81                 // Method "<init>":(Ljava/lang/String;I)V
       145: putstatic     #34                 // Field ANNOUNCEMENT:Lext/mods/gameserver/enums/SayType;
       148: new           #1                  // class ext/mods/gameserver/enums/SayType
       151: dup
       152: ldc           #92                 // String BOAT
       154: bipush        11
       156: invokespecial #81                 // Method "<init>":(Ljava/lang/String;I)V
       159: putstatic     #37                 // Field BOAT:Lext/mods/gameserver/enums/SayType;
       162: new           #1                  // class ext/mods/gameserver/enums/SayType
       165: dup
       166: ldc           #93                 // String L2FRIEND
       168: bipush        12
       170: invokespecial #81                 // Method "<init>":(Ljava/lang/String;I)V
       173: putstatic     #40                 // Field L2FRIEND:Lext/mods/gameserver/enums/SayType;
       176: new           #1                  // class ext/mods/gameserver/enums/SayType
       179: dup
       180: ldc           #94                 // String MSNCHAT
       182: bipush        13
       184: invokespecial #81                 // Method "<init>":(Ljava/lang/String;I)V
       187: putstatic     #43                 // Field MSNCHAT:Lext/mods/gameserver/enums/SayType;
       190: new           #1                  // class ext/mods/gameserver/enums/SayType
       193: dup
       194: ldc           #95                 // String PARTYMATCH_ROOM
       196: bipush        14
       198: invokespecial #81                 // Method "<init>":(Ljava/lang/String;I)V
       201: putstatic     #46                 // Field PARTYMATCH_ROOM:Lext/mods/gameserver/enums/SayType;
       204: new           #1                  // class ext/mods/gameserver/enums/SayType
       207: dup
       208: ldc           #96                 // String PARTYROOM_COMMANDER
       210: bipush        15
       212: invokespecial #81                 // Method "<init>":(Ljava/lang/String;I)V
       215: putstatic     #49                 // Field PARTYROOM_COMMANDER:Lext/mods/gameserver/enums/SayType;
       218: new           #1                  // class ext/mods/gameserver/enums/SayType
       221: dup
       222: ldc           #97                 // String PARTYROOM_ALL
       224: bipush        16
       226: invokespecial #81                 // Method "<init>":(Ljava/lang/String;I)V
       229: putstatic     #52                 // Field PARTYROOM_ALL:Lext/mods/gameserver/enums/SayType;
       232: new           #1                  // class ext/mods/gameserver/enums/SayType
       235: dup
       236: ldc           #98                 // String HERO_VOICE
       238: bipush        17
       240: invokespecial #81                 // Method "<init>":(Ljava/lang/String;I)V
       243: putstatic     #55                 // Field HERO_VOICE:Lext/mods/gameserver/enums/SayType;
       246: new           #1                  // class ext/mods/gameserver/enums/SayType
       249: dup
       250: ldc           #99                 // String CRITICAL_ANNOUNCE
       252: bipush        18
       254: invokespecial #81                 // Method "<init>":(Ljava/lang/String;I)V
       257: putstatic     #58                 // Field CRITICAL_ANNOUNCE:Lext/mods/gameserver/enums/SayType;
       260: invokestatic  #100                // Method $values:()[Lext/mods/gameserver/enums/SayType;
       263: putstatic     #61                 // Field $VALUES:[Lext/mods/gameserver/enums/SayType;
       266: invokestatic  #104                // Method values:()[Lext/mods/gameserver/enums/SayType;
       269: putstatic     #107                // Field VALUES:[Lext/mods/gameserver/enums/SayType;
       272: return
      LineNumberTable:
        line 22: 0
        line 23: 13
        line 24: 26
        line 25: 39
        line 26: 52
        line 27: 65
        line 28: 78
        line 29: 92
        line 30: 106
        line 31: 120
        line 32: 134
        line 33: 148
        line 34: 162
        line 35: 176
        line 36: 190
        line 37: 204
        line 38: 218
        line 39: 232
        line 40: 246
        line 20: 260
        line 42: 266
}
Signature: #121                         // Ljava/lang/Enum<Lext/mods/gameserver/enums/SayType;>;
SourceFile: "SayType.java"
