// Bytecode for: ext.mods.gameserver.enums.SealType
// File: ext\mods\gameserver\enums\SealType.class

Classfile /c:/Users/User/Desktop/BrProject/bin/main/ext/mods/gameserver/enums/SealType.class
  Last modified 9 de jul de 2026; size 1815 bytes
  MD5 checksum f857cf70860045ac30d760007264e060
  Compiled from "SealType.java"
public final class ext.mods.gameserver.enums.SealType extends java.lang.Enum<ext.mods.gameserver.enums.SealType>
  minor version: 0
  major version: 69
  flags: (0x4031) ACC_PUBLIC, ACC_FINAL, ACC_SUPER, ACC_ENUM
  this_class: #1                          // ext/mods/gameserver/enums/SealType
  super_class: #26                        // java/lang/Enum
  interfaces: 0, fields: 8, methods: 7, attributes: 2
Constant pool:
   #1 = Class              #2             // ext/mods/gameserver/enums/SealType
   #2 = Utf8               ext/mods/gameserver/enums/SealType
   #3 = Fieldref           #1.#4          // ext/mods/gameserver/enums/SealType.NONE:Lext/mods/gameserver/enums/SealType;
   #4 = NameAndType        #5:#6          // NONE:Lext/mods/gameserver/enums/SealType;
   #5 = Utf8               NONE
   #6 = Utf8               Lext/mods/gameserver/enums/SealType;
   #7 = Fieldref           #1.#8          // ext/mods/gameserver/enums/SealType.AVARICE:Lext/mods/gameserver/enums/SealType;
   #8 = NameAndType        #9:#6          // AVARICE:Lext/mods/gameserver/enums/SealType;
   #9 = Utf8               AVARICE
  #10 = Fieldref           #1.#11         // ext/mods/gameserver/enums/SealType.GNOSIS:Lext/mods/gameserver/enums/SealType;
  #11 = NameAndType        #12:#6         // GNOSIS:Lext/mods/gameserver/enums/SealType;
  #12 = Utf8               GNOSIS
  #13 = Fieldref           #1.#14         // ext/mods/gameserver/enums/SealType.STRIFE:Lext/mods/gameserver/enums/SealType;
  #14 = NameAndType        #15:#6         // STRIFE:Lext/mods/gameserver/enums/SealType;
  #15 = Utf8               STRIFE
  #16 = Fieldref           #1.#17         // ext/mods/gameserver/enums/SealType.$VALUES:[Lext/mods/gameserver/enums/SealType;
  #17 = NameAndType        #18:#19        // $VALUES:[Lext/mods/gameserver/enums/SealType;
  #18 = Utf8               $VALUES
  #19 = Utf8               [Lext/mods/gameserver/enums/SealType;
  #20 = Methodref          #21.#22        // "[Lext/mods/gameserver/enums/SealType;".clone:()Ljava/lang/Object;
  #21 = Class              #19            // "[Lext/mods/gameserver/enums/SealType;"
  #22 = NameAndType        #23:#24        // clone:()Ljava/lang/Object;
  #23 = Utf8               clone
  #24 = Utf8               ()Ljava/lang/Object;
  #25 = Methodref          #26.#27        // java/lang/Enum.valueOf:(Ljava/lang/Class;Ljava/lang/String;)Ljava/lang/Enum;
  #26 = Class              #28            // java/lang/Enum
  #27 = NameAndType        #29:#30        // valueOf:(Ljava/lang/Class;Ljava/lang/String;)Ljava/lang/Enum;
  #28 = Utf8               java/lang/Enum
  #29 = Utf8               valueOf
  #30 = Utf8               (Ljava/lang/Class;Ljava/lang/String;)Ljava/lang/Enum;
  #31 = Methodref          #26.#32        // java/lang/Enum."<init>":(Ljava/lang/String;I)V
  #32 = NameAndType        #33:#34        // "<init>":(Ljava/lang/String;I)V
  #33 = Utf8               <init>
  #34 = Utf8               (Ljava/lang/String;I)V
  #35 = Fieldref           #1.#36         // ext/mods/gameserver/enums/SealType._shortName:Ljava/lang/String;
  #36 = NameAndType        #37:#38        // _shortName:Ljava/lang/String;
  #37 = Utf8               _shortName
  #38 = Utf8               Ljava/lang/String;
  #39 = Fieldref           #1.#40         // ext/mods/gameserver/enums/SealType._fullName:Ljava/lang/String;
  #40 = NameAndType        #41:#38        // _fullName:Ljava/lang/String;
  #41 = Utf8               _fullName
  #42 = String             #5             // NONE
  #43 = String             #44            //
  #44 = Utf8
  #45 = Methodref          #1.#46         // ext/mods/gameserver/enums/SealType."<init>":(Ljava/lang/String;ILjava/lang/String;Ljava/lang/String;)V
  #46 = NameAndType        #33:#47        // "<init>":(Ljava/lang/String;ILjava/lang/String;Ljava/lang/String;)V
  #47 = Utf8               (Ljava/lang/String;ILjava/lang/String;Ljava/lang/String;)V
  #48 = String             #9             // AVARICE
  #49 = String             #50            // Avarice
  #50 = Utf8               Avarice
  #51 = String             #52            // Seal of Avarice
  #52 = Utf8               Seal of Avarice
  #53 = String             #12            // GNOSIS
  #54 = String             #55            // Gnosis
  #55 = Utf8               Gnosis
  #56 = String             #57            // Seal of Gnosis
  #57 = Utf8               Seal of Gnosis
  #58 = String             #15            // STRIFE
  #59 = String             #60            // Strife
  #60 = Utf8               Strife
  #61 = String             #62            // Seal of Strife
  #62 = Utf8               Seal of Strife
  #63 = Methodref          #1.#64         // ext/mods/gameserver/enums/SealType.$values:()[Lext/mods/gameserver/enums/SealType;
  #64 = NameAndType        #65:#66        // $values:()[Lext/mods/gameserver/enums/SealType;
  #65 = Utf8               $values
  #66 = Utf8               ()[Lext/mods/gameserver/enums/SealType;
  #67 = Methodref          #1.#68         // ext/mods/gameserver/enums/SealType.values:()[Lext/mods/gameserver/enums/SealType;
  #68 = NameAndType        #69:#66        // values:()[Lext/mods/gameserver/enums/SealType;
  #69 = Utf8               values
  #70 = Fieldref           #1.#71         // ext/mods/gameserver/enums/SealType.VALUES:[Lext/mods/gameserver/enums/SealType;
  #71 = NameAndType        #72:#19        // VALUES:[Lext/mods/gameserver/enums/SealType;
  #72 = Utf8               VALUES
  #73 = Utf8               Code
  #74 = Utf8               LineNumberTable
  #75 = Utf8               (Ljava/lang/String;)Lext/mods/gameserver/enums/SealType;
  #76 = Utf8               LocalVariableTable
  #77 = Utf8               name
  #78 = Utf8               MethodParameters
  #79 = Utf8               this
  #80 = Utf8               shortName
  #81 = Utf8               fullName
  #82 = Utf8               Signature
  #83 = Utf8               (Ljava/lang/String;Ljava/lang/String;)V
  #84 = Utf8               getShortName
  #85 = Utf8               ()Ljava/lang/String;
  #86 = Utf8               getFullName
  #87 = Utf8               <clinit>
  #88 = Utf8               ()V
  #89 = Utf8               Ljava/lang/Enum<Lext/mods/gameserver/enums/SealType;>;
  #90 = Utf8               SourceFile
  #91 = Utf8               SealType.java
{
  public static final ext.mods.gameserver.enums.SealType NONE;
    descriptor: Lext/mods/gameserver/enums/SealType;
    flags: (0x4019) ACC_PUBLIC, ACC_STATIC, ACC_FINAL, ACC_ENUM

  public static final ext.mods.gameserver.enums.SealType AVARICE;
    descriptor: Lext/mods/gameserver/enums/SealType;
    flags: (0x4019) ACC_PUBLIC, ACC_STATIC, ACC_FINAL, ACC_ENUM

  public static final ext.mods.gameserver.enums.SealType GNOSIS;
    descriptor: Lext/mods/gameserver/enums/SealType;
    flags: (0x4019) ACC_PUBLIC, ACC_STATIC, ACC_FINAL, ACC_ENUM

  public static final ext.mods.gameserver.enums.SealType STRIFE;
    descriptor: Lext/mods/gameserver/enums/SealType;
    flags: (0x4019) ACC_PUBLIC, ACC_STATIC, ACC_FINAL, ACC_ENUM

  public static final ext.mods.gameserver.enums.SealType[] VALUES;
    descriptor: [Lext/mods/gameserver/enums/SealType;
    flags: (0x0019) ACC_PUBLIC, ACC_STATIC, ACC_FINAL

  public static ext.mods.gameserver.enums.SealType[] values();
    descriptor: ()[Lext/mods/gameserver/enums/SealType;
    flags: (0x0009) ACC_PUBLIC, ACC_STATIC
    Code:
      stack=1, locals=0, args_size=0
         0: getstatic     #16                 // Field $VALUES:[Lext/mods/gameserver/enums/SealType;
         3: invokevirtual #20                 // Method "[Lext/mods/gameserver/enums/SealType;".clone:()Ljava/lang/Object;
         6: checkcast     #21                 // class "[Lext/mods/gameserver/enums/SealType;"
         9: areturn
      LineNumberTable:
        line 20: 0

  public static ext.mods.gameserver.enums.SealType valueOf(java.lang.String);
    descriptor: (Ljava/lang/String;)Lext/mods/gameserver/enums/SealType;
    flags: (0x0009) ACC_PUBLIC, ACC_STATIC
    Code:
      stack=2, locals=1, args_size=1
         0: ldc           #1                  // class ext/mods/gameserver/enums/SealType
         2: aload_0
         3: invokestatic  #25                 // Method java/lang/Enum.valueOf:(Ljava/lang/Class;Ljava/lang/String;)Ljava/lang/Enum;
         6: checkcast     #1                  // class ext/mods/gameserver/enums/SealType
         9: areturn
      LineNumberTable:
        line 20: 0
      LocalVariableTable:
        Start  Length  Slot  Name   Signature
            0      10     0  name   Ljava/lang/String;
    MethodParameters:
      Name                           Flags
      <no name>                      mandated

  public java.lang.String getShortName();
    descriptor: ()Ljava/lang/String;
    flags: (0x0001) ACC_PUBLIC
    Code:
      stack=1, locals=1, args_size=1
         0: aload_0
         1: getfield      #35                 // Field _shortName:Ljava/lang/String;
         4: areturn
      LineNumberTable:
        line 38: 0
      LocalVariableTable:
        Start  Length  Slot  Name   Signature
            0       5     0  this   Lext/mods/gameserver/enums/SealType;

  public java.lang.String getFullName();
    descriptor: ()Ljava/lang/String;
    flags: (0x0001) ACC_PUBLIC
    Code:
      stack=1, locals=1, args_size=1
         0: aload_0
         1: getfield      #39                 // Field _fullName:Ljava/lang/String;
         4: areturn
      LineNumberTable:
        line 43: 0
      LocalVariableTable:
        Start  Length  Slot  Name   Signature
            0       5     0  this   Lext/mods/gameserver/enums/SealType;

  static {};
    descriptor: ()V
    flags: (0x0008) ACC_STATIC
    Code:
      stack=6, locals=0, args_size=0
         0: new           #1                  // class ext/mods/gameserver/enums/SealType
         3: dup
         4: ldc           #42                 // String NONE
         6: iconst_0
         7: ldc           #43                 // String
         9: ldc           #43                 // String
        11: invokespecial #45                 // Method "<init>":(Ljava/lang/String;ILjava/lang/String;Ljava/lang/String;)V
        14: putstatic     #3                  // Field NONE:Lext/mods/gameserver/enums/SealType;
        17: new           #1                  // class ext/mods/gameserver/enums/SealType
        20: dup
        21: ldc           #48                 // String AVARICE
        23: iconst_1
        24: ldc           #49                 // String Avarice
        26: ldc           #51                 // String Seal of Avarice
        28: invokespecial #45                 // Method "<init>":(Ljava/lang/String;ILjava/lang/String;Ljava/lang/String;)V
        31: putstatic     #7                  // Field AVARICE:Lext/mods/gameserver/enums/SealType;
        34: new           #1                  // class ext/mods/gameserver/enums/SealType
        37: dup
        38: ldc           #53                 // String GNOSIS
        40: iconst_2
        41: ldc           #54                 // String Gnosis
        43: ldc           #56                 // String Seal of Gnosis
        45: invokespecial #45                 // Method "<init>":(Ljava/lang/String;ILjava/lang/String;Ljava/lang/String;)V
        48: putstatic     #10                 // Field GNOSIS:Lext/mods/gameserver/enums/SealType;
        51: new           #1                  // class ext/mods/gameserver/enums/SealType
        54: dup
        55: ldc           #58                 // String STRIFE
        57: iconst_3
        58: ldc           #59                 // String Strife
        60: ldc           #61                 // String Seal of Strife
        62: invokespecial #45                 // Method "<init>":(Ljava/lang/String;ILjava/lang/String;Ljava/lang/String;)V
        65: putstatic     #13                 // Field STRIFE:Lext/mods/gameserver/enums/SealType;
        68: invokestatic  #63                 // Method $values:()[Lext/mods/gameserver/enums/SealType;
        71: putstatic     #16                 // Field $VALUES:[Lext/mods/gameserver/enums/SealType;
        74: invokestatic  #67                 // Method values:()[Lext/mods/gameserver/enums/SealType;
        77: putstatic     #70                 // Field VALUES:[Lext/mods/gameserver/enums/SealType;
        80: return
      LineNumberTable:
        line 22: 0
        line 23: 17
        line 24: 34
        line 25: 51
        line 20: 68
        line 46: 74
}
Signature: #89                          // Ljava/lang/Enum<Lext/mods/gameserver/enums/SealType;>;
SourceFile: "SealType.java"
