// Bytecode for: ext.mods.gameserver.geoengine.pathfinding.model.PathResult$Companion
// File: ext\mods\gameserver\geoengine\pathfinding\model\PathResult$Companion.class

Classfile /c:/Users/User/Desktop/BrProject/bin/main/ext/mods/gameserver/geoengine/pathfinding/model/PathResult$Companion.class
  Last modified 9 de jul de 2026; size 1308 bytes
  MD5 checksum a520049ede3e6cd57e6e7f19e95ebd6e
  Compiled from "Location.kt"
public final class ext.mods.gameserver.geoengine.pathfinding.model.PathResult$Companion
  minor version: 0
  major version: 69
  flags: (0x0031) ACC_PUBLIC, ACC_FINAL, ACC_SUPER
  this_class: #2                          // ext/mods/gameserver/geoengine/pathfinding/model/PathResult$Companion
  super_class: #4                         // java/lang/Object
  interfaces: 0, fields: 0, methods: 3, attributes: 3
Constant pool:
   #1 = Utf8               ext/mods/gameserver/geoengine/pathfinding/model/PathResult$Companion
   #2 = Class              #1             // ext/mods/gameserver/geoengine/pathfinding/model/PathResult$Companion
   #3 = Utf8               java/lang/Object
   #4 = Class              #3             // java/lang/Object
   #5 = Utf8               <init>
   #6 = Utf8               ()V
   #7 = NameAndType        #5:#6          // "<init>":()V
   #8 = Methodref          #4.#7          // java/lang/Object."<init>":()V
   #9 = Utf8               this
  #10 = Utf8               Lext/mods/gameserver/geoengine/pathfinding/model/PathResult$Companion;
  #11 = Utf8               failure
  #12 = Utf8               ()Lext/mods/gameserver/geoengine/pathfinding/model/PathResult;
  #13 = Utf8               Lorg/jetbrains/annotations/NotNull;
  #14 = Utf8               ext/mods/gameserver/geoengine/pathfinding/model/PathResult
  #15 = Class              #14            // ext/mods/gameserver/geoengine/pathfinding/model/PathResult
  #16 = Utf8               kotlin/collections/CollectionsKt
  #17 = Class              #16            // kotlin/collections/CollectionsKt
  #18 = Utf8               emptyList
  #19 = Utf8               ()Ljava/util/List;
  #20 = NameAndType        #18:#19        // emptyList:()Ljava/util/List;
  #21 = Methodref          #17.#20        // kotlin/collections/CollectionsKt.emptyList:()Ljava/util/List;
  #22 = Utf8               (Ljava/util/List;IJZ)V
  #23 = NameAndType        #5:#22         // "<init>":(Ljava/util/List;IJZ)V
  #24 = Methodref          #15.#23        // ext/mods/gameserver/geoengine/pathfinding/model/PathResult."<init>":(Ljava/util/List;IJZ)V
  #25 = Utf8               (Lkotlin/jvm/internal/DefaultConstructorMarker;)V
  #26 = Methodref          #2.#7          // ext/mods/gameserver/geoengine/pathfinding/model/PathResult$Companion."<init>":()V
  #27 = Utf8               $constructor_marker
  #28 = Utf8               Lkotlin/jvm/internal/DefaultConstructorMarker;
  #29 = Utf8               Lkotlin/Metadata;
  #30 = Utf8               mv
  #31 = Integer            2
  #32 = Integer            3
  #33 = Integer            0
  #34 = Utf8               k
  #35 = Integer            1
  #36 = Utf8               xi
  #37 = Integer            48
  #38 = Utf8               d1
  #39 = Utf8               \u0000\u0012\n\u0002\u0018\u0002\n\u0002\u0010\u0000\n\u0002\b\u0003\n\u0002\u0018\u0002\n\u0000\b\u0086\u0003\u0018\u00002\u00020\u0001B\t\b\u0002¢\u0006\u0004\b\u0002\u0010\u0003J\u0006\u0010\u0004\u001a\u00020\u0005¨\u0006\u0006
  #40 = Utf8               d2
  #41 = Utf8
  #42 = Utf8               Lext/mods/gameserver/geoengine/pathfinding/model/PathResult;
  #43 = Utf8               Brproject
  #44 = Utf8               Companion
  #45 = Utf8               Location.kt
  #46 = Utf8               Code
  #47 = Utf8               LineNumberTable
  #48 = Utf8               LocalVariableTable
  #49 = Utf8               RuntimeInvisibleAnnotations
  #50 = Utf8               InnerClasses
  #51 = Utf8               SourceFile
  #52 = Utf8               RuntimeVisibleAnnotations
{
  public final ext.mods.gameserver.geoengine.pathfinding.model.PathResult failure();
    descriptor: ()Lext/mods/gameserver/geoengine/pathfinding/model/PathResult;
    flags: (0x0011) ACC_PUBLIC, ACC_FINAL
    Code:
      stack=7, locals=1, args_size=1
         0: new           #15                 // class ext/mods/gameserver/geoengine/pathfinding/model/PathResult
         3: dup
         4: invokestatic  #21                 // Method kotlin/collections/CollectionsKt.emptyList:()Ljava/util/List;
         7: iconst_0
         8: lconst_0
         9: iconst_0
        10: invokespecial #24                 // Method ext/mods/gameserver/geoengine/pathfinding/model/PathResult."<init>":(Ljava/util/List;IJZ)V
        13: areturn
      LineNumberTable:
        line 159: 0
      LocalVariableTable:
        Start  Length  Slot  Name   Signature
            0      14     0  this   Lext/mods/gameserver/geoengine/pathfinding/model/PathResult$Companion;
    RuntimeInvisibleAnnotations:
      0: #13()
        org.jetbrains.annotations.NotNull

  public ext.mods.gameserver.geoengine.pathfinding.model.PathResult$Companion(kotlin.jvm.internal.DefaultConstructorMarker);
    descriptor: (Lkotlin/jvm/internal/DefaultConstructorMarker;)V
    flags: (0x1001) ACC_PUBLIC, ACC_SYNTHETIC
    Code:
      stack=1, locals=2, args_size=2
         0: aload_0
         1: invokespecial #26                 // Method "<init>":()V
         4: return
      LocalVariableTable:
        Start  Length  Slot  Name   Signature
            0       5     0  this   Lext/mods/gameserver/geoengine/pathfinding/model/PathResult$Companion;
            0       5     1 $constructor_marker   Lkotlin/jvm/internal/DefaultConstructorMarker;
}
InnerClasses:
  public static final #44= #2 of #15;     // Companion=class ext/mods/gameserver/geoengine/pathfinding/model/PathResult$Companion of class ext/mods/gameserver/geoengine/pathfinding/model/PathResult
SourceFile: "Location.kt"
RuntimeVisibleAnnotations:
  0: #29(#30=[I#31,I#32,I#33],#34=I#35,#36=I#37,#38=[s#39],#40=[s#10,s#41,s#5,s#6,s#11,s#42,s#43])
    kotlin.Metadata(
      mv=[2,3,0]
      k=1
      xi=48
      d1=["\u0000\u0012\n\u0002\u0018\u0002\n\u0002\u0010\u0000\n\u0002\b\u0003\n\u0002\u0018\u0002\n\u0000\b\u0086\u0003\u0018\u00002\u00020\u0001B\t\b\u0002¢\u0006\u0004\b\u0002\u0010\u0003J\u0006\u0010\u0004\u001a\u00020\u0005¨\u0006\u0006"]
      d2=["Lext/mods/gameserver/geoengine/pathfinding/model/PathResult$Companion;","","<init>","()V","failure","Lext/mods/gameserver/geoengine/pathfinding/model/PathResult;","Brproject"]
    )
