// Bytecode for: ext.mods.commons.gui.tools.CreateItemDialog
// File: ext\mods\commons\gui\tools\CreateItemDialog.class

Classfile /c:/Users/User/Desktop/BrProject/bin/main/ext/mods/commons/gui/tools/CreateItemDialog.class
  Last modified 9 de jul de 2026; size 9770 bytes
  MD5 checksum 7a4cae0c4dbb01a8de1ac7348fbb2118
  Compiled from "CreateItemDialog.java"
public class ext.mods.commons.gui.tools.CreateItemDialog extends javax.swing.JDialog
  minor version: 0
  major version: 69
  flags: (0x0021) ACC_PUBLIC, ACC_SUPER
  this_class: #12                         // ext/mods/commons/gui/tools/CreateItemDialog
  super_class: #6                         // javax/swing/JDialog
  interfaces: 0, fields: 3, methods: 5, attributes: 4
Constant pool:
    #1 = InvokeDynamic      #0:#2         // #0:makeConcatWithConstants:(Ljava/lang/String;)Ljava/lang/String;
    #2 = NameAndType        #3:#4         // makeConcatWithConstants:(Ljava/lang/String;)Ljava/lang/String;
    #3 = Utf8               makeConcatWithConstants
    #4 = Utf8               (Ljava/lang/String;)Ljava/lang/String;
    #5 = Methodref          #6.#7         // javax/swing/JDialog."<init>":(Ljava/awt/Frame;Ljava/lang/String;Z)V
    #6 = Class              #8            // javax/swing/JDialog
    #7 = NameAndType        #9:#10        // "<init>":(Ljava/awt/Frame;Ljava/lang/String;Z)V
    #8 = Utf8               javax/swing/JDialog
    #9 = Utf8               <init>
   #10 = Utf8               (Ljava/awt/Frame;Ljava/lang/String;Z)V
   #11 = Fieldref           #12.#13       // ext/mods/commons/gui/tools/CreateItemDialog._playerName:Ljava/lang/String;
   #12 = Class              #14           // ext/mods/commons/gui/tools/CreateItemDialog
   #13 = NameAndType        #15:#16       // _playerName:Ljava/lang/String;
   #14 = Utf8               ext/mods/commons/gui/tools/CreateItemDialog
   #15 = Utf8               _playerName
   #16 = Utf8               Ljava/lang/String;
   #17 = Fieldref           #12.#18       // ext/mods/commons/gui/tools/CreateItemDialog._parentFrame:Ljavax/swing/JFrame;
   #18 = NameAndType        #19:#20       // _parentFrame:Ljavax/swing/JFrame;
   #19 = Utf8               _parentFrame
   #20 = Utf8               Ljavax/swing/JFrame;
   #21 = Methodref          #12.#22       // ext/mods/commons/gui/tools/CreateItemDialog.setSize:(II)V
   #22 = NameAndType        #23:#24       // setSize:(II)V
   #23 = Utf8               setSize
   #24 = Utf8               (II)V
   #25 = Class              #26           // java/awt/GridLayout
   #26 = Utf8               java/awt/GridLayout
   #27 = Methodref          #25.#28       // java/awt/GridLayout."<init>":(IIII)V
   #28 = NameAndType        #9:#29        // "<init>":(IIII)V
   #29 = Utf8               (IIII)V
   #30 = Methodref          #12.#31       // ext/mods/commons/gui/tools/CreateItemDialog.setLayout:(Ljava/awt/LayoutManager;)V
   #31 = NameAndType        #32:#33       // setLayout:(Ljava/awt/LayoutManager;)V
   #32 = Utf8               setLayout
   #33 = Utf8               (Ljava/awt/LayoutManager;)V
   #34 = Class              #35           // javax/swing/JLabel
   #35 = Utf8               javax/swing/JLabel
   #36 = String             #37           // Item Id:
   #37 = Utf8               Item Id:
   #38 = Methodref          #34.#39       // javax/swing/JLabel."<init>":(Ljava/lang/String;)V
   #39 = NameAndType        #9:#40        // "<init>":(Ljava/lang/String;)V
   #40 = Utf8               (Ljava/lang/String;)V
   #41 = Class              #42           // javax/swing/JTextField
   #42 = Utf8               javax/swing/JTextField
   #43 = Methodref          #41.#44       // javax/swing/JTextField."<init>":()V
   #44 = NameAndType        #9:#45        // "<init>":()V
   #45 = Utf8               ()V
   #46 = String             #47           // Amount:
   #47 = Utf8               Amount:
   #48 = String             #49           // Location:
   #49 = Utf8               Location:
   #50 = Class              #51           // javax/swing/JComboBox
   #51 = Utf8               javax/swing/JComboBox
   #52 = Methodref          #50.#44       // javax/swing/JComboBox."<init>":()V
   #53 = String             #54           // INVENTORY
   #54 = Utf8               INVENTORY
   #55 = Methodref          #50.#56       // javax/swing/JComboBox.addItem:(Ljava/lang/Object;)V
   #56 = NameAndType        #57:#58       // addItem:(Ljava/lang/Object;)V
   #57 = Utf8               addItem
   #58 = Utf8               (Ljava/lang/Object;)V
   #59 = String             #60           // WAREHOUSE
   #60 = Utf8               WAREHOUSE
   #61 = String             #62           // CLANWH
   #62 = Utf8               CLANWH
   #63 = String             #64           // Apply Enchant:
   #64 = Utf8               Apply Enchant:
   #65 = Class              #66           // javax/swing/JCheckBox
   #66 = Utf8               javax/swing/JCheckBox
   #67 = Methodref          #65.#44       // javax/swing/JCheckBox."<init>":()V
   #68 = String             #69           // Enchant Level:
   #69 = Utf8               Enchant Level:
   #70 = Methodref          #34.#71       // javax/swing/JLabel.setEnabled:(Z)V
   #71 = NameAndType        #72:#73       // setEnabled:(Z)V
   #72 = Utf8               setEnabled
   #73 = Utf8               (Z)V
   #74 = Methodref          #41.#71       // javax/swing/JTextField.setEnabled:(Z)V
   #75 = InvokeDynamic      #1:#76        // #1:actionPerformed:(Ljavax/swing/JCheckBox;Ljavax/swing/JLabel;Ljavax/swing/JTextField;)Ljava/awt/event/ActionListener;
   #76 = NameAndType        #77:#78       // actionPerformed:(Ljavax/swing/JCheckBox;Ljavax/swing/JLabel;Ljavax/swing/JTextField;)Ljava/awt/event/ActionListener;
   #77 = Utf8               actionPerformed
   #78 = Utf8               (Ljavax/swing/JCheckBox;Ljavax/swing/JLabel;Ljavax/swing/JTextField;)Ljava/awt/event/ActionListener;
   #79 = Methodref          #65.#80       // javax/swing/JCheckBox.addActionListener:(Ljava/awt/event/ActionListener;)V
   #80 = NameAndType        #81:#82       // addActionListener:(Ljava/awt/event/ActionListener;)V
   #81 = Utf8               addActionListener
   #82 = Utf8               (Ljava/awt/event/ActionListener;)V
   #83 = Class              #84           // javax/swing/JButton
   #84 = Utf8               javax/swing/JButton
   #85 = String             #86           // Apply
   #86 = Utf8               Apply
   #87 = Methodref          #83.#39       // javax/swing/JButton."<init>":(Ljava/lang/String;)V
   #88 = Class              #89           // ext/mods/commons/gui/tools/CreateItemDialog$1
   #89 = Utf8               ext/mods/commons/gui/tools/CreateItemDialog$1
   #90 = Methodref          #88.#91       // ext/mods/commons/gui/tools/CreateItemDialog$1."<init>":(Lext/mods/commons/gui/tools/CreateItemDialog;Ljavax/swing/JTextField;Ljavax/swing/JTextField;Ljavax/swing/JComboBox;Ljavax/swing/JCheckBox;Ljavax/swing/JTextField;)V
   #91 = NameAndType        #9:#92        // "<init>":(Lext/mods/commons/gui/tools/CreateItemDialog;Ljavax/swing/JTextField;Ljavax/swing/JTextField;Ljavax/swing/JComboBox;Ljavax/swing/JCheckBox;Ljavax/swing/JTextField;)V
   #92 = Utf8               (Lext/mods/commons/gui/tools/CreateItemDialog;Ljavax/swing/JTextField;Ljavax/swing/JTextField;Ljavax/swing/JComboBox;Ljavax/swing/JCheckBox;Ljavax/swing/JTextField;)V
   #93 = Methodref          #83.#80       // javax/swing/JButton.addActionListener:(Ljava/awt/event/ActionListener;)V
   #94 = Methodref          #12.#95       // ext/mods/commons/gui/tools/CreateItemDialog.add:(Ljava/awt/Component;)Ljava/awt/Component;
   #95 = NameAndType        #96:#97       // add:(Ljava/awt/Component;)Ljava/awt/Component;
   #96 = Utf8               add
   #97 = Utf8               (Ljava/awt/Component;)Ljava/awt/Component;
   #98 = Methodref          #34.#44       // javax/swing/JLabel."<init>":()V
   #99 = Methodref          #12.#100      // ext/mods/commons/gui/tools/CreateItemDialog.setLocationRelativeTo:(Ljava/awt/Component;)V
  #100 = NameAndType        #101:#102     // setLocationRelativeTo:(Ljava/awt/Component;)V
  #101 = Utf8               setLocationRelativeTo
  #102 = Utf8               (Ljava/awt/Component;)V
  #103 = Methodref          #104.#105     // ext/mods/gameserver/model/World.getInstance:()Lext/mods/gameserver/model/World;
  #104 = Class              #106          // ext/mods/gameserver/model/World
  #105 = NameAndType        #107:#108     // getInstance:()Lext/mods/gameserver/model/World;
  #106 = Utf8               ext/mods/gameserver/model/World
  #107 = Utf8               getInstance
  #108 = Utf8               ()Lext/mods/gameserver/model/World;
  #109 = Methodref          #104.#110     // ext/mods/gameserver/model/World.getPlayer:(Ljava/lang/String;)Lext/mods/gameserver/model/actor/Player;
  #110 = NameAndType        #111:#112     // getPlayer:(Ljava/lang/String;)Lext/mods/gameserver/model/actor/Player;
  #111 = Utf8               getPlayer
  #112 = Utf8               (Ljava/lang/String;)Lext/mods/gameserver/model/actor/Player;
  #113 = Methodref          #114.#115     // ext/mods/gameserver/model/actor/Player.addItem:(IIZ)Lext/mods/gameserver/model/item/instance/ItemInstance;
  #114 = Class              #116          // ext/mods/gameserver/model/actor/Player
  #115 = NameAndType        #57:#117      // addItem:(IIZ)Lext/mods/gameserver/model/item/instance/ItemInstance;
  #116 = Utf8               ext/mods/gameserver/model/actor/Player
  #117 = Utf8               (IIZ)Lext/mods/gameserver/model/item/instance/ItemInstance;
  #118 = Methodref          #119.#120     // ext/mods/gameserver/model/item/instance/ItemInstance.setEnchantLevel:(ILext/mods/gameserver/model/actor/Playable;)V
  #119 = Class              #121          // ext/mods/gameserver/model/item/instance/ItemInstance
  #120 = NameAndType        #122:#123     // setEnchantLevel:(ILext/mods/gameserver/model/actor/Playable;)V
  #121 = Utf8               ext/mods/gameserver/model/item/instance/ItemInstance
  #122 = Utf8               setEnchantLevel
  #123 = Utf8               (ILext/mods/gameserver/model/actor/Playable;)V
  #124 = Methodref          #119.#125     // ext/mods/gameserver/model/item/instance/ItemInstance.getCount:()I
  #125 = NameAndType        #126:#127     // getCount:()I
  #126 = Utf8               getCount
  #127 = Utf8               ()I
  #128 = Fieldref           #129.#130     // ext/mods/gameserver/network/SystemMessageId.S1_OBTAINED_S3_S2:Lext/mods/gameserver/network/SystemMessageId;
  #129 = Class              #131          // ext/mods/gameserver/network/SystemMessageId
  #130 = NameAndType        #132:#133     // S1_OBTAINED_S3_S2:Lext/mods/gameserver/network/SystemMessageId;
  #131 = Utf8               ext/mods/gameserver/network/SystemMessageId
  #132 = Utf8               S1_OBTAINED_S3_S2
  #133 = Utf8               Lext/mods/gameserver/network/SystemMessageId;
  #134 = Methodref          #135.#136     // ext/mods/gameserver/network/serverpackets/SystemMessage.getSystemMessage:(Lext/mods/gameserver/network/SystemMessageId;)Lext/mods/gameserver/network/serverpackets/SystemMessage;
  #135 = Class              #137          // ext/mods/gameserver/network/serverpackets/SystemMessage
  #136 = NameAndType        #138:#139     // getSystemMessage:(Lext/mods/gameserver/network/SystemMessageId;)Lext/mods/gameserver/network/serverpackets/SystemMessage;
  #137 = Utf8               ext/mods/gameserver/network/serverpackets/SystemMessage
  #138 = Utf8               getSystemMessage
  #139 = Utf8               (Lext/mods/gameserver/network/SystemMessageId;)Lext/mods/gameserver/network/serverpackets/SystemMessage;
  #140 = Methodref          #135.#141     // ext/mods/gameserver/network/serverpackets/SystemMessage.addCharName:(Lext/mods/gameserver/model/actor/Creature;)Lext/mods/gameserver/network/serverpackets/SystemMessage;
  #141 = NameAndType        #142:#143     // addCharName:(Lext/mods/gameserver/model/actor/Creature;)Lext/mods/gameserver/network/serverpackets/SystemMessage;
  #142 = Utf8               addCharName
  #143 = Utf8               (Lext/mods/gameserver/model/actor/Creature;)Lext/mods/gameserver/network/serverpackets/SystemMessage;
  #144 = Methodref          #135.#145     // ext/mods/gameserver/network/serverpackets/SystemMessage.addItemName:(Lext/mods/gameserver/model/item/instance/ItemInstance;)Lext/mods/gameserver/network/serverpackets/SystemMessage;
  #145 = NameAndType        #146:#147     // addItemName:(Lext/mods/gameserver/model/item/instance/ItemInstance;)Lext/mods/gameserver/network/serverpackets/SystemMessage;
  #146 = Utf8               addItemName
  #147 = Utf8               (Lext/mods/gameserver/model/item/instance/ItemInstance;)Lext/mods/gameserver/network/serverpackets/SystemMessage;
  #148 = Methodref          #135.#149     // ext/mods/gameserver/network/serverpackets/SystemMessage.addItemNumber:(I)Lext/mods/gameserver/network/serverpackets/SystemMessage;
  #149 = NameAndType        #150:#151     // addItemNumber:(I)Lext/mods/gameserver/network/serverpackets/SystemMessage;
  #150 = Utf8               addItemNumber
  #151 = Utf8               (I)Lext/mods/gameserver/network/serverpackets/SystemMessage;
  #152 = Methodref          #114.#153     // ext/mods/gameserver/model/actor/Player.sendPacket:(Lext/mods/gameserver/network/serverpackets/L2GameServerPacket;)V
  #153 = NameAndType        #154:#155     // sendPacket:(Lext/mods/gameserver/network/serverpackets/L2GameServerPacket;)V
  #154 = Utf8               sendPacket
  #155 = Utf8               (Lext/mods/gameserver/network/serverpackets/L2GameServerPacket;)V
  #156 = Methodref          #119.#157     // ext/mods/gameserver/model/item/instance/ItemInstance.getEnchantLevel:()I
  #157 = NameAndType        #158:#127     // getEnchantLevel:()I
  #158 = Utf8               getEnchantLevel
  #159 = Fieldref           #129.#160     // ext/mods/gameserver/network/SystemMessageId.S1_OBTAINED_S2_S3:Lext/mods/gameserver/network/SystemMessageId;
  #160 = NameAndType        #161:#133     // S1_OBTAINED_S2_S3:Lext/mods/gameserver/network/SystemMessageId;
  #161 = Utf8               S1_OBTAINED_S2_S3
  #162 = Methodref          #135.#163     // ext/mods/gameserver/network/serverpackets/SystemMessage.addNumber:(I)Lext/mods/gameserver/network/serverpackets/SystemMessage;
  #163 = NameAndType        #164:#151     // addNumber:(I)Lext/mods/gameserver/network/serverpackets/SystemMessage;
  #164 = Utf8               addNumber
  #165 = Fieldref           #129.#166     // ext/mods/gameserver/network/SystemMessageId.S1_OBTAINED_S2:Lext/mods/gameserver/network/SystemMessageId;
  #166 = NameAndType        #167:#133     // S1_OBTAINED_S2:Lext/mods/gameserver/network/SystemMessageId;
  #167 = Utf8               S1_OBTAINED_S2
  #168 = Class              #169          // ext/mods/gameserver/network/serverpackets/ItemList
  #169 = Utf8               ext/mods/gameserver/network/serverpackets/ItemList
  #170 = Methodref          #168.#171     // ext/mods/gameserver/network/serverpackets/ItemList."<init>":(Lext/mods/gameserver/model/actor/Player;Z)V
  #171 = NameAndType        #9:#172       // "<init>":(Lext/mods/gameserver/model/actor/Player;Z)V
  #172 = Utf8               (Lext/mods/gameserver/model/actor/Player;Z)V
  #173 = InvokeDynamic      #2:#2         // #2:makeConcatWithConstants:(Ljava/lang/String;)Ljava/lang/String;
  #174 = String             #175          // Success
  #175 = Utf8               Success
  #176 = Class              #177          // javax/swing/JOptionPane
  #177 = Utf8               javax/swing/JOptionPane
  #178 = Methodref          #176.#179     // javax/swing/JOptionPane.showMessageDialog:(Ljava/awt/Component;Ljava/lang/Object;Ljava/lang/String;I)V
  #179 = NameAndType        #180:#181     // showMessageDialog:(Ljava/awt/Component;Ljava/lang/Object;Ljava/lang/String;I)V
  #180 = Utf8               showMessageDialog
  #181 = Utf8               (Ljava/awt/Component;Ljava/lang/Object;Ljava/lang/String;I)V
  #182 = Methodref          #12.#183      // ext/mods/commons/gui/tools/CreateItemDialog.getItemLocation:(Ljava/lang/String;)Lext/mods/gameserver/enums/items/ItemLocation;
  #183 = NameAndType        #184:#185     // getItemLocation:(Ljava/lang/String;)Lext/mods/gameserver/enums/items/ItemLocation;
  #184 = Utf8               getItemLocation
  #185 = Utf8               (Ljava/lang/String;)Lext/mods/gameserver/enums/items/ItemLocation;
  #186 = Methodref          #12.#187      // ext/mods/commons/gui/tools/CreateItemDialog.giveItemToOfflinePlayer:(Ljava/lang/String;IIILext/mods/gameserver/enums/items/ItemLocation;)V
  #187 = NameAndType        #188:#189     // giveItemToOfflinePlayer:(Ljava/lang/String;IIILext/mods/gameserver/enums/items/ItemLocation;)V
  #188 = Utf8               giveItemToOfflinePlayer
  #189 = Utf8               (Ljava/lang/String;IIILext/mods/gameserver/enums/items/ItemLocation;)V
  #190 = InvokeDynamic      #3:#2         // #3:makeConcatWithConstants:(Ljava/lang/String;)Ljava/lang/String;
  #191 = String             #192          // Invalid location selected.
  #192 = Utf8               Invalid location selected.
  #193 = String             #194          // Error
  #194 = Utf8               Error
  #195 = Methodref          #196.#197     // ext/mods/commons/pool/ConnectionPool.getConnection:()Ljava/sql/Connection;
  #196 = Class              #198          // ext/mods/commons/pool/ConnectionPool
  #197 = NameAndType        #199:#200     // getConnection:()Ljava/sql/Connection;
  #198 = Utf8               ext/mods/commons/pool/ConnectionPool
  #199 = Utf8               getConnection
  #200 = Utf8               ()Ljava/sql/Connection;
  #201 = String             #202          // SELECT obj_Id FROM characters WHERE char_name=?
  #202 = Utf8               SELECT obj_Id FROM characters WHERE char_name=?
  #203 = InterfaceMethodref #204.#205     // java/sql/Connection.prepareStatement:(Ljava/lang/String;)Ljava/sql/PreparedStatement;
  #204 = Class              #206          // java/sql/Connection
  #205 = NameAndType        #207:#208     // prepareStatement:(Ljava/lang/String;)Ljava/sql/PreparedStatement;
  #206 = Utf8               java/sql/Connection
  #207 = Utf8               prepareStatement
  #208 = Utf8               (Ljava/lang/String;)Ljava/sql/PreparedStatement;
  #209 = String             #210          // INSERT INTO items (owner_id,item_id,count,loc,loc_data,enchant_level,object_id,custom_type1,custom_type2,mana_left,time) VALUES (?,?,?,?,?,?,?,?,?,?,?)
  #210 = Utf8               INSERT INTO items (owner_id,item_id,count,loc,loc_data,enchant_level,object_id,custom_type1,custom_type2,mana_left,time) VALUES (?,?,?,?,?,?,?,?,?,?,?)
  #211 = Methodref          #212.#213     // ext/mods/gameserver/data/xml/ItemData.getInstance:()Lext/mods/gameserver/data/xml/ItemData;
  #212 = Class              #214          // ext/mods/gameserver/data/xml/ItemData
  #213 = NameAndType        #107:#215     // getInstance:()Lext/mods/gameserver/data/xml/ItemData;
  #214 = Utf8               ext/mods/gameserver/data/xml/ItemData
  #215 = Utf8               ()Lext/mods/gameserver/data/xml/ItemData;
  #216 = Methodref          #212.#217     // ext/mods/gameserver/data/xml/ItemData.getTemplate:(I)Lext/mods/gameserver/model/item/kind/Item;
  #217 = NameAndType        #218:#219     // getTemplate:(I)Lext/mods/gameserver/model/item/kind/Item;
  #218 = Utf8               getTemplate
  #219 = Utf8               (I)Lext/mods/gameserver/model/item/kind/Item;
  #220 = Methodref          #221.#222     // ext/mods/gameserver/idfactory/IdFactory.getInstance:()Lext/mods/gameserver/idfactory/IdFactory;
  #221 = Class              #223          // ext/mods/gameserver/idfactory/IdFactory
  #222 = NameAndType        #107:#224     // getInstance:()Lext/mods/gameserver/idfactory/IdFactory;
  #223 = Utf8               ext/mods/gameserver/idfactory/IdFactory
  #224 = Utf8               ()Lext/mods/gameserver/idfactory/IdFactory;
  #225 = Methodref          #221.#226     // ext/mods/gameserver/idfactory/IdFactory.getNextId:()I
  #226 = NameAndType        #227:#127     // getNextId:()I
  #227 = Utf8               getNextId
  #228 = InterfaceMethodref #229.#230     // java/sql/PreparedStatement.setString:(ILjava/lang/String;)V
  #229 = Class              #231          // java/sql/PreparedStatement
  #230 = NameAndType        #232:#233     // setString:(ILjava/lang/String;)V
  #231 = Utf8               java/sql/PreparedStatement
  #232 = Utf8               setString
  #233 = Utf8               (ILjava/lang/String;)V
  #234 = InterfaceMethodref #229.#235     // java/sql/PreparedStatement.executeQuery:()Ljava/sql/ResultSet;
  #235 = NameAndType        #236:#237     // executeQuery:()Ljava/sql/ResultSet;
  #236 = Utf8               executeQuery
  #237 = Utf8               ()Ljava/sql/ResultSet;
  #238 = InterfaceMethodref #239.#240     // java/sql/ResultSet.next:()Z
  #239 = Class              #241          // java/sql/ResultSet
  #240 = NameAndType        #242:#243     // next:()Z
  #241 = Utf8               java/sql/ResultSet
  #242 = Utf8               next
  #243 = Utf8               ()Z
  #244 = InterfaceMethodref #239.#245     // java/sql/ResultSet.getInt:(I)I
  #245 = NameAndType        #246:#247     // getInt:(I)I
  #246 = Utf8               getInt
  #247 = Utf8               (I)I
  #248 = InterfaceMethodref #239.#249     // java/sql/ResultSet.close:()V
  #249 = NameAndType        #250:#45      // close:()V
  #250 = Utf8               close
  #251 = InterfaceMethodref #229.#249     // java/sql/PreparedStatement.close:()V
  #252 = InterfaceMethodref #204.#249     // java/sql/Connection.close:()V
  #253 = Methodref          #254.#255     // ext/mods/gameserver/model/item/kind/Item.isStackable:()Z
  #254 = Class              #256          // ext/mods/gameserver/model/item/kind/Item
  #255 = NameAndType        #257:#243     // isStackable:()Z
  #256 = Utf8               ext/mods/gameserver/model/item/kind/Item
  #257 = Utf8               isStackable
  #258 = InterfaceMethodref #229.#259     // java/sql/PreparedStatement.setInt:(II)V
  #259 = NameAndType        #260:#24      // setInt:(II)V
  #260 = Utf8               setInt
  #261 = Methodref          #254.#262     // ext/mods/gameserver/model/item/kind/Item.getItemId:()I
  #262 = NameAndType        #263:#127     // getItemId:()I
  #263 = Utf8               getItemId
  #264 = Methodref          #265.#266     // ext/mods/gameserver/enums/items/ItemLocation.name:()Ljava/lang/String;
  #265 = Class              #267          // ext/mods/gameserver/enums/items/ItemLocation
  #266 = NameAndType        #268:#269     // name:()Ljava/lang/String;
  #267 = Utf8               ext/mods/gameserver/enums/items/ItemLocation
  #268 = Utf8               name
  #269 = Utf8               ()Ljava/lang/String;
  #270 = InterfaceMethodref #229.#271     // java/sql/PreparedStatement.setLong:(IJ)V
  #271 = NameAndType        #272:#273     // setLong:(IJ)V
  #272 = Utf8               setLong
  #273 = Utf8               (IJ)V
  #274 = InterfaceMethodref #229.#275     // java/sql/PreparedStatement.executeUpdate:()I
  #275 = NameAndType        #276:#127     // executeUpdate:()I
  #276 = Utf8               executeUpdate
  #277 = Class              #278          // java/lang/Throwable
  #278 = Utf8               java/lang/Throwable
  #279 = Methodref          #277.#280     // java/lang/Throwable.addSuppressed:(Ljava/lang/Throwable;)V
  #280 = NameAndType        #281:#282     // addSuppressed:(Ljava/lang/Throwable;)V
  #281 = Utf8               addSuppressed
  #282 = Utf8               (Ljava/lang/Throwable;)V
  #283 = Class              #284          // java/sql/SQLException
  #284 = Utf8               java/sql/SQLException
  #285 = Methodref          #286.#287     // java/lang/String.toUpperCase:()Ljava/lang/String;
  #286 = Class              #288          // java/lang/String
  #287 = NameAndType        #289:#269     // toUpperCase:()Ljava/lang/String;
  #288 = Utf8               java/lang/String
  #289 = Utf8               toUpperCase
  #290 = Methodref          #286.#291     // java/lang/String.hashCode:()I
  #291 = NameAndType        #292:#127     // hashCode:()I
  #292 = Utf8               hashCode
  #293 = Methodref          #286.#294     // java/lang/String.equals:(Ljava/lang/Object;)Z
  #294 = NameAndType        #295:#296     // equals:(Ljava/lang/Object;)Z
  #295 = Utf8               equals
  #296 = Utf8               (Ljava/lang/Object;)Z
  #297 = Fieldref           #265.#298     // ext/mods/gameserver/enums/items/ItemLocation.INVENTORY:Lext/mods/gameserver/enums/items/ItemLocation;
  #298 = NameAndType        #54:#299      // INVENTORY:Lext/mods/gameserver/enums/items/ItemLocation;
  #299 = Utf8               Lext/mods/gameserver/enums/items/ItemLocation;
  #300 = Fieldref           #265.#301     // ext/mods/gameserver/enums/items/ItemLocation.WAREHOUSE:Lext/mods/gameserver/enums/items/ItemLocation;
  #301 = NameAndType        #60:#299      // WAREHOUSE:Lext/mods/gameserver/enums/items/ItemLocation;
  #302 = Fieldref           #265.#303     // ext/mods/gameserver/enums/items/ItemLocation.CLANWH:Lext/mods/gameserver/enums/items/ItemLocation;
  #303 = NameAndType        #62:#299      // CLANWH:Lext/mods/gameserver/enums/items/ItemLocation;
  #304 = Methodref          #65.#305      // javax/swing/JCheckBox.isSelected:()Z
  #305 = NameAndType        #306:#243     // isSelected:()Z
  #306 = Utf8               isSelected
  #307 = Utf8               serialVersionUID
  #308 = Utf8               J
  #309 = Utf8               ConstantValue
  #310 = Long               1l
  #312 = Utf8               (Ljavax/swing/JFrame;Ljava/lang/String;)V
  #313 = Utf8               Code
  #314 = Utf8               LineNumberTable
  #315 = Utf8               LocalVariableTable
  #316 = Utf8               this
  #317 = Utf8               Lext/mods/commons/gui/tools/CreateItemDialog;
  #318 = Utf8               mainFrame
  #319 = Utf8               playerName
  #320 = Utf8               lblItemId
  #321 = Utf8               Ljavax/swing/JLabel;
  #322 = Utf8               txtItemId
  #323 = Utf8               Ljavax/swing/JTextField;
  #324 = Utf8               lblAmount
  #325 = Utf8               txtAmount
  #326 = Utf8               lblLocation
  #327 = Utf8               locationComboBox
  #328 = Utf8               Ljavax/swing/JComboBox;
  #329 = Utf8               lblEnchant
  #330 = Utf8               enchantCheckBox
  #331 = Utf8               Ljavax/swing/JCheckBox;
  #332 = Utf8               lblEnchantLevel
  #333 = Utf8               txtEnchantLevel
  #334 = Utf8               btnSetVip
  #335 = Utf8               Ljavax/swing/JButton;
  #336 = Utf8               LocalVariableTypeTable
  #337 = Utf8               Ljavax/swing/JComboBox<Ljava/lang/String;>;
  #338 = Utf8               addCreateItem
  #339 = Utf8               (Ljava/lang/String;IILjava/lang/String;ILjavax/swing/JFrame;)V
  #340 = Utf8               itemcreate
  #341 = Utf8               Lext/mods/gameserver/model/item/instance/ItemInstance;
  #342 = Utf8               location
  #343 = Utf8               itemid
  #344 = Utf8               I
  #345 = Utf8               amount
  #346 = Utf8               locationName
  #347 = Utf8               enchantLevel
  #348 = Utf8               player
  #349 = Utf8               Lext/mods/gameserver/model/actor/Player;
  #350 = Utf8               StackMapTable
  #351 = Utf8               objId
  #352 = Utf8               result
  #353 = Utf8               Ljava/sql/ResultSet;
  #354 = Utf8               item
  #355 = Utf8               Lext/mods/gameserver/model/item/kind/Item;
  #356 = Utf8               objectId
  #357 = Utf8               insertStatement
  #358 = Utf8               Ljava/sql/PreparedStatement;
  #359 = Utf8               selectStatement
  #360 = Utf8               con
  #361 = Utf8               Ljava/sql/Connection;
  #362 = Utf8               playername
  #363 = Utf8               id
  #364 = Utf8               count
  #365 = Utf8               lambda$new$0
  #366 = Utf8               (Ljavax/swing/JCheckBox;Ljavax/swing/JLabel;Ljavax/swing/JTextField;Ljava/awt/event/ActionEvent;)V
  #367 = Utf8               e
  #368 = Utf8               Ljava/awt/event/ActionEvent;
  #369 = Utf8               isChecked
  #370 = Utf8               Z
  #371 = Utf8               SourceFile
  #372 = Utf8               CreateItemDialog.java
  #373 = Utf8               NestMembers
  #374 = Utf8               BootstrapMethods
  #375 = String             #376          // Create Item: \u0001
  #376 = Utf8               Create Item: \u0001
  #377 = MethodType         #378          //  (Ljava/awt/event/ActionEvent;)V
  #378 = Utf8               (Ljava/awt/event/ActionEvent;)V
  #379 = MethodHandle       6:#380        // REF_invokeStatic ext/mods/commons/gui/tools/CreateItemDialog.lambda$new$0:(Ljavax/swing/JCheckBox;Ljavax/swing/JLabel;Ljavax/swing/JTextField;Ljava/awt/event/ActionEvent;)V
  #380 = Methodref          #12.#381      // ext/mods/commons/gui/tools/CreateItemDialog.lambda$new$0:(Ljavax/swing/JCheckBox;Ljavax/swing/JLabel;Ljavax/swing/JTextField;Ljava/awt/event/ActionEvent;)V
  #381 = NameAndType        #365:#366     // lambda$new$0:(Ljavax/swing/JCheckBox;Ljavax/swing/JLabel;Ljavax/swing/JTextField;Ljava/awt/event/ActionEvent;)V
  #382 = String             #383          // Create Item successfully for \u0001
  #383 = Utf8               Create Item successfully for \u0001
  #384 = String             #385          // Item created successfully for \u0001
  #385 = Utf8               Item created successfully for \u0001
  #386 = MethodHandle       6:#387        // REF_invokeStatic java/lang/invoke/StringConcatFactory.makeConcatWithConstants:(Ljava/lang/invoke/MethodHandles$Lookup;Ljava/lang/String;Ljava/lang/invoke/MethodType;Ljava/lang/String;[Ljava/lang/Object;)Ljava/lang/invoke/CallSite;
  #387 = Methodref          #388.#389     // java/lang/invoke/StringConcatFactory.makeConcatWithConstants:(Ljava/lang/invoke/MethodHandles$Lookup;Ljava/lang/String;Ljava/lang/invoke/MethodType;Ljava/lang/String;[Ljava/lang/Object;)Ljava/lang/invoke/CallSite;
  #388 = Class              #390          // java/lang/invoke/StringConcatFactory
  #389 = NameAndType        #3:#391       // makeConcatWithConstants:(Ljava/lang/invoke/MethodHandles$Lookup;Ljava/lang/String;Ljava/lang/invoke/MethodType;Ljava/lang/String;[Ljava/lang/Object;)Ljava/lang/invoke/CallSite;
  #390 = Utf8               java/lang/invoke/StringConcatFactory
  #391 = Utf8               (Ljava/lang/invoke/MethodHandles$Lookup;Ljava/lang/String;Ljava/lang/invoke/MethodType;Ljava/lang/String;[Ljava/lang/Object;)Ljava/lang/invoke/CallSite;
  #392 = MethodHandle       6:#393        // REF_invokeStatic java/lang/invoke/LambdaMetafactory.metafactory:(Ljava/lang/invoke/MethodHandles$Lookup;Ljava/lang/String;Ljava/lang/invoke/MethodType;Ljava/lang/invoke/MethodType;Ljava/lang/invoke/MethodHandle;Ljava/lang/invoke/MethodType;)Ljava/lang/invoke/CallSite;
  #393 = Methodref          #394.#395     // java/lang/invoke/LambdaMetafactory.metafactory:(Ljava/lang/invoke/MethodHandles$Lookup;Ljava/lang/String;Ljava/lang/invoke/MethodType;Ljava/lang/invoke/MethodType;Ljava/lang/invoke/MethodHandle;Ljava/lang/invoke/MethodType;)Ljava/lang/invoke/CallSite;
  #394 = Class              #396          // java/lang/invoke/LambdaMetafactory
  #395 = NameAndType        #397:#398     // metafactory:(Ljava/lang/invoke/MethodHandles$Lookup;Ljava/lang/String;Ljava/lang/invoke/MethodType;Ljava/lang/invoke/MethodType;Ljava/lang/invoke/MethodHandle;Ljava/lang/invoke/MethodType;)Ljava/lang/invoke/CallSite;
  #396 = Utf8               java/lang/invoke/LambdaMetafactory
  #397 = Utf8               metafactory
  #398 = Utf8               (Ljava/lang/invoke/MethodHandles$Lookup;Ljava/lang/String;Ljava/lang/invoke/MethodType;Ljava/lang/invoke/MethodType;Ljava/lang/invoke/MethodHandle;Ljava/lang/invoke/MethodType;)Ljava/lang/invoke/CallSite;
  #399 = Utf8               InnerClasses
  #400 = Class              #401          // java/lang/invoke/MethodHandles$Lookup
  #401 = Utf8               java/lang/invoke/MethodHandles$Lookup
  #402 = Class              #403          // java/lang/invoke/MethodHandles
  #403 = Utf8               java/lang/invoke/MethodHandles
  #404 = Utf8               Lookup
{
  public ext.mods.commons.gui.tools.CreateItemDialog(javax.swing.JFrame, java.lang.String);
    descriptor: (Ljavax/swing/JFrame;Ljava/lang/String;)V
    flags: (0x0001) ACC_PUBLIC
    Code:
      stack=9, locals=14, args_size=3
         0: aload_0
         1: aload_1
         2: aload_2
         3: invokedynamic #1,  0              // InvokeDynamic #0:makeConcatWithConstants:(Ljava/lang/String;)Ljava/lang/String;
         8: iconst_1
         9: invokespecial #5                  // Method javax/swing/JDialog."<init>":(Ljava/awt/Frame;Ljava/lang/String;Z)V
        12: aload_0
        13: aload_2
        14: putfield      #11                 // Field _playerName:Ljava/lang/String;
        17: aload_0
        18: aload_1
        19: putfield      #17                 // Field _parentFrame:Ljavax/swing/JFrame;
        22: aload_0
        23: sipush        350
        26: sipush        230
        29: invokevirtual #21                 // Method setSize:(II)V
        32: aload_0
        33: new           #25                 // class java/awt/GridLayout
        36: dup
        37: bipush        7
        39: iconst_2
        40: iconst_5
        41: iconst_5
        42: invokespecial #27                 // Method java/awt/GridLayout."<init>":(IIII)V
        45: invokevirtual #30                 // Method setLayout:(Ljava/awt/LayoutManager;)V
        48: new           #34                 // class javax/swing/JLabel
        51: dup
        52: ldc           #36                 // String Item Id:
        54: invokespecial #38                 // Method javax/swing/JLabel."<init>":(Ljava/lang/String;)V
        57: astore_3
        58: new           #41                 // class javax/swing/JTextField
        61: dup
        62: invokespecial #43                 // Method javax/swing/JTextField."<init>":()V
        65: astore        4
        67: new           #34                 // class javax/swing/JLabel
        70: dup
        71: ldc           #46                 // String Amount:
        73: invokespecial #38                 // Method javax/swing/JLabel."<init>":(Ljava/lang/String;)V
        76: astore        5
        78: new           #41                 // class javax/swing/JTextField
        81: dup
        82: invokespecial #43                 // Method javax/swing/JTextField."<init>":()V
        85: astore        6
        87: new           #34                 // class javax/swing/JLabel
        90: dup
        91: ldc           #48                 // String Location:
        93: invokespecial #38                 // Method javax/swing/JLabel."<init>":(Ljava/lang/String;)V
        96: astore        7
        98: new           #50                 // class javax/swing/JComboBox
       101: dup
       102: invokespecial #52                 // Method javax/swing/JComboBox."<init>":()V
       105: astore        8
       107: aload         8
       109: ldc           #53                 // String INVENTORY
       111: invokevirtual #55                 // Method javax/swing/JComboBox.addItem:(Ljava/lang/Object;)V
       114: aload         8
       116: ldc           #59                 // String WAREHOUSE
       118: invokevirtual #55                 // Method javax/swing/JComboBox.addItem:(Ljava/lang/Object;)V
       121: aload         8
       123: ldc           #61                 // String CLANWH
       125: invokevirtual #55                 // Method javax/swing/JComboBox.addItem:(Ljava/lang/Object;)V
       128: new           #34                 // class javax/swing/JLabel
       131: dup
       132: ldc           #63                 // String Apply Enchant:
       134: invokespecial #38                 // Method javax/swing/JLabel."<init>":(Ljava/lang/String;)V
       137: astore        9
       139: new           #65                 // class javax/swing/JCheckBox
       142: dup
       143: invokespecial #67                 // Method javax/swing/JCheckBox."<init>":()V
       146: astore        10
       148: new           #34                 // class javax/swing/JLabel
       151: dup
       152: ldc           #68                 // String Enchant Level:
       154: invokespecial #38                 // Method javax/swing/JLabel."<init>":(Ljava/lang/String;)V
       157: astore        11
       159: new           #41                 // class javax/swing/JTextField
       162: dup
       163: invokespecial #43                 // Method javax/swing/JTextField."<init>":()V
       166: astore        12
       168: aload         11
       170: iconst_0
       171: invokevirtual #70                 // Method javax/swing/JLabel.setEnabled:(Z)V
       174: aload         12
       176: iconst_0
       177: invokevirtual #74                 // Method javax/swing/JTextField.setEnabled:(Z)V
       180: aload         10
       182: aload         10
       184: aload         11
       186: aload         12
       188: invokedynamic #75,  0             // InvokeDynamic #1:actionPerformed:(Ljavax/swing/JCheckBox;Ljavax/swing/JLabel;Ljavax/swing/JTextField;)Ljava/awt/event/ActionListener;
       193: invokevirtual #79                 // Method javax/swing/JCheckBox.addActionListener:(Ljava/awt/event/ActionListener;)V
       196: new           #83                 // class javax/swing/JButton
       199: dup
       200: ldc           #85                 // String Apply
       202: invokespecial #87                 // Method javax/swing/JButton."<init>":(Ljava/lang/String;)V
       205: astore        13
       207: aload         13
       209: new           #88                 // class ext/mods/commons/gui/tools/CreateItemDialog$1
       212: dup
       213: aload_0
       214: aload         4
       216: aload         6
       218: aload         8
       220: aload         10
       222: aload         12
       224: invokespecial #90                 // Method ext/mods/commons/gui/tools/CreateItemDialog$1."<init>":(Lext/mods/commons/gui/tools/CreateItemDialog;Ljavax/swing/JTextField;Ljavax/swing/JTextField;Ljavax/swing/JComboBox;Ljavax/swing/JCheckBox;Ljavax/swing/JTextField;)V
       227: invokevirtual #93                 // Method javax/swing/JButton.addActionListener:(Ljava/awt/event/ActionListener;)V
       230: aload_0
       231: aload_3
       232: invokevirtual #94                 // Method add:(Ljava/awt/Component;)Ljava/awt/Component;
       235: pop
       236: aload_0
       237: aload         4
       239: invokevirtual #94                 // Method add:(Ljava/awt/Component;)Ljava/awt/Component;
       242: pop
       243: aload_0
       244: aload         5
       246: invokevirtual #94                 // Method add:(Ljava/awt/Component;)Ljava/awt/Component;
       249: pop
       250: aload_0
       251: aload         6
       253: invokevirtual #94                 // Method add:(Ljava/awt/Component;)Ljava/awt/Component;
       256: pop
       257: aload_0
       258: aload         7
       260: invokevirtual #94                 // Method add:(Ljava/awt/Component;)Ljava/awt/Component;
       263: pop
       264: aload_0
       265: aload         8
       267: invokevirtual #94                 // Method add:(Ljava/awt/Component;)Ljava/awt/Component;
       270: pop
       271: aload_0
       272: aload         9
       274: invokevirtual #94                 // Method add:(Ljava/awt/Component;)Ljava/awt/Component;
       277: pop
       278: aload_0
       279: aload         10
       281: invokevirtual #94                 // Method add:(Ljava/awt/Component;)Ljava/awt/Component;
       284: pop
       285: aload_0
       286: aload         11
       288: invokevirtual #94                 // Method add:(Ljava/awt/Component;)Ljava/awt/Component;
       291: pop
       292: aload_0
       293: aload         12
       295: invokevirtual #94                 // Method add:(Ljava/awt/Component;)Ljava/awt/Component;
       298: pop
       299: aload_0
       300: new           #34                 // class javax/swing/JLabel
       303: dup
       304: invokespecial #98                 // Method javax/swing/JLabel."<init>":()V
       307: invokevirtual #94                 // Method add:(Ljava/awt/Component;)Ljava/awt/Component;
       310: pop
       311: aload_0
       312: aload         13
       314: invokevirtual #94                 // Method add:(Ljava/awt/Component;)Ljava/awt/Component;
       317: pop
       318: aload_0
       319: aload_1
       320: invokevirtual #99                 // Method setLocationRelativeTo:(Ljava/awt/Component;)V
       323: return
      LineNumberTable:
        line 54: 0
        line 55: 12
        line 56: 17
        line 58: 22
        line 59: 32
        line 61: 48
        line 62: 58
        line 63: 67
        line 64: 78
        line 65: 87
        line 66: 98
        line 67: 107
        line 68: 114
        line 69: 121
        line 70: 128
        line 71: 139
        line 72: 148
        line 73: 159
        line 74: 168
        line 75: 174
        line 77: 180
        line 83: 196
        line 84: 207
        line 103: 230
        line 104: 236
        line 105: 243
        line 106: 250
        line 107: 257
        line 108: 264
        line 109: 271
        line 110: 278
        line 111: 285
        line 112: 292
        line 113: 299
        line 114: 311
        line 116: 318
        line 117: 323
      LocalVariableTable:
        Start  Length  Slot  Name   Signature
            0     324     0  this   Lext/mods/commons/gui/tools/CreateItemDialog;
            0     324     1 mainFrame   Ljavax/swing/JFrame;
            0     324     2 playerName   Ljava/lang/String;
           58     266     3 lblItemId   Ljavax/swing/JLabel;
           67     257     4 txtItemId   Ljavax/swing/JTextField;
           78     246     5 lblAmount   Ljavax/swing/JLabel;
           87     237     6 txtAmount   Ljavax/swing/JTextField;
           98     226     7 lblLocation   Ljavax/swing/JLabel;
          107     217     8 locationComboBox   Ljavax/swing/JComboBox;
          139     185     9 lblEnchant   Ljavax/swing/JLabel;
          148     176    10 enchantCheckBox   Ljavax/swing/JCheckBox;
          159     165    11 lblEnchantLevel   Ljavax/swing/JLabel;
          168     156    12 txtEnchantLevel   Ljavax/swing/JTextField;
          207     117    13 btnSetVip   Ljavax/swing/JButton;
      LocalVariableTypeTable:
        Start  Length  Slot  Name   Signature
          107     217     8 locationComboBox   Ljavax/swing/JComboBox<Ljava/lang/String;>;

  public static void giveItemToOfflinePlayer(java.lang.String, int, int, int, ext.mods.gameserver.enums.items.ItemLocation);
    descriptor: (Ljava/lang/String;IIILext/mods/gameserver/enums/items/ItemLocation;)V
    flags: (0x0009) ACC_PUBLIC, ACC_STATIC
    Code:
      stack=4, locals=13, args_size=5
         0: invokestatic  #195                // Method ext/mods/commons/pool/ConnectionPool.getConnection:()Ljava/sql/Connection;
         3: astore        5
         5: aload         5
         7: ldc           #201                // String SELECT obj_Id FROM characters WHERE char_name=?
         9: invokeinterface #203,  2          // InterfaceMethod java/sql/Connection.prepareStatement:(Ljava/lang/String;)Ljava/sql/PreparedStatement;
        14: astore        6
        16: aload         5
        18: ldc           #209                // String INSERT INTO items (owner_id,item_id,count,loc,loc_data,enchant_level,object_id,custom_type1,custom_type2,mana_left,time) VALUES (?,?,?,?,?,?,?,?,?,?,?)
        20: invokeinterface #203,  2          // InterfaceMethod java/sql/Connection.prepareStatement:(Ljava/lang/String;)Ljava/sql/PreparedStatement;
        25: astore        7
        27: invokestatic  #211                // Method ext/mods/gameserver/data/xml/ItemData.getInstance:()Lext/mods/gameserver/data/xml/ItemData;
        30: iload_1
        31: invokevirtual #216                // Method ext/mods/gameserver/data/xml/ItemData.getTemplate:(I)Lext/mods/gameserver/model/item/kind/Item;
        34: astore        8
        36: invokestatic  #220                // Method ext/mods/gameserver/idfactory/IdFactory.getInstance:()Lext/mods/gameserver/idfactory/IdFactory;
        39: invokevirtual #225                // Method ext/mods/gameserver/idfactory/IdFactory.getNextId:()I
        42: istore        9
        44: aload         6
        46: iconst_1
        47: aload_0
        48: invokeinterface #228,  3          // InterfaceMethod java/sql/PreparedStatement.setString:(ILjava/lang/String;)V
        53: aload         6
        55: invokeinterface #234,  1          // InterfaceMethod java/sql/PreparedStatement.executeQuery:()Ljava/sql/ResultSet;
        60: astore        10
        62: iconst_0
        63: istore        11
        65: aload         10
        67: invokeinterface #238,  1          // InterfaceMethod java/sql/ResultSet.next:()Z
        72: ifeq          85
        75: aload         10
        77: iconst_1
        78: invokeinterface #244,  2          // InterfaceMethod java/sql/ResultSet.getInt:(I)I
        83: istore        11
        85: iload         11
        87: ifne          139
        90: aload         10
        92: ifnull        102
        95: aload         10
        97: invokeinterface #248,  1          // InterfaceMethod java/sql/ResultSet.close:()V
       102: aload         7
       104: ifnull        114
       107: aload         7
       109: invokeinterface #251,  1          // InterfaceMethod java/sql/PreparedStatement.close:()V
       114: aload         6
       116: ifnull        126
       119: aload         6
       121: invokeinterface #251,  1          // InterfaceMethod java/sql/PreparedStatement.close:()V
       126: aload         5
       128: ifnull        138
       131: aload         5
       133: invokeinterface #252,  1          // InterfaceMethod java/sql/Connection.close:()V
       138: return
       139: aload         8
       141: ifnonnull     193
       144: aload         10
       146: ifnull        156
       149: aload         10
       151: invokeinterface #248,  1          // InterfaceMethod java/sql/ResultSet.close:()V
       156: aload         7
       158: ifnull        168
       161: aload         7
       163: invokeinterface #251,  1          // InterfaceMethod java/sql/PreparedStatement.close:()V
       168: aload         6
       170: ifnull        180
       173: aload         6
       175: invokeinterface #251,  1          // InterfaceMethod java/sql/PreparedStatement.close:()V
       180: aload         5
       182: ifnull        192
       185: aload         5
       187: invokeinterface #252,  1          // InterfaceMethod java/sql/Connection.close:()V
       192: return
       193: iload_2
       194: iconst_1
       195: if_icmple     255
       198: aload         8
       200: invokevirtual #253                // Method ext/mods/gameserver/model/item/kind/Item.isStackable:()Z
       203: ifne          255
       206: aload         10
       208: ifnull        218
       211: aload         10
       213: invokeinterface #248,  1          // InterfaceMethod java/sql/ResultSet.close:()V
       218: aload         7
       220: ifnull        230
       223: aload         7
       225: invokeinterface #251,  1          // InterfaceMethod java/sql/PreparedStatement.close:()V
       230: aload         6
       232: ifnull        242
       235: aload         6
       237: invokeinterface #251,  1          // InterfaceMethod java/sql/PreparedStatement.close:()V
       242: aload         5
       244: ifnull        254
       247: aload         5
       249: invokeinterface #252,  1          // InterfaceMethod java/sql/Connection.close:()V
       254: return
       255: aload         7
       257: iconst_1
       258: iload         11
       260: invokeinterface #258,  3          // InterfaceMethod java/sql/PreparedStatement.setInt:(II)V
       265: aload         7
       267: iconst_2
       268: aload         8
       270: invokevirtual #261                // Method ext/mods/gameserver/model/item/kind/Item.getItemId:()I
       273: invokeinterface #258,  3          // InterfaceMethod java/sql/PreparedStatement.setInt:(II)V
       278: aload         7
       280: iconst_3
       281: iload_2
       282: invokeinterface #258,  3          // InterfaceMethod java/sql/PreparedStatement.setInt:(II)V
       287: aload         7
       289: iconst_4
       290: aload         4
       292: invokevirtual #264                // Method ext/mods/gameserver/enums/items/ItemLocation.name:()Ljava/lang/String;
       295: invokeinterface #228,  3          // InterfaceMethod java/sql/PreparedStatement.setString:(ILjava/lang/String;)V
       300: aload         7
       302: iconst_5
       303: iconst_0
       304: invokeinterface #258,  3          // InterfaceMethod java/sql/PreparedStatement.setInt:(II)V
       309: aload         7
       311: bipush        6
       313: iload_3
       314: invokeinterface #258,  3          // InterfaceMethod java/sql/PreparedStatement.setInt:(II)V
       319: aload         7
       321: bipush        7
       323: iload         9
       325: invokeinterface #258,  3          // InterfaceMethod java/sql/PreparedStatement.setInt:(II)V
       330: aload         7
       332: bipush        8
       334: iconst_0
       335: invokeinterface #258,  3          // InterfaceMethod java/sql/PreparedStatement.setInt:(II)V
       340: aload         7
       342: bipush        9
       344: iconst_0
       345: invokeinterface #258,  3          // InterfaceMethod java/sql/PreparedStatement.setInt:(II)V
       350: aload         7
       352: bipush        10
       354: iconst_m1
       355: invokeinterface #258,  3          // InterfaceMethod java/sql/PreparedStatement.setInt:(II)V
       360: aload         7
       362: bipush        11
       364: lconst_0
       365: invokeinterface #270,  4          // InterfaceMethod java/sql/PreparedStatement.setLong:(IJ)V
       370: aload         7
       372: invokeinterface #274,  1          // InterfaceMethod java/sql/PreparedStatement.executeUpdate:()I
       377: pop
       378: aload         10
       380: ifnull        422
       383: aload         10
       385: invokeinterface #248,  1          // InterfaceMethod java/sql/ResultSet.close:()V
       390: goto          422
       393: astore        11
       395: aload         10
       397: ifnull        419
       400: aload         10
       402: invokeinterface #248,  1          // InterfaceMethod java/sql/ResultSet.close:()V
       407: goto          419
       410: astore        12
       412: aload         11
       414: aload         12
       416: invokevirtual #279                // Method java/lang/Throwable.addSuppressed:(Ljava/lang/Throwable;)V
       419: aload         11
       421: athrow
       422: aload         7
       424: ifnull        466
       427: aload         7
       429: invokeinterface #251,  1          // InterfaceMethod java/sql/PreparedStatement.close:()V
       434: goto          466
       437: astore        8
       439: aload         7
       441: ifnull        463
       444: aload         7
       446: invokeinterface #251,  1          // InterfaceMethod java/sql/PreparedStatement.close:()V
       451: goto          463
       454: astore        9
       456: aload         8
       458: aload         9
       460: invokevirtual #279                // Method java/lang/Throwable.addSuppressed:(Ljava/lang/Throwable;)V
       463: aload         8
       465: athrow
       466: aload         6
       468: ifnull        510
       471: aload         6
       473: invokeinterface #251,  1          // InterfaceMethod java/sql/PreparedStatement.close:()V
       478: goto          510
       481: astore        7
       483: aload         6
       485: ifnull        507
       488: aload         6
       490: invokeinterface #251,  1          // InterfaceMethod java/sql/PreparedStatement.close:()V
       495: goto          507
       498: astore        8
       500: aload         7
       502: aload         8
       504: invokevirtual #279                // Method java/lang/Throwable.addSuppressed:(Ljava/lang/Throwable;)V
       507: aload         7
       509: athrow
       510: aload         5
       512: ifnull        554
       515: aload         5
       517: invokeinterface #252,  1          // InterfaceMethod java/sql/Connection.close:()V
       522: goto          554
       525: astore        6
       527: aload         5
       529: ifnull        551
       532: aload         5
       534: invokeinterface #252,  1          // InterfaceMethod java/sql/Connection.close:()V
       539: goto          551
       542: astore        7
       544: aload         6
       546: aload         7
       548: invokevirtual #279                // Method java/lang/Throwable.addSuppressed:(Ljava/lang/Throwable;)V
       551: aload         6
       553: athrow
       554: goto          559
       557: astore        5
       559: return
      Exception table:
         from    to  target type
            62    90   393   Class java/lang/Throwable
           139   144   393   Class java/lang/Throwable
           193   206   393   Class java/lang/Throwable
           255   378   393   Class java/lang/Throwable
           400   407   410   Class java/lang/Throwable
            27   102   437   Class java/lang/Throwable
           139   156   437   Class java/lang/Throwable
           193   218   437   Class java/lang/Throwable
           255   422   437   Class java/lang/Throwable
           444   451   454   Class java/lang/Throwable
            16   114   481   Class java/lang/Throwable
           139   168   481   Class java/lang/Throwable
           193   230   481   Class java/lang/Throwable
           255   466   481   Class java/lang/Throwable
           488   495   498   Class java/lang/Throwable
             5   126   525   Class java/lang/Throwable
           139   180   525   Class java/lang/Throwable
           193   242   525   Class java/lang/Throwable
           255   510   525   Class java/lang/Throwable
           532   539   542   Class java/lang/Throwable
             0   138   557   Class java/sql/SQLException
           139   192   557   Class java/sql/SQLException
           193   254   557   Class java/sql/SQLException
           255   554   557   Class java/sql/SQLException
      LineNumberTable:
        line 152: 0
        line 154: 27
        line 155: 36
        line 157: 44
        line 158: 53
        line 159: 62
        line 161: 65
        line 162: 75
        line 165: 85
        line 190: 90
        line 191: 102
        line 166: 138
        line 169: 139
        line 190: 144
        line 191: 156
        line 170: 192
        line 173: 193
        line 190: 206
        line 191: 218
        line 174: 254
        line 177: 255
        line 178: 265
        line 179: 278
        line 180: 287
        line 181: 300
        line 182: 309
        line 183: 319
        line 184: 330
        line 185: 340
        line 186: 350
        line 187: 360
        line 189: 370
        line 190: 378
        line 158: 393
        line 191: 422
        line 152: 437
        line 191: 466
        line 152: 481
        line 191: 510
        line 152: 525
        line 192: 554
        line 191: 557
        line 193: 559
      LocalVariableTable:
        Start  Length  Slot  Name   Signature
           65     313    11 objId   I
           62     360    10 result   Ljava/sql/ResultSet;
           36     386     8  item   Lext/mods/gameserver/model/item/kind/Item;
           44     378     9 objectId   I
           27     439     7 insertStatement   Ljava/sql/PreparedStatement;
           16     494     6 selectStatement   Ljava/sql/PreparedStatement;
            5     549     5   con   Ljava/sql/Connection;
            0     560     0 playername   Ljava/lang/String;
            0     560     1    id   I
            0     560     2 count   I
            0     560     3 enchantLevel   I
            0     560     4 location   Lext/mods/gameserver/enums/items/ItemLocation;
      StackMapTable: number_of_entries = 34
        frame_type = 255 /* full_frame */
          offset_delta = 85
          locals = [ class java/lang/String, int, int, int, class ext/mods/gameserver/enums/items/ItemLocation, class java/sql/Connection, class java/sql/PreparedStatement, class java/sql/PreparedStatement, class ext/mods/gameserver/model/item/kind/Item, int, class java/sql/ResultSet, int ]
          stack = []
        frame_type = 16 /* same */
        frame_type = 11 /* same */
        frame_type = 11 /* same */
        frame_type = 11 /* same */
        frame_type = 0 /* same */
        frame_type = 16 /* same */
        frame_type = 11 /* same */
        frame_type = 11 /* same */
        frame_type = 11 /* same */
        frame_type = 0 /* same */
        frame_type = 24 /* same */
        frame_type = 11 /* same */
        frame_type = 11 /* same */
        frame_type = 11 /* same */
        frame_type = 0 /* same */
        frame_type = 255 /* full_frame */
          offset_delta = 137
          locals = [ class java/lang/String, int, int, int, class ext/mods/gameserver/enums/items/ItemLocation, class java/sql/Connection, class java/sql/PreparedStatement, class java/sql/PreparedStatement, class ext/mods/gameserver/model/item/kind/Item, int, class java/sql/ResultSet ]
          stack = [ class java/lang/Throwable ]
        frame_type = 255 /* full_frame */
          offset_delta = 16
          locals = [ class java/lang/String, int, int, int, class ext/mods/gameserver/enums/items/ItemLocation, class java/sql/Connection, class java/sql/PreparedStatement, class java/sql/PreparedStatement, class ext/mods/gameserver/model/item/kind/Item, int, class java/sql/ResultSet, class java/lang/Throwable ]
          stack = [ class java/lang/Throwable ]
        frame_type = 8 /* same */
        frame_type = 255 /* full_frame */
          offset_delta = 2
          locals = [ class java/lang/String, int, int, int, class ext/mods/gameserver/enums/items/ItemLocation, class java/sql/Connection, class java/sql/PreparedStatement, class java/sql/PreparedStatement ]
          stack = []
        frame_type = 78 /* same_locals_1_stack_item */
          stack = [ class java/lang/Throwable ]
        frame_type = 255 /* full_frame */
          offset_delta = 16
          locals = [ class java/lang/String, int, int, int, class ext/mods/gameserver/enums/items/ItemLocation, class java/sql/Connection, class java/sql/PreparedStatement, class java/sql/PreparedStatement, class java/lang/Throwable ]
          stack = [ class java/lang/Throwable ]
        frame_type = 8 /* same */
        frame_type = 249 /* chop */
          offset_delta = 2
        frame_type = 78 /* same_locals_1_stack_item */
          stack = [ class java/lang/Throwable ]
        frame_type = 255 /* full_frame */
          offset_delta = 16
          locals = [ class java/lang/String, int, int, int, class ext/mods/gameserver/enums/items/ItemLocation, class java/sql/Connection, class java/sql/PreparedStatement, class java/lang/Throwable ]
          stack = [ class java/lang/Throwable ]
        frame_type = 8 /* same */
        frame_type = 249 /* chop */
          offset_delta = 2
        frame_type = 78 /* same_locals_1_stack_item */
          stack = [ class java/lang/Throwable ]
        frame_type = 255 /* full_frame */
          offset_delta = 16
          locals = [ class java/lang/String, int, int, int, class ext/mods/gameserver/enums/items/ItemLocation, class java/sql/Connection, class java/lang/Throwable ]
          stack = [ class java/lang/Throwable ]
        frame_type = 8 /* same */
        frame_type = 249 /* chop */
          offset_delta = 2
        frame_type = 66 /* same_locals_1_stack_item */
          stack = [ class java/sql/SQLException ]
        frame_type = 1 /* same */
}
SourceFile: "CreateItemDialog.java"
NestMembers:
  ext/mods/commons/gui/tools/CreateItemDialog$1
BootstrapMethods:
  0: #386 REF_invokeStatic java/lang/invoke/StringConcatFactory.makeConcatWithConstants:(Ljava/lang/invoke/MethodHandles$Lookup;Ljava/lang/String;Ljava/lang/invoke/MethodType;Ljava/lang/String;[Ljava/lang/Object;)Ljava/lang/invoke/CallSite;
    Method arguments:
      #375 Create Item: \u0001
  1: #392 REF_invokeStatic java/lang/invoke/LambdaMetafactory.metafactory:(Ljava/lang/invoke/MethodHandles$Lookup;Ljava/lang/String;Ljava/lang/invoke/MethodType;Ljava/lang/invoke/MethodType;Ljava/lang/invoke/MethodHandle;Ljava/lang/invoke/MethodType;)Ljava/lang/invoke/CallSite;
    Method arguments:
      #377 (Ljava/awt/event/ActionEvent;)V
      #379 REF_invokeStatic ext/mods/commons/gui/tools/CreateItemDialog.lambda$new$0:(Ljavax/swing/JCheckBox;Ljavax/swing/JLabel;Ljavax/swing/JTextField;Ljava/awt/event/ActionEvent;)V
      #377 (Ljava/awt/event/ActionEvent;)V
  2: #386 REF_invokeStatic java/lang/invoke/StringConcatFactory.makeConcatWithConstants:(Ljava/lang/invoke/MethodHandles$Lookup;Ljava/lang/String;Ljava/lang/invoke/MethodType;Ljava/lang/String;[Ljava/lang/Object;)Ljava/lang/invoke/CallSite;
    Method arguments:
      #382 Create Item successfully for \u0001
  3: #386 REF_invokeStatic java/lang/invoke/StringConcatFactory.makeConcatWithConstants:(Ljava/lang/invoke/MethodHandles$Lookup;Ljava/lang/String;Ljava/lang/invoke/MethodType;Ljava/lang/String;[Ljava/lang/Object;)Ljava/lang/invoke/CallSite;
    Method arguments:
      #384 Item created successfully for \u0001
InnerClasses:
  #88;                                    // class ext/mods/commons/gui/tools/CreateItemDialog$1
  public static final #404= #400 of #402; // Lookup=class java/lang/invoke/MethodHandles$Lookup of class java/lang/invoke/MethodHandles
