// Bytecode for: ext.mods.commons.gui.tools.SearchItemFrame
// File: ext\mods\commons\gui\tools\SearchItemFrame.class

Classfile /c:/Users/User/Desktop/BrProject/bin/main/ext/mods/commons/gui/tools/SearchItemFrame.class
  Last modified 9 de jul de 2026; size 4472 bytes
  MD5 checksum 5ad76bfb84e13542dce0d4d843982be1
  Compiled from "SearchItemFrame.java"
public class ext.mods.commons.gui.tools.SearchItemFrame extends javax.swing.JFrame
  minor version: 0
  major version: 69
  flags: (0x0021) ACC_PUBLIC, ACC_SUPER
  this_class: #16                         // ext/mods/commons/gui/tools/SearchItemFrame
  super_class: #4                         // javax/swing/JFrame
  interfaces: 0, fields: 1, methods: 2, attributes: 3
Constant pool:
    #1 = String             #2            // Search Item Manager
    #2 = Utf8               Search Item Manager
    #3 = Methodref          #4.#5         // javax/swing/JFrame."<init>":(Ljava/lang/String;)V
    #4 = Class              #6            // javax/swing/JFrame
    #5 = NameAndType        #7:#8         // "<init>":(Ljava/lang/String;)V
    #6 = Utf8               javax/swing/JFrame
    #7 = Utf8               <init>
    #8 = Utf8               (Ljava/lang/String;)V
    #9 = Methodref          #10.#11       // ext/mods/commons/gui/GuiUtils.loadIcons:()Ljava/util/List;
   #10 = Class              #12           // ext/mods/commons/gui/GuiUtils
   #11 = NameAndType        #13:#14       // loadIcons:()Ljava/util/List;
   #12 = Utf8               ext/mods/commons/gui/GuiUtils
   #13 = Utf8               loadIcons
   #14 = Utf8               ()Ljava/util/List;
   #15 = Methodref          #16.#17       // ext/mods/commons/gui/tools/SearchItemFrame.setIconImages:(Ljava/util/List;)V
   #16 = Class              #18           // ext/mods/commons/gui/tools/SearchItemFrame
   #17 = NameAndType        #19:#20       // setIconImages:(Ljava/util/List;)V
   #18 = Utf8               ext/mods/commons/gui/tools/SearchItemFrame
   #19 = Utf8               setIconImages
   #20 = Utf8               (Ljava/util/List;)V
   #21 = Methodref          #16.#22       // ext/mods/commons/gui/tools/SearchItemFrame.setSize:(II)V
   #22 = NameAndType        #23:#24       // setSize:(II)V
   #23 = Utf8               setSize
   #24 = Utf8               (II)V
   #25 = Class              #26           // java/awt/BorderLayout
   #26 = Utf8               java/awt/BorderLayout
   #27 = Methodref          #25.#28       // java/awt/BorderLayout."<init>":()V
   #28 = NameAndType        #7:#29        // "<init>":()V
   #29 = Utf8               ()V
   #30 = Methodref          #16.#31       // ext/mods/commons/gui/tools/SearchItemFrame.setLayout:(Ljava/awt/LayoutManager;)V
   #31 = NameAndType        #32:#33       // setLayout:(Ljava/awt/LayoutManager;)V
   #32 = Utf8               setLayout
   #33 = Utf8               (Ljava/awt/LayoutManager;)V
   #34 = Class              #35           // javax/swing/JPanel
   #35 = Utf8               javax/swing/JPanel
   #36 = Methodref          #34.#28       // javax/swing/JPanel."<init>":()V
   #37 = Class              #38           // java/awt/FlowLayout
   #38 = Utf8               java/awt/FlowLayout
   #39 = Methodref          #37.#40       // java/awt/FlowLayout."<init>":(III)V
   #40 = NameAndType        #7:#41        // "<init>":(III)V
   #41 = Utf8               (III)V
   #42 = Methodref          #34.#31       // javax/swing/JPanel.setLayout:(Ljava/awt/LayoutManager;)V
   #43 = Class              #44           // javax/swing/JLabel
   #44 = Utf8               javax/swing/JLabel
   #45 = String             #46           // Item Name:
   #46 = Utf8               Item Name:
   #47 = Methodref          #43.#5        // javax/swing/JLabel."<init>":(Ljava/lang/String;)V
   #48 = Class              #49           // javax/swing/JTextField
   #49 = Utf8               javax/swing/JTextField
   #50 = Methodref          #48.#51       // javax/swing/JTextField."<init>":(I)V
   #51 = NameAndType        #7:#52        // "<init>":(I)V
   #52 = Utf8               (I)V
   #53 = Class              #54           // javax/swing/JButton
   #54 = Utf8               javax/swing/JButton
   #55 = String             #56           // Search
   #56 = Utf8               Search
   #57 = Methodref          #53.#5        // javax/swing/JButton."<init>":(Ljava/lang/String;)V
   #58 = Methodref          #34.#59       // javax/swing/JPanel.add:(Ljava/awt/Component;)Ljava/awt/Component;
   #59 = NameAndType        #60:#61       // add:(Ljava/awt/Component;)Ljava/awt/Component;
   #60 = Utf8               add
   #61 = Utf8               (Ljava/awt/Component;)Ljava/awt/Component;
   #62 = String             #63           // North
   #63 = Utf8               North
   #64 = Methodref          #16.#65       // ext/mods/commons/gui/tools/SearchItemFrame.add:(Ljava/awt/Component;Ljava/lang/Object;)V
   #65 = NameAndType        #60:#66       // add:(Ljava/awt/Component;Ljava/lang/Object;)V
   #66 = Utf8               (Ljava/awt/Component;Ljava/lang/Object;)V
   #67 = Class              #68           // javax/swing/JTable
   #68 = Utf8               javax/swing/JTable
   #69 = Methodref          #67.#28       // javax/swing/JTable."<init>":()V
   #70 = Class              #71           // javax/swing/table/DefaultTableModel
   #71 = Utf8               javax/swing/table/DefaultTableModel
   #72 = Class              #73           // java/lang/String
   #73 = Utf8               java/lang/String
   #74 = String             #75           // Item ID
   #75 = Utf8               Item ID
   #76 = String             #77           // Item Name
   #77 = Utf8               Item Name
   #78 = Methodref          #70.#79       // javax/swing/table/DefaultTableModel."<init>":([Ljava/lang/Object;I)V
   #79 = NameAndType        #7:#80        // "<init>":([Ljava/lang/Object;I)V
   #80 = Utf8               ([Ljava/lang/Object;I)V
   #81 = Methodref          #67.#82       // javax/swing/JTable.setModel:(Ljavax/swing/table/TableModel;)V
   #82 = NameAndType        #83:#84       // setModel:(Ljavax/swing/table/TableModel;)V
   #83 = Utf8               setModel
   #84 = Utf8               (Ljavax/swing/table/TableModel;)V
   #85 = Class              #86           // javax/swing/JScrollPane
   #86 = Utf8               javax/swing/JScrollPane
   #87 = Methodref          #85.#88       // javax/swing/JScrollPane."<init>":(Ljava/awt/Component;)V
   #88 = NameAndType        #7:#89        // "<init>":(Ljava/awt/Component;)V
   #89 = Utf8               (Ljava/awt/Component;)V
   #90 = Class              #91           // java/awt/Dimension
   #91 = Utf8               java/awt/Dimension
   #92 = Methodref          #90.#93       // java/awt/Dimension."<init>":(II)V
   #93 = NameAndType        #7:#24        // "<init>":(II)V
   #94 = Methodref          #85.#95       // javax/swing/JScrollPane.setPreferredSize:(Ljava/awt/Dimension;)V
   #95 = NameAndType        #96:#97       // setPreferredSize:(Ljava/awt/Dimension;)V
   #96 = Utf8               setPreferredSize
   #97 = Utf8               (Ljava/awt/Dimension;)V
   #98 = String             #99           // Center
   #99 = Utf8               Center
  #100 = InvokeDynamic      #0:#101       // #0:actionPerformed:(Ljavax/swing/JTextField;Ljavax/swing/JFrame;Ljavax/swing/table/DefaultTableModel;)Ljava/awt/event/ActionListener;
  #101 = NameAndType        #102:#103     // actionPerformed:(Ljavax/swing/JTextField;Ljavax/swing/JFrame;Ljavax/swing/table/DefaultTableModel;)Ljava/awt/event/ActionListener;
  #102 = Utf8               actionPerformed
  #103 = Utf8               (Ljavax/swing/JTextField;Ljavax/swing/JFrame;Ljavax/swing/table/DefaultTableModel;)Ljava/awt/event/ActionListener;
  #104 = Methodref          #53.#105      // javax/swing/JButton.addActionListener:(Ljava/awt/event/ActionListener;)V
  #105 = NameAndType        #106:#107     // addActionListener:(Ljava/awt/event/ActionListener;)V
  #106 = Utf8               addActionListener
  #107 = Utf8               (Ljava/awt/event/ActionListener;)V
  #108 = Methodref          #16.#109      // ext/mods/commons/gui/tools/SearchItemFrame.setLocationRelativeTo:(Ljava/awt/Component;)V
  #109 = NameAndType        #110:#89      // setLocationRelativeTo:(Ljava/awt/Component;)V
  #110 = Utf8               setLocationRelativeTo
  #111 = Methodref          #48.#112      // javax/swing/JTextField.getText:()Ljava/lang/String;
  #112 = NameAndType        #113:#114     // getText:()Ljava/lang/String;
  #113 = Utf8               getText
  #114 = Utf8               ()Ljava/lang/String;
  #115 = Methodref          #72.#116      // java/lang/String.trim:()Ljava/lang/String;
  #116 = NameAndType        #117:#114     // trim:()Ljava/lang/String;
  #117 = Utf8               trim
  #118 = Methodref          #72.#119      // java/lang/String.isEmpty:()Z
  #119 = NameAndType        #120:#121     // isEmpty:()Z
  #120 = Utf8               isEmpty
  #121 = Utf8               ()Z
  #122 = String             #123          // Please enter an Item Name.
  #123 = Utf8               Please enter an Item Name.
  #124 = String             #125          // Error
  #125 = Utf8               Error
  #126 = Class              #127          // javax/swing/JOptionPane
  #127 = Utf8               javax/swing/JOptionPane
  #128 = Methodref          #126.#129     // javax/swing/JOptionPane.showMessageDialog:(Ljava/awt/Component;Ljava/lang/Object;Ljava/lang/String;I)V
  #129 = NameAndType        #130:#131     // showMessageDialog:(Ljava/awt/Component;Ljava/lang/Object;Ljava/lang/String;I)V
  #130 = Utf8               showMessageDialog
  #131 = Utf8               (Ljava/awt/Component;Ljava/lang/Object;Ljava/lang/String;I)V
  #132 = Methodref          #133.#134     // ext/mods/gameserver/data/xml/ItemData.getInstance:()Lext/mods/gameserver/data/xml/ItemData;
  #133 = Class              #135          // ext/mods/gameserver/data/xml/ItemData
  #134 = NameAndType        #136:#137     // getInstance:()Lext/mods/gameserver/data/xml/ItemData;
  #135 = Utf8               ext/mods/gameserver/data/xml/ItemData
  #136 = Utf8               getInstance
  #137 = Utf8               ()Lext/mods/gameserver/data/xml/ItemData;
  #138 = Methodref          #133.#139     // ext/mods/gameserver/data/xml/ItemData.searchItemsByName:(Ljava/lang/String;)Ljava/util/List;
  #139 = NameAndType        #140:#141     // searchItemsByName:(Ljava/lang/String;)Ljava/util/List;
  #140 = Utf8               searchItemsByName
  #141 = Utf8               (Ljava/lang/String;)Ljava/util/List;
  #142 = Methodref          #70.#143      // javax/swing/table/DefaultTableModel.setRowCount:(I)V
  #143 = NameAndType        #144:#52      // setRowCount:(I)V
  #144 = Utf8               setRowCount
  #145 = InterfaceMethodref #146.#147     // java/util/List.iterator:()Ljava/util/Iterator;
  #146 = Class              #148          // java/util/List
  #147 = NameAndType        #149:#150     // iterator:()Ljava/util/Iterator;
  #148 = Utf8               java/util/List
  #149 = Utf8               iterator
  #150 = Utf8               ()Ljava/util/Iterator;
  #151 = InterfaceMethodref #152.#153     // java/util/Iterator.hasNext:()Z
  #152 = Class              #154          // java/util/Iterator
  #153 = NameAndType        #155:#121     // hasNext:()Z
  #154 = Utf8               java/util/Iterator
  #155 = Utf8               hasNext
  #156 = InterfaceMethodref #152.#157     // java/util/Iterator.next:()Ljava/lang/Object;
  #157 = NameAndType        #158:#159     // next:()Ljava/lang/Object;
  #158 = Utf8               next
  #159 = Utf8               ()Ljava/lang/Object;
  #160 = Class              #161          // ext/mods/gameserver/model/item/kind/Item
  #161 = Utf8               ext/mods/gameserver/model/item/kind/Item
  #162 = Class              #163          // java/lang/Object
  #163 = Utf8               java/lang/Object
  #164 = Methodref          #160.#165     // ext/mods/gameserver/model/item/kind/Item.getItemId:()I
  #165 = NameAndType        #166:#167     // getItemId:()I
  #166 = Utf8               getItemId
  #167 = Utf8               ()I
  #168 = Methodref          #169.#170     // java/lang/Integer.valueOf:(I)Ljava/lang/Integer;
  #169 = Class              #171          // java/lang/Integer
  #170 = NameAndType        #172:#173     // valueOf:(I)Ljava/lang/Integer;
  #171 = Utf8               java/lang/Integer
  #172 = Utf8               valueOf
  #173 = Utf8               (I)Ljava/lang/Integer;
  #174 = Methodref          #160.#175     // ext/mods/gameserver/model/item/kind/Item.getName:()Ljava/lang/String;
  #175 = NameAndType        #176:#114     // getName:()Ljava/lang/String;
  #176 = Utf8               getName
  #177 = Methodref          #70.#178      // javax/swing/table/DefaultTableModel.addRow:([Ljava/lang/Object;)V
  #178 = NameAndType        #179:#180     // addRow:([Ljava/lang/Object;)V
  #179 = Utf8               addRow
  #180 = Utf8               ([Ljava/lang/Object;)V
  #181 = Utf8               serialVersionUID
  #182 = Utf8               J
  #183 = Utf8               ConstantValue
  #184 = Long               1l
  #186 = Utf8               Code
  #187 = Utf8               LineNumberTable
  #188 = Utf8               LocalVariableTable
  #189 = Utf8               this
  #190 = Utf8               Lext/mods/commons/gui/tools/SearchItemFrame;
  #191 = Utf8               itemSearchPanel
  #192 = Utf8               Ljavax/swing/JPanel;
  #193 = Utf8               lblItemName
  #194 = Utf8               Ljavax/swing/JLabel;
  #195 = Utf8               txtItemName
  #196 = Utf8               Ljavax/swing/JTextField;
  #197 = Utf8               btnItemSearch
  #198 = Utf8               Ljavax/swing/JButton;
  #199 = Utf8               itemTable
  #200 = Utf8               Ljavax/swing/JTable;
  #201 = Utf8               itemModel
  #202 = Utf8               Ljavax/swing/table/DefaultTableModel;
  #203 = Utf8               itemScrollPane
  #204 = Utf8               Ljavax/swing/JScrollPane;
  #205 = Utf8               thisFrame
  #206 = Utf8               Ljavax/swing/JFrame;
  #207 = Utf8               lambda$new$0
  #208 = Utf8               (Ljavax/swing/JTextField;Ljavax/swing/JFrame;Ljavax/swing/table/DefaultTableModel;Ljava/awt/event/ActionEvent;)V
  #209 = Utf8               item
  #210 = Utf8               Lext/mods/gameserver/model/item/kind/Item;
  #211 = Utf8               i$
  #212 = Utf8               Ljava/util/Iterator;
  #213 = Utf8               e
  #214 = Utf8               Ljava/awt/event/ActionEvent;
  #215 = Utf8               itemName
  #216 = Utf8               Ljava/lang/String;
  #217 = Utf8               itemTableInstance
  #218 = Utf8               Lext/mods/gameserver/data/xml/ItemData;
  #219 = Utf8               items
  #220 = Utf8               Ljava/util/List;
  #221 = Utf8               LocalVariableTypeTable
  #222 = Utf8               Ljava/util/List<Lext/mods/gameserver/model/item/kind/Item;>;
  #223 = Utf8               StackMapTable
  #224 = Utf8               SourceFile
  #225 = Utf8               SearchItemFrame.java
  #226 = Utf8               BootstrapMethods
  #227 = MethodType         #228          //  (Ljava/awt/event/ActionEvent;)V
  #228 = Utf8               (Ljava/awt/event/ActionEvent;)V
  #229 = MethodHandle       6:#230        // REF_invokeStatic ext/mods/commons/gui/tools/SearchItemFrame.lambda$new$0:(Ljavax/swing/JTextField;Ljavax/swing/JFrame;Ljavax/swing/table/DefaultTableModel;Ljava/awt/event/ActionEvent;)V
  #230 = Methodref          #16.#231      // ext/mods/commons/gui/tools/SearchItemFrame.lambda$new$0:(Ljavax/swing/JTextField;Ljavax/swing/JFrame;Ljavax/swing/table/DefaultTableModel;Ljava/awt/event/ActionEvent;)V
  #231 = NameAndType        #207:#208     // lambda$new$0:(Ljavax/swing/JTextField;Ljavax/swing/JFrame;Ljavax/swing/table/DefaultTableModel;Ljava/awt/event/ActionEvent;)V
  #232 = MethodHandle       6:#233        // REF_invokeStatic java/lang/invoke/LambdaMetafactory.metafactory:(Ljava/lang/invoke/MethodHandles$Lookup;Ljava/lang/String;Ljava/lang/invoke/MethodType;Ljava/lang/invoke/MethodType;Ljava/lang/invoke/MethodHandle;Ljava/lang/invoke/MethodType;)Ljava/lang/invoke/CallSite;
  #233 = Methodref          #234.#235     // java/lang/invoke/LambdaMetafactory.metafactory:(Ljava/lang/invoke/MethodHandles$Lookup;Ljava/lang/String;Ljava/lang/invoke/MethodType;Ljava/lang/invoke/MethodType;Ljava/lang/invoke/MethodHandle;Ljava/lang/invoke/MethodType;)Ljava/lang/invoke/CallSite;
  #234 = Class              #236          // java/lang/invoke/LambdaMetafactory
  #235 = NameAndType        #237:#238     // metafactory:(Ljava/lang/invoke/MethodHandles$Lookup;Ljava/lang/String;Ljava/lang/invoke/MethodType;Ljava/lang/invoke/MethodType;Ljava/lang/invoke/MethodHandle;Ljava/lang/invoke/MethodType;)Ljava/lang/invoke/CallSite;
  #236 = Utf8               java/lang/invoke/LambdaMetafactory
  #237 = Utf8               metafactory
  #238 = Utf8               (Ljava/lang/invoke/MethodHandles$Lookup;Ljava/lang/String;Ljava/lang/invoke/MethodType;Ljava/lang/invoke/MethodType;Ljava/lang/invoke/MethodHandle;Ljava/lang/invoke/MethodType;)Ljava/lang/invoke/CallSite;
  #239 = Utf8               InnerClasses
  #240 = Class              #241          // java/lang/invoke/MethodHandles$Lookup
  #241 = Utf8               java/lang/invoke/MethodHandles$Lookup
  #242 = Class              #243          // java/lang/invoke/MethodHandles
  #243 = Utf8               java/lang/invoke/MethodHandles
  #244 = Utf8               Lookup
{
  public ext.mods.commons.gui.tools.SearchItemFrame();
    descriptor: ()V
    flags: (0x0001) ACC_PUBLIC
    Code:
      stack=6, locals=9, args_size=1
         0: aload_0
         1: ldc           #1                  // String Search Item Manager
         3: invokespecial #3                  // Method javax/swing/JFrame."<init>":(Ljava/lang/String;)V
         6: aload_0
         7: invokestatic  #9                  // Method ext/mods/commons/gui/GuiUtils.loadIcons:()Ljava/util/List;
        10: invokevirtual #15                 // Method setIconImages:(Ljava/util/List;)V
        13: aload_0
        14: sipush        600
        17: sipush        300
        20: invokevirtual #21                 // Method setSize:(II)V
        23: aload_0
        24: new           #25                 // class java/awt/BorderLayout
        27: dup
        28: invokespecial #27                 // Method java/awt/BorderLayout."<init>":()V
        31: invokevirtual #30                 // Method setLayout:(Ljava/awt/LayoutManager;)V
        34: new           #34                 // class javax/swing/JPanel
        37: dup
        38: invokespecial #36                 // Method javax/swing/JPanel."<init>":()V
        41: astore_1
        42: aload_1
        43: new           #37                 // class java/awt/FlowLayout
        46: dup
        47: iconst_1
        48: bipush        10
        50: bipush        10
        52: invokespecial #39                 // Method java/awt/FlowLayout."<init>":(III)V
        55: invokevirtual #42                 // Method javax/swing/JPanel.setLayout:(Ljava/awt/LayoutManager;)V
        58: new           #43                 // class javax/swing/JLabel
        61: dup
        62: ldc           #45                 // String Item Name:
        64: invokespecial #47                 // Method javax/swing/JLabel."<init>":(Ljava/lang/String;)V
        67: astore_2
        68: new           #48                 // class javax/swing/JTextField
        71: dup
        72: bipush        20
        74: invokespecial #50                 // Method javax/swing/JTextField."<init>":(I)V
        77: astore_3
        78: new           #53                 // class javax/swing/JButton
        81: dup
        82: ldc           #55                 // String Search
        84: invokespecial #57                 // Method javax/swing/JButton."<init>":(Ljava/lang/String;)V
        87: astore        4
        89: aload_1
        90: aload_2
        91: invokevirtual #58                 // Method javax/swing/JPanel.add:(Ljava/awt/Component;)Ljava/awt/Component;
        94: pop
        95: aload_1
        96: aload_3
        97: invokevirtual #58                 // Method javax/swing/JPanel.add:(Ljava/awt/Component;)Ljava/awt/Component;
       100: pop
       101: aload_1
       102: aload         4
       104: invokevirtual #58                 // Method javax/swing/JPanel.add:(Ljava/awt/Component;)Ljava/awt/Component;
       107: pop
       108: aload_0
       109: aload_1
       110: ldc           #62                 // String North
       112: invokevirtual #64                 // Method add:(Ljava/awt/Component;Ljava/lang/Object;)V
       115: new           #67                 // class javax/swing/JTable
       118: dup
       119: invokespecial #69                 // Method javax/swing/JTable."<init>":()V
       122: astore        5
       124: new           #70                 // class javax/swing/table/DefaultTableModel
       127: dup
       128: iconst_2
       129: anewarray     #72                 // class java/lang/String
       132: dup
       133: iconst_0
       134: ldc           #74                 // String Item ID
       136: aastore
       137: dup
       138: iconst_1
       139: ldc           #76                 // String Item Name
       141: aastore
       142: iconst_0
       143: invokespecial #78                 // Method javax/swing/table/DefaultTableModel."<init>":([Ljava/lang/Object;I)V
       146: astore        6
       148: aload         5
       150: aload         6
       152: invokevirtual #81                 // Method javax/swing/JTable.setModel:(Ljavax/swing/table/TableModel;)V
       155: new           #85                 // class javax/swing/JScrollPane
       158: dup
       159: aload         5
       161: invokespecial #87                 // Method javax/swing/JScrollPane."<init>":(Ljava/awt/Component;)V
       164: astore        7
       166: aload         7
       168: new           #90                 // class java/awt/Dimension
       171: dup
       172: sipush        580
       175: sipush        200
       178: invokespecial #92                 // Method java/awt/Dimension."<init>":(II)V
       181: invokevirtual #94                 // Method javax/swing/JScrollPane.setPreferredSize:(Ljava/awt/Dimension;)V
       184: aload_0
       185: aload         7
       187: ldc           #98                 // String Center
       189: invokevirtual #64                 // Method add:(Ljava/awt/Component;Ljava/lang/Object;)V
       192: aload_0
       193: astore        8
       195: aload         4
       197: aload_3
       198: aload         8
       200: aload         6
       202: invokedynamic #100,  0            // InvokeDynamic #0:actionPerformed:(Ljavax/swing/JTextField;Ljavax/swing/JFrame;Ljavax/swing/table/DefaultTableModel;)Ljava/awt/event/ActionListener;
       207: invokevirtual #104                // Method javax/swing/JButton.addActionListener:(Ljava/awt/event/ActionListener;)V
       210: aload_0
       211: aconst_null
       212: invokevirtual #108                // Method setLocationRelativeTo:(Ljava/awt/Component;)V
       215: return
      LineNumberTable:
        line 42: 0
        line 43: 6
        line 44: 13
        line 45: 23
        line 47: 34
        line 48: 42
        line 50: 58
        line 51: 68
        line 52: 78
        line 54: 89
        line 55: 95
        line 56: 101
        line 58: 108
        line 60: 115
        line 61: 124
        line 64: 148
        line 66: 155
        line 67: 166
        line 69: 184
        line 71: 192
        line 72: 195
        line 90: 210
        line 91: 215
      LocalVariableTable:
        Start  Length  Slot  Name   Signature
            0     216     0  this   Lext/mods/commons/gui/tools/SearchItemFrame;
           42     174     1 itemSearchPanel   Ljavax/swing/JPanel;
           68     148     2 lblItemName   Ljavax/swing/JLabel;
           78     138     3 txtItemName   Ljavax/swing/JTextField;
           89     127     4 btnItemSearch   Ljavax/swing/JButton;
          124      92     5 itemTable   Ljavax/swing/JTable;
          148      68     6 itemModel   Ljavax/swing/table/DefaultTableModel;
          166      50     7 itemScrollPane   Ljavax/swing/JScrollPane;
          195      21     8 thisFrame   Ljavax/swing/JFrame;
}
SourceFile: "SearchItemFrame.java"
BootstrapMethods:
  0: #232 REF_invokeStatic java/lang/invoke/LambdaMetafactory.metafactory:(Ljava/lang/invoke/MethodHandles$Lookup;Ljava/lang/String;Ljava/lang/invoke/MethodType;Ljava/lang/invoke/MethodType;Ljava/lang/invoke/MethodHandle;Ljava/lang/invoke/MethodType;)Ljava/lang/invoke/CallSite;
    Method arguments:
      #227 (Ljava/awt/event/ActionEvent;)V
      #229 REF_invokeStatic ext/mods/commons/gui/tools/SearchItemFrame.lambda$new$0:(Ljavax/swing/JTextField;Ljavax/swing/JFrame;Ljavax/swing/table/DefaultTableModel;Ljava/awt/event/ActionEvent;)V
      #227 (Ljava/awt/event/ActionEvent;)V
InnerClasses:
  public static final #244= #240 of #242; // Lookup=class java/lang/invoke/MethodHandles$Lookup of class java/lang/invoke/MethodHandles
