// Bytecode for: ext.mods.commons.gui.InterfaceGS
// File: ext\mods\commons\gui\InterfaceGS.class

Classfile /c:/Users/User/Desktop/BrProject/bin/main/ext/mods/commons/gui/InterfaceGS.class
  Last modified 9 de jul de 2026; size 17383 bytes
  MD5 checksum 73ef9d1c634864f1a193a08fe7632fe1
  Compiled from "InterfaceGS.java"
public class ext.mods.commons.gui.InterfaceGS
  minor version: 0
  major version: 69
  flags: (0x0021) ACC_PUBLIC, ACC_SUPER
  this_class: #13                         // ext/mods/commons/gui/InterfaceGS
  super_class: #2                         // java/lang/Object
  interfaces: 0, fields: 10, methods: 36, attributes: 4
Constant pool:
    #1 = Methodref          #2.#3         // java/lang/Object."<init>":()V
    #2 = Class              #4            // java/lang/Object
    #3 = NameAndType        #5:#6         // "<init>":()V
    #4 = Utf8               java/lang/Object
    #5 = Utf8               <init>
    #6 = Utf8               ()V
    #7 = Methodref          #8.#9         // ext/mods/commons/gui/ThemeManager.applyTheme:()V
    #8 = Class              #10           // ext/mods/commons/gui/ThemeManager
    #9 = NameAndType        #11:#6        // applyTheme:()V
   #10 = Utf8               ext/mods/commons/gui/ThemeManager
   #11 = Utf8               applyTheme
   #12 = Methodref          #13.#14       // ext/mods/commons/gui/InterfaceGS.initialize:()V
   #13 = Class              #15           // ext/mods/commons/gui/InterfaceGS
   #14 = NameAndType        #16:#6        // initialize:()V
   #15 = Utf8               ext/mods/commons/gui/InterfaceGS
   #16 = Utf8               initialize
   #17 = Class              #18           // javax/swing/JTextArea
   #18 = Utf8               javax/swing/JTextArea
   #19 = Methodref          #17.#3        // javax/swing/JTextArea."<init>":()V
   #20 = Fieldref           #13.#21       // ext/mods/commons/gui/InterfaceGS.console:Ljavax/swing/JTextArea;
   #21 = NameAndType        #22:#23       // console:Ljavax/swing/JTextArea;
   #22 = Utf8               console
   #23 = Utf8               Ljavax/swing/JTextArea;
   #24 = Methodref          #17.#25       // javax/swing/JTextArea.setEditable:(Z)V
   #25 = NameAndType        #26:#27       // setEditable:(Z)V
   #26 = Utf8               setEditable
   #27 = Utf8               (Z)V
   #28 = Methodref          #17.#29       // javax/swing/JTextArea.setLineWrap:(Z)V
   #29 = NameAndType        #30:#27       // setLineWrap:(Z)V
   #30 = Utf8               setLineWrap
   #31 = Methodref          #17.#32       // javax/swing/JTextArea.setWrapStyleWord:(Z)V
   #32 = NameAndType        #33:#27       // setWrapStyleWord:(Z)V
   #33 = Utf8               setWrapStyleWord
   #34 = Fieldref           #35.#36       // javax/swing/DropMode.INSERT:Ljavax/swing/DropMode;
   #35 = Class              #37           // javax/swing/DropMode
   #36 = NameAndType        #38:#39       // INSERT:Ljavax/swing/DropMode;
   #37 = Utf8               javax/swing/DropMode
   #38 = Utf8               INSERT
   #39 = Utf8               Ljavax/swing/DropMode;
   #40 = Methodref          #17.#41       // javax/swing/JTextArea.setDropMode:(Ljavax/swing/DropMode;)V
   #41 = NameAndType        #42:#43       // setDropMode:(Ljavax/swing/DropMode;)V
   #42 = Utf8               setDropMode
   #43 = Utf8               (Ljavax/swing/DropMode;)V
   #44 = Class              #45           // java/awt/Font
   #45 = Utf8               java/awt/Font
   #46 = String             #47           // Monospaced
   #47 = Utf8               Monospaced
   #48 = Methodref          #44.#49       // java/awt/Font."<init>":(Ljava/lang/String;II)V
   #49 = NameAndType        #5:#50        // "<init>":(Ljava/lang/String;II)V
   #50 = Utf8               (Ljava/lang/String;II)V
   #51 = Methodref          #17.#52       // javax/swing/JTextArea.setFont:(Ljava/awt/Font;)V
   #52 = NameAndType        #53:#54       // setFont:(Ljava/awt/Font;)V
   #53 = Utf8               setFont
   #54 = Utf8               (Ljava/awt/Font;)V
   #55 = Methodref          #17.#56       // javax/swing/JTextArea.getDocument:()Ljavax/swing/text/Document;
   #56 = NameAndType        #57:#58       // getDocument:()Ljavax/swing/text/Document;
   #57 = Utf8               getDocument
   #58 = Utf8               ()Ljavax/swing/text/Document;
   #59 = Class              #60           // ext/mods/commons/gui/InterfaceLimit
   #60 = Utf8               ext/mods/commons/gui/InterfaceLimit
   #61 = Methodref          #59.#62       // ext/mods/commons/gui/InterfaceLimit."<init>":(I)V
   #62 = NameAndType        #5:#63        // "<init>":(I)V
   #63 = Utf8               (I)V
   #64 = InterfaceMethodref #65.#66       // javax/swing/text/Document.addDocumentListener:(Ljavax/swing/event/DocumentListener;)V
   #65 = Class              #67           // javax/swing/text/Document
   #66 = NameAndType        #68:#69       // addDocumentListener:(Ljavax/swing/event/DocumentListener;)V
   #67 = Utf8               javax/swing/text/Document
   #68 = Utf8               addDocumentListener
   #69 = Utf8               (Ljavax/swing/event/DocumentListener;)V
   #70 = Fieldref           #8.#71        // ext/mods/commons/gui/ThemeManager.COMPONENT_BACKGROUND:Ljava/awt/Color;
   #71 = NameAndType        #72:#73       // COMPONENT_BACKGROUND:Ljava/awt/Color;
   #72 = Utf8               COMPONENT_BACKGROUND
   #73 = Utf8               Ljava/awt/Color;
   #74 = Methodref          #17.#75       // javax/swing/JTextArea.setBackground:(Ljava/awt/Color;)V
   #75 = NameAndType        #76:#77       // setBackground:(Ljava/awt/Color;)V
   #76 = Utf8               setBackground
   #77 = Utf8               (Ljava/awt/Color;)V
   #78 = Fieldref           #8.#79        // ext/mods/commons/gui/ThemeManager.TEXT_COLOR:Ljava/awt/Color;
   #79 = NameAndType        #80:#73       // TEXT_COLOR:Ljava/awt/Color;
   #80 = Utf8               TEXT_COLOR
   #81 = Methodref          #17.#82       // javax/swing/JTextArea.setForeground:(Ljava/awt/Color;)V
   #82 = NameAndType        #83:#77       // setForeground:(Ljava/awt/Color;)V
   #83 = Utf8               setForeground
   #84 = String             #85           // ./config/geoengine.properties
   #85 = Utf8               ./config/geoengine.properties
   #86 = Methodref          #87.#88       // ext/mods/commons/gui/GuiUtils.loadProperties:(Ljava/lang/String;)Ljava/util/Properties;
   #87 = Class              #89           // ext/mods/commons/gui/GuiUtils
   #88 = NameAndType        #90:#91       // loadProperties:(Ljava/lang/String;)Ljava/util/Properties;
   #89 = Utf8               ext/mods/commons/gui/GuiUtils
   #90 = Utf8               loadProperties
   #91 = Utf8               (Ljava/lang/String;)Ljava/util/Properties;
   #92 = String             #93           // ./config/server.properties
   #93 = Utf8               ./config/server.properties
   #94 = String             #95           // UseMinimalGeoOnly
   #95 = Utf8               UseMinimalGeoOnly
   #96 = String             #97           // false
   #97 = Utf8               false
   #98 = Methodref          #99.#100      // java/util/Properties.getProperty:(Ljava/lang/String;Ljava/lang/String;)Ljava/lang/String;
   #99 = Class              #101          // java/util/Properties
  #100 = NameAndType        #102:#103     // getProperty:(Ljava/lang/String;Ljava/lang/String;)Ljava/lang/String;
  #101 = Utf8               java/util/Properties
  #102 = Utf8               getProperty
  #103 = Utf8               (Ljava/lang/String;Ljava/lang/String;)Ljava/lang/String;
  #104 = Methodref          #105.#106     // java/lang/Boolean.parseBoolean:(Ljava/lang/String;)Z
  #105 = Class              #107          // java/lang/Boolean
  #106 = NameAndType        #108:#109     // parseBoolean:(Ljava/lang/String;)Z
  #107 = Utf8               java/lang/Boolean
  #108 = Utf8               parseBoolean
  #109 = Utf8               (Ljava/lang/String;)Z
  #110 = String             #111          // Developer
  #111 = Utf8               Developer
  #112 = String             #113          // World
  #113 = Utf8               World
  #114 = String             #115          // World - Light/Developer Mode
  #115 = Utf8               World - Light/Developer Mode
  #116 = String             #117          // World - Light Mode
  #117 = Utf8               World - Light Mode
  #118 = String             #119          // World - Developer Mode
  #119 = Utf8               World - Developer Mode
  #120 = Class              #121          // javax/swing/JFrame
  #121 = Utf8               javax/swing/JFrame
  #122 = Methodref          #120.#123     // javax/swing/JFrame."<init>":(Ljava/lang/String;)V
  #123 = NameAndType        #5:#124       // "<init>":(Ljava/lang/String;)V
  #124 = Utf8               (Ljava/lang/String;)V
  #125 = Fieldref           #13.#126      // ext/mods/commons/gui/InterfaceGS.frame:Ljavax/swing/JFrame;
  #126 = NameAndType        #127:#128     // frame:Ljavax/swing/JFrame;
  #127 = Utf8               frame
  #128 = Utf8               Ljavax/swing/JFrame;
  #129 = Methodref          #120.#130     // javax/swing/JFrame.setUndecorated:(Z)V
  #130 = NameAndType        #131:#27      // setUndecorated:(Z)V
  #131 = Utf8               setUndecorated
  #132 = Class              #133          // ext/mods/commons/gui/ComponentResizer
  #133 = Utf8               ext/mods/commons/gui/ComponentResizer
  #134 = Methodref          #132.#135     // ext/mods/commons/gui/ComponentResizer."<init>":(Ljava/awt/Window;)V
  #135 = NameAndType        #5:#136       // "<init>":(Ljava/awt/Window;)V
  #136 = Utf8               (Ljava/awt/Window;)V
  #137 = Methodref          #13.#138      // ext/mods/commons/gui/InterfaceGS.createMenuBar:()Ljavax/swing/JMenuBar;
  #138 = NameAndType        #139:#140     // createMenuBar:()Ljavax/swing/JMenuBar;
  #139 = Utf8               createMenuBar
  #140 = Utf8               ()Ljavax/swing/JMenuBar;
  #141 = InvokeDynamic      #0:#142       // #0:run:(Lext/mods/commons/gui/InterfaceGS;)Ljava/lang/Runnable;
  #142 = NameAndType        #143:#144     // run:(Lext/mods/commons/gui/InterfaceGS;)Ljava/lang/Runnable;
  #143 = Utf8               run
  #144 = Utf8               (Lext/mods/commons/gui/InterfaceGS;)Ljava/lang/Runnable;
  #145 = Fieldref           #146.#147     // java/io/File.separator:Ljava/lang/String;
  #146 = Class              #148          // java/io/File
  #147 = NameAndType        #149:#150     // separator:Ljava/lang/String;
  #148 = Utf8               java/io/File
  #149 = Utf8               separator
  #150 = Utf8               Ljava/lang/String;
  #151 = InvokeDynamic      #1:#152       // #1:makeConcatWithConstants:(Ljava/lang/String;Ljava/lang/String;)Ljava/lang/String;
  #152 = NameAndType        #153:#103     // makeConcatWithConstants:(Ljava/lang/String;Ljava/lang/String;)Ljava/lang/String;
  #153 = Utf8               makeConcatWithConstants
  #154 = Class              #155          // ext/mods/commons/gui/CustomTopPanel
  #155 = Utf8               ext/mods/commons/gui/CustomTopPanel
  #156 = Methodref          #154.#157     // ext/mods/commons/gui/CustomTopPanel."<init>":(Ljavax/swing/JFrame;Ljavax/swing/JMenuBar;Ljava/lang/Runnable;ZLjava/lang/String;)V
  #157 = NameAndType        #5:#158       // "<init>":(Ljavax/swing/JFrame;Ljavax/swing/JMenuBar;Ljava/lang/Runnable;ZLjava/lang/String;)V
  #158 = Utf8               (Ljavax/swing/JFrame;Ljavax/swing/JMenuBar;Ljava/lang/Runnable;ZLjava/lang/String;)V
  #159 = Fieldref           #13.#160      // ext/mods/commons/gui/InterfaceGS.topPanel:Lext/mods/commons/gui/CustomTopPanel;
  #160 = NameAndType        #161:#162     // topPanel:Lext/mods/commons/gui/CustomTopPanel;
  #161 = Utf8               topPanel
  #162 = Utf8               Lext/mods/commons/gui/CustomTopPanel;
  #163 = Class              #164          // javax/swing/JPanel
  #164 = Utf8               javax/swing/JPanel
  #165 = Class              #166          // java/awt/BorderLayout
  #166 = Utf8               java/awt/BorderLayout
  #167 = Methodref          #165.#3       // java/awt/BorderLayout."<init>":()V
  #168 = Methodref          #163.#169     // javax/swing/JPanel."<init>":(Ljava/awt/LayoutManager;)V
  #169 = NameAndType        #5:#170       // "<init>":(Ljava/awt/LayoutManager;)V
  #170 = Utf8               (Ljava/awt/LayoutManager;)V
  #171 = String             #172          // North
  #172 = Utf8               North
  #173 = Methodref          #163.#174     // javax/swing/JPanel.add:(Ljava/awt/Component;Ljava/lang/Object;)V
  #174 = NameAndType        #175:#176     // add:(Ljava/awt/Component;Ljava/lang/Object;)V
  #175 = Utf8               add
  #176 = Utf8               (Ljava/awt/Component;Ljava/lang/Object;)V
  #177 = Class              #178          // ext/mods/commons/gui/InterfaceGSInfo
  #178 = Utf8               ext/mods/commons/gui/InterfaceGSInfo
  #179 = Methodref          #177.#3       // ext/mods/commons/gui/InterfaceGSInfo."<init>":()V
  #180 = Fieldref           #13.#181      // ext/mods/commons/gui/InterfaceGS.systemPanel:Ljavax/swing/JPanel;
  #181 = NameAndType        #182:#183     // systemPanel:Ljavax/swing/JPanel;
  #182 = Utf8               systemPanel
  #183 = Utf8               Ljavax/swing/JPanel;
  #184 = Class              #185          // ext/mods/commons/gui/InterfaceCoroutinePoolMetrics
  #185 = Utf8               ext/mods/commons/gui/InterfaceCoroutinePoolMetrics
  #186 = Methodref          #184.#3       // ext/mods/commons/gui/InterfaceCoroutinePoolMetrics."<init>":()V
  #187 = Fieldref           #13.#188      // ext/mods/commons/gui/InterfaceGS.metricsPanel:Ljavax/swing/JPanel;
  #188 = NameAndType        #189:#183     // metricsPanel:Ljavax/swing/JPanel;
  #189 = Utf8               metricsPanel
  #190 = Class              #191          // javax/swing/JScrollPane
  #191 = Utf8               javax/swing/JScrollPane
  #192 = Methodref          #190.#193     // javax/swing/JScrollPane."<init>":(Ljava/awt/Component;)V
  #193 = NameAndType        #5:#194       // "<init>":(Ljava/awt/Component;)V
  #194 = Utf8               (Ljava/awt/Component;)V
  #195 = Fieldref           #13.#196      // ext/mods/commons/gui/InterfaceGS.scrollPanel:Ljavax/swing/JScrollPane;
  #196 = NameAndType        #197:#198     // scrollPanel:Ljavax/swing/JScrollPane;
  #197 = Utf8               scrollPanel
  #198 = Utf8               Ljavax/swing/JScrollPane;
  #199 = Methodref          #190.#200     // javax/swing/JScrollPane.setBorder:(Ljavax/swing/border/Border;)V
  #200 = NameAndType        #201:#202     // setBorder:(Ljavax/swing/border/Border;)V
  #201 = Utf8               setBorder
  #202 = Utf8               (Ljavax/swing/border/Border;)V
  #203 = Methodref          #190.#204     // javax/swing/JScrollPane.getViewport:()Ljavax/swing/JViewport;
  #204 = NameAndType        #205:#206     // getViewport:()Ljavax/swing/JViewport;
  #205 = Utf8               getViewport
  #206 = Utf8               ()Ljavax/swing/JViewport;
  #207 = Methodref          #208.#75      // javax/swing/JViewport.setBackground:(Ljava/awt/Color;)V
  #208 = Class              #209          // javax/swing/JViewport
  #209 = Utf8               javax/swing/JViewport
  #210 = Methodref          #190.#211     // javax/swing/JScrollPane.getVerticalScrollBar:()Ljavax/swing/JScrollBar;
  #211 = NameAndType        #212:#213     // getVerticalScrollBar:()Ljavax/swing/JScrollBar;
  #212 = Utf8               getVerticalScrollBar
  #213 = Utf8               ()Ljavax/swing/JScrollBar;
  #214 = Class              #215          // ext/mods/commons/gui/ModernUI$ModernScrollBarUI
  #215 = Utf8               ext/mods/commons/gui/ModernUI$ModernScrollBarUI
  #216 = Methodref          #214.#3       // ext/mods/commons/gui/ModernUI$ModernScrollBarUI."<init>":()V
  #217 = Methodref          #218.#219     // javax/swing/JScrollBar.setUI:(Ljavax/swing/plaf/ScrollBarUI;)V
  #218 = Class              #220          // javax/swing/JScrollBar
  #219 = NameAndType        #221:#222     // setUI:(Ljavax/swing/plaf/ScrollBarUI;)V
  #220 = Utf8               javax/swing/JScrollBar
  #221 = Utf8               setUI
  #222 = Utf8               (Ljavax/swing/plaf/ScrollBarUI;)V
  #223 = Class              #224          // java/awt/Dimension
  #224 = Utf8               java/awt/Dimension
  #225 = Methodref          #223.#226     // java/awt/Dimension."<init>":(II)V
  #226 = NameAndType        #5:#227       // "<init>":(II)V
  #227 = Utf8               (II)V
  #228 = Methodref          #218.#229     // javax/swing/JScrollBar.setPreferredSize:(Ljava/awt/Dimension;)V
  #229 = NameAndType        #230:#231     // setPreferredSize:(Ljava/awt/Dimension;)V
  #230 = Utf8               setPreferredSize
  #231 = Utf8               (Ljava/awt/Dimension;)V
  #232 = Methodref          #218.#233     // javax/swing/JScrollBar.setUnitIncrement:(I)V
  #233 = NameAndType        #234:#63      // setUnitIncrement:(I)V
  #234 = Utf8               setUnitIncrement
  #235 = Class              #236          // javax/swing/JLayeredPane
  #236 = Utf8               javax/swing/JLayeredPane
  #237 = Methodref          #235.#3       // javax/swing/JLayeredPane."<init>":()V
  #238 = Fieldref           #13.#239      // ext/mods/commons/gui/InterfaceGS.layeredPanel:Ljavax/swing/JLayeredPane;
  #239 = NameAndType        #240:#241     // layeredPanel:Ljavax/swing/JLayeredPane;
  #240 = Utf8               layeredPanel
  #241 = Utf8               Ljavax/swing/JLayeredPane;
  #242 = Methodref          #243.#244     // java/lang/Integer.valueOf:(I)Ljava/lang/Integer;
  #243 = Class              #245          // java/lang/Integer
  #244 = NameAndType        #246:#247     // valueOf:(I)Ljava/lang/Integer;
  #245 = Utf8               java/lang/Integer
  #246 = Utf8               valueOf
  #247 = Utf8               (I)Ljava/lang/Integer;
  #248 = Methodref          #235.#174     // javax/swing/JLayeredPane.add:(Ljava/awt/Component;Ljava/lang/Object;)V
  #249 = String             #250          // Center
  #250 = Utf8               Center
  #251 = Methodref          #120.#252     // javax/swing/JFrame.getContentPane:()Ljava/awt/Container;
  #252 = NameAndType        #253:#254     // getContentPane:()Ljava/awt/Container;
  #253 = Utf8               getContentPane
  #254 = Utf8               ()Ljava/awt/Container;
  #255 = Methodref          #256.#257     // java/awt/Container.add:(Ljava/awt/Component;)Ljava/awt/Component;
  #256 = Class              #258          // java/awt/Container
  #257 = NameAndType        #175:#259     // add:(Ljava/awt/Component;)Ljava/awt/Component;
  #258 = Utf8               java/awt/Container
  #259 = Utf8               (Ljava/awt/Component;)Ljava/awt/Component;
  #260 = Class              #261          // java/awt/Component
  #261 = Utf8               java/awt/Component
  #262 = Methodref          #132.#263     // ext/mods/commons/gui/ComponentResizer.registerComponent:([Ljava/awt/Component;)V
  #263 = NameAndType        #264:#265     // registerComponent:([Ljava/awt/Component;)V
  #264 = Utf8               registerComponent
  #265 = Utf8               ([Ljava/awt/Component;)V
  #266 = Class              #267          // ext/mods/commons/gui/InterfaceGS$1
  #267 = Utf8               ext/mods/commons/gui/InterfaceGS$1
  #268 = Methodref          #266.#269     // ext/mods/commons/gui/InterfaceGS$1."<init>":(Lext/mods/commons/gui/InterfaceGS;)V
  #269 = NameAndType        #5:#270       // "<init>":(Lext/mods/commons/gui/InterfaceGS;)V
  #270 = Utf8               (Lext/mods/commons/gui/InterfaceGS;)V
  #271 = Methodref          #120.#272     // javax/swing/JFrame.addWindowStateListener:(Ljava/awt/event/WindowStateListener;)V
  #272 = NameAndType        #273:#274     // addWindowStateListener:(Ljava/awt/event/WindowStateListener;)V
  #273 = Utf8               addWindowStateListener
  #274 = Utf8               (Ljava/awt/event/WindowStateListener;)V
  #275 = Class              #276          // ext/mods/commons/gui/InterfaceGS$2
  #276 = Utf8               ext/mods/commons/gui/InterfaceGS$2
  #277 = Methodref          #275.#269     // ext/mods/commons/gui/InterfaceGS$2."<init>":(Lext/mods/commons/gui/InterfaceGS;)V
  #278 = Methodref          #120.#279     // javax/swing/JFrame.addComponentListener:(Ljava/awt/event/ComponentListener;)V
  #279 = NameAndType        #280:#281     // addComponentListener:(Ljava/awt/event/ComponentListener;)V
  #280 = Utf8               addComponentListener
  #281 = Utf8               (Ljava/awt/event/ComponentListener;)V
  #282 = Class              #283          // javax/swing/WindowConstants
  #283 = Utf8               javax/swing/WindowConstants
  #284 = Methodref          #120.#285     // javax/swing/JFrame.setDefaultCloseOperation:(I)V
  #285 = NameAndType        #286:#63      // setDefaultCloseOperation:(I)V
  #286 = Utf8               setDefaultCloseOperation
  #287 = Class              #288          // ext/mods/commons/gui/InterfaceGS$3
  #288 = Utf8               ext/mods/commons/gui/InterfaceGS$3
  #289 = Methodref          #287.#269     // ext/mods/commons/gui/InterfaceGS$3."<init>":(Lext/mods/commons/gui/InterfaceGS;)V
  #290 = Methodref          #120.#291     // javax/swing/JFrame.addWindowListener:(Ljava/awt/event/WindowListener;)V
  #291 = NameAndType        #292:#293     // addWindowListener:(Ljava/awt/event/WindowListener;)V
  #292 = Utf8               addWindowListener
  #293 = Utf8               (Ljava/awt/event/WindowListener;)V
  #294 = Methodref          #87.#295      // ext/mods/commons/gui/GuiUtils.loadIcons:()Ljava/util/List;
  #295 = NameAndType        #296:#297     // loadIcons:()Ljava/util/List;
  #296 = Utf8               loadIcons
  #297 = Utf8               ()Ljava/util/List;
  #298 = Methodref          #120.#299     // javax/swing/JFrame.setIconImages:(Ljava/util/List;)V
  #299 = NameAndType        #300:#301     // setIconImages:(Ljava/util/List;)V
  #300 = Utf8               setIconImages
  #301 = Utf8               (Ljava/util/List;)V
  #302 = Methodref          #120.#303     // javax/swing/JFrame.setSize:(II)V
  #303 = NameAndType        #304:#227     // setSize:(II)V
  #304 = Utf8               setSize
  #305 = Methodref          #120.#306     // javax/swing/JFrame.setLocationRelativeTo:(Ljava/awt/Component;)V
  #306 = NameAndType        #307:#194     // setLocationRelativeTo:(Ljava/awt/Component;)V
  #307 = Utf8               setLocationRelativeTo
  #308 = Methodref          #13.#309      // ext/mods/commons/gui/InterfaceGS.redirectSystemStreams:()V
  #309 = NameAndType        #310:#6       // redirectSystemStreams:()V
  #310 = Utf8               redirectSystemStreams
  #311 = Methodref          #120.#312     // javax/swing/JFrame.setVisible:(Z)V
  #312 = NameAndType        #313:#27      // setVisible:(Z)V
  #313 = Utf8               setVisible
  #314 = InvokeDynamic      #2:#142       // #2:run:(Lext/mods/commons/gui/InterfaceGS;)Ljava/lang/Runnable;
  #315 = Methodref          #316.#317     // javax/swing/SwingUtilities.invokeLater:(Ljava/lang/Runnable;)V
  #316 = Class              #318          // javax/swing/SwingUtilities
  #317 = NameAndType        #319:#320     // invokeLater:(Ljava/lang/Runnable;)V
  #318 = Utf8               javax/swing/SwingUtilities
  #319 = Utf8               invokeLater
  #320 = Utf8               (Ljava/lang/Runnable;)V
  #321 = Class              #322          // javax/swing/JMenuBar
  #322 = Utf8               javax/swing/JMenuBar
  #323 = Methodref          #321.#3       // javax/swing/JMenuBar."<init>":()V
  #324 = Fieldref           #325.#326     // ext/mods/commons/gui/ModernUI.BG_DARK:Ljava/awt/Color;
  #325 = Class              #327          // ext/mods/commons/gui/ModernUI
  #326 = NameAndType        #328:#73      // BG_DARK:Ljava/awt/Color;
  #327 = Utf8               ext/mods/commons/gui/ModernUI
  #328 = Utf8               BG_DARK
  #329 = Methodref          #321.#75      // javax/swing/JMenuBar.setBackground:(Ljava/awt/Color;)V
  #330 = Methodref          #331.#332     // javax/swing/BorderFactory.createEmptyBorder:()Ljavax/swing/border/Border;
  #331 = Class              #333          // javax/swing/BorderFactory
  #332 = NameAndType        #334:#335     // createEmptyBorder:()Ljavax/swing/border/Border;
  #333 = Utf8               javax/swing/BorderFactory
  #334 = Utf8               createEmptyBorder
  #335 = Utf8               ()Ljavax/swing/border/Border;
  #336 = Methodref          #321.#200     // javax/swing/JMenuBar.setBorder:(Ljavax/swing/border/Border;)V
  #337 = String             #338          // Game
  #338 = Utf8               Game
  #339 = Methodref          #13.#340      // ext/mods/commons/gui/InterfaceGS.createMenu:(Ljava/lang/String;I)Ljavax/swing/JMenu;
  #340 = NameAndType        #341:#342     // createMenu:(Ljava/lang/String;I)Ljavax/swing/JMenu;
  #341 = Utf8               createMenu
  #342 = Utf8               (Ljava/lang/String;I)Ljavax/swing/JMenu;
  #343 = String             #344          // Shutdown
  #344 = Utf8               Shutdown
  #345 = InvokeDynamic      #3:#346       // #3:actionPerformed:(Lext/mods/commons/gui/InterfaceGS;)Ljava/awt/event/ActionListener;
  #346 = NameAndType        #347:#348     // actionPerformed:(Lext/mods/commons/gui/InterfaceGS;)Ljava/awt/event/ActionListener;
  #347 = Utf8               actionPerformed
  #348 = Utf8               (Lext/mods/commons/gui/InterfaceGS;)Ljava/awt/event/ActionListener;
  #349 = Methodref          #13.#350      // ext/mods/commons/gui/InterfaceGS.createMenuItem:(Ljava/lang/String;ILjava/awt/event/ActionListener;)Ljavax/swing/JMenuItem;
  #350 = NameAndType        #351:#352     // createMenuItem:(Ljava/lang/String;ILjava/awt/event/ActionListener;)Ljavax/swing/JMenuItem;
  #351 = Utf8               createMenuItem
  #352 = Utf8               (Ljava/lang/String;ILjava/awt/event/ActionListener;)Ljavax/swing/JMenuItem;
  #353 = Methodref          #354.#355     // javax/swing/JMenu.add:(Ljavax/swing/JMenuItem;)Ljavax/swing/JMenuItem;
  #354 = Class              #356          // javax/swing/JMenu
  #355 = NameAndType        #175:#357     // add:(Ljavax/swing/JMenuItem;)Ljavax/swing/JMenuItem;
  #356 = Utf8               javax/swing/JMenu
  #357 = Utf8               (Ljavax/swing/JMenuItem;)Ljavax/swing/JMenuItem;
  #358 = String             #359          // Restart
  #359 = Utf8               Restart
  #360 = InvokeDynamic      #4:#346       // #4:actionPerformed:(Lext/mods/commons/gui/InterfaceGS;)Ljava/awt/event/ActionListener;
  #361 = String             #362          // Abort
  #362 = Utf8               Abort
  #363 = InvokeDynamic      #5:#346       // #5:actionPerformed:(Lext/mods/commons/gui/InterfaceGS;)Ljava/awt/event/ActionListener;
  #364 = String             #365          // Administrator
  #365 = Utf8               Administrator
  #366 = String             #367          // Change Access
  #367 = Utf8               Change Access
  #368 = InvokeDynamic      #6:#346       // #6:actionPerformed:(Lext/mods/commons/gui/InterfaceGS;)Ljava/awt/event/ActionListener;
  #369 = String             #370          // Search Item
  #370 = Utf8               Search Item
  #371 = InvokeDynamic      #7:#372       // #7:actionPerformed:()Ljava/awt/event/ActionListener;
  #372 = NameAndType        #347:#373     // actionPerformed:()Ljava/awt/event/ActionListener;
  #373 = Utf8               ()Ljava/awt/event/ActionListener;
  #374 = String             #375          // Players
  #375 = Utf8               Players
  #376 = String             #377          // Repair Player
  #377 = Utf8               Repair Player
  #378 = InvokeDynamic      #8:#346       // #8:actionPerformed:(Lext/mods/commons/gui/InterfaceGS;)Ljava/awt/event/ActionListener;
  #379 = String             #380          // Create Item
  #380 = Utf8               Create Item
  #381 = InvokeDynamic      #9:#346       // #9:actionPerformed:(Lext/mods/commons/gui/InterfaceGS;)Ljava/awt/event/ActionListener;
  #382 = String             #383          // Balance
  #383 = Utf8               Balance
  #384 = String             #385          // Damage
  #385 = Utf8               Damage
  #386 = InvokeDynamic      #10:#372      // #10:actionPerformed:()Ljava/awt/event/ActionListener;
  #387 = String             #388          // Defence
  #388 = Utf8               Defence
  #389 = InvokeDynamic      #11:#372      // #11:actionPerformed:()Ljava/awt/event/ActionListener;
  #390 = String             #391          // Vulnerability
  #391 = Utf8               Vulnerability
  #392 = InvokeDynamic      #12:#372      // #12:actionPerformed:()Ljava/awt/event/ActionListener;
  #393 = String             #394          // Announce
  #394 = Utf8               Announce
  #395 = String             #396          // Normal
  #396 = Utf8               Normal
  #397 = InvokeDynamic      #13:#346      // #13:actionPerformed:(Lext/mods/commons/gui/InterfaceGS;)Ljava/awt/event/ActionListener;
  #398 = String             #399          // Critical
  #399 = Utf8               Critical
  #400 = InvokeDynamic      #14:#346      // #14:actionPerformed:(Lext/mods/commons/gui/InterfaceGS;)Ljava/awt/event/ActionListener;
  #401 = String             #402          // Tools
  #402 = Utf8               Tools
  #403 = String             #404          // Multisell Creator
  #404 = Utf8               Multisell Creator
  #405 = InvokeDynamic      #15:#346      // #15:actionPerformed:(Lext/mods/commons/gui/InterfaceGS;)Ljava/awt/event/ActionListener;
  #406 = String             #407          // Item Creator
  #407 = Utf8               Item Creator
  #408 = InvokeDynamic      #16:#346      // #16:actionPerformed:(Lext/mods/commons/gui/InterfaceGS;)Ljava/awt/event/ActionListener;
  #409 = String             #410          // Reload
  #410 = Utf8               Reload
  #411 = String             #412          // Access
  #412 = Utf8               Access
  #413 = InvokeDynamic      #17:#346      // #17:actionPerformed:(Lext/mods/commons/gui/InterfaceGS;)Ljava/awt/event/ActionListener;
  #414 = String             #415          // Buylists
  #415 = Utf8               Buylists
  #416 = InvokeDynamic      #18:#346      // #18:actionPerformed:(Lext/mods/commons/gui/InterfaceGS;)Ljava/awt/event/ActionListener;
  #417 = String             #418          // Configs
  #418 = Utf8               Configs
  #419 = InvokeDynamic      #19:#346      // #19:actionPerformed:(Lext/mods/commons/gui/InterfaceGS;)Ljava/awt/event/ActionListener;
  #420 = String             #421          // Farm Event
  #421 = Utf8               Farm Event
  #422 = InvokeDynamic      #20:#346      // #20:actionPerformed:(Lext/mods/commons/gui/InterfaceGS;)Ljava/awt/event/ActionListener;
  #423 = String             #424          // Items
  #424 = Utf8               Items
  #425 = InvokeDynamic      #21:#346      // #21:actionPerformed:(Lext/mods/commons/gui/InterfaceGS;)Ljava/awt/event/ActionListener;
  #426 = String             #427          // Multisells
  #427 = Utf8               Multisells
  #428 = InvokeDynamic      #22:#346      // #22:actionPerformed:(Lext/mods/commons/gui/InterfaceGS;)Ljava/awt/event/ActionListener;
  #429 = String             #430          // Skills
  #430 = Utf8               Skills
  #431 = InvokeDynamic      #23:#346      // #23:actionPerformed:(Lext/mods/commons/gui/InterfaceGS;)Ljava/awt/event/ActionListener;
  #432 = String             #433          // Zones
  #433 = Utf8               Zones
  #434 = InvokeDynamic      #24:#346      // #24:actionPerformed:(Lext/mods/commons/gui/InterfaceGS;)Ljava/awt/event/ActionListener;
  #435 = String             #436          // Font
  #436 = Utf8               Font
  #437 = Class              #438          // java/lang/String
  #438 = Utf8               java/lang/String
  #439 = String             #440          // 10
  #440 = Utf8               10
  #441 = String             #442          // 13
  #442 = Utf8               13
  #443 = String             #444          // 16
  #444 = Utf8               16
  #445 = String             #446          // 21
  #446 = Utf8               21
  #447 = String             #448          // 27
  #448 = Utf8               27
  #449 = String             #450          // 33
  #450 = Utf8               33
  #451 = InvokeDynamic      #25:#452      // #25:actionPerformed:(Lext/mods/commons/gui/InterfaceGS;Ljava/lang/String;)Ljava/awt/event/ActionListener;
  #452 = NameAndType        #347:#453     // actionPerformed:(Lext/mods/commons/gui/InterfaceGS;Ljava/lang/String;)Ljava/awt/event/ActionListener;
  #453 = Utf8               (Lext/mods/commons/gui/InterfaceGS;Ljava/lang/String;)Ljava/awt/event/ActionListener;
  #454 = String             #455          // Help
  #455 = Utf8               Help
  #456 = String             #457          // About
  #457 = Utf8               About
  #458 = InvokeDynamic      #26:#372      // #26:actionPerformed:()Ljava/awt/event/ActionListener;
  #459 = Methodref          #321.#460     // javax/swing/JMenuBar.add:(Ljavax/swing/JMenu;)Ljavax/swing/JMenu;
  #460 = NameAndType        #175:#461     // add:(Ljavax/swing/JMenu;)Ljavax/swing/JMenu;
  #461 = Utf8               (Ljavax/swing/JMenu;)Ljavax/swing/JMenu;
  #462 = Methodref          #354.#123     // javax/swing/JMenu."<init>":(Ljava/lang/String;)V
  #463 = String             #464          // Segoe UI
  #464 = Utf8               Segoe UI
  #465 = Methodref          #354.#52      // javax/swing/JMenu.setFont:(Ljava/awt/Font;)V
  #466 = Methodref          #354.#82      // javax/swing/JMenu.setForeground:(Ljava/awt/Color;)V
  #467 = Class              #468          // javax/swing/JMenuItem
  #468 = Utf8               javax/swing/JMenuItem
  #469 = Methodref          #467.#123     // javax/swing/JMenuItem."<init>":(Ljava/lang/String;)V
  #470 = Methodref          #467.#52      // javax/swing/JMenuItem.setFont:(Ljava/awt/Font;)V
  #471 = Fieldref           #8.#472       // ext/mods/commons/gui/ThemeManager.VERY_DARK_BACKGROUND:Ljava/awt/Color;
  #472 = NameAndType        #473:#73      // VERY_DARK_BACKGROUND:Ljava/awt/Color;
  #473 = Utf8               VERY_DARK_BACKGROUND
  #474 = Methodref          #467.#75      // javax/swing/JMenuItem.setBackground:(Ljava/awt/Color;)V
  #475 = Fieldref           #8.#476       // ext/mods/commons/gui/ThemeManager.TEXT_SELECTED:Ljava/awt/Color;
  #476 = NameAndType        #477:#73      // TEXT_SELECTED:Ljava/awt/Color;
  #477 = Utf8               TEXT_SELECTED
  #478 = Methodref          #467.#82      // javax/swing/JMenuItem.setForeground:(Ljava/awt/Color;)V
  #479 = Methodref          #467.#480     // javax/swing/JMenuItem.addActionListener:(Ljava/awt/event/ActionListener;)V
  #480 = NameAndType        #481:#482     // addActionListener:(Ljava/awt/event/ActionListener;)V
  #481 = Utf8               addActionListener
  #482 = Utf8               (Ljava/awt/event/ActionListener;)V
  #483 = String             #484          // true
  #484 = Utf8               true
  #485 = String             #486          // brproject.launcher.spawned
  #486 = Utf8               brproject.launcher.spawned
  #487 = Methodref          #488.#489     // java/lang/System.getProperty:(Ljava/lang/String;)Ljava/lang/String;
  #488 = Class              #490          // java/lang/System
  #489 = NameAndType        #102:#491     // getProperty:(Ljava/lang/String;)Ljava/lang/String;
  #490 = Utf8               java/lang/System
  #491 = Utf8               (Ljava/lang/String;)Ljava/lang/String;
  #492 = Methodref          #437.#493     // java/lang/String.equalsIgnoreCase:(Ljava/lang/String;)Z
  #493 = NameAndType        #494:#109     // equalsIgnoreCase:(Ljava/lang/String;)Z
  #494 = Utf8               equalsIgnoreCase
  #495 = Methodref          #496.#497     // java/lang/Runtime.getRuntime:()Ljava/lang/Runtime;
  #496 = Class              #498          // java/lang/Runtime
  #497 = NameAndType        #499:#500     // getRuntime:()Ljava/lang/Runtime;
  #498 = Utf8               java/lang/Runtime
  #499 = Utf8               getRuntime
  #500 = Utf8               ()Ljava/lang/Runtime;
  #501 = Methodref          #496.#502     // java/lang/Runtime.halt:(I)V
  #502 = NameAndType        #503:#63      // halt:(I)V
  #503 = Utf8               halt
  #504 = Methodref          #505.#506     // ext/mods/gameserver/LoginServerThread.getInstance:()Lext/mods/gameserver/LoginServerThread;
  #505 = Class              #507          // ext/mods/gameserver/LoginServerThread
  #506 = NameAndType        #508:#509     // getInstance:()Lext/mods/gameserver/LoginServerThread;
  #507 = Utf8               ext/mods/gameserver/LoginServerThread
  #508 = Utf8               getInstance
  #509 = Utf8               ()Lext/mods/gameserver/LoginServerThread;
  #510 = Methodref          #505.#511     // ext/mods/gameserver/LoginServerThread.getServerName:()Ljava/lang/String;
  #511 = NameAndType        #512:#513     // getServerName:()Ljava/lang/String;
  #512 = Utf8               getServerName
  #513 = Utf8               ()Ljava/lang/String;
  #514 = Methodref          #437.#515     // java/lang/String.isEmpty:()Z
  #515 = NameAndType        #516:#517     // isEmpty:()Z
  #516 = Utf8               isEmpty
  #517 = Utf8               ()Z
  #518 = Class              #519          // java/lang/Exception
  #519 = Utf8               java/lang/Exception
  #520 = String             #521          // Shutdown server immediately?
  #521 = Utf8               Shutdown server immediately?
  #522 = String             #523          // Select an option
  #523 = Utf8               Select an option
  #524 = Class              #525          // javax/swing/JOptionPane
  #525 = Utf8               javax/swing/JOptionPane
  #526 = Fieldref           #13.#527      // ext/mods/commons/gui/InterfaceGS.shutdownOptions:[Ljava/lang/String;
  #527 = NameAndType        #528:#529     // shutdownOptions:[Ljava/lang/String;
  #528 = Utf8               shutdownOptions
  #529 = Utf8               [Ljava/lang/String;
  #530 = Methodref          #524.#531     // javax/swing/JOptionPane.showOptionDialog:(Ljava/awt/Component;Ljava/lang/Object;Ljava/lang/String;IILjavax/swing/Icon;[Ljava/lang/Object;Ljava/lang/Object;)I
  #531 = NameAndType        #532:#533     // showOptionDialog:(Ljava/awt/Component;Ljava/lang/Object;Ljava/lang/String;IILjavax/swing/Icon;[Ljava/lang/Object;Ljava/lang/Object;)I
  #532 = Utf8               showOptionDialog
  #533 = Utf8               (Ljava/awt/Component;Ljava/lang/Object;Ljava/lang/String;IILjavax/swing/Icon;[Ljava/lang/Object;Ljava/lang/Object;)I
  #534 = Methodref          #535.#536     // ext/mods/gameserver/Shutdown.getInstance:()Lext/mods/gameserver/Shutdown;
  #535 = Class              #537          // ext/mods/gameserver/Shutdown
  #536 = NameAndType        #508:#538     // getInstance:()Lext/mods/gameserver/Shutdown;
  #537 = Utf8               ext/mods/gameserver/Shutdown
  #538 = Utf8               ()Lext/mods/gameserver/Shutdown;
  #539 = Methodref          #535.#540     // ext/mods/gameserver/Shutdown.startShutdown:(Lext/mods/gameserver/model/actor/Player;IZ)V
  #540 = NameAndType        #541:#542     // startShutdown:(Lext/mods/gameserver/model/actor/Player;IZ)V
  #541 = Utf8               startShutdown
  #542 = Utf8               (Lext/mods/gameserver/model/actor/Player;IZ)V
  #543 = Methodref          #488.#544     // java/lang/System.exit:(I)V
  #544 = NameAndType        #545:#63      // exit:(I)V
  #545 = Utf8               exit
  #546 = Class              #547          // ext/mods/commons/gui/InterfaceGS$4
  #547 = Utf8               ext/mods/commons/gui/InterfaceGS$4
  #548 = Methodref          #546.#269     // ext/mods/commons/gui/InterfaceGS$4."<init>":(Lext/mods/commons/gui/InterfaceGS;)V
  #549 = Class              #550          // java/io/PrintStream
  #550 = Utf8               java/io/PrintStream
  #551 = Methodref          #549.#552     // java/io/PrintStream."<init>":(Ljava/io/OutputStream;Z)V
  #552 = NameAndType        #5:#553       // "<init>":(Ljava/io/OutputStream;Z)V
  #553 = Utf8               (Ljava/io/OutputStream;Z)V
  #554 = Methodref          #488.#555     // java/lang/System.setOut:(Ljava/io/PrintStream;)V
  #555 = NameAndType        #556:#557     // setOut:(Ljava/io/PrintStream;)V
  #556 = Utf8               setOut
  #557 = Utf8               (Ljava/io/PrintStream;)V
  #558 = Methodref          #488.#559     // java/lang/System.setErr:(Ljava/io/PrintStream;)V
  #559 = NameAndType        #560:#557     // setErr:(Ljava/io/PrintStream;)V
  #560 = Utf8               setErr
  #561 = InvokeDynamic      #27:#562      // #27:run:(Lext/mods/commons/gui/InterfaceGS;Ljava/lang/String;)Ljava/lang/Runnable;
  #562 = NameAndType        #143:#563     // run:(Lext/mods/commons/gui/InterfaceGS;Ljava/lang/String;)Ljava/lang/Runnable;
  #563 = Utf8               (Lext/mods/commons/gui/InterfaceGS;Ljava/lang/String;)Ljava/lang/Runnable;
  #564 = String             #565          // Item Generator
  #565 = Utf8               Item Generator
  #566 = Class              #567          // javax/swing/JTabbedPane
  #567 = Utf8               javax/swing/JTabbedPane
  #568 = Methodref          #566.#3       // javax/swing/JTabbedPane."<init>":()V
  #569 = String             #570          // Armor
  #570 = Utf8               Armor
  #571 = Class              #572          // ext/mods/security/gui/items/amors/ArmorsXMLGenerator
  #572 = Utf8               ext/mods/security/gui/items/amors/ArmorsXMLGenerator
  #573 = Methodref          #571.#3       // ext/mods/security/gui/items/amors/ArmorsXMLGenerator."<init>":()V
  #574 = Methodref          #566.#575     // javax/swing/JTabbedPane.addTab:(Ljava/lang/String;Ljava/awt/Component;)V
  #575 = NameAndType        #576:#577     // addTab:(Ljava/lang/String;Ljava/awt/Component;)V
  #576 = Utf8               addTab
  #577 = Utf8               (Ljava/lang/String;Ljava/awt/Component;)V
  #578 = String             #579          // Weapon
  #579 = Utf8               Weapon
  #580 = String             #581          // EtcItem
  #581 = Utf8               EtcItem
  #582 = Methodref          #120.#257     // javax/swing/JFrame.add:(Ljava/awt/Component;)Ljava/awt/Component;
  #583 = Methodref          #17.#584      // javax/swing/JTextArea.append:(Ljava/lang/String;)V
  #584 = NameAndType        #585:#124     // append:(Ljava/lang/String;)V
  #585 = Utf8               append
  #586 = InterfaceMethodref #65.#587      // javax/swing/text/Document.getLength:()I
  #587 = NameAndType        #588:#589     // getLength:()I
  #588 = Utf8               getLength
  #589 = Utf8               ()I
  #590 = Methodref          #17.#591      // javax/swing/JTextArea.setCaretPosition:(I)V
  #591 = NameAndType        #592:#63      // setCaretPosition:(I)V
  #592 = Utf8               setCaretPosition
  #593 = Class              #594          // ext/mods/commons/gui/InterfaceAbout
  #594 = Utf8               ext/mods/commons/gui/InterfaceAbout
  #595 = Methodref          #593.#3       // ext/mods/commons/gui/InterfaceAbout."<init>":()V
  #596 = Methodref          #243.#597     // java/lang/Integer.parseInt:(Ljava/lang/String;)I
  #597 = NameAndType        #598:#599     // parseInt:(Ljava/lang/String;)I
  #598 = Utf8               parseInt
  #599 = Utf8               (Ljava/lang/String;)I
  #600 = Methodref          #601.#602     // ext/mods/commons/gui/actions/ReloadActions.reloadZones:(Ljavax/swing/JFrame;)V
  #601 = Class              #603          // ext/mods/commons/gui/actions/ReloadActions
  #602 = NameAndType        #604:#605     // reloadZones:(Ljavax/swing/JFrame;)V
  #603 = Utf8               ext/mods/commons/gui/actions/ReloadActions
  #604 = Utf8               reloadZones
  #605 = Utf8               (Ljavax/swing/JFrame;)V
  #606 = Methodref          #601.#607     // ext/mods/commons/gui/actions/ReloadActions.reloadSkills:(Ljavax/swing/JFrame;)V
  #607 = NameAndType        #608:#605     // reloadSkills:(Ljavax/swing/JFrame;)V
  #608 = Utf8               reloadSkills
  #609 = Methodref          #601.#610     // ext/mods/commons/gui/actions/ReloadActions.reloadMultisells:(Ljavax/swing/JFrame;)V
  #610 = NameAndType        #611:#605     // reloadMultisells:(Ljavax/swing/JFrame;)V
  #611 = Utf8               reloadMultisells
  #612 = Methodref          #601.#613     // ext/mods/commons/gui/actions/ReloadActions.reloadItems:(Ljavax/swing/JFrame;)V
  #613 = NameAndType        #614:#605     // reloadItems:(Ljavax/swing/JFrame;)V
  #614 = Utf8               reloadItems
  #615 = Methodref          #601.#616     // ext/mods/commons/gui/actions/ReloadActions.reloadFarmEvent:(Ljavax/swing/JFrame;)V
  #616 = NameAndType        #617:#605     // reloadFarmEvent:(Ljavax/swing/JFrame;)V
  #617 = Utf8               reloadFarmEvent
  #618 = Methodref          #601.#619     // ext/mods/commons/gui/actions/ReloadActions.reloadConfigs:(Ljavax/swing/JFrame;)V
  #619 = NameAndType        #620:#605     // reloadConfigs:(Ljavax/swing/JFrame;)V
  #620 = Utf8               reloadConfigs
  #621 = Methodref          #601.#622     // ext/mods/commons/gui/actions/ReloadActions.reloadBuylists:(Ljavax/swing/JFrame;)V
  #622 = NameAndType        #623:#605     // reloadBuylists:(Ljavax/swing/JFrame;)V
  #623 = Utf8               reloadBuylists
  #624 = Methodref          #601.#625     // ext/mods/commons/gui/actions/ReloadActions.reloadAccess:(Ljavax/swing/JFrame;)V
  #625 = NameAndType        #626:#605     // reloadAccess:(Ljavax/swing/JFrame;)V
  #626 = Utf8               reloadAccess
  #627 = Methodref          #13.#628      // ext/mods/commons/gui/InterfaceGS.abrirItemsBuilder:()V
  #628 = NameAndType        #629:#6       // abrirItemsBuilder:()V
  #629 = Utf8               abrirItemsBuilder
  #630 = Class              #631          // ext/mods/commons/gui/tools/MultisellBuilderDialog
  #631 = Utf8               ext/mods/commons/gui/tools/MultisellBuilderDialog
  #632 = Methodref          #630.#633     // ext/mods/commons/gui/tools/MultisellBuilderDialog."<init>":(Ljavax/swing/JFrame;)V
  #633 = NameAndType        #5:#605       // "<init>":(Ljavax/swing/JFrame;)V
  #634 = Methodref          #630.#312     // ext/mods/commons/gui/tools/MultisellBuilderDialog.setVisible:(Z)V
  #635 = Methodref          #636.#637     // ext/mods/commons/gui/actions/ServerActions.criticalAnnounce:(Ljavax/swing/JFrame;)V
  #636 = Class              #638          // ext/mods/commons/gui/actions/ServerActions
  #637 = NameAndType        #639:#605     // criticalAnnounce:(Ljavax/swing/JFrame;)V
  #638 = Utf8               ext/mods/commons/gui/actions/ServerActions
  #639 = Utf8               criticalAnnounce
  #640 = Methodref          #636.#641     // ext/mods/commons/gui/actions/ServerActions.normalAnnounce:(Ljavax/swing/JFrame;)V
  #641 = NameAndType        #642:#605     // normalAnnounce:(Ljavax/swing/JFrame;)V
  #642 = Utf8               normalAnnounce
  #643 = Class              #644          // ext/mods/commons/gui/tools/VulnerabilityBalanceFrame
  #644 = Utf8               ext/mods/commons/gui/tools/VulnerabilityBalanceFrame
  #645 = Methodref          #643.#3       // ext/mods/commons/gui/tools/VulnerabilityBalanceFrame."<init>":()V
  #646 = Methodref          #643.#312     // ext/mods/commons/gui/tools/VulnerabilityBalanceFrame.setVisible:(Z)V
  #647 = Class              #648          // ext/mods/commons/gui/tools/DefenceBalanceFrame
  #648 = Utf8               ext/mods/commons/gui/tools/DefenceBalanceFrame
  #649 = Methodref          #647.#3       // ext/mods/commons/gui/tools/DefenceBalanceFrame."<init>":()V
  #650 = Methodref          #647.#312     // ext/mods/commons/gui/tools/DefenceBalanceFrame.setVisible:(Z)V
  #651 = Class              #652          // ext/mods/commons/gui/tools/DamageBalanceFrame
  #652 = Utf8               ext/mods/commons/gui/tools/DamageBalanceFrame
  #653 = Methodref          #651.#3       // ext/mods/commons/gui/tools/DamageBalanceFrame."<init>":()V
  #654 = Methodref          #651.#312     // ext/mods/commons/gui/tools/DamageBalanceFrame.setVisible:(Z)V
  #655 = String             #656          // Enter player name:
  #656 = Utf8               Enter player name:
  #657 = Methodref          #524.#658     // javax/swing/JOptionPane.showInputDialog:(Ljava/awt/Component;Ljava/lang/Object;Ljava/lang/String;I)Ljava/lang/String;
  #658 = NameAndType        #659:#660     // showInputDialog:(Ljava/awt/Component;Ljava/lang/Object;Ljava/lang/String;I)Ljava/lang/String;
  #659 = Utf8               showInputDialog
  #660 = Utf8               (Ljava/awt/Component;Ljava/lang/Object;Ljava/lang/String;I)Ljava/lang/String;
  #661 = Class              #662          // ext/mods/commons/gui/tools/CreateItemDialog
  #662 = Utf8               ext/mods/commons/gui/tools/CreateItemDialog
  #663 = Methodref          #661.#664     // ext/mods/commons/gui/tools/CreateItemDialog."<init>":(Ljavax/swing/JFrame;Ljava/lang/String;)V
  #664 = NameAndType        #5:#665       // "<init>":(Ljavax/swing/JFrame;Ljava/lang/String;)V
  #665 = Utf8               (Ljavax/swing/JFrame;Ljava/lang/String;)V
  #666 = Methodref          #661.#312     // ext/mods/commons/gui/tools/CreateItemDialog.setVisible:(Z)V
  #667 = Methodref          #668.#669     // ext/mods/commons/gui/actions/PlayerActions.repairPlayer:(Ljavax/swing/JFrame;)V
  #668 = Class              #670          // ext/mods/commons/gui/actions/PlayerActions
  #669 = NameAndType        #671:#605     // repairPlayer:(Ljavax/swing/JFrame;)V
  #670 = Utf8               ext/mods/commons/gui/actions/PlayerActions
  #671 = Utf8               repairPlayer
  #672 = Class              #673          // ext/mods/commons/gui/tools/SearchItemFrame
  #673 = Utf8               ext/mods/commons/gui/tools/SearchItemFrame
  #674 = Methodref          #672.#3       // ext/mods/commons/gui/tools/SearchItemFrame."<init>":()V
  #675 = Methodref          #672.#312     // ext/mods/commons/gui/tools/SearchItemFrame.setVisible:(Z)V
  #676 = Methodref          #668.#677     // ext/mods/commons/gui/actions/PlayerActions.changeAccess:(Ljavax/swing/JFrame;)V
  #677 = NameAndType        #678:#605     // changeAccess:(Ljavax/swing/JFrame;)V
  #678 = Utf8               changeAccess
  #679 = Methodref          #636.#680     // ext/mods/commons/gui/actions/ServerActions.abort:(Ljavax/swing/JFrame;)V
  #680 = NameAndType        #681:#605     // abort:(Ljavax/swing/JFrame;)V
  #681 = Utf8               abort
  #682 = Methodref          #636.#683     // ext/mods/commons/gui/actions/ServerActions.restart:(Ljavax/swing/JFrame;)V
  #683 = NameAndType        #684:#605     // restart:(Ljavax/swing/JFrame;)V
  #684 = Utf8               restart
  #685 = Methodref          #636.#686     // ext/mods/commons/gui/actions/ServerActions.shutdown:(Ljavax/swing/JFrame;)V
  #686 = NameAndType        #687:#605     // shutdown:(Ljavax/swing/JFrame;)V
  #687 = Utf8               shutdown
  #688 = Class              #689          // java/awt/event/ComponentEvent
  #689 = Utf8               java/awt/event/ComponentEvent
  #690 = Methodref          #688.#691     // java/awt/event/ComponentEvent."<init>":(Ljava/awt/Component;I)V
  #691 = NameAndType        #5:#692       // "<init>":(Ljava/awt/Component;I)V
  #692 = Utf8               (Ljava/awt/Component;I)V
  #693 = Methodref          #120.#694     // javax/swing/JFrame.dispatchEvent:(Ljava/awt/AWTEvent;)V
  #694 = NameAndType        #695:#696     // dispatchEvent:(Ljava/awt/AWTEvent;)V
  #695 = Utf8               dispatchEvent
  #696 = Utf8               (Ljava/awt/AWTEvent;)V
  #697 = String             #698          // Cancel
  #698 = Utf8               Cancel
  #699 = Methodref          #700.#701     // java/lang/Thread.setDefaultUncaughtExceptionHandler:(Ljava/lang/Thread$UncaughtExceptionHandler;)V
  #700 = Class              #702          // java/lang/Thread
  #701 = NameAndType        #703:#704     // setDefaultUncaughtExceptionHandler:(Ljava/lang/Thread$UncaughtExceptionHandler;)V
  #702 = Utf8               java/lang/Thread
  #703 = Utf8               setDefaultUncaughtExceptionHandler
  #704 = Utf8               (Ljava/lang/Thread$UncaughtExceptionHandler;)V
  #705 = Utf8               DEFAULT_WIDTH
  #706 = Utf8               I
  #707 = Utf8               ConstantValue
  #708 = Integer            850
  #709 = Utf8               DEFAULT_HEIGHT
  #710 = Integer            517
  #711 = Utf8               Code
  #712 = Utf8               LineNumberTable
  #713 = Utf8               LocalVariableTable
  #714 = Utf8               this
  #715 = Utf8               Lext/mods/commons/gui/InterfaceGS;
  #716 = Utf8               geoProps
  #717 = Utf8               Ljava/util/Properties;
  #718 = Utf8               serverProps
  #719 = Utf8               isLightMode
  #720 = Utf8               Z
  #721 = Utf8               isDevMode
  #722 = Utf8               worldTitle
  #723 = Utf8               resizer
  #724 = Utf8               Lext/mods/commons/gui/ComponentResizer;
  #725 = Utf8               menuBar
  #726 = Utf8               Ljavax/swing/JMenuBar;
  #727 = Utf8               closeAction
  #728 = Utf8               Ljava/lang/Runnable;
  #729 = Utf8               iconPath
  #730 = Utf8               mainPanel
  #731 = Utf8               StackMapTable
  #732 = Utf8               font
  #733 = Utf8               mnActions
  #734 = Utf8               Ljavax/swing/JMenu;
  #735 = Utf8               mnAdmin
  #736 = Utf8               mnCharacters
  #737 = Utf8               mnBalance
  #738 = Utf8               mnAnnounce
  #739 = Utf8               mnTools
  #740 = Utf8               mnReload
  #741 = Utf8               mnFont
  #742 = Utf8               fonts
  #743 = Utf8               mnHelp
  #744 = Class              #529          // "[Ljava/lang/String;"
  #745 = Utf8               title
  #746 = Utf8               fontSize
  #747 = Utf8               menu
  #748 = Utf8               listener
  #749 = Utf8               Ljava/awt/event/ActionListener;
  #750 = Utf8               item
  #751 = Utf8               Ljavax/swing/JMenuItem;
  #752 = Utf8               closeGameWindow
  #753 = Utf8               lsThread
  #754 = Utf8               Lext/mods/gameserver/LoginServerThread;
  #755 = Utf8               serverName
  #756 = Utf8               isFullyConnected
  #757 = Utf8               out
  #758 = Utf8               Ljava/io/OutputStream;
  #759 = Utf8               updateConsole
  #760 = Utf8               text
  #761 = Utf8               itemFrame
  #762 = Utf8               tabbedPane
  #763 = Utf8               Ljavax/swing/JTabbedPane;
  #764 = Utf8               lambda$updateConsole$0
  #765 = Utf8               lambda$createMenuBar$23
  #766 = Utf8               (Ljava/awt/event/ActionEvent;)V
  #767 = Utf8               e
  #768 = Utf8               Ljava/awt/event/ActionEvent;
  #769 = Utf8               lambda$createMenuBar$22
  #770 = Utf8               (Ljava/lang/String;Ljava/awt/event/ActionEvent;)V
  #771 = Utf8               lambda$createMenuBar$21
  #772 = Utf8               lambda$createMenuBar$20
  #773 = Utf8               lambda$createMenuBar$19
  #774 = Utf8               lambda$createMenuBar$18
  #775 = Utf8               lambda$createMenuBar$17
  #776 = Utf8               lambda$createMenuBar$16
  #777 = Utf8               lambda$createMenuBar$15
  #778 = Utf8               lambda$createMenuBar$14
  #779 = Utf8               lambda$createMenuBar$13
  #780 = Utf8               lambda$createMenuBar$12
  #781 = Utf8               lambda$createMenuBar$11
  #782 = Utf8               lambda$createMenuBar$10
  #783 = Utf8               lambda$createMenuBar$9
  #784 = Utf8               lambda$createMenuBar$8
  #785 = Utf8               lambda$createMenuBar$7
  #786 = Utf8               lambda$createMenuBar$6
  #787 = Utf8               playerName
  #788 = Utf8               lambda$createMenuBar$5
  #789 = Utf8               lambda$createMenuBar$4
  #790 = Utf8               lambda$createMenuBar$3
  #791 = Utf8               lambda$createMenuBar$2
  #792 = Utf8               lambda$createMenuBar$1
  #793 = Utf8               lambda$createMenuBar$0
  #794 = Utf8               lambda$initialize$0
  #795 = Utf8               <clinit>
  #796 = Utf8               SourceFile
  #797 = Utf8               InterfaceGS.java
  #798 = Utf8               NestMembers
  #799 = Utf8               BootstrapMethods
  #800 = MethodType         #6            //  ()V
  #801 = MethodHandle       5:#802        // REF_invokeVirtual ext/mods/commons/gui/InterfaceGS.closeGameWindow:()V
  #802 = Methodref          #13.#803      // ext/mods/commons/gui/InterfaceGS.closeGameWindow:()V
  #803 = NameAndType        #752:#6       // closeGameWindow:()V
  #804 = String             #805          // ..\u0001images\u000116x16.png
  #805 = Utf8               ..\u0001images\u000116x16.png
  #806 = MethodHandle       5:#807        // REF_invokeVirtual ext/mods/commons/gui/InterfaceGS.lambda$initialize$0:()V
  #807 = Methodref          #13.#808      // ext/mods/commons/gui/InterfaceGS.lambda$initialize$0:()V
  #808 = NameAndType        #794:#6       // lambda$initialize$0:()V
  #809 = MethodType         #766          //  (Ljava/awt/event/ActionEvent;)V
  #810 = MethodHandle       5:#811        // REF_invokeVirtual ext/mods/commons/gui/InterfaceGS.lambda$createMenuBar$0:(Ljava/awt/event/ActionEvent;)V
  #811 = Methodref          #13.#812      // ext/mods/commons/gui/InterfaceGS.lambda$createMenuBar$0:(Ljava/awt/event/ActionEvent;)V
  #812 = NameAndType        #793:#766     // lambda$createMenuBar$0:(Ljava/awt/event/ActionEvent;)V
  #813 = MethodHandle       5:#814        // REF_invokeVirtual ext/mods/commons/gui/InterfaceGS.lambda$createMenuBar$1:(Ljava/awt/event/ActionEvent;)V
  #814 = Methodref          #13.#815      // ext/mods/commons/gui/InterfaceGS.lambda$createMenuBar$1:(Ljava/awt/event/ActionEvent;)V
  #815 = NameAndType        #792:#766     // lambda$createMenuBar$1:(Ljava/awt/event/ActionEvent;)V
  #816 = MethodHandle       5:#817        // REF_invokeVirtual ext/mods/commons/gui/InterfaceGS.lambda$createMenuBar$2:(Ljava/awt/event/ActionEvent;)V
  #817 = Methodref          #13.#818      // ext/mods/commons/gui/InterfaceGS.lambda$createMenuBar$2:(Ljava/awt/event/ActionEvent;)V
  #818 = NameAndType        #791:#766     // lambda$createMenuBar$2:(Ljava/awt/event/ActionEvent;)V
  #819 = MethodHandle       5:#820        // REF_invokeVirtual ext/mods/commons/gui/InterfaceGS.lambda$createMenuBar$3:(Ljava/awt/event/ActionEvent;)V
  #820 = Methodref          #13.#821      // ext/mods/commons/gui/InterfaceGS.lambda$createMenuBar$3:(Ljava/awt/event/ActionEvent;)V
  #821 = NameAndType        #790:#766     // lambda$createMenuBar$3:(Ljava/awt/event/ActionEvent;)V
  #822 = MethodHandle       6:#823        // REF_invokeStatic ext/mods/commons/gui/InterfaceGS.lambda$createMenuBar$4:(Ljava/awt/event/ActionEvent;)V
  #823 = Methodref          #13.#824      // ext/mods/commons/gui/InterfaceGS.lambda$createMenuBar$4:(Ljava/awt/event/ActionEvent;)V
  #824 = NameAndType        #789:#766     // lambda$createMenuBar$4:(Ljava/awt/event/ActionEvent;)V
  #825 = MethodHandle       5:#826        // REF_invokeVirtual ext/mods/commons/gui/InterfaceGS.lambda$createMenuBar$5:(Ljava/awt/event/ActionEvent;)V
  #826 = Methodref          #13.#827      // ext/mods/commons/gui/InterfaceGS.lambda$createMenuBar$5:(Ljava/awt/event/ActionEvent;)V
  #827 = NameAndType        #788:#766     // lambda$createMenuBar$5:(Ljava/awt/event/ActionEvent;)V
  #828 = MethodHandle       5:#829        // REF_invokeVirtual ext/mods/commons/gui/InterfaceGS.lambda$createMenuBar$6:(Ljava/awt/event/ActionEvent;)V
  #829 = Methodref          #13.#830      // ext/mods/commons/gui/InterfaceGS.lambda$createMenuBar$6:(Ljava/awt/event/ActionEvent;)V
  #830 = NameAndType        #786:#766     // lambda$createMenuBar$6:(Ljava/awt/event/ActionEvent;)V
  #831 = MethodHandle       6:#832        // REF_invokeStatic ext/mods/commons/gui/InterfaceGS.lambda$createMenuBar$7:(Ljava/awt/event/ActionEvent;)V
  #832 = Methodref          #13.#833      // ext/mods/commons/gui/InterfaceGS.lambda$createMenuBar$7:(Ljava/awt/event/ActionEvent;)V
  #833 = NameAndType        #785:#766     // lambda$createMenuBar$7:(Ljava/awt/event/ActionEvent;)V
  #834 = MethodHandle       6:#835        // REF_invokeStatic ext/mods/commons/gui/InterfaceGS.lambda$createMenuBar$8:(Ljava/awt/event/ActionEvent;)V
  #835 = Methodref          #13.#836      // ext/mods/commons/gui/InterfaceGS.lambda$createMenuBar$8:(Ljava/awt/event/ActionEvent;)V
  #836 = NameAndType        #784:#766     // lambda$createMenuBar$8:(Ljava/awt/event/ActionEvent;)V
  #837 = MethodHandle       6:#838        // REF_invokeStatic ext/mods/commons/gui/InterfaceGS.lambda$createMenuBar$9:(Ljava/awt/event/ActionEvent;)V
  #838 = Methodref          #13.#839      // ext/mods/commons/gui/InterfaceGS.lambda$createMenuBar$9:(Ljava/awt/event/ActionEvent;)V
  #839 = NameAndType        #783:#766     // lambda$createMenuBar$9:(Ljava/awt/event/ActionEvent;)V
  #840 = MethodHandle       5:#841        // REF_invokeVirtual ext/mods/commons/gui/InterfaceGS.lambda$createMenuBar$10:(Ljava/awt/event/ActionEvent;)V
  #841 = Methodref          #13.#842      // ext/mods/commons/gui/InterfaceGS.lambda$createMenuBar$10:(Ljava/awt/event/ActionEvent;)V
  #842 = NameAndType        #782:#766     // lambda$createMenuBar$10:(Ljava/awt/event/ActionEvent;)V
  #843 = MethodHandle       5:#844        // REF_invokeVirtual ext/mods/commons/gui/InterfaceGS.lambda$createMenuBar$11:(Ljava/awt/event/ActionEvent;)V
  #844 = Methodref          #13.#845      // ext/mods/commons/gui/InterfaceGS.lambda$createMenuBar$11:(Ljava/awt/event/ActionEvent;)V
  #845 = NameAndType        #781:#766     // lambda$createMenuBar$11:(Ljava/awt/event/ActionEvent;)V
  #846 = MethodHandle       5:#847        // REF_invokeVirtual ext/mods/commons/gui/InterfaceGS.lambda$createMenuBar$12:(Ljava/awt/event/ActionEvent;)V
  #847 = Methodref          #13.#848      // ext/mods/commons/gui/InterfaceGS.lambda$createMenuBar$12:(Ljava/awt/event/ActionEvent;)V
  #848 = NameAndType        #780:#766     // lambda$createMenuBar$12:(Ljava/awt/event/ActionEvent;)V
  #849 = MethodHandle       5:#850        // REF_invokeVirtual ext/mods/commons/gui/InterfaceGS.lambda$createMenuBar$13:(Ljava/awt/event/ActionEvent;)V
  #850 = Methodref          #13.#851      // ext/mods/commons/gui/InterfaceGS.lambda$createMenuBar$13:(Ljava/awt/event/ActionEvent;)V
  #851 = NameAndType        #779:#766     // lambda$createMenuBar$13:(Ljava/awt/event/ActionEvent;)V
  #852 = MethodHandle       5:#853        // REF_invokeVirtual ext/mods/commons/gui/InterfaceGS.lambda$createMenuBar$14:(Ljava/awt/event/ActionEvent;)V
  #853 = Methodref          #13.#854      // ext/mods/commons/gui/InterfaceGS.lambda$createMenuBar$14:(Ljava/awt/event/ActionEvent;)V
  #854 = NameAndType        #778:#766     // lambda$createMenuBar$14:(Ljava/awt/event/ActionEvent;)V
  #855 = MethodHandle       5:#856        // REF_invokeVirtual ext/mods/commons/gui/InterfaceGS.lambda$createMenuBar$15:(Ljava/awt/event/ActionEvent;)V
  #856 = Methodref          #13.#857      // ext/mods/commons/gui/InterfaceGS.lambda$createMenuBar$15:(Ljava/awt/event/ActionEvent;)V
  #857 = NameAndType        #777:#766     // lambda$createMenuBar$15:(Ljava/awt/event/ActionEvent;)V
  #858 = MethodHandle       5:#859        // REF_invokeVirtual ext/mods/commons/gui/InterfaceGS.lambda$createMenuBar$16:(Ljava/awt/event/ActionEvent;)V
  #859 = Methodref          #13.#860      // ext/mods/commons/gui/InterfaceGS.lambda$createMenuBar$16:(Ljava/awt/event/ActionEvent;)V
  #860 = NameAndType        #776:#766     // lambda$createMenuBar$16:(Ljava/awt/event/ActionEvent;)V
  #861 = MethodHandle       5:#862        // REF_invokeVirtual ext/mods/commons/gui/InterfaceGS.lambda$createMenuBar$17:(Ljava/awt/event/ActionEvent;)V
  #862 = Methodref          #13.#863      // ext/mods/commons/gui/InterfaceGS.lambda$createMenuBar$17:(Ljava/awt/event/ActionEvent;)V
  #863 = NameAndType        #775:#766     // lambda$createMenuBar$17:(Ljava/awt/event/ActionEvent;)V
  #864 = MethodHandle       5:#865        // REF_invokeVirtual ext/mods/commons/gui/InterfaceGS.lambda$createMenuBar$18:(Ljava/awt/event/ActionEvent;)V
  #865 = Methodref          #13.#866      // ext/mods/commons/gui/InterfaceGS.lambda$createMenuBar$18:(Ljava/awt/event/ActionEvent;)V
  #866 = NameAndType        #774:#766     // lambda$createMenuBar$18:(Ljava/awt/event/ActionEvent;)V
  #867 = MethodHandle       5:#868        // REF_invokeVirtual ext/mods/commons/gui/InterfaceGS.lambda$createMenuBar$19:(Ljava/awt/event/ActionEvent;)V
  #868 = Methodref          #13.#869      // ext/mods/commons/gui/InterfaceGS.lambda$createMenuBar$19:(Ljava/awt/event/ActionEvent;)V
  #869 = NameAndType        #773:#766     // lambda$createMenuBar$19:(Ljava/awt/event/ActionEvent;)V
  #870 = MethodHandle       5:#871        // REF_invokeVirtual ext/mods/commons/gui/InterfaceGS.lambda$createMenuBar$20:(Ljava/awt/event/ActionEvent;)V
  #871 = Methodref          #13.#872      // ext/mods/commons/gui/InterfaceGS.lambda$createMenuBar$20:(Ljava/awt/event/ActionEvent;)V
  #872 = NameAndType        #772:#766     // lambda$createMenuBar$20:(Ljava/awt/event/ActionEvent;)V
  #873 = MethodHandle       5:#874        // REF_invokeVirtual ext/mods/commons/gui/InterfaceGS.lambda$createMenuBar$21:(Ljava/awt/event/ActionEvent;)V
  #874 = Methodref          #13.#875      // ext/mods/commons/gui/InterfaceGS.lambda$createMenuBar$21:(Ljava/awt/event/ActionEvent;)V
  #875 = NameAndType        #771:#766     // lambda$createMenuBar$21:(Ljava/awt/event/ActionEvent;)V
  #876 = MethodHandle       5:#877        // REF_invokeVirtual ext/mods/commons/gui/InterfaceGS.lambda$createMenuBar$22:(Ljava/lang/String;Ljava/awt/event/ActionEvent;)V
  #877 = Methodref          #13.#878      // ext/mods/commons/gui/InterfaceGS.lambda$createMenuBar$22:(Ljava/lang/String;Ljava/awt/event/ActionEvent;)V
  #878 = NameAndType        #769:#770     // lambda$createMenuBar$22:(Ljava/lang/String;Ljava/awt/event/ActionEvent;)V
  #879 = MethodHandle       6:#880        // REF_invokeStatic ext/mods/commons/gui/InterfaceGS.lambda$createMenuBar$23:(Ljava/awt/event/ActionEvent;)V
  #880 = Methodref          #13.#881      // ext/mods/commons/gui/InterfaceGS.lambda$createMenuBar$23:(Ljava/awt/event/ActionEvent;)V
  #881 = NameAndType        #765:#766     // lambda$createMenuBar$23:(Ljava/awt/event/ActionEvent;)V
  #882 = MethodHandle       5:#883        // REF_invokeVirtual ext/mods/commons/gui/InterfaceGS.lambda$updateConsole$0:(Ljava/lang/String;)V
  #883 = Methodref          #13.#884      // ext/mods/commons/gui/InterfaceGS.lambda$updateConsole$0:(Ljava/lang/String;)V
  #884 = NameAndType        #764:#124     // lambda$updateConsole$0:(Ljava/lang/String;)V
  #885 = MethodHandle       6:#886        // REF_invokeStatic java/lang/invoke/LambdaMetafactory.metafactory:(Ljava/lang/invoke/MethodHandles$Lookup;Ljava/lang/String;Ljava/lang/invoke/MethodType;Ljava/lang/invoke/MethodType;Ljava/lang/invoke/MethodHandle;Ljava/lang/invoke/MethodType;)Ljava/lang/invoke/CallSite;
  #886 = Methodref          #887.#888     // java/lang/invoke/LambdaMetafactory.metafactory:(Ljava/lang/invoke/MethodHandles$Lookup;Ljava/lang/String;Ljava/lang/invoke/MethodType;Ljava/lang/invoke/MethodType;Ljava/lang/invoke/MethodHandle;Ljava/lang/invoke/MethodType;)Ljava/lang/invoke/CallSite;
  #887 = Class              #889          // java/lang/invoke/LambdaMetafactory
  #888 = NameAndType        #890:#891     // metafactory:(Ljava/lang/invoke/MethodHandles$Lookup;Ljava/lang/String;Ljava/lang/invoke/MethodType;Ljava/lang/invoke/MethodType;Ljava/lang/invoke/MethodHandle;Ljava/lang/invoke/MethodType;)Ljava/lang/invoke/CallSite;
  #889 = Utf8               java/lang/invoke/LambdaMetafactory
  #890 = Utf8               metafactory
  #891 = Utf8               (Ljava/lang/invoke/MethodHandles$Lookup;Ljava/lang/String;Ljava/lang/invoke/MethodType;Ljava/lang/invoke/MethodType;Ljava/lang/invoke/MethodHandle;Ljava/lang/invoke/MethodType;)Ljava/lang/invoke/CallSite;
  #892 = MethodHandle       6:#893        // REF_invokeStatic java/lang/invoke/StringConcatFactory.makeConcatWithConstants:(Ljava/lang/invoke/MethodHandles$Lookup;Ljava/lang/String;Ljava/lang/invoke/MethodType;Ljava/lang/String;[Ljava/lang/Object;)Ljava/lang/invoke/CallSite;
  #893 = Methodref          #894.#895     // java/lang/invoke/StringConcatFactory.makeConcatWithConstants:(Ljava/lang/invoke/MethodHandles$Lookup;Ljava/lang/String;Ljava/lang/invoke/MethodType;Ljava/lang/String;[Ljava/lang/Object;)Ljava/lang/invoke/CallSite;
  #894 = Class              #896          // java/lang/invoke/StringConcatFactory
  #895 = NameAndType        #153:#897     // makeConcatWithConstants:(Ljava/lang/invoke/MethodHandles$Lookup;Ljava/lang/String;Ljava/lang/invoke/MethodType;Ljava/lang/String;[Ljava/lang/Object;)Ljava/lang/invoke/CallSite;
  #896 = Utf8               java/lang/invoke/StringConcatFactory
  #897 = Utf8               (Ljava/lang/invoke/MethodHandles$Lookup;Ljava/lang/String;Ljava/lang/invoke/MethodType;Ljava/lang/String;[Ljava/lang/Object;)Ljava/lang/invoke/CallSite;
  #898 = Utf8               InnerClasses
  #899 = Utf8               ModernScrollBarUI
  #900 = Class              #901          // java/lang/Thread$UncaughtExceptionHandler
  #901 = Utf8               java/lang/Thread$UncaughtExceptionHandler
  #902 = Utf8               UncaughtExceptionHandler
  #903 = Class              #904          // java/lang/invoke/MethodHandles$Lookup
  #904 = Utf8               java/lang/invoke/MethodHandles$Lookup
  #905 = Class              #906          // java/lang/invoke/MethodHandles
  #906 = Utf8               java/lang/invoke/MethodHandles
  #907 = Utf8               Lookup
{
  public ext.mods.commons.gui.InterfaceGS();
    descriptor: ()V
    flags: (0x0001) ACC_PUBLIC
    Code:
      stack=1, locals=1, args_size=1
         0: aload_0
         1: invokespecial #1                  // Method java/lang/Object."<init>":()V
         4: invokestatic  #7                  // Method ext/mods/commons/gui/ThemeManager.applyTheme:()V
         7: aload_0
         8: invokevirtual #12                 // Method initialize:()V
        11: return
      LineNumberTable:
        line 69: 0
        line 70: 4
        line 71: 7
        line 72: 11
      LocalVariableTable:
        Start  Length  Slot  Name   Signature
            0      12     0  this   Lext/mods/commons/gui/InterfaceGS;

  static {};
    descriptor: ()V
    flags: (0x0008) ACC_STATIC
    Code:
      stack=4, locals=0, args_size=0
         0: iconst_2
         1: anewarray     #437                // class java/lang/String
         4: dup
         5: iconst_0
         6: ldc_w         #343                // String Shutdown
         9: aastore
        10: dup
        11: iconst_1
        12: ldc_w         #697                // String Cancel
        15: aastore
        16: putstatic     #526                // Field shutdownOptions:[Ljava/lang/String;
        19: aconst_null
        20: invokestatic  #699                // Method java/lang/Thread.setDefaultUncaughtExceptionHandler:(Ljava/lang/Thread$UncaughtExceptionHandler;)V
        23: return
      LineNumberTable:
        line 55: 0
        line 67: 19
}
SourceFile: "InterfaceGS.java"
NestMembers:
  ext/mods/commons/gui/InterfaceGS$4
  ext/mods/commons/gui/InterfaceGS$3
  ext/mods/commons/gui/InterfaceGS$2
  ext/mods/commons/gui/InterfaceGS$1
BootstrapMethods:
  0: #885 REF_invokeStatic java/lang/invoke/LambdaMetafactory.metafactory:(Ljava/lang/invoke/MethodHandles$Lookup;Ljava/lang/String;Ljava/lang/invoke/MethodType;Ljava/lang/invoke/MethodType;Ljava/lang/invoke/MethodHandle;Ljava/lang/invoke/MethodType;)Ljava/lang/invoke/CallSite;
    Method arguments:
      #800 ()V
      #801 REF_invokeVirtual ext/mods/commons/gui/InterfaceGS.closeGameWindow:()V
      #800 ()V
  1: #892 REF_invokeStatic java/lang/invoke/StringConcatFactory.makeConcatWithConstants:(Ljava/lang/invoke/MethodHandles$Lookup;Ljava/lang/String;Ljava/lang/invoke/MethodType;Ljava/lang/String;[Ljava/lang/Object;)Ljava/lang/invoke/CallSite;
    Method arguments:
      #804 ..\u0001images\u000116x16.png
  2: #885 REF_invokeStatic java/lang/invoke/LambdaMetafactory.metafactory:(Ljava/lang/invoke/MethodHandles$Lookup;Ljava/lang/String;Ljava/lang/invoke/MethodType;Ljava/lang/invoke/MethodType;Ljava/lang/invoke/MethodHandle;Ljava/lang/invoke/MethodType;)Ljava/lang/invoke/CallSite;
    Method arguments:
      #800 ()V
      #806 REF_invokeVirtual ext/mods/commons/gui/InterfaceGS.lambda$initialize$0:()V
      #800 ()V
  3: #885 REF_invokeStatic java/lang/invoke/LambdaMetafactory.metafactory:(Ljava/lang/invoke/MethodHandles$Lookup;Ljava/lang/String;Ljava/lang/invoke/MethodType;Ljava/lang/invoke/MethodType;Ljava/lang/invoke/MethodHandle;Ljava/lang/invoke/MethodType;)Ljava/lang/invoke/CallSite;
    Method arguments:
      #809 (Ljava/awt/event/ActionEvent;)V
      #810 REF_invokeVirtual ext/mods/commons/gui/InterfaceGS.lambda$createMenuBar$0:(Ljava/awt/event/ActionEvent;)V
      #809 (Ljava/awt/event/ActionEvent;)V
  4: #885 REF_invokeStatic java/lang/invoke/LambdaMetafactory.metafactory:(Ljava/lang/invoke/MethodHandles$Lookup;Ljava/lang/String;Ljava/lang/invoke/MethodType;Ljava/lang/invoke/MethodType;Ljava/lang/invoke/MethodHandle;Ljava/lang/invoke/MethodType;)Ljava/lang/invoke/CallSite;
    Method arguments:
      #809 (Ljava/awt/event/ActionEvent;)V
      #813 REF_invokeVirtual ext/mods/commons/gui/InterfaceGS.lambda$createMenuBar$1:(Ljava/awt/event/ActionEvent;)V
      #809 (Ljava/awt/event/ActionEvent;)V
  5: #885 REF_invokeStatic java/lang/invoke/LambdaMetafactory.metafactory:(Ljava/lang/invoke/MethodHandles$Lookup;Ljava/lang/String;Ljava/lang/invoke/MethodType;Ljava/lang/invoke/MethodType;Ljava/lang/invoke/MethodHandle;Ljava/lang/invoke/MethodType;)Ljava/lang/invoke/CallSite;
    Method arguments:
      #809 (Ljava/awt/event/ActionEvent;)V
      #816 REF_invokeVirtual ext/mods/commons/gui/InterfaceGS.lambda$createMenuBar$2:(Ljava/awt/event/ActionEvent;)V
      #809 (Ljava/awt/event/ActionEvent;)V
  6: #885 REF_invokeStatic java/lang/invoke/LambdaMetafactory.metafactory:(Ljava/lang/invoke/MethodHandles$Lookup;Ljava/lang/String;Ljava/lang/invoke/MethodType;Ljava/lang/invoke/MethodType;Ljava/lang/invoke/MethodHandle;Ljava/lang/invoke/MethodType;)Ljava/lang/invoke/CallSite;
    Method arguments:
      #809 (Ljava/awt/event/ActionEvent;)V
      #819 REF_invokeVirtual ext/mods/commons/gui/InterfaceGS.lambda$createMenuBar$3:(Ljava/awt/event/ActionEvent;)V
      #809 (Ljava/awt/event/ActionEvent;)V
  7: #885 REF_invokeStatic java/lang/invoke/LambdaMetafactory.metafactory:(Ljava/lang/invoke/MethodHandles$Lookup;Ljava/lang/String;Ljava/lang/invoke/MethodType;Ljava/lang/invoke/MethodType;Ljava/lang/invoke/MethodHandle;Ljava/lang/invoke/MethodType;)Ljava/lang/invoke/CallSite;
    Method arguments:
      #809 (Ljava/awt/event/ActionEvent;)V
      #822 REF_invokeStatic ext/mods/commons/gui/InterfaceGS.lambda$createMenuBar$4:(Ljava/awt/event/ActionEvent;)V
      #809 (Ljava/awt/event/ActionEvent;)V
  8: #885 REF_invokeStatic java/lang/invoke/LambdaMetafactory.metafactory:(Ljava/lang/invoke/MethodHandles$Lookup;Ljava/lang/String;Ljava/lang/invoke/MethodType;Ljava/lang/invoke/MethodType;Ljava/lang/invoke/MethodHandle;Ljava/lang/invoke/MethodType;)Ljava/lang/invoke/CallSite;
    Method arguments:
      #809 (Ljava/awt/event/ActionEvent;)V
      #825 REF_invokeVirtual ext/mods/commons/gui/InterfaceGS.lambda$createMenuBar$5:(Ljava/awt/event/ActionEvent;)V
      #809 (Ljava/awt/event/ActionEvent;)V
  9: #885 REF_invokeStatic java/lang/invoke/LambdaMetafactory.metafactory:(Ljava/lang/invoke/MethodHandles$Lookup;Ljava/lang/String;Ljava/lang/invoke/MethodType;Ljava/lang/invoke/MethodType;Ljava/lang/invoke/MethodHandle;Ljava/lang/invoke/MethodType;)Ljava/lang/invoke/CallSite;
    Method arguments:
      #809 (Ljava/awt/event/ActionEvent;)V
      #828 REF_invokeVirtual ext/mods/commons/gui/InterfaceGS.lambda$createMenuBar$6:(Ljava/awt/event/ActionEvent;)V
      #809 (Ljava/awt/event/ActionEvent;)V
  10: #885 REF_invokeStatic java/lang/invoke/LambdaMetafactory.metafactory:(Ljava/lang/invoke/MethodHandles$Lookup;Ljava/lang/String;Ljava/lang/invoke/MethodType;Ljava/lang/invoke/MethodType;Ljava/lang/invoke/MethodHandle;Ljava/lang/invoke/MethodType;)Ljava/lang/invoke/CallSite;
    Method arguments:
      #809 (Ljava/awt/event/ActionEvent;)V
      #831 REF_invokeStatic ext/mods/commons/gui/InterfaceGS.lambda$createMenuBar$7:(Ljava/awt/event/ActionEvent;)V
      #809 (Ljava/awt/event/ActionEvent;)V
  11: #885 REF_invokeStatic java/lang/invoke/LambdaMetafactory.metafactory:(Ljava/lang/invoke/MethodHandles$Lookup;Ljava/lang/String;Ljava/lang/invoke/MethodType;Ljava/lang/invoke/MethodType;Ljava/lang/invoke/MethodHandle;Ljava/lang/invoke/MethodType;)Ljava/lang/invoke/CallSite;
    Method arguments:
      #809 (Ljava/awt/event/ActionEvent;)V
      #834 REF_invokeStatic ext/mods/commons/gui/InterfaceGS.lambda$createMenuBar$8:(Ljava/awt/event/ActionEvent;)V
      #809 (Ljava/awt/event/ActionEvent;)V
  12: #885 REF_invokeStatic java/lang/invoke/LambdaMetafactory.metafactory:(Ljava/lang/invoke/MethodHandles$Lookup;Ljava/lang/String;Ljava/lang/invoke/MethodType;Ljava/lang/invoke/MethodType;Ljava/lang/invoke/MethodHandle;Ljava/lang/invoke/MethodType;)Ljava/lang/invoke/CallSite;
    Method arguments:
      #809 (Ljava/awt/event/ActionEvent;)V
      #837 REF_invokeStatic ext/mods/commons/gui/InterfaceGS.lambda$createMenuBar$9:(Ljava/awt/event/ActionEvent;)V
      #809 (Ljava/awt/event/ActionEvent;)V
  13: #885 REF_invokeStatic java/lang/invoke/LambdaMetafactory.metafactory:(Ljava/lang/invoke/MethodHandles$Lookup;Ljava/lang/String;Ljava/lang/invoke/MethodType;Ljava/lang/invoke/MethodType;Ljava/lang/invoke/MethodHandle;Ljava/lang/invoke/MethodType;)Ljava/lang/invoke/CallSite;
    Method arguments:
      #809 (Ljava/awt/event/ActionEvent;)V
      #840 REF_invokeVirtual ext/mods/commons/gui/InterfaceGS.lambda$createMenuBar$10:(Ljava/awt/event/ActionEvent;)V
      #809 (Ljava/awt/event/ActionEvent;)V
  14: #885 REF_invokeStatic java/lang/invoke/LambdaMetafactory.metafactory:(Ljava/lang/invoke/MethodHandles$Lookup;Ljava/lang/String;Ljava/lang/invoke/MethodType;Ljava/lang/invoke/MethodType;Ljava/lang/invoke/MethodHandle;Ljava/lang/invoke/MethodType;)Ljava/lang/invoke/CallSite;
    Method arguments:
      #809 (Ljava/awt/event/ActionEvent;)V
      #843 REF_invokeVirtual ext/mods/commons/gui/InterfaceGS.lambda$createMenuBar$11:(Ljava/awt/event/ActionEvent;)V
      #809 (Ljava/awt/event/ActionEvent;)V
  15: #885 REF_invokeStatic java/lang/invoke/LambdaMetafactory.metafactory:(Ljava/lang/invoke/MethodHandles$Lookup;Ljava/lang/String;Ljava/lang/invoke/MethodType;Ljava/lang/invoke/MethodType;Ljava/lang/invoke/MethodHandle;Ljava/lang/invoke/MethodType;)Ljava/lang/invoke/CallSite;
    Method arguments:
      #809 (Ljava/awt/event/ActionEvent;)V
      #846 REF_invokeVirtual ext/mods/commons/gui/InterfaceGS.lambda$createMenuBar$12:(Ljava/awt/event/ActionEvent;)V
      #809 (Ljava/awt/event/ActionEvent;)V
  16: #885 REF_invokeStatic java/lang/invoke/LambdaMetafactory.metafactory:(Ljava/lang/invoke/MethodHandles$Lookup;Ljava/lang/String;Ljava/lang/invoke/MethodType;Ljava/lang/invoke/MethodType;Ljava/lang/invoke/MethodHandle;Ljava/lang/invoke/MethodType;)Ljava/lang/invoke/CallSite;
    Method arguments:
      #809 (Ljava/awt/event/ActionEvent;)V
      #849 REF_invokeVirtual ext/mods/commons/gui/InterfaceGS.lambda$createMenuBar$13:(Ljava/awt/event/ActionEvent;)V
      #809 (Ljava/awt/event/ActionEvent;)V
  17: #885 REF_invokeStatic java/lang/invoke/LambdaMetafactory.metafactory:(Ljava/lang/invoke/MethodHandles$Lookup;Ljava/lang/String;Ljava/lang/invoke/MethodType;Ljava/lang/invoke/MethodType;Ljava/lang/invoke/MethodHandle;Ljava/lang/invoke/MethodType;)Ljava/lang/invoke/CallSite;
    Method arguments:
      #809 (Ljava/awt/event/ActionEvent;)V
      #852 REF_invokeVirtual ext/mods/commons/gui/InterfaceGS.lambda$createMenuBar$14:(Ljava/awt/event/ActionEvent;)V
      #809 (Ljava/awt/event/ActionEvent;)V
  18: #885 REF_invokeStatic java/lang/invoke/LambdaMetafactory.metafactory:(Ljava/lang/invoke/MethodHandles$Lookup;Ljava/lang/String;Ljava/lang/invoke/MethodType;Ljava/lang/invoke/MethodType;Ljava/lang/invoke/MethodHandle;Ljava/lang/invoke/MethodType;)Ljava/lang/invoke/CallSite;
    Method arguments:
      #809 (Ljava/awt/event/ActionEvent;)V
      #855 REF_invokeVirtual ext/mods/commons/gui/InterfaceGS.lambda$createMenuBar$15:(Ljava/awt/event/ActionEvent;)V
      #809 (Ljava/awt/event/ActionEvent;)V
  19: #885 REF_invokeStatic java/lang/invoke/LambdaMetafactory.metafactory:(Ljava/lang/invoke/MethodHandles$Lookup;Ljava/lang/String;Ljava/lang/invoke/MethodType;Ljava/lang/invoke/MethodType;Ljava/lang/invoke/MethodHandle;Ljava/lang/invoke/MethodType;)Ljava/lang/invoke/CallSite;
    Method arguments:
      #809 (Ljava/awt/event/ActionEvent;)V
      #858 REF_invokeVirtual ext/mods/commons/gui/InterfaceGS.lambda$createMenuBar$16:(Ljava/awt/event/ActionEvent;)V
      #809 (Ljava/awt/event/ActionEvent;)V
  20: #885 REF_invokeStatic java/lang/invoke/LambdaMetafactory.metafactory:(Ljava/lang/invoke/MethodHandles$Lookup;Ljava/lang/String;Ljava/lang/invoke/MethodType;Ljava/lang/invoke/MethodType;Ljava/lang/invoke/MethodHandle;Ljava/lang/invoke/MethodType;)Ljava/lang/invoke/CallSite;
    Method arguments:
      #809 (Ljava/awt/event/ActionEvent;)V
      #861 REF_invokeVirtual ext/mods/commons/gui/InterfaceGS.lambda$createMenuBar$17:(Ljava/awt/event/ActionEvent;)V
      #809 (Ljava/awt/event/ActionEvent;)V
  21: #885 REF_invokeStatic java/lang/invoke/LambdaMetafactory.metafactory:(Ljava/lang/invoke/MethodHandles$Lookup;Ljava/lang/String;Ljava/lang/invoke/MethodType;Ljava/lang/invoke/MethodType;Ljava/lang/invoke/MethodHandle;Ljava/lang/invoke/MethodType;)Ljava/lang/invoke/CallSite;
    Method arguments:
      #809 (Ljava/awt/event/ActionEvent;)V
      #864 REF_invokeVirtual ext/mods/commons/gui/InterfaceGS.lambda$createMenuBar$18:(Ljava/awt/event/ActionEvent;)V
      #809 (Ljava/awt/event/ActionEvent;)V
  22: #885 REF_invokeStatic java/lang/invoke/LambdaMetafactory.metafactory:(Ljava/lang/invoke/MethodHandles$Lookup;Ljava/lang/String;Ljava/lang/invoke/MethodType;Ljava/lang/invoke/MethodType;Ljava/lang/invoke/MethodHandle;Ljava/lang/invoke/MethodType;)Ljava/lang/invoke/CallSite;
    Method arguments:
      #809 (Ljava/awt/event/ActionEvent;)V
      #867 REF_invokeVirtual ext/mods/commons/gui/InterfaceGS.lambda$createMenuBar$19:(Ljava/awt/event/ActionEvent;)V
      #809 (Ljava/awt/event/ActionEvent;)V
  23: #885 REF_invokeStatic java/lang/invoke/LambdaMetafactory.metafactory:(Ljava/lang/invoke/MethodHandles$Lookup;Ljava/lang/String;Ljava/lang/invoke/MethodType;Ljava/lang/invoke/MethodType;Ljava/lang/invoke/MethodHandle;Ljava/lang/invoke/MethodType;)Ljava/lang/invoke/CallSite;
    Method arguments:
      #809 (Ljava/awt/event/ActionEvent;)V
      #870 REF_invokeVirtual ext/mods/commons/gui/InterfaceGS.lambda$createMenuBar$20:(Ljava/awt/event/ActionEvent;)V
      #809 (Ljava/awt/event/ActionEvent;)V
  24: #885 REF_invokeStatic java/lang/invoke/LambdaMetafactory.metafactory:(Ljava/lang/invoke/MethodHandles$Lookup;Ljava/lang/String;Ljava/lang/invoke/MethodType;Ljava/lang/invoke/MethodType;Ljava/lang/invoke/MethodHandle;Ljava/lang/invoke/MethodType;)Ljava/lang/invoke/CallSite;
    Method arguments:
      #809 (Ljava/awt/event/ActionEvent;)V
      #873 REF_invokeVirtual ext/mods/commons/gui/InterfaceGS.lambda$createMenuBar$21:(Ljava/awt/event/ActionEvent;)V
      #809 (Ljava/awt/event/ActionEvent;)V
  25: #885 REF_invokeStatic java/lang/invoke/LambdaMetafactory.metafactory:(Ljava/lang/invoke/MethodHandles$Lookup;Ljava/lang/String;Ljava/lang/invoke/MethodType;Ljava/lang/invoke/MethodType;Ljava/lang/invoke/MethodHandle;Ljava/lang/invoke/MethodType;)Ljava/lang/invoke/CallSite;
    Method arguments:
      #809 (Ljava/awt/event/ActionEvent;)V
      #876 REF_invokeVirtual ext/mods/commons/gui/InterfaceGS.lambda$createMenuBar$22:(Ljava/lang/String;Ljava/awt/event/ActionEvent;)V
      #809 (Ljava/awt/event/ActionEvent;)V
  26: #885 REF_invokeStatic java/lang/invoke/LambdaMetafactory.metafactory:(Ljava/lang/invoke/MethodHandles$Lookup;Ljava/lang/String;Ljava/lang/invoke/MethodType;Ljava/lang/invoke/MethodType;Ljava/lang/invoke/MethodHandle;Ljava/lang/invoke/MethodType;)Ljava/lang/invoke/CallSite;
    Method arguments:
      #809 (Ljava/awt/event/ActionEvent;)V
      #879 REF_invokeStatic ext/mods/commons/gui/InterfaceGS.lambda$createMenuBar$23:(Ljava/awt/event/ActionEvent;)V
      #809 (Ljava/awt/event/ActionEvent;)V
  27: #885 REF_invokeStatic java/lang/invoke/LambdaMetafactory.metafactory:(Ljava/lang/invoke/MethodHandles$Lookup;Ljava/lang/String;Ljava/lang/invoke/MethodType;Ljava/lang/invoke/MethodType;Ljava/lang/invoke/MethodHandle;Ljava/lang/invoke/MethodType;)Ljava/lang/invoke/CallSite;
    Method arguments:
      #800 ()V
      #882 REF_invokeVirtual ext/mods/commons/gui/InterfaceGS.lambda$updateConsole$0:(Ljava/lang/String;)V
      #800 ()V
InnerClasses:
  public static #899= #214 of #325;       // ModernScrollBarUI=class ext/mods/commons/gui/ModernUI$ModernScrollBarUI of class ext/mods/commons/gui/ModernUI
  #266;                                   // class ext/mods/commons/gui/InterfaceGS$1
  #275;                                   // class ext/mods/commons/gui/InterfaceGS$2
  #287;                                   // class ext/mods/commons/gui/InterfaceGS$3
  #546;                                   // class ext/mods/commons/gui/InterfaceGS$4
  public static #902= #900 of #700;       // UncaughtExceptionHandler=class java/lang/Thread$UncaughtExceptionHandler of class java/lang/Thread
  public static final #907= #903 of #905; // Lookup=class java/lang/invoke/MethodHandles$Lookup of class java/lang/invoke/MethodHandles
