// Bytecode for: ext.mods.commons.gui.InterfaceLSInfo$1
// File: ext\mods\commons\gui\InterfaceLSInfo$1.class

Classfile /c:/Users/User/Desktop/BrProject/bin/main/ext/mods/commons/gui/InterfaceLSInfo$1.class
  Last modified 9 de jul de 2026; size 5180 bytes
  MD5 checksum 5920060ae144ef9cea982b30b66151ad
  Compiled from "InterfaceLSInfo.java"
class ext.mods.commons.gui.InterfaceLSInfo$1 extends java.util.TimerTask
  minor version: 0
  major version: 69
  flags: (0x0020) ACC_SUPER
  this_class: #8                          // ext/mods/commons/gui/InterfaceLSInfo$1
  super_class: #14                        // java/util/TimerTask
  interfaces: 0, fields: 1, methods: 3, attributes: 5
Constant pool:
    #1 = Methodref          #2.#3         // java/util/Objects.requireNonNull:(Ljava/lang/Object;)Ljava/lang/Object;
    #2 = Class              #4            // java/util/Objects
    #3 = NameAndType        #5:#6         // requireNonNull:(Ljava/lang/Object;)Ljava/lang/Object;
    #4 = Utf8               java/util/Objects
    #5 = Utf8               requireNonNull
    #6 = Utf8               (Ljava/lang/Object;)Ljava/lang/Object;
    #7 = Fieldref           #8.#9         // ext/mods/commons/gui/InterfaceLSInfo$1.this$0:Lext/mods/commons/gui/InterfaceLSInfo;
    #8 = Class              #10           // ext/mods/commons/gui/InterfaceLSInfo$1
    #9 = NameAndType        #11:#12       // this$0:Lext/mods/commons/gui/InterfaceLSInfo;
   #10 = Utf8               ext/mods/commons/gui/InterfaceLSInfo$1
   #11 = Utf8               this$0
   #12 = Utf8               Lext/mods/commons/gui/InterfaceLSInfo;
   #13 = Methodref          #14.#15       // java/util/TimerTask."<init>":()V
   #14 = Class              #16           // java/util/TimerTask
   #15 = NameAndType        #17:#18       // "<init>":()V
   #16 = Utf8               java/util/TimerTask
   #17 = Utf8               <init>
   #18 = Utf8               ()V
   #19 = Methodref          #20.#21       // java/lang/Runtime.getRuntime:()Ljava/lang/Runtime;
   #20 = Class              #22           // java/lang/Runtime
   #21 = NameAndType        #23:#24       // getRuntime:()Ljava/lang/Runtime;
   #22 = Utf8               java/lang/Runtime
   #23 = Utf8               getRuntime
   #24 = Utf8               ()Ljava/lang/Runtime;
   #25 = Methodref          #20.#26       // java/lang/Runtime.totalMemory:()J
   #26 = NameAndType        #27:#28       // totalMemory:()J
   #27 = Utf8               totalMemory
   #28 = Utf8               ()J
   #29 = Methodref          #20.#30       // java/lang/Runtime.freeMemory:()J
   #30 = NameAndType        #31:#28       // freeMemory:()J
   #31 = Utf8               freeMemory
   #32 = Methodref          #33.#34       // java/lang/System.currentTimeMillis:()J
   #33 = Class              #35           // java/lang/System
   #34 = NameAndType        #36:#28       // currentTimeMillis:()J
   #35 = Utf8               java/lang/System
   #36 = Utf8               currentTimeMillis
   #37 = Fieldref           #38.#39       // ext/mods/commons/gui/InterfaceLSInfo.START_TIME:J
   #38 = Class              #40           // ext/mods/commons/gui/InterfaceLSInfo
   #39 = NameAndType        #41:#42       // START_TIME:J
   #40 = Utf8               ext/mods/commons/gui/InterfaceLSInfo
   #41 = Utf8               START_TIME
   #42 = Utf8               J
   #43 = Methodref          #38.#44       // ext/mods/commons/gui/InterfaceLSInfo.getDurationBreakdown:(J)Ljava/lang/String;
   #44 = NameAndType        #45:#46       // getDurationBreakdown:(J)Ljava/lang/String;
   #45 = Utf8               getDurationBreakdown
   #46 = Utf8               (J)Ljava/lang/String;
   #47 = Methodref          #48.#49       // ext/mods/loginserver/data/manager/GameServerManager.getInstance:()Lext/mods/loginserver/data/manager/GameServerManager;
   #48 = Class              #50           // ext/mods/loginserver/data/manager/GameServerManager
   #49 = NameAndType        #51:#52       // getInstance:()Lext/mods/loginserver/data/manager/GameServerManager;
   #50 = Utf8               ext/mods/loginserver/data/manager/GameServerManager
   #51 = Utf8               getInstance
   #52 = Utf8               ()Lext/mods/loginserver/data/manager/GameServerManager;
   #53 = Methodref          #48.#54       // ext/mods/loginserver/data/manager/GameServerManager.getRegisteredGameServers:()Ljava/util/Map;
   #54 = NameAndType        #55:#56       // getRegisteredGameServers:()Ljava/util/Map;
   #55 = Utf8               getRegisteredGameServers
   #56 = Utf8               ()Ljava/util/Map;
   #57 = InterfaceMethodref #58.#59       // java/util/Map.size:()I
   #58 = Class              #60           // java/util/Map
   #59 = NameAndType        #61:#62       // size:()I
   #60 = Utf8               java/util/Map
   #61 = Utf8               size
   #62 = Utf8               ()I
   #63 = InterfaceMethodref #58.#64       // java/util/Map.values:()Ljava/util/Collection;
   #64 = NameAndType        #65:#66       // values:()Ljava/util/Collection;
   #65 = Utf8               values
   #66 = Utf8               ()Ljava/util/Collection;
   #67 = InterfaceMethodref #68.#69       // java/util/Collection.stream:()Ljava/util/stream/Stream;
   #68 = Class              #70           // java/util/Collection
   #69 = NameAndType        #71:#72       // stream:()Ljava/util/stream/Stream;
   #70 = Utf8               java/util/Collection
   #71 = Utf8               stream
   #72 = Utf8               ()Ljava/util/stream/Stream;
   #73 = InvokeDynamic      #0:#74        // #0:test:()Ljava/util/function/Predicate;
   #74 = NameAndType        #75:#76       // test:()Ljava/util/function/Predicate;
   #75 = Utf8               test
   #76 = Utf8               ()Ljava/util/function/Predicate;
   #77 = InterfaceMethodref #78.#79       // java/util/stream/Stream.filter:(Ljava/util/function/Predicate;)Ljava/util/stream/Stream;
   #78 = Class              #80           // java/util/stream/Stream
   #79 = NameAndType        #81:#82       // filter:(Ljava/util/function/Predicate;)Ljava/util/stream/Stream;
   #80 = Utf8               java/util/stream/Stream
   #81 = Utf8               filter
   #82 = Utf8               (Ljava/util/function/Predicate;)Ljava/util/stream/Stream;
   #83 = InterfaceMethodref #78.#84       // java/util/stream/Stream.count:()J
   #84 = NameAndType        #85:#28       // count:()J
   #85 = Utf8               count
   #86 = Class              #87           // java/lang/ExceptionInInitializerError
   #87 = Utf8               java/lang/ExceptionInInitializerError
   #88 = Class              #89           // java/lang/NoClassDefFoundError
   #89 = Utf8               java/lang/NoClassDefFoundError
   #90 = Class              #91           // java/lang/Exception
   #91 = Utf8               java/lang/Exception
   #92 = InvokeDynamic      #1:#93        // #1:makeConcatWithConstants:(JI)Ljava/lang/String;
   #93 = NameAndType        #94:#95       // makeConcatWithConstants:(JI)Ljava/lang/String;
   #94 = Utf8               makeConcatWithConstants
   #95 = Utf8               (JI)Ljava/lang/String;
   #96 = Methodref          #97.#98       // ext/mods/loginserver/LoginController.getInstance:()Lext/mods/loginserver/LoginController;
   #97 = Class              #99           // ext/mods/loginserver/LoginController
   #98 = NameAndType        #51:#100      // getInstance:()Lext/mods/loginserver/LoginController;
   #99 = Utf8               ext/mods/loginserver/LoginController
  #100 = Utf8               ()Lext/mods/loginserver/LoginController;
  #101 = Methodref          #97.#102      // ext/mods/loginserver/LoginController.getOnlinePlayerCount:()I
  #102 = NameAndType        #103:#62      // getOnlinePlayerCount:()I
  #103 = Utf8               getOnlinePlayerCount
  #104 = Methodref          #105.#106     // ext/mods/loginserver/data/sql/AccountTable.getInstance:()Lext/mods/loginserver/data/sql/AccountTable;
  #105 = Class              #107          // ext/mods/loginserver/data/sql/AccountTable
  #106 = NameAndType        #51:#108      // getInstance:()Lext/mods/loginserver/data/sql/AccountTable;
  #107 = Utf8               ext/mods/loginserver/data/sql/AccountTable
  #108 = Utf8               ()Lext/mods/loginserver/data/sql/AccountTable;
  #109 = Methodref          #105.#110     // ext/mods/loginserver/data/sql/AccountTable.getAccountCount:()I
  #110 = NameAndType        #111:#62      // getAccountCount:()I
  #111 = Utf8               getAccountCount
  #112 = Methodref          #113.#114     // ext/mods/loginserver/data/manager/IpBanManager.getInstance:()Lext/mods/loginserver/data/manager/IpBanManager;
  #113 = Class              #115          // ext/mods/loginserver/data/manager/IpBanManager
  #114 = NameAndType        #51:#116      // getInstance:()Lext/mods/loginserver/data/manager/IpBanManager;
  #115 = Utf8               ext/mods/loginserver/data/manager/IpBanManager
  #116 = Utf8               ()Lext/mods/loginserver/data/manager/IpBanManager;
  #117 = Methodref          #113.#118     // ext/mods/loginserver/data/manager/IpBanManager.getBannedIps:()Ljava/util/Map;
  #118 = NameAndType        #119:#56      // getBannedIps:()Ljava/util/Map;
  #119 = Utf8               getBannedIps
  #120 = InvokeDynamic      #2:#121       // #2:run:(Lext/mods/commons/gui/InterfaceLSInfo$1;Ljava/lang/String;Ljava/lang/String;IIIJJ)Ljava/lang/Runnable;
  #121 = NameAndType        #122:#123     // run:(Lext/mods/commons/gui/InterfaceLSInfo$1;Ljava/lang/String;Ljava/lang/String;IIIJJ)Ljava/lang/Runnable;
  #122 = Utf8               run
  #123 = Utf8               (Lext/mods/commons/gui/InterfaceLSInfo$1;Ljava/lang/String;Ljava/lang/String;IIIJJ)Ljava/lang/Runnable;
  #124 = Methodref          #125.#126     // javax/swing/SwingUtilities.invokeLater:(Ljava/lang/Runnable;)V
  #125 = Class              #127          // javax/swing/SwingUtilities
  #126 = NameAndType        #128:#129     // invokeLater:(Ljava/lang/Runnable;)V
  #127 = Utf8               javax/swing/SwingUtilities
  #128 = Utf8               invokeLater
  #129 = Utf8               (Ljava/lang/Runnable;)V
  #130 = Fieldref           #38.#131      // ext/mods/commons/gui/InterfaceLSInfo.rowUptime:Lext/mods/commons/gui/InterfaceLSInfo$InfoRow;
  #131 = NameAndType        #132:#133     // rowUptime:Lext/mods/commons/gui/InterfaceLSInfo$InfoRow;
  #132 = Utf8               rowUptime
  #133 = Utf8               Lext/mods/commons/gui/InterfaceLSInfo$InfoRow;
  #134 = Methodref          #135.#136     // ext/mods/commons/gui/InterfaceLSInfo$InfoRow.setValue:(Ljava/lang/String;)V
  #135 = Class              #137          // ext/mods/commons/gui/InterfaceLSInfo$InfoRow
  #136 = NameAndType        #138:#139     // setValue:(Ljava/lang/String;)V
  #137 = Utf8               ext/mods/commons/gui/InterfaceLSInfo$InfoRow
  #138 = Utf8               setValue
  #139 = Utf8               (Ljava/lang/String;)V
  #140 = Fieldref           #38.#141      // ext/mods/commons/gui/InterfaceLSInfo.rowGSLink:Lext/mods/commons/gui/InterfaceLSInfo$InfoRow;
  #141 = NameAndType        #142:#133     // rowGSLink:Lext/mods/commons/gui/InterfaceLSInfo$InfoRow;
  #142 = Utf8               rowGSLink
  #143 = Fieldref           #38.#144      // ext/mods/commons/gui/InterfaceLSInfo.rowSessions:Lext/mods/commons/gui/InterfaceLSInfo$InfoRow;
  #144 = NameAndType        #145:#133     // rowSessions:Lext/mods/commons/gui/InterfaceLSInfo$InfoRow;
  #145 = Utf8               rowSessions
  #146 = Methodref          #147.#148     // java/lang/String.valueOf:(I)Ljava/lang/String;
  #147 = Class              #149          // java/lang/String
  #148 = NameAndType        #150:#151     // valueOf:(I)Ljava/lang/String;
  #149 = Utf8               java/lang/String
  #150 = Utf8               valueOf
  #151 = Utf8               (I)Ljava/lang/String;
  #152 = Fieldref           #38.#153      // ext/mods/commons/gui/InterfaceLSInfo.rowAccounts:Lext/mods/commons/gui/InterfaceLSInfo$InfoRow;
  #153 = NameAndType        #154:#133     // rowAccounts:Lext/mods/commons/gui/InterfaceLSInfo$InfoRow;
  #154 = Utf8               rowAccounts
  #155 = String             #156          // %,d
  #156 = Utf8               %,d
  #157 = Class              #158          // java/lang/Object
  #158 = Utf8               java/lang/Object
  #159 = Methodref          #160.#161     // java/lang/Integer.valueOf:(I)Ljava/lang/Integer;
  #160 = Class              #162          // java/lang/Integer
  #161 = NameAndType        #150:#163     // valueOf:(I)Ljava/lang/Integer;
  #162 = Utf8               java/lang/Integer
  #163 = Utf8               (I)Ljava/lang/Integer;
  #164 = Methodref          #147.#165     // java/lang/String.format:(Ljava/lang/String;[Ljava/lang/Object;)Ljava/lang/String;
  #165 = NameAndType        #166:#167     // format:(Ljava/lang/String;[Ljava/lang/Object;)Ljava/lang/String;
  #166 = Utf8               format
  #167 = Utf8               (Ljava/lang/String;[Ljava/lang/Object;)Ljava/lang/String;
  #168 = Fieldref           #38.#169      // ext/mods/commons/gui/InterfaceLSInfo.rowBannedIPs:Lext/mods/commons/gui/InterfaceLSInfo$InfoRow;
  #169 = NameAndType        #170:#133     // rowBannedIPs:Lext/mods/commons/gui/InterfaceLSInfo$InfoRow;
  #170 = Utf8               rowBannedIPs
  #171 = Fieldref           #38.#172      // ext/mods/commons/gui/InterfaceLSInfo.barMemory:Lext/mods/commons/gui/InterfaceLSInfo$MetricBar;
  #172 = NameAndType        #173:#174     // barMemory:Lext/mods/commons/gui/InterfaceLSInfo$MetricBar;
  #173 = Utf8               barMemory
  #174 = Utf8               Lext/mods/commons/gui/InterfaceLSInfo$MetricBar;
  #175 = String             #176          // Memory
  #176 = Utf8               Memory
  #177 = Methodref          #38.#178      // ext/mods/commons/gui/InterfaceLSInfo.formatMemorySize:(J)Ljava/lang/String;
  #178 = NameAndType        #179:#46      // formatMemorySize:(J)Ljava/lang/String;
  #179 = Utf8               formatMemorySize
  #180 = InvokeDynamic      #3:#181       // #3:makeConcatWithConstants:(Ljava/lang/String;Ljava/lang/String;)Ljava/lang/String;
  #181 = NameAndType        #94:#182      // makeConcatWithConstants:(Ljava/lang/String;Ljava/lang/String;)Ljava/lang/String;
  #182 = Utf8               (Ljava/lang/String;Ljava/lang/String;)Ljava/lang/String;
  #183 = Long               1024l
  #185 = Methodref          #186.#187     // ext/mods/commons/gui/InterfaceLSInfo$MetricBar.set:(Ljava/lang/String;Ljava/lang/String;II)V
  #186 = Class              #188          // ext/mods/commons/gui/InterfaceLSInfo$MetricBar
  #187 = NameAndType        #189:#190     // set:(Ljava/lang/String;Ljava/lang/String;II)V
  #188 = Utf8               ext/mods/commons/gui/InterfaceLSInfo$MetricBar
  #189 = Utf8               set
  #190 = Utf8               (Ljava/lang/String;Ljava/lang/String;II)V
  #191 = Utf8               (Lext/mods/commons/gui/InterfaceLSInfo;)V
  #192 = Utf8               Code
  #193 = Utf8               LineNumberTable
  #194 = Utf8               LocalVariableTable
  #195 = Utf8               this
  #196 = Utf8               Lext/mods/commons/gui/InterfaceLSInfo$1;
  #197 = Utf8               MethodParameters
  #198 = Utf8               gsm
  #199 = Utf8               Lext/mods/loginserver/data/manager/GameServerManager;
  #200 = Utf8               e
  #201 = Utf8               Ljava/lang/LinkageError;
  #202 = Utf8               Ljava/lang/Exception;
  #203 = Utf8               rt
  #204 = Utf8               Ljava/lang/Runtime;
  #205 = Utf8               usedMemory
  #206 = Utf8               uptimeStr
  #207 = Utf8               Ljava/lang/String;
  #208 = Utf8               totalGS
  #209 = Utf8               I
  #210 = Utf8               onlineGS
  #211 = Utf8               gsStatus
  #212 = Utf8               sessionsCount
  #213 = Utf8               accCount
  #214 = Utf8               bansCount
  #215 = Utf8               StackMapTable
  #216 = Class              #217          // java/lang/LinkageError
  #217 = Utf8               java/lang/LinkageError
  #218 = Utf8               lambda$run$0
  #219 = Utf8               (Ljava/lang/String;Ljava/lang/String;IIIJJ)V
  #220 = Utf8               SourceFile
  #221 = Utf8               InterfaceLSInfo.java
  #222 = Utf8               EnclosingMethod
  #223 = NameAndType        #224:#18      // startUpdateTask:()V
  #224 = Utf8               startUpdateTask
  #225 = Utf8               NestHost
  #226 = Utf8               BootstrapMethods
  #227 = MethodType         #228          //  (Ljava/lang/Object;)Z
  #228 = Utf8               (Ljava/lang/Object;)Z
  #229 = MethodHandle       5:#230        // REF_invokeVirtual ext/mods/loginserver/model/GameServerInfo.isAuthed:()Z
  #230 = Methodref          #231.#232     // ext/mods/loginserver/model/GameServerInfo.isAuthed:()Z
  #231 = Class              #233          // ext/mods/loginserver/model/GameServerInfo
  #232 = NameAndType        #234:#235     // isAuthed:()Z
  #233 = Utf8               ext/mods/loginserver/model/GameServerInfo
  #234 = Utf8               isAuthed
  #235 = Utf8               ()Z
  #236 = MethodType         #237          //  (Lext/mods/loginserver/model/GameServerInfo;)Z
  #237 = Utf8               (Lext/mods/loginserver/model/GameServerInfo;)Z
  #238 = String             #239          // \u0001 / \u0001 Online
  #239 = Utf8               \u0001 / \u0001 Online
  #240 = MethodType         #18           //  ()V
  #241 = MethodHandle       5:#242        // REF_invokeVirtual ext/mods/commons/gui/InterfaceLSInfo$1.lambda$run$0:(Ljava/lang/String;Ljava/lang/String;IIIJJ)V
  #242 = Methodref          #8.#243       // ext/mods/commons/gui/InterfaceLSInfo$1.lambda$run$0:(Ljava/lang/String;Ljava/lang/String;IIIJJ)V
  #243 = NameAndType        #218:#219     // lambda$run$0:(Ljava/lang/String;Ljava/lang/String;IIIJJ)V
  #244 = String             #245          // \u0001 / \u0001
  #245 = Utf8               \u0001 / \u0001
  #246 = MethodHandle       6:#247        // REF_invokeStatic java/lang/invoke/LambdaMetafactory.metafactory:(Ljava/lang/invoke/MethodHandles$Lookup;Ljava/lang/String;Ljava/lang/invoke/MethodType;Ljava/lang/invoke/MethodType;Ljava/lang/invoke/MethodHandle;Ljava/lang/invoke/MethodType;)Ljava/lang/invoke/CallSite;
  #247 = Methodref          #248.#249     // java/lang/invoke/LambdaMetafactory.metafactory:(Ljava/lang/invoke/MethodHandles$Lookup;Ljava/lang/String;Ljava/lang/invoke/MethodType;Ljava/lang/invoke/MethodType;Ljava/lang/invoke/MethodHandle;Ljava/lang/invoke/MethodType;)Ljava/lang/invoke/CallSite;
  #248 = Class              #250          // java/lang/invoke/LambdaMetafactory
  #249 = NameAndType        #251:#252     // metafactory:(Ljava/lang/invoke/MethodHandles$Lookup;Ljava/lang/String;Ljava/lang/invoke/MethodType;Ljava/lang/invoke/MethodType;Ljava/lang/invoke/MethodHandle;Ljava/lang/invoke/MethodType;)Ljava/lang/invoke/CallSite;
  #250 = Utf8               java/lang/invoke/LambdaMetafactory
  #251 = Utf8               metafactory
  #252 = Utf8               (Ljava/lang/invoke/MethodHandles$Lookup;Ljava/lang/String;Ljava/lang/invoke/MethodType;Ljava/lang/invoke/MethodType;Ljava/lang/invoke/MethodHandle;Ljava/lang/invoke/MethodType;)Ljava/lang/invoke/CallSite;
  #253 = MethodHandle       6:#254        // REF_invokeStatic java/lang/invoke/StringConcatFactory.makeConcatWithConstants:(Ljava/lang/invoke/MethodHandles$Lookup;Ljava/lang/String;Ljava/lang/invoke/MethodType;Ljava/lang/String;[Ljava/lang/Object;)Ljava/lang/invoke/CallSite;
  #254 = Methodref          #255.#256     // java/lang/invoke/StringConcatFactory.makeConcatWithConstants:(Ljava/lang/invoke/MethodHandles$Lookup;Ljava/lang/String;Ljava/lang/invoke/MethodType;Ljava/lang/String;[Ljava/lang/Object;)Ljava/lang/invoke/CallSite;
  #255 = Class              #257          // java/lang/invoke/StringConcatFactory
  #256 = NameAndType        #94:#258      // makeConcatWithConstants:(Ljava/lang/invoke/MethodHandles$Lookup;Ljava/lang/String;Ljava/lang/invoke/MethodType;Ljava/lang/String;[Ljava/lang/Object;)Ljava/lang/invoke/CallSite;
  #257 = Utf8               java/lang/invoke/StringConcatFactory
  #258 = Utf8               (Ljava/lang/invoke/MethodHandles$Lookup;Ljava/lang/String;Ljava/lang/invoke/MethodType;Ljava/lang/String;[Ljava/lang/Object;)Ljava/lang/invoke/CallSite;
  #259 = Utf8               InnerClasses
  #260 = Utf8               InfoRow
  #261 = Utf8               MetricBar
  #262 = Class              #263          // java/lang/invoke/MethodHandles$Lookup
  #263 = Utf8               java/lang/invoke/MethodHandles$Lookup
  #264 = Class              #265          // java/lang/invoke/MethodHandles
  #265 = Utf8               java/lang/invoke/MethodHandles
  #266 = Utf8               Lookup
{
  final ext.mods.commons.gui.InterfaceLSInfo this$0;
    descriptor: Lext/mods/commons/gui/InterfaceLSInfo;
    flags: (0x1010) ACC_FINAL, ACC_SYNTHETIC

  ext.mods.commons.gui.InterfaceLSInfo$1(ext.mods.commons.gui.InterfaceLSInfo);
    descriptor: (Lext/mods/commons/gui/InterfaceLSInfo;)V
    flags: (0x0000)
    Code:
      stack=3, locals=2, args_size=2
         0: aload_0
         1: aload_1
         2: dup
         3: invokestatic  #1                  // Method java/util/Objects.requireNonNull:(Ljava/lang/Object;)Ljava/lang/Object;
         6: pop
         7: putfield      #7                  // Field this$0:Lext/mods/commons/gui/InterfaceLSInfo;
        10: aload_0
        11: invokespecial #13                 // Method java/util/TimerTask."<init>":()V
        14: return
      LineNumberTable:
        line 84: 0
      LocalVariableTable:
        Start  Length  Slot  Name   Signature
            0      15     0  this   Lext/mods/commons/gui/InterfaceLSInfo$1;
            0      15     1 this$0   Lext/mods/commons/gui/InterfaceLSInfo;
    MethodParameters:
      Name                           Flags
      <no name>                      final mandated

  public void run();
    descriptor: ()V
    flags: (0x0001) ACC_PUBLIC
    Code:
      stack=10, locals=14, args_size=1
         0: invokestatic  #19                 // Method java/lang/Runtime.getRuntime:()Ljava/lang/Runtime;
         3: astore_1
         4: aload_1
         5: invokevirtual #25                 // Method java/lang/Runtime.totalMemory:()J
         8: lstore_2
         9: lload_2
        10: aload_1
        11: invokevirtual #29                 // Method java/lang/Runtime.freeMemory:()J
        14: lsub
        15: lstore        4
        17: invokestatic  #32                 // Method java/lang/System.currentTimeMillis:()J
        20: getstatic     #37                 // Field ext/mods/commons/gui/InterfaceLSInfo.START_TIME:J
        23: lsub
        24: invokestatic  #43                 // Method ext/mods/commons/gui/InterfaceLSInfo.getDurationBreakdown:(J)Ljava/lang/String;
        27: astore        6
        29: iconst_0
        30: istore        7
        32: lconst_0
        33: lstore        8
        35: invokestatic  #47                 // Method ext/mods/loginserver/data/manager/GameServerManager.getInstance:()Lext/mods/loginserver/data/manager/GameServerManager;
        38: astore        10
        40: aload         10
        42: ifnull        89
        45: aload         10
        47: invokevirtual #53                 // Method ext/mods/loginserver/data/manager/GameServerManager.getRegisteredGameServers:()Ljava/util/Map;
        50: invokeinterface #57,  1           // InterfaceMethod java/util/Map.size:()I
        55: istore        7
        57: aload         10
        59: invokevirtual #53                 // Method ext/mods/loginserver/data/manager/GameServerManager.getRegisteredGameServers:()Ljava/util/Map;
        62: invokeinterface #63,  1           // InterfaceMethod java/util/Map.values:()Ljava/util/Collection;
        67: invokeinterface #67,  1           // InterfaceMethod java/util/Collection.stream:()Ljava/util/stream/Stream;
        72: invokedynamic #73,  0             // InvokeDynamic #0:test:()Ljava/util/function/Predicate;
        77: invokeinterface #77,  2           // InterfaceMethod java/util/stream/Stream.filter:(Ljava/util/function/Predicate;)Ljava/util/stream/Stream;
        82: invokeinterface #83,  1           // InterfaceMethod java/util/stream/Stream.count:()J
        87: lstore        8
        89: goto          111
        92: astore        10
        94: iconst_0
        95: istore        7
        97: lconst_0
        98: lstore        8
       100: goto          111
       103: astore        10
       105: iconst_0
       106: istore        7
       108: lconst_0
       109: lstore        8
       111: lload         8
       113: iload         7
       115: invokedynamic #92,  0             // InvokeDynamic #1:makeConcatWithConstants:(JI)Ljava/lang/String;
       120: astore        10
       122: invokestatic  #96                 // Method ext/mods/loginserver/LoginController.getInstance:()Lext/mods/loginserver/LoginController;
       125: invokevirtual #101                // Method ext/mods/loginserver/LoginController.getOnlinePlayerCount:()I
       128: istore        11
       130: invokestatic  #104                // Method ext/mods/loginserver/data/sql/AccountTable.getInstance:()Lext/mods/loginserver/data/sql/AccountTable;
       133: invokevirtual #109                // Method ext/mods/loginserver/data/sql/AccountTable.getAccountCount:()I
       136: istore        12
       138: invokestatic  #112                // Method ext/mods/loginserver/data/manager/IpBanManager.getInstance:()Lext/mods/loginserver/data/manager/IpBanManager;
       141: invokevirtual #117                // Method ext/mods/loginserver/data/manager/IpBanManager.getBannedIps:()Ljava/util/Map;
       144: invokeinterface #57,  1           // InterfaceMethod java/util/Map.size:()I
       149: istore        13
       151: aload_0
       152: aload         6
       154: aload         10
       156: iload         11
       158: iload         12
       160: iload         13
       162: lload         4
       164: lload_2
       165: invokedynamic #120,  0            // InvokeDynamic #2:run:(Lext/mods/commons/gui/InterfaceLSInfo$1;Ljava/lang/String;Ljava/lang/String;IIIJJ)Ljava/lang/Runnable;
       170: invokestatic  #124                // Method javax/swing/SwingUtilities.invokeLater:(Ljava/lang/Runnable;)V
       173: goto          177
       176: astore_1
       177: return
      Exception table:
         from    to  target type
            35    89    92   Class java/lang/ExceptionInInitializerError
            35    89    92   Class java/lang/NoClassDefFoundError
            35    89   103   Class java/lang/Exception
             0   173   176   Class java/lang/Exception
      LineNumberTable:
        line 88: 0
        line 89: 4
        line 90: 9
        line 92: 17
        line 94: 29
        line 95: 32
        line 97: 35
        line 98: 40
        line 99: 45
        line 100: 57
        line 101: 62
        line 102: 67
        line 103: 77
        line 104: 82
        line 112: 89
        line 106: 92
        line 107: 94
        line 108: 97
        line 112: 100
        line 109: 103
        line 110: 105
        line 111: 108
        line 114: 111
        line 116: 122
        line 117: 130
        line 118: 138
        line 120: 151
        line 134: 173
        line 135: 177
      LocalVariableTable:
        Start  Length  Slot  Name   Signature
           40      49    10   gsm   Lext/mods/loginserver/data/manager/GameServerManager;
           94       6    10     e   Ljava/lang/LinkageError;
          105       6    10     e   Ljava/lang/Exception;
            4     169     1    rt   Ljava/lang/Runtime;
            9     164     2 totalMemory   J
           17     156     4 usedMemory   J
           29     144     6 uptimeStr   Ljava/lang/String;
           32     141     7 totalGS   I
           35     138     8 onlineGS   J
          122      51    10 gsStatus   Ljava/lang/String;
          130      43    11 sessionsCount   I
          138      35    12 accCount   I
          151      22    13 bansCount   I
            0     178     0  this   Lext/mods/commons/gui/InterfaceLSInfo$1;
      StackMapTable: number_of_entries = 6
        frame_type = 255 /* full_frame */
          offset_delta = 89
          locals = [ class ext/mods/commons/gui/InterfaceLSInfo$1, class java/lang/Runtime, long, long, class java/lang/String, int, long ]
          stack = []
        frame_type = 66 /* same_locals_1_stack_item */
          stack = [ class java/lang/LinkageError ]
        frame_type = 74 /* same_locals_1_stack_item */
          stack = [ class java/lang/Exception ]
        frame_type = 7 /* same */
        frame_type = 255 /* full_frame */
          offset_delta = 64
          locals = [ class ext/mods/commons/gui/InterfaceLSInfo$1 ]
          stack = [ class java/lang/Exception ]
        frame_type = 0 /* same */
}
SourceFile: "InterfaceLSInfo.java"
EnclosingMethod: #38.#223               // ext.mods.commons.gui.InterfaceLSInfo.startUpdateTask
NestHost: class ext/mods/commons/gui/InterfaceLSInfo
BootstrapMethods:
  0: #246 REF_invokeStatic java/lang/invoke/LambdaMetafactory.metafactory:(Ljava/lang/invoke/MethodHandles$Lookup;Ljava/lang/String;Ljava/lang/invoke/MethodType;Ljava/lang/invoke/MethodType;Ljava/lang/invoke/MethodHandle;Ljava/lang/invoke/MethodType;)Ljava/lang/invoke/CallSite;
    Method arguments:
      #227 (Ljava/lang/Object;)Z
      #229 REF_invokeVirtual ext/mods/loginserver/model/GameServerInfo.isAuthed:()Z
      #236 (Lext/mods/loginserver/model/GameServerInfo;)Z
  1: #253 REF_invokeStatic java/lang/invoke/StringConcatFactory.makeConcatWithConstants:(Ljava/lang/invoke/MethodHandles$Lookup;Ljava/lang/String;Ljava/lang/invoke/MethodType;Ljava/lang/String;[Ljava/lang/Object;)Ljava/lang/invoke/CallSite;
    Method arguments:
      #238 \u0001 / \u0001 Online
  2: #246 REF_invokeStatic java/lang/invoke/LambdaMetafactory.metafactory:(Ljava/lang/invoke/MethodHandles$Lookup;Ljava/lang/String;Ljava/lang/invoke/MethodType;Ljava/lang/invoke/MethodType;Ljava/lang/invoke/MethodHandle;Ljava/lang/invoke/MethodType;)Ljava/lang/invoke/CallSite;
    Method arguments:
      #240 ()V
      #241 REF_invokeVirtual ext/mods/commons/gui/InterfaceLSInfo$1.lambda$run$0:(Ljava/lang/String;Ljava/lang/String;IIIJJ)V
      #240 ()V
  3: #253 REF_invokeStatic java/lang/invoke/StringConcatFactory.makeConcatWithConstants:(Ljava/lang/invoke/MethodHandles$Lookup;Ljava/lang/String;Ljava/lang/invoke/MethodType;Ljava/lang/String;[Ljava/lang/Object;)Ljava/lang/invoke/CallSite;
    Method arguments:
      #244 \u0001 / \u0001
InnerClasses:
  #8;                                     // class ext/mods/commons/gui/InterfaceLSInfo$1
  public static final #266= #262 of #264; // Lookup=class java/lang/invoke/MethodHandles$Lookup of class java/lang/invoke/MethodHandles
