// Bytecode for: ext.mods.commons.gui.InterfaceLS
// File: ext\mods\commons\gui\InterfaceLS.class

Classfile /c:/Users/User/Desktop/BrProject/bin/main/ext/mods/commons/gui/InterfaceLS.class
  Last modified 9 de jul de 2026; size 11440 bytes
  MD5 checksum ffed221d72d2ac1b3121ab9c5ad2f088
  Compiled from "InterfaceLS.java"
public class ext.mods.commons.gui.InterfaceLS
  minor version: 0
  major version: 69
  flags: (0x0021) ACC_PUBLIC, ACC_SUPER
  this_class: #13                         // ext/mods/commons/gui/InterfaceLS
  super_class: #2                         // java/lang/Object
  interfaces: 0, fields: 10, methods: 17, attributes: 4
Constant pool:
    #1 = Methodref          #2.#3         // java/lang/Object."<init>":()V
    #2 = Class              #4            // java/lang/Object
    #3 = NameAndType        #5:#6         // "<init>":()V
    #4 = Utf8               java/lang/Object
    #5 = Utf8               <init>
    #6 = Utf8               ()V
    #7 = Methodref          #8.#9         // ext/mods/commons/gui/ThemeManager.applyTheme:()V
    #8 = Class              #10           // ext/mods/commons/gui/ThemeManager
    #9 = NameAndType        #11:#6        // applyTheme:()V
   #10 = Utf8               ext/mods/commons/gui/ThemeManager
   #11 = Utf8               applyTheme
   #12 = Methodref          #13.#14       // ext/mods/commons/gui/InterfaceLS.initialize:()V
   #13 = Class              #15           // ext/mods/commons/gui/InterfaceLS
   #14 = NameAndType        #16:#6        // initialize:()V
   #15 = Utf8               ext/mods/commons/gui/InterfaceLS
   #16 = Utf8               initialize
   #17 = Class              #18           // javax/swing/JTextArea
   #18 = Utf8               javax/swing/JTextArea
   #19 = Methodref          #17.#3        // javax/swing/JTextArea."<init>":()V
   #20 = Fieldref           #13.#21       // ext/mods/commons/gui/InterfaceLS.console:Ljavax/swing/JTextArea;
   #21 = NameAndType        #22:#23       // console:Ljavax/swing/JTextArea;
   #22 = Utf8               console
   #23 = Utf8               Ljavax/swing/JTextArea;
   #24 = Methodref          #17.#25       // javax/swing/JTextArea.setEditable:(Z)V
   #25 = NameAndType        #26:#27       // setEditable:(Z)V
   #26 = Utf8               setEditable
   #27 = Utf8               (Z)V
   #28 = Methodref          #17.#29       // javax/swing/JTextArea.setLineWrap:(Z)V
   #29 = NameAndType        #30:#27       // setLineWrap:(Z)V
   #30 = Utf8               setLineWrap
   #31 = Methodref          #17.#32       // javax/swing/JTextArea.setWrapStyleWord:(Z)V
   #32 = NameAndType        #33:#27       // setWrapStyleWord:(Z)V
   #33 = Utf8               setWrapStyleWord
   #34 = Fieldref           #35.#36       // javax/swing/DropMode.INSERT:Ljavax/swing/DropMode;
   #35 = Class              #37           // javax/swing/DropMode
   #36 = NameAndType        #38:#39       // INSERT:Ljavax/swing/DropMode;
   #37 = Utf8               javax/swing/DropMode
   #38 = Utf8               INSERT
   #39 = Utf8               Ljavax/swing/DropMode;
   #40 = Methodref          #17.#41       // javax/swing/JTextArea.setDropMode:(Ljavax/swing/DropMode;)V
   #41 = NameAndType        #42:#43       // setDropMode:(Ljavax/swing/DropMode;)V
   #42 = Utf8               setDropMode
   #43 = Utf8               (Ljavax/swing/DropMode;)V
   #44 = Class              #45           // java/awt/Font
   #45 = Utf8               java/awt/Font
   #46 = String             #47           // Monospaced
   #47 = Utf8               Monospaced
   #48 = Methodref          #44.#49       // java/awt/Font."<init>":(Ljava/lang/String;II)V
   #49 = NameAndType        #5:#50        // "<init>":(Ljava/lang/String;II)V
   #50 = Utf8               (Ljava/lang/String;II)V
   #51 = Methodref          #17.#52       // javax/swing/JTextArea.setFont:(Ljava/awt/Font;)V
   #52 = NameAndType        #53:#54       // setFont:(Ljava/awt/Font;)V
   #53 = Utf8               setFont
   #54 = Utf8               (Ljava/awt/Font;)V
   #55 = Methodref          #17.#56       // javax/swing/JTextArea.getDocument:()Ljavax/swing/text/Document;
   #56 = NameAndType        #57:#58       // getDocument:()Ljavax/swing/text/Document;
   #57 = Utf8               getDocument
   #58 = Utf8               ()Ljavax/swing/text/Document;
   #59 = Class              #60           // ext/mods/commons/gui/InterfaceLimit
   #60 = Utf8               ext/mods/commons/gui/InterfaceLimit
   #61 = Methodref          #59.#62       // ext/mods/commons/gui/InterfaceLimit."<init>":(I)V
   #62 = NameAndType        #5:#63        // "<init>":(I)V
   #63 = Utf8               (I)V
   #64 = InterfaceMethodref #65.#66       // javax/swing/text/Document.addDocumentListener:(Ljavax/swing/event/DocumentListener;)V
   #65 = Class              #67           // javax/swing/text/Document
   #66 = NameAndType        #68:#69       // addDocumentListener:(Ljavax/swing/event/DocumentListener;)V
   #67 = Utf8               javax/swing/text/Document
   #68 = Utf8               addDocumentListener
   #69 = Utf8               (Ljavax/swing/event/DocumentListener;)V
   #70 = Fieldref           #8.#71        // ext/mods/commons/gui/ThemeManager.COMPONENT_BACKGROUND:Ljava/awt/Color;
   #71 = NameAndType        #72:#73       // COMPONENT_BACKGROUND:Ljava/awt/Color;
   #72 = Utf8               COMPONENT_BACKGROUND
   #73 = Utf8               Ljava/awt/Color;
   #74 = Methodref          #17.#75       // javax/swing/JTextArea.setBackground:(Ljava/awt/Color;)V
   #75 = NameAndType        #76:#77       // setBackground:(Ljava/awt/Color;)V
   #76 = Utf8               setBackground
   #77 = Utf8               (Ljava/awt/Color;)V
   #78 = Fieldref           #8.#79        // ext/mods/commons/gui/ThemeManager.TEXT_COLOR:Ljava/awt/Color;
   #79 = NameAndType        #80:#73       // TEXT_COLOR:Ljava/awt/Color;
   #80 = Utf8               TEXT_COLOR
   #81 = Methodref          #17.#82       // javax/swing/JTextArea.setForeground:(Ljava/awt/Color;)V
   #82 = NameAndType        #83:#77       // setForeground:(Ljava/awt/Color;)V
   #83 = Utf8               setForeground
   #84 = Class              #85           // javax/swing/JFrame
   #85 = Utf8               javax/swing/JFrame
   #86 = String             #87           // Auth
   #87 = Utf8               Auth
   #88 = Methodref          #84.#89       // javax/swing/JFrame."<init>":(Ljava/lang/String;)V
   #89 = NameAndType        #5:#90        // "<init>":(Ljava/lang/String;)V
   #90 = Utf8               (Ljava/lang/String;)V
   #91 = Fieldref           #13.#92       // ext/mods/commons/gui/InterfaceLS.frame:Ljavax/swing/JFrame;
   #92 = NameAndType        #93:#94       // frame:Ljavax/swing/JFrame;
   #93 = Utf8               frame
   #94 = Utf8               Ljavax/swing/JFrame;
   #95 = Methodref          #84.#96       // javax/swing/JFrame.setUndecorated:(Z)V
   #96 = NameAndType        #97:#27       // setUndecorated:(Z)V
   #97 = Utf8               setUndecorated
   #98 = Class              #99           // ext/mods/commons/gui/ComponentResizer
   #99 = Utf8               ext/mods/commons/gui/ComponentResizer
  #100 = Methodref          #98.#101      // ext/mods/commons/gui/ComponentResizer."<init>":(Ljava/awt/Window;)V
  #101 = NameAndType        #5:#102       // "<init>":(Ljava/awt/Window;)V
  #102 = Utf8               (Ljava/awt/Window;)V
  #103 = Methodref          #13.#104      // ext/mods/commons/gui/InterfaceLS.createMenuBar:()Ljavax/swing/JMenuBar;
  #104 = NameAndType        #105:#106     // createMenuBar:()Ljavax/swing/JMenuBar;
  #105 = Utf8               createMenuBar
  #106 = Utf8               ()Ljavax/swing/JMenuBar;
  #107 = InvokeDynamic      #0:#108       // #0:run:(Lext/mods/commons/gui/InterfaceLS;)Ljava/lang/Runnable;
  #108 = NameAndType        #109:#110     // run:(Lext/mods/commons/gui/InterfaceLS;)Ljava/lang/Runnable;
  #109 = Utf8               run
  #110 = Utf8               (Lext/mods/commons/gui/InterfaceLS;)Ljava/lang/Runnable;
  #111 = Fieldref           #112.#113     // java/io/File.separator:Ljava/lang/String;
  #112 = Class              #114          // java/io/File
  #113 = NameAndType        #115:#116     // separator:Ljava/lang/String;
  #114 = Utf8               java/io/File
  #115 = Utf8               separator
  #116 = Utf8               Ljava/lang/String;
  #117 = InvokeDynamic      #1:#118       // #1:makeConcatWithConstants:(Ljava/lang/String;)Ljava/lang/String;
  #118 = NameAndType        #119:#120     // makeConcatWithConstants:(Ljava/lang/String;)Ljava/lang/String;
  #119 = Utf8               makeConcatWithConstants
  #120 = Utf8               (Ljava/lang/String;)Ljava/lang/String;
  #121 = Methodref          #112.#89      // java/io/File."<init>":(Ljava/lang/String;)V
  #122 = Methodref          #112.#123     // java/io/File.exists:()Z
  #123 = NameAndType        #124:#125     // exists:()Z
  #124 = Utf8               exists
  #125 = Utf8               ()Z
  #126 = InvokeDynamic      #2:#127       // #2:makeConcatWithConstants:(Ljava/lang/String;Ljava/lang/String;)Ljava/lang/String;
  #127 = NameAndType        #119:#128     // makeConcatWithConstants:(Ljava/lang/String;Ljava/lang/String;)Ljava/lang/String;
  #128 = Utf8               (Ljava/lang/String;Ljava/lang/String;)Ljava/lang/String;
  #129 = Class              #130          // ext/mods/commons/gui/CustomTopPanel
  #130 = Utf8               ext/mods/commons/gui/CustomTopPanel
  #131 = Methodref          #129.#132     // ext/mods/commons/gui/CustomTopPanel."<init>":(Ljavax/swing/JFrame;Ljavax/swing/JMenuBar;Ljava/lang/Runnable;ZLjava/lang/String;)V
  #132 = NameAndType        #5:#133       // "<init>":(Ljavax/swing/JFrame;Ljavax/swing/JMenuBar;Ljava/lang/Runnable;ZLjava/lang/String;)V
  #133 = Utf8               (Ljavax/swing/JFrame;Ljavax/swing/JMenuBar;Ljava/lang/Runnable;ZLjava/lang/String;)V
  #134 = Fieldref           #13.#135      // ext/mods/commons/gui/InterfaceLS.topPanel:Lext/mods/commons/gui/CustomTopPanel;
  #135 = NameAndType        #136:#137     // topPanel:Lext/mods/commons/gui/CustomTopPanel;
  #136 = Utf8               topPanel
  #137 = Utf8               Lext/mods/commons/gui/CustomTopPanel;
  #138 = Class              #139          // java/awt/BorderLayout
  #139 = Utf8               java/awt/BorderLayout
  #140 = String             #141          // North
  #141 = Utf8               North
  #142 = Methodref          #84.#143      // javax/swing/JFrame.add:(Ljava/awt/Component;Ljava/lang/Object;)V
  #143 = NameAndType        #144:#145     // add:(Ljava/awt/Component;Ljava/lang/Object;)V
  #144 = Utf8               add
  #145 = Utf8               (Ljava/awt/Component;Ljava/lang/Object;)V
  #146 = Class              #147          // javax/swing/JScrollPane
  #147 = Utf8               javax/swing/JScrollPane
  #148 = Methodref          #146.#149     // javax/swing/JScrollPane."<init>":(Ljava/awt/Component;)V
  #149 = NameAndType        #5:#150       // "<init>":(Ljava/awt/Component;)V
  #150 = Utf8               (Ljava/awt/Component;)V
  #151 = Fieldref           #13.#152      // ext/mods/commons/gui/InterfaceLS.scrollPanel:Ljavax/swing/JScrollPane;
  #152 = NameAndType        #153:#154     // scrollPanel:Ljavax/swing/JScrollPane;
  #153 = Utf8               scrollPanel
  #154 = Utf8               Ljavax/swing/JScrollPane;
  #155 = Methodref          #146.#156     // javax/swing/JScrollPane.getViewport:()Ljavax/swing/JViewport;
  #156 = NameAndType        #157:#158     // getViewport:()Ljavax/swing/JViewport;
  #157 = Utf8               getViewport
  #158 = Utf8               ()Ljavax/swing/JViewport;
  #159 = Methodref          #160.#75      // javax/swing/JViewport.setBackground:(Ljava/awt/Color;)V
  #160 = Class              #161          // javax/swing/JViewport
  #161 = Utf8               javax/swing/JViewport
  #162 = Fieldref           #8.#163       // ext/mods/commons/gui/ThemeManager.VERY_DARK_BACKGROUND:Ljava/awt/Color;
  #163 = NameAndType        #164:#73      // VERY_DARK_BACKGROUND:Ljava/awt/Color;
  #164 = Utf8               VERY_DARK_BACKGROUND
  #165 = Methodref          #146.#75      // javax/swing/JScrollPane.setBackground:(Ljava/awt/Color;)V
  #166 = Methodref          #146.#167     // javax/swing/JScrollPane.setBorder:(Ljavax/swing/border/Border;)V
  #167 = NameAndType        #168:#169     // setBorder:(Ljavax/swing/border/Border;)V
  #168 = Utf8               setBorder
  #169 = Utf8               (Ljavax/swing/border/Border;)V
  #170 = Methodref          #146.#171     // javax/swing/JScrollPane.getVerticalScrollBar:()Ljavax/swing/JScrollBar;
  #171 = NameAndType        #172:#173     // getVerticalScrollBar:()Ljavax/swing/JScrollBar;
  #172 = Utf8               getVerticalScrollBar
  #173 = Utf8               ()Ljavax/swing/JScrollBar;
  #174 = Class              #175          // ext/mods/commons/gui/ModernUI$ModernScrollBarUI
  #175 = Utf8               ext/mods/commons/gui/ModernUI$ModernScrollBarUI
  #176 = Methodref          #174.#3       // ext/mods/commons/gui/ModernUI$ModernScrollBarUI."<init>":()V
  #177 = Methodref          #178.#179     // javax/swing/JScrollBar.setUI:(Ljavax/swing/plaf/ScrollBarUI;)V
  #178 = Class              #180          // javax/swing/JScrollBar
  #179 = NameAndType        #181:#182     // setUI:(Ljavax/swing/plaf/ScrollBarUI;)V
  #180 = Utf8               javax/swing/JScrollBar
  #181 = Utf8               setUI
  #182 = Utf8               (Ljavax/swing/plaf/ScrollBarUI;)V
  #183 = Class              #184          // java/awt/Dimension
  #184 = Utf8               java/awt/Dimension
  #185 = Methodref          #183.#186     // java/awt/Dimension."<init>":(II)V
  #186 = NameAndType        #5:#187       // "<init>":(II)V
  #187 = Utf8               (II)V
  #188 = Methodref          #178.#189     // javax/swing/JScrollBar.setPreferredSize:(Ljava/awt/Dimension;)V
  #189 = NameAndType        #190:#191     // setPreferredSize:(Ljava/awt/Dimension;)V
  #190 = Utf8               setPreferredSize
  #191 = Utf8               (Ljava/awt/Dimension;)V
  #192 = Class              #193          // ext/mods/commons/gui/InterfaceLSInfo
  #193 = Utf8               ext/mods/commons/gui/InterfaceLSInfo
  #194 = Methodref          #192.#3       // ext/mods/commons/gui/InterfaceLSInfo."<init>":()V
  #195 = Fieldref           #13.#196      // ext/mods/commons/gui/InterfaceLS.infoPanel:Ljavax/swing/JPanel;
  #196 = NameAndType        #197:#198     // infoPanel:Ljavax/swing/JPanel;
  #197 = Utf8               infoPanel
  #198 = Utf8               Ljavax/swing/JPanel;
  #199 = Class              #200          // javax/swing/JLayeredPane
  #200 = Utf8               javax/swing/JLayeredPane
  #201 = Methodref          #199.#3       // javax/swing/JLayeredPane."<init>":()V
  #202 = Fieldref           #13.#203      // ext/mods/commons/gui/InterfaceLS.layeredPanel:Ljavax/swing/JLayeredPane;
  #203 = NameAndType        #204:#205     // layeredPanel:Ljavax/swing/JLayeredPane;
  #204 = Utf8               layeredPanel
  #205 = Utf8               Ljavax/swing/JLayeredPane;
  #206 = Methodref          #207.#208     // java/lang/Integer.valueOf:(I)Ljava/lang/Integer;
  #207 = Class              #209          // java/lang/Integer
  #208 = NameAndType        #210:#211     // valueOf:(I)Ljava/lang/Integer;
  #209 = Utf8               java/lang/Integer
  #210 = Utf8               valueOf
  #211 = Utf8               (I)Ljava/lang/Integer;
  #212 = Methodref          #199.#143     // javax/swing/JLayeredPane.add:(Ljava/awt/Component;Ljava/lang/Object;)V
  #213 = String             #214          // Center
  #214 = Utf8               Center
  #215 = Class              #216          // java/awt/Component
  #216 = Utf8               java/awt/Component
  #217 = Methodref          #98.#218      // ext/mods/commons/gui/ComponentResizer.registerComponent:([Ljava/awt/Component;)V
  #218 = NameAndType        #219:#220     // registerComponent:([Ljava/awt/Component;)V
  #219 = Utf8               registerComponent
  #220 = Utf8               ([Ljava/awt/Component;)V
  #221 = Class              #222          // ext/mods/commons/gui/InterfaceLS$1
  #222 = Utf8               ext/mods/commons/gui/InterfaceLS$1
  #223 = Methodref          #221.#224     // ext/mods/commons/gui/InterfaceLS$1."<init>":(Lext/mods/commons/gui/InterfaceLS;)V
  #224 = NameAndType        #5:#225       // "<init>":(Lext/mods/commons/gui/InterfaceLS;)V
  #225 = Utf8               (Lext/mods/commons/gui/InterfaceLS;)V
  #226 = Methodref          #84.#227      // javax/swing/JFrame.addWindowStateListener:(Ljava/awt/event/WindowStateListener;)V
  #227 = NameAndType        #228:#229     // addWindowStateListener:(Ljava/awt/event/WindowStateListener;)V
  #228 = Utf8               addWindowStateListener
  #229 = Utf8               (Ljava/awt/event/WindowStateListener;)V
  #230 = Class              #231          // ext/mods/commons/gui/InterfaceLS$2
  #231 = Utf8               ext/mods/commons/gui/InterfaceLS$2
  #232 = Methodref          #230.#224     // ext/mods/commons/gui/InterfaceLS$2."<init>":(Lext/mods/commons/gui/InterfaceLS;)V
  #233 = Methodref          #84.#234      // javax/swing/JFrame.addComponentListener:(Ljava/awt/event/ComponentListener;)V
  #234 = NameAndType        #235:#236     // addComponentListener:(Ljava/awt/event/ComponentListener;)V
  #235 = Utf8               addComponentListener
  #236 = Utf8               (Ljava/awt/event/ComponentListener;)V
  #237 = Class              #238          // javax/swing/WindowConstants
  #238 = Utf8               javax/swing/WindowConstants
  #239 = Methodref          #84.#240      // javax/swing/JFrame.setDefaultCloseOperation:(I)V
  #240 = NameAndType        #241:#63      // setDefaultCloseOperation:(I)V
  #241 = Utf8               setDefaultCloseOperation
  #242 = Class              #243          // ext/mods/commons/gui/InterfaceLS$3
  #243 = Utf8               ext/mods/commons/gui/InterfaceLS$3
  #244 = Methodref          #242.#224     // ext/mods/commons/gui/InterfaceLS$3."<init>":(Lext/mods/commons/gui/InterfaceLS;)V
  #245 = Methodref          #84.#246      // javax/swing/JFrame.addWindowListener:(Ljava/awt/event/WindowListener;)V
  #246 = NameAndType        #247:#248     // addWindowListener:(Ljava/awt/event/WindowListener;)V
  #247 = Utf8               addWindowListener
  #248 = Utf8               (Ljava/awt/event/WindowListener;)V
  #249 = Methodref          #250.#251     // ext/mods/commons/gui/GuiUtils.loadIcons:()Ljava/util/List;
  #250 = Class              #252          // ext/mods/commons/gui/GuiUtils
  #251 = NameAndType        #253:#254     // loadIcons:()Ljava/util/List;
  #252 = Utf8               ext/mods/commons/gui/GuiUtils
  #253 = Utf8               loadIcons
  #254 = Utf8               ()Ljava/util/List;
  #255 = Methodref          #84.#256      // javax/swing/JFrame.setIconImages:(Ljava/util/List;)V
  #256 = NameAndType        #257:#258     // setIconImages:(Ljava/util/List;)V
  #257 = Utf8               setIconImages
  #258 = Utf8               (Ljava/util/List;)V
  #259 = Methodref          #84.#260      // javax/swing/JFrame.setSize:(II)V
  #260 = NameAndType        #261:#187     // setSize:(II)V
  #261 = Utf8               setSize
  #262 = Methodref          #84.#263      // javax/swing/JFrame.setLocationRelativeTo:(Ljava/awt/Component;)V
  #263 = NameAndType        #264:#150     // setLocationRelativeTo:(Ljava/awt/Component;)V
  #264 = Utf8               setLocationRelativeTo
  #265 = Methodref          #13.#266      // ext/mods/commons/gui/InterfaceLS.redirectSystemStreams:()V
  #266 = NameAndType        #267:#6       // redirectSystemStreams:()V
  #267 = Utf8               redirectSystemStreams
  #268 = Methodref          #84.#269      // javax/swing/JFrame.setVisible:(Z)V
  #269 = NameAndType        #270:#27      // setVisible:(Z)V
  #270 = Utf8               setVisible
  #271 = InvokeDynamic      #3:#108       // #3:run:(Lext/mods/commons/gui/InterfaceLS;)Ljava/lang/Runnable;
  #272 = Methodref          #273.#274     // javax/swing/SwingUtilities.invokeLater:(Ljava/lang/Runnable;)V
  #273 = Class              #275          // javax/swing/SwingUtilities
  #274 = NameAndType        #276:#277     // invokeLater:(Ljava/lang/Runnable;)V
  #275 = Utf8               javax/swing/SwingUtilities
  #276 = Utf8               invokeLater
  #277 = Utf8               (Ljava/lang/Runnable;)V
  #278 = Class              #279          // javax/swing/JMenu
  #279 = Utf8               javax/swing/JMenu
  #280 = Methodref          #278.#89      // javax/swing/JMenu."<init>":(Ljava/lang/String;)V
  #281 = Methodref          #278.#82      // javax/swing/JMenu.setForeground:(Ljava/awt/Color;)V
  #282 = Class              #283          // javax/swing/JMenuItem
  #283 = Utf8               javax/swing/JMenuItem
  #284 = Methodref          #282.#89      // javax/swing/JMenuItem."<init>":(Ljava/lang/String;)V
  #285 = Methodref          #282.#75      // javax/swing/JMenuItem.setBackground:(Ljava/awt/Color;)V
  #286 = Fieldref           #8.#287       // ext/mods/commons/gui/ThemeManager.TEXT_SELECTED:Ljava/awt/Color;
  #287 = NameAndType        #288:#73      // TEXT_SELECTED:Ljava/awt/Color;
  #288 = Utf8               TEXT_SELECTED
  #289 = Methodref          #282.#82      // javax/swing/JMenuItem.setForeground:(Ljava/awt/Color;)V
  #290 = Methodref          #282.#291     // javax/swing/JMenuItem.addActionListener:(Ljava/awt/event/ActionListener;)V
  #291 = NameAndType        #292:#293     // addActionListener:(Ljava/awt/event/ActionListener;)V
  #292 = Utf8               addActionListener
  #293 = Utf8               (Ljava/awt/event/ActionListener;)V
  #294 = InvokeDynamic      #4:#295       // #4:actionPerformed:(Lext/mods/commons/gui/InterfaceLS;Ljava/lang/String;)Ljava/awt/event/ActionListener;
  #295 = NameAndType        #296:#297     // actionPerformed:(Lext/mods/commons/gui/InterfaceLS;Ljava/lang/String;)Ljava/awt/event/ActionListener;
  #296 = Utf8               actionPerformed
  #297 = Utf8               (Lext/mods/commons/gui/InterfaceLS;Ljava/lang/String;)Ljava/awt/event/ActionListener;
  #298 = Class              #299          // javax/swing/JMenuBar
  #299 = Utf8               javax/swing/JMenuBar
  #300 = Methodref          #298.#3       // javax/swing/JMenuBar."<init>":()V
  #301 = Fieldref           #302.#303     // ext/mods/commons/gui/ModernUI.TEXT_GRAY:Ljava/awt/Color;
  #302 = Class              #304          // ext/mods/commons/gui/ModernUI
  #303 = NameAndType        #305:#73      // TEXT_GRAY:Ljava/awt/Color;
  #304 = Utf8               ext/mods/commons/gui/ModernUI
  #305 = Utf8               TEXT_GRAY
  #306 = Methodref          #298.#75      // javax/swing/JMenuBar.setBackground:(Ljava/awt/Color;)V
  #307 = Methodref          #308.#309     // javax/swing/BorderFactory.createEmptyBorder:()Ljavax/swing/border/Border;
  #308 = Class              #310          // javax/swing/BorderFactory
  #309 = NameAndType        #311:#312     // createEmptyBorder:()Ljavax/swing/border/Border;
  #310 = Utf8               javax/swing/BorderFactory
  #311 = Utf8               createEmptyBorder
  #312 = Utf8               ()Ljavax/swing/border/Border;
  #313 = Methodref          #298.#167     // javax/swing/JMenuBar.setBorder:(Ljavax/swing/border/Border;)V
  #314 = String             #315          // Login
  #315 = Utf8               Login
  #316 = Methodref          #13.#317      // ext/mods/commons/gui/InterfaceLS.createMenu:(Ljava/lang/String;)Ljavax/swing/JMenu;
  #317 = NameAndType        #318:#319     // createMenu:(Ljava/lang/String;)Ljavax/swing/JMenu;
  #318 = Utf8               createMenu
  #319 = Utf8               (Ljava/lang/String;)Ljavax/swing/JMenu;
  #320 = String             #321          // Shutdown
  #321 = Utf8               Shutdown
  #322 = InvokeDynamic      #5:#323       // #5:actionPerformed:(Lext/mods/commons/gui/InterfaceLS;)Ljava/awt/event/ActionListener;
  #323 = NameAndType        #296:#324     // actionPerformed:(Lext/mods/commons/gui/InterfaceLS;)Ljava/awt/event/ActionListener;
  #324 = Utf8               (Lext/mods/commons/gui/InterfaceLS;)Ljava/awt/event/ActionListener;
  #325 = Methodref          #13.#326      // ext/mods/commons/gui/InterfaceLS.createMenuItem:(Ljava/lang/String;Ljava/awt/event/ActionListener;)Ljavax/swing/JMenuItem;
  #326 = NameAndType        #327:#328     // createMenuItem:(Ljava/lang/String;Ljava/awt/event/ActionListener;)Ljavax/swing/JMenuItem;
  #327 = Utf8               createMenuItem
  #328 = Utf8               (Ljava/lang/String;Ljava/awt/event/ActionListener;)Ljavax/swing/JMenuItem;
  #329 = Methodref          #278.#330     // javax/swing/JMenu.add:(Ljavax/swing/JMenuItem;)Ljavax/swing/JMenuItem;
  #330 = NameAndType        #144:#331     // add:(Ljavax/swing/JMenuItem;)Ljavax/swing/JMenuItem;
  #331 = Utf8               (Ljavax/swing/JMenuItem;)Ljavax/swing/JMenuItem;
  #332 = String             #333          // Restart
  #333 = Utf8               Restart
  #334 = InvokeDynamic      #6:#323       // #6:actionPerformed:(Lext/mods/commons/gui/InterfaceLS;)Ljava/awt/event/ActionListener;
  #335 = String             #336          // Font
  #336 = Utf8               Font
  #337 = Class              #338          // java/lang/String
  #338 = Utf8               java/lang/String
  #339 = String             #340          // 10
  #340 = Utf8               10
  #341 = String             #342          // 13
  #342 = Utf8               13
  #343 = String             #344          // 16
  #344 = Utf8               16
  #345 = String             #346          // 20
  #346 = Utf8               20
  #347 = String             #348          // 24
  #348 = Utf8               24
  #349 = Methodref          #13.#350      // ext/mods/commons/gui/InterfaceLS.createFontMenuItem:(Ljava/lang/String;)Ljavax/swing/JMenuItem;
  #350 = NameAndType        #351:#352     // createFontMenuItem:(Ljava/lang/String;)Ljavax/swing/JMenuItem;
  #351 = Utf8               createFontMenuItem
  #352 = Utf8               (Ljava/lang/String;)Ljavax/swing/JMenuItem;
  #353 = String             #354          // Help
  #354 = Utf8               Help
  #355 = String             #356          // About
  #356 = Utf8               About
  #357 = InvokeDynamic      #7:#358       // #7:actionPerformed:()Ljava/awt/event/ActionListener;
  #358 = NameAndType        #296:#359     // actionPerformed:()Ljava/awt/event/ActionListener;
  #359 = Utf8               ()Ljava/awt/event/ActionListener;
  #360 = Methodref          #298.#361     // javax/swing/JMenuBar.add:(Ljavax/swing/JMenu;)Ljavax/swing/JMenu;
  #361 = NameAndType        #144:#362     // add:(Ljavax/swing/JMenu;)Ljavax/swing/JMenu;
  #362 = Utf8               (Ljavax/swing/JMenu;)Ljavax/swing/JMenu;
  #363 = String             #364          // true
  #364 = Utf8               true
  #365 = String             #366          // brproject.launcher.spawned
  #366 = Utf8               brproject.launcher.spawned
  #367 = Methodref          #368.#369     // java/lang/System.getProperty:(Ljava/lang/String;)Ljava/lang/String;
  #368 = Class              #370          // java/lang/System
  #369 = NameAndType        #371:#120     // getProperty:(Ljava/lang/String;)Ljava/lang/String;
  #370 = Utf8               java/lang/System
  #371 = Utf8               getProperty
  #372 = Methodref          #337.#373     // java/lang/String.equalsIgnoreCase:(Ljava/lang/String;)Z
  #373 = NameAndType        #374:#375     // equalsIgnoreCase:(Ljava/lang/String;)Z
  #374 = Utf8               equalsIgnoreCase
  #375 = Utf8               (Ljava/lang/String;)Z
  #376 = Methodref          #377.#378     // ext/mods/loginserver/LoginServer.getInstance:()Lext/mods/loginserver/LoginServer;
  #377 = Class              #379          // ext/mods/loginserver/LoginServer
  #378 = NameAndType        #380:#381     // getInstance:()Lext/mods/loginserver/LoginServer;
  #379 = Utf8               ext/mods/loginserver/LoginServer
  #380 = Utf8               getInstance
  #381 = Utf8               ()Lext/mods/loginserver/LoginServer;
  #382 = Methodref          #377.#383     // ext/mods/loginserver/LoginServer.shutdown:(Z)V
  #383 = NameAndType        #384:#27      // shutdown:(Z)V
  #384 = Utf8               shutdown
  #385 = Methodref          #386.#387     // ext/mods/loginserver/data/manager/GameServerManager.getInstance:()Lext/mods/loginserver/data/manager/GameServerManager;
  #386 = Class              #388          // ext/mods/loginserver/data/manager/GameServerManager
  #387 = NameAndType        #380:#389     // getInstance:()Lext/mods/loginserver/data/manager/GameServerManager;
  #388 = Utf8               ext/mods/loginserver/data/manager/GameServerManager
  #389 = Utf8               ()Lext/mods/loginserver/data/manager/GameServerManager;
  #390 = Methodref          #386.#391     // ext/mods/loginserver/data/manager/GameServerManager.getGameServersCount:()I
  #391 = NameAndType        #392:#393     // getGameServersCount:()I
  #392 = Utf8               getGameServersCount
  #393 = Utf8               ()I
  #394 = Class              #395          // java/lang/Exception
  #395 = Utf8               java/lang/Exception
  #396 = String             #397          // Shutdown LoginServer?
  #397 = Utf8               Shutdown LoginServer?
  #398 = String             #399          // GameServers are connected!
  #399 = Utf8               GameServers are connected!
  #400 = Class              #401          // javax/swing/JOptionPane
  #401 = Utf8               javax/swing/JOptionPane
  #402 = Fieldref           #13.#403      // ext/mods/commons/gui/InterfaceLS.shutdownOptions:[Ljava/lang/String;
  #403 = NameAndType        #404:#405     // shutdownOptions:[Ljava/lang/String;
  #404 = Utf8               shutdownOptions
  #405 = Utf8               [Ljava/lang/String;
  #406 = Methodref          #400.#407     // javax/swing/JOptionPane.showOptionDialog:(Ljava/awt/Component;Ljava/lang/Object;Ljava/lang/String;IILjavax/swing/Icon;[Ljava/lang/Object;Ljava/lang/Object;)I
  #407 = NameAndType        #408:#409     // showOptionDialog:(Ljava/awt/Component;Ljava/lang/Object;Ljava/lang/String;IILjavax/swing/Icon;[Ljava/lang/Object;Ljava/lang/Object;)I
  #408 = Utf8               showOptionDialog
  #409 = Utf8               (Ljava/awt/Component;Ljava/lang/Object;Ljava/lang/String;IILjavax/swing/Icon;[Ljava/lang/Object;Ljava/lang/Object;)I
  #410 = InvokeDynamic      #8:#411       // #8:run:(Lext/mods/commons/gui/InterfaceLS;Ljava/lang/String;)Ljava/lang/Runnable;
  #411 = NameAndType        #109:#412     // run:(Lext/mods/commons/gui/InterfaceLS;Ljava/lang/String;)Ljava/lang/Runnable;
  #412 = Utf8               (Lext/mods/commons/gui/InterfaceLS;Ljava/lang/String;)Ljava/lang/Runnable;
  #413 = Class              #414          // ext/mods/commons/gui/InterfaceLS$4
  #414 = Utf8               ext/mods/commons/gui/InterfaceLS$4
  #415 = Methodref          #413.#224     // ext/mods/commons/gui/InterfaceLS$4."<init>":(Lext/mods/commons/gui/InterfaceLS;)V
  #416 = Class              #417          // java/io/PrintStream
  #417 = Utf8               java/io/PrintStream
  #418 = Methodref          #416.#419     // java/io/PrintStream."<init>":(Ljava/io/OutputStream;Z)V
  #419 = NameAndType        #5:#420       // "<init>":(Ljava/io/OutputStream;Z)V
  #420 = Utf8               (Ljava/io/OutputStream;Z)V
  #421 = Methodref          #368.#422     // java/lang/System.setOut:(Ljava/io/PrintStream;)V
  #422 = NameAndType        #423:#424     // setOut:(Ljava/io/PrintStream;)V
  #423 = Utf8               setOut
  #424 = Utf8               (Ljava/io/PrintStream;)V
  #425 = Methodref          #368.#426     // java/lang/System.setErr:(Ljava/io/PrintStream;)V
  #426 = NameAndType        #427:#424     // setErr:(Ljava/io/PrintStream;)V
  #427 = Utf8               setErr
  #428 = Methodref          #13.#429      // ext/mods/commons/gui/InterfaceLS.installJavaUtilLoggingHandler:()V
  #429 = NameAndType        #430:#6       // installJavaUtilLoggingHandler:()V
  #430 = Utf8               installJavaUtilLoggingHandler
  #431 = String             #432          //
  #432 = Utf8
  #433 = Methodref          #434.#435     // java/util/logging/Logger.getLogger:(Ljava/lang/String;)Ljava/util/logging/Logger;
  #434 = Class              #436          // java/util/logging/Logger
  #435 = NameAndType        #437:#438     // getLogger:(Ljava/lang/String;)Ljava/util/logging/Logger;
  #436 = Utf8               java/util/logging/Logger
  #437 = Utf8               getLogger
  #438 = Utf8               (Ljava/lang/String;)Ljava/util/logging/Logger;
  #439 = Class              #440          // ext/mods/commons/gui/InterfaceLS$5
  #440 = Utf8               ext/mods/commons/gui/InterfaceLS$5
  #441 = Methodref          #439.#224     // ext/mods/commons/gui/InterfaceLS$5."<init>":(Lext/mods/commons/gui/InterfaceLS;)V
  #442 = Fieldref           #443.#444     // java/util/logging/Level.ALL:Ljava/util/logging/Level;
  #443 = Class              #445          // java/util/logging/Level
  #444 = NameAndType        #446:#447     // ALL:Ljava/util/logging/Level;
  #445 = Utf8               java/util/logging/Level
  #446 = Utf8               ALL
  #447 = Utf8               Ljava/util/logging/Level;
  #448 = Methodref          #449.#450     // java/util/logging/Handler.setLevel:(Ljava/util/logging/Level;)V
  #449 = Class              #451          // java/util/logging/Handler
  #450 = NameAndType        #452:#453     // setLevel:(Ljava/util/logging/Level;)V
  #451 = Utf8               java/util/logging/Handler
  #452 = Utf8               setLevel
  #453 = Utf8               (Ljava/util/logging/Level;)V
  #454 = Methodref          #434.#455     // java/util/logging/Logger.addHandler:(Ljava/util/logging/Handler;)V
  #455 = NameAndType        #456:#457     // addHandler:(Ljava/util/logging/Handler;)V
  #456 = Utf8               addHandler
  #457 = Utf8               (Ljava/util/logging/Handler;)V
  #458 = Methodref          #17.#459      // javax/swing/JTextArea.append:(Ljava/lang/String;)V
  #459 = NameAndType        #460:#90      // append:(Ljava/lang/String;)V
  #460 = Utf8               append
  #461 = InterfaceMethodref #65.#462      // javax/swing/text/Document.getLength:()I
  #462 = NameAndType        #463:#393     // getLength:()I
  #463 = Utf8               getLength
  #464 = Methodref          #17.#465      // javax/swing/JTextArea.setCaretPosition:(I)V
  #465 = NameAndType        #466:#63      // setCaretPosition:(I)V
  #466 = Utf8               setCaretPosition
  #467 = Class              #468          // ext/mods/commons/gui/InterfaceAbout
  #468 = Utf8               ext/mods/commons/gui/InterfaceAbout
  #469 = Methodref          #467.#3       // ext/mods/commons/gui/InterfaceAbout."<init>":()V
  #470 = String             #471          // Restart LoginServer?
  #471 = Utf8               Restart LoginServer?
  #472 = String             #473          // Confirm
  #473 = Utf8               Confirm
  #474 = Fieldref           #13.#475      // ext/mods/commons/gui/InterfaceLS.restartOptions:[Ljava/lang/String;
  #475 = NameAndType        #476:#405     // restartOptions:[Ljava/lang/String;
  #476 = Utf8               restartOptions
  #477 = String             #478          // Consolas
  #478 = Utf8               Consolas
  #479 = Methodref          #207.#480     // java/lang/Integer.parseInt:(Ljava/lang/String;)I
  #480 = NameAndType        #481:#482     // parseInt:(Ljava/lang/String;)I
  #481 = Utf8               parseInt
  #482 = Utf8               (Ljava/lang/String;)I
  #483 = Class              #484          // java/awt/event/ComponentEvent
  #484 = Utf8               java/awt/event/ComponentEvent
  #485 = Methodref          #483.#486     // java/awt/event/ComponentEvent."<init>":(Ljava/awt/Component;I)V
  #486 = NameAndType        #5:#487       // "<init>":(Ljava/awt/Component;I)V
  #487 = Utf8               (Ljava/awt/Component;I)V
  #488 = Methodref          #84.#489      // javax/swing/JFrame.dispatchEvent:(Ljava/awt/AWTEvent;)V
  #489 = NameAndType        #490:#491     // dispatchEvent:(Ljava/awt/AWTEvent;)V
  #490 = Utf8               dispatchEvent
  #491 = Utf8               (Ljava/awt/AWTEvent;)V
  #492 = String             #493          // Cancel
  #493 = Utf8               Cancel
  #494 = Utf8               DEFAULT_WIDTH
  #495 = Utf8               I
  #496 = Utf8               ConstantValue
  #497 = Integer            850
  #498 = Utf8               DEFAULT_HEIGHT
  #499 = Integer            517
  #500 = Utf8               Code
  #501 = Utf8               LineNumberTable
  #502 = Utf8               LocalVariableTable
  #503 = Utf8               this
  #504 = Utf8               Lext/mods/commons/gui/InterfaceLS;
  #505 = Utf8               resizer
  #506 = Utf8               Lext/mods/commons/gui/ComponentResizer;
  #507 = Utf8               menuBar
  #508 = Utf8               Ljavax/swing/JMenuBar;
  #509 = Utf8               closeAction
  #510 = Utf8               Ljava/lang/Runnable;
  #511 = Utf8               iconPath
  #512 = Utf8               StackMapTable
  #513 = Class              #514          // java/lang/Runnable
  #514 = Utf8               java/lang/Runnable
  #515 = Utf8               title
  #516 = Utf8               menu
  #517 = Utf8               Ljavax/swing/JMenu;
  #518 = Utf8               listener
  #519 = Utf8               Ljava/awt/event/ActionListener;
  #520 = Utf8               item
  #521 = Utf8               Ljavax/swing/JMenuItem;
  #522 = Utf8               size
  #523 = Utf8               loginMenu
  #524 = Utf8               fontMenu
  #525 = Utf8               helpMenu
  #526 = Class              #405          // "[Ljava/lang/String;"
  #527 = Utf8               closeLoginWindow
  #528 = Utf8               hasConnectedServers
  #529 = Utf8               Z
  #530 = Utf8               updateConsole
  #531 = Utf8               text
  #532 = Utf8               out
  #533 = Utf8               Ljava/io/OutputStream;
  #534 = Utf8               root
  #535 = Utf8               Ljava/util/logging/Logger;
  #536 = Utf8               handler
  #537 = Utf8               Ljava/util/logging/Handler;
  #538 = Utf8               lambda$updateConsole$0
  #539 = Utf8               lambda$createMenuBar$2
  #540 = Utf8               (Ljava/awt/event/ActionEvent;)V
  #541 = Utf8               e
  #542 = Utf8               Ljava/awt/event/ActionEvent;
  #543 = Utf8               lambda$createMenuBar$1
  #544 = Utf8               lambda$createMenuBar$0
  #545 = Utf8               lambda$createFontMenuItem$0
  #546 = Utf8               (Ljava/lang/String;Ljava/awt/event/ActionEvent;)V
  #547 = Utf8               lambda$initialize$0
  #548 = Utf8               <clinit>
  #549 = Utf8               SourceFile
  #550 = Utf8               InterfaceLS.java
  #551 = Utf8               NestMembers
  #552 = Utf8               BootstrapMethods
  #553 = MethodType         #6            //  ()V
  #554 = MethodHandle       5:#555        // REF_invokeVirtual ext/mods/commons/gui/InterfaceLS.closeLoginWindow:()V
  #555 = Methodref          #13.#556      // ext/mods/commons/gui/InterfaceLS.closeLoginWindow:()V
  #556 = NameAndType        #527:#6       // closeLoginWindow:()V
  #557 = String             #558          // images\u000116x16.png
  #558 = Utf8               images\u000116x16.png
  #559 = String             #560          // ..\u0001images\u000116x16.png
  #560 = Utf8               ..\u0001images\u000116x16.png
  #561 = MethodHandle       5:#562        // REF_invokeVirtual ext/mods/commons/gui/InterfaceLS.lambda$initialize$0:()V
  #562 = Methodref          #13.#563      // ext/mods/commons/gui/InterfaceLS.lambda$initialize$0:()V
  #563 = NameAndType        #547:#6       // lambda$initialize$0:()V
  #564 = MethodType         #540          //  (Ljava/awt/event/ActionEvent;)V
  #565 = MethodHandle       5:#566        // REF_invokeVirtual ext/mods/commons/gui/InterfaceLS.lambda$createFontMenuItem$0:(Ljava/lang/String;Ljava/awt/event/ActionEvent;)V
  #566 = Methodref          #13.#567      // ext/mods/commons/gui/InterfaceLS.lambda$createFontMenuItem$0:(Ljava/lang/String;Ljava/awt/event/ActionEvent;)V
  #567 = NameAndType        #545:#546     // lambda$createFontMenuItem$0:(Ljava/lang/String;Ljava/awt/event/ActionEvent;)V
  #568 = MethodHandle       5:#569        // REF_invokeVirtual ext/mods/commons/gui/InterfaceLS.lambda$createMenuBar$0:(Ljava/awt/event/ActionEvent;)V
  #569 = Methodref          #13.#570      // ext/mods/commons/gui/InterfaceLS.lambda$createMenuBar$0:(Ljava/awt/event/ActionEvent;)V
  #570 = NameAndType        #544:#540     // lambda$createMenuBar$0:(Ljava/awt/event/ActionEvent;)V
  #571 = MethodHandle       5:#572        // REF_invokeVirtual ext/mods/commons/gui/InterfaceLS.lambda$createMenuBar$1:(Ljava/awt/event/ActionEvent;)V
  #572 = Methodref          #13.#573      // ext/mods/commons/gui/InterfaceLS.lambda$createMenuBar$1:(Ljava/awt/event/ActionEvent;)V
  #573 = NameAndType        #543:#540     // lambda$createMenuBar$1:(Ljava/awt/event/ActionEvent;)V
  #574 = MethodHandle       6:#575        // REF_invokeStatic ext/mods/commons/gui/InterfaceLS.lambda$createMenuBar$2:(Ljava/awt/event/ActionEvent;)V
  #575 = Methodref          #13.#576      // ext/mods/commons/gui/InterfaceLS.lambda$createMenuBar$2:(Ljava/awt/event/ActionEvent;)V
  #576 = NameAndType        #539:#540     // lambda$createMenuBar$2:(Ljava/awt/event/ActionEvent;)V
  #577 = MethodHandle       5:#578        // REF_invokeVirtual ext/mods/commons/gui/InterfaceLS.lambda$updateConsole$0:(Ljava/lang/String;)V
  #578 = Methodref          #13.#579      // ext/mods/commons/gui/InterfaceLS.lambda$updateConsole$0:(Ljava/lang/String;)V
  #579 = NameAndType        #538:#90      // lambda$updateConsole$0:(Ljava/lang/String;)V
  #580 = MethodHandle       6:#581        // REF_invokeStatic java/lang/invoke/LambdaMetafactory.metafactory:(Ljava/lang/invoke/MethodHandles$Lookup;Ljava/lang/String;Ljava/lang/invoke/MethodType;Ljava/lang/invoke/MethodType;Ljava/lang/invoke/MethodHandle;Ljava/lang/invoke/MethodType;)Ljava/lang/invoke/CallSite;
  #581 = Methodref          #582.#583     // java/lang/invoke/LambdaMetafactory.metafactory:(Ljava/lang/invoke/MethodHandles$Lookup;Ljava/lang/String;Ljava/lang/invoke/MethodType;Ljava/lang/invoke/MethodType;Ljava/lang/invoke/MethodHandle;Ljava/lang/invoke/MethodType;)Ljava/lang/invoke/CallSite;
  #582 = Class              #584          // java/lang/invoke/LambdaMetafactory
  #583 = NameAndType        #585:#586     // metafactory:(Ljava/lang/invoke/MethodHandles$Lookup;Ljava/lang/String;Ljava/lang/invoke/MethodType;Ljava/lang/invoke/MethodType;Ljava/lang/invoke/MethodHandle;Ljava/lang/invoke/MethodType;)Ljava/lang/invoke/CallSite;
  #584 = Utf8               java/lang/invoke/LambdaMetafactory
  #585 = Utf8               metafactory
  #586 = Utf8               (Ljava/lang/invoke/MethodHandles$Lookup;Ljava/lang/String;Ljava/lang/invoke/MethodType;Ljava/lang/invoke/MethodType;Ljava/lang/invoke/MethodHandle;Ljava/lang/invoke/MethodType;)Ljava/lang/invoke/CallSite;
  #587 = MethodHandle       6:#588        // REF_invokeStatic java/lang/invoke/StringConcatFactory.makeConcatWithConstants:(Ljava/lang/invoke/MethodHandles$Lookup;Ljava/lang/String;Ljava/lang/invoke/MethodType;Ljava/lang/String;[Ljava/lang/Object;)Ljava/lang/invoke/CallSite;
  #588 = Methodref          #589.#590     // java/lang/invoke/StringConcatFactory.makeConcatWithConstants:(Ljava/lang/invoke/MethodHandles$Lookup;Ljava/lang/String;Ljava/lang/invoke/MethodType;Ljava/lang/String;[Ljava/lang/Object;)Ljava/lang/invoke/CallSite;
  #589 = Class              #591          // java/lang/invoke/StringConcatFactory
  #590 = NameAndType        #119:#592     // makeConcatWithConstants:(Ljava/lang/invoke/MethodHandles$Lookup;Ljava/lang/String;Ljava/lang/invoke/MethodType;Ljava/lang/String;[Ljava/lang/Object;)Ljava/lang/invoke/CallSite;
  #591 = Utf8               java/lang/invoke/StringConcatFactory
  #592 = Utf8               (Ljava/lang/invoke/MethodHandles$Lookup;Ljava/lang/String;Ljava/lang/invoke/MethodType;Ljava/lang/String;[Ljava/lang/Object;)Ljava/lang/invoke/CallSite;
  #593 = Utf8               InnerClasses
  #594 = Utf8               ModernScrollBarUI
  #595 = Class              #596          // java/lang/invoke/MethodHandles$Lookup
  #596 = Utf8               java/lang/invoke/MethodHandles$Lookup
  #597 = Class              #598          // java/lang/invoke/MethodHandles
  #598 = Utf8               java/lang/invoke/MethodHandles
  #599 = Utf8               Lookup
{
  public ext.mods.commons.gui.InterfaceLS();
    descriptor: ()V
    flags: (0x0001) ACC_PUBLIC
    Code:
      stack=1, locals=1, args_size=1
         0: aload_0
         1: invokespecial #1                  // Method java/lang/Object."<init>":()V
         4: invokestatic  #7                  // Method ext/mods/commons/gui/ThemeManager.applyTheme:()V
         7: aload_0
         8: invokevirtual #12                 // Method initialize:()V
        11: return
      LineNumberTable:
        line 68: 0
        line 69: 4
        line 70: 7
        line 71: 11
      LocalVariableTable:
        Start  Length  Slot  Name   Signature
            0      12     0  this   Lext/mods/commons/gui/InterfaceLS;

  static {};
    descriptor: ()V
    flags: (0x0008) ACC_STATIC
    Code:
      stack=4, locals=0, args_size=0
         0: iconst_2
         1: anewarray     #337                // class java/lang/String
         4: dup
         5: iconst_0
         6: ldc_w         #320                // String Shutdown
         9: aastore
        10: dup
        11: iconst_1
        12: ldc_w         #492                // String Cancel
        15: aastore
        16: putstatic     #402                // Field shutdownOptions:[Ljava/lang/String;
        19: iconst_2
        20: anewarray     #337                // class java/lang/String
        23: dup
        24: iconst_0
        25: ldc_w         #332                // String Restart
        28: aastore
        29: dup
        30: iconst_1
        31: ldc_w         #492                // String Cancel
        34: aastore
        35: putstatic     #474                // Field restartOptions:[Ljava/lang/String;
        38: return
      LineNumberTable:
        line 56: 0
        line 57: 19
}
SourceFile: "InterfaceLS.java"
NestMembers:
  ext/mods/commons/gui/InterfaceLS$5
  ext/mods/commons/gui/InterfaceLS$4
  ext/mods/commons/gui/InterfaceLS$3
  ext/mods/commons/gui/InterfaceLS$2
  ext/mods/commons/gui/InterfaceLS$1
BootstrapMethods:
  0: #580 REF_invokeStatic java/lang/invoke/LambdaMetafactory.metafactory:(Ljava/lang/invoke/MethodHandles$Lookup;Ljava/lang/String;Ljava/lang/invoke/MethodType;Ljava/lang/invoke/MethodType;Ljava/lang/invoke/MethodHandle;Ljava/lang/invoke/MethodType;)Ljava/lang/invoke/CallSite;
    Method arguments:
      #553 ()V
      #554 REF_invokeVirtual ext/mods/commons/gui/InterfaceLS.closeLoginWindow:()V
      #553 ()V
  1: #587 REF_invokeStatic java/lang/invoke/StringConcatFactory.makeConcatWithConstants:(Ljava/lang/invoke/MethodHandles$Lookup;Ljava/lang/String;Ljava/lang/invoke/MethodType;Ljava/lang/String;[Ljava/lang/Object;)Ljava/lang/invoke/CallSite;
    Method arguments:
      #557 images\u000116x16.png
  2: #587 REF_invokeStatic java/lang/invoke/StringConcatFactory.makeConcatWithConstants:(Ljava/lang/invoke/MethodHandles$Lookup;Ljava/lang/String;Ljava/lang/invoke/MethodType;Ljava/lang/String;[Ljava/lang/Object;)Ljava/lang/invoke/CallSite;
    Method arguments:
      #559 ..\u0001images\u000116x16.png
  3: #580 REF_invokeStatic java/lang/invoke/LambdaMetafactory.metafactory:(Ljava/lang/invoke/MethodHandles$Lookup;Ljava/lang/String;Ljava/lang/invoke/MethodType;Ljava/lang/invoke/MethodType;Ljava/lang/invoke/MethodHandle;Ljava/lang/invoke/MethodType;)Ljava/lang/invoke/CallSite;
    Method arguments:
      #553 ()V
      #561 REF_invokeVirtual ext/mods/commons/gui/InterfaceLS.lambda$initialize$0:()V
      #553 ()V
  4: #580 REF_invokeStatic java/lang/invoke/LambdaMetafactory.metafactory:(Ljava/lang/invoke/MethodHandles$Lookup;Ljava/lang/String;Ljava/lang/invoke/MethodType;Ljava/lang/invoke/MethodType;Ljava/lang/invoke/MethodHandle;Ljava/lang/invoke/MethodType;)Ljava/lang/invoke/CallSite;
    Method arguments:
      #564 (Ljava/awt/event/ActionEvent;)V
      #565 REF_invokeVirtual ext/mods/commons/gui/InterfaceLS.lambda$createFontMenuItem$0:(Ljava/lang/String;Ljava/awt/event/ActionEvent;)V
      #564 (Ljava/awt/event/ActionEvent;)V
  5: #580 REF_invokeStatic java/lang/invoke/LambdaMetafactory.metafactory:(Ljava/lang/invoke/MethodHandles$Lookup;Ljava/lang/String;Ljava/lang/invoke/MethodType;Ljava/lang/invoke/MethodType;Ljava/lang/invoke/MethodHandle;Ljava/lang/invoke/MethodType;)Ljava/lang/invoke/CallSite;
    Method arguments:
      #564 (Ljava/awt/event/ActionEvent;)V
      #568 REF_invokeVirtual ext/mods/commons/gui/InterfaceLS.lambda$createMenuBar$0:(Ljava/awt/event/ActionEvent;)V
      #564 (Ljava/awt/event/ActionEvent;)V
  6: #580 REF_invokeStatic java/lang/invoke/LambdaMetafactory.metafactory:(Ljava/lang/invoke/MethodHandles$Lookup;Ljava/lang/String;Ljava/lang/invoke/MethodType;Ljava/lang/invoke/MethodType;Ljava/lang/invoke/MethodHandle;Ljava/lang/invoke/MethodType;)Ljava/lang/invoke/CallSite;
    Method arguments:
      #564 (Ljava/awt/event/ActionEvent;)V
      #571 REF_invokeVirtual ext/mods/commons/gui/InterfaceLS.lambda$createMenuBar$1:(Ljava/awt/event/ActionEvent;)V
      #564 (Ljava/awt/event/ActionEvent;)V
  7: #580 REF_invokeStatic java/lang/invoke/LambdaMetafactory.metafactory:(Ljava/lang/invoke/MethodHandles$Lookup;Ljava/lang/String;Ljava/lang/invoke/MethodType;Ljava/lang/invoke/MethodType;Ljava/lang/invoke/MethodHandle;Ljava/lang/invoke/MethodType;)Ljava/lang/invoke/CallSite;
    Method arguments:
      #564 (Ljava/awt/event/ActionEvent;)V
      #574 REF_invokeStatic ext/mods/commons/gui/InterfaceLS.lambda$createMenuBar$2:(Ljava/awt/event/ActionEvent;)V
      #564 (Ljava/awt/event/ActionEvent;)V
  8: #580 REF_invokeStatic java/lang/invoke/LambdaMetafactory.metafactory:(Ljava/lang/invoke/MethodHandles$Lookup;Ljava/lang/String;Ljava/lang/invoke/MethodType;Ljava/lang/invoke/MethodType;Ljava/lang/invoke/MethodHandle;Ljava/lang/invoke/MethodType;)Ljava/lang/invoke/CallSite;
    Method arguments:
      #553 ()V
      #577 REF_invokeVirtual ext/mods/commons/gui/InterfaceLS.lambda$updateConsole$0:(Ljava/lang/String;)V
      #553 ()V
InnerClasses:
  public static #594= #174 of #302;       // ModernScrollBarUI=class ext/mods/commons/gui/ModernUI$ModernScrollBarUI of class ext/mods/commons/gui/ModernUI
  #221;                                   // class ext/mods/commons/gui/InterfaceLS$1
  #230;                                   // class ext/mods/commons/gui/InterfaceLS$2
  #242;                                   // class ext/mods/commons/gui/InterfaceLS$3
  #413;                                   // class ext/mods/commons/gui/InterfaceLS$4
  #439;                                   // class ext/mods/commons/gui/InterfaceLS$5
  public static final #599= #595 of #597; // Lookup=class java/lang/invoke/MethodHandles$Lookup of class java/lang/invoke/MethodHandles
