// Bytecode for: ext.mods.commons.gui.InterfaceBalance
// File: ext\mods\commons\gui\InterfaceBalance.class

Classfile /c:/Users/User/Desktop/BrProject/bin/main/ext/mods/commons/gui/InterfaceBalance.class
  Last modified 9 de jul de 2026; size 15581 bytes
  MD5 checksum f29166118cd02c938000997ec9932348
  Compiled from "InterfaceBalance.java"
public class ext.mods.commons.gui.InterfaceBalance
  minor version: 0
  major version: 69
  flags: (0x0021) ACC_PUBLIC, ACC_SUPER
  this_class: #64                         // ext/mods/commons/gui/InterfaceBalance
  super_class: #2                         // java/lang/Object
  interfaces: 0, fields: 2, methods: 12, attributes: 4
Constant pool:
    #1 = Methodref          #2.#3         // java/lang/Object."<init>":()V
    #2 = Class              #4            // java/lang/Object
    #3 = NameAndType        #5:#6         // "<init>":()V
    #4 = Utf8               java/lang/Object
    #5 = Utf8               <init>
    #6 = Utf8               ()V
    #7 = String             #8            // control
    #8 = Utf8               control
    #9 = Class              #10           // java/awt/Color
   #10 = Utf8               java/awt/Color
   #11 = Methodref          #9.#12        // java/awt/Color."<init>":(III)V
   #12 = NameAndType        #5:#13        // "<init>":(III)V
   #13 = Utf8               (III)V
   #14 = Methodref          #15.#16       // javax/swing/UIManager.put:(Ljava/lang/Object;Ljava/lang/Object;)Ljava/lang/Object;
   #15 = Class              #17           // javax/swing/UIManager
   #16 = NameAndType        #18:#19       // put:(Ljava/lang/Object;Ljava/lang/Object;)Ljava/lang/Object;
   #17 = Utf8               javax/swing/UIManager
   #18 = Utf8               put
   #19 = Utf8               (Ljava/lang/Object;Ljava/lang/Object;)Ljava/lang/Object;
   #20 = String             #21           // info
   #21 = Utf8               info
   #22 = String             #23           // nimbusBase
   #23 = Utf8               nimbusBase
   #24 = String             #25           // nimbusBlueGrey
   #25 = Utf8               nimbusBlueGrey
   #26 = String             #27           // nimbusLightBackground
   #27 = Utf8               nimbusLightBackground
   #28 = String             #29           // text
   #29 = Utf8               text
   #30 = String             #31           // nimbusSelectionBackground
   #31 = Utf8               nimbusSelectionBackground
   #32 = String             #33           // nimbusSelectedText
   #33 = Utf8               nimbusSelectedText
   #34 = String             #35           // nimbusFocus
   #35 = Utf8               nimbusFocus
   #36 = String             #37           // nimbusDisabledText
   #37 = Utf8               nimbusDisabledText
   #38 = String             #39           // nimbusRed
   #39 = Utf8               nimbusRed
   #40 = String             #41           // nimbusOrange
   #41 = Utf8               nimbusOrange
   #42 = String             #43           // nimbusGreen
   #43 = Utf8               nimbusGreen
   #44 = String             #45           // nimbusAlertYellow
   #45 = Utf8               nimbusAlertYellow
   #46 = String             #47           // nimbusInfoBlue
   #47 = Utf8               nimbusInfoBlue
   #48 = Class              #49           // javax/swing/plaf/nimbus/NimbusLookAndFeel
   #49 = Utf8               javax/swing/plaf/nimbus/NimbusLookAndFeel
   #50 = Methodref          #48.#3        // javax/swing/plaf/nimbus/NimbusLookAndFeel."<init>":()V
   #51 = Methodref          #15.#52       // javax/swing/UIManager.setLookAndFeel:(Ljavax/swing/LookAndFeel;)V
   #52 = NameAndType        #53:#54       // setLookAndFeel:(Ljavax/swing/LookAndFeel;)V
   #53 = Utf8               setLookAndFeel
   #54 = Utf8               (Ljavax/swing/LookAndFeel;)V
   #55 = Class              #56           // java/lang/Exception
   #56 = Utf8               java/lang/Exception
   #57 = Methodref          #55.#58       // java/lang/Exception.printStackTrace:()V
   #58 = NameAndType        #59:#6        // printStackTrace:()V
   #59 = Utf8               printStackTrace
   #60 = Class              #61           // javax/swing/JTextArea
   #61 = Utf8               javax/swing/JTextArea
   #62 = Methodref          #60.#3        // javax/swing/JTextArea."<init>":()V
   #63 = Fieldref           #64.#65       // ext/mods/commons/gui/InterfaceBalance.txtrConsole:Ljavax/swing/JTextArea;
   #64 = Class              #66           // ext/mods/commons/gui/InterfaceBalance
   #65 = NameAndType        #67:#68       // txtrConsole:Ljavax/swing/JTextArea;
   #66 = Utf8               ext/mods/commons/gui/InterfaceBalance
   #67 = Utf8               txtrConsole
   #68 = Utf8               Ljavax/swing/JTextArea;
   #69 = Methodref          #60.#70       // javax/swing/JTextArea.setEditable:(Z)V
   #70 = NameAndType        #71:#72       // setEditable:(Z)V
   #71 = Utf8               setEditable
   #72 = Utf8               (Z)V
   #73 = Methodref          #60.#74       // javax/swing/JTextArea.setLineWrap:(Z)V
   #74 = NameAndType        #75:#72       // setLineWrap:(Z)V
   #75 = Utf8               setLineWrap
   #76 = Methodref          #60.#77       // javax/swing/JTextArea.setWrapStyleWord:(Z)V
   #77 = NameAndType        #78:#72       // setWrapStyleWord:(Z)V
   #78 = Utf8               setWrapStyleWord
   #79 = Fieldref           #80.#81       // javax/swing/DropMode.INSERT:Ljavax/swing/DropMode;
   #80 = Class              #82           // javax/swing/DropMode
   #81 = NameAndType        #83:#84       // INSERT:Ljavax/swing/DropMode;
   #82 = Utf8               javax/swing/DropMode
   #83 = Utf8               INSERT
   #84 = Utf8               Ljavax/swing/DropMode;
   #85 = Methodref          #60.#86       // javax/swing/JTextArea.setDropMode:(Ljavax/swing/DropMode;)V
   #86 = NameAndType        #87:#88       // setDropMode:(Ljavax/swing/DropMode;)V
   #87 = Utf8               setDropMode
   #88 = Utf8               (Ljavax/swing/DropMode;)V
   #89 = Class              #90           // java/awt/Font
   #90 = Utf8               java/awt/Font
   #91 = String             #92           // Monospaced
   #92 = Utf8               Monospaced
   #93 = Methodref          #89.#94       // java/awt/Font."<init>":(Ljava/lang/String;II)V
   #94 = NameAndType        #5:#95        // "<init>":(Ljava/lang/String;II)V
   #95 = Utf8               (Ljava/lang/String;II)V
   #96 = Methodref          #60.#97       // javax/swing/JTextArea.setFont:(Ljava/awt/Font;)V
   #97 = NameAndType        #98:#99       // setFont:(Ljava/awt/Font;)V
   #98 = Utf8               setFont
   #99 = Utf8               (Ljava/awt/Font;)V
  #100 = Methodref          #60.#101      // javax/swing/JTextArea.getDocument:()Ljavax/swing/text/Document;
  #101 = NameAndType        #102:#103     // getDocument:()Ljavax/swing/text/Document;
  #102 = Utf8               getDocument
  #103 = Utf8               ()Ljavax/swing/text/Document;
  #104 = Class              #105          // ext/mods/commons/gui/InterfaceLimit
  #105 = Utf8               ext/mods/commons/gui/InterfaceLimit
  #106 = Methodref          #104.#107     // ext/mods/commons/gui/InterfaceLimit."<init>":(I)V
  #107 = NameAndType        #5:#108       // "<init>":(I)V
  #108 = Utf8               (I)V
  #109 = InterfaceMethodref #110.#111     // javax/swing/text/Document.addDocumentListener:(Ljavax/swing/event/DocumentListener;)V
  #110 = Class              #112          // javax/swing/text/Document
  #111 = NameAndType        #113:#114     // addDocumentListener:(Ljavax/swing/event/DocumentListener;)V
  #112 = Utf8               javax/swing/text/Document
  #113 = Utf8               addDocumentListener
  #114 = Utf8               (Ljavax/swing/event/DocumentListener;)V
  #115 = Class              #116          // javax/swing/JMenuBar
  #116 = Utf8               javax/swing/JMenuBar
  #117 = Methodref          #115.#3       // javax/swing/JMenuBar."<init>":()V
  #118 = String             #119          // Segoe UI
  #119 = Utf8               Segoe UI
  #120 = Methodref          #115.#97      // javax/swing/JMenuBar.setFont:(Ljava/awt/Font;)V
  #121 = Class              #122          // javax/swing/JMenu
  #122 = Utf8               javax/swing/JMenu
  #123 = String             #124          // Option
  #124 = Utf8               Option
  #125 = Methodref          #121.#126     // javax/swing/JMenu."<init>":(Ljava/lang/String;)V
  #126 = NameAndType        #5:#127       // "<init>":(Ljava/lang/String;)V
  #127 = Utf8               (Ljava/lang/String;)V
  #128 = Methodref          #121.#97      // javax/swing/JMenu.setFont:(Ljava/awt/Font;)V
  #129 = Methodref          #115.#130     // javax/swing/JMenuBar.add:(Ljavax/swing/JMenu;)Ljavax/swing/JMenu;
  #130 = NameAndType        #131:#132     // add:(Ljavax/swing/JMenu;)Ljavax/swing/JMenu;
  #131 = Utf8               add
  #132 = Utf8               (Ljavax/swing/JMenu;)Ljavax/swing/JMenu;
  #133 = Class              #134          // javax/swing/JMenuItem
  #134 = Utf8               javax/swing/JMenuItem
  #135 = String             #136          // Damage
  #136 = Utf8               Damage
  #137 = Methodref          #133.#126     // javax/swing/JMenuItem."<init>":(Ljava/lang/String;)V
  #138 = InvokeDynamic      #0:#139       // #0:actionPerformed:(Lext/mods/commons/gui/InterfaceBalance;)Ljava/awt/event/ActionListener;
  #139 = NameAndType        #140:#141     // actionPerformed:(Lext/mods/commons/gui/InterfaceBalance;)Ljava/awt/event/ActionListener;
  #140 = Utf8               actionPerformed
  #141 = Utf8               (Lext/mods/commons/gui/InterfaceBalance;)Ljava/awt/event/ActionListener;
  #142 = Methodref          #133.#143     // javax/swing/JMenuItem.addActionListener:(Ljava/awt/event/ActionListener;)V
  #143 = NameAndType        #144:#145     // addActionListener:(Ljava/awt/event/ActionListener;)V
  #144 = Utf8               addActionListener
  #145 = Utf8               (Ljava/awt/event/ActionListener;)V
  #146 = Methodref          #121.#147     // javax/swing/JMenu.add:(Ljavax/swing/JMenuItem;)Ljavax/swing/JMenuItem;
  #147 = NameAndType        #131:#148     // add:(Ljavax/swing/JMenuItem;)Ljavax/swing/JMenuItem;
  #148 = Utf8               (Ljavax/swing/JMenuItem;)Ljavax/swing/JMenuItem;
  #149 = String             #150          // Defence
  #150 = Utf8               Defence
  #151 = InvokeDynamic      #1:#139       // #1:actionPerformed:(Lext/mods/commons/gui/InterfaceBalance;)Ljava/awt/event/ActionListener;
  #152 = String             #153          // Vulnerability
  #153 = Utf8               Vulnerability
  #154 = InvokeDynamic      #2:#139       // #2:actionPerformed:(Lext/mods/commons/gui/InterfaceBalance;)Ljava/awt/event/ActionListener;
  #155 = String             #156          // Font
  #156 = Utf8               Font
  #157 = Class              #158          // java/lang/String
  #158 = Utf8               java/lang/String
  #159 = String             #160          // 10
  #160 = Utf8               10
  #161 = String             #162          // 13
  #162 = Utf8               13
  #163 = String             #164          // 16
  #164 = Utf8               16
  #165 = String             #166          // 21
  #166 = Utf8               21
  #167 = String             #168          // 27
  #168 = Utf8               27
  #169 = String             #170          // 33
  #170 = Utf8               33
  #171 = Methodref          #133.#97      // javax/swing/JMenuItem.setFont:(Ljava/awt/Font;)V
  #172 = InvokeDynamic      #3:#173       // #3:actionPerformed:(Lext/mods/commons/gui/InterfaceBalance;Ljava/lang/String;)Ljava/awt/event/ActionListener;
  #173 = NameAndType        #140:#174     // actionPerformed:(Lext/mods/commons/gui/InterfaceBalance;Ljava/lang/String;)Ljava/awt/event/ActionListener;
  #174 = Utf8               (Lext/mods/commons/gui/InterfaceBalance;Ljava/lang/String;)Ljava/awt/event/ActionListener;
  #175 = Class              #176          // java/util/ArrayList
  #176 = Utf8               java/util/ArrayList
  #177 = Methodref          #175.#3       // java/util/ArrayList."<init>":()V
  #178 = Class              #179          // javax/swing/ImageIcon
  #179 = Utf8               javax/swing/ImageIcon
  #180 = Fieldref           #181.#182     // java/io/File.separator:Ljava/lang/String;
  #181 = Class              #183          // java/io/File
  #182 = NameAndType        #184:#185     // separator:Ljava/lang/String;
  #183 = Utf8               java/io/File
  #184 = Utf8               separator
  #185 = Utf8               Ljava/lang/String;
  #186 = InvokeDynamic      #4:#187       // #4:makeConcatWithConstants:(Ljava/lang/String;Ljava/lang/String;)Ljava/lang/String;
  #187 = NameAndType        #188:#189     // makeConcatWithConstants:(Ljava/lang/String;Ljava/lang/String;)Ljava/lang/String;
  #188 = Utf8               makeConcatWithConstants
  #189 = Utf8               (Ljava/lang/String;Ljava/lang/String;)Ljava/lang/String;
  #190 = Methodref          #178.#126     // javax/swing/ImageIcon."<init>":(Ljava/lang/String;)V
  #191 = Methodref          #178.#192     // javax/swing/ImageIcon.getImage:()Ljava/awt/Image;
  #192 = NameAndType        #193:#194     // getImage:()Ljava/awt/Image;
  #193 = Utf8               getImage
  #194 = Utf8               ()Ljava/awt/Image;
  #195 = InterfaceMethodref #196.#197     // java/util/List.add:(Ljava/lang/Object;)Z
  #196 = Class              #198          // java/util/List
  #197 = NameAndType        #131:#199     // add:(Ljava/lang/Object;)Z
  #198 = Utf8               java/util/List
  #199 = Utf8               (Ljava/lang/Object;)Z
  #200 = InvokeDynamic      #5:#187       // #5:makeConcatWithConstants:(Ljava/lang/String;Ljava/lang/String;)Ljava/lang/String;
  #201 = Class              #202          // javax/swing/JScrollPane
  #202 = Utf8               javax/swing/JScrollPane
  #203 = Methodref          #201.#204     // javax/swing/JScrollPane."<init>":(Ljava/awt/Component;)V
  #204 = NameAndType        #5:#205       // "<init>":(Ljava/awt/Component;)V
  #205 = Utf8               (Ljava/awt/Component;)V
  #206 = Class              #207          // javax/swing/JFrame
  #207 = Utf8               javax/swing/JFrame
  #208 = String             #209          // Balance
  #209 = Utf8               Balance
  #210 = Methodref          #206.#126     // javax/swing/JFrame."<init>":(Ljava/lang/String;)V
  #211 = Class              #212          // javax/swing/WindowConstants
  #212 = Utf8               javax/swing/WindowConstants
  #213 = Methodref          #206.#214     // javax/swing/JFrame.setDefaultCloseOperation:(I)V
  #214 = NameAndType        #215:#108     // setDefaultCloseOperation:(I)V
  #215 = Utf8               setDefaultCloseOperation
  #216 = Class              #217          // ext/mods/commons/gui/InterfaceBalance$7
  #217 = Utf8               ext/mods/commons/gui/InterfaceBalance$7
  #218 = Methodref          #216.#219     // ext/mods/commons/gui/InterfaceBalance$7."<init>":(Lext/mods/commons/gui/InterfaceBalance;Ljavax/swing/JFrame;)V
  #219 = NameAndType        #5:#220       // "<init>":(Lext/mods/commons/gui/InterfaceBalance;Ljavax/swing/JFrame;)V
  #220 = Utf8               (Lext/mods/commons/gui/InterfaceBalance;Ljavax/swing/JFrame;)V
  #221 = Methodref          #206.#222     // javax/swing/JFrame.addWindowListener:(Ljava/awt/event/WindowListener;)V
  #222 = NameAndType        #223:#224     // addWindowListener:(Ljava/awt/event/WindowListener;)V
  #223 = Utf8               addWindowListener
  #224 = Utf8               (Ljava/awt/event/WindowListener;)V
  #225 = Class              #226          // ext/mods/commons/gui/InterfaceBalance$8
  #226 = Utf8               ext/mods/commons/gui/InterfaceBalance$8
  #227 = Methodref          #225.#228     // ext/mods/commons/gui/InterfaceBalance$8."<init>":(Lext/mods/commons/gui/InterfaceBalance;Ljavax/swing/JScrollPane;Ljavax/swing/JFrame;)V
  #228 = NameAndType        #5:#229       // "<init>":(Lext/mods/commons/gui/InterfaceBalance;Ljavax/swing/JScrollPane;Ljavax/swing/JFrame;)V
  #229 = Utf8               (Lext/mods/commons/gui/InterfaceBalance;Ljavax/swing/JScrollPane;Ljavax/swing/JFrame;)V
  #230 = Methodref          #206.#231     // javax/swing/JFrame.addComponentListener:(Ljava/awt/event/ComponentListener;)V
  #231 = NameAndType        #232:#233     // addComponentListener:(Ljava/awt/event/ComponentListener;)V
  #232 = Utf8               addComponentListener
  #233 = Utf8               (Ljava/awt/event/ComponentListener;)V
  #234 = Methodref          #206.#235     // javax/swing/JFrame.setJMenuBar:(Ljavax/swing/JMenuBar;)V
  #235 = NameAndType        #236:#237     // setJMenuBar:(Ljavax/swing/JMenuBar;)V
  #236 = Utf8               setJMenuBar
  #237 = Utf8               (Ljavax/swing/JMenuBar;)V
  #238 = Methodref          #206.#239     // javax/swing/JFrame.setIconImages:(Ljava/util/List;)V
  #239 = NameAndType        #240:#241     // setIconImages:(Ljava/util/List;)V
  #240 = Utf8               setIconImages
  #241 = Utf8               (Ljava/util/List;)V
  #242 = Methodref          #206.#243     // javax/swing/JFrame.getContentPane:()Ljava/awt/Container;
  #243 = NameAndType        #244:#245     // getContentPane:()Ljava/awt/Container;
  #244 = Utf8               getContentPane
  #245 = Utf8               ()Ljava/awt/Container;
  #246 = Class              #247          // java/awt/BorderLayout
  #247 = Utf8               java/awt/BorderLayout
  #248 = Methodref          #246.#3       // java/awt/BorderLayout."<init>":()V
  #249 = Methodref          #250.#251     // java/awt/Container.setLayout:(Ljava/awt/LayoutManager;)V
  #250 = Class              #252          // java/awt/Container
  #251 = NameAndType        #253:#254     // setLayout:(Ljava/awt/LayoutManager;)V
  #252 = Utf8               java/awt/Container
  #253 = Utf8               setLayout
  #254 = Utf8               (Ljava/awt/LayoutManager;)V
  #255 = String             #256          // Center
  #256 = Utf8               Center
  #257 = Methodref          #206.#258     // javax/swing/JFrame.add:(Ljava/awt/Component;Ljava/lang/Object;)V
  #258 = NameAndType        #131:#259     // add:(Ljava/awt/Component;Ljava/lang/Object;)V
  #259 = Utf8               (Ljava/awt/Component;Ljava/lang/Object;)V
  #260 = Class              #261          // java/awt/Dimension
  #261 = Utf8               java/awt/Dimension
  #262 = Methodref          #260.#263     // java/awt/Dimension."<init>":(II)V
  #263 = NameAndType        #5:#264       // "<init>":(II)V
  #264 = Utf8               (II)V
  #265 = Methodref          #250.#266     // java/awt/Container.setPreferredSize:(Ljava/awt/Dimension;)V
  #266 = NameAndType        #267:#268     // setPreferredSize:(Ljava/awt/Dimension;)V
  #267 = Utf8               setPreferredSize
  #268 = Utf8               (Ljava/awt/Dimension;)V
  #269 = Methodref          #206.#270     // javax/swing/JFrame.pack:()V
  #270 = NameAndType        #271:#6       // pack:()V
  #271 = Utf8               pack
  #272 = Methodref          #206.#273     // javax/swing/JFrame.setLocationRelativeTo:(Ljava/awt/Component;)V
  #273 = NameAndType        #274:#205     // setLocationRelativeTo:(Ljava/awt/Component;)V
  #274 = Utf8               setLocationRelativeTo
  #275 = Methodref          #64.#276      // ext/mods/commons/gui/InterfaceBalance.redirectSystemStreams:()V
  #276 = NameAndType        #277:#6       // redirectSystemStreams:()V
  #277 = Utf8               redirectSystemStreams
  #278 = Methodref          #206.#279     // javax/swing/JFrame.setVisible:(Z)V
  #279 = NameAndType        #280:#72      // setVisible:(Z)V
  #280 = Utf8               setVisible
  #281 = Methodref          #206.#282     // javax/swing/JFrame.toFront:()V
  #282 = NameAndType        #283:#6       // toFront:()V
  #283 = Utf8               toFront
  #284 = Class              #285          // java/awt/Frame
  #285 = Utf8               java/awt/Frame
  #286 = Methodref          #206.#287     // javax/swing/JFrame.setState:(I)V
  #287 = NameAndType        #288:#108     // setState:(I)V
  #288 = Utf8               setState
  #289 = Class              #290          // ext/mods/commons/gui/InterfaceBalance$9
  #290 = Utf8               ext/mods/commons/gui/InterfaceBalance$9
  #291 = Methodref          #289.#292     // ext/mods/commons/gui/InterfaceBalance$9."<init>":(Lext/mods/commons/gui/InterfaceBalance;)V
  #292 = NameAndType        #5:#293       // "<init>":(Lext/mods/commons/gui/InterfaceBalance;)V
  #293 = Utf8               (Lext/mods/commons/gui/InterfaceBalance;)V
  #294 = Class              #295          // java/io/PrintStream
  #295 = Utf8               java/io/PrintStream
  #296 = Methodref          #294.#297     // java/io/PrintStream."<init>":(Ljava/io/OutputStream;Z)V
  #297 = NameAndType        #5:#298       // "<init>":(Ljava/io/OutputStream;Z)V
  #298 = Utf8               (Ljava/io/OutputStream;Z)V
  #299 = Methodref          #300.#301     // java/lang/System.setOut:(Ljava/io/PrintStream;)V
  #300 = Class              #302          // java/lang/System
  #301 = NameAndType        #303:#304     // setOut:(Ljava/io/PrintStream;)V
  #302 = Utf8               java/lang/System
  #303 = Utf8               setOut
  #304 = Utf8               (Ljava/io/PrintStream;)V
  #305 = Methodref          #300.#306     // java/lang/System.setErr:(Ljava/io/PrintStream;)V
  #306 = NameAndType        #307:#304     // setErr:(Ljava/io/PrintStream;)V
  #307 = Utf8               setErr
  #308 = InvokeDynamic      #6:#309       // #6:run:(Lext/mods/commons/gui/InterfaceBalance;Ljava/lang/String;)Ljava/lang/Runnable;
  #309 = NameAndType        #310:#311     // run:(Lext/mods/commons/gui/InterfaceBalance;Ljava/lang/String;)Ljava/lang/Runnable;
  #310 = Utf8               run
  #311 = Utf8               (Lext/mods/commons/gui/InterfaceBalance;Ljava/lang/String;)Ljava/lang/Runnable;
  #312 = Methodref          #313.#314     // javax/swing/SwingUtilities.invokeLater:(Ljava/lang/Runnable;)V
  #313 = Class              #315          // javax/swing/SwingUtilities
  #314 = NameAndType        #316:#317     // invokeLater:(Ljava/lang/Runnable;)V
  #315 = Utf8               javax/swing/SwingUtilities
  #316 = Utf8               invokeLater
  #317 = Utf8               (Ljava/lang/Runnable;)V
  #318 = Methodref          #60.#319      // javax/swing/JTextArea.append:(Ljava/lang/String;)V
  #319 = NameAndType        #320:#127     // append:(Ljava/lang/String;)V
  #320 = Utf8               append
  #321 = Methodref          #60.#322      // javax/swing/JTextArea.getText:()Ljava/lang/String;
  #322 = NameAndType        #323:#324     // getText:()Ljava/lang/String;
  #323 = Utf8               getText
  #324 = Utf8               ()Ljava/lang/String;
  #325 = Methodref          #157.#326     // java/lang/String.length:()I
  #326 = NameAndType        #327:#328     // length:()I
  #327 = Utf8               length
  #328 = Utf8               ()I
  #329 = Methodref          #60.#330      // javax/swing/JTextArea.setCaretPosition:(I)V
  #330 = NameAndType        #331:#108     // setCaretPosition:(I)V
  #331 = Utf8               setCaretPosition
  #332 = Methodref          #333.#334     // java/lang/Integer.parseInt:(Ljava/lang/String;)I
  #333 = Class              #335          // java/lang/Integer
  #334 = NameAndType        #336:#337     // parseInt:(Ljava/lang/String;)I
  #335 = Utf8               java/lang/Integer
  #336 = Utf8               parseInt
  #337 = Utf8               (Ljava/lang/String;)I
  #338 = String             #339          // Information Balance
  #339 = Utf8               Information Balance
  #340 = Class              #341          // ext/mods/commons/gui/vulnerabilityefence
  #341 = Utf8               ext/mods/commons/gui/vulnerabilityefence
  #342 = Methodref          #340.#3       // ext/mods/commons/gui/vulnerabilityefence."<init>":()V
  #343 = Class              #344          // javax/swing/JTable
  #344 = Utf8               javax/swing/JTable
  #345 = Methodref          #343.#346     // javax/swing/JTable."<init>":(Ljavax/swing/table/TableModel;)V
  #346 = NameAndType        #5:#347       // "<init>":(Ljavax/swing/table/TableModel;)V
  #347 = Utf8               (Ljavax/swing/table/TableModel;)V
  #348 = Class              #349          // ext/mods/commons/gui/InterfaceBalance$5
  #349 = Utf8               ext/mods/commons/gui/InterfaceBalance$5
  #350 = Methodref          #348.#292     // ext/mods/commons/gui/InterfaceBalance$5."<init>":(Lext/mods/commons/gui/InterfaceBalance;)V
  #351 = Methodref          #343.#352     // javax/swing/JTable.getColumnModel:()Ljavax/swing/table/TableColumnModel;
  #352 = NameAndType        #353:#354     // getColumnModel:()Ljavax/swing/table/TableColumnModel;
  #353 = Utf8               getColumnModel
  #354 = Utf8               ()Ljavax/swing/table/TableColumnModel;
  #355 = InterfaceMethodref #356.#357     // javax/swing/table/TableColumnModel.getColumn:(I)Ljavax/swing/table/TableColumn;
  #356 = Class              #358          // javax/swing/table/TableColumnModel
  #357 = NameAndType        #359:#360     // getColumn:(I)Ljavax/swing/table/TableColumn;
  #358 = Utf8               javax/swing/table/TableColumnModel
  #359 = Utf8               getColumn
  #360 = Utf8               (I)Ljavax/swing/table/TableColumn;
  #361 = Methodref          #362.#363     // javax/swing/table/TableColumn.setCellRenderer:(Ljavax/swing/table/TableCellRenderer;)V
  #362 = Class              #364          // javax/swing/table/TableColumn
  #363 = NameAndType        #365:#366     // setCellRenderer:(Ljavax/swing/table/TableCellRenderer;)V
  #364 = Utf8               javax/swing/table/TableColumn
  #365 = Utf8               setCellRenderer
  #366 = Utf8               (Ljavax/swing/table/TableCellRenderer;)V
  #367 = Class              #368          // javax/swing/JPanel
  #368 = Utf8               javax/swing/JPanel
  #369 = Methodref          #367.#370     // javax/swing/JPanel."<init>":(Ljava/awt/LayoutManager;)V
  #370 = NameAndType        #5:#254       // "<init>":(Ljava/awt/LayoutManager;)V
  #371 = Class              #372          // javax/swing/JLabel
  #372 = Utf8               javax/swing/JLabel
  #373 = String             #374          // Filtrar Type:
  #374 = Utf8               Filtrar Type:
  #375 = Methodref          #371.#126     // javax/swing/JLabel."<init>":(Ljava/lang/String;)V
  #376 = Class              #377          // javax/swing/JTextField
  #377 = Utf8               javax/swing/JTextField
  #378 = Methodref          #376.#3       // javax/swing/JTextField."<init>":()V
  #379 = String             #380          // West
  #380 = Utf8               West
  #381 = Methodref          #367.#258     // javax/swing/JPanel.add:(Ljava/awt/Component;Ljava/lang/Object;)V
  #382 = Methodref          #376.#101     // javax/swing/JTextField.getDocument:()Ljavax/swing/text/Document;
  #383 = Class              #384          // ext/mods/commons/gui/InterfaceBalance$6
  #384 = Utf8               ext/mods/commons/gui/InterfaceBalance$6
  #385 = Methodref          #383.#386     // ext/mods/commons/gui/InterfaceBalance$6."<init>":(Lext/mods/commons/gui/InterfaceBalance;Lext/mods/commons/gui/vulnerabilityefence;Ljavax/swing/JTextField;)V
  #386 = NameAndType        #5:#387       // "<init>":(Lext/mods/commons/gui/InterfaceBalance;Lext/mods/commons/gui/vulnerabilityefence;Ljavax/swing/JTextField;)V
  #387 = Utf8               (Lext/mods/commons/gui/InterfaceBalance;Lext/mods/commons/gui/vulnerabilityefence;Ljavax/swing/JTextField;)V
  #388 = Class              #389          // javax/swing/JButton
  #389 = Utf8               javax/swing/JButton
  #390 = String             #391          // ?
  #391 = Utf8               ?
  #392 = Methodref          #388.#126     // javax/swing/JButton."<init>":(Ljava/lang/String;)V
  #393 = String             #394          // Clique para entender o sistema de vulnerabilidade por tipo de skill
  #394 = Utf8               Clique para entender o sistema de vulnerabilidade por tipo de skill
  #395 = Methodref          #388.#396     // javax/swing/JButton.setToolTipText:(Ljava/lang/String;)V
  #396 = NameAndType        #397:#127     // setToolTipText:(Ljava/lang/String;)V
  #397 = Utf8               setToolTipText
  #398 = InvokeDynamic      #7:#399       // #7:actionPerformed:(Ljavax/swing/JFrame;)Ljava/awt/event/ActionListener;
  #399 = NameAndType        #140:#400     // actionPerformed:(Ljavax/swing/JFrame;)Ljava/awt/event/ActionListener;
  #400 = Utf8               (Ljavax/swing/JFrame;)Ljava/awt/event/ActionListener;
  #401 = Methodref          #388.#143     // javax/swing/JButton.addActionListener:(Ljava/awt/event/ActionListener;)V
  #402 = String             #403          // North
  #403 = Utf8               North
  #404 = String             #405          // East
  #405 = Utf8               East
  #406 = Methodref          #206.#407     // javax/swing/JFrame.setContentPane:(Ljava/awt/Container;)V
  #407 = NameAndType        #408:#409     // setContentPane:(Ljava/awt/Container;)V
  #408 = Utf8               setContentPane
  #409 = Utf8               (Ljava/awt/Container;)V
  #410 = Methodref          #206.#411     // javax/swing/JFrame.setSize:(II)V
  #411 = NameAndType        #412:#264     // setSize:(II)V
  #412 = Utf8               setSize
  #413 = String             #414          // ? PAINEL DE VULNERABILIDADE POR TIPO DE SKILL\n\n? Esta aba permite controlar o quanto as classes são vulneráveis a efeitos de habilidades (skills) específicas.\n\n? Skill Type ? Define o tipo de efeito da skill (ex: PARALYZE, SLEEP, STUN etc).\n? Multiplier ? Define o modificador de chance que o tipo de efeito terá ao ser aplicado na vítima.\n\n? Valor 1.0: Chance normal da skill.\n? Valor acima de 1.0: Aumenta a chance de aplicação (ex: 1.2 = 20% mais fácil de aplicar).\n? Valor abaixo de 1.0: Reduz a chance de aplicação (ex: 0.8 = 20% mais difícil de aplicar).\n\n? Esses valores atuam sobre a **resistência global** de todas as classes a cada tipo de efeito.\n? Por exemplo, se STUN estiver com 0.8, todas as classes do jogo terão 20% mais resistência contra stun.\n\n? Use esse painel para balancear o impacto de efeitos de controle no PvP/PvE, reduzindo abusos ou fortalecendo tipos pouco usados.
  #414 = Utf8               ? PAINEL DE VULNERABILIDADE POR TIPO DE SKILL\n\n? Esta aba permite controlar o quanto as classes são vulneráveis a efeitos de habilidades (skills) específicas.\n\n? Skill Type ? Define o tipo de efeito da skill (ex: PARALYZE, SLEEP, STUN etc).\n? Multiplier ? Define o modificador de chance que o tipo de efeito terá ao ser aplicado na vítima.\n\n? Valor 1.0: Chance normal da skill.\n? Valor acima de 1.0: Aumenta a chance de aplicação (ex: 1.2 = 20% mais fácil de aplicar).\n? Valor abaixo de 1.0: Reduz a chance de aplicação (ex: 0.8 = 20% mais difícil de aplicar).\n\n? Esses valores atuam sobre a **resistência global** de todas as classes a cada tipo de efeito.\n? Por exemplo, se STUN estiver com 0.8, todas as classes do jogo terão 20% mais resistência contra stun.\n\n? Use esse painel para balancear o impacto de efeitos de controle no PvP/PvE, reduzindo abusos ou fortalecendo tipos pouco usados.
  #415 = String             #416          // Ajuda - Vulnerabilidades de Skills
  #416 = Utf8               Ajuda - Vulnerabilidades de Skills
  #417 = Class              #418          // javax/swing/JOptionPane
  #418 = Utf8               javax/swing/JOptionPane
  #419 = Methodref          #417.#420     // javax/swing/JOptionPane.showMessageDialog:(Ljava/awt/Component;Ljava/lang/Object;Ljava/lang/String;I)V
  #420 = NameAndType        #421:#422     // showMessageDialog:(Ljava/awt/Component;Ljava/lang/Object;Ljava/lang/String;I)V
  #421 = Utf8               showMessageDialog
  #422 = Utf8               (Ljava/awt/Component;Ljava/lang/Object;Ljava/lang/String;I)V
  #423 = Class              #424          // ext/mods/commons/gui/defence
  #424 = Utf8               ext/mods/commons/gui/defence
  #425 = Methodref          #423.#3       // ext/mods/commons/gui/defence."<init>":()V
  #426 = Class              #427          // ext/mods/commons/gui/InterfaceBalance$3
  #427 = Utf8               ext/mods/commons/gui/InterfaceBalance$3
  #428 = Methodref          #426.#292     // ext/mods/commons/gui/InterfaceBalance$3."<init>":(Lext/mods/commons/gui/InterfaceBalance;)V
  #429 = String             #430          // Filtrar classe:
  #430 = Utf8               Filtrar classe:
  #431 = Class              #432          // ext/mods/commons/gui/InterfaceBalance$4
  #432 = Utf8               ext/mods/commons/gui/InterfaceBalance$4
  #433 = Methodref          #431.#434     // ext/mods/commons/gui/InterfaceBalance$4."<init>":(Lext/mods/commons/gui/InterfaceBalance;Lext/mods/commons/gui/defence;Ljavax/swing/JTextField;)V
  #434 = NameAndType        #5:#435       // "<init>":(Lext/mods/commons/gui/InterfaceBalance;Lext/mods/commons/gui/defence;Ljavax/swing/JTextField;)V
  #435 = Utf8               (Lext/mods/commons/gui/InterfaceBalance;Lext/mods/commons/gui/defence;Ljavax/swing/JTextField;)V
  #436 = String             #437          // Clique para entender o sistema de defesa entre classes
  #437 = Utf8               Clique para entender o sistema de defesa entre classes
  #438 = InvokeDynamic      #8:#399       // #8:actionPerformed:(Ljavax/swing/JFrame;)Ljava/awt/event/ActionListener;
  #439 = String             #440          // ? PAINEL DE BALANCEAMENTO DE DEFESA ENTRE CLASSES\n\n? Este painel permite controlar a defesa física (P.Def) e mágica (M.Def) que uma classe recebe contra outra.\n? Cada linha representa o modificador de defesa que a classe Target (alvo) terá ao enfrentar a classe Attacker (atacante).\n\n? P.Def ? Controla a defesa física que será aplicada contra ataques físicos.\n? M.Def ? Controla a defesa mágica que será aplicada contra ataques mágicos.\n\n? Valor 1.0: Defesa normal, sem alteração.\n? Valor acima de 1.0: Aumenta a defesa (ex: 1.2 = 20% a mais de resistência).\n? Valor abaixo de 1.0: Reduz a defesa (ex: 0.8 = 20% mais vulnerável).\n\n? Os valores modificam diretamente a resistência que o alvo terá ao ser atacado por aquela classe.\n? Os valores coloridos indicam modificações:\n   - Verde: aumento de defesa.\n   - Vermelho: redução de defesa.\n\n? Use o campo de filtro para buscar uma classe específica e ajustar suas vulnerabilidades defensivas.
  #440 = Utf8               ? PAINEL DE BALANCEAMENTO DE DEFESA ENTRE CLASSES\n\n? Este painel permite controlar a defesa física (P.Def) e mágica (M.Def) que uma classe recebe contra outra.\n? Cada linha representa o modificador de defesa que a classe Target (alvo) terá ao enfrentar a classe Attacker (atacante).\n\n? P.Def ? Controla a defesa física que será aplicada contra ataques físicos.\n? M.Def ? Controla a defesa mágica que será aplicada contra ataques mágicos.\n\n? Valor 1.0: Defesa normal, sem alteração.\n? Valor acima de 1.0: Aumenta a defesa (ex: 1.2 = 20% a mais de resistência).\n? Valor abaixo de 1.0: Reduz a defesa (ex: 0.8 = 20% mais vulnerável).\n\n? Os valores modificam diretamente a resistência que o alvo terá ao ser atacado por aquela classe.\n? Os valores coloridos indicam modificações:\n   - Verde: aumento de defesa.\n   - Vermelho: redução de defesa.\n\n? Use o campo de filtro para buscar uma classe específica e ajustar suas vulnerabilidades defensivas.
  #441 = String             #442          // Ajuda - Sistema de Defesa
  #442 = Utf8               Ajuda - Sistema de Defesa
  #443 = Class              #444          // ext/mods/commons/gui/damage
  #444 = Utf8               ext/mods/commons/gui/damage
  #445 = Methodref          #443.#3       // ext/mods/commons/gui/damage."<init>":()V
  #446 = Class              #447          // ext/mods/commons/gui/InterfaceBalance$1
  #447 = Utf8               ext/mods/commons/gui/InterfaceBalance$1
  #448 = Methodref          #446.#292     // ext/mods/commons/gui/InterfaceBalance$1."<init>":(Lext/mods/commons/gui/InterfaceBalance;)V
  #449 = Class              #450          // ext/mods/commons/gui/InterfaceBalance$2
  #450 = Utf8               ext/mods/commons/gui/InterfaceBalance$2
  #451 = Methodref          #449.#452     // ext/mods/commons/gui/InterfaceBalance$2."<init>":(Lext/mods/commons/gui/InterfaceBalance;Lext/mods/commons/gui/damage;Ljavax/swing/JTextField;)V
  #452 = NameAndType        #5:#453       // "<init>":(Lext/mods/commons/gui/InterfaceBalance;Lext/mods/commons/gui/damage;Ljavax/swing/JTextField;)V
  #453 = Utf8               (Lext/mods/commons/gui/InterfaceBalance;Lext/mods/commons/gui/damage;Ljavax/swing/JTextField;)V
  #454 = String             #455          // Clique para entender o sistema de balanceamento
  #455 = Utf8               Clique para entender o sistema de balanceamento
  #456 = InvokeDynamic      #9:#399       // #9:actionPerformed:(Ljavax/swing/JFrame;)Ljava/awt/event/ActionListener;
  #457 = String             #458          // ? PAINEL DE BALANCEAMENTO DE DANO ENTRE CLASSES\n\n? Este painel permite controlar o dano físico (P.Atk) e mágico (M.Atk) entre classes PvP.\n? Cada linha representa o modificador de dano de uma classe (Attacker) contra outra (Target).\n\n? P.Atk ? Controla o dano físico causado.\n? M.Atk ? Controla o dano mágico causado.\n\n? Valor 1.0: Dano normal, sem alteração.\n? Valor acima de 1.0: Aumenta o dano (ex: 1.2 = 20% a mais).\n? Valor abaixo de 1.0: Reduz o dano (ex: 0.8 = 20% a menos).\n\n? Os valores modificam diretamente o cálculo do dano final entre as classes.\n? Os valores coloridos indicam modificações:\n   - Verde: aumento de dano.\n   - Vermelho: redução de dano.\n\n? Use o filtro acima para buscar uma classe específica e editar seus modificadores.
  #458 = Utf8               ? PAINEL DE BALANCEAMENTO DE DANO ENTRE CLASSES\n\n? Este painel permite controlar o dano físico (P.Atk) e mágico (M.Atk) entre classes PvP.\n? Cada linha representa o modificador de dano de uma classe (Attacker) contra outra (Target).\n\n? P.Atk ? Controla o dano físico causado.\n? M.Atk ? Controla o dano mágico causado.\n\n? Valor 1.0: Dano normal, sem alteração.\n? Valor acima de 1.0: Aumenta o dano (ex: 1.2 = 20% a mais).\n? Valor abaixo de 1.0: Reduz o dano (ex: 0.8 = 20% a menos).\n\n? Os valores modificam diretamente o cálculo do dano final entre as classes.\n? Os valores coloridos indicam modificações:\n   - Verde: aumento de dano.\n   - Vermelho: redução de dano.\n\n? Use o filtro acima para buscar uma classe específica e editar seus modificadores.
  #459 = String             #460          // Ajuda - Sistema de Balanceamento
  #460 = Utf8               Ajuda - Sistema de Balanceamento
  #461 = String             #462          // Shutdown
  #462 = Utf8               Shutdown
  #463 = String             #464          // Cancel
  #464 = Utf8               Cancel
  #465 = Fieldref           #64.#466      // ext/mods/commons/gui/InterfaceBalance.shutdownOptions:[Ljava/lang/String;
  #466 = NameAndType        #467:#468     // shutdownOptions:[Ljava/lang/String;
  #467 = Utf8               shutdownOptions
  #468 = Utf8               [Ljava/lang/String;
  #469 = Utf8               Code
  #470 = Utf8               LineNumberTable
  #471 = Utf8               LocalVariableTable
  #472 = Utf8               e
  #473 = Utf8               Ljava/lang/Exception;
  #474 = Utf8               mntmFont
  #475 = Utf8               Ljavax/swing/JMenuItem;
  #476 = Utf8               font
  #477 = Utf8               this
  #478 = Utf8               Lext/mods/commons/gui/InterfaceBalance;
  #479 = Utf8               menuBar
  #480 = Utf8               Ljavax/swing/JMenuBar;
  #481 = Utf8               mnBalance
  #482 = Utf8               Ljavax/swing/JMenu;
  #483 = Utf8               viewModifiers
  #484 = Utf8               viewDefence
  #485 = Utf8               viewvulnerability
  #486 = Utf8               mnFont
  #487 = Utf8               fonts
  #488 = Utf8               icons
  #489 = Utf8               Ljava/util/List;
  #490 = Utf8               scrollPanel
  #491 = Utf8               Ljavax/swing/JScrollPane;
  #492 = Utf8               frame
  #493 = Utf8               Ljavax/swing/JFrame;
  #494 = Utf8               LocalVariableTypeTable
  #495 = Utf8               Ljava/util/List<Ljava/awt/Image;>;
  #496 = Utf8               StackMapTable
  #497 = Class              #468          // "[Ljava/lang/String;"
  #498 = Utf8               out
  #499 = Utf8               Ljava/io/OutputStream;
  #500 = Utf8               updateTextArea
  #501 = Utf8               lambda$updateTextArea$0
  #502 = Utf8               lambda$new$6
  #503 = Utf8               (Ljava/lang/String;Ljava/awt/event/ActionEvent;)V
  #504 = Utf8               arg0
  #505 = Utf8               Ljava/awt/event/ActionEvent;
  #506 = Utf8               lambda$new$4
  #507 = Utf8               (Ljava/awt/event/ActionEvent;)V
  #508 = Utf8               i
  #509 = Utf8               I
  #510 = Utf8               balanceFrame
  #511 = Utf8               model
  #512 = Utf8               Lext/mods/commons/gui/vulnerabilityefence;
  #513 = Utf8               table
  #514 = Utf8               Ljavax/swing/JTable;
  #515 = Utf8               scroll
  #516 = Utf8               customRenderer
  #517 = Utf8               Ljavax/swing/table/DefaultTableCellRenderer;
  #518 = Utf8               topPanel
  #519 = Utf8               Ljavax/swing/JPanel;
  #520 = Utf8               label
  #521 = Utf8               Ljavax/swing/JLabel;
  #522 = Utf8               filterField
  #523 = Utf8               Ljavax/swing/JTextField;
  #524 = Utf8               helpButton
  #525 = Utf8               Ljavax/swing/JButton;
  #526 = Utf8               mainPanel
  #527 = Class              #528          // java/awt/event/ActionEvent
  #528 = Utf8               java/awt/event/ActionEvent
  #529 = Class              #530          // javax/swing/table/DefaultTableCellRenderer
  #530 = Utf8               javax/swing/table/DefaultTableCellRenderer
  #531 = Utf8               lambda$new$5
  #532 = Utf8               (Ljavax/swing/JFrame;Ljava/awt/event/ActionEvent;)V
  #533 = Utf8               e2
  #534 = Utf8               message
  #535 = Utf8               lambda$new$2
  #536 = Utf8               Lext/mods/commons/gui/defence;
  #537 = Utf8               lambda$new$3
  #538 = Utf8               lambda$new$0
  #539 = Utf8               Lext/mods/commons/gui/damage;
  #540 = Utf8               lambda$new$1
  #541 = Utf8               <clinit>
  #542 = Utf8               SourceFile
  #543 = Utf8               InterfaceBalance.java
  #544 = Utf8               NestMembers
  #545 = Utf8               BootstrapMethods
  #546 = MethodType         #507          //  (Ljava/awt/event/ActionEvent;)V
  #547 = MethodHandle       5:#548        // REF_invokeVirtual ext/mods/commons/gui/InterfaceBalance.lambda$new$0:(Ljava/awt/event/ActionEvent;)V
  #548 = Methodref          #64.#549      // ext/mods/commons/gui/InterfaceBalance.lambda$new$0:(Ljava/awt/event/ActionEvent;)V
  #549 = NameAndType        #538:#507     // lambda$new$0:(Ljava/awt/event/ActionEvent;)V
  #550 = MethodHandle       5:#551        // REF_invokeVirtual ext/mods/commons/gui/InterfaceBalance.lambda$new$2:(Ljava/awt/event/ActionEvent;)V
  #551 = Methodref          #64.#552      // ext/mods/commons/gui/InterfaceBalance.lambda$new$2:(Ljava/awt/event/ActionEvent;)V
  #552 = NameAndType        #535:#507     // lambda$new$2:(Ljava/awt/event/ActionEvent;)V
  #553 = MethodHandle       5:#554        // REF_invokeVirtual ext/mods/commons/gui/InterfaceBalance.lambda$new$4:(Ljava/awt/event/ActionEvent;)V
  #554 = Methodref          #64.#555      // ext/mods/commons/gui/InterfaceBalance.lambda$new$4:(Ljava/awt/event/ActionEvent;)V
  #555 = NameAndType        #506:#507     // lambda$new$4:(Ljava/awt/event/ActionEvent;)V
  #556 = MethodHandle       5:#557        // REF_invokeVirtual ext/mods/commons/gui/InterfaceBalance.lambda$new$6:(Ljava/lang/String;Ljava/awt/event/ActionEvent;)V
  #557 = Methodref          #64.#558      // ext/mods/commons/gui/InterfaceBalance.lambda$new$6:(Ljava/lang/String;Ljava/awt/event/ActionEvent;)V
  #558 = NameAndType        #502:#503     // lambda$new$6:(Ljava/lang/String;Ljava/awt/event/ActionEvent;)V
  #559 = String             #560          // ..\u0001images\u000116x16.png
  #560 = Utf8               ..\u0001images\u000116x16.png
  #561 = String             #562          // ..\u0001images\u000132x32.png
  #562 = Utf8               ..\u0001images\u000132x32.png
  #563 = MethodType         #6            //  ()V
  #564 = MethodHandle       5:#565        // REF_invokeVirtual ext/mods/commons/gui/InterfaceBalance.lambda$updateTextArea$0:(Ljava/lang/String;)V
  #565 = Methodref          #64.#566      // ext/mods/commons/gui/InterfaceBalance.lambda$updateTextArea$0:(Ljava/lang/String;)V
  #566 = NameAndType        #501:#127     // lambda$updateTextArea$0:(Ljava/lang/String;)V
  #567 = MethodHandle       6:#568        // REF_invokeStatic ext/mods/commons/gui/InterfaceBalance.lambda$new$5:(Ljavax/swing/JFrame;Ljava/awt/event/ActionEvent;)V
  #568 = Methodref          #64.#569      // ext/mods/commons/gui/InterfaceBalance.lambda$new$5:(Ljavax/swing/JFrame;Ljava/awt/event/ActionEvent;)V
  #569 = NameAndType        #531:#532     // lambda$new$5:(Ljavax/swing/JFrame;Ljava/awt/event/ActionEvent;)V
  #570 = MethodHandle       6:#571        // REF_invokeStatic ext/mods/commons/gui/InterfaceBalance.lambda$new$3:(Ljavax/swing/JFrame;Ljava/awt/event/ActionEvent;)V
  #571 = Methodref          #64.#572      // ext/mods/commons/gui/InterfaceBalance.lambda$new$3:(Ljavax/swing/JFrame;Ljava/awt/event/ActionEvent;)V
  #572 = NameAndType        #537:#532     // lambda$new$3:(Ljavax/swing/JFrame;Ljava/awt/event/ActionEvent;)V
  #573 = MethodHandle       6:#574        // REF_invokeStatic ext/mods/commons/gui/InterfaceBalance.lambda$new$1:(Ljavax/swing/JFrame;Ljava/awt/event/ActionEvent;)V
  #574 = Methodref          #64.#575      // ext/mods/commons/gui/InterfaceBalance.lambda$new$1:(Ljavax/swing/JFrame;Ljava/awt/event/ActionEvent;)V
  #575 = NameAndType        #540:#532     // lambda$new$1:(Ljavax/swing/JFrame;Ljava/awt/event/ActionEvent;)V
  #576 = MethodHandle       6:#577        // REF_invokeStatic java/lang/invoke/LambdaMetafactory.metafactory:(Ljava/lang/invoke/MethodHandles$Lookup;Ljava/lang/String;Ljava/lang/invoke/MethodType;Ljava/lang/invoke/MethodType;Ljava/lang/invoke/MethodHandle;Ljava/lang/invoke/MethodType;)Ljava/lang/invoke/CallSite;
  #577 = Methodref          #578.#579     // java/lang/invoke/LambdaMetafactory.metafactory:(Ljava/lang/invoke/MethodHandles$Lookup;Ljava/lang/String;Ljava/lang/invoke/MethodType;Ljava/lang/invoke/MethodType;Ljava/lang/invoke/MethodHandle;Ljava/lang/invoke/MethodType;)Ljava/lang/invoke/CallSite;
  #578 = Class              #580          // java/lang/invoke/LambdaMetafactory
  #579 = NameAndType        #581:#582     // metafactory:(Ljava/lang/invoke/MethodHandles$Lookup;Ljava/lang/String;Ljava/lang/invoke/MethodType;Ljava/lang/invoke/MethodType;Ljava/lang/invoke/MethodHandle;Ljava/lang/invoke/MethodType;)Ljava/lang/invoke/CallSite;
  #580 = Utf8               java/lang/invoke/LambdaMetafactory
  #581 = Utf8               metafactory
  #582 = Utf8               (Ljava/lang/invoke/MethodHandles$Lookup;Ljava/lang/String;Ljava/lang/invoke/MethodType;Ljava/lang/invoke/MethodType;Ljava/lang/invoke/MethodHandle;Ljava/lang/invoke/MethodType;)Ljava/lang/invoke/CallSite;
  #583 = MethodHandle       6:#584        // REF_invokeStatic java/lang/invoke/StringConcatFactory.makeConcatWithConstants:(Ljava/lang/invoke/MethodHandles$Lookup;Ljava/lang/String;Ljava/lang/invoke/MethodType;Ljava/lang/String;[Ljava/lang/Object;)Ljava/lang/invoke/CallSite;
  #584 = Methodref          #585.#586     // java/lang/invoke/StringConcatFactory.makeConcatWithConstants:(Ljava/lang/invoke/MethodHandles$Lookup;Ljava/lang/String;Ljava/lang/invoke/MethodType;Ljava/lang/String;[Ljava/lang/Object;)Ljava/lang/invoke/CallSite;
  #585 = Class              #587          // java/lang/invoke/StringConcatFactory
  #586 = NameAndType        #188:#588     // makeConcatWithConstants:(Ljava/lang/invoke/MethodHandles$Lookup;Ljava/lang/String;Ljava/lang/invoke/MethodType;Ljava/lang/String;[Ljava/lang/Object;)Ljava/lang/invoke/CallSite;
  #587 = Utf8               java/lang/invoke/StringConcatFactory
  #588 = Utf8               (Ljava/lang/invoke/MethodHandles$Lookup;Ljava/lang/String;Ljava/lang/invoke/MethodType;Ljava/lang/String;[Ljava/lang/Object;)Ljava/lang/invoke/CallSite;
  #589 = Utf8               InnerClasses
  #590 = Class              #591          // java/lang/invoke/MethodHandles$Lookup
  #591 = Utf8               java/lang/invoke/MethodHandles$Lookup
  #592 = Class              #593          // java/lang/invoke/MethodHandles
  #593 = Utf8               java/lang/invoke/MethodHandles
  #594 = Utf8               Lookup
{
  javax.swing.JTextArea txtrConsole;
    descriptor: Ljavax/swing/JTextArea;
    flags: (0x0000)

  static final java.lang.String[] shutdownOptions;
    descriptor: [Ljava/lang/String;
    flags: (0x0018) ACC_STATIC, ACC_FINAL

  public ext.mods.commons.gui.InterfaceBalance();
    descriptor: ()V
    flags: (0x0001) ACC_PUBLIC
    Code:
      stack=6, locals=13, args_size=1
         0: aload_0
         1: invokespecial #1                  // Method java/lang/Object."<init>":()V
         4: ldc           #7                  // String control
         6: new           #9                  // class java/awt/Color
         9: dup
        10: bipush        40
        12: bipush        40
        14: bipush        40
        16: invokespecial #11                 // Method java/awt/Color."<init>":(III)V
        19: invokestatic  #14                 // Method javax/swing/UIManager.put:(Ljava/lang/Object;Ljava/lang/Object;)Ljava/lang/Object;
        22: pop
        23: ldc           #20                 // String info
        25: new           #9                  // class java/awt/Color
        28: dup
        29: bipush        60
        31: bipush        63
        33: bipush        65
        35: invokespecial #11                 // Method java/awt/Color."<init>":(III)V
        38: invokestatic  #14                 // Method javax/swing/UIManager.put:(Ljava/lang/Object;Ljava/lang/Object;)Ljava/lang/Object;
        41: pop
        42: ldc           #22                 // String nimbusBase
        44: new           #9                  // class java/awt/Color
        47: dup
        48: bipush        30
        50: bipush        30
        52: bipush        30
        54: invokespecial #11                 // Method java/awt/Color."<init>":(III)V
        57: invokestatic  #14                 // Method javax/swing/UIManager.put:(Ljava/lang/Object;Ljava/lang/Object;)Ljava/lang/Object;
        60: pop
        61: ldc           #24                 // String nimbusBlueGrey
        63: new           #9                  // class java/awt/Color
        66: dup
        67: bipush        70
        69: bipush        73
        71: bipush        75
        73: invokespecial #11                 // Method java/awt/Color."<init>":(III)V
        76: invokestatic  #14                 // Method javax/swing/UIManager.put:(Ljava/lang/Object;Ljava/lang/Object;)Ljava/lang/Object;
        79: pop
        80: ldc           #26                 // String nimbusLightBackground
        82: new           #9                  // class java/awt/Color
        85: dup
        86: bipush        30
        88: bipush        30
        90: bipush        30
        92: invokespecial #11                 // Method java/awt/Color."<init>":(III)V
        95: invokestatic  #14                 // Method javax/swing/UIManager.put:(Ljava/lang/Object;Ljava/lang/Object;)Ljava/lang/Object;
        98: pop
        99: ldc           #28                 // String text
       101: new           #9                  // class java/awt/Color
       104: dup
       105: sipush        220
       108: sipush        220
       111: sipush        220
       114: invokespecial #11                 // Method java/awt/Color."<init>":(III)V
       117: invokestatic  #14                 // Method javax/swing/UIManager.put:(Ljava/lang/Object;Ljava/lang/Object;)Ljava/lang/Object;
       120: pop
       121: ldc           #30                 // String nimbusSelectionBackground
       123: new           #9                  // class java/awt/Color
       126: dup
       127: bipush        60
       129: bipush        120
       131: sipush        200
       134: invokespecial #11                 // Method java/awt/Color."<init>":(III)V
       137: invokestatic  #14                 // Method javax/swing/UIManager.put:(Ljava/lang/Object;Ljava/lang/Object;)Ljava/lang/Object;
       140: pop
       141: ldc           #32                 // String nimbusSelectedText
       143: new           #9                  // class java/awt/Color
       146: dup
       147: sipush        255
       150: sipush        255
       153: sipush        255
       156: invokespecial #11                 // Method java/awt/Color."<init>":(III)V
       159: invokestatic  #14                 // Method javax/swing/UIManager.put:(Ljava/lang/Object;Ljava/lang/Object;)Ljava/lang/Object;
       162: pop
       163: ldc           #34                 // String nimbusFocus
       165: new           #9                  // class java/awt/Color
       168: dup
       169: bipush        100
       171: sipush        150
       174: sipush        255
       177: invokespecial #11                 // Method java/awt/Color."<init>":(III)V
       180: invokestatic  #14                 // Method javax/swing/UIManager.put:(Ljava/lang/Object;Ljava/lang/Object;)Ljava/lang/Object;
       183: pop
       184: ldc           #36                 // String nimbusDisabledText
       186: new           #9                  // class java/awt/Color
       189: dup
       190: bipush        100
       192: bipush        100
       194: bipush        100
       196: invokespecial #11                 // Method java/awt/Color."<init>":(III)V
       199: invokestatic  #14                 // Method javax/swing/UIManager.put:(Ljava/lang/Object;Ljava/lang/Object;)Ljava/lang/Object;
       202: pop
       203: ldc           #38                 // String nimbusRed
       205: new           #9                  // class java/awt/Color
       208: dup
       209: sipush        150
       212: bipush        60
       214: bipush        60
       216: invokespecial #11                 // Method java/awt/Color."<init>":(III)V
       219: invokestatic  #14                 // Method javax/swing/UIManager.put:(Ljava/lang/Object;Ljava/lang/Object;)Ljava/lang/Object;
       222: pop
       223: ldc           #40                 // String nimbusOrange
       225: new           #9                  // class java/awt/Color
       228: dup
       229: sipush        200
       232: bipush        120
       234: bipush        60
       236: invokespecial #11                 // Method java/awt/Color."<init>":(III)V
       239: invokestatic  #14                 // Method javax/swing/UIManager.put:(Ljava/lang/Object;Ljava/lang/Object;)Ljava/lang/Object;
       242: pop
       243: ldc           #42                 // String nimbusGreen
       245: new           #9                  // class java/awt/Color
       248: dup
       249: bipush        100
       251: sipush        160
       254: bipush        100
       256: invokespecial #11                 // Method java/awt/Color."<init>":(III)V
       259: invokestatic  #14                 // Method javax/swing/UIManager.put:(Ljava/lang/Object;Ljava/lang/Object;)Ljava/lang/Object;
       262: pop
       263: ldc           #44                 // String nimbusAlertYellow
       265: new           #9                  // class java/awt/Color
       268: dup
       269: sipush        255
       272: sipush        210
       275: bipush        60
       277: invokespecial #11                 // Method java/awt/Color."<init>":(III)V
       280: invokestatic  #14                 // Method javax/swing/UIManager.put:(Ljava/lang/Object;Ljava/lang/Object;)Ljava/lang/Object;
       283: pop
       284: ldc           #46                 // String nimbusInfoBlue
       286: new           #9                  // class java/awt/Color
       289: dup
       290: bipush        80
       292: sipush        140
       295: sipush        255
       298: invokespecial #11                 // Method java/awt/Color."<init>":(III)V
       301: invokestatic  #14                 // Method javax/swing/UIManager.put:(Ljava/lang/Object;Ljava/lang/Object;)Ljava/lang/Object;
       304: pop
       305: new           #48                 // class javax/swing/plaf/nimbus/NimbusLookAndFeel
       308: dup
       309: invokespecial #50                 // Method javax/swing/plaf/nimbus/NimbusLookAndFeel."<init>":()V
       312: invokestatic  #51                 // Method javax/swing/UIManager.setLookAndFeel:(Ljavax/swing/LookAndFeel;)V
       315: goto          323
       318: astore_1
       319: aload_1
       320: invokevirtual #57                 // Method java/lang/Exception.printStackTrace:()V
       323: aload_0
       324: new           #60                 // class javax/swing/JTextArea
       327: dup
       328: invokespecial #62                 // Method javax/swing/JTextArea."<init>":()V
       331: putfield      #63                 // Field txtrConsole:Ljavax/swing/JTextArea;
       334: aload_0
       335: getfield      #63                 // Field txtrConsole:Ljavax/swing/JTextArea;
       338: iconst_0
       339: invokevirtual #69                 // Method javax/swing/JTextArea.setEditable:(Z)V
       342: aload_0
       343: getfield      #63                 // Field txtrConsole:Ljavax/swing/JTextArea;
       346: iconst_1
       347: invokevirtual #73                 // Method javax/swing/JTextArea.setLineWrap:(Z)V
       350: aload_0
       351: getfield      #63                 // Field txtrConsole:Ljavax/swing/JTextArea;
       354: iconst_1
       355: invokevirtual #76                 // Method javax/swing/JTextArea.setWrapStyleWord:(Z)V
       358: aload_0
       359: getfield      #63                 // Field txtrConsole:Ljavax/swing/JTextArea;
       362: getstatic     #79                 // Field javax/swing/DropMode.INSERT:Ljavax/swing/DropMode;
       365: invokevirtual #85                 // Method javax/swing/JTextArea.setDropMode:(Ljavax/swing/DropMode;)V
       368: aload_0
       369: getfield      #63                 // Field txtrConsole:Ljavax/swing/JTextArea;
       372: new           #89                 // class java/awt/Font
       375: dup
       376: ldc           #91                 // String Monospaced
       378: iconst_0
       379: bipush        12
       381: invokespecial #93                 // Method java/awt/Font."<init>":(Ljava/lang/String;II)V
       384: invokevirtual #96                 // Method javax/swing/JTextArea.setFont:(Ljava/awt/Font;)V
       387: aload_0
       388: getfield      #63                 // Field txtrConsole:Ljavax/swing/JTextArea;
       391: invokevirtual #100                // Method javax/swing/JTextArea.getDocument:()Ljavax/swing/text/Document;
       394: new           #104                // class ext/mods/commons/gui/InterfaceLimit
       397: dup
       398: sipush        500
       401: invokespecial #106                // Method ext/mods/commons/gui/InterfaceLimit."<init>":(I)V
       404: invokeinterface #109,  2          // InterfaceMethod javax/swing/text/Document.addDocumentListener:(Ljavax/swing/event/DocumentListener;)V
       409: new           #115                // class javax/swing/JMenuBar
       412: dup
       413: invokespecial #117                // Method javax/swing/JMenuBar."<init>":()V
       416: astore_1
       417: aload_1
       418: new           #89                 // class java/awt/Font
       421: dup
       422: ldc           #118                // String Segoe UI
       424: iconst_0
       425: bipush        12
       427: invokespecial #93                 // Method java/awt/Font."<init>":(Ljava/lang/String;II)V
       430: invokevirtual #120                // Method javax/swing/JMenuBar.setFont:(Ljava/awt/Font;)V
       433: new           #121                // class javax/swing/JMenu
       436: dup
       437: ldc           #123                // String Option
       439: invokespecial #125                // Method javax/swing/JMenu."<init>":(Ljava/lang/String;)V
       442: astore_2
       443: aload_2
       444: new           #89                 // class java/awt/Font
       447: dup
       448: ldc           #118                // String Segoe UI
       450: iconst_0
       451: bipush        12
       453: invokespecial #93                 // Method java/awt/Font."<init>":(Ljava/lang/String;II)V
       456: invokevirtual #128                // Method javax/swing/JMenu.setFont:(Ljava/awt/Font;)V
       459: aload_1
       460: aload_2
       461: invokevirtual #129                // Method javax/swing/JMenuBar.add:(Ljavax/swing/JMenu;)Ljavax/swing/JMenu;
       464: pop
       465: new           #133                // class javax/swing/JMenuItem
       468: dup
       469: ldc           #135                // String Damage
       471: invokespecial #137                // Method javax/swing/JMenuItem."<init>":(Ljava/lang/String;)V
       474: astore_3
       475: aload_3
       476: aload_0
       477: invokedynamic #138,  0            // InvokeDynamic #0:actionPerformed:(Lext/mods/commons/gui/InterfaceBalance;)Ljava/awt/event/ActionListener;
       482: invokevirtual #142                // Method javax/swing/JMenuItem.addActionListener:(Ljava/awt/event/ActionListener;)V
       485: aload_2
       486: aload_3
       487: invokevirtual #146                // Method javax/swing/JMenu.add:(Ljavax/swing/JMenuItem;)Ljavax/swing/JMenuItem;
       490: pop
       491: new           #133                // class javax/swing/JMenuItem
       494: dup
       495: ldc           #149                // String Defence
       497: invokespecial #137                // Method javax/swing/JMenuItem."<init>":(Ljava/lang/String;)V
       500: astore        4
       502: aload         4
       504: aload_0
       505: invokedynamic #151,  0            // InvokeDynamic #1:actionPerformed:(Lext/mods/commons/gui/InterfaceBalance;)Ljava/awt/event/ActionListener;
       510: invokevirtual #142                // Method javax/swing/JMenuItem.addActionListener:(Ljava/awt/event/ActionListener;)V
       513: aload_2
       514: aload         4
       516: invokevirtual #146                // Method javax/swing/JMenu.add:(Ljavax/swing/JMenuItem;)Ljavax/swing/JMenuItem;
       519: pop
       520: new           #133                // class javax/swing/JMenuItem
       523: dup
       524: ldc           #152                // String Vulnerability
       526: invokespecial #137                // Method javax/swing/JMenuItem."<init>":(Ljava/lang/String;)V
       529: astore        5
       531: aload         5
       533: aload_0
       534: invokedynamic #154,  0            // InvokeDynamic #2:actionPerformed:(Lext/mods/commons/gui/InterfaceBalance;)Ljava/awt/event/ActionListener;
       539: invokevirtual #142                // Method javax/swing/JMenuItem.addActionListener:(Ljava/awt/event/ActionListener;)V
       542: aload_2
       543: aload         5
       545: invokevirtual #146                // Method javax/swing/JMenu.add:(Ljavax/swing/JMenuItem;)Ljavax/swing/JMenuItem;
       548: pop
       549: new           #121                // class javax/swing/JMenu
       552: dup
       553: ldc           #155                // String Font
       555: invokespecial #125                // Method javax/swing/JMenu."<init>":(Ljava/lang/String;)V
       558: astore        6
       560: aload         6
       562: new           #89                 // class java/awt/Font
       565: dup
       566: ldc           #118                // String Segoe UI
       568: iconst_0
       569: bipush        12
       571: invokespecial #93                 // Method java/awt/Font."<init>":(Ljava/lang/String;II)V
       574: invokevirtual #128                // Method javax/swing/JMenu.setFont:(Ljava/awt/Font;)V
       577: aload_1
       578: aload         6
       580: invokevirtual #129                // Method javax/swing/JMenuBar.add:(Ljavax/swing/JMenu;)Ljavax/swing/JMenu;
       583: pop
       584: bipush        6
       586: anewarray     #157                // class java/lang/String
       589: dup
       590: iconst_0
       591: ldc           #159                // String 10
       593: aastore
       594: dup
       595: iconst_1
       596: ldc           #161                // String 13
       598: aastore
       599: dup
       600: iconst_2
       601: ldc           #163                // String 16
       603: aastore
       604: dup
       605: iconst_3
       606: ldc           #165                // String 21
       608: aastore
       609: dup
       610: iconst_4
       611: ldc           #167                // String 27
       613: aastore
       614: dup
       615: iconst_5
       616: ldc           #169                // String 33
       618: aastore
       619: astore        7
       621: aload         7
       623: astore        8
       625: aload         8
       627: arraylength
       628: istore        9
       630: iconst_0
       631: istore        10
       633: iload         10
       635: iload         9
       637: if_icmpge     702
       640: aload         8
       642: iload         10
       644: aaload
       645: astore        11
       647: new           #133                // class javax/swing/JMenuItem
       650: dup
       651: aload         11
       653: invokespecial #137                // Method javax/swing/JMenuItem."<init>":(Ljava/lang/String;)V
       656: astore        12
       658: aload         12
       660: new           #89                 // class java/awt/Font
       663: dup
       664: ldc           #118                // String Segoe UI
       666: iconst_0
       667: bipush        12
       669: invokespecial #93                 // Method java/awt/Font."<init>":(Ljava/lang/String;II)V
       672: invokevirtual #171                // Method javax/swing/JMenuItem.setFont:(Ljava/awt/Font;)V
       675: aload         12
       677: aload_0
       678: aload         11
       680: invokedynamic #172,  0            // InvokeDynamic #3:actionPerformed:(Lext/mods/commons/gui/InterfaceBalance;Ljava/lang/String;)Ljava/awt/event/ActionListener;
       685: invokevirtual #142                // Method javax/swing/JMenuItem.addActionListener:(Ljava/awt/event/ActionListener;)V
       688: aload         6
       690: aload         12
       692: invokevirtual #146                // Method javax/swing/JMenu.add:(Ljavax/swing/JMenuItem;)Ljavax/swing/JMenuItem;
       695: pop
       696: iinc          10, 1
       699: goto          633
       702: new           #175                // class java/util/ArrayList
       705: dup
       706: invokespecial #177                // Method java/util/ArrayList."<init>":()V
       709: astore        8
       711: aload         8
       713: new           #178                // class javax/swing/ImageIcon
       716: dup
       717: getstatic     #180                // Field java/io/File.separator:Ljava/lang/String;
       720: getstatic     #180                // Field java/io/File.separator:Ljava/lang/String;
       723: invokedynamic #186,  0            // InvokeDynamic #4:makeConcatWithConstants:(Ljava/lang/String;Ljava/lang/String;)Ljava/lang/String;
       728: invokespecial #190                // Method javax/swing/ImageIcon."<init>":(Ljava/lang/String;)V
       731: invokevirtual #191                // Method javax/swing/ImageIcon.getImage:()Ljava/awt/Image;
       734: invokeinterface #195,  2          // InterfaceMethod java/util/List.add:(Ljava/lang/Object;)Z
       739: pop
       740: aload         8
       742: new           #178                // class javax/swing/ImageIcon
       745: dup
       746: getstatic     #180                // Field java/io/File.separator:Ljava/lang/String;
       749: getstatic     #180                // Field java/io/File.separator:Ljava/lang/String;
       752: invokedynamic #200,  0            // InvokeDynamic #5:makeConcatWithConstants:(Ljava/lang/String;Ljava/lang/String;)Ljava/lang/String;
       757: invokespecial #190                // Method javax/swing/ImageIcon."<init>":(Ljava/lang/String;)V
       760: invokevirtual #191                // Method javax/swing/ImageIcon.getImage:()Ljava/awt/Image;
       763: invokeinterface #195,  2          // InterfaceMethod java/util/List.add:(Ljava/lang/Object;)Z
       768: pop
       769: new           #201                // class javax/swing/JScrollPane
       772: dup
       773: aload_0
       774: getfield      #63                 // Field txtrConsole:Ljavax/swing/JTextArea;
       777: invokespecial #203                // Method javax/swing/JScrollPane."<init>":(Ljava/awt/Component;)V
       780: astore        9
       782: new           #206                // class javax/swing/JFrame
       785: dup
       786: ldc           #208                // String Balance
       788: invokespecial #210                // Method javax/swing/JFrame."<init>":(Ljava/lang/String;)V
       791: astore        10
       793: aload         10
       795: iconst_0
       796: invokevirtual #213                // Method javax/swing/JFrame.setDefaultCloseOperation:(I)V
       799: aload         10
       801: new           #216                // class ext/mods/commons/gui/InterfaceBalance$7
       804: dup
       805: aload_0
       806: aload         10
       808: invokespecial #218                // Method ext/mods/commons/gui/InterfaceBalance$7."<init>":(Lext/mods/commons/gui/InterfaceBalance;Ljavax/swing/JFrame;)V
       811: invokevirtual #221                // Method javax/swing/JFrame.addWindowListener:(Ljava/awt/event/WindowListener;)V
       814: aload         10
       816: new           #225                // class ext/mods/commons/gui/InterfaceBalance$8
       819: dup
       820: aload_0
       821: aload         9
       823: aload         10
       825: invokespecial #227                // Method ext/mods/commons/gui/InterfaceBalance$8."<init>":(Lext/mods/commons/gui/InterfaceBalance;Ljavax/swing/JScrollPane;Ljavax/swing/JFrame;)V
       828: invokevirtual #230                // Method javax/swing/JFrame.addComponentListener:(Ljava/awt/event/ComponentListener;)V
       831: aload         10
       833: aload_1
       834: invokevirtual #234                // Method javax/swing/JFrame.setJMenuBar:(Ljavax/swing/JMenuBar;)V
       837: aload         10
       839: aload         8
       841: invokevirtual #238                // Method javax/swing/JFrame.setIconImages:(Ljava/util/List;)V
       844: aload         10
       846: invokevirtual #242                // Method javax/swing/JFrame.getContentPane:()Ljava/awt/Container;
       849: new           #246                // class java/awt/BorderLayout
       852: dup
       853: invokespecial #248                // Method java/awt/BorderLayout."<init>":()V
       856: invokevirtual #249                // Method java/awt/Container.setLayout:(Ljava/awt/LayoutManager;)V
       859: aload         10
       861: aload         9
       863: ldc           #255                // String Center
       865: invokevirtual #257                // Method javax/swing/JFrame.add:(Ljava/awt/Component;Ljava/lang/Object;)V
       868: aload         10
       870: invokevirtual #242                // Method javax/swing/JFrame.getContentPane:()Ljava/awt/Container;
       873: new           #260                // class java/awt/Dimension
       876: dup
       877: sipush        400
       880: sipush        360
       883: invokespecial #262                // Method java/awt/Dimension."<init>":(II)V
       886: invokevirtual #265                // Method java/awt/Container.setPreferredSize:(Ljava/awt/Dimension;)V
       889: aload         10
       891: invokevirtual #269                // Method javax/swing/JFrame.pack:()V
       894: aload         10
       896: aconst_null
       897: invokevirtual #272                // Method javax/swing/JFrame.setLocationRelativeTo:(Ljava/awt/Component;)V
       900: aload_0
       901: invokevirtual #275                // Method redirectSystemStreams:()V
       904: aload         10
       906: iconst_1
       907: invokevirtual #278                // Method javax/swing/JFrame.setVisible:(Z)V
       910: aload         10
       912: invokevirtual #281                // Method javax/swing/JFrame.toFront:()V
       915: aload         10
       917: iconst_1
       918: invokevirtual #286                // Method javax/swing/JFrame.setState:(I)V
       921: aload         10
       923: iconst_0
       924: invokevirtual #286                // Method javax/swing/JFrame.setState:(I)V
       927: return
      Exception table:
         from    to  target type
             4   315   318   Class java/lang/Exception
      LineNumberTable:
        line 70: 0
        line 73: 4
        line 74: 23
        line 75: 42
        line 76: 61
        line 77: 80
        line 78: 99
        line 80: 121
        line 81: 141
        line 82: 163
        line 84: 184
        line 86: 203
        line 87: 223
        line 88: 243
        line 89: 263
        line 90: 284
        line 92: 305
        line 97: 315
        line 94: 318
        line 96: 319
        line 99: 323
        line 100: 334
        line 101: 342
        line 102: 350
        line 103: 358
        line 104: 368
        line 105: 387
        line 107: 409
        line 108: 417
        line 110: 433
        line 111: 443
        line 112: 459
        line 114: 465
        line 115: 475
        line 215: 485
        line 218: 491
        line 219: 502
        line 318: 513
        line 321: 520
        line 322: 531
        line 423: 542
        line 425: 549
        line 426: 560
        line 427: 577
        line 429: 584
        line 438: 621
        line 440: 647
        line 441: 658
        line 442: 675
        line 443: 688
        line 438: 696
        line 446: 702
        line 447: 711
        line 448: 740
        line 451: 769
        line 453: 782
        line 454: 793
        line 455: 799
        line 467: 814
        line 476: 831
        line 477: 837
        line 478: 844
        line 479: 859
        line 480: 868
        line 481: 889
        line 482: 894
        line 484: 900
        line 486: 904
        line 487: 910
        line 488: 915
        line 489: 921
        line 491: 927
      LocalVariableTable:
        Start  Length  Slot  Name   Signature
          319       4     1     e   Ljava/lang/Exception;
          658      38    12 mntmFont   Ljavax/swing/JMenuItem;
          647      49    11  font   Ljava/lang/String;
            0     928     0  this   Lext/mods/commons/gui/InterfaceBalance;
          417     511     1 menuBar   Ljavax/swing/JMenuBar;
          443     485     2 mnBalance   Ljavax/swing/JMenu;
          475     453     3 viewModifiers   Ljavax/swing/JMenuItem;
          502     426     4 viewDefence   Ljavax/swing/JMenuItem;
          531     397     5 viewvulnerability   Ljavax/swing/JMenuItem;
          560     368     6 mnFont   Ljavax/swing/JMenu;
          621     307     7 fonts   [Ljava/lang/String;
          711     217     8 icons   Ljava/util/List;
          782     146     9 scrollPanel   Ljavax/swing/JScrollPane;
          793     135    10 frame   Ljavax/swing/JFrame;
      LocalVariableTypeTable:
        Start  Length  Slot  Name   Signature
          711     217     8 icons   Ljava/util/List<Ljava/awt/Image;>;
      StackMapTable: number_of_entries = 4
        frame_type = 255 /* full_frame */
          offset_delta = 318
          locals = [ class ext/mods/commons/gui/InterfaceBalance ]
          stack = [ class java/lang/Exception ]
        frame_type = 4 /* same */
        frame_type = 255 /* full_frame */
          offset_delta = 309
          locals = [ class ext/mods/commons/gui/InterfaceBalance, class javax/swing/JMenuBar, class javax/swing/JMenu, class javax/swing/JMenuItem, class javax/swing/JMenuItem, class javax/swing/JMenuItem, class javax/swing/JMenu, class "[Ljava/lang/String;", class "[Ljava/lang/String;", int, int ]
          stack = []
        frame_type = 248 /* chop */
          offset_delta = 68

  void updateTextArea(java.lang.String);
    descriptor: (Ljava/lang/String;)V
    flags: (0x0000)
    Code:
      stack=2, locals=2, args_size=2
         0: aload_0
         1: aload_1
         2: invokedynamic #308,  0            // InvokeDynamic #6:run:(Lext/mods/commons/gui/InterfaceBalance;Ljava/lang/String;)Ljava/lang/Runnable;
         7: invokestatic  #312                // Method javax/swing/SwingUtilities.invokeLater:(Ljava/lang/Runnable;)V
        10: return
      LineNumberTable:
        line 522: 0
        line 527: 10
      LocalVariableTable:
        Start  Length  Slot  Name   Signature
            0      11     0  this   Lext/mods/commons/gui/InterfaceBalance;
            0      11     1  text   Ljava/lang/String;

  static {};
    descriptor: ()V
    flags: (0x0008) ACC_STATIC
    Code:
      stack=4, locals=0, args_size=0
         0: iconst_2
         1: anewarray     #157                // class java/lang/String
         4: dup
         5: iconst_0
         6: ldc_w         #461                // String Shutdown
         9: aastore
        10: dup
        11: iconst_1
        12: ldc_w         #463                // String Cancel
        15: aastore
        16: putstatic     #465                // Field shutdownOptions:[Ljava/lang/String;
        19: return
      LineNumberTable:
        line 63: 0
}
SourceFile: "InterfaceBalance.java"
NestMembers:
  ext/mods/commons/gui/InterfaceBalance$9
  ext/mods/commons/gui/InterfaceBalance$8
  ext/mods/commons/gui/InterfaceBalance$7
  ext/mods/commons/gui/InterfaceBalance$6
  ext/mods/commons/gui/InterfaceBalance$5
  ext/mods/commons/gui/InterfaceBalance$4
  ext/mods/commons/gui/InterfaceBalance$3
  ext/mods/commons/gui/InterfaceBalance$2
  ext/mods/commons/gui/InterfaceBalance$1
BootstrapMethods:
  0: #576 REF_invokeStatic java/lang/invoke/LambdaMetafactory.metafactory:(Ljava/lang/invoke/MethodHandles$Lookup;Ljava/lang/String;Ljava/lang/invoke/MethodType;Ljava/lang/invoke/MethodType;Ljava/lang/invoke/MethodHandle;Ljava/lang/invoke/MethodType;)Ljava/lang/invoke/CallSite;
    Method arguments:
      #546 (Ljava/awt/event/ActionEvent;)V
      #547 REF_invokeVirtual ext/mods/commons/gui/InterfaceBalance.lambda$new$0:(Ljava/awt/event/ActionEvent;)V
      #546 (Ljava/awt/event/ActionEvent;)V
  1: #576 REF_invokeStatic java/lang/invoke/LambdaMetafactory.metafactory:(Ljava/lang/invoke/MethodHandles$Lookup;Ljava/lang/String;Ljava/lang/invoke/MethodType;Ljava/lang/invoke/MethodType;Ljava/lang/invoke/MethodHandle;Ljava/lang/invoke/MethodType;)Ljava/lang/invoke/CallSite;
    Method arguments:
      #546 (Ljava/awt/event/ActionEvent;)V
      #550 REF_invokeVirtual ext/mods/commons/gui/InterfaceBalance.lambda$new$2:(Ljava/awt/event/ActionEvent;)V
      #546 (Ljava/awt/event/ActionEvent;)V
  2: #576 REF_invokeStatic java/lang/invoke/LambdaMetafactory.metafactory:(Ljava/lang/invoke/MethodHandles$Lookup;Ljava/lang/String;Ljava/lang/invoke/MethodType;Ljava/lang/invoke/MethodType;Ljava/lang/invoke/MethodHandle;Ljava/lang/invoke/MethodType;)Ljava/lang/invoke/CallSite;
    Method arguments:
      #546 (Ljava/awt/event/ActionEvent;)V
      #553 REF_invokeVirtual ext/mods/commons/gui/InterfaceBalance.lambda$new$4:(Ljava/awt/event/ActionEvent;)V
      #546 (Ljava/awt/event/ActionEvent;)V
  3: #576 REF_invokeStatic java/lang/invoke/LambdaMetafactory.metafactory:(Ljava/lang/invoke/MethodHandles$Lookup;Ljava/lang/String;Ljava/lang/invoke/MethodType;Ljava/lang/invoke/MethodType;Ljava/lang/invoke/MethodHandle;Ljava/lang/invoke/MethodType;)Ljava/lang/invoke/CallSite;
    Method arguments:
      #546 (Ljava/awt/event/ActionEvent;)V
      #556 REF_invokeVirtual ext/mods/commons/gui/InterfaceBalance.lambda$new$6:(Ljava/lang/String;Ljava/awt/event/ActionEvent;)V
      #546 (Ljava/awt/event/ActionEvent;)V
  4: #583 REF_invokeStatic java/lang/invoke/StringConcatFactory.makeConcatWithConstants:(Ljava/lang/invoke/MethodHandles$Lookup;Ljava/lang/String;Ljava/lang/invoke/MethodType;Ljava/lang/String;[Ljava/lang/Object;)Ljava/lang/invoke/CallSite;
    Method arguments:
      #559 ..\u0001images\u000116x16.png
  5: #583 REF_invokeStatic java/lang/invoke/StringConcatFactory.makeConcatWithConstants:(Ljava/lang/invoke/MethodHandles$Lookup;Ljava/lang/String;Ljava/lang/invoke/MethodType;Ljava/lang/String;[Ljava/lang/Object;)Ljava/lang/invoke/CallSite;
    Method arguments:
      #561 ..\u0001images\u000132x32.png
  6: #576 REF_invokeStatic java/lang/invoke/LambdaMetafactory.metafactory:(Ljava/lang/invoke/MethodHandles$Lookup;Ljava/lang/String;Ljava/lang/invoke/MethodType;Ljava/lang/invoke/MethodType;Ljava/lang/invoke/MethodHandle;Ljava/lang/invoke/MethodType;)Ljava/lang/invoke/CallSite;
    Method arguments:
      #563 ()V
      #564 REF_invokeVirtual ext/mods/commons/gui/InterfaceBalance.lambda$updateTextArea$0:(Ljava/lang/String;)V
      #563 ()V
  7: #576 REF_invokeStatic java/lang/invoke/LambdaMetafactory.metafactory:(Ljava/lang/invoke/MethodHandles$Lookup;Ljava/lang/String;Ljava/lang/invoke/MethodType;Ljava/lang/invoke/MethodType;Ljava/lang/invoke/MethodHandle;Ljava/lang/invoke/MethodType;)Ljava/lang/invoke/CallSite;
    Method arguments:
      #546 (Ljava/awt/event/ActionEvent;)V
      #567 REF_invokeStatic ext/mods/commons/gui/InterfaceBalance.lambda$new$5:(Ljavax/swing/JFrame;Ljava/awt/event/ActionEvent;)V
      #546 (Ljava/awt/event/ActionEvent;)V
  8: #576 REF_invokeStatic java/lang/invoke/LambdaMetafactory.metafactory:(Ljava/lang/invoke/MethodHandles$Lookup;Ljava/lang/String;Ljava/lang/invoke/MethodType;Ljava/lang/invoke/MethodType;Ljava/lang/invoke/MethodHandle;Ljava/lang/invoke/MethodType;)Ljava/lang/invoke/CallSite;
    Method arguments:
      #546 (Ljava/awt/event/ActionEvent;)V
      #570 REF_invokeStatic ext/mods/commons/gui/InterfaceBalance.lambda$new$3:(Ljavax/swing/JFrame;Ljava/awt/event/ActionEvent;)V
      #546 (Ljava/awt/event/ActionEvent;)V
  9: #576 REF_invokeStatic java/lang/invoke/LambdaMetafactory.metafactory:(Ljava/lang/invoke/MethodHandles$Lookup;Ljava/lang/String;Ljava/lang/invoke/MethodType;Ljava/lang/invoke/MethodType;Ljava/lang/invoke/MethodHandle;Ljava/lang/invoke/MethodType;)Ljava/lang/invoke/CallSite;
    Method arguments:
      #546 (Ljava/awt/event/ActionEvent;)V
      #573 REF_invokeStatic ext/mods/commons/gui/InterfaceBalance.lambda$new$1:(Ljavax/swing/JFrame;Ljava/awt/event/ActionEvent;)V
      #546 (Ljava/awt/event/ActionEvent;)V
InnerClasses:
  #216;                                   // class ext/mods/commons/gui/InterfaceBalance$7
  #225;                                   // class ext/mods/commons/gui/InterfaceBalance$8
  #289;                                   // class ext/mods/commons/gui/InterfaceBalance$9
  #348;                                   // class ext/mods/commons/gui/InterfaceBalance$5
  #383;                                   // class ext/mods/commons/gui/InterfaceBalance$6
  #426;                                   // class ext/mods/commons/gui/InterfaceBalance$3
  #431;                                   // class ext/mods/commons/gui/InterfaceBalance$4
  #446;                                   // class ext/mods/commons/gui/InterfaceBalance$1
  #449;                                   // class ext/mods/commons/gui/InterfaceBalance$2
  public static final #594= #590 of #592; // Lookup=class java/lang/invoke/MethodHandles$Lookup of class java/lang/invoke/MethodHandles
