// Bytecode for: ext.mods.commons.gui.ThemeManager
// File: ext\mods\commons\gui\ThemeManager.class

Classfile /c:/Users/User/Desktop/BrProject/bin/main/ext/mods/commons/gui/ThemeManager.class
  Last modified 9 de jul de 2026; size 2967 bytes
  MD5 checksum b199c00c72f6719eb0006e97d6db97dc
  Compiled from "ThemeManager.java"
public class ext.mods.commons.gui.ThemeManager
  minor version: 0
  major version: 69
  flags: (0x0021) ACC_PUBLIC, ACC_SUPER
  this_class: #26                         // ext/mods/commons/gui/ThemeManager
  super_class: #2                         // java/lang/Object
  interfaces: 0, fields: 8, methods: 4, attributes: 1
Constant pool:
    #1 = Methodref          #2.#3         // java/lang/Object."<init>":()V
    #2 = Class              #4            // java/lang/Object
    #3 = NameAndType        #5:#6         // "<init>":()V
    #4 = Utf8               java/lang/Object
    #5 = Utf8               <init>
    #6 = Utf8               ()V
    #7 = String             #8            // true
    #8 = Utf8               true
    #9 = String             #10           // brproject.safe.graphics
   #10 = Utf8               brproject.safe.graphics
   #11 = Methodref          #12.#13       // java/lang/System.getProperty:(Ljava/lang/String;)Ljava/lang/String;
   #12 = Class              #14           // java/lang/System
   #13 = NameAndType        #15:#16       // getProperty:(Ljava/lang/String;)Ljava/lang/String;
   #14 = Utf8               java/lang/System
   #15 = Utf8               getProperty
   #16 = Utf8               (Ljava/lang/String;)Ljava/lang/String;
   #17 = Methodref          #18.#19       // java/lang/String.equalsIgnoreCase:(Ljava/lang/String;)Z
   #18 = Class              #20           // java/lang/String
   #19 = NameAndType        #21:#22       // equalsIgnoreCase:(Ljava/lang/String;)Z
   #20 = Utf8               java/lang/String
   #21 = Utf8               equalsIgnoreCase
   #22 = Utf8               (Ljava/lang/String;)Z
   #23 = String             #24           // control
   #24 = Utf8               control
   #25 = Fieldref           #26.#27       // ext/mods/commons/gui/ThemeManager.COMPONENT_BACKGROUND:Ljava/awt/Color;
   #26 = Class              #28           // ext/mods/commons/gui/ThemeManager
   #27 = NameAndType        #29:#30       // COMPONENT_BACKGROUND:Ljava/awt/Color;
   #28 = Utf8               ext/mods/commons/gui/ThemeManager
   #29 = Utf8               COMPONENT_BACKGROUND
   #30 = Utf8               Ljava/awt/Color;
   #31 = Methodref          #32.#33       // javax/swing/UIManager.put:(Ljava/lang/Object;Ljava/lang/Object;)Ljava/lang/Object;
   #32 = Class              #34           // javax/swing/UIManager
   #33 = NameAndType        #35:#36       // put:(Ljava/lang/Object;Ljava/lang/Object;)Ljava/lang/Object;
   #34 = Utf8               javax/swing/UIManager
   #35 = Utf8               put
   #36 = Utf8               (Ljava/lang/Object;Ljava/lang/Object;)Ljava/lang/Object;
   #37 = String             #38           // info
   #38 = Utf8               info
   #39 = Fieldref           #26.#40       // ext/mods/commons/gui/ThemeManager.BORDER_COLOR:Ljava/awt/Color;
   #40 = NameAndType        #41:#30       // BORDER_COLOR:Ljava/awt/Color;
   #41 = Utf8               BORDER_COLOR
   #42 = String             #43           // nimbusBase
   #43 = Utf8               nimbusBase
   #44 = Fieldref           #26.#45       // ext/mods/commons/gui/ThemeManager.BASE_PURPLE:Ljava/awt/Color;
   #45 = NameAndType        #46:#30       // BASE_PURPLE:Ljava/awt/Color;
   #46 = Utf8               BASE_PURPLE
   #47 = String             #48           // nimbusLightBackground
   #48 = Utf8               nimbusLightBackground
   #49 = Fieldref           #26.#50       // ext/mods/commons/gui/ThemeManager.VERY_DARK_BACKGROUND:Ljava/awt/Color;
   #50 = NameAndType        #51:#30       // VERY_DARK_BACKGROUND:Ljava/awt/Color;
   #51 = Utf8               VERY_DARK_BACKGROUND
   #52 = String             #53           // text
   #53 = Utf8               text
   #54 = Fieldref           #26.#55       // ext/mods/commons/gui/ThemeManager.TEXT_COLOR:Ljava/awt/Color;
   #55 = NameAndType        #56:#30       // TEXT_COLOR:Ljava/awt/Color;
   #56 = Utf8               TEXT_COLOR
   #57 = String             #58           // Panel.background
   #58 = Utf8               Panel.background
   #59 = String             #60           // TextArea.background
   #60 = Utf8               TextArea.background
   #61 = String             #62           // TextField.background
   #62 = Utf8               TextField.background
   #63 = String             #64           // List.background
   #64 = Utf8               List.background
   #65 = String             #66           // Table.background
   #66 = Utf8               Table.background
   #67 = String             #68           // ScrollPane.background
   #68 = Utf8               ScrollPane.background
   #69 = String             #70           // Viewport.background
   #70 = Utf8               Viewport.background
   #71 = String             #72           // nimbusBlueGrey
   #72 = Utf8               nimbusBlueGrey
   #73 = String             #74           // nimbusSelectedText
   #74 = Utf8               nimbusSelectedText
   #75 = Fieldref           #26.#76       // ext/mods/commons/gui/ThemeManager.TEXT_SELECTED:Ljava/awt/Color;
   #76 = NameAndType        #77:#30       // TEXT_SELECTED:Ljava/awt/Color;
   #77 = Utf8               TEXT_SELECTED
   #78 = String             #79           // nimbusSelectionBackground
   #79 = Utf8               nimbusSelectionBackground
   #80 = String             #81           // nimbusFocus
   #81 = Utf8               nimbusFocus
   #82 = String             #83           // MenuBar.background
   #83 = Utf8               MenuBar.background
   #84 = String             #85           // MenuBar.border
   #85 = Utf8               MenuBar.border
   #86 = Methodref          #87.#88       // javax/swing/BorderFactory.createMatteBorder:(IIIILjava/awt/Color;)Ljavax/swing/border/MatteBorder;
   #87 = Class              #89           // javax/swing/BorderFactory
   #88 = NameAndType        #90:#91       // createMatteBorder:(IIIILjava/awt/Color;)Ljavax/swing/border/MatteBorder;
   #89 = Utf8               javax/swing/BorderFactory
   #90 = Utf8               createMatteBorder
   #91 = Utf8               (IIIILjava/awt/Color;)Ljavax/swing/border/MatteBorder;
   #92 = String             #93           // Menu.foreground
   #93 = Utf8               Menu.foreground
   #94 = String             #95           // Menu.background
   #95 = Utf8               Menu.background
   #96 = String             #97           // Menu.selectionBackground
   #97 = Utf8               Menu.selectionBackground
   #98 = String             #99           // Menu.selectionForeground
   #99 = Utf8               Menu.selectionForeground
  #100 = String             #101          // MenuItem.background
  #101 = Utf8               MenuItem.background
  #102 = String             #103          // MenuItem.foreground
  #103 = Utf8               MenuItem.foreground
  #104 = String             #105          // MenuItem.selectionBackground
  #105 = Utf8               MenuItem.selectionBackground
  #106 = String             #107          // MenuItem.selectionForeground
  #107 = Utf8               MenuItem.selectionForeground
  #108 = String             #109          // PopupMenu.background
  #109 = Utf8               PopupMenu.background
  #110 = Fieldref           #26.#111      // ext/mods/commons/gui/ThemeManager.MENU_POPUP_BACKGROUND:Ljava/awt/Color;
  #111 = NameAndType        #112:#30      // MENU_POPUP_BACKGROUND:Ljava/awt/Color;
  #112 = Utf8               MENU_POPUP_BACKGROUND
  #113 = String             #114          // PopupMenu.border
  #114 = Utf8               PopupMenu.border
  #115 = Methodref          #87.#116      // javax/swing/BorderFactory.createLineBorder:(Ljava/awt/Color;)Ljavax/swing/border/Border;
  #116 = NameAndType        #117:#118     // createLineBorder:(Ljava/awt/Color;)Ljavax/swing/border/Border;
  #117 = Utf8               createLineBorder
  #118 = Utf8               (Ljava/awt/Color;)Ljavax/swing/border/Border;
  #119 = Class              #120          // javax/swing/plaf/nimbus/NimbusLookAndFeel
  #120 = Utf8               javax/swing/plaf/nimbus/NimbusLookAndFeel
  #121 = Methodref          #119.#3       // javax/swing/plaf/nimbus/NimbusLookAndFeel."<init>":()V
  #122 = Methodref          #32.#123      // javax/swing/UIManager.setLookAndFeel:(Ljavax/swing/LookAndFeel;)V
  #123 = NameAndType        #124:#125     // setLookAndFeel:(Ljavax/swing/LookAndFeel;)V
  #124 = Utf8               setLookAndFeel
  #125 = Utf8               (Ljavax/swing/LookAndFeel;)V
  #126 = Class              #127          // java/lang/Exception
  #127 = Utf8               java/lang/Exception
  #128 = Fieldref           #12.#129      // java/lang/System.err:Ljava/io/PrintStream;
  #129 = NameAndType        #130:#131     // err:Ljava/io/PrintStream;
  #130 = Utf8               err
  #131 = Utf8               Ljava/io/PrintStream;
  #132 = String             #133          // Erro ao aplicar o tema:
  #133 = Utf8               Erro ao aplicar o tema:
  #134 = Methodref          #135.#136     // java/io/PrintStream.println:(Ljava/lang/String;)V
  #135 = Class              #137          // java/io/PrintStream
  #136 = NameAndType        #138:#139     // println:(Ljava/lang/String;)V
  #137 = Utf8               java/io/PrintStream
  #138 = Utf8               println
  #139 = Utf8               (Ljava/lang/String;)V
  #140 = Methodref          #126.#141     // java/lang/Exception.printStackTrace:()V
  #141 = NameAndType        #142:#6       // printStackTrace:()V
  #142 = Utf8               printStackTrace
  #143 = Class              #144          // java/awt/Color
  #144 = Utf8               java/awt/Color
  #145 = Methodref          #143.#146     // java/awt/Color."<init>":(III)V
  #146 = NameAndType        #5:#147       // "<init>":(III)V
  #147 = Utf8               (III)V
  #148 = Fieldref           #143.#149     // java/awt/Color.BLACK:Ljava/awt/Color;
  #149 = NameAndType        #150:#30      // BLACK:Ljava/awt/Color;
  #150 = Utf8               BLACK
  #151 = Fieldref           #26.#152      // ext/mods/commons/gui/ThemeManager.SOFT_PURPLE_SELECTION:Ljava/awt/Color;
  #152 = NameAndType        #153:#30      // SOFT_PURPLE_SELECTION:Ljava/awt/Color;
  #153 = Utf8               SOFT_PURPLE_SELECTION
  #154 = Utf8               Code
  #155 = Utf8               LineNumberTable
  #156 = Utf8               LocalVariableTable
  #157 = Utf8               this
  #158 = Utf8               Lext/mods/commons/gui/ThemeManager;
  #159 = Utf8               isSafeGraphics
  #160 = Utf8               ()Z
  #161 = Utf8               applyTheme
  #162 = Utf8               e
  #163 = Utf8               Ljava/lang/Exception;
  #164 = Utf8               StackMapTable
  #165 = Utf8               <clinit>
  #166 = Utf8               SourceFile
  #167 = Utf8               ThemeManager.java
{
  public static final java.awt.Color VERY_DARK_BACKGROUND;
    descriptor: Ljava/awt/Color;
    flags: (0x0019) ACC_PUBLIC, ACC_STATIC, ACC_FINAL

  public static final java.awt.Color COMPONENT_BACKGROUND;
    descriptor: Ljava/awt/Color;
    flags: (0x0019) ACC_PUBLIC, ACC_STATIC, ACC_FINAL

  public static final java.awt.Color MENU_POPUP_BACKGROUND;
    descriptor: Ljava/awt/Color;
    flags: (0x0019) ACC_PUBLIC, ACC_STATIC, ACC_FINAL

  public static final java.awt.Color BORDER_COLOR;
    descriptor: Ljava/awt/Color;
    flags: (0x0019) ACC_PUBLIC, ACC_STATIC, ACC_FINAL

  public static final java.awt.Color BASE_PURPLE;
    descriptor: Ljava/awt/Color;
    flags: (0x0019) ACC_PUBLIC, ACC_STATIC, ACC_FINAL

  public static final java.awt.Color SOFT_PURPLE_SELECTION;
    descriptor: Ljava/awt/Color;
    flags: (0x0019) ACC_PUBLIC, ACC_STATIC, ACC_FINAL

  public static final java.awt.Color TEXT_COLOR;
    descriptor: Ljava/awt/Color;
    flags: (0x0019) ACC_PUBLIC, ACC_STATIC, ACC_FINAL

  public static final java.awt.Color TEXT_SELECTED;
    descriptor: Ljava/awt/Color;
    flags: (0x0019) ACC_PUBLIC, ACC_STATIC, ACC_FINAL

  public ext.mods.commons.gui.ThemeManager();
    descriptor: ()V
    flags: (0x0001) ACC_PUBLIC
    Code:
      stack=1, locals=1, args_size=1
         0: aload_0
         1: invokespecial #1                  // Method java/lang/Object."<init>":()V
         4: return
      LineNumberTable:
        line 25: 0
      LocalVariableTable:
        Start  Length  Slot  Name   Signature
            0       5     0  this   Lext/mods/commons/gui/ThemeManager;

  public static boolean isSafeGraphics();
    descriptor: ()Z
    flags: (0x0009) ACC_PUBLIC, ACC_STATIC
    Code:
      stack=2, locals=0, args_size=0
         0: ldc           #7                  // String true
         2: ldc           #9                  // String brproject.safe.graphics
         4: invokestatic  #11                 // Method java/lang/System.getProperty:(Ljava/lang/String;)Ljava/lang/String;
         7: invokevirtual #17                 // Method java/lang/String.equalsIgnoreCase:(Ljava/lang/String;)Z
        10: ireturn
      LineNumberTable:
        line 29: 0

  public static void applyTheme();
    descriptor: ()V
    flags: (0x0009) ACC_PUBLIC, ACC_STATIC
    Code:
      stack=6, locals=1, args_size=0
         0: ldc           #23                 // String control
         2: getstatic     #25                 // Field COMPONENT_BACKGROUND:Ljava/awt/Color;
         5: invokestatic  #31                 // Method javax/swing/UIManager.put:(Ljava/lang/Object;Ljava/lang/Object;)Ljava/lang/Object;
         8: pop
         9: ldc           #37                 // String info
        11: getstatic     #39                 // Field BORDER_COLOR:Ljava/awt/Color;
        14: invokestatic  #31                 // Method javax/swing/UIManager.put:(Ljava/lang/Object;Ljava/lang/Object;)Ljava/lang/Object;
        17: pop
        18: ldc           #42                 // String nimbusBase
        20: getstatic     #44                 // Field BASE_PURPLE:Ljava/awt/Color;
        23: invokestatic  #31                 // Method javax/swing/UIManager.put:(Ljava/lang/Object;Ljava/lang/Object;)Ljava/lang/Object;
        26: pop
        27: ldc           #47                 // String nimbusLightBackground
        29: getstatic     #49                 // Field VERY_DARK_BACKGROUND:Ljava/awt/Color;
        32: invokestatic  #31                 // Method javax/swing/UIManager.put:(Ljava/lang/Object;Ljava/lang/Object;)Ljava/lang/Object;
        35: pop
        36: ldc           #52                 // String text
        38: getstatic     #54                 // Field TEXT_COLOR:Ljava/awt/Color;
        41: invokestatic  #31                 // Method javax/swing/UIManager.put:(Ljava/lang/Object;Ljava/lang/Object;)Ljava/lang/Object;
        44: pop
        45: ldc           #57                 // String Panel.background
        47: getstatic     #25                 // Field COMPONENT_BACKGROUND:Ljava/awt/Color;
        50: invokestatic  #31                 // Method javax/swing/UIManager.put:(Ljava/lang/Object;Ljava/lang/Object;)Ljava/lang/Object;
        53: pop
        54: ldc           #59                 // String TextArea.background
        56: getstatic     #25                 // Field COMPONENT_BACKGROUND:Ljava/awt/Color;
        59: invokestatic  #31                 // Method javax/swing/UIManager.put:(Ljava/lang/Object;Ljava/lang/Object;)Ljava/lang/Object;
        62: pop
        63: ldc           #61                 // String TextField.background
        65: getstatic     #25                 // Field COMPONENT_BACKGROUND:Ljava/awt/Color;
        68: invokestatic  #31                 // Method javax/swing/UIManager.put:(Ljava/lang/Object;Ljava/lang/Object;)Ljava/lang/Object;
        71: pop
        72: ldc           #63                 // String List.background
        74: getstatic     #25                 // Field COMPONENT_BACKGROUND:Ljava/awt/Color;
        77: invokestatic  #31                 // Method javax/swing/UIManager.put:(Ljava/lang/Object;Ljava/lang/Object;)Ljava/lang/Object;
        80: pop
        81: ldc           #65                 // String Table.background
        83: getstatic     #25                 // Field COMPONENT_BACKGROUND:Ljava/awt/Color;
        86: invokestatic  #31                 // Method javax/swing/UIManager.put:(Ljava/lang/Object;Ljava/lang/Object;)Ljava/lang/Object;
        89: pop
        90: ldc           #67                 // String ScrollPane.background
        92: getstatic     #49                 // Field VERY_DARK_BACKGROUND:Ljava/awt/Color;
        95: invokestatic  #31                 // Method javax/swing/UIManager.put:(Ljava/lang/Object;Ljava/lang/Object;)Ljava/lang/Object;
        98: pop
        99: ldc           #69                 // String Viewport.background
       101: getstatic     #25                 // Field COMPONENT_BACKGROUND:Ljava/awt/Color;
       104: invokestatic  #31                 // Method javax/swing/UIManager.put:(Ljava/lang/Object;Ljava/lang/Object;)Ljava/lang/Object;
       107: pop
       108: ldc           #71                 // String nimbusBlueGrey
       110: getstatic     #25                 // Field COMPONENT_BACKGROUND:Ljava/awt/Color;
       113: invokestatic  #31                 // Method javax/swing/UIManager.put:(Ljava/lang/Object;Ljava/lang/Object;)Ljava/lang/Object;
       116: pop
       117: ldc           #73                 // String nimbusSelectedText
       119: getstatic     #75                 // Field TEXT_SELECTED:Ljava/awt/Color;
       122: invokestatic  #31                 // Method javax/swing/UIManager.put:(Ljava/lang/Object;Ljava/lang/Object;)Ljava/lang/Object;
       125: pop
       126: ldc           #78                 // String nimbusSelectionBackground
       128: getstatic     #44                 // Field BASE_PURPLE:Ljava/awt/Color;
       131: invokestatic  #31                 // Method javax/swing/UIManager.put:(Ljava/lang/Object;Ljava/lang/Object;)Ljava/lang/Object;
       134: pop
       135: ldc           #80                 // String nimbusFocus
       137: getstatic     #44                 // Field BASE_PURPLE:Ljava/awt/Color;
       140: invokestatic  #31                 // Method javax/swing/UIManager.put:(Ljava/lang/Object;Ljava/lang/Object;)Ljava/lang/Object;
       143: pop
       144: ldc           #82                 // String MenuBar.background
       146: getstatic     #49                 // Field VERY_DARK_BACKGROUND:Ljava/awt/Color;
       149: invokestatic  #31                 // Method javax/swing/UIManager.put:(Ljava/lang/Object;Ljava/lang/Object;)Ljava/lang/Object;
       152: pop
       153: ldc           #84                 // String MenuBar.border
       155: iconst_0
       156: iconst_0
       157: iconst_1
       158: iconst_0
       159: getstatic     #39                 // Field BORDER_COLOR:Ljava/awt/Color;
       162: invokestatic  #86                 // Method javax/swing/BorderFactory.createMatteBorder:(IIIILjava/awt/Color;)Ljavax/swing/border/MatteBorder;
       165: invokestatic  #31                 // Method javax/swing/UIManager.put:(Ljava/lang/Object;Ljava/lang/Object;)Ljava/lang/Object;
       168: pop
       169: ldc           #92                 // String Menu.foreground
       171: getstatic     #54                 // Field TEXT_COLOR:Ljava/awt/Color;
       174: invokestatic  #31                 // Method javax/swing/UIManager.put:(Ljava/lang/Object;Ljava/lang/Object;)Ljava/lang/Object;
       177: pop
       178: ldc           #94                 // String Menu.background
       180: getstatic     #49                 // Field VERY_DARK_BACKGROUND:Ljava/awt/Color;
       183: invokestatic  #31                 // Method javax/swing/UIManager.put:(Ljava/lang/Object;Ljava/lang/Object;)Ljava/lang/Object;
       186: pop
       187: ldc           #96                 // String Menu.selectionBackground
       189: getstatic     #44                 // Field BASE_PURPLE:Ljava/awt/Color;
       192: invokestatic  #31                 // Method javax/swing/UIManager.put:(Ljava/lang/Object;Ljava/lang/Object;)Ljava/lang/Object;
       195: pop
       196: ldc           #98                 // String Menu.selectionForeground
       198: getstatic     #75                 // Field TEXT_SELECTED:Ljava/awt/Color;
       201: invokestatic  #31                 // Method javax/swing/UIManager.put:(Ljava/lang/Object;Ljava/lang/Object;)Ljava/lang/Object;
       204: pop
       205: ldc           #100                // String MenuItem.background
       207: getstatic     #49                 // Field VERY_DARK_BACKGROUND:Ljava/awt/Color;
       210: invokestatic  #31                 // Method javax/swing/UIManager.put:(Ljava/lang/Object;Ljava/lang/Object;)Ljava/lang/Object;
       213: pop
       214: ldc           #102                // String MenuItem.foreground
       216: getstatic     #54                 // Field TEXT_COLOR:Ljava/awt/Color;
       219: invokestatic  #31                 // Method javax/swing/UIManager.put:(Ljava/lang/Object;Ljava/lang/Object;)Ljava/lang/Object;
       222: pop
       223: ldc           #104                // String MenuItem.selectionBackground
       225: getstatic     #44                 // Field BASE_PURPLE:Ljava/awt/Color;
       228: invokestatic  #31                 // Method javax/swing/UIManager.put:(Ljava/lang/Object;Ljava/lang/Object;)Ljava/lang/Object;
       231: pop
       232: ldc           #106                // String MenuItem.selectionForeground
       234: getstatic     #75                 // Field TEXT_SELECTED:Ljava/awt/Color;
       237: invokestatic  #31                 // Method javax/swing/UIManager.put:(Ljava/lang/Object;Ljava/lang/Object;)Ljava/lang/Object;
       240: pop
       241: ldc           #108                // String PopupMenu.background
       243: getstatic     #110                // Field MENU_POPUP_BACKGROUND:Ljava/awt/Color;
       246: invokestatic  #31                 // Method javax/swing/UIManager.put:(Ljava/lang/Object;Ljava/lang/Object;)Ljava/lang/Object;
       249: pop
       250: ldc           #113                // String PopupMenu.border
       252: getstatic     #39                 // Field BORDER_COLOR:Ljava/awt/Color;
       255: invokestatic  #115                // Method javax/swing/BorderFactory.createLineBorder:(Ljava/awt/Color;)Ljavax/swing/border/Border;
       258: invokestatic  #31                 // Method javax/swing/UIManager.put:(Ljava/lang/Object;Ljava/lang/Object;)Ljava/lang/Object;
       261: pop
       262: new           #119                // class javax/swing/plaf/nimbus/NimbusLookAndFeel
       265: dup
       266: invokespecial #121                // Method javax/swing/plaf/nimbus/NimbusLookAndFeel."<init>":()V
       269: invokestatic  #122                // Method javax/swing/UIManager.setLookAndFeel:(Ljavax/swing/LookAndFeel;)V
       272: ldc           #57                 // String Panel.background
       274: getstatic     #25                 // Field COMPONENT_BACKGROUND:Ljava/awt/Color;
       277: invokestatic  #31                 // Method javax/swing/UIManager.put:(Ljava/lang/Object;Ljava/lang/Object;)Ljava/lang/Object;
       280: pop
       281: ldc           #69                 // String Viewport.background
       283: getstatic     #25                 // Field COMPONENT_BACKGROUND:Ljava/awt/Color;
       286: invokestatic  #31                 // Method javax/swing/UIManager.put:(Ljava/lang/Object;Ljava/lang/Object;)Ljava/lang/Object;
       289: pop
       290: goto          306
       293: astore_0
       294: getstatic     #128                // Field java/lang/System.err:Ljava/io/PrintStream;
       297: ldc           #132                // String Erro ao aplicar o tema:
       299: invokevirtual #134                // Method java/io/PrintStream.println:(Ljava/lang/String;)V
       302: aload_0
       303: invokevirtual #140                // Method java/lang/Exception.printStackTrace:()V
       306: return
      Exception table:
         from    to  target type
             0   290   293   Class java/lang/Exception
      LineNumberTable:
        line 45: 0
        line 46: 9
        line 47: 18
        line 48: 27
        line 49: 36
        line 51: 45
        line 52: 54
        line 53: 63
        line 54: 72
        line 55: 81
        line 56: 90
        line 57: 99
        line 58: 108
        line 60: 117
        line 61: 126
        line 62: 135
        line 64: 144
        line 65: 153
        line 66: 169
        line 67: 178
        line 68: 187
        line 69: 196
        line 71: 205
        line 72: 214
        line 73: 223
        line 74: 232
        line 76: 241
        line 77: 250
        line 79: 262
        line 81: 272
        line 82: 281
        line 87: 290
        line 84: 293
        line 85: 294
        line 86: 302
        line 88: 306
      LocalVariableTable:
        Start  Length  Slot  Name   Signature
          294      12     0     e   Ljava/lang/Exception;
      StackMapTable: number_of_entries = 2
        frame_type = 247 /* same_locals_1_stack_item_frame_extended */
          offset_delta = 293
          stack = [ class java/lang/Exception ]
        frame_type = 12 /* same */

  static {};
    descriptor: ()V
    flags: (0x0008) ACC_STATIC
    Code:
      stack=5, locals=0, args_size=0
         0: new           #143                // class java/awt/Color
         3: dup
         4: bipush        10
         6: bipush        10
         8: bipush        15
        10: invokespecial #145                // Method java/awt/Color."<init>":(III)V
        13: putstatic     #49                 // Field VERY_DARK_BACKGROUND:Ljava/awt/Color;
        16: new           #143                // class java/awt/Color
        19: dup
        20: bipush        10
        22: bipush        10
        24: bipush        15
        26: invokespecial #145                // Method java/awt/Color."<init>":(III)V
        29: putstatic     #25                 // Field COMPONENT_BACKGROUND:Ljava/awt/Color;
        32: getstatic     #148                // Field java/awt/Color.BLACK:Ljava/awt/Color;
        35: putstatic     #110                // Field MENU_POPUP_BACKGROUND:Ljava/awt/Color;
        38: new           #143                // class java/awt/Color
        41: dup
        42: bipush        80
        44: iconst_0
        45: bipush        120
        47: invokespecial #145                // Method java/awt/Color."<init>":(III)V
        50: putstatic     #39                 // Field BORDER_COLOR:Ljava/awt/Color;
        53: new           #143                // class java/awt/Color
        56: dup
        57: bipush        90
        59: bipush        30
        61: sipush        180
        64: invokespecial #145                // Method java/awt/Color."<init>":(III)V
        67: putstatic     #44                 // Field BASE_PURPLE:Ljava/awt/Color;
        70: new           #143                // class java/awt/Color
        73: dup
        74: bipush        120
        76: bipush        45
        78: sipush        200
        81: invokespecial #145                // Method java/awt/Color."<init>":(III)V
        84: putstatic     #151                // Field SOFT_PURPLE_SELECTION:Ljava/awt/Color;
        87: new           #143                // class java/awt/Color
        90: dup
        91: sipush        220
        94: sipush        220
        97: sipush        230
       100: invokespecial #145                // Method java/awt/Color."<init>":(III)V
       103: putstatic     #54                 // Field TEXT_COLOR:Ljava/awt/Color;
       106: getstatic     #148                // Field java/awt/Color.BLACK:Ljava/awt/Color;
       109: putstatic     #75                 // Field TEXT_SELECTED:Ljava/awt/Color;
       112: return
      LineNumberTable:
        line 32: 0
        line 33: 16
        line 34: 32
        line 35: 38
        line 37: 53
        line 38: 70
        line 40: 87
        line 41: 106
}
SourceFile: "ThemeManager.java"
