// Bytecode for: ext.mods.gameserver.handler.admincommandhandlers.AdminMaintenance
// File: ext\mods\gameserver\handler\admincommandhandlers\AdminMaintenance.class

Classfile /c:/Users/User/Desktop/BrProject/bin/main/ext/mods/gameserver/handler/admincommandhandlers/AdminMaintenance.class
  Last modified 9 de jul de 2026; size 5814 bytes
  MD5 checksum 54e17a9eb8c30fe69a70b1d4098eb928
  Compiled from "AdminMaintenance.java"
public class ext.mods.gameserver.handler.admincommandhandlers.AdminMaintenance implements ext.mods.gameserver.handler.IAdminCommandHandler
  minor version: 0
  major version: 69
  flags: (0x0021) ACC_PUBLIC, ACC_SUPER
  this_class: #23                         // ext/mods/gameserver/handler/admincommandhandlers/AdminMaintenance
  super_class: #2                         // java/lang/Object
  interfaces: 1, fields: 1, methods: 5, attributes: 3
Constant pool:
    #1 = Methodref          #2.#3         // java/lang/Object."<init>":()V
    #2 = Class              #4            // java/lang/Object
    #3 = NameAndType        #5:#6         // "<init>":()V
    #4 = Utf8               java/lang/Object
    #5 = Utf8               <init>
    #6 = Utf8               ()V
    #7 = Class              #8            // java/util/StringTokenizer
    #8 = Utf8               java/util/StringTokenizer
    #9 = String             #10           //
   #10 = Utf8
   #11 = Methodref          #7.#12        // java/util/StringTokenizer."<init>":(Ljava/lang/String;Ljava/lang/String;)V
   #12 = NameAndType        #5:#13        // "<init>":(Ljava/lang/String;Ljava/lang/String;)V
   #13 = Utf8               (Ljava/lang/String;Ljava/lang/String;)V
   #14 = Methodref          #7.#15        // java/util/StringTokenizer.nextToken:()Ljava/lang/String;
   #15 = NameAndType        #16:#17       // nextToken:()Ljava/lang/String;
   #16 = Utf8               nextToken
   #17 = Utf8               ()Ljava/lang/String;
   #18 = Methodref          #7.#19        // java/util/StringTokenizer.hasMoreTokens:()Z
   #19 = NameAndType        #20:#21       // hasMoreTokens:()Z
   #20 = Utf8               hasMoreTokens
   #21 = Utf8               ()Z
   #22 = Methodref          #23.#24       // ext/mods/gameserver/handler/admincommandhandlers/AdminMaintenance.sendHtmlForm:(Lext/mods/gameserver/model/actor/Player;)V
   #23 = Class              #25           // ext/mods/gameserver/handler/admincommandhandlers/AdminMaintenance
   #24 = NameAndType        #26:#27       // sendHtmlForm:(Lext/mods/gameserver/model/actor/Player;)V
   #25 = Utf8               ext/mods/gameserver/handler/admincommandhandlers/AdminMaintenance
   #26 = Utf8               sendHtmlForm
   #27 = Utf8               (Lext/mods/gameserver/model/actor/Player;)V
   #28 = Methodref          #29.#30       // java/lang/String.hashCode:()I
   #29 = Class              #31           // java/lang/String
   #30 = NameAndType        #32:#33       // hashCode:()I
   #31 = Utf8               java/lang/String
   #32 = Utf8               hashCode
   #33 = Utf8               ()I
   #34 = String             #35           // shutdown
   #35 = Utf8               shutdown
   #36 = Methodref          #29.#37       // java/lang/String.equals:(Ljava/lang/Object;)Z
   #37 = NameAndType        #38:#39       // equals:(Ljava/lang/Object;)Z
   #38 = Utf8               equals
   #39 = Utf8               (Ljava/lang/Object;)Z
   #40 = String             #41           // restart
   #41 = Utf8               restart
   #42 = String             #43           // abort
   #43 = Utf8               abort
   #44 = String             #45           // gmonly
   #45 = Utf8               gmonly
   #46 = String             #47           // all
   #47 = Utf8               all
   #48 = String             #49           // max
   #49 = Utf8               max
   #50 = Methodref          #51.#52       // ext/mods/gameserver/Shutdown.getInstance:()Lext/mods/gameserver/Shutdown;
   #51 = Class              #53           // ext/mods/gameserver/Shutdown
   #52 = NameAndType        #54:#55       // getInstance:()Lext/mods/gameserver/Shutdown;
   #53 = Utf8               ext/mods/gameserver/Shutdown
   #54 = Utf8               getInstance
   #55 = Utf8               ()Lext/mods/gameserver/Shutdown;
   #56 = Methodref          #57.#58       // java/lang/Integer.parseInt:(Ljava/lang/String;)I
   #57 = Class              #59           // java/lang/Integer
   #58 = NameAndType        #60:#61       // parseInt:(Ljava/lang/String;)I
   #59 = Utf8               java/lang/Integer
   #60 = Utf8               parseInt
   #61 = Utf8               (Ljava/lang/String;)I
   #62 = Methodref          #51.#63       // ext/mods/gameserver/Shutdown.startShutdown:(Lext/mods/gameserver/model/actor/Player;IZ)V
   #63 = NameAndType        #64:#65       // startShutdown:(Lext/mods/gameserver/model/actor/Player;IZ)V
   #64 = Utf8               startShutdown
   #65 = Utf8               (Lext/mods/gameserver/model/actor/Player;IZ)V
   #66 = Methodref          #51.#67       // ext/mods/gameserver/Shutdown.abort:(Lext/mods/gameserver/model/actor/Player;)V
   #67 = NameAndType        #43:#27       // abort:(Lext/mods/gameserver/model/actor/Player;)V
   #68 = Methodref          #69.#70       // ext/mods/gameserver/LoginServerThread.getInstance:()Lext/mods/gameserver/LoginServerThread;
   #69 = Class              #71           // ext/mods/gameserver/LoginServerThread
   #70 = NameAndType        #54:#72       // getInstance:()Lext/mods/gameserver/LoginServerThread;
   #71 = Utf8               ext/mods/gameserver/LoginServerThread
   #72 = Utf8               ()Lext/mods/gameserver/LoginServerThread;
   #73 = Fieldref           #74.#75       // ext/mods/commons/network/ServerType.GM_ONLY:Lext/mods/commons/network/ServerType;
   #74 = Class              #76           // ext/mods/commons/network/ServerType
   #75 = NameAndType        #77:#78       // GM_ONLY:Lext/mods/commons/network/ServerType;
   #76 = Utf8               ext/mods/commons/network/ServerType
   #77 = Utf8               GM_ONLY
   #78 = Utf8               Lext/mods/commons/network/ServerType;
   #79 = Methodref          #69.#80       // ext/mods/gameserver/LoginServerThread.setServerType:(Lext/mods/commons/network/ServerType;)V
   #80 = NameAndType        #81:#82       // setServerType:(Lext/mods/commons/network/ServerType;)V
   #81 = Utf8               setServerType
   #82 = Utf8               (Lext/mods/commons/network/ServerType;)V
   #83 = Fieldref           #84.#85       // ext/mods/Config.SERVER_GMONLY:Z
   #84 = Class              #86           // ext/mods/Config
   #85 = NameAndType        #87:#88       // SERVER_GMONLY:Z
   #86 = Utf8               ext/mods/Config
   #87 = Utf8               SERVER_GMONLY
   #88 = Utf8               Z
   #89 = String             #90           // Server is now set as GMonly.
   #90 = Utf8               Server is now set as GMonly.
   #91 = Methodref          #92.#93       // ext/mods/gameserver/model/actor/Player.sendMessage:(Ljava/lang/String;)V
   #92 = Class              #94           // ext/mods/gameserver/model/actor/Player
   #93 = NameAndType        #95:#96       // sendMessage:(Ljava/lang/String;)V
   #94 = Utf8               ext/mods/gameserver/model/actor/Player
   #95 = Utf8               sendMessage
   #96 = Utf8               (Ljava/lang/String;)V
   #97 = Fieldref           #74.#98       // ext/mods/commons/network/ServerType.AUTO:Lext/mods/commons/network/ServerType;
   #98 = NameAndType        #99:#78       // AUTO:Lext/mods/commons/network/ServerType;
   #99 = Utf8               AUTO
  #100 = String             #101          // Server isn\'t set as GMonly anymore.
  #101 = Utf8               Server isn\'t set as GMonly anymore.
  #102 = Methodref          #69.#103      // ext/mods/gameserver/LoginServerThread.setMaxPlayer:(I)V
  #103 = NameAndType        #104:#105     // setMaxPlayer:(I)V
  #104 = Utf8               setMaxPlayer
  #105 = Utf8               (I)V
  #106 = InvokeDynamic      #0:#107       // #0:makeConcatWithConstants:(I)Ljava/lang/String;
  #107 = NameAndType        #108:#109     // makeConcatWithConstants:(I)Ljava/lang/String;
  #108 = Utf8               makeConcatWithConstants
  #109 = Utf8               (I)Ljava/lang/String;
  #110 = Class              #111          // java/lang/Exception
  #111 = Utf8               java/lang/Exception
  #112 = String             #113          // Usage: //server <shutdown|restart|abort|gmonly|all|max> time in seconds.
  #113 = Utf8               Usage: //server <shutdown|restart|abort|gmonly|all|max> time in seconds.
  #114 = Class              #115          // ext/mods/gameserver/network/serverpackets/NpcHtmlMessage
  #115 = Utf8               ext/mods/gameserver/network/serverpackets/NpcHtmlMessage
  #116 = Methodref          #114.#117     // ext/mods/gameserver/network/serverpackets/NpcHtmlMessage."<init>":(I)V
  #117 = NameAndType        #5:#105       // "<init>":(I)V
  #118 = Methodref          #92.#119      // ext/mods/gameserver/model/actor/Player.getLocale:()Ljava/util/Locale;
  #119 = NameAndType        #120:#121     // getLocale:()Ljava/util/Locale;
  #120 = Utf8               getLocale
  #121 = Utf8               ()Ljava/util/Locale;
  #122 = String             #123          // html/admin/maintenance.htm
  #123 = Utf8               html/admin/maintenance.htm
  #124 = Methodref          #114.#125     // ext/mods/gameserver/network/serverpackets/NpcHtmlMessage.setFile:(Ljava/util/Locale;Ljava/lang/String;)V
  #125 = NameAndType        #126:#127     // setFile:(Ljava/util/Locale;Ljava/lang/String;)V
  #126 = Utf8               setFile
  #127 = Utf8               (Ljava/util/Locale;Ljava/lang/String;)V
  #128 = String             #129          // %count%
  #129 = Utf8               %count%
  #130 = Methodref          #131.#132     // ext/mods/gameserver/model/World.getInstance:()Lext/mods/gameserver/model/World;
  #131 = Class              #133          // ext/mods/gameserver/model/World
  #132 = NameAndType        #54:#134      // getInstance:()Lext/mods/gameserver/model/World;
  #133 = Utf8               ext/mods/gameserver/model/World
  #134 = Utf8               ()Lext/mods/gameserver/model/World;
  #135 = Methodref          #131.#136     // ext/mods/gameserver/model/World.getPlayers:()Ljava/util/Collection;
  #136 = NameAndType        #137:#138     // getPlayers:()Ljava/util/Collection;
  #137 = Utf8               getPlayers
  #138 = Utf8               ()Ljava/util/Collection;
  #139 = InterfaceMethodref #140.#141     // java/util/Collection.size:()I
  #140 = Class              #142          // java/util/Collection
  #141 = NameAndType        #143:#33      // size:()I
  #142 = Utf8               java/util/Collection
  #143 = Utf8               size
  #144 = Methodref          #114.#145     // ext/mods/gameserver/network/serverpackets/NpcHtmlMessage.replace:(Ljava/lang/String;I)V
  #145 = NameAndType        #146:#147     // replace:(Ljava/lang/String;I)V
  #146 = Utf8               replace
  #147 = Utf8               (Ljava/lang/String;I)V
  #148 = String             #149          // %used%
  #149 = Utf8               %used%
  #150 = Methodref          #151.#152     // ext/mods/commons/util/SysUtil.getUsedMemory:()J
  #151 = Class              #153          // ext/mods/commons/util/SysUtil
  #152 = NameAndType        #154:#155     // getUsedMemory:()J
  #153 = Utf8               ext/mods/commons/util/SysUtil
  #154 = Utf8               getUsedMemory
  #155 = Utf8               ()J
  #156 = Methodref          #114.#157     // ext/mods/gameserver/network/serverpackets/NpcHtmlMessage.replace:(Ljava/lang/String;J)V
  #157 = NameAndType        #146:#158     // replace:(Ljava/lang/String;J)V
  #158 = Utf8               (Ljava/lang/String;J)V
  #159 = String             #160          // %server_name%
  #160 = Utf8               %server_name%
  #161 = Methodref          #69.#162      // ext/mods/gameserver/LoginServerThread.getServerName:()Ljava/lang/String;
  #162 = NameAndType        #163:#17      // getServerName:()Ljava/lang/String;
  #163 = Utf8               getServerName
  #164 = Methodref          #114.#165     // ext/mods/gameserver/network/serverpackets/NpcHtmlMessage.replace:(Ljava/lang/String;Ljava/lang/String;)V
  #165 = NameAndType        #146:#13      // replace:(Ljava/lang/String;Ljava/lang/String;)V
  #166 = String             #167          // %status%
  #167 = Utf8               %status%
  #168 = Methodref          #69.#169      // ext/mods/gameserver/LoginServerThread.getServerType:()Lext/mods/commons/network/ServerType;
  #169 = NameAndType        #170:#171     // getServerType:()Lext/mods/commons/network/ServerType;
  #170 = Utf8               getServerType
  #171 = Utf8               ()Lext/mods/commons/network/ServerType;
  #172 = Methodref          #74.#173      // ext/mods/commons/network/ServerType.getName:()Ljava/lang/String;
  #173 = NameAndType        #174:#17      // getName:()Ljava/lang/String;
  #174 = Utf8               getName
  #175 = String             #176          // %max_players%
  #176 = Utf8               %max_players%
  #177 = Methodref          #69.#178      // ext/mods/gameserver/LoginServerThread.getMaxPlayers:()I
  #178 = NameAndType        #179:#33      // getMaxPlayers:()I
  #179 = Utf8               getMaxPlayers
  #180 = String             #181          // %time%
  #181 = Utf8               %time%
  #182 = Methodref          #183.#184     // ext/mods/gameserver/taskmanager/GameTimeTaskManager.getInstance:()Lext/mods/gameserver/taskmanager/GameTimeTaskManager;
  #183 = Class              #185          // ext/mods/gameserver/taskmanager/GameTimeTaskManager
  #184 = NameAndType        #54:#186      // getInstance:()Lext/mods/gameserver/taskmanager/GameTimeTaskManager;
  #185 = Utf8               ext/mods/gameserver/taskmanager/GameTimeTaskManager
  #186 = Utf8               ()Lext/mods/gameserver/taskmanager/GameTimeTaskManager;
  #187 = Methodref          #183.#188     // ext/mods/gameserver/taskmanager/GameTimeTaskManager.getGameTimeFormated:()Ljava/lang/String;
  #188 = NameAndType        #189:#17      // getGameTimeFormated:()Ljava/lang/String;
  #189 = Utf8               getGameTimeFormated
  #190 = Methodref          #191.#192     // ext/mods/gameserver/GameServer.getInstance:()Lext/mods/gameserver/GameServer;
  #191 = Class              #193          // ext/mods/gameserver/GameServer
  #192 = NameAndType        #54:#194      // getInstance:()Lext/mods/gameserver/GameServer;
  #193 = Utf8               ext/mods/gameserver/GameServer
  #194 = Utf8               ()Lext/mods/gameserver/GameServer;
  #195 = Methodref          #191.#196     // ext/mods/gameserver/GameServer.getServerStartTime:()J
  #196 = NameAndType        #197:#155     // getServerStartTime:()J
  #197 = Utf8               getServerStartTime
  #198 = Methodref          #199.#200     // java/time/Instant.ofEpochMilli:(J)Ljava/time/Instant;
  #199 = Class              #201          // java/time/Instant
  #200 = NameAndType        #202:#203     // ofEpochMilli:(J)Ljava/time/Instant;
  #201 = Utf8               java/time/Instant
  #202 = Utf8               ofEpochMilli
  #203 = Utf8               (J)Ljava/time/Instant;
  #204 = Methodref          #199.#205     // java/time/Instant.now:()Ljava/time/Instant;
  #205 = NameAndType        #206:#207     // now:()Ljava/time/Instant;
  #206 = Utf8               now
  #207 = Utf8               ()Ljava/time/Instant;
  #208 = Methodref          #209.#210     // java/time/Duration.between:(Ljava/time/temporal/Temporal;Ljava/time/temporal/Temporal;)Ljava/time/Duration;
  #209 = Class              #211          // java/time/Duration
  #210 = NameAndType        #212:#213     // between:(Ljava/time/temporal/Temporal;Ljava/time/temporal/Temporal;)Ljava/time/Duration;
  #211 = Utf8               java/time/Duration
  #212 = Utf8               between
  #213 = Utf8               (Ljava/time/temporal/Temporal;Ljava/time/temporal/Temporal;)Ljava/time/Duration;
  #214 = String             #215          // %server_start_time%
  #215 = Utf8               %server_start_time%
  #216 = String             #217          // yyyy-MM-dd HH:mm:ss
  #217 = Utf8               yyyy-MM-dd HH:mm:ss
  #218 = Methodref          #219.#220     // java/time/format/DateTimeFormatter.ofPattern:(Ljava/lang/String;)Ljava/time/format/DateTimeFormatter;
  #219 = Class              #221          // java/time/format/DateTimeFormatter
  #220 = NameAndType        #222:#223     // ofPattern:(Ljava/lang/String;)Ljava/time/format/DateTimeFormatter;
  #221 = Utf8               java/time/format/DateTimeFormatter
  #222 = Utf8               ofPattern
  #223 = Utf8               (Ljava/lang/String;)Ljava/time/format/DateTimeFormatter;
  #224 = Methodref          #225.#226     // java/time/ZoneId.systemDefault:()Ljava/time/ZoneId;
  #225 = Class              #227          // java/time/ZoneId
  #226 = NameAndType        #228:#229     // systemDefault:()Ljava/time/ZoneId;
  #227 = Utf8               java/time/ZoneId
  #228 = Utf8               systemDefault
  #229 = Utf8               ()Ljava/time/ZoneId;
  #230 = Methodref          #219.#231     // java/time/format/DateTimeFormatter.withZone:(Ljava/time/ZoneId;)Ljava/time/format/DateTimeFormatter;
  #231 = NameAndType        #232:#233     // withZone:(Ljava/time/ZoneId;)Ljava/time/format/DateTimeFormatter;
  #232 = Utf8               withZone
  #233 = Utf8               (Ljava/time/ZoneId;)Ljava/time/format/DateTimeFormatter;
  #234 = Methodref          #219.#235     // java/time/format/DateTimeFormatter.format:(Ljava/time/temporal/TemporalAccessor;)Ljava/lang/String;
  #235 = NameAndType        #236:#237     // format:(Ljava/time/temporal/TemporalAccessor;)Ljava/lang/String;
  #236 = Utf8               format
  #237 = Utf8               (Ljava/time/temporal/TemporalAccessor;)Ljava/lang/String;
  #238 = String             #239          // %uptime%
  #239 = Utf8               %uptime%
  #240 = String             #241          // %d hours, %d minutes, %d seconds
  #241 = Utf8               %d hours, %d minutes, %d seconds
  #242 = Methodref          #209.#243     // java/time/Duration.toHours:()J
  #243 = NameAndType        #244:#155     // toHours:()J
  #244 = Utf8               toHours
  #245 = Methodref          #246.#247     // java/lang/Long.valueOf:(J)Ljava/lang/Long;
  #246 = Class              #248          // java/lang/Long
  #247 = NameAndType        #249:#250     // valueOf:(J)Ljava/lang/Long;
  #248 = Utf8               java/lang/Long
  #249 = Utf8               valueOf
  #250 = Utf8               (J)Ljava/lang/Long;
  #251 = Methodref          #209.#252     // java/time/Duration.toMinutes:()J
  #252 = NameAndType        #253:#155     // toMinutes:()J
  #253 = Utf8               toMinutes
  #254 = Long               60l
  #256 = Methodref          #209.#257     // java/time/Duration.toSeconds:()J
  #257 = NameAndType        #258:#155     // toSeconds:()J
  #258 = Utf8               toSeconds
  #259 = Methodref          #29.#260      // java/lang/String.format:(Ljava/lang/String;[Ljava/lang/Object;)Ljava/lang/String;
  #260 = NameAndType        #236:#261     // format:(Ljava/lang/String;[Ljava/lang/Object;)Ljava/lang/String;
  #261 = Utf8               (Ljava/lang/String;[Ljava/lang/Object;)Ljava/lang/String;
  #262 = Methodref          #92.#263      // ext/mods/gameserver/model/actor/Player.sendPacket:(Lext/mods/gameserver/network/serverpackets/L2GameServerPacket;)V
  #263 = NameAndType        #264:#265     // sendPacket:(Lext/mods/gameserver/network/serverpackets/L2GameServerPacket;)V
  #264 = Utf8               sendPacket
  #265 = Utf8               (Lext/mods/gameserver/network/serverpackets/L2GameServerPacket;)V
  #266 = Fieldref           #23.#267      // ext/mods/gameserver/handler/admincommandhandlers/AdminMaintenance.ADMIN_COMMANDS:[Ljava/lang/String;
  #267 = NameAndType        #268:#269     // ADMIN_COMMANDS:[Ljava/lang/String;
  #268 = Utf8               ADMIN_COMMANDS
  #269 = Utf8               [Ljava/lang/String;
  #270 = String             #271          // admin_server
  #271 = Utf8               admin_server
  #272 = Class              #273          // ext/mods/gameserver/handler/IAdminCommandHandler
  #273 = Utf8               ext/mods/gameserver/handler/IAdminCommandHandler
  #274 = Utf8               Code
  #275 = Utf8               LineNumberTable
  #276 = Utf8               LocalVariableTable
  #277 = Utf8               this
  #278 = Utf8               Lext/mods/gameserver/handler/admincommandhandlers/AdminMaintenance;
  #279 = Utf8               useAdminCommand
  #280 = Utf8               (Ljava/lang/String;Lext/mods/gameserver/model/actor/Player;)V
  #281 = Utf8               number
  #282 = Utf8               I
  #283 = Utf8               e
  #284 = Utf8               Ljava/lang/Exception;
  #285 = Utf8               command
  #286 = Utf8               Ljava/lang/String;
  #287 = Utf8               player
  #288 = Utf8               Lext/mods/gameserver/model/actor/Player;
  #289 = Utf8               st
  #290 = Utf8               Ljava/util/StringTokenizer;
  #291 = Utf8               StackMapTable
  #292 = Utf8               html
  #293 = Utf8               Lext/mods/gameserver/network/serverpackets/NpcHtmlMessage;
  #294 = Utf8               serverStartTime
  #295 = Utf8               Ljava/time/Instant;
  #296 = Utf8               uptime
  #297 = Utf8               Ljava/time/Duration;
  #298 = Utf8               getAdminCommandList
  #299 = Utf8               ()[Ljava/lang/String;
  #300 = Utf8               <clinit>
  #301 = Utf8               SourceFile
  #302 = Utf8               AdminMaintenance.java
  #303 = Utf8               BootstrapMethods
  #304 = String             #305          // Server maximum player amount is set to \u0001.
  #305 = Utf8               Server maximum player amount is set to \u0001.
  #306 = MethodHandle       6:#307        // REF_invokeStatic java/lang/invoke/StringConcatFactory.makeConcatWithConstants:(Ljava/lang/invoke/MethodHandles$Lookup;Ljava/lang/String;Ljava/lang/invoke/MethodType;Ljava/lang/String;[Ljava/lang/Object;)Ljava/lang/invoke/CallSite;
  #307 = Methodref          #308.#309     // java/lang/invoke/StringConcatFactory.makeConcatWithConstants:(Ljava/lang/invoke/MethodHandles$Lookup;Ljava/lang/String;Ljava/lang/invoke/MethodType;Ljava/lang/String;[Ljava/lang/Object;)Ljava/lang/invoke/CallSite;
  #308 = Class              #310          // java/lang/invoke/StringConcatFactory
  #309 = NameAndType        #108:#311     // makeConcatWithConstants:(Ljava/lang/invoke/MethodHandles$Lookup;Ljava/lang/String;Ljava/lang/invoke/MethodType;Ljava/lang/String;[Ljava/lang/Object;)Ljava/lang/invoke/CallSite;
  #310 = Utf8               java/lang/invoke/StringConcatFactory
  #311 = Utf8               (Ljava/lang/invoke/MethodHandles$Lookup;Ljava/lang/String;Ljava/lang/invoke/MethodType;Ljava/lang/String;[Ljava/lang/Object;)Ljava/lang/invoke/CallSite;
  #312 = Utf8               InnerClasses
  #313 = Class              #314          // java/lang/invoke/MethodHandles$Lookup
  #314 = Utf8               java/lang/invoke/MethodHandles$Lookup
  #315 = Class              #316          // java/lang/invoke/MethodHandles
  #316 = Utf8               java/lang/invoke/MethodHandles
  #317 = Utf8               Lookup
{
  public ext.mods.gameserver.handler.admincommandhandlers.AdminMaintenance();
    descriptor: ()V
    flags: (0x0001) ACC_PUBLIC
    Code:
      stack=1, locals=1, args_size=1
         0: aload_0
         1: invokespecial #1                  // Method java/lang/Object."<init>":()V
         4: return
      LineNumberTable:
        line 39: 0
      LocalVariableTable:
        Start  Length  Slot  Name   Signature
            0       5     0  this   Lext/mods/gameserver/handler/admincommandhandlers/AdminMaintenance;

  public void useAdminCommand(java.lang.String, ext.mods.gameserver.model.actor.Player);
    descriptor: (Ljava/lang/String;Lext/mods/gameserver/model/actor/Player;)V
    flags: (0x0001) ACC_PUBLIC
    Code:
      stack=4, locals=7, args_size=3
         0: new           #7                  // class java/util/StringTokenizer
         3: dup
         4: aload_1
         5: ldc           #9                  // String
         7: invokespecial #11                 // Method java/util/StringTokenizer."<init>":(Ljava/lang/String;Ljava/lang/String;)V
        10: astore_3
        11: aload_3
        12: invokevirtual #14                 // Method java/util/StringTokenizer.nextToken:()Ljava/lang/String;
        15: pop
        16: aload_3
        17: invokevirtual #18                 // Method java/util/StringTokenizer.hasMoreTokens:()Z
        20: ifne          28
        23: aload_2
        24: invokestatic  #22                 // Method sendHtmlForm:(Lext/mods/gameserver/model/actor/Player;)V
        27: return
        28: aload_3
        29: invokevirtual #14                 // Method java/util/StringTokenizer.nextToken:()Ljava/lang/String;
        32: astore        4
        34: iconst_m1
        35: istore        5
        37: aload         4
        39: invokevirtual #28                 // Method java/lang/String.hashCode:()I
        42: lookupswitch  { // 6

             -1242084974: 148

              -169343402: 100

                   96673: 164

                  107876: 180

                92611376: 132

              1097506319: 116
                 default: 193
            }
       100: aload         4
       102: ldc           #34                 // String shutdown
       104: invokevirtual #36                 // Method java/lang/String.equals:(Ljava/lang/Object;)Z
       107: ifeq          193
       110: iconst_0
       111: istore        5
       113: goto          193
       116: aload         4
       118: ldc           #40                 // String restart
       120: invokevirtual #36                 // Method java/lang/String.equals:(Ljava/lang/Object;)Z
       123: ifeq          193
       126: iconst_1
       127: istore        5
       129: goto          193
       132: aload         4
       134: ldc           #42                 // String abort
       136: invokevirtual #36                 // Method java/lang/String.equals:(Ljava/lang/Object;)Z
       139: ifeq          193
       142: iconst_2
       143: istore        5
       145: goto          193
       148: aload         4
       150: ldc           #44                 // String gmonly
       152: invokevirtual #36                 // Method java/lang/String.equals:(Ljava/lang/Object;)Z
       155: ifeq          193
       158: iconst_3
       159: istore        5
       161: goto          193
       164: aload         4
       166: ldc           #46                 // String all
       168: invokevirtual #36                 // Method java/lang/String.equals:(Ljava/lang/Object;)Z
       171: ifeq          193
       174: iconst_4
       175: istore        5
       177: goto          193
       180: aload         4
       182: ldc           #48                 // String max
       184: invokevirtual #36                 // Method java/lang/String.equals:(Ljava/lang/Object;)Z
       187: ifeq          193
       190: iconst_5
       191: istore        5
       193: iload         5
       195: tableswitch   { // 0 to 5

                       0: 232

                       1: 250

                       2: 268

                       3: 278

                       4: 300

                       5: 322
                 default: 350
            }
       232: invokestatic  #50                 // Method ext/mods/gameserver/Shutdown.getInstance:()Lext/mods/gameserver/Shutdown;
       235: aload_2
       236: aload_3
       237: invokevirtual #14                 // Method java/util/StringTokenizer.nextToken:()Ljava/lang/String;
       240: invokestatic  #56                 // Method java/lang/Integer.parseInt:(Ljava/lang/String;)I
       243: iconst_0
       244: invokevirtual #62                 // Method ext/mods/gameserver/Shutdown.startShutdown:(Lext/mods/gameserver/model/actor/Player;IZ)V
       247: goto          350
       250: invokestatic  #50                 // Method ext/mods/gameserver/Shutdown.getInstance:()Lext/mods/gameserver/Shutdown;
       253: aload_2
       254: aload_3
       255: invokevirtual #14                 // Method java/util/StringTokenizer.nextToken:()Ljava/lang/String;
       258: invokestatic  #56                 // Method java/lang/Integer.parseInt:(Ljava/lang/String;)I
       261: iconst_1
       262: invokevirtual #62                 // Method ext/mods/gameserver/Shutdown.startShutdown:(Lext/mods/gameserver/model/actor/Player;IZ)V
       265: goto          350
       268: invokestatic  #50                 // Method ext/mods/gameserver/Shutdown.getInstance:()Lext/mods/gameserver/Shutdown;
       271: aload_2
       272: invokevirtual #66                 // Method ext/mods/gameserver/Shutdown.abort:(Lext/mods/gameserver/model/actor/Player;)V
       275: goto          350
       278: invokestatic  #68                 // Method ext/mods/gameserver/LoginServerThread.getInstance:()Lext/mods/gameserver/LoginServerThread;
       281: getstatic     #73                 // Field ext/mods/commons/network/ServerType.GM_ONLY:Lext/mods/commons/network/ServerType;
       284: invokevirtual #79                 // Method ext/mods/gameserver/LoginServerThread.setServerType:(Lext/mods/commons/network/ServerType;)V
       287: iconst_1
       288: putstatic     #83                 // Field ext/mods/Config.SERVER_GMONLY:Z
       291: aload_2
       292: ldc           #89                 // String Server is now set as GMonly.
       294: invokevirtual #91                 // Method ext/mods/gameserver/model/actor/Player.sendMessage:(Ljava/lang/String;)V
       297: goto          350
       300: invokestatic  #68                 // Method ext/mods/gameserver/LoginServerThread.getInstance:()Lext/mods/gameserver/LoginServerThread;
       303: getstatic     #97                 // Field ext/mods/commons/network/ServerType.AUTO:Lext/mods/commons/network/ServerType;
       306: invokevirtual #79                 // Method ext/mods/gameserver/LoginServerThread.setServerType:(Lext/mods/commons/network/ServerType;)V
       309: iconst_0
       310: putstatic     #83                 // Field ext/mods/Config.SERVER_GMONLY:Z
       313: aload_2
       314: ldc           #100                // String Server isn\'t set as GMonly anymore.
       316: invokevirtual #91                 // Method ext/mods/gameserver/model/actor/Player.sendMessage:(Ljava/lang/String;)V
       319: goto          350
       322: aload_3
       323: invokevirtual #14                 // Method java/util/StringTokenizer.nextToken:()Ljava/lang/String;
       326: invokestatic  #56                 // Method java/lang/Integer.parseInt:(Ljava/lang/String;)I
       329: istore        6
       331: invokestatic  #68                 // Method ext/mods/gameserver/LoginServerThread.getInstance:()Lext/mods/gameserver/LoginServerThread;
       334: iload         6
       336: invokevirtual #102                // Method ext/mods/gameserver/LoginServerThread.setMaxPlayer:(I)V
       339: aload_2
       340: iload         6
       342: invokedynamic #106,  0            // InvokeDynamic #0:makeConcatWithConstants:(I)Ljava/lang/String;
       347: invokevirtual #91                 // Method ext/mods/gameserver/model/actor/Player.sendMessage:(Ljava/lang/String;)V
       350: goto          361
       353: astore        4
       355: aload_2
       356: ldc           #112                // String Usage: //server <shutdown|restart|abort|gmonly|all|max> time in seconds.
       358: invokevirtual #91                 // Method ext/mods/gameserver/model/actor/Player.sendMessage:(Ljava/lang/String;)V
       361: aload_2
       362: invokestatic  #22                 // Method sendHtmlForm:(Lext/mods/gameserver/model/actor/Player;)V
       365: return
      Exception table:
         from    to  target type
            28   350   353   Class java/lang/Exception
      LineNumberTable:
        line 49: 0
        line 50: 11
        line 52: 16
        line 54: 23
        line 55: 27
        line 60: 28
        line 63: 232
        line 64: 247
        line 67: 250
        line 68: 265
        line 71: 268
        line 72: 275
        line 75: 278
        line 76: 287
        line 78: 291
        line 79: 297
        line 82: 300
        line 83: 309
        line 85: 313
        line 86: 319
        line 89: 322
        line 91: 331
        line 92: 339
        line 99: 350
        line 96: 353
        line 98: 355
        line 100: 361
        line 101: 365
      LocalVariableTable:
        Start  Length  Slot  Name   Signature
          331      19     6 number   I
          355       6     4     e   Ljava/lang/Exception;
            0     366     0  this   Lext/mods/gameserver/handler/admincommandhandlers/AdminMaintenance;
            0     366     1 command   Ljava/lang/String;
            0     366     2 player   Lext/mods/gameserver/model/actor/Player;
           11     355     3    st   Ljava/util/StringTokenizer;
      StackMapTable: number_of_entries = 17
        frame_type = 252 /* append */
          offset_delta = 28
          locals = [ class java/util/StringTokenizer ]
        frame_type = 253 /* append */
          offset_delta = 71
          locals = [ class java/lang/String, int ]
        frame_type = 15 /* same */
        frame_type = 15 /* same */
        frame_type = 15 /* same */
        frame_type = 15 /* same */
        frame_type = 15 /* same */
        frame_type = 12 /* same */
        frame_type = 38 /* same */
        frame_type = 17 /* same */
        frame_type = 17 /* same */
        frame_type = 9 /* same */
        frame_type = 21 /* same */
        frame_type = 21 /* same */
        frame_type = 249 /* chop */
          offset_delta = 27
        frame_type = 66 /* same_locals_1_stack_item */
          stack = [ class java/lang/Exception ]
        frame_type = 7 /* same */

  public java.lang.String[] getAdminCommandList();
    descriptor: ()[Ljava/lang/String;
    flags: (0x0001) ACC_PUBLIC
    Code:
      stack=1, locals=1, args_size=1
         0: getstatic     #266                // Field ADMIN_COMMANDS:[Ljava/lang/String;
         3: areturn
      LineNumberTable:
        line 127: 0
      LocalVariableTable:
        Start  Length  Slot  Name   Signature
            0       4     0  this   Lext/mods/gameserver/handler/admincommandhandlers/AdminMaintenance;

  static {};
    descriptor: ()V
    flags: (0x0008) ACC_STATIC
    Code:
      stack=4, locals=0, args_size=0
         0: iconst_1
         1: anewarray     #29                 // class java/lang/String
         4: dup
         5: iconst_0
         6: ldc_w         #270                // String admin_server
         9: aastore
        10: putstatic     #266                // Field ADMIN_COMMANDS:[Ljava/lang/String;
        13: return
      LineNumberTable:
        line 41: 0
}
SourceFile: "AdminMaintenance.java"
BootstrapMethods:
  0: #306 REF_invokeStatic java/lang/invoke/StringConcatFactory.makeConcatWithConstants:(Ljava/lang/invoke/MethodHandles$Lookup;Ljava/lang/String;Ljava/lang/invoke/MethodType;Ljava/lang/String;[Ljava/lang/Object;)Ljava/lang/invoke/CallSite;
    Method arguments:
      #304 Server maximum player amount is set to \u0001.
InnerClasses:
  public static final #317= #313 of #315; // Lookup=class java/lang/invoke/MethodHandles$Lookup of class java/lang/invoke/MethodHandles
