// Bytecode for: ext.mods.gameserver.handler.admincommandhandlers.AdminReload
// File: ext\mods\gameserver\handler\admincommandhandlers\AdminReload.class

Classfile /c:/Users/User/Desktop/BrProject/bin/main/ext/mods/gameserver/handler/admincommandhandlers/AdminReload.class
  Last modified 9 de jul de 2026; size 9522 bytes
  MD5 checksum 825e80458e67bfab7e63fbc66a0ef10c
  Compiled from "AdminReload.java"
public class ext.mods.gameserver.handler.admincommandhandlers.AdminReload implements ext.mods.gameserver.handler.IAdminCommandHandler
  minor version: 0
  major version: 69
  flags: (0x0021) ACC_PUBLIC, ACC_SUPER
  this_class: #392                        // ext/mods/gameserver/handler/admincommandhandlers/AdminReload
  super_class: #2                         // java/lang/Object
  interfaces: 1, fields: 2, methods: 5, attributes: 1
Constant pool:
    #1 = Methodref          #2.#3         // java/lang/Object."<init>":()V
    #2 = Class              #4            // java/lang/Object
    #3 = NameAndType        #5:#6         // "<init>":()V
    #4 = Utf8               java/lang/Object
    #5 = Utf8               <init>
    #6 = Utf8               ()V
    #7 = Class              #8            // java/util/StringTokenizer
    #8 = Utf8               java/util/StringTokenizer
    #9 = Methodref          #7.#10        // java/util/StringTokenizer."<init>":(Ljava/lang/String;)V
   #10 = NameAndType        #5:#11        // "<init>":(Ljava/lang/String;)V
   #11 = Utf8               (Ljava/lang/String;)V
   #12 = Methodref          #7.#13        // java/util/StringTokenizer.nextToken:()Ljava/lang/String;
   #13 = NameAndType        #14:#15       // nextToken:()Ljava/lang/String;
   #14 = Utf8               nextToken
   #15 = Utf8               ()Ljava/lang/String;
   #16 = String             #17           // admin
   #17 = Utf8               admin
   #18 = Methodref          #19.#20       // java/lang/String.startsWith:(Ljava/lang/String;)Z
   #19 = Class              #21           // java/lang/String
   #20 = NameAndType        #22:#23       // startsWith:(Ljava/lang/String;)Z
   #21 = Utf8               java/lang/String
   #22 = Utf8               startsWith
   #23 = Utf8               (Ljava/lang/String;)Z
   #24 = Methodref          #25.#26       // ext/mods/gameserver/data/xml/AdminData.getInstance:()Lext/mods/gameserver/data/xml/AdminData;
   #25 = Class              #27           // ext/mods/gameserver/data/xml/AdminData
   #26 = NameAndType        #28:#29       // getInstance:()Lext/mods/gameserver/data/xml/AdminData;
   #27 = Utf8               ext/mods/gameserver/data/xml/AdminData
   #28 = Utf8               getInstance
   #29 = Utf8               ()Lext/mods/gameserver/data/xml/AdminData;
   #30 = Methodref          #25.#31       // ext/mods/gameserver/data/xml/AdminData.reload:()V
   #31 = NameAndType        #32:#6        // reload:()V
   #32 = Utf8               reload
   #33 = String             #34           // Admin data has been reloaded.
   #34 = Utf8               Admin data has been reloaded.
   #35 = Methodref          #36.#37       // ext/mods/gameserver/model/actor/Player.sendMessage:(Ljava/lang/String;)V
   #36 = Class              #38           // ext/mods/gameserver/model/actor/Player
   #37 = NameAndType        #39:#11       // sendMessage:(Ljava/lang/String;)V
   #38 = Utf8               ext/mods/gameserver/model/actor/Player
   #39 = Utf8               sendMessage
   #40 = String             #41           // announcement
   #41 = Utf8               announcement
   #42 = Methodref          #43.#44       // ext/mods/gameserver/data/xml/AnnouncementData.getInstance:()Lext/mods/gameserver/data/xml/AnnouncementData;
   #43 = Class              #45           // ext/mods/gameserver/data/xml/AnnouncementData
   #44 = NameAndType        #28:#46       // getInstance:()Lext/mods/gameserver/data/xml/AnnouncementData;
   #45 = Utf8               ext/mods/gameserver/data/xml/AnnouncementData
   #46 = Utf8               ()Lext/mods/gameserver/data/xml/AnnouncementData;
   #47 = Methodref          #43.#31       // ext/mods/gameserver/data/xml/AnnouncementData.reload:()V
   #48 = String             #49           // The content of announcements.xml has been reloaded.
   #49 = Utf8               The content of announcements.xml has been reloaded.
   #50 = String             #51           // auction
   #51 = Utf8               auction
   #52 = Methodref          #53.#54       // ext/mods/gameserver/custom/data/AuctionCurrencies.getInstance:()Lext/mods/gameserver/custom/data/AuctionCurrencies;
   #53 = Class              #55           // ext/mods/gameserver/custom/data/AuctionCurrencies
   #54 = NameAndType        #28:#56       // getInstance:()Lext/mods/gameserver/custom/data/AuctionCurrencies;
   #55 = Utf8               ext/mods/gameserver/custom/data/AuctionCurrencies
   #56 = Utf8               ()Lext/mods/gameserver/custom/data/AuctionCurrencies;
   #57 = Methodref          #53.#31       // ext/mods/gameserver/custom/data/AuctionCurrencies.reload:()V
   #58 = String             #59           // Auction have been reloaded.
   #59 = Utf8               Auction have been reloaded.
   #60 = String             #61           // boat
   #61 = Utf8               boat
   #62 = Methodref          #63.#64       // ext/mods/gameserver/data/xml/BoatData.getInstance:()Lext/mods/gameserver/data/xml/BoatData;
   #63 = Class              #65           // ext/mods/gameserver/data/xml/BoatData
   #64 = NameAndType        #28:#66       // getInstance:()Lext/mods/gameserver/data/xml/BoatData;
   #65 = Utf8               ext/mods/gameserver/data/xml/BoatData
   #66 = Utf8               ()Lext/mods/gameserver/data/xml/BoatData;
   #67 = Methodref          #63.#31       // ext/mods/gameserver/data/xml/BoatData.reload:()V
   #68 = String             #69           // Boat have been reloaded.
   #69 = Utf8               Boat have been reloaded.
   #70 = String             #71           // buylist
   #71 = Utf8               buylist
   #72 = Methodref          #73.#74       // ext/mods/gameserver/data/manager/BuyListManager.getInstance:()Lext/mods/gameserver/data/manager/BuyListManager;
   #73 = Class              #75           // ext/mods/gameserver/data/manager/BuyListManager
   #74 = NameAndType        #28:#76       // getInstance:()Lext/mods/gameserver/data/manager/BuyListManager;
   #75 = Utf8               ext/mods/gameserver/data/manager/BuyListManager
   #76 = Utf8               ()Lext/mods/gameserver/data/manager/BuyListManager;
   #77 = Methodref          #73.#31       // ext/mods/gameserver/data/manager/BuyListManager.reload:()V
   #78 = String             #79           // Buylists have been reloaded.
   #79 = Utf8               Buylists have been reloaded.
   #80 = String             #81           // capsule
   #81 = Utf8               capsule
   #82 = Methodref          #83.#84       // ext/mods/CapsuleBox/CapsuleBoxData.getInstance:()Lext/mods/CapsuleBox/CapsuleBoxData;
   #83 = Class              #85           // ext/mods/CapsuleBox/CapsuleBoxData
   #84 = NameAndType        #28:#86       // getInstance:()Lext/mods/CapsuleBox/CapsuleBoxData;
   #85 = Utf8               ext/mods/CapsuleBox/CapsuleBoxData
   #86 = Utf8               ()Lext/mods/CapsuleBox/CapsuleBoxData;
   #87 = Methodref          #83.#31       // ext/mods/CapsuleBox/CapsuleBoxData.reload:()V
   #88 = String             #89           // Capsule Box have been reloaded.
   #89 = Utf8               Capsule Box have been reloaded.
   #90 = String             #91           // config
   #91 = Utf8               config
   #92 = Methodref          #93.#94       // ext/mods/Config.loadGameServer:()V
   #93 = Class              #95           // ext/mods/Config
   #94 = NameAndType        #96:#6        // loadGameServer:()V
   #95 = Utf8               ext/mods/Config
   #96 = Utf8               loadGameServer
   #97 = String             #98           // Configs files have been reloaded.
   #98 = Utf8               Configs files have been reloaded.
   #99 = String             #100          // crest
  #100 = Utf8               crest
  #101 = Methodref          #102.#103     // ext/mods/gameserver/data/cache/CrestCache.getInstance:()Lext/mods/gameserver/data/cache/CrestCache;
  #102 = Class              #104          // ext/mods/gameserver/data/cache/CrestCache
  #103 = NameAndType        #28:#105      // getInstance:()Lext/mods/gameserver/data/cache/CrestCache;
  #104 = Utf8               ext/mods/gameserver/data/cache/CrestCache
  #105 = Utf8               ()Lext/mods/gameserver/data/cache/CrestCache;
  #106 = Methodref          #102.#31      // ext/mods/gameserver/data/cache/CrestCache.reload:()V
  #107 = String             #108          // Crests have been reloaded.
  #108 = Utf8               Crests have been reloaded.
  #109 = String             #110          // cw
  #110 = Utf8               cw
  #111 = Methodref          #112.#113     // ext/mods/gameserver/data/manager/CursedWeaponManager.getInstance:()Lext/mods/gameserver/data/manager/CursedWeaponManager;
  #112 = Class              #114          // ext/mods/gameserver/data/manager/CursedWeaponManager
  #113 = NameAndType        #28:#115      // getInstance:()Lext/mods/gameserver/data/manager/CursedWeaponManager;
  #114 = Utf8               ext/mods/gameserver/data/manager/CursedWeaponManager
  #115 = Utf8               ()Lext/mods/gameserver/data/manager/CursedWeaponManager;
  #116 = Methodref          #112.#31      // ext/mods/gameserver/data/manager/CursedWeaponManager.reload:()V
  #117 = String             #118          // Cursed weapons have been reloaded.
  #118 = Utf8               Cursed weapons have been reloaded.
  #119 = String             #120          // donate
  #120 = Utf8               donate
  #121 = Methodref          #122.#123     // ext/mods/gameserver/custom/data/DonateData.getInstance:()Lext/mods/gameserver/custom/data/DonateData;
  #122 = Class              #124          // ext/mods/gameserver/custom/data/DonateData
  #123 = NameAndType        #28:#125      // getInstance:()Lext/mods/gameserver/custom/data/DonateData;
  #124 = Utf8               ext/mods/gameserver/custom/data/DonateData
  #125 = Utf8               ()Lext/mods/gameserver/custom/data/DonateData;
  #126 = Methodref          #122.#31      // ext/mods/gameserver/custom/data/DonateData.reload:()V
  #127 = String             #128          // Donate have been reloaded.
  #128 = Utf8               Donate have been reloaded.
  #129 = String             #130          // door
  #130 = Utf8               door
  #131 = Methodref          #132.#133     // ext/mods/gameserver/data/xml/DoorData.getInstance:()Lext/mods/gameserver/data/xml/DoorData;
  #132 = Class              #134          // ext/mods/gameserver/data/xml/DoorData
  #133 = NameAndType        #28:#135      // getInstance:()Lext/mods/gameserver/data/xml/DoorData;
  #134 = Utf8               ext/mods/gameserver/data/xml/DoorData
  #135 = Utf8               ()Lext/mods/gameserver/data/xml/DoorData;
  #136 = Methodref          #132.#31      // ext/mods/gameserver/data/xml/DoorData.reload:()V
  #137 = String             #138          // Doors instance has been reloaded.
  #138 = Utf8               Doors instance has been reloaded.
  #139 = String             #140          // enchant
  #140 = Utf8               enchant
  #141 = Methodref          #142.#143     // ext/mods/gameserver/custom/data/EnchantData.getInstance:()Lext/mods/gameserver/custom/data/EnchantData;
  #142 = Class              #144          // ext/mods/gameserver/custom/data/EnchantData
  #143 = NameAndType        #28:#145      // getInstance:()Lext/mods/gameserver/custom/data/EnchantData;
  #144 = Utf8               ext/mods/gameserver/custom/data/EnchantData
  #145 = Utf8               ()Lext/mods/gameserver/custom/data/EnchantData;
  #146 = Methodref          #142.#31      // ext/mods/gameserver/custom/data/EnchantData.reload:()V
  #147 = String             #148          // Enchant have been reloaded.
  #148 = Utf8               Enchant have been reloaded.
  #149 = String             #150          // farm_event
  #150 = Utf8               farm_event
  #151 = Methodref          #152.#153     // ext/mods/Crypta/RandomManager.getInstance:()Lext/mods/Crypta/RandomManager;
  #152 = Class              #154          // ext/mods/Crypta/RandomManager
  #153 = NameAndType        #28:#155      // getInstance:()Lext/mods/Crypta/RandomManager;
  #154 = Utf8               ext/mods/Crypta/RandomManager
  #155 = Utf8               ()Lext/mods/Crypta/RandomManager;
  #156 = String             #157          // AdminReload: RandomManager is not available.
  #157 = Utf8               AdminReload: RandomManager is not available.
  #158 = Methodref          #152.#31      // ext/mods/Crypta/RandomManager.reload:()V
  #159 = String             #160          // Random Farm Mod has been reloaded.
  #160 = Utf8               Random Farm Mod has been reloaded.
  #161 = Class              #162          // java/lang/Exception
  #162 = Utf8               java/lang/Exception
  #163 = String             #164          // AdminReload: Error accessing RandomManager.
  #164 = Utf8               AdminReload: Error accessing RandomManager.
  #165 = Methodref          #161.#166     // java/lang/Exception.printStackTrace:()V
  #166 = NameAndType        #167:#6       // printStackTrace:()V
  #167 = Utf8               printStackTrace
  #168 = String             #169          // global_drop
  #169 = Utf8               global_drop
  #170 = Methodref          #171.#172     // ext/mods/Crypta/GlobalDropManager.getInstance:()Lext/mods/Crypta/GlobalDropManager;
  #171 = Class              #173          // ext/mods/Crypta/GlobalDropManager
  #172 = NameAndType        #28:#174      // getInstance:()Lext/mods/Crypta/GlobalDropManager;
  #173 = Utf8               ext/mods/Crypta/GlobalDropManager
  #174 = Utf8               ()Lext/mods/Crypta/GlobalDropManager;
  #175 = String             #176          // AdminReload: GlobalDropManager is not available.
  #176 = Utf8               AdminReload: GlobalDropManager is not available.
  #177 = Methodref          #171.#31      // ext/mods/Crypta/GlobalDropManager.reload:()V
  #178 = String             #179          // Global Drop Mod has been reloaded.
  #179 = Utf8               Global Drop Mod has been reloaded.
  #180 = String             #181          // AdminReload: Error accessing GlobalDropManager.
  #181 = Utf8               AdminReload: Error accessing GlobalDropManager.
  #182 = String             #183          // htm
  #183 = Utf8               htm
  #184 = Methodref          #185.#186     // ext/mods/gameserver/data/HTMLData.getInstance:()Lext/mods/gameserver/data/HTMLData;
  #185 = Class              #187          // ext/mods/gameserver/data/HTMLData
  #186 = NameAndType        #28:#188      // getInstance:()Lext/mods/gameserver/data/HTMLData;
  #187 = Utf8               ext/mods/gameserver/data/HTMLData
  #188 = Utf8               ()Lext/mods/gameserver/data/HTMLData;
  #189 = Methodref          #185.#31      // ext/mods/gameserver/data/HTMLData.reload:()V
  #190 = String             #191          // The HTM cache has been reloaded.
  #191 = Utf8               The HTM cache has been reloaded.
  #192 = String             #193          // item
  #193 = Utf8               item
  #194 = Methodref          #195.#196     // ext/mods/gameserver/data/xml/ItemData.getInstance:()Lext/mods/gameserver/data/xml/ItemData;
  #195 = Class              #197          // ext/mods/gameserver/data/xml/ItemData
  #196 = NameAndType        #28:#198      // getInstance:()Lext/mods/gameserver/data/xml/ItemData;
  #197 = Utf8               ext/mods/gameserver/data/xml/ItemData
  #198 = Utf8               ()Lext/mods/gameserver/data/xml/ItemData;
  #199 = Methodref          #195.#31      // ext/mods/gameserver/data/xml/ItemData.reload:()V
  #200 = String             #201          // Items\' templates have been reloaded.
  #201 = Utf8               Items\' templates have been reloaded.
  #202 = String             #203          // mission
  #203 = Utf8               mission
  #204 = Methodref          #205.#206     // ext/mods/gameserver/custom/data/MissionData.getInstance:()Lext/mods/gameserver/custom/data/MissionData;
  #205 = Class              #207          // ext/mods/gameserver/custom/data/MissionData
  #206 = NameAndType        #28:#208      // getInstance:()Lext/mods/gameserver/custom/data/MissionData;
  #207 = Utf8               ext/mods/gameserver/custom/data/MissionData
  #208 = Utf8               ()Lext/mods/gameserver/custom/data/MissionData;
  #209 = Methodref          #205.#31      // ext/mods/gameserver/custom/data/MissionData.reload:()V
  #210 = String             #211          // Mission have been reloaded.
  #211 = Utf8               Mission have been reloaded.
  #212 = String             #213          // multisell
  #213 = Utf8               multisell
  #214 = Methodref          #19.#215      // java/lang/String.equals:(Ljava/lang/Object;)Z
  #215 = NameAndType        #216:#217     // equals:(Ljava/lang/Object;)Z
  #216 = Utf8               equals
  #217 = Utf8               (Ljava/lang/Object;)Z
  #218 = Methodref          #219.#220     // ext/mods/gameserver/data/xml/MultisellData.getInstance:()Lext/mods/gameserver/data/xml/MultisellData;
  #219 = Class              #221          // ext/mods/gameserver/data/xml/MultisellData
  #220 = NameAndType        #28:#222      // getInstance:()Lext/mods/gameserver/data/xml/MultisellData;
  #221 = Utf8               ext/mods/gameserver/data/xml/MultisellData
  #222 = Utf8               ()Lext/mods/gameserver/data/xml/MultisellData;
  #223 = Methodref          #219.#31      // ext/mods/gameserver/data/xml/MultisellData.reload:()V
  #224 = String             #225          // The multisell instance has been reloaded.
  #225 = Utf8               The multisell instance has been reloaded.
  #226 = String             #227          // npc
  #227 = Utf8               npc
  #228 = Methodref          #229.#230     // ext/mods/gameserver/data/xml/NpcData.getInstance:()Lext/mods/gameserver/data/xml/NpcData;
  #229 = Class              #231          // ext/mods/gameserver/data/xml/NpcData
  #230 = NameAndType        #28:#232      // getInstance:()Lext/mods/gameserver/data/xml/NpcData;
  #231 = Utf8               ext/mods/gameserver/data/xml/NpcData
  #232 = Utf8               ()Lext/mods/gameserver/data/xml/NpcData;
  #233 = Methodref          #229.#31      // ext/mods/gameserver/data/xml/NpcData.reload:()V
  #234 = Methodref          #235.#236     // ext/mods/gameserver/data/xml/ScriptData.getInstance:()Lext/mods/gameserver/data/xml/ScriptData;
  #235 = Class              #237          // ext/mods/gameserver/data/xml/ScriptData
  #236 = NameAndType        #28:#238      // getInstance:()Lext/mods/gameserver/data/xml/ScriptData;
  #237 = Utf8               ext/mods/gameserver/data/xml/ScriptData
  #238 = Utf8               ()Lext/mods/gameserver/data/xml/ScriptData;
  #239 = Methodref          #235.#31      // ext/mods/gameserver/data/xml/ScriptData.reload:()V
  #240 = String             #241          // NPCs templates and Scripts have been reloaded.
  #241 = Utf8               NPCs templates and Scripts have been reloaded.
  #242 = String             #243          // npcwalker
  #243 = Utf8               npcwalker
  #244 = Methodref          #245.#246     // ext/mods/gameserver/data/xml/WalkerRouteData.getInstance:()Lext/mods/gameserver/data/xml/WalkerRouteData;
  #245 = Class              #247          // ext/mods/gameserver/data/xml/WalkerRouteData
  #246 = NameAndType        #28:#248      // getInstance:()Lext/mods/gameserver/data/xml/WalkerRouteData;
  #247 = Utf8               ext/mods/gameserver/data/xml/WalkerRouteData
  #248 = Utf8               ()Lext/mods/gameserver/data/xml/WalkerRouteData;
  #249 = Methodref          #245.#31      // ext/mods/gameserver/data/xml/WalkerRouteData.reload:()V
  #250 = String             #251          // Walking routes have been reloaded.
  #251 = Utf8               Walking routes have been reloaded.
  #252 = String             #253          // observer
  #253 = Utf8               observer
  #254 = Methodref          #255.#256     // ext/mods/gameserver/data/xml/ObserverGroupData.getInstance:()Lext/mods/gameserver/data/xml/ObserverGroupData;
  #255 = Class              #257          // ext/mods/gameserver/data/xml/ObserverGroupData
  #256 = NameAndType        #28:#258      // getInstance:()Lext/mods/gameserver/data/xml/ObserverGroupData;
  #257 = Utf8               ext/mods/gameserver/data/xml/ObserverGroupData
  #258 = Utf8               ()Lext/mods/gameserver/data/xml/ObserverGroupData;
  #259 = Methodref          #255.#31      // ext/mods/gameserver/data/xml/ObserverGroupData.reload:()V
  #260 = String             #261          // ObserverGroupData have been reloaded.
  #261 = Utf8               ObserverGroupData have been reloaded.
  #262 = String             #263          // pccafe
  #263 = Utf8               pccafe
  #264 = Methodref          #265.#266     // ext/mods/gameserver/custom/data/PcCafeData.getInstance:()Lext/mods/gameserver/custom/data/PcCafeData;
  #265 = Class              #267          // ext/mods/gameserver/custom/data/PcCafeData
  #266 = NameAndType        #28:#268      // getInstance:()Lext/mods/gameserver/custom/data/PcCafeData;
  #267 = Utf8               ext/mods/gameserver/custom/data/PcCafeData
  #268 = Utf8               ()Lext/mods/gameserver/custom/data/PcCafeData;
  #269 = Methodref          #265.#31      // ext/mods/gameserver/custom/data/PcCafeData.reload:()V
  #270 = String             #271          // PcCafe have been reloaded.
  #271 = Utf8               PcCafe have been reloaded.
  #272 = String             #273          // poly
  #273 = Utf8               poly
  #274 = Methodref          #275.#276     // ext/mods/gameserver/custom/data/PolymorphData.getInstance:()Lext/mods/gameserver/custom/data/PolymorphData;
  #275 = Class              #277          // ext/mods/gameserver/custom/data/PolymorphData
  #276 = NameAndType        #28:#278      // getInstance:()Lext/mods/gameserver/custom/data/PolymorphData;
  #277 = Utf8               ext/mods/gameserver/custom/data/PolymorphData
  #278 = Utf8               ()Lext/mods/gameserver/custom/data/PolymorphData;
  #279 = Methodref          #275.#31      // ext/mods/gameserver/custom/data/PolymorphData.reload:()V
  #280 = String             #281          // Polymorph templates have been reloaded.
  #281 = Utf8               Polymorph templates have been reloaded.
  #282 = String             #283          // pvpdata
  #283 = Utf8               pvpdata
  #284 = Methodref          #285.#286     // ext/mods/gameserver/custom/data/PvPData.getInstance:()Lext/mods/gameserver/custom/data/PvPData;
  #285 = Class              #287          // ext/mods/gameserver/custom/data/PvPData
  #286 = NameAndType        #28:#288      // getInstance:()Lext/mods/gameserver/custom/data/PvPData;
  #287 = Utf8               ext/mods/gameserver/custom/data/PvPData
  #288 = Utf8               ()Lext/mods/gameserver/custom/data/PvPData;
  #289 = Methodref          #285.#31      // ext/mods/gameserver/custom/data/PvPData.reload:()V
  #290 = String             #291          // PvPData have been reloaded.
  #291 = Utf8               PvPData have been reloaded.
  #292 = String             #293          // quests
  #293 = Utf8               quests
  #294 = Methodref          #295.#296     // ext/mods/quests/QuestData.getInstance:()Lext/mods/quests/QuestData;
  #295 = Class              #297          // ext/mods/quests/QuestData
  #296 = NameAndType        #28:#298      // getInstance:()Lext/mods/quests/QuestData;
  #297 = Utf8               ext/mods/quests/QuestData
  #298 = Utf8               ()Lext/mods/quests/QuestData;
  #299 = Methodref          #295.#31      // ext/mods/quests/QuestData.reload:()V
  #300 = String             #301          // QuestCustomData have been reloaded.
  #301 = Utf8               QuestCustomData have been reloaded.
  #302 = String             #303          // restart
  #303 = Utf8               restart
  #304 = Methodref          #305.#306     // ext/mods/gameserver/data/xml/RestartPointData.getInstance:()Lext/mods/gameserver/data/xml/RestartPointData;
  #305 = Class              #307          // ext/mods/gameserver/data/xml/RestartPointData
  #306 = NameAndType        #28:#308      // getInstance:()Lext/mods/gameserver/data/xml/RestartPointData;
  #307 = Utf8               ext/mods/gameserver/data/xml/RestartPointData
  #308 = Utf8               ()Lext/mods/gameserver/data/xml/RestartPointData;
  #309 = Methodref          #305.#31      // ext/mods/gameserver/data/xml/RestartPointData.reload:()V
  #310 = String             #311          // RestartPointData have been reloaded.
  #311 = Utf8               RestartPointData have been reloaded.
  #312 = String             #313          // script
  #313 = Utf8               script
  #314 = String             #315          // Scripts have been reloaded.
  #315 = Utf8               Scripts have been reloaded.
  #316 = String             #317          // skins
  #317 = Utf8               skins
  #318 = Methodref          #319.#320     // ext/mods/dressme/DressMeData.getInstance:()Lext/mods/dressme/DressMeData;
  #319 = Class              #321          // ext/mods/dressme/DressMeData
  #320 = NameAndType        #28:#322      // getInstance:()Lext/mods/dressme/DressMeData;
  #321 = Utf8               ext/mods/dressme/DressMeData
  #322 = Utf8               ()Lext/mods/dressme/DressMeData;
  #323 = Methodref          #319.#31      // ext/mods/dressme/DressMeData.reload:()V
  #324 = String             #325          // Skins have been reloaded.
  #325 = Utf8               Skins have been reloaded.
  #326 = String             #327          // skill
  #327 = Utf8               skill
  #328 = Methodref          #329.#330     // ext/mods/gameserver/data/SkillTable.getInstance:()Lext/mods/gameserver/data/SkillTable;
  #329 = Class              #331          // ext/mods/gameserver/data/SkillTable
  #330 = NameAndType        #28:#332      // getInstance:()Lext/mods/gameserver/data/SkillTable;
  #331 = Utf8               ext/mods/gameserver/data/SkillTable
  #332 = Utf8               ()Lext/mods/gameserver/data/SkillTable;
  #333 = Methodref          #329.#31      // ext/mods/gameserver/data/SkillTable.reload:()V
  #334 = String             #335          // Skills\' XMLs have been reloaded.
  #335 = Utf8               Skills\' XMLs have been reloaded.
  #336 = String             #337          // spawnlist
  #337 = Utf8               spawnlist
  #338 = Methodref          #339.#340     // ext/mods/gameserver/data/manager/SpawnManager.getInstance:()Lext/mods/gameserver/data/manager/SpawnManager;
  #339 = Class              #341          // ext/mods/gameserver/data/manager/SpawnManager
  #340 = NameAndType        #28:#342      // getInstance:()Lext/mods/gameserver/data/manager/SpawnManager;
  #341 = Utf8               ext/mods/gameserver/data/manager/SpawnManager
  #342 = Utf8               ()Lext/mods/gameserver/data/manager/SpawnManager;
  #343 = Methodref          #339.#344     // ext/mods/gameserver/data/manager/SpawnManager.despawn:()V
  #344 = NameAndType        #345:#6       // despawn:()V
  #345 = Utf8               despawn
  #346 = Methodref          #347.#348     // ext/mods/gameserver/model/World.getInstance:()Lext/mods/gameserver/model/World;
  #347 = Class              #349          // ext/mods/gameserver/model/World
  #348 = NameAndType        #28:#350      // getInstance:()Lext/mods/gameserver/model/World;
  #349 = Utf8               ext/mods/gameserver/model/World
  #350 = Utf8               ()Lext/mods/gameserver/model/World;
  #351 = Methodref          #347.#352     // ext/mods/gameserver/model/World.deleteVisibleNpcSpawns:()V
  #352 = NameAndType        #353:#6       // deleteVisibleNpcSpawns:()V
  #353 = Utf8               deleteVisibleNpcSpawns
  #354 = Methodref          #339.#31      // ext/mods/gameserver/data/manager/SpawnManager.reload:()V
  #355 = String             #356          // sysstring
  #356 = Utf8               sysstring
  #357 = Methodref          #358.#359     // ext/mods/gameserver/data/xml/SysString.getInstance:()Lext/mods/gameserver/data/xml/SysString;
  #358 = Class              #360          // ext/mods/gameserver/data/xml/SysString
  #359 = NameAndType        #28:#361      // getInstance:()Lext/mods/gameserver/data/xml/SysString;
  #360 = Utf8               ext/mods/gameserver/data/xml/SysString
  #361 = Utf8               ()Lext/mods/gameserver/data/xml/SysString;
  #362 = Methodref          #358.#31      // ext/mods/gameserver/data/xml/SysString.reload:()V
  #363 = String             #364          // SysString have been reloaded.
  #364 = Utf8               SysString have been reloaded.
  #365 = String             #366          // teleport
  #366 = Utf8               teleport
  #367 = Methodref          #368.#369     // ext/mods/gameserver/data/xml/InstantTeleportData.getInstance:()Lext/mods/gameserver/data/xml/InstantTeleportData;
  #368 = Class              #370          // ext/mods/gameserver/data/xml/InstantTeleportData
  #369 = NameAndType        #28:#371      // getInstance:()Lext/mods/gameserver/data/xml/InstantTeleportData;
  #370 = Utf8               ext/mods/gameserver/data/xml/InstantTeleportData
  #371 = Utf8               ()Lext/mods/gameserver/data/xml/InstantTeleportData;
  #372 = Methodref          #368.#31      // ext/mods/gameserver/data/xml/InstantTeleportData.reload:()V
  #373 = Methodref          #374.#375     // ext/mods/gameserver/data/xml/TeleportData.getInstance:()Lext/mods/gameserver/data/xml/TeleportData;
  #374 = Class              #376          // ext/mods/gameserver/data/xml/TeleportData
  #375 = NameAndType        #28:#377      // getInstance:()Lext/mods/gameserver/data/xml/TeleportData;
  #376 = Utf8               ext/mods/gameserver/data/xml/TeleportData
  #377 = Utf8               ()Lext/mods/gameserver/data/xml/TeleportData;
  #378 = Methodref          #374.#31      // ext/mods/gameserver/data/xml/TeleportData.reload:()V
  #379 = String             #380          // Teleport locations have been reloaded.
  #380 = Utf8               Teleport locations have been reloaded.
  #381 = String             #382          // zone
  #382 = Utf8               zone
  #383 = Methodref          #384.#385     // ext/mods/gameserver/data/manager/ZoneManager.getInstance:()Lext/mods/gameserver/data/manager/ZoneManager;
  #384 = Class              #386          // ext/mods/gameserver/data/manager/ZoneManager
  #385 = NameAndType        #28:#387      // getInstance:()Lext/mods/gameserver/data/manager/ZoneManager;
  #386 = Utf8               ext/mods/gameserver/data/manager/ZoneManager
  #387 = Utf8               ()Lext/mods/gameserver/data/manager/ZoneManager;
  #388 = Methodref          #384.#31      // ext/mods/gameserver/data/manager/ZoneManager.reload:()V
  #389 = String             #390          // Zones have been reloaded.
  #390 = Utf8               Zones have been reloaded.
  #391 = Methodref          #392.#393     // ext/mods/gameserver/handler/admincommandhandlers/AdminReload.sendUsage:(Lext/mods/gameserver/model/actor/Player;)V
  #392 = Class              #394          // ext/mods/gameserver/handler/admincommandhandlers/AdminReload
  #393 = NameAndType        #395:#396     // sendUsage:(Lext/mods/gameserver/model/actor/Player;)V
  #394 = Utf8               ext/mods/gameserver/handler/admincommandhandlers/AdminReload
  #395 = Utf8               sendUsage
  #396 = Utf8               (Lext/mods/gameserver/model/actor/Player;)V
  #397 = Methodref          #7.#398       // java/util/StringTokenizer.hasMoreTokens:()Z
  #398 = NameAndType        #399:#400     // hasMoreTokens:()Z
  #399 = Utf8               hasMoreTokens
  #400 = Utf8               ()Z
  #401 = String             #402          // Usage : //reload <admin|announcement|auction|boat|buylist>
  #402 = Utf8               Usage : //reload <admin|announcement|auction|boat|buylist>
  #403 = String             #404          // Usage : //reload <capsule|config|crest|cw|donate|door>
  #404 = Utf8               Usage : //reload <capsule|config|crest|cw|donate|door>
  #405 = String             #406          // Usage : //reload <enchant|farm_event|global_drop|htm|item|mission>
  #406 = Utf8               Usage : //reload <enchant|farm_event|global_drop|htm|item|mission>
  #407 = String             #408          // Usage : //reload <multisell|npc|npcwalker|observer|pccafe|poly>
  #408 = Utf8               Usage : //reload <multisell|npc|npcwalker|observer|pccafe|poly>
  #409 = String             #410          // Usage : //reload <pvpdata|quests|restart|script|skins|skill>
  #410 = Utf8               Usage : //reload <pvpdata|quests|restart|script|skins|skill>
  #411 = String             #412          // Usage : //reload <spawnlist|sysstring|teleport|zone>
  #412 = Utf8               Usage : //reload <spawnlist|sysstring|teleport|zone>
  #413 = Fieldref           #392.#414     // ext/mods/gameserver/handler/admincommandhandlers/AdminReload.ADMIN_COMMANDS:[Ljava/lang/String;
  #414 = NameAndType        #415:#416     // ADMIN_COMMANDS:[Ljava/lang/String;
  #415 = Utf8               ADMIN_COMMANDS
  #416 = Utf8               [Ljava/lang/String;
  #417 = Class              #418          // ext/mods/commons/logging/CLogger
  #418 = Utf8               ext/mods/commons/logging/CLogger
  #419 = Methodref          #420.#421     // java/lang/Class.getName:()Ljava/lang/String;
  #420 = Class              #422          // java/lang/Class
  #421 = NameAndType        #423:#15      // getName:()Ljava/lang/String;
  #422 = Utf8               java/lang/Class
  #423 = Utf8               getName
  #424 = Methodref          #417.#10      // ext/mods/commons/logging/CLogger."<init>":(Ljava/lang/String;)V
  #425 = Fieldref           #392.#426     // ext/mods/gameserver/handler/admincommandhandlers/AdminReload.LOGGER:Lext/mods/commons/logging/CLogger;
  #426 = NameAndType        #427:#428     // LOGGER:Lext/mods/commons/logging/CLogger;
  #427 = Utf8               LOGGER
  #428 = Utf8               Lext/mods/commons/logging/CLogger;
  #429 = String             #430          // admin_reload
  #430 = Utf8               admin_reload
  #431 = Class              #432          // ext/mods/gameserver/handler/IAdminCommandHandler
  #432 = Utf8               ext/mods/gameserver/handler/IAdminCommandHandler
  #433 = Utf8               Code
  #434 = Utf8               LineNumberTable
  #435 = Utf8               LocalVariableTable
  #436 = Utf8               this
  #437 = Utf8               Lext/mods/gameserver/handler/admincommandhandlers/AdminReload;
  #438 = Utf8               useAdminCommand
  #439 = Utf8               (Ljava/lang/String;Lext/mods/gameserver/model/actor/Player;)V
  #440 = Utf8               e
  #441 = Utf8               Ljava/lang/Exception;
  #442 = Utf8               RandomManagerIntance
  #443 = Utf8               Ljava/lang/Object;
  #444 = Utf8               blobaldrops
  #445 = Utf8               type
  #446 = Utf8               Ljava/lang/String;
  #447 = Utf8               command
  #448 = Utf8               player
  #449 = Utf8               Lext/mods/gameserver/model/actor/Player;
  #450 = Utf8               st
  #451 = Utf8               Ljava/util/StringTokenizer;
  #452 = Utf8               StackMapTable
  #453 = Utf8               getAdminCommandList
  #454 = Utf8               ()[Ljava/lang/String;
  #455 = Utf8               <clinit>
  #456 = Utf8               SourceFile
  #457 = Utf8               AdminReload.java
{
  public static final ext.mods.commons.logging.CLogger LOGGER;
    descriptor: Lext/mods/commons/logging/CLogger;
    flags: (0x0019) ACC_PUBLIC, ACC_STATIC, ACC_FINAL

  public ext.mods.gameserver.handler.admincommandhandlers.AdminReload();
    descriptor: ()V
    flags: (0x0001) ACC_PUBLIC
    Code:
      stack=1, locals=1, args_size=1
         0: aload_0
         1: invokespecial #1                  // Method java/lang/Object."<init>":()V
         4: return
      LineNumberTable:
        line 64: 0
      LocalVariableTable:
        Start  Length  Slot  Name   Signature
            0       5     0  this   Lext/mods/gameserver/handler/admincommandhandlers/AdminReload;

  public void useAdminCommand(java.lang.String, ext.mods.gameserver.model.actor.Player);
    descriptor: (Ljava/lang/String;Lext/mods/gameserver/model/actor/Player;)V
    flags: (0x0001) ACC_PUBLIC
    Code:
      stack=3, locals=7, args_size=3
         0: new           #7                  // class java/util/StringTokenizer
         3: dup
         4: aload_1
         5: invokespecial #9                  // Method java/util/StringTokenizer."<init>":(Ljava/lang/String;)V
         8: astore_3
         9: aload_3
        10: invokevirtual #12                 // Method java/util/StringTokenizer.nextToken:()Ljava/lang/String;
        13: pop
        14: aload_3
        15: invokevirtual #12                 // Method java/util/StringTokenizer.nextToken:()Ljava/lang/String;
        18: astore        4
        20: aload         4
        22: ldc           #16                 // String admin
        24: invokevirtual #18                 // Method java/lang/String.startsWith:(Ljava/lang/String;)Z
        27: ifeq          45
        30: invokestatic  #24                 // Method ext/mods/gameserver/data/xml/AdminData.getInstance:()Lext/mods/gameserver/data/xml/AdminData;
        33: invokevirtual #30                 // Method ext/mods/gameserver/data/xml/AdminData.reload:()V
        36: aload_2
        37: ldc           #33                 // String Admin data has been reloaded.
        39: invokevirtual #35                 // Method ext/mods/gameserver/model/actor/Player.sendMessage:(Ljava/lang/String;)V
        42: goto          969
        45: aload         4
        47: ldc           #40                 // String announcement
        49: invokevirtual #18                 // Method java/lang/String.startsWith:(Ljava/lang/String;)Z
        52: ifeq          70
        55: invokestatic  #42                 // Method ext/mods/gameserver/data/xml/AnnouncementData.getInstance:()Lext/mods/gameserver/data/xml/AnnouncementData;
        58: invokevirtual #47                 // Method ext/mods/gameserver/data/xml/AnnouncementData.reload:()V
        61: aload_2
        62: ldc           #48                 // String The content of announcements.xml has been reloaded.
        64: invokevirtual #35                 // Method ext/mods/gameserver/model/actor/Player.sendMessage:(Ljava/lang/String;)V
        67: goto          969
        70: aload         4
        72: ldc           #50                 // String auction
        74: invokevirtual #18                 // Method java/lang/String.startsWith:(Ljava/lang/String;)Z
        77: ifeq          95
        80: invokestatic  #52                 // Method ext/mods/gameserver/custom/data/AuctionCurrencies.getInstance:()Lext/mods/gameserver/custom/data/AuctionCurrencies;
        83: invokevirtual #57                 // Method ext/mods/gameserver/custom/data/AuctionCurrencies.reload:()V
        86: aload_2
        87: ldc           #58                 // String Auction have been reloaded.
        89: invokevirtual #35                 // Method ext/mods/gameserver/model/actor/Player.sendMessage:(Ljava/lang/String;)V
        92: goto          969
        95: aload         4
        97: ldc           #60                 // String boat
        99: invokevirtual #18                 // Method java/lang/String.startsWith:(Ljava/lang/String;)Z
       102: ifeq          120
       105: invokestatic  #62                 // Method ext/mods/gameserver/data/xml/BoatData.getInstance:()Lext/mods/gameserver/data/xml/BoatData;
       108: invokevirtual #67                 // Method ext/mods/gameserver/data/xml/BoatData.reload:()V
       111: aload_2
       112: ldc           #68                 // String Boat have been reloaded.
       114: invokevirtual #35                 // Method ext/mods/gameserver/model/actor/Player.sendMessage:(Ljava/lang/String;)V
       117: goto          969
       120: aload         4
       122: ldc           #70                 // String buylist
       124: invokevirtual #18                 // Method java/lang/String.startsWith:(Ljava/lang/String;)Z
       127: ifeq          145
       130: invokestatic  #72                 // Method ext/mods/gameserver/data/manager/BuyListManager.getInstance:()Lext/mods/gameserver/data/manager/BuyListManager;
       133: invokevirtual #77                 // Method ext/mods/gameserver/data/manager/BuyListManager.reload:()V
       136: aload_2
       137: ldc           #78                 // String Buylists have been reloaded.
       139: invokevirtual #35                 // Method ext/mods/gameserver/model/actor/Player.sendMessage:(Ljava/lang/String;)V
       142: goto          969
       145: aload         4
       147: ldc           #80                 // String capsule
       149: invokevirtual #18                 // Method java/lang/String.startsWith:(Ljava/lang/String;)Z
       152: ifeq          170
       155: invokestatic  #82                 // Method ext/mods/CapsuleBox/CapsuleBoxData.getInstance:()Lext/mods/CapsuleBox/CapsuleBoxData;
       158: invokevirtual #87                 // Method ext/mods/CapsuleBox/CapsuleBoxData.reload:()V
       161: aload_2
       162: ldc           #88                 // String Capsule Box have been reloaded.
       164: invokevirtual #35                 // Method ext/mods/gameserver/model/actor/Player.sendMessage:(Ljava/lang/String;)V
       167: goto          969
       170: aload         4
       172: ldc           #90                 // String config
       174: invokevirtual #18                 // Method java/lang/String.startsWith:(Ljava/lang/String;)Z
       177: ifeq          192
       180: invokestatic  #92                 // Method ext/mods/Config.loadGameServer:()V
       183: aload_2
       184: ldc           #97                 // String Configs files have been reloaded.
       186: invokevirtual #35                 // Method ext/mods/gameserver/model/actor/Player.sendMessage:(Ljava/lang/String;)V
       189: goto          969
       192: aload         4
       194: ldc           #99                 // String crest
       196: invokevirtual #18                 // Method java/lang/String.startsWith:(Ljava/lang/String;)Z
       199: ifeq          217
       202: invokestatic  #101                // Method ext/mods/gameserver/data/cache/CrestCache.getInstance:()Lext/mods/gameserver/data/cache/CrestCache;
       205: invokevirtual #106                // Method ext/mods/gameserver/data/cache/CrestCache.reload:()V
       208: aload_2
       209: ldc           #107                // String Crests have been reloaded.
       211: invokevirtual #35                 // Method ext/mods/gameserver/model/actor/Player.sendMessage:(Ljava/lang/String;)V
       214: goto          969
       217: aload         4
       219: ldc           #109                // String cw
       221: invokevirtual #18                 // Method java/lang/String.startsWith:(Ljava/lang/String;)Z
       224: ifeq          242
       227: invokestatic  #111                // Method ext/mods/gameserver/data/manager/CursedWeaponManager.getInstance:()Lext/mods/gameserver/data/manager/CursedWeaponManager;
       230: invokevirtual #116                // Method ext/mods/gameserver/data/manager/CursedWeaponManager.reload:()V
       233: aload_2
       234: ldc           #117                // String Cursed weapons have been reloaded.
       236: invokevirtual #35                 // Method ext/mods/gameserver/model/actor/Player.sendMessage:(Ljava/lang/String;)V
       239: goto          969
       242: aload         4
       244: ldc           #119                // String donate
       246: invokevirtual #18                 // Method java/lang/String.startsWith:(Ljava/lang/String;)Z
       249: ifeq          267
       252: invokestatic  #121                // Method ext/mods/gameserver/custom/data/DonateData.getInstance:()Lext/mods/gameserver/custom/data/DonateData;
       255: invokevirtual #126                // Method ext/mods/gameserver/custom/data/DonateData.reload:()V
       258: aload_2
       259: ldc           #127                // String Donate have been reloaded.
       261: invokevirtual #35                 // Method ext/mods/gameserver/model/actor/Player.sendMessage:(Ljava/lang/String;)V
       264: goto          969
       267: aload         4
       269: ldc           #129                // String door
       271: invokevirtual #18                 // Method java/lang/String.startsWith:(Ljava/lang/String;)Z
       274: ifeq          292
       277: invokestatic  #131                // Method ext/mods/gameserver/data/xml/DoorData.getInstance:()Lext/mods/gameserver/data/xml/DoorData;
       280: invokevirtual #136                // Method ext/mods/gameserver/data/xml/DoorData.reload:()V
       283: aload_2
       284: ldc           #137                // String Doors instance has been reloaded.
       286: invokevirtual #35                 // Method ext/mods/gameserver/model/actor/Player.sendMessage:(Ljava/lang/String;)V
       289: goto          969
       292: aload         4
       294: ldc           #139                // String enchant
       296: invokevirtual #18                 // Method java/lang/String.startsWith:(Ljava/lang/String;)Z
       299: ifeq          317
       302: invokestatic  #141                // Method ext/mods/gameserver/custom/data/EnchantData.getInstance:()Lext/mods/gameserver/custom/data/EnchantData;
       305: invokevirtual #146                // Method ext/mods/gameserver/custom/data/EnchantData.reload:()V
       308: aload_2
       309: ldc           #147                // String Enchant have been reloaded.
       311: invokevirtual #35                 // Method ext/mods/gameserver/model/actor/Player.sendMessage:(Ljava/lang/String;)V
       314: goto          969
       317: aload         4
       319: ldc           #149                // String farm_event
       321: invokevirtual #18                 // Method java/lang/String.startsWith:(Ljava/lang/String;)Z
       324: ifeq          376
       327: invokestatic  #151                // Method ext/mods/Crypta/RandomManager.getInstance:()Lext/mods/Crypta/RandomManager;
       330: astore        5
       332: aload         5
       334: ifnonnull     344
       337: aload_2
       338: ldc           #156                // String AdminReload: RandomManager is not available.
       340: invokevirtual #35                 // Method ext/mods/gameserver/model/actor/Player.sendMessage:(Ljava/lang/String;)V
       343: return
       344: invokestatic  #151                // Method ext/mods/Crypta/RandomManager.getInstance:()Lext/mods/Crypta/RandomManager;
       347: invokevirtual #158                // Method ext/mods/Crypta/RandomManager.reload:()V
       350: aload_2
       351: ldc           #159                // String Random Farm Mod has been reloaded.
       353: invokevirtual #35                 // Method ext/mods/gameserver/model/actor/Player.sendMessage:(Ljava/lang/String;)V
       356: goto          373
       359: astore        6
       361: aload_2
       362: ldc           #163                // String AdminReload: Error accessing RandomManager.
       364: invokevirtual #35                 // Method ext/mods/gameserver/model/actor/Player.sendMessage:(Ljava/lang/String;)V
       367: aload         6
       369: invokevirtual #165                // Method java/lang/Exception.printStackTrace:()V
       372: return
       373: goto          969
       376: aload         4
       378: ldc           #168                // String global_drop
       380: invokevirtual #18                 // Method java/lang/String.startsWith:(Ljava/lang/String;)Z
       383: ifeq          435
       386: invokestatic  #170                // Method ext/mods/Crypta/GlobalDropManager.getInstance:()Lext/mods/Crypta/GlobalDropManager;
       389: astore        5
       391: aload         5
       393: ifnonnull     403
       396: aload_2
       397: ldc           #175                // String AdminReload: GlobalDropManager is not available.
       399: invokevirtual #35                 // Method ext/mods/gameserver/model/actor/Player.sendMessage:(Ljava/lang/String;)V
       402: return
       403: invokestatic  #170                // Method ext/mods/Crypta/GlobalDropManager.getInstance:()Lext/mods/Crypta/GlobalDropManager;
       406: invokevirtual #177                // Method ext/mods/Crypta/GlobalDropManager.reload:()V
       409: aload_2
       410: ldc           #178                // String Global Drop Mod has been reloaded.
       412: invokevirtual #35                 // Method ext/mods/gameserver/model/actor/Player.sendMessage:(Ljava/lang/String;)V
       415: goto          432
       418: astore        6
       420: aload_2
       421: ldc           #180                // String AdminReload: Error accessing GlobalDropManager.
       423: invokevirtual #35                 // Method ext/mods/gameserver/model/actor/Player.sendMessage:(Ljava/lang/String;)V
       426: aload         6
       428: invokevirtual #165                // Method java/lang/Exception.printStackTrace:()V
       431: return
       432: goto          969
       435: aload         4
       437: ldc           #182                // String htm
       439: invokevirtual #18                 // Method java/lang/String.startsWith:(Ljava/lang/String;)Z
       442: ifeq          460
       445: invokestatic  #184                // Method ext/mods/gameserver/data/HTMLData.getInstance:()Lext/mods/gameserver/data/HTMLData;
       448: invokevirtual #189                // Method ext/mods/gameserver/data/HTMLData.reload:()V
       451: aload_2
       452: ldc           #190                // String The HTM cache has been reloaded.
       454: invokevirtual #35                 // Method ext/mods/gameserver/model/actor/Player.sendMessage:(Ljava/lang/String;)V
       457: goto          969
       460: aload         4
       462: ldc           #192                // String item
       464: invokevirtual #18                 // Method java/lang/String.startsWith:(Ljava/lang/String;)Z
       467: ifeq          485
       470: invokestatic  #194                // Method ext/mods/gameserver/data/xml/ItemData.getInstance:()Lext/mods/gameserver/data/xml/ItemData;
       473: invokevirtual #199                // Method ext/mods/gameserver/data/xml/ItemData.reload:()V
       476: aload_2
       477: ldc           #200                // String Items\' templates have been reloaded.
       479: invokevirtual #35                 // Method ext/mods/gameserver/model/actor/Player.sendMessage:(Ljava/lang/String;)V
       482: goto          969
       485: aload         4
       487: ldc           #202                // String mission
       489: invokevirtual #18                 // Method java/lang/String.startsWith:(Ljava/lang/String;)Z
       492: ifeq          510
       495: invokestatic  #204                // Method ext/mods/gameserver/custom/data/MissionData.getInstance:()Lext/mods/gameserver/custom/data/MissionData;
       498: invokevirtual #209                // Method ext/mods/gameserver/custom/data/MissionData.reload:()V
       501: aload_2
       502: ldc           #210                // String Mission have been reloaded.
       504: invokevirtual #35                 // Method ext/mods/gameserver/model/actor/Player.sendMessage:(Ljava/lang/String;)V
       507: goto          969
       510: aload         4
       512: ldc           #212                // String multisell
       514: invokevirtual #214                // Method java/lang/String.equals:(Ljava/lang/Object;)Z
       517: ifeq          535
       520: invokestatic  #218                // Method ext/mods/gameserver/data/xml/MultisellData.getInstance:()Lext/mods/gameserver/data/xml/MultisellData;
       523: invokevirtual #223                // Method ext/mods/gameserver/data/xml/MultisellData.reload:()V
       526: aload_2
       527: ldc           #224                // String The multisell instance has been reloaded.
       529: invokevirtual #35                 // Method ext/mods/gameserver/model/actor/Player.sendMessage:(Ljava/lang/String;)V
       532: goto          969
       535: aload         4
       537: ldc           #226                // String npc
       539: invokevirtual #214                // Method java/lang/String.equals:(Ljava/lang/Object;)Z
       542: ifeq          566
       545: invokestatic  #228                // Method ext/mods/gameserver/data/xml/NpcData.getInstance:()Lext/mods/gameserver/data/xml/NpcData;
       548: invokevirtual #233                // Method ext/mods/gameserver/data/xml/NpcData.reload:()V
       551: invokestatic  #234                // Method ext/mods/gameserver/data/xml/ScriptData.getInstance:()Lext/mods/gameserver/data/xml/ScriptData;
       554: invokevirtual #239                // Method ext/mods/gameserver/data/xml/ScriptData.reload:()V
       557: aload_2
       558: ldc           #240                // String NPCs templates and Scripts have been reloaded.
       560: invokevirtual #35                 // Method ext/mods/gameserver/model/actor/Player.sendMessage:(Ljava/lang/String;)V
       563: goto          969
       566: aload         4
       568: ldc           #242                // String npcwalker
       570: invokevirtual #18                 // Method java/lang/String.startsWith:(Ljava/lang/String;)Z
       573: ifeq          591
       576: invokestatic  #244                // Method ext/mods/gameserver/data/xml/WalkerRouteData.getInstance:()Lext/mods/gameserver/data/xml/WalkerRouteData;
       579: invokevirtual #249                // Method ext/mods/gameserver/data/xml/WalkerRouteData.reload:()V
       582: aload_2
       583: ldc           #250                // String Walking routes have been reloaded.
       585: invokevirtual #35                 // Method ext/mods/gameserver/model/actor/Player.sendMessage:(Ljava/lang/String;)V
       588: goto          969
       591: aload         4
       593: ldc           #252                // String observer
       595: invokevirtual #18                 // Method java/lang/String.startsWith:(Ljava/lang/String;)Z
       598: ifeq          617
       601: invokestatic  #254                // Method ext/mods/gameserver/data/xml/ObserverGroupData.getInstance:()Lext/mods/gameserver/data/xml/ObserverGroupData;
       604: invokevirtual #259                // Method ext/mods/gameserver/data/xml/ObserverGroupData.reload:()V
       607: aload_2
       608: ldc_w         #260                // String ObserverGroupData have been reloaded.
       611: invokevirtual #35                 // Method ext/mods/gameserver/model/actor/Player.sendMessage:(Ljava/lang/String;)V
       614: goto          969
       617: aload         4
       619: ldc_w         #262                // String pccafe
       622: invokevirtual #18                 // Method java/lang/String.startsWith:(Ljava/lang/String;)Z
       625: ifeq          644
       628: invokestatic  #264                // Method ext/mods/gameserver/custom/data/PcCafeData.getInstance:()Lext/mods/gameserver/custom/data/PcCafeData;
       631: invokevirtual #269                // Method ext/mods/gameserver/custom/data/PcCafeData.reload:()V
       634: aload_2
       635: ldc_w         #270                // String PcCafe have been reloaded.
       638: invokevirtual #35                 // Method ext/mods/gameserver/model/actor/Player.sendMessage:(Ljava/lang/String;)V
       641: goto          969
       644: aload         4
       646: ldc_w         #272                // String poly
       649: invokevirtual #18                 // Method java/lang/String.startsWith:(Ljava/lang/String;)Z
       652: ifeq          671
       655: invokestatic  #274                // Method ext/mods/gameserver/custom/data/PolymorphData.getInstance:()Lext/mods/gameserver/custom/data/PolymorphData;
       658: invokevirtual #279                // Method ext/mods/gameserver/custom/data/PolymorphData.reload:()V
       661: aload_2
       662: ldc_w         #280                // String Polymorph templates have been reloaded.
       665: invokevirtual #35                 // Method ext/mods/gameserver/model/actor/Player.sendMessage:(Ljava/lang/String;)V
       668: goto          969
       671: aload         4
       673: ldc_w         #282                // String pvpdata
       676: invokevirtual #18                 // Method java/lang/String.startsWith:(Ljava/lang/String;)Z
       679: ifeq          698
       682: invokestatic  #284                // Method ext/mods/gameserver/custom/data/PvPData.getInstance:()Lext/mods/gameserver/custom/data/PvPData;
       685: invokevirtual #289                // Method ext/mods/gameserver/custom/data/PvPData.reload:()V
       688: aload_2
       689: ldc_w         #290                // String PvPData have been reloaded.
       692: invokevirtual #35                 // Method ext/mods/gameserver/model/actor/Player.sendMessage:(Ljava/lang/String;)V
       695: goto          969
       698: aload         4
       700: ldc_w         #292                // String quests
       703: invokevirtual #18                 // Method java/lang/String.startsWith:(Ljava/lang/String;)Z
       706: ifeq          725
       709: invokestatic  #294                // Method ext/mods/quests/QuestData.getInstance:()Lext/mods/quests/QuestData;
       712: invokevirtual #299                // Method ext/mods/quests/QuestData.reload:()V
       715: aload_2
       716: ldc_w         #300                // String QuestCustomData have been reloaded.
       719: invokevirtual #35                 // Method ext/mods/gameserver/model/actor/Player.sendMessage:(Ljava/lang/String;)V
       722: goto          969
       725: aload         4
       727: ldc_w         #302                // String restart
       730: invokevirtual #18                 // Method java/lang/String.startsWith:(Ljava/lang/String;)Z
       733: ifeq          752
       736: invokestatic  #304                // Method ext/mods/gameserver/data/xml/RestartPointData.getInstance:()Lext/mods/gameserver/data/xml/RestartPointData;
       739: invokevirtual #309                // Method ext/mods/gameserver/data/xml/RestartPointData.reload:()V
       742: aload_2
       743: ldc_w         #310                // String RestartPointData have been reloaded.
       746: invokevirtual #35                 // Method ext/mods/gameserver/model/actor/Player.sendMessage:(Ljava/lang/String;)V
       749: goto          969
       752: aload         4
       754: ldc_w         #312                // String script
       757: invokevirtual #214                // Method java/lang/String.equals:(Ljava/lang/Object;)Z
       760: ifeq          779
       763: invokestatic  #234                // Method ext/mods/gameserver/data/xml/ScriptData.getInstance:()Lext/mods/gameserver/data/xml/ScriptData;
       766: invokevirtual #239                // Method ext/mods/gameserver/data/xml/ScriptData.reload:()V
       769: aload_2
       770: ldc_w         #314                // String Scripts have been reloaded.
       773: invokevirtual #35                 // Method ext/mods/gameserver/model/actor/Player.sendMessage:(Ljava/lang/String;)V
       776: goto          969
       779: aload         4
       781: ldc_w         #316                // String skins
       784: invokevirtual #18                 // Method java/lang/String.startsWith:(Ljava/lang/String;)Z
       787: ifeq          806
       790: invokestatic  #318                // Method ext/mods/dressme/DressMeData.getInstance:()Lext/mods/dressme/DressMeData;
       793: invokevirtual #323                // Method ext/mods/dressme/DressMeData.reload:()V
       796: aload_2
       797: ldc_w         #324                // String Skins have been reloaded.
       800: invokevirtual #35                 // Method ext/mods/gameserver/model/actor/Player.sendMessage:(Ljava/lang/String;)V
       803: goto          969
       806: aload         4
       808: ldc_w         #326                // String skill
       811: invokevirtual #18                 // Method java/lang/String.startsWith:(Ljava/lang/String;)Z
       814: ifeq          833
       817: invokestatic  #328                // Method ext/mods/gameserver/data/SkillTable.getInstance:()Lext/mods/gameserver/data/SkillTable;
       820: invokevirtual #333                // Method ext/mods/gameserver/data/SkillTable.reload:()V
       823: aload_2
       824: ldc_w         #334                // String Skills\' XMLs have been reloaded.
       827: invokevirtual #35                 // Method ext/mods/gameserver/model/actor/Player.sendMessage:(Ljava/lang/String;)V
       830: goto          969
       833: aload         4
       835: ldc_w         #336                // String spawnlist
       838: invokevirtual #18                 // Method java/lang/String.startsWith:(Ljava/lang/String;)Z
       841: ifeq          877
       844: invokestatic  #338                // Method ext/mods/gameserver/data/manager/SpawnManager.getInstance:()Lext/mods/gameserver/data/manager/SpawnManager;
       847: invokevirtual #343                // Method ext/mods/gameserver/data/manager/SpawnManager.despawn:()V
       850: invokestatic  #346                // Method ext/mods/gameserver/model/World.getInstance:()Lext/mods/gameserver/model/World;
       853: invokevirtual #351                // Method ext/mods/gameserver/model/World.deleteVisibleNpcSpawns:()V
       856: invokestatic  #228                // Method ext/mods/gameserver/data/xml/NpcData.getInstance:()Lext/mods/gameserver/data/xml/NpcData;
       859: invokevirtual #233                // Method ext/mods/gameserver/data/xml/NpcData.reload:()V
       862: invokestatic  #234                // Method ext/mods/gameserver/data/xml/ScriptData.getInstance:()Lext/mods/gameserver/data/xml/ScriptData;
       865: invokevirtual #239                // Method ext/mods/gameserver/data/xml/ScriptData.reload:()V
       868: invokestatic  #338                // Method ext/mods/gameserver/data/manager/SpawnManager.getInstance:()Lext/mods/gameserver/data/manager/SpawnManager;
       871: invokevirtual #354                // Method ext/mods/gameserver/data/manager/SpawnManager.reload:()V
       874: goto          969
       877: aload         4
       879: ldc_w         #355                // String sysstring
       882: invokevirtual #18                 // Method java/lang/String.startsWith:(Ljava/lang/String;)Z
       885: ifeq          904
       888: invokestatic  #357                // Method ext/mods/gameserver/data/xml/SysString.getInstance:()Lext/mods/gameserver/data/xml/SysString;
       891: invokevirtual #362                // Method ext/mods/gameserver/data/xml/SysString.reload:()V
       894: aload_2
       895: ldc_w         #363                // String SysString have been reloaded.
       898: invokevirtual #35                 // Method ext/mods/gameserver/model/actor/Player.sendMessage:(Ljava/lang/String;)V
       901: goto          969
       904: aload         4
       906: ldc_w         #365                // String teleport
       909: invokevirtual #18                 // Method java/lang/String.startsWith:(Ljava/lang/String;)Z
       912: ifeq          937
       915: invokestatic  #367                // Method ext/mods/gameserver/data/xml/InstantTeleportData.getInstance:()Lext/mods/gameserver/data/xml/InstantTeleportData;
       918: invokevirtual #372                // Method ext/mods/gameserver/data/xml/InstantTeleportData.reload:()V
       921: invokestatic  #373                // Method ext/mods/gameserver/data/xml/TeleportData.getInstance:()Lext/mods/gameserver/data/xml/TeleportData;
       924: invokevirtual #378                // Method ext/mods/gameserver/data/xml/TeleportData.reload:()V
       927: aload_2
       928: ldc_w         #379                // String Teleport locations have been reloaded.
       931: invokevirtual #35                 // Method ext/mods/gameserver/model/actor/Player.sendMessage:(Ljava/lang/String;)V
       934: goto          969
       937: aload         4
       939: ldc_w         #381                // String zone
       942: invokevirtual #18                 // Method java/lang/String.startsWith:(Ljava/lang/String;)Z
       945: ifeq          964
       948: invokestatic  #383                // Method ext/mods/gameserver/data/manager/ZoneManager.getInstance:()Lext/mods/gameserver/data/manager/ZoneManager;
       951: invokevirtual #388                // Method ext/mods/gameserver/data/manager/ZoneManager.reload:()V
       954: aload_2
       955: ldc_w         #389                // String Zones have been reloaded.
       958: invokevirtual #35                 // Method ext/mods/gameserver/model/actor/Player.sendMessage:(Ljava/lang/String;)V
       961: goto          969
       964: aload_0
       965: aload_2
       966: invokevirtual #391                // Method sendUsage:(Lext/mods/gameserver/model/actor/Player;)V
       969: aload_3
       970: invokevirtual #397                // Method java/util/StringTokenizer.hasMoreTokens:()Z
       973: ifne          14
       976: goto          986
       979: astore        4
       981: aload_0
       982: aload_2
       983: invokevirtual #391                // Method sendUsage:(Lext/mods/gameserver/model/actor/Player;)V
       986: return
      Exception table:
         from    to  target type
           344   356   359   Class java/lang/Exception
           403   415   418   Class java/lang/Exception
            14   343   979   Class java/lang/Exception
           344   372   979   Class java/lang/Exception
           373   402   979   Class java/lang/Exception
           403   431   979   Class java/lang/Exception
           432   976   979   Class java/lang/Exception
      LineNumberTable:
        line 75: 0
        line 76: 9
        line 82: 14
        line 85: 20
        line 87: 30
        line 88: 36
        line 90: 45
        line 92: 55
        line 93: 61
        line 95: 70
        line 97: 80
        line 98: 86
        line 100: 95
        line 102: 105
        line 103: 111
        line 105: 120
        line 107: 130
        line 108: 136
        line 110: 145
        line 112: 155
        line 113: 161
        line 115: 170
        line 117: 180
        line 118: 183
        line 120: 192
        line 122: 202
        line 123: 208
        line 125: 217
        line 127: 227
        line 128: 233
        line 130: 242
        line 132: 252
        line 133: 258
        line 135: 267
        line 137: 277
        line 138: 283
        line 140: 292
        line 142: 302
        line 143: 308
        line 145: 317
        line 148: 327
        line 149: 332
        line 151: 337
        line 152: 343
        line 157: 344
        line 158: 350
        line 165: 356
        line 160: 359
        line 162: 361
        line 163: 367
        line 164: 372
        line 167: 373
        line 168: 376
        line 171: 386
        line 172: 391
        line 174: 396
        line 175: 402
        line 180: 403
        line 181: 409
        line 188: 415
        line 183: 418
        line 185: 420
        line 186: 426
        line 187: 431
        line 192: 432
        line 193: 435
        line 195: 445
        line 196: 451
        line 198: 460
        line 200: 470
        line 201: 476
        line 203: 485
        line 205: 495
        line 206: 501
        line 208: 510
        line 210: 520
        line 211: 526
        line 213: 535
        line 215: 545
        line 216: 551
        line 217: 557
        line 219: 566
        line 221: 576
        line 222: 582
        line 224: 591
        line 226: 601
        line 227: 607
        line 229: 617
        line 231: 628
        line 232: 634
        line 234: 644
        line 236: 655
        line 237: 661
        line 239: 671
        line 241: 682
        line 242: 688
        line 244: 698
        line 246: 709
        line 247: 715
        line 249: 725
        line 251: 736
        line 252: 742
        line 254: 752
        line 256: 763
        line 257: 769
        line 259: 779
        line 261: 790
        line 262: 796
        line 264: 806
        line 266: 817
        line 267: 823
        line 269: 833
        line 271: 844
        line 272: 850
        line 273: 856
        line 274: 862
        line 275: 868
        line 277: 877
        line 279: 888
        line 280: 894
        line 282: 904
        line 284: 915
        line 285: 921
        line 286: 927
        line 288: 937
        line 290: 948
        line 291: 954
        line 294: 964
        line 296: 969
        line 301: 976
        line 298: 979
        line 300: 981
        line 302: 986
      LocalVariableTable:
        Start  Length  Slot  Name   Signature
          361      12     6     e   Ljava/lang/Exception;
          332      41     5 RandomManagerIntance   Ljava/lang/Object;
          420      12     6     e   Ljava/lang/Exception;
          391      41     5 blobaldrops   Ljava/lang/Object;
           20     949     4  type   Ljava/lang/String;
          981       5     4     e   Ljava/lang/Exception;
            0     987     0  this   Lext/mods/gameserver/handler/admincommandhandlers/AdminReload;
            0     987     1 command   Ljava/lang/String;
            0     987     2 player   Lext/mods/gameserver/model/actor/Player;
            9     978     3    st   Ljava/util/StringTokenizer;
      StackMapTable: number_of_entries = 43
        frame_type = 252 /* append */
          offset_delta = 14
          locals = [ class java/util/StringTokenizer ]
        frame_type = 252 /* append */
          offset_delta = 30
          locals = [ class java/lang/String ]
        frame_type = 24 /* same */
        frame_type = 24 /* same */
        frame_type = 24 /* same */
        frame_type = 24 /* same */
        frame_type = 24 /* same */
        frame_type = 21 /* same */
        frame_type = 24 /* same */
        frame_type = 24 /* same */
        frame_type = 24 /* same */
        frame_type = 24 /* same */
        frame_type = 24 /* same */
        frame_type = 252 /* append */
          offset_delta = 26
          locals = [ class java/lang/Object ]
        frame_type = 78 /* same_locals_1_stack_item */
          stack = [ class java/lang/Exception ]
        frame_type = 250 /* chop */
          offset_delta = 13
        frame_type = 2 /* same */
        frame_type = 252 /* append */
          offset_delta = 26
          locals = [ class java/lang/Object ]
        frame_type = 78 /* same_locals_1_stack_item */
          stack = [ class java/lang/Exception ]
        frame_type = 250 /* chop */
          offset_delta = 13
        frame_type = 2 /* same */
        frame_type = 24 /* same */
        frame_type = 24 /* same */
        frame_type = 24 /* same */
        frame_type = 24 /* same */
        frame_type = 30 /* same */
        frame_type = 24 /* same */
        frame_type = 25 /* same */
        frame_type = 26 /* same */
        frame_type = 26 /* same */
        frame_type = 26 /* same */
        frame_type = 26 /* same */
        frame_type = 26 /* same */
        frame_type = 26 /* same */
        frame_type = 26 /* same */
        frame_type = 26 /* same */
        frame_type = 43 /* same */
        frame_type = 26 /* same */
        frame_type = 32 /* same */
        frame_type = 26 /* same */
        frame_type = 250 /* chop */
          offset_delta = 4
        frame_type = 73 /* same_locals_1_stack_item */
          stack = [ class java/lang/Exception ]
        frame_type = 6 /* same */

  public void sendUsage(ext.mods.gameserver.model.actor.Player);
    descriptor: (Lext/mods/gameserver/model/actor/Player;)V
    flags: (0x0001) ACC_PUBLIC
    Code:
      stack=2, locals=2, args_size=2
         0: aload_1
         1: ldc_w         #401                // String Usage : //reload <admin|announcement|auction|boat|buylist>
         4: invokevirtual #35                 // Method ext/mods/gameserver/model/actor/Player.sendMessage:(Ljava/lang/String;)V
         7: aload_1
         8: ldc_w         #403                // String Usage : //reload <capsule|config|crest|cw|donate|door>
        11: invokevirtual #35                 // Method ext/mods/gameserver/model/actor/Player.sendMessage:(Ljava/lang/String;)V
        14: aload_1
        15: ldc_w         #405                // String Usage : //reload <enchant|farm_event|global_drop|htm|item|mission>
        18: invokevirtual #35                 // Method ext/mods/gameserver/model/actor/Player.sendMessage:(Ljava/lang/String;)V
        21: aload_1
        22: ldc_w         #407                // String Usage : //reload <multisell|npc|npcwalker|observer|pccafe|poly>
        25: invokevirtual #35                 // Method ext/mods/gameserver/model/actor/Player.sendMessage:(Ljava/lang/String;)V
        28: aload_1
        29: ldc_w         #409                // String Usage : //reload <pvpdata|quests|restart|script|skins|skill>
        32: invokevirtual #35                 // Method ext/mods/gameserver/model/actor/Player.sendMessage:(Ljava/lang/String;)V
        35: aload_1
        36: ldc_w         #411                // String Usage : //reload <spawnlist|sysstring|teleport|zone>
        39: invokevirtual #35                 // Method ext/mods/gameserver/model/actor/Player.sendMessage:(Ljava/lang/String;)V
        42: return
      LineNumberTable:
        line 306: 0
        line 307: 7
        line 308: 14
        line 309: 21
        line 310: 28
        line 311: 35
        line 312: 42
      LocalVariableTable:
        Start  Length  Slot  Name   Signature
            0      43     0  this   Lext/mods/gameserver/handler/admincommandhandlers/AdminReload;
            0      43     1 player   Lext/mods/gameserver/model/actor/Player;

  public java.lang.String[] getAdminCommandList();
    descriptor: ()[Ljava/lang/String;
    flags: (0x0001) ACC_PUBLIC
    Code:
      stack=1, locals=1, args_size=1
         0: getstatic     #413                // Field ADMIN_COMMANDS:[Ljava/lang/String;
         3: areturn
      LineNumberTable:
        line 317: 0
      LocalVariableTable:
        Start  Length  Slot  Name   Signature
            0       4     0  this   Lext/mods/gameserver/handler/admincommandhandlers/AdminReload;

  static {};
    descriptor: ()V
    flags: (0x0008) ACC_STATIC
    Code:
      stack=4, locals=0, args_size=0
         0: new           #417                // class ext/mods/commons/logging/CLogger
         3: dup
         4: ldc_w         #392                // class ext/mods/gameserver/handler/admincommandhandlers/AdminReload
         7: invokevirtual #419                // Method java/lang/Class.getName:()Ljava/lang/String;
        10: invokespecial #424                // Method ext/mods/commons/logging/CLogger."<init>":(Ljava/lang/String;)V
        13: putstatic     #425                // Field LOGGER:Lext/mods/commons/logging/CLogger;
        16: iconst_1
        17: anewarray     #19                 // class java/lang/String
        20: dup
        21: iconst_0
        22: ldc_w         #429                // String admin_reload
        25: aastore
        26: putstatic     #413                // Field ADMIN_COMMANDS:[Ljava/lang/String;
        29: return
      LineNumberTable:
        line 66: 0
        line 67: 16
}
SourceFile: "AdminReload.java"
