// Bytecode for: ext.mods.gameserver.handler.admincommandhandlers.AdminEvent
// File: ext\mods\gameserver\handler\admincommandhandlers\AdminEvent.class

Classfile /c:/Users/User/Desktop/BrProject/bin/main/ext/mods/gameserver/handler/admincommandhandlers/AdminEvent.class
  Last modified 9 de jul de 2026; size 2497 bytes
  MD5 checksum 97249800cb5c5eb38df82bc0067a7639
  Compiled from "AdminEvent.java"
public class ext.mods.gameserver.handler.admincommandhandlers.AdminEvent implements ext.mods.gameserver.handler.IAdminCommandHandler
  minor version: 0
  major version: 69
  flags: (0x0021) ACC_PUBLIC, ACC_SUPER
  this_class: #35                         // ext/mods/gameserver/handler/admincommandhandlers/AdminEvent
  super_class: #2                         // java/lang/Object
  interfaces: 1, fields: 1, methods: 4, attributes: 1
Constant pool:
    #1 = Methodref          #2.#3         // java/lang/Object."<init>":()V
    #2 = Class              #4            // java/lang/Object
    #3 = NameAndType        #5:#6         // "<init>":()V
    #4 = Utf8               java/lang/Object
    #5 = Utf8               <init>
    #6 = Utf8               ()V
    #7 = String             #8            //
    #8 = Utf8
    #9 = Class              #10           // java/util/StringTokenizer
   #10 = Utf8               java/util/StringTokenizer
   #11 = String             #12           //
   #12 = Utf8
   #13 = Methodref          #9.#14        // java/util/StringTokenizer."<init>":(Ljava/lang/String;Ljava/lang/String;)V
   #14 = NameAndType        #5:#15        // "<init>":(Ljava/lang/String;Ljava/lang/String;)V
   #15 = Utf8               (Ljava/lang/String;Ljava/lang/String;)V
   #16 = Methodref          #9.#17        // java/util/StringTokenizer.nextToken:()Ljava/lang/String;
   #17 = NameAndType        #18:#19       // nextToken:()Ljava/lang/String;
   #18 = Utf8               nextToken
   #19 = Utf8               ()Ljava/lang/String;
   #20 = Methodref          #9.#21        // java/util/StringTokenizer.hasMoreTokens:()Z
   #21 = NameAndType        #22:#23       // hasMoreTokens:()Z
   #22 = Utf8               hasMoreTokens
   #23 = Utf8               ()Z
   #24 = String             #25           // admin_event_start
   #25 = Utf8               admin_event_start
   #26 = Methodref          #27.#28       // java/lang/String.startsWith:(Ljava/lang/String;)Z
   #27 = Class              #29           // java/lang/String
   #28 = NameAndType        #30:#31       // startsWith:(Ljava/lang/String;)Z
   #29 = Utf8               java/lang/String
   #30 = Utf8               startsWith
   #31 = Utf8               (Ljava/lang/String;)Z
   #32 = String             #33           // events/default.htm
   #33 = Utf8               events/default.htm
   #34 = Methodref          #35.#36       // ext/mods/gameserver/handler/admincommandhandlers/AdminEvent.sendFile:(Lext/mods/gameserver/model/actor/Player;Ljava/lang/String;)V
   #35 = Class              #37           // ext/mods/gameserver/handler/admincommandhandlers/AdminEvent
   #36 = NameAndType        #38:#39       // sendFile:(Lext/mods/gameserver/model/actor/Player;Ljava/lang/String;)V
   #37 = Utf8               ext/mods/gameserver/handler/admincommandhandlers/AdminEvent
   #38 = Utf8               sendFile
   #39 = Utf8               (Lext/mods/gameserver/model/actor/Player;Ljava/lang/String;)V
   #40 = Methodref          #41.#42       // ext/mods/gameserver/data/xml/ScriptData.getInstance:()Lext/mods/gameserver/data/xml/ScriptData;
   #41 = Class              #43           // ext/mods/gameserver/data/xml/ScriptData
   #42 = NameAndType        #44:#45       // getInstance:()Lext/mods/gameserver/data/xml/ScriptData;
   #43 = Utf8               ext/mods/gameserver/data/xml/ScriptData
   #44 = Utf8               getInstance
   #45 = Utf8               ()Lext/mods/gameserver/data/xml/ScriptData;
   #46 = Methodref          #41.#47       // ext/mods/gameserver/data/xml/ScriptData.getQuest:(Ljava/lang/String;)Lext/mods/gameserver/scripting/Quest;
   #47 = NameAndType        #48:#49       // getQuest:(Ljava/lang/String;)Lext/mods/gameserver/scripting/Quest;
   #48 = Utf8               getQuest
   #49 = Utf8               (Ljava/lang/String;)Lext/mods/gameserver/scripting/Quest;
   #50 = Class              #51           // ext/mods/gameserver/scripting/script/event/Events
   #51 = Utf8               ext/mods/gameserver/scripting/script/event/Events
   #52 = Methodref          #50.#53       // ext/mods/gameserver/scripting/script/event/Events.eventStart:(I)Z
   #53 = NameAndType        #54:#55       // eventStart:(I)Z
   #54 = Utf8               eventStart
   #55 = Utf8               (I)Z
   #56 = Methodref          #57.#58       // ext/mods/gameserver/model/actor/Player.getSysString:(I[Ljava/lang/Object;)Ljava/lang/String;
   #57 = Class              #59           // ext/mods/gameserver/model/actor/Player
   #58 = NameAndType        #60:#61       // getSysString:(I[Ljava/lang/Object;)Ljava/lang/String;
   #59 = Utf8               ext/mods/gameserver/model/actor/Player
   #60 = Utf8               getSysString
   #61 = Utf8               (I[Ljava/lang/Object;)Ljava/lang/String;
   #62 = Methodref          #57.#63       // ext/mods/gameserver/model/actor/Player.sendMessage:(Ljava/lang/String;)V
   #63 = NameAndType        #64:#65       // sendMessage:(Ljava/lang/String;)V
   #64 = Utf8               sendMessage
   #65 = Utf8               (Ljava/lang/String;)V
   #66 = Class              #67           // java/lang/Exception
   #67 = Utf8               java/lang/Exception
   #68 = String             #69           // : //event_start <eventname>
   #69 = Utf8               : //event_start <eventname>
   #70 = String             #71           // admin_event_stop
   #71 = Utf8               admin_event_stop
   #72 = Methodref          #50.#73       // ext/mods/gameserver/scripting/script/event/Events.eventStop:()Z
   #73 = NameAndType        #74:#23       // eventStop:()Z
   #74 = Utf8               eventStop
   #75 = Fieldref           #35.#76       // ext/mods/gameserver/handler/admincommandhandlers/AdminEvent.ADMIN_COMMANDS:[Ljava/lang/String;
   #76 = NameAndType        #77:#78       // ADMIN_COMMANDS:[Ljava/lang/String;
   #77 = Utf8               ADMIN_COMMANDS
   #78 = Utf8               [Ljava/lang/String;
   #79 = Class              #80           // ext/mods/gameserver/handler/IAdminCommandHandler
   #80 = Utf8               ext/mods/gameserver/handler/IAdminCommandHandler
   #81 = Utf8               Code
   #82 = Utf8               LineNumberTable
   #83 = Utf8               LocalVariableTable
   #84 = Utf8               this
   #85 = Utf8               Lext/mods/gameserver/handler/admincommandhandlers/AdminEvent;
   #86 = Utf8               useAdminCommand
   #87 = Utf8               (Ljava/lang/String;Lext/mods/gameserver/model/actor/Player;)V
   #88 = Utf8               event
   #89 = Utf8               Lext/mods/gameserver/scripting/script/event/Events;
   #90 = Utf8               e
   #91 = Utf8               Ljava/lang/Exception;
   #92 = Utf8               command
   #93 = Utf8               Ljava/lang/String;
   #94 = Utf8               player
   #95 = Utf8               Lext/mods/gameserver/model/actor/Player;
   #96 = Utf8               eventName
   #97 = Utf8               st
   #98 = Utf8               Ljava/util/StringTokenizer;
   #99 = Utf8               StackMapTable
  #100 = Utf8               getAdminCommandList
  #101 = Utf8               ()[Ljava/lang/String;
  #102 = Utf8               <clinit>
  #103 = Utf8               SourceFile
  #104 = Utf8               AdminEvent.java
{
  public ext.mods.gameserver.handler.admincommandhandlers.AdminEvent();
    descriptor: ()V
    flags: (0x0001) ACC_PUBLIC
    Code:
      stack=1, locals=1, args_size=1
         0: aload_0
         1: invokespecial #1                  // Method java/lang/Object."<init>":()V
         4: return
      LineNumberTable:
        line 27: 0
      LocalVariableTable:
        Start  Length  Slot  Name   Signature
            0       5     0  this   Lext/mods/gameserver/handler/admincommandhandlers/AdminEvent;

  public void useAdminCommand(java.lang.String, ext.mods.gameserver.model.actor.Player);
    descriptor: (Ljava/lang/String;Lext/mods/gameserver/model/actor/Player;)V
    flags: (0x0001) ACC_PUBLIC
    Code:
      stack=7, locals=6, args_size=3
         0: ldc           #7                  // String
         2: astore_3
         3: new           #9                  // class java/util/StringTokenizer
         6: dup
         7: aload_1
         8: ldc           #11                 // String
        10: invokespecial #13                 // Method java/util/StringTokenizer."<init>":(Ljava/lang/String;Ljava/lang/String;)V
        13: astore        4
        15: aload         4
        17: invokevirtual #16                 // Method java/util/StringTokenizer.nextToken:()Ljava/lang/String;
        20: pop
        21: aload         4
        23: invokevirtual #20                 // Method java/util/StringTokenizer.hasMoreTokens:()Z
        26: ifeq          35
        29: aload         4
        31: invokevirtual #16                 // Method java/util/StringTokenizer.nextToken:()Ljava/lang/String;
        34: astore_3
        35: aload_1
        36: ldc           #24                 // String admin_event_start
        38: invokevirtual #26                 // Method java/lang/String.startsWith:(Ljava/lang/String;)Z
        41: ifeq          156
        44: aload_0
        45: aload_2
        46: ldc           #32                 // String events/default.htm
        48: invokevirtual #34                 // Method sendFile:(Lext/mods/gameserver/model/actor/Player;Ljava/lang/String;)V
        51: aload_3
        52: ifnull        121
        55: invokestatic  #40                 // Method ext/mods/gameserver/data/xml/ScriptData.getInstance:()Lext/mods/gameserver/data/xml/ScriptData;
        58: aload_3
        59: invokevirtual #46                 // Method ext/mods/gameserver/data/xml/ScriptData.getQuest:(Ljava/lang/String;)Lext/mods/gameserver/scripting/Quest;
        62: checkcast     #50                 // class ext/mods/gameserver/scripting/script/event/Events
        65: astore        5
        67: aload         5
        69: ifnull        121
        72: aload         5
        74: iconst_1
        75: invokevirtual #52                 // Method ext/mods/gameserver/scripting/script/event/Events.eventStart:(I)Z
        78: ifeq          101
        81: aload_2
        82: aload_2
        83: sipush        10116
        86: iconst_1
        87: anewarray     #2                  // class java/lang/Object
        90: dup
        91: iconst_0
        92: aload_3
        93: aastore
        94: invokevirtual #56                 // Method ext/mods/gameserver/model/actor/Player.getSysString:(I[Ljava/lang/Object;)Ljava/lang/String;
        97: invokevirtual #62                 // Method ext/mods/gameserver/model/actor/Player.sendMessage:(Ljava/lang/String;)V
       100: return
       101: aload_2
       102: aload_2
       103: sipush        10117
       106: iconst_1
       107: anewarray     #2                  // class java/lang/Object
       110: dup
       111: iconst_0
       112: aload_3
       113: aastore
       114: invokevirtual #56                 // Method ext/mods/gameserver/model/actor/Player.getSysString:(I[Ljava/lang/Object;)Ljava/lang/String;
       117: invokevirtual #62                 // Method ext/mods/gameserver/model/actor/Player.sendMessage:(Ljava/lang/String;)V
       120: return
       121: goto          273
       124: astore        5
       126: aload_2
       127: aload_2
       128: sipush        10120
       131: iconst_1
       132: anewarray     #2                  // class java/lang/Object
       135: dup
       136: iconst_0
       137: ldc           #68                 // String : //event_start <eventname>
       139: aastore
       140: invokevirtual #56                 // Method ext/mods/gameserver/model/actor/Player.getSysString:(I[Ljava/lang/Object;)Ljava/lang/String;
       143: invokevirtual #62                 // Method ext/mods/gameserver/model/actor/Player.sendMessage:(Ljava/lang/String;)V
       146: aload_0
       147: aload_2
       148: ldc           #32                 // String events/default.htm
       150: invokevirtual #34                 // Method sendFile:(Lext/mods/gameserver/model/actor/Player;Ljava/lang/String;)V
       153: goto          273
       156: aload_1
       157: ldc           #70                 // String admin_event_stop
       159: invokevirtual #26                 // Method java/lang/String.startsWith:(Ljava/lang/String;)Z
       162: ifeq          273
       165: aload_0
       166: aload_2
       167: ldc           #32                 // String events/default.htm
       169: invokevirtual #34                 // Method sendFile:(Lext/mods/gameserver/model/actor/Player;Ljava/lang/String;)V
       172: aload_3
       173: ifnull        241
       176: invokestatic  #40                 // Method ext/mods/gameserver/data/xml/ScriptData.getInstance:()Lext/mods/gameserver/data/xml/ScriptData;
       179: aload_3
       180: invokevirtual #46                 // Method ext/mods/gameserver/data/xml/ScriptData.getQuest:(Ljava/lang/String;)Lext/mods/gameserver/scripting/Quest;
       183: checkcast     #50                 // class ext/mods/gameserver/scripting/script/event/Events
       186: astore        5
       188: aload         5
       190: ifnull        241
       193: aload         5
       195: invokevirtual #72                 // Method ext/mods/gameserver/scripting/script/event/Events.eventStop:()Z
       198: ifeq          221
       201: aload_2
       202: aload_2
       203: sipush        10118
       206: iconst_1
       207: anewarray     #2                  // class java/lang/Object
       210: dup
       211: iconst_0
       212: aload_3
       213: aastore
       214: invokevirtual #56                 // Method ext/mods/gameserver/model/actor/Player.getSysString:(I[Ljava/lang/Object;)Ljava/lang/String;
       217: invokevirtual #62                 // Method ext/mods/gameserver/model/actor/Player.sendMessage:(Ljava/lang/String;)V
       220: return
       221: aload_2
       222: aload_2
       223: sipush        10119
       226: iconst_1
       227: anewarray     #2                  // class java/lang/Object
       230: dup
       231: iconst_0
       232: aload_3
       233: aastore
       234: invokevirtual #56                 // Method ext/mods/gameserver/model/actor/Player.getSysString:(I[Ljava/lang/Object;)Ljava/lang/String;
       237: invokevirtual #62                 // Method ext/mods/gameserver/model/actor/Player.sendMessage:(Ljava/lang/String;)V
       240: return
       241: goto          273
       244: astore        5
       246: aload_2
       247: aload_2
       248: sipush        10120
       251: iconst_1
       252: anewarray     #2                  // class java/lang/Object
       255: dup
       256: iconst_0
       257: ldc           #68                 // String : //event_start <eventname>
       259: aastore
       260: invokevirtual #56                 // Method ext/mods/gameserver/model/actor/Player.getSysString:(I[Ljava/lang/Object;)Ljava/lang/String;
       263: invokevirtual #62                 // Method ext/mods/gameserver/model/actor/Player.sendMessage:(Ljava/lang/String;)V
       266: aload_0
       267: aload_2
       268: ldc           #32                 // String events/default.htm
       270: invokevirtual #34                 // Method sendFile:(Lext/mods/gameserver/model/actor/Player;Ljava/lang/String;)V
       273: return
      Exception table:
         from    to  target type
            51   100   124   Class java/lang/Exception
           101   120   124   Class java/lang/Exception
           165   220   244   Class java/lang/Exception
           221   240   244   Class java/lang/Exception
      LineNumberTable:
        line 38: 0
        line 39: 3
        line 40: 15
        line 42: 21
        line 43: 29
        line 45: 35
        line 47: 44
        line 50: 51
        line 52: 55
        line 53: 67
        line 55: 72
        line 57: 81
        line 58: 100
        line 61: 101
        line 62: 120
        line 70: 121
        line 66: 124
        line 68: 126
        line 69: 146
        line 70: 153
        line 72: 156
        line 76: 165
        line 77: 172
        line 79: 176
        line 80: 188
        line 82: 193
        line 84: 201
        line 85: 220
        line 87: 221
        line 88: 240
        line 96: 241
        line 92: 244
        line 94: 246
        line 95: 266
        line 99: 273
      LocalVariableTable:
        Start  Length  Slot  Name   Signature
           67      54     5 event   Lext/mods/gameserver/scripting/script/event/Events;
          126      27     5     e   Ljava/lang/Exception;
          188      53     5 event   Lext/mods/gameserver/scripting/script/event/Events;
          246      27     5     e   Ljava/lang/Exception;
            0     274     0  this   Lext/mods/gameserver/handler/admincommandhandlers/AdminEvent;
            0     274     1 command   Ljava/lang/String;
            0     274     2 player   Lext/mods/gameserver/model/actor/Player;
            3     271     3 eventName   Ljava/lang/String;
           15     259     4    st   Ljava/util/StringTokenizer;
      StackMapTable: number_of_entries = 9
        frame_type = 253 /* append */
          offset_delta = 35
          locals = [ class java/lang/String, class java/util/StringTokenizer ]
        frame_type = 252 /* append */
          offset_delta = 65
          locals = [ class ext/mods/gameserver/scripting/script/event/Events ]
        frame_type = 250 /* chop */
          offset_delta = 19
        frame_type = 66 /* same_locals_1_stack_item */
          stack = [ class java/lang/Exception ]
        frame_type = 31 /* same */
        frame_type = 252 /* append */
          offset_delta = 64
          locals = [ class ext/mods/gameserver/scripting/script/event/Events ]
        frame_type = 250 /* chop */
          offset_delta = 19
        frame_type = 66 /* same_locals_1_stack_item */
          stack = [ class java/lang/Exception ]
        frame_type = 28 /* same */

  public java.lang.String[] getAdminCommandList();
    descriptor: ()[Ljava/lang/String;
    flags: (0x0001) ACC_PUBLIC
    Code:
      stack=1, locals=1, args_size=1
         0: getstatic     #75                 // Field ADMIN_COMMANDS:[Ljava/lang/String;
         3: areturn
      LineNumberTable:
        line 105: 0
      LocalVariableTable:
        Start  Length  Slot  Name   Signature
            0       4     0  this   Lext/mods/gameserver/handler/admincommandhandlers/AdminEvent;

  static {};
    descriptor: ()V
    flags: (0x0008) ACC_STATIC
    Code:
      stack=4, locals=0, args_size=0
         0: iconst_2
         1: anewarray     #27                 // class java/lang/String
         4: dup
         5: iconst_0
         6: ldc           #24                 // String admin_event_start
         8: aastore
         9: dup
        10: iconst_1
        11: ldc           #70                 // String admin_event_stop
        13: aastore
        14: putstatic     #75                 // Field ADMIN_COMMANDS:[Ljava/lang/String;
        17: return
      LineNumberTable:
        line 29: 0
}
SourceFile: "AdminEvent.java"
