// Bytecode for: ext.mods.gameserver.handler.admincommandhandlers.AdminPledge
// File: ext\mods\gameserver\handler\admincommandhandlers\AdminPledge.class

Classfile /c:/Users/User/Desktop/BrProject/bin/main/ext/mods/gameserver/handler/admincommandhandlers/AdminPledge.class
  Last modified 9 de jul de 2026; size 5930 bytes
  MD5 checksum ef589e634ed287f88560037aadb56510
  Compiled from "AdminPledge.java"
public class ext.mods.gameserver.handler.admincommandhandlers.AdminPledge implements ext.mods.gameserver.handler.IAdminCommandHandler
  minor version: 0
  major version: 69
  flags: (0x0021) ACC_PUBLIC, ACC_SUPER
  this_class: #8                          // ext/mods/gameserver/handler/admincommandhandlers/AdminPledge
  super_class: #2                         // java/lang/Object
  interfaces: 1, fields: 1, methods: 4, attributes: 3
Constant pool:
    #1 = Methodref          #2.#3         // java/lang/Object."<init>":()V
    #2 = Class              #4            // java/lang/Object
    #3 = NameAndType        #5:#6         // "<init>":()V
    #4 = Utf8               java/lang/Object
    #5 = Utf8               <init>
    #6 = Utf8               ()V
    #7 = Methodref          #8.#9         // ext/mods/gameserver/handler/admincommandhandlers/AdminPledge.getTargetPlayer:(Lext/mods/gameserver/model/actor/Player;Z)Lext/mods/gameserver/model/actor/Player;
    #8 = Class              #10           // ext/mods/gameserver/handler/admincommandhandlers/AdminPledge
    #9 = NameAndType        #11:#12       // getTargetPlayer:(Lext/mods/gameserver/model/actor/Player;Z)Lext/mods/gameserver/model/actor/Player;
   #10 = Utf8               ext/mods/gameserver/handler/admincommandhandlers/AdminPledge
   #11 = Utf8               getTargetPlayer
   #12 = Utf8               (Lext/mods/gameserver/model/actor/Player;Z)Lext/mods/gameserver/model/actor/Player;
   #13 = String             #14           // admin_pledge
   #14 = Utf8               admin_pledge
   #15 = Methodref          #16.#17       // java/lang/String.startsWith:(Ljava/lang/String;)Z
   #16 = Class              #18           // java/lang/String
   #17 = NameAndType        #19:#20       // startsWith:(Ljava/lang/String;)Z
   #18 = Utf8               java/lang/String
   #19 = Utf8               startsWith
   #20 = Utf8               (Ljava/lang/String;)Z
   #21 = Class              #22           // java/util/StringTokenizer
   #22 = Utf8               java/util/StringTokenizer
   #23 = String             #24           //
   #24 = Utf8
   #25 = Methodref          #21.#26       // java/util/StringTokenizer."<init>":(Ljava/lang/String;Ljava/lang/String;)V
   #26 = NameAndType        #5:#27        // "<init>":(Ljava/lang/String;Ljava/lang/String;)V
   #27 = Utf8               (Ljava/lang/String;Ljava/lang/String;)V
   #28 = Methodref          #21.#29       // java/util/StringTokenizer.nextToken:()Ljava/lang/String;
   #29 = NameAndType        #30:#31       // nextToken:()Ljava/lang/String;
   #30 = Utf8               nextToken
   #31 = Utf8               ()Ljava/lang/String;
   #32 = String             #33           // create
   #33 = Utf8               create
   #34 = Methodref          #16.#35       // java/lang/String.equals:(Ljava/lang/Object;)Z
   #35 = NameAndType        #36:#37       // equals:(Ljava/lang/Object;)Z
   #36 = Utf8               equals
   #37 = Utf8               (Ljava/lang/Object;)Z
   #38 = Methodref          #39.#40       // ext/mods/gameserver/model/actor/Player.getClanCreateExpiryTime:()J
   #39 = Class              #41           // ext/mods/gameserver/model/actor/Player
   #40 = NameAndType        #42:#43       // getClanCreateExpiryTime:()J
   #41 = Utf8               ext/mods/gameserver/model/actor/Player
   #42 = Utf8               getClanCreateExpiryTime
   #43 = Utf8               ()J
   #44 = Methodref          #39.#45       // ext/mods/gameserver/model/actor/Player.setClanCreateExpiryTime:(J)V
   #45 = NameAndType        #46:#47       // setClanCreateExpiryTime:(J)V
   #46 = Utf8               setClanCreateExpiryTime
   #47 = Utf8               (J)V
   #48 = Methodref          #49.#50       // ext/mods/gameserver/data/sql/ClanTable.getInstance:()Lext/mods/gameserver/data/sql/ClanTable;
   #49 = Class              #51           // ext/mods/gameserver/data/sql/ClanTable
   #50 = NameAndType        #52:#53       // getInstance:()Lext/mods/gameserver/data/sql/ClanTable;
   #51 = Utf8               ext/mods/gameserver/data/sql/ClanTable
   #52 = Utf8               getInstance
   #53 = Utf8               ()Lext/mods/gameserver/data/sql/ClanTable;
   #54 = Methodref          #49.#55       // ext/mods/gameserver/data/sql/ClanTable.createClan:(Lext/mods/gameserver/model/actor/Player;Ljava/lang/String;)Lext/mods/gameserver/model/pledge/Clan;
   #55 = NameAndType        #56:#57       // createClan:(Lext/mods/gameserver/model/actor/Player;Ljava/lang/String;)Lext/mods/gameserver/model/pledge/Clan;
   #56 = Utf8               createClan
   #57 = Utf8               (Lext/mods/gameserver/model/actor/Player;Ljava/lang/String;)Lext/mods/gameserver/model/pledge/Clan;
   #58 = Methodref          #39.#59       // ext/mods/gameserver/model/actor/Player.getName:()Ljava/lang/String;
   #59 = NameAndType        #60:#31       // getName:()Ljava/lang/String;
   #60 = Utf8               getName
   #61 = InvokeDynamic      #0:#62        // #0:makeConcatWithConstants:(Ljava/lang/String;Ljava/lang/String;)Ljava/lang/String;
   #62 = NameAndType        #63:#64       // makeConcatWithConstants:(Ljava/lang/String;Ljava/lang/String;)Ljava/lang/String;
   #63 = Utf8               makeConcatWithConstants
   #64 = Utf8               (Ljava/lang/String;Ljava/lang/String;)Ljava/lang/String;
   #65 = Methodref          #39.#66       // ext/mods/gameserver/model/actor/Player.sendMessage:(Ljava/lang/String;)V
   #66 = NameAndType        #67:#68       // sendMessage:(Ljava/lang/String;)V
   #67 = Utf8               sendMessage
   #68 = Utf8               (Ljava/lang/String;)V
   #69 = String             #70           // There was a problem while creating the clan.
   #70 = Utf8               There was a problem while creating the clan.
   #71 = Class              #72           // java/lang/Exception
   #72 = Utf8               java/lang/Exception
   #73 = String             #74           // Invalid string parameter for //pledge create.
   #74 = Utf8               Invalid string parameter for //pledge create.
   #75 = Methodref          #39.#76       // ext/mods/gameserver/model/actor/Player.getClan:()Lext/mods/gameserver/model/pledge/Clan;
   #76 = NameAndType        #77:#78       // getClan:()Lext/mods/gameserver/model/pledge/Clan;
   #77 = Utf8               getClan
   #78 = Utf8               ()Lext/mods/gameserver/model/pledge/Clan;
   #79 = Fieldref           #80.#81       // ext/mods/gameserver/network/SystemMessageId.TARGET_MUST_BE_IN_CLAN:Lext/mods/gameserver/network/SystemMessageId;
   #80 = Class              #82           // ext/mods/gameserver/network/SystemMessageId
   #81 = NameAndType        #83:#84       // TARGET_MUST_BE_IN_CLAN:Lext/mods/gameserver/network/SystemMessageId;
   #82 = Utf8               ext/mods/gameserver/network/SystemMessageId
   #83 = Utf8               TARGET_MUST_BE_IN_CLAN
   #84 = Utf8               Lext/mods/gameserver/network/SystemMessageId;
   #85 = Methodref          #39.#86       // ext/mods/gameserver/model/actor/Player.sendPacket:(Lext/mods/gameserver/network/SystemMessageId;)V
   #86 = NameAndType        #87:#88       // sendPacket:(Lext/mods/gameserver/network/SystemMessageId;)V
   #87 = Utf8               sendPacket
   #88 = Utf8               (Lext/mods/gameserver/network/SystemMessageId;)V
   #89 = String             #90           // game_menu.htm
   #90 = Utf8               game_menu.htm
   #91 = Methodref          #8.#92        // ext/mods/gameserver/handler/admincommandhandlers/AdminPledge.sendFile:(Lext/mods/gameserver/model/actor/Player;Ljava/lang/String;)V
   #92 = NameAndType        #93:#94       // sendFile:(Lext/mods/gameserver/model/actor/Player;Ljava/lang/String;)V
   #93 = Utf8               sendFile
   #94 = Utf8               (Lext/mods/gameserver/model/actor/Player;Ljava/lang/String;)V
   #95 = String             #96           // dismiss
   #96 = Utf8               dismiss
   #97 = Methodref          #49.#98       // ext/mods/gameserver/data/sql/ClanTable.destroyClan:(Lext/mods/gameserver/model/pledge/Clan;)V
   #98 = NameAndType        #99:#100      // destroyClan:(Lext/mods/gameserver/model/pledge/Clan;)V
   #99 = Utf8               destroyClan
  #100 = Utf8               (Lext/mods/gameserver/model/pledge/Clan;)V
  #101 = String             #102          // The clan is now disbanded.
  #102 = Utf8               The clan is now disbanded.
  #103 = String             #104          // info
  #104 = Utf8               info
  #105 = Class              #106          // ext/mods/gameserver/network/serverpackets/GMViewPledgeInfo
  #106 = Utf8               ext/mods/gameserver/network/serverpackets/GMViewPledgeInfo
  #107 = Methodref          #105.#108     // ext/mods/gameserver/network/serverpackets/GMViewPledgeInfo."<init>":(Lext/mods/gameserver/model/pledge/Clan;Lext/mods/gameserver/model/actor/Player;)V
  #108 = NameAndType        #5:#109       // "<init>":(Lext/mods/gameserver/model/pledge/Clan;Lext/mods/gameserver/model/actor/Player;)V
  #109 = Utf8               (Lext/mods/gameserver/model/pledge/Clan;Lext/mods/gameserver/model/actor/Player;)V
  #110 = Methodref          #39.#111      // ext/mods/gameserver/model/actor/Player.sendPacket:(Lext/mods/gameserver/network/serverpackets/L2GameServerPacket;)V
  #111 = NameAndType        #87:#112      // sendPacket:(Lext/mods/gameserver/network/serverpackets/L2GameServerPacket;)V
  #112 = Utf8               (Lext/mods/gameserver/network/serverpackets/L2GameServerPacket;)V
  #113 = String             #114          // level
  #114 = Utf8               level
  #115 = Methodref          #116.#117     // java/lang/Integer.parseInt:(Ljava/lang/String;)I
  #116 = Class              #118          // java/lang/Integer
  #117 = NameAndType        #119:#120     // parseInt:(Ljava/lang/String;)I
  #118 = Utf8               java/lang/Integer
  #119 = Utf8               parseInt
  #120 = Utf8               (Ljava/lang/String;)I
  #121 = Methodref          #122.#123     // ext/mods/gameserver/model/pledge/Clan.changeLevel:(I)V
  #122 = Class              #124          // ext/mods/gameserver/model/pledge/Clan
  #123 = NameAndType        #125:#126     // changeLevel:(I)V
  #124 = Utf8               ext/mods/gameserver/model/pledge/Clan
  #125 = Utf8               changeLevel
  #126 = Utf8               (I)V
  #127 = Methodref          #122.#59      // ext/mods/gameserver/model/pledge/Clan.getName:()Ljava/lang/String;
  #128 = InvokeDynamic      #1:#129       // #1:makeConcatWithConstants:(Ljava/lang/String;I)Ljava/lang/String;
  #129 = NameAndType        #63:#130      // makeConcatWithConstants:(Ljava/lang/String;I)Ljava/lang/String;
  #130 = Utf8               (Ljava/lang/String;I)Ljava/lang/String;
  #131 = String             #132          // This clan level is incorrect. Put a number between 0 and 8.
  #132 = Utf8               This clan level is incorrect. Put a number between 0 and 8.
  #133 = String             #134          // Invalid number parameter for //pledge setlevel.
  #134 = Utf8               Invalid number parameter for //pledge setlevel.
  #135 = String             #136          // rep
  #136 = Utf8               rep
  #137 = Methodref          #122.#138     // ext/mods/gameserver/model/pledge/Clan.getLevel:()I
  #138 = NameAndType        #139:#140     // getLevel:()I
  #139 = Utf8               getLevel
  #140 = Utf8               ()I
  #141 = String             #142          // Only clans of level 5 or above may receive reputation points.
  #142 = Utf8               Only clans of level 5 or above may receive reputation points.
  #143 = Methodref          #122.#144     // ext/mods/gameserver/model/pledge/Clan.addReputationScore:(I)Z
  #144 = NameAndType        #145:#146     // addReputationScore:(I)Z
  #145 = Utf8               addReputationScore
  #146 = Utf8               (I)Z
  #147 = String             #148          // added
  #148 = Utf8               added
  #149 = String             #150          // removed
  #150 = Utf8               removed
  #151 = Methodref          #152.#153     // java/lang/Math.abs:(I)I
  #152 = Class              #154          // java/lang/Math
  #153 = NameAndType        #155:#156     // abs:(I)I
  #154 = Utf8               java/lang/Math
  #155 = Utf8               abs
  #156 = Utf8               (I)I
  #157 = String             #158          // to
  #158 = Utf8               to
  #159 = String             #160          // from
  #160 = Utf8               from
  #161 = Methodref          #122.#162     // ext/mods/gameserver/model/pledge/Clan.getReputationScore:()I
  #162 = NameAndType        #163:#140     // getReputationScore:()I
  #163 = Utf8               getReputationScore
  #164 = InvokeDynamic      #2:#165       // #2:makeConcatWithConstants:(Ljava/lang/String;ILjava/lang/String;Ljava/lang/String;I)Ljava/lang/String;
  #165 = NameAndType        #63:#166      // makeConcatWithConstants:(Ljava/lang/String;ILjava/lang/String;Ljava/lang/String;I)Ljava/lang/String;
  #166 = Utf8               (Ljava/lang/String;ILjava/lang/String;Ljava/lang/String;I)Ljava/lang/String;
  #167 = String             #168          // Invalid number parameter for //pledge rep.
  #168 = Utf8               Invalid number parameter for //pledge rep.
  #169 = String             #170          // transfer
  #170 = Utf8               transfer
  #171 = Methodref          #39.#172      // ext/mods/gameserver/model/actor/Player.getObjectId:()I
  #172 = NameAndType        #173:#140     // getObjectId:()I
  #173 = Utf8               getObjectId
  #174 = Methodref          #122.#175     // ext/mods/gameserver/model/pledge/Clan.getClanMember:(I)Lext/mods/gameserver/model/pledge/ClanMember;
  #175 = NameAndType        #176:#177     // getClanMember:(I)Lext/mods/gameserver/model/pledge/ClanMember;
  #176 = Utf8               getClanMember
  #177 = Utf8               (I)Lext/mods/gameserver/model/pledge/ClanMember;
  #178 = InvokeDynamic      #3:#62        // #3:makeConcatWithConstants:(Ljava/lang/String;Ljava/lang/String;)Ljava/lang/String;
  #179 = Methodref          #122.#180     // ext/mods/gameserver/model/pledge/Clan.getLeader:()Lext/mods/gameserver/model/pledge/ClanMember;
  #180 = NameAndType        #181:#182     // getLeader:()Lext/mods/gameserver/model/pledge/ClanMember;
  #181 = Utf8               getLeader
  #182 = Utf8               ()Lext/mods/gameserver/model/pledge/ClanMember;
  #183 = InvokeDynamic      #4:#62        // #4:makeConcatWithConstants:(Ljava/lang/String;Ljava/lang/String;)Ljava/lang/String;
  #184 = Methodref          #122.#185     // ext/mods/gameserver/model/pledge/Clan.setNewLeader:(Lext/mods/gameserver/model/pledge/ClanMember;)V
  #185 = NameAndType        #186:#187     // setNewLeader:(Lext/mods/gameserver/model/pledge/ClanMember;)V
  #186 = Utf8               setNewLeader
  #187 = Utf8               (Lext/mods/gameserver/model/pledge/ClanMember;)V
  #188 = Methodref          #189.#59      // ext/mods/gameserver/model/pledge/ClanMember.getName:()Ljava/lang/String;
  #189 = Class              #190          // ext/mods/gameserver/model/pledge/ClanMember
  #190 = Utf8               ext/mods/gameserver/model/pledge/ClanMember
  #191 = InvokeDynamic      #5:#62        // #5:makeConcatWithConstants:(Ljava/lang/String;Ljava/lang/String;)Ljava/lang/String;
  #192 = String             #193          // Usage: //pledge create|dismiss|info|level|rep|transfer
  #193 = Utf8               Usage: //pledge create|dismiss|info|level|rep|transfer
  #194 = Fieldref           #8.#195       // ext/mods/gameserver/handler/admincommandhandlers/AdminPledge.ADMIN_COMMANDS:[Ljava/lang/String;
  #195 = NameAndType        #196:#197     // ADMIN_COMMANDS:[Ljava/lang/String;
  #196 = Utf8               ADMIN_COMMANDS
  #197 = Utf8               [Ljava/lang/String;
  #198 = Class              #199          // ext/mods/gameserver/handler/IAdminCommandHandler
  #199 = Utf8               ext/mods/gameserver/handler/IAdminCommandHandler
  #200 = Utf8               Code
  #201 = Utf8               LineNumberTable
  #202 = Utf8               LocalVariableTable
  #203 = Utf8               this
  #204 = Utf8               Lext/mods/gameserver/handler/admincommandhandlers/AdminPledge;
  #205 = Utf8               useAdminCommand
  #206 = Utf8               (Ljava/lang/String;Lext/mods/gameserver/model/actor/Player;)V
  #207 = Utf8               parameter
  #208 = Utf8               Ljava/lang/String;
  #209 = Utf8               cet
  #210 = Utf8               J
  #211 = Utf8               clan
  #212 = Utf8               Lext/mods/gameserver/model/pledge/Clan;
  #213 = Utf8               e
  #214 = Utf8               Ljava/lang/Exception;
  #215 = Utf8               I
  #216 = Utf8               points
  #217 = Utf8               member
  #218 = Utf8               Lext/mods/gameserver/model/pledge/ClanMember;
  #219 = Utf8               targetClan
  #220 = Utf8               action
  #221 = Utf8               st
  #222 = Utf8               Ljava/util/StringTokenizer;
  #223 = Utf8               command
  #224 = Utf8               player
  #225 = Utf8               Lext/mods/gameserver/model/actor/Player;
  #226 = Utf8               targetPlayer
  #227 = Utf8               StackMapTable
  #228 = Utf8               getAdminCommandList
  #229 = Utf8               ()[Ljava/lang/String;
  #230 = Utf8               <clinit>
  #231 = Utf8               SourceFile
  #232 = Utf8               AdminPledge.java
  #233 = Utf8               BootstrapMethods
  #234 = String             #235          // Clan \u0001 have been created. Clan leader is \u0001.
  #235 = Utf8               Clan \u0001 have been created. Clan leader is \u0001.
  #236 = String             #237          // You have set clan \u0001 to level \u0001
  #237 = Utf8               You have set clan \u0001 to level \u0001
  #238 = String             #239          // You \u0001\u0001 points \u0001\u0001\'s reputation. Their current score is: \u0001
  #239 = Utf8               You \u0001\u0001 points \u0001\u0001\'s reputation. Their current score is: \u0001
  #240 = String             #241          // \u0001 can\'t be set as the new Clan leader of \u0001.
  #241 = Utf8               \u0001 can\'t be set as the new Clan leader of \u0001.
  #242 = String             #243          // \u0001 is already the Clan leader of \u0001.
  #243 = Utf8               \u0001 is already the Clan leader of \u0001.
  #244 = String             #245          // You set \u0001 as the new Clan leader of \u0001.
  #245 = Utf8               You set \u0001 as the new Clan leader of \u0001.
  #246 = MethodHandle       6:#247        // REF_invokeStatic java/lang/invoke/StringConcatFactory.makeConcatWithConstants:(Ljava/lang/invoke/MethodHandles$Lookup;Ljava/lang/String;Ljava/lang/invoke/MethodType;Ljava/lang/String;[Ljava/lang/Object;)Ljava/lang/invoke/CallSite;
  #247 = Methodref          #248.#249     // java/lang/invoke/StringConcatFactory.makeConcatWithConstants:(Ljava/lang/invoke/MethodHandles$Lookup;Ljava/lang/String;Ljava/lang/invoke/MethodType;Ljava/lang/String;[Ljava/lang/Object;)Ljava/lang/invoke/CallSite;
  #248 = Class              #250          // java/lang/invoke/StringConcatFactory
  #249 = NameAndType        #63:#251      // makeConcatWithConstants:(Ljava/lang/invoke/MethodHandles$Lookup;Ljava/lang/String;Ljava/lang/invoke/MethodType;Ljava/lang/String;[Ljava/lang/Object;)Ljava/lang/invoke/CallSite;
  #250 = Utf8               java/lang/invoke/StringConcatFactory
  #251 = Utf8               (Ljava/lang/invoke/MethodHandles$Lookup;Ljava/lang/String;Ljava/lang/invoke/MethodType;Ljava/lang/String;[Ljava/lang/Object;)Ljava/lang/invoke/CallSite;
  #252 = Utf8               InnerClasses
  #253 = Class              #254          // java/lang/invoke/MethodHandles$Lookup
  #254 = Utf8               java/lang/invoke/MethodHandles$Lookup
  #255 = Class              #256          // java/lang/invoke/MethodHandles
  #256 = Utf8               java/lang/invoke/MethodHandles
  #257 = Utf8               Lookup
{
  public ext.mods.gameserver.handler.admincommandhandlers.AdminPledge();
    descriptor: ()V
    flags: (0x0001) ACC_PUBLIC
    Code:
      stack=1, locals=1, args_size=1
         0: aload_0
         1: invokespecial #1                  // Method java/lang/Object."<init>":()V
         4: return
      LineNumberTable:
        line 30: 0
      LocalVariableTable:
        Start  Length  Slot  Name   Signature
            0       5     0  this   Lext/mods/gameserver/handler/admincommandhandlers/AdminPledge;

  public void useAdminCommand(java.lang.String, ext.mods.gameserver.model.actor.Player);
    descriptor: (Ljava/lang/String;Lext/mods/gameserver/model/actor/Player;)V
    flags: (0x0001) ACC_PUBLIC
    Code:
      stack=6, locals=10, args_size=3
         0: aload_0
         1: aload_2
         2: iconst_1
         3: invokevirtual #7                  // Method getTargetPlayer:(Lext/mods/gameserver/model/actor/Player;Z)Lext/mods/gameserver/model/actor/Player;
         6: astore_3
         7: aload_1
         8: ldc           #13                 // String admin_pledge
        10: invokevirtual #15                 // Method java/lang/String.startsWith:(Ljava/lang/String;)Z
        13: ifeq          511
        16: new           #21                 // class java/util/StringTokenizer
        19: dup
        20: aload_1
        21: ldc           #23                 // String
        23: invokespecial #25                 // Method java/util/StringTokenizer."<init>":(Ljava/lang/String;Ljava/lang/String;)V
        26: astore        4
        28: aload         4
        30: invokevirtual #28                 // Method java/util/StringTokenizer.nextToken:()Ljava/lang/String;
        33: pop
        34: aload         4
        36: invokevirtual #28                 // Method java/util/StringTokenizer.nextToken:()Ljava/lang/String;
        39: astore        5
        41: aload         5
        43: ldc           #32                 // String create
        45: invokevirtual #34                 // Method java/lang/String.equals:(Ljava/lang/Object;)Z
        48: ifeq          129
        51: aload         4
        53: invokevirtual #28                 // Method java/util/StringTokenizer.nextToken:()Ljava/lang/String;
        56: astore        6
        58: aload_3
        59: invokevirtual #38                 // Method ext/mods/gameserver/model/actor/Player.getClanCreateExpiryTime:()J
        62: lstore        7
        64: aload_3
        65: lconst_0
        66: invokevirtual #44                 // Method ext/mods/gameserver/model/actor/Player.setClanCreateExpiryTime:(J)V
        69: invokestatic  #48                 // Method ext/mods/gameserver/data/sql/ClanTable.getInstance:()Lext/mods/gameserver/data/sql/ClanTable;
        72: aload_3
        73: aload         6
        75: invokevirtual #54                 // Method ext/mods/gameserver/data/sql/ClanTable.createClan:(Lext/mods/gameserver/model/actor/Player;Ljava/lang/String;)Lext/mods/gameserver/model/pledge/Clan;
        78: astore        9
        80: aload         9
        82: ifnull        103
        85: aload_2
        86: aload         6
        88: aload_3
        89: invokevirtual #58                 // Method ext/mods/gameserver/model/actor/Player.getName:()Ljava/lang/String;
        92: invokedynamic #61,  0             // InvokeDynamic #0:makeConcatWithConstants:(Ljava/lang/String;Ljava/lang/String;)Ljava/lang/String;
        97: invokevirtual #65                 // Method ext/mods/gameserver/model/actor/Player.sendMessage:(Ljava/lang/String;)V
       100: goto          115
       103: aload_3
       104: lload         7
       106: invokevirtual #44                 // Method ext/mods/gameserver/model/actor/Player.setClanCreateExpiryTime:(J)V
       109: aload_2
       110: ldc           #69                 // String There was a problem while creating the clan.
       112: invokevirtual #65                 // Method ext/mods/gameserver/model/actor/Player.sendMessage:(Ljava/lang/String;)V
       115: goto          500
       118: astore        6
       120: aload_2
       121: ldc           #73                 // String Invalid string parameter for //pledge create.
       123: invokevirtual #65                 // Method ext/mods/gameserver/model/actor/Player.sendMessage:(Ljava/lang/String;)V
       126: goto          500
       129: aload_3
       130: invokevirtual #75                 // Method ext/mods/gameserver/model/actor/Player.getClan:()Lext/mods/gameserver/model/pledge/Clan;
       133: astore        6
       135: aload         6
       137: ifnonnull     155
       140: aload_2
       141: getstatic     #79                 // Field ext/mods/gameserver/network/SystemMessageId.TARGET_MUST_BE_IN_CLAN:Lext/mods/gameserver/network/SystemMessageId;
       144: invokevirtual #85                 // Method ext/mods/gameserver/model/actor/Player.sendPacket:(Lext/mods/gameserver/network/SystemMessageId;)V
       147: aload_0
       148: aload_2
       149: ldc           #89                 // String game_menu.htm
       151: invokevirtual #91                 // Method sendFile:(Lext/mods/gameserver/model/actor/Player;Ljava/lang/String;)V
       154: return
       155: aload         5
       157: ldc           #95                 // String dismiss
       159: invokevirtual #34                 // Method java/lang/String.equals:(Ljava/lang/Object;)Z
       162: ifeq          182
       165: invokestatic  #48                 // Method ext/mods/gameserver/data/sql/ClanTable.getInstance:()Lext/mods/gameserver/data/sql/ClanTable;
       168: aload         6
       170: invokevirtual #97                 // Method ext/mods/gameserver/data/sql/ClanTable.destroyClan:(Lext/mods/gameserver/model/pledge/Clan;)V
       173: aload_2
       174: ldc           #101                // String The clan is now disbanded.
       176: invokevirtual #65                 // Method ext/mods/gameserver/model/actor/Player.sendMessage:(Ljava/lang/String;)V
       179: goto          500
       182: aload         5
       184: ldc           #103                // String info
       186: invokevirtual #34                 // Method java/lang/String.equals:(Ljava/lang/Object;)Z
       189: ifeq          209
       192: aload_2
       193: new           #105                // class ext/mods/gameserver/network/serverpackets/GMViewPledgeInfo
       196: dup
       197: aload         6
       199: aload_3
       200: invokespecial #107                // Method ext/mods/gameserver/network/serverpackets/GMViewPledgeInfo."<init>":(Lext/mods/gameserver/model/pledge/Clan;Lext/mods/gameserver/model/actor/Player;)V
       203: invokevirtual #110                // Method ext/mods/gameserver/model/actor/Player.sendPacket:(Lext/mods/gameserver/network/serverpackets/L2GameServerPacket;)V
       206: goto          500
       209: aload         5
       211: ldc           #113                // String level
       213: invokevirtual #34                 // Method java/lang/String.equals:(Ljava/lang/Object;)Z
       216: ifeq          287
       219: aload         4
       221: invokevirtual #28                 // Method java/util/StringTokenizer.nextToken:()Ljava/lang/String;
       224: invokestatic  #115                // Method java/lang/Integer.parseInt:(Ljava/lang/String;)I
       227: istore        7
       229: iload         7
       231: iflt          267
       234: iload         7
       236: bipush        9
       238: if_icmpge     267
       241: aload         6
       243: iload         7
       245: invokevirtual #121                // Method ext/mods/gameserver/model/pledge/Clan.changeLevel:(I)V
       248: aload_2
       249: aload         6
       251: invokevirtual #127                // Method ext/mods/gameserver/model/pledge/Clan.getName:()Ljava/lang/String;
       254: iload         7
       256: invokedynamic #128,  0            // InvokeDynamic #1:makeConcatWithConstants:(Ljava/lang/String;I)Ljava/lang/String;
       261: invokevirtual #65                 // Method ext/mods/gameserver/model/actor/Player.sendMessage:(Ljava/lang/String;)V
       264: goto          273
       267: aload_2
       268: ldc           #131                // String This clan level is incorrect. Put a number between 0 and 8.
       270: invokevirtual #65                 // Method ext/mods/gameserver/model/actor/Player.sendMessage:(Ljava/lang/String;)V
       273: goto          500
       276: astore        7
       278: aload_2
       279: ldc           #133                // String Invalid number parameter for //pledge setlevel.
       281: invokevirtual #65                 // Method ext/mods/gameserver/model/actor/Player.sendMessage:(Ljava/lang/String;)V
       284: goto          500
       287: aload         5
       289: ldc           #135                // String rep
       291: invokevirtual #15                 // Method java/lang/String.startsWith:(Ljava/lang/String;)Z
       294: ifeq          400
       297: aload         4
       299: invokevirtual #28                 // Method java/util/StringTokenizer.nextToken:()Ljava/lang/String;
       302: invokestatic  #115                // Method java/lang/Integer.parseInt:(Ljava/lang/String;)I
       305: istore        7
       307: aload         6
       309: invokevirtual #137                // Method ext/mods/gameserver/model/pledge/Clan.getLevel:()I
       312: iconst_5
       313: if_icmpge     330
       316: aload_2
       317: ldc           #141                // String Only clans of level 5 or above may receive reputation points.
       319: invokevirtual #65                 // Method ext/mods/gameserver/model/actor/Player.sendMessage:(Ljava/lang/String;)V
       322: aload_0
       323: aload_2
       324: ldc           #89                 // String game_menu.htm
       326: invokevirtual #91                 // Method sendFile:(Lext/mods/gameserver/model/actor/Player;Ljava/lang/String;)V
       329: return
       330: aload         6
       332: iload         7
       334: invokevirtual #143                // Method ext/mods/gameserver/model/pledge/Clan.addReputationScore:(I)Z
       337: pop
       338: aload_2
       339: iload         7
       341: ifle          349
       344: ldc           #147                // String added
       346: goto          351
       349: ldc           #149                // String removed
       351: iload         7
       353: invokestatic  #151                // Method java/lang/Math.abs:(I)I
       356: iload         7
       358: ifle          366
       361: ldc           #157                // String to
       363: goto          368
       366: ldc           #159                // String from
       368: aload         6
       370: invokevirtual #127                // Method ext/mods/gameserver/model/pledge/Clan.getName:()Ljava/lang/String;
       373: aload         6
       375: invokevirtual #161                // Method ext/mods/gameserver/model/pledge/Clan.getReputationScore:()I
       378: invokedynamic #164,  0            // InvokeDynamic #2:makeConcatWithConstants:(Ljava/lang/String;ILjava/lang/String;Ljava/lang/String;I)Ljava/lang/String;
       383: invokevirtual #65                 // Method ext/mods/gameserver/model/actor/Player.sendMessage:(Ljava/lang/String;)V
       386: goto          500
       389: astore        7
       391: aload_2
       392: ldc           #167                // String Invalid number parameter for //pledge rep.
       394: invokevirtual #65                 // Method ext/mods/gameserver/model/actor/Player.sendMessage:(Ljava/lang/String;)V
       397: goto          500
       400: aload         5
       402: ldc           #169                // String transfer
       404: invokevirtual #15                 // Method java/lang/String.startsWith:(Ljava/lang/String;)Z
       407: ifeq          500
       410: aload         6
       412: aload_3
       413: invokevirtual #171                // Method ext/mods/gameserver/model/actor/Player.getObjectId:()I
       416: invokevirtual #174                // Method ext/mods/gameserver/model/pledge/Clan.getClanMember:(I)Lext/mods/gameserver/model/pledge/ClanMember;
       419: astore        7
       421: aload         7
       423: ifnonnull     445
       426: aload_2
       427: aload_3
       428: invokevirtual #58                 // Method ext/mods/gameserver/model/actor/Player.getName:()Ljava/lang/String;
       431: aload         6
       433: invokevirtual #127                // Method ext/mods/gameserver/model/pledge/Clan.getName:()Ljava/lang/String;
       436: invokedynamic #178,  0            // InvokeDynamic #3:makeConcatWithConstants:(Ljava/lang/String;Ljava/lang/String;)Ljava/lang/String;
       441: invokevirtual #65                 // Method ext/mods/gameserver/model/actor/Player.sendMessage:(Ljava/lang/String;)V
       444: return
       445: aload         6
       447: invokevirtual #179                // Method ext/mods/gameserver/model/pledge/Clan.getLeader:()Lext/mods/gameserver/model/pledge/ClanMember;
       450: aload         7
       452: if_acmpne     474
       455: aload_2
       456: aload_3
       457: invokevirtual #58                 // Method ext/mods/gameserver/model/actor/Player.getName:()Ljava/lang/String;
       460: aload         6
       462: invokevirtual #127                // Method ext/mods/gameserver/model/pledge/Clan.getName:()Ljava/lang/String;
       465: invokedynamic #183,  0            // InvokeDynamic #4:makeConcatWithConstants:(Ljava/lang/String;Ljava/lang/String;)Ljava/lang/String;
       470: invokevirtual #65                 // Method ext/mods/gameserver/model/actor/Player.sendMessage:(Ljava/lang/String;)V
       473: return
       474: aload         6
       476: aload         7
       478: invokevirtual #184                // Method ext/mods/gameserver/model/pledge/Clan.setNewLeader:(Lext/mods/gameserver/model/pledge/ClanMember;)V
       481: aload_2
       482: aload         7
       484: invokevirtual #188                // Method ext/mods/gameserver/model/pledge/ClanMember.getName:()Ljava/lang/String;
       487: aload         6
       489: invokevirtual #127                // Method ext/mods/gameserver/model/pledge/Clan.getName:()Ljava/lang/String;
       492: invokedynamic #191,  0            // InvokeDynamic #5:makeConcatWithConstants:(Ljava/lang/String;Ljava/lang/String;)Ljava/lang/String;
       497: invokevirtual #65                 // Method ext/mods/gameserver/model/actor/Player.sendMessage:(Ljava/lang/String;)V
       500: goto          511
       503: astore        5
       505: aload_2
       506: ldc           #192                // String Usage: //pledge create|dismiss|info|level|rep|transfer
       508: invokevirtual #65                 // Method ext/mods/gameserver/model/actor/Player.sendMessage:(Ljava/lang/String;)V
       511: aload_0
       512: aload_2
       513: ldc           #89                 // String game_menu.htm
       515: invokevirtual #91                 // Method sendFile:(Lext/mods/gameserver/model/actor/Player;Ljava/lang/String;)V
       518: return
      Exception table:
         from    to  target type
            51   115   118   Class java/lang/Exception
           219   273   276   Class java/lang/Exception
           297   329   389   Class java/lang/Exception
           330   386   389   Class java/lang/Exception
            34   154   503   Class java/lang/Exception
           155   329   503   Class java/lang/Exception
           330   444   503   Class java/lang/Exception
           445   473   503   Class java/lang/Exception
           474   500   503   Class java/lang/Exception
      LineNumberTable:
        line 40: 0
        line 42: 7
        line 44: 16
        line 45: 28
        line 49: 34
        line 51: 41
        line 55: 51
        line 56: 58
        line 58: 64
        line 60: 69
        line 61: 80
        line 62: 85
        line 65: 103
        line 66: 109
        line 72: 115
        line 69: 118
        line 71: 120
        line 72: 126
        line 76: 129
        line 77: 135
        line 79: 140
        line 80: 147
        line 81: 154
        line 84: 155
        line 86: 165
        line 87: 173
        line 89: 182
        line 90: 192
        line 91: 209
        line 95: 219
        line 96: 229
        line 98: 241
        line 99: 248
        line 102: 267
        line 107: 273
        line 104: 276
        line 106: 278
        line 107: 284
        line 109: 287
        line 113: 297
        line 115: 307
        line 117: 316
        line 118: 322
        line 119: 329
        line 122: 330
        line 123: 338
        line 128: 386
        line 125: 389
        line 127: 391
        line 128: 397
        line 130: 400
        line 132: 410
        line 133: 421
        line 135: 426
        line 136: 444
        line 139: 445
        line 141: 455
        line 142: 473
        line 145: 474
        line 146: 481
        line 153: 500
        line 150: 503
        line 152: 505
        line 155: 511
        line 156: 518
      LocalVariableTable:
        Start  Length  Slot  Name   Signature
           58      57     6 parameter   Ljava/lang/String;
           64      51     7   cet   J
           80      35     9  clan   Lext/mods/gameserver/model/pledge/Clan;
          120       6     6     e   Ljava/lang/Exception;
          229      44     7 level   I
          278       6     7     e   Ljava/lang/Exception;
          307      79     7 points   I
          391       6     7     e   Ljava/lang/Exception;
          421      79     7 member   Lext/mods/gameserver/model/pledge/ClanMember;
          135     365     6 targetClan   Lext/mods/gameserver/model/pledge/Clan;
           41     459     5 action   Ljava/lang/String;
          505       6     5     e   Ljava/lang/Exception;
           28     483     4    st   Ljava/util/StringTokenizer;
            0     519     0  this   Lext/mods/gameserver/handler/admincommandhandlers/AdminPledge;
            0     519     1 command   Ljava/lang/String;
            0     519     2 player   Lext/mods/gameserver/model/actor/Player;
            7     512     3 targetPlayer   Lext/mods/gameserver/model/actor/Player;
      StackMapTable: number_of_entries = 23
        frame_type = 255 /* full_frame */
          offset_delta = 103
          locals = [ class ext/mods/gameserver/handler/admincommandhandlers/AdminPledge, class java/lang/String, class ext/mods/gameserver/model/actor/Player, class ext/mods/gameserver/model/actor/Player, class java/util/StringTokenizer, class java/lang/String, class java/lang/String, long, class ext/mods/gameserver/model/pledge/Clan ]
          stack = []
        frame_type = 248 /* chop */
          offset_delta = 11
        frame_type = 66 /* same_locals_1_stack_item */
          stack = [ class java/lang/Exception ]
        frame_type = 10 /* same */
        frame_type = 252 /* append */
          offset_delta = 25
          locals = [ class ext/mods/gameserver/model/pledge/Clan ]
        frame_type = 26 /* same */
        frame_type = 26 /* same */
        frame_type = 252 /* append */
          offset_delta = 57
          locals = [ int ]
        frame_type = 250 /* chop */
          offset_delta = 5
        frame_type = 66 /* same_locals_1_stack_item */
          stack = [ class java/lang/Exception ]
        frame_type = 10 /* same */
        frame_type = 252 /* append */
          offset_delta = 42
          locals = [ int ]
        frame_type = 82 /* same_locals_1_stack_item */
          stack = [ class ext/mods/gameserver/model/actor/Player ]
        frame_type = 255 /* full_frame */
          offset_delta = 1
          locals = [ class ext/mods/gameserver/handler/admincommandhandlers/AdminPledge, class java/lang/String, class ext/mods/gameserver/model/actor/Player, class ext/mods/gameserver/model/actor/Player, class java/util/StringTokenizer, class java/lang/String, class ext/mods/gameserver/model/pledge/Clan, int ]
          stack = [ class ext/mods/gameserver/model/actor/Player, class java/lang/String ]
        frame_type = 255 /* full_frame */
          offset_delta = 14
          locals = [ class ext/mods/gameserver/handler/admincommandhandlers/AdminPledge, class java/lang/String, class ext/mods/gameserver/model/actor/Player, class ext/mods/gameserver/model/actor/Player, class java/util/StringTokenizer, class java/lang/String, class ext/mods/gameserver/model/pledge/Clan, int ]
          stack = [ class ext/mods/gameserver/model/actor/Player, class java/lang/String, int ]
        frame_type = 255 /* full_frame */
          offset_delta = 1
          locals = [ class ext/mods/gameserver/handler/admincommandhandlers/AdminPledge, class java/lang/String, class ext/mods/gameserver/model/actor/Player, class ext/mods/gameserver/model/actor/Player, class java/util/StringTokenizer, class java/lang/String, class ext/mods/gameserver/model/pledge/Clan, int ]
          stack = [ class ext/mods/gameserver/model/actor/Player, class java/lang/String, int, class java/lang/String ]
        frame_type = 255 /* full_frame */
          offset_delta = 20
          locals = [ class ext/mods/gameserver/handler/admincommandhandlers/AdminPledge, class java/lang/String, class ext/mods/gameserver/model/actor/Player, class ext/mods/gameserver/model/actor/Player, class java/util/StringTokenizer, class java/lang/String, class ext/mods/gameserver/model/pledge/Clan ]
          stack = [ class java/lang/Exception ]
        frame_type = 10 /* same */
        frame_type = 252 /* append */
          offset_delta = 44
          locals = [ class ext/mods/gameserver/model/pledge/ClanMember ]
        frame_type = 28 /* same */
        frame_type = 248 /* chop */
          offset_delta = 25
        frame_type = 66 /* same_locals_1_stack_item */
          stack = [ class java/lang/Exception ]
        frame_type = 250 /* chop */
          offset_delta = 7

  public java.lang.String[] getAdminCommandList();
    descriptor: ()[Ljava/lang/String;
    flags: (0x0001) ACC_PUBLIC
    Code:
      stack=1, locals=1, args_size=1
         0: getstatic     #194                // Field ADMIN_COMMANDS:[Ljava/lang/String;
         3: areturn
      LineNumberTable:
        line 161: 0
      LocalVariableTable:
        Start  Length  Slot  Name   Signature
            0       4     0  this   Lext/mods/gameserver/handler/admincommandhandlers/AdminPledge;

  static {};
    descriptor: ()V
    flags: (0x0008) ACC_STATIC
    Code:
      stack=4, locals=0, args_size=0
         0: iconst_1
         1: anewarray     #16                 // class java/lang/String
         4: dup
         5: iconst_0
         6: ldc           #13                 // String admin_pledge
         8: aastore
         9: putstatic     #194                // Field ADMIN_COMMANDS:[Ljava/lang/String;
        12: return
      LineNumberTable:
        line 32: 0
}
SourceFile: "AdminPledge.java"
BootstrapMethods:
  0: #246 REF_invokeStatic java/lang/invoke/StringConcatFactory.makeConcatWithConstants:(Ljava/lang/invoke/MethodHandles$Lookup;Ljava/lang/String;Ljava/lang/invoke/MethodType;Ljava/lang/String;[Ljava/lang/Object;)Ljava/lang/invoke/CallSite;
    Method arguments:
      #234 Clan \u0001 have been created. Clan leader is \u0001.
  1: #246 REF_invokeStatic java/lang/invoke/StringConcatFactory.makeConcatWithConstants:(Ljava/lang/invoke/MethodHandles$Lookup;Ljava/lang/String;Ljava/lang/invoke/MethodType;Ljava/lang/String;[Ljava/lang/Object;)Ljava/lang/invoke/CallSite;
    Method arguments:
      #236 You have set clan \u0001 to level \u0001
  2: #246 REF_invokeStatic java/lang/invoke/StringConcatFactory.makeConcatWithConstants:(Ljava/lang/invoke/MethodHandles$Lookup;Ljava/lang/String;Ljava/lang/invoke/MethodType;Ljava/lang/String;[Ljava/lang/Object;)Ljava/lang/invoke/CallSite;
    Method arguments:
      #238 You \u0001\u0001 points \u0001\u0001\'s reputation. Their current score is: \u0001
  3: #246 REF_invokeStatic java/lang/invoke/StringConcatFactory.makeConcatWithConstants:(Ljava/lang/invoke/MethodHandles$Lookup;Ljava/lang/String;Ljava/lang/invoke/MethodType;Ljava/lang/String;[Ljava/lang/Object;)Ljava/lang/invoke/CallSite;
    Method arguments:
      #240 \u0001 can\'t be set as the new Clan leader of \u0001.
  4: #246 REF_invokeStatic java/lang/invoke/StringConcatFactory.makeConcatWithConstants:(Ljava/lang/invoke/MethodHandles$Lookup;Ljava/lang/String;Ljava/lang/invoke/MethodType;Ljava/lang/String;[Ljava/lang/Object;)Ljava/lang/invoke/CallSite;
    Method arguments:
      #242 \u0001 is already the Clan leader of \u0001.
  5: #246 REF_invokeStatic java/lang/invoke/StringConcatFactory.makeConcatWithConstants:(Ljava/lang/invoke/MethodHandles$Lookup;Ljava/lang/String;Ljava/lang/invoke/MethodType;Ljava/lang/String;[Ljava/lang/Object;)Ljava/lang/invoke/CallSite;
    Method arguments:
      #244 You set \u0001 as the new Clan leader of \u0001.
InnerClasses:
  public static final #257= #253 of #255; // Lookup=class java/lang/invoke/MethodHandles$Lookup of class java/lang/invoke/MethodHandles
