// Bytecode for: ext.mods.commons.gui.InterfaceLSInfo$InfoRow
// File: ext\mods\commons\gui\InterfaceLSInfo$InfoRow.class

Classfile /c:/Users/User/Desktop/BrProject/bin/main/ext/mods/commons/gui/InterfaceLSInfo$InfoRow.class
  Last modified 9 de jul de 2026; size 2252 bytes
  MD5 checksum 1aaacab2b9fc87a832021b845ed62757
  Compiled from "InterfaceLSInfo.java"
class ext.mods.commons.gui.InterfaceLSInfo$InfoRow extends javax.swing.JComponent
  minor version: 0
  major version: 69
  flags: (0x0020) ACC_SUPER
  this_class: #8                          // ext/mods/commons/gui/InterfaceLSInfo$InfoRow
  super_class: #2                         // javax/swing/JComponent
  interfaces: 0, fields: 2, methods: 3, attributes: 3
Constant pool:
    #1 = Methodref          #2.#3         // javax/swing/JComponent."<init>":()V
    #2 = Class              #4            // javax/swing/JComponent
    #3 = NameAndType        #5:#6         // "<init>":()V
    #4 = Utf8               javax/swing/JComponent
    #5 = Utf8               <init>
    #6 = Utf8               ()V
    #7 = Fieldref           #8.#9         // ext/mods/commons/gui/InterfaceLSInfo$InfoRow.label:Ljava/lang/String;
    #8 = Class              #10           // ext/mods/commons/gui/InterfaceLSInfo$InfoRow
    #9 = NameAndType        #11:#12       // label:Ljava/lang/String;
   #10 = Utf8               ext/mods/commons/gui/InterfaceLSInfo$InfoRow
   #11 = Utf8               label
   #12 = Utf8               Ljava/lang/String;
   #13 = Fieldref           #8.#14        // ext/mods/commons/gui/InterfaceLSInfo$InfoRow.value:Ljava/lang/String;
   #14 = NameAndType        #15:#12       // value:Ljava/lang/String;
   #15 = Utf8               value
   #16 = Class              #17           // java/awt/Dimension
   #17 = Utf8               java/awt/Dimension
   #18 = Methodref          #16.#19       // java/awt/Dimension."<init>":(II)V
   #19 = NameAndType        #5:#20        // "<init>":(II)V
   #20 = Utf8               (II)V
   #21 = Methodref          #8.#22        // ext/mods/commons/gui/InterfaceLSInfo$InfoRow.setPreferredSize:(Ljava/awt/Dimension;)V
   #22 = NameAndType        #23:#24       // setPreferredSize:(Ljava/awt/Dimension;)V
   #23 = Utf8               setPreferredSize
   #24 = Utf8               (Ljava/awt/Dimension;)V
   #25 = Methodref          #8.#26        // ext/mods/commons/gui/InterfaceLSInfo$InfoRow.setMaximumSize:(Ljava/awt/Dimension;)V
   #26 = NameAndType        #27:#24       // setMaximumSize:(Ljava/awt/Dimension;)V
   #27 = Utf8               setMaximumSize
   #28 = Class              #29           // java/awt/Component
   #29 = Utf8               java/awt/Component
   #30 = Methodref          #8.#31        // ext/mods/commons/gui/InterfaceLSInfo$InfoRow.setAlignmentX:(F)V
   #31 = NameAndType        #32:#33       // setAlignmentX:(F)V
   #32 = Utf8               setAlignmentX
   #33 = Utf8               (F)V
   #34 = Methodref          #35.#36       // java/lang/String.equals:(Ljava/lang/Object;)Z
   #35 = Class              #37           // java/lang/String
   #36 = NameAndType        #38:#39       // equals:(Ljava/lang/Object;)Z
   #37 = Utf8               java/lang/String
   #38 = Utf8               equals
   #39 = Utf8               (Ljava/lang/Object;)Z
   #40 = Methodref          #8.#41        // ext/mods/commons/gui/InterfaceLSInfo$InfoRow.repaint:()V
   #41 = NameAndType        #42:#6        // repaint:()V
   #42 = Utf8               repaint
   #43 = Methodref          #44.#45       // java/awt/Graphics.create:()Ljava/awt/Graphics;
   #44 = Class              #46           // java/awt/Graphics
   #45 = NameAndType        #47:#48       // create:()Ljava/awt/Graphics;
   #46 = Utf8               java/awt/Graphics
   #47 = Utf8               create
   #48 = Utf8               ()Ljava/awt/Graphics;
   #49 = Class              #50           // java/awt/Graphics2D
   #50 = Utf8               java/awt/Graphics2D
   #51 = Fieldref           #52.#53       // java/awt/RenderingHints.KEY_ANTIALIASING:Ljava/awt/RenderingHints$Key;
   #52 = Class              #54           // java/awt/RenderingHints
   #53 = NameAndType        #55:#56       // KEY_ANTIALIASING:Ljava/awt/RenderingHints$Key;
   #54 = Utf8               java/awt/RenderingHints
   #55 = Utf8               KEY_ANTIALIASING
   #56 = Utf8               Ljava/awt/RenderingHints$Key;
   #57 = Fieldref           #52.#58       // java/awt/RenderingHints.VALUE_ANTIALIAS_ON:Ljava/lang/Object;
   #58 = NameAndType        #59:#60       // VALUE_ANTIALIAS_ON:Ljava/lang/Object;
   #59 = Utf8               VALUE_ANTIALIAS_ON
   #60 = Utf8               Ljava/lang/Object;
   #61 = Methodref          #49.#62       // java/awt/Graphics2D.setRenderingHint:(Ljava/awt/RenderingHints$Key;Ljava/lang/Object;)V
   #62 = NameAndType        #63:#64       // setRenderingHint:(Ljava/awt/RenderingHints$Key;Ljava/lang/Object;)V
   #63 = Utf8               setRenderingHint
   #64 = Utf8               (Ljava/awt/RenderingHints$Key;Ljava/lang/Object;)V
   #65 = Methodref          #8.#66        // ext/mods/commons/gui/InterfaceLSInfo$InfoRow.getWidth:()I
   #66 = NameAndType        #67:#68       // getWidth:()I
   #67 = Utf8               getWidth
   #68 = Utf8               ()I
   #69 = Class              #70           // java/awt/Font
   #70 = Utf8               java/awt/Font
   #71 = String             #72           // Segoe UI
   #72 = Utf8               Segoe UI
   #73 = Methodref          #69.#74       // java/awt/Font."<init>":(Ljava/lang/String;II)V
   #74 = NameAndType        #5:#75        // "<init>":(Ljava/lang/String;II)V
   #75 = Utf8               (Ljava/lang/String;II)V
   #76 = Methodref          #49.#77       // java/awt/Graphics2D.setFont:(Ljava/awt/Font;)V
   #77 = NameAndType        #78:#79       // setFont:(Ljava/awt/Font;)V
   #78 = Utf8               setFont
   #79 = Utf8               (Ljava/awt/Font;)V
   #80 = Methodref          #49.#81       // java/awt/Graphics2D.getFontMetrics:()Ljava/awt/FontMetrics;
   #81 = NameAndType        #82:#83       // getFontMetrics:()Ljava/awt/FontMetrics;
   #82 = Utf8               getFontMetrics
   #83 = Utf8               ()Ljava/awt/FontMetrics;
   #84 = Fieldref           #85.#86       // ext/mods/commons/gui/ModernUI.TEXT_GRAY:Ljava/awt/Color;
   #85 = Class              #87           // ext/mods/commons/gui/ModernUI
   #86 = NameAndType        #88:#89       // TEXT_GRAY:Ljava/awt/Color;
   #87 = Utf8               ext/mods/commons/gui/ModernUI
   #88 = Utf8               TEXT_GRAY
   #89 = Utf8               Ljava/awt/Color;
   #90 = Methodref          #49.#91       // java/awt/Graphics2D.setColor:(Ljava/awt/Color;)V
   #91 = NameAndType        #92:#93       // setColor:(Ljava/awt/Color;)V
   #92 = Utf8               setColor
   #93 = Utf8               (Ljava/awt/Color;)V
   #94 = Methodref          #49.#95       // java/awt/Graphics2D.drawString:(Ljava/lang/String;II)V
   #95 = NameAndType        #96:#75       // drawString:(Ljava/lang/String;II)V
   #96 = Utf8               drawString
   #97 = Fieldref           #85.#98       // ext/mods/commons/gui/ModernUI.TEXT_WHITE:Ljava/awt/Color;
   #98 = NameAndType        #99:#89       // TEXT_WHITE:Ljava/awt/Color;
   #99 = Utf8               TEXT_WHITE
  #100 = Methodref          #101.#102     // java/awt/FontMetrics.stringWidth:(Ljava/lang/String;)I
  #101 = Class              #103          // java/awt/FontMetrics
  #102 = NameAndType        #104:#105     // stringWidth:(Ljava/lang/String;)I
  #103 = Utf8               java/awt/FontMetrics
  #104 = Utf8               stringWidth
  #105 = Utf8               (Ljava/lang/String;)I
  #106 = Methodref          #49.#107      // java/awt/Graphics2D.dispose:()V
  #107 = NameAndType        #108:#6       // dispose:()V
  #108 = Utf8               dispose
  #109 = Utf8               (Ljava/lang/String;Ljava/lang/String;)V
  #110 = Utf8               Code
  #111 = Utf8               LineNumberTable
  #112 = Utf8               LocalVariableTable
  #113 = Utf8               this
  #114 = Utf8               Lext/mods/commons/gui/InterfaceLSInfo$InfoRow;
  #115 = Utf8               setValue
  #116 = Utf8               (Ljava/lang/String;)V
  #117 = Utf8               val
  #118 = Utf8               StackMapTable
  #119 = Utf8               paintComponent
  #120 = Utf8               (Ljava/awt/Graphics;)V
  #121 = Utf8               g
  #122 = Utf8               Ljava/awt/Graphics;
  #123 = Utf8               g2
  #124 = Utf8               Ljava/awt/Graphics2D;
  #125 = Utf8               w
  #126 = Utf8               I
  #127 = Utf8               fm
  #128 = Utf8               Ljava/awt/FontMetrics;
  #129 = Utf8               SourceFile
  #130 = Utf8               InterfaceLSInfo.java
  #131 = Utf8               NestHost
  #132 = Class              #133          // ext/mods/commons/gui/InterfaceLSInfo
  #133 = Utf8               ext/mods/commons/gui/InterfaceLSInfo
  #134 = Utf8               InnerClasses
  #135 = Utf8               InfoRow
  #136 = Class              #137          // java/awt/RenderingHints$Key
  #137 = Utf8               java/awt/RenderingHints$Key
  #138 = Utf8               Key
{
  public ext.mods.commons.gui.InterfaceLSInfo$InfoRow(java.lang.String, java.lang.String);
    descriptor: (Ljava/lang/String;Ljava/lang/String;)V
    flags: (0x0001) ACC_PUBLIC
    Code:
      stack=5, locals=3, args_size=3
         0: aload_0
         1: invokespecial #1                  // Method javax/swing/JComponent."<init>":()V
         4: aload_0
         5: aload_1
         6: putfield      #7                  // Field label:Ljava/lang/String;
         9: aload_0
        10: aload_2
        11: putfield      #13                 // Field value:Ljava/lang/String;
        14: aload_0
        15: new           #16                 // class java/awt/Dimension
        18: dup
        19: sipush        200
        22: bipush        20
        24: invokespecial #18                 // Method java/awt/Dimension."<init>":(II)V
        27: invokevirtual #21                 // Method setPreferredSize:(Ljava/awt/Dimension;)V
        30: aload_0
        31: new           #16                 // class java/awt/Dimension
        34: dup
        35: sipush        320
        38: bipush        20
        40: invokespecial #18                 // Method java/awt/Dimension."<init>":(II)V
        43: invokevirtual #25                 // Method setMaximumSize:(Ljava/awt/Dimension;)V
        46: aload_0
        47: fconst_0
        48: invokevirtual #30                 // Method setAlignmentX:(F)V
        51: return
      LineNumberTable:
        line 166: 0
        line 167: 4
        line 168: 9
        line 170: 14
        line 171: 30
        line 172: 46
        line 173: 51
      LocalVariableTable:
        Start  Length  Slot  Name   Signature
            0      52     0  this   Lext/mods/commons/gui/InterfaceLSInfo$InfoRow;
            0      52     1 label   Ljava/lang/String;
            0      52     2 value   Ljava/lang/String;

  public void setValue(java.lang.String);
    descriptor: (Ljava/lang/String;)V
    flags: (0x0001) ACC_PUBLIC
    Code:
      stack=2, locals=2, args_size=2
         0: aload_0
         1: getfield      #13                 // Field value:Ljava/lang/String;
         4: aload_1
         5: invokevirtual #34                 // Method java/lang/String.equals:(Ljava/lang/Object;)Z
         8: ifne          20
        11: aload_0
        12: aload_1
        13: putfield      #13                 // Field value:Ljava/lang/String;
        16: aload_0
        17: invokevirtual #40                 // Method repaint:()V
        20: return
      LineNumberTable:
        line 176: 0
        line 177: 11
        line 178: 16
        line 180: 20
      LocalVariableTable:
        Start  Length  Slot  Name   Signature
            0      21     0  this   Lext/mods/commons/gui/InterfaceLSInfo$InfoRow;
            0      21     1   val   Ljava/lang/String;
      StackMapTable: number_of_entries = 1
        frame_type = 20 /* same */

  protected void paintComponent(java.awt.Graphics);
    descriptor: (Ljava/awt/Graphics;)V
    flags: (0x0004) ACC_PROTECTED
    Code:
      stack=6, locals=5, args_size=2
         0: aload_1
         1: invokevirtual #43                 // Method java/awt/Graphics.create:()Ljava/awt/Graphics;
         4: checkcast     #49                 // class java/awt/Graphics2D
         7: astore_2
         8: aload_2
         9: getstatic     #51                 // Field java/awt/RenderingHints.KEY_ANTIALIASING:Ljava/awt/RenderingHints$Key;
        12: getstatic     #57                 // Field java/awt/RenderingHints.VALUE_ANTIALIAS_ON:Ljava/lang/Object;
        15: invokevirtual #61                 // Method java/awt/Graphics2D.setRenderingHint:(Ljava/awt/RenderingHints$Key;Ljava/lang/Object;)V
        18: aload_0
        19: invokevirtual #65                 // Method getWidth:()I
        22: istore_3
        23: aload_2
        24: new           #69                 // class java/awt/Font
        27: dup
        28: ldc           #71                 // String Segoe UI
        30: iconst_0
        31: bipush        11
        33: invokespecial #73                 // Method java/awt/Font."<init>":(Ljava/lang/String;II)V
        36: invokevirtual #76                 // Method java/awt/Graphics2D.setFont:(Ljava/awt/Font;)V
        39: aload_2
        40: invokevirtual #80                 // Method java/awt/Graphics2D.getFontMetrics:()Ljava/awt/FontMetrics;
        43: astore        4
        45: aload_2
        46: getstatic     #84                 // Field ext/mods/commons/gui/ModernUI.TEXT_GRAY:Ljava/awt/Color;
        49: invokevirtual #90                 // Method java/awt/Graphics2D.setColor:(Ljava/awt/Color;)V
        52: aload_2
        53: aload_0
        54: getfield      #7                  // Field label:Ljava/lang/String;
        57: iconst_0
        58: bipush        11
        60: invokevirtual #94                 // Method java/awt/Graphics2D.drawString:(Ljava/lang/String;II)V
        63: aload_2
        64: getstatic     #97                 // Field ext/mods/commons/gui/ModernUI.TEXT_WHITE:Ljava/awt/Color;
        67: invokevirtual #90                 // Method java/awt/Graphics2D.setColor:(Ljava/awt/Color;)V
        70: aload_2
        71: aload_0
        72: getfield      #13                 // Field value:Ljava/lang/String;
        75: iload_3
        76: aload         4
        78: aload_0
        79: getfield      #13                 // Field value:Ljava/lang/String;
        82: invokevirtual #100                // Method java/awt/FontMetrics.stringWidth:(Ljava/lang/String;)I
        85: isub
        86: bipush        11
        88: invokevirtual #94                 // Method java/awt/Graphics2D.drawString:(Ljava/lang/String;II)V
        91: aload_2
        92: invokevirtual #106                // Method java/awt/Graphics2D.dispose:()V
        95: return
      LineNumberTable:
        line 184: 0
        line 185: 8
        line 187: 18
        line 189: 23
        line 190: 39
        line 192: 45
        line 193: 52
        line 195: 63
        line 196: 70
        line 198: 91
        line 199: 95
      LocalVariableTable:
        Start  Length  Slot  Name   Signature
            0      96     0  this   Lext/mods/commons/gui/InterfaceLSInfo$InfoRow;
            0      96     1     g   Ljava/awt/Graphics;
            8      88     2    g2   Ljava/awt/Graphics2D;
           23      73     3     w   I
           45      51     4    fm   Ljava/awt/FontMetrics;
}
SourceFile: "InterfaceLSInfo.java"
NestHost: class ext/mods/commons/gui/InterfaceLSInfo
InnerClasses:
  public static abstract #138= #136 of #52; // Key=class java/awt/RenderingHints$Key of class java/awt/RenderingHints
