// Bytecode for: ext.mods.commons.gui.InterfaceGSInfo$1
// File: ext\mods\commons\gui\InterfaceGSInfo$1.class

Classfile /c:/Users/User/Desktop/BrProject/bin/main/ext/mods/commons/gui/InterfaceGSInfo$1.class
  Last modified 9 de jul de 2026; size 1658 bytes
  MD5 checksum 5f41dfacbf6a70a7e0dc028d8e5cdc9c
  Compiled from "InterfaceGSInfo.java"
class ext.mods.commons.gui.InterfaceGSInfo$1 extends java.util.TimerTask
  minor version: 0
  major version: 69
  flags: (0x0020) ACC_SUPER
  this_class: #8                          // ext/mods/commons/gui/InterfaceGSInfo$1
  super_class: #14                        // java/util/TimerTask
  interfaces: 0, fields: 1, methods: 3, attributes: 5
Constant pool:
   #1 = Methodref          #2.#3          // java/util/Objects.requireNonNull:(Ljava/lang/Object;)Ljava/lang/Object;
   #2 = Class              #4             // java/util/Objects
   #3 = NameAndType        #5:#6          // requireNonNull:(Ljava/lang/Object;)Ljava/lang/Object;
   #4 = Utf8               java/util/Objects
   #5 = Utf8               requireNonNull
   #6 = Utf8               (Ljava/lang/Object;)Ljava/lang/Object;
   #7 = Fieldref           #8.#9          // ext/mods/commons/gui/InterfaceGSInfo$1.this$0:Lext/mods/commons/gui/InterfaceGSInfo;
   #8 = Class              #10            // ext/mods/commons/gui/InterfaceGSInfo$1
   #9 = NameAndType        #11:#12        // this$0:Lext/mods/commons/gui/InterfaceGSInfo;
  #10 = Utf8               ext/mods/commons/gui/InterfaceGSInfo$1
  #11 = Utf8               this$0
  #12 = Utf8               Lext/mods/commons/gui/InterfaceGSInfo;
  #13 = Methodref          #14.#15        // java/util/TimerTask."<init>":()V
  #14 = Class              #16            // java/util/TimerTask
  #15 = NameAndType        #17:#18        // "<init>":()V
  #16 = Utf8               java/util/TimerTask
  #17 = Utf8               <init>
  #18 = Utf8               ()V
  #19 = InvokeDynamic      #0:#20         // #0:run:(Lext/mods/commons/gui/InterfaceGSInfo$1;)Ljava/lang/Runnable;
  #20 = NameAndType        #21:#22        // run:(Lext/mods/commons/gui/InterfaceGSInfo$1;)Ljava/lang/Runnable;
  #21 = Utf8               run
  #22 = Utf8               (Lext/mods/commons/gui/InterfaceGSInfo$1;)Ljava/lang/Runnable;
  #23 = Methodref          #24.#25        // javax/swing/SwingUtilities.invokeLater:(Ljava/lang/Runnable;)V
  #24 = Class              #26            // javax/swing/SwingUtilities
  #25 = NameAndType        #27:#28        // invokeLater:(Ljava/lang/Runnable;)V
  #26 = Utf8               javax/swing/SwingUtilities
  #27 = Utf8               invokeLater
  #28 = Utf8               (Ljava/lang/Runnable;)V
  #29 = Fieldref           #30.#31        // ext/mods/commons/gui/InterfaceGSInfo.rowProtocol:Lext/mods/commons/gui/InterfaceGSInfo$InfoRow;
  #30 = Class              #32            // ext/mods/commons/gui/InterfaceGSInfo
  #31 = NameAndType        #33:#34        // rowProtocol:Lext/mods/commons/gui/InterfaceGSInfo$InfoRow;
  #32 = Utf8               ext/mods/commons/gui/InterfaceGSInfo
  #33 = Utf8               rowProtocol
  #34 = Utf8               Lext/mods/commons/gui/InterfaceGSInfo$InfoRow;
  #35 = String             #36            // 730 | 746
  #36 = Utf8               730 | 746
  #37 = Methodref          #38.#39        // ext/mods/commons/gui/InterfaceGSInfo$InfoRow.setValue:(Ljava/lang/String;)V
  #38 = Class              #40            // ext/mods/commons/gui/InterfaceGSInfo$InfoRow
  #39 = NameAndType        #41:#42        // setValue:(Ljava/lang/String;)V
  #40 = Utf8               ext/mods/commons/gui/InterfaceGSInfo$InfoRow
  #41 = Utf8               setValue
  #42 = Utf8               (Ljava/lang/String;)V
  #43 = Utf8               (Lext/mods/commons/gui/InterfaceGSInfo;)V
  #44 = Utf8               Code
  #45 = Utf8               LineNumberTable
  #46 = Utf8               LocalVariableTable
  #47 = Utf8               this
  #48 = Utf8               Lext/mods/commons/gui/InterfaceGSInfo$1;
  #49 = Utf8               MethodParameters
  #50 = Utf8               lambda$run$0
  #51 = Utf8               SourceFile
  #52 = Utf8               InterfaceGSInfo.java
  #53 = Utf8               EnclosingMethod
  #54 = NameAndType        #55:#18        // startUpdateTask:()V
  #55 = Utf8               startUpdateTask
  #56 = Utf8               NestHost
  #57 = Utf8               BootstrapMethods
  #58 = MethodType         #18            //  ()V
  #59 = MethodHandle       5:#60          // REF_invokeVirtual ext/mods/commons/gui/InterfaceGSInfo$1.lambda$run$0:()V
  #60 = Methodref          #8.#61         // ext/mods/commons/gui/InterfaceGSInfo$1.lambda$run$0:()V
  #61 = NameAndType        #50:#18        // lambda$run$0:()V
  #62 = MethodHandle       6:#63          // REF_invokeStatic java/lang/invoke/LambdaMetafactory.metafactory:(Ljava/lang/invoke/MethodHandles$Lookup;Ljava/lang/String;Ljava/lang/invoke/MethodType;Ljava/lang/invoke/MethodType;Ljava/lang/invoke/MethodHandle;Ljava/lang/invoke/MethodType;)Ljava/lang/invoke/CallSite;
  #63 = Methodref          #64.#65        // java/lang/invoke/LambdaMetafactory.metafactory:(Ljava/lang/invoke/MethodHandles$Lookup;Ljava/lang/String;Ljava/lang/invoke/MethodType;Ljava/lang/invoke/MethodType;Ljava/lang/invoke/MethodHandle;Ljava/lang/invoke/MethodType;)Ljava/lang/invoke/CallSite;
  #64 = Class              #66            // java/lang/invoke/LambdaMetafactory
  #65 = NameAndType        #67:#68        // metafactory:(Ljava/lang/invoke/MethodHandles$Lookup;Ljava/lang/String;Ljava/lang/invoke/MethodType;Ljava/lang/invoke/MethodType;Ljava/lang/invoke/MethodHandle;Ljava/lang/invoke/MethodType;)Ljava/lang/invoke/CallSite;
  #66 = Utf8               java/lang/invoke/LambdaMetafactory
  #67 = Utf8               metafactory
  #68 = Utf8               (Ljava/lang/invoke/MethodHandles$Lookup;Ljava/lang/String;Ljava/lang/invoke/MethodType;Ljava/lang/invoke/MethodType;Ljava/lang/invoke/MethodHandle;Ljava/lang/invoke/MethodType;)Ljava/lang/invoke/CallSite;
  #69 = Utf8               InnerClasses
  #70 = Utf8               InfoRow
  #71 = Class              #72            // java/lang/invoke/MethodHandles$Lookup
  #72 = Utf8               java/lang/invoke/MethodHandles$Lookup
  #73 = Class              #74            // java/lang/invoke/MethodHandles
  #74 = Utf8               java/lang/invoke/MethodHandles
  #75 = Utf8               Lookup
{
  final ext.mods.commons.gui.InterfaceGSInfo this$0;
    descriptor: Lext/mods/commons/gui/InterfaceGSInfo;
    flags: (0x1010) ACC_FINAL, ACC_SYNTHETIC

  ext.mods.commons.gui.InterfaceGSInfo$1(ext.mods.commons.gui.InterfaceGSInfo);
    descriptor: (Lext/mods/commons/gui/InterfaceGSInfo;)V
    flags: (0x0000)
    Code:
      stack=3, locals=2, args_size=2
         0: aload_0
         1: aload_1
         2: dup
         3: invokestatic  #1                  // Method java/util/Objects.requireNonNull:(Ljava/lang/Object;)Ljava/lang/Object;
         6: pop
         7: putfield      #7                  // Field this$0:Lext/mods/commons/gui/InterfaceGSInfo;
        10: aload_0
        11: invokespecial #13                 // Method java/util/TimerTask."<init>":()V
        14: return
      LineNumberTable:
        line 86: 0
      LocalVariableTable:
        Start  Length  Slot  Name   Signature
            0      15     0  this   Lext/mods/commons/gui/InterfaceGSInfo$1;
            0      15     1 this$0   Lext/mods/commons/gui/InterfaceGSInfo;
    MethodParameters:
      Name                           Flags
      <no name>                      final mandated

  public void run();
    descriptor: ()V
    flags: (0x0001) ACC_PUBLIC
    Code:
      stack=1, locals=1, args_size=1
         0: aload_0
         1: invokedynamic #19,  0             // InvokeDynamic #0:run:(Lext/mods/commons/gui/InterfaceGSInfo$1;)Ljava/lang/Runnable;
         6: invokestatic  #23                 // Method javax/swing/SwingUtilities.invokeLater:(Ljava/lang/Runnable;)V
         9: return
      LineNumberTable:
        line 89: 0
        line 90: 9
      LocalVariableTable:
        Start  Length  Slot  Name   Signature
            0      10     0  this   Lext/mods/commons/gui/InterfaceGSInfo$1;
}
SourceFile: "InterfaceGSInfo.java"
EnclosingMethod: #30.#54                // ext.mods.commons.gui.InterfaceGSInfo.startUpdateTask
NestHost: class ext/mods/commons/gui/InterfaceGSInfo
BootstrapMethods:
  0: #62 REF_invokeStatic java/lang/invoke/LambdaMetafactory.metafactory:(Ljava/lang/invoke/MethodHandles$Lookup;Ljava/lang/String;Ljava/lang/invoke/MethodType;Ljava/lang/invoke/MethodType;Ljava/lang/invoke/MethodHandle;Ljava/lang/invoke/MethodType;)Ljava/lang/invoke/CallSite;
    Method arguments:
      #58 ()V
      #59 REF_invokeVirtual ext/mods/commons/gui/InterfaceGSInfo$1.lambda$run$0:()V
      #58 ()V
InnerClasses:
  #8;                                     // class ext/mods/commons/gui/InterfaceGSInfo$1
  public static final #75= #71 of #73;    // Lookup=class java/lang/invoke/MethodHandles$Lookup of class java/lang/invoke/MethodHandles
