// Bytecode for: ext.mods.commons.gui.ModernUI$NeonButton
// File: ext\mods\commons\gui\ModernUI$NeonButton.class

Classfile /c:/Users/User/Desktop/BrProject/bin/main/ext/mods/commons/gui/ModernUI$NeonButton.class
  Last modified 9 de jul de 2026; size 3585 bytes
  MD5 checksum f77413d57461748ba078ae61b690cb6f
  Compiled from "ModernUI.java"
public class ext.mods.commons.gui.ModernUI$NeonButton extends javax.swing.JButton
  minor version: 0
  major version: 69
  flags: (0x0021) ACC_PUBLIC, ACC_SUPER
  this_class: #11                         // ext/mods/commons/gui/ModernUI$NeonButton
  super_class: #17                        // javax/swing/JButton
  interfaces: 0, fields: 4, methods: 3, attributes: 3
Constant pool:
    #1 = Fieldref           #2.#3         // ext/mods/commons/gui/ModernUI.NEON_GREEN:Ljava/awt/Color;
    #2 = Class              #4            // ext/mods/commons/gui/ModernUI
    #3 = NameAndType        #5:#6         // NEON_GREEN:Ljava/awt/Color;
    #4 = Utf8               ext/mods/commons/gui/ModernUI
    #5 = Utf8               NEON_GREEN
    #6 = Utf8               Ljava/awt/Color;
    #7 = Fieldref           #2.#8         // ext/mods/commons/gui/ModernUI.NEON_PURPLE:Ljava/awt/Color;
    #8 = NameAndType        #9:#6         // NEON_PURPLE:Ljava/awt/Color;
    #9 = Utf8               NEON_PURPLE
   #10 = Methodref          #11.#12       // ext/mods/commons/gui/ModernUI$NeonButton."<init>":(Ljava/lang/String;Ljava/awt/Color;Ljava/awt/Color;ZLjavax/swing/Icon;)V
   #11 = Class              #13           // ext/mods/commons/gui/ModernUI$NeonButton
   #12 = NameAndType        #14:#15       // "<init>":(Ljava/lang/String;Ljava/awt/Color;Ljava/awt/Color;ZLjavax/swing/Icon;)V
   #13 = Utf8               ext/mods/commons/gui/ModernUI$NeonButton
   #14 = Utf8               <init>
   #15 = Utf8               (Ljava/lang/String;Ljava/awt/Color;Ljava/awt/Color;ZLjavax/swing/Icon;)V
   #16 = Methodref          #17.#18       // javax/swing/JButton."<init>":(Ljava/lang/String;)V
   #17 = Class              #19           // javax/swing/JButton
   #18 = NameAndType        #14:#20       // "<init>":(Ljava/lang/String;)V
   #19 = Utf8               javax/swing/JButton
   #20 = Utf8               (Ljava/lang/String;)V
   #21 = Fieldref           #11.#22       // ext/mods/commons/gui/ModernUI$NeonButton.isHovered:Z
   #22 = NameAndType        #23:#24       // isHovered:Z
   #23 = Utf8               isHovered
   #24 = Utf8               Z
   #25 = Fieldref           #11.#26       // ext/mods/commons/gui/ModernUI$NeonButton.c1:Ljava/awt/Color;
   #26 = NameAndType        #27:#6        // c1:Ljava/awt/Color;
   #27 = Utf8               c1
   #28 = Fieldref           #11.#29       // ext/mods/commons/gui/ModernUI$NeonButton.c2:Ljava/awt/Color;
   #29 = NameAndType        #30:#6        // c2:Ljava/awt/Color;
   #30 = Utf8               c2
   #31 = Fieldref           #11.#32       // ext/mods/commons/gui/ModernUI$NeonButton.isOutline:Z
   #32 = NameAndType        #33:#24       // isOutline:Z
   #33 = Utf8               isOutline
   #34 = Methodref          #11.#35       // ext/mods/commons/gui/ModernUI$NeonButton.setIcon:(Ljavax/swing/Icon;)V
   #35 = NameAndType        #36:#37       // setIcon:(Ljavax/swing/Icon;)V
   #36 = Utf8               setIcon
   #37 = Utf8               (Ljavax/swing/Icon;)V
   #38 = Methodref          #11.#39       // ext/mods/commons/gui/ModernUI$NeonButton.setContentAreaFilled:(Z)V
   #39 = NameAndType        #40:#41       // setContentAreaFilled:(Z)V
   #40 = Utf8               setContentAreaFilled
   #41 = Utf8               (Z)V
   #42 = Methodref          #11.#43       // ext/mods/commons/gui/ModernUI$NeonButton.setFocusPainted:(Z)V
   #43 = NameAndType        #44:#41       // setFocusPainted:(Z)V
   #44 = Utf8               setFocusPainted
   #45 = Methodref          #11.#46       // ext/mods/commons/gui/ModernUI$NeonButton.setBorderPainted:(Z)V
   #46 = NameAndType        #47:#41       // setBorderPainted:(Z)V
   #47 = Utf8               setBorderPainted
   #48 = Fieldref           #2.#49        // ext/mods/commons/gui/ModernUI.TEXT_WHITE:Ljava/awt/Color;
   #49 = NameAndType        #50:#6        // TEXT_WHITE:Ljava/awt/Color;
   #50 = Utf8               TEXT_WHITE
   #51 = Methodref          #11.#52       // ext/mods/commons/gui/ModernUI$NeonButton.setForeground:(Ljava/awt/Color;)V
   #52 = NameAndType        #53:#54       // setForeground:(Ljava/awt/Color;)V
   #53 = Utf8               setForeground
   #54 = Utf8               (Ljava/awt/Color;)V
   #55 = Class              #56           // java/awt/Font
   #56 = Utf8               java/awt/Font
   #57 = String             #58           // Segoe UI
   #58 = Utf8               Segoe UI
   #59 = Methodref          #55.#60       // java/awt/Font."<init>":(Ljava/lang/String;II)V
   #60 = NameAndType        #14:#61       // "<init>":(Ljava/lang/String;II)V
   #61 = Utf8               (Ljava/lang/String;II)V
   #62 = Methodref          #11.#63       // ext/mods/commons/gui/ModernUI$NeonButton.setFont:(Ljava/awt/Font;)V
   #63 = NameAndType        #64:#65       // setFont:(Ljava/awt/Font;)V
   #64 = Utf8               setFont
   #65 = Utf8               (Ljava/awt/Font;)V
   #66 = Class              #67           // java/awt/Cursor
   #67 = Utf8               java/awt/Cursor
   #68 = Methodref          #66.#69       // java/awt/Cursor.getPredefinedCursor:(I)Ljava/awt/Cursor;
   #69 = NameAndType        #70:#71       // getPredefinedCursor:(I)Ljava/awt/Cursor;
   #70 = Utf8               getPredefinedCursor
   #71 = Utf8               (I)Ljava/awt/Cursor;
   #72 = Methodref          #11.#73       // ext/mods/commons/gui/ModernUI$NeonButton.setCursor:(Ljava/awt/Cursor;)V
   #73 = NameAndType        #74:#75       // setCursor:(Ljava/awt/Cursor;)V
   #74 = Utf8               setCursor
   #75 = Utf8               (Ljava/awt/Cursor;)V
   #76 = Class              #77           // ext/mods/commons/gui/ModernUI$NeonButton$1
   #77 = Utf8               ext/mods/commons/gui/ModernUI$NeonButton$1
   #78 = Methodref          #76.#79       // ext/mods/commons/gui/ModernUI$NeonButton$1."<init>":(Lext/mods/commons/gui/ModernUI$NeonButton;)V
   #79 = NameAndType        #14:#80       // "<init>":(Lext/mods/commons/gui/ModernUI$NeonButton;)V
   #80 = Utf8               (Lext/mods/commons/gui/ModernUI$NeonButton;)V
   #81 = Methodref          #11.#82       // ext/mods/commons/gui/ModernUI$NeonButton.addMouseListener:(Ljava/awt/event/MouseListener;)V
   #82 = NameAndType        #83:#84       // addMouseListener:(Ljava/awt/event/MouseListener;)V
   #83 = Utf8               addMouseListener
   #84 = Utf8               (Ljava/awt/event/MouseListener;)V
   #85 = Methodref          #86.#87       // java/awt/Graphics.create:()Ljava/awt/Graphics;
   #86 = Class              #88           // java/awt/Graphics
   #87 = NameAndType        #89:#90       // create:()Ljava/awt/Graphics;
   #88 = Utf8               java/awt/Graphics
   #89 = Utf8               create
   #90 = Utf8               ()Ljava/awt/Graphics;
   #91 = Class              #92           // java/awt/Graphics2D
   #92 = Utf8               java/awt/Graphics2D
   #93 = Fieldref           #94.#95       // java/awt/RenderingHints.KEY_ANTIALIASING:Ljava/awt/RenderingHints$Key;
   #94 = Class              #96           // java/awt/RenderingHints
   #95 = NameAndType        #97:#98       // KEY_ANTIALIASING:Ljava/awt/RenderingHints$Key;
   #96 = Utf8               java/awt/RenderingHints
   #97 = Utf8               KEY_ANTIALIASING
   #98 = Utf8               Ljava/awt/RenderingHints$Key;
   #99 = Fieldref           #94.#100      // java/awt/RenderingHints.VALUE_ANTIALIAS_ON:Ljava/lang/Object;
  #100 = NameAndType        #101:#102     // VALUE_ANTIALIAS_ON:Ljava/lang/Object;
  #101 = Utf8               VALUE_ANTIALIAS_ON
  #102 = Utf8               Ljava/lang/Object;
  #103 = Methodref          #91.#104      // java/awt/Graphics2D.setRenderingHint:(Ljava/awt/RenderingHints$Key;Ljava/lang/Object;)V
  #104 = NameAndType        #105:#106     // setRenderingHint:(Ljava/awt/RenderingHints$Key;Ljava/lang/Object;)V
  #105 = Utf8               setRenderingHint
  #106 = Utf8               (Ljava/awt/RenderingHints$Key;Ljava/lang/Object;)V
  #107 = Methodref          #11.#108      // ext/mods/commons/gui/ModernUI$NeonButton.getWidth:()I
  #108 = NameAndType        #109:#110     // getWidth:()I
  #109 = Utf8               getWidth
  #110 = Utf8               ()I
  #111 = Methodref          #11.#112      // ext/mods/commons/gui/ModernUI$NeonButton.getHeight:()I
  #112 = NameAndType        #113:#110     // getHeight:()I
  #113 = Utf8               getHeight
  #114 = Methodref          #115.#116     // ext/mods/commons/gui/ThemeManager.isSafeGraphics:()Z
  #115 = Class              #117          // ext/mods/commons/gui/ThemeManager
  #116 = NameAndType        #118:#119     // isSafeGraphics:()Z
  #117 = Utf8               ext/mods/commons/gui/ThemeManager
  #118 = Utf8               isSafeGraphics
  #119 = Utf8               ()Z
  #120 = Methodref          #91.#121      // java/awt/Graphics2D.setColor:(Ljava/awt/Color;)V
  #121 = NameAndType        #122:#54      // setColor:(Ljava/awt/Color;)V
  #122 = Utf8               setColor
  #123 = Class              #124          // java/awt/GradientPaint
  #124 = Utf8               java/awt/GradientPaint
  #125 = Methodref          #123.#126     // java/awt/GradientPaint."<init>":(FFLjava/awt/Color;FFLjava/awt/Color;)V
  #126 = NameAndType        #14:#127      // "<init>":(FFLjava/awt/Color;FFLjava/awt/Color;)V
  #127 = Utf8               (FFLjava/awt/Color;FFLjava/awt/Color;)V
  #128 = Methodref          #91.#129      // java/awt/Graphics2D.setPaint:(Ljava/awt/Paint;)V
  #129 = NameAndType        #130:#131     // setPaint:(Ljava/awt/Paint;)V
  #130 = Utf8               setPaint
  #131 = Utf8               (Ljava/awt/Paint;)V
  #132 = Class              #133          // java/awt/BasicStroke
  #133 = Utf8               java/awt/BasicStroke
  #134 = Float              1.5f
  #135 = Methodref          #132.#136     // java/awt/BasicStroke."<init>":(F)V
  #136 = NameAndType        #14:#137      // "<init>":(F)V
  #137 = Utf8               (F)V
  #138 = Methodref          #91.#139      // java/awt/Graphics2D.setStroke:(Ljava/awt/Stroke;)V
  #139 = NameAndType        #140:#141     // setStroke:(Ljava/awt/Stroke;)V
  #140 = Utf8               setStroke
  #141 = Utf8               (Ljava/awt/Stroke;)V
  #142 = Methodref          #91.#143      // java/awt/Graphics2D.drawRoundRect:(IIIIII)V
  #143 = NameAndType        #144:#145     // drawRoundRect:(IIIIII)V
  #144 = Utf8               drawRoundRect
  #145 = Utf8               (IIIIII)V
  #146 = Class              #147          // java/awt/AlphaComposite
  #147 = Utf8               java/awt/AlphaComposite
  #148 = Float              0.2f
  #149 = Methodref          #146.#150     // java/awt/AlphaComposite.getInstance:(IF)Ljava/awt/AlphaComposite;
  #150 = NameAndType        #151:#152     // getInstance:(IF)Ljava/awt/AlphaComposite;
  #151 = Utf8               getInstance
  #152 = Utf8               (IF)Ljava/awt/AlphaComposite;
  #153 = Methodref          #91.#154      // java/awt/Graphics2D.setComposite:(Ljava/awt/Composite;)V
  #154 = NameAndType        #155:#156     // setComposite:(Ljava/awt/Composite;)V
  #155 = Utf8               setComposite
  #156 = Utf8               (Ljava/awt/Composite;)V
  #157 = Methodref          #91.#158      // java/awt/Graphics2D.fillRoundRect:(IIIIII)V
  #158 = NameAndType        #159:#145     // fillRoundRect:(IIIIII)V
  #159 = Utf8               fillRoundRect
  #160 = Methodref          #161.#162     // java/awt/Color.brighter:()Ljava/awt/Color;
  #161 = Class              #163          // java/awt/Color
  #162 = NameAndType        #164:#165     // brighter:()Ljava/awt/Color;
  #163 = Utf8               java/awt/Color
  #164 = Utf8               brighter
  #165 = Utf8               ()Ljava/awt/Color;
  #166 = Methodref          #161.#167     // java/awt/Color.getRed:()I
  #167 = NameAndType        #168:#110     // getRed:()I
  #168 = Utf8               getRed
  #169 = Methodref          #161.#170     // java/awt/Color.getGreen:()I
  #170 = NameAndType        #171:#110     // getGreen:()I
  #171 = Utf8               getGreen
  #172 = Methodref          #161.#173     // java/awt/Color.getBlue:()I
  #173 = NameAndType        #174:#110     // getBlue:()I
  #174 = Utf8               getBlue
  #175 = Methodref          #161.#176     // java/awt/Color."<init>":(III)V
  #176 = NameAndType        #14:#177      // "<init>":(III)V
  #177 = Utf8               (III)V
  #178 = Methodref          #161.#179     // java/awt/Color."<init>":(IIII)V
  #179 = NameAndType        #14:#180      // "<init>":(IIII)V
  #180 = Utf8               (IIII)V
  #181 = Methodref          #17.#182      // javax/swing/JButton.paintComponent:(Ljava/awt/Graphics;)V
  #182 = NameAndType        #183:#184     // paintComponent:(Ljava/awt/Graphics;)V
  #183 = Utf8               paintComponent
  #184 = Utf8               (Ljava/awt/Graphics;)V
  #185 = Methodref          #91.#186      // java/awt/Graphics2D.dispose:()V
  #186 = NameAndType        #187:#188     // dispose:()V
  #187 = Utf8               dispose
  #188 = Utf8               ()V
  #189 = Utf8               Code
  #190 = Utf8               LineNumberTable
  #191 = Utf8               LocalVariableTable
  #192 = Utf8               this
  #193 = Utf8               Lext/mods/commons/gui/ModernUI$NeonButton;
  #194 = Utf8               text
  #195 = Utf8               Ljava/lang/String;
  #196 = Utf8               icon
  #197 = Utf8               Ljavax/swing/Icon;
  #198 = Utf8               StackMapTable
  #199 = Class              #200          // java/lang/String
  #200 = Utf8               java/lang/String
  #201 = Class              #202          // javax/swing/Icon
  #202 = Utf8               javax/swing/Icon
  #203 = Utf8               start
  #204 = Utf8               end
  #205 = Utf8               g
  #206 = Utf8               Ljava/awt/Graphics;
  #207 = Utf8               g2d
  #208 = Utf8               Ljava/awt/Graphics2D;
  #209 = Utf8               w
  #210 = Utf8               I
  #211 = Utf8               h
  #212 = Utf8               arc
  #213 = Utf8               SourceFile
  #214 = Utf8               ModernUI.java
  #215 = Utf8               NestHost
  #216 = Utf8               InnerClasses
  #217 = Utf8               NeonButton
  #218 = Class              #219          // java/awt/RenderingHints$Key
  #219 = Utf8               java/awt/RenderingHints$Key
  #220 = Utf8               Key
{
  public ext.mods.commons.gui.ModernUI$NeonButton(java.lang.String);
    descriptor: (Ljava/lang/String;)V
    flags: (0x0001) ACC_PUBLIC
    Code:
      stack=6, locals=2, args_size=2
         0: aload_0
         1: aload_1
         2: getstatic     #1                  // Field ext/mods/commons/gui/ModernUI.NEON_GREEN:Ljava/awt/Color;
         5: getstatic     #7                  // Field ext/mods/commons/gui/ModernUI.NEON_PURPLE:Ljava/awt/Color;
         8: iconst_0
         9: aconst_null
        10: invokespecial #10                 // Method "<init>":(Ljava/lang/String;Ljava/awt/Color;Ljava/awt/Color;ZLjavax/swing/Icon;)V
        13: return
      LineNumberTable:
        line 134: 0
        line 135: 13
      LocalVariableTable:
        Start  Length  Slot  Name   Signature
            0      14     0  this   Lext/mods/commons/gui/ModernUI$NeonButton;
            0      14     1  text   Ljava/lang/String;

  public ext.mods.commons.gui.ModernUI$NeonButton(java.lang.String, java.awt.Color, java.awt.Color, boolean, javax.swing.Icon);
    descriptor: (Ljava/lang/String;Ljava/awt/Color;Ljava/awt/Color;ZLjavax/swing/Icon;)V
    flags: (0x0001) ACC_PUBLIC
    Code:
      stack=6, locals=6, args_size=6
         0: aload_0
         1: aload_1
         2: invokespecial #16                 // Method javax/swing/JButton."<init>":(Ljava/lang/String;)V
         5: aload_0
         6: iconst_0
         7: putfield      #21                 // Field isHovered:Z
        10: aload_0
        11: aload_2
        12: putfield      #25                 // Field c1:Ljava/awt/Color;
        15: aload_0
        16: aload_3
        17: putfield      #28                 // Field c2:Ljava/awt/Color;
        20: aload_0
        21: iload         4
        23: putfield      #31                 // Field isOutline:Z
        26: aload         5
        28: ifnull        37
        31: aload_0
        32: aload         5
        34: invokevirtual #34                 // Method setIcon:(Ljavax/swing/Icon;)V
        37: aload_0
        38: iconst_0
        39: invokevirtual #38                 // Method setContentAreaFilled:(Z)V
        42: aload_0
        43: iconst_0
        44: invokevirtual #42                 // Method setFocusPainted:(Z)V
        47: aload_0
        48: iconst_0
        49: invokevirtual #45                 // Method setBorderPainted:(Z)V
        52: aload_0
        53: getstatic     #48                 // Field ext/mods/commons/gui/ModernUI.TEXT_WHITE:Ljava/awt/Color;
        56: invokevirtual #51                 // Method setForeground:(Ljava/awt/Color;)V
        59: aload_0
        60: new           #55                 // class java/awt/Font
        63: dup
        64: ldc           #57                 // String Segoe UI
        66: iconst_1
        67: bipush        12
        69: invokespecial #59                 // Method java/awt/Font."<init>":(Ljava/lang/String;II)V
        72: invokevirtual #62                 // Method setFont:(Ljava/awt/Font;)V
        75: aload_0
        76: bipush        12
        78: invokestatic  #68                 // Method java/awt/Cursor.getPredefinedCursor:(I)Ljava/awt/Cursor;
        81: invokevirtual #72                 // Method setCursor:(Ljava/awt/Cursor;)V
        84: aload_0
        85: new           #76                 // class ext/mods/commons/gui/ModernUI$NeonButton$1
        88: dup
        89: aload_0
        90: invokespecial #78                 // Method ext/mods/commons/gui/ModernUI$NeonButton$1."<init>":(Lext/mods/commons/gui/ModernUI$NeonButton;)V
        93: invokevirtual #81                 // Method addMouseListener:(Ljava/awt/event/MouseListener;)V
        96: return
      LineNumberTable:
        line 138: 0
        line 130: 5
        line 139: 10
        line 140: 26
        line 141: 37
        line 142: 52
        line 143: 59
        line 144: 75
        line 145: 84
        line 149: 96
      LocalVariableTable:
        Start  Length  Slot  Name   Signature
            0      97     0  this   Lext/mods/commons/gui/ModernUI$NeonButton;
            0      97     1  text   Ljava/lang/String;
            0      97     2    c1   Ljava/awt/Color;
            0      97     3    c2   Ljava/awt/Color;
            0      97     4 isOutline   Z
            0      97     5  icon   Ljavax/swing/Icon;
      StackMapTable: number_of_entries = 1
        frame_type = 255 /* full_frame */
          offset_delta = 37
          locals = [ class ext/mods/commons/gui/ModernUI$NeonButton, class java/lang/String, class java/awt/Color, class java/awt/Color, int, class javax/swing/Icon ]
          stack = []

  protected void paintComponent(java.awt.Graphics);
    descriptor: (Ljava/awt/Graphics;)V
    flags: (0x0004) ACC_PROTECTED
    Code:
      stack=9, locals=8, args_size=2
         0: aload_1
         1: invokevirtual #85                 // Method java/awt/Graphics.create:()Ljava/awt/Graphics;
         4: checkcast     #91                 // class java/awt/Graphics2D
         7: astore_2
         8: aload_2
         9: getstatic     #93                 // Field java/awt/RenderingHints.KEY_ANTIALIASING:Ljava/awt/RenderingHints$Key;
        12: getstatic     #99                 // Field java/awt/RenderingHints.VALUE_ANTIALIAS_ON:Ljava/lang/Object;
        15: invokevirtual #103                // Method java/awt/Graphics2D.setRenderingHint:(Ljava/awt/RenderingHints$Key;Ljava/lang/Object;)V
        18: aload_0
        19: invokevirtual #107                // Method getWidth:()I
        22: istore_3
        23: aload_0
        24: invokevirtual #111                // Method getHeight:()I
        27: istore        4
        29: bipush        12
        31: istore        5
        33: aload_0
        34: getfield      #31                 // Field isOutline:Z
        37: ifeq          148
        40: invokestatic  #114                // Method ext/mods/commons/gui/ThemeManager.isSafeGraphics:()Z
        43: ifeq          57
        46: aload_2
        47: aload_0
        48: getfield      #25                 // Field c1:Ljava/awt/Color;
        51: invokevirtual #120                // Method java/awt/Graphics2D.setColor:(Ljava/awt/Color;)V
        54: goto          81
        57: aload_2
        58: new           #123                // class java/awt/GradientPaint
        61: dup
        62: fconst_0
        63: fconst_0
        64: aload_0
        65: getfield      #25                 // Field c1:Ljava/awt/Color;
        68: iload_3
        69: i2f
        70: fconst_0
        71: aload_0
        72: getfield      #28                 // Field c2:Ljava/awt/Color;
        75: invokespecial #125                // Method java/awt/GradientPaint."<init>":(FFLjava/awt/Color;FFLjava/awt/Color;)V
        78: invokevirtual #128                // Method java/awt/Graphics2D.setPaint:(Ljava/awt/Paint;)V
        81: aload_2
        82: new           #132                // class java/awt/BasicStroke
        85: dup
        86: ldc           #134                // float 1.5f
        88: invokespecial #135                // Method java/awt/BasicStroke."<init>":(F)V
        91: invokevirtual #138                // Method java/awt/Graphics2D.setStroke:(Ljava/awt/Stroke;)V
        94: aload_2
        95: iconst_1
        96: iconst_1
        97: iload_3
        98: iconst_3
        99: isub
       100: iload         4
       102: iconst_3
       103: isub
       104: iload         5
       106: iload         5
       108: invokevirtual #142                // Method java/awt/Graphics2D.drawRoundRect:(IIIIII)V
       111: aload_0
       112: getfield      #21                 // Field isHovered:Z
       115: ifeq          325
       118: aload_2
       119: iconst_3
       120: ldc           #148                // float 0.2f
       122: invokestatic  #149                // Method java/awt/AlphaComposite.getInstance:(IF)Ljava/awt/AlphaComposite;
       125: invokevirtual #153                // Method java/awt/Graphics2D.setComposite:(Ljava/awt/Composite;)V
       128: aload_2
       129: iconst_1
       130: iconst_1
       131: iload_3
       132: iconst_3
       133: isub
       134: iload         4
       136: iconst_3
       137: isub
       138: iload         5
       140: iload         5
       142: invokevirtual #157                // Method java/awt/Graphics2D.fillRoundRect:(IIIIII)V
       145: goto          325
       148: aload_0
       149: getfield      #21                 // Field isHovered:Z
       152: ifeq          165
       155: aload_0
       156: getfield      #25                 // Field c1:Ljava/awt/Color;
       159: invokevirtual #160                // Method java/awt/Color.brighter:()Ljava/awt/Color;
       162: goto          169
       165: aload_0
       166: getfield      #25                 // Field c1:Ljava/awt/Color;
       169: astore        6
       171: aload_0
       172: getfield      #21                 // Field isHovered:Z
       175: ifeq          188
       178: aload_0
       179: getfield      #28                 // Field c2:Ljava/awt/Color;
       182: invokevirtual #160                // Method java/awt/Color.brighter:()Ljava/awt/Color;
       185: goto          192
       188: aload_0
       189: getfield      #28                 // Field c2:Ljava/awt/Color;
       192: astore        7
       194: invokestatic  #114                // Method ext/mods/commons/gui/ThemeManager.isSafeGraphics:()Z
       197: ifeq          253
       200: aload_2
       201: new           #161                // class java/awt/Color
       204: dup
       205: aload         6
       207: invokevirtual #166                // Method java/awt/Color.getRed:()I
       210: aload         7
       212: invokevirtual #166                // Method java/awt/Color.getRed:()I
       215: iadd
       216: iconst_2
       217: idiv
       218: aload         6
       220: invokevirtual #169                // Method java/awt/Color.getGreen:()I
       223: aload         7
       225: invokevirtual #169                // Method java/awt/Color.getGreen:()I
       228: iadd
       229: iconst_2
       230: idiv
       231: aload         6
       233: invokevirtual #172                // Method java/awt/Color.getBlue:()I
       236: aload         7
       238: invokevirtual #172                // Method java/awt/Color.getBlue:()I
       241: iadd
       242: iconst_2
       243: idiv
       244: invokespecial #175                // Method java/awt/Color."<init>":(III)V
       247: invokevirtual #120                // Method java/awt/Graphics2D.setColor:(Ljava/awt/Color;)V
       250: goto          273
       253: aload_2
       254: new           #123                // class java/awt/GradientPaint
       257: dup
       258: fconst_0
       259: fconst_0
       260: aload         6
       262: iload_3
       263: i2f
       264: fconst_0
       265: aload         7
       267: invokespecial #125                // Method java/awt/GradientPaint."<init>":(FFLjava/awt/Color;FFLjava/awt/Color;)V
       270: invokevirtual #128                // Method java/awt/Graphics2D.setPaint:(Ljava/awt/Paint;)V
       273: aload_2
       274: iconst_0
       275: iconst_0
       276: iload_3
       277: iload         4
       279: iload         5
       281: iload         5
       283: invokevirtual #157                // Method java/awt/Graphics2D.fillRoundRect:(IIIIII)V
       286: aload_2
       287: new           #161                // class java/awt/Color
       290: dup
       291: sipush        255
       294: sipush        255
       297: sipush        255
       300: bipush        40
       302: invokespecial #178                // Method java/awt/Color."<init>":(IIII)V
       305: invokevirtual #120                // Method java/awt/Graphics2D.setColor:(Ljava/awt/Color;)V
       308: aload_2
       309: iconst_1
       310: iconst_1
       311: iload_3
       312: iconst_3
       313: isub
       314: iload         4
       316: iconst_3
       317: isub
       318: iload         5
       320: iload         5
       322: invokevirtual #142                // Method java/awt/Graphics2D.drawRoundRect:(IIIIII)V
       325: aload_0
       326: aload_1
       327: invokespecial #181                // Method javax/swing/JButton.paintComponent:(Ljava/awt/Graphics;)V
       330: aload_2
       331: invokevirtual #185                // Method java/awt/Graphics2D.dispose:()V
       334: return
      LineNumberTable:
        line 153: 0
        line 154: 8
        line 155: 18
        line 156: 29
        line 158: 33
        line 159: 40
        line 160: 46
        line 162: 57
        line 164: 81
        line 165: 94
        line 166: 111
        line 167: 118
        line 168: 128
        line 171: 148
        line 172: 171
        line 173: 194
        line 174: 200
        line 176: 253
        line 178: 273
        line 180: 286
        line 181: 308
        line 183: 325
        line 184: 330
        line 185: 334
      LocalVariableTable:
        Start  Length  Slot  Name   Signature
          171     154     6 start   Ljava/awt/Color;
          194     131     7   end   Ljava/awt/Color;
            0     335     0  this   Lext/mods/commons/gui/ModernUI$NeonButton;
            0     335     1     g   Ljava/awt/Graphics;
            8     327     2   g2d   Ljava/awt/Graphics2D;
           23     312     3     w   I
           29     306     4     h   I
           33     302     5   arc   I
      StackMapTable: number_of_entries = 10
        frame_type = 255 /* full_frame */
          offset_delta = 57
          locals = [ class ext/mods/commons/gui/ModernUI$NeonButton, class java/awt/Graphics, class java/awt/Graphics2D, int, int, int ]
          stack = []
        frame_type = 23 /* same */
        frame_type = 251 /* same_frame_extended */
          offset_delta = 66
        frame_type = 16 /* same */
        frame_type = 67 /* same_locals_1_stack_item */
          stack = [ class java/awt/Color ]
        frame_type = 252 /* append */
          offset_delta = 18
          locals = [ class java/awt/Color ]
        frame_type = 67 /* same_locals_1_stack_item */
          stack = [ class java/awt/Color ]
        frame_type = 252 /* append */
          offset_delta = 60
          locals = [ class java/awt/Color ]
        frame_type = 19 /* same */
        frame_type = 249 /* chop */
          offset_delta = 51
}
SourceFile: "ModernUI.java"
NestHost: class ext/mods/commons/gui/ModernUI
InnerClasses:
  public static #217= #11 of #2;          // NeonButton=class ext/mods/commons/gui/ModernUI$NeonButton of class ext/mods/commons/gui/ModernUI
  #76;                                    // class ext/mods/commons/gui/ModernUI$NeonButton$1
  public static abstract #220= #218 of #94; // Key=class java/awt/RenderingHints$Key of class java/awt/RenderingHints
