// Bytecode for: ext.mods.gameserver.model.craft.RecipeItemMaker
// File: ext\mods\gameserver\model\craft\RecipeItemMaker.class

Classfile /c:/Users/User/Desktop/BrProject/bin/main/ext/mods/gameserver/model/craft/RecipeItemMaker.class
  Last modified 9 de jul de 2026; size 8555 bytes
  MD5 checksum e9a1d8438c64c839c124075c143a144d
  Compiled from "RecipeItemMaker.java"
public class ext.mods.gameserver.model.craft.RecipeItemMaker implements java.lang.Runnable
  minor version: 0
  major version: 69
  flags: (0x0021) ACC_PUBLIC, ACC_SUPER
  this_class: #8                          // ext/mods/gameserver/model/craft/RecipeItemMaker
  super_class: #2                         // java/lang/Object
  interfaces: 1, fields: 8, methods: 7, attributes: 1
Constant pool:
    #1 = Methodref          #2.#3         // java/lang/Object."<init>":()V
    #2 = Class              #4            // java/lang/Object
    #3 = NameAndType        #5:#6         // "<init>":()V
    #4 = Utf8               java/lang/Object
    #5 = Utf8               <init>
    #6 = Utf8               ()V
    #7 = Fieldref           #8.#9         // ext/mods/gameserver/model/craft/RecipeItemMaker._player:Lext/mods/gameserver/model/actor/Player;
    #8 = Class              #10           // ext/mods/gameserver/model/craft/RecipeItemMaker
    #9 = NameAndType        #11:#12       // _player:Lext/mods/gameserver/model/actor/Player;
   #10 = Utf8               ext/mods/gameserver/model/craft/RecipeItemMaker
   #11 = Utf8               _player
   #12 = Utf8               Lext/mods/gameserver/model/actor/Player;
   #13 = Fieldref           #8.#14        // ext/mods/gameserver/model/craft/RecipeItemMaker._target:Lext/mods/gameserver/model/actor/Player;
   #14 = NameAndType        #15:#12       // _target:Lext/mods/gameserver/model/actor/Player;
   #15 = Utf8               _target
   #16 = Fieldref           #8.#17        // ext/mods/gameserver/model/craft/RecipeItemMaker._recipe:Lext/mods/gameserver/model/records/Recipe;
   #17 = NameAndType        #18:#19       // _recipe:Lext/mods/gameserver/model/records/Recipe;
   #18 = Utf8               _recipe
   #19 = Utf8               Lext/mods/gameserver/model/records/Recipe;
   #20 = Fieldref           #8.#21        // ext/mods/gameserver/model/craft/RecipeItemMaker._isValid:Z
   #21 = NameAndType        #22:#23       // _isValid:Z
   #22 = Utf8               _isValid
   #23 = Utf8               Z
   #24 = Methodref          #25.#26       // ext/mods/gameserver/model/records/Recipe.isDwarven:()Z
   #25 = Class              #27           // ext/mods/gameserver/model/records/Recipe
   #26 = NameAndType        #28:#29       // isDwarven:()Z
   #27 = Utf8               ext/mods/gameserver/model/records/Recipe
   #28 = Utf8               isDwarven
   #29 = Utf8               ()Z
   #30 = Class              #31           // ext/mods/gameserver/skills/L2Skill
   #31 = Utf8               ext/mods/gameserver/skills/L2Skill
   #32 = Fieldref           #8.#33        // ext/mods/gameserver/model/craft/RecipeItemMaker._skillId:I
   #33 = NameAndType        #34:#35       // _skillId:I
   #34 = Utf8               _skillId
   #35 = Utf8               I
   #36 = Methodref          #37.#38       // ext/mods/gameserver/model/actor/Player.getSkillLevel:(I)I
   #37 = Class              #39           // ext/mods/gameserver/model/actor/Player
   #38 = NameAndType        #40:#41       // getSkillLevel:(I)I
   #39 = Utf8               ext/mods/gameserver/model/actor/Player
   #40 = Utf8               getSkillLevel
   #41 = Utf8               (I)I
   #42 = Fieldref           #8.#43        // ext/mods/gameserver/model/craft/RecipeItemMaker._skillLevel:I
   #43 = NameAndType        #44:#35       // _skillLevel:I
   #44 = Utf8               _skillLevel
   #45 = Methodref          #25.#46       // ext/mods/gameserver/model/records/Recipe.mpCost:()I
   #46 = NameAndType        #47:#48       // mpCost:()I
   #47 = Utf8               mpCost
   #48 = Utf8               ()I
   #49 = Fieldref           #8.#50        // ext/mods/gameserver/model/craft/RecipeItemMaker._manaRequired:D
   #50 = NameAndType        #51:#52       // _manaRequired:D
   #51 = Utf8               _manaRequired
   #52 = Utf8               D
   #53 = Methodref          #37.#54       // ext/mods/gameserver/model/actor/Player.setCrafting:(Z)V
   #54 = NameAndType        #55:#56       // setCrafting:(Z)V
   #55 = Utf8               setCrafting
   #56 = Utf8               (Z)V
   #57 = Methodref          #37.#58       // ext/mods/gameserver/model/actor/Player.isAlikeDead:()Z
   #58 = NameAndType        #59:#29       // isAlikeDead:()Z
   #59 = Utf8               isAlikeDead
   #60 = Fieldref           #61.#62       // ext/mods/gameserver/network/serverpackets/ActionFailed.STATIC_PACKET:Lext/mods/gameserver/network/serverpackets/ActionFailed;
   #61 = Class              #63           // ext/mods/gameserver/network/serverpackets/ActionFailed
   #62 = NameAndType        #64:#65       // STATIC_PACKET:Lext/mods/gameserver/network/serverpackets/ActionFailed;
   #63 = Utf8               ext/mods/gameserver/network/serverpackets/ActionFailed
   #64 = Utf8               STATIC_PACKET
   #65 = Utf8               Lext/mods/gameserver/network/serverpackets/ActionFailed;
   #66 = Methodref          #37.#67       // ext/mods/gameserver/model/actor/Player.sendPacket:(Lext/mods/gameserver/network/serverpackets/L2GameServerPacket;)V
   #67 = NameAndType        #68:#69       // sendPacket:(Lext/mods/gameserver/network/serverpackets/L2GameServerPacket;)V
   #68 = Utf8               sendPacket
   #69 = Utf8               (Lext/mods/gameserver/network/serverpackets/L2GameServerPacket;)V
   #70 = Methodref          #8.#71        // ext/mods/gameserver/model/craft/RecipeItemMaker.abort:()V
   #71 = NameAndType        #72:#6        // abort:()V
   #72 = Utf8               abort
   #73 = Methodref          #37.#74       // ext/mods/gameserver/model/actor/Player.isProcessingTransaction:()Z
   #74 = NameAndType        #75:#29       // isProcessingTransaction:()Z
   #75 = Utf8               isProcessingTransaction
   #76 = Methodref          #37.#77       // ext/mods/gameserver/model/actor/Player.getCast:()Lext/mods/gameserver/model/actor/cast/PlayerCast;
   #77 = NameAndType        #78:#79       // getCast:()Lext/mods/gameserver/model/actor/cast/PlayerCast;
   #78 = Utf8               getCast
   #79 = Utf8               ()Lext/mods/gameserver/model/actor/cast/PlayerCast;
   #80 = Methodref          #81.#82       // ext/mods/gameserver/model/actor/cast/PlayerCast.isCastingNow:()Z
   #81 = Class              #83           // ext/mods/gameserver/model/actor/cast/PlayerCast
   #82 = NameAndType        #84:#29       // isCastingNow:()Z
   #83 = Utf8               ext/mods/gameserver/model/actor/cast/PlayerCast
   #84 = Utf8               isCastingNow
   #85 = Methodref          #37.#86       // ext/mods/gameserver/model/actor/Player.isAllSkillsDisabled:()Z
   #86 = NameAndType        #87:#29       // isAllSkillsDisabled:()Z
   #87 = Utf8               isAllSkillsDisabled
   #88 = Fieldref           #89.#90       // ext/mods/gameserver/network/SystemMessageId.NO_RECIPE_BOOK_WHILE_CASTING:Lext/mods/gameserver/network/SystemMessageId;
   #89 = Class              #91           // ext/mods/gameserver/network/SystemMessageId
   #90 = NameAndType        #92:#93       // NO_RECIPE_BOOK_WHILE_CASTING:Lext/mods/gameserver/network/SystemMessageId;
   #91 = Utf8               ext/mods/gameserver/network/SystemMessageId
   #92 = Utf8               NO_RECIPE_BOOK_WHILE_CASTING
   #93 = Utf8               Lext/mods/gameserver/network/SystemMessageId;
   #94 = Methodref          #37.#95       // ext/mods/gameserver/model/actor/Player.sendPacket:(Lext/mods/gameserver/network/SystemMessageId;)V
   #95 = NameAndType        #68:#96       // sendPacket:(Lext/mods/gameserver/network/SystemMessageId;)V
   #96 = Utf8               (Lext/mods/gameserver/network/SystemMessageId;)V
   #97 = Methodref          #37.#98       // ext/mods/gameserver/model/actor/Player.getInventory:()Lext/mods/gameserver/model/itemcontainer/PcInventory;
   #98 = NameAndType        #99:#100      // getInventory:()Lext/mods/gameserver/model/itemcontainer/PcInventory;
   #99 = Utf8               getInventory
  #100 = Utf8               ()Lext/mods/gameserver/model/itemcontainer/PcInventory;
  #101 = Methodref          #25.#102      // ext/mods/gameserver/model/records/Recipe.product:()Lext/mods/gameserver/model/holder/IntIntHolder;
  #102 = NameAndType        #103:#104     // product:()Lext/mods/gameserver/model/holder/IntIntHolder;
  #103 = Utf8               product
  #104 = Utf8               ()Lext/mods/gameserver/model/holder/IntIntHolder;
  #105 = Methodref          #106.#107     // ext/mods/gameserver/model/holder/IntIntHolder.getWeight:()I
  #106 = Class              #108          // ext/mods/gameserver/model/holder/IntIntHolder
  #107 = NameAndType        #109:#48      // getWeight:()I
  #108 = Utf8               ext/mods/gameserver/model/holder/IntIntHolder
  #109 = Utf8               getWeight
  #110 = Methodref          #111.#112     // ext/mods/gameserver/model/itemcontainer/PcInventory.validateWeight:(I)Z
  #111 = Class              #113          // ext/mods/gameserver/model/itemcontainer/PcInventory
  #112 = NameAndType        #114:#115     // validateWeight:(I)Z
  #113 = Utf8               ext/mods/gameserver/model/itemcontainer/PcInventory
  #114 = Utf8               validateWeight
  #115 = Utf8               (I)Z
  #116 = Fieldref           #89.#117      // ext/mods/gameserver/network/SystemMessageId.WEIGHT_LIMIT_EXCEEDED:Lext/mods/gameserver/network/SystemMessageId;
  #117 = NameAndType        #118:#93      // WEIGHT_LIMIT_EXCEEDED:Lext/mods/gameserver/network/SystemMessageId;
  #118 = Utf8               WEIGHT_LIMIT_EXCEEDED
  #119 = Methodref          #25.#120      // ext/mods/gameserver/model/records/Recipe.level:()I
  #120 = NameAndType        #121:#48      // level:()I
  #121 = Utf8               level
  #122 = Methodref          #37.#123      // ext/mods/gameserver/model/actor/Player.getManufactureList:()Lext/mods/gameserver/model/craft/ManufactureList;
  #123 = NameAndType        #124:#125     // getManufactureList:()Lext/mods/gameserver/model/craft/ManufactureList;
  #124 = Utf8               getManufactureList
  #125 = Utf8               ()Lext/mods/gameserver/model/craft/ManufactureList;
  #126 = Methodref          #127.#128     // ext/mods/gameserver/model/craft/ManufactureList.iterator:()Ljava/util/Iterator;
  #127 = Class              #129          // ext/mods/gameserver/model/craft/ManufactureList
  #128 = NameAndType        #130:#131     // iterator:()Ljava/util/Iterator;
  #129 = Utf8               ext/mods/gameserver/model/craft/ManufactureList
  #130 = Utf8               iterator
  #131 = Utf8               ()Ljava/util/Iterator;
  #132 = InterfaceMethodref #133.#134     // java/util/Iterator.hasNext:()Z
  #133 = Class              #135          // java/util/Iterator
  #134 = NameAndType        #136:#29      // hasNext:()Z
  #135 = Utf8               java/util/Iterator
  #136 = Utf8               hasNext
  #137 = InterfaceMethodref #133.#138     // java/util/Iterator.next:()Ljava/lang/Object;
  #138 = NameAndType        #139:#140     // next:()Ljava/lang/Object;
  #139 = Utf8               next
  #140 = Utf8               ()Ljava/lang/Object;
  #141 = Class              #142          // ext/mods/gameserver/model/records/ManufactureItem
  #142 = Utf8               ext/mods/gameserver/model/records/ManufactureItem
  #143 = Methodref          #141.#144     // ext/mods/gameserver/model/records/ManufactureItem.recipeId:()I
  #144 = NameAndType        #145:#48      // recipeId:()I
  #145 = Utf8               recipeId
  #146 = Methodref          #25.#147      // ext/mods/gameserver/model/records/Recipe.id:()I
  #147 = NameAndType        #148:#48      // id:()I
  #148 = Utf8               id
  #149 = Methodref          #141.#150     // ext/mods/gameserver/model/records/ManufactureItem.cost:()I
  #150 = NameAndType        #151:#48      // cost:()I
  #151 = Utf8               cost
  #152 = Fieldref           #8.#153       // ext/mods/gameserver/model/craft/RecipeItemMaker._price:I
  #153 = NameAndType        #154:#35      // _price:I
  #154 = Utf8               _price
  #155 = Methodref          #37.#156      // ext/mods/gameserver/model/actor/Player.getAdena:()I
  #156 = NameAndType        #157:#48      // getAdena:()I
  #157 = Utf8               getAdena
  #158 = Fieldref           #89.#159      // ext/mods/gameserver/network/SystemMessageId.YOU_NOT_ENOUGH_ADENA:Lext/mods/gameserver/network/SystemMessageId;
  #159 = NameAndType        #160:#93      // YOU_NOT_ENOUGH_ADENA:Lext/mods/gameserver/network/SystemMessageId;
  #160 = Utf8               YOU_NOT_ENOUGH_ADENA
  #161 = Methodref          #8.#162       // ext/mods/gameserver/model/craft/RecipeItemMaker.listItems:(Z)Z
  #162 = NameAndType        #163:#164     // listItems:(Z)Z
  #163 = Utf8               listItems
  #164 = Utf8               (Z)Z
  #165 = Methodref          #37.#166      // ext/mods/gameserver/model/actor/Player.getStatus:()Lext/mods/gameserver/model/actor/status/PlayerStatus;
  #166 = NameAndType        #167:#168     // getStatus:()Lext/mods/gameserver/model/actor/status/PlayerStatus;
  #167 = Utf8               getStatus
  #168 = Utf8               ()Lext/mods/gameserver/model/actor/status/PlayerStatus;
  #169 = Methodref          #170.#171     // ext/mods/gameserver/model/actor/status/PlayerStatus.getMp:()D
  #170 = Class              #172          // ext/mods/gameserver/model/actor/status/PlayerStatus
  #171 = NameAndType        #173:#174     // getMp:()D
  #172 = Utf8               ext/mods/gameserver/model/actor/status/PlayerStatus
  #173 = Utf8               getMp
  #174 = Utf8               ()D
  #175 = Fieldref           #89.#176      // ext/mods/gameserver/network/SystemMessageId.NOT_ENOUGH_MP:Lext/mods/gameserver/network/SystemMessageId;
  #176 = NameAndType        #177:#93      // NOT_ENOUGH_MP:Lext/mods/gameserver/network/SystemMessageId;
  #177 = Utf8               NOT_ENOUGH_MP
  #178 = Methodref          #111.#179     // ext/mods/gameserver/model/itemcontainer/PcInventory.validateCapacity:(I)Z
  #179 = NameAndType        #180:#115     // validateCapacity:(I)Z
  #180 = Utf8               validateCapacity
  #181 = Fieldref           #89.#182      // ext/mods/gameserver/network/SystemMessageId.SLOTS_FULL:Lext/mods/gameserver/network/SystemMessageId;
  #182 = NameAndType        #183:#93      // SLOTS_FULL:Lext/mods/gameserver/network/SystemMessageId;
  #183 = Utf8               SLOTS_FULL
  #184 = Fieldref           #185.#186     // ext/mods/Config.IS_CRAFTING_ENABLED:Z
  #185 = Class              #187          // ext/mods/Config
  #186 = NameAndType        #188:#23      // IS_CRAFTING_ENABLED:Z
  #187 = Utf8               ext/mods/Config
  #188 = Utf8               IS_CRAFTING_ENABLED
  #189 = String             #190          // Item creation is currently disabled.
  #190 = Utf8               Item creation is currently disabled.
  #191 = Methodref          #37.#192      // ext/mods/gameserver/model/actor/Player.sendMessage:(Ljava/lang/String;)V
  #192 = NameAndType        #193:#194     // sendMessage:(Ljava/lang/String;)V
  #193 = Utf8               sendMessage
  #194 = Utf8               (Ljava/lang/String;)V
  #195 = Methodref          #37.#196      // ext/mods/gameserver/model/actor/Player.isOnline:()Z
  #196 = NameAndType        #197:#29      // isOnline:()Z
  #197 = Utf8               isOnline
  #198 = Methodref          #170.#199     // ext/mods/gameserver/model/actor/status/PlayerStatus.reduceMp:(D)D
  #199 = NameAndType        #200:#201     // reduceMp:(D)D
  #200 = Utf8               reduceMp
  #201 = Utf8               (D)D
  #202 = Methodref          #111.#203     // ext/mods/gameserver/model/itemcontainer/PcInventory.getAdenaInstance:()Lext/mods/gameserver/model/item/instance/ItemInstance;
  #203 = NameAndType        #204:#205     // getAdenaInstance:()Lext/mods/gameserver/model/item/instance/ItemInstance;
  #204 = Utf8               getAdenaInstance
  #205 = Utf8               ()Lext/mods/gameserver/model/item/instance/ItemInstance;
  #206 = Methodref          #207.#208     // ext/mods/gameserver/model/item/instance/ItemInstance.getObjectId:()I
  #207 = Class              #209          // ext/mods/gameserver/model/item/instance/ItemInstance
  #208 = NameAndType        #210:#48      // getObjectId:()I
  #209 = Utf8               ext/mods/gameserver/model/item/instance/ItemInstance
  #210 = Utf8               getObjectId
  #211 = Methodref          #37.#212      // ext/mods/gameserver/model/actor/Player.transferItem:(IILext/mods/gameserver/model/actor/Playable;)Lext/mods/gameserver/model/item/instance/ItemInstance;
  #212 = NameAndType        #213:#214     // transferItem:(IILext/mods/gameserver/model/actor/Playable;)Lext/mods/gameserver/model/item/instance/ItemInstance;
  #213 = Utf8               transferItem
  #214 = Utf8               (IILext/mods/gameserver/model/actor/Playable;)Lext/mods/gameserver/model/item/instance/ItemInstance;
  #215 = Methodref          #216.#217     // ext/mods/commons/random/Rnd.get:(I)I
  #216 = Class              #218          // ext/mods/commons/random/Rnd
  #217 = NameAndType        #219:#41      // get:(I)I
  #218 = Utf8               ext/mods/commons/random/Rnd
  #219 = Utf8               get
  #220 = Methodref          #25.#221      // ext/mods/gameserver/model/records/Recipe.successRate:()I
  #221 = NameAndType        #222:#48      // successRate:()I
  #222 = Utf8               successRate
  #223 = Methodref          #37.#224      // ext/mods/gameserver/model/actor/Player.getMissions:()Lext/mods/gameserver/model/actor/container/player/MissionList;
  #224 = NameAndType        #225:#226     // getMissions:()Lext/mods/gameserver/model/actor/container/player/MissionList;
  #225 = Utf8               getMissions
  #226 = Utf8               ()Lext/mods/gameserver/model/actor/container/player/MissionList;
  #227 = Fieldref           #228.#229     // ext/mods/gameserver/enums/actors/MissionType.CRAFT_SUCCESS:Lext/mods/gameserver/enums/actors/MissionType;
  #228 = Class              #230          // ext/mods/gameserver/enums/actors/MissionType
  #229 = NameAndType        #231:#232     // CRAFT_SUCCESS:Lext/mods/gameserver/enums/actors/MissionType;
  #230 = Utf8               ext/mods/gameserver/enums/actors/MissionType
  #231 = Utf8               CRAFT_SUCCESS
  #232 = Utf8               Lext/mods/gameserver/enums/actors/MissionType;
  #233 = Methodref          #234.#235     // ext/mods/gameserver/model/actor/container/player/MissionList.update:(Lext/mods/gameserver/enums/actors/MissionType;)V
  #234 = Class              #236          // ext/mods/gameserver/model/actor/container/player/MissionList
  #235 = NameAndType        #237:#238     // update:(Lext/mods/gameserver/enums/actors/MissionType;)V
  #236 = Utf8               ext/mods/gameserver/model/actor/container/player/MissionList
  #237 = Utf8               update
  #238 = Utf8               (Lext/mods/gameserver/enums/actors/MissionType;)V
  #239 = Methodref          #8.#240       // ext/mods/gameserver/model/craft/RecipeItemMaker.rewardPlayer:()V
  #240 = NameAndType        #241:#6       // rewardPlayer:()V
  #241 = Utf8               rewardPlayer
  #242 = Methodref          #8.#243       // ext/mods/gameserver/model/craft/RecipeItemMaker.updateMakeInfo:(Z)V
  #243 = NameAndType        #244:#56      // updateMakeInfo:(Z)V
  #244 = Utf8               updateMakeInfo
  #245 = Fieldref           #89.#246      // ext/mods/gameserver/network/SystemMessageId.CREATION_OF_S2_FOR_S1_AT_S3_ADENA_FAILED:Lext/mods/gameserver/network/SystemMessageId;
  #246 = NameAndType        #247:#93      // CREATION_OF_S2_FOR_S1_AT_S3_ADENA_FAILED:Lext/mods/gameserver/network/SystemMessageId;
  #247 = Utf8               CREATION_OF_S2_FOR_S1_AT_S3_ADENA_FAILED
  #248 = Methodref          #249.#250     // ext/mods/gameserver/network/serverpackets/SystemMessage.getSystemMessage:(Lext/mods/gameserver/network/SystemMessageId;)Lext/mods/gameserver/network/serverpackets/SystemMessage;
  #249 = Class              #251          // ext/mods/gameserver/network/serverpackets/SystemMessage
  #250 = NameAndType        #252:#253     // getSystemMessage:(Lext/mods/gameserver/network/SystemMessageId;)Lext/mods/gameserver/network/serverpackets/SystemMessage;
  #251 = Utf8               ext/mods/gameserver/network/serverpackets/SystemMessage
  #252 = Utf8               getSystemMessage
  #253 = Utf8               (Lext/mods/gameserver/network/SystemMessageId;)Lext/mods/gameserver/network/serverpackets/SystemMessage;
  #254 = Methodref          #249.#255     // ext/mods/gameserver/network/serverpackets/SystemMessage.addCharName:(Lext/mods/gameserver/model/actor/Creature;)Lext/mods/gameserver/network/serverpackets/SystemMessage;
  #255 = NameAndType        #256:#257     // addCharName:(Lext/mods/gameserver/model/actor/Creature;)Lext/mods/gameserver/network/serverpackets/SystemMessage;
  #256 = Utf8               addCharName
  #257 = Utf8               (Lext/mods/gameserver/model/actor/Creature;)Lext/mods/gameserver/network/serverpackets/SystemMessage;
  #258 = Methodref          #106.#259     // ext/mods/gameserver/model/holder/IntIntHolder.getId:()I
  #259 = NameAndType        #260:#48      // getId:()I
  #260 = Utf8               getId
  #261 = Methodref          #249.#262     // ext/mods/gameserver/network/serverpackets/SystemMessage.addItemName:(I)Lext/mods/gameserver/network/serverpackets/SystemMessage;
  #262 = NameAndType        #263:#264     // addItemName:(I)Lext/mods/gameserver/network/serverpackets/SystemMessage;
  #263 = Utf8               addItemName
  #264 = Utf8               (I)Lext/mods/gameserver/network/serverpackets/SystemMessage;
  #265 = Methodref          #249.#266     // ext/mods/gameserver/network/serverpackets/SystemMessage.addItemNumber:(I)Lext/mods/gameserver/network/serverpackets/SystemMessage;
  #266 = NameAndType        #267:#264     // addItemNumber:(I)Lext/mods/gameserver/network/serverpackets/SystemMessage;
  #267 = Utf8               addItemNumber
  #268 = Fieldref           #89.#269      // ext/mods/gameserver/network/SystemMessageId.S1_FAILED_TO_CREATE_S2_FOR_S3_ADENA:Lext/mods/gameserver/network/SystemMessageId;
  #269 = NameAndType        #270:#93      // S1_FAILED_TO_CREATE_S2_FOR_S3_ADENA:Lext/mods/gameserver/network/SystemMessageId;
  #270 = Utf8               S1_FAILED_TO_CREATE_S2_FOR_S3_ADENA
  #271 = Fieldref           #89.#272      // ext/mods/gameserver/network/SystemMessageId.ITEM_MIXING_FAILED:Lext/mods/gameserver/network/SystemMessageId;
  #272 = NameAndType        #273:#93      // ITEM_MIXING_FAILED:Lext/mods/gameserver/network/SystemMessageId;
  #273 = Utf8               ITEM_MIXING_FAILED
  #274 = Fieldref           #228.#275     // ext/mods/gameserver/enums/actors/MissionType.CRAFT_FAIL:Lext/mods/gameserver/enums/actors/MissionType;
  #275 = NameAndType        #276:#232     // CRAFT_FAIL:Lext/mods/gameserver/enums/actors/MissionType;
  #276 = Utf8               CRAFT_FAIL
  #277 = Class              #278          // ext/mods/gameserver/network/serverpackets/RecipeItemMakeInfo
  #278 = Utf8               ext/mods/gameserver/network/serverpackets/RecipeItemMakeInfo
  #279 = Methodref          #277.#280     // ext/mods/gameserver/network/serverpackets/RecipeItemMakeInfo."<init>":(ILext/mods/gameserver/model/actor/Player;I)V
  #280 = NameAndType        #5:#281       // "<init>":(ILext/mods/gameserver/model/actor/Player;I)V
  #281 = Utf8               (ILext/mods/gameserver/model/actor/Player;I)V
  #282 = Class              #283          // ext/mods/gameserver/network/serverpackets/RecipeShopItemInfo
  #283 = Utf8               ext/mods/gameserver/network/serverpackets/RecipeShopItemInfo
  #284 = Methodref          #282.#285     // ext/mods/gameserver/network/serverpackets/RecipeShopItemInfo."<init>":(Lext/mods/gameserver/model/actor/Player;I)V
  #285 = NameAndType        #5:#286       // "<init>":(Lext/mods/gameserver/model/actor/Player;I)V
  #286 = Utf8               (Lext/mods/gameserver/model/actor/Player;I)V
  #287 = Methodref          #25.#288      // ext/mods/gameserver/model/records/Recipe.materials:()Ljava/util/List;
  #288 = NameAndType        #289:#290     // materials:()Ljava/util/List;
  #289 = Utf8               materials
  #290 = Utf8               ()Ljava/util/List;
  #291 = InterfaceMethodref #292.#128     // java/util/List.iterator:()Ljava/util/Iterator;
  #292 = Class              #293          // java/util/List
  #293 = Utf8               java/util/List
  #294 = Methodref          #106.#295     // ext/mods/gameserver/model/holder/IntIntHolder.getValue:()I
  #295 = NameAndType        #296:#48      // getValue:()I
  #296 = Utf8               getValue
  #297 = Methodref          #298.#299     // ext/mods/gameserver/model/itemcontainer/Inventory.getItemByItemId:(I)Lext/mods/gameserver/model/item/instance/ItemInstance;
  #298 = Class              #300          // ext/mods/gameserver/model/itemcontainer/Inventory
  #299 = NameAndType        #301:#302     // getItemByItemId:(I)Lext/mods/gameserver/model/item/instance/ItemInstance;
  #300 = Utf8               ext/mods/gameserver/model/itemcontainer/Inventory
  #301 = Utf8               getItemByItemId
  #302 = Utf8               (I)Lext/mods/gameserver/model/item/instance/ItemInstance;
  #303 = Methodref          #207.#304     // ext/mods/gameserver/model/item/instance/ItemInstance.getCount:()I
  #304 = NameAndType        #305:#48      // getCount:()I
  #305 = Utf8               getCount
  #306 = Fieldref           #89.#307      // ext/mods/gameserver/network/SystemMessageId.MISSING_S2_S1_TO_CREATE:Lext/mods/gameserver/network/SystemMessageId;
  #307 = NameAndType        #308:#93      // MISSING_S2_S1_TO_CREATE:Lext/mods/gameserver/network/SystemMessageId;
  #308 = Utf8               MISSING_S2_S1_TO_CREATE
  #309 = Methodref          #298.#310     // ext/mods/gameserver/model/itemcontainer/Inventory.destroyItemByItemId:(II)Lext/mods/gameserver/model/item/instance/ItemInstance;
  #310 = NameAndType        #311:#312     // destroyItemByItemId:(II)Lext/mods/gameserver/model/item/instance/ItemInstance;
  #311 = Utf8               destroyItemByItemId
  #312 = Utf8               (II)Lext/mods/gameserver/model/item/instance/ItemInstance;
  #313 = Fieldref           #89.#314      // ext/mods/gameserver/network/SystemMessageId.S2_S1_DISAPPEARED:Lext/mods/gameserver/network/SystemMessageId;
  #314 = NameAndType        #315:#93      // S2_S1_DISAPPEARED:Lext/mods/gameserver/network/SystemMessageId;
  #315 = Utf8               S2_S1_DISAPPEARED
  #316 = Fieldref           #89.#317      // ext/mods/gameserver/network/SystemMessageId.S1_DISAPPEARED:Lext/mods/gameserver/network/SystemMessageId;
  #317 = NameAndType        #318:#93      // S1_DISAPPEARED:Lext/mods/gameserver/network/SystemMessageId;
  #318 = Utf8               S1_DISAPPEARED
  #319 = Methodref          #111.#320     // ext/mods/gameserver/model/itemcontainer/PcInventory.addItem:(II)Lext/mods/gameserver/model/item/instance/ItemInstance;
  #320 = NameAndType        #321:#312     // addItem:(II)Lext/mods/gameserver/model/item/instance/ItemInstance;
  #321 = Utf8               addItem
  #322 = Fieldref           #89.#323      // ext/mods/gameserver/network/SystemMessageId.S2_CREATED_FOR_S1_FOR_S3_ADENA:Lext/mods/gameserver/network/SystemMessageId;
  #323 = NameAndType        #324:#93      // S2_CREATED_FOR_S1_FOR_S3_ADENA:Lext/mods/gameserver/network/SystemMessageId;
  #324 = Utf8               S2_CREATED_FOR_S1_FOR_S3_ADENA
  #325 = Methodref          #37.#326      // ext/mods/gameserver/model/actor/Player.getName:()Ljava/lang/String;
  #326 = NameAndType        #327:#328     // getName:()Ljava/lang/String;
  #327 = Utf8               getName
  #328 = Utf8               ()Ljava/lang/String;
  #329 = Methodref          #249.#330     // ext/mods/gameserver/network/serverpackets/SystemMessage.addString:(Ljava/lang/String;)Lext/mods/gameserver/network/serverpackets/SystemMessage;
  #330 = NameAndType        #331:#332     // addString:(Ljava/lang/String;)Lext/mods/gameserver/network/serverpackets/SystemMessage;
  #331 = Utf8               addString
  #332 = Utf8               (Ljava/lang/String;)Lext/mods/gameserver/network/serverpackets/SystemMessage;
  #333 = Fieldref           #89.#334      // ext/mods/gameserver/network/SystemMessageId.S1_CREATED_S2_FOR_S3_ADENA:Lext/mods/gameserver/network/SystemMessageId;
  #334 = NameAndType        #335:#93      // S1_CREATED_S2_FOR_S3_ADENA:Lext/mods/gameserver/network/SystemMessageId;
  #335 = Utf8               S1_CREATED_S2_FOR_S3_ADENA
  #336 = Fieldref           #89.#337      // ext/mods/gameserver/network/SystemMessageId.S2_S3_S_CREATED_FOR_S1_FOR_S4_ADENA:Lext/mods/gameserver/network/SystemMessageId;
  #337 = NameAndType        #338:#93      // S2_S3_S_CREATED_FOR_S1_FOR_S4_ADENA:Lext/mods/gameserver/network/SystemMessageId;
  #338 = Utf8               S2_S3_S_CREATED_FOR_S1_FOR_S4_ADENA
  #339 = Methodref          #249.#340     // ext/mods/gameserver/network/serverpackets/SystemMessage.addNumber:(I)Lext/mods/gameserver/network/serverpackets/SystemMessage;
  #340 = NameAndType        #341:#264     // addNumber:(I)Lext/mods/gameserver/network/serverpackets/SystemMessage;
  #341 = Utf8               addNumber
  #342 = Fieldref           #89.#343      // ext/mods/gameserver/network/SystemMessageId.S1_CREATED_S2_S3_S_FOR_S4_ADENA:Lext/mods/gameserver/network/SystemMessageId;
  #343 = NameAndType        #344:#93      // S1_CREATED_S2_S3_S_FOR_S4_ADENA:Lext/mods/gameserver/network/SystemMessageId;
  #344 = Utf8               S1_CREATED_S2_S3_S_FOR_S4_ADENA
  #345 = Fieldref           #89.#346      // ext/mods/gameserver/network/SystemMessageId.EARNED_S2_S1_S:Lext/mods/gameserver/network/SystemMessageId;
  #346 = NameAndType        #347:#93      // EARNED_S2_S1_S:Lext/mods/gameserver/network/SystemMessageId;
  #347 = Utf8               EARNED_S2_S1_S
  #348 = Fieldref           #89.#349      // ext/mods/gameserver/network/SystemMessageId.EARNED_ITEM_S1:Lext/mods/gameserver/network/SystemMessageId;
  #349 = NameAndType        #350:#93      // EARNED_ITEM_S1:Lext/mods/gameserver/network/SystemMessageId;
  #350 = Utf8               EARNED_ITEM_S1
  #351 = Methodref          #37.#352      // ext/mods/gameserver/model/actor/Player.sendIU:()V
  #352 = NameAndType        #353:#6       // sendIU:()V
  #353 = Utf8               sendIU
  #354 = Class              #355          // java/lang/Runnable
  #355 = Utf8               java/lang/Runnable
  #356 = Utf8               (Lext/mods/gameserver/model/actor/Player;Lext/mods/gameserver/model/records/Recipe;Lext/mods/gameserver/model/actor/Player;)V
  #357 = Utf8               Code
  #358 = Utf8               LineNumberTable
  #359 = Utf8               LocalVariableTable
  #360 = Utf8               temp
  #361 = Utf8               Lext/mods/gameserver/model/records/ManufactureItem;
  #362 = Utf8               this
  #363 = Utf8               Lext/mods/gameserver/model/craft/RecipeItemMaker;
  #364 = Utf8               player
  #365 = Utf8               recipe
  #366 = Utf8               target
  #367 = Utf8               StackMapTable
  #368 = Utf8               run
  #369 = Utf8               adenaTransfer
  #370 = Utf8               Lext/mods/gameserver/model/item/instance/ItemInstance;
  #371 = Utf8               success
  #372 = Utf8               item
  #373 = Utf8               quantity
  #374 = Utf8               material
  #375 = Utf8               Lext/mods/gameserver/model/holder/IntIntHolder;
  #376 = Utf8               remove
  #377 = Utf8               inv
  #378 = Utf8               Lext/mods/gameserver/model/itemcontainer/Inventory;
  #379 = Utf8               gotAllMats
  #380 = Utf8               itemId
  #381 = Utf8               itemCount
  #382 = Utf8               isValid
  #383 = Utf8               SourceFile
  #384 = Utf8               RecipeItemMaker.java
{
  protected final ext.mods.gameserver.model.records.Recipe _recipe;
    descriptor: Lext/mods/gameserver/model/records/Recipe;
    flags: (0x0014) ACC_PROTECTED, ACC_FINAL

  protected final ext.mods.gameserver.model.actor.Player _player;
    descriptor: Lext/mods/gameserver/model/actor/Player;
    flags: (0x0014) ACC_PROTECTED, ACC_FINAL

  protected final ext.mods.gameserver.model.actor.Player _target;
    descriptor: Lext/mods/gameserver/model/actor/Player;
    flags: (0x0014) ACC_PROTECTED, ACC_FINAL

  protected final int _skillId;
    descriptor: I
    flags: (0x0014) ACC_PROTECTED, ACC_FINAL

  protected final int _skillLevel;
    descriptor: I
    flags: (0x0014) ACC_PROTECTED, ACC_FINAL

  protected double _manaRequired;
    descriptor: D
    flags: (0x0004) ACC_PROTECTED

  protected int _price;
    descriptor: I
    flags: (0x0004) ACC_PROTECTED

  public ext.mods.gameserver.model.craft.RecipeItemMaker(ext.mods.gameserver.model.actor.Player, ext.mods.gameserver.model.records.Recipe, ext.mods.gameserver.model.actor.Player);
    descriptor: (Lext/mods/gameserver/model/actor/Player;Lext/mods/gameserver/model/records/Recipe;Lext/mods/gameserver/model/actor/Player;)V
    flags: (0x0001) ACC_PUBLIC
    Code:
      stack=4, locals=6, args_size=4
         0: aload_0
         1: invokespecial #1                  // Method java/lang/Object."<init>":()V
         4: aload_0
         5: aload_1
         6: putfield      #7                  // Field _player:Lext/mods/gameserver/model/actor/Player;
         9: aload_0
        10: aload_3
        11: putfield      #13                 // Field _target:Lext/mods/gameserver/model/actor/Player;
        14: aload_0
        15: aload_2
        16: putfield      #16                 // Field _recipe:Lext/mods/gameserver/model/records/Recipe;
        19: aload_0
        20: iconst_0
        21: putfield      #20                 // Field _isValid:Z
        24: aload_0
        25: aload_0
        26: getfield      #16                 // Field _recipe:Lext/mods/gameserver/model/records/Recipe;
        29: invokevirtual #24                 // Method ext/mods/gameserver/model/records/Recipe.isDwarven:()Z
        32: ifeq          41
        35: sipush        172
        38: goto          44
        41: sipush        1320
        44: putfield      #32                 // Field _skillId:I
        47: aload_0
        48: aload_0
        49: getfield      #7                  // Field _player:Lext/mods/gameserver/model/actor/Player;
        52: aload_0
        53: getfield      #32                 // Field _skillId:I
        56: invokevirtual #36                 // Method ext/mods/gameserver/model/actor/Player.getSkillLevel:(I)I
        59: putfield      #42                 // Field _skillLevel:I
        62: aload_0
        63: aload_0
        64: getfield      #16                 // Field _recipe:Lext/mods/gameserver/model/records/Recipe;
        67: invokevirtual #45                 // Method ext/mods/gameserver/model/records/Recipe.mpCost:()I
        70: i2d
        71: putfield      #49                 // Field _manaRequired:D
        74: aload_0
        75: getfield      #7                  // Field _player:Lext/mods/gameserver/model/actor/Player;
        78: iconst_1
        79: invokevirtual #53                 // Method ext/mods/gameserver/model/actor/Player.setCrafting:(Z)V
        82: aload_0
        83: getfield      #7                  // Field _player:Lext/mods/gameserver/model/actor/Player;
        86: invokevirtual #57                 // Method ext/mods/gameserver/model/actor/Player.isAlikeDead:()Z
        89: ifne          102
        92: aload_0
        93: getfield      #13                 // Field _target:Lext/mods/gameserver/model/actor/Player;
        96: invokevirtual #57                 // Method ext/mods/gameserver/model/actor/Player.isAlikeDead:()Z
        99: ifeq          117
       102: aload_0
       103: getfield      #7                  // Field _player:Lext/mods/gameserver/model/actor/Player;
       106: getstatic     #60                 // Field ext/mods/gameserver/network/serverpackets/ActionFailed.STATIC_PACKET:Lext/mods/gameserver/network/serverpackets/ActionFailed;
       109: invokevirtual #66                 // Method ext/mods/gameserver/model/actor/Player.sendPacket:(Lext/mods/gameserver/network/serverpackets/L2GameServerPacket;)V
       112: aload_0
       113: invokevirtual #70                 // Method abort:()V
       116: return
       117: aload_0
       118: getfield      #7                  // Field _player:Lext/mods/gameserver/model/actor/Player;
       121: invokevirtual #73                 // Method ext/mods/gameserver/model/actor/Player.isProcessingTransaction:()Z
       124: ifne          137
       127: aload_0
       128: getfield      #13                 // Field _target:Lext/mods/gameserver/model/actor/Player;
       131: invokevirtual #73                 // Method ext/mods/gameserver/model/actor/Player.isProcessingTransaction:()Z
       134: ifeq          152
       137: aload_0
       138: getfield      #13                 // Field _target:Lext/mods/gameserver/model/actor/Player;
       141: getstatic     #60                 // Field ext/mods/gameserver/network/serverpackets/ActionFailed.STATIC_PACKET:Lext/mods/gameserver/network/serverpackets/ActionFailed;
       144: invokevirtual #66                 // Method ext/mods/gameserver/model/actor/Player.sendPacket:(Lext/mods/gameserver/network/serverpackets/L2GameServerPacket;)V
       147: aload_0
       148: invokevirtual #70                 // Method abort:()V
       151: return
       152: aload_0
       153: getfield      #7                  // Field _player:Lext/mods/gameserver/model/actor/Player;
       156: invokevirtual #76                 // Method ext/mods/gameserver/model/actor/Player.getCast:()Lext/mods/gameserver/model/actor/cast/PlayerCast;
       159: invokevirtual #80                 // Method ext/mods/gameserver/model/actor/cast/PlayerCast.isCastingNow:()Z
       162: ifne          175
       165: aload_0
       166: getfield      #7                  // Field _player:Lext/mods/gameserver/model/actor/Player;
       169: invokevirtual #85                 // Method ext/mods/gameserver/model/actor/Player.isAllSkillsDisabled:()Z
       172: ifeq          186
       175: aload_0
       176: getfield      #7                  // Field _player:Lext/mods/gameserver/model/actor/Player;
       179: getstatic     #88                 // Field ext/mods/gameserver/network/SystemMessageId.NO_RECIPE_BOOK_WHILE_CASTING:Lext/mods/gameserver/network/SystemMessageId;
       182: invokevirtual #94                 // Method ext/mods/gameserver/model/actor/Player.sendPacket:(Lext/mods/gameserver/network/SystemMessageId;)V
       185: return
       186: aload_0
       187: getfield      #13                 // Field _target:Lext/mods/gameserver/model/actor/Player;
       190: invokevirtual #97                 // Method ext/mods/gameserver/model/actor/Player.getInventory:()Lext/mods/gameserver/model/itemcontainer/PcInventory;
       193: aload_0
       194: getfield      #16                 // Field _recipe:Lext/mods/gameserver/model/records/Recipe;
       197: invokevirtual #101                // Method ext/mods/gameserver/model/records/Recipe.product:()Lext/mods/gameserver/model/holder/IntIntHolder;
       200: invokevirtual #105                // Method ext/mods/gameserver/model/holder/IntIntHolder.getWeight:()I
       203: invokevirtual #110                // Method ext/mods/gameserver/model/itemcontainer/PcInventory.validateWeight:(I)Z
       206: ifne          234
       209: aload_0
       210: getfield      #13                 // Field _target:Lext/mods/gameserver/model/actor/Player;
       213: getstatic     #116                // Field ext/mods/gameserver/network/SystemMessageId.WEIGHT_LIMIT_EXCEEDED:Lext/mods/gameserver/network/SystemMessageId;
       216: invokevirtual #94                 // Method ext/mods/gameserver/model/actor/Player.sendPacket:(Lext/mods/gameserver/network/SystemMessageId;)V
       219: aload_0
       220: getfield      #13                 // Field _target:Lext/mods/gameserver/model/actor/Player;
       223: getstatic     #60                 // Field ext/mods/gameserver/network/serverpackets/ActionFailed.STATIC_PACKET:Lext/mods/gameserver/network/serverpackets/ActionFailed;
       226: invokevirtual #66                 // Method ext/mods/gameserver/model/actor/Player.sendPacket:(Lext/mods/gameserver/network/serverpackets/L2GameServerPacket;)V
       229: aload_0
       230: invokevirtual #70                 // Method abort:()V
       233: return
       234: aload_0
       235: getfield      #16                 // Field _recipe:Lext/mods/gameserver/model/records/Recipe;
       238: invokevirtual #119                // Method ext/mods/gameserver/model/records/Recipe.level:()I
       241: aload_0
       242: getfield      #42                 // Field _skillLevel:I
       245: if_icmple     263
       248: aload_0
       249: getfield      #7                  // Field _player:Lext/mods/gameserver/model/actor/Player;
       252: getstatic     #60                 // Field ext/mods/gameserver/network/serverpackets/ActionFailed.STATIC_PACKET:Lext/mods/gameserver/network/serverpackets/ActionFailed;
       255: invokevirtual #66                 // Method ext/mods/gameserver/model/actor/Player.sendPacket:(Lext/mods/gameserver/network/serverpackets/L2GameServerPacket;)V
       258: aload_0
       259: invokevirtual #70                 // Method abort:()V
       262: return
       263: aload_0
       264: getfield      #7                  // Field _player:Lext/mods/gameserver/model/actor/Player;
       267: aload_0
       268: getfield      #13                 // Field _target:Lext/mods/gameserver/model/actor/Player;
       271: if_acmpeq     364
       274: aload_0
       275: getfield      #7                  // Field _player:Lext/mods/gameserver/model/actor/Player;
       278: invokevirtual #122                // Method ext/mods/gameserver/model/actor/Player.getManufactureList:()Lext/mods/gameserver/model/craft/ManufactureList;
       281: invokevirtual #126                // Method ext/mods/gameserver/model/craft/ManufactureList.iterator:()Ljava/util/Iterator;
       284: astore        4
       286: aload         4
       288: invokeinterface #132,  1          // InterfaceMethod java/util/Iterator.hasNext:()Z
       293: ifeq          364
       296: aload         4
       298: invokeinterface #137,  1          // InterfaceMethod java/util/Iterator.next:()Ljava/lang/Object;
       303: checkcast     #141                // class ext/mods/gameserver/model/records/ManufactureItem
       306: astore        5
       308: aload         5
       310: invokevirtual #143                // Method ext/mods/gameserver/model/records/ManufactureItem.recipeId:()I
       313: aload_0
       314: getfield      #16                 // Field _recipe:Lext/mods/gameserver/model/records/Recipe;
       317: invokevirtual #146                // Method ext/mods/gameserver/model/records/Recipe.id:()I
       320: if_icmpne     361
       323: aload_0
       324: aload         5
       326: invokevirtual #149                // Method ext/mods/gameserver/model/records/ManufactureItem.cost:()I
       329: putfield      #152                // Field _price:I
       332: aload_0
       333: getfield      #13                 // Field _target:Lext/mods/gameserver/model/actor/Player;
       336: invokevirtual #155                // Method ext/mods/gameserver/model/actor/Player.getAdena:()I
       339: aload_0
       340: getfield      #152                // Field _price:I
       343: if_icmpge     364
       346: aload_0
       347: getfield      #13                 // Field _target:Lext/mods/gameserver/model/actor/Player;
       350: getstatic     #158                // Field ext/mods/gameserver/network/SystemMessageId.YOU_NOT_ENOUGH_ADENA:Lext/mods/gameserver/network/SystemMessageId;
       353: invokevirtual #94                 // Method ext/mods/gameserver/model/actor/Player.sendPacket:(Lext/mods/gameserver/network/SystemMessageId;)V
       356: aload_0
       357: invokevirtual #70                 // Method abort:()V
       360: return
       361: goto          286
       364: aload_0
       365: iconst_0
       366: invokevirtual #161                // Method listItems:(Z)Z
       369: ifne          377
       372: aload_0
       373: invokevirtual #70                 // Method abort:()V
       376: return
       377: aload_0
       378: getfield      #7                  // Field _player:Lext/mods/gameserver/model/actor/Player;
       381: invokevirtual #165                // Method ext/mods/gameserver/model/actor/Player.getStatus:()Lext/mods/gameserver/model/actor/status/PlayerStatus;
       384: invokevirtual #169                // Method ext/mods/gameserver/model/actor/status/PlayerStatus.getMp:()D
       387: aload_0
       388: getfield      #49                 // Field _manaRequired:D
       391: dcmpg
       392: ifge          410
       395: aload_0
       396: getfield      #13                 // Field _target:Lext/mods/gameserver/model/actor/Player;
       399: getstatic     #175                // Field ext/mods/gameserver/network/SystemMessageId.NOT_ENOUGH_MP:Lext/mods/gameserver/network/SystemMessageId;
       402: invokevirtual #94                 // Method ext/mods/gameserver/model/actor/Player.sendPacket:(Lext/mods/gameserver/network/SystemMessageId;)V
       405: aload_0
       406: invokevirtual #70                 // Method abort:()V
       409: return
       410: aload_0
       411: getfield      #13                 // Field _target:Lext/mods/gameserver/model/actor/Player;
       414: invokevirtual #97                 // Method ext/mods/gameserver/model/actor/Player.getInventory:()Lext/mods/gameserver/model/itemcontainer/PcInventory;
       417: iconst_1
       418: invokevirtual #178                // Method ext/mods/gameserver/model/itemcontainer/PcInventory.validateCapacity:(I)Z
       421: ifne          439
       424: aload_0
       425: getfield      #13                 // Field _target:Lext/mods/gameserver/model/actor/Player;
       428: getstatic     #181                // Field ext/mods/gameserver/network/SystemMessageId.SLOTS_FULL:Lext/mods/gameserver/network/SystemMessageId;
       431: invokevirtual #94                 // Method ext/mods/gameserver/model/actor/Player.sendPacket:(Lext/mods/gameserver/network/SystemMessageId;)V
       434: aload_0
       435: invokevirtual #70                 // Method abort:()V
       438: return
       439: aload_0
       440: getfield      #7                  // Field _player:Lext/mods/gameserver/model/actor/Player;
       443: iconst_0
       444: invokevirtual #53                 // Method ext/mods/gameserver/model/actor/Player.setCrafting:(Z)V
       447: aload_0
       448: iconst_1
       449: putfield      #20                 // Field _isValid:Z
       452: return
      LineNumberTable:
        line 55: 0
        line 56: 4
        line 57: 9
        line 58: 14
        line 60: 19
        line 61: 24
        line 62: 47
        line 64: 62
        line 66: 74
        line 68: 82
        line 70: 102
        line 71: 112
        line 72: 116
        line 75: 117
        line 77: 137
        line 78: 147
        line 79: 151
        line 82: 152
        line 84: 175
        line 85: 185
        line 88: 186
        line 90: 209
        line 91: 219
        line 92: 229
        line 93: 233
        line 96: 234
        line 98: 248
        line 99: 258
        line 100: 262
        line 103: 263
        line 105: 274
        line 107: 308
        line 109: 323
        line 110: 332
        line 112: 346
        line 113: 356
        line 114: 360
        line 118: 361
        line 121: 364
        line 123: 372
        line 124: 376
        line 127: 377
        line 129: 395
        line 130: 405
        line 131: 409
        line 134: 410
        line 136: 424
        line 137: 434
        line 138: 438
        line 141: 439
        line 142: 447
        line 143: 452
      LocalVariableTable:
        Start  Length  Slot  Name   Signature
          308      53     5  temp   Lext/mods/gameserver/model/records/ManufactureItem;
            0     453     0  this   Lext/mods/gameserver/model/craft/RecipeItemMaker;
            0     453     1 player   Lext/mods/gameserver/model/actor/Player;
            0     453     2 recipe   Lext/mods/gameserver/model/records/Recipe;
            0     453     3 target   Lext/mods/gameserver/model/actor/Player;
      StackMapTable: number_of_entries = 16
        frame_type = 255 /* full_frame */
          offset_delta = 41
          locals = [ class ext/mods/gameserver/model/craft/RecipeItemMaker, class ext/mods/gameserver/model/actor/Player, class ext/mods/gameserver/model/records/Recipe, class ext/mods/gameserver/model/actor/Player ]
          stack = [ class ext/mods/gameserver/model/craft/RecipeItemMaker ]
        frame_type = 255 /* full_frame */
          offset_delta = 2
          locals = [ class ext/mods/gameserver/model/craft/RecipeItemMaker, class ext/mods/gameserver/model/actor/Player, class ext/mods/gameserver/model/records/Recipe, class ext/mods/gameserver/model/actor/Player ]
          stack = [ class ext/mods/gameserver/model/craft/RecipeItemMaker, int ]
        frame_type = 57 /* same */
        frame_type = 14 /* same */
        frame_type = 19 /* same */
        frame_type = 14 /* same */
        frame_type = 22 /* same */
        frame_type = 10 /* same */
        frame_type = 47 /* same */
        frame_type = 28 /* same */
        frame_type = 252 /* append */
          offset_delta = 22
          locals = [ class java/util/Iterator ]
        frame_type = 251 /* same_frame_extended */
          offset_delta = 74
        frame_type = 250 /* chop */
          offset_delta = 2
        frame_type = 12 /* same */
        frame_type = 32 /* same */
        frame_type = 28 /* same */

  public void run();
    descriptor: ()V
    flags: (0x0001) ACC_PUBLIC
    Code:
      stack=4, locals=2, args_size=1
         0: getstatic     #184                // Field ext/mods/Config.IS_CRAFTING_ENABLED:Z
         3: ifne          20
         6: aload_0
         7: getfield      #13                 // Field _target:Lext/mods/gameserver/model/actor/Player;
        10: ldc           #189                // String Item creation is currently disabled.
        12: invokevirtual #191                // Method ext/mods/gameserver/model/actor/Player.sendMessage:(Ljava/lang/String;)V
        15: aload_0
        16: invokevirtual #70                 // Method abort:()V
        19: return
        20: aload_0
        21: getfield      #7                  // Field _player:Lext/mods/gameserver/model/actor/Player;
        24: ifnull        34
        27: aload_0
        28: getfield      #13                 // Field _target:Lext/mods/gameserver/model/actor/Player;
        31: ifnonnull     39
        34: aload_0
        35: invokevirtual #70                 // Method abort:()V
        38: return
        39: aload_0
        40: getfield      #7                  // Field _player:Lext/mods/gameserver/model/actor/Player;
        43: invokevirtual #195                // Method ext/mods/gameserver/model/actor/Player.isOnline:()Z
        46: ifeq          59
        49: aload_0
        50: getfield      #13                 // Field _target:Lext/mods/gameserver/model/actor/Player;
        53: invokevirtual #195                // Method ext/mods/gameserver/model/actor/Player.isOnline:()Z
        56: ifne          64
        59: aload_0
        60: invokevirtual #70                 // Method abort:()V
        63: return
        64: aload_0
        65: getfield      #7                  // Field _player:Lext/mods/gameserver/model/actor/Player;
        68: invokevirtual #165                // Method ext/mods/gameserver/model/actor/Player.getStatus:()Lext/mods/gameserver/model/actor/status/PlayerStatus;
        71: aload_0
        72: getfield      #49                 // Field _manaRequired:D
        75: invokevirtual #198                // Method ext/mods/gameserver/model/actor/status/PlayerStatus.reduceMp:(D)D
        78: pop2
        79: aload_0
        80: getfield      #13                 // Field _target:Lext/mods/gameserver/model/actor/Player;
        83: aload_0
        84: getfield      #7                  // Field _player:Lext/mods/gameserver/model/actor/Player;
        87: if_acmpeq     145
        90: aload_0
        91: getfield      #152                // Field _price:I
        94: ifle          145
        97: aload_0
        98: getfield      #13                 // Field _target:Lext/mods/gameserver/model/actor/Player;
       101: aload_0
       102: getfield      #13                 // Field _target:Lext/mods/gameserver/model/actor/Player;
       105: invokevirtual #97                 // Method ext/mods/gameserver/model/actor/Player.getInventory:()Lext/mods/gameserver/model/itemcontainer/PcInventory;
       108: invokevirtual #202                // Method ext/mods/gameserver/model/itemcontainer/PcInventory.getAdenaInstance:()Lext/mods/gameserver/model/item/instance/ItemInstance;
       111: invokevirtual #206                // Method ext/mods/gameserver/model/item/instance/ItemInstance.getObjectId:()I
       114: aload_0
       115: getfield      #152                // Field _price:I
       118: aload_0
       119: getfield      #7                  // Field _player:Lext/mods/gameserver/model/actor/Player;
       122: invokevirtual #211                // Method ext/mods/gameserver/model/actor/Player.transferItem:(IILext/mods/gameserver/model/actor/Playable;)Lext/mods/gameserver/model/item/instance/ItemInstance;
       125: astore_1
       126: aload_1
       127: ifnonnull     145
       130: aload_0
       131: getfield      #13                 // Field _target:Lext/mods/gameserver/model/actor/Player;
       134: getstatic     #158                // Field ext/mods/gameserver/network/SystemMessageId.YOU_NOT_ENOUGH_ADENA:Lext/mods/gameserver/network/SystemMessageId;
       137: invokevirtual #94                 // Method ext/mods/gameserver/model/actor/Player.sendPacket:(Lext/mods/gameserver/network/SystemMessageId;)V
       140: aload_0
       141: invokevirtual #70                 // Method abort:()V
       144: return
       145: aload_0
       146: iconst_1
       147: invokevirtual #161                // Method listItems:(Z)Z
       150: ifne          158
       153: aload_0
       154: invokevirtual #70                 // Method abort:()V
       157: return
       158: bipush        100
       160: invokestatic  #215                // Method ext/mods/commons/random/Rnd.get:(I)I
       163: aload_0
       164: getfield      #16                 // Field _recipe:Lext/mods/gameserver/model/records/Recipe;
       167: invokevirtual #220                // Method ext/mods/gameserver/model/records/Recipe.successRate:()I
       170: if_icmpge     198
       173: aload_0
       174: getfield      #7                  // Field _player:Lext/mods/gameserver/model/actor/Player;
       177: invokevirtual #223                // Method ext/mods/gameserver/model/actor/Player.getMissions:()Lext/mods/gameserver/model/actor/container/player/MissionList;
       180: getstatic     #227                // Field ext/mods/gameserver/enums/actors/MissionType.CRAFT_SUCCESS:Lext/mods/gameserver/enums/actors/MissionType;
       183: invokevirtual #233                // Method ext/mods/gameserver/model/actor/container/player/MissionList.update:(Lext/mods/gameserver/enums/actors/MissionType;)V
       186: aload_0
       187: invokevirtual #239                // Method rewardPlayer:()V
       190: aload_0
       191: iconst_1
       192: invokevirtual #242                // Method updateMakeInfo:(Z)V
       195: goto          320
       198: aload_0
       199: getfield      #13                 // Field _target:Lext/mods/gameserver/model/actor/Player;
       202: aload_0
       203: getfield      #7                  // Field _player:Lext/mods/gameserver/model/actor/Player;
       206: if_acmpeq     292
       209: aload_0
       210: getfield      #7                  // Field _player:Lext/mods/gameserver/model/actor/Player;
       213: getstatic     #245                // Field ext/mods/gameserver/network/SystemMessageId.CREATION_OF_S2_FOR_S1_AT_S3_ADENA_FAILED:Lext/mods/gameserver/network/SystemMessageId;
       216: invokestatic  #248                // Method ext/mods/gameserver/network/serverpackets/SystemMessage.getSystemMessage:(Lext/mods/gameserver/network/SystemMessageId;)Lext/mods/gameserver/network/serverpackets/SystemMessage;
       219: aload_0
       220: getfield      #13                 // Field _target:Lext/mods/gameserver/model/actor/Player;
       223: invokevirtual #254                // Method ext/mods/gameserver/network/serverpackets/SystemMessage.addCharName:(Lext/mods/gameserver/model/actor/Creature;)Lext/mods/gameserver/network/serverpackets/SystemMessage;
       226: aload_0
       227: getfield      #16                 // Field _recipe:Lext/mods/gameserver/model/records/Recipe;
       230: invokevirtual #101                // Method ext/mods/gameserver/model/records/Recipe.product:()Lext/mods/gameserver/model/holder/IntIntHolder;
       233: invokevirtual #258                // Method ext/mods/gameserver/model/holder/IntIntHolder.getId:()I
       236: invokevirtual #261                // Method ext/mods/gameserver/network/serverpackets/SystemMessage.addItemName:(I)Lext/mods/gameserver/network/serverpackets/SystemMessage;
       239: aload_0
       240: getfield      #152                // Field _price:I
       243: invokevirtual #265                // Method ext/mods/gameserver/network/serverpackets/SystemMessage.addItemNumber:(I)Lext/mods/gameserver/network/serverpackets/SystemMessage;
       246: invokevirtual #66                 // Method ext/mods/gameserver/model/actor/Player.sendPacket:(Lext/mods/gameserver/network/serverpackets/L2GameServerPacket;)V
       249: aload_0
       250: getfield      #13                 // Field _target:Lext/mods/gameserver/model/actor/Player;
       253: getstatic     #268                // Field ext/mods/gameserver/network/SystemMessageId.S1_FAILED_TO_CREATE_S2_FOR_S3_ADENA:Lext/mods/gameserver/network/SystemMessageId;
       256: invokestatic  #248                // Method ext/mods/gameserver/network/serverpackets/SystemMessage.getSystemMessage:(Lext/mods/gameserver/network/SystemMessageId;)Lext/mods/gameserver/network/serverpackets/SystemMessage;
       259: aload_0
       260: getfield      #7                  // Field _player:Lext/mods/gameserver/model/actor/Player;
       263: invokevirtual #254                // Method ext/mods/gameserver/network/serverpackets/SystemMessage.addCharName:(Lext/mods/gameserver/model/actor/Creature;)Lext/mods/gameserver/network/serverpackets/SystemMessage;
       266: aload_0
       267: getfield      #16                 // Field _recipe:Lext/mods/gameserver/model/records/Recipe;
       270: invokevirtual #101                // Method ext/mods/gameserver/model/records/Recipe.product:()Lext/mods/gameserver/model/holder/IntIntHolder;
       273: invokevirtual #258                // Method ext/mods/gameserver/model/holder/IntIntHolder.getId:()I
       276: invokevirtual #261                // Method ext/mods/gameserver/network/serverpackets/SystemMessage.addItemName:(I)Lext/mods/gameserver/network/serverpackets/SystemMessage;
       279: aload_0
       280: getfield      #152                // Field _price:I
       283: invokevirtual #265                // Method ext/mods/gameserver/network/serverpackets/SystemMessage.addItemNumber:(I)Lext/mods/gameserver/network/serverpackets/SystemMessage;
       286: invokevirtual #66                 // Method ext/mods/gameserver/model/actor/Player.sendPacket:(Lext/mods/gameserver/network/serverpackets/L2GameServerPacket;)V
       289: goto          302
       292: aload_0
       293: getfield      #13                 // Field _target:Lext/mods/gameserver/model/actor/Player;
       296: getstatic     #271                // Field ext/mods/gameserver/network/SystemMessageId.ITEM_MIXING_FAILED:Lext/mods/gameserver/network/SystemMessageId;
       299: invokevirtual #94                 // Method ext/mods/gameserver/model/actor/Player.sendPacket:(Lext/mods/gameserver/network/SystemMessageId;)V
       302: aload_0
       303: iconst_0
       304: invokevirtual #242                // Method updateMakeInfo:(Z)V
       307: aload_0
       308: getfield      #7                  // Field _player:Lext/mods/gameserver/model/actor/Player;
       311: invokevirtual #223                // Method ext/mods/gameserver/model/actor/Player.getMissions:()Lext/mods/gameserver/model/actor/container/player/MissionList;
       314: getstatic     #274                // Field ext/mods/gameserver/enums/actors/MissionType.CRAFT_FAIL:Lext/mods/gameserver/enums/actors/MissionType;
       317: invokevirtual #233                // Method ext/mods/gameserver/model/actor/container/player/MissionList.update:(Lext/mods/gameserver/enums/actors/MissionType;)V
       320: aload_0
       321: getfield      #7                  // Field _player:Lext/mods/gameserver/model/actor/Player;
       324: iconst_0
       325: invokevirtual #53                 // Method ext/mods/gameserver/model/actor/Player.setCrafting:(Z)V
       328: return
      LineNumberTable:
        line 148: 0
        line 150: 6
        line 151: 15
        line 152: 19
        line 155: 20
        line 157: 34
        line 158: 38
        line 161: 39
        line 163: 59
        line 164: 63
        line 167: 64
        line 169: 79
        line 171: 97
        line 172: 126
        line 174: 130
        line 175: 140
        line 176: 144
        line 180: 145
        line 182: 153
        line 183: 157
        line 186: 158
        line 188: 173
        line 189: 186
        line 190: 190
        line 194: 198
        line 196: 209
        line 197: 249
        line 200: 292
        line 202: 302
        line 203: 307
        line 206: 320
        line 207: 328
      LocalVariableTable:
        Start  Length  Slot  Name   Signature
          126      19     1 adenaTransfer   Lext/mods/gameserver/model/item/instance/ItemInstance;
            0     329     0  this   Lext/mods/gameserver/model/craft/RecipeItemMaker;
      StackMapTable: number_of_entries = 11
        frame_type = 20 /* same */
        frame_type = 13 /* same */
        frame_type = 4 /* same */
        frame_type = 19 /* same */
        frame_type = 4 /* same */
        frame_type = 251 /* same_frame_extended */
          offset_delta = 80
        frame_type = 12 /* same */
        frame_type = 39 /* same */
        frame_type = 251 /* same_frame_extended */
          offset_delta = 93
        frame_type = 9 /* same */
        frame_type = 17 /* same */

  public boolean isValid();
    descriptor: ()Z
    flags: (0x0001) ACC_PUBLIC
    Code:
      stack=1, locals=1, args_size=1
         0: aload_0
         1: getfield      #20                 // Field _isValid:Z
         4: ireturn
      LineNumberTable:
        line 306: 0
      LocalVariableTable:
        Start  Length  Slot  Name   Signature
            0       5     0  this   Lext/mods/gameserver/model/craft/RecipeItemMaker;
}
SourceFile: "RecipeItemMaker.java"
